Workbook

Sheet README
A1: Indonesia NCD FAIR Choices - cost & value workbook (formula edition)
A3: section | B3: detail
A4: Purpose | B4: Costing, budget impact and mortality-based cost-effectiveness for the FAIR Choices CVD interventions selected in indonesia_model_inputs.xlsx.
A5: How to read | B5: Grey cells are R-generated source values; light-blue cells are LIVE Excel formulas; pale-yellow cells on Calculation_Assumptions are editable controls. Change a yellow control and the blue results recompute. Calculation_Map lists every dependency.
A6: Scenarios | B6: Baseline + one scenario per selected valid intervention + a combined 'all' scenario. Membership derives only from the workbook selections (Model 04).
A7: Baseline pairing | B7: Deaths averted = baseline deaths - scenario deaths, matched at location x year x age x sex x cause (aggregated to year x cause here).
A8: CVD 40q30 | B8: CVD_40q30 / CVD_40q30_Age give the period probability of dying from the six CVD causes (ihd, istroke, hstroke, hhd, rhd, cmd) between exact ages 30 and 70, per scenario/HTN-target/year. The life table (m_x, q_x, l_x, l_{x+1}) is live Excel formula off grey CVD deaths and de-duplicated population; cvd_40q30 = 100*(1-l_70/l_30) reconciles to the Model 07 value. cvd_40q30 and the absolute reduction are PERCENT on a 0-100 scale (format 0.000), NOT Excel's fractional %.
A9: Model aggregates | B9: Annual_Mortality carries the R health aggregates (cases, deaths, baseline); Annual_Cost carries the full-precision R population quantity before the PIN fraction. The 157k-row state trace stays in the companion R workbook.
A10: Costing | B10: annual_cost = population_in_need x coverage(t) x frequency x unit_cost. PIN measure maps 'all'->eligible population, 'prevalence'->sick stock, 'incidence'->new cases.
A11: Shared costs | B11: Components flagged 'shared-count-once' (cost_join_key ...__C_SHARED) are counted once at intervention level, never once per affected cause (see Annual_Cost shared_duplicate_count and QA).
A12: Budget impact | B12: Budget impact reports UNDISCOUNTED baseline, scenario, incremental and cumulative incremental cost. Discounted costs are separate columns.
A13: Cost-effectiveness | B13: USD per death averted = cumulative discounted incremental cost / cumulative (undiscounted) deaths averted over the horizon. Not a DALY-based ICER.
A14: Economic value | B14: Reference-Case benefit-cost analysis (2019 Robinson et al. Guidelines): Health_Outcomes (Model 07 averted deaths/YLL/YLD/DALY & life-years gained), Economic_Value (Model 08 VSL/VSLY source with LIVE VSL-transfer, floor, VSLY, discount and PV-benefit formulas) and Benefit_Cost (PV benefits, PV costs converted to the benefit basis, net benefit and BCR). Preferred VSL = MAX(160xGNIpc_US x (GNIpc_IDN/GNIpc_US)^1.5, 20xGNIpc_IDN); 100x/160x GNI sensitivities. PARTIAL mortality-benefit BCA -- not a full societal BCA, and distinct from Cost_Effectiveness (USD per death averted).
... A18: Deferred | B18: Health outcomes (deaths averted, YLL/YLD/DALY averted, life-years gained) now come from Model 07 (Health_Outcomes); life-expectancy and disability-weight sources are documented via Model 07.

Sheet Run_Metadata
A1: item | B1: value
A2: Workbook title | B2: Indonesia NCD FAIR Choices - cost & value
A3: Run date | B3: 2026-08-27
A4: Model / pipeline | B4: CVD FAIR Choices (Models 00-06 -> 09)
A5: Input workbook | B5: C:/Users/wrgar/OneDrive - UW/02Work/WorldBank-Indonesia/uw-wb-indonesia-ncd//data/indonesia_70_30_30_to_70_70_70_inputs.xlsx
A6: Model output source | B6: output/out_model/model_output_*.rds (Model 06)
A7: Location | B7: Indonesia
A8: Analysis years | B8: =Calculation_Assumptions!B2&"-"&Calculation_Assumptions!B3 -> 2025-2050
A9: Baseline scenario | B9: =Calculation_Assumptions!B4 -> baseline
A10: Scenarios costed | B10: S_70_30_30_TO_70_70_70
A11: Cost discount rate | B11: =Calculation_Assumptions!B5 -> 0.03
A12: Cost price year | B12: =Calculation_Assumptions!B6 -> 2023
A13: Currency | B13: =Calculation_Assumptions!B7 -> USD
A14: Economic perspective | B14: =Calculation_Assumptions!B8 -> health_system
A15: Coverage scale-up shape | B15: =Calculation_Assumptions!B9 -> piecewise_linear
A16: Downstream cost offsets | B16: =Calculation_Assumptions!B10 -> 0
A17: Health outcomes (DALYs/YLL/YLD) | B17: Out of scope in this stage (deferred)
A18: R version | B18: R version 4.5.1 (2025-06-13 ucrt)
A19: openxlsx / data.table | B19: 4.2.8 / 1.17.8

Sheet Scenario_Catalog
A1: scenario | B1: scenario_label | C1: intervention_family | D1: scenario_level | E1: scenario_role | F1: parent_package_id | G1: intervention_ids | H1: n_interventions
A2: baseline | B2: Baseline (no new intervention) | C2: baseline | D2: baseline | H2: 0
A3: S_70_30_30_TO_70_70_70 | B3: 70-30-30 -> 70-70-70 hypertension/cholesterol + diabetes cascade | C3: cascade_70_30_30_to_70_70_70 | D3: combined | E3: combined | G3: I_CVD_PRIMARY; I_T2D_TREATMENT | H3: 2

Sheet Cascade_Assumptions
A1: parameter_id | B1: value | C1: unit | D1: description | E1: source | F1: source_workbook_cell
A2: analysis_start_year | B2: 2025 | C2: year | D2: First modeled year | E2: Agreed analysis horizon | F2: Assumptions![parameter_id=analysis_start_year]
A3: analysis_end_year | B3: 2050 | C3: year | D3: Last modeled year | E3: Agreed analysis horizon | F3: Assumptions![parameter_id=analysis_end_year]
A4: first_target_year | B4: 2030 | C4: year | D4: Year to achieve 70-30-30 | E4: World Bank/UW request, 27 Aug 2026 | F4: Assumptions![parameter_id=first_target_year]
A5: final_target_year | B5: 2040 | C5: year | D5: Year to achieve 70-70-70 | E5: World Bank/UW request, 27 Aug 2026 | F5: Assumptions![parameter_id=final_target_year]
A6: target_diagnosis_share | B6: 0.7 | C6: proportion | D6: Diagnosis step for both targets | E6: World Bank/UW request | F6: Assumptions![parameter_id=target_diagnosis_share]
A7: first_target_treatment_conditional | B7: 0.3 | C7: proportion | D7: Treated among diagnosed in 2030 | E7: 70-30-30 definition | F7: Assumptions![parameter_id=first_target_treatment_conditional]
A8: first_target_control_conditional | B8: 0.3 | C8: proportion | D8: Controlled among treated in 2030 | E8: 70-30-30 definition | F8: Assumptions![parameter_id=first_target_control_conditional]
A9: final_target_treatment_conditional | B9: 0.7 | C9: proportion | D9: Treated among diagnosed in 2040 | E9: 70-70-70 definition | F9: Assumptions![parameter_id=final_target_treatment_conditional]
A10: final_target_control_conditional | B10: 0.7 | C10: proportion | D10: Controlled among treated in 2040 | E10: 70-70-70 definition | F10: Assumptions![parameter_id=final_target_control_conditional]
A11: treated_uncontrolled_effect_fraction | B11: 0.5 | C11: share of full effect | D11: Effect received when treated but uncontrolled | E11: World Bank/UW request | F11: Assumptions![parameter_id=treated_uncontrolled_effect_fraction]
A12: first_target_effective_coverage_exact | B12: 0.1365 | C12: proportion | D12: Exact 70-30-30 effective coverage; no rounding override | E12: World Bank/UW cascade specification | F12: Assumptions![parameter_id=first_target_effective_coverage_exact]
A13: final_target_effective_coverage_exact | B13: 0.4165 | C13: proportion | D13: Exact 70-70-70 effective coverage; no rounding override | E13: World Bank/UW cascade specification | F13: Assumptions![parameter_id=final_target_effective_coverage_exact]
A14: diabetes_baseline_control_among_treated | B14: 0.34210526 | C14: proportion | D14: Derived as 6.5% controlled / 19.0% treated in the 2023 national diabetes cascade; editable | E14: Muharram et al. medRxiv 2026; peer-reviewed national estimate 32.0% HbA1c<7% | F14: Assumptions![parameter_id=diabetes_baseline_control_among_treated]
A15: diabetes_baseline_diagnosis_conditioning | B15: 1 | C15: proportion | D15: Conditions directly on all people with diabetes so reported treatment is reproduced | E15: Explicit modeling assumption | F15: Assumptions![parameter_id=diabetes_baseline_diagnosis_conditioning]
A16: cholesterol_coverage_proxy | B16: hypertension | C16: text | D16: Cholesterol coverage follows hypertension coverage | E16: World Bank/UW request | F16: Assumptions![parameter_id=cholesterol_coverage_proxy]
A17: scale_up_shape | B17: piecewise_linear | C17: text | D17: Linear to 2030, then linear to 2040 | E17: World Bank/UW request | F17: Assumptions![parameter_id=scale_up_shape]
A18: post_target_rule | B18: hold | C18: text | D18: Maintain achieved level after 2040 | E18: World Bank/UW request | F18: Assumptions![parameter_id=post_target_rule]
A19: prevent_coverage_backsliding | B19: 1 | C19: 0/1 | D19: When a measured baseline already exceeds a milestone, retain baseline rather than scale down | E19: Scale-up interpretation | F19: Assumptions![parameter_id=prevent_coverage_backsliding]
A20: scenario_id | B20: S_70_30_30_TO_70_70_70 | C20: text | D20: Stable scenario identifier | E20: This analysis | F20: Assumptions![parameter_id=scenario_id]
A21: cost_discount_rate | B21: 0.03 | C21: proportion/year | D21: Annual cost discount rate | E21: Supplied Indonesia input workbook | F21: Assumptions![parameter_id=cost_discount_rate]
A22: health_discount_rate | B22: 0.03 | C22: proportion/year | D22: Annual health discount rate | E22: Supplied Indonesia input workbook | F22: Assumptions![parameter_id=health_discount_rate]
A23: cost_price_year | B23: 2023 | C23: USD year | D23: Reporting price year | E23: Supplied Indonesia input workbook | F23: Assumptions![parameter_id=cost_price_year]
A24: currency | B24: USD | C24: currency | D24: Reporting currency | E24: Supplied Indonesia input workbook | F24: Assumptions![parameter_id=currency]

Sheet Cascade_Trajectory
A1: intervention_id | B1: risk_factor_id | C1: sex | D1: year | E1: phase | F1: baseline_effective_coverage | G1: target_2030_effective | H1: target_2040_effective | I1: controlled_share | J1: treated_uncontrolled_share | K1: half_effect_fraction | L1: scenario_effective_coverage | M1: effective_from_components | N1: model_effective_coverage_used
A2: I_CVD_PRIMARY | B2: RF_HTN | C2: Men | D2: 2025 | E2: Scale to 70-30-30 | F2: 0.094852977 | G2: 0.1365 | H2: 0.4165 | I2: 0.035834751 | J2: 0.11803645 | K2: 0.5 | L2: 0.094852977 | M2: =I2+Cascade_Assumptions!$B$11*J2 -> 0.094852977 | N2: =L2 -> 0.094852977
A3: I_CVD_PRIMARY | B3: RF_HTN | C3: Men | D3: 2026 | E3: Scale to 70-30-30 | F3: 0.094852977 | G3: 0.1365 | H3: 0.4165 | L3: 0.10318238 | N3: =L3 -> 0.10318238
A4: I_CVD_PRIMARY | B4: RF_HTN | C4: Men | D4: 2027 | E4: Scale to 70-30-30 | F4: 0.094852977 | G4: 0.1365 | H4: 0.4165 | L4: 0.11151179 | N4: =L4 -> 0.11151179
A5: I_CVD_PRIMARY | B5: RF_HTN | C5: Men | D5: 2028 | E5: Scale to 70-30-30 | F5: 0.094852977 | G5: 0.1365 | H5: 0.4165 | L5: 0.11984119 | N5: =L5 -> 0.11984119
A6: I_CVD_PRIMARY | B6: RF_HTN | C6: Men | D6: 2029 | E6: Scale to 70-30-30 | F6: 0.094852977 | G6: 0.1365 | H6: 0.4165 | L6: 0.1281706 | N6: =L6 -> 0.1281706
A7: I_CVD_PRIMARY | B7: RF_HTN | C7: Men | D7: 2030 | E7: Scale to 70-30-30 | F7: 0.094852977 | G7: 0.1365 | H7: 0.4165 | I7: 0.063 | J7: 0.147 | K7: 0.5 | L7: 0.1365 | M7: =I7+Cascade_Assumptions!$B$11*J7 -> 0.1365 | N7: =L7 -> 0.1365
A8: I_CVD_PRIMARY | B8: RF_HTN | C8: Men | D8: 2031 | E8: Scale to 70-70-70 | F8: 0.094852977 | G8: 0.1365 | H8: 0.4165 | L8: 0.1645 | N8: =L8 -> 0.1645
A9: I_CVD_PRIMARY | B9: RF_HTN | C9: Men | D9: 2032 | E9: Scale to 70-70-70 | F9: 0.094852977 | G9: 0.1365 | H9: 0.4165 | L9: 0.1925 | N9: =L9 -> 0.1925
A10: I_CVD_PRIMARY | B10: RF_HTN | C10: Men | D10: 2033 | E10: Scale to 70-70-70 | F10: 0.094852977 | G10: 0.1365 | H10: 0.4165 | L10: 0.2205 | N10: =L10 -> 0.2205
A11: I_CVD_PRIMARY | B11: RF_HTN | C11: Men | D11: 2034 | E11: Scale to 70-70-70 | F11: 0.094852977 | G11: 0.1365 | H11: 0.4165 | L11: 0.2485 | N11: =L11 -> 0.2485
A12: I_CVD_PRIMARY | B12: RF_HTN | C12: Men | D12: 2035 | E12: Scale to 70-70-70 | F12: 0.094852977 | G12: 0.1365 | H12: 0.4165 | L12: 0.2765 | N12: =L12 -> 0.2765
A13: I_CVD_PRIMARY | B13: RF_HTN | C13: Men | D13: 2036 | E13: Scale to 70-70-70 | F13: 0.094852977 | G13: 0.1365 | H13: 0.4165 | L13: 0.3045 | N13: =L13 -> 0.3045
A14: I_CVD_PRIMARY | B14: RF_HTN | C14: Men | D14: 2037 | E14: Scale to 70-70-70 | F14: 0.094852977 | G14: 0.1365 | H14: 0.4165 | L14: 0.3325 | N14: =L14 -> 0.3325
A15: I_CVD_PRIMARY | B15: RF_HTN | C15: Men | D15: 2038 | E15: Scale to 70-70-70 | F15: 0.094852977 | G15: 0.1365 | H15: 0.4165 | L15: 0.3605 | N15: =L15 -> 0.3605
A16: I_CVD_PRIMARY | B16: RF_HTN | C16: Men | D16: 2039 | E16: Scale to 70-70-70 | F16: 0.094852977 | G16: 0.1365 | H16: 0.4165 | L16: 0.3885 | N16: =L16 -> 0.3885
A17: I_CVD_PRIMARY | B17: RF_HTN | C17: Men | D17: 2040 | E17: Scale to 70-70-70 | F17: 0.094852977 | G17: 0.1365 | H17: 0.4165 | I17: 0.343 | J17: 0.147 | K17: 0.5 | L17: 0.4165 | M17: =I17+Cascade_Assumptions!$B$11*J17 -> 0.4165 | N17: =L17 -> 0.4165
A18: I_CVD_PRIMARY | B18: RF_HTN | C18: Men | D18: 2041 | E18: Maintain 70-70-70 | F18: 0.094852977 | G18: 0.1365 | H18: 0.4165 | L18: 0.4165 | N18: =L18 -> 0.4165
A19: I_CVD_PRIMARY | B19: RF_HTN | C19: Men | D19: 2042 | E19: Maintain 70-70-70 | F19: 0.094852977 | G19: 0.1365 | H19: 0.4165 | L19: 0.4165 | N19: =L19 -> 0.4165
A20: I_CVD_PRIMARY | B20: RF_HTN | C20: Men | D20: 2043 | E20: Maintain 70-70-70 | F20: 0.094852977 | G20: 0.1365 | H20: 0.4165 | L20: 0.4165 | N20: =L20 -> 0.4165
A21: I_CVD_PRIMARY | B21: RF_HTN | C21: Men | D21: 2044 | E21: Maintain 70-70-70 | F21: 0.094852977 | G21: 0.1365 | H21: 0.4165 | L21: 0.4165 | N21: =L21 -> 0.4165
A22: I_CVD_PRIMARY | B22: RF_HTN | C22: Men | D22: 2045 | E22: Maintain 70-70-70 | F22: 0.094852977 | G22: 0.1365 | H22: 0.4165 | L22: 0.4165 | N22: =L22 -> 0.4165
A23: I_CVD_PRIMARY | B23: RF_HTN | C23: Men | D23: 2046 | E23: Maintain 70-70-70 | F23: 0.094852977 | G23: 0.1365 | H23: 0.4165 | L23: 0.4165 | N23: =L23 -> 0.4165
A24: I_CVD_PRIMARY | B24: RF_HTN | C24: Men | D24: 2047 | E24: Maintain 70-70-70 | F24: 0.094852977 | G24: 0.1365 | H24: 0.4165 | L24: 0.4165 | N24: =L24 -> 0.4165
A25: I_CVD_PRIMARY | B25: RF_HTN | C25: Men | D25: 2048 | E25: Maintain 70-70-70 | F25: 0.094852977 | G25: 0.1365 | H25: 0.4165 | L25: 0.4165 | N25: =L25 -> 0.4165
A26: I_CVD_PRIMARY | B26: RF_HTN | C26: Men | D26: 2049 | E26: Maintain 70-70-70 | F26: 0.094852977 | G26: 0.1365 | H26: 0.4165 | L26: 0.4165 | N26: =L26 -> 0.4165
A27: I_CVD_PRIMARY | B27: RF_HTN | C27: Men | D27: 2050 | E27: Maintain 70-70-70 | F27: 0.094852977 | G27: 0.1365 | H27: 0.4165 | L27: 0.4165 | N27: =L27 -> 0.4165
A28: I_CVD_PRIMARY | B28: RF_HTN | C28: Women | D28: 2025 | E28: Scale to 70-30-30 | F28: 0.13268074 | G28: 0.1365 | H28: 0.4165 | I28: 0.051214394 | J28: 0.16293269 | K28: 0.5 | L28: 0.13268074 | M28: =I28+Cascade_Assumptions!$B$11*J28 -> 0.13268074 | N28: =L28 -> 0.13268074
A29: I_CVD_PRIMARY | B29: RF_HTN | C29: Women | D29: 2026 | E29: Scale to 70-30-30 | F29: 0.13268074 | G29: 0.1365 | H29: 0.4165 | L29: 0.13344459 | N29: =L29 -> 0.13344459
A30: I_CVD_PRIMARY | B30: RF_HTN | C30: Women | D30: 2027 | E30: Scale to 70-30-30 | F30: 0.13268074 | G30: 0.1365 | H30: 0.4165 | L30: 0.13420844 | N30: =L30 -> 0.13420844
A31: I_CVD_PRIMARY | B31: RF_HTN | C31: Women | D31: 2028 | E31: Scale to 70-30-30 | F31: 0.13268074 | G31: 0.1365 | H31: 0.4165 | L31: 0.1349723 | N31: =L31 -> 0.1349723
A32: I_CVD_PRIMARY | B32: RF_HTN | C32: Women | D32: 2029 | E32: Scale to 70-30-30 | F32: 0.13268074 | G32: 0.1365 | H32: 0.4165 | L32: 0.13573615 | N32: =L32 -> 0.13573615
A33: I_CVD_PRIMARY | B33: RF_HTN | C33: Women | D33: 2030 | E33: Scale to 70-30-30 | F33: 0.13268074 | G33: 0.1365 | H33: 0.4165 | I33: 0.063 | J33: 0.147 | K33: 0.5 | L33: 0.1365 | M33: =I33+Cascade_Assumptions!$B$11*J33 -> 0.1365 | N33: =L33 -> 0.1365
A34: I_CVD_PRIMARY | B34: RF_HTN | C34: Women | D34: 2031 | E34: Scale to 70-70-70 | F34: 0.13268074 | G34: 0.1365 | H34: 0.4165 | L34: 0.1645 | N34: =L34 -> 0.1645
A35: I_CVD_PRIMARY | B35: RF_HTN | C35: Women | D35: 2032 | E35: Scale to 70-70-70 | F35: 0.13268074 | G35: 0.1365 | H35: 0.4165 | L35: 0.1925 | N35: =L35 -> 0.1925
A36: I_CVD_PRIMARY | B36: RF_HTN | C36: Women | D36: 2033 | E36: Scale to 70-70-70 | F36: 0.13268074 | G36: 0.1365 | H36: 0.4165 | L36: 0.2205 | N36: =L36 -> 0.2205
A37: I_CVD_PRIMARY | B37: RF_HTN | C37: Women | D37: 2034 | E37: Scale to 70-70-70 | F37: 0.13268074 | G37: 0.1365 | H37: 0.4165 | L37: 0.2485 | N37: =L37 -> 0.2485
A38: I_CVD_PRIMARY | B38: RF_HTN | C38: Women | D38: 2035 | E38: Scale to 70-70-70 | F38: 0.13268074 | G38: 0.1365 | H38: 0.4165 | L38: 0.2765 | N38: =L38 -> 0.2765
A39: I_CVD_PRIMARY | B39: RF_HTN | C39: Women | D39: 2036 | E39: Scale to 70-70-70 | F39: 0.13268074 | G39: 0.1365 | H39: 0.4165 | L39: 0.3045 | N39: =L39 -> 0.3045
A40: I_CVD_PRIMARY | B40: RF_HTN | C40: Women | D40: 2037 | E40: Scale to 70-70-70 | F40: 0.13268074 | G40: 0.1365 | H40: 0.4165 | L40: 0.3325 | N40: =L40 -> 0.3325
A41: I_CVD_PRIMARY | B41: RF_HTN | C41: Women | D41: 2038 | E41: Scale to 70-70-70 | F41: 0.13268074 | G41: 0.1365 | H41: 0.4165 | L41: 0.3605 | N41: =L41 -> 0.3605
A42: I_CVD_PRIMARY | B42: RF_HTN | C42: Women | D42: 2039 | E42: Scale to 70-70-70 | F42: 0.13268074 | G42: 0.1365 | H42: 0.4165 | L42: 0.3885 | N42: =L42 -> 0.3885
A43: I_CVD_PRIMARY | B43: RF_HTN | C43: Women | D43: 2040 | E43: Scale to 70-70-70 | F43: 0.13268074 | G43: 0.1365 | H43: 0.4165 | I43: 0.343 | J43: 0.147 | K43: 0.5 | L43: 0.4165 | M43: =I43+Cascade_Assumptions!$B$11*J43 -> 0.4165 | N43: =L43 -> 0.4165
A44: I_CVD_PRIMARY | B44: RF_HTN | C44: Women | D44: 2041 | E44: Maintain 70-70-70 | F44: 0.13268074 | G44: 0.1365 | H44: 0.4165 | L44: 0.4165 | N44: =L44 -> 0.4165
A45: I_CVD_PRIMARY | B45: RF_HTN | C45: Women | D45: 2042 | E45: Maintain 70-70-70 | F45: 0.13268074 | G45: 0.1365 | H45: 0.4165 | L45: 0.4165 | N45: =L45 -> 0.4165
A46: I_CVD_PRIMARY | B46: RF_HTN | C46: Women | D46: 2043 | E46: Maintain 70-70-70 | F46: 0.13268074 | G46: 0.1365 | H46: 0.4165 | L46: 0.4165 | N46: =L46 -> 0.4165
A47: I_CVD_PRIMARY | B47: RF_HTN | C47: Women | D47: 2044 | E47: Maintain 70-70-70 | F47: 0.13268074 | G47: 0.1365 | H47: 0.4165 | L47: 0.4165 | N47: =L47 -> 0.4165
A48: I_CVD_PRIMARY | B48: RF_HTN | C48: Women | D48: 2045 | E48: Maintain 70-70-70 | F48: 0.13268074 | G48: 0.1365 | H48: 0.4165 | L48: 0.4165 | N48: =L48 -> 0.4165
A49: I_CVD_PRIMARY | B49: RF_HTN | C49: Women | D49: 2046 | E49: Maintain 70-70-70 | F49: 0.13268074 | G49: 0.1365 | H49: 0.4165 | L49: 0.4165 | N49: =L49 -> 0.4165
A50: I_CVD_PRIMARY | B50: RF_HTN | C50: Women | D50: 2047 | E50: Maintain 70-70-70 | F50: 0.13268074 | G50: 0.1365 | H50: 0.4165 | L50: 0.4165 | N50: =L50 -> 0.4165
A51: I_CVD_PRIMARY | B51: RF_HTN | C51: Women | D51: 2048 | E51: Maintain 70-70-70 | F51: 0.13268074 | G51: 0.1365 | H51: 0.4165 | L51: 0.4165 | N51: =L51 -> 0.4165
A52: I_CVD_PRIMARY | B52: RF_HTN | C52: Women | D52: 2049 | E52: Maintain 70-70-70 | F52: 0.13268074 | G52: 0.1365 | H52: 0.4165 | L52: 0.4165 | N52: =L52 -> 0.4165
A53: I_CVD_PRIMARY | B53: RF_HTN | C53: Women | D53: 2050 | E53: Maintain 70-70-70 | F53: 0.13268074 | G53: 0.1365 | H53: 0.4165 | L53: 0.4165 | N53: =L53 -> 0.4165
A54: I_T2D_TREATMENT | B54: RF_T2D | C54: Men | D54: 2025 | E54: Scale to 70-30-30 | F54: 0.13031153 | G54: 0.1365 | H54: 0.4165 | I54: 0.066433328 | J54: 0.1277564 | K54: 0.5 | L54: 0.13031153 | M54: =I54+Cascade_Assumptions!$B$11*J54 -> 0.13031153 | N54: =L54 -> 0.13031153
A55: I_T2D_TREATMENT | B55: RF_T2D | C55: Men | D55: 2026 | E55: Scale to 70-30-30 | F55: 0.13031153 | G55: 0.1365 | H55: 0.4165 | L55: 0.13154922 | N55: =L55 -> 0.13154922
A56: I_T2D_TREATMENT | B56: RF_T2D | C56: Men | D56: 2027 | E56: Scale to 70-30-30 | F56: 0.13031153 | G56: 0.1365 | H56: 0.4165 | L56: 0.13278692 | N56: =L56 -> 0.13278692
A57: I_T2D_TREATMENT | B57: RF_T2D | C57: Men | D57: 2028 | E57: Scale to 70-30-30 | F57: 0.13031153 | G57: 0.1365 | H57: 0.4165 | L57: 0.13402461 | N57: =L57 -> 0.13402461
A58: I_T2D_TREATMENT | B58: RF_T2D | C58: Men | D58: 2029 | E58: Scale to 70-30-30 | F58: 0.13031153 | G58: 0.1365 | H58: 0.4165 | L58: 0.13526231 | N58: =L58 -> 0.13526231
A59: I_T2D_TREATMENT | B59: RF_T2D | C59: Men | D59: 2030 | E59: Scale to 70-30-30 | F59: 0.13031153 | G59: 0.1365 | H59: 0.4165 | I59: 0.063 | J59: 0.147 | K59: 0.5 | L59: 0.1365 | M59: =I59+Cascade_Assumptions!$B$11*J59 -> 0.1365 | N59: =L59 -> 0.1365
A60: I_T2D_TREATMENT | B60: RF_T2D | C60: Men | D60: 2031 | E60: Scale to 70-70-70 | F60: 0.13031153 | G60: 0.1365 | H60: 0.4165 | L60: 0.1645 | N60: =L60 -> 0.1645
A61: I_T2D_TREATMENT | B61: RF_T2D | C61: Men | D61: 2032 | E61: Scale to 70-70-70 | F61: 0.13031153 | G61: 0.1365 | H61: 0.4165 | L61: 0.1925 | N61: =L61 -> 0.1925
A62: I_T2D_TREATMENT | B62: RF_T2D | C62: Men | D62: 2033 | E62: Scale to 70-70-70 | F62: 0.13031153 | G62: 0.1365 | H62: 0.4165 | L62: 0.2205 | N62: =L62 -> 0.2205
A63: I_T2D_TREATMENT | B63: RF_T2D | C63: Men | D63: 2034 | E63: Scale to 70-70-70 | F63: 0.13031153 | G63: 0.1365 | H63: 0.4165 | L63: 0.2485 | N63: =L63 -> 0.2485
A64: I_T2D_TREATMENT | B64: RF_T2D | C64: Men | D64: 2035 | E64: Scale to 70-70-70 | F64: 0.13031153 | G64: 0.1365 | H64: 0.4165 | L64: 0.2765 | N64: =L64 -> 0.2765
A65: I_T2D_TREATMENT | B65: RF_T2D | C65: Men | D65: 2036 | E65: Scale to 70-70-70 | F65: 0.13031153 | G65: 0.1365 | H65: 0.4165 | L65: 0.3045 | N65: =L65 -> 0.3045
A66: I_T2D_TREATMENT | B66: RF_T2D | C66: Men | D66: 2037 | E66: Scale to 70-70-70 | F66: 0.13031153 | G66: 0.1365 | H66: 0.4165 | L66: 0.3325 | N66: =L66 -> 0.3325
A67: I_T2D_TREATMENT | B67: RF_T2D | C67: Men | D67: 2038 | E67: Scale to 70-70-70 | F67: 0.13031153 | G67: 0.1365 | H67: 0.4165 | L67: 0.3605 | N67: =L67 -> 0.3605
A68: I_T2D_TREATMENT | B68: RF_T2D | C68: Men | D68: 2039 | E68: Scale to 70-70-70 | F68: 0.13031153 | G68: 0.1365 | H68: 0.4165 | L68: 0.3885 | N68: =L68 -> 0.3885
A69: I_T2D_TREATMENT | B69: RF_T2D | C69: Men | D69: 2040 | E69: Scale to 70-70-70 | F69: 0.13031153 | G69: 0.1365 | H69: 0.4165 | I69: 0.343 | J69: 0.147 | K69: 0.5 | L69: 0.4165 | M69: =I69+Cascade_Assumptions!$B$11*J69 -> 0.4165 | N69: =L69 -> 0.4165
A70: I_T2D_TREATMENT | B70: RF_T2D | C70: Men | D70: 2041 | E70: Maintain 70-70-70 | F70: 0.13031153 | G70: 0.1365 | H70: 0.4165 | L70: 0.4165 | N70: =L70 -> 0.4165
A71: I_T2D_TREATMENT | B71: RF_T2D | C71: Men | D71: 2042 | E71: Maintain 70-70-70 | F71: 0.13031153 | G71: 0.1365 | H71: 0.4165 | L71: 0.4165 | N71: =L71 -> 0.4165
A72: I_T2D_TREATMENT | B72: RF_T2D | C72: Men | D72: 2043 | E72: Maintain 70-70-70 | F72: 0.13031153 | G72: 0.1365 | H72: 0.4165 | L72: 0.4165 | N72: =L72 -> 0.4165
A73: I_T2D_TREATMENT | B73: RF_T2D | C73: Men | D73: 2044 | E73: Maintain 70-70-70 | F73: 0.13031153 | G73: 0.1365 | H73: 0.4165 | L73: 0.4165 | N73: =L73 -> 0.4165
A74: I_T2D_TREATMENT | B74: RF_T2D | C74: Men | D74: 2045 | E74: Maintain 70-70-70 | F74: 0.13031153 | G74: 0.1365 | H74: 0.4165 | L74: 0.4165 | N74: =L74 -> 0.4165
A75: I_T2D_TREATMENT | B75: RF_T2D | C75: Men | D75: 2046 | E75: Maintain 70-70-70 | F75: 0.13031153 | G75: 0.1365 | H75: 0.4165 | L75: 0.4165 | N75: =L75 -> 0.4165
A76: I_T2D_TREATMENT | B76: RF_T2D | C76: Men | D76: 2047 | E76: Maintain 70-70-70 | F76: 0.13031153 | G76: 0.1365 | H76: 0.4165 | L76: 0.4165 | N76: =L76 -> 0.4165
A77: I_T2D_TREATMENT | B77: RF_T2D | C77: Men | D77: 2048 | E77: Maintain 70-70-70 | F77: 0.13031153 | G77: 0.1365 | H77: 0.4165 | L77: 0.4165 | N77: =L77 -> 0.4165
A78: I_T2D_TREATMENT | B78: RF_T2D | C78: Men | D78: 2049 | E78: Maintain 70-70-70 | F78: 0.13031153 | G78: 0.1365 | H78: 0.4165 | L78: 0.4165 | N78: =L78 -> 0.4165
A79: I_T2D_TREATMENT | B79: RF_T2D | C79: Men | D79: 2050 | E79: Maintain 70-70-70 | F79: 0.13031153 | G79: 0.1365 | H79: 0.4165 | L79: 0.4165 | N79: =L79 -> 0.4165
A80: I_T2D_TREATMENT | B80: RF_T2D | C80: Women | D80: 2025 | E80: Scale to 70-30-30 | F80: 0.1655177 | G80: 0.1365 | H80: 0.4165 | I80: 0.084381571 | J80: 0.16227225 | K80: 0.5 | L80: 0.1655177 | M80: =I80+Cascade_Assumptions!$B$11*J80 -> 0.1655177 | N80: =L80 -> 0.1655177
A81: I_T2D_TREATMENT | B81: RF_T2D | C81: Women | D81: 2026 | E81: Scale to 70-30-30 | F81: 0.1655177 | G81: 0.1365 | H81: 0.4165 | L81: 0.1655177 | N81: =L81 -> 0.1655177
A82: I_T2D_TREATMENT | B82: RF_T2D | C82: Women | D82: 2027 | E82: Scale to 70-30-30 | F82: 0.1655177 | G82: 0.1365 | H82: 0.4165 | L82: 0.1655177 | N82: =L82 -> 0.1655177
A83: I_T2D_TREATMENT | B83: RF_T2D | C83: Women | D83: 2028 | E83: Scale to 70-30-30 | F83: 0.1655177 | G83: 0.1365 | H83: 0.4165 | L83: 0.1655177 | N83: =L83 -> 0.1655177
A84: I_T2D_TREATMENT | B84: RF_T2D | C84: Women | D84: 2029 | E84: Scale to 70-30-30 | F84: 0.1655177 | G84: 0.1365 | H84: 0.4165 | L84: 0.1655177 | N84: =L84 -> 0.1655177
A85: I_T2D_TREATMENT | B85: RF_T2D | C85: Women | D85: 2030 | E85: Scale to 70-30-30 | F85: 0.1655177 | G85: 0.1365 | H85: 0.4165 | I85: 0.063 | J85: 0.147 | K85: 0.5 | L85: 0.1655177 | M85: =I85+Cascade_Assumptions!$B$11*J85 -> 0.1365 | N85: =L85 -> 0.1655177
A86: I_T2D_TREATMENT | B86: RF_T2D | C86: Women | D86: 2031 | E86: Scale to 70-70-70 | F86: 0.1655177 | G86: 0.1365 | H86: 0.4165 | L86: 0.19061593 | N86: =L86 -> 0.19061593
A87: I_T2D_TREATMENT | B87: RF_T2D | C87: Women | D87: 2032 | E87: Scale to 70-70-70 | F87: 0.1655177 | G87: 0.1365 | H87: 0.4165 | L87: 0.21571416 | N87: =L87 -> 0.21571416
A88: I_T2D_TREATMENT | B88: RF_T2D | C88: Women | D88: 2033 | E88: Scale to 70-70-70 | F88: 0.1655177 | G88: 0.1365 | H88: 0.4165 | L88: 0.24081239 | N88: =L88 -> 0.24081239
A89: I_T2D_TREATMENT | B89: RF_T2D | C89: Women | D89: 2034 | E89: Scale to 70-70-70 | F89: 0.1655177 | G89: 0.1365 | H89: 0.4165 | L89: 0.26591062 | N89: =L89 -> 0.26591062
A90: I_T2D_TREATMENT | B90: RF_T2D | C90: Women | D90: 2035 | E90: Scale to 70-70-70 | F90: 0.1655177 | G90: 0.1365 | H90: 0.4165 | L90: 0.29100885 | N90: =L90 -> 0.29100885
A91: I_T2D_TREATMENT | B91: RF_T2D | C91: Women | D91: 2036 | E91: Scale to 70-70-70 | F91: 0.1655177 | G91: 0.1365 | H91: 0.4165 | L91: 0.31610708 | N91: =L91 -> 0.31610708
A92: I_T2D_TREATMENT | B92: RF_T2D | C92: Women | D92: 2037 | E92: Scale to 70-70-70 | F92: 0.1655177 | G92: 0.1365 | H92: 0.4165 | L92: 0.34120531 | N92: =L92 -> 0.34120531
A93: I_T2D_TREATMENT | B93: RF_T2D | C93: Women | D93: 2038 | E93: Scale to 70-70-70 | F93: 0.1655177 | G93: 0.1365 | H93: 0.4165 | L93: 0.36630354 | N93: =L93 -> 0.36630354
A94: I_T2D_TREATMENT | B94: RF_T2D | C94: Women | D94: 2039 | E94: Scale to 70-70-70 | F94: 0.1655177 | G94: 0.1365 | H94: 0.4165 | L94: 0.39140177 | N94: =L94 -> 0.39140177
A95: I_T2D_TREATMENT | B95: RF_T2D | C95: Women | D95: 2040 | E95: Scale to 70-70-70 | F95: 0.1655177 | G95: 0.1365 | H95: 0.4165 | I95: 0.343 | J95: 0.147 | K95: 0.5 | L95: 0.4165 | M95: =I95+Cascade_Assumptions!$B$11*J95 -> 0.4165 | N95: =L95 -> 0.4165
A96: I_T2D_TREATMENT | B96: RF_T2D | C96: Women | D96: 2041 | E96: Maintain 70-70-70 | F96: 0.1655177 | G96: 0.1365 | H96: 0.4165 | L96: 0.4165 | N96: =L96 -> 0.4165
A97: I_T2D_TREATMENT | B97: RF_T2D | C97: Women | D97: 2042 | E97: Maintain 70-70-70 | F97: 0.1655177 | G97: 0.1365 | H97: 0.4165 | L97: 0.4165 | N97: =L97 -> 0.4165
A98: I_T2D_TREATMENT | B98: RF_T2D | C98: Women | D98: 2043 | E98: Maintain 70-70-70 | F98: 0.1655177 | G98: 0.1365 | H98: 0.4165 | L98: 0.4165 | N98: =L98 -> 0.4165
A99: I_T2D_TREATMENT | B99: RF_T2D | C99: Women | D99: 2044 | E99: Maintain 70-70-70 | F99: 0.1655177 | G99: 0.1365 | H99: 0.4165 | L99: 0.4165 | N99: =L99 -> 0.4165
A100: I_T2D_TREATMENT | B100: RF_T2D | C100: Women | D100: 2045 | E100: Maintain 70-70-70 | F100: 0.1655177 | G100: 0.1365 | H100: 0.4165 | L100: 0.4165 | N100: =L100 -> 0.4165
...

Sheet Cascade_QA
A1: check_id | B1: check | C1: controlled_share | D1: treated_uncontrolled_share | E1: excel_effective | F1: expected_effective | G1: r_value | H1: status
A2: QAC01 | B2: 2030 effective coverage reconstructs to 0.1365 | C2: 0.063 | D2: 0.147 | E2: =C2+Cascade_Assumptions!$B$11*D2 -> 0.1365 | F2: 0.1365 | H2: =IF(ABS(E2-F2)<0.0000001,"PASS","CHECK") -> PASS
A3: QAC02 | B3: 2040 effective coverage reconstructs to 0.4165 | C3: 0.343 | D3: 0.147 | E3: =C3+Cascade_Assumptions!$B$11*D3 -> 0.4165 | F3: 0.4165 | H3: =IF(ABS(E3-F3)<0.0000001,"PASS","CHECK") -> PASS
A4: QAC03 | B4: Excel model_effective_coverage_used ties to R (by construction) | G4: 0 | H4: PASS
A5: QAC04 | B5: R adapter vs workbook Model_Input_View multipliers | G5: 0 | H5: =IF(G5<0.000001,"PASS","FAIL") -> PASS
A6: QAC05 | B6: Effective coverage is monotonic (no backsliding) | G6: 0 | H6: =IF(G6=0,"PASS","FAIL") -> PASS

Sheet Selected_Interventions
A1: intervention_id | B1: intervention_cause_key | C1: intervention_name | D1: cause_id | E1: cause_code | F1: model_name | G1: transition_from | H1: transition_to | I1: model_transition | J1: effect_value | K1: affected_fraction | L1: baseline_coverage | M1: target_coverage | N1: start_year | O1: target_year | P1: adjusted_effect_at_target | Q1: cost_join_key | R1: cost_scope | S1: effect_review | T1: coverage_review | U1: key_count | V1: formula_status
A2: I_CVD_PRIMARY | B2: I_CVD_PRIMARY__C_HHD | C2: Primary prevention of CVD | D2: C_HHD | E2: hhd | F2: Hypertensive heart disease | G2: well | H2: sick | I2: incidence | J2: 0.47 | K2: 1 | L2: 0.11376686 | M2: 0.4165 | N2: 2025 | O2: 2040 | P2: =IF(OR(J2="",K2="",L2="",M2=""),"",ROUND(K2*(J2*(M2-L2)/(1-J2*L2)),4)) -> 0.1503 | Q2: I_CVD_PRIMARY__C_SHARED | R2: shared-count-once | S2: Provisional | T2: OK (cascade trajectory) | U2: =COUNTIF($B$2:$B$7,B2) -> 1 | V2: =IF(U2=1,"OK","DUPLICATE KEY") -> OK
A3: I_CVD_PRIMARY | B3: I_CVD_PRIMARY__C_ICH | C3: Primary prevention of CVD | D3: C_ICH | E3: hstroke | F3: Intracerebral hemorrhage | G3: well | H3: sick | I3: incidence | J3: 0.49 | K3: 0.8 | L3: 0.11376686 | M3: 0.4165 | N3: 2025 | O3: 2040 | P3: =IF(OR(J3="",K3="",L3="",M3=""),"",ROUND(K3*(J3*(M3-L3)/(1-J3*L3)),4)) -> 0.1257 | Q3: I_CVD_PRIMARY__C_SHARED | R3: shared-count-once | S3: Provisional | T3: OK (cascade trajectory) | U3: =COUNTIF($B$2:$B$7,B3) -> 1 | V3: =IF(U3=1,"OK","DUPLICATE KEY") -> OK
A4: I_CVD_PRIMARY | B4: I_CVD_PRIMARY__C_IHD | C4: Primary prevention of CVD | D4: C_IHD | E4: ihd | F4: Ischemic heart disease | G4: well | H4: sick | I4: incidence | J4: 0.58 | K4: 0.8 | L4: 0.11376686 | M4: 0.4165 | N4: 2025 | O4: 2040 | P4: =IF(OR(J4="",K4="",L4="",M4=""),"",ROUND(K4*(J4*(M4-L4)/(1-J4*L4)),4)) -> 0.1504 | Q4: I_CVD_PRIMARY__C_SHARED | R4: shared-count-once | S4: Provisional | T4: OK (cascade trajectory) | U4: =COUNTIF($B$2:$B$7,B4) -> 1 | V4: =IF(U4=1,"OK","DUPLICATE KEY") -> OK
A5: I_CVD_PRIMARY | B5: I_CVD_PRIMARY__C_IS | C5: Primary prevention of CVD | D5: C_IS | E5: istroke | F5: Ischemic stroke | G5: well | H5: sick | I5: incidence | J5: 0.54 | K5: 0.8 | L5: 0.11376686 | M5: 0.4165 | N5: 2025 | O5: 2040 | P5: =IF(OR(J5="",K5="",L5="",M5=""),"",ROUND(K5*(J5*(M5-L5)/(1-J5*L5)),4)) -> 0.1393 | Q5: I_CVD_PRIMARY__C_SHARED | R5: shared-count-once | S5: Provisional | T5: OK (cascade trajectory) | U5: =COUNTIF($B$2:$B$7,B5) -> 1 | V5: =IF(U5=1,"OK","DUPLICATE KEY") -> OK
A6: I_T2D_TREATMENT | B6: I_T2D_TREATMENT__C_T2D | C6: Longitudinal treatment of type 2 diabetes | D6: C_T2D | E6: dm2 | F6: Type 2 diabetes | G6: sick | H6: dead_t2d | I6: case_fatality | J6: 0.28 | K6: 1 | L6: 0.14791461 | M6: 0.4165 | N6: 2025 | O6: 2040 | P6: =IF(OR(J6="",K6="",L6="",M6=""),"",ROUND(K6*(J6*(M6-L6)/(1-J6*L6)),4)) -> 0.0785 | Q6: I_T2D_TREATMENT__C_T2D | R6: cause-specific | S6: Provisional | T6: OK (cascade trajectory) | U6: =COUNTIF($B$2:$B$7,B6) -> 1 | V6: =IF(U6=1,"OK","DUPLICATE KEY") -> OK
A7: I_T2D_TREATMENT | B7: I_T2D_TREATMENT__C_IHD | C7: Longitudinal treatment of type 2 diabetes | D7: C_IHD | E7: ihd | F7: Ischemic heart disease | G7: sick | H7: dead_ihd | I7: case_fatality | J7: 0.15 | K7: 0.15 | L7: 0.14791461 | M7: 0.4165 | N7: 2025 | O7: 2040 | P7: =IF(OR(J7="",K7="",L7="",M7=""),"",ROUND(K7*(J7*(M7-L7)/(1-J7*L7)),4)) -> 0.0062 | Q7: I_T2D_TREATMENT__C_T2D | R7: shared-count-once | S7: Review | T7: OK (cascade trajectory) | U7: =COUNTIF($B$2:$B$7,B7) -> 1 | V7: =IF(U7=1,"OK","DUPLICATE KEY") -> OK

Sheet Cost_Components
A1: cost_record_id | B1: cost_component_key | C1: cost_option | D1: intervention_id | E1: cause_id | F1: cause_code | G1: cost_join_key | H1: cost_scope | I1: cost_component | J1: population_in_need_measure | K1: population_in_need_fraction | L1: frequency_per_year | M1: c_age_start | N1: c_age_stop | O1: c_sex | P1: unit_cost_usd | Q1: price_year | R1: indonesia_adjusted_flag | S1: cov_baseline | T1: cov_target | U1: cov_start_year | V1: cov_target_year | W1: cost_review | X1: cost_ready
A2: COST_PRIMARY_TX_A | B2: CC_PRIMARY_HTN_STATIN | C2: Option A (selected) | D2: I_CVD_PRIMARY | E2: C_SHARED | G2: I_CVD_PRIMARY__C_SHARED | H2: shared-count-once | I2: Antihypertensives and statins for absolute CVD risk >20% | J2: all | K2: 0.06 | L2: 1 | M2: 30 | N2: 95 | O2: Both | P2: 22.2296 | Q2: 2023 | R2: 1 | S2: =IFERROR(INDEX(Selected_Interventions!$L$2:$L$7,MATCH(G2,Selected_Interventions!$Q$2:$Q$7,0)),"") -> 0.11376686 | T2: =IFERROR(INDEX(Selected_Interventions!$M$2:$M$7,MATCH(G2,Selected_Interventions!$Q$2:$Q$7,0)),"") -> 0.4165 | U2: =IFERROR(INDEX(Selected_Interventions!$N$2:$N$7,MATCH(G2,Selected_Interventions!$Q$2:$Q$7,0)),"") -> 2025 | V2: =IFERROR(INDEX(Selected_Interventions!$O$2:$O$7,MATCH(G2,Selected_Interventions!$Q$2:$Q$7,0)),"") -> 2040 | W2: Review | X2: =IF(AND(P2<>"",P2>=0,S2<>"",K2<>"",K2>=0,K2<=1,OR(J2="all",J2="prevalence",J2="incidence")),1,0) -> 1
A3: COST_PRIMARY_SCREEN_A | B3: CC_PRIMARY_SCREENING | C3: Option A (selected) | D3: I_CVD_PRIMARY | E3: C_SHARED | G3: I_CVD_PRIMARY__C_SHARED | H3: shared-count-once | I3: CVD targeted screening | J3: all | K3: 0.2 | L3: 1 | M3: 30 | N3: 95 | O3: Both | P3: 1.291584 | Q3: 2023 | R3: 1 | S3: =IFERROR(INDEX(Selected_Interventions!$L$2:$L$7,MATCH(G3,Selected_Interventions!$Q$2:$Q$7,0)),"") -> 0.11376686 | T3: =IFERROR(INDEX(Selected_Interventions!$M$2:$M$7,MATCH(G3,Selected_Interventions!$Q$2:$Q$7,0)),"") -> 0.4165 | U3: =IFERROR(INDEX(Selected_Interventions!$N$2:$N$7,MATCH(G3,Selected_Interventions!$Q$2:$Q$7,0)),"") -> 2025 | V3: =IFERROR(INDEX(Selected_Interventions!$O$2:$O$7,MATCH(G3,Selected_Interventions!$Q$2:$Q$7,0)),"") -> 2040 | W3: Review | X3: =IF(AND(P3<>"",P3>=0,S3<>"",K3<>"",K3>=0,K3<=1,OR(J3="all",J3="prevalence",J3="incidence")),1,0) -> 1
A4: COST_T2D_INSULIN | B4: CC_T2D_INSULIN | C4: Base | D4: I_T2D_TREATMENT | E4: C_T2D | F4: dm2 | G4: I_T2D_TREATMENT__C_T2D | H4: cause-specific | I4: Diabetes management, insulin dependent | J4: prevalence | K4: 0.2 | L4: 1 | M4: 30 | N4: 95 | O4: Both | P4: 1154.0355 | Q4: 2023 | R4: 1 | S4: =IFERROR(INDEX(Selected_Interventions!$L$2:$L$7,MATCH(G4,Selected_Interventions!$Q$2:$Q$7,0)),"") -> 0.14791461 | T4: =IFERROR(INDEX(Selected_Interventions!$M$2:$M$7,MATCH(G4,Selected_Interventions!$Q$2:$Q$7,0)),"") -> 0.4165 | U4: =IFERROR(INDEX(Selected_Interventions!$N$2:$N$7,MATCH(G4,Selected_Interventions!$Q$2:$Q$7,0)),"") -> 2025 | V4: =IFERROR(INDEX(Selected_Interventions!$O$2:$O$7,MATCH(G4,Selected_Interventions!$Q$2:$Q$7,0)),"") -> 2040 | W4: Ready | X4: =IF(AND(P4<>"",P4>=0,S4<>"",K4<>"",K4>=0,K4<=1,OR(J4="all",J4="prevalence",J4="incidence")),1,0) -> 1
A5: COST_T2D_NONINSULIN | B5: CC_T2D_NONINSULIN | C5: Base | D5: I_T2D_TREATMENT | E5: C_T2D | F5: dm2 | G5: I_T2D_TREATMENT__C_T2D | H5: cause-specific | I5: Diabetes management, non insulin dependent | J5: prevalence | K5: 0.6 | L5: 1 | M5: 30 | N5: 95 | O5: Both | P5: 752.57623 | Q5: 2023 | R5: 1 | S5: =IFERROR(INDEX(Selected_Interventions!$L$2:$L$7,MATCH(G5,Selected_Interventions!$Q$2:$Q$7,0)),"") -> 0.14791461 | T5: =IFERROR(INDEX(Selected_Interventions!$M$2:$M$7,MATCH(G5,Selected_Interventions!$Q$2:$Q$7,0)),"") -> 0.4165 | U5: =IFERROR(INDEX(Selected_Interventions!$N$2:$N$7,MATCH(G5,Selected_Interventions!$Q$2:$Q$7,0)),"") -> 2025 | V5: =IFERROR(INDEX(Selected_Interventions!$O$2:$O$7,MATCH(G5,Selected_Interventions!$Q$2:$Q$7,0)),"") -> 2040 | W5: Ready | X5: =IF(AND(P5<>"",P5>=0,S5<>"",K5<>"",K5>=0,K5<=1,OR(J5="all",J5="prevalence",J5="incidence")),1,0) -> 1
A6: COST_T2D_SCREEN | B6: CC_T2D_SCREENING | C6: Base | D6: I_T2D_TREATMENT | E6: C_T2D | F6: dm2 | G6: I_T2D_TREATMENT__C_T2D | H6: cause-specific | I6: Diabetes opportunistic screening | J6: all | K6: 0.2 | L6: 1 | M6: 30 | N6: 95 | O6: Both | P6: 0.70495848 | Q6: 2023 | R6: 1 | S6: =IFERROR(INDEX(Selected_Interventions!$L$2:$L$7,MATCH(G6,Selected_Interventions!$Q$2:$Q$7,0)),"") -> 0.14791461 | T6: =IFERROR(INDEX(Selected_Interventions!$M$2:$M$7,MATCH(G6,Selected_Interventions!$Q$2:$Q$7,0)),"") -> 0.4165 | U6: =IFERROR(INDEX(Selected_Interventions!$N$2:$N$7,MATCH(G6,Selected_Interventions!$Q$2:$Q$7,0)),"") -> 2025 | V6: =IFERROR(INDEX(Selected_Interventions!$O$2:$O$7,MATCH(G6,Selected_Interventions!$Q$2:$Q$7,0)),"") -> 2040 | W6: Ready | X6: =IF(AND(P6<>"",P6>=0,S6<>"",K6<>"",K6>=0,K6<=1,OR(J6="all",J6="prevalence",J6="incidence")),1,0) -> 1

Sheet Annual_Mortality
A1: scenario | B1: scenario_label | C1: year | D1: cause | E1: cases | F1: cause_deaths | G1: base_deaths | H1: deaths_averted | I1: base_cases | J1: cases_averted
A2: S_70_30_30_TO_70_70_70 | B2: 70-30-30 -> 70-70-70 hypertension/cholesterol + diabetes cascade | C2: 2025 | D2: cmd | E2: 8428.906 | F2: 9668.8228 | G2: 9668.8228 | H2: =G2-F2 -> 0 | I2: 8428.906 | J2: =I2-E2 -> 0
A3: S_70_30_30_TO_70_70_70 | B3: 70-30-30 -> 70-70-70 hypertension/cholesterol + diabetes cascade | C3: 2025 | D3: dm2 | E3: 479897.33 | F3: 159105.61 | G3: 159105.61 | H3: =G3-F3 -> 0 | I3: 479897.33 | J3: =I3-E3 -> 0
A4: S_70_30_30_TO_70_70_70 | B4: 70-30-30 -> 70-70-70 hypertension/cholesterol + diabetes cascade | C4: 2025 | D4: hhd | E4: 76355.817 | F4: 63094.531 | G4: 63094.531 | H4: =G4-F4 -> 0 | I4: 76355.817 | J4: =I4-E4 -> 0
A5: S_70_30_30_TO_70_70_70 | B5: 70-30-30 -> 70-70-70 hypertension/cholesterol + diabetes cascade | C5: 2025 | D5: hstroke | E5: 207904.95 | F5: 240064.29 | G5: 240064.29 | H5: =G5-F5 -> 0 | I5: 207904.95 | J5: =I5-E5 -> 0
A6: S_70_30_30_TO_70_70_70 | B6: 70-30-30 -> 70-70-70 hypertension/cholesterol + diabetes cascade | C6: 2025 | D6: ihd | E6: 306292.01 | F6: 368786.79 | G6: 368786.79 | H6: =G6-F6 -> 0 | I6: 306292.01 | J6: =I6-E6 -> 0
A7: S_70_30_30_TO_70_70_70 | B7: 70-30-30 -> 70-70-70 hypertension/cholesterol + diabetes cascade | C7: 2025 | D7: istroke | E7: 197300.31 | F7: 222132.33 | G7: 222132.33 | H7: =G7-F7 -> 0 | I7: 197300.31 | J7: =I7-E7 -> 0
A8: S_70_30_30_TO_70_70_70 | B8: 70-30-30 -> 70-70-70 hypertension/cholesterol + diabetes cascade | C8: 2025 | D8: rhd | E8: 34256.139 | F8: 4628.4589 | G8: 4628.4589 | H8: =G8-F8 -> 0 | I8: 34256.139 | J8: =I8-E8 -> 0
A9: S_70_30_30_TO_70_70_70 | B9: 70-30-30 -> 70-70-70 hypertension/cholesterol + diabetes cascade | C9: 2026 | D9: cmd | E9: 8487.1725 | F9: 8630.3167 | G9: 8630.3167 | H9: =G9-F9 -> 0 | I9: 8487.1725 | J9: =I9-E9 -> 0
A10: S_70_30_30_TO_70_70_70 | B10: 70-30-30 -> 70-70-70 hypertension/cholesterol + diabetes cascade | C10: 2026 | D10: dm2 | E10: 487916.82 | F10: 158982.03 | G10: 159012.29 | H10: =G10-F10 -> 30.264394 | I10: 487916.82 | J10: =I10-E10 -> 0
A11: S_70_30_30_TO_70_70_70 | B11: 70-30-30 -> 70-70-70 hypertension/cholesterol + diabetes cascade | C11: 2026 | D11: hhd | E11: 77731.461 | F11: 59835.223 | G11: 59835.223 | H11: =G11-F11 -> 0 | I11: 77888.093 | J11: =I11-E11 -> 156.63199
A12: S_70_30_30_TO_70_70_70 | B12: 70-30-30 -> 70-70-70 hypertension/cholesterol + diabetes cascade | C12: 2026 | D12: hstroke | E12: 211661.78 | F12: 217295.45 | G12: 217295.45 | H12: =G12-F12 -> 0 | I12: 212035.13 | J12: =I12-E12 -> 373.34704
A13: S_70_30_30_TO_70_70_70 | B13: 70-30-30 -> 70-70-70 hypertension/cholesterol + diabetes cascade | C13: 2026 | D13: ihd | E13: 312510.74 | F13: 341944.06 | G13: 341949.4 | H13: =G13-F13 -> 5.3434396 | I13: 313184.01 | J13: =I13-E13 -> 673.26756
... A365: baseline | B365: Baseline (no new intervention) | C365: 2050 | D365: rhd | E365: 33050.354 | F365: 3414.3732 | G365: 3414.3732 | H365: =G365-F365 -> 0 | I365: 33050.354 | J365: =I365-E365 -> 0

Sheet Health_Outcomes
A1: scenario | B1: scenario_label | C1: year | D1: modeled_deaths | E1: baseline_deaths | F1: deaths_averted | G1: modeled_cases | H1: baseline_cases | I1: cases_averted | J1: yll | K1: base_yll | L1: yll_averted | M1: yld | N1: base_yld | O1: yld_averted | P1: daly | Q1: base_daly | R1: dalys_averted | S1: life_years_gained
A2: S_70_30_30_TO_70_70_70 | B2: 70-30-30 -> 70-70-70 hypertension/cholesterol + diabetes cascade | C2: 2025 | D2: 1067480.8 | E2: 1067480.8 | F2: =E2-D2 -> 0 | G2: 1310435.5 | H2: 1310435.5 | I2: =H2-G2 -> 0 | J2: 13787600 | K2: 13787600 | L2: =K2-J2 -> 0 | M2: 2532778.1 | N2: 2532778.1 | O2: =N2-M2 -> 0 | P2: 16320378 | Q2: 16320378 | R2: =Q2-P2 -> 0 | S2: =L2 -> 0
A3: S_70_30_30_TO_70_70_70 | B3: 70-30-30 -> 70-70-70 hypertension/cholesterol + diabetes cascade | C3: 2026 | D3: 988228.4 | E3: 988264.01 | F3: =E3-D3 -> 35.607834 | G3: 1333917.2 | H3: 1335499.8 | I3: =H3-G3 -> 1582.5916 | J3: 13277788 | K3: 13278266 | L3: =K3-J3 -> 478.73259 | M3: 2502931.9 | N3: 2503113.8 | O3: =N3-M3 -> 181.92052 | P3: 15780720 | Q3: 15781380 | R3: =Q3-P3 -> 660.65311 | S3: =L3 -> 478.73259
A4: S_70_30_30_TO_70_70_70 | B4: 70-30-30 -> 70-70-70 hypertension/cholesterol + diabetes cascade | C4: 2027 | D4: 949264.03 | E4: 949562.22 | F4: =E4-D4 -> 298.18274 | G4: 1359906.5 | H4: 1363154.3 | I4: =H4-G4 -> 3247.834 | J4: 12987806 | K4: 12992035 | L4: =K4-J4 -> 4229.0226 | M4: 2482891.1 | N4: 2483407.1 | O4: =N4-M4 -> 515.95624 | P4: 15470697 | Q4: 15475442 | R4: =Q4-P4 -> 4744.9789 | S4: =L4 -> 4229.0226
A5: S_70_30_30_TO_70_70_70 | B5: 70-30-30 -> 70-70-70 hypertension/cholesterol + diabetes cascade | C5: 2028 | D5: 926448.71 | E5: 927155.13 | F5: =E5-D5 -> 706.42037 | G5: 1387213.5 | H5: 1392211.2 | I5: =H5-G5 -> 4997.7491 | J5: 12802365 | K5: 12812694 | L5: =K5-J5 -> 10328.318 | M5: 2469844.7 | N5: 2470833.6 | O5: =N5-M5 -> 988.85715 | P5: 15272210 | Q5: 15283527 | R5: =Q5-P5 -> 11317.175 | S5: =L5 -> 10328.318
A6: S_70_30_30_TO_70_70_70 | B6: 70-30-30 -> 70-70-70 hypertension/cholesterol + diabetes cascade | C6: 2029 | D6: 913539.82 | E6: 914778.28 | F6: =E6-D6 -> 1238.4598 | G6: 1415376.7 | H6: 1422211.3 | I6: =H6-G6 -> 6834.6045 | J6: 12696432 | K6: 12714850 | L6: =K6-J6 -> 18417.507 | M6: 2462110.4 | N6: 2463702.1 | O6: =N6-M6 -> 1591.7739 | P6: 15158542 | Q6: 15178552 | R6: =Q6-P6 -> 20009.281 | S6: =L6 -> 18417.507
A7: S_70_30_30_TO_70_70_70 | B7: 70-30-30 -> 70-70-70 hypertension/cholesterol + diabetes cascade | C7: 2030 | D7: 907172.06 | E7: 909052.97 | F7: =E7-D7 -> 1880.9183 | G7: 1444111.1 | H7: 1452871.1 | I7: =H7-G7 -> 8760.0221 | J7: 12636399 | K7: 12664641 | L7: =K7-J7 -> 28241.963 | M7: 2458567.2 | N7: 2460885.7 | O7: =N7-M7 -> 2318.4214 | P7: 15094966 | Q7: 15125527 | R7: =Q7-P7 -> 30560.385 | S7: =L7 -> 28241.963
A8: S_70_30_30_TO_70_70_70 | B8: 70-30-30 -> 70-70-70 hypertension/cholesterol + diabetes cascade | C8: 2031 | D8: 902972.53 | E8: 907044.24 | F8: =E8-D8 -> 4071.7085 | G8: 1464851.5 | H8: 1483835.4 | I8: =H8-G8 -> 18983.872 | J8: 12598180 | K8: 12656050 | L8: =K8-J8 -> 57869.036 | M8: 2457757.4 | N8: 2461774.3 | O8: =N8-M8 -> 4016.8844 | P8: 15055938 | Q8: 15117824 | R8: =Q8-P8 -> 61885.92 | S8: =L8 -> 57869.036
A9: S_70_30_30_TO_70_70_70 | B9: 70-30-30 -> 70-70-70 hypertension/cholesterol + diabetes cascade | C9: 2032 | D9: 901420.28 | E9: 908870.88 | F9: =E9-D9 -> 7450.5935 | G9: 1485232.9 | H9: 1514938.3 | I9: =H9-G9 -> 29705.409 | J9: 12572523 | K9: 12676617 | L9: =K9-J9 -> 104094.46 | M9: 2459146.6 | N9: 2465693.1 | O9: =N9-M9 -> 6546.5329 | P9: 15031669 | Q9: 15142310 | R9: =Q9-P9 -> 110640.99 | S9: =L9 -> 104094.46
A10: S_70_30_30_TO_70_70_70 | B10: 70-30-30 -> 70-70-70 hypertension/cholesterol + diabetes cascade | C10: 2033 | D10: 901875.45 | E10: 913563.02 | F10: =E10-D10 -> 11687.569 | G10: 1505164.2 | H10: 1546062.3 | I10: =H10-G10 -> 40898.109 | J10: 12555272 | K10: 12718240 | L10: =K10-J10 -> 162967.44 | M10: 2462306.4 | N10: 2472136.3 | O10: =N10-M10 -> 9829.9476 | P10: 15017579 | Q10: 15190376 | R10: =Q10-P10 -> 172797.39 | S10: =L10 -> 162967.44
A11: S_70_30_30_TO_70_70_70 | B11: 70-30-30 -> 70-70-70 hypertension/cholesterol + diabetes cascade | C11: 2034 | D11: 904062.59 | E11: 920723.39 | F11: =E11-D11 -> 16660.797 | G11: 1524865.1 | H11: 1577410.5 | I11: =H11-G11 -> 52545.428 | J11: 12560562 | K11: 12793363 | L11: =K11-J11 -> 232801.26 | M11: 2466903.6 | N11: 2480715.2 | O11: =N11-M11 -> 13811.612 | P11: 15027466 | Q11: 15274079 | R11: =Q11-P11 -> 246612.87 | S11: =L11 -> 232801.26
A12: S_70_30_30_TO_70_70_70 | B12: 70-30-30 -> 70-70-70 hypertension/cholesterol + diabetes cascade | C12: 2035 | D12: 907779.26 | E12: 930075.42 | F12: =E12-D12 -> 22296.163 | G12: 1544452.3 | H12: 1609084.4 | I12: =H12-G12 -> 64632.029 | J12: 12572880 | K12: 12885098 | L12: =K12-J12 -> 312217.85 | M12: 2472636.6 | N12: 2491084.7 | O12: =N12-M12 -> 18448.107 | P12: 15045516 | Q12: 15376182 | R12: =Q12-P12 -> 330665.95 | S12: =L12 -> 312217.85
A13: S_70_30_30_TO_70_70_70 | B13: 70-30-30 -> 70-70-70 hypertension/cholesterol + diabetes cascade | C13: 2036 | D13: 913082.2 | E13: 941635.34 | F13: =E13-D13 -> 28553.139 | G13: 1563949.1 | H13: 1641090.6 | I13: =H13-G13 -> 77141.587 | J13: 12593721 | K13: 12994091 | L13: =K13-J13 -> 400370.5 | M13: 2479196.3 | N13: 2502898 | O13: =N13-M13 -> 23701.706 | P13: 15072917 | Q13: 15496989 | R13: =Q13-P13 -> 424072.21 | S13: =L13 -> 400370.5
... A27: S_70_30_30_TO_70_70_70 | B27: 70-30-30 -> 70-70-70 hypertension/cholesterol + diabetes cascade | C27: 2050 | D27: 1091622.8 | E27: 1189997.7 | F27: =E27-D27 -> 98374.925 | G27: 1951392.3 | H27: 2089872.9 | I27: =H27-G27 -> 138480.64 | J27: 13708939 | K27: 15111483 | L27: =K27-J27 -> 1402543.5 | M27: 2642063.5 | N27: 2736683.5 | O27: =N27-M27 -> 94620.016 | P27: 16351003 | Q27: 17848166 | R27: =Q27-P27 -> 1497163.5 | S27: =L27 -> 1402543.5

Sheet CVD_40q30
A1: location | B1: scenario | C1: scenario_label | D1: intervention_family | E1: scenario_role | F1: parent_package_id | G1: htn_target_scenario | H1: year | I1: cvd_40q30 | J1: baseline_cvd_40q30 | K1: absolute_reduction_pp | L1: percent_reduction | M1: cvd_40q30_r | N1: recon_status
A2: Indonesia | B2: S_70_30_30_TO_70_70_70 | C2: 70-30-30 -> 70-70-70 hypertension/cholesterol + diabetes cascade | D2: cascade_70_30_30_to_70_70_70 | E2: combined | G2: htncov2_aspirational | H2: 2025 | I2: =100*(1-(SUMIFS(CVD_40q30_Age!$M$2:$M$2081,CVD_40q30_Age!$A$2:$A$2081,A2,CVD_40q30_Age!$B$2:$B$2081,B2,CVD_40q30_Age!$E$2:$E$2081,G2,CVD_40q30_Age!$F$2:$F$2081,H2,CVD_40q30_Age!$G$2:$G$2081,69))/(SUMIFS(CVD_40q30_Age!$L$2:$L$2081,CVD_40q30_Age!$A$2:$A$2081,A2,CVD_40q30_Age!$B$2:$B$2081,B2,CVD_40q30_Age!$E$2:$E$2081,G2,CVD_40q30_Age!$F$2:$F$2081,H2,CVD_40q30_Age!$G$2:$G$2081,30))) -> 14.504478 | J2: =SUMIFS($I$2:$I$53,$A$2:$A$53,A2,$G$2:$G$53,G2,$H$2:$H$53,H2,$B$2:$B$53,"baseline") -> 14.504478 | K2: =J2-I2 -> 0 | L2: =IF(J2=0,"",100*(J2-I2)/J2) -> 0 | M2: 14.504478 | N2: =IF(ABS(I2-M2)<=0.001,"match","mismatch") -> match
A3: Indonesia | B3: S_70_30_30_TO_70_70_70 | C3: 70-30-30 -> 70-70-70 hypertension/cholesterol + diabetes cascade | D3: cascade_70_30_30_to_70_70_70 | E3: combined | G3: htncov2_aspirational | H3: 2026 | I3: =100*(1-(SUMIFS(CVD_40q30_Age!$M$2:$M$2081,CVD_40q30_Age!$A$2:$A$2081,A3,CVD_40q30_Age!$B$2:$B$2081,B3,CVD_40q30_Age!$E$2:$E$2081,G3,CVD_40q30_Age!$F$2:$F$2081,H3,CVD_40q30_Age!$G$2:$G$2081,69))/(SUMIFS(CVD_40q30_Age!$L$2:$L$2081,CVD_40q30_Age!$A$2:$A$2081,A3,CVD_40q30_Age!$B$2:$B$2081,B3,CVD_40q30_Age!$E$2:$E$2081,G3,CVD_40q30_Age!$F$2:$F$2081,H3,CVD_40q30_Age!$G$2:$G$2081,30))) -> 13.740436 | J3: =SUMIFS($I$2:$I$53,$A$2:$A$53,A3,$G$2:$G$53,G3,$H$2:$H$53,H3,$B$2:$B$53,"baseline") -> 13.740526 | K3: =J3-I3 -> 8.9519892e-05 | L3: =IF(J3=0,"",100*(J3-I3)/J3) -> 0.00065150267 | M3: 13.740436 | N3: =IF(ABS(I3-M3)<=0.001,"match","mismatch") -> match
A4: Indonesia | B4: S_70_30_30_TO_70_70_70 | C4: 70-30-30 -> 70-70-70 hypertension/cholesterol + diabetes cascade | D4: cascade_70_30_30_to_70_70_70 | E4: combined | G4: htncov2_aspirational | H4: 2027 | I4: =100*(1-(SUMIFS(CVD_40q30_Age!$M$2:$M$2081,CVD_40q30_Age!$A$2:$A$2081,A4,CVD_40q30_Age!$B$2:$B$2081,B4,CVD_40q30_Age!$E$2:$E$2081,G4,CVD_40q30_Age!$F$2:$F$2081,H4,CVD_40q30_Age!$G$2:$G$2081,69))/(SUMIFS(CVD_40q30_Age!$L$2:$L$2081,CVD_40q30_Age!$A$2:$A$2081,A4,CVD_40q30_Age!$B$2:$B$2081,B4,CVD_40q30_Age!$E$2:$E$2081,G4,CVD_40q30_Age!$F$2:$F$2081,H4,CVD_40q30_Age!$G$2:$G$2081,30))) -> 13.093748 | J4: =SUMIFS($I$2:$I$53,$A$2:$A$53,A4,$G$2:$G$53,G4,$H$2:$H$53,H4,$B$2:$B$53,"baseline") -> 13.098116 | K4: =J4-I4 -> 0.0043681399 | L4: =IF(J4=0,"",100*(J4-I4)/J4) -> 0.033349375 | M4: 13.093748 | N4: =IF(ABS(I4-M4)<=0.001,"match","mismatch") -> match
A5: Indonesia | B5: S_70_30_30_TO_70_70_70 | C5: 70-30-30 -> 70-70-70 hypertension/cholesterol + diabetes cascade | D5: cascade_70_30_30_to_70_70_70 | E5: combined | G5: htncov2_aspirational | H5: 2028 | I5: =100*(1-(SUMIFS(CVD_40q30_Age!$M$2:$M$2081,CVD_40q30_Age!$A$2:$A$2081,A5,CVD_40q30_Age!$B$2:$B$2081,B5,CVD_40q30_Age!$E$2:$E$2081,G5,CVD_40q30_Age!$F$2:$F$2081,H5,CVD_40q30_Age!$G$2:$G$2081,69))/(SUMIFS(CVD_40q30_Age!$L$2:$L$2081,CVD_40q30_Age!$A$2:$A$2081,A5,CVD_40q30_Age!$B$2:$B$2081,B5,CVD_40q30_Age!$E$2:$E$2081,G5,CVD_40q30_Age!$F$2:$F$2081,H5,CVD_40q30_Age!$G$2:$G$2081,30))) -> 12.551954 | J5: =SUMIFS($I$2:$I$53,$A$2:$A$53,A5,$G$2:$G$53,G5,$H$2:$H$53,H5,$B$2:$B$53,"baseline") -> 12.563551 | K5: =J5-I5 -> 0.011596595 | L5: =IF(J5=0,"",100*(J5-I5)/J5) -> 0.092303481 | M5: 12.551954 | N5: =IF(ABS(I5-M5)<=0.001,"match","mismatch") -> match
A6: Indonesia | B6: S_70_30_30_TO_70_70_70 | C6: 70-30-30 -> 70-70-70 hypertension/cholesterol + diabetes cascade | D6: cascade_70_30_30_to_70_70_70 | E6: combined | G6: htncov2_aspirational | H6: 2029 | I6: =100*(1-(SUMIFS(CVD_40q30_Age!$M$2:$M$2081,CVD_40q30_Age!$A$2:$A$2081,A6,CVD_40q30_Age!$B$2:$B$2081,B6,CVD_40q30_Age!$E$2:$E$2081,G6,CVD_40q30_Age!$F$2:$F$2081,H6,CVD_40q30_Age!$G$2:$G$2081,69))/(SUMIFS(CVD_40q30_Age!$L$2:$L$2081,CVD_40q30_Age!$A$2:$A$2081,A6,CVD_40q30_Age!$B$2:$B$2081,B6,CVD_40q30_Age!$E$2:$E$2081,G6,CVD_40q30_Age!$F$2:$F$2081,H6,CVD_40q30_Age!$G$2:$G$2081,30))) -> 12.09671 | J6: =SUMIFS($I$2:$I$53,$A$2:$A$53,A6,$G$2:$G$53,G6,$H$2:$H$53,H6,$B$2:$B$53,"baseline") -> 12.11775 | K6: =J6-I6 -> 0.021040036 | L6: =IF(J6=0,"",100*(J6-I6)/J6) -> 0.17362988 | M6: 12.09671 | N6: =IF(ABS(I6-M6)<=0.001,"match","mismatch") -> match
A7: Indonesia | B7: S_70_30_30_TO_70_70_70 | C7: 70-30-30 -> 70-70-70 hypertension/cholesterol + diabetes cascade | D7: cascade_70_30_30_to_70_70_70 | E7: combined | G7: htncov2_aspirational | H7: 2030 | I7: =100*(1-(SUMIFS(CVD_40q30_Age!$M$2:$M$2081,CVD_40q30_Age!$A$2:$A$2081,A7,CVD_40q30_Age!$B$2:$B$2081,B7,CVD_40q30_Age!$E$2:$E$2081,G7,CVD_40q30_Age!$F$2:$F$2081,H7,CVD_40q30_Age!$G$2:$G$2081,69))/(SUMIFS(CVD_40q30_Age!$L$2:$L$2081,CVD_40q30_Age!$A$2:$A$2081,A7,CVD_40q30_Age!$B$2:$B$2081,B7,CVD_40q30_Age!$E$2:$E$2081,G7,CVD_40q30_Age!$F$2:$F$2081,H7,CVD_40q30_Age!$G$2:$G$2081,30))) -> 11.714752 | J7: =SUMIFS($I$2:$I$53,$A$2:$A$53,A7,$G$2:$G$53,G7,$H$2:$H$53,H7,$B$2:$B$53,"baseline") -> 11.74693 | K7: =J7-I7 -> 0.032177915 | L7: =IF(J7=0,"",100*(J7-I7)/J7) -> 0.27392616 | M7: 11.714752 | N7: =IF(ABS(I7-M7)<=0.001,"match","mismatch") -> match
A8: Indonesia | B8: S_70_30_30_TO_70_70_70 | C8: 70-30-30 -> 70-70-70 hypertension/cholesterol + diabetes cascade | D8: cascade_70_30_30_to_70_70_70 | E8: combined | G8: htncov2_aspirational | H8: 2031 | I8: =100*(1-(SUMIFS(CVD_40q30_Age!$M$2:$M$2081,CVD_40q30_Age!$A$2:$A$2081,A8,CVD_40q30_Age!$B$2:$B$2081,B8,CVD_40q30_Age!$E$2:$E$2081,G8,CVD_40q30_Age!$F$2:$F$2081,H8,CVD_40q30_Age!$G$2:$G$2081,69))/(SUMIFS(CVD_40q30_Age!$L$2:$L$2081,CVD_40q30_Age!$A$2:$A$2081,A8,CVD_40q30_Age!$B$2:$B$2081,B8,CVD_40q30_Age!$E$2:$E$2081,G8,CVD_40q30_Age!$F$2:$F$2081,H8,CVD_40q30_Age!$G$2:$G$2081,30))) -> 11.365926 | J8: =SUMIFS($I$2:$I$53,$A$2:$A$53,A8,$G$2:$G$53,G8,$H$2:$H$53,H8,$B$2:$B$53,"baseline") -> 11.413097 | K8: =J8-I8 -> 0.047170649 | L8: =IF(J8=0,"",100*(J8-I8)/J8) -> 0.41330281 | M8: 11.365926 | N8: =IF(ABS(I8-M8)<=0.001,"match","mismatch") -> match
A9: Indonesia | B9: S_70_30_30_TO_70_70_70 | C9: 70-30-30 -> 70-70-70 hypertension/cholesterol + diabetes cascade | D9: cascade_70_30_30_to_70_70_70 | E9: combined | G9: htncov2_aspirational | H9: 2032 | I9: =100*(1-(SUMIFS(CVD_40q30_Age!$M$2:$M$2081,CVD_40q30_Age!$A$2:$A$2081,A9,CVD_40q30_Age!$B$2:$B$2081,B9,CVD_40q30_Age!$E$2:$E$2081,G9,CVD_40q30_Age!$F$2:$F$2081,H9,CVD_40q30_Age!$G$2:$G$2081,69))/(SUMIFS(CVD_40q30_Age!$L$2:$L$2081,CVD_40q30_Age!$A$2:$A$2081,A9,CVD_40q30_Age!$B$2:$B$2081,B9,CVD_40q30_Age!$E$2:$E$2081,G9,CVD_40q30_Age!$F$2:$F$2081,H9,CVD_40q30_Age!$G$2:$G$2081,30))) -> 11.035675 | J9: =SUMIFS($I$2:$I$53,$A$2:$A$53,A9,$G$2:$G$53,G9,$H$2:$H$53,H9,$B$2:$B$53,"baseline") -> 11.115398 | K9: =J9-I9 -> 0.079723741 | L9: =IF(J9=0,"",100*(J9-I9)/J9) -> 0.71723691 | M9: 11.035675 | N9: =IF(ABS(I9-M9)<=0.001,"match","mismatch") -> match
A10: Indonesia | B10: S_70_30_30_TO_70_70_70 | C10: 70-30-30 -> 70-70-70 hypertension/cholesterol + diabetes cascade | D10: cascade_70_30_30_to_70_70_70 | E10: combined | G10: htncov2_aspirational | H10: 2033 | I10: =100*(1-(SUMIFS(CVD_40q30_Age!$M$2:$M$2081,CVD_40q30_Age!$A$2:$A$2081,A10,CVD_40q30_Age!$B$2:$B$2081,B10,CVD_40q30_Age!$E$2:$E$2081,G10,CVD_40q30_Age!$F$2:$F$2081,H10,CVD_40q30_Age!$G$2:$G$2081,69))/(SUMIFS(CVD_40q30_Age!$L$2:$L$2081,CVD_40q30_Age!$A$2:$A$2081,A10,CVD_40q30_Age!$B$2:$B$2081,B10,CVD_40q30_Age!$E$2:$E$2081,G10,CVD_40q30_Age!$F$2:$F$2081,H10,CVD_40q30_Age!$G$2:$G$2081,30))) -> 10.726589 | J10: =SUMIFS($I$2:$I$53,$A$2:$A$53,A10,$G$2:$G$53,G10,$H$2:$H$53,H10,$B$2:$B$53,"baseline") -> 10.851472 | K10: =J10-I10 -> 0.1248834 | L10: =IF(J10=0,"",100*(J10-I10)/J10) -> 1.1508429 | M10: 10.726589 | N10: =IF(ABS(I10-M10)<=0.001,"match","mismatch") -> match
A11: Indonesia | B11: S_70_30_30_TO_70_70_70 | C11: 70-30-30 -> 70-70-70 hypertension/cholesterol + diabetes cascade | D11: cascade_70_30_30_to_70_70_70 | E11: combined | G11: htncov2_aspirational | H11: 2034 | I11: =100*(1-(SUMIFS(CVD_40q30_Age!$M$2:$M$2081,CVD_40q30_Age!$A$2:$A$2081,A11,CVD_40q30_Age!$B$2:$B$2081,B11,CVD_40q30_Age!$E$2:$E$2081,G11,CVD_40q30_Age!$F$2:$F$2081,H11,CVD_40q30_Age!$G$2:$G$2081,69))/(SUMIFS(CVD_40q30_Age!$L$2:$L$2081,CVD_40q30_Age!$A$2:$A$2081,A11,CVD_40q30_Age!$B$2:$B$2081,B11,CVD_40q30_Age!$E$2:$E$2081,G11,CVD_40q30_Age!$F$2:$F$2081,H11,CVD_40q30_Age!$G$2:$G$2081,30))) -> 10.446096 | J11: =SUMIFS($I$2:$I$53,$A$2:$A$53,A11,$G$2:$G$53,G11,$H$2:$H$53,H11,$B$2:$B$53,"baseline") -> 10.625758 | K11: =J11-I11 -> 0.17966279 | L11: =IF(J11=0,"",100*(J11-I11)/J11) -> 1.6908232 | M11: 10.446096 | N11: =IF(ABS(I11-M11)<=0.001,"match","mismatch") -> match
A12: Indonesia | B12: S_70_30_30_TO_70_70_70 | C12: 70-30-30 -> 70-70-70 hypertension/cholesterol + diabetes cascade | D12: cascade_70_30_30_to_70_70_70 | E12: combined | G12: htncov2_aspirational | H12: 2035 | I12: =100*(1-(SUMIFS(CVD_40q30_Age!$M$2:$M$2081,CVD_40q30_Age!$A$2:$A$2081,A12,CVD_40q30_Age!$B$2:$B$2081,B12,CVD_40q30_Age!$E$2:$E$2081,G12,CVD_40q30_Age!$F$2:$F$2081,H12,CVD_40q30_Age!$G$2:$G$2081,69))/(SUMIFS(CVD_40q30_Age!$L$2:$L$2081,CVD_40q30_Age!$A$2:$A$2081,A12,CVD_40q30_Age!$B$2:$B$2081,B12,CVD_40q30_Age!$E$2:$E$2081,G12,CVD_40q30_Age!$F$2:$F$2081,H12,CVD_40q30_Age!$G$2:$G$2081,30))) -> 10.189223 | J12: =SUMIFS($I$2:$I$53,$A$2:$A$53,A12,$G$2:$G$53,G12,$H$2:$H$53,H12,$B$2:$B$53,"baseline") -> 10.431088 | K12: =J12-I12 -> 0.24186518 | L12: =IF(J12=0,"",100*(J12-I12)/J12) -> 2.3186956 | M12: 10.189223 | N12: =IF(ABS(I12-M12)<=0.001,"match","mismatch") -> match
A13: Indonesia | B13: S_70_30_30_TO_70_70_70 | C13: 70-30-30 -> 70-70-70 hypertension/cholesterol + diabetes cascade | D13: cascade_70_30_30_to_70_70_70 | E13: combined | G13: htncov2_aspirational | H13: 2036 | I13: =100*(1-(SUMIFS(CVD_40q30_Age!$M$2:$M$2081,CVD_40q30_Age!$A$2:$A$2081,A13,CVD_40q30_Age!$B$2:$B$2081,B13,CVD_40q30_Age!$E$2:$E$2081,G13,CVD_40q30_Age!$F$2:$F$2081,H13,CVD_40q30_Age!$G$2:$G$2081,69))/(SUMIFS(CVD_40q30_Age!$L$2:$L$2081,CVD_40q30_Age!$A$2:$A$2081,A13,CVD_40q30_Age!$B$2:$B$2081,B13,CVD_40q30_Age!$E$2:$E$2081,G13,CVD_40q30_Age!$F$2:$F$2081,H13,CVD_40q30_Age!$G$2:$G$2081,30))) -> 9.9563929 | J13: =SUMIFS($I$2:$I$53,$A$2:$A$53,A13,$G$2:$G$53,G13,$H$2:$H$53,H13,$B$2:$B$53,"baseline") -> 10.266493 | K13: =J13-I13 -> 0.3101001 | L13: =IF(J13=0,"",100*(J13-I13)/J13) -> 3.0205066 | M13: 9.9563929 | N13: =IF(ABS(I13-M13)<=0.001,"match","mismatch") -> match
... A27: Indonesia | B27: S_70_30_30_TO_70_70_70 | C27: 70-30-30 -> 70-70-70 hypertension/cholesterol + diabetes cascade | D27: cascade_70_30_30_to_70_70_70 | E27: combined | G27: htncov2_aspirational | H27: 2050 | I27: =100*(1-(SUMIFS(CVD_40q30_Age!$M$2:$M$2081,CVD_40q30_Age!$A$2:$A$2081,A27,CVD_40q30_Age!$B$2:$B$2081,B27,CVD_40q30_Age!$E$2:$E$2081,G27,CVD_40q30_Age!$F$2:$F$2081,H27,CVD_40q30_Age!$G$2:$G$2081,69))/(SUMIFS(CVD_40q30_Age!$L$2:$L$2081,CVD_40q30_Age!$A$2:$A$2081,A27,CVD_40q30_Age!$B$2:$B$2081,B27,CVD_40q30_Age!$E$2:$E$2081,G27,CVD_40q30_Age!$F$2:$F$2081,H27,CVD_40q30_Age!$G$2:$G$2081,30))) -> 8.0775538 | J27: =SUMIFS($I$2:$I$53,$A$2:$A$53,A27,$G$2:$G$53,G27,$H$2:$H$53,H27,$B$2:$B$53,"baseline") -> 9.0836246 | K27: =J27-I27 -> 1.0060709 | L27: =IF(J27=0,"",100*(J27-I27)/J27) -> 11.075654 | M27: 8.0775538 | N27: =IF(ABS(I27-M27)<=0.001,"match","mismatch") -> match
A28: Indonesia | B28: baseline | C28: Baseline (no new intervention) | D28: baseline | G28: htncov2_aspirational | H28: 2025 | I28: =100*(1-(SUMIFS(CVD_40q30_Age!$M$2:$M$2081,CVD_40q30_Age!$A$2:$A$2081,A28,CVD_40q30_Age!$B$2:$B$2081,B28,CVD_40q30_Age!$E$2:$E$2081,G28,CVD_40q30_Age!$F$2:$F$2081,H28,CVD_40q30_Age!$G$2:$G$2081,69))/(SUMIFS(CVD_40q30_Age!$L$2:$L$2081,CVD_40q30_Age!$A$2:$A$2081,A28,CVD_40q30_Age!$B$2:$B$2081,B28,CVD_40q30_Age!$E$2:$E$2081,G28,CVD_40q30_Age!$F$2:$F$2081,H28,CVD_40q30_Age!$G$2:$G$2081,30))) -> 14.504478 | J28: =SUMIFS($I$2:$I$53,$A$2:$A$53,A28,$G$2:$G$53,G28,$H$2:$H$53,H28,$B$2:$B$53,"baseline") -> 14.504478 | K28: =J28-I28 -> 0 | L28: =IF(J28=0,"",100*(J28-I28)/J28) -> 0 | M28: 14.504478 | N28: =IF(ABS(I28-M28)<=0.001,"match","mismatch") -> match
A29: Indonesia | B29: baseline | C29: Baseline (no new intervention) | D29: baseline | G29: htncov2_aspirational | H29: 2026 | I29: =100*(1-(SUMIFS(CVD_40q30_Age!$M$2:$M$2081,CVD_40q30_Age!$A$2:$A$2081,A29,CVD_40q30_Age!$B$2:$B$2081,B29,CVD_40q30_Age!$E$2:$E$2081,G29,CVD_40q30_Age!$F$2:$F$2081,H29,CVD_40q30_Age!$G$2:$G$2081,69))/(SUMIFS(CVD_40q30_Age!$L$2:$L$2081,CVD_40q30_Age!$A$2:$A$2081,A29,CVD_40q30_Age!$B$2:$B$2081,B29,CVD_40q30_Age!$E$2:$E$2081,G29,CVD_40q30_Age!$F$2:$F$2081,H29,CVD_40q30_Age!$G$2:$G$2081,30))) -> 13.740526 | J29: =SUMIFS($I$2:$I$53,$A$2:$A$53,A29,$G$2:$G$53,G29,$H$2:$H$53,H29,$B$2:$B$53,"baseline") -> 13.740526 | K29: =J29-I29 -> 0 | L29: =IF(J29=0,"",100*(J29-I29)/J29) -> 0 | M29: 13.740526 | N29: =IF(ABS(I29-M29)<=0.001,"match","mismatch") -> match
A30: Indonesia | B30: baseline | C30: Baseline (no new intervention) | D30: baseline | G30: htncov2_aspirational | H30: 2027 | I30: =100*(1-(SUMIFS(CVD_40q30_Age!$M$2:$M$2081,CVD_40q30_Age!$A$2:$A$2081,A30,CVD_40q30_Age!$B$2:$B$2081,B30,CVD_40q30_Age!$E$2:$E$2081,G30,CVD_40q30_Age!$F$2:$F$2081,H30,CVD_40q30_Age!$G$2:$G$2081,69))/(SUMIFS(CVD_40q30_Age!$L$2:$L$2081,CVD_40q30_Age!$A$2:$A$2081,A30,CVD_40q30_Age!$B$2:$B$2081,B30,CVD_40q30_Age!$E$2:$E$2081,G30,CVD_40q30_Age!$F$2:$F$2081,H30,CVD_40q30_Age!$G$2:$G$2081,30))) -> 13.098116 | J30: =SUMIFS($I$2:$I$53,$A$2:$A$53,A30,$G$2:$G$53,G30,$H$2:$H$53,H30,$B$2:$B$53,"baseline") -> 13.098116 | K30: =J30-I30 -> 0 | L30: =IF(J30=0,"",100*(J30-I30)/J30) -> 0 | M30: 13.098116 | N30: =IF(ABS(I30-M30)<=0.001,"match","mismatch") -> match
A31: Indonesia | B31: baseline | C31: Baseline (no new intervention) | D31: baseline | G31: htncov2_aspirational | H31: 2028 | I31: =100*(1-(SUMIFS(CVD_40q30_Age!$M$2:$M$2081,CVD_40q30_Age!$A$2:$A$2081,A31,CVD_40q30_Age!$B$2:$B$2081,B31,CVD_40q30_Age!$E$2:$E$2081,G31,CVD_40q30_Age!$F$2:$F$2081,H31,CVD_40q30_Age!$G$2:$G$2081,69))/(SUMIFS(CVD_40q30_Age!$L$2:$L$2081,CVD_40q30_Age!$A$2:$A$2081,A31,CVD_40q30_Age!$B$2:$B$2081,B31,CVD_40q30_Age!$E$2:$E$2081,G31,CVD_40q30_Age!$F$2:$F$2081,H31,CVD_40q30_Age!$G$2:$G$2081,30))) -> 12.563551 | J31: =SUMIFS($I$2:$I$53,$A$2:$A$53,A31,$G$2:$G$53,G31,$H$2:$H$53,H31,$B$2:$B$53,"baseline") -> 12.563551 | K31: =J31-I31 -> 0 | L31: =IF(J31=0,"",100*(J31-I31)/J31) -> 0 | M31: 12.563551 | N31: =IF(ABS(I31-M31)<=0.001,"match","mismatch") -> match
A32: Indonesia | B32: baseline | C32: Baseline (no new intervention) | D32: baseline | G32: htncov2_aspirational | H32: 2029 | I32: =100*(1-(SUMIFS(CVD_40q30_Age!$M$2:$M$2081,CVD_40q30_Age!$A$2:$A$2081,A32,CVD_40q30_Age!$B$2:$B$2081,B32,CVD_40q30_Age!$E$2:$E$2081,G32,CVD_40q30_Age!$F$2:$F$2081,H32,CVD_40q30_Age!$G$2:$G$2081,69))/(SUMIFS(CVD_40q30_Age!$L$2:$L$2081,CVD_40q30_Age!$A$2:$A$2081,A32,CVD_40q30_Age!$B$2:$B$2081,B32,CVD_40q30_Age!$E$2:$E$2081,G32,CVD_40q30_Age!$F$2:$F$2081,H32,CVD_40q30_Age!$G$2:$G$2081,30))) -> 12.11775 | J32: =SUMIFS($I$2:$I$53,$A$2:$A$53,A32,$G$2:$G$53,G32,$H$2:$H$53,H32,$B$2:$B$53,"baseline") -> 12.11775 | K32: =J32-I32 -> 0 | L32: =IF(J32=0,"",100*(J32-I32)/J32) -> 0 | M32: 12.11775 | N32: =IF(ABS(I32-M32)<=0.001,"match","mismatch") -> match
A33: Indonesia | B33: baseline | C33: Baseline (no new intervention) | D33: baseline | G33: htncov2_aspirational | H33: 2030 | I33: =100*(1-(SUMIFS(CVD_40q30_Age!$M$2:$M$2081,CVD_40q30_Age!$A$2:$A$2081,A33,CVD_40q30_Age!$B$2:$B$2081,B33,CVD_40q30_Age!$E$2:$E$2081,G33,CVD_40q30_Age!$F$2:$F$2081,H33,CVD_40q30_Age!$G$2:$G$2081,69))/(SUMIFS(CVD_40q30_Age!$L$2:$L$2081,CVD_40q30_Age!$A$2:$A$2081,A33,CVD_40q30_Age!$B$2:$B$2081,B33,CVD_40q30_Age!$E$2:$E$2081,G33,CVD_40q30_Age!$F$2:$F$2081,H33,CVD_40q30_Age!$G$2:$G$2081,30))) -> 11.74693 | J33: =SUMIFS($I$2:$I$53,$A$2:$A$53,A33,$G$2:$G$53,G33,$H$2:$H$53,H33,$B$2:$B$53,"baseline") -> 11.74693 | K33: =J33-I33 -> 0 | L33: =IF(J33=0,"",100*(J33-I33)/J33) -> 0 | M33: 11.74693 | N33: =IF(ABS(I33-M33)<=0.001,"match","mismatch") -> match
A34: Indonesia | B34: baseline | C34: Baseline (no new intervention) | D34: baseline | G34: htncov2_aspirational | H34: 2031 | I34: =100*(1-(SUMIFS(CVD_40q30_Age!$M$2:$M$2081,CVD_40q30_Age!$A$2:$A$2081,A34,CVD_40q30_Age!$B$2:$B$2081,B34,CVD_40q30_Age!$E$2:$E$2081,G34,CVD_40q30_Age!$F$2:$F$2081,H34,CVD_40q30_Age!$G$2:$G$2081,69))/(SUMIFS(CVD_40q30_Age!$L$2:$L$2081,CVD_40q30_Age!$A$2:$A$2081,A34,CVD_40q30_Age!$B$2:$B$2081,B34,CVD_40q30_Age!$E$2:$E$2081,G34,CVD_40q30_Age!$F$2:$F$2081,H34,CVD_40q30_Age!$G$2:$G$2081,30))) -> 11.413097 | J34: =SUMIFS($I$2:$I$53,$A$2:$A$53,A34,$G$2:$G$53,G34,$H$2:$H$53,H34,$B$2:$B$53,"baseline") -> 11.413097 | K34: =J34-I34 -> 0 | L34: =IF(J34=0,"",100*(J34-I34)/J34) -> 0 | M34: 11.413097 | N34: =IF(ABS(I34-M34)<=0.001,"match","mismatch") -> match
A35: Indonesia | B35: baseline | C35: Baseline (no new intervention) | D35: baseline | G35: htncov2_aspirational | H35: 2032 | I35: =100*(1-(SUMIFS(CVD_40q30_Age!$M$2:$M$2081,CVD_40q30_Age!$A$2:$A$2081,A35,CVD_40q30_Age!$B$2:$B$2081,B35,CVD_40q30_Age!$E$2:$E$2081,G35,CVD_40q30_Age!$F$2:$F$2081,H35,CVD_40q30_Age!$G$2:$G$2081,69))/(SUMIFS(CVD_40q30_Age!$L$2:$L$2081,CVD_40q30_Age!$A$2:$A$2081,A35,CVD_40q30_Age!$B$2:$B$2081,B35,CVD_40q30_Age!$E$2:$E$2081,G35,CVD_40q30_Age!$F$2:$F$2081,H35,CVD_40q30_Age!$G$2:$G$2081,30))) -> 11.115398 | J35: =SUMIFS($I$2:$I$53,$A$2:$A$53,A35,$G$2:$G$53,G35,$H$2:$H$53,H35,$B$2:$B$53,"baseline") -> 11.115398 | K35: =J35-I35 -> 0 | L35: =IF(J35=0,"",100*(J35-I35)/J35) -> 0 | M35: 11.115398 | N35: =IF(ABS(I35-M35)<=0.001,"match","mismatch") -> match
A36: Indonesia | B36: baseline | C36: Baseline (no new intervention) | D36: baseline | G36: htncov2_aspirational | H36: 2033 | I36: =100*(1-(SUMIFS(CVD_40q30_Age!$M$2:$M$2081,CVD_40q30_Age!$A$2:$A$2081,A36,CVD_40q30_Age!$B$2:$B$2081,B36,CVD_40q30_Age!$E$2:$E$2081,G36,CVD_40q30_Age!$F$2:$F$2081,H36,CVD_40q30_Age!$G$2:$G$2081,69))/(SUMIFS(CVD_40q30_Age!$L$2:$L$2081,CVD_40q30_Age!$A$2:$A$2081,A36,CVD_40q30_Age!$B$2:$B$2081,B36,CVD_40q30_Age!$E$2:$E$2081,G36,CVD_40q30_Age!$F$2:$F$2081,H36,CVD_40q30_Age!$G$2:$G$2081,30))) -> 10.851472 | J36: =SUMIFS($I$2:$I$53,$A$2:$A$53,A36,$G$2:$G$53,G36,$H$2:$H$53,H36,$B$2:$B$53,"baseline") -> 10.851472 | K36: =J36-I36 -> 0 | L36: =IF(J36=0,"",100*(J36-I36)/J36) -> 0 | M36: 10.851472 | N36: =IF(ABS(I36-M36)<=0.001,"match","mismatch") -> match
A37: Indonesia | B37: baseline | C37: Baseline (no new intervention) | D37: baseline | G37: htncov2_aspirational | H37: 2034 | I37: =100*(1-(SUMIFS(CVD_40q30_Age!$M$2:$M$2081,CVD_40q30_Age!$A$2:$A$2081,A37,CVD_40q30_Age!$B$2:$B$2081,B37,CVD_40q30_Age!$E$2:$E$2081,G37,CVD_40q30_Age!$F$2:$F$2081,H37,CVD_40q30_Age!$G$2:$G$2081,69))/(SUMIFS(CVD_40q30_Age!$L$2:$L$2081,CVD_40q30_Age!$A$2:$A$2081,A37,CVD_40q30_Age!$B$2:$B$2081,B37,CVD_40q30_Age!$E$2:$E$2081,G37,CVD_40q30_Age!$F$2:$F$2081,H37,CVD_40q30_Age!$G$2:$G$2081,30))) -> 10.625758 | J37: =SUMIFS($I$2:$I$53,$A$2:$A$53,A37,$G$2:$G$53,G37,$H$2:$H$53,H37,$B$2:$B$53,"baseline") -> 10.625758 | K37: =J37-I37 -> 0 | L37: =IF(J37=0,"",100*(J37-I37)/J37) -> 0 | M37: 10.625758 | N37: =IF(ABS(I37-M37)<=0.001,"match","mismatch") -> match
A38: Indonesia | B38: baseline | C38: Baseline (no new intervention) | D38: baseline | G38: htncov2_aspirational | H38: 2035 | I38: =100*(1-(SUMIFS(CVD_40q30_Age!$M$2:$M$2081,CVD_40q30_Age!$A$2:$A$2081,A38,CVD_40q30_Age!$B$2:$B$2081,B38,CVD_40q30_Age!$E$2:$E$2081,G38,CVD_40q30_Age!$F$2:$F$2081,H38,CVD_40q30_Age!$G$2:$G$2081,69))/(SUMIFS(CVD_40q30_Age!$L$2:$L$2081,CVD_40q30_Age!$A$2:$A$2081,A38,CVD_40q30_Age!$B$2:$B$2081,B38,CVD_40q30_Age!$E$2:$E$2081,G38,CVD_40q30_Age!$F$2:$F$2081,H38,CVD_40q30_Age!$G$2:$G$2081,30))) -> 10.431088 | J38: =SUMIFS($I$2:$I$53,$A$2:$A$53,A38,$G$2:$G$53,G38,$H$2:$H$53,H38,$B$2:$B$53,"baseline") -> 10.431088 | K38: =J38-I38 -> 0 | L38: =IF(J38=0,"",100*(J38-I38)/J38) -> 0 | M38: 10.431088 | N38: =IF(ABS(I38-M38)<=0.001,"match","mismatch") -> match
A39: Indonesia | B39: baseline | C39: Baseline (no new intervention) | D39: baseline | G39: htncov2_aspirational | H39: 2036 | I39: =100*(1-(SUMIFS(CVD_40q30_Age!$M$2:$M$2081,CVD_40q30_Age!$A$2:$A$2081,A39,CVD_40q30_Age!$B$2:$B$2081,B39,CVD_40q30_Age!$E$2:$E$2081,G39,CVD_40q30_Age!$F$2:$F$2081,H39,CVD_40q30_Age!$G$2:$G$2081,69))/(SUMIFS(CVD_40q30_Age!$L$2:$L$2081,CVD_40q30_Age!$A$2:$A$2081,A39,CVD_40q30_Age!$B$2:$B$2081,B39,CVD_40q30_Age!$E$2:$E$2081,G39,CVD_40q30_Age!$F$2:$F$2081,H39,CVD_40q30_Age!$G$2:$G$2081,30))) -> 10.266493 | J39: =SUMIFS($I$2:$I$53,$A$2:$A$53,A39,$G$2:$G$53,G39,$H$2:$H$53,H39,$B$2:$B$53,"baseline") -> 10.266493 | K39: =J39-I39 -> 0 | L39: =IF(J39=0,"",100*(J39-I39)/J39) -> 0 | M39: 10.266493 | N39: =IF(ABS(I39-M39)<=0.001,"match","mismatch") -> match
... A53: Indonesia | B53: baseline | C53: Baseline (no new intervention) | D53: baseline | G53: htncov2_aspirational | H53: 2050 | I53: =100*(1-(SUMIFS(CVD_40q30_Age!$M$2:$M$2081,CVD_40q30_Age!$A$2:$A$2081,A53,CVD_40q30_Age!$B$2:$B$2081,B53,CVD_40q30_Age!$E$2:$E$2081,G53,CVD_40q30_Age!$F$2:$F$2081,H53,CVD_40q30_Age!$G$2:$G$2081,69))/(SUMIFS(CVD_40q30_Age!$L$2:$L$2081,CVD_40q30_Age!$A$2:$A$2081,A53,CVD_40q30_Age!$B$2:$B$2081,B53,CVD_40q30_Age!$E$2:$E$2081,G53,CVD_40q30_Age!$F$2:$F$2081,H53,CVD_40q30_Age!$G$2:$G$2081,30))) -> 9.0836246 | J53: =SUMIFS($I$2:$I$53,$A$2:$A$53,A53,$G$2:$G$53,G53,$H$2:$H$53,H53,$B$2:$B$53,"baseline") -> 9.0836246 | K53: =J53-I53 -> 0 | L53: =IF(J53=0,"",100*(J53-I53)/J53) -> 0 | M53: 9.0836246 | N53: =IF(ABS(I53-M53)<=0.001,"match","mismatch") -> match

Sheet CVD_40q30_Age
A1: location | B1: scenario | C1: scenario_label | D1: intervention_family | E1: htn_target_scenario | F1: year | G1: age | H1: cvd_deaths | I1: population | J1: m_x | K1: q_x | L1: l_x | M1: l_x_next
A2: Indonesia | B2: S_70_30_30_TO_70_70_70 | C2: 70-30-30 -> 70-70-70 hypertension/cholesterol + diabetes cascade | D2: cascade_70_30_30_to_70_70_70 | E2: htncov2_aspirational | F2: 2025 | G2: 30 | H2: 917.59069 | I2: 4325986.9 | J2: =IF(I2>0,H2/I2,0) -> 0.0002121113 | K2: =1-EXP(-J2) -> 0.0002120888 | L2: =IF(G2=30,1,M1) -> 1 | M2: =L2*(1-K2) -> 0.99978791
A3: Indonesia | B3: S_70_30_30_TO_70_70_70 | C3: 70-30-30 -> 70-70-70 hypertension/cholesterol + diabetes cascade | D3: cascade_70_30_30_to_70_70_70 | E3: htncov2_aspirational | F3: 2025 | G3: 31 | H3: 1309.867 | I3: 4272907.5 | J3: =IF(I3>0,H3/I3,0) -> 0.00030655169 | K3: =1-EXP(-J3) -> 0.00030650471 | L3: =IF(G3=30,1,M2) -> 0.99978791 | M3: =L3*(1-K3) -> 0.99948147
A4: Indonesia | B4: S_70_30_30_TO_70_70_70 | C4: 70-30-30 -> 70-70-70 hypertension/cholesterol + diabetes cascade | D4: cascade_70_30_30_to_70_70_70 | E4: htncov2_aspirational | F4: 2025 | G4: 32 | H4: 1349.7571 | I4: 4222809.1 | J4: =IF(I4>0,H4/I4,0) -> 0.00031963488 | K4: =1-EXP(-J4) -> 0.0003195838 | L4: =IF(G4=30,1,M3) -> 0.99948147 | M4: =L4*(1-K4) -> 0.99916205
A5: Indonesia | B5: S_70_30_30_TO_70_70_70 | C5: 70-30-30 -> 70-70-70 hypertension/cholesterol + diabetes cascade | D5: cascade_70_30_30_to_70_70_70 | E5: htncov2_aspirational | F5: 2025 | G5: 33 | H5: 1419.193 | I5: 4208311.5 | J5: =IF(I5>0,H5/I5,0) -> 0.00033723573 | K5: =1-EXP(-J5) -> 0.00033717887 | L5: =IF(G5=30,1,M4) -> 0.99916205 | M5: =L5*(1-K5) -> 0.99882516
A6: Indonesia | B6: S_70_30_30_TO_70_70_70 | C6: 70-30-30 -> 70-70-70 hypertension/cholesterol + diabetes cascade | D6: cascade_70_30_30_to_70_70_70 | E6: htncov2_aspirational | F6: 2025 | G6: 34 | H6: 1510.9799 | I6: 4188390.2 | J6: =IF(I6>0,H6/I6,0) -> 0.00036075432 | K6: =1-EXP(-J6) -> 0.00036068925 | L6: =IF(G6=30,1,M5) -> 0.99882516 | M6: =L6*(1-K6) -> 0.99846489
A7: Indonesia | B7: S_70_30_30_TO_70_70_70 | C7: 70-30-30 -> 70-70-70 hypertension/cholesterol + diabetes cascade | D7: cascade_70_30_30_to_70_70_70 | E7: htncov2_aspirational | F7: 2025 | G7: 35 | H7: 1631.109 | I7: 4172291.6 | J7: =IF(I7>0,H7/I7,0) -> 0.00039093841 | K7: =1-EXP(-J7) -> 0.000390862 | L7: =IF(G7=30,1,M6) -> 0.99846489 | M7: =L7*(1-K7) -> 0.99807463
A8: Indonesia | B8: S_70_30_30_TO_70_70_70 | C8: 70-30-30 -> 70-70-70 hypertension/cholesterol + diabetes cascade | D8: cascade_70_30_30_to_70_70_70 | E8: htncov2_aspirational | F8: 2025 | G8: 36 | H8: 2229.743 | I8: 4179862.9 | J8: =IF(I8>0,H8/I8,0) -> 0.00053344883 | K8: =1-EXP(-J8) -> 0.00053330657 | L8: =IF(G8=30,1,M7) -> 0.99807463 | M8: =L8*(1-K8) -> 0.99754235
A9: Indonesia | B9: S_70_30_30_TO_70_70_70 | C9: 70-30-30 -> 70-70-70 hypertension/cholesterol + diabetes cascade | D9: cascade_70_30_30_to_70_70_70 | E9: htncov2_aspirational | F9: 2025 | G9: 37 | H9: 2512.8458 | I9: 4141889 | J9: =IF(I9>0,H9/I9,0) -> 0.00060669077 | K9: =1-EXP(-J9) -> 0.00060650677 | L9: =IF(G9=30,1,M8) -> 0.99754235 | M9: =L9*(1-K9) -> 0.99693733
A10: Indonesia | B10: S_70_30_30_TO_70_70_70 | C10: 70-30-30 -> 70-70-70 hypertension/cholesterol + diabetes cascade | D10: cascade_70_30_30_to_70_70_70 | E10: htncov2_aspirational | F10: 2025 | G10: 38 | H10: 2815.5382 | I10: 4095336.8 | J10: =IF(I10>0,H10/I10,0) -> 0.00068749857 | K10: =1-EXP(-J10) -> 0.00068726229 | L10: =IF(G10=30,1,M9) -> 0.99693733 | M10: =L10*(1-K10) -> 0.99625218
A11: Indonesia | B11: S_70_30_30_TO_70_70_70 | C11: 70-30-30 -> 70-70-70 hypertension/cholesterol + diabetes cascade | D11: cascade_70_30_30_to_70_70_70 | E11: htncov2_aspirational | F11: 2025 | G11: 39 | H11: 3074.2181 | I11: 4111651.4 | J11: =IF(I11>0,H11/I11,0) -> 0.00074768453 | K11: =1-EXP(-J11) -> 0.00074740509 | L11: =IF(G11=30,1,M10) -> 0.99625218 | M11: =L11*(1-K11) -> 0.99550757
A12: Indonesia | B12: S_70_30_30_TO_70_70_70 | C12: 70-30-30 -> 70-70-70 hypertension/cholesterol + diabetes cascade | D12: cascade_70_30_30_to_70_70_70 | E12: htncov2_aspirational | F12: 2025 | G12: 40 | H12: 3465.9809 | I12: 4186115.1 | J12: =IF(I12>0,H12/I12,0) -> 0.00082797076 | K12: =1-EXP(-J12) -> 0.00082762809 | L12: =IF(G12=30,1,M11) -> 0.99550757 | M12: =L12*(1-K12) -> 0.99468366
A13: Indonesia | B13: S_70_30_30_TO_70_70_70 | C13: 70-30-30 -> 70-70-70 hypertension/cholesterol + diabetes cascade | D13: cascade_70_30_30_to_70_70_70 | E13: htncov2_aspirational | F13: 2025 | G13: 41 | H13: 4701.8658 | I13: 4219085.5 | J13: =IF(I13>0,H13/I13,0) -> 0.0011144277 | K13: =1-EXP(-J13) -> 0.001113807 | L13: =IF(G13=30,1,M12) -> 0.99468366 | M13: =L13*(1-K13) -> 0.99357578
... A2081: Indonesia | B2081: baseline | C2081: Baseline (no new intervention) | D2081: baseline | E2081: htncov2_aspirational | F2081: 2050 | G2081: 69 | H2081: 25381.645 | I2081: 3216965.3 | J2081: =IF(I2081>0,H2081/I2081,0) -> 0.0078899344 | K2081: =1-EXP(-J2081) -> 0.0078588905 | L2081: =IF(G2081=30,1,M2080) -> 0.91636537 | M2081: =L2081*(1-K2081) -> 0.90916375

Sheet Annual_Cost
A1: scenario | B1: year | C1: intervention_id | D1: cause_code | E1: cost_record_id | F1: cost_component_key | G1: cost_join_key | H1: cost_scope | I1: population_in_need_measure | J1: population_in_need_fraction | K1: coverage_scenario | L1: coverage_baseline | M1: frequency_per_year | N1: unit_cost_usd | O1: pin_scenario | P1: pin_baseline | Q1: annual_cost_baseline | R1: annual_cost_scenario | S1: annual_cost_incremental | T1: indonesia_adjusted_flag | U1: price_year | V1: discount_factor | W1: disc_cost_baseline | X1: disc_cost_scenario | Y1: disc_cost_incremental | Z1: cov_target | AA1: cov_start_year | AB1: cov_target_year | AC1: c_age_start | AD1: c_age_stop | AE1: c_sex | AF1: r_quantity_scenario | AG1: r_quantity_baseline | AH1: shared_duplicate_count
A2: S_70_30_30_TO_70_70_70 | B2: 2025 | C2: I_CVD_PRIMARY | E2: COST_PRIMARY_SCREEN_A | F2: CC_PRIMARY_SCREENING | G2: I_CVD_PRIMARY__C_SHARED | H2: shared-count-once | I2: all | J2: =IFERROR(INDEX(Cost_Components!$K$2:$K$6,MATCH(E2,Cost_Components!$A$2:$A$6,0)),"") -> 0.2 | K2: 0.11376686 | L2: =IFERROR(INDEX(Cost_Components!$S$2:$S$6,MATCH(E2,Cost_Components!$A$2:$A$6,0)),"") -> 0.11376686 | M2: =IFERROR(INDEX(Cost_Components!$L$2:$L$6,MATCH(E2,Cost_Components!$A$2:$A$6,0)),"") -> 1 | N2: =IFERROR(INDEX(Cost_Components!$P$2:$P$6,MATCH(E2,Cost_Components!$A$2:$A$6,0)),"") -> 1.291584 | O2: =AF2*J2 -> 30364900 | P2: =AG2*J2 -> 30364900 | Q2: =P2*L2*M2*N2 -> 4461801.7 | R2: =O2*K2*M2*N2 -> 4461801.7 | S2: =R2-Q2 -> 0 | T2: =IFERROR(INDEX(Cost_Components!$R$2:$R$6,MATCH(E2,Cost_Components!$A$2:$A$6,0)),"") -> 1 | U2: =IFERROR(INDEX(Cost_Components!$Q$2:$Q$6,MATCH(E2,Cost_Components!$A$2:$A$6,0)),"") -> 2023 | V2: =1/(1+Calculation_Assumptions!$B$5)^(B2-Calculation_Assumptions!$B$2) -> 1 | W2: =Q2*V2 -> 4461801.7 | X2: =R2*V2 -> 4461801.7 | Y2: =S2*V2 -> 0 | Z2: =IFERROR(INDEX(Cost_Components!$T$2:$T$6,MATCH(E2,Cost_Components!$A$2:$A$6,0)),"") -> 0.4165 | AA2: =IFERROR(INDEX(Cost_Components!$U$2:$U$6,MATCH(E2,Cost_Components!$A$2:$A$6,0)),"") -> 2025 | AB2: =IFERROR(INDEX(Cost_Components!$V$2:$V$6,MATCH(E2,Cost_Components!$A$2:$A$6,0)),"") -> 2040 | AC2: =IFERROR(INDEX(Cost_Components!$M$2:$M$6,MATCH(E2,Cost_Components!$A$2:$A$6,0)),"") -> 30 | AD2: =IFERROR(INDEX(Cost_Components!$N$2:$N$6,MATCH(E2,Cost_Components!$A$2:$A$6,0)),"") -> 95 | AE2: =IFERROR(INDEX(Cost_Components!$O$2:$O$6,MATCH(E2,Cost_Components!$A$2:$A$6,0)),"") -> Both | AF2: 1.518245e+08 | AG2: 1.518245e+08 | AH2: =IF(H2="shared-count-once",COUNTIFS($A$2:$A$131,A2,$B$2:$B$131,B2,$E$2:$E$131,E2),1) -> 1
A3: S_70_30_30_TO_70_70_70 | B3: 2026 | C3: I_CVD_PRIMARY | E3: COST_PRIMARY_SCREEN_A | F3: CC_PRIMARY_SCREENING | G3: I_CVD_PRIMARY__C_SHARED | H3: shared-count-once | I3: all | J3: =IFERROR(INDEX(Cost_Components!$K$2:$K$6,MATCH(E3,Cost_Components!$A$2:$A$6,0)),"") -> 0.2 | K3: 0.11831349 | L3: =IFERROR(INDEX(Cost_Components!$S$2:$S$6,MATCH(E3,Cost_Components!$A$2:$A$6,0)),"") -> 0.11376686 | M3: =IFERROR(INDEX(Cost_Components!$L$2:$L$6,MATCH(E3,Cost_Components!$A$2:$A$6,0)),"") -> 1 | N3: =IFERROR(INDEX(Cost_Components!$P$2:$P$6,MATCH(E3,Cost_Components!$A$2:$A$6,0)),"") -> 1.291584 | O3: =AF3*J3 -> 30765556 | P3: =AG3*J3 -> 30765556 | Q3: =P3*L3*M3*N3 -> 4520673.9 | R3: =O3*K3*M3*N3 -> 4701340.1 | S3: =R3-Q3 -> 180666.19 | T3: =IFERROR(INDEX(Cost_Components!$R$2:$R$6,MATCH(E3,Cost_Components!$A$2:$A$6,0)),"") -> 1 | U3: =IFERROR(INDEX(Cost_Components!$Q$2:$Q$6,MATCH(E3,Cost_Components!$A$2:$A$6,0)),"") -> 2023 | V3: =1/(1+Calculation_Assumptions!$B$5)^(B3-Calculation_Assumptions!$B$2) -> 0.97087379 | W3: =Q3*V3 -> 4389003.8 | X3: =R3*V3 -> 4564407.9 | Y3: =S3*V3 -> 175404.07 | Z3: =IFERROR(INDEX(Cost_Components!$T$2:$T$6,MATCH(E3,Cost_Components!$A$2:$A$6,0)),"") -> 0.4165 | AA3: =IFERROR(INDEX(Cost_Components!$U$2:$U$6,MATCH(E3,Cost_Components!$A$2:$A$6,0)),"") -> 2025 | AB3: =IFERROR(INDEX(Cost_Components!$V$2:$V$6,MATCH(E3,Cost_Components!$A$2:$A$6,0)),"") -> 2040 | AC3: =IFERROR(INDEX(Cost_Components!$M$2:$M$6,MATCH(E3,Cost_Components!$A$2:$A$6,0)),"") -> 30 | AD3: =IFERROR(INDEX(Cost_Components!$N$2:$N$6,MATCH(E3,Cost_Components!$A$2:$A$6,0)),"") -> 95 | AE3: =IFERROR(INDEX(Cost_Components!$O$2:$O$6,MATCH(E3,Cost_Components!$A$2:$A$6,0)),"") -> Both | AF3: 1.5382778e+08 | AG3: 1.5382778e+08 | AH3: =IF(H3="shared-count-once",COUNTIFS($A$2:$A$131,A3,$B$2:$B$131,B3,$E$2:$E$131,E3),1) -> 1
A4: S_70_30_30_TO_70_70_70 | B4: 2027 | C4: I_CVD_PRIMARY | E4: COST_PRIMARY_SCREEN_A | F4: CC_PRIMARY_SCREENING | G4: I_CVD_PRIMARY__C_SHARED | H4: shared-count-once | I4: all | J4: =IFERROR(INDEX(Cost_Components!$K$2:$K$6,MATCH(E4,Cost_Components!$A$2:$A$6,0)),"") -> 0.2 | K4: 0.12286011 | L4: =IFERROR(INDEX(Cost_Components!$S$2:$S$6,MATCH(E4,Cost_Components!$A$2:$A$6,0)),"") -> 0.11376686 | M4: =IFERROR(INDEX(Cost_Components!$L$2:$L$6,MATCH(E4,Cost_Components!$A$2:$A$6,0)),"") -> 1 | N4: =IFERROR(INDEX(Cost_Components!$P$2:$P$6,MATCH(E4,Cost_Components!$A$2:$A$6,0)),"") -> 1.291584 | O4: =AF4*J4 -> 31208345 | P4: =AG4*J4 -> 31208338 | Q4: =P4*L4*M4*N4 -> 4585736.1 | R4: =O4*K4*M4*N4 -> 4952270 | S4: =R4-Q4 -> 366533.9 | T4: =IFERROR(INDEX(Cost_Components!$R$2:$R$6,MATCH(E4,Cost_Components!$A$2:$A$6,0)),"") -> 1 | U4: =IFERROR(INDEX(Cost_Components!$Q$2:$Q$6,MATCH(E4,Cost_Components!$A$2:$A$6,0)),"") -> 2023 | V4: =1/(1+Calculation_Assumptions!$B$5)^(B4-Calculation_Assumptions!$B$2) -> 0.94259591 | W4: =Q4*V4 -> 4322496.1 | X4: =R4*V4 -> 4667989.4 | Y4: =S4*V4 -> 345493.35 | Z4: =IFERROR(INDEX(Cost_Components!$T$2:$T$6,MATCH(E4,Cost_Components!$A$2:$A$6,0)),"") -> 0.4165 | AA4: =IFERROR(INDEX(Cost_Components!$U$2:$U$6,MATCH(E4,Cost_Components!$A$2:$A$6,0)),"") -> 2025 | AB4: =IFERROR(INDEX(Cost_Components!$V$2:$V$6,MATCH(E4,Cost_Components!$A$2:$A$6,0)),"") -> 2040 | AC4: =IFERROR(INDEX(Cost_Components!$M$2:$M$6,MATCH(E4,Cost_Components!$A$2:$A$6,0)),"") -> 30 | AD4: =IFERROR(INDEX(Cost_Components!$N$2:$N$6,MATCH(E4,Cost_Components!$A$2:$A$6,0)),"") -> 95 | AE4: =IFERROR(INDEX(Cost_Components!$O$2:$O$6,MATCH(E4,Cost_Components!$A$2:$A$6,0)),"") -> Both | AF4: 1.5604173e+08 | AG4: 1.5604169e+08 | AH4: =IF(H4="shared-count-once",COUNTIFS($A$2:$A$131,A4,$B$2:$B$131,B4,$E$2:$E$131,E4),1) -> 1
A5: S_70_30_30_TO_70_70_70 | B5: 2028 | C5: I_CVD_PRIMARY | E5: COST_PRIMARY_SCREEN_A | F5: CC_PRIMARY_SCREENING | G5: I_CVD_PRIMARY__C_SHARED | H5: shared-count-once | I5: all | J5: =IFERROR(INDEX(Cost_Components!$K$2:$K$6,MATCH(E5,Cost_Components!$A$2:$A$6,0)),"") -> 0.2 | K5: 0.12740674 | L5: =IFERROR(INDEX(Cost_Components!$S$2:$S$6,MATCH(E5,Cost_Components!$A$2:$A$6,0)),"") -> 0.11376686 | M5: =IFERROR(INDEX(Cost_Components!$L$2:$L$6,MATCH(E5,Cost_Components!$A$2:$A$6,0)),"") -> 1 | N5: =IFERROR(INDEX(Cost_Components!$P$2:$P$6,MATCH(E5,Cost_Components!$A$2:$A$6,0)),"") -> 1.291584 | O5: =AF5*J5 -> 31656678 | P5: =AG5*J5 -> 31656609 | Q5: =P5*L5*M5*N5 -> 4651604.9 | R5: =O5*K5*M5*N5 -> 5209312.4 | S5: =R5-Q5 -> 557707.58 | T5: =IFERROR(INDEX(Cost_Components!$R$2:$R$6,MATCH(E5,Cost_Components!$A$2:$A$6,0)),"") -> 1 | U5: =IFERROR(INDEX(Cost_Components!$Q$2:$Q$6,MATCH(E5,Cost_Components!$A$2:$A$6,0)),"") -> 2023 | V5: =1/(1+Calculation_Assumptions!$B$5)^(B5-Calculation_Assumptions!$B$2) -> 0.91514166 | W5: =Q5*V5 -> 4256877.4 | X5: =R5*V5 -> 4767258.8 | Y5: =S5*V5 -> 510381.44 | Z5: =IFERROR(INDEX(Cost_Components!$T$2:$T$6,MATCH(E5,Cost_Components!$A$2:$A$6,0)),"") -> 0.4165 | AA5: =IFERROR(INDEX(Cost_Components!$U$2:$U$6,MATCH(E5,Cost_Components!$A$2:$A$6,0)),"") -> 2025 | AB5: =IFERROR(INDEX(Cost_Components!$V$2:$V$6,MATCH(E5,Cost_Components!$A$2:$A$6,0)),"") -> 2040 | AC5: =IFERROR(INDEX(Cost_Components!$M$2:$M$6,MATCH(E5,Cost_Components!$A$2:$A$6,0)),"") -> 30 | AD5: =IFERROR(INDEX(Cost_Components!$N$2:$N$6,MATCH(E5,Cost_Components!$A$2:$A$6,0)),"") -> 95 | AE5: =IFERROR(INDEX(Cost_Components!$O$2:$O$6,MATCH(E5,Cost_Components!$A$2:$A$6,0)),"") -> Both | AF5: 1.5828339e+08 | AG5: 1.5828305e+08 | AH5: =IF(H5="shared-count-once",COUNTIFS($A$2:$A$131,A5,$B$2:$B$131,B5,$E$2:$E$131,E5),1) -> 1
A6: S_70_30_30_TO_70_70_70 | B6: 2029 | C6: I_CVD_PRIMARY | E6: COST_PRIMARY_SCREEN_A | F6: CC_PRIMARY_SCREENING | G6: I_CVD_PRIMARY__C_SHARED | H6: shared-count-once | I6: all | J6: =IFERROR(INDEX(Cost_Components!$K$2:$K$6,MATCH(E6,Cost_Components!$A$2:$A$6,0)),"") -> 0.2 | K6: 0.13195337 | L6: =IFERROR(INDEX(Cost_Components!$S$2:$S$6,MATCH(E6,Cost_Components!$A$2:$A$6,0)),"") -> 0.11376686 | M6: =IFERROR(INDEX(Cost_Components!$L$2:$L$6,MATCH(E6,Cost_Components!$A$2:$A$6,0)),"") -> 1 | N6: =IFERROR(INDEX(Cost_Components!$P$2:$P$6,MATCH(E6,Cost_Components!$A$2:$A$6,0)),"") -> 1.291584 | O6: =AF6*J6 -> 32100475 | P6: =AG6*J6 -> 32100264 | Q6: =P6*L6*M6*N6 -> 4716795.2 | R6: =O6*K6*M6*N6 -> 5470847.5 | S6: =R6-Q6 -> 754052.27 | T6: =IFERROR(INDEX(Cost_Components!$R$2:$R$6,MATCH(E6,Cost_Components!$A$2:$A$6,0)),"") -> 1 | U6: =IFERROR(INDEX(Cost_Components!$Q$2:$Q$6,MATCH(E6,Cost_Components!$A$2:$A$6,0)),"") -> 2023 | V6: =1/(1+Calculation_Assumptions!$B$5)^(B6-Calculation_Assumptions!$B$2) -> 0.88848705 | W6: =Q6*V6 -> 4190811.4 | X6: =R6*V6 -> 4860777.1 | Y6: =S6*V6 -> 669965.67 | Z6: =IFERROR(INDEX(Cost_Components!$T$2:$T$6,MATCH(E6,Cost_Components!$A$2:$A$6,0)),"") -> 0.4165 | AA6: =IFERROR(INDEX(Cost_Components!$U$2:$U$6,MATCH(E6,Cost_Components!$A$2:$A$6,0)),"") -> 2025 | AB6: =IFERROR(INDEX(Cost_Components!$V$2:$V$6,MATCH(E6,Cost_Components!$A$2:$A$6,0)),"") -> 2040 | AC6: =IFERROR(INDEX(Cost_Components!$M$2:$M$6,MATCH(E6,Cost_Components!$A$2:$A$6,0)),"") -> 30 | AD6: =IFERROR(INDEX(Cost_Components!$N$2:$N$6,MATCH(E6,Cost_Components!$A$2:$A$6,0)),"") -> 95 | AE6: =IFERROR(INDEX(Cost_Components!$O$2:$O$6,MATCH(E6,Cost_Components!$A$2:$A$6,0)),"") -> Both | AF6: 1.6050237e+08 | AG6: 1.6050132e+08 | AH6: =IF(H6="shared-count-once",COUNTIFS($A$2:$A$131,A6,$B$2:$B$131,B6,$E$2:$E$131,E6),1) -> 1
A7: S_70_30_30_TO_70_70_70 | B7: 2030 | C7: I_CVD_PRIMARY | E7: COST_PRIMARY_SCREEN_A | F7: CC_PRIMARY_SCREENING | G7: I_CVD_PRIMARY__C_SHARED | H7: shared-count-once | I7: all | J7: =IFERROR(INDEX(Cost_Components!$K$2:$K$6,MATCH(E7,Cost_Components!$A$2:$A$6,0)),"") -> 0.2 | K7: 0.1365 | L7: =IFERROR(INDEX(Cost_Components!$S$2:$S$6,MATCH(E7,Cost_Components!$A$2:$A$6,0)),"") -> 0.11376686 | M7: =IFERROR(INDEX(Cost_Components!$L$2:$L$6,MATCH(E7,Cost_Components!$A$2:$A$6,0)),"") -> 1 | N7: =IFERROR(INDEX(Cost_Components!$P$2:$P$6,MATCH(E7,Cost_Components!$A$2:$A$6,0)),"") -> 1.291584 | O7: =AF7*J7 -> 32490352 | P7: =AG7*J7 -> 32530776 | Q7: =P7*L7*M7*N7 -> 4780054.5 | R7: =O7*K7*M7*N7 -> 5728088.6 | S7: =R7-Q7 -> 948034.16 | T7: =IFERROR(INDEX(Cost_Components!$R$2:$R$6,MATCH(E7,Cost_Components!$A$2:$A$6,0)),"") -> 1 | U7: =IFERROR(INDEX(Cost_Components!$Q$2:$Q$6,MATCH(E7,Cost_Components!$A$2:$A$6,0)),"") -> 2023 | V7: =1/(1+Calculation_Assumptions!$B$5)^(B7-Calculation_Assumptions!$B$2) -> 0.86260878 | W7: =Q7*V7 -> 4123317 | X7: =R7*V7 -> 4941099.6 | Y7: =S7*V7 -> 817782.59 | Z7: =IFERROR(INDEX(Cost_Components!$T$2:$T$6,MATCH(E7,Cost_Components!$A$2:$A$6,0)),"") -> 0.4165 | AA7: =IFERROR(INDEX(Cost_Components!$U$2:$U$6,MATCH(E7,Cost_Components!$A$2:$A$6,0)),"") -> 2025 | AB7: =IFERROR(INDEX(Cost_Components!$V$2:$V$6,MATCH(E7,Cost_Components!$A$2:$A$6,0)),"") -> 2040 | AC7: =IFERROR(INDEX(Cost_Components!$M$2:$M$6,MATCH(E7,Cost_Components!$A$2:$A$6,0)),"") -> 30 | AD7: =IFERROR(INDEX(Cost_Components!$N$2:$N$6,MATCH(E7,Cost_Components!$A$2:$A$6,0)),"") -> 95 | AE7: =IFERROR(INDEX(Cost_Components!$O$2:$O$6,MATCH(E7,Cost_Components!$A$2:$A$6,0)),"") -> Both | AF7: 1.6245176e+08 | AG7: 1.6265388e+08 | AH7: =IF(H7="shared-count-once",COUNTIFS($A$2:$A$131,A7,$B$2:$B$131,B7,$E$2:$E$131,E7),1) -> 1
A8: S_70_30_30_TO_70_70_70 | B8: 2031 | C8: I_CVD_PRIMARY | E8: COST_PRIMARY_SCREEN_A | F8: CC_PRIMARY_SCREENING | G8: I_CVD_PRIMARY__C_SHARED | H8: shared-count-once | I8: all | J8: =IFERROR(INDEX(Cost_Components!$K$2:$K$6,MATCH(E8,Cost_Components!$A$2:$A$6,0)),"") -> 0.2 | K8: 0.1645 | L8: =IFERROR(INDEX(Cost_Components!$S$2:$S$6,MATCH(E8,Cost_Components!$A$2:$A$6,0)),"") -> 0.11376686 | M8: =IFERROR(INDEX(Cost_Components!$L$2:$L$6,MATCH(E8,Cost_Components!$A$2:$A$6,0)),"") -> 1 | N8: =IFERROR(INDEX(Cost_Components!$P$2:$P$6,MATCH(E8,Cost_Components!$A$2:$A$6,0)),"") -> 1.291584 | O8: =AF8*J8 -> 32921479 | P8: =AG8*J8 -> 32956928 | Q8: =P8*L8*M8*N8 -> 4842673 | R8: =O8*K8*M8*N8 -> 6994680.6 | S8: =R8-Q8 -> 2152007.7 | T8: =IFERROR(INDEX(Cost_Components!$R$2:$R$6,MATCH(E8,Cost_Components!$A$2:$A$6,0)),"") -> 1 | U8: =IFERROR(INDEX(Cost_Components!$Q$2:$Q$6,MATCH(E8,Cost_Components!$A$2:$A$6,0)),"") -> 2023 | V8: =1/(1+Calculation_Assumptions!$B$5)^(B8-Calculation_Assumptions!$B$2) -> 0.83748426 | W8: =Q8*V8 -> 4055662.4 | X8: =R8*V8 -> 5857934.9 | Y8: =S8*V8 -> 1802272.5 | Z8: =IFERROR(INDEX(Cost_Components!$T$2:$T$6,MATCH(E8,Cost_Components!$A$2:$A$6,0)),"") -> 0.4165 | AA8: =IFERROR(INDEX(Cost_Components!$U$2:$U$6,MATCH(E8,Cost_Components!$A$2:$A$6,0)),"") -> 2025 | AB8: =IFERROR(INDEX(Cost_Components!$V$2:$V$6,MATCH(E8,Cost_Components!$A$2:$A$6,0)),"") -> 2040 | AC8: =IFERROR(INDEX(Cost_Components!$M$2:$M$6,MATCH(E8,Cost_Components!$A$2:$A$6,0)),"") -> 30 | AD8: =IFERROR(INDEX(Cost_Components!$N$2:$N$6,MATCH(E8,Cost_Components!$A$2:$A$6,0)),"") -> 95 | AE8: =IFERROR(INDEX(Cost_Components!$O$2:$O$6,MATCH(E8,Cost_Components!$A$2:$A$6,0)),"") -> Both | AF8: 1.6460739e+08 | AG8: 1.6478464e+08 | AH8: =IF(H8="shared-count-once",COUNTIFS($A$2:$A$131,A8,$B$2:$B$131,B8,$E$2:$E$131,E8),1) -> 1
A9: S_70_30_30_TO_70_70_70 | B9: 2032 | C9: I_CVD_PRIMARY | E9: COST_PRIMARY_SCREEN_A | F9: CC_PRIMARY_SCREENING | G9: I_CVD_PRIMARY__C_SHARED | H9: shared-count-once | I9: all | J9: =IFERROR(INDEX(Cost_Components!$K$2:$K$6,MATCH(E9,Cost_Components!$A$2:$A$6,0)),"") -> 0.2 | K9: 0.1925 | L9: =IFERROR(INDEX(Cost_Components!$S$2:$S$6,MATCH(E9,Cost_Components!$A$2:$A$6,0)),"") -> 0.11376686 | M9: =IFERROR(INDEX(Cost_Components!$L$2:$L$6,MATCH(E9,Cost_Components!$A$2:$A$6,0)),"") -> 1 | N9: =IFERROR(INDEX(Cost_Components!$P$2:$P$6,MATCH(E9,Cost_Components!$A$2:$A$6,0)),"") -> 1.291584 | O9: =AF9*J9 -> 33344844 | P9: =AG9*J9 -> 33381996 | Q9: =P9*L9*M9*N9 -> 4905132.2 | R9: =O9*K9*M9*N9 -> 8290526 | S9: =R9-Q9 -> 3385393.8 | T9: =IFERROR(INDEX(Cost_Components!$R$2:$R$6,MATCH(E9,Cost_Components!$A$2:$A$6,0)),"") -> 1 | U9: =IFERROR(INDEX(Cost_Components!$Q$2:$Q$6,MATCH(E9,Cost_Components!$A$2:$A$6,0)),"") -> 2023 | V9: =1/(1+Calculation_Assumptions!$B$5)^(B9-Calculation_Assumptions!$B$2) -> 0.81309151 | W9: =Q9*V9 -> 3988321.4 | X9: =R9*V9 -> 6740956.3 | Y9: =S9*V9 -> 2752634.9 | Z9: =IFERROR(INDEX(Cost_Components!$T$2:$T$6,MATCH(E9,Cost_Components!$A$2:$A$6,0)),"") -> 0.4165 | AA9: =IFERROR(INDEX(Cost_Components!$U$2:$U$6,MATCH(E9,Cost_Components!$A$2:$A$6,0)),"") -> 2025 | AB9: =IFERROR(INDEX(Cost_Components!$V$2:$V$6,MATCH(E9,Cost_Components!$A$2:$A$6,0)),"") -> 2040 | AC9: =IFERROR(INDEX(Cost_Components!$M$2:$M$6,MATCH(E9,Cost_Components!$A$2:$A$6,0)),"") -> 30 | AD9: =IFERROR(INDEX(Cost_Components!$N$2:$N$6,MATCH(E9,Cost_Components!$A$2:$A$6,0)),"") -> 95 | AE9: =IFERROR(INDEX(Cost_Components!$O$2:$O$6,MATCH(E9,Cost_Components!$A$2:$A$6,0)),"") -> Both | AF9: 1.6672422e+08 | AG9: 1.6690998e+08 | AH9: =IF(H9="shared-count-once",COUNTIFS($A$2:$A$131,A9,$B$2:$B$131,B9,$E$2:$E$131,E9),1) -> 1
A10: S_70_30_30_TO_70_70_70 | B10: 2033 | C10: I_CVD_PRIMARY | E10: COST_PRIMARY_SCREEN_A | F10: CC_PRIMARY_SCREENING | G10: I_CVD_PRIMARY__C_SHARED | H10: shared-count-once | I10: all | J10: =IFERROR(INDEX(Cost_Components!$K$2:$K$6,MATCH(E10,Cost_Components!$A$2:$A$6,0)),"") -> 0.2 | K10: 0.2205 | L10: =IFERROR(INDEX(Cost_Components!$S$2:$S$6,MATCH(E10,Cost_Components!$A$2:$A$6,0)),"") -> 0.11376686 | M10: =IFERROR(INDEX(Cost_Components!$L$2:$L$6,MATCH(E10,Cost_Components!$A$2:$A$6,0)),"") -> 1 | N10: =IFERROR(INDEX(Cost_Components!$P$2:$P$6,MATCH(E10,Cost_Components!$A$2:$A$6,0)),"") -> 1.291584 | O10: =AF10*J10 -> 33772899 | P10: =AG10*J10 -> 33804980 | Q10: =P10*L10*M10*N10 -> 4967285.2 | R10: =O10*K10*M10*N10 -> 9618328.2 | S10: =R10-Q10 -> 4651043 | T10: =IFERROR(INDEX(Cost_Components!$R$2:$R$6,MATCH(E10,Cost_Components!$A$2:$A$6,0)),"") -> 1 | U10: =IFERROR(INDEX(Cost_Components!$Q$2:$Q$6,MATCH(E10,Cost_Components!$A$2:$A$6,0)),"") -> 2023 | V10: =1/(1+Calculation_Assumptions!$B$5)^(B10-Calculation_Assumptions!$B$2) -> 0.78940923 | W10: =Q10*V10 -> 3921220.8 | X10: =R10*V10 -> 7592797.1 | Y10: =S10*V10 -> 3671576.3 | Z10: =IFERROR(INDEX(Cost_Components!$T$2:$T$6,MATCH(E10,Cost_Components!$A$2:$A$6,0)),"") -> 0.4165 | AA10: =IFERROR(INDEX(Cost_Components!$U$2:$U$6,MATCH(E10,Cost_Components!$A$2:$A$6,0)),"") -> 2025 | AB10: =IFERROR(INDEX(Cost_Components!$V$2:$V$6,MATCH(E10,Cost_Components!$A$2:$A$6,0)),"") -> 2040 | AC10: =IFERROR(INDEX(Cost_Components!$M$2:$M$6,MATCH(E10,Cost_Components!$A$2:$A$6,0)),"") -> 30 | AD10: =IFERROR(INDEX(Cost_Components!$N$2:$N$6,MATCH(E10,Cost_Components!$A$2:$A$6,0)),"") -> 95 | AE10: =IFERROR(INDEX(Cost_Components!$O$2:$O$6,MATCH(E10,Cost_Components!$A$2:$A$6,0)),"") -> Both | AF10: 1.688645e+08 | AG10: 1.690249e+08 | AH10: =IF(H10="shared-count-once",COUNTIFS($A$2:$A$131,A10,$B$2:$B$131,B10,$E$2:$E$131,E10),1) -> 1
A11: S_70_30_30_TO_70_70_70 | B11: 2034 | C11: I_CVD_PRIMARY | E11: COST_PRIMARY_SCREEN_A | F11: CC_PRIMARY_SCREENING | G11: I_CVD_PRIMARY__C_SHARED | H11: shared-count-once | I11: all | J11: =IFERROR(INDEX(Cost_Components!$K$2:$K$6,MATCH(E11,Cost_Components!$A$2:$A$6,0)),"") -> 0.2 | K11: 0.2485 | L11: =IFERROR(INDEX(Cost_Components!$S$2:$S$6,MATCH(E11,Cost_Components!$A$2:$A$6,0)),"") -> 0.11376686 | M11: =IFERROR(INDEX(Cost_Components!$L$2:$L$6,MATCH(E11,Cost_Components!$A$2:$A$6,0)),"") -> 1 | N11: =IFERROR(INDEX(Cost_Components!$P$2:$P$6,MATCH(E11,Cost_Components!$A$2:$A$6,0)),"") -> 1.291584 | O11: =AF11*J11 -> 34203334 | P11: =AG11*J11 -> 34229811 | Q11: =P11*L11*M11*N11 -> 5029709.7 | R11: =O11*K11*M11*N11 -> 10977855 | S11: =R11-Q11 -> 5948145.4 | T11: =IFERROR(INDEX(Cost_Components!$R$2:$R$6,MATCH(E11,Cost_Components!$A$2:$A$6,0)),"") -> 1 | U11: =IFERROR(INDEX(Cost_Components!$Q$2:$Q$6,MATCH(E11,Cost_Components!$A$2:$A$6,0)),"") -> 2023 | V11: =1/(1+Calculation_Assumptions!$B$5)^(B11-Calculation_Assumptions!$B$2) -> 0.76641673 | W11: =Q11*V11 -> 3854853.7 | X11: =R11*V11 -> 8413611.8 | Y11: =S11*V11 -> 4558758.1 | Z11: =IFERROR(INDEX(Cost_Components!$T$2:$T$6,MATCH(E11,Cost_Components!$A$2:$A$6,0)),"") -> 0.4165 | AA11: =IFERROR(INDEX(Cost_Components!$U$2:$U$6,MATCH(E11,Cost_Components!$A$2:$A$6,0)),"") -> 2025 | AB11: =IFERROR(INDEX(Cost_Components!$V$2:$V$6,MATCH(E11,Cost_Components!$A$2:$A$6,0)),"") -> 2040 | AC11: =IFERROR(INDEX(Cost_Components!$M$2:$M$6,MATCH(E11,Cost_Components!$A$2:$A$6,0)),"") -> 30 | AD11: =IFERROR(INDEX(Cost_Components!$N$2:$N$6,MATCH(E11,Cost_Components!$A$2:$A$6,0)),"") -> 95 | AE11: =IFERROR(INDEX(Cost_Components!$O$2:$O$6,MATCH(E11,Cost_Components!$A$2:$A$6,0)),"") -> Both | AF11: 1.7101667e+08 | AG11: 1.7114905e+08 | AH11: =IF(H11="shared-count-once",COUNTIFS($A$2:$A$131,A11,$B$2:$B$131,B11,$E$2:$E$131,E11),1) -> 1
A12: S_70_30_30_TO_70_70_70 | B12: 2035 | C12: I_CVD_PRIMARY | E12: COST_PRIMARY_SCREEN_A | F12: CC_PRIMARY_SCREENING | G12: I_CVD_PRIMARY__C_SHARED | H12: shared-count-once | I12: all | J12: =IFERROR(INDEX(Cost_Components!$K$2:$K$6,MATCH(E12,Cost_Components!$A$2:$A$6,0)),"") -> 0.2 | K12: 0.2765 | L12: =IFERROR(INDEX(Cost_Components!$S$2:$S$6,MATCH(E12,Cost_Components!$A$2:$A$6,0)),"") -> 0.11376686 | M12: =IFERROR(INDEX(Cost_Components!$L$2:$L$6,MATCH(E12,Cost_Components!$A$2:$A$6,0)),"") -> 1 | N12: =IFERROR(INDEX(Cost_Components!$P$2:$P$6,MATCH(E12,Cost_Components!$A$2:$A$6,0)),"") -> 1.291584 | O12: =AF12*J12 -> 34646568 | P12: =AG12*J12 -> 34666732 | Q12: =P12*L12*M12*N12 -> 5093910.6 | R12: =O12*K12*M12*N12 -> 12373086 | S12: =R12-Q12 -> 7279175 | T12: =IFERROR(INDEX(Cost_Components!$R$2:$R$6,MATCH(E12,Cost_Components!$A$2:$A$6,0)),"") -> 1 | U12: =IFERROR(INDEX(Cost_Components!$Q$2:$Q$6,MATCH(E12,Cost_Components!$A$2:$A$6,0)),"") -> 2023 | V12: =1/(1+Calculation_Assumptions!$B$5)^(B12-Calculation_Assumptions!$B$2) -> 0.74409391 | W12: =Q12*V12 -> 3790347.9 | X12: =R12*V12 -> 9206737.7 | Y12: =S12*V12 -> 5416389.8 | Z12: =IFERROR(INDEX(Cost_Components!$T$2:$T$6,MATCH(E12,Cost_Components!$A$2:$A$6,0)),"") -> 0.4165 | AA12: =IFERROR(INDEX(Cost_Components!$U$2:$U$6,MATCH(E12,Cost_Components!$A$2:$A$6,0)),"") -> 2025 | AB12: =IFERROR(INDEX(Cost_Components!$V$2:$V$6,MATCH(E12,Cost_Components!$A$2:$A$6,0)),"") -> 2040 | AC12: =IFERROR(INDEX(Cost_Components!$M$2:$M$6,MATCH(E12,Cost_Components!$A$2:$A$6,0)),"") -> 30 | AD12: =IFERROR(INDEX(Cost_Components!$N$2:$N$6,MATCH(E12,Cost_Components!$A$2:$A$6,0)),"") -> 95 | AE12: =IFERROR(INDEX(Cost_Components!$O$2:$O$6,MATCH(E12,Cost_Components!$A$2:$A$6,0)),"") -> Both | AF12: 1.7323284e+08 | AG12: 1.7333366e+08 | AH12: =IF(H12="shared-count-once",COUNTIFS($A$2:$A$131,A12,$B$2:$B$131,B12,$E$2:$E$131,E12),1) -> 1
A13: S_70_30_30_TO_70_70_70 | B13: 2036 | C13: I_CVD_PRIMARY | E13: COST_PRIMARY_SCREEN_A | F13: CC_PRIMARY_SCREENING | G13: I_CVD_PRIMARY__C_SHARED | H13: shared-count-once | I13: all | J13: =IFERROR(INDEX(Cost_Components!$K$2:$K$6,MATCH(E13,Cost_Components!$A$2:$A$6,0)),"") -> 0.2 | K13: 0.3045 | L13: =IFERROR(INDEX(Cost_Components!$S$2:$S$6,MATCH(E13,Cost_Components!$A$2:$A$6,0)),"") -> 0.11376686 | M13: =IFERROR(INDEX(Cost_Components!$L$2:$L$6,MATCH(E13,Cost_Components!$A$2:$A$6,0)),"") -> 1 | N13: =IFERROR(INDEX(Cost_Components!$P$2:$P$6,MATCH(E13,Cost_Components!$A$2:$A$6,0)),"") -> 1.291584 | O13: =AF13*J13 -> 35101379 | P13: =AG13*J13 -> 35114478 | Q13: =P13*L13*M13*N13 -> 5159702.2 | R13: =O13*K13*M13*N13 -> 13804928 | S13: =R13-Q13 -> 8645225.5 | T13: =IFERROR(INDEX(Cost_Components!$R$2:$R$6,MATCH(E13,Cost_Components!$A$2:$A$6,0)),"") -> 1 | U13: =IFERROR(INDEX(Cost_Components!$Q$2:$Q$6,MATCH(E13,Cost_Components!$A$2:$A$6,0)),"") -> 2023 | V13: =1/(1+Calculation_Assumptions!$B$5)^(B13-Calculation_Assumptions!$B$2) -> 0.72242128 | W13: =Q13*V13 -> 3727478.6 | X13: =R13*V13 -> 9972973.4 | Y13: =S13*V13 -> 6245494.8 | Z13: =IFERROR(INDEX(Cost_Components!$T$2:$T$6,MATCH(E13,Cost_Components!$A$2:$A$6,0)),"") -> 0.4165 | AA13: =IFERROR(INDEX(Cost_Components!$U$2:$U$6,MATCH(E13,Cost_Components!$A$2:$A$6,0)),"") -> 2025 | AB13: =IFERROR(INDEX(Cost_Components!$V$2:$V$6,MATCH(E13,Cost_Components!$A$2:$A$6,0)),"") -> 2040 | AC13: =IFERROR(INDEX(Cost_Components!$M$2:$M$6,MATCH(E13,Cost_Components!$A$2:$A$6,0)),"") -> 30 | AD13: =IFERROR(INDEX(Cost_Components!$N$2:$N$6,MATCH(E13,Cost_Components!$A$2:$A$6,0)),"") -> 95 | AE13: =IFERROR(INDEX(Cost_Components!$O$2:$O$6,MATCH(E13,Cost_Components!$A$2:$A$6,0)),"") -> Both | AF13: 1.755069e+08 | AG13: 1.7557239e+08 | AH13: =IF(H13="shared-count-once",COUNTIFS($A$2:$A$131,A13,$B$2:$B$131,B13,$E$2:$E$131,E13),1) -> 1
... A53: S_70_30_30_TO_70_70_70 | B53: 2050 | C53: I_CVD_PRIMARY | E53: COST_PRIMARY_TX_A | F53: CC_PRIMARY_HTN_STATIN | G53: I_CVD_PRIMARY__C_SHARED | H53: shared-count-once | I53: all | J53: =IFERROR(INDEX(Cost_Components!$K$2:$K$6,MATCH(E53,Cost_Components!$A$2:$A$6,0)),"") -> 0.06 | K53: 0.4165 | L53: =IFERROR(INDEX(Cost_Components!$S$2:$S$6,MATCH(E53,Cost_Components!$A$2:$A$6,0)),"") -> 0.11376686 | M53: =IFERROR(INDEX(Cost_Components!$L$2:$L$6,MATCH(E53,Cost_Components!$A$2:$A$6,0)),"") -> 1 | N53: =IFERROR(INDEX(Cost_Components!$P$2:$P$6,MATCH(E53,Cost_Components!$A$2:$A$6,0)),"") -> 22.2296 | O53: =AF53*J53 -> 12187255 | P53: =AG53*J53 -> 12135578 | Q53: =P53*L53*M53*N53 -> 30690776 | R53: =O53*K53*M53*N53 -> 1.1283727e+08 | S53: =R53-Q53 -> 82146489 | T53: =IFERROR(INDEX(Cost_Components!$R$2:$R$6,MATCH(E53,Cost_Components!$A$2:$A$6,0)),"") -> 1 | U53: =IFERROR(INDEX(Cost_Components!$Q$2:$Q$6,MATCH(E53,Cost_Components!$A$2:$A$6,0)),"") -> 2023 | V53: =1/(1+Calculation_Assumptions!$B$5)^(B53-Calculation_Assumptions!$B$2) -> 0.47760557 | W53: =Q53*V53 -> 14658086 | X53: =R53*V53 -> 53891706 | Y53: =S53*V53 -> 39233621 | Z53: =IFERROR(INDEX(Cost_Components!$T$2:$T$6,MATCH(E53,Cost_Components!$A$2:$A$6,0)),"") -> 0.4165 | AA53: =IFERROR(INDEX(Cost_Components!$U$2:$U$6,MATCH(E53,Cost_Components!$A$2:$A$6,0)),"") -> 2025 | AB53: =IFERROR(INDEX(Cost_Components!$V$2:$V$6,MATCH(E53,Cost_Components!$A$2:$A$6,0)),"") -> 2040 | AC53: =IFERROR(INDEX(Cost_Components!$M$2:$M$6,MATCH(E53,Cost_Components!$A$2:$A$6,0)),"") -> 30 | AD53: =IFERROR(INDEX(Cost_Components!$N$2:$N$6,MATCH(E53,Cost_Components!$A$2:$A$6,0)),"") -> 95 | AE53: =IFERROR(INDEX(Cost_Components!$O$2:$O$6,MATCH(E53,Cost_Components!$A$2:$A$6,0)),"") -> Both | AF53: 2.0312092e+08 | AG53: 2.0225963e+08 | AH53: =IF(H53="shared-count-once",COUNTIFS($A$2:$A$131,A53,$B$2:$B$131,B53,$E$2:$E$131,E53),1) -> 1
A54: S_70_30_30_TO_70_70_70 | B54: 2025 | C54: I_T2D_TREATMENT | D54: dm2 | E54: COST_T2D_SCREEN | F54: CC_T2D_SCREENING | G54: I_T2D_TREATMENT__C_T2D | H54: cause-specific | I54: all | J54: =IFERROR(INDEX(Cost_Components!$K$2:$K$6,MATCH(E54,Cost_Components!$A$2:$A$6,0)),"") -> 0.2 | K54: 0.14791461 | L54: =IFERROR(INDEX(Cost_Components!$S$2:$S$6,MATCH(E54,Cost_Components!$A$2:$A$6,0)),"") -> 0.14791461 | M54: =IFERROR(INDEX(Cost_Components!$L$2:$L$6,MATCH(E54,Cost_Components!$A$2:$A$6,0)),"") -> 1 | N54: =IFERROR(INDEX(Cost_Components!$P$2:$P$6,MATCH(E54,Cost_Components!$A$2:$A$6,0)),"") -> 0.70495848 | O54: =AF54*J54 -> 30364900 | P54: =AG54*J54 -> 30364900 | Q54: =P54*L54*M54*N54 -> 3166259.2 | R54: =O54*K54*M54*N54 -> 3166259.2 | S54: =R54-Q54 -> 0 | T54: =IFERROR(INDEX(Cost_Components!$R$2:$R$6,MATCH(E54,Cost_Components!$A$2:$A$6,0)),"") -> 1 | U54: =IFERROR(INDEX(Cost_Components!$Q$2:$Q$6,MATCH(E54,Cost_Components!$A$2:$A$6,0)),"") -> 2023 | V54: =1/(1+Calculation_Assumptions!$B$5)^(B54-Calculation_Assumptions!$B$2) -> 1 | W54: =Q54*V54 -> 3166259.2 | X54: =R54*V54 -> 3166259.2 | Y54: =S54*V54 -> 0 | Z54: =IFERROR(INDEX(Cost_Components!$T$2:$T$6,MATCH(E54,Cost_Components!$A$2:$A$6,0)),"") -> 0.4165 | AA54: =IFERROR(INDEX(Cost_Components!$U$2:$U$6,MATCH(E54,Cost_Components!$A$2:$A$6,0)),"") -> 2025 | AB54: =IFERROR(INDEX(Cost_Components!$V$2:$V$6,MATCH(E54,Cost_Components!$A$2:$A$6,0)),"") -> 2040 | AC54: =IFERROR(INDEX(Cost_Components!$M$2:$M$6,MATCH(E54,Cost_Components!$A$2:$A$6,0)),"") -> 30 | AD54: =IFERROR(INDEX(Cost_Components!$N$2:$N$6,MATCH(E54,Cost_Components!$A$2:$A$6,0)),"") -> 95 | AE54: =IFERROR(INDEX(Cost_Components!$O$2:$O$6,MATCH(E54,Cost_Components!$A$2:$A$6,0)),"") -> Both | AF54: 1.518245e+08 | AG54: 1.518245e+08 | AH54: =IF(H54="shared-count-once",COUNTIFS($A$2:$A$131,A54,$B$2:$B$131,B54,$E$2:$E$131,E54),1) -> 1
A55: S_70_30_30_TO_70_70_70 | B55: 2026 | C55: I_T2D_TREATMENT | D55: dm2 | E55: COST_T2D_SCREEN | F55: CC_T2D_SCREENING | G55: I_T2D_TREATMENT__C_T2D | H55: cause-specific | I55: all | J55: =IFERROR(INDEX(Cost_Components!$K$2:$K$6,MATCH(E55,Cost_Components!$A$2:$A$6,0)),"") -> 0.2 | K55: 0.14853346 | L55: =IFERROR(INDEX(Cost_Components!$S$2:$S$6,MATCH(E55,Cost_Components!$A$2:$A$6,0)),"") -> 0.14791461 | M55: =IFERROR(INDEX(Cost_Components!$L$2:$L$6,MATCH(E55,Cost_Components!$A$2:$A$6,0)),"") -> 1 | N55: =IFERROR(INDEX(Cost_Components!$P$2:$P$6,MATCH(E55,Cost_Components!$A$2:$A$6,0)),"") -> 0.70495848 | O55: =AF55*J55 -> 30765556 | P55: =AG55*J55 -> 30765556 | Q55: =P55*L55*M55*N55 -> 3208037.1 | R55: =O55*K55*M55*N55 -> 3221458.9 | S55: =R55-Q55 -> 13421.83 | T55: =IFERROR(INDEX(Cost_Components!$R$2:$R$6,MATCH(E55,Cost_Components!$A$2:$A$6,0)),"") -> 1 | U55: =IFERROR(INDEX(Cost_Components!$Q$2:$Q$6,MATCH(E55,Cost_Components!$A$2:$A$6,0)),"") -> 2023 | V55: =1/(1+Calculation_Assumptions!$B$5)^(B55-Calculation_Assumptions!$B$2) -> 0.97087379 | W55: =Q55*V55 -> 3114599.1 | X55: =R55*V55 -> 3127630 | Y55: =S55*V55 -> 13030.903 | Z55: =IFERROR(INDEX(Cost_Components!$T$2:$T$6,MATCH(E55,Cost_Components!$A$2:$A$6,0)),"") -> 0.4165 | AA55: =IFERROR(INDEX(Cost_Components!$U$2:$U$6,MATCH(E55,Cost_Components!$A$2:$A$6,0)),"") -> 2025 | AB55: =IFERROR(INDEX(Cost_Components!$V$2:$V$6,MATCH(E55,Cost_Components!$A$2:$A$6,0)),"") -> 2040 | AC55: =IFERROR(INDEX(Cost_Components!$M$2:$M$6,MATCH(E55,Cost_Components!$A$2:$A$6,0)),"") -> 30 | AD55: =IFERROR(INDEX(Cost_Components!$N$2:$N$6,MATCH(E55,Cost_Components!$A$2:$A$6,0)),"") -> 95 | AE55: =IFERROR(INDEX(Cost_Components!$O$2:$O$6,MATCH(E55,Cost_Components!$A$2:$A$6,0)),"") -> Both | AF55: 1.5382778e+08 | AG55: 1.5382778e+08 | AH55: =IF(H55="shared-count-once",COUNTIFS($A$2:$A$131,A55,$B$2:$B$131,B55,$E$2:$E$131,E55),1) -> 1
A56: S_70_30_30_TO_70_70_70 | B56: 2027 | C56: I_T2D_TREATMENT | D56: dm2 | E56: COST_T2D_SCREEN | F56: CC_T2D_SCREENING | G56: I_T2D_TREATMENT__C_T2D | H56: cause-specific | I56: all | J56: =IFERROR(INDEX(Cost_Components!$K$2:$K$6,MATCH(E56,Cost_Components!$A$2:$A$6,0)),"") -> 0.2 | K56: 0.14915231 | L56: =IFERROR(INDEX(Cost_Components!$S$2:$S$6,MATCH(E56,Cost_Components!$A$2:$A$6,0)),"") -> 0.14791461 | M56: =IFERROR(INDEX(Cost_Components!$L$2:$L$6,MATCH(E56,Cost_Components!$A$2:$A$6,0)),"") -> 1 | N56: =IFERROR(INDEX(Cost_Components!$P$2:$P$6,MATCH(E56,Cost_Components!$A$2:$A$6,0)),"") -> 0.70495848 | O56: =AF56*J56 -> 31208345 | P56: =AG56*J56 -> 31208338 | Q56: =P56*L56*M56*N56 -> 3254207.6 | R56: =O56*K56*M56*N56 -> 3281438.4 | S56: =R56-Q56 -> 27230.77 | T56: =IFERROR(INDEX(Cost_Components!$R$2:$R$6,MATCH(E56,Cost_Components!$A$2:$A$6,0)),"") -> 1 | U56: =IFERROR(INDEX(Cost_Components!$Q$2:$Q$6,MATCH(E56,Cost_Components!$A$2:$A$6,0)),"") -> 2023 | V56: =1/(1+Calculation_Assumptions!$B$5)^(B56-Calculation_Assumptions!$B$2) -> 0.94259591 | W56: =Q56*V56 -> 3067402.8 | X56: =R56*V56 -> 3093070.4 | Y56: =S56*V56 -> 25667.612 | Z56: =IFERROR(INDEX(Cost_Components!$T$2:$T$6,MATCH(E56,Cost_Components!$A$2:$A$6,0)),"") -> 0.4165 | AA56: =IFERROR(INDEX(Cost_Components!$U$2:$U$6,MATCH(E56,Cost_Components!$A$2:$A$6,0)),"") -> 2025 | AB56: =IFERROR(INDEX(Cost_Components!$V$2:$V$6,MATCH(E56,Cost_Components!$A$2:$A$6,0)),"") -> 2040 | AC56: =IFERROR(INDEX(Cost_Components!$M$2:$M$6,MATCH(E56,Cost_Components!$A$2:$A$6,0)),"") -> 30 | AD56: =IFERROR(INDEX(Cost_Components!$N$2:$N$6,MATCH(E56,Cost_Components!$A$2:$A$6,0)),"") -> 95 | AE56: =IFERROR(INDEX(Cost_Components!$O$2:$O$6,MATCH(E56,Cost_Components!$A$2:$A$6,0)),"") -> Both | AF56: 1.5604173e+08 | AG56: 1.5604169e+08 | AH56: =IF(H56="shared-count-once",COUNTIFS($A$2:$A$131,A56,$B$2:$B$131,B56,$E$2:$E$131,E56),1) -> 1
A57: S_70_30_30_TO_70_70_70 | B57: 2028 | C57: I_T2D_TREATMENT | D57: dm2 | E57: COST_T2D_SCREEN | F57: CC_T2D_SCREENING | G57: I_T2D_TREATMENT__C_T2D | H57: cause-specific | I57: all | J57: =IFERROR(INDEX(Cost_Components!$K$2:$K$6,MATCH(E57,Cost_Components!$A$2:$A$6,0)),"") -> 0.2 | K57: 0.14977115 | L57: =IFERROR(INDEX(Cost_Components!$S$2:$S$6,MATCH(E57,Cost_Components!$A$2:$A$6,0)),"") -> 0.14791461 | M57: =IFERROR(INDEX(Cost_Components!$L$2:$L$6,MATCH(E57,Cost_Components!$A$2:$A$6,0)),"") -> 1 | N57: =IFERROR(INDEX(Cost_Components!$P$2:$P$6,MATCH(E57,Cost_Components!$A$2:$A$6,0)),"") -> 0.70495848 | O57: =AF57*J57 -> 31656678 | P57: =AG57*J57 -> 31656609 | Q57: =P57*L57*M57*N57 -> 3300950.5 | R57: =O57*K57*M57*N57 -> 3342389.4 | S57: =R57-Q57 -> 41438.911 | T57: =IFERROR(INDEX(Cost_Components!$R$2:$R$6,MATCH(E57,Cost_Components!$A$2:$A$6,0)),"") -> 1 | U57: =IFERROR(INDEX(Cost_Components!$Q$2:$Q$6,MATCH(E57,Cost_Components!$A$2:$A$6,0)),"") -> 2023 | V57: =1/(1+Calculation_Assumptions!$B$5)^(B57-Calculation_Assumptions!$B$2) -> 0.91514166 | W57: =Q57*V57 -> 3020837.3 | X57: =R57*V57 -> 3058759.8 | Y57: =S57*V57 -> 37922.473 | Z57: =IFERROR(INDEX(Cost_Components!$T$2:$T$6,MATCH(E57,Cost_Components!$A$2:$A$6,0)),"") -> 0.4165 | AA57: =IFERROR(INDEX(Cost_Components!$U$2:$U$6,MATCH(E57,Cost_Components!$A$2:$A$6,0)),"") -> 2025 | AB57: =IFERROR(INDEX(Cost_Components!$V$2:$V$6,MATCH(E57,Cost_Components!$A$2:$A$6,0)),"") -> 2040 | AC57: =IFERROR(INDEX(Cost_Components!$M$2:$M$6,MATCH(E57,Cost_Components!$A$2:$A$6,0)),"") -> 30 | AD57: =IFERROR(INDEX(Cost_Components!$N$2:$N$6,MATCH(E57,Cost_Components!$A$2:$A$6,0)),"") -> 95 | AE57: =IFERROR(INDEX(Cost_Components!$O$2:$O$6,MATCH(E57,Cost_Components!$A$2:$A$6,0)),"") -> Both | AF57: 1.5828339e+08 | AG57: 1.5828305e+08 | AH57: =IF(H57="shared-count-once",COUNTIFS($A$2:$A$131,A57,$B$2:$B$131,B57,$E$2:$E$131,E57),1) -> 1
A58: S_70_30_30_TO_70_70_70 | B58: 2029 | C58: I_T2D_TREATMENT | D58: dm2 | E58: COST_T2D_SCREEN | F58: CC_T2D_SCREENING | G58: I_T2D_TREATMENT__C_T2D | H58: cause-specific | I58: all | J58: =IFERROR(INDEX(Cost_Components!$K$2:$K$6,MATCH(E58,Cost_Components!$A$2:$A$6,0)),"") -> 0.2 | K58: 0.15039 | L58: =IFERROR(INDEX(Cost_Components!$S$2:$S$6,MATCH(E58,Cost_Components!$A$2:$A$6,0)),"") -> 0.14791461 | M58: =IFERROR(INDEX(Cost_Components!$L$2:$L$6,MATCH(E58,Cost_Components!$A$2:$A$6,0)),"") -> 1 | N58: =IFERROR(INDEX(Cost_Components!$P$2:$P$6,MATCH(E58,Cost_Components!$A$2:$A$6,0)),"") -> 0.70495848 | O58: =AF58*J58 -> 32100475 | P58: =AG58*J58 -> 32100264 | Q58: =P58*L58*M58*N58 -> 3347212 | R58: =O58*K58*M58*N58 -> 3403250.8 | S58: =R58-Q58 -> 56038.837 | T58: =IFERROR(INDEX(Cost_Components!$R$2:$R$6,MATCH(E58,Cost_Components!$A$2:$A$6,0)),"") -> 1 | U58: =IFERROR(INDEX(Cost_Components!$Q$2:$Q$6,MATCH(E58,Cost_Components!$A$2:$A$6,0)),"") -> 2023 | V58: =1/(1+Calculation_Assumptions!$B$5)^(B58-Calculation_Assumptions!$B$2) -> 0.88848705 | W58: =Q58*V58 -> 2973954.5 | X58: =R58*V58 -> 3023744.3 | Y58: =S58*V58 -> 49789.781 | Z58: =IFERROR(INDEX(Cost_Components!$T$2:$T$6,MATCH(E58,Cost_Components!$A$2:$A$6,0)),"") -> 0.4165 | AA58: =IFERROR(INDEX(Cost_Components!$U$2:$U$6,MATCH(E58,Cost_Components!$A$2:$A$6,0)),"") -> 2025 | AB58: =IFERROR(INDEX(Cost_Components!$V$2:$V$6,MATCH(E58,Cost_Components!$A$2:$A$6,0)),"") -> 2040 | AC58: =IFERROR(INDEX(Cost_Components!$M$2:$M$6,MATCH(E58,Cost_Components!$A$2:$A$6,0)),"") -> 30 | AD58: =IFERROR(INDEX(Cost_Components!$N$2:$N$6,MATCH(E58,Cost_Components!$A$2:$A$6,0)),"") -> 95 | AE58: =IFERROR(INDEX(Cost_Components!$O$2:$O$6,MATCH(E58,Cost_Components!$A$2:$A$6,0)),"") -> Both | AF58: 1.6050237e+08 | AG58: 1.6050132e+08 | AH58: =IF(H58="shared-count-once",COUNTIFS($A$2:$A$131,A58,$B$2:$B$131,B58,$E$2:$E$131,E58),1) -> 1
A59: S_70_30_30_TO_70_70_70 | B59: 2030 | C59: I_T2D_TREATMENT | D59: dm2 | E59: COST_T2D_SCREEN | F59: CC_T2D_SCREENING | G59: I_T2D_TREATMENT__C_T2D | H59: cause-specific | I59: all | J59: =IFERROR(INDEX(Cost_Components!$K$2:$K$6,MATCH(E59,Cost_Components!$A$2:$A$6,0)),"") -> 0.2 | K59: 0.15100885 | L59: =IFERROR(INDEX(Cost_Components!$S$2:$S$6,MATCH(E59,Cost_Components!$A$2:$A$6,0)),"") -> 0.14791461 | M59: =IFERROR(INDEX(Cost_Components!$L$2:$L$6,MATCH(E59,Cost_Components!$A$2:$A$6,0)),"") -> 1 | N59: =IFERROR(INDEX(Cost_Components!$P$2:$P$6,MATCH(E59,Cost_Components!$A$2:$A$6,0)),"") -> 0.70495848 | O59: =AF59*J59 -> 32490352 | P59: =AG59*J59 -> 32530776 | Q59: =P59*L59*M59*N59 -> 3392103.1 | R59: =O59*K59*M59*N59 -> 3458759.4 | S59: =R59-Q59 -> 66656.306 | T59: =IFERROR(INDEX(Cost_Components!$R$2:$R$6,MATCH(E59,Cost_Components!$A$2:$A$6,0)),"") -> 1 | U59: =IFERROR(INDEX(Cost_Components!$Q$2:$Q$6,MATCH(E59,Cost_Components!$A$2:$A$6,0)),"") -> 2023 | V59: =1/(1+Calculation_Assumptions!$B$5)^(B59-Calculation_Assumptions!$B$2) -> 0.86260878 | W59: =Q59*V59 -> 2926058 | X59: =R59*V59 -> 2983556.3 | Y59: =S59*V59 -> 57498.315 | Z59: =IFERROR(INDEX(Cost_Components!$T$2:$T$6,MATCH(E59,Cost_Components!$A$2:$A$6,0)),"") -> 0.4165 | AA59: =IFERROR(INDEX(Cost_Components!$U$2:$U$6,MATCH(E59,Cost_Components!$A$2:$A$6,0)),"") -> 2025 | AB59: =IFERROR(INDEX(Cost_Components!$V$2:$V$6,MATCH(E59,Cost_Components!$A$2:$A$6,0)),"") -> 2040 | AC59: =IFERROR(INDEX(Cost_Components!$M$2:$M$6,MATCH(E59,Cost_Components!$A$2:$A$6,0)),"") -> 30 | AD59: =IFERROR(INDEX(Cost_Components!$N$2:$N$6,MATCH(E59,Cost_Components!$A$2:$A$6,0)),"") -> 95 | AE59: =IFERROR(INDEX(Cost_Components!$O$2:$O$6,MATCH(E59,Cost_Components!$A$2:$A$6,0)),"") -> Both | AF59: 1.6245176e+08 | AG59: 1.6265388e+08 | AH59: =IF(H59="shared-count-once",COUNTIFS($A$2:$A$131,A59,$B$2:$B$131,B59,$E$2:$E$131,E59),1) -> 1
A60: S_70_30_30_TO_70_70_70 | B60: 2031 | C60: I_T2D_TREATMENT | D60: dm2 | E60: COST_T2D_SCREEN | F60: CC_T2D_SCREENING | G60: I_T2D_TREATMENT__C_T2D | H60: cause-specific | I60: all | J60: =IFERROR(INDEX(Cost_Components!$K$2:$K$6,MATCH(E60,Cost_Components!$A$2:$A$6,0)),"") -> 0.2 | K60: 0.17755796 | L60: =IFERROR(INDEX(Cost_Components!$S$2:$S$6,MATCH(E60,Cost_Components!$A$2:$A$6,0)),"") -> 0.14791461 | M60: =IFERROR(INDEX(Cost_Components!$L$2:$L$6,MATCH(E60,Cost_Components!$A$2:$A$6,0)),"") -> 1 | N60: =IFERROR(INDEX(Cost_Components!$P$2:$P$6,MATCH(E60,Cost_Components!$A$2:$A$6,0)),"") -> 0.70495848 | O60: =AF60*J60 -> 32921479 | P60: =AG60*J60 -> 32956928 | Q60: =P60*L60*M60*N60 -> 3436539.5 | R60: =O60*K60*M60*N60 -> 4120814.1 | S60: =R60-Q60 -> 684274.6 | T60: =IFERROR(INDEX(Cost_Components!$R$2:$R$6,MATCH(E60,Cost_Components!$A$2:$A$6,0)),"") -> 1 | U60: =IFERROR(INDEX(Cost_Components!$Q$2:$Q$6,MATCH(E60,Cost_Components!$A$2:$A$6,0)),"") -> 2023 | V60: =1/(1+Calculation_Assumptions!$B$5)^(B60-Calculation_Assumptions!$B$2) -> 0.83748426 | W60: =Q60*V60 -> 2878047.7 | X60: =R60*V60 -> 3451117 | Y60: =S60*V60 -> 573069.21 | Z60: =IFERROR(INDEX(Cost_Components!$T$2:$T$6,MATCH(E60,Cost_Components!$A$2:$A$6,0)),"") -> 0.4165 | AA60: =IFERROR(INDEX(Cost_Components!$U$2:$U$6,MATCH(E60,Cost_Components!$A$2:$A$6,0)),"") -> 2025 | AB60: =IFERROR(INDEX(Cost_Components!$V$2:$V$6,MATCH(E60,Cost_Components!$A$2:$A$6,0)),"") -> 2040 | AC60: =IFERROR(INDEX(Cost_Components!$M$2:$M$6,MATCH(E60,Cost_Components!$A$2:$A$6,0)),"") -> 30 | AD60: =IFERROR(INDEX(Cost_Components!$N$2:$N$6,MATCH(E60,Cost_Components!$A$2:$A$6,0)),"") -> 95 | AE60: =IFERROR(INDEX(Cost_Components!$O$2:$O$6,MATCH(E60,Cost_Components!$A$2:$A$6,0)),"") -> Both | AF60: 1.6460739e+08 | AG60: 1.6478464e+08 | AH60: =IF(H60="shared-count-once",COUNTIFS($A$2:$A$131,A60,$B$2:$B$131,B60,$E$2:$E$131,E60),1) -> 1
A61: S_70_30_30_TO_70_70_70 | B61: 2032 | C61: I_T2D_TREATMENT | D61: dm2 | E61: COST_T2D_SCREEN | F61: CC_T2D_SCREENING | G61: I_T2D_TREATMENT__C_T2D | H61: cause-specific | I61: all | J61: =IFERROR(INDEX(Cost_Components!$K$2:$K$6,MATCH(E61,Cost_Components!$A$2:$A$6,0)),"") -> 0.2 | K61: 0.20410708 | L61: =IFERROR(INDEX(Cost_Components!$S$2:$S$6,MATCH(E61,Cost_Components!$A$2:$A$6,0)),"") -> 0.14791461 | M61: =IFERROR(INDEX(Cost_Components!$L$2:$L$6,MATCH(E61,Cost_Components!$A$2:$A$6,0)),"") -> 1 | N61: =IFERROR(INDEX(Cost_Components!$P$2:$P$6,MATCH(E61,Cost_Components!$A$2:$A$6,0)),"") -> 0.70495848 | O61: =AF61*J61 -> 33344844 | P61: =AG61*J61 -> 33381996 | Q61: =P61*L61*M61*N61 -> 3480862.9 | R61: =O61*K61*M61*N61 -> 4797890.1 | S61: =R61-Q61 -> 1317027.2 | T61: =IFERROR(INDEX(Cost_Components!$R$2:$R$6,MATCH(E61,Cost_Components!$A$2:$A$6,0)),"") -> 1 | U61: =IFERROR(INDEX(Cost_Components!$Q$2:$Q$6,MATCH(E61,Cost_Components!$A$2:$A$6,0)),"") -> 2023 | V61: =1/(1+Calculation_Assumptions!$B$5)^(B61-Calculation_Assumptions!$B$2) -> 0.81309151 | W61: =Q61*V61 -> 2830260.1 | X61: =R61*V61 -> 3901123.7 | Y61: =S61*V61 -> 1070863.7 | Z61: =IFERROR(INDEX(Cost_Components!$T$2:$T$6,MATCH(E61,Cost_Components!$A$2:$A$6,0)),"") -> 0.4165 | AA61: =IFERROR(INDEX(Cost_Components!$U$2:$U$6,MATCH(E61,Cost_Components!$A$2:$A$6,0)),"") -> 2025 | AB61: =IFERROR(INDEX(Cost_Components!$V$2:$V$6,MATCH(E61,Cost_Components!$A$2:$A$6,0)),"") -> 2040 | AC61: =IFERROR(INDEX(Cost_Components!$M$2:$M$6,MATCH(E61,Cost_Components!$A$2:$A$6,0)),"") -> 30 | AD61: =IFERROR(INDEX(Cost_Components!$N$2:$N$6,MATCH(E61,Cost_Components!$A$2:$A$6,0)),"") -> 95 | AE61: =IFERROR(INDEX(Cost_Components!$O$2:$O$6,MATCH(E61,Cost_Components!$A$2:$A$6,0)),"") -> Both | AF61: 1.6672422e+08 | AG61: 1.6690998e+08 | AH61: =IF(H61="shared-count-once",COUNTIFS($A$2:$A$131,A61,$B$2:$B$131,B61,$E$2:$E$131,E61),1) -> 1
A62: S_70_30_30_TO_70_70_70 | B62: 2033 | C62: I_T2D_TREATMENT | D62: dm2 | E62: COST_T2D_SCREEN | F62: CC_T2D_SCREENING | G62: I_T2D_TREATMENT__C_T2D | H62: cause-specific | I62: all | J62: =IFERROR(INDEX(Cost_Components!$K$2:$K$6,MATCH(E62,Cost_Components!$A$2:$A$6,0)),"") -> 0.2 | K62: 0.23065619 | L62: =IFERROR(INDEX(Cost_Components!$S$2:$S$6,MATCH(E62,Cost_Components!$A$2:$A$6,0)),"") -> 0.14791461 | M62: =IFERROR(INDEX(Cost_Components!$L$2:$L$6,MATCH(E62,Cost_Components!$A$2:$A$6,0)),"") -> 1 | N62: =IFERROR(INDEX(Cost_Components!$P$2:$P$6,MATCH(E62,Cost_Components!$A$2:$A$6,0)),"") -> 0.70495848 | O62: =AF62*J62 -> 33772899 | P62: =AG62*J62 -> 33804980 | Q62: =P62*L62*M62*N62 -> 3524969 | R62: =O62*K62*M62*N62 -> 5491576 | S62: =R62-Q62 -> 1966607.1 | T62: =IFERROR(INDEX(Cost_Components!$R$2:$R$6,MATCH(E62,Cost_Components!$A$2:$A$6,0)),"") -> 1 | U62: =IFERROR(INDEX(Cost_Components!$Q$2:$Q$6,MATCH(E62,Cost_Components!$A$2:$A$6,0)),"") -> 2023 | V62: =1/(1+Calculation_Assumptions!$B$5)^(B62-Calculation_Assumptions!$B$2) -> 0.78940923 | W62: =Q62*V62 -> 2782643 | X62: =R62*V62 -> 4335100.8 | Y62: =S62*V62 -> 1552457.8 | Z62: =IFERROR(INDEX(Cost_Components!$T$2:$T$6,MATCH(E62,Cost_Components!$A$2:$A$6,0)),"") -> 0.4165 | AA62: =IFERROR(INDEX(Cost_Components!$U$2:$U$6,MATCH(E62,Cost_Components!$A$2:$A$6,0)),"") -> 2025 | AB62: =IFERROR(INDEX(Cost_Components!$V$2:$V$6,MATCH(E62,Cost_Components!$A$2:$A$6,0)),"") -> 2040 | AC62: =IFERROR(INDEX(Cost_Components!$M$2:$M$6,MATCH(E62,Cost_Components!$A$2:$A$6,0)),"") -> 30 | AD62: =IFERROR(INDEX(Cost_Components!$N$2:$N$6,MATCH(E62,Cost_Components!$A$2:$A$6,0)),"") -> 95 | AE62: =IFERROR(INDEX(Cost_Components!$O$2:$O$6,MATCH(E62,Cost_Components!$A$2:$A$6,0)),"") -> Both | AF62: 1.688645e+08 | AG62: 1.690249e+08 | AH62: =IF(H62="shared-count-once",COUNTIFS($A$2:$A$131,A62,$B$2:$B$131,B62,$E$2:$E$131,E62),1) -> 1
A63: S_70_30_30_TO_70_70_70 | B63: 2034 | C63: I_T2D_TREATMENT | D63: dm2 | E63: COST_T2D_SCREEN | F63: CC_T2D_SCREENING | G63: I_T2D_TREATMENT__C_T2D | H63: cause-specific | I63: all | J63: =IFERROR(INDEX(Cost_Components!$K$2:$K$6,MATCH(E63,Cost_Components!$A$2:$A$6,0)),"") -> 0.2 | K63: 0.25720531 | L63: =IFERROR(INDEX(Cost_Components!$S$2:$S$6,MATCH(E63,Cost_Components!$A$2:$A$6,0)),"") -> 0.14791461 | M63: =IFERROR(INDEX(Cost_Components!$L$2:$L$6,MATCH(E63,Cost_Components!$A$2:$A$6,0)),"") -> 1 | N63: =IFERROR(INDEX(Cost_Components!$P$2:$P$6,MATCH(E63,Cost_Components!$A$2:$A$6,0)),"") -> 0.70495848 | O63: =AF63*J63 -> 34203334 | P63: =AG63*J63 -> 34229811 | Q63: =P63*L63*M63*N63 -> 3569267.7 | R63: =O63*K63*M63*N63 -> 6201716.5 | S63: =R63-Q63 -> 2632448.8 | T63: =IFERROR(INDEX(Cost_Components!$R$2:$R$6,MATCH(E63,Cost_Components!$A$2:$A$6,0)),"") -> 1 | U63: =IFERROR(INDEX(Cost_Components!$Q$2:$Q$6,MATCH(E63,Cost_Components!$A$2:$A$6,0)),"") -> 2023 | V63: =1/(1+Calculation_Assumptions!$B$5)^(B63-Calculation_Assumptions!$B$2) -> 0.76641673 | W63: =Q63*V63 -> 2735546.5 | X63: =R63*V63 -> 4753099.3 | Y63: =S63*V63 -> 2017552.8 | Z63: =IFERROR(INDEX(Cost_Components!$T$2:$T$6,MATCH(E63,Cost_Components!$A$2:$A$6,0)),"") -> 0.4165 | AA63: =IFERROR(INDEX(Cost_Components!$U$2:$U$6,MATCH(E63,Cost_Components!$A$2:$A$6,0)),"") -> 2025 | AB63: =IFERROR(INDEX(Cost_Components!$V$2:$V$6,MATCH(E63,Cost_Components!$A$2:$A$6,0)),"") -> 2040 | AC63: =IFERROR(INDEX(Cost_Components!$M$2:$M$6,MATCH(E63,Cost_Components!$A$2:$A$6,0)),"") -> 30 | AD63: =IFERROR(INDEX(Cost_Components!$N$2:$N$6,MATCH(E63,Cost_Components!$A$2:$A$6,0)),"") -> 95 | AE63: =IFERROR(INDEX(Cost_Components!$O$2:$O$6,MATCH(E63,Cost_Components!$A$2:$A$6,0)),"") -> Both | AF63: 1.7101667e+08 | AG63: 1.7114905e+08 | AH63: =IF(H63="shared-count-once",COUNTIFS($A$2:$A$131,A63,$B$2:$B$131,B63,$E$2:$E$131,E63),1) -> 1
A64: S_70_30_30_TO_70_70_70 | B64: 2035 | C64: I_T2D_TREATMENT | D64: dm2 | E64: COST_T2D_SCREEN | F64: CC_T2D_SCREENING | G64: I_T2D_TREATMENT__C_T2D | H64: cause-specific | I64: all | J64: =IFERROR(INDEX(Cost_Components!$K$2:$K$6,MATCH(E64,Cost_Components!$A$2:$A$6,0)),"") -> 0.2 | K64: 0.28375442 | L64: =IFERROR(INDEX(Cost_Components!$S$2:$S$6,MATCH(E64,Cost_Components!$A$2:$A$6,0)),"") -> 0.14791461 | M64: =IFERROR(INDEX(Cost_Components!$L$2:$L$6,MATCH(E64,Cost_Components!$A$2:$A$6,0)),"") -> 1 | N64: =IFERROR(INDEX(Cost_Components!$P$2:$P$6,MATCH(E64,Cost_Components!$A$2:$A$6,0)),"") -> 0.70495848 | O64: =AF64*J64 -> 34646568 | P64: =AG64*J64 -> 34666732 | Q64: =P64*L64*M64*N64 -> 3614827 | R64: =O64*K64*M64*N64 -> 6930529.3 | S64: =R64-Q64 -> 3315702.3 | T64: =IFERROR(INDEX(Cost_Components!$R$2:$R$6,MATCH(E64,Cost_Components!$A$2:$A$6,0)),"") -> 1 | U64: =IFERROR(INDEX(Cost_Components!$Q$2:$Q$6,MATCH(E64,Cost_Components!$A$2:$A$6,0)),"") -> 2023 | V64: =1/(1+Calculation_Assumptions!$B$5)^(B64-Calculation_Assumptions!$B$2) -> 0.74409391 | W64: =Q64*V64 -> 2689770.8 | X64: =R64*V64 -> 5156964.7 | Y64: =S64*V64 -> 2467193.9 | Z64: =IFERROR(INDEX(Cost_Components!$T$2:$T$6,MATCH(E64,Cost_Components!$A$2:$A$6,0)),"") -> 0.4165 | AA64: =IFERROR(INDEX(Cost_Components!$U$2:$U$6,MATCH(E64,Cost_Components!$A$2:$A$6,0)),"") -> 2025 | AB64: =IFERROR(INDEX(Cost_Components!$V$2:$V$6,MATCH(E64,Cost_Components!$A$2:$A$6,0)),"") -> 2040 | AC64: =IFERROR(INDEX(Cost_Components!$M$2:$M$6,MATCH(E64,Cost_Components!$A$2:$A$6,0)),"") -> 30 | AD64: =IFERROR(INDEX(Cost_Components!$N$2:$N$6,MATCH(E64,Cost_Components!$A$2:$A$6,0)),"") -> 95 | AE64: =IFERROR(INDEX(Cost_Components!$O$2:$O$6,MATCH(E64,Cost_Components!$A$2:$A$6,0)),"") -> Both | AF64: 1.7323284e+08 | AG64: 1.7333366e+08 | AH64: =IF(H64="shared-count-once",COUNTIFS($A$2:$A$131,A64,$B$2:$B$131,B64,$E$2:$E$131,E64),1) -> 1
A65: S_70_30_30_TO_70_70_70 | B65: 2036 | C65: I_T2D_TREATMENT | D65: dm2 | E65: COST_T2D_SCREEN | F65: CC_T2D_SCREENING | G65: I_T2D_TREATMENT__C_T2D | H65: cause-specific | I65: all | J65: =IFERROR(INDEX(Cost_Components!$K$2:$K$6,MATCH(E65,Cost_Components!$A$2:$A$6,0)),"") -> 0.2 | K65: 0.31030354 | L65: =IFERROR(INDEX(Cost_Components!$S$2:$S$6,MATCH(E65,Cost_Components!$A$2:$A$6,0)),"") -> 0.14791461 | M65: =IFERROR(INDEX(Cost_Components!$L$2:$L$6,MATCH(E65,Cost_Components!$A$2:$A$6,0)),"") -> 1 | N65: =IFERROR(INDEX(Cost_Components!$P$2:$P$6,MATCH(E65,Cost_Components!$A$2:$A$6,0)),"") -> 0.70495848 | O65: =AF65*J65 -> 35101379 | P65: =AG65*J65 -> 35114478 | Q65: =P65*L65*M65*N65 -> 3661515.1 | R65: =O65*K65*M65*N65 -> 7678465.7 | S65: =R65-Q65 -> 4016950.6 | T65: =IFERROR(INDEX(Cost_Components!$R$2:$R$6,MATCH(E65,Cost_Components!$A$2:$A$6,0)),"") -> 1 | U65: =IFERROR(INDEX(Cost_Components!$Q$2:$Q$6,MATCH(E65,Cost_Components!$A$2:$A$6,0)),"") -> 2023 | V65: =1/(1+Calculation_Assumptions!$B$5)^(B65-Calculation_Assumptions!$B$2) -> 0.72242128 | W65: =Q65*V65 -> 2645156.4 | X65: =R65*V65 -> 5547087 | Y65: =S65*V65 -> 2901930.5 | Z65: =IFERROR(INDEX(Cost_Components!$T$2:$T$6,MATCH(E65,Cost_Components!$A$2:$A$6,0)),"") -> 0.4165 | AA65: =IFERROR(INDEX(Cost_Components!$U$2:$U$6,MATCH(E65,Cost_Components!$A$2:$A$6,0)),"") -> 2025 | AB65: =IFERROR(INDEX(Cost_Components!$V$2:$V$6,MATCH(E65,Cost_Components!$A$2:$A$6,0)),"") -> 2040 | AC65: =IFERROR(INDEX(Cost_Components!$M$2:$M$6,MATCH(E65,Cost_Components!$A$2:$A$6,0)),"") -> 30 | AD65: =IFERROR(INDEX(Cost_Components!$N$2:$N$6,MATCH(E65,Cost_Components!$A$2:$A$6,0)),"") -> 95 | AE65: =IFERROR(INDEX(Cost_Components!$O$2:$O$6,MATCH(E65,Cost_Components!$A$2:$A$6,0)),"") -> Both | AF65: 1.755069e+08 | AG65: 1.7557239e+08 | AH65: =IF(H65="shared-count-once",COUNTIFS($A$2:$A$131,A65,$B$2:$B$131,B65,$E$2:$E$131,E65),1) -> 1
... A131: S_70_30_30_TO_70_70_70 | B131: 2050 | C131: I_T2D_TREATMENT | D131: dm2 | E131: COST_T2D_INSULIN | F131: CC_T2D_INSULIN | G131: I_T2D_TREATMENT__C_T2D | H131: cause-specific | I131: prevalence | J131: =IFERROR(INDEX(Cost_Components!$K$2:$K$6,MATCH(E131,Cost_Components!$A$2:$A$6,0)),"") -> 0.2 | K131: 0.4165 | L131: =IFERROR(INDEX(Cost_Components!$S$2:$S$6,MATCH(E131,Cost_Components!$A$2:$A$6,0)),"") -> 0.14791461 | M131: =IFERROR(INDEX(Cost_Components!$L$2:$L$6,MATCH(E131,Cost_Components!$A$2:$A$6,0)),"") -> 1 | N131: =IFERROR(INDEX(Cost_Components!$P$2:$P$6,MATCH(E131,Cost_Components!$A$2:$A$6,0)),"") -> 1154.0355 | O131: =AF131*J131 -> 3274485.5 | P131: =AG131*J131 -> 3243716.4 | Q131: =P131*L131*M131*N131 -> 5.5369822e+08 | R131: =O131*K131*M131*N131 -> 1.5739004e+09 | S131: =R131-Q131 -> 1.0202022e+09 | T131: =IFERROR(INDEX(Cost_Components!$R$2:$R$6,MATCH(E131,Cost_Components!$A$2:$A$6,0)),"") -> 1 | U131: =IFERROR(INDEX(Cost_Components!$Q$2:$Q$6,MATCH(E131,Cost_Components!$A$2:$A$6,0)),"") -> 2023 | V131: =1/(1+Calculation_Assumptions!$B$5)^(B131-Calculation_Assumptions!$B$2) -> 0.47760557 | W131: =Q131*V131 -> 2.6444935e+08 | X131: =R131*V131 -> 7.5170361e+08 | Y131: =S131*V131 -> 4.8725426e+08 | Z131: =IFERROR(INDEX(Cost_Components!$T$2:$T$6,MATCH(E131,Cost_Components!$A$2:$A$6,0)),"") -> 0.4165 | AA131: =IFERROR(INDEX(Cost_Components!$U$2:$U$6,MATCH(E131,Cost_Components!$A$2:$A$6,0)),"") -> 2025 | AB131: =IFERROR(INDEX(Cost_Components!$V$2:$V$6,MATCH(E131,Cost_Components!$A$2:$A$6,0)),"") -> 2040 | AC131: =IFERROR(INDEX(Cost_Components!$M$2:$M$6,MATCH(E131,Cost_Components!$A$2:$A$6,0)),"") -> 30 | AD131: =IFERROR(INDEX(Cost_Components!$N$2:$N$6,MATCH(E131,Cost_Components!$A$2:$A$6,0)),"") -> 95 | AE131: =IFERROR(INDEX(Cost_Components!$O$2:$O$6,MATCH(E131,Cost_Components!$A$2:$A$6,0)),"") -> Both | AF131: 16372428 | AG131: 16218582 | AH131: =IF(H131="shared-count-once",COUNTIFS($A$2:$A$131,A131,$B$2:$B$131,B131,$E$2:$E$131,E131),1) -> 1

Sheet Budget_Impact
A1: scenario | B1: year | C1: baseline_cost | D1: scenario_cost | E1: incremental_cost | F1: disc_incremental_cost | G1: cumulative_incremental_cost | H1: cumulative_disc_incremental_cost
A2: S_70_30_30_TO_70_70_70 | B2: 2025 | C2: =SUMIFS(Annual_Cost!$Q$2:$Q$131,Annual_Cost!$A$2:$A$131,A2,Annual_Cost!$B$2:$B$131,B2) -> 1.5493456e+09 | D2: =SUMIFS(Annual_Cost!$R$2:$R$131,Annual_Cost!$A$2:$A$131,A2,Annual_Cost!$B$2:$B$131,B2) -> 1.5493456e+09 | E2: =SUMIFS(Annual_Cost!$S$2:$S$131,Annual_Cost!$A$2:$A$131,A2,Annual_Cost!$B$2:$B$131,B2) -> 0 | F2: =SUMIFS(Annual_Cost!$Y$2:$Y$131,Annual_Cost!$A$2:$A$131,A2,Annual_Cost!$B$2:$B$131,B2) -> 0 | G2: =SUMIFS($E$2:E2,$A$2:A2,A2) -> 0 | H2: =SUMIFS($F$2:F2,$A$2:A2,A2) -> 0
A3: S_70_30_30_TO_70_70_70 | B3: 2026 | C3: =SUMIFS(Annual_Cost!$Q$2:$Q$131,Annual_Cost!$A$2:$A$131,A3,Annual_Cost!$B$2:$B$131,B3) -> 1.5557129e+09 | D3: =SUMIFS(Annual_Cost!$R$2:$R$131,Annual_Cost!$A$2:$A$131,A3,Annual_Cost!$B$2:$B$131,B3) -> 1.5632217e+09 | E3: =SUMIFS(Annual_Cost!$S$2:$S$131,Annual_Cost!$A$2:$A$131,A3,Annual_Cost!$B$2:$B$131,B3) -> 7508801 | F3: =SUMIFS(Annual_Cost!$Y$2:$Y$131,Annual_Cost!$A$2:$A$131,A3,Annual_Cost!$B$2:$B$131,B3) -> 7290098 | G3: =SUMIFS($E$2:E3,$A$2:A3,A3) -> 7508801 | H3: =SUMIFS($F$2:F3,$A$2:A3,A3) -> 7290098
A4: S_70_30_30_TO_70_70_70 | B4: 2027 | C4: =SUMIFS(Annual_Cost!$Q$2:$Q$131,Annual_Cost!$A$2:$A$131,A4,Annual_Cost!$B$2:$B$131,B4) -> 1.562571e+09 | D4: =SUMIFS(Annual_Cost!$R$2:$R$131,Annual_Cost!$A$2:$A$131,A4,Annual_Cost!$B$2:$B$131,B4) -> 1.5776775e+09 | E4: =SUMIFS(Annual_Cost!$S$2:$S$131,Annual_Cost!$A$2:$A$131,A4,Annual_Cost!$B$2:$B$131,B4) -> 15106492 | F4: =SUMIFS(Annual_Cost!$Y$2:$Y$131,Annual_Cost!$A$2:$A$131,A4,Annual_Cost!$B$2:$B$131,B4) -> 14239317 | G4: =SUMIFS($E$2:E4,$A$2:A4,A4) -> 22615293 | H4: =SUMIFS($F$2:F4,$A$2:A4,A4) -> 21529415
A5: S_70_30_30_TO_70_70_70 | B5: 2028 | C5: =SUMIFS(Annual_Cost!$Q$2:$Q$131,Annual_Cost!$A$2:$A$131,A5,Annual_Cost!$B$2:$B$131,B5) -> 1.5696323e+09 | D5: =SUMIFS(Annual_Cost!$R$2:$R$131,Annual_Cost!$A$2:$A$131,A5,Annual_Cost!$B$2:$B$131,B5) -> 1.5924285e+09 | E5: =SUMIFS(Annual_Cost!$S$2:$S$131,Annual_Cost!$A$2:$A$131,A5,Annual_Cost!$B$2:$B$131,B5) -> 22796161 | F5: =SUMIFS(Annual_Cost!$Y$2:$Y$131,Annual_Cost!$A$2:$A$131,A5,Annual_Cost!$B$2:$B$131,B5) -> 20861717 | G5: =SUMIFS($E$2:E5,$A$2:A5,A5) -> 45411454 | H5: =SUMIFS($F$2:F5,$A$2:A5,A5) -> 42391132
A6: S_70_30_30_TO_70_70_70 | B6: 2029 | C6: =SUMIFS(Annual_Cost!$Q$2:$Q$131,Annual_Cost!$A$2:$A$131,A6,Annual_Cost!$B$2:$B$131,B6) -> 1.5765531e+09 | D6: =SUMIFS(Annual_Cost!$R$2:$R$131,Annual_Cost!$A$2:$A$131,A6,Annual_Cost!$B$2:$B$131,B6) -> 1.607127e+09 | E6: =SUMIFS(Annual_Cost!$S$2:$S$131,Annual_Cost!$A$2:$A$131,A6,Annual_Cost!$B$2:$B$131,B6) -> 30573947 | F6: =SUMIFS(Annual_Cost!$Y$2:$Y$131,Annual_Cost!$A$2:$A$131,A6,Annual_Cost!$B$2:$B$131,B6) -> 27164556 | G6: =SUMIFS($E$2:E6,$A$2:A6,A6) -> 75985400 | H6: =SUMIFS($F$2:F6,$A$2:A6,A6) -> 69555688
A7: S_70_30_30_TO_70_70_70 | B7: 2030 | C7: =SUMIFS(Annual_Cost!$Q$2:$Q$131,Annual_Cost!$A$2:$A$131,A7,Annual_Cost!$B$2:$B$131,B7) -> 1.5833483e+09 | D7: =SUMIFS(Annual_Cost!$R$2:$R$131,Annual_Cost!$A$2:$A$131,A7,Annual_Cost!$B$2:$B$131,B7) -> 1.6217362e+09 | E7: =SUMIFS(Annual_Cost!$S$2:$S$131,Annual_Cost!$A$2:$A$131,A7,Annual_Cost!$B$2:$B$131,B7) -> 38387980 | F7: =SUMIFS(Annual_Cost!$Y$2:$Y$131,Annual_Cost!$A$2:$A$131,A7,Annual_Cost!$B$2:$B$131,B7) -> 33113809 | G7: =SUMIFS($E$2:E7,$A$2:A7,A7) -> 1.1437338e+08 | H7: =SUMIFS($F$2:F7,$A$2:A7,A7) -> 1.026695e+08
A8: S_70_30_30_TO_70_70_70 | B8: 2031 | C8: =SUMIFS(Annual_Cost!$Q$2:$Q$131,Annual_Cost!$A$2:$A$131,A8,Annual_Cost!$B$2:$B$131,B8) -> 1.5901058e+09 | D8: =SUMIFS(Annual_Cost!$R$2:$R$131,Annual_Cost!$A$2:$A$131,A8,Annual_Cost!$B$2:$B$131,B8) -> 1.9162791e+09 | E8: =SUMIFS(Annual_Cost!$S$2:$S$131,Annual_Cost!$A$2:$A$131,A8,Annual_Cost!$B$2:$B$131,B8) -> 3.2617329e+08 | F8: =SUMIFS(Annual_Cost!$Y$2:$Y$131,Annual_Cost!$A$2:$A$131,A8,Annual_Cost!$B$2:$B$131,B8) -> 2.7316499e+08 | G8: =SUMIFS($E$2:E8,$A$2:A8,A8) -> 4.4054667e+08 | H8: =SUMIFS($F$2:F8,$A$2:A8,A8) -> 3.7583449e+08
A9: S_70_30_30_TO_70_70_70 | B9: 2032 | C9: =SUMIFS(Annual_Cost!$Q$2:$Q$131,Annual_Cost!$A$2:$A$131,A9,Annual_Cost!$B$2:$B$131,B9) -> 1.596651e+09 | D9: =SUMIFS(Annual_Cost!$R$2:$R$131,Annual_Cost!$A$2:$A$131,A9,Annual_Cost!$B$2:$B$131,B9) -> 2.2132192e+09 | E9: =SUMIFS(Annual_Cost!$S$2:$S$131,Annual_Cost!$A$2:$A$131,A9,Annual_Cost!$B$2:$B$131,B9) -> 6.1656828e+08 | F9: =SUMIFS(Annual_Cost!$Y$2:$Y$131,Annual_Cost!$A$2:$A$131,A9,Annual_Cost!$B$2:$B$131,B9) -> 5.0132644e+08 | G9: =SUMIFS($E$2:E9,$A$2:A9,A9) -> 1.057115e+09 | H9: =SUMIFS($F$2:F9,$A$2:A9,A9) -> 8.7716093e+08
A10: S_70_30_30_TO_70_70_70 | B10: 2033 | C10: =SUMIFS(Annual_Cost!$Q$2:$Q$131,Annual_Cost!$A$2:$A$131,A10,Annual_Cost!$B$2:$B$131,B10) -> 1.6027623e+09 | D10: =SUMIFS(Annual_Cost!$R$2:$R$131,Annual_Cost!$A$2:$A$131,A10,Annual_Cost!$B$2:$B$131,B10) -> 2.5121756e+09 | E10: =SUMIFS(Annual_Cost!$S$2:$S$131,Annual_Cost!$A$2:$A$131,A10,Annual_Cost!$B$2:$B$131,B10) -> 9.0941334e+08 | F10: =SUMIFS(Annual_Cost!$Y$2:$Y$131,Annual_Cost!$A$2:$A$131,A10,Annual_Cost!$B$2:$B$131,B10) -> 7.1789929e+08 | G10: =SUMIFS($E$2:E10,$A$2:A10,A10) -> 1.9665283e+09 | H10: =SUMIFS($F$2:F10,$A$2:A10,A10) -> 1.5950602e+09
A11: S_70_30_30_TO_70_70_70 | B11: 2034 | C11: =SUMIFS(Annual_Cost!$Q$2:$Q$131,Annual_Cost!$A$2:$A$131,A11,Annual_Cost!$B$2:$B$131,B11) -> 1.6083605e+09 | D11: =SUMIFS(Annual_Cost!$R$2:$R$131,Annual_Cost!$A$2:$A$131,A11,Annual_Cost!$B$2:$B$131,B11) -> 2.8128267e+09 | E11: =SUMIFS(Annual_Cost!$S$2:$S$131,Annual_Cost!$A$2:$A$131,A11,Annual_Cost!$B$2:$B$131,B11) -> 1.2044662e+09 | F11: =SUMIFS(Annual_Cost!$Y$2:$Y$131,Annual_Cost!$A$2:$A$131,A11,Annual_Cost!$B$2:$B$131,B11) -> 9.2312306e+08 | G11: =SUMIFS($E$2:E11,$A$2:A11,A11) -> 3.1709945e+09 | H11: =SUMIFS($F$2:F11,$A$2:A11,A11) -> 2.5181833e+09
A12: S_70_30_30_TO_70_70_70 | B12: 2035 | C12: =SUMIFS(Annual_Cost!$Q$2:$Q$131,Annual_Cost!$A$2:$A$131,A12,Annual_Cost!$B$2:$B$131,B12) -> 1.6136639e+09 | D12: =SUMIFS(Annual_Cost!$R$2:$R$131,Annual_Cost!$A$2:$A$131,A12,Annual_Cost!$B$2:$B$131,B12) -> 3.1153781e+09 | E12: =SUMIFS(Annual_Cost!$S$2:$S$131,Annual_Cost!$A$2:$A$131,A12,Annual_Cost!$B$2:$B$131,B12) -> 1.5017143e+09 | F12: =SUMIFS(Annual_Cost!$Y$2:$Y$131,Annual_Cost!$A$2:$A$131,A12,Annual_Cost!$B$2:$B$131,B12) -> 1.1174165e+09 | G12: =SUMIFS($E$2:E12,$A$2:A12,A12) -> 4.6727088e+09 | H12: =SUMIFS($F$2:F12,$A$2:A12,A12) -> 3.6355997e+09
A13: S_70_30_30_TO_70_70_70 | B13: 2036 | C13: =SUMIFS(Annual_Cost!$Q$2:$Q$131,Annual_Cost!$A$2:$A$131,A13,Annual_Cost!$B$2:$B$131,B13) -> 1.6190918e+09 | D13: =SUMIFS(Annual_Cost!$R$2:$R$131,Annual_Cost!$A$2:$A$131,A13,Annual_Cost!$B$2:$B$131,B13) -> 3.4206108e+09 | E13: =SUMIFS(Annual_Cost!$S$2:$S$131,Annual_Cost!$A$2:$A$131,A13,Annual_Cost!$B$2:$B$131,B13) -> 1.801519e+09 | F13: =SUMIFS(Annual_Cost!$Y$2:$Y$131,Annual_Cost!$A$2:$A$131,A13,Annual_Cost!$B$2:$B$131,B13) -> 1.3014556e+09 | G13: =SUMIFS($E$2:E13,$A$2:A13,A13) -> 6.4742277e+09 | H13: =SUMIFS($F$2:F13,$A$2:A13,A13) -> 4.9370554e+09
... A27: S_70_30_30_TO_70_70_70 | B27: 2050 | C27: =SUMIFS(Annual_Cost!$Q$2:$Q$131,Annual_Cost!$A$2:$A$131,A27,Annual_Cost!$B$2:$B$131,B27) -> 1.6777936e+09 | D27: =SUMIFS(Annual_Cost!$R$2:$R$131,Annual_Cost!$A$2:$A$131,A27,Annual_Cost!$B$2:$B$131,B27) -> 4.799662e+09 | E27: =SUMIFS(Annual_Cost!$S$2:$S$131,Annual_Cost!$A$2:$A$131,A27,Annual_Cost!$B$2:$B$131,B27) -> 3.1218684e+09 | F27: =SUMIFS(Annual_Cost!$Y$2:$Y$131,Annual_Cost!$A$2:$A$131,A27,Annual_Cost!$B$2:$B$131,B27) -> 1.4910217e+09 | G27: =SUMIFS($E$2:E27,$A$2:A27,A27) -> 4.7577917e+10 | H27: =SUMIFS($F$2:F27,$A$2:A27,A27) -> 2.8668786e+10

Sheet Cost_Effectiveness
A1: scenario | B1: scenario_label | C1: deaths_averted | D1: cases_averted | E1: incremental_cost | F1: disc_incremental_cost | G1: cost_per_death_averted | H1: dominance | I1: reconciliation_status
A2: S_70_30_30_TO_70_70_70 | B2: 70-30-30 -> 70-70-70 hypertension/cholesterol + diabetes cascade | C2: =SUMIFS(Annual_Mortality!$H$2:$H$365,Annual_Mortality!$A$2:$A$365,A2) -> 1129892.8 | D2: =SUMIFS(Annual_Mortality!$J$2:$J$365,Annual_Mortality!$A$2:$A$365,A2) -> 2114232.3 | E2: =SUMIFS(Budget_Impact!$E$2:$E$27,Budget_Impact!$A$2:$A$27,A2) -> 4.7577917e+10 | F2: =SUMIFS(Budget_Impact!$F$2:$F$27,Budget_Impact!$A$2:$A$27,A2) -> 2.8668786e+10 | G2: =IF(C2>0,F2/C2,"") -> 25373.013 | H2: =IF(AND(C2>0,F2<0),"Dominant (more health, lower cost)",IF(AND(C2<=0,F2>0),"Dominated (less/no health, higher cost)",IF(AND(C2<=0,F2<=0),"No deaths averted; ratio not defined","USD per death averted"))) -> USD per death averted | I2: =IF(AND(ABS(F2-SUMIFS(Budget_Impact!$F$2:$F$27,Budget_Impact!$A$2:$A$27,A2))<=Calculation_Assumptions!$B$11,ABS(C2-SUMIFS(Annual_Mortality!$H$2:$H$365,Annual_Mortality!$A$2:$A$365,A2))<=Calculation_Assumptions!$B$11),"consistent","mismatch") -> consistent

Sheet Economic_Value
A1: scenario | B1: scenario_label | C1: year | D1: deaths_averted | E1: life_years_gained | F1: gni_pc_idn | G1: gni_pc_usa | H1: population | I1: le_avg_adult | J1: vsl_transfer_prefloor | K1: vsl_floor | L1: vsl_preferred | M1: vsl_over_gnipc | N1: vsl_gni100 | O1: vsl_gni160 | P1: vsly_preferred | Q1: econ_value_vsl_undisc | R1: econ_value_vsly_undisc | S1: econ_value_vsl100_undisc | T1: econ_value_vsl160_undisc | U1: disc_factor | V1: pv_vsl_pref | W1: pv_vsly_pref | X1: pv_vsl100 | Y1: pv_vsl160 | Z1: total_national_gni | AA1: pv_national_gni | AB1: annual_benefit_share_gni
A2: S_70_30_30_TO_70_70_70 | B2: 70-30-30 -> 70-70-70 hypertension/cholesterol + diabetes cascade | C2: 2025 | D2: 0 | E2: 0 | F2: 13851.491 | G2: 74136.371 | H2: 2.8572124e+08 | I2: 37.51 | J2: =Calculation_Assumptions!$B$25*G2*(F2/G2)^Calculation_Assumptions!$B$26 -> 957963.83 | K2: =Calculation_Assumptions!$B$27*F2 -> 277029.82 | L2: =MAX(J2,K2) -> 957963.83 | M2: =IF(F2=0,"",L2/F2) -> 69.159618 | N2: =Calculation_Assumptions!$B$28*F2 -> 1385149.1 | O2: =Calculation_Assumptions!$B$29*F2 -> 2216238.6 | P2: =IF(I2=0,"",L2/I2) -> 25538.892 | Q2: =L2*D2 -> 0 | R2: =P2*E2 -> 0 | S2: =N2*D2 -> 0 | T2: =O2*D2 -> 0 | U2: =1/(1+Calculation_Assumptions!$B$22)^(C2-Calculation_Assumptions!$B$21) -> 1 | V2: =Q2*U2 -> 0 | W2: =R2*U2 -> 0 | X2: =S2*U2 -> 0 | Y2: =T2*U2 -> 0 | Z2: =H2*F2 -> 3.9576651e+12 | AA2: =Z2*U2 -> 3.9576651e+12 | AB2: =IF(Z2=0,"",Q2/Z2) -> 0
A3: S_70_30_30_TO_70_70_70 | B3: 70-30-30 -> 70-70-70 hypertension/cholesterol + diabetes cascade | C3: 2026 | D3: 35.607834 | E3: 478.73259 | F3: 14370.1 | G3: 75186.41 | H3: 2.8788678e+08 | I3: 37.5883 | J3: =Calculation_Assumptions!$B$25*G3*(F3/G3)^Calculation_Assumptions!$B$26 -> 1005171.1 | K3: =Calculation_Assumptions!$B$27*F3 -> 287402.01 | L3: =MAX(J3,K3) -> 1005171.1 | M3: =IF(F3=0,"",L3/F3) -> 69.948791 | N3: =Calculation_Assumptions!$B$28*F3 -> 1437010 | O3: =Calculation_Assumptions!$B$29*F3 -> 2299216.1 | P3: =IF(I3=0,"",L3/I3) -> 26741.596 | Q3: =L3*D3 -> 35791967 | R3: =P3*E3 -> 12802074 | S3: =N3*D3 -> 51168815 | T3: =O3*D3 -> 81870103 | U3: =1/(1+Calculation_Assumptions!$B$22)^(C3-Calculation_Assumptions!$B$21) -> 0.97087379 | V3: =Q3*U3 -> 34749483 | W3: =R3*U3 -> 12429198 | X3: =S3*U3 -> 49678461 | Y3: =T3*U3 -> 79485537 | Z3: =H3*F3 -> 4.136962e+12 | AA3: =Z3*U3 -> 4.0164679e+12 | AB3: =IF(Z3=0,"",Q3/Z3) -> 8.6517515e-06
A4: S_70_30_30_TO_70_70_70 | B4: 70-30-30 -> 70-70-70 hypertension/cholesterol + diabetes cascade | C4: 2027 | D4: 298.18274 | E4: 4229.0226 | F4: 14908.127 | G4: 76251.321 | H4: 289986522 | I4: 37.6736 | J4: =Calculation_Assumptions!$B$25*G4*(F4/G4)^Calculation_Assumptions!$B$26 -> 1054704.8 | K4: =Calculation_Assumptions!$B$27*F4 -> 298162.54 | L4: =MAX(J4,K4) -> 1054704.8 | M4: =IF(F4=0,"",L4/F4) -> 70.746969 | N4: =Calculation_Assumptions!$B$28*F4 -> 1490812.7 | O4: =Calculation_Assumptions!$B$29*F4 -> 2385300.3 | P4: =IF(I4=0,"",L4/I4) -> 27995.859 | Q4: =L4*D4 -> 3.1449476e+08 | R4: =P4*E4 -> 1.1839512e+08 | S4: =N4*D4 -> 4.4453461e+08 | T4: =O4*D4 -> 7.1125538e+08 | U4: =1/(1+Calculation_Assumptions!$B$22)^(C4-Calculation_Assumptions!$B$21) -> 0.94259591 | V4: =Q4*U4 -> 2.9644148e+08 | W4: =R4*U4 -> 1.1159876e+08 | X4: =S4*U4 -> 4.1901651e+08 | Y4: =T4*U4 -> 6.7042641e+08 | Z4: =H4*F4 -> 4.3231559e+12 | AA4: =Z4*U4 -> 4.074989e+12 | AB4: =IF(Z4=0,"",Q4/Z4) -> 7.274657e-05
A5: S_70_30_30_TO_70_70_70 | B5: 70-30-30 -> 70-70-70 hypertension/cholesterol + diabetes cascade | C5: 2028 | D5: 706.42037 | E5: 10328.318 | F5: 15466.297 | G5: 77331.315 | H5: 2.9201678e+08 | I5: 36.834 | J5: =Calculation_Assumptions!$B$25*G5*(F5/G5)^Calculation_Assumptions!$B$26 -> 1106679.4 | K5: =Calculation_Assumptions!$B$27*F5 -> 309325.95 | L5: =MAX(J5,K5) -> 1106679.4 | M5: =IF(F5=0,"",L5/F5) -> 71.554255 | N5: =Calculation_Assumptions!$B$28*F5 -> 1546629.7 | O5: =Calculation_Assumptions!$B$29*F5 -> 2474607.6 | P5: =IF(I5=0,"",L5/I5) -> 30045.05 | Q5: =L5*D5 -> 7.8178085e+08 | R5: =P5*E5 -> 3.1031483e+08 | S5: =N5*D5 -> 1.0925707e+09 | T5: =O5*D5 -> 1.7481132e+09 | U5: =1/(1+Calculation_Assumptions!$B$22)^(C5-Calculation_Assumptions!$B$21) -> 0.91514166 | V5: =Q5*U5 -> 7.1544023e+08 | W5: =R5*U5 -> 2.8398203e+08 | X5: =S5*U5 -> 9.99857e+08 | Y5: =T5*U5 -> 1.5997712e+09 | Z5: =H5*F5 -> 4.5164183e+12 | AA5: =Z5*U5 -> 4.1331626e+12 | AB5: =IF(Z5=0,"",Q5/Z5) -> 0.00017309753
A6: S_70_30_30_TO_70_70_70 | B6: 70-30-30 -> 70-70-70 hypertension/cholesterol + diabetes cascade | C6: 2029 | D6: 1238.4598 | E6: 18417.507 | F6: 16045.366 | G6: 78426.606 | H6: 293978109 | I6: 36.9118 | J6: =Calculation_Assumptions!$B$25*G6*(F6/G6)^Calculation_Assumptions!$B$26 -> 1161215.2 | K6: =Calculation_Assumptions!$B$27*F6 -> 320907.32 | L6: =MAX(J6,K6) -> 1161215.2 | M6: =IF(F6=0,"",L6/F6) -> 72.370752 | N6: =Calculation_Assumptions!$B$28*F6 -> 1604536.6 | O6: =Calculation_Assumptions!$B$29*F6 -> 2567258.6 | P6: =IF(I6=0,"",L6/I6) -> 31459.187 | Q6: =L6*D6 -> 1.4381183e+09 | R6: =P6*E6 -> 5.793998e+08 | S6: =N6*D6 -> 1.987154e+09 | T6: =O6*D6 -> 3.1794465e+09 | U6: =1/(1+Calculation_Assumptions!$B$22)^(C6-Calculation_Assumptions!$B$21) -> 0.88848705 | V6: =Q6*U6 -> 1.2777495e+09 | W6: =R6*U6 -> 5.1478922e+08 | X6: =S6*U6 -> 1.7655606e+09 | Y6: =T6*U6 -> 2.824897e+09 | Z6: =H6*F6 -> 4.7169864e+12 | AA6: =Z6*U6 -> 4.1909813e+12 | AB6: =IF(Z6=0,"",Q6/Z6) -> 0.00030488075
A7: S_70_30_30_TO_70_70_70 | B7: 70-30-30 -> 70-70-70 hypertension/cholesterol + diabetes cascade | C7: 2030 | D7: 1880.9183 | E7: 28241.963 | F7: 16646.116 | G7: 79537.41 | H7: 295876648 | I7: 36.9927 | J7: =Calculation_Assumptions!$B$25*G7*(F7/G7)^Calculation_Assumptions!$B$26 -> 1218438.5 | K7: =Calculation_Assumptions!$B$27*F7 -> 332922.31 | L7: =MAX(J7,K7) -> 1218438.5 | M7: =IF(F7=0,"",L7/F7) -> 73.196567 | N7: =Calculation_Assumptions!$B$28*F7 -> 1664611.6 | O7: =Calculation_Assumptions!$B$29*F7 -> 2663378.5 | P7: =IF(I7=0,"",L7/I7) -> 32937.269 | Q7: =L7*D7 -> 2.2917834e+09 | R7: =P7*E7 -> 9.3021315e+08 | S7: =N7*D7 -> 3.1309984e+09 | T7: =O7*D7 -> 5.0095975e+09 | U7: =1/(1+Calculation_Assumptions!$B$22)^(C7-Calculation_Assumptions!$B$21) -> 0.86260878 | V7: =Q7*U7 -> 1.9769125e+09 | W7: =R7*U7 -> 8.0241004e+08 | X7: =S7*U7 -> 2.7008267e+09 | Y7: =T7*U7 -> 4.3213228e+09 | Z7: =H7*F7 -> 4.9251969e+12 | AA7: =Z7*U7 -> 4.2485181e+12 | AB7: =IF(Z7=0,"",Q7/Z7) -> 0.00046531812
A8: S_70_30_30_TO_70_70_70 | B8: 70-30-30 -> 70-70-70 hypertension/cholesterol + diabetes cascade | C8: 2031 | D8: 4071.7085 | E8: 57869.036 | F8: 17161.073 | G8: 80420.157 | H8: 297719748 | I8: 37.0895 | J8: =Calculation_Assumptions!$B$25*G8*(F8/G8)^Calculation_Assumptions!$B$26 -> 1268394.1 | K8: =Calculation_Assumptions!$B$27*F8 -> 343221.47 | L8: =MAX(J8,K8) -> 1268394.1 | M8: =IF(F8=0,"",L8/F8) -> 73.911114 | N8: =Calculation_Assumptions!$B$28*F8 -> 1716107.3 | O8: =Calculation_Assumptions!$B$29*F8 -> 2745771.8 | P8: =IF(I8=0,"",L8/I8) -> 34198.198 | Q8: =L8*D8 -> 5.1645309e+09 | R8: =P8*E8 -> 1.9790167e+09 | S8: =N8*D8 -> 6.9874888e+09 | T8: =O8*D8 -> 1.1179982e+10 | U8: =1/(1+Calculation_Assumptions!$B$22)^(C8-Calculation_Assumptions!$B$21) -> 0.83748426 | V8: =Q8*U8 -> 4.3252133e+09 | W8: =R8*U8 -> 1.6573954e+09 | X8: =S8*U8 -> 5.8519119e+09 | Y8: =T8*U8 -> 9.363059e+09 | Z8: =H8*F8 -> 5.1091905e+12 | AA8: =Z8*U8 -> 4.2788666e+12 | AB8: =IF(Z8=0,"",Q8/Z8) -> 0.0010108315
A9: S_70_30_30_TO_70_70_70 | B9: 70-30-30 -> 70-70-70 hypertension/cholesterol + diabetes cascade | C9: 2032 | D9: 7450.5935 | E9: 104094.46 | F9: 17691.962 | G9: 81312.7 | H9: 2.9951066e+08 | I9: 37.1904 | J9: =Calculation_Assumptions!$B$25*G9*(F9/G9)^Calculation_Assumptions!$B$26 -> 1320397.8 | K9: =Calculation_Assumptions!$B$27*F9 -> 353839.24 | L9: =MAX(J9,K9) -> 1320397.8 | M9: =IF(F9=0,"",L9/F9) -> 74.632637 | N9: =Calculation_Assumptions!$B$28*F9 -> 1769196.2 | O9: =Calculation_Assumptions!$B$29*F9 -> 2830713.9 | P9: =IF(I9=0,"",L9/I9) -> 35503.726 | Q9: =L9*D9 -> 9.837747e+09 | R9: =P9*E9 -> 3.695741e+09 | S9: =N9*D9 -> 1.3181562e+10 | T9: =O9*D9 -> 2.1090498e+10 | U9: =1/(1+Calculation_Assumptions!$B$22)^(C9-Calculation_Assumptions!$B$21) -> 0.81309151 | V9: =Q9*U9 -> 7.9989886e+09 | W9: =R9*U9 -> 3.0049756e+09 | X9: =S9*U9 -> 1.0717816e+10 | Y9: =T9*U9 -> 1.7148505e+10 | Z9: =H9*F9 -> 5.2989312e+12 | AA9: =Z9*U9 -> 4.308516e+12 | AB9: =IF(Z9=0,"",Q9/Z9) -> 0.0018565531
A10: S_70_30_30_TO_70_70_70 | B10: 70-30-30 -> 70-70-70 hypertension/cholesterol + diabetes cascade | C10: 2033 | D10: 11687.569 | E10: 162967.44 | F10: 18239.273 | G10: 82215.15 | H10: 3.0125098e+08 | I10: 37.2975 | J10: =Calculation_Assumptions!$B$25*G10*(F10/G10)^Calculation_Assumptions!$B$26 -> 1374533.6 | K10: =Calculation_Assumptions!$B$27*F10 -> 364785.47 | L10: =MAX(J10,K10) -> 1374533.6 | M10: =IF(F10=0,"",L10/F10) -> 75.361203 | N10: =Calculation_Assumptions!$B$28*F10 -> 1823927.3 | O10: =Calculation_Assumptions!$B$29*F10 -> 2918283.7 | P10: =IF(I10=0,"",L10/I10) -> 36853.237 | Q10: =L10*D10 -> 1.6064956e+10 | R10: =P10*E10 -> 6.0058778e+09 | S10: =N10*D10 -> 2.1317277e+10 | T10: =O10*D10 -> 3.4107643e+10 | U10: =1/(1+Calculation_Assumptions!$B$22)^(C10-Calculation_Assumptions!$B$21) -> 0.78940923 | V10: =Q10*U10 -> 1.2681825e+10 | W10: =R10*U10 -> 4.7410954e+09 | X10: =S10*U10 -> 1.6828055e+10 | Y10: =T10*U10 -> 2.6924888e+10 | Z10: =H10*F10 -> 5.4945991e+12 | AA10: =Z10*U10 -> 4.3374872e+12 | AB10: =IF(Z10=0,"",Q10/Z10) -> 0.0029237722
A11: S_70_30_30_TO_70_70_70 | B11: 70-30-30 -> 70-70-70 hypertension/cholesterol + diabetes cascade | C11: 2034 | D11: 16660.797 | E11: 232801.26 | F11: 18803.516 | G11: 83127.615 | H11: 302938573 | I11: 37.4064 | J11: =Calculation_Assumptions!$B$25*G11*(F11/G11)^Calculation_Assumptions!$B$26 -> 1430889 | K11: =Calculation_Assumptions!$B$27*F11 -> 376070.33 | L11: =MAX(J11,K11) -> 1430889 | M11: =IF(F11=0,"",L11/F11) -> 76.096882 | N11: =Calculation_Assumptions!$B$28*F11 -> 1880351.6 | O11: =Calculation_Assumptions!$B$29*F11 -> 3008562.6 | P11: =IF(I11=0,"",L11/I11) -> 38252.517 | Q11: =L11*D11 -> 2.383975e+10 | R11: =P11*E11 -> 8.9052342e+09 | S11: =N11*D11 -> 3.1328157e+10 | T11: =O11*D11 -> 5.0125051e+10 | U11: =1/(1+Calculation_Assumptions!$B$22)^(C11-Calculation_Assumptions!$B$21) -> 0.76641673 | V11: =Q11*U11 -> 1.8271184e+10 | W11: =R11*U11 -> 6.8251205e+09 | X11: =S11*U11 -> 2.4010424e+10 | Y11: =T11*U11 -> 3.8416678e+10 | Z11: =H11*F11 -> 5.6963105e+12 | AA11: =Z11*U11 -> 4.3657476e+12 | AB11: =IF(Z11=0,"",Q11/Z11) -> 0.0041851213
A12: S_70_30_30_TO_70_70_70 | B12: 70-30-30 -> 70-70-70 hypertension/cholesterol + diabetes cascade | C12: 2035 | D12: 22296.163 | E12: 312217.85 | F12: 19385.215 | G12: 84050.207 | H12: 304566622 | I12: 37.5179 | J12: =Calculation_Assumptions!$B$25*G12*(F12/G12)^Calculation_Assumptions!$B$26 -> 1489554.9 | K12: =Calculation_Assumptions!$B$27*F12 -> 387704.3 | L12: =MAX(J12,K12) -> 1489554.9 | M12: =IF(F12=0,"",L12/F12) -> 76.839742 | N12: =Calculation_Assumptions!$B$28*F12 -> 1938521.5 | O12: =Calculation_Assumptions!$B$29*F12 -> 3101634.4 | P12: =IF(I12=0,"",L12/I12) -> 39702.513 | Q12: =L12*D12 -> 3.3211359e+10 | R12: =P12*E12 -> 1.2395833e+10 | S12: =N12*D12 -> 4.3221591e+10 | T12: =O12*D12 -> 6.9154545e+10 | U12: =1/(1+Calculation_Assumptions!$B$22)^(C12-Calculation_Assumptions!$B$21) -> 0.74409391 | V12: =Q12*U12 -> 2.471237e+10 | W12: =R12*U12 -> 9.2236639e+09 | X12: =S12*U12 -> 3.2160923e+10 | Y12: =T12*U12 -> 5.1457476e+10 | Z12: =H12*F12 -> 5.9040894e+12 | AA12: =Z12*U12 -> 4.393197e+12 | AB12: =IF(Z12=0,"",Q12/Z12) -> 0.005625145
A13: S_70_30_30_TO_70_70_70 | B13: 70-30-30 -> 70-70-70 hypertension/cholesterol + diabetes cascade | C13: 2036 | D13: 28553.139 | E13: 400370.5 | F13: 19931.358 | G13: 84847.857 | H13: 306135098 | I13: 37.6267 | J13: =Calculation_Assumptions!$B$25*G13*(F13/G13)^Calculation_Assumptions!$B$26 -> 1545627.7 | K13: =Calculation_Assumptions!$B$27*F13 -> 398627.16 | L13: =MAX(J13,K13) -> 1545627.7 | M13: =IF(F13=0,"",L13/F13) -> 77.547534 | N13: =Calculation_Assumptions!$B$28*F13 -> 1993135.8 | O13: =Calculation_Assumptions!$B$29*F13 -> 3189017.3 | P13: =IF(I13=0,"",L13/I13) -> 41077.949 | Q13: =L13*D13 -> 4.4132521e+10 | R13: =P13*E13 -> 1.6446399e+10 | S13: =N13*D13 -> 5.6910283e+10 | T13: =O13*D13 -> 9.1056453e+10 | U13: =1/(1+Calculation_Assumptions!$B$22)^(C13-Calculation_Assumptions!$B$21) -> 0.72242128 | V13: =Q13*U13 -> 3.1882272e+10 | W13: =R13*U13 -> 1.1881229e+10 | X13: =S13*U13 -> 4.1113199e+10 | Y13: =T13*U13 -> 6.5781119e+10 | Z13: =H13*F13 -> 6.1016883e+12 | AA13: =Z13*U13 -> 4.4079894e+12 | AB13: =IF(Z13=0,"",Q13/Z13) -> 0.0072328377
... A27: S_70_30_30_TO_70_70_70 | B27: 70-30-30 -> 70-70-70 hypertension/cholesterol + diabetes cascade | C27: 2050 | D27: 98374.925 | E27: 1402543.5 | F27: 28211.06 | G27: 95832.888 | H27: 3.2071295e+08 | I27: 38.286 | J27: =Calculation_Assumptions!$B$25*G27*(F27/G27)^Calculation_Assumptions!$B$26 -> 2449017.1 | K27: =Calculation_Assumptions!$B$27*F27 -> 564221.21 | L27: =MAX(J27,K27) -> 2449017.1 | M27: =IF(F27=0,"",L27/F27) -> 86.810529 | N27: =Calculation_Assumptions!$B$28*F27 -> 2821106 | O27: =Calculation_Assumptions!$B$29*F27 -> 4513769.7 | P27: =IF(I27=0,"",L27/I27) -> 63966.386 | Q27: =L27*D27 -> 2.4092187e+11 | R27: =P27*E27 -> 8.971564e+10 | S27: =N27*D27 -> 2.775261e+11 | T27: =O27*D27 -> 4.4404175e+11 | U27: =1/(1+Calculation_Assumptions!$B$22)^(C27-Calculation_Assumptions!$B$21) -> 0.47760557 | V27: =Q27*U27 -> 1.1506563e+11 | W27: =R27*U27 -> 4.2848689e+10 | X27: =S27*U27 -> 1.3254801e+11 | Y27: =T27*U27 -> 2.1207681e+11 | Z27: =H27*F27 -> 9.0476524e+12 | AA27: =Z27*U27 -> 4.3212092e+12 | AB27: =IF(Z27=0,"",Q27/Z27) -> 0.026628109

Sheet Benefit_Cost
A1: scenario | B1: scenario_label | C1: intervention_family | D1: scenario_level | E1: valuation_method | F1: valuation_case | G1: pv_benefits | H1: pv_costs | I1: pv_net_benefit | J1: benefit_cost_ratio | K1: pv_national_gni | L1: benefit_gni_share | M1: decision | N1: scope_note
A2: S_70_30_30_TO_70_70_70 | B2: 70-30-30 -> 70-70-70 hypertension/cholesterol + diabetes cascade | C2: cascade_70_30_30_to_70_70_70 | D2: combined | E2: VSL | F2: preferred (elasticity 1.5, 20x floor) | G2: =SUMIFS(Economic_Value!$V$2:$V$27,Economic_Value!$A$2:$A$27,A2) -> 1.3064951e+12 | H2: =SUMPRODUCT((Budget_Impact!$A$2:$A$27=A2)*Budget_Impact!$E$2:$E$27*(1/(1+Calculation_Assumptions!$B$22)^(Budget_Impact!$B$2:$B$27-Calculation_Assumptions!$B$21)))*Calculation_Assumptions!$B$34 -> 8.6006359e+10 | I2: =G2-H2 -> 1.2204887e+12 | J2: =IF(H2>0,G2/H2,"") -> 15.19068 | K2: =SUMIFS(Economic_Value!$AA$2:$AA$27,Economic_Value!$A$2:$A$27,A2) -> 1.1253145e+14 | L2: =IF(K2=0,"",G2/K2) -> 0.011610044 | M2: =IF(H2<=0,"cost-saving or ratio not meaningful (PV cost<=0)",IF(J2>=1,"benefits exceed costs (BCR>=1)","costs exceed benefits (BCR<1)")) -> benefits exceed costs (BCR>=1) | N2: Partial mortality-benefit BCA (preferred (elasticity 1.5, 20x floor)). Benefits = averted-mortality VSL/VSLY in PPP int$; costs = implementation/health-system converted to PPP int$ (market USD x cost_to_bca_currency_factor). Omits morbidity, productivity and downstream cost offsets.
A3: S_70_30_30_TO_70_70_70 | B3: 70-30-30 -> 70-70-70 hypertension/cholesterol + diabetes cascade | C3: cascade_70_30_30_to_70_70_70 | D3: combined | E3: VSLY | F3: preferred (VSLY from preferred VSL) | G3: =SUMIFS(Economic_Value!$W$2:$W$27,Economic_Value!$A$2:$A$27,A3) -> 4.8878471e+11 | H3: =SUMPRODUCT((Budget_Impact!$A$2:$A$27=A3)*Budget_Impact!$E$2:$E$27*(1/(1+Calculation_Assumptions!$B$22)^(Budget_Impact!$B$2:$B$27-Calculation_Assumptions!$B$21)))*Calculation_Assumptions!$B$34 -> 8.6006359e+10 | I3: =G3-H3 -> 4.0277836e+11 | J3: =IF(H3>0,G3/H3,"") -> 5.683123 | K3: =SUMIFS(Economic_Value!$AA$2:$AA$27,Economic_Value!$A$2:$A$27,A3) -> 1.1253145e+14 | L3: =IF(K3=0,"",G3/K3) -> 0.0043435387 | M3: =IF(H3<=0,"cost-saving or ratio not meaningful (PV cost<=0)",IF(J3>=1,"benefits exceed costs (BCR>=1)","costs exceed benefits (BCR<1)")) -> benefits exceed costs (BCR>=1) | N3: Partial mortality-benefit BCA (preferred (elasticity 1.5, 20x floor)). Benefits = averted-mortality VSL/VSLY in PPP int$; costs = implementation/health-system converted to PPP int$ (market USD x cost_to_bca_currency_factor). Omits morbidity, productivity and downstream cost offsets.
A4: S_70_30_30_TO_70_70_70 | B4: 70-30-30 -> 70-70-70 hypertension/cholesterol + diabetes cascade | C4: cascade_70_30_30_to_70_70_70 | D4: combined | E4: VSL | F4: sensitivity: 100x GNI per capita | G4: =SUMIFS(Economic_Value!$X$2:$X$27,Economic_Value!$A$2:$A$27,A4) -> 1.5795849e+12 | H4: =SUMPRODUCT((Budget_Impact!$A$2:$A$27=A4)*Budget_Impact!$E$2:$E$27*(1/(1+Calculation_Assumptions!$B$22)^(Budget_Impact!$B$2:$B$27-Calculation_Assumptions!$B$21)))*Calculation_Assumptions!$B$34 -> 8.6006359e+10 | I4: =G4-H4 -> 1.4935786e+12 | J4: =IF(H4>0,G4/H4,"") -> 18.365909 | K4: =SUMIFS(Economic_Value!$AA$2:$AA$27,Economic_Value!$A$2:$A$27,A4) -> 1.1253145e+14 | L4: =IF(K4=0,"",G4/K4) -> 0.014036831 | M4: =IF(H4<=0,"cost-saving or ratio not meaningful (PV cost<=0)",IF(J4>=1,"benefits exceed costs (BCR>=1)","costs exceed benefits (BCR<1)")) -> benefits exceed costs (BCR>=1) | N4: Partial mortality-benefit BCA (preferred (elasticity 1.5, 20x floor)). Benefits = averted-mortality VSL/VSLY in PPP int$; costs = implementation/health-system converted to PPP int$ (market USD x cost_to_bca_currency_factor). Omits morbidity, productivity and downstream cost offsets.
A5: S_70_30_30_TO_70_70_70 | B5: 70-30-30 -> 70-70-70 hypertension/cholesterol + diabetes cascade | C5: cascade_70_30_30_to_70_70_70 | D5: combined | E5: VSL | F5: sensitivity: 160x GNI per capita | G5: =SUMIFS(Economic_Value!$Y$2:$Y$27,Economic_Value!$A$2:$A$27,A5) -> 2.5273359e+12 | H5: =SUMPRODUCT((Budget_Impact!$A$2:$A$27=A5)*Budget_Impact!$E$2:$E$27*(1/(1+Calculation_Assumptions!$B$22)^(Budget_Impact!$B$2:$B$27-Calculation_Assumptions!$B$21)))*Calculation_Assumptions!$B$34 -> 8.6006359e+10 | I5: =G5-H5 -> 2.4413295e+12 | J5: =IF(H5>0,G5/H5,"") -> 29.385454 | K5: =SUMIFS(Economic_Value!$AA$2:$AA$27,Economic_Value!$A$2:$A$27,A5) -> 1.1253145e+14 | L5: =IF(K5=0,"",G5/K5) -> 0.022458929 | M5: =IF(H5<=0,"cost-saving or ratio not meaningful (PV cost<=0)",IF(J5>=1,"benefits exceed costs (BCR>=1)","costs exceed benefits (BCR<1)")) -> benefits exceed costs (BCR>=1) | N5: Partial mortality-benefit BCA (preferred (elasticity 1.5, 20x floor)). Benefits = averted-mortality VSL/VSLY in PPP int$; costs = implementation/health-system converted to PPP int$ (market USD x cost_to_bca_currency_factor). Omits morbidity, productivity and downstream cost offsets.

Sheet QA_Checks
A1: check | B1: expected | C1: actual | D1: status | E1: note
A2: Intervention-cause key uniqueness | B2: 0 | C2: =COUNTIF(Selected_Interventions!$U$2:$U$7,">1") -> 0 | D2: =IF(C2=0,"PASS","FAIL") -> PASS | E2: Each selected link key appears once
A3: Workbook FAIL-level issues | B3: 0 | C3: =COUNTIF(Input_Diagnostic!$E$2:$E$2,"FAIL") -> 0 | D3: =IF(C3=0,"PASS","REVIEW") -> PASS | E3: Blocked links/scenarios excluded (see Selected_Interventions / Input_Diagnostic)
A4: Workbook REVIEW-level issues | B4: 0 | C4: =COUNTIF(Input_Diagnostic!$E$2:$E$2,"REVIEW") -> 0 | D4: =IF(C4=0,"PASS","REVIEW") -> PASS | E4: Flagged but usable (e.g. cost not Indonesia-adjusted, missing optional component)
A5: Every scenario paired to baseline | B5: TRUE | C5: =COUNTBLANK(Annual_Mortality!$G$2:$G$365)=0 -> TRUE | D5: =IF(C5=TRUE,"PASS","FAIL") -> PASS | E5: Deaths averted = baseline - scenario at matched location/year/cause
A6: No impossible negative states | B6: 0 | C6: =Calculation_Assumptions!$B$16 -> 0 | D6: =IF(C6=0,"PASS","FAIL") -> PASS | E6: well/sick/new_cases/cause_deaths/population >= 0
A7: Stock/flow identity pop = well + sick + all-cause deaths | B7: <= limit | C7: =Calculation_Assumptions!$B$14 -> 127.1 | D7: =IF(C7<=Calculation_Assumptions!$B$12,"PASS","REVIEW") -> PASS | E7: Per cause row; small residual from 95+ pooling / rounding
A8: Background mortality constant across cause (not duplicated) | B8: 1 | C8: =Calculation_Assumptions!$B$15 -> 1 | D8: =IF(C8=1,"PASS","FAIL") -> PASS | E8: all.mx taken once per stratum in the R Background sheet
A9: Cost reconciliation (components -> budget impact) | B9: <= tol | C9: =ABS(SUM(Budget_Impact!$D$2:$D$27)-SUM(Annual_Cost!$R$2:$R$131))+ABS(SUM(Budget_Impact!$C$2:$C$27)-SUM(Annual_Cost!$Q$2:$Q$131)) -> 7.6293945e-06 | D9: =IF(C9<=Calculation_Assumptions!$B$11,"PASS","FAIL") -> PASS | E9: Excel component rows sum to Excel annual totals within tolerance
A10: Shared cost counted once per stratum/year | B10: 0 | C10: =COUNTIF(Annual_Cost!$AH$2:$AH$131,">1") -> 0 | D10: =IF(C10=0,"PASS","FAIL") -> PASS | E10: shared-count-once components appear once per scenario-year
A11: CEA reconciliation (detail -> summary ratio) | B11: consistent | C11: =IF(COUNTIF(Cost_Effectiveness!$I$2:$I$2,"mismatch")=0,"consistent","mismatch") -> consistent | D11: =IF(C11="consistent","PASS","FAIL") -> PASS | E11: Every Cost_Effectiveness row's internal reconciliation is consistent
A12: Excel vs R: deaths averted (anchor scenario) | B12: match R | C12: =INDEX(Cost_Effectiveness!$C$2:$C$2,MATCH(Calculation_Assumptions!$B$20,Cost_Effectiveness!$A$2:$A$2,0)) -> 1129892.8 | D12: =IF(ABS(C12-Calculation_Assumptions!$B$17)<=ABS(Calculation_Assumptions!$B$17)*0.000001+0.5,"PASS","FAIL") -> PASS | E12: Excel CEA deaths averted reconciles to the R engine value
A13: Excel vs R: discounted incremental cost (anchor scenario) | B13: match R | C13: =INDEX(Cost_Effectiveness!$F$2:$F$2,MATCH(Calculation_Assumptions!$B$20,Cost_Effectiveness!$A$2:$A$2,0)) -> 2.8668786e+10 | D13: =IF(ABS(C13-Calculation_Assumptions!$B$18)<=ABS(Calculation_Assumptions!$B$18)*0.000001+1,"PASS","FAIL") -> PASS | E13: Excel CEA discounted incremental cost reconciles to the R engine value
A14: Excel vs R: cost per death averted (anchor scenario) | B14: match R | C14: =INDEX(Cost_Effectiveness!$G$2:$G$2,MATCH(Calculation_Assumptions!$B$20,Cost_Effectiveness!$A$2:$A$2,0)) -> 25373.013 | D14: =IF(ABS(C14-Calculation_Assumptions!$B$19)<=ABS(Calculation_Assumptions!$B$19)*0.000001+1,"PASS","FAIL") -> PASS | E14: Excel CEA USD per death averted reconciles to the R engine value
A15: VSL floor applied (preferred VSL >= 20x GNI floor) | B15: 0 | C15: =SUMPRODUCT((Economic_Value!$L$2:$L$27<Economic_Value!$K$2:$K$27)*1) -> 0 | D15: =IF(C15=0,"PASS","FAIL") -> PASS | E15: No Economic_Value row has preferred VSL below the 20x GNI-per-capita floor
A16: Reference-case VSL parameters (elasticity 1.5, US ratio 160, 20x floor) | B16: as_specified | C16: =IF(AND(Calculation_Assumptions!$B$26=1.5,Calculation_Assumptions!$B$25=160,Calculation_Assumptions!$B$27=20),"as_specified","edited") -> as_specified | D16: =IF(C16="as_specified","PASS","REVIEW") -> PASS | E16: Reference case = elasticity 1.5 transfer, 160x US ratio, 20x GNI floor (Robinson et al. 2019)
A17: Benefit and cost on the same price year (BCA basis) | B17: match | C17: =IF(Calculation_Assumptions!$B$33=Calculation_Assumptions!$B$6,"match","mismatch") -> match | D17: =IF(C17="match","PASS","REVIEW") -> PASS | E17: bca_price_year equals the cost price year, so benefits and costs share a real price basis
A18: Benefit_Cost scenarios all present in Health_Outcomes | B18: 0 | C18: =SUMPRODUCT((COUNTIF(Health_Outcomes!$A$2:$A$27,Benefit_Cost!$A$2:$A$5)=0)*1) -> 0 | D18: =IF(C18=0,"PASS","FAIL") -> PASS | E18: Every scenario x valuation-case row in Benefit_Cost has a matching Health_Outcomes scenario
A19: CVD 40q30 Excel vs R (all rows match) | B19: 0 | C19: =COUNTIF(CVD_40q30!$N$2:$N$53,"mismatch") -> 0 | D19: =IF(C19=0,"PASS","FAIL") -> PASS | E19: CVD_40q30 recon_status has no 'mismatch' (life-table formula reconciles to Model 07)

Sheet Input_Diagnostic
A1: scope | B1: item_key | C1: field | D1: problem | E1: severity

Sheet Methods_and_Sources
A1: method_id | B1: concept | C1: formula_or_rule | D1: source
A2: M01 | B2: Incremental coverage | C2: delta_cov(t) = coverage(t) - baseline_coverage | D2: FairChoices_Methods sheet + https://fairchoices.w.uib.no/documentation/fairchoices-methods/
A3: M02 | B3: FAIR adjusted effect | C3: e_adj(t) = effect_value * delta_cov(t) / (1 - effect_value * baseline_coverage) | D3: FairChoices_Methods sheet + https://fairchoices.w.uib.no/documentation/fairchoices-methods/
A4: M03 | B4: Affected fraction | C4: transition_effect(t) = e_adj(t) * affected_fraction | D4: FairChoices_Methods sheet + https://fairchoices.w.uib.no/documentation/fairchoices-methods/
A5: M04 | B5: Adjusted transition | C5: p_scenario(t) = p_baseline(t) * (1 - transition_effect(t)); prevention->incidence (IR/eff_ir), management->case fatality (CF/eff_cf) | D5: FairChoices_Methods sheet + https://fairchoices.w.uib.no/documentation/fairchoices-methods/
A6: M05 | B6: HF/severe mapping | C6: workbook sick_hf / sick_severe collapse onto the single 'sick' state via affected_fraction; NO new Markov states | D6: Model 04 translation table (Indonesia Markov adaptation)
A7: M06 | B7: Annual component cost | C7: annual_cost = population_in_need * coverage(t) * frequency_per_year * unit_cost_usd | D7: FairChoices_Methods sheet / input workbook
A8: M07 | B8: Shared cost | C8: shared-count-once components counted once per intervention & eligible stratum, not once per affected cause | D8: FairChoices_Methods sheet / input workbook
A9: M08 | B9: Discounting | C9: discount_factor(t) = 1 / (1 + cost_discount_rate)^(t - analysis_start_year); costs discounted, death counts undiscounted | D9: FairChoices_Methods sheet / input workbook
A10: M09 | B10: Budget impact | C10: incremental = scenario_cost - baseline_cost (undiscounted headline; discounted reported separately) | D10: FairChoices_Methods sheet / input workbook
A11: M10 | B11: Cost-effectiveness | C11: USD per death averted = cumulative discounted incremental cost / cumulative deaths averted | D11: FairChoices_Methods sheet / input workbook
A12: M11 | B12: FAIR unit-cost markups | C12: not re-applied where indonesia_adjusted_flag = 1 (supplied adjusted costs already include them) | D12: FairChoices_Methods M08
... A19: M18 | B19: CVD 40q30 (period life table) | C19: Period CVD 40q30 over the six CVD causes (ihd, istroke, hstroke, hhd, rhd, cmd), exact ages 30-69: sexes combined before the rate, m_x=(D_F+D_M)/(N_F+N_M), q_x=1-EXP(-m_x), l_30=1, l_{x+1}=l_x(1-q_x), 40q30=100*(1-l_70/l_30). CVD_40q30_Age carries the live life-table formulas; CVD_40q30 has the metric, shared-baseline pairing, absolute (pp) and relative (%) reduction, all reconciled to the Model 07 R value. cvd_40q30 is a PERCENT on a 0-100 scale (format 0.000, not Excel %). Population is de-duplicated across causes (never summed over the six causes). | D19: Model 07 (07_cvd_40q30.rds) / Model 09

Sheet Calculation_Assumptions
A1: parameter_id | B1: value | C1: unit | D1: role | E1: description | F1: source
A2: analysis_start_year | B2: 2025 | C2: year | D2: formula control | E2: First model and discount year | F2: indonesia_model_inputs.xlsx / Model 09
A3: analysis_end_year | B3: 2050 | C3: year | D3: formula control | E3: Last model year | F3: indonesia_model_inputs.xlsx / Model 09
A4: baseline_scenario_id | B4: baseline | C4: scenario id | D4: formula control | E4: Comparator used for health and cost calculations | F4: Model 04 / Model 09
A5: cost_discount_rate | B5: 0.03 | C5: proportion/year | D5: formula control | E5: Annual discount rate applied to costs only | F5: indonesia_model_inputs.xlsx / Model 09
A6: cost_price_year | B6: 2023 | C6: USD year | D6: metadata | E6: Reporting price year | F6: indonesia_model_inputs.xlsx
A7: currency | B7: USD | C7: currency | D7: metadata | E7: Workbook reporting currency | F7: indonesia_model_inputs.xlsx
A8: economic_perspective | B8: health_system | C8: text | D8: metadata | E8: Economic evaluation perspective | F8: indonesia_model_inputs.xlsx
A9: scale_up_shape | B9: piecewise_linear | C9: text | D9: formula control | E9: Coverage increases linearly from start to target year | F9: indonesia_model_inputs.xlsx
A10: downstream_cost_offsets | B10: 0 | C10: 0/1 flag | D10: scope | E10: Downstream disease-cost offsets excluded at this stage | F10: indonesia_model_inputs.xlsx
A11: formula_tolerance | B11: 0.001 | C11: USD/count | D11: QA control | E11: Absolute reconciliation tolerance (internal Excel checks) | F11: Workbook QA rule
A12: stock_flow_residual_limit | B12: 1000 | C12: persons | D12: QA control | E12: Review threshold used by the R stock/flow check | F12: Model 09
A13: trace_precision | B13: 2 | C13: decimal places | D13: audit note | E13: Exported model traces are rounded; R quantity helpers keep full precision | F13: Model 09 export rule
A14: r_stock_flow_max_residual | B14: 127.1 | C14: persons | D14: R QA source | E14: Maximum stock/flow residual computed in R before export | F14: Model 09 current run
A15: r_background_distinct_count | B15: 1 | C15: count | D15: R QA source | E15: Max distinct all-cause mortality values across causes (R) | F15: Model 09 current run
A16: r_negative_state_count | B16: 0 | C16: count | D16: R QA source | E16: Count of impossible negative state/flow values (R) | F16: Model 09 current run
A17: r_deaths_averted_anchor | B17: 1129892.8 | C17: deaths | D17: R reconciliation source | E17: R engine deaths averted for the anchor scenario | F17: Model 09 current run (R CEA)
A18: r_disc_incremental_cost_anchor | B18: 2.8668786e+10 | C18: USD | D18: R reconciliation source | E18: R engine discounted incremental cost for the anchor scenario | F18: Model 09 current run (R CEA)
A19: r_cost_per_death_anchor | B19: 25373.013 | C19: USD/death | D19: R reconciliation source | E19: R engine USD per death averted for the anchor scenario | F19: Model 09 current run (R CEA)
A20: qa_anchor_scenario | B20: S_70_30_30_TO_70_70_70 | C20: scenario id | D20: R reconciliation source | E20: Scenario used for the Excel-vs-R reconciliation checks | F20: Model 09 current run (R CEA)
A21: bca_base_year | B21: 2025 | C21: year | D21: BCA control | E21: BCA base year (benefits and costs discounted to this year) | F21: Robinson et al. 2019 Reference Case Guidelines (via input workbook / Model 08)
A22: bca_discount_rate_primary | B22: 0.03 | C22: proportion/year | D22: BCA control | E22: Primary real discount rate for BOTH benefits and costs | F22: Robinson et al. 2019 Reference Case Guidelines (via input workbook / Model 08)
A23: bca_discount_rate_sensitivity_3pct | B23: 0.03 | C23: proportion/year | D23: BCA control | E23: Standardized sensitivity discount rate (3%) | F23: Robinson et al. 2019 Reference Case Guidelines (via input workbook / Model 08)
A24: bca_discount_rate_sensitivity_2x_gdp_pc_growth | B24: 0.08 | C24: proportion/year | D24: BCA control | E24: Standardized sensitivity: 2x near-term real GDP-pc growth (workbook default) | F24: Robinson et al. 2019 Reference Case Guidelines (via input workbook / Model 08)
A25: vsl_us_gni_ratio | B25: 160 | C25: ratio (VSL/GNIpc) | D25: BCA control | E25: US reference VSL-to-GNI-per-capita ratio | F25: Robinson et al. 2019 Reference Case Guidelines (via input workbook / Model 08)
A26: vsl_income_elasticity_preferred | B26: 1.5 | C26: elasticity | D26: BCA control | E26: Income elasticity of VSL (preferred) | F26: Robinson et al. 2019 Reference Case Guidelines (via input workbook / Model 08)
A27: vsl_floor_gni_multiple | B27: 20 | C27: ratio (VSL/GNIpc) | D27: BCA control | E27: Floor: VSL not below this multiple of GNI per capita | F27: Robinson et al. 2019 Reference Case Guidelines (via input workbook / Model 08)
A28: vsl_sensitivity_gni_multiple_100 | B28: 100 | C28: ratio (VSL/GNIpc) | D28: BCA control | E28: Sensitivity: VSL = 100x GNI per capita | F28: Robinson et al. 2019 Reference Case Guidelines (via input workbook / Model 08)
A29: vsl_sensitivity_gni_multiple_160 | B29: 160 | C29: ratio (VSL/GNIpc) | D29: BCA control | E29: Sensitivity: VSL = 160x GNI per capita | F29: Robinson et al. 2019 Reference Case Guidelines (via input workbook / Model 08)
A30: vsly_adult_min_age | B30: 15 | C30: age (years) | D30: BCA control | E30: Working-age lower bound (VSLY avg-adult-age) | F30: Robinson et al. 2019 Reference Case Guidelines (via input workbook / Model 08)
A31: vsly_adult_max_age | B31: 64 | C31: age (years) | D31: BCA control | E31: Working-age upper bound (VSLY avg-adult-age) | F31: Robinson et al. 2019 Reference Case Guidelines (via input workbook / Model 08)
A32: bca_currency_basis | B32: PPP_international_dollars | C32: text | D32: BCA control | E32: Common monetary basis for benefits and costs | F32: Robinson et al. 2019 Reference Case Guidelines (via input workbook / Model 08)
A33: bca_price_year | B33: 2023 | C33: year | D33: BCA control | E33: Real price year for benefits and costs | F33: Robinson et al. 2019 Reference Case Guidelines (via input workbook / Model 08)
A34: cost_to_bca_currency_factor | B34: 3 | C34: int$ per market US$ | D34: BCA control | E34: Market-USD cost -> PPP int$ multiplier | F34: Robinson et al. 2019 Reference Case Guidelines (via input workbook / Model 08)
A35: bca_standing | B35: societal | C35: text | D35: BCA control | E35: BCA standing / perspective | F35: Robinson et al. 2019 Reference Case Guidelines (via input workbook / Model 08)
A36: bca_scope | B36: partial_mortality_benefit | C36: text | D36: BCA control | E36: BCA scope (partial mortality-benefit vs full societal) | F36: Robinson et al. 2019 Reference Case Guidelines (via input workbook / Model 08)
A37: bca_discount_rate_sensitivity_2x_gdp_pc_growth_computed | B37: 0.074881374 | C37: proportion/year | D37: BCA control | E37: 2x near-term real GDP-pc growth recomputed from SSP2 by Model 08 | F37: Robinson et al. 2019 Reference Case Guidelines (via input workbook / Model 08)

Sheet Calculation_Map
A1: output_sheet | B1: formula_columns | C1: depends_on | D1: calculation | E1: source_role
A2: Selected_Interventions | B2: P, U:V | C2: selected health links (J:M) | D2: Adjusted effect at target; key uniqueness/status | E2: Workbook formula
A3: Cost_Components | B3: S:V, X | C3: Selected_Interventions | D3: Coverage link (INDEX/MATCH) and cost-readiness rule | E3: Workbook formula
A4: Annual_Mortality | B4: H, J | C4: R aggregates E:G, I | D4: Deaths averted and cases averted | E4: Workbook formula
A5: Health_Outcomes | B5: F,I,L,O,R,S | C5: Model 07 modeled/baseline health (grey D:E,G:H,J:K,M:N,P:Q) | D5: Deaths/cases/YLL/YLD/DALY averted and life-years gained (baseline - intervention) | E5: Workbook formula
A6: CVD_40q30_Age | B6: J:M | C6: CVD deaths + de-duplicated population (grey H:I) | D6: m_x=deaths/pop, q_x=1-EXP(-m_x), recursive l_x, l_{x+1} (period life table, ages 30-69) | E6: Workbook formula
A7: CVD_40q30 | B7: I,J,K,L,N | C7: CVD_40q30_Age life table; baseline SUMIFS; R anchor (M) | D7: CVD 40q30 = 100*(1-l_70/l_30); baseline-paired absolute (pp) & relative (%) reduction; R reconciliation | E7: Workbook formula
A8: Annual_Cost | B8: J:AE, AH | C8: Cost_Components; Calculation_Assumptions; R quantity AF:AG | D8: Coverage path, PIN, annual + discounted cost, shared-cost QA | E8: Workbook formula
A9: Annual_Cost | B9: AF:AG | C9: full-precision Model 06 output | D9: Scenario/baseline quantity before the PIN fraction | E9: Workbook formula
A10: Budget_Impact | B10: C:H | C10: Annual_Cost | D10: Annual and cumulative cost by scenario | E10: Workbook formula
A11: Cost_Effectiveness | B11: C:I | C11: Annual_Mortality; Budget_Impact; Calculation_Assumptions | D11: Cumulative health, cost, cost/death, dominance, reconciliation | E11: Workbook formula
A12: Economic_Value | B12: J:AB | C12: Model 08 source (grey D:I); Calculation_Assumptions BCA controls | D12: Reference-Case VSL (elast 1.5 + 20x floor) & 100x/160x, VSLY, undisc & PV benefits, GNI shares | E12: Workbook formula
... A16: Companion R workbook | B16: none | C16: Model 06 / Model 09 | D16: Detailed Model_State_Trace and Background_Mortality | E16: R source data
