Workbook

Sheet Summary
A1: scenario | B1: scenario_label | C1: intervention_family | D1: scenario_level | E1: n_interventions | F1: analysis_start_year | G1: analysis_end_year | H1: cases_averted | I1: deaths_averted | J1: ylls_averted | K1: ylds_averted | L1: dalys_averted | M1: life_years_gained | N1: cvd_40q30_start_pct | O1: cvd_40q30_end_pct | P1: cvd_40q30_abs_reduction_pp_end | Q1: cvd_40q30_pct_reduction_end | R1: incremental_cost | S1: disc_incremental_cost | T1: cost_per_death_averted | U1: cost_per_daly_averted | V1: pv_benefits | W1: pv_costs | X1: pv_net_benefit | Y1: benefit_cost_ratio
A2: baseline | B2: Baseline (no new intervention) | C2: baseline | D2: baseline | E2: 0 | F2: ='Calculation_Assumptions'!$B$2 | G2: ='Calculation_Assumptions'!$B$3 | H2: =SUMIFS('Health_Outcomes'!$I$2:$I$235,'Health_Outcomes'!$A$2:$A$235,A2) | I2: =SUMIFS('Health_Outcomes'!$F$2:$F$235,'Health_Outcomes'!$A$2:$A$235,A2) | J2: =SUMIFS('Health_Outcomes'!$L$2:$L$235,'Health_Outcomes'!$A$2:$A$235,A2) | K2: =SUMIFS('Health_Outcomes'!$O$2:$O$235,'Health_Outcomes'!$A$2:$A$235,A2) | L2: =SUMIFS('Health_Outcomes'!$R$2:$R$235,'Health_Outcomes'!$A$2:$A$235,A2) | M2: =SUMIFS('Health_Outcomes'!$S$2:$S$235,'Health_Outcomes'!$A$2:$A$235,A2) | N2: =SUMIFS('CVD_40q30'!$I$2:$I$261,'CVD_40q30'!$B$2:$B$261,A2,'CVD_40q30'!$H$2:$H$261,F2) | O2: =SUMIFS('CVD_40q30'!$I$2:$I$261,'CVD_40q30'!$B$2:$B$261,A2,'CVD_40q30'!$H$2:$H$261,G2) | P2: =SUMIFS('CVD_40q30'!$K$2:$K$261,'CVD_40q30'!$B$2:$B$261,A2,'CVD_40q30'!$H$2:$H$261,G2) | Q2: =SUMIFS('CVD_40q30'!$L$2:$L$261,'CVD_40q30'!$B$2:$B$261,A2,'CVD_40q30'!$H$2:$H$261,G2) | R2: =SUMIFS('Budget_Impact'!$E$2:$E$235,'Budget_Impact'!$A$2:$A$235,A2) | S2: =SUMIFS('Budget_Impact'!$F$2:$F$235,'Budget_Impact'!$A$2:$A$235,A2) | T2: =IF(I2>0,S2/I2,"") | U2: =IF(L2>0,S2/L2,"") | V2: =SUMIFS('Benefit_Cost'!$G$2:$G$37,'Benefit_Cost'!$A$2:$A$37,A2,'Benefit_Cost'!$F$2:$F$37,"preferred (elasticity 1.5, 20x floor)") | W2: =SUMIFS('Benefit_Cost'!$H$2:$H$37,'Benefit_Cost'!$A$2:$A$37,A2,'Benefit_Cost'!$F$2:$F$37,"preferred (elasticity 1.5, 20x floor)") | X2: =V2-W2 | Y2: =IF(W2>0,V2/W2,"")
A3: S_70_30_30_TO_70_70_70 | B3: 70-30-30 -> 70-70-70 hypertension/cholesterol + diabetes cascade | C3: cascade_70_30_30_to_70_70_70 | D3: combined | E3: 2 | F3: ='Calculation_Assumptions'!$B$2 | G3: ='Calculation_Assumptions'!$B$3 | H3: =SUMIFS('Health_Outcomes'!$I$2:$I$235,'Health_Outcomes'!$A$2:$A$235,A3) | I3: =SUMIFS('Health_Outcomes'!$F$2:$F$235,'Health_Outcomes'!$A$2:$A$235,A3) | J3: =SUMIFS('Health_Outcomes'!$L$2:$L$235,'Health_Outcomes'!$A$2:$A$235,A3) | K3: =SUMIFS('Health_Outcomes'!$O$2:$O$235,'Health_Outcomes'!$A$2:$A$235,A3) | L3: =SUMIFS('Health_Outcomes'!$R$2:$R$235,'Health_Outcomes'!$A$2:$A$235,A3) | M3: =SUMIFS('Health_Outcomes'!$S$2:$S$235,'Health_Outcomes'!$A$2:$A$235,A3) | N3: =SUMIFS('CVD_40q30'!$I$2:$I$261,'CVD_40q30'!$B$2:$B$261,A3,'CVD_40q30'!$H$2:$H$261,F3) | O3: =SUMIFS('CVD_40q30'!$I$2:$I$261,'CVD_40q30'!$B$2:$B$261,A3,'CVD_40q30'!$H$2:$H$261,G3) | P3: =SUMIFS('CVD_40q30'!$K$2:$K$261,'CVD_40q30'!$B$2:$B$261,A3,'CVD_40q30'!$H$2:$H$261,G3) | Q3: =SUMIFS('CVD_40q30'!$L$2:$L$261,'CVD_40q30'!$B$2:$B$261,A3,'CVD_40q30'!$H$2:$H$261,G3) | R3: =SUMIFS('Budget_Impact'!$E$2:$E$235,'Budget_Impact'!$A$2:$A$235,A3) | S3: =SUMIFS('Budget_Impact'!$F$2:$F$235,'Budget_Impact'!$A$2:$A$235,A3) | T3: =IF(I3>0,S3/I3,"") | U3: =IF(L3>0,S3/L3,"") | V3: =SUMIFS('Benefit_Cost'!$G$2:$G$37,'Benefit_Cost'!$A$2:$A$37,A3,'Benefit_Cost'!$F$2:$F$37,"preferred (elasticity 1.5, 20x floor)") | W3: =SUMIFS('Benefit_Cost'!$H$2:$H$37,'Benefit_Cost'!$A$2:$A$37,A3,'Benefit_Cost'!$F$2:$F$37,"preferred (elasticity 1.5, 20x floor)") | X3: =V3-W3 | Y3: =IF(W3>0,V3/W3,"")
A4: I_PH_TOBACCO_TAX | B4: Tobacco tax | C4: public_health | D4: standalone | E4: 1 | F4: ='Calculation_Assumptions'!$B$2 | G4: ='Calculation_Assumptions'!$B$3 | H4: =SUMIFS('Health_Outcomes'!$I$2:$I$235,'Health_Outcomes'!$A$2:$A$235,A4) | I4: =SUMIFS('Health_Outcomes'!$F$2:$F$235,'Health_Outcomes'!$A$2:$A$235,A4) | J4: =SUMIFS('Health_Outcomes'!$L$2:$L$235,'Health_Outcomes'!$A$2:$A$235,A4) | K4: =SUMIFS('Health_Outcomes'!$O$2:$O$235,'Health_Outcomes'!$A$2:$A$235,A4) | L4: =SUMIFS('Health_Outcomes'!$R$2:$R$235,'Health_Outcomes'!$A$2:$A$235,A4) | M4: =SUMIFS('Health_Outcomes'!$S$2:$S$235,'Health_Outcomes'!$A$2:$A$235,A4) | N4: =SUMIFS('CVD_40q30'!$I$2:$I$261,'CVD_40q30'!$B$2:$B$261,A4,'CVD_40q30'!$H$2:$H$261,F4) | O4: =SUMIFS('CVD_40q30'!$I$2:$I$261,'CVD_40q30'!$B$2:$B$261,A4,'CVD_40q30'!$H$2:$H$261,G4) | P4: =SUMIFS('CVD_40q30'!$K$2:$K$261,'CVD_40q30'!$B$2:$B$261,A4,'CVD_40q30'!$H$2:$H$261,G4) | Q4: =SUMIFS('CVD_40q30'!$L$2:$L$261,'CVD_40q30'!$B$2:$B$261,A4,'CVD_40q30'!$H$2:$H$261,G4) | R4: =SUMIFS('Budget_Impact'!$E$2:$E$235,'Budget_Impact'!$A$2:$A$235,A4) | S4: =SUMIFS('Budget_Impact'!$F$2:$F$235,'Budget_Impact'!$A$2:$A$235,A4) | T4: =IF(I4>0,S4/I4,"") | U4: =IF(L4>0,S4/L4,"") | V4: =SUMIFS('Benefit_Cost'!$G$2:$G$37,'Benefit_Cost'!$A$2:$A$37,A4,'Benefit_Cost'!$F$2:$F$37,"preferred (elasticity 1.5, 20x floor)") | W4: =SUMIFS('Benefit_Cost'!$H$2:$H$37,'Benefit_Cost'!$A$2:$A$37,A4,'Benefit_Cost'!$F$2:$F$37,"preferred (elasticity 1.5, 20x floor)") | X4: =V4-W4 | Y4: =IF(W4>0,V4/W4,"")
A5: I_PH_TOB_CLEAN_AIR | B5: Smoke-free / clean-air law | C5: public_health | D5: standalone | E5: 1 | F5: ='Calculation_Assumptions'!$B$2 | G5: ='Calculation_Assumptions'!$B$3 | H5: =SUMIFS('Health_Outcomes'!$I$2:$I$235,'Health_Outcomes'!$A$2:$A$235,A5) | I5: =SUMIFS('Health_Outcomes'!$F$2:$F$235,'Health_Outcomes'!$A$2:$A$235,A5) | J5: =SUMIFS('Health_Outcomes'!$L$2:$L$235,'Health_Outcomes'!$A$2:$A$235,A5) | K5: =SUMIFS('Health_Outcomes'!$O$2:$O$235,'Health_Outcomes'!$A$2:$A$235,A5) | L5: =SUMIFS('Health_Outcomes'!$R$2:$R$235,'Health_Outcomes'!$A$2:$A$235,A5) | M5: =SUMIFS('Health_Outcomes'!$S$2:$S$235,'Health_Outcomes'!$A$2:$A$235,A5) | N5: =SUMIFS('CVD_40q30'!$I$2:$I$261,'CVD_40q30'!$B$2:$B$261,A5,'CVD_40q30'!$H$2:$H$261,F5) | O5: =SUMIFS('CVD_40q30'!$I$2:$I$261,'CVD_40q30'!$B$2:$B$261,A5,'CVD_40q30'!$H$2:$H$261,G5) | P5: =SUMIFS('CVD_40q30'!$K$2:$K$261,'CVD_40q30'!$B$2:$B$261,A5,'CVD_40q30'!$H$2:$H$261,G5) | Q5: =SUMIFS('CVD_40q30'!$L$2:$L$261,'CVD_40q30'!$B$2:$B$261,A5,'CVD_40q30'!$H$2:$H$261,G5) | R5: =SUMIFS('Budget_Impact'!$E$2:$E$235,'Budget_Impact'!$A$2:$A$235,A5) | S5: =SUMIFS('Budget_Impact'!$F$2:$F$235,'Budget_Impact'!$A$2:$A$235,A5) | T5: =IF(I5>0,S5/I5,"") | U5: =IF(L5>0,S5/L5,"") | V5: =SUMIFS('Benefit_Cost'!$G$2:$G$37,'Benefit_Cost'!$A$2:$A$37,A5,'Benefit_Cost'!$F$2:$F$37,"preferred (elasticity 1.5, 20x floor)") | W5: =SUMIFS('Benefit_Cost'!$H$2:$H$37,'Benefit_Cost'!$A$2:$A$37,A5,'Benefit_Cost'!$F$2:$F$37,"preferred (elasticity 1.5, 20x floor)") | X5: =V5-W5 | Y5: =IF(W5>0,V5/W5,"")
A6: I_PH_TOB_MEDIA | B6: Tobacco mass-media campaign | C6: public_health | D6: standalone | E6: 1 | F6: ='Calculation_Assumptions'!$B$2 | G6: ='Calculation_Assumptions'!$B$3 | H6: =SUMIFS('Health_Outcomes'!$I$2:$I$235,'Health_Outcomes'!$A$2:$A$235,A6) | I6: =SUMIFS('Health_Outcomes'!$F$2:$F$235,'Health_Outcomes'!$A$2:$A$235,A6) | J6: =SUMIFS('Health_Outcomes'!$L$2:$L$235,'Health_Outcomes'!$A$2:$A$235,A6) | K6: =SUMIFS('Health_Outcomes'!$O$2:$O$235,'Health_Outcomes'!$A$2:$A$235,A6) | L6: =SUMIFS('Health_Outcomes'!$R$2:$R$235,'Health_Outcomes'!$A$2:$A$235,A6) | M6: =SUMIFS('Health_Outcomes'!$S$2:$S$235,'Health_Outcomes'!$A$2:$A$235,A6) | N6: =SUMIFS('CVD_40q30'!$I$2:$I$261,'CVD_40q30'!$B$2:$B$261,A6,'CVD_40q30'!$H$2:$H$261,F6) | O6: =SUMIFS('CVD_40q30'!$I$2:$I$261,'CVD_40q30'!$B$2:$B$261,A6,'CVD_40q30'!$H$2:$H$261,G6) | P6: =SUMIFS('CVD_40q30'!$K$2:$K$261,'CVD_40q30'!$B$2:$B$261,A6,'CVD_40q30'!$H$2:$H$261,G6) | Q6: =SUMIFS('CVD_40q30'!$L$2:$L$261,'CVD_40q30'!$B$2:$B$261,A6,'CVD_40q30'!$H$2:$H$261,G6) | R6: =SUMIFS('Budget_Impact'!$E$2:$E$235,'Budget_Impact'!$A$2:$A$235,A6) | S6: =SUMIFS('Budget_Impact'!$F$2:$F$235,'Budget_Impact'!$A$2:$A$235,A6) | T6: =IF(I6>0,S6/I6,"") | U6: =IF(L6>0,S6/L6,"") | V6: =SUMIFS('Benefit_Cost'!$G$2:$G$37,'Benefit_Cost'!$A$2:$A$37,A6,'Benefit_Cost'!$F$2:$F$37,"preferred (elasticity 1.5, 20x floor)") | W6: =SUMIFS('Benefit_Cost'!$H$2:$H$37,'Benefit_Cost'!$A$2:$A$37,A6,'Benefit_Cost'!$F$2:$F$37,"preferred (elasticity 1.5, 20x floor)") | X6: =V6-W6 | Y6: =IF(W6>0,V6/W6,"")
A7: I_PH_TOB_AD_BAN | B7: Tobacco advertising ban | C7: public_health | D7: standalone | E7: 1 | F7: ='Calculation_Assumptions'!$B$2 | G7: ='Calculation_Assumptions'!$B$3 | H7: =SUMIFS('Health_Outcomes'!$I$2:$I$235,'Health_Outcomes'!$A$2:$A$235,A7) | I7: =SUMIFS('Health_Outcomes'!$F$2:$F$235,'Health_Outcomes'!$A$2:$A$235,A7) | J7: =SUMIFS('Health_Outcomes'!$L$2:$L$235,'Health_Outcomes'!$A$2:$A$235,A7) | K7: =SUMIFS('Health_Outcomes'!$O$2:$O$235,'Health_Outcomes'!$A$2:$A$235,A7) | L7: =SUMIFS('Health_Outcomes'!$R$2:$R$235,'Health_Outcomes'!$A$2:$A$235,A7) | M7: =SUMIFS('Health_Outcomes'!$S$2:$S$235,'Health_Outcomes'!$A$2:$A$235,A7) | N7: =SUMIFS('CVD_40q30'!$I$2:$I$261,'CVD_40q30'!$B$2:$B$261,A7,'CVD_40q30'!$H$2:$H$261,F7) | O7: =SUMIFS('CVD_40q30'!$I$2:$I$261,'CVD_40q30'!$B$2:$B$261,A7,'CVD_40q30'!$H$2:$H$261,G7) | P7: =SUMIFS('CVD_40q30'!$K$2:$K$261,'CVD_40q30'!$B$2:$B$261,A7,'CVD_40q30'!$H$2:$H$261,G7) | Q7: =SUMIFS('CVD_40q30'!$L$2:$L$261,'CVD_40q30'!$B$2:$B$261,A7,'CVD_40q30'!$H$2:$H$261,G7) | R7: =SUMIFS('Budget_Impact'!$E$2:$E$235,'Budget_Impact'!$A$2:$A$235,A7) | S7: =SUMIFS('Budget_Impact'!$F$2:$F$235,'Budget_Impact'!$A$2:$A$235,A7) | T7: =IF(I7>0,S7/I7,"") | U7: =IF(L7>0,S7/L7,"") | V7: =SUMIFS('Benefit_Cost'!$G$2:$G$37,'Benefit_Cost'!$A$2:$A$37,A7,'Benefit_Cost'!$F$2:$F$37,"preferred (elasticity 1.5, 20x floor)") | W7: =SUMIFS('Benefit_Cost'!$H$2:$H$37,'Benefit_Cost'!$A$2:$A$37,A7,'Benefit_Cost'!$F$2:$F$37,"preferred (elasticity 1.5, 20x floor)") | X7: =V7-W7 | Y7: =IF(W7>0,V7/W7,"")
A8: I_PH_TOBACCO_POLICY | B8: Tobacco policy package | C8: public_health | D8: package | E8: 3 | F8: ='Calculation_Assumptions'!$B$2 | G8: ='Calculation_Assumptions'!$B$3 | H8: =SUMIFS('Health_Outcomes'!$I$2:$I$235,'Health_Outcomes'!$A$2:$A$235,A8) | I8: =SUMIFS('Health_Outcomes'!$F$2:$F$235,'Health_Outcomes'!$A$2:$A$235,A8) | J8: =SUMIFS('Health_Outcomes'!$L$2:$L$235,'Health_Outcomes'!$A$2:$A$235,A8) | K8: =SUMIFS('Health_Outcomes'!$O$2:$O$235,'Health_Outcomes'!$A$2:$A$235,A8) | L8: =SUMIFS('Health_Outcomes'!$R$2:$R$235,'Health_Outcomes'!$A$2:$A$235,A8) | M8: =SUMIFS('Health_Outcomes'!$S$2:$S$235,'Health_Outcomes'!$A$2:$A$235,A8) | N8: =SUMIFS('CVD_40q30'!$I$2:$I$261,'CVD_40q30'!$B$2:$B$261,A8,'CVD_40q30'!$H$2:$H$261,F8) | O8: =SUMIFS('CVD_40q30'!$I$2:$I$261,'CVD_40q30'!$B$2:$B$261,A8,'CVD_40q30'!$H$2:$H$261,G8) | P8: =SUMIFS('CVD_40q30'!$K$2:$K$261,'CVD_40q30'!$B$2:$B$261,A8,'CVD_40q30'!$H$2:$H$261,G8) | Q8: =SUMIFS('CVD_40q30'!$L$2:$L$261,'CVD_40q30'!$B$2:$B$261,A8,'CVD_40q30'!$H$2:$H$261,G8) | R8: =SUMIFS('Budget_Impact'!$E$2:$E$235,'Budget_Impact'!$A$2:$A$235,A8) | S8: =SUMIFS('Budget_Impact'!$F$2:$F$235,'Budget_Impact'!$A$2:$A$235,A8) | T8: =IF(I8>0,S8/I8,"") | U8: =IF(L8>0,S8/L8,"") | V8: =SUMIFS('Benefit_Cost'!$G$2:$G$37,'Benefit_Cost'!$A$2:$A$37,A8,'Benefit_Cost'!$F$2:$F$37,"preferred (elasticity 1.5, 20x floor)") | W8: =SUMIFS('Benefit_Cost'!$H$2:$H$37,'Benefit_Cost'!$A$2:$A$37,A8,'Benefit_Cost'!$F$2:$F$37,"preferred (elasticity 1.5, 20x floor)") | X8: =V8-W8 | Y8: =IF(W8>0,V8/W8,"")
A9: all_public_health | B9: All selected public-health interventions (combined) | C9: public_health | D9: combined | E9: 4 | F9: ='Calculation_Assumptions'!$B$2 | G9: ='Calculation_Assumptions'!$B$3 | H9: =SUMIFS('Health_Outcomes'!$I$2:$I$235,'Health_Outcomes'!$A$2:$A$235,A9) | I9: =SUMIFS('Health_Outcomes'!$F$2:$F$235,'Health_Outcomes'!$A$2:$A$235,A9) | J9: =SUMIFS('Health_Outcomes'!$L$2:$L$235,'Health_Outcomes'!$A$2:$A$235,A9) | K9: =SUMIFS('Health_Outcomes'!$O$2:$O$235,'Health_Outcomes'!$A$2:$A$235,A9) | L9: =SUMIFS('Health_Outcomes'!$R$2:$R$235,'Health_Outcomes'!$A$2:$A$235,A9) | M9: =SUMIFS('Health_Outcomes'!$S$2:$S$235,'Health_Outcomes'!$A$2:$A$235,A9) | N9: =SUMIFS('CVD_40q30'!$I$2:$I$261,'CVD_40q30'!$B$2:$B$261,A9,'CVD_40q30'!$H$2:$H$261,F9) | O9: =SUMIFS('CVD_40q30'!$I$2:$I$261,'CVD_40q30'!$B$2:$B$261,A9,'CVD_40q30'!$H$2:$H$261,G9) | P9: =SUMIFS('CVD_40q30'!$K$2:$K$261,'CVD_40q30'!$B$2:$B$261,A9,'CVD_40q30'!$H$2:$H$261,G9) | Q9: =SUMIFS('CVD_40q30'!$L$2:$L$261,'CVD_40q30'!$B$2:$B$261,A9,'CVD_40q30'!$H$2:$H$261,G9) | R9: =SUMIFS('Budget_Impact'!$E$2:$E$235,'Budget_Impact'!$A$2:$A$235,A9) | S9: =SUMIFS('Budget_Impact'!$F$2:$F$235,'Budget_Impact'!$A$2:$A$235,A9) | T9: =IF(I9>0,S9/I9,"") | U9: =IF(L9>0,S9/L9,"") | V9: =SUMIFS('Benefit_Cost'!$G$2:$G$37,'Benefit_Cost'!$A$2:$A$37,A9,'Benefit_Cost'!$F$2:$F$37,"preferred (elasticity 1.5, 20x floor)") | W9: =SUMIFS('Benefit_Cost'!$H$2:$H$37,'Benefit_Cost'!$A$2:$A$37,A9,'Benefit_Cost'!$F$2:$F$37,"preferred (elasticity 1.5, 20x floor)") | X9: =V9-W9 | Y9: =IF(W9>0,V9/W9,"")
A10: all_cascade_public_health | B10: 70-30-30 -> 70-70-70 cascade + all public-health interventions (combined) | C10: cascade_public_health | D10: combined | E10: 6 | F10: ='Calculation_Assumptions'!$B$2 | G10: ='Calculation_Assumptions'!$B$3 | H10: =SUMIFS('Health_Outcomes'!$I$2:$I$235,'Health_Outcomes'!$A$2:$A$235,A10) | I10: =SUMIFS('Health_Outcomes'!$F$2:$F$235,'Health_Outcomes'!$A$2:$A$235,A10) | J10: =SUMIFS('Health_Outcomes'!$L$2:$L$235,'Health_Outcomes'!$A$2:$A$235,A10) | K10: =SUMIFS('Health_Outcomes'!$O$2:$O$235,'Health_Outcomes'!$A$2:$A$235,A10) | L10: =SUMIFS('Health_Outcomes'!$R$2:$R$235,'Health_Outcomes'!$A$2:$A$235,A10) | M10: =SUMIFS('Health_Outcomes'!$S$2:$S$235,'Health_Outcomes'!$A$2:$A$235,A10) | N10: =SUMIFS('CVD_40q30'!$I$2:$I$261,'CVD_40q30'!$B$2:$B$261,A10,'CVD_40q30'!$H$2:$H$261,F10) | O10: =SUMIFS('CVD_40q30'!$I$2:$I$261,'CVD_40q30'!$B$2:$B$261,A10,'CVD_40q30'!$H$2:$H$261,G10) | P10: =SUMIFS('CVD_40q30'!$K$2:$K$261,'CVD_40q30'!$B$2:$B$261,A10,'CVD_40q30'!$H$2:$H$261,G10) | Q10: =SUMIFS('CVD_40q30'!$L$2:$L$261,'CVD_40q30'!$B$2:$B$261,A10,'CVD_40q30'!$H$2:$H$261,G10) | R10: =SUMIFS('Budget_Impact'!$E$2:$E$235,'Budget_Impact'!$A$2:$A$235,A10) | S10: =SUMIFS('Budget_Impact'!$F$2:$F$235,'Budget_Impact'!$A$2:$A$235,A10) | T10: =IF(I10>0,S10/I10,"") | U10: =IF(L10>0,S10/L10,"") | V10: =SUMIFS('Benefit_Cost'!$G$2:$G$37,'Benefit_Cost'!$A$2:$A$37,A10,'Benefit_Cost'!$F$2:$F$37,"preferred (elasticity 1.5, 20x floor)") | W10: =SUMIFS('Benefit_Cost'!$H$2:$H$37,'Benefit_Cost'!$A$2:$A$37,A10,'Benefit_Cost'!$F$2:$F$37,"preferred (elasticity 1.5, 20x floor)") | X10: =V10-W10 | Y10: =IF(W10>0,V10/W10,"")
A11: S_70_30_30_TO_70_70_70_I_PH_TOBACCO_TAX | B11: 70-30-30 -> 70-70-70 cascade + tobacco tax | C11: cascade_public_health | D11: combined | E11: 3 | F11: ='Calculation_Assumptions'!$B$2 | G11: ='Calculation_Assumptions'!$B$3 | H11: =SUMIFS('Health_Outcomes'!$I$2:$I$235,'Health_Outcomes'!$A$2:$A$235,A11) | I11: =SUMIFS('Health_Outcomes'!$F$2:$F$235,'Health_Outcomes'!$A$2:$A$235,A11) | J11: =SUMIFS('Health_Outcomes'!$L$2:$L$235,'Health_Outcomes'!$A$2:$A$235,A11) | K11: =SUMIFS('Health_Outcomes'!$O$2:$O$235,'Health_Outcomes'!$A$2:$A$235,A11) | L11: =SUMIFS('Health_Outcomes'!$R$2:$R$235,'Health_Outcomes'!$A$2:$A$235,A11) | M11: =SUMIFS('Health_Outcomes'!$S$2:$S$235,'Health_Outcomes'!$A$2:$A$235,A11) | N11: =SUMIFS('CVD_40q30'!$I$2:$I$261,'CVD_40q30'!$B$2:$B$261,A11,'CVD_40q30'!$H$2:$H$261,F11) | O11: =SUMIFS('CVD_40q30'!$I$2:$I$261,'CVD_40q30'!$B$2:$B$261,A11,'CVD_40q30'!$H$2:$H$261,G11) | P11: =SUMIFS('CVD_40q30'!$K$2:$K$261,'CVD_40q30'!$B$2:$B$261,A11,'CVD_40q30'!$H$2:$H$261,G11) | Q11: =SUMIFS('CVD_40q30'!$L$2:$L$261,'CVD_40q30'!$B$2:$B$261,A11,'CVD_40q30'!$H$2:$H$261,G11) | R11: =SUMIFS('Budget_Impact'!$E$2:$E$235,'Budget_Impact'!$A$2:$A$235,A11) | S11: =SUMIFS('Budget_Impact'!$F$2:$F$235,'Budget_Impact'!$A$2:$A$235,A11) | T11: =IF(I11>0,S11/I11,"") | U11: =IF(L11>0,S11/L11,"") | V11: =SUMIFS('Benefit_Cost'!$G$2:$G$37,'Benefit_Cost'!$A$2:$A$37,A11,'Benefit_Cost'!$F$2:$F$37,"preferred (elasticity 1.5, 20x floor)") | W11: =SUMIFS('Benefit_Cost'!$H$2:$H$37,'Benefit_Cost'!$A$2:$A$37,A11,'Benefit_Cost'!$F$2:$F$37,"preferred (elasticity 1.5, 20x floor)") | X11: =V11-W11 | Y11: =IF(W11>0,V11/W11,"")

Sheet README
A1: section | B1: detail
A2: Purpose | B2: Combined 70-30-30 -> 70-70-70 cascade + public-health (fiscal/regulatory) costing, budget impact, cost-effectiveness, CVD 40q30 and Reference-Case benefit-cost analysis in one workbook.
A3: Scope | B3: Baseline (once) + the 70-30-30 -> 70-70-70 cascade scenario + every public-health scenario + the genuine joint 'all_cascade_public_health' scenario. intervention_family tags each scenario baseline / cascade_70_30_30_to_70_70_70 / public_health / cascade_public_health.
A4: How to read | B4: Grey cells are R source values; light-blue cells are LIVE Excel formulas; pale-yellow cells on Calculation_Assumptions are editable controls. The joint scenario is highlighted (orange) on Summary. Calculation_Map lists the dependency chain.
A5: Scenarios | B5: See Summary and Scenario_Catalog. Family-specific input/audit sheets are prefixed CL_ (cascade clinical arm) and PH_ (public-health) where the two source schemas differ.
A6: The joint scenario | B6: 'all_cascade_public_health' is produced by a SINGLE Model 06 projection that applies the clinical (fair_wb) and public-health (ph_wb) engines once each to the same baseline-rate copy -- it is NEVER the arithmetic sum of the separate 'all' and 'all_public_health' outputs.
A7: Costing the joint scenario | B7: Joint cost = clinical components (clinical costing rule) + public-health components (per-capita policy rule), BOTH computed against the joint scenario's own Model 06 population/state. family provenance is retained on every Annual_Cost row and keys are collision-safe (family|cost_record_id). Budget_Impact carries the four *_cost_per_capita columns as LIVE formulae (= that year's cost / national_population); national_population (grey R-source) is each year's national Indonesia population from out_model/model_output_Indonesia_htncov2_aspirational.rds (baseline series, de-duplicated across cause). Annual_Cost carries the matching per-component per-capita formulae, and Cost_Effectiveness carries the scenario mean annual incremental/discounted per-capita (2026-2050).
A8: CVD 40q30 | B8: CVD_40q30 / CVD_40q30_Age give the period probability of dying from the six CVD causes between exact ages 30 and 70 (percent on a 0-100 scale). The life table (m_x, q_x, l_x, l_{x+1}) is live Excel formula; cvd_40q30 reconciles to the Model 07 R value.
A9: Benefit-cost | B9: Reference-Case VSL/VSLY benefit-cost (Robinson et al. 2019) on Health_Outcomes / Economic_Value / Benefit_Cost; PARTIAL mortality-benefit BCA.
A10: Colour legend | B10: header dark-blue; formula light-blue; R-source grey; editable-input pale-yellow; QA green/red/orange.

Sheet Run_Metadata
A1: field | B1: value
A2: workbook | B2: indonesia_model_cost_value_70_30_30_to_70_70_70_public_health_formulae.xlsx
A3: generated_by | B3: Model 09 (09_cost_value.R)
A4: clinical_workbook | B4: indonesia_70_30_30_to_70_70_70_inputs.xlsx
A5: public_health_workbook | B5: indonesia_model_inputs_public_health_updated_mortality.xlsx
A6: baseline_scenario | B6: baseline
A7: joint_scenario | B7: all_cascade_public_health
A8: n_clinical_scenarios | B8: 1
A9: n_public_health_scenarios | B9: 6
A10: analysis_years | B10: 2025-2050
A11: location | B11: Indonesia

Sheet Scenario_Catalog
A1: scenario | B1: scenario_label | C1: intervention_family | D1: scenario_level | E1: scenario_role | F1: parent_package_id | G1: intervention_ids | H1: n_interventions
A2: baseline | B2: Baseline (no new intervention) | C2: baseline | D2: baseline | H2: 0
A3: S_70_30_30_TO_70_70_70 | B3: 70-30-30 -> 70-70-70 hypertension/cholesterol + diabetes cascade | C3: cascade_70_30_30_to_70_70_70 | D3: combined | E3: combined | G3: I_CVD_PRIMARY; I_T2D_TREATMENT | H3: 2
A4: I_PH_TOBACCO_TAX | B4: Tobacco tax | C4: public_health | D4: standalone | E4: standalone | G4: I_PH_TOBACCO_TAX | H4: 1
A5: I_PH_TOB_CLEAN_AIR | B5: Smoke-free / clean-air law | C5: public_health | D5: standalone | E5: child | F5: I_PH_TOBACCO_POLICY | G5: I_PH_TOB_CLEAN_AIR | H5: 1
A6: I_PH_TOB_MEDIA | B6: Tobacco mass-media campaign | C6: public_health | D6: standalone | E6: child | F6: I_PH_TOBACCO_POLICY | G6: I_PH_TOB_MEDIA | H6: 1
A7: I_PH_TOB_AD_BAN | B7: Tobacco advertising ban | C7: public_health | D7: standalone | E7: child | F7: I_PH_TOBACCO_POLICY | G7: I_PH_TOB_AD_BAN | H7: 1
A8: I_PH_TOBACCO_POLICY | B8: Tobacco policy package | C8: public_health | D8: package | E8: package | F8: I_PH_TOBACCO_POLICY | G8: I_PH_TOB_CLEAN_AIR; I_PH_TOB_MEDIA; I_PH_TOB_AD_BAN | H8: 3
A9: all_public_health | B9: All selected public-health interventions (combined) | C9: public_health | D9: combined | E9: combined | G9: I_PH_TOBACCO_TAX; I_PH_TOB_AD_BAN; I_PH_TOB_CLEAN_AIR; I_PH_TOB_MEDIA | H9: 4
A10: all_cascade_public_health | B10: 70-30-30 -> 70-70-70 cascade + all public-health interventions (combined) | C10: cascade_public_health | D10: combined | E10: combined | G10: I_CVD_PRIMARY; I_T2D_TREATMENT; I_PH_TOBACCO_TAX; I_PH_TOB_AD_BAN; I_PH_TOB_CLEAN_AIR; I_PH_TOB_MEDIA | H10: 6
A11: S_70_30_30_TO_70_70_70_I_PH_TOBACCO_TAX | B11: 70-30-30 -> 70-70-70 cascade + tobacco tax | C11: cascade_public_health | D11: combined | E11: combined | G11: I_CVD_PRIMARY; I_T2D_TREATMENT; I_PH_TOBACCO_TAX | H11: 3

Sheet CL_Selected_Interventions
A1: intervention_id | B1: intervention_cause_key | C1: cause_code | D1: model_transition | E1: effect_value | F1: affected_fraction | G1: baseline_coverage | H1: target_coverage | I1: start_year | J1: target_year
A2: I_CVD_PRIMARY | B2: I_CVD_PRIMARY__C_HHD | C2: hhd | D2: incidence | E2: 0.47 | F2: 1 | G2: 0.14506229 | H2: 0.4165 | I2: 2025 | J2: 2040
A3: I_CVD_PRIMARY | B3: I_CVD_PRIMARY__C_ICH | C3: hstroke | D3: incidence | E3: 0.49 | F3: 0.8 | G3: 0.14506229 | H3: 0.4165 | I3: 2025 | J3: 2040
A4: I_CVD_PRIMARY | B4: I_CVD_PRIMARY__C_IHD | C4: ihd | D4: incidence | E4: 0.58 | F4: 0.8 | G4: 0.14506229 | H4: 0.4165 | I4: 2025 | J4: 2040
A5: I_CVD_PRIMARY | B5: I_CVD_PRIMARY__C_IS | C5: istroke | D5: incidence | E5: 0.54 | F5: 0.8 | G5: 0.14506229 | H5: 0.4165 | I5: 2025 | J5: 2040
A6: I_T2D_TREATMENT | B6: I_T2D_TREATMENT__C_IHD | C6: ihd | D6: case_fatality | E6: 0.15 | F6: 0.15 | G6: 0.033768828 | H6: 0.4165 | I6: 2025 | J6: 2040
A7: I_T2D_TREATMENT | B7: I_T2D_TREATMENT__C_T2D | C7: dm2 | D7: case_fatality | E7: 0.28 | F7: 1 | G7: 0.033768828 | H7: 0.4165 | I7: 2025 | J7: 2040

Sheet CL_Cost_Components
A1: cost_record_id | B1: intervention_id | C1: cause_code | D1: cost_component | E1: cost_scope | F1: population_in_need_measure | G1: population_in_need_fraction | H1: frequency_per_year | I1: unit_cost_usd | J1: cov_baseline | K1: cov_target | L1: cost_ready
A2: COST_PRIMARY_SCREEN_A | B2: I_CVD_PRIMARY | D2: CVD targeted screening | E2: shared-count-once | F2: all | G2: 0.2 | H2: 1 | I2: 1.291584 | J2: 0.14506229 | K2: 0.4165 | L2: TRUE
A3: COST_PRIMARY_TX_A | B3: I_CVD_PRIMARY | D3: Antihypertensives and statins for absolute CVD risk >20% | E3: shared-count-once | F3: all | G3: 0.06 | H3: 1 | I3: 69.3 | J3: 0.14506229 | K3: 0.4165 | L3: TRUE
A4: COST_T2D_SCREEN | B4: I_T2D_TREATMENT | C4: dm2 | D4: Diabetes opportunistic screening | E4: cause-specific | F4: all | G4: 1e-05 | H4: 1 | I4: 0.70495848 | J4: 0.033768828 | K4: 0.4165 | L4: TRUE
A5: COST_T2D_NONINSULIN | B5: I_T2D_TREATMENT | C5: dm2 | D5: Diabetes management, non insulin dependent | E5: cause-specific | F5: prevalence | G5: 0.6 | H5: 1 | I5: 82.68 | J5: 0.033768828 | K5: 0.4165 | L5: TRUE
A6: COST_T2D_INSULIN | B6: I_T2D_TREATMENT | C6: dm2 | D6: Diabetes management, insulin dependent | E6: cause-specific | F6: prevalence | G6: 0.2 | H6: 1 | I6: 82.68 | J6: 0.033768828 | K6: 0.4165 | L6: TRUE

Sheet PH_Selected_Interventions
A1: intervention_id | B1: intervention_cause_key | C1: cause_code | D1: model_transition | E1: transition_from | F1: transition_to | G1: effect_model | H1: baseline_exposure | I1: target_exposure | J1: response_value | K1: start_year | L1: target_year
A2: I_PH_TOBACCO_TAX | B2: I_PH_TOBACCO_TAX__C_ICH | C2: hstroke | D2: incidence | E2: well | F2: sick | G2: direct_smoking_prevalence_shift_rr | H2: 0.303 | I2: 0.19722936 | J2: 1.19 | K2: 2026 | L2: 2030
A3: I_PH_TOBACCO_TAX | B3: I_PH_TOBACCO_TAX__C_ICH__SICK_DEAD | C3: hstroke | D3: case_fatality | E3: sick | F3: dead | G3: tobacco_mortality_prevalence_shift_rr | H3: 0.303 | I3: 0.19722936 | J3: 3 | K3: 2026 | L3: 2030
A4: I_PH_TOBACCO_TAX | B4: I_PH_TOBACCO_TAX__C_IHD | C4: ihd | D4: incidence | E4: well | F4: sick | G4: direct_smoking_prevalence_shift_rr | H4: 0.303 | I4: 0.19722936 | J4: 1.6 | K4: 2026 | L4: 2030
A5: I_PH_TOBACCO_TAX | B5: I_PH_TOBACCO_TAX__C_IHD__SICK_DEAD | C5: ihd | D5: case_fatality | E5: sick | F5: dead | G5: tobacco_mortality_prevalence_shift_rr | H5: 0.303 | I5: 0.19722936 | J5: 3 | K5: 2026 | L5: 2030
A6: I_PH_TOBACCO_TAX | B6: I_PH_TOBACCO_TAX__C_IS | C6: istroke | D6: incidence | E6: well | F6: sick | G6: direct_smoking_prevalence_shift_rr | H6: 0.303 | I6: 0.19722936 | J6: 1.38 | K6: 2026 | L6: 2030
A7: I_PH_TOBACCO_TAX | B7: I_PH_TOBACCO_TAX__C_IS__SICK_DEAD | C7: istroke | D7: case_fatality | E7: sick | F7: dead | G7: tobacco_mortality_prevalence_shift_rr | H7: 0.303 | I7: 0.19722936 | J7: 3 | K7: 2026 | L7: 2030
A8: I_PH_TOBACCO_TAX | B8: I_PH_TOBACCO_TAX__C_T2DM | C8: dm2 | D8: incidence | E8: well | F8: sick | G8: direct_smoking_prevalence_shift_rr | H8: 0.303 | I8: 0.19722936 | J8: 1.37 | K8: 2026 | L8: 2030
A9: I_PH_TOB_AD_BAN | B9: I_PH_TOB_AD_BAN__C_ICH | C9: hstroke | D9: incidence | E9: well | F9: sick | G9: direct_smoking_prevalence_shift_rr | H9: 0.303 | I9: 0.29088 | J9: 1.19 | K9: 2026 | L9: 2030
A10: I_PH_TOB_AD_BAN | B10: I_PH_TOB_AD_BAN__C_ICH__SICK_DEAD | C10: hstroke | D10: case_fatality | E10: sick | F10: dead | G10: tobacco_mortality_prevalence_shift_rr | H10: 0.303 | I10: 0.29088 | J10: 3 | K10: 2026 | L10: 2030
A11: I_PH_TOB_AD_BAN | B11: I_PH_TOB_AD_BAN__C_IHD | C11: ihd | D11: incidence | E11: well | F11: sick | G11: direct_smoking_prevalence_shift_rr | H11: 0.303 | I11: 0.29088 | J11: 1.6 | K11: 2026 | L11: 2030
A12: I_PH_TOB_AD_BAN | B12: I_PH_TOB_AD_BAN__C_IHD__SICK_DEAD | C12: ihd | D12: case_fatality | E12: sick | F12: dead | G12: tobacco_mortality_prevalence_shift_rr | H12: 0.303 | I12: 0.29088 | J12: 3 | K12: 2026 | L12: 2030
A13: I_PH_TOB_AD_BAN | B13: I_PH_TOB_AD_BAN__C_IS | C13: istroke | D13: incidence | E13: well | F13: sick | G13: direct_smoking_prevalence_shift_rr | H13: 0.303 | I13: 0.29088 | J13: 1.38 | K13: 2026 | L13: 2030
... A29: I_PH_TOB_MEDIA | B29: I_PH_TOB_MEDIA__C_T2DM | C29: dm2 | D29: incidence | E29: well | F29: sick | G29: direct_smoking_prevalence_shift_rr | H29: 0.303 | I29: 0.283305 | J29: 1.37 | K29: 2026 | L29: 2030

Sheet PH_Cost_Components
A1: cost_record_id | B1: intervention_id | C1: parent_package_id | D1: cost_component | E1: cost_scope | F1: population_in_need_fraction | G1: frequency_per_year | H1: unit_cost_usd | I1: c_age_start | J1: c_age_stop | K1: c_sex | L1: cost_ready
A2: COST_PH_TOB_TAX | B2: I_PH_TOBACCO_TAX | C2: I_PH_TOBACCO_TAX | D2: Annual intersectoral policy implementation | E2: shared-count-once | F2: 1 | G2: 1 | H2: 0.04 | I2: 0 | J2: 95 | K2: Both | L2: TRUE
A3: COST_PH_TOB_AD_BAN | B3: I_PH_TOB_AD_BAN | C3: I_PH_TOBACCO_POLICY | D3: Annual intersectoral policy implementation | E3: component-count-once | F3: 1 | G3: 1 | H3: 0.0077 | I3: 0 | J3: 95 | K3: Both | L3: TRUE
A4: COST_PH_TOB_CLEAN_AIR | B4: I_PH_TOB_CLEAN_AIR | C4: I_PH_TOBACCO_POLICY | D4: Annual intersectoral policy implementation | E4: component-count-once | F4: 1 | G4: 1 | H4: 0.0077 | I4: 0 | J4: 95 | K4: Both | L4: TRUE
A5: COST_PH_TOB_MEDIA | B5: I_PH_TOB_MEDIA | C5: I_PH_TOBACCO_POLICY | D5: Annual intersectoral policy implementation | E5: component-count-once | F5: 1 | G5: 1 | H5: 0.0077 | I5: 0 | J5: 95 | K5: Both | L5: TRUE

Sheet PH_Scenario_Hierarchy
A1: parent_scenario_id | B1: parent_scenario_name | C1: intervention_id | D1: intervention_name | E1: package_group | F1: scenario_role | G1: include_in_parent_scenario | H1: standalone_scenario_id | I1: parent_aggregation_rule | J1: outcome_reporting_rule | K1: cost_reporting_rule | L1: component_order | M1: source_note | N1: is_runnable | O1: is_parent_package
A2: I_PH_TOBACCO_TAX | B2: Tobacco tax | C2: I_PH_TOBACCO_TAX | D2: Tobacco tax | E2: Tobacco | F2: standalone | G2: 1 | H2: I_PH_TOBACCO_TAX | I2: single intervention | J2: report intervention | K2: report intervention cost | L2: 1 | M2: Fiscal | N2: TRUE | O2: FALSE
A3: I_PH_ALCOHOL_TAX | B3: Alcohol tax | C3: I_PH_ALCOHOL_TAX | D3: Alcohol tax | E3: Alcohol | F3: standalone | G3: 1 | H3: I_PH_ALCOHOL_TAX | I3: single intervention | J3: report intervention | K3: report intervention cost | L3: 1 | M3: Fiscal | N3: FALSE | O3: FALSE
A4: I_PH_TOBACCO_POLICY | B4: Tobacco policy package | C4: I_PH_TOB_CLEAN_AIR | D4: Smoke-free / clean-air law | E4: Tobacco | F4: child | G4: 1 | H4: I_PH_TOB_CLEAN_AIR | I4: run children jointly | J4: report child and parent | K4: sum child costs; rerun health jointly | L4: 1 | M4: MPOWER | N4: TRUE | O4: FALSE
A5: I_PH_TOBACCO_POLICY | B5: Tobacco policy package | C5: I_PH_TOB_MEDIA | D5: Tobacco mass-media campaign | E5: Tobacco | F5: child | G5: 1 | H5: I_PH_TOB_MEDIA | I5: run children jointly | J5: report child and parent | K5: sum child costs; rerun health jointly | L5: 2 | M5: MPOWER | N5: TRUE | O5: FALSE
A6: I_PH_TOBACCO_POLICY | B6: Tobacco policy package | C6: I_PH_TOB_AD_BAN | D6: Tobacco advertising ban | E6: Tobacco | F6: child | G6: 1 | H6: I_PH_TOB_AD_BAN | I6: run children jointly | J6: report child and parent | K6: sum child costs; rerun health jointly | L6: 3 | M6: MPOWER | N6: TRUE | O6: FALSE
A7: I_PH_ALCOHOL_POLICY | B7: Alcohol advertising policy | C7: I_PH_ALCOHOL_POLICY | D7: Alcohol advertising ban | E7: Alcohol | F7: standalone | G7: 1 | H7: I_PH_ALCOHOL_POLICY | I7: single intervention | J7: report intervention | K7: report intervention cost | L7: 1 | M7: Alcohol policy | N7: FALSE | O7: FALSE
A8: I_PH_SALT_POLICY | B8: Salt policy package | C8: I_PH_SALT_REFORM | D8: Mandatory sodium reformulation | E8: Diet | F8: child | G8: 1 | H8: I_PH_SALT_REFORM | I8: run children jointly | J8: report child and parent | K8: sum child costs; rerun health jointly | L8: 1 | M8: SHAKE | N8: FALSE | O8: FALSE
A9: I_PH_SALT_POLICY | B9: Salt policy package | C9: I_PH_SALT_FOPL | D9: Sodium front-of-pack labelling | E9: Diet | F9: child | G9: 1 | H9: I_PH_SALT_FOPL | I9: run children jointly | J9: report child and parent | K9: sum child costs; rerun health jointly | L9: 2 | M9: SHAKE | N9: FALSE | O9: FALSE
A10: I_PH_SALT_POLICY | B10: Salt policy package | C10: I_PH_SALT_MEDIA | D10: Sodium mass-media campaign | E10: Diet | F10: child | G10: 1 | H10: I_PH_SALT_MEDIA | I10: run children jointly | J10: report child and parent | K10: sum child costs; rerun health jointly | L10: 3 | M10: SHAKE | N10: FALSE | O10: FALSE
A11: I_PH_SALT_POLICY | B11: Salt policy package | C11: I_PH_SALT_ENV | D11: Supportive public-institution environment | E11: Diet | F11: child | G11: 1 | H11: I_PH_SALT_ENV | I11: run children jointly | J11: report child and parent | K11: sum child costs; rerun health jointly | L11: 4 | M11: SHAKE | N11: FALSE | O11: FALSE
A12: I_PH_TFA_POLICY | B12: Industrial TFA regulation | C12: I_PH_TFA_POLICY | D12: Industrial trans-fat elimination regulation | E12: Diet | F12: standalone | G12: 1 | H12: I_PH_TFA_POLICY | I12: single intervention | J12: report intervention | K12: report intervention cost | L12: 1 | M12: REPLACE | N12: FALSE | O12: FALSE
A13: I_PH_SSB_TAX | B13: SSB tax | C13: I_PH_SSB_TAX | D13: Sugar-sweetened beverage tax | E13: Diet | F13: standalone | G13: 1 | H13: I_PH_SSB_TAX | I13: single intervention | J13: report intervention | K13: report intervention cost | L13: 1 | M13: Fiscal | N13: FALSE | O13: FALSE

Sheet Annual_Mortality
A1: scenario | B1: scenario_label | C1: year | D1: cause | E1: cases | F1: cause_deaths | G1: base_cases | H1: base_deaths | I1: deaths_averted | J1: cases_averted
A2: I_PH_TOBACCO_POLICY | B2: Tobacco policy package | C2: 2025 | D2: cmd | E2: 11293.859 | F2: 8456.0911 | G2: 11293.859 | H2: 8456.0911 | I2: =H2-F2 | J2: =G2-E2
A3: I_PH_TOBACCO_POLICY | B3: Tobacco policy package | C3: 2025 | D3: dm2 | E3: 796801.79 | F3: 124437.1 | G3: 796801.79 | H3: 124437.1 | I3: =H3-F3 | J3: =G3-E3
A4: I_PH_TOBACCO_POLICY | B4: Tobacco policy package | C4: 2025 | D4: hhd | E4: 110599.34 | F4: 70978.798 | G4: 110599.34 | H4: 70978.798 | I4: =H4-F4 | J4: =G4-E4
A5: I_PH_TOBACCO_POLICY | B5: Tobacco policy package | C5: 2025 | D5: hstroke | E5: 269908.91 | F5: 250549.93 | G5: 269908.91 | H5: 250549.93 | I5: =H5-F5 | J5: =G5-E5
A6: I_PH_TOBACCO_POLICY | B6: Tobacco policy package | C6: 2025 | D6: ihd | E6: 605290.56 | F6: 336235.04 | G6: 605290.56 | H6: 336235.04 | I6: =H6-F6 | J6: =G6-E6
A7: I_PH_TOBACCO_POLICY | B7: Tobacco policy package | C7: 2025 | D7: istroke | E7: 328703.7 | F7: 165181.23 | G7: 328703.7 | H7: 165181.23 | I7: =H7-F7 | J7: =G7-E7
A8: I_PH_TOBACCO_POLICY | B8: Tobacco policy package | C8: 2025 | D8: rhd | E8: 12601.519 | F8: 3955.3071 | G8: 12601.519 | H8: 3955.3071 | I8: =H8-F8 | J8: =G8-E8
A9: I_PH_TOBACCO_POLICY | B9: Tobacco policy package | C9: 2026 | D9: cmd | E9: 11413.94 | F9: 8503.0488 | G9: 11413.94 | H9: 8503.0488 | I9: =H9-F9 | J9: =G9-E9
A10: I_PH_TOBACCO_POLICY | B10: Tobacco policy package | C10: 2026 | D10: dm2 | E10: 813844.57 | F10: 128333.95 | G10: 813844.57 | H10: 128333.95 | I10: =H10-F10 | J10: =G10-E10
A11: I_PH_TOBACCO_POLICY | B11: Tobacco policy package | C11: 2026 | D11: hhd | E11: 113261.47 | F11: 72339.688 | G11: 113261.47 | H11: 72339.688 | I11: =H11-F11 | J11: =G11-E11
A12: I_PH_TOBACCO_POLICY | B12: Tobacco policy package | C12: 2026 | D12: hstroke | E12: 273941.16 | F12: 253872.84 | G12: 274200.58 | H12: 254910.75 | I12: =H12-F12 | J12: =G12-E12
A13: I_PH_TOBACCO_POLICY | B13: Tobacco policy package | C13: 2026 | D13: ihd | E13: 618348.3 | F13: 343153.28 | G13: 620097.59 | H13: 344917.06 | I13: =H13-F13 | J13: =G13-E13
... A1639: all_public_health | B1639: All selected public-health interventions (combined) | C1639: 2050 | D1639: rhd | E1639: 11459.37 | F1639: 1051.1546 | G1639: 11458.332 | H1639: 1051.1139 | I1639: =H1639-F1639 | J1639: =G1639-E1639

Sheet Health_Outcomes
A1: scenario | B1: scenario_label | C1: year | D1: modeled_deaths | E1: baseline_deaths | F1: deaths_averted | G1: modeled_cases | H1: baseline_cases | I1: cases_averted | J1: yll | K1: base_yll | L1: yll_averted | M1: yld | N1: base_yld | O1: yld_averted | P1: daly | Q1: base_daly | R1: dalys_averted | S1: life_years_gained
A2: all_cascade_public_health | B2: 70-30-30 -> 70-70-70 cascade + all public-health interventions (combined) | C2: 2025 | D2: 959793.5 | E2: 959793.5 | F2: =E2-D2 | G2: 2135199.7 | H2: 2135199.7 | I2: =H2-G2 | J2: 13078631 | K2: 13078631 | L2: =K2-J2 | M2: 2439867.8 | N2: 2439867.8 | O2: =N2-M2 | P2: 15518499 | Q2: 15518499 | R2: =Q2-P2 | S2: =L2
A3: all_cascade_public_health | B3: 70-30-30 -> 70-70-70 cascade + all public-health interventions (combined) | C3: 2026 | D3: 968627.47 | E3: 980780.31 | F3: =E3-D3 | G3: 2172766.1 | H3: 2181019.5 | I3: =H3-G3 | J3: 13175557 | K3: 13376482 | L3: =K3-J3 | M3: 2495730 | N3: 2495093.1 | O3: =N3-M3 | P3: 15671287 | Q3: 15871576 | R3: =Q3-P3 | S3: =L3
A4: all_cascade_public_health | B4: 70-30-30 -> 70-70-70 cascade + all public-health interventions (combined) | C4: 2027 | D4: 979659.58 | E4: 1003320.8 | F4: =E4-D4 | G4: 2209291.3 | H4: 2228341.8 | I4: =H4-G4 | J4: 13281863 | K4: 13677395 | L4: =K4-J4 | M4: 2552762.7 | N4: 2551241 | O4: =N4-M4 | P4: 15834626 | Q4: 16228636 | R4: =Q4-P4 | S4: =L4
A5: all_cascade_public_health | B5: 70-30-30 -> 70-70-70 cascade + all public-health interventions (combined) | C5: 2028 | D5: 992527.08 | E5: 1027500.5 | F5: =E5-D5 | G5: 2258185.4 | H5: 2288120.7 | I5: =H5-G5 | J5: 13386409 | K5: 13973850 | L5: =K5-J5 | M5: 2611686.6 | N5: 2609119.5 | O5: =N5-M5 | P5: 15998095 | Q5: 16582969 | R5: =Q5-P5 | S5: =L5
A6: all_cascade_public_health | B6: 70-30-30 -> 70-70-70 cascade + all public-health interventions (combined) | C6: 2029 | D6: 1004558.9 | E6: 1053610.4 | F6: =E6-D6 | G6: 2294315.2 | H6: 2336688.1 | I6: =H6-G6 | J6: 13473060 | K6: 14290695 | L6: =K6-J6 | M6: 2671286.5 | N6: 2667387.1 | O6: =N6-M6 | P6: 16144347 | Q6: 16958082 | R6: =Q6-P6 | S6: =L6
A7: all_cascade_public_health | B7: 70-30-30 -> 70-70-70 cascade + all public-health interventions (combined) | C7: 2030 | D7: 1017729.3 | E7: 1080810.2 | F7: =E7-D7 | G7: 2331704.4 | H7: 2386448.8 | I7: =H7-G7 | J7: 13554564 | K7: 14601429 | L7: =K7-J7 | M7: 2731390.7 | N7: 2725934.8 | O7: =N7-M7 | P7: 16285954 | Q7: 17327364 | R7: =Q7-P7 | S7: =L7
A8: all_cascade_public_health | B8: 70-30-30 -> 70-70-70 cascade + all public-health interventions (combined) | C8: 2031 | D8: 1041784.5 | E8: 1107157.6 | F8: =E8-D8 | G8: 2360648.5 | H8: 2435295.4 | I8: =H8-G8 | J8: 13824538 | K8: 14910263 | L8: =K8-J8 | M8: 2789570.4 | N8: 2784742.8 | O8: =N8-M8 | P8: 16614108 | Q8: 17695005 | R8: =Q8-P8 | S8: =L8
A9: all_cascade_public_health | B9: 70-30-30 -> 70-70-70 cascade + all public-health interventions (combined) | C9: 2032 | D9: 1063438.1 | E9: 1133979.8 | F9: =E9-D9 | G9: 2391076.6 | H9: 2486226.9 | I9: =H9-G9 | J9: 14053501 | K9: 15212725 | L9: =K9-J9 | M9: 2846341.8 | N9: 2843886.5 | O9: =N9-M9 | P9: 16899842 | Q9: 18056611 | R9: =Q9-P9 | S9: =L9
A10: all_cascade_public_health | B10: 70-30-30 -> 70-70-70 cascade + all public-health interventions (combined) | C10: 2033 | D10: 1083048.5 | E10: 1160519 | F10: =E10-D10 | G10: 2427671.7 | H10: 2544179.9 | I10: =H10-G10 | J10: 14242624 | K10: 15498147 | L10: =K10-J10 | M10: 2902475.9 | N10: 2903939 | O10: =N10-M10 | P10: 17145100 | Q10: 18402086 | R10: =Q10-P10 | S10: =L10
A11: all_cascade_public_health | B11: 70-30-30 -> 70-70-70 cascade + all public-health interventions (combined) | C11: 2034 | D11: 1104600.1 | E11: 1187394.6 | F11: =E11-D11 | G11: 2455296.5 | H11: 2591241.8 | I11: =H11-G11 | J11: 14467426 | K11: 15799428 | L11: =K11-J11 | M11: 2956997.9 | N11: 2963891.1 | O11: =N11-M11 | P11: 17424424 | Q11: 18763320 | R11: =Q11-P11 | S11: =L11
A12: all_cascade_public_health | B12: 70-30-30 -> 70-70-70 cascade + all public-health interventions (combined) | C12: 2035 | D12: 1124823.9 | E12: 1214326 | F12: =E12-D12 | G12: 2481664.4 | H12: 2637338.6 | I12: =H12-G12 | J12: 14666544 | K12: 16093446 | L12: =K12-J12 | M12: 3009917.3 | N12: 3023565.8 | O12: =N12-M12 | P12: 17676461 | Q12: 19117012 | R12: =Q12-P12 | S12: =L12
A13: all_cascade_public_health | B13: 70-30-30 -> 70-70-70 cascade + all public-health interventions (combined) | C13: 2036 | D13: 1133885.7 | E13: 1242005.2 | F13: =E13-D13 | G13: 2506159.8 | H13: 2687815.4 | I13: =H13-G13 | J13: 14722608 | K13: 16387284 | L13: =K13-J13 | M13: 3062312.6 | N13: 3083207.2 | O13: =N13-M13 | P13: 17784920 | Q13: 19470491 | R13: =Q13-P13 | S13: =L13
... A235: S_70_30_30_TO_70_70_70_I_PH_TOBACCO_TAX | B235: 70-30-30 -> 70-70-70 cascade + tobacco tax | C235: 2050 | D235: 1402000.1 | E235: 1604008.5 | F235: =E235-D235 | G235: 3012341.6 | H235: 3257199.3 | I235: =H235-G235 | J235: 16631506 | K235: 19570013 | L235: =K235-J235 | M235: 3730041.4 | N235: 3846594.4 | O235: =N235-M235 | P235: 20361548 | Q235: 23416608 | R235: =Q235-P235 | S235: =L235

Sheet CVD_40q30
A1: location | B1: scenario | C1: scenario_label | D1: intervention_family | E1: scenario_role | F1: parent_package_id | G1: htn_target_scenario | H1: year | I1: cvd_40q30 | J1: baseline_cvd_40q30 | K1: absolute_reduction_pp | L1: percent_reduction | M1: cvd_40q30_r | N1: recon_status
A2: Indonesia | B2: I_PH_TOBACCO_POLICY | C2: Tobacco policy package | D2: public_health | E2: package | F2: I_PH_TOBACCO_POLICY | G2: htncov2_aspirational | H2: 2025 | I2: =100*(1-(SUMIFS('CVD_40q30_Age'!$M$2:$M$10401,'CVD_40q30_Age'!$A$2:$A$10401,A2,'CVD_40q30_Age'!$B$2:$B$10401,B2,'CVD_40q30_Age'!$E$2:$E$10401,G2,'CVD_40q30_Age'!$F$2:$F$10401,H2,'CVD_40q30_Age'!$G$2:$G$10401,69))/(SUMIFS('CVD_40q30_Age'!$L$2:$L$10401,'CVD_40q30_Age'!$A$2:$A$10401,A2,'CVD_40q30_Age'!$B$2:$B$10401,B2,'CVD_40q30_Age'!$E$2:$E$10401,G2,'CVD_40q30_Age'!$F$2:$F$10401,H2,'CVD_40q30_Age'!$G$2:$G$10401,30))) | J2: =SUMIFS($I$2:$I$261,$A$2:$A$261,A2,$G$2:$G$261,G2,$H$2:$H$261,H2,$B$2:$B$261,"baseline") | K2: =J2-I2 | L2: =IF(J2=0,"",100*(J2-I2)/J2) | M2: 14.594863 | N2: =IF(ABS(I2-M2)<=0.001,"match","mismatch")
A3: Indonesia | B3: I_PH_TOBACCO_POLICY | C3: Tobacco policy package | D3: public_health | E3: package | F3: I_PH_TOBACCO_POLICY | G3: htncov2_aspirational | H3: 2026 | I3: =100*(1-(SUMIFS('CVD_40q30_Age'!$M$2:$M$10401,'CVD_40q30_Age'!$A$2:$A$10401,A3,'CVD_40q30_Age'!$B$2:$B$10401,B3,'CVD_40q30_Age'!$E$2:$E$10401,G3,'CVD_40q30_Age'!$F$2:$F$10401,H3,'CVD_40q30_Age'!$G$2:$G$10401,69))/(SUMIFS('CVD_40q30_Age'!$L$2:$L$10401,'CVD_40q30_Age'!$A$2:$A$10401,A3,'CVD_40q30_Age'!$B$2:$B$10401,B3,'CVD_40q30_Age'!$E$2:$E$10401,G3,'CVD_40q30_Age'!$F$2:$F$10401,H3,'CVD_40q30_Age'!$G$2:$G$10401,30))) | J3: =SUMIFS($I$2:$I$261,$A$2:$A$261,A3,$G$2:$G$261,G3,$H$2:$H$261,H3,$B$2:$B$261,"baseline") | K3: =J3-I3 | L3: =IF(J3=0,"",100*(J3-I3)/J3) | M3: 14.456941 | N3: =IF(ABS(I3-M3)<=0.001,"match","mismatch")
A4: Indonesia | B4: I_PH_TOBACCO_POLICY | C4: Tobacco policy package | D4: public_health | E4: package | F4: I_PH_TOBACCO_POLICY | G4: htncov2_aspirational | H4: 2027 | I4: =100*(1-(SUMIFS('CVD_40q30_Age'!$M$2:$M$10401,'CVD_40q30_Age'!$A$2:$A$10401,A4,'CVD_40q30_Age'!$B$2:$B$10401,B4,'CVD_40q30_Age'!$E$2:$E$10401,G4,'CVD_40q30_Age'!$F$2:$F$10401,H4,'CVD_40q30_Age'!$G$2:$G$10401,69))/(SUMIFS('CVD_40q30_Age'!$L$2:$L$10401,'CVD_40q30_Age'!$A$2:$A$10401,A4,'CVD_40q30_Age'!$B$2:$B$10401,B4,'CVD_40q30_Age'!$E$2:$E$10401,G4,'CVD_40q30_Age'!$F$2:$F$10401,H4,'CVD_40q30_Age'!$G$2:$G$10401,30))) | J4: =SUMIFS($I$2:$I$261,$A$2:$A$261,A4,$G$2:$G$261,G4,$H$2:$H$261,H4,$B$2:$B$261,"baseline") | K4: =J4-I4 | L4: =IF(J4=0,"",100*(J4-I4)/J4) | M4: 14.314466 | N4: =IF(ABS(I4-M4)<=0.001,"match","mismatch")
A5: Indonesia | B5: I_PH_TOBACCO_POLICY | C5: Tobacco policy package | D5: public_health | E5: package | F5: I_PH_TOBACCO_POLICY | G5: htncov2_aspirational | H5: 2028 | I5: =100*(1-(SUMIFS('CVD_40q30_Age'!$M$2:$M$10401,'CVD_40q30_Age'!$A$2:$A$10401,A5,'CVD_40q30_Age'!$B$2:$B$10401,B5,'CVD_40q30_Age'!$E$2:$E$10401,G5,'CVD_40q30_Age'!$F$2:$F$10401,H5,'CVD_40q30_Age'!$G$2:$G$10401,69))/(SUMIFS('CVD_40q30_Age'!$L$2:$L$10401,'CVD_40q30_Age'!$A$2:$A$10401,A5,'CVD_40q30_Age'!$B$2:$B$10401,B5,'CVD_40q30_Age'!$E$2:$E$10401,G5,'CVD_40q30_Age'!$F$2:$F$10401,H5,'CVD_40q30_Age'!$G$2:$G$10401,30))) | J5: =SUMIFS($I$2:$I$261,$A$2:$A$261,A5,$G$2:$G$261,G5,$H$2:$H$261,H5,$B$2:$B$261,"baseline") | K5: =J5-I5 | L5: =IF(J5=0,"",100*(J5-I5)/J5) | M5: 14.175458 | N5: =IF(ABS(I5-M5)<=0.001,"match","mismatch")
A6: Indonesia | B6: I_PH_TOBACCO_POLICY | C6: Tobacco policy package | D6: public_health | E6: package | F6: I_PH_TOBACCO_POLICY | G6: htncov2_aspirational | H6: 2029 | I6: =100*(1-(SUMIFS('CVD_40q30_Age'!$M$2:$M$10401,'CVD_40q30_Age'!$A$2:$A$10401,A6,'CVD_40q30_Age'!$B$2:$B$10401,B6,'CVD_40q30_Age'!$E$2:$E$10401,G6,'CVD_40q30_Age'!$F$2:$F$10401,H6,'CVD_40q30_Age'!$G$2:$G$10401,69))/(SUMIFS('CVD_40q30_Age'!$L$2:$L$10401,'CVD_40q30_Age'!$A$2:$A$10401,A6,'CVD_40q30_Age'!$B$2:$B$10401,B6,'CVD_40q30_Age'!$E$2:$E$10401,G6,'CVD_40q30_Age'!$F$2:$F$10401,H6,'CVD_40q30_Age'!$G$2:$G$10401,30))) | J6: =SUMIFS($I$2:$I$261,$A$2:$A$261,A6,$G$2:$G$261,G6,$H$2:$H$261,H6,$B$2:$B$261,"baseline") | K6: =J6-I6 | L6: =IF(J6=0,"",100*(J6-I6)/J6) | M6: 14.033685 | N6: =IF(ABS(I6-M6)<=0.001,"match","mismatch")
A7: Indonesia | B7: I_PH_TOBACCO_POLICY | C7: Tobacco policy package | D7: public_health | E7: package | F7: I_PH_TOBACCO_POLICY | G7: htncov2_aspirational | H7: 2030 | I7: =100*(1-(SUMIFS('CVD_40q30_Age'!$M$2:$M$10401,'CVD_40q30_Age'!$A$2:$A$10401,A7,'CVD_40q30_Age'!$B$2:$B$10401,B7,'CVD_40q30_Age'!$E$2:$E$10401,G7,'CVD_40q30_Age'!$F$2:$F$10401,H7,'CVD_40q30_Age'!$G$2:$G$10401,69))/(SUMIFS('CVD_40q30_Age'!$L$2:$L$10401,'CVD_40q30_Age'!$A$2:$A$10401,A7,'CVD_40q30_Age'!$B$2:$B$10401,B7,'CVD_40q30_Age'!$E$2:$E$10401,G7,'CVD_40q30_Age'!$F$2:$F$10401,H7,'CVD_40q30_Age'!$G$2:$G$10401,30))) | J7: =SUMIFS($I$2:$I$261,$A$2:$A$261,A7,$G$2:$G$261,G7,$H$2:$H$261,H7,$B$2:$B$261,"baseline") | K7: =J7-I7 | L7: =IF(J7=0,"",100*(J7-I7)/J7) | M7: 13.886552 | N7: =IF(ABS(I7-M7)<=0.001,"match","mismatch")
A8: Indonesia | B8: I_PH_TOBACCO_POLICY | C8: Tobacco policy package | D8: public_health | E8: package | F8: I_PH_TOBACCO_POLICY | G8: htncov2_aspirational | H8: 2031 | I8: =100*(1-(SUMIFS('CVD_40q30_Age'!$M$2:$M$10401,'CVD_40q30_Age'!$A$2:$A$10401,A8,'CVD_40q30_Age'!$B$2:$B$10401,B8,'CVD_40q30_Age'!$E$2:$E$10401,G8,'CVD_40q30_Age'!$F$2:$F$10401,H8,'CVD_40q30_Age'!$G$2:$G$10401,69))/(SUMIFS('CVD_40q30_Age'!$L$2:$L$10401,'CVD_40q30_Age'!$A$2:$A$10401,A8,'CVD_40q30_Age'!$B$2:$B$10401,B8,'CVD_40q30_Age'!$E$2:$E$10401,G8,'CVD_40q30_Age'!$F$2:$F$10401,H8,'CVD_40q30_Age'!$G$2:$G$10401,30))) | J8: =SUMIFS($I$2:$I$261,$A$2:$A$261,A8,$G$2:$G$261,G8,$H$2:$H$261,H8,$B$2:$B$261,"baseline") | K8: =J8-I8 | L8: =IF(J8=0,"",100*(J8-I8)/J8) | M8: 13.779364 | N8: =IF(ABS(I8-M8)<=0.001,"match","mismatch")
A9: Indonesia | B9: I_PH_TOBACCO_POLICY | C9: Tobacco policy package | D9: public_health | E9: package | F9: I_PH_TOBACCO_POLICY | G9: htncov2_aspirational | H9: 2032 | I9: =100*(1-(SUMIFS('CVD_40q30_Age'!$M$2:$M$10401,'CVD_40q30_Age'!$A$2:$A$10401,A9,'CVD_40q30_Age'!$B$2:$B$10401,B9,'CVD_40q30_Age'!$E$2:$E$10401,G9,'CVD_40q30_Age'!$F$2:$F$10401,H9,'CVD_40q30_Age'!$G$2:$G$10401,69))/(SUMIFS('CVD_40q30_Age'!$L$2:$L$10401,'CVD_40q30_Age'!$A$2:$A$10401,A9,'CVD_40q30_Age'!$B$2:$B$10401,B9,'CVD_40q30_Age'!$E$2:$E$10401,G9,'CVD_40q30_Age'!$F$2:$F$10401,H9,'CVD_40q30_Age'!$G$2:$G$10401,30))) | J9: =SUMIFS($I$2:$I$261,$A$2:$A$261,A9,$G$2:$G$261,G9,$H$2:$H$261,H9,$B$2:$B$261,"baseline") | K9: =J9-I9 | L9: =IF(J9=0,"",100*(J9-I9)/J9) | M9: 13.661763 | N9: =IF(ABS(I9-M9)<=0.001,"match","mismatch")
A10: Indonesia | B10: I_PH_TOBACCO_POLICY | C10: Tobacco policy package | D10: public_health | E10: package | F10: I_PH_TOBACCO_POLICY | G10: htncov2_aspirational | H10: 2033 | I10: =100*(1-(SUMIFS('CVD_40q30_Age'!$M$2:$M$10401,'CVD_40q30_Age'!$A$2:$A$10401,A10,'CVD_40q30_Age'!$B$2:$B$10401,B10,'CVD_40q30_Age'!$E$2:$E$10401,G10,'CVD_40q30_Age'!$F$2:$F$10401,H10,'CVD_40q30_Age'!$G$2:$G$10401,69))/(SUMIFS('CVD_40q30_Age'!$L$2:$L$10401,'CVD_40q30_Age'!$A$2:$A$10401,A10,'CVD_40q30_Age'!$B$2:$B$10401,B10,'CVD_40q30_Age'!$E$2:$E$10401,G10,'CVD_40q30_Age'!$F$2:$F$10401,H10,'CVD_40q30_Age'!$G$2:$G$10401,30))) | J10: =SUMIFS($I$2:$I$261,$A$2:$A$261,A10,$G$2:$G$261,G10,$H$2:$H$261,H10,$B$2:$B$261,"baseline") | K10: =J10-I10 | L10: =IF(J10=0,"",100*(J10-I10)/J10) | M10: 13.531395 | N10: =IF(ABS(I10-M10)<=0.001,"match","mismatch")
A11: Indonesia | B11: I_PH_TOBACCO_POLICY | C11: Tobacco policy package | D11: public_health | E11: package | F11: I_PH_TOBACCO_POLICY | G11: htncov2_aspirational | H11: 2034 | I11: =100*(1-(SUMIFS('CVD_40q30_Age'!$M$2:$M$10401,'CVD_40q30_Age'!$A$2:$A$10401,A11,'CVD_40q30_Age'!$B$2:$B$10401,B11,'CVD_40q30_Age'!$E$2:$E$10401,G11,'CVD_40q30_Age'!$F$2:$F$10401,H11,'CVD_40q30_Age'!$G$2:$G$10401,69))/(SUMIFS('CVD_40q30_Age'!$L$2:$L$10401,'CVD_40q30_Age'!$A$2:$A$10401,A11,'CVD_40q30_Age'!$B$2:$B$10401,B11,'CVD_40q30_Age'!$E$2:$E$10401,G11,'CVD_40q30_Age'!$F$2:$F$10401,H11,'CVD_40q30_Age'!$G$2:$G$10401,30))) | J11: =SUMIFS($I$2:$I$261,$A$2:$A$261,A11,$G$2:$G$261,G11,$H$2:$H$261,H11,$B$2:$B$261,"baseline") | K11: =J11-I11 | L11: =IF(J11=0,"",100*(J11-I11)/J11) | M11: 13.419038 | N11: =IF(ABS(I11-M11)<=0.001,"match","mismatch")
A12: Indonesia | B12: I_PH_TOBACCO_POLICY | C12: Tobacco policy package | D12: public_health | E12: package | F12: I_PH_TOBACCO_POLICY | G12: htncov2_aspirational | H12: 2035 | I12: =100*(1-(SUMIFS('CVD_40q30_Age'!$M$2:$M$10401,'CVD_40q30_Age'!$A$2:$A$10401,A12,'CVD_40q30_Age'!$B$2:$B$10401,B12,'CVD_40q30_Age'!$E$2:$E$10401,G12,'CVD_40q30_Age'!$F$2:$F$10401,H12,'CVD_40q30_Age'!$G$2:$G$10401,69))/(SUMIFS('CVD_40q30_Age'!$L$2:$L$10401,'CVD_40q30_Age'!$A$2:$A$10401,A12,'CVD_40q30_Age'!$B$2:$B$10401,B12,'CVD_40q30_Age'!$E$2:$E$10401,G12,'CVD_40q30_Age'!$F$2:$F$10401,H12,'CVD_40q30_Age'!$G$2:$G$10401,30))) | J12: =SUMIFS($I$2:$I$261,$A$2:$A$261,A12,$G$2:$G$261,G12,$H$2:$H$261,H12,$B$2:$B$261,"baseline") | K12: =J12-I12 | L12: =IF(J12=0,"",100*(J12-I12)/J12) | M12: 13.29789 | N12: =IF(ABS(I12-M12)<=0.001,"match","mismatch")
A13: Indonesia | B13: I_PH_TOBACCO_POLICY | C13: Tobacco policy package | D13: public_health | E13: package | F13: I_PH_TOBACCO_POLICY | G13: htncov2_aspirational | H13: 2036 | I13: =100*(1-(SUMIFS('CVD_40q30_Age'!$M$2:$M$10401,'CVD_40q30_Age'!$A$2:$A$10401,A13,'CVD_40q30_Age'!$B$2:$B$10401,B13,'CVD_40q30_Age'!$E$2:$E$10401,G13,'CVD_40q30_Age'!$F$2:$F$10401,H13,'CVD_40q30_Age'!$G$2:$G$10401,69))/(SUMIFS('CVD_40q30_Age'!$L$2:$L$10401,'CVD_40q30_Age'!$A$2:$A$10401,A13,'CVD_40q30_Age'!$B$2:$B$10401,B13,'CVD_40q30_Age'!$E$2:$E$10401,G13,'CVD_40q30_Age'!$F$2:$F$10401,H13,'CVD_40q30_Age'!$G$2:$G$10401,30))) | J13: =SUMIFS($I$2:$I$261,$A$2:$A$261,A13,$G$2:$G$261,G13,$H$2:$H$261,H13,$B$2:$B$261,"baseline") | K13: =J13-I13 | L13: =IF(J13=0,"",100*(J13-I13)/J13) | M13: 13.14275 | N13: =IF(ABS(I13-M13)<=0.001,"match","mismatch")
... A27: Indonesia | B27: I_PH_TOBACCO_POLICY | C27: Tobacco policy package | D27: public_health | E27: package | F27: I_PH_TOBACCO_POLICY | G27: htncov2_aspirational | H27: 2050 | I27: =100*(1-(SUMIFS('CVD_40q30_Age'!$M$2:$M$10401,'CVD_40q30_Age'!$A$2:$A$10401,A27,'CVD_40q30_Age'!$B$2:$B$10401,B27,'CVD_40q30_Age'!$E$2:$E$10401,G27,'CVD_40q30_Age'!$F$2:$F$10401,H27,'CVD_40q30_Age'!$G$2:$G$10401,69))/(SUMIFS('CVD_40q30_Age'!$L$2:$L$10401,'CVD_40q30_Age'!$A$2:$A$10401,A27,'CVD_40q30_Age'!$B$2:$B$10401,B27,'CVD_40q30_Age'!$E$2:$E$10401,G27,'CVD_40q30_Age'!$F$2:$F$10401,H27,'CVD_40q30_Age'!$G$2:$G$10401,30))) | J27: =SUMIFS($I$2:$I$261,$A$2:$A$261,A27,$G$2:$G$261,G27,$H$2:$H$261,H27,$B$2:$B$261,"baseline") | K27: =J27-I27 | L27: =IF(J27=0,"",100*(J27-I27)/J27) | M27: 11.26863 | N27: =IF(ABS(I27-M27)<=0.001,"match","mismatch")
A28: Indonesia | B28: I_PH_TOBACCO_TAX | C28: Tobacco tax | D28: public_health | E28: standalone | G28: htncov2_aspirational | H28: 2025 | I28: =100*(1-(SUMIFS('CVD_40q30_Age'!$M$2:$M$10401,'CVD_40q30_Age'!$A$2:$A$10401,A28,'CVD_40q30_Age'!$B$2:$B$10401,B28,'CVD_40q30_Age'!$E$2:$E$10401,G28,'CVD_40q30_Age'!$F$2:$F$10401,H28,'CVD_40q30_Age'!$G$2:$G$10401,69))/(SUMIFS('CVD_40q30_Age'!$L$2:$L$10401,'CVD_40q30_Age'!$A$2:$A$10401,A28,'CVD_40q30_Age'!$B$2:$B$10401,B28,'CVD_40q30_Age'!$E$2:$E$10401,G28,'CVD_40q30_Age'!$F$2:$F$10401,H28,'CVD_40q30_Age'!$G$2:$G$10401,30))) | J28: =SUMIFS($I$2:$I$261,$A$2:$A$261,A28,$G$2:$G$261,G28,$H$2:$H$261,H28,$B$2:$B$261,"baseline") | K28: =J28-I28 | L28: =IF(J28=0,"",100*(J28-I28)/J28) | M28: 14.594863 | N28: =IF(ABS(I28-M28)<=0.001,"match","mismatch")
A29: Indonesia | B29: I_PH_TOBACCO_TAX | C29: Tobacco tax | D29: public_health | E29: standalone | G29: htncov2_aspirational | H29: 2026 | I29: =100*(1-(SUMIFS('CVD_40q30_Age'!$M$2:$M$10401,'CVD_40q30_Age'!$A$2:$A$10401,A29,'CVD_40q30_Age'!$B$2:$B$10401,B29,'CVD_40q30_Age'!$E$2:$E$10401,G29,'CVD_40q30_Age'!$F$2:$F$10401,H29,'CVD_40q30_Age'!$G$2:$G$10401,69))/(SUMIFS('CVD_40q30_Age'!$L$2:$L$10401,'CVD_40q30_Age'!$A$2:$A$10401,A29,'CVD_40q30_Age'!$B$2:$B$10401,B29,'CVD_40q30_Age'!$E$2:$E$10401,G29,'CVD_40q30_Age'!$F$2:$F$10401,H29,'CVD_40q30_Age'!$G$2:$G$10401,30))) | J29: =SUMIFS($I$2:$I$261,$A$2:$A$261,A29,$G$2:$G$261,G29,$H$2:$H$261,H29,$B$2:$B$261,"baseline") | K29: =J29-I29 | L29: =IF(J29=0,"",100*(J29-I29)/J29) | M29: 14.381953 | N29: =IF(ABS(I29-M29)<=0.001,"match","mismatch")
A30: Indonesia | B30: I_PH_TOBACCO_TAX | C30: Tobacco tax | D30: public_health | E30: standalone | G30: htncov2_aspirational | H30: 2027 | I30: =100*(1-(SUMIFS('CVD_40q30_Age'!$M$2:$M$10401,'CVD_40q30_Age'!$A$2:$A$10401,A30,'CVD_40q30_Age'!$B$2:$B$10401,B30,'CVD_40q30_Age'!$E$2:$E$10401,G30,'CVD_40q30_Age'!$F$2:$F$10401,H30,'CVD_40q30_Age'!$G$2:$G$10401,69))/(SUMIFS('CVD_40q30_Age'!$L$2:$L$10401,'CVD_40q30_Age'!$A$2:$A$10401,A30,'CVD_40q30_Age'!$B$2:$B$10401,B30,'CVD_40q30_Age'!$E$2:$E$10401,G30,'CVD_40q30_Age'!$F$2:$F$10401,H30,'CVD_40q30_Age'!$G$2:$G$10401,30))) | J30: =SUMIFS($I$2:$I$261,$A$2:$A$261,A30,$G$2:$G$261,G30,$H$2:$H$261,H30,$B$2:$B$261,"baseline") | K30: =J30-I30 | L30: =IF(J30=0,"",100*(J30-I30)/J30) | M30: 14.169602 | N30: =IF(ABS(I30-M30)<=0.001,"match","mismatch")
A31: Indonesia | B31: I_PH_TOBACCO_TAX | C31: Tobacco tax | D31: public_health | E31: standalone | G31: htncov2_aspirational | H31: 2028 | I31: =100*(1-(SUMIFS('CVD_40q30_Age'!$M$2:$M$10401,'CVD_40q30_Age'!$A$2:$A$10401,A31,'CVD_40q30_Age'!$B$2:$B$10401,B31,'CVD_40q30_Age'!$E$2:$E$10401,G31,'CVD_40q30_Age'!$F$2:$F$10401,H31,'CVD_40q30_Age'!$G$2:$G$10401,69))/(SUMIFS('CVD_40q30_Age'!$L$2:$L$10401,'CVD_40q30_Age'!$A$2:$A$10401,A31,'CVD_40q30_Age'!$B$2:$B$10401,B31,'CVD_40q30_Age'!$E$2:$E$10401,G31,'CVD_40q30_Age'!$F$2:$F$10401,H31,'CVD_40q30_Age'!$G$2:$G$10401,30))) | J31: =SUMIFS($I$2:$I$261,$A$2:$A$261,A31,$G$2:$G$261,G31,$H$2:$H$261,H31,$B$2:$B$261,"baseline") | K31: =J31-I31 | L31: =IF(J31=0,"",100*(J31-I31)/J31) | M31: 13.963807 | N31: =IF(ABS(I31-M31)<=0.001,"match","mismatch")
A32: Indonesia | B32: I_PH_TOBACCO_TAX | C32: Tobacco tax | D32: public_health | E32: standalone | G32: htncov2_aspirational | H32: 2029 | I32: =100*(1-(SUMIFS('CVD_40q30_Age'!$M$2:$M$10401,'CVD_40q30_Age'!$A$2:$A$10401,A32,'CVD_40q30_Age'!$B$2:$B$10401,B32,'CVD_40q30_Age'!$E$2:$E$10401,G32,'CVD_40q30_Age'!$F$2:$F$10401,H32,'CVD_40q30_Age'!$G$2:$G$10401,69))/(SUMIFS('CVD_40q30_Age'!$L$2:$L$10401,'CVD_40q30_Age'!$A$2:$A$10401,A32,'CVD_40q30_Age'!$B$2:$B$10401,B32,'CVD_40q30_Age'!$E$2:$E$10401,G32,'CVD_40q30_Age'!$F$2:$F$10401,H32,'CVD_40q30_Age'!$G$2:$G$10401,30))) | J32: =SUMIFS($I$2:$I$261,$A$2:$A$261,A32,$G$2:$G$261,G32,$H$2:$H$261,H32,$B$2:$B$261,"baseline") | K32: =J32-I32 | L32: =IF(J32=0,"",100*(J32-I32)/J32) | M32: 13.740179 | N32: =IF(ABS(I32-M32)<=0.001,"match","mismatch")
A33: Indonesia | B33: I_PH_TOBACCO_TAX | C33: Tobacco tax | D33: public_health | E33: standalone | G33: htncov2_aspirational | H33: 2030 | I33: =100*(1-(SUMIFS('CVD_40q30_Age'!$M$2:$M$10401,'CVD_40q30_Age'!$A$2:$A$10401,A33,'CVD_40q30_Age'!$B$2:$B$10401,B33,'CVD_40q30_Age'!$E$2:$E$10401,G33,'CVD_40q30_Age'!$F$2:$F$10401,H33,'CVD_40q30_Age'!$G$2:$G$10401,69))/(SUMIFS('CVD_40q30_Age'!$L$2:$L$10401,'CVD_40q30_Age'!$A$2:$A$10401,A33,'CVD_40q30_Age'!$B$2:$B$10401,B33,'CVD_40q30_Age'!$E$2:$E$10401,G33,'CVD_40q30_Age'!$F$2:$F$10401,H33,'CVD_40q30_Age'!$G$2:$G$10401,30))) | J33: =SUMIFS($I$2:$I$261,$A$2:$A$261,A33,$G$2:$G$261,G33,$H$2:$H$261,H33,$B$2:$B$261,"baseline") | K33: =J33-I33 | L33: =IF(J33=0,"",100*(J33-I33)/J33) | M33: 13.513396 | N33: =IF(ABS(I33-M33)<=0.001,"match","mismatch")
A34: Indonesia | B34: I_PH_TOBACCO_TAX | C34: Tobacco tax | D34: public_health | E34: standalone | G34: htncov2_aspirational | H34: 2031 | I34: =100*(1-(SUMIFS('CVD_40q30_Age'!$M$2:$M$10401,'CVD_40q30_Age'!$A$2:$A$10401,A34,'CVD_40q30_Age'!$B$2:$B$10401,B34,'CVD_40q30_Age'!$E$2:$E$10401,G34,'CVD_40q30_Age'!$F$2:$F$10401,H34,'CVD_40q30_Age'!$G$2:$G$10401,69))/(SUMIFS('CVD_40q30_Age'!$L$2:$L$10401,'CVD_40q30_Age'!$A$2:$A$10401,A34,'CVD_40q30_Age'!$B$2:$B$10401,B34,'CVD_40q30_Age'!$E$2:$E$10401,G34,'CVD_40q30_Age'!$F$2:$F$10401,H34,'CVD_40q30_Age'!$G$2:$G$10401,30))) | J34: =SUMIFS($I$2:$I$261,$A$2:$A$261,A34,$G$2:$G$261,G34,$H$2:$H$261,H34,$B$2:$B$261,"baseline") | K34: =J34-I34 | L34: =IF(J34=0,"",100*(J34-I34)/J34) | M34: 13.405571 | N34: =IF(ABS(I34-M34)<=0.001,"match","mismatch")
A35: Indonesia | B35: I_PH_TOBACCO_TAX | C35: Tobacco tax | D35: public_health | E35: standalone | G35: htncov2_aspirational | H35: 2032 | I35: =100*(1-(SUMIFS('CVD_40q30_Age'!$M$2:$M$10401,'CVD_40q30_Age'!$A$2:$A$10401,A35,'CVD_40q30_Age'!$B$2:$B$10401,B35,'CVD_40q30_Age'!$E$2:$E$10401,G35,'CVD_40q30_Age'!$F$2:$F$10401,H35,'CVD_40q30_Age'!$G$2:$G$10401,69))/(SUMIFS('CVD_40q30_Age'!$L$2:$L$10401,'CVD_40q30_Age'!$A$2:$A$10401,A35,'CVD_40q30_Age'!$B$2:$B$10401,B35,'CVD_40q30_Age'!$E$2:$E$10401,G35,'CVD_40q30_Age'!$F$2:$F$10401,H35,'CVD_40q30_Age'!$G$2:$G$10401,30))) | J35: =SUMIFS($I$2:$I$261,$A$2:$A$261,A35,$G$2:$G$261,G35,$H$2:$H$261,H35,$B$2:$B$261,"baseline") | K35: =J35-I35 | L35: =IF(J35=0,"",100*(J35-I35)/J35) | M35: 13.283934 | N35: =IF(ABS(I35-M35)<=0.001,"match","mismatch")
A36: Indonesia | B36: I_PH_TOBACCO_TAX | C36: Tobacco tax | D36: public_health | E36: standalone | G36: htncov2_aspirational | H36: 2033 | I36: =100*(1-(SUMIFS('CVD_40q30_Age'!$M$2:$M$10401,'CVD_40q30_Age'!$A$2:$A$10401,A36,'CVD_40q30_Age'!$B$2:$B$10401,B36,'CVD_40q30_Age'!$E$2:$E$10401,G36,'CVD_40q30_Age'!$F$2:$F$10401,H36,'CVD_40q30_Age'!$G$2:$G$10401,69))/(SUMIFS('CVD_40q30_Age'!$L$2:$L$10401,'CVD_40q30_Age'!$A$2:$A$10401,A36,'CVD_40q30_Age'!$B$2:$B$10401,B36,'CVD_40q30_Age'!$E$2:$E$10401,G36,'CVD_40q30_Age'!$F$2:$F$10401,H36,'CVD_40q30_Age'!$G$2:$G$10401,30))) | J36: =SUMIFS($I$2:$I$261,$A$2:$A$261,A36,$G$2:$G$261,G36,$H$2:$H$261,H36,$B$2:$B$261,"baseline") | K36: =J36-I36 | L36: =IF(J36=0,"",100*(J36-I36)/J36) | M36: 13.14763 | N36: =IF(ABS(I36-M36)<=0.001,"match","mismatch")
A37: Indonesia | B37: I_PH_TOBACCO_TAX | C37: Tobacco tax | D37: public_health | E37: standalone | G37: htncov2_aspirational | H37: 2034 | I37: =100*(1-(SUMIFS('CVD_40q30_Age'!$M$2:$M$10401,'CVD_40q30_Age'!$A$2:$A$10401,A37,'CVD_40q30_Age'!$B$2:$B$10401,B37,'CVD_40q30_Age'!$E$2:$E$10401,G37,'CVD_40q30_Age'!$F$2:$F$10401,H37,'CVD_40q30_Age'!$G$2:$G$10401,69))/(SUMIFS('CVD_40q30_Age'!$L$2:$L$10401,'CVD_40q30_Age'!$A$2:$A$10401,A37,'CVD_40q30_Age'!$B$2:$B$10401,B37,'CVD_40q30_Age'!$E$2:$E$10401,G37,'CVD_40q30_Age'!$F$2:$F$10401,H37,'CVD_40q30_Age'!$G$2:$G$10401,30))) | J37: =SUMIFS($I$2:$I$261,$A$2:$A$261,A37,$G$2:$G$261,G37,$H$2:$H$261,H37,$B$2:$B$261,"baseline") | K37: =J37-I37 | L37: =IF(J37=0,"",100*(J37-I37)/J37) | M37: 13.044187 | N37: =IF(ABS(I37-M37)<=0.001,"match","mismatch")
A38: Indonesia | B38: I_PH_TOBACCO_TAX | C38: Tobacco tax | D38: public_health | E38: standalone | G38: htncov2_aspirational | H38: 2035 | I38: =100*(1-(SUMIFS('CVD_40q30_Age'!$M$2:$M$10401,'CVD_40q30_Age'!$A$2:$A$10401,A38,'CVD_40q30_Age'!$B$2:$B$10401,B38,'CVD_40q30_Age'!$E$2:$E$10401,G38,'CVD_40q30_Age'!$F$2:$F$10401,H38,'CVD_40q30_Age'!$G$2:$G$10401,69))/(SUMIFS('CVD_40q30_Age'!$L$2:$L$10401,'CVD_40q30_Age'!$A$2:$A$10401,A38,'CVD_40q30_Age'!$B$2:$B$10401,B38,'CVD_40q30_Age'!$E$2:$E$10401,G38,'CVD_40q30_Age'!$F$2:$F$10401,H38,'CVD_40q30_Age'!$G$2:$G$10401,30))) | J38: =SUMIFS($I$2:$I$261,$A$2:$A$261,A38,$G$2:$G$261,G38,$H$2:$H$261,H38,$B$2:$B$261,"baseline") | K38: =J38-I38 | L38: =IF(J38=0,"",100*(J38-I38)/J38) | M38: 12.929814 | N38: =IF(ABS(I38-M38)<=0.001,"match","mismatch")
A39: Indonesia | B39: I_PH_TOBACCO_TAX | C39: Tobacco tax | D39: public_health | E39: standalone | G39: htncov2_aspirational | H39: 2036 | I39: =100*(1-(SUMIFS('CVD_40q30_Age'!$M$2:$M$10401,'CVD_40q30_Age'!$A$2:$A$10401,A39,'CVD_40q30_Age'!$B$2:$B$10401,B39,'CVD_40q30_Age'!$E$2:$E$10401,G39,'CVD_40q30_Age'!$F$2:$F$10401,H39,'CVD_40q30_Age'!$G$2:$G$10401,69))/(SUMIFS('CVD_40q30_Age'!$L$2:$L$10401,'CVD_40q30_Age'!$A$2:$A$10401,A39,'CVD_40q30_Age'!$B$2:$B$10401,B39,'CVD_40q30_Age'!$E$2:$E$10401,G39,'CVD_40q30_Age'!$F$2:$F$10401,H39,'CVD_40q30_Age'!$G$2:$G$10401,30))) | J39: =SUMIFS($I$2:$I$261,$A$2:$A$261,A39,$G$2:$G$261,G39,$H$2:$H$261,H39,$B$2:$B$261,"baseline") | K39: =J39-I39 | L39: =IF(J39=0,"",100*(J39-I39)/J39) | M39: 12.730235 | N39: =IF(ABS(I39-M39)<=0.001,"match","mismatch")
... A53: Indonesia | B53: I_PH_TOBACCO_TAX | C53: Tobacco tax | D53: public_health | E53: standalone | G53: htncov2_aspirational | H53: 2050 | I53: =100*(1-(SUMIFS('CVD_40q30_Age'!$M$2:$M$10401,'CVD_40q30_Age'!$A$2:$A$10401,A53,'CVD_40q30_Age'!$B$2:$B$10401,B53,'CVD_40q30_Age'!$E$2:$E$10401,G53,'CVD_40q30_Age'!$F$2:$F$10401,H53,'CVD_40q30_Age'!$G$2:$G$10401,69))/(SUMIFS('CVD_40q30_Age'!$L$2:$L$10401,'CVD_40q30_Age'!$A$2:$A$10401,A53,'CVD_40q30_Age'!$B$2:$B$10401,B53,'CVD_40q30_Age'!$E$2:$E$10401,G53,'CVD_40q30_Age'!$F$2:$F$10401,H53,'CVD_40q30_Age'!$G$2:$G$10401,30))) | J53: =SUMIFS($I$2:$I$261,$A$2:$A$261,A53,$G$2:$G$261,G53,$H$2:$H$261,H53,$B$2:$B$261,"baseline") | K53: =J53-I53 | L53: =IF(J53=0,"",100*(J53-I53)/J53) | M53: 10.758791 | N53: =IF(ABS(I53-M53)<=0.001,"match","mismatch")
A54: Indonesia | B54: I_PH_TOB_AD_BAN | C54: Tobacco advertising ban | D54: public_health | E54: child | F54: I_PH_TOBACCO_POLICY | G54: htncov2_aspirational | H54: 2025 | I54: =100*(1-(SUMIFS('CVD_40q30_Age'!$M$2:$M$10401,'CVD_40q30_Age'!$A$2:$A$10401,A54,'CVD_40q30_Age'!$B$2:$B$10401,B54,'CVD_40q30_Age'!$E$2:$E$10401,G54,'CVD_40q30_Age'!$F$2:$F$10401,H54,'CVD_40q30_Age'!$G$2:$G$10401,69))/(SUMIFS('CVD_40q30_Age'!$L$2:$L$10401,'CVD_40q30_Age'!$A$2:$A$10401,A54,'CVD_40q30_Age'!$B$2:$B$10401,B54,'CVD_40q30_Age'!$E$2:$E$10401,G54,'CVD_40q30_Age'!$F$2:$F$10401,H54,'CVD_40q30_Age'!$G$2:$G$10401,30))) | J54: =SUMIFS($I$2:$I$261,$A$2:$A$261,A54,$G$2:$G$261,G54,$H$2:$H$261,H54,$B$2:$B$261,"baseline") | K54: =J54-I54 | L54: =IF(J54=0,"",100*(J54-I54)/J54) | M54: 14.594863 | N54: =IF(ABS(I54-M54)<=0.001,"match","mismatch")
A55: Indonesia | B55: I_PH_TOB_AD_BAN | C55: Tobacco advertising ban | D55: public_health | E55: child | F55: I_PH_TOBACCO_POLICY | G55: htncov2_aspirational | H55: 2026 | I55: =100*(1-(SUMIFS('CVD_40q30_Age'!$M$2:$M$10401,'CVD_40q30_Age'!$A$2:$A$10401,A55,'CVD_40q30_Age'!$B$2:$B$10401,B55,'CVD_40q30_Age'!$E$2:$E$10401,G55,'CVD_40q30_Age'!$F$2:$F$10401,H55,'CVD_40q30_Age'!$G$2:$G$10401,69))/(SUMIFS('CVD_40q30_Age'!$L$2:$L$10401,'CVD_40q30_Age'!$A$2:$A$10401,A55,'CVD_40q30_Age'!$B$2:$B$10401,B55,'CVD_40q30_Age'!$E$2:$E$10401,G55,'CVD_40q30_Age'!$F$2:$F$10401,H55,'CVD_40q30_Age'!$G$2:$G$10401,30))) | J55: =SUMIFS($I$2:$I$261,$A$2:$A$261,A55,$G$2:$G$261,G55,$H$2:$H$261,H55,$B$2:$B$261,"baseline") | K55: =J55-I55 | L55: =IF(J55=0,"",100*(J55-I55)/J55) | M55: 14.504247 | N55: =IF(ABS(I55-M55)<=0.001,"match","mismatch")
A56: Indonesia | B56: I_PH_TOB_AD_BAN | C56: Tobacco advertising ban | D56: public_health | E56: child | F56: I_PH_TOBACCO_POLICY | G56: htncov2_aspirational | H56: 2027 | I56: =100*(1-(SUMIFS('CVD_40q30_Age'!$M$2:$M$10401,'CVD_40q30_Age'!$A$2:$A$10401,A56,'CVD_40q30_Age'!$B$2:$B$10401,B56,'CVD_40q30_Age'!$E$2:$E$10401,G56,'CVD_40q30_Age'!$F$2:$F$10401,H56,'CVD_40q30_Age'!$G$2:$G$10401,69))/(SUMIFS('CVD_40q30_Age'!$L$2:$L$10401,'CVD_40q30_Age'!$A$2:$A$10401,A56,'CVD_40q30_Age'!$B$2:$B$10401,B56,'CVD_40q30_Age'!$E$2:$E$10401,G56,'CVD_40q30_Age'!$F$2:$F$10401,H56,'CVD_40q30_Age'!$G$2:$G$10401,30))) | J56: =SUMIFS($I$2:$I$261,$A$2:$A$261,A56,$G$2:$G$261,G56,$H$2:$H$261,H56,$B$2:$B$261,"baseline") | K56: =J56-I56 | L56: =IF(J56=0,"",100*(J56-I56)/J56) | M56: 14.405248 | N56: =IF(ABS(I56-M56)<=0.001,"match","mismatch")
A57: Indonesia | B57: I_PH_TOB_AD_BAN | C57: Tobacco advertising ban | D57: public_health | E57: child | F57: I_PH_TOBACCO_POLICY | G57: htncov2_aspirational | H57: 2028 | I57: =100*(1-(SUMIFS('CVD_40q30_Age'!$M$2:$M$10401,'CVD_40q30_Age'!$A$2:$A$10401,A57,'CVD_40q30_Age'!$B$2:$B$10401,B57,'CVD_40q30_Age'!$E$2:$E$10401,G57,'CVD_40q30_Age'!$F$2:$F$10401,H57,'CVD_40q30_Age'!$G$2:$G$10401,69))/(SUMIFS('CVD_40q30_Age'!$L$2:$L$10401,'CVD_40q30_Age'!$A$2:$A$10401,A57,'CVD_40q30_Age'!$B$2:$B$10401,B57,'CVD_40q30_Age'!$E$2:$E$10401,G57,'CVD_40q30_Age'!$F$2:$F$10401,H57,'CVD_40q30_Age'!$G$2:$G$10401,30))) | J57: =SUMIFS($I$2:$I$261,$A$2:$A$261,A57,$G$2:$G$261,G57,$H$2:$H$261,H57,$B$2:$B$261,"baseline") | K57: =J57-I57 | L57: =IF(J57=0,"",100*(J57-I57)/J57) | M57: 14.30719 | N57: =IF(ABS(I57-M57)<=0.001,"match","mismatch")
A58: Indonesia | B58: I_PH_TOB_AD_BAN | C58: Tobacco advertising ban | D58: public_health | E58: child | F58: I_PH_TOBACCO_POLICY | G58: htncov2_aspirational | H58: 2029 | I58: =100*(1-(SUMIFS('CVD_40q30_Age'!$M$2:$M$10401,'CVD_40q30_Age'!$A$2:$A$10401,A58,'CVD_40q30_Age'!$B$2:$B$10401,B58,'CVD_40q30_Age'!$E$2:$E$10401,G58,'CVD_40q30_Age'!$F$2:$F$10401,H58,'CVD_40q30_Age'!$G$2:$G$10401,69))/(SUMIFS('CVD_40q30_Age'!$L$2:$L$10401,'CVD_40q30_Age'!$A$2:$A$10401,A58,'CVD_40q30_Age'!$B$2:$B$10401,B58,'CVD_40q30_Age'!$E$2:$E$10401,G58,'CVD_40q30_Age'!$F$2:$F$10401,H58,'CVD_40q30_Age'!$G$2:$G$10401,30))) | J58: =SUMIFS($I$2:$I$261,$A$2:$A$261,A58,$G$2:$G$261,G58,$H$2:$H$261,H58,$B$2:$B$261,"baseline") | K58: =J58-I58 | L58: =IF(J58=0,"",100*(J58-I58)/J58) | M58: 14.214917 | N58: =IF(ABS(I58-M58)<=0.001,"match","mismatch")
A59: Indonesia | B59: I_PH_TOB_AD_BAN | C59: Tobacco advertising ban | D59: public_health | E59: child | F59: I_PH_TOBACCO_POLICY | G59: htncov2_aspirational | H59: 2030 | I59: =100*(1-(SUMIFS('CVD_40q30_Age'!$M$2:$M$10401,'CVD_40q30_Age'!$A$2:$A$10401,A59,'CVD_40q30_Age'!$B$2:$B$10401,B59,'CVD_40q30_Age'!$E$2:$E$10401,G59,'CVD_40q30_Age'!$F$2:$F$10401,H59,'CVD_40q30_Age'!$G$2:$G$10401,69))/(SUMIFS('CVD_40q30_Age'!$L$2:$L$10401,'CVD_40q30_Age'!$A$2:$A$10401,A59,'CVD_40q30_Age'!$B$2:$B$10401,B59,'CVD_40q30_Age'!$E$2:$E$10401,G59,'CVD_40q30_Age'!$F$2:$F$10401,H59,'CVD_40q30_Age'!$G$2:$G$10401,30))) | J59: =SUMIFS($I$2:$I$261,$A$2:$A$261,A59,$G$2:$G$261,G59,$H$2:$H$261,H59,$B$2:$B$261,"baseline") | K59: =J59-I59 | L59: =IF(J59=0,"",100*(J59-I59)/J59) | M59: 14.115155 | N59: =IF(ABS(I59-M59)<=0.001,"match","mismatch")
A60: Indonesia | B60: I_PH_TOB_AD_BAN | C60: Tobacco advertising ban | D60: public_health | E60: child | F60: I_PH_TOBACCO_POLICY | G60: htncov2_aspirational | H60: 2031 | I60: =100*(1-(SUMIFS('CVD_40q30_Age'!$M$2:$M$10401,'CVD_40q30_Age'!$A$2:$A$10401,A60,'CVD_40q30_Age'!$B$2:$B$10401,B60,'CVD_40q30_Age'!$E$2:$E$10401,G60,'CVD_40q30_Age'!$F$2:$F$10401,H60,'CVD_40q30_Age'!$G$2:$G$10401,69))/(SUMIFS('CVD_40q30_Age'!$L$2:$L$10401,'CVD_40q30_Age'!$A$2:$A$10401,A60,'CVD_40q30_Age'!$B$2:$B$10401,B60,'CVD_40q30_Age'!$E$2:$E$10401,G60,'CVD_40q30_Age'!$F$2:$F$10401,H60,'CVD_40q30_Age'!$G$2:$G$10401,30))) | J60: =SUMIFS($I$2:$I$261,$A$2:$A$261,A60,$G$2:$G$261,G60,$H$2:$H$261,H60,$B$2:$B$261,"baseline") | K60: =J60-I60 | L60: =IF(J60=0,"",100*(J60-I60)/J60) | M60: 14.008189 | N60: =IF(ABS(I60-M60)<=0.001,"match","mismatch")
A61: Indonesia | B61: I_PH_TOB_AD_BAN | C61: Tobacco advertising ban | D61: public_health | E61: child | F61: I_PH_TOBACCO_POLICY | G61: htncov2_aspirational | H61: 2032 | I61: =100*(1-(SUMIFS('CVD_40q30_Age'!$M$2:$M$10401,'CVD_40q30_Age'!$A$2:$A$10401,A61,'CVD_40q30_Age'!$B$2:$B$10401,B61,'CVD_40q30_Age'!$E$2:$E$10401,G61,'CVD_40q30_Age'!$F$2:$F$10401,H61,'CVD_40q30_Age'!$G$2:$G$10401,69))/(SUMIFS('CVD_40q30_Age'!$L$2:$L$10401,'CVD_40q30_Age'!$A$2:$A$10401,A61,'CVD_40q30_Age'!$B$2:$B$10401,B61,'CVD_40q30_Age'!$E$2:$E$10401,G61,'CVD_40q30_Age'!$F$2:$F$10401,H61,'CVD_40q30_Age'!$G$2:$G$10401,30))) | J61: =SUMIFS($I$2:$I$261,$A$2:$A$261,A61,$G$2:$G$261,G61,$H$2:$H$261,H61,$B$2:$B$261,"baseline") | K61: =J61-I61 | L61: =IF(J61=0,"",100*(J61-I61)/J61) | M61: 13.892993 | N61: =IF(ABS(I61-M61)<=0.001,"match","mismatch")
A62: Indonesia | B62: I_PH_TOB_AD_BAN | C62: Tobacco advertising ban | D62: public_health | E62: child | F62: I_PH_TOBACCO_POLICY | G62: htncov2_aspirational | H62: 2033 | I62: =100*(1-(SUMIFS('CVD_40q30_Age'!$M$2:$M$10401,'CVD_40q30_Age'!$A$2:$A$10401,A62,'CVD_40q30_Age'!$B$2:$B$10401,B62,'CVD_40q30_Age'!$E$2:$E$10401,G62,'CVD_40q30_Age'!$F$2:$F$10401,H62,'CVD_40q30_Age'!$G$2:$G$10401,69))/(SUMIFS('CVD_40q30_Age'!$L$2:$L$10401,'CVD_40q30_Age'!$A$2:$A$10401,A62,'CVD_40q30_Age'!$B$2:$B$10401,B62,'CVD_40q30_Age'!$E$2:$E$10401,G62,'CVD_40q30_Age'!$F$2:$F$10401,H62,'CVD_40q30_Age'!$G$2:$G$10401,30))) | J62: =SUMIFS($I$2:$I$261,$A$2:$A$261,A62,$G$2:$G$261,G62,$H$2:$H$261,H62,$B$2:$B$261,"baseline") | K62: =J62-I62 | L62: =IF(J62=0,"",100*(J62-I62)/J62) | M62: 13.766245 | N62: =IF(ABS(I62-M62)<=0.001,"match","mismatch")
A63: Indonesia | B63: I_PH_TOB_AD_BAN | C63: Tobacco advertising ban | D63: public_health | E63: child | F63: I_PH_TOBACCO_POLICY | G63: htncov2_aspirational | H63: 2034 | I63: =100*(1-(SUMIFS('CVD_40q30_Age'!$M$2:$M$10401,'CVD_40q30_Age'!$A$2:$A$10401,A63,'CVD_40q30_Age'!$B$2:$B$10401,B63,'CVD_40q30_Age'!$E$2:$E$10401,G63,'CVD_40q30_Age'!$F$2:$F$10401,H63,'CVD_40q30_Age'!$G$2:$G$10401,69))/(SUMIFS('CVD_40q30_Age'!$L$2:$L$10401,'CVD_40q30_Age'!$A$2:$A$10401,A63,'CVD_40q30_Age'!$B$2:$B$10401,B63,'CVD_40q30_Age'!$E$2:$E$10401,G63,'CVD_40q30_Age'!$F$2:$F$10401,H63,'CVD_40q30_Age'!$G$2:$G$10401,30))) | J63: =SUMIFS($I$2:$I$261,$A$2:$A$261,A63,$G$2:$G$261,G63,$H$2:$H$261,H63,$B$2:$B$261,"baseline") | K63: =J63-I63 | L63: =IF(J63=0,"",100*(J63-I63)/J63) | M63: 13.64883 | N63: =IF(ABS(I63-M63)<=0.001,"match","mismatch")
A64: Indonesia | B64: I_PH_TOB_AD_BAN | C64: Tobacco advertising ban | D64: public_health | E64: child | F64: I_PH_TOBACCO_POLICY | G64: htncov2_aspirational | H64: 2035 | I64: =100*(1-(SUMIFS('CVD_40q30_Age'!$M$2:$M$10401,'CVD_40q30_Age'!$A$2:$A$10401,A64,'CVD_40q30_Age'!$B$2:$B$10401,B64,'CVD_40q30_Age'!$E$2:$E$10401,G64,'CVD_40q30_Age'!$F$2:$F$10401,H64,'CVD_40q30_Age'!$G$2:$G$10401,69))/(SUMIFS('CVD_40q30_Age'!$L$2:$L$10401,'CVD_40q30_Age'!$A$2:$A$10401,A64,'CVD_40q30_Age'!$B$2:$B$10401,B64,'CVD_40q30_Age'!$E$2:$E$10401,G64,'CVD_40q30_Age'!$F$2:$F$10401,H64,'CVD_40q30_Age'!$G$2:$G$10401,30))) | J64: =SUMIFS($I$2:$I$261,$A$2:$A$261,A64,$G$2:$G$261,G64,$H$2:$H$261,H64,$B$2:$B$261,"baseline") | K64: =J64-I64 | L64: =IF(J64=0,"",100*(J64-I64)/J64) | M64: 13.523924 | N64: =IF(ABS(I64-M64)<=0.001,"match","mismatch")
A65: Indonesia | B65: I_PH_TOB_AD_BAN | C65: Tobacco advertising ban | D65: public_health | E65: child | F65: I_PH_TOBACCO_POLICY | G65: htncov2_aspirational | H65: 2036 | I65: =100*(1-(SUMIFS('CVD_40q30_Age'!$M$2:$M$10401,'CVD_40q30_Age'!$A$2:$A$10401,A65,'CVD_40q30_Age'!$B$2:$B$10401,B65,'CVD_40q30_Age'!$E$2:$E$10401,G65,'CVD_40q30_Age'!$F$2:$F$10401,H65,'CVD_40q30_Age'!$G$2:$G$10401,69))/(SUMIFS('CVD_40q30_Age'!$L$2:$L$10401,'CVD_40q30_Age'!$A$2:$A$10401,A65,'CVD_40q30_Age'!$B$2:$B$10401,B65,'CVD_40q30_Age'!$E$2:$E$10401,G65,'CVD_40q30_Age'!$F$2:$F$10401,H65,'CVD_40q30_Age'!$G$2:$G$10401,30))) | J65: =SUMIFS($I$2:$I$261,$A$2:$A$261,A65,$G$2:$G$261,G65,$H$2:$H$261,H65,$B$2:$B$261,"baseline") | K65: =J65-I65 | L65: =IF(J65=0,"",100*(J65-I65)/J65) | M65: 13.395091 | N65: =IF(ABS(I65-M65)<=0.001,"match","mismatch")
... A131: Indonesia | B131: I_PH_TOB_MEDIA | C131: Tobacco mass-media campaign | D131: public_health | E131: child | F131: I_PH_TOBACCO_POLICY | G131: htncov2_aspirational | H131: 2050 | I131: =100*(1-(SUMIFS('CVD_40q30_Age'!$M$2:$M$10401,'CVD_40q30_Age'!$A$2:$A$10401,A131,'CVD_40q30_Age'!$B$2:$B$10401,B131,'CVD_40q30_Age'!$E$2:$E$10401,G131,'CVD_40q30_Age'!$F$2:$F$10401,H131,'CVD_40q30_Age'!$G$2:$G$10401,69))/(SUMIFS('CVD_40q30_Age'!$L$2:$L$10401,'CVD_40q30_Age'!$A$2:$A$10401,A131,'CVD_40q30_Age'!$B$2:$B$10401,B131,'CVD_40q30_Age'!$E$2:$E$10401,G131,'CVD_40q30_Age'!$F$2:$F$10401,H131,'CVD_40q30_Age'!$G$2:$G$10401,30))) | J131: =SUMIFS($I$2:$I$261,$A$2:$A$261,A131,$G$2:$G$261,G131,$H$2:$H$261,H131,$B$2:$B$261,"baseline") | K131: =J131-I131 | L131: =IF(J131=0,"",100*(J131-I131)/J131) | M131: 11.514637 | N131: =IF(ABS(I131-M131)<=0.001,"match","mismatch")
A132: Indonesia | B132: S_70_30_30_TO_70_70_70 | C132: 70-30-30 -> 70-70-70 hypertension/cholesterol + diabetes cascade | D132: cascade_70_30_30_to_70_70_70 | E132: combined | G132: htncov2_aspirational | H132: 2025 | I132: =100*(1-(SUMIFS('CVD_40q30_Age'!$M$2:$M$10401,'CVD_40q30_Age'!$A$2:$A$10401,A132,'CVD_40q30_Age'!$B$2:$B$10401,B132,'CVD_40q30_Age'!$E$2:$E$10401,G132,'CVD_40q30_Age'!$F$2:$F$10401,H132,'CVD_40q30_Age'!$G$2:$G$10401,69))/(SUMIFS('CVD_40q30_Age'!$L$2:$L$10401,'CVD_40q30_Age'!$A$2:$A$10401,A132,'CVD_40q30_Age'!$B$2:$B$10401,B132,'CVD_40q30_Age'!$E$2:$E$10401,G132,'CVD_40q30_Age'!$F$2:$F$10401,H132,'CVD_40q30_Age'!$G$2:$G$10401,30))) | J132: =SUMIFS($I$2:$I$261,$A$2:$A$261,A132,$G$2:$G$261,G132,$H$2:$H$261,H132,$B$2:$B$261,"baseline") | K132: =J132-I132 | L132: =IF(J132=0,"",100*(J132-I132)/J132) | M132: 14.594863 | N132: =IF(ABS(I132-M132)<=0.001,"match","mismatch")
A133: Indonesia | B133: S_70_30_30_TO_70_70_70 | C133: 70-30-30 -> 70-70-70 hypertension/cholesterol + diabetes cascade | D133: cascade_70_30_30_to_70_70_70 | E133: combined | G133: htncov2_aspirational | H133: 2026 | I133: =100*(1-(SUMIFS('CVD_40q30_Age'!$M$2:$M$10401,'CVD_40q30_Age'!$A$2:$A$10401,A133,'CVD_40q30_Age'!$B$2:$B$10401,B133,'CVD_40q30_Age'!$E$2:$E$10401,G133,'CVD_40q30_Age'!$F$2:$F$10401,H133,'CVD_40q30_Age'!$G$2:$G$10401,69))/(SUMIFS('CVD_40q30_Age'!$L$2:$L$10401,'CVD_40q30_Age'!$A$2:$A$10401,A133,'CVD_40q30_Age'!$B$2:$B$10401,B133,'CVD_40q30_Age'!$E$2:$E$10401,G133,'CVD_40q30_Age'!$F$2:$F$10401,H133,'CVD_40q30_Age'!$G$2:$G$10401,30))) | J133: =SUMIFS($I$2:$I$261,$A$2:$A$261,A133,$G$2:$G$261,G133,$H$2:$H$261,H133,$B$2:$B$261,"baseline") | K133: =J133-I133 | L133: =IF(J133=0,"",100*(J133-I133)/J133) | M133: 14.517405 | N133: =IF(ABS(I133-M133)<=0.001,"match","mismatch")
A134: Indonesia | B134: S_70_30_30_TO_70_70_70 | C134: 70-30-30 -> 70-70-70 hypertension/cholesterol + diabetes cascade | D134: cascade_70_30_30_to_70_70_70 | E134: combined | G134: htncov2_aspirational | H134: 2027 | I134: =100*(1-(SUMIFS('CVD_40q30_Age'!$M$2:$M$10401,'CVD_40q30_Age'!$A$2:$A$10401,A134,'CVD_40q30_Age'!$B$2:$B$10401,B134,'CVD_40q30_Age'!$E$2:$E$10401,G134,'CVD_40q30_Age'!$F$2:$F$10401,H134,'CVD_40q30_Age'!$G$2:$G$10401,69))/(SUMIFS('CVD_40q30_Age'!$L$2:$L$10401,'CVD_40q30_Age'!$A$2:$A$10401,A134,'CVD_40q30_Age'!$B$2:$B$10401,B134,'CVD_40q30_Age'!$E$2:$E$10401,G134,'CVD_40q30_Age'!$F$2:$F$10401,H134,'CVD_40q30_Age'!$G$2:$G$10401,30))) | J134: =SUMIFS($I$2:$I$261,$A$2:$A$261,A134,$G$2:$G$261,G134,$H$2:$H$261,H134,$B$2:$B$261,"baseline") | K134: =J134-I134 | L134: =IF(J134=0,"",100*(J134-I134)/J134) | M134: 14.430362 | N134: =IF(ABS(I134-M134)<=0.001,"match","mismatch")
A135: Indonesia | B135: S_70_30_30_TO_70_70_70 | C135: 70-30-30 -> 70-70-70 hypertension/cholesterol + diabetes cascade | D135: cascade_70_30_30_to_70_70_70 | E135: combined | G135: htncov2_aspirational | H135: 2028 | I135: =100*(1-(SUMIFS('CVD_40q30_Age'!$M$2:$M$10401,'CVD_40q30_Age'!$A$2:$A$10401,A135,'CVD_40q30_Age'!$B$2:$B$10401,B135,'CVD_40q30_Age'!$E$2:$E$10401,G135,'CVD_40q30_Age'!$F$2:$F$10401,H135,'CVD_40q30_Age'!$G$2:$G$10401,69))/(SUMIFS('CVD_40q30_Age'!$L$2:$L$10401,'CVD_40q30_Age'!$A$2:$A$10401,A135,'CVD_40q30_Age'!$B$2:$B$10401,B135,'CVD_40q30_Age'!$E$2:$E$10401,G135,'CVD_40q30_Age'!$F$2:$F$10401,H135,'CVD_40q30_Age'!$G$2:$G$10401,30))) | J135: =SUMIFS($I$2:$I$261,$A$2:$A$261,A135,$G$2:$G$261,G135,$H$2:$H$261,H135,$B$2:$B$261,"baseline") | K135: =J135-I135 | L135: =IF(J135=0,"",100*(J135-I135)/J135) | M135: 14.343499 | N135: =IF(ABS(I135-M135)<=0.001,"match","mismatch")
A136: Indonesia | B136: S_70_30_30_TO_70_70_70 | C136: 70-30-30 -> 70-70-70 hypertension/cholesterol + diabetes cascade | D136: cascade_70_30_30_to_70_70_70 | E136: combined | G136: htncov2_aspirational | H136: 2029 | I136: =100*(1-(SUMIFS('CVD_40q30_Age'!$M$2:$M$10401,'CVD_40q30_Age'!$A$2:$A$10401,A136,'CVD_40q30_Age'!$B$2:$B$10401,B136,'CVD_40q30_Age'!$E$2:$E$10401,G136,'CVD_40q30_Age'!$F$2:$F$10401,H136,'CVD_40q30_Age'!$G$2:$G$10401,69))/(SUMIFS('CVD_40q30_Age'!$L$2:$L$10401,'CVD_40q30_Age'!$A$2:$A$10401,A136,'CVD_40q30_Age'!$B$2:$B$10401,B136,'CVD_40q30_Age'!$E$2:$E$10401,G136,'CVD_40q30_Age'!$F$2:$F$10401,H136,'CVD_40q30_Age'!$G$2:$G$10401,30))) | J136: =SUMIFS($I$2:$I$261,$A$2:$A$261,A136,$G$2:$G$261,G136,$H$2:$H$261,H136,$B$2:$B$261,"baseline") | K136: =J136-I136 | L136: =IF(J136=0,"",100*(J136-I136)/J136) | M136: 14.26539 | N136: =IF(ABS(I136-M136)<=0.001,"match","mismatch")
A137: Indonesia | B137: S_70_30_30_TO_70_70_70 | C137: 70-30-30 -> 70-70-70 hypertension/cholesterol + diabetes cascade | D137: cascade_70_30_30_to_70_70_70 | E137: combined | G137: htncov2_aspirational | H137: 2030 | I137: =100*(1-(SUMIFS('CVD_40q30_Age'!$M$2:$M$10401,'CVD_40q30_Age'!$A$2:$A$10401,A137,'CVD_40q30_Age'!$B$2:$B$10401,B137,'CVD_40q30_Age'!$E$2:$E$10401,G137,'CVD_40q30_Age'!$F$2:$F$10401,H137,'CVD_40q30_Age'!$G$2:$G$10401,69))/(SUMIFS('CVD_40q30_Age'!$L$2:$L$10401,'CVD_40q30_Age'!$A$2:$A$10401,A137,'CVD_40q30_Age'!$B$2:$B$10401,B137,'CVD_40q30_Age'!$E$2:$E$10401,G137,'CVD_40q30_Age'!$F$2:$F$10401,H137,'CVD_40q30_Age'!$G$2:$G$10401,30))) | J137: =SUMIFS($I$2:$I$261,$A$2:$A$261,A137,$G$2:$G$261,G137,$H$2:$H$261,H137,$B$2:$B$261,"baseline") | K137: =J137-I137 | L137: =IF(J137=0,"",100*(J137-I137)/J137) | M137: 14.179191 | N137: =IF(ABS(I137-M137)<=0.001,"match","mismatch")
A138: Indonesia | B138: S_70_30_30_TO_70_70_70 | C138: 70-30-30 -> 70-70-70 hypertension/cholesterol + diabetes cascade | D138: cascade_70_30_30_to_70_70_70 | E138: combined | G138: htncov2_aspirational | H138: 2031 | I138: =100*(1-(SUMIFS('CVD_40q30_Age'!$M$2:$M$10401,'CVD_40q30_Age'!$A$2:$A$10401,A138,'CVD_40q30_Age'!$B$2:$B$10401,B138,'CVD_40q30_Age'!$E$2:$E$10401,G138,'CVD_40q30_Age'!$F$2:$F$10401,H138,'CVD_40q30_Age'!$G$2:$G$10401,69))/(SUMIFS('CVD_40q30_Age'!$L$2:$L$10401,'CVD_40q30_Age'!$A$2:$A$10401,A138,'CVD_40q30_Age'!$B$2:$B$10401,B138,'CVD_40q30_Age'!$E$2:$E$10401,G138,'CVD_40q30_Age'!$F$2:$F$10401,H138,'CVD_40q30_Age'!$G$2:$G$10401,30))) | J138: =SUMIFS($I$2:$I$261,$A$2:$A$261,A138,$G$2:$G$261,G138,$H$2:$H$261,H138,$B$2:$B$261,"baseline") | K138: =J138-I138 | L138: =IF(J138=0,"",100*(J138-I138)/J138) | M138: 14.068906 | N138: =IF(ABS(I138-M138)<=0.001,"match","mismatch")
A139: Indonesia | B139: S_70_30_30_TO_70_70_70 | C139: 70-30-30 -> 70-70-70 hypertension/cholesterol + diabetes cascade | D139: cascade_70_30_30_to_70_70_70 | E139: combined | G139: htncov2_aspirational | H139: 2032 | I139: =100*(1-(SUMIFS('CVD_40q30_Age'!$M$2:$M$10401,'CVD_40q30_Age'!$A$2:$A$10401,A139,'CVD_40q30_Age'!$B$2:$B$10401,B139,'CVD_40q30_Age'!$E$2:$E$10401,G139,'CVD_40q30_Age'!$F$2:$F$10401,H139,'CVD_40q30_Age'!$G$2:$G$10401,69))/(SUMIFS('CVD_40q30_Age'!$L$2:$L$10401,'CVD_40q30_Age'!$A$2:$A$10401,A139,'CVD_40q30_Age'!$B$2:$B$10401,B139,'CVD_40q30_Age'!$E$2:$E$10401,G139,'CVD_40q30_Age'!$F$2:$F$10401,H139,'CVD_40q30_Age'!$G$2:$G$10401,30))) | J139: =SUMIFS($I$2:$I$261,$A$2:$A$261,A139,$G$2:$G$261,G139,$H$2:$H$261,H139,$B$2:$B$261,"baseline") | K139: =J139-I139 | L139: =IF(J139=0,"",100*(J139-I139)/J139) | M139: 13.92344 | N139: =IF(ABS(I139-M139)<=0.001,"match","mismatch")
A140: Indonesia | B140: S_70_30_30_TO_70_70_70 | C140: 70-30-30 -> 70-70-70 hypertension/cholesterol + diabetes cascade | D140: cascade_70_30_30_to_70_70_70 | E140: combined | G140: htncov2_aspirational | H140: 2033 | I140: =100*(1-(SUMIFS('CVD_40q30_Age'!$M$2:$M$10401,'CVD_40q30_Age'!$A$2:$A$10401,A140,'CVD_40q30_Age'!$B$2:$B$10401,B140,'CVD_40q30_Age'!$E$2:$E$10401,G140,'CVD_40q30_Age'!$F$2:$F$10401,H140,'CVD_40q30_Age'!$G$2:$G$10401,69))/(SUMIFS('CVD_40q30_Age'!$L$2:$L$10401,'CVD_40q30_Age'!$A$2:$A$10401,A140,'CVD_40q30_Age'!$B$2:$B$10401,B140,'CVD_40q30_Age'!$E$2:$E$10401,G140,'CVD_40q30_Age'!$F$2:$F$10401,H140,'CVD_40q30_Age'!$G$2:$G$10401,30))) | J140: =SUMIFS($I$2:$I$261,$A$2:$A$261,A140,$G$2:$G$261,G140,$H$2:$H$261,H140,$B$2:$B$261,"baseline") | K140: =J140-I140 | L140: =IF(J140=0,"",100*(J140-I140)/J140) | M140: 13.747204 | N140: =IF(ABS(I140-M140)<=0.001,"match","mismatch")
A141: Indonesia | B141: S_70_30_30_TO_70_70_70 | C141: 70-30-30 -> 70-70-70 hypertension/cholesterol + diabetes cascade | D141: cascade_70_30_30_to_70_70_70 | E141: combined | G141: htncov2_aspirational | H141: 2034 | I141: =100*(1-(SUMIFS('CVD_40q30_Age'!$M$2:$M$10401,'CVD_40q30_Age'!$A$2:$A$10401,A141,'CVD_40q30_Age'!$B$2:$B$10401,B141,'CVD_40q30_Age'!$E$2:$E$10401,G141,'CVD_40q30_Age'!$F$2:$F$10401,H141,'CVD_40q30_Age'!$G$2:$G$10401,69))/(SUMIFS('CVD_40q30_Age'!$L$2:$L$10401,'CVD_40q30_Age'!$A$2:$A$10401,A141,'CVD_40q30_Age'!$B$2:$B$10401,B141,'CVD_40q30_Age'!$E$2:$E$10401,G141,'CVD_40q30_Age'!$F$2:$F$10401,H141,'CVD_40q30_Age'!$G$2:$G$10401,30))) | J141: =SUMIFS($I$2:$I$261,$A$2:$A$261,A141,$G$2:$G$261,G141,$H$2:$H$261,H141,$B$2:$B$261,"baseline") | K141: =J141-I141 | L141: =IF(J141=0,"",100*(J141-I141)/J141) | M141: 13.562151 | N141: =IF(ABS(I141-M141)<=0.001,"match","mismatch")
A142: Indonesia | B142: S_70_30_30_TO_70_70_70 | C142: 70-30-30 -> 70-70-70 hypertension/cholesterol + diabetes cascade | D142: cascade_70_30_30_to_70_70_70 | E142: combined | G142: htncov2_aspirational | H142: 2035 | I142: =100*(1-(SUMIFS('CVD_40q30_Age'!$M$2:$M$10401,'CVD_40q30_Age'!$A$2:$A$10401,A142,'CVD_40q30_Age'!$B$2:$B$10401,B142,'CVD_40q30_Age'!$E$2:$E$10401,G142,'CVD_40q30_Age'!$F$2:$F$10401,H142,'CVD_40q30_Age'!$G$2:$G$10401,69))/(SUMIFS('CVD_40q30_Age'!$L$2:$L$10401,'CVD_40q30_Age'!$A$2:$A$10401,A142,'CVD_40q30_Age'!$B$2:$B$10401,B142,'CVD_40q30_Age'!$E$2:$E$10401,G142,'CVD_40q30_Age'!$F$2:$F$10401,H142,'CVD_40q30_Age'!$G$2:$G$10401,30))) | J142: =SUMIFS($I$2:$I$261,$A$2:$A$261,A142,$G$2:$G$261,G142,$H$2:$H$261,H142,$B$2:$B$261,"baseline") | K142: =J142-I142 | L142: =IF(J142=0,"",100*(J142-I142)/J142) | M142: 13.357604 | N142: =IF(ABS(I142-M142)<=0.001,"match","mismatch")
A143: Indonesia | B143: S_70_30_30_TO_70_70_70 | C143: 70-30-30 -> 70-70-70 hypertension/cholesterol + diabetes cascade | D143: cascade_70_30_30_to_70_70_70 | E143: combined | G143: htncov2_aspirational | H143: 2036 | I143: =100*(1-(SUMIFS('CVD_40q30_Age'!$M$2:$M$10401,'CVD_40q30_Age'!$A$2:$A$10401,A143,'CVD_40q30_Age'!$B$2:$B$10401,B143,'CVD_40q30_Age'!$E$2:$E$10401,G143,'CVD_40q30_Age'!$F$2:$F$10401,H143,'CVD_40q30_Age'!$G$2:$G$10401,69))/(SUMIFS('CVD_40q30_Age'!$L$2:$L$10401,'CVD_40q30_Age'!$A$2:$A$10401,A143,'CVD_40q30_Age'!$B$2:$B$10401,B143,'CVD_40q30_Age'!$E$2:$E$10401,G143,'CVD_40q30_Age'!$F$2:$F$10401,H143,'CVD_40q30_Age'!$G$2:$G$10401,30))) | J143: =SUMIFS($I$2:$I$261,$A$2:$A$261,A143,$G$2:$G$261,G143,$H$2:$H$261,H143,$B$2:$B$261,"baseline") | K143: =J143-I143 | L143: =IF(J143=0,"",100*(J143-I143)/J143) | M143: 13.150929 | N143: =IF(ABS(I143-M143)<=0.001,"match","mismatch")
... A261: Indonesia | B261: baseline | C261: Baseline (no new intervention) | D261: baseline | E261: baseline | G261: htncov2_aspirational | H261: 2050 | I261: =100*(1-(SUMIFS('CVD_40q30_Age'!$M$2:$M$10401,'CVD_40q30_Age'!$A$2:$A$10401,A261,'CVD_40q30_Age'!$B$2:$B$10401,B261,'CVD_40q30_Age'!$E$2:$E$10401,G261,'CVD_40q30_Age'!$F$2:$F$10401,H261,'CVD_40q30_Age'!$G$2:$G$10401,69))/(SUMIFS('CVD_40q30_Age'!$L$2:$L$10401,'CVD_40q30_Age'!$A$2:$A$10401,A261,'CVD_40q30_Age'!$B$2:$B$10401,B261,'CVD_40q30_Age'!$E$2:$E$10401,G261,'CVD_40q30_Age'!$F$2:$F$10401,H261,'CVD_40q30_Age'!$G$2:$G$10401,30))) | J261: =SUMIFS($I$2:$I$261,$A$2:$A$261,A261,$G$2:$G$261,G261,$H$2:$H$261,H261,$B$2:$B$261,"baseline") | K261: =J261-I261 | L261: =IF(J261=0,"",100*(J261-I261)/J261) | M261: 11.686287 | N261: =IF(ABS(I261-M261)<=0.001,"match","mismatch")

Sheet CVD_40q30_Age
A1: location | B1: scenario | C1: scenario_label | D1: intervention_family | E1: htn_target_scenario | F1: year | G1: age | H1: cvd_deaths | I1: population | J1: m_x | K1: q_x | L1: l_x | M1: l_x_next
A2: Indonesia | B2: I_PH_TOBACCO_POLICY | C2: Tobacco policy package | D2: public_health | E2: htncov2_aspirational | F2: 2025 | G2: 30 | H2: 1282.1481 | I2: 4467259 | J2: =IF(I2>0,H2/I2,0) | K2: =1-EXP(-J2) | L2: =IF(G2=30,1,M1) | M2: =L2*(1-K2)
A3: Indonesia | B3: I_PH_TOBACCO_POLICY | C3: Tobacco policy package | D3: public_health | E3: htncov2_aspirational | F3: 2025 | G3: 31 | H3: 1315.2391 | I3: 4410712.4 | J3: =IF(I3>0,H3/I3,0) | K3: =1-EXP(-J3) | L3: =IF(G3=30,1,M2) | M3: =L3*(1-K3)
A4: Indonesia | B4: I_PH_TOBACCO_POLICY | C4: Tobacco policy package | D4: public_health | E4: htncov2_aspirational | F4: 2025 | G4: 32 | H4: 1358.3687 | I4: 4358505.8 | J4: =IF(I4>0,H4/I4,0) | K4: =1-EXP(-J4) | L4: =IF(G4=30,1,M3) | M4: =L4*(1-K4)
A5: Indonesia | B5: I_PH_TOBACCO_POLICY | C5: Tobacco policy package | D5: public_health | E5: htncov2_aspirational | F5: 2025 | G5: 33 | H5: 1441.8419 | I5: 4398745.9 | J5: =IF(I5>0,H5/I5,0) | K5: =1-EXP(-J5) | L5: =IF(G5=30,1,M4) | M5: =L5*(1-K5)
A6: Indonesia | B6: I_PH_TOBACCO_POLICY | C6: Tobacco policy package | D6: public_health | E6: htncov2_aspirational | F6: 2025 | G6: 34 | H6: 1533.7871 | I6: 4419468.6 | J6: =IF(I6>0,H6/I6,0) | K6: =1-EXP(-J6) | L6: =IF(G6=30,1,M5) | M6: =L6*(1-K6)
A7: Indonesia | B7: I_PH_TOBACCO_POLICY | C7: Tobacco policy package | D7: public_health | E7: htncov2_aspirational | F7: 2025 | G7: 35 | H7: 3016.1069 | I7: 6509663.4 | J7: =IF(I7>0,H7/I7,0) | K7: =1-EXP(-J7) | L7: =IF(G7=30,1,M6) | M7: =L7*(1-K7)
A8: Indonesia | B8: I_PH_TOBACCO_POLICY | C8: Tobacco policy package | D8: public_health | E8: htncov2_aspirational | F8: 2025 | G8: 36 | H8: 2254.7093 | I8: 4383096 | J8: =IF(I8>0,H8/I8,0) | K8: =1-EXP(-J8) | L8: =IF(G8=30,1,M7) | M8: =L8*(1-K8)
A9: Indonesia | B9: I_PH_TOBACCO_POLICY | C9: Tobacco policy package | D9: public_health | E9: htncov2_aspirational | F9: 2025 | G9: 37 | H9: 2406.7285 | I9: 4369642.3 | J9: =IF(I9>0,H9/I9,0) | K9: =1-EXP(-J9) | L9: =IF(G9=30,1,M8) | M9: =L9*(1-K9)
A10: Indonesia | B10: I_PH_TOBACCO_POLICY | C10: Tobacco policy package | D10: public_health | E10: htncov2_aspirational | F10: 2025 | G10: 38 | H10: 2504.2649 | I10: 4239505.9 | J10: =IF(I10>0,H10/I10,0) | K10: =1-EXP(-J10) | L10: =IF(G10=30,1,M9) | M10: =L10*(1-K10)
A11: Indonesia | B11: I_PH_TOBACCO_POLICY | C11: Tobacco policy package | D11: public_health | E11: htncov2_aspirational | F11: 2025 | G11: 39 | H11: 2668.8504 | I11: 4208510.7 | J11: =IF(I11>0,H11/I11,0) | K11: =1-EXP(-J11) | L11: =IF(G11=30,1,M10) | M11: =L11*(1-K11)
A12: Indonesia | B12: I_PH_TOBACCO_POLICY | C12: Tobacco policy package | D12: public_health | E12: htncov2_aspirational | F12: 2025 | G12: 40 | H12: 3657.3454 | I12: 4272859.9 | J12: =IF(I12>0,H12/I12,0) | K12: =1-EXP(-J12) | L12: =IF(G12=30,1,M11) | M12: =L12*(1-K12)
A13: Indonesia | B13: I_PH_TOBACCO_POLICY | C13: Tobacco policy package | D13: public_health | E13: htncov2_aspirational | F13: 2025 | G13: 41 | H13: 4027.1377 | I13: 4362484.7 | J13: =IF(I13>0,H13/I13,0) | K13: =1-EXP(-J13) | L13: =IF(G13=30,1,M12) | M13: =L13*(1-K13)
... A10401: Indonesia | B10401: baseline | C10401: Baseline (no new intervention) | D10401: baseline | E10401: htncov2_aspirational | F10401: 2050 | G10401: 69 | H10401: 35334.467 | I10401: 3180308.9 | J10401: =IF(I10401>0,H10401/I10401,0) | K10401: =1-EXP(-J10401) | L10401: =IF(G10401=30,1,M10400) | M10401: =L10401*(1-K10401)

Sheet Annual_Cost
A1: scenario | B1: family | C1: year | D1: intervention_id | E1: cost_record_id | F1: cost_key | G1: cost_component | H1: cause_code | I1: cost_scope | J1: pin_measure | K1: pin_fraction | L1: frequency_per_year | M1: unit_cost_usd | N1: q_scenario | O1: q_baseline | P1: covimpl_scenario | Q1: covimpl_baseline | R1: discount_factor | S1: pin_scenario | T1: pin_baseline | U1: annual_cost_baseline | V1: annual_cost_scenario | W1: annual_cost_incremental | X1: disc_cost_incremental | Y1: indonesia_adjusted_flag | Z1: price_year | AA1: review_status | AB1: shared_duplicate_count | AC1: national_population | AD1: annual_cost_baseline_per_capita | AE1: annual_cost_scenario_per_capita | AF1: annual_cost_incremental_per_capita | AG1: disc_cost_incremental_per_capita
A2: S_70_30_30_TO_70_70_70 | B2: cascade_70_30_30_to_70_70_70 | C2: 2025 | D2: I_CVD_PRIMARY | E2: COST_PRIMARY_SCREEN_A | F2: cascade_70_30_30_to_70_70_70|COST_PRIMARY_SCREEN_A | G2: CVD targeted screening | I2: shared-count-once | J2: all | K2: 0.2 | L2: 1 | M2: 1.291584 | N2: 1.5509319e+08 | O2: 1.5509319e+08 | P2: 0.14506229 | Q2: 0.14506229 | R2: =1/(1+'Calculation_Assumptions'!$B$5)^(C2-'Calculation_Assumptions'!$B$2) | S2: =N2*K2 | T2: =O2*K2 | U2: =T2*Q2*L2*M2 | V2: =S2*P2*L2*M2 | W2: =V2-U2 | X2: =W2*R2 | Y2: 1 | Z2: 2023 | AA2: Review | AB2: =IF(I2="shared-count-once",COUNTIFS($A$2:$A$807,A2,$C$2:$C$807,C2,$E$2:$E$807,E2,$B$2:$B$807,B2),1) | AC2: 2.8839191e+08 | AD2: =IF(AC2=0,"",U2/AC2) | AE2: =IF(AC2=0,"",V2/AC2) | AF2: =IF(AC2=0,"",W2/AC2) | AG2: =IF(AC2=0,"",X2/AC2)
A3: S_70_30_30_TO_70_70_70 | B3: cascade_70_30_30_to_70_70_70 | C3: 2026 | D3: I_CVD_PRIMARY | E3: COST_PRIMARY_SCREEN_A | F3: cascade_70_30_30_to_70_70_70|COST_PRIMARY_SCREEN_A | G3: CVD targeted screening | I3: shared-count-once | J3: all | K3: 0.2 | L3: 1 | M3: 1.291584 | N3: 1.5750383e+08 | O3: 1.5750383e+08 | P3: 0.14506229 | Q3: 0.14506229 | R3: =1/(1+'Calculation_Assumptions'!$B$5)^(C3-'Calculation_Assumptions'!$B$2) | S3: =N3*K3 | T3: =O3*K3 | U3: =T3*Q3*L3*M3 | V3: =S3*P3*L3*M3 | W3: =V3-U3 | X3: =W3*R3 | Y3: 1 | Z3: 2023 | AA3: Review | AB3: =IF(I3="shared-count-once",COUNTIFS($A$2:$A$807,A3,$C$2:$C$807,C3,$E$2:$E$807,E3,$B$2:$B$807,B3),1) | AC3: 2.9047213e+08 | AD3: =IF(AC3=0,"",U3/AC3) | AE3: =IF(AC3=0,"",V3/AC3) | AF3: =IF(AC3=0,"",W3/AC3) | AG3: =IF(AC3=0,"",X3/AC3)
A4: S_70_30_30_TO_70_70_70 | B4: cascade_70_30_30_to_70_70_70 | C4: 2027 | D4: I_CVD_PRIMARY | E4: COST_PRIMARY_SCREEN_A | F4: cascade_70_30_30_to_70_70_70|COST_PRIMARY_SCREEN_A | G4: CVD targeted screening | I4: shared-count-once | J4: all | K4: 0.2 | L4: 1 | M4: 1.291584 | N4: 1.5995805e+08 | O4: 1.5995711e+08 | P4: 0.14506229 | Q4: 0.14506229 | R4: =1/(1+'Calculation_Assumptions'!$B$5)^(C4-'Calculation_Assumptions'!$B$2) | S4: =N4*K4 | T4: =O4*K4 | U4: =T4*Q4*L4*M4 | V4: =S4*P4*L4*M4 | W4: =V4-U4 | X4: =W4*R4 | Y4: 1 | Z4: 2023 | AA4: Review | AB4: =IF(I4="shared-count-once",COUNTIFS($A$2:$A$807,A4,$C$2:$C$807,C4,$E$2:$E$807,E4,$B$2:$B$807,B4),1) | AC4: 2.9250508e+08 | AD4: =IF(AC4=0,"",U4/AC4) | AE4: =IF(AC4=0,"",V4/AC4) | AF4: =IF(AC4=0,"",W4/AC4) | AG4: =IF(AC4=0,"",X4/AC4)
A5: S_70_30_30_TO_70_70_70 | B5: cascade_70_30_30_to_70_70_70 | C5: 2028 | D5: I_CVD_PRIMARY | E5: COST_PRIMARY_SCREEN_A | F5: cascade_70_30_30_to_70_70_70|COST_PRIMARY_SCREEN_A | G5: CVD targeted screening | I5: shared-count-once | J5: all | K5: 0.2 | L5: 1 | M5: 1.291584 | N5: 1.6220713e+08 | O5: 1.6220434e+08 | P5: 0.14506229 | Q5: 0.14506229 | R5: =1/(1+'Calculation_Assumptions'!$B$5)^(C5-'Calculation_Assumptions'!$B$2) | S5: =N5*K5 | T5: =O5*K5 | U5: =T5*Q5*L5*M5 | V5: =S5*P5*L5*M5 | W5: =V5-U5 | X5: =W5*R5 | Y5: 1 | Z5: 2023 | AA5: Review | AB5: =IF(I5="shared-count-once",COUNTIFS($A$2:$A$807,A5,$C$2:$C$807,C5,$E$2:$E$807,E5,$B$2:$B$807,B5),1) | AC5: 2.9448471e+08 | AD5: =IF(AC5=0,"",U5/AC5) | AE5: =IF(AC5=0,"",V5/AC5) | AF5: =IF(AC5=0,"",W5/AC5) | AG5: =IF(AC5=0,"",X5/AC5)
A6: S_70_30_30_TO_70_70_70 | B6: cascade_70_30_30_to_70_70_70 | C6: 2029 | D6: I_CVD_PRIMARY | E6: COST_PRIMARY_SCREEN_A | F6: cascade_70_30_30_to_70_70_70|COST_PRIMARY_SCREEN_A | G6: CVD targeted screening | I6: shared-count-once | J6: all | K6: 0.2 | L6: 1 | M6: 1.291584 | N6: 1.6436006e+08 | O6: 1.6435451e+08 | P6: 0.14506229 | Q6: 0.14506229 | R6: =1/(1+'Calculation_Assumptions'!$B$5)^(C6-'Calculation_Assumptions'!$B$2) | S6: =N6*K6 | T6: =O6*K6 | U6: =T6*Q6*L6*M6 | V6: =S6*P6*L6*M6 | W6: =V6-U6 | X6: =W6*R6 | Y6: 1 | Z6: 2023 | AA6: Review | AB6: =IF(I6="shared-count-once",COUNTIFS($A$2:$A$807,A6,$C$2:$C$807,C6,$E$2:$E$807,E6,$B$2:$B$807,B6),1) | AC6: 2.9641403e+08 | AD6: =IF(AC6=0,"",U6/AC6) | AE6: =IF(AC6=0,"",V6/AC6) | AF6: =IF(AC6=0,"",W6/AC6) | AG6: =IF(AC6=0,"",X6/AC6)
A7: S_70_30_30_TO_70_70_70 | B7: cascade_70_30_30_to_70_70_70 | C7: 2030 | D7: I_CVD_PRIMARY | E7: COST_PRIMARY_SCREEN_A | F7: cascade_70_30_30_to_70_70_70|COST_PRIMARY_SCREEN_A | G7: CVD targeted screening | I7: shared-count-once | J7: all | K7: 0.2 | L7: 1 | M7: 1.291584 | N7: 1.664419e+08 | O7: 1.6641555e+08 | P7: 0.14506229 | Q7: 0.14506229 | R7: =1/(1+'Calculation_Assumptions'!$B$5)^(C7-'Calculation_Assumptions'!$B$2) | S7: =N7*K7 | T7: =O7*K7 | U7: =T7*Q7*L7*M7 | V7: =S7*P7*L7*M7 | W7: =V7-U7 | X7: =W7*R7 | Y7: 1 | Z7: 2023 | AA7: Review | AB7: =IF(I7="shared-count-once",COUNTIFS($A$2:$A$807,A7,$C$2:$C$807,C7,$E$2:$E$807,E7,$B$2:$B$807,B7),1) | AC7: 2.982894e+08 | AD7: =IF(AC7=0,"",U7/AC7) | AE7: =IF(AC7=0,"",V7/AC7) | AF7: =IF(AC7=0,"",W7/AC7) | AG7: =IF(AC7=0,"",X7/AC7)
A8: S_70_30_30_TO_70_70_70 | B8: cascade_70_30_30_to_70_70_70 | C8: 2031 | D8: I_CVD_PRIMARY | E8: COST_PRIMARY_SCREEN_A | F8: cascade_70_30_30_to_70_70_70|COST_PRIMARY_SCREEN_A | G8: CVD targeted screening | I8: shared-count-once | J8: all | K8: 0.2 | L8: 1 | M8: 1.291584 | N8: 1.6849138e+08 | O8: 1.6846129e+08 | P8: 0.17220606 | Q8: 0.14506229 | R8: =1/(1+'Calculation_Assumptions'!$B$5)^(C8-'Calculation_Assumptions'!$B$2) | S8: =N8*K8 | T8: =O8*K8 | U8: =T8*Q8*L8*M8 | V8: =S8*P8*L8*M8 | W8: =V8-U8 | X8: =W8*R8 | Y8: 1 | Z8: 2023 | AA8: Review | AB8: =IF(I8="shared-count-once",COUNTIFS($A$2:$A$807,A8,$C$2:$C$807,C8,$E$2:$E$807,E8,$B$2:$B$807,B8),1) | AC8: 3.0011964e+08 | AD8: =IF(AC8=0,"",U8/AC8) | AE8: =IF(AC8=0,"",V8/AC8) | AF8: =IF(AC8=0,"",W8/AC8) | AG8: =IF(AC8=0,"",X8/AC8)
A9: S_70_30_30_TO_70_70_70 | B9: cascade_70_30_30_to_70_70_70 | C9: 2032 | D9: I_CVD_PRIMARY | E9: COST_PRIMARY_SCREEN_A | F9: cascade_70_30_30_to_70_70_70|COST_PRIMARY_SCREEN_A | G9: CVD targeted screening | I9: shared-count-once | J9: all | K9: 0.2 | L9: 1 | M9: 1.291584 | N9: 1.7051198e+08 | O9: 1.7047662e+08 | P9: 0.19934983 | Q9: 0.14506229 | R9: =1/(1+'Calculation_Assumptions'!$B$5)^(C9-'Calculation_Assumptions'!$B$2) | S9: =N9*K9 | T9: =O9*K9 | U9: =T9*Q9*L9*M9 | V9: =S9*P9*L9*M9 | W9: =V9-U9 | X9: =W9*R9 | Y9: 1 | Z9: 2023 | AA9: Review | AB9: =IF(I9="shared-count-once",COUNTIFS($A$2:$A$807,A9,$C$2:$C$807,C9,$E$2:$E$807,E9,$B$2:$B$807,B9),1) | AC9: 3.0190463e+08 | AD9: =IF(AC9=0,"",U9/AC9) | AE9: =IF(AC9=0,"",V9/AC9) | AF9: =IF(AC9=0,"",W9/AC9) | AG9: =IF(AC9=0,"",X9/AC9)
A10: S_70_30_30_TO_70_70_70 | B10: cascade_70_30_30_to_70_70_70 | C10: 2033 | D10: I_CVD_PRIMARY | E10: COST_PRIMARY_SCREEN_A | F10: cascade_70_30_30_to_70_70_70|COST_PRIMARY_SCREEN_A | G10: CVD targeted screening | I10: shared-count-once | J10: all | K10: 0.2 | L10: 1 | M10: 1.291584 | N10: 1.725064e+08 | O10: 1.7246151e+08 | P10: 0.2264936 | Q10: 0.14506229 | R10: =1/(1+'Calculation_Assumptions'!$B$5)^(C10-'Calculation_Assumptions'!$B$2) | S10: =N10*K10 | T10: =O10*K10 | U10: =T10*Q10*L10*M10 | V10: =S10*P10*L10*M10 | W10: =V10-U10 | X10: =W10*R10 | Y10: 1 | Z10: 2023 | AA10: Review | AB10: =IF(I10="shared-count-once",COUNTIFS($A$2:$A$807,A10,$C$2:$C$807,C10,$E$2:$E$807,E10,$B$2:$B$807,B10),1) | AC10: 3.0364428e+08 | AD10: =IF(AC10=0,"",U10/AC10) | AE10: =IF(AC10=0,"",V10/AC10) | AF10: =IF(AC10=0,"",W10/AC10) | AG10: =IF(AC10=0,"",X10/AC10)
A11: S_70_30_30_TO_70_70_70 | B11: cascade_70_30_30_to_70_70_70 | C11: 2034 | D11: I_CVD_PRIMARY | E11: COST_PRIMARY_SCREEN_A | F11: cascade_70_30_30_to_70_70_70|COST_PRIMARY_SCREEN_A | G11: CVD targeted screening | I11: shared-count-once | J11: all | K11: 0.2 | L11: 1 | M11: 1.291584 | N11: 1.7450473e+08 | O11: 1.7446169e+08 | P11: 0.25363737 | Q11: 0.14506229 | R11: =1/(1+'Calculation_Assumptions'!$B$5)^(C11-'Calculation_Assumptions'!$B$2) | S11: =N11*K11 | T11: =O11*K11 | U11: =T11*Q11*L11*M11 | V11: =S11*P11*L11*M11 | W11: =V11-U11 | X11: =W11*R11 | Y11: 1 | Z11: 2023 | AA11: Review | AB11: =IF(I11="shared-count-once",COUNTIFS($A$2:$A$807,A11,$C$2:$C$807,C11,$E$2:$E$807,E11,$B$2:$B$807,B11),1) | AC11: 3.0533254e+08 | AD11: =IF(AC11=0,"",U11/AC11) | AE11: =IF(AC11=0,"",V11/AC11) | AF11: =IF(AC11=0,"",W11/AC11) | AG11: =IF(AC11=0,"",X11/AC11)
A12: S_70_30_30_TO_70_70_70 | B12: cascade_70_30_30_to_70_70_70 | C12: 2035 | D12: I_CVD_PRIMARY | E12: COST_PRIMARY_SCREEN_A | F12: cascade_70_30_30_to_70_70_70|COST_PRIMARY_SCREEN_A | G12: CVD targeted screening | I12: shared-count-once | J12: all | K12: 0.2 | L12: 1 | M12: 1.291584 | N12: 1.7660191e+08 | O12: 1.7653877e+08 | P12: 0.28078114 | Q12: 0.14506229 | R12: =1/(1+'Calculation_Assumptions'!$B$5)^(C12-'Calculation_Assumptions'!$B$2) | S12: =N12*K12 | T12: =O12*K12 | U12: =T12*Q12*L12*M12 | V12: =S12*P12*L12*M12 | W12: =V12-U12 | X12: =W12*R12 | Y12: 1 | Z12: 2023 | AA12: Review | AB12: =IF(I12="shared-count-once",COUNTIFS($A$2:$A$807,A12,$C$2:$C$807,C12,$E$2:$E$807,E12,$B$2:$B$807,B12),1) | AC12: 3.0696465e+08 | AD12: =IF(AC12=0,"",U12/AC12) | AE12: =IF(AC12=0,"",V12/AC12) | AF12: =IF(AC12=0,"",W12/AC12) | AG12: =IF(AC12=0,"",X12/AC12)
A13: S_70_30_30_TO_70_70_70 | B13: cascade_70_30_30_to_70_70_70 | C13: 2036 | D13: I_CVD_PRIMARY | E13: COST_PRIMARY_SCREEN_A | F13: cascade_70_30_30_to_70_70_70|COST_PRIMARY_SCREEN_A | G13: CVD targeted screening | I13: shared-count-once | J13: all | K13: 0.2 | L13: 1 | M13: 1.291584 | N13: 1.7871375e+08 | O13: 1.7862366e+08 | P13: 0.30792491 | Q13: 0.14506229 | R13: =1/(1+'Calculation_Assumptions'!$B$5)^(C13-'Calculation_Assumptions'!$B$2) | S13: =N13*K13 | T13: =O13*K13 | U13: =T13*Q13*L13*M13 | V13: =S13*P13*L13*M13 | W13: =V13-U13 | X13: =W13*R13 | Y13: 1 | Z13: 2023 | AA13: Review | AB13: =IF(I13="shared-count-once",COUNTIFS($A$2:$A$807,A13,$C$2:$C$807,C13,$E$2:$E$807,E13,$B$2:$B$807,B13),1) | AC13: 3.0854277e+08 | AD13: =IF(AC13=0,"",U13/AC13) | AE13: =IF(AC13=0,"",V13/AC13) | AF13: =IF(AC13=0,"",W13/AC13) | AG13: =IF(AC13=0,"",X13/AC13)
... A53: S_70_30_30_TO_70_70_70 | B53: cascade_70_30_30_to_70_70_70 | C53: 2050 | D53: I_CVD_PRIMARY | E53: COST_PRIMARY_TX_A | F53: cascade_70_30_30_to_70_70_70|COST_PRIMARY_TX_A | G53: Antihypertensives and statins for absolute CVD risk >20% | I53: shared-count-once | J53: all | K53: 0.06 | L53: 1 | M53: 69.3 | N53: 2.0363039e+08 | O53: 2.024798e+08 | P53: 0.4165 | Q53: 0.14506229 | R53: =1/(1+'Calculation_Assumptions'!$B$5)^(C53-'Calculation_Assumptions'!$B$2) | S53: =N53*K53 | T53: =O53*K53 | U53: =T53*Q53*L53*M53 | V53: =S53*P53*L53*M53 | W53: =V53-U53 | X53: =W53*R53 | Y53: 1 | Z53: 2023 | AA53: Review | AB53: =IF(I53="shared-count-once",COUNTIFS($A$2:$A$807,A53,$C$2:$C$807,C53,$E$2:$E$807,E53,$B$2:$B$807,B53),1) | AC53: 3.2331204e+08 | AD53: =IF(AC53=0,"",U53/AC53) | AE53: =IF(AC53=0,"",V53/AC53) | AF53: =IF(AC53=0,"",W53/AC53) | AG53: =IF(AC53=0,"",X53/AC53)
A54: S_70_30_30_TO_70_70_70 | B54: cascade_70_30_30_to_70_70_70 | C54: 2025 | D54: I_T2D_TREATMENT | E54: COST_T2D_SCREEN | F54: cascade_70_30_30_to_70_70_70|COST_T2D_SCREEN | G54: Diabetes opportunistic screening | H54: dm2 | I54: cause-specific | J54: all | K54: 1e-05 | L54: 1 | M54: 0.70495848 | N54: 1.5509319e+08 | O54: 1.5509319e+08 | P54: 0.033768828 | Q54: 0.033768828 | R54: =1/(1+'Calculation_Assumptions'!$B$5)^(C54-'Calculation_Assumptions'!$B$2) | S54: =N54*K54 | T54: =O54*K54 | U54: =T54*Q54*L54*M54 | V54: =S54*P54*L54*M54 | W54: =V54-U54 | X54: =W54*R54 | Y54: 1 | Z54: 2023 | AA54: Ready | AB54: =IF(I54="shared-count-once",COUNTIFS($A$2:$A$807,A54,$C$2:$C$807,C54,$E$2:$E$807,E54,$B$2:$B$807,B54),1) | AC54: 2.8839191e+08 | AD54: =IF(AC54=0,"",U54/AC54) | AE54: =IF(AC54=0,"",V54/AC54) | AF54: =IF(AC54=0,"",W54/AC54) | AG54: =IF(AC54=0,"",X54/AC54)
A55: S_70_30_30_TO_70_70_70 | B55: cascade_70_30_30_to_70_70_70 | C55: 2026 | D55: I_T2D_TREATMENT | E55: COST_T2D_SCREEN | F55: cascade_70_30_30_to_70_70_70|COST_T2D_SCREEN | G55: Diabetes opportunistic screening | H55: dm2 | I55: cause-specific | J55: all | K55: 1e-05 | L55: 1 | M55: 0.70495848 | N55: 1.5750383e+08 | O55: 1.5750383e+08 | P55: 0.054315063 | Q55: 0.033768828 | R55: =1/(1+'Calculation_Assumptions'!$B$5)^(C55-'Calculation_Assumptions'!$B$2) | S55: =N55*K55 | T55: =O55*K55 | U55: =T55*Q55*L55*M55 | V55: =S55*P55*L55*M55 | W55: =V55-U55 | X55: =W55*R55 | Y55: 1 | Z55: 2023 | AA55: Ready | AB55: =IF(I55="shared-count-once",COUNTIFS($A$2:$A$807,A55,$C$2:$C$807,C55,$E$2:$E$807,E55,$B$2:$B$807,B55),1) | AC55: 2.9047213e+08 | AD55: =IF(AC55=0,"",U55/AC55) | AE55: =IF(AC55=0,"",V55/AC55) | AF55: =IF(AC55=0,"",W55/AC55) | AG55: =IF(AC55=0,"",X55/AC55)
A56: S_70_30_30_TO_70_70_70 | B56: cascade_70_30_30_to_70_70_70 | C56: 2027 | D56: I_T2D_TREATMENT | E56: COST_T2D_SCREEN | F56: cascade_70_30_30_to_70_70_70|COST_T2D_SCREEN | G56: Diabetes opportunistic screening | H56: dm2 | I56: cause-specific | J56: all | K56: 1e-05 | L56: 1 | M56: 0.70495848 | N56: 1.5995805e+08 | O56: 1.5995711e+08 | P56: 0.074861297 | Q56: 0.033768828 | R56: =1/(1+'Calculation_Assumptions'!$B$5)^(C56-'Calculation_Assumptions'!$B$2) | S56: =N56*K56 | T56: =O56*K56 | U56: =T56*Q56*L56*M56 | V56: =S56*P56*L56*M56 | W56: =V56-U56 | X56: =W56*R56 | Y56: 1 | Z56: 2023 | AA56: Ready | AB56: =IF(I56="shared-count-once",COUNTIFS($A$2:$A$807,A56,$C$2:$C$807,C56,$E$2:$E$807,E56,$B$2:$B$807,B56),1) | AC56: 2.9250508e+08 | AD56: =IF(AC56=0,"",U56/AC56) | AE56: =IF(AC56=0,"",V56/AC56) | AF56: =IF(AC56=0,"",W56/AC56) | AG56: =IF(AC56=0,"",X56/AC56)
A57: S_70_30_30_TO_70_70_70 | B57: cascade_70_30_30_to_70_70_70 | C57: 2028 | D57: I_T2D_TREATMENT | E57: COST_T2D_SCREEN | F57: cascade_70_30_30_to_70_70_70|COST_T2D_SCREEN | G57: Diabetes opportunistic screening | H57: dm2 | I57: cause-specific | J57: all | K57: 1e-05 | L57: 1 | M57: 0.70495848 | N57: 1.6220713e+08 | O57: 1.6220434e+08 | P57: 0.095407531 | Q57: 0.033768828 | R57: =1/(1+'Calculation_Assumptions'!$B$5)^(C57-'Calculation_Assumptions'!$B$2) | S57: =N57*K57 | T57: =O57*K57 | U57: =T57*Q57*L57*M57 | V57: =S57*P57*L57*M57 | W57: =V57-U57 | X57: =W57*R57 | Y57: 1 | Z57: 2023 | AA57: Ready | AB57: =IF(I57="shared-count-once",COUNTIFS($A$2:$A$807,A57,$C$2:$C$807,C57,$E$2:$E$807,E57,$B$2:$B$807,B57),1) | AC57: 2.9448471e+08 | AD57: =IF(AC57=0,"",U57/AC57) | AE57: =IF(AC57=0,"",V57/AC57) | AF57: =IF(AC57=0,"",W57/AC57) | AG57: =IF(AC57=0,"",X57/AC57)
A58: S_70_30_30_TO_70_70_70 | B58: cascade_70_30_30_to_70_70_70 | C58: 2029 | D58: I_T2D_TREATMENT | E58: COST_T2D_SCREEN | F58: cascade_70_30_30_to_70_70_70|COST_T2D_SCREEN | G58: Diabetes opportunistic screening | H58: dm2 | I58: cause-specific | J58: all | K58: 1e-05 | L58: 1 | M58: 0.70495848 | N58: 1.6436006e+08 | O58: 1.6435451e+08 | P58: 0.11595377 | Q58: 0.033768828 | R58: =1/(1+'Calculation_Assumptions'!$B$5)^(C58-'Calculation_Assumptions'!$B$2) | S58: =N58*K58 | T58: =O58*K58 | U58: =T58*Q58*L58*M58 | V58: =S58*P58*L58*M58 | W58: =V58-U58 | X58: =W58*R58 | Y58: 1 | Z58: 2023 | AA58: Ready | AB58: =IF(I58="shared-count-once",COUNTIFS($A$2:$A$807,A58,$C$2:$C$807,C58,$E$2:$E$807,E58,$B$2:$B$807,B58),1) | AC58: 2.9641403e+08 | AD58: =IF(AC58=0,"",U58/AC58) | AE58: =IF(AC58=0,"",V58/AC58) | AF58: =IF(AC58=0,"",W58/AC58) | AG58: =IF(AC58=0,"",X58/AC58)
A59: S_70_30_30_TO_70_70_70 | B59: cascade_70_30_30_to_70_70_70 | C59: 2030 | D59: I_T2D_TREATMENT | E59: COST_T2D_SCREEN | F59: cascade_70_30_30_to_70_70_70|COST_T2D_SCREEN | G59: Diabetes opportunistic screening | H59: dm2 | I59: cause-specific | J59: all | K59: 1e-05 | L59: 1 | M59: 0.70495848 | N59: 1.664419e+08 | O59: 1.6641555e+08 | P59: 0.1365 | Q59: 0.033768828 | R59: =1/(1+'Calculation_Assumptions'!$B$5)^(C59-'Calculation_Assumptions'!$B$2) | S59: =N59*K59 | T59: =O59*K59 | U59: =T59*Q59*L59*M59 | V59: =S59*P59*L59*M59 | W59: =V59-U59 | X59: =W59*R59 | Y59: 1 | Z59: 2023 | AA59: Ready | AB59: =IF(I59="shared-count-once",COUNTIFS($A$2:$A$807,A59,$C$2:$C$807,C59,$E$2:$E$807,E59,$B$2:$B$807,B59),1) | AC59: 2.982894e+08 | AD59: =IF(AC59=0,"",U59/AC59) | AE59: =IF(AC59=0,"",V59/AC59) | AF59: =IF(AC59=0,"",W59/AC59) | AG59: =IF(AC59=0,"",X59/AC59)
A60: S_70_30_30_TO_70_70_70 | B60: cascade_70_30_30_to_70_70_70 | C60: 2031 | D60: I_T2D_TREATMENT | E60: COST_T2D_SCREEN | F60: cascade_70_30_30_to_70_70_70|COST_T2D_SCREEN | G60: Diabetes opportunistic screening | H60: dm2 | I60: cause-specific | J60: all | K60: 1e-05 | L60: 1 | M60: 0.70495848 | N60: 1.6849138e+08 | O60: 1.6846129e+08 | P60: 0.1645 | Q60: 0.033768828 | R60: =1/(1+'Calculation_Assumptions'!$B$5)^(C60-'Calculation_Assumptions'!$B$2) | S60: =N60*K60 | T60: =O60*K60 | U60: =T60*Q60*L60*M60 | V60: =S60*P60*L60*M60 | W60: =V60-U60 | X60: =W60*R60 | Y60: 1 | Z60: 2023 | AA60: Ready | AB60: =IF(I60="shared-count-once",COUNTIFS($A$2:$A$807,A60,$C$2:$C$807,C60,$E$2:$E$807,E60,$B$2:$B$807,B60),1) | AC60: 3.0011964e+08 | AD60: =IF(AC60=0,"",U60/AC60) | AE60: =IF(AC60=0,"",V60/AC60) | AF60: =IF(AC60=0,"",W60/AC60) | AG60: =IF(AC60=0,"",X60/AC60)
A61: S_70_30_30_TO_70_70_70 | B61: cascade_70_30_30_to_70_70_70 | C61: 2032 | D61: I_T2D_TREATMENT | E61: COST_T2D_SCREEN | F61: cascade_70_30_30_to_70_70_70|COST_T2D_SCREEN | G61: Diabetes opportunistic screening | H61: dm2 | I61: cause-specific | J61: all | K61: 1e-05 | L61: 1 | M61: 0.70495848 | N61: 1.7051198e+08 | O61: 1.7047662e+08 | P61: 0.1925 | Q61: 0.033768828 | R61: =1/(1+'Calculation_Assumptions'!$B$5)^(C61-'Calculation_Assumptions'!$B$2) | S61: =N61*K61 | T61: =O61*K61 | U61: =T61*Q61*L61*M61 | V61: =S61*P61*L61*M61 | W61: =V61-U61 | X61: =W61*R61 | Y61: 1 | Z61: 2023 | AA61: Ready | AB61: =IF(I61="shared-count-once",COUNTIFS($A$2:$A$807,A61,$C$2:$C$807,C61,$E$2:$E$807,E61,$B$2:$B$807,B61),1) | AC61: 3.0190463e+08 | AD61: =IF(AC61=0,"",U61/AC61) | AE61: =IF(AC61=0,"",V61/AC61) | AF61: =IF(AC61=0,"",W61/AC61) | AG61: =IF(AC61=0,"",X61/AC61)
A62: S_70_30_30_TO_70_70_70 | B62: cascade_70_30_30_to_70_70_70 | C62: 2033 | D62: I_T2D_TREATMENT | E62: COST_T2D_SCREEN | F62: cascade_70_30_30_to_70_70_70|COST_T2D_SCREEN | G62: Diabetes opportunistic screening | H62: dm2 | I62: cause-specific | J62: all | K62: 1e-05 | L62: 1 | M62: 0.70495848 | N62: 1.725064e+08 | O62: 1.7246151e+08 | P62: 0.2205 | Q62: 0.033768828 | R62: =1/(1+'Calculation_Assumptions'!$B$5)^(C62-'Calculation_Assumptions'!$B$2) | S62: =N62*K62 | T62: =O62*K62 | U62: =T62*Q62*L62*M62 | V62: =S62*P62*L62*M62 | W62: =V62-U62 | X62: =W62*R62 | Y62: 1 | Z62: 2023 | AA62: Ready | AB62: =IF(I62="shared-count-once",COUNTIFS($A$2:$A$807,A62,$C$2:$C$807,C62,$E$2:$E$807,E62,$B$2:$B$807,B62),1) | AC62: 3.0364428e+08 | AD62: =IF(AC62=0,"",U62/AC62) | AE62: =IF(AC62=0,"",V62/AC62) | AF62: =IF(AC62=0,"",W62/AC62) | AG62: =IF(AC62=0,"",X62/AC62)
A63: S_70_30_30_TO_70_70_70 | B63: cascade_70_30_30_to_70_70_70 | C63: 2034 | D63: I_T2D_TREATMENT | E63: COST_T2D_SCREEN | F63: cascade_70_30_30_to_70_70_70|COST_T2D_SCREEN | G63: Diabetes opportunistic screening | H63: dm2 | I63: cause-specific | J63: all | K63: 1e-05 | L63: 1 | M63: 0.70495848 | N63: 1.7450473e+08 | O63: 1.7446169e+08 | P63: 0.2485 | Q63: 0.033768828 | R63: =1/(1+'Calculation_Assumptions'!$B$5)^(C63-'Calculation_Assumptions'!$B$2) | S63: =N63*K63 | T63: =O63*K63 | U63: =T63*Q63*L63*M63 | V63: =S63*P63*L63*M63 | W63: =V63-U63 | X63: =W63*R63 | Y63: 1 | Z63: 2023 | AA63: Ready | AB63: =IF(I63="shared-count-once",COUNTIFS($A$2:$A$807,A63,$C$2:$C$807,C63,$E$2:$E$807,E63,$B$2:$B$807,B63),1) | AC63: 3.0533254e+08 | AD63: =IF(AC63=0,"",U63/AC63) | AE63: =IF(AC63=0,"",V63/AC63) | AF63: =IF(AC63=0,"",W63/AC63) | AG63: =IF(AC63=0,"",X63/AC63)
A64: S_70_30_30_TO_70_70_70 | B64: cascade_70_30_30_to_70_70_70 | C64: 2035 | D64: I_T2D_TREATMENT | E64: COST_T2D_SCREEN | F64: cascade_70_30_30_to_70_70_70|COST_T2D_SCREEN | G64: Diabetes opportunistic screening | H64: dm2 | I64: cause-specific | J64: all | K64: 1e-05 | L64: 1 | M64: 0.70495848 | N64: 1.7660191e+08 | O64: 1.7653877e+08 | P64: 0.2765 | Q64: 0.033768828 | R64: =1/(1+'Calculation_Assumptions'!$B$5)^(C64-'Calculation_Assumptions'!$B$2) | S64: =N64*K64 | T64: =O64*K64 | U64: =T64*Q64*L64*M64 | V64: =S64*P64*L64*M64 | W64: =V64-U64 | X64: =W64*R64 | Y64: 1 | Z64: 2023 | AA64: Ready | AB64: =IF(I64="shared-count-once",COUNTIFS($A$2:$A$807,A64,$C$2:$C$807,C64,$E$2:$E$807,E64,$B$2:$B$807,B64),1) | AC64: 3.0696465e+08 | AD64: =IF(AC64=0,"",U64/AC64) | AE64: =IF(AC64=0,"",V64/AC64) | AF64: =IF(AC64=0,"",W64/AC64) | AG64: =IF(AC64=0,"",X64/AC64)
A65: S_70_30_30_TO_70_70_70 | B65: cascade_70_30_30_to_70_70_70 | C65: 2036 | D65: I_T2D_TREATMENT | E65: COST_T2D_SCREEN | F65: cascade_70_30_30_to_70_70_70|COST_T2D_SCREEN | G65: Diabetes opportunistic screening | H65: dm2 | I65: cause-specific | J65: all | K65: 1e-05 | L65: 1 | M65: 0.70495848 | N65: 1.7871375e+08 | O65: 1.7862366e+08 | P65: 0.3045 | Q65: 0.033768828 | R65: =1/(1+'Calculation_Assumptions'!$B$5)^(C65-'Calculation_Assumptions'!$B$2) | S65: =N65*K65 | T65: =O65*K65 | U65: =T65*Q65*L65*M65 | V65: =S65*P65*L65*M65 | W65: =V65-U65 | X65: =W65*R65 | Y65: 1 | Z65: 2023 | AA65: Ready | AB65: =IF(I65="shared-count-once",COUNTIFS($A$2:$A$807,A65,$C$2:$C$807,C65,$E$2:$E$807,E65,$B$2:$B$807,B65),1) | AC65: 3.0854277e+08 | AD65: =IF(AC65=0,"",U65/AC65) | AE65: =IF(AC65=0,"",V65/AC65) | AF65: =IF(AC65=0,"",W65/AC65) | AG65: =IF(AC65=0,"",X65/AC65)
... A131: S_70_30_30_TO_70_70_70 | B131: cascade_70_30_30_to_70_70_70 | C131: 2050 | D131: I_T2D_TREATMENT | E131: COST_T2D_INSULIN | F131: cascade_70_30_30_to_70_70_70|COST_T2D_INSULIN | G131: Diabetes management, insulin dependent | H131: dm2 | I131: cause-specific | J131: prevalence | K131: 0.2 | L131: 1 | M131: 82.68 | N131: 25275788 | O131: 25030421 | P131: 0.4165 | Q131: 0.033768828 | R131: =1/(1+'Calculation_Assumptions'!$B$5)^(C131-'Calculation_Assumptions'!$B$2) | S131: =N131*K131 | T131: =O131*K131 | U131: =T131*Q131*L131*M131 | V131: =S131*P131*L131*M131 | W131: =V131-U131 | X131: =W131*R131 | Y131: 1 | Z131: 2023 | AA131: Ready | AB131: =IF(I131="shared-count-once",COUNTIFS($A$2:$A$807,A131,$C$2:$C$807,C131,$E$2:$E$807,E131,$B$2:$B$807,B131),1) | AC131: 3.2331204e+08 | AD131: =IF(AC131=0,"",U131/AC131) | AE131: =IF(AC131=0,"",V131/AC131) | AF131: =IF(AC131=0,"",W131/AC131) | AG131: =IF(AC131=0,"",X131/AC131)
A132: I_PH_TOBACCO_TAX | B132: public_health | C132: 2025 | D132: I_PH_TOBACCO_TAX | E132: COST_PH_TOB_TAX | F132: public_health|COST_PH_TOB_TAX | G132: Annual intersectoral policy implementation | I132: shared-count-once | J132: all | K132: 1 | L132: 1 | M132: 0.04 | N132: 2.9188657e+08 | O132: 2.9122395e+08 | P132: 0 | Q132: 0 | R132: =1/(1+'Calculation_Assumptions'!$B$5)^(C132-'Calculation_Assumptions'!$B$2) | S132: =N132*K132 | T132: =O132*K132 | U132: =T132*Q132*L132*M132 | V132: =S132*P132*L132*M132 | W132: =V132-U132 | X132: =W132*R132 | Y132: 0 | Z132: 2017 | AA132: Review | AB132: =IF(I132="shared-count-once",COUNTIFS($A$2:$A$807,A132,$C$2:$C$807,C132,$E$2:$E$807,E132,$B$2:$B$807,B132),1) | AC132: 2.8839191e+08 | AD132: =IF(AC132=0,"",U132/AC132) | AE132: =IF(AC132=0,"",V132/AC132) | AF132: =IF(AC132=0,"",W132/AC132) | AG132: =IF(AC132=0,"",X132/AC132)
A133: I_PH_TOBACCO_TAX | B133: public_health | C133: 2026 | D133: I_PH_TOBACCO_TAX | E133: COST_PH_TOB_TAX | F133: public_health|COST_PH_TOB_TAX | G133: Annual intersectoral policy implementation | I133: shared-count-once | J133: all | K133: 1 | L133: 1 | M133: 0.04 | N133: 2.9382881e+08 | O133: 2.9321247e+08 | P133: 0.33333333 | Q133: 0 | R133: =1/(1+'Calculation_Assumptions'!$B$5)^(C133-'Calculation_Assumptions'!$B$2) | S133: =N133*K133 | T133: =O133*K133 | U133: =T133*Q133*L133*M133 | V133: =S133*P133*L133*M133 | W133: =V133-U133 | X133: =W133*R133 | Y133: 0 | Z133: 2017 | AA133: Review | AB133: =IF(I133="shared-count-once",COUNTIFS($A$2:$A$807,A133,$C$2:$C$807,C133,$E$2:$E$807,E133,$B$2:$B$807,B133),1) | AC133: 2.9047213e+08 | AD133: =IF(AC133=0,"",U133/AC133) | AE133: =IF(AC133=0,"",V133/AC133) | AF133: =IF(AC133=0,"",W133/AC133) | AG133: =IF(AC133=0,"",X133/AC133)
A134: I_PH_TOBACCO_TAX | B134: public_health | C134: 2027 | D134: I_PH_TOBACCO_TAX | E134: COST_PH_TOB_TAX | F134: public_health|COST_PH_TOB_TAX | G134: Annual intersectoral policy implementation | I134: shared-count-once | J134: all | K134: 1 | L134: 1 | M134: 0.04 | N134: 2.9574911e+08 | O134: 2.9519612e+08 | P134: 0.66666667 | Q134: 0 | R134: =1/(1+'Calculation_Assumptions'!$B$5)^(C134-'Calculation_Assumptions'!$B$2) | S134: =N134*K134 | T134: =O134*K134 | U134: =T134*Q134*L134*M134 | V134: =S134*P134*L134*M134 | W134: =V134-U134 | X134: =W134*R134 | Y134: 0 | Z134: 2017 | AA134: Review | AB134: =IF(I134="shared-count-once",COUNTIFS($A$2:$A$807,A134,$C$2:$C$807,C134,$E$2:$E$807,E134,$B$2:$B$807,B134),1) | AC134: 2.9250508e+08 | AD134: =IF(AC134=0,"",U134/AC134) | AE134: =IF(AC134=0,"",V134/AC134) | AF134: =IF(AC134=0,"",W134/AC134) | AG134: =IF(AC134=0,"",X134/AC134)
A135: I_PH_TOBACCO_TAX | B135: public_health | C135: 2028 | D135: I_PH_TOBACCO_TAX | E135: COST_PH_TOB_TAX | F135: public_health|COST_PH_TOB_TAX | G135: Annual intersectoral policy implementation | I135: shared-count-once | J135: all | K135: 1 | L135: 1 | M135: 0.04 | N135: 2.9746234e+08 | O135: 2.9710793e+08 | P135: 1 | Q135: 0 | R135: =1/(1+'Calculation_Assumptions'!$B$5)^(C135-'Calculation_Assumptions'!$B$2) | S135: =N135*K135 | T135: =O135*K135 | U135: =T135*Q135*L135*M135 | V135: =S135*P135*L135*M135 | W135: =V135-U135 | X135: =W135*R135 | Y135: 0 | Z135: 2017 | AA135: Review | AB135: =IF(I135="shared-count-once",COUNTIFS($A$2:$A$807,A135,$C$2:$C$807,C135,$E$2:$E$807,E135,$B$2:$B$807,B135),1) | AC135: 2.9448471e+08 | AD135: =IF(AC135=0,"",U135/AC135) | AE135: =IF(AC135=0,"",V135/AC135) | AF135: =IF(AC135=0,"",W135/AC135) | AG135: =IF(AC135=0,"",X135/AC135)
A136: I_PH_TOBACCO_TAX | B136: public_health | C136: 2029 | D136: I_PH_TOBACCO_TAX | E136: COST_PH_TOB_TAX | F136: public_health|COST_PH_TOB_TAX | G136: Annual intersectoral policy implementation | I136: shared-count-once | J136: all | K136: 1 | L136: 1 | M136: 0.04 | N136: 2.9933347e+08 | O136: 2.9898117e+08 | P136: 1 | Q136: 0 | R136: =1/(1+'Calculation_Assumptions'!$B$5)^(C136-'Calculation_Assumptions'!$B$2) | S136: =N136*K136 | T136: =O136*K136 | U136: =T136*Q136*L136*M136 | V136: =S136*P136*L136*M136 | W136: =V136-U136 | X136: =W136*R136 | Y136: 0 | Z136: 2017 | AA136: Review | AB136: =IF(I136="shared-count-once",COUNTIFS($A$2:$A$807,A136,$C$2:$C$807,C136,$E$2:$E$807,E136,$B$2:$B$807,B136),1) | AC136: 2.9641403e+08 | AD136: =IF(AC136=0,"",U136/AC136) | AE136: =IF(AC136=0,"",V136/AC136) | AF136: =IF(AC136=0,"",W136/AC136) | AG136: =IF(AC136=0,"",X136/AC136)
A137: I_PH_TOBACCO_TAX | B137: public_health | C137: 2030 | D137: I_PH_TOBACCO_TAX | E137: COST_PH_TOB_TAX | F137: public_health|COST_PH_TOB_TAX | G137: Annual intersectoral policy implementation | I137: shared-count-once | J137: all | K137: 1 | L137: 1 | M137: 0.04 | N137: 3.0116162e+08 | O137: 3.0078424e+08 | P137: 1 | Q137: 0 | R137: =1/(1+'Calculation_Assumptions'!$B$5)^(C137-'Calculation_Assumptions'!$B$2) | S137: =N137*K137 | T137: =O137*K137 | U137: =T137*Q137*L137*M137 | V137: =S137*P137*L137*M137 | W137: =V137-U137 | X137: =W137*R137 | Y137: 0 | Z137: 2017 | AA137: Review | AB137: =IF(I137="shared-count-once",COUNTIFS($A$2:$A$807,A137,$C$2:$C$807,C137,$E$2:$E$807,E137,$B$2:$B$807,B137),1) | AC137: 2.982894e+08 | AD137: =IF(AC137=0,"",U137/AC137) | AE137: =IF(AC137=0,"",V137/AC137) | AF137: =IF(AC137=0,"",W137/AC137) | AG137: =IF(AC137=0,"",X137/AC137)
A138: I_PH_TOBACCO_TAX | B138: public_health | C138: 2031 | D138: I_PH_TOBACCO_TAX | E138: COST_PH_TOB_TAX | F138: public_health|COST_PH_TOB_TAX | G138: Annual intersectoral policy implementation | I138: shared-count-once | J138: all | K138: 1 | L138: 1 | M138: 0.04 | N138: 3.0295494e+08 | O138: 3.0256162e+08 | P138: 1 | Q138: 0 | R138: =1/(1+'Calculation_Assumptions'!$B$5)^(C138-'Calculation_Assumptions'!$B$2) | S138: =N138*K138 | T138: =O138*K138 | U138: =T138*Q138*L138*M138 | V138: =S138*P138*L138*M138 | W138: =V138-U138 | X138: =W138*R138 | Y138: 0 | Z138: 2017 | AA138: Review | AB138: =IF(I138="shared-count-once",COUNTIFS($A$2:$A$807,A138,$C$2:$C$807,C138,$E$2:$E$807,E138,$B$2:$B$807,B138),1) | AC138: 3.0011964e+08 | AD138: =IF(AC138=0,"",U138/AC138) | AE138: =IF(AC138=0,"",V138/AC138) | AF138: =IF(AC138=0,"",W138/AC138) | AG138: =IF(AC138=0,"",X138/AC138)
A139: I_PH_TOBACCO_TAX | B139: public_health | C139: 2032 | D139: I_PH_TOBACCO_TAX | E139: COST_PH_TOB_TAX | F139: public_health|COST_PH_TOB_TAX | G139: Annual intersectoral policy implementation | I139: shared-count-once | J139: all | K139: 1 | L139: 1 | M139: 0.04 | N139: 3.0470609e+08 | O139: 3.0429691e+08 | P139: 1 | Q139: 0 | R139: =1/(1+'Calculation_Assumptions'!$B$5)^(C139-'Calculation_Assumptions'!$B$2) | S139: =N139*K139 | T139: =O139*K139 | U139: =T139*Q139*L139*M139 | V139: =S139*P139*L139*M139 | W139: =V139-U139 | X139: =W139*R139 | Y139: 0 | Z139: 2017 | AA139: Review | AB139: =IF(I139="shared-count-once",COUNTIFS($A$2:$A$807,A139,$C$2:$C$807,C139,$E$2:$E$807,E139,$B$2:$B$807,B139),1) | AC139: 3.0190463e+08 | AD139: =IF(AC139=0,"",U139/AC139) | AE139: =IF(AC139=0,"",V139/AC139) | AF139: =IF(AC139=0,"",W139/AC139) | AG139: =IF(AC139=0,"",X139/AC139)
A140: I_PH_TOBACCO_TAX | B140: public_health | C140: 2033 | D140: I_PH_TOBACCO_TAX | E140: COST_PH_TOB_TAX | F140: public_health|COST_PH_TOB_TAX | G140: Annual intersectoral policy implementation | I140: shared-count-once | J140: all | K140: 1 | L140: 1 | M140: 0.04 | N140: 3.0641568e+08 | O140: 3.0599004e+08 | P140: 1 | Q140: 0 | R140: =1/(1+'Calculation_Assumptions'!$B$5)^(C140-'Calculation_Assumptions'!$B$2) | S140: =N140*K140 | T140: =O140*K140 | U140: =T140*Q140*L140*M140 | V140: =S140*P140*L140*M140 | W140: =V140-U140 | X140: =W140*R140 | Y140: 0 | Z140: 2017 | AA140: Review | AB140: =IF(I140="shared-count-once",COUNTIFS($A$2:$A$807,A140,$C$2:$C$807,C140,$E$2:$E$807,E140,$B$2:$B$807,B140),1) | AC140: 3.0364428e+08 | AD140: =IF(AC140=0,"",U140/AC140) | AE140: =IF(AC140=0,"",V140/AC140) | AF140: =IF(AC140=0,"",W140/AC140) | AG140: =IF(AC140=0,"",X140/AC140)
A141: I_PH_TOBACCO_TAX | B141: public_health | C141: 2034 | D141: I_PH_TOBACCO_TAX | E141: COST_PH_TOB_TAX | F141: public_health|COST_PH_TOB_TAX | G141: Annual intersectoral policy implementation | I141: shared-count-once | J141: all | K141: 1 | L141: 1 | M141: 0.04 | N141: 3.0807674e+08 | O141: 3.0763553e+08 | P141: 1 | Q141: 0 | R141: =1/(1+'Calculation_Assumptions'!$B$5)^(C141-'Calculation_Assumptions'!$B$2) | S141: =N141*K141 | T141: =O141*K141 | U141: =T141*Q141*L141*M141 | V141: =S141*P141*L141*M141 | W141: =V141-U141 | X141: =W141*R141 | Y141: 0 | Z141: 2017 | AA141: Review | AB141: =IF(I141="shared-count-once",COUNTIFS($A$2:$A$807,A141,$C$2:$C$807,C141,$E$2:$E$807,E141,$B$2:$B$807,B141),1) | AC141: 3.0533254e+08 | AD141: =IF(AC141=0,"",U141/AC141) | AE141: =IF(AC141=0,"",V141/AC141) | AF141: =IF(AC141=0,"",W141/AC141) | AG141: =IF(AC141=0,"",X141/AC141)
A142: I_PH_TOBACCO_TAX | B142: public_health | C142: 2035 | D142: I_PH_TOBACCO_TAX | E142: COST_PH_TOB_TAX | F142: public_health|COST_PH_TOB_TAX | G142: Annual intersectoral policy implementation | I142: shared-count-once | J142: all | K142: 1 | L142: 1 | M142: 0.04 | N142: 3.0968454e+08 | O142: 3.0922818e+08 | P142: 1 | Q142: 0 | R142: =1/(1+'Calculation_Assumptions'!$B$5)^(C142-'Calculation_Assumptions'!$B$2) | S142: =N142*K142 | T142: =O142*K142 | U142: =T142*Q142*L142*M142 | V142: =S142*P142*L142*M142 | W142: =V142-U142 | X142: =W142*R142 | Y142: 0 | Z142: 2017 | AA142: Review | AB142: =IF(I142="shared-count-once",COUNTIFS($A$2:$A$807,A142,$C$2:$C$807,C142,$E$2:$E$807,E142,$B$2:$B$807,B142),1) | AC142: 3.0696465e+08 | AD142: =IF(AC142=0,"",U142/AC142) | AE142: =IF(AC142=0,"",V142/AC142) | AF142: =IF(AC142=0,"",W142/AC142) | AG142: =IF(AC142=0,"",X142/AC142)
A143: I_PH_TOBACCO_TAX | B143: public_health | C143: 2036 | D143: I_PH_TOBACCO_TAX | E143: COST_PH_TOB_TAX | F143: public_health|COST_PH_TOB_TAX | G143: Annual intersectoral policy implementation | I143: shared-count-once | J143: all | K143: 1 | L143: 1 | M143: 0.04 | N143: 3.1124032e+08 | O143: 3.1076948e+08 | P143: 1 | Q143: 0 | R143: =1/(1+'Calculation_Assumptions'!$B$5)^(C143-'Calculation_Assumptions'!$B$2) | S143: =N143*K143 | T143: =O143*K143 | U143: =T143*Q143*L143*M143 | V143: =S143*P143*L143*M143 | W143: =V143-U143 | X143: =W143*R143 | Y143: 0 | Z143: 2017 | AA143: Review | AB143: =IF(I143="shared-count-once",COUNTIFS($A$2:$A$807,A143,$C$2:$C$807,C143,$E$2:$E$807,E143,$B$2:$B$807,B143),1) | AC143: 3.0854277e+08 | AD143: =IF(AC143=0,"",U143/AC143) | AE143: =IF(AC143=0,"",V143/AC143) | AF143: =IF(AC143=0,"",W143/AC143) | AG143: =IF(AC143=0,"",X143/AC143)
... A469: all_cascade_public_health | B469: cascade_70_30_30_to_70_70_70 | C469: 2050 | D469: I_CVD_PRIMARY | E469: COST_PRIMARY_TX_A | F469: cascade_70_30_30_to_70_70_70|COST_PRIMARY_TX_A | G469: Antihypertensives and statins for absolute CVD risk >20% | I469: shared-count-once | J469: all | K469: 0.06 | L469: 1 | M469: 69.3 | N469: 2.0512485e+08 | O469: 2.024798e+08 | P469: 0.4165 | Q469: 0.14506229 | R469: =1/(1+'Calculation_Assumptions'!$B$5)^(C469-'Calculation_Assumptions'!$B$2) | S469: =N469*K469 | T469: =O469*K469 | U469: =T469*Q469*L469*M469 | V469: =S469*P469*L469*M469 | W469: =V469-U469 | X469: =W469*R469 | Y469: 1 | Z469: 2023 | AA469: Review | AB469: =IF(I469="shared-count-once",COUNTIFS($A$2:$A$807,A469,$C$2:$C$807,C469,$E$2:$E$807,E469,$B$2:$B$807,B469),1) | AC469: 3.2331204e+08 | AD469: =IF(AC469=0,"",U469/AC469) | AE469: =IF(AC469=0,"",V469/AC469) | AF469: =IF(AC469=0,"",W469/AC469) | AG469: =IF(AC469=0,"",X469/AC469)
A470: all_cascade_public_health | B470: cascade_70_30_30_to_70_70_70 | C470: 2025 | D470: I_T2D_TREATMENT | E470: COST_T2D_SCREEN | F470: cascade_70_30_30_to_70_70_70|COST_T2D_SCREEN | G470: Diabetes opportunistic screening | H470: dm2 | I470: cause-specific | J470: all | K470: 1e-05 | L470: 1 | M470: 0.70495848 | N470: 1.5575581e+08 | O470: 1.5509319e+08 | P470: 0.033768828 | Q470: 0.033768828 | R470: =1/(1+'Calculation_Assumptions'!$B$5)^(C470-'Calculation_Assumptions'!$B$2) | S470: =N470*K470 | T470: =O470*K470 | U470: =T470*Q470*L470*M470 | V470: =S470*P470*L470*M470 | W470: =V470-U470 | X470: =W470*R470 | Y470: 1 | Z470: 2023 | AA470: Ready | AB470: =IF(I470="shared-count-once",COUNTIFS($A$2:$A$807,A470,$C$2:$C$807,C470,$E$2:$E$807,E470,$B$2:$B$807,B470),1) | AC470: 2.8839191e+08 | AD470: =IF(AC470=0,"",U470/AC470) | AE470: =IF(AC470=0,"",V470/AC470) | AF470: =IF(AC470=0,"",W470/AC470) | AG470: =IF(AC470=0,"",X470/AC470)
A471: all_cascade_public_health | B471: cascade_70_30_30_to_70_70_70 | C471: 2026 | D471: I_T2D_TREATMENT | E471: COST_T2D_SCREEN | F471: cascade_70_30_30_to_70_70_70|COST_T2D_SCREEN | G471: Diabetes opportunistic screening | H471: dm2 | I471: cause-specific | J471: all | K471: 1e-05 | L471: 1 | M471: 0.70495848 | N471: 1.5812016e+08 | O471: 1.5750383e+08 | P471: 0.054315063 | Q471: 0.033768828 | R471: =1/(1+'Calculation_Assumptions'!$B$5)^(C471-'Calculation_Assumptions'!$B$2) | S471: =N471*K471 | T471: =O471*K471 | U471: =T471*Q471*L471*M471 | V471: =S471*P471*L471*M471 | W471: =V471-U471 | X471: =W471*R471 | Y471: 1 | Z471: 2023 | AA471: Ready | AB471: =IF(I471="shared-count-once",COUNTIFS($A$2:$A$807,A471,$C$2:$C$807,C471,$E$2:$E$807,E471,$B$2:$B$807,B471),1) | AC471: 2.9047213e+08 | AD471: =IF(AC471=0,"",U471/AC471) | AE471: =IF(AC471=0,"",V471/AC471) | AF471: =IF(AC471=0,"",W471/AC471) | AG471: =IF(AC471=0,"",X471/AC471)
A472: all_cascade_public_health | B472: cascade_70_30_30_to_70_70_70 | C472: 2027 | D472: I_T2D_TREATMENT | E472: COST_T2D_SCREEN | F472: cascade_70_30_30_to_70_70_70|COST_T2D_SCREEN | G472: Diabetes opportunistic screening | H472: dm2 | I472: cause-specific | J472: all | K472: 1e-05 | L472: 1 | M472: 0.70495848 | N472: 1.6052319e+08 | O472: 1.5995711e+08 | P472: 0.074861297 | Q472: 0.033768828 | R472: =1/(1+'Calculation_Assumptions'!$B$5)^(C472-'Calculation_Assumptions'!$B$2) | S472: =N472*K472 | T472: =O472*K472 | U472: =T472*Q472*L472*M472 | V472: =S472*P472*L472*M472 | W472: =V472-U472 | X472: =W472*R472 | Y472: 1 | Z472: 2023 | AA472: Ready | AB472: =IF(I472="shared-count-once",COUNTIFS($A$2:$A$807,A472,$C$2:$C$807,C472,$E$2:$E$807,E472,$B$2:$B$807,B472),1) | AC472: 2.9250508e+08 | AD472: =IF(AC472=0,"",U472/AC472) | AE472: =IF(AC472=0,"",V472/AC472) | AF472: =IF(AC472=0,"",W472/AC472) | AG472: =IF(AC472=0,"",X472/AC472)
A473: all_cascade_public_health | B473: cascade_70_30_30_to_70_70_70 | C473: 2028 | D473: I_T2D_TREATMENT | E473: COST_T2D_SCREEN | F473: cascade_70_30_30_to_70_70_70|COST_T2D_SCREEN | G473: Diabetes opportunistic screening | H473: dm2 | I473: cause-specific | J473: all | K473: 1e-05 | L473: 1 | M473: 0.70495848 | N473: 1.6276802e+08 | O473: 1.6220434e+08 | P473: 0.095407531 | Q473: 0.033768828 | R473: =1/(1+'Calculation_Assumptions'!$B$5)^(C473-'Calculation_Assumptions'!$B$2) | S473: =N473*K473 | T473: =O473*K473 | U473: =T473*Q473*L473*M473 | V473: =S473*P473*L473*M473 | W473: =V473-U473 | X473: =W473*R473 | Y473: 1 | Z473: 2023 | AA473: Ready | AB473: =IF(I473="shared-count-once",COUNTIFS($A$2:$A$807,A473,$C$2:$C$807,C473,$E$2:$E$807,E473,$B$2:$B$807,B473),1) | AC473: 2.9448471e+08 | AD473: =IF(AC473=0,"",U473/AC473) | AE473: =IF(AC473=0,"",V473/AC473) | AF473: =IF(AC473=0,"",W473/AC473) | AG473: =IF(AC473=0,"",X473/AC473)
A474: all_cascade_public_health | B474: cascade_70_30_30_to_70_70_70 | C474: 2029 | D474: I_T2D_TREATMENT | E474: COST_T2D_SCREEN | F474: cascade_70_30_30_to_70_70_70|COST_T2D_SCREEN | G474: Diabetes opportunistic screening | H474: dm2 | I474: cause-specific | J474: all | K474: 1e-05 | L474: 1 | M474: 0.70495848 | N474: 1.6490438e+08 | O474: 1.6435451e+08 | P474: 0.11595377 | Q474: 0.033768828 | R474: =1/(1+'Calculation_Assumptions'!$B$5)^(C474-'Calculation_Assumptions'!$B$2) | S474: =N474*K474 | T474: =O474*K474 | U474: =T474*Q474*L474*M474 | V474: =S474*P474*L474*M474 | W474: =V474-U474 | X474: =W474*R474 | Y474: 1 | Z474: 2023 | AA474: Ready | AB474: =IF(I474="shared-count-once",COUNTIFS($A$2:$A$807,A474,$C$2:$C$807,C474,$E$2:$E$807,E474,$B$2:$B$807,B474),1) | AC474: 2.9641403e+08 | AD474: =IF(AC474=0,"",U474/AC474) | AE474: =IF(AC474=0,"",V474/AC474) | AF474: =IF(AC474=0,"",W474/AC474) | AG474: =IF(AC474=0,"",X474/AC474)
A475: all_cascade_public_health | B475: cascade_70_30_30_to_70_70_70 | C475: 2030 | D475: I_T2D_TREATMENT | E475: COST_T2D_SCREEN | F475: cascade_70_30_30_to_70_70_70|COST_T2D_SCREEN | G475: Diabetes opportunistic screening | H475: dm2 | I475: cause-specific | J475: all | K475: 1e-05 | L475: 1 | M475: 0.70495848 | N475: 1.669667e+08 | O475: 1.6641555e+08 | P475: 0.1365 | Q475: 0.033768828 | R475: =1/(1+'Calculation_Assumptions'!$B$5)^(C475-'Calculation_Assumptions'!$B$2) | S475: =N475*K475 | T475: =O475*K475 | U475: =T475*Q475*L475*M475 | V475: =S475*P475*L475*M475 | W475: =V475-U475 | X475: =W475*R475 | Y475: 1 | Z475: 2023 | AA475: Ready | AB475: =IF(I475="shared-count-once",COUNTIFS($A$2:$A$807,A475,$C$2:$C$807,C475,$E$2:$E$807,E475,$B$2:$B$807,B475),1) | AC475: 2.982894e+08 | AD475: =IF(AC475=0,"",U475/AC475) | AE475: =IF(AC475=0,"",V475/AC475) | AF475: =IF(AC475=0,"",W475/AC475) | AG475: =IF(AC475=0,"",X475/AC475)
A476: all_cascade_public_health | B476: cascade_70_30_30_to_70_70_70 | C476: 2031 | D476: I_T2D_TREATMENT | E476: COST_T2D_SCREEN | F476: cascade_70_30_30_to_70_70_70|COST_T2D_SCREEN | G476: Diabetes opportunistic screening | H476: dm2 | I476: cause-specific | J476: all | K476: 1e-05 | L476: 1 | M476: 0.70495848 | N476: 1.6904566e+08 | O476: 1.6846129e+08 | P476: 0.1645 | Q476: 0.033768828 | R476: =1/(1+'Calculation_Assumptions'!$B$5)^(C476-'Calculation_Assumptions'!$B$2) | S476: =N476*K476 | T476: =O476*K476 | U476: =T476*Q476*L476*M476 | V476: =S476*P476*L476*M476 | W476: =V476-U476 | X476: =W476*R476 | Y476: 1 | Z476: 2023 | AA476: Ready | AB476: =IF(I476="shared-count-once",COUNTIFS($A$2:$A$807,A476,$C$2:$C$807,C476,$E$2:$E$807,E476,$B$2:$B$807,B476),1) | AC476: 3.0011964e+08 | AD476: =IF(AC476=0,"",U476/AC476) | AE476: =IF(AC476=0,"",V476/AC476) | AF476: =IF(AC476=0,"",W476/AC476) | AG476: =IF(AC476=0,"",X476/AC476)
A477: all_cascade_public_health | B477: cascade_70_30_30_to_70_70_70 | C477: 2032 | D477: I_T2D_TREATMENT | E477: COST_T2D_SCREEN | F477: cascade_70_30_30_to_70_70_70|COST_T2D_SCREEN | G477: Diabetes opportunistic screening | H477: dm2 | I477: cause-specific | J477: all | K477: 1e-05 | L477: 1 | M477: 0.70495848 | N477: 1.7107992e+08 | O477: 1.7047662e+08 | P477: 0.1925 | Q477: 0.033768828 | R477: =1/(1+'Calculation_Assumptions'!$B$5)^(C477-'Calculation_Assumptions'!$B$2) | S477: =N477*K477 | T477: =O477*K477 | U477: =T477*Q477*L477*M477 | V477: =S477*P477*L477*M477 | W477: =V477-U477 | X477: =W477*R477 | Y477: 1 | Z477: 2023 | AA477: Ready | AB477: =IF(I477="shared-count-once",COUNTIFS($A$2:$A$807,A477,$C$2:$C$807,C477,$E$2:$E$807,E477,$B$2:$B$807,B477),1) | AC477: 3.0190463e+08 | AD477: =IF(AC477=0,"",U477/AC477) | AE477: =IF(AC477=0,"",V477/AC477) | AF477: =IF(AC477=0,"",W477/AC477) | AG477: =IF(AC477=0,"",X477/AC477)
A478: all_cascade_public_health | B478: cascade_70_30_30_to_70_70_70 | C478: 2033 | D478: I_T2D_TREATMENT | E478: COST_T2D_SCREEN | F478: cascade_70_30_30_to_70_70_70|COST_T2D_SCREEN | G478: Diabetes opportunistic screening | H478: dm2 | I478: cause-specific | J478: all | K478: 1e-05 | L478: 1 | M478: 0.70495848 | N478: 1.7309047e+08 | O478: 1.7246151e+08 | P478: 0.2205 | Q478: 0.033768828 | R478: =1/(1+'Calculation_Assumptions'!$B$5)^(C478-'Calculation_Assumptions'!$B$2) | S478: =N478*K478 | T478: =O478*K478 | U478: =T478*Q478*L478*M478 | V478: =S478*P478*L478*M478 | W478: =V478-U478 | X478: =W478*R478 | Y478: 1 | Z478: 2023 | AA478: Ready | AB478: =IF(I478="shared-count-once",COUNTIFS($A$2:$A$807,A478,$C$2:$C$807,C478,$E$2:$E$807,E478,$B$2:$B$807,B478),1) | AC478: 3.0364428e+08 | AD478: =IF(AC478=0,"",U478/AC478) | AE478: =IF(AC478=0,"",V478/AC478) | AF478: =IF(AC478=0,"",W478/AC478) | AG478: =IF(AC478=0,"",X478/AC478)
A479: all_cascade_public_health | B479: cascade_70_30_30_to_70_70_70 | C479: 2034 | D479: I_T2D_TREATMENT | E479: COST_T2D_SCREEN | F479: cascade_70_30_30_to_70_70_70|COST_T2D_SCREEN | G479: Diabetes opportunistic screening | H479: dm2 | I479: cause-specific | J479: all | K479: 1e-05 | L479: 1 | M479: 0.70495848 | N479: 1.7512252e+08 | O479: 1.7446169e+08 | P479: 0.2485 | Q479: 0.033768828 | R479: =1/(1+'Calculation_Assumptions'!$B$5)^(C479-'Calculation_Assumptions'!$B$2) | S479: =N479*K479 | T479: =O479*K479 | U479: =T479*Q479*L479*M479 | V479: =S479*P479*L479*M479 | W479: =V479-U479 | X479: =W479*R479 | Y479: 1 | Z479: 2023 | AA479: Ready | AB479: =IF(I479="shared-count-once",COUNTIFS($A$2:$A$807,A479,$C$2:$C$807,C479,$E$2:$E$807,E479,$B$2:$B$807,B479),1) | AC479: 3.0533254e+08 | AD479: =IF(AC479=0,"",U479/AC479) | AE479: =IF(AC479=0,"",V479/AC479) | AF479: =IF(AC479=0,"",W479/AC479) | AG479: =IF(AC479=0,"",X479/AC479)
A480: all_cascade_public_health | B480: cascade_70_30_30_to_70_70_70 | C480: 2035 | D480: I_T2D_TREATMENT | E480: COST_T2D_SCREEN | F480: cascade_70_30_30_to_70_70_70|COST_T2D_SCREEN | G480: Diabetes opportunistic screening | H480: dm2 | I480: cause-specific | J480: all | K480: 1e-05 | L480: 1 | M480: 0.70495848 | N480: 1.7722031e+08 | O480: 1.7653877e+08 | P480: 0.2765 | Q480: 0.033768828 | R480: =1/(1+'Calculation_Assumptions'!$B$5)^(C480-'Calculation_Assumptions'!$B$2) | S480: =N480*K480 | T480: =O480*K480 | U480: =T480*Q480*L480*M480 | V480: =S480*P480*L480*M480 | W480: =V480-U480 | X480: =W480*R480 | Y480: 1 | Z480: 2023 | AA480: Ready | AB480: =IF(I480="shared-count-once",COUNTIFS($A$2:$A$807,A480,$C$2:$C$807,C480,$E$2:$E$807,E480,$B$2:$B$807,B480),1) | AC480: 3.0696465e+08 | AD480: =IF(AC480=0,"",U480/AC480) | AE480: =IF(AC480=0,"",V480/AC480) | AF480: =IF(AC480=0,"",W480/AC480) | AG480: =IF(AC480=0,"",X480/AC480)
A481: all_cascade_public_health | B481: cascade_70_30_30_to_70_70_70 | C481: 2036 | D481: I_T2D_TREATMENT | E481: COST_T2D_SCREEN | F481: cascade_70_30_30_to_70_70_70|COST_T2D_SCREEN | G481: Diabetes opportunistic screening | H481: dm2 | I481: cause-specific | J481: all | K481: 1e-05 | L481: 1 | M481: 0.70495848 | N481: 1.7934995e+08 | O481: 1.7862366e+08 | P481: 0.3045 | Q481: 0.033768828 | R481: =1/(1+'Calculation_Assumptions'!$B$5)^(C481-'Calculation_Assumptions'!$B$2) | S481: =N481*K481 | T481: =O481*K481 | U481: =T481*Q481*L481*M481 | V481: =S481*P481*L481*M481 | W481: =V481-U481 | X481: =W481*R481 | Y481: 1 | Z481: 2023 | AA481: Ready | AB481: =IF(I481="shared-count-once",COUNTIFS($A$2:$A$807,A481,$C$2:$C$807,C481,$E$2:$E$807,E481,$B$2:$B$807,B481),1) | AC481: 3.0854277e+08 | AD481: =IF(AC481=0,"",U481/AC481) | AE481: =IF(AC481=0,"",V481/AC481) | AF481: =IF(AC481=0,"",W481/AC481) | AG481: =IF(AC481=0,"",X481/AC481)
... A547: all_cascade_public_health | B547: cascade_70_30_30_to_70_70_70 | C547: 2050 | D547: I_T2D_TREATMENT | E547: COST_T2D_INSULIN | F547: cascade_70_30_30_to_70_70_70|COST_T2D_INSULIN | G547: Diabetes management, insulin dependent | H547: dm2 | I547: cause-specific | J547: prevalence | K547: 0.2 | L547: 1 | M547: 82.68 | N547: 24835417 | O547: 25030421 | P547: 0.4165 | Q547: 0.033768828 | R547: =1/(1+'Calculation_Assumptions'!$B$5)^(C547-'Calculation_Assumptions'!$B$2) | S547: =N547*K547 | T547: =O547*K547 | U547: =T547*Q547*L547*M547 | V547: =S547*P547*L547*M547 | W547: =V547-U547 | X547: =W547*R547 | Y547: 1 | Z547: 2023 | AA547: Ready | AB547: =IF(I547="shared-count-once",COUNTIFS($A$2:$A$807,A547,$C$2:$C$807,C547,$E$2:$E$807,E547,$B$2:$B$807,B547),1) | AC547: 3.2331204e+08 | AD547: =IF(AC547=0,"",U547/AC547) | AE547: =IF(AC547=0,"",V547/AC547) | AF547: =IF(AC547=0,"",W547/AC547) | AG547: =IF(AC547=0,"",X547/AC547)
A548: all_cascade_public_health | B548: public_health | C548: 2025 | D548: I_PH_TOBACCO_TAX | E548: COST_PH_TOB_TAX | F548: public_health|COST_PH_TOB_TAX | G548: Annual intersectoral policy implementation | I548: shared-count-once | J548: all | K548: 1 | L548: 1 | M548: 0.04 | N548: 2.9188657e+08 | O548: 2.9122395e+08 | P548: 0 | Q548: 0 | R548: =1/(1+'Calculation_Assumptions'!$B$5)^(C548-'Calculation_Assumptions'!$B$2) | S548: =N548*K548 | T548: =O548*K548 | U548: =T548*Q548*L548*M548 | V548: =S548*P548*L548*M548 | W548: =V548-U548 | X548: =W548*R548 | Y548: 0 | Z548: 2017 | AA548: Review | AB548: =IF(I548="shared-count-once",COUNTIFS($A$2:$A$807,A548,$C$2:$C$807,C548,$E$2:$E$807,E548,$B$2:$B$807,B548),1) | AC548: 2.8839191e+08 | AD548: =IF(AC548=0,"",U548/AC548) | AE548: =IF(AC548=0,"",V548/AC548) | AF548: =IF(AC548=0,"",W548/AC548) | AG548: =IF(AC548=0,"",X548/AC548)
A549: all_cascade_public_health | B549: public_health | C549: 2026 | D549: I_PH_TOBACCO_TAX | E549: COST_PH_TOB_TAX | F549: public_health|COST_PH_TOB_TAX | G549: Annual intersectoral policy implementation | I549: shared-count-once | J549: all | K549: 1 | L549: 1 | M549: 0.04 | N549: 2.9382881e+08 | O549: 2.9321247e+08 | P549: 0.33333333 | Q549: 0 | R549: =1/(1+'Calculation_Assumptions'!$B$5)^(C549-'Calculation_Assumptions'!$B$2) | S549: =N549*K549 | T549: =O549*K549 | U549: =T549*Q549*L549*M549 | V549: =S549*P549*L549*M549 | W549: =V549-U549 | X549: =W549*R549 | Y549: 0 | Z549: 2017 | AA549: Review | AB549: =IF(I549="shared-count-once",COUNTIFS($A$2:$A$807,A549,$C$2:$C$807,C549,$E$2:$E$807,E549,$B$2:$B$807,B549),1) | AC549: 2.9047213e+08 | AD549: =IF(AC549=0,"",U549/AC549) | AE549: =IF(AC549=0,"",V549/AC549) | AF549: =IF(AC549=0,"",W549/AC549) | AG549: =IF(AC549=0,"",X549/AC549)
A550: all_cascade_public_health | B550: public_health | C550: 2027 | D550: I_PH_TOBACCO_TAX | E550: COST_PH_TOB_TAX | F550: public_health|COST_PH_TOB_TAX | G550: Annual intersectoral policy implementation | I550: shared-count-once | J550: all | K550: 1 | L550: 1 | M550: 0.04 | N550: 2.9576227e+08 | O550: 2.9519612e+08 | P550: 0.66666667 | Q550: 0 | R550: =1/(1+'Calculation_Assumptions'!$B$5)^(C550-'Calculation_Assumptions'!$B$2) | S550: =N550*K550 | T550: =O550*K550 | U550: =T550*Q550*L550*M550 | V550: =S550*P550*L550*M550 | W550: =V550-U550 | X550: =W550*R550 | Y550: 0 | Z550: 2017 | AA550: Review | AB550: =IF(I550="shared-count-once",COUNTIFS($A$2:$A$807,A550,$C$2:$C$807,C550,$E$2:$E$807,E550,$B$2:$B$807,B550),1) | AC550: 2.9250508e+08 | AD550: =IF(AC550=0,"",U550/AC550) | AE550: =IF(AC550=0,"",V550/AC550) | AF550: =IF(AC550=0,"",W550/AC550) | AG550: =IF(AC550=0,"",X550/AC550)
A551: all_cascade_public_health | B551: public_health | C551: 2028 | D551: I_PH_TOBACCO_TAX | E551: COST_PH_TOB_TAX | F551: public_health|COST_PH_TOB_TAX | G551: Annual intersectoral policy implementation | I551: shared-count-once | J551: all | K551: 1 | L551: 1 | M551: 0.04 | N551: 2.9767181e+08 | O551: 2.9710793e+08 | P551: 1 | Q551: 0 | R551: =1/(1+'Calculation_Assumptions'!$B$5)^(C551-'Calculation_Assumptions'!$B$2) | S551: =N551*K551 | T551: =O551*K551 | U551: =T551*Q551*L551*M551 | V551: =S551*P551*L551*M551 | W551: =V551-U551 | X551: =W551*R551 | Y551: 0 | Z551: 2017 | AA551: Review | AB551: =IF(I551="shared-count-once",COUNTIFS($A$2:$A$807,A551,$C$2:$C$807,C551,$E$2:$E$807,E551,$B$2:$B$807,B551),1) | AC551: 2.9448471e+08 | AD551: =IF(AC551=0,"",U551/AC551) | AE551: =IF(AC551=0,"",V551/AC551) | AF551: =IF(AC551=0,"",W551/AC551) | AG551: =IF(AC551=0,"",X551/AC551)
A552: all_cascade_public_health | B552: public_health | C552: 2029 | D552: I_PH_TOBACCO_TAX | E552: COST_PH_TOB_TAX | F552: public_health|COST_PH_TOB_TAX | G552: Annual intersectoral policy implementation | I552: shared-count-once | J552: all | K552: 1 | L552: 1 | M552: 0.04 | N552: 2.9953139e+08 | O552: 2.9898117e+08 | P552: 1 | Q552: 0 | R552: =1/(1+'Calculation_Assumptions'!$B$5)^(C552-'Calculation_Assumptions'!$B$2) | S552: =N552*K552 | T552: =O552*K552 | U552: =T552*Q552*L552*M552 | V552: =S552*P552*L552*M552 | W552: =V552-U552 | X552: =W552*R552 | Y552: 0 | Z552: 2017 | AA552: Review | AB552: =IF(I552="shared-count-once",COUNTIFS($A$2:$A$807,A552,$C$2:$C$807,C552,$E$2:$E$807,E552,$B$2:$B$807,B552),1) | AC552: 2.9641403e+08 | AD552: =IF(AC552=0,"",U552/AC552) | AE552: =IF(AC552=0,"",V552/AC552) | AF552: =IF(AC552=0,"",W552/AC552) | AG552: =IF(AC552=0,"",X552/AC552)
A553: all_cascade_public_health | B553: public_health | C553: 2030 | D553: I_PH_TOBACCO_TAX | E553: COST_PH_TOB_TAX | F553: public_health|COST_PH_TOB_TAX | G553: Annual intersectoral policy implementation | I553: shared-count-once | J553: all | K553: 1 | L553: 1 | M553: 0.04 | N553: 3.0133589e+08 | O553: 3.0078424e+08 | P553: 1 | Q553: 0 | R553: =1/(1+'Calculation_Assumptions'!$B$5)^(C553-'Calculation_Assumptions'!$B$2) | S553: =N553*K553 | T553: =O553*K553 | U553: =T553*Q553*L553*M553 | V553: =S553*P553*L553*M553 | W553: =V553-U553 | X553: =W553*R553 | Y553: 0 | Z553: 2017 | AA553: Review | AB553: =IF(I553="shared-count-once",COUNTIFS($A$2:$A$807,A553,$C$2:$C$807,C553,$E$2:$E$807,E553,$B$2:$B$807,B553),1) | AC553: 2.982894e+08 | AD553: =IF(AC553=0,"",U553/AC553) | AE553: =IF(AC553=0,"",V553/AC553) | AF553: =IF(AC553=0,"",W553/AC553) | AG553: =IF(AC553=0,"",X553/AC553)
A554: all_cascade_public_health | B554: public_health | C554: 2031 | D554: I_PH_TOBACCO_TAX | E554: COST_PH_TOB_TAX | F554: public_health|COST_PH_TOB_TAX | G554: Annual intersectoral policy implementation | I554: shared-count-once | J554: all | K554: 1 | L554: 1 | M554: 0.04 | N554: 3.0314663e+08 | O554: 3.0256162e+08 | P554: 1 | Q554: 0 | R554: =1/(1+'Calculation_Assumptions'!$B$5)^(C554-'Calculation_Assumptions'!$B$2) | S554: =N554*K554 | T554: =O554*K554 | U554: =T554*Q554*L554*M554 | V554: =S554*P554*L554*M554 | W554: =V554-U554 | X554: =W554*R554 | Y554: 0 | Z554: 2017 | AA554: Review | AB554: =IF(I554="shared-count-once",COUNTIFS($A$2:$A$807,A554,$C$2:$C$807,C554,$E$2:$E$807,E554,$B$2:$B$807,B554),1) | AC554: 3.0011964e+08 | AD554: =IF(AC554=0,"",U554/AC554) | AE554: =IF(AC554=0,"",V554/AC554) | AF554: =IF(AC554=0,"",W554/AC554) | AG554: =IF(AC554=0,"",X554/AC554)
A555: all_cascade_public_health | B555: public_health | C555: 2032 | D555: I_PH_TOBACCO_TAX | E555: COST_PH_TOB_TAX | F555: public_health|COST_PH_TOB_TAX | G555: Annual intersectoral policy implementation | I555: shared-count-once | J555: all | K555: 1 | L555: 1 | M555: 0.04 | N555: 3.0490092e+08 | O555: 3.0429691e+08 | P555: 1 | Q555: 0 | R555: =1/(1+'Calculation_Assumptions'!$B$5)^(C555-'Calculation_Assumptions'!$B$2) | S555: =N555*K555 | T555: =O555*K555 | U555: =T555*Q555*L555*M555 | V555: =S555*P555*L555*M555 | W555: =V555-U555 | X555: =W555*R555 | Y555: 0 | Z555: 2017 | AA555: Review | AB555: =IF(I555="shared-count-once",COUNTIFS($A$2:$A$807,A555,$C$2:$C$807,C555,$E$2:$E$807,E555,$B$2:$B$807,B555),1) | AC555: 3.0190463e+08 | AD555: =IF(AC555=0,"",U555/AC555) | AE555: =IF(AC555=0,"",V555/AC555) | AF555: =IF(AC555=0,"",W555/AC555) | AG555: =IF(AC555=0,"",X555/AC555)
A556: all_cascade_public_health | B556: public_health | C556: 2033 | D556: I_PH_TOBACCO_TAX | E556: COST_PH_TOB_TAX | F556: public_health|COST_PH_TOB_TAX | G556: Annual intersectoral policy implementation | I556: shared-count-once | J556: all | K556: 1 | L556: 1 | M556: 0.04 | N556: 3.0661979e+08 | O556: 3.0599004e+08 | P556: 1 | Q556: 0 | R556: =1/(1+'Calculation_Assumptions'!$B$5)^(C556-'Calculation_Assumptions'!$B$2) | S556: =N556*K556 | T556: =O556*K556 | U556: =T556*Q556*L556*M556 | V556: =S556*P556*L556*M556 | W556: =V556-U556 | X556: =W556*R556 | Y556: 0 | Z556: 2017 | AA556: Review | AB556: =IF(I556="shared-count-once",COUNTIFS($A$2:$A$807,A556,$C$2:$C$807,C556,$E$2:$E$807,E556,$B$2:$B$807,B556),1) | AC556: 3.0364428e+08 | AD556: =IF(AC556=0,"",U556/AC556) | AE556: =IF(AC556=0,"",V556/AC556) | AF556: =IF(AC556=0,"",W556/AC556) | AG556: =IF(AC556=0,"",X556/AC556)
A557: all_cascade_public_health | B557: public_health | C557: 2034 | D557: I_PH_TOBACCO_TAX | E557: COST_PH_TOB_TAX | F557: public_health|COST_PH_TOB_TAX | G557: Annual intersectoral policy implementation | I557: shared-count-once | J557: all | K557: 1 | L557: 1 | M557: 0.04 | N557: 3.082972e+08 | O557: 3.0763553e+08 | P557: 1 | Q557: 0 | R557: =1/(1+'Calculation_Assumptions'!$B$5)^(C557-'Calculation_Assumptions'!$B$2) | S557: =N557*K557 | T557: =O557*K557 | U557: =T557*Q557*L557*M557 | V557: =S557*P557*L557*M557 | W557: =V557-U557 | X557: =W557*R557 | Y557: 0 | Z557: 2017 | AA557: Review | AB557: =IF(I557="shared-count-once",COUNTIFS($A$2:$A$807,A557,$C$2:$C$807,C557,$E$2:$E$807,E557,$B$2:$B$807,B557),1) | AC557: 3.0533254e+08 | AD557: =IF(AC557=0,"",U557/AC557) | AE557: =IF(AC557=0,"",V557/AC557) | AF557: =IF(AC557=0,"",W557/AC557) | AG557: =IF(AC557=0,"",X557/AC557)
A558: all_cascade_public_health | B558: public_health | C558: 2035 | D558: I_PH_TOBACCO_TAX | E558: COST_PH_TOB_TAX | F558: public_health|COST_PH_TOB_TAX | G558: Annual intersectoral policy implementation | I558: shared-count-once | J558: all | K558: 1 | L558: 1 | M558: 0.04 | N558: 3.0991059e+08 | O558: 3.0922818e+08 | P558: 1 | Q558: 0 | R558: =1/(1+'Calculation_Assumptions'!$B$5)^(C558-'Calculation_Assumptions'!$B$2) | S558: =N558*K558 | T558: =O558*K558 | U558: =T558*Q558*L558*M558 | V558: =S558*P558*L558*M558 | W558: =V558-U558 | X558: =W558*R558 | Y558: 0 | Z558: 2017 | AA558: Review | AB558: =IF(I558="shared-count-once",COUNTIFS($A$2:$A$807,A558,$C$2:$C$807,C558,$E$2:$E$807,E558,$B$2:$B$807,B558),1) | AC558: 3.0696465e+08 | AD558: =IF(AC558=0,"",U558/AC558) | AE558: =IF(AC558=0,"",V558/AC558) | AF558: =IF(AC558=0,"",W558/AC558) | AG558: =IF(AC558=0,"",X558/AC558)
A559: all_cascade_public_health | B559: public_health | C559: 2036 | D559: I_PH_TOBACCO_TAX | E559: COST_PH_TOB_TAX | F559: public_health|COST_PH_TOB_TAX | G559: Annual intersectoral policy implementation | I559: shared-count-once | J559: all | K559: 1 | L559: 1 | M559: 0.04 | N559: 3.1149663e+08 | O559: 3.1076948e+08 | P559: 1 | Q559: 0 | R559: =1/(1+'Calculation_Assumptions'!$B$5)^(C559-'Calculation_Assumptions'!$B$2) | S559: =N559*K559 | T559: =O559*K559 | U559: =T559*Q559*L559*M559 | V559: =S559*P559*L559*M559 | W559: =V559-U559 | X559: =W559*R559 | Y559: 0 | Z559: 2017 | AA559: Review | AB559: =IF(I559="shared-count-once",COUNTIFS($A$2:$A$807,A559,$C$2:$C$807,C559,$E$2:$E$807,E559,$B$2:$B$807,B559),1) | AC559: 3.0854277e+08 | AD559: =IF(AC559=0,"",U559/AC559) | AE559: =IF(AC559=0,"",V559/AC559) | AF559: =IF(AC559=0,"",W559/AC559) | AG559: =IF(AC559=0,"",X559/AC559)
... A703: S_70_30_30_TO_70_70_70_I_PH_TOBACCO_TAX | B703: cascade_70_30_30_to_70_70_70 | C703: 2050 | D703: I_CVD_PRIMARY | E703: COST_PRIMARY_TX_A | F703: cascade_70_30_30_to_70_70_70|COST_PRIMARY_TX_A | G703: Antihypertensives and statins for absolute CVD risk >20% | I703: shared-count-once | J703: all | K703: 0.06 | L703: 1 | M703: 69.3 | N703: 2.0466249e+08 | O703: 2.024798e+08 | P703: 0.4165 | Q703: 0.14506229 | R703: =1/(1+'Calculation_Assumptions'!$B$5)^(C703-'Calculation_Assumptions'!$B$2) | S703: =N703*K703 | T703: =O703*K703 | U703: =T703*Q703*L703*M703 | V703: =S703*P703*L703*M703 | W703: =V703-U703 | X703: =W703*R703 | Y703: 1 | Z703: 2023 | AA703: Review | AB703: =IF(I703="shared-count-once",COUNTIFS($A$2:$A$807,A703,$C$2:$C$807,C703,$E$2:$E$807,E703,$B$2:$B$807,B703),1) | AC703: 3.2331204e+08 | AD703: =IF(AC703=0,"",U703/AC703) | AE703: =IF(AC703=0,"",V703/AC703) | AF703: =IF(AC703=0,"",W703/AC703) | AG703: =IF(AC703=0,"",X703/AC703)
A704: S_70_30_30_TO_70_70_70_I_PH_TOBACCO_TAX | B704: cascade_70_30_30_to_70_70_70 | C704: 2025 | D704: I_T2D_TREATMENT | E704: COST_T2D_SCREEN | F704: cascade_70_30_30_to_70_70_70|COST_T2D_SCREEN | G704: Diabetes opportunistic screening | H704: dm2 | I704: cause-specific | J704: all | K704: 1e-05 | L704: 1 | M704: 0.70495848 | N704: 1.5575581e+08 | O704: 1.5509319e+08 | P704: 0.033768828 | Q704: 0.033768828 | R704: =1/(1+'Calculation_Assumptions'!$B$5)^(C704-'Calculation_Assumptions'!$B$2) | S704: =N704*K704 | T704: =O704*K704 | U704: =T704*Q704*L704*M704 | V704: =S704*P704*L704*M704 | W704: =V704-U704 | X704: =W704*R704 | Y704: 1 | Z704: 2023 | AA704: Ready | AB704: =IF(I704="shared-count-once",COUNTIFS($A$2:$A$807,A704,$C$2:$C$807,C704,$E$2:$E$807,E704,$B$2:$B$807,B704),1) | AC704: 2.8839191e+08 | AD704: =IF(AC704=0,"",U704/AC704) | AE704: =IF(AC704=0,"",V704/AC704) | AF704: =IF(AC704=0,"",W704/AC704) | AG704: =IF(AC704=0,"",X704/AC704)
A705: S_70_30_30_TO_70_70_70_I_PH_TOBACCO_TAX | B705: cascade_70_30_30_to_70_70_70 | C705: 2026 | D705: I_T2D_TREATMENT | E705: COST_T2D_SCREEN | F705: cascade_70_30_30_to_70_70_70|COST_T2D_SCREEN | G705: Diabetes opportunistic screening | H705: dm2 | I705: cause-specific | J705: all | K705: 1e-05 | L705: 1 | M705: 0.70495848 | N705: 1.5812016e+08 | O705: 1.5750383e+08 | P705: 0.054315063 | Q705: 0.033768828 | R705: =1/(1+'Calculation_Assumptions'!$B$5)^(C705-'Calculation_Assumptions'!$B$2) | S705: =N705*K705 | T705: =O705*K705 | U705: =T705*Q705*L705*M705 | V705: =S705*P705*L705*M705 | W705: =V705-U705 | X705: =W705*R705 | Y705: 1 | Z705: 2023 | AA705: Ready | AB705: =IF(I705="shared-count-once",COUNTIFS($A$2:$A$807,A705,$C$2:$C$807,C705,$E$2:$E$807,E705,$B$2:$B$807,B705),1) | AC705: 2.9047213e+08 | AD705: =IF(AC705=0,"",U705/AC705) | AE705: =IF(AC705=0,"",V705/AC705) | AF705: =IF(AC705=0,"",W705/AC705) | AG705: =IF(AC705=0,"",X705/AC705)
A706: S_70_30_30_TO_70_70_70_I_PH_TOBACCO_TAX | B706: cascade_70_30_30_to_70_70_70 | C706: 2027 | D706: I_T2D_TREATMENT | E706: COST_T2D_SCREEN | F706: cascade_70_30_30_to_70_70_70|COST_T2D_SCREEN | G706: Diabetes opportunistic screening | H706: dm2 | I706: cause-specific | J706: all | K706: 1e-05 | L706: 1 | M706: 0.70495848 | N706: 1.6051958e+08 | O706: 1.5995711e+08 | P706: 0.074861297 | Q706: 0.033768828 | R706: =1/(1+'Calculation_Assumptions'!$B$5)^(C706-'Calculation_Assumptions'!$B$2) | S706: =N706*K706 | T706: =O706*K706 | U706: =T706*Q706*L706*M706 | V706: =S706*P706*L706*M706 | W706: =V706-U706 | X706: =W706*R706 | Y706: 1 | Z706: 2023 | AA706: Ready | AB706: =IF(I706="shared-count-once",COUNTIFS($A$2:$A$807,A706,$C$2:$C$807,C706,$E$2:$E$807,E706,$B$2:$B$807,B706),1) | AC706: 2.9250508e+08 | AD706: =IF(AC706=0,"",U706/AC706) | AE706: =IF(AC706=0,"",V706/AC706) | AF706: =IF(AC706=0,"",W706/AC706) | AG706: =IF(AC706=0,"",X706/AC706)
A707: S_70_30_30_TO_70_70_70_I_PH_TOBACCO_TAX | B707: cascade_70_30_30_to_70_70_70 | C707: 2028 | D707: I_T2D_TREATMENT | E707: COST_T2D_SCREEN | F707: cascade_70_30_30_to_70_70_70|COST_T2D_SCREEN | G707: Diabetes opportunistic screening | H707: dm2 | I707: cause-specific | J707: all | K707: 1e-05 | L707: 1 | M707: 0.70495848 | N707: 1.6273731e+08 | O707: 1.6220434e+08 | P707: 0.095407531 | Q707: 0.033768828 | R707: =1/(1+'Calculation_Assumptions'!$B$5)^(C707-'Calculation_Assumptions'!$B$2) | S707: =N707*K707 | T707: =O707*K707 | U707: =T707*Q707*L707*M707 | V707: =S707*P707*L707*M707 | W707: =V707-U707 | X707: =W707*R707 | Y707: 1 | Z707: 2023 | AA707: Ready | AB707: =IF(I707="shared-count-once",COUNTIFS($A$2:$A$807,A707,$C$2:$C$807,C707,$E$2:$E$807,E707,$B$2:$B$807,B707),1) | AC707: 2.9448471e+08 | AD707: =IF(AC707=0,"",U707/AC707) | AE707: =IF(AC707=0,"",V707/AC707) | AF707: =IF(AC707=0,"",W707/AC707) | AG707: =IF(AC707=0,"",X707/AC707)
A708: S_70_30_30_TO_70_70_70_I_PH_TOBACCO_TAX | B708: cascade_70_30_30_to_70_70_70 | C708: 2029 | D708: I_T2D_TREATMENT | E708: COST_T2D_SCREEN | F708: cascade_70_30_30_to_70_70_70|COST_T2D_SCREEN | G708: Diabetes opportunistic screening | H708: dm2 | I708: cause-specific | J708: all | K708: 1e-05 | L708: 1 | M708: 0.70495848 | N708: 1.6486559e+08 | O708: 1.6435451e+08 | P708: 0.11595377 | Q708: 0.033768828 | R708: =1/(1+'Calculation_Assumptions'!$B$5)^(C708-'Calculation_Assumptions'!$B$2) | S708: =N708*K708 | T708: =O708*K708 | U708: =T708*Q708*L708*M708 | V708: =S708*P708*L708*M708 | W708: =V708-U708 | X708: =W708*R708 | Y708: 1 | Z708: 2023 | AA708: Ready | AB708: =IF(I708="shared-count-once",COUNTIFS($A$2:$A$807,A708,$C$2:$C$807,C708,$E$2:$E$807,E708,$B$2:$B$807,B708),1) | AC708: 2.9641403e+08 | AD708: =IF(AC708=0,"",U708/AC708) | AE708: =IF(AC708=0,"",V708/AC708) | AF708: =IF(AC708=0,"",W708/AC708) | AG708: =IF(AC708=0,"",X708/AC708)
A709: S_70_30_30_TO_70_70_70_I_PH_TOBACCO_TAX | B709: cascade_70_30_30_to_70_70_70 | C709: 2030 | D709: I_T2D_TREATMENT | E709: COST_T2D_SCREEN | F709: cascade_70_30_30_to_70_70_70|COST_T2D_SCREEN | G709: Diabetes opportunistic screening | H709: dm2 | I709: cause-specific | J709: all | K709: 1e-05 | L709: 1 | M709: 0.70495848 | N709: 1.6693285e+08 | O709: 1.6641555e+08 | P709: 0.1365 | Q709: 0.033768828 | R709: =1/(1+'Calculation_Assumptions'!$B$5)^(C709-'Calculation_Assumptions'!$B$2) | S709: =N709*K709 | T709: =O709*K709 | U709: =T709*Q709*L709*M709 | V709: =S709*P709*L709*M709 | W709: =V709-U709 | X709: =W709*R709 | Y709: 1 | Z709: 2023 | AA709: Ready | AB709: =IF(I709="shared-count-once",COUNTIFS($A$2:$A$807,A709,$C$2:$C$807,C709,$E$2:$E$807,E709,$B$2:$B$807,B709),1) | AC709: 2.982894e+08 | AD709: =IF(AC709=0,"",U709/AC709) | AE709: =IF(AC709=0,"",V709/AC709) | AF709: =IF(AC709=0,"",W709/AC709) | AG709: =IF(AC709=0,"",X709/AC709)
A710: S_70_30_30_TO_70_70_70_I_PH_TOBACCO_TAX | B710: cascade_70_30_30_to_70_70_70 | C710: 2031 | D710: I_T2D_TREATMENT | E710: COST_T2D_SCREEN | F710: cascade_70_30_30_to_70_70_70|COST_T2D_SCREEN | G710: Diabetes opportunistic screening | H710: dm2 | I710: cause-specific | J710: all | K710: 1e-05 | L710: 1 | M710: 0.70495848 | N710: 1.6897808e+08 | O710: 1.6846129e+08 | P710: 0.1645 | Q710: 0.033768828 | R710: =1/(1+'Calculation_Assumptions'!$B$5)^(C710-'Calculation_Assumptions'!$B$2) | S710: =N710*K710 | T710: =O710*K710 | U710: =T710*Q710*L710*M710 | V710: =S710*P710*L710*M710 | W710: =V710-U710 | X710: =W710*R710 | Y710: 1 | Z710: 2023 | AA710: Ready | AB710: =IF(I710="shared-count-once",COUNTIFS($A$2:$A$807,A710,$C$2:$C$807,C710,$E$2:$E$807,E710,$B$2:$B$807,B710),1) | AC710: 3.0011964e+08 | AD710: =IF(AC710=0,"",U710/AC710) | AE710: =IF(AC710=0,"",V710/AC710) | AF710: =IF(AC710=0,"",W710/AC710) | AG710: =IF(AC710=0,"",X710/AC710)
A711: S_70_30_30_TO_70_70_70_I_PH_TOBACCO_TAX | B711: cascade_70_30_30_to_70_70_70 | C711: 2032 | D711: I_T2D_TREATMENT | E711: COST_T2D_SCREEN | F711: cascade_70_30_30_to_70_70_70|COST_T2D_SCREEN | G711: Diabetes opportunistic screening | H711: dm2 | I711: cause-specific | J711: all | K711: 1e-05 | L711: 1 | M711: 0.70495848 | N711: 1.7099597e+08 | O711: 1.7047662e+08 | P711: 0.1925 | Q711: 0.033768828 | R711: =1/(1+'Calculation_Assumptions'!$B$5)^(C711-'Calculation_Assumptions'!$B$2) | S711: =N711*K711 | T711: =O711*K711 | U711: =T711*Q711*L711*M711 | V711: =S711*P711*L711*M711 | W711: =V711-U711 | X711: =W711*R711 | Y711: 1 | Z711: 2023 | AA711: Ready | AB711: =IF(I711="shared-count-once",COUNTIFS($A$2:$A$807,A711,$C$2:$C$807,C711,$E$2:$E$807,E711,$B$2:$B$807,B711),1) | AC711: 3.0190463e+08 | AD711: =IF(AC711=0,"",U711/AC711) | AE711: =IF(AC711=0,"",V711/AC711) | AF711: =IF(AC711=0,"",W711/AC711) | AG711: =IF(AC711=0,"",X711/AC711)
A712: S_70_30_30_TO_70_70_70_I_PH_TOBACCO_TAX | B712: cascade_70_30_30_to_70_70_70 | C712: 2033 | D712: I_T2D_TREATMENT | E712: COST_T2D_SCREEN | F712: cascade_70_30_30_to_70_70_70|COST_T2D_SCREEN | G712: Diabetes opportunistic screening | H712: dm2 | I712: cause-specific | J712: all | K712: 1e-05 | L712: 1 | M712: 0.70495848 | N712: 1.7298942e+08 | O712: 1.7246151e+08 | P712: 0.2205 | Q712: 0.033768828 | R712: =1/(1+'Calculation_Assumptions'!$B$5)^(C712-'Calculation_Assumptions'!$B$2) | S712: =N712*K712 | T712: =O712*K712 | U712: =T712*Q712*L712*M712 | V712: =S712*P712*L712*M712 | W712: =V712-U712 | X712: =W712*R712 | Y712: 1 | Z712: 2023 | AA712: Ready | AB712: =IF(I712="shared-count-once",COUNTIFS($A$2:$A$807,A712,$C$2:$C$807,C712,$E$2:$E$807,E712,$B$2:$B$807,B712),1) | AC712: 3.0364428e+08 | AD712: =IF(AC712=0,"",U712/AC712) | AE712: =IF(AC712=0,"",V712/AC712) | AF712: =IF(AC712=0,"",W712/AC712) | AG712: =IF(AC712=0,"",X712/AC712)
A713: S_70_30_30_TO_70_70_70_I_PH_TOBACCO_TAX | B713: cascade_70_30_30_to_70_70_70 | C713: 2034 | D713: I_T2D_TREATMENT | E713: COST_T2D_SCREEN | F713: cascade_70_30_30_to_70_70_70|COST_T2D_SCREEN | G713: Diabetes opportunistic screening | H713: dm2 | I713: cause-specific | J713: all | K713: 1e-05 | L713: 1 | M713: 0.70495848 | N713: 1.7500443e+08 | O713: 1.7446169e+08 | P713: 0.2485 | Q713: 0.033768828 | R713: =1/(1+'Calculation_Assumptions'!$B$5)^(C713-'Calculation_Assumptions'!$B$2) | S713: =N713*K713 | T713: =O713*K713 | U713: =T713*Q713*L713*M713 | V713: =S713*P713*L713*M713 | W713: =V713-U713 | X713: =W713*R713 | Y713: 1 | Z713: 2023 | AA713: Ready | AB713: =IF(I713="shared-count-once",COUNTIFS($A$2:$A$807,A713,$C$2:$C$807,C713,$E$2:$E$807,E713,$B$2:$B$807,B713),1) | AC713: 3.0533254e+08 | AD713: =IF(AC713=0,"",U713/AC713) | AE713: =IF(AC713=0,"",V713/AC713) | AF713: =IF(AC713=0,"",W713/AC713) | AG713: =IF(AC713=0,"",X713/AC713)
A714: S_70_30_30_TO_70_70_70_I_PH_TOBACCO_TAX | B714: cascade_70_30_30_to_70_70_70 | C714: 2035 | D714: I_T2D_TREATMENT | E714: COST_T2D_SCREEN | F714: cascade_70_30_30_to_70_70_70|COST_T2D_SCREEN | G714: Diabetes opportunistic screening | H714: dm2 | I714: cause-specific | J714: all | K714: 1e-05 | L714: 1 | M714: 0.70495848 | N714: 1.7710313e+08 | O714: 1.7653877e+08 | P714: 0.2765 | Q714: 0.033768828 | R714: =1/(1+'Calculation_Assumptions'!$B$5)^(C714-'Calculation_Assumptions'!$B$2) | S714: =N714*K714 | T714: =O714*K714 | U714: =T714*Q714*L714*M714 | V714: =S714*P714*L714*M714 | W714: =V714-U714 | X714: =W714*R714 | Y714: 1 | Z714: 2023 | AA714: Ready | AB714: =IF(I714="shared-count-once",COUNTIFS($A$2:$A$807,A714,$C$2:$C$807,C714,$E$2:$E$807,E714,$B$2:$B$807,B714),1) | AC714: 3.0696465e+08 | AD714: =IF(AC714=0,"",U714/AC714) | AE714: =IF(AC714=0,"",V714/AC714) | AF714: =IF(AC714=0,"",W714/AC714) | AG714: =IF(AC714=0,"",X714/AC714)
A715: S_70_30_30_TO_70_70_70_I_PH_TOBACCO_TAX | B715: cascade_70_30_30_to_70_70_70 | C715: 2036 | D715: I_T2D_TREATMENT | E715: COST_T2D_SCREEN | F715: cascade_70_30_30_to_70_70_70|COST_T2D_SCREEN | G715: Diabetes opportunistic screening | H715: dm2 | I715: cause-specific | J715: all | K715: 1e-05 | L715: 1 | M715: 0.70495848 | N715: 1.7921755e+08 | O715: 1.7862366e+08 | P715: 0.3045 | Q715: 0.033768828 | R715: =1/(1+'Calculation_Assumptions'!$B$5)^(C715-'Calculation_Assumptions'!$B$2) | S715: =N715*K715 | T715: =O715*K715 | U715: =T715*Q715*L715*M715 | V715: =S715*P715*L715*M715 | W715: =V715-U715 | X715: =W715*R715 | Y715: 1 | Z715: 2023 | AA715: Ready | AB715: =IF(I715="shared-count-once",COUNTIFS($A$2:$A$807,A715,$C$2:$C$807,C715,$E$2:$E$807,E715,$B$2:$B$807,B715),1) | AC715: 3.0854277e+08 | AD715: =IF(AC715=0,"",U715/AC715) | AE715: =IF(AC715=0,"",V715/AC715) | AF715: =IF(AC715=0,"",W715/AC715) | AG715: =IF(AC715=0,"",X715/AC715)
... A781: S_70_30_30_TO_70_70_70_I_PH_TOBACCO_TAX | B781: cascade_70_30_30_to_70_70_70 | C781: 2050 | D781: I_T2D_TREATMENT | E781: COST_T2D_INSULIN | F781: cascade_70_30_30_to_70_70_70|COST_T2D_INSULIN | G781: Diabetes management, insulin dependent | H781: dm2 | I781: cause-specific | J781: prevalence | K781: 0.2 | L781: 1 | M781: 82.68 | N781: 24972888 | O781: 25030421 | P781: 0.4165 | Q781: 0.033768828 | R781: =1/(1+'Calculation_Assumptions'!$B$5)^(C781-'Calculation_Assumptions'!$B$2) | S781: =N781*K781 | T781: =O781*K781 | U781: =T781*Q781*L781*M781 | V781: =S781*P781*L781*M781 | W781: =V781-U781 | X781: =W781*R781 | Y781: 1 | Z781: 2023 | AA781: Ready | AB781: =IF(I781="shared-count-once",COUNTIFS($A$2:$A$807,A781,$C$2:$C$807,C781,$E$2:$E$807,E781,$B$2:$B$807,B781),1) | AC781: 3.2331204e+08 | AD781: =IF(AC781=0,"",U781/AC781) | AE781: =IF(AC781=0,"",V781/AC781) | AF781: =IF(AC781=0,"",W781/AC781) | AG781: =IF(AC781=0,"",X781/AC781)
A782: S_70_30_30_TO_70_70_70_I_PH_TOBACCO_TAX | B782: public_health | C782: 2025 | D782: I_PH_TOBACCO_TAX | E782: COST_PH_TOB_TAX | F782: public_health|COST_PH_TOB_TAX | G782: Annual intersectoral policy implementation | I782: shared-count-once | J782: all | K782: 1 | L782: 1 | M782: 0.04 | N782: 2.9188657e+08 | O782: 2.9122395e+08 | P782: 0 | Q782: 0 | R782: =1/(1+'Calculation_Assumptions'!$B$5)^(C782-'Calculation_Assumptions'!$B$2) | S782: =N782*K782 | T782: =O782*K782 | U782: =T782*Q782*L782*M782 | V782: =S782*P782*L782*M782 | W782: =V782-U782 | X782: =W782*R782 | Y782: 0 | Z782: 2017 | AA782: Review | AB782: =IF(I782="shared-count-once",COUNTIFS($A$2:$A$807,A782,$C$2:$C$807,C782,$E$2:$E$807,E782,$B$2:$B$807,B782),1) | AC782: 2.8839191e+08 | AD782: =IF(AC782=0,"",U782/AC782) | AE782: =IF(AC782=0,"",V782/AC782) | AF782: =IF(AC782=0,"",W782/AC782) | AG782: =IF(AC782=0,"",X782/AC782)
A783: S_70_30_30_TO_70_70_70_I_PH_TOBACCO_TAX | B783: public_health | C783: 2026 | D783: I_PH_TOBACCO_TAX | E783: COST_PH_TOB_TAX | F783: public_health|COST_PH_TOB_TAX | G783: Annual intersectoral policy implementation | I783: shared-count-once | J783: all | K783: 1 | L783: 1 | M783: 0.04 | N783: 2.9382881e+08 | O783: 2.9321247e+08 | P783: 0.33333333 | Q783: 0 | R783: =1/(1+'Calculation_Assumptions'!$B$5)^(C783-'Calculation_Assumptions'!$B$2) | S783: =N783*K783 | T783: =O783*K783 | U783: =T783*Q783*L783*M783 | V783: =S783*P783*L783*M783 | W783: =V783-U783 | X783: =W783*R783 | Y783: 0 | Z783: 2017 | AA783: Review | AB783: =IF(I783="shared-count-once",COUNTIFS($A$2:$A$807,A783,$C$2:$C$807,C783,$E$2:$E$807,E783,$B$2:$B$807,B783),1) | AC783: 2.9047213e+08 | AD783: =IF(AC783=0,"",U783/AC783) | AE783: =IF(AC783=0,"",V783/AC783) | AF783: =IF(AC783=0,"",W783/AC783) | AG783: =IF(AC783=0,"",X783/AC783)
A784: S_70_30_30_TO_70_70_70_I_PH_TOBACCO_TAX | B784: public_health | C784: 2027 | D784: I_PH_TOBACCO_TAX | E784: COST_PH_TOB_TAX | F784: public_health|COST_PH_TOB_TAX | G784: Annual intersectoral policy implementation | I784: shared-count-once | J784: all | K784: 1 | L784: 1 | M784: 0.04 | N784: 2.9575863e+08 | O784: 2.9519612e+08 | P784: 0.66666667 | Q784: 0 | R784: =1/(1+'Calculation_Assumptions'!$B$5)^(C784-'Calculation_Assumptions'!$B$2) | S784: =N784*K784 | T784: =O784*K784 | U784: =T784*Q784*L784*M784 | V784: =S784*P784*L784*M784 | W784: =V784-U784 | X784: =W784*R784 | Y784: 0 | Z784: 2017 | AA784: Review | AB784: =IF(I784="shared-count-once",COUNTIFS($A$2:$A$807,A784,$C$2:$C$807,C784,$E$2:$E$807,E784,$B$2:$B$807,B784),1) | AC784: 2.9250508e+08 | AD784: =IF(AC784=0,"",U784/AC784) | AE784: =IF(AC784=0,"",V784/AC784) | AF784: =IF(AC784=0,"",W784/AC784) | AG784: =IF(AC784=0,"",X784/AC784)
A785: S_70_30_30_TO_70_70_70_I_PH_TOBACCO_TAX | B785: public_health | C785: 2028 | D785: I_PH_TOBACCO_TAX | E785: COST_PH_TOB_TAX | F785: public_health|COST_PH_TOB_TAX | G785: Annual intersectoral policy implementation | I785: shared-count-once | J785: all | K785: 1 | L785: 1 | M785: 0.04 | N785: 2.9764104e+08 | O785: 2.9710793e+08 | P785: 1 | Q785: 0 | R785: =1/(1+'Calculation_Assumptions'!$B$5)^(C785-'Calculation_Assumptions'!$B$2) | S785: =N785*K785 | T785: =O785*K785 | U785: =T785*Q785*L785*M785 | V785: =S785*P785*L785*M785 | W785: =V785-U785 | X785: =W785*R785 | Y785: 0 | Z785: 2017 | AA785: Review | AB785: =IF(I785="shared-count-once",COUNTIFS($A$2:$A$807,A785,$C$2:$C$807,C785,$E$2:$E$807,E785,$B$2:$B$807,B785),1) | AC785: 2.9448471e+08 | AD785: =IF(AC785=0,"",U785/AC785) | AE785: =IF(AC785=0,"",V785/AC785) | AF785: =IF(AC785=0,"",W785/AC785) | AG785: =IF(AC785=0,"",X785/AC785)
A786: S_70_30_30_TO_70_70_70_I_PH_TOBACCO_TAX | B786: public_health | C786: 2029 | D786: I_PH_TOBACCO_TAX | E786: COST_PH_TOB_TAX | F786: public_health|COST_PH_TOB_TAX | G786: Annual intersectoral policy implementation | I786: shared-count-once | J786: all | K786: 1 | L786: 1 | M786: 0.04 | N786: 2.9949249e+08 | O786: 2.9898117e+08 | P786: 1 | Q786: 0 | R786: =1/(1+'Calculation_Assumptions'!$B$5)^(C786-'Calculation_Assumptions'!$B$2) | S786: =N786*K786 | T786: =O786*K786 | U786: =T786*Q786*L786*M786 | V786: =S786*P786*L786*M786 | W786: =V786-U786 | X786: =W786*R786 | Y786: 0 | Z786: 2017 | AA786: Review | AB786: =IF(I786="shared-count-once",COUNTIFS($A$2:$A$807,A786,$C$2:$C$807,C786,$E$2:$E$807,E786,$B$2:$B$807,B786),1) | AC786: 2.9641403e+08 | AD786: =IF(AC786=0,"",U786/AC786) | AE786: =IF(AC786=0,"",V786/AC786) | AF786: =IF(AC786=0,"",W786/AC786) | AG786: =IF(AC786=0,"",X786/AC786)
A787: S_70_30_30_TO_70_70_70_I_PH_TOBACCO_TAX | B787: public_health | C787: 2030 | D787: I_PH_TOBACCO_TAX | E787: COST_PH_TOB_TAX | F787: public_health|COST_PH_TOB_TAX | G787: Annual intersectoral policy implementation | I787: shared-count-once | J787: all | K787: 1 | L787: 1 | M787: 0.04 | N787: 3.013019e+08 | O787: 3.0078424e+08 | P787: 1 | Q787: 0 | R787: =1/(1+'Calculation_Assumptions'!$B$5)^(C787-'Calculation_Assumptions'!$B$2) | S787: =N787*K787 | T787: =O787*K787 | U787: =T787*Q787*L787*M787 | V787: =S787*P787*L787*M787 | W787: =V787-U787 | X787: =W787*R787 | Y787: 0 | Z787: 2017 | AA787: Review | AB787: =IF(I787="shared-count-once",COUNTIFS($A$2:$A$807,A787,$C$2:$C$807,C787,$E$2:$E$807,E787,$B$2:$B$807,B787),1) | AC787: 2.982894e+08 | AD787: =IF(AC787=0,"",U787/AC787) | AE787: =IF(AC787=0,"",V787/AC787) | AF787: =IF(AC787=0,"",W787/AC787) | AG787: =IF(AC787=0,"",X787/AC787)
A788: S_70_30_30_TO_70_70_70_I_PH_TOBACCO_TAX | B788: public_health | C788: 2031 | D788: I_PH_TOBACCO_TAX | E788: COST_PH_TOB_TAX | F788: public_health|COST_PH_TOB_TAX | G788: Annual intersectoral policy implementation | I788: shared-count-once | J788: all | K788: 1 | L788: 1 | M788: 0.04 | N788: 3.0307887e+08 | O788: 3.0256162e+08 | P788: 1 | Q788: 0 | R788: =1/(1+'Calculation_Assumptions'!$B$5)^(C788-'Calculation_Assumptions'!$B$2) | S788: =N788*K788 | T788: =O788*K788 | U788: =T788*Q788*L788*M788 | V788: =S788*P788*L788*M788 | W788: =V788-U788 | X788: =W788*R788 | Y788: 0 | Z788: 2017 | AA788: Review | AB788: =IF(I788="shared-count-once",COUNTIFS($A$2:$A$807,A788,$C$2:$C$807,C788,$E$2:$E$807,E788,$B$2:$B$807,B788),1) | AC788: 3.0011964e+08 | AD788: =IF(AC788=0,"",U788/AC788) | AE788: =IF(AC788=0,"",V788/AC788) | AF788: =IF(AC788=0,"",W788/AC788) | AG788: =IF(AC788=0,"",X788/AC788)
A789: S_70_30_30_TO_70_70_70_I_PH_TOBACCO_TAX | B789: public_health | C789: 2032 | D789: I_PH_TOBACCO_TAX | E789: COST_PH_TOB_TAX | F789: public_health|COST_PH_TOB_TAX | G789: Annual intersectoral policy implementation | I789: shared-count-once | J789: all | K789: 1 | L789: 1 | M789: 0.04 | N789: 3.0481677e+08 | O789: 3.0429691e+08 | P789: 1 | Q789: 0 | R789: =1/(1+'Calculation_Assumptions'!$B$5)^(C789-'Calculation_Assumptions'!$B$2) | S789: =N789*K789 | T789: =O789*K789 | U789: =T789*Q789*L789*M789 | V789: =S789*P789*L789*M789 | W789: =V789-U789 | X789: =W789*R789 | Y789: 0 | Z789: 2017 | AA789: Review | AB789: =IF(I789="shared-count-once",COUNTIFS($A$2:$A$807,A789,$C$2:$C$807,C789,$E$2:$E$807,E789,$B$2:$B$807,B789),1) | AC789: 3.0190463e+08 | AD789: =IF(AC789=0,"",U789/AC789) | AE789: =IF(AC789=0,"",V789/AC789) | AF789: =IF(AC789=0,"",W789/AC789) | AG789: =IF(AC789=0,"",X789/AC789)
A790: S_70_30_30_TO_70_70_70_I_PH_TOBACCO_TAX | B790: public_health | C790: 2033 | D790: I_PH_TOBACCO_TAX | E790: COST_PH_TOB_TAX | F790: public_health|COST_PH_TOB_TAX | G790: Annual intersectoral policy implementation | I790: shared-count-once | J790: all | K790: 1 | L790: 1 | M790: 0.04 | N790: 3.0651852e+08 | O790: 3.0599004e+08 | P790: 1 | Q790: 0 | R790: =1/(1+'Calculation_Assumptions'!$B$5)^(C790-'Calculation_Assumptions'!$B$2) | S790: =N790*K790 | T790: =O790*K790 | U790: =T790*Q790*L790*M790 | V790: =S790*P790*L790*M790 | W790: =V790-U790 | X790: =W790*R790 | Y790: 0 | Z790: 2017 | AA790: Review | AB790: =IF(I790="shared-count-once",COUNTIFS($A$2:$A$807,A790,$C$2:$C$807,C790,$E$2:$E$807,E790,$B$2:$B$807,B790),1) | AC790: 3.0364428e+08 | AD790: =IF(AC790=0,"",U790/AC790) | AE790: =IF(AC790=0,"",V790/AC790) | AF790: =IF(AC790=0,"",W790/AC790) | AG790: =IF(AC790=0,"",X790/AC790)
A791: S_70_30_30_TO_70_70_70_I_PH_TOBACCO_TAX | B791: public_health | C791: 2034 | D791: I_PH_TOBACCO_TAX | E791: COST_PH_TOB_TAX | F791: public_health|COST_PH_TOB_TAX | G791: Annual intersectoral policy implementation | I791: shared-count-once | J791: all | K791: 1 | L791: 1 | M791: 0.04 | N791: 3.0817887e+08 | O791: 3.0763553e+08 | P791: 1 | Q791: 0 | R791: =1/(1+'Calculation_Assumptions'!$B$5)^(C791-'Calculation_Assumptions'!$B$2) | S791: =N791*K791 | T791: =O791*K791 | U791: =T791*Q791*L791*M791 | V791: =S791*P791*L791*M791 | W791: =V791-U791 | X791: =W791*R791 | Y791: 0 | Z791: 2017 | AA791: Review | AB791: =IF(I791="shared-count-once",COUNTIFS($A$2:$A$807,A791,$C$2:$C$807,C791,$E$2:$E$807,E791,$B$2:$B$807,B791),1) | AC791: 3.0533254e+08 | AD791: =IF(AC791=0,"",U791/AC791) | AE791: =IF(AC791=0,"",V791/AC791) | AF791: =IF(AC791=0,"",W791/AC791) | AG791: =IF(AC791=0,"",X791/AC791)
A792: S_70_30_30_TO_70_70_70_I_PH_TOBACCO_TAX | B792: public_health | C792: 2035 | D792: I_PH_TOBACCO_TAX | E792: COST_PH_TOB_TAX | F792: public_health|COST_PH_TOB_TAX | G792: Annual intersectoral policy implementation | I792: shared-count-once | J792: all | K792: 1 | L792: 1 | M792: 0.04 | N792: 3.0979317e+08 | O792: 3.0922818e+08 | P792: 1 | Q792: 0 | R792: =1/(1+'Calculation_Assumptions'!$B$5)^(C792-'Calculation_Assumptions'!$B$2) | S792: =N792*K792 | T792: =O792*K792 | U792: =T792*Q792*L792*M792 | V792: =S792*P792*L792*M792 | W792: =V792-U792 | X792: =W792*R792 | Y792: 0 | Z792: 2017 | AA792: Review | AB792: =IF(I792="shared-count-once",COUNTIFS($A$2:$A$807,A792,$C$2:$C$807,C792,$E$2:$E$807,E792,$B$2:$B$807,B792),1) | AC792: 3.0696465e+08 | AD792: =IF(AC792=0,"",U792/AC792) | AE792: =IF(AC792=0,"",V792/AC792) | AF792: =IF(AC792=0,"",W792/AC792) | AG792: =IF(AC792=0,"",X792/AC792)
A793: S_70_30_30_TO_70_70_70_I_PH_TOBACCO_TAX | B793: public_health | C793: 2036 | D793: I_PH_TOBACCO_TAX | E793: COST_PH_TOB_TAX | F793: public_health|COST_PH_TOB_TAX | G793: Annual intersectoral policy implementation | I793: shared-count-once | J793: all | K793: 1 | L793: 1 | M793: 0.04 | N793: 3.1136398e+08 | O793: 3.1076948e+08 | P793: 1 | Q793: 0 | R793: =1/(1+'Calculation_Assumptions'!$B$5)^(C793-'Calculation_Assumptions'!$B$2) | S793: =N793*K793 | T793: =O793*K793 | U793: =T793*Q793*L793*M793 | V793: =S793*P793*L793*M793 | W793: =V793-U793 | X793: =W793*R793 | Y793: 0 | Z793: 2017 | AA793: Review | AB793: =IF(I793="shared-count-once",COUNTIFS($A$2:$A$807,A793,$C$2:$C$807,C793,$E$2:$E$807,E793,$B$2:$B$807,B793),1) | AC793: 3.0854277e+08 | AD793: =IF(AC793=0,"",U793/AC793) | AE793: =IF(AC793=0,"",V793/AC793) | AF793: =IF(AC793=0,"",W793/AC793) | AG793: =IF(AC793=0,"",X793/AC793)
... A807: S_70_30_30_TO_70_70_70_I_PH_TOBACCO_TAX | B807: public_health | C807: 2050 | D807: I_PH_TOBACCO_TAX | E807: COST_PH_TOB_TAX | F807: public_health|COST_PH_TOB_TAX | G807: Annual intersectoral policy implementation | I807: shared-count-once | J807: all | K807: 1 | L807: 1 | M807: 0.04 | N807: 3.2745436e+08 | O807: 3.2527129e+08 | P807: 1 | Q807: 0 | R807: =1/(1+'Calculation_Assumptions'!$B$5)^(C807-'Calculation_Assumptions'!$B$2) | S807: =N807*K807 | T807: =O807*K807 | U807: =T807*Q807*L807*M807 | V807: =S807*P807*L807*M807 | W807: =V807-U807 | X807: =W807*R807 | Y807: 0 | Z807: 2017 | AA807: Review | AB807: =IF(I807="shared-count-once",COUNTIFS($A$2:$A$807,A807,$C$2:$C$807,C807,$E$2:$E$807,E807,$B$2:$B$807,B807),1) | AC807: 3.2331204e+08 | AD807: =IF(AC807=0,"",U807/AC807) | AE807: =IF(AC807=0,"",V807/AC807) | AF807: =IF(AC807=0,"",W807/AC807) | AG807: =IF(AC807=0,"",X807/AC807)

Sheet Budget_Impact
A1: scenario | B1: year | C1: baseline_cost | D1: scenario_cost | E1: incremental_cost | F1: disc_incremental_cost | G1: cumulative_incremental_cost | H1: cumulative_disc_incremental_cost | I1: national_population | J1: baseline_cost_per_capita | K1: scenario_cost_per_capita | L1: incremental_cost_per_capita | M1: disc_incremental_cost_per_capita
A2: I_PH_TOBACCO_POLICY | B2: 2025 | C2: =SUMIFS('Annual_Cost'!$U$2:$U$807,'Annual_Cost'!$A$2:$A$807,A2,'Annual_Cost'!$C$2:$C$807,B2) | D2: =SUMIFS('Annual_Cost'!$V$2:$V$807,'Annual_Cost'!$A$2:$A$807,A2,'Annual_Cost'!$C$2:$C$807,B2) | E2: =SUMIFS('Annual_Cost'!$W$2:$W$807,'Annual_Cost'!$A$2:$A$807,A2,'Annual_Cost'!$C$2:$C$807,B2) | F2: =SUMIFS('Annual_Cost'!$X$2:$X$807,'Annual_Cost'!$A$2:$A$807,A2,'Annual_Cost'!$C$2:$C$807,B2) | G2: =SUMIFS($E$2:E2,$A$2:A2,A2) | H2: =SUMIFS($F$2:F2,$A$2:A2,A2) | I2: 2.8839191e+08 | J2: =IF(I2=0,"",C2/I2) | K2: =IF(I2=0,"",D2/I2) | L2: =IF(I2=0,"",E2/I2) | M2: =IF(I2=0,"",F2/I2)
A3: I_PH_TOBACCO_POLICY | B3: 2026 | C3: =SUMIFS('Annual_Cost'!$U$2:$U$807,'Annual_Cost'!$A$2:$A$807,A3,'Annual_Cost'!$C$2:$C$807,B3) | D3: =SUMIFS('Annual_Cost'!$V$2:$V$807,'Annual_Cost'!$A$2:$A$807,A3,'Annual_Cost'!$C$2:$C$807,B3) | E3: =SUMIFS('Annual_Cost'!$W$2:$W$807,'Annual_Cost'!$A$2:$A$807,A3,'Annual_Cost'!$C$2:$C$807,B3) | F3: =SUMIFS('Annual_Cost'!$X$2:$X$807,'Annual_Cost'!$A$2:$A$807,A3,'Annual_Cost'!$C$2:$C$807,B3) | G3: =SUMIFS($E$2:E3,$A$2:A3,A3) | H3: =SUMIFS($F$2:F3,$A$2:A3,A3) | I3: 2.9047213e+08 | J3: =IF(I3=0,"",C3/I3) | K3: =IF(I3=0,"",D3/I3) | L3: =IF(I3=0,"",E3/I3) | M3: =IF(I3=0,"",F3/I3)
A4: I_PH_TOBACCO_POLICY | B4: 2027 | C4: =SUMIFS('Annual_Cost'!$U$2:$U$807,'Annual_Cost'!$A$2:$A$807,A4,'Annual_Cost'!$C$2:$C$807,B4) | D4: =SUMIFS('Annual_Cost'!$V$2:$V$807,'Annual_Cost'!$A$2:$A$807,A4,'Annual_Cost'!$C$2:$C$807,B4) | E4: =SUMIFS('Annual_Cost'!$W$2:$W$807,'Annual_Cost'!$A$2:$A$807,A4,'Annual_Cost'!$C$2:$C$807,B4) | F4: =SUMIFS('Annual_Cost'!$X$2:$X$807,'Annual_Cost'!$A$2:$A$807,A4,'Annual_Cost'!$C$2:$C$807,B4) | G4: =SUMIFS($E$2:E4,$A$2:A4,A4) | H4: =SUMIFS($F$2:F4,$A$2:A4,A4) | I4: 2.9250508e+08 | J4: =IF(I4=0,"",C4/I4) | K4: =IF(I4=0,"",D4/I4) | L4: =IF(I4=0,"",E4/I4) | M4: =IF(I4=0,"",F4/I4)
A5: I_PH_TOBACCO_POLICY | B5: 2028 | C5: =SUMIFS('Annual_Cost'!$U$2:$U$807,'Annual_Cost'!$A$2:$A$807,A5,'Annual_Cost'!$C$2:$C$807,B5) | D5: =SUMIFS('Annual_Cost'!$V$2:$V$807,'Annual_Cost'!$A$2:$A$807,A5,'Annual_Cost'!$C$2:$C$807,B5) | E5: =SUMIFS('Annual_Cost'!$W$2:$W$807,'Annual_Cost'!$A$2:$A$807,A5,'Annual_Cost'!$C$2:$C$807,B5) | F5: =SUMIFS('Annual_Cost'!$X$2:$X$807,'Annual_Cost'!$A$2:$A$807,A5,'Annual_Cost'!$C$2:$C$807,B5) | G5: =SUMIFS($E$2:E5,$A$2:A5,A5) | H5: =SUMIFS($F$2:F5,$A$2:A5,A5) | I5: 2.9448471e+08 | J5: =IF(I5=0,"",C5/I5) | K5: =IF(I5=0,"",D5/I5) | L5: =IF(I5=0,"",E5/I5) | M5: =IF(I5=0,"",F5/I5)
A6: I_PH_TOBACCO_POLICY | B6: 2029 | C6: =SUMIFS('Annual_Cost'!$U$2:$U$807,'Annual_Cost'!$A$2:$A$807,A6,'Annual_Cost'!$C$2:$C$807,B6) | D6: =SUMIFS('Annual_Cost'!$V$2:$V$807,'Annual_Cost'!$A$2:$A$807,A6,'Annual_Cost'!$C$2:$C$807,B6) | E6: =SUMIFS('Annual_Cost'!$W$2:$W$807,'Annual_Cost'!$A$2:$A$807,A6,'Annual_Cost'!$C$2:$C$807,B6) | F6: =SUMIFS('Annual_Cost'!$X$2:$X$807,'Annual_Cost'!$A$2:$A$807,A6,'Annual_Cost'!$C$2:$C$807,B6) | G6: =SUMIFS($E$2:E6,$A$2:A6,A6) | H6: =SUMIFS($F$2:F6,$A$2:A6,A6) | I6: 2.9641403e+08 | J6: =IF(I6=0,"",C6/I6) | K6: =IF(I6=0,"",D6/I6) | L6: =IF(I6=0,"",E6/I6) | M6: =IF(I6=0,"",F6/I6)
A7: I_PH_TOBACCO_POLICY | B7: 2030 | C7: =SUMIFS('Annual_Cost'!$U$2:$U$807,'Annual_Cost'!$A$2:$A$807,A7,'Annual_Cost'!$C$2:$C$807,B7) | D7: =SUMIFS('Annual_Cost'!$V$2:$V$807,'Annual_Cost'!$A$2:$A$807,A7,'Annual_Cost'!$C$2:$C$807,B7) | E7: =SUMIFS('Annual_Cost'!$W$2:$W$807,'Annual_Cost'!$A$2:$A$807,A7,'Annual_Cost'!$C$2:$C$807,B7) | F7: =SUMIFS('Annual_Cost'!$X$2:$X$807,'Annual_Cost'!$A$2:$A$807,A7,'Annual_Cost'!$C$2:$C$807,B7) | G7: =SUMIFS($E$2:E7,$A$2:A7,A7) | H7: =SUMIFS($F$2:F7,$A$2:A7,A7) | I7: 2.982894e+08 | J7: =IF(I7=0,"",C7/I7) | K7: =IF(I7=0,"",D7/I7) | L7: =IF(I7=0,"",E7/I7) | M7: =IF(I7=0,"",F7/I7)
A8: I_PH_TOBACCO_POLICY | B8: 2031 | C8: =SUMIFS('Annual_Cost'!$U$2:$U$807,'Annual_Cost'!$A$2:$A$807,A8,'Annual_Cost'!$C$2:$C$807,B8) | D8: =SUMIFS('Annual_Cost'!$V$2:$V$807,'Annual_Cost'!$A$2:$A$807,A8,'Annual_Cost'!$C$2:$C$807,B8) | E8: =SUMIFS('Annual_Cost'!$W$2:$W$807,'Annual_Cost'!$A$2:$A$807,A8,'Annual_Cost'!$C$2:$C$807,B8) | F8: =SUMIFS('Annual_Cost'!$X$2:$X$807,'Annual_Cost'!$A$2:$A$807,A8,'Annual_Cost'!$C$2:$C$807,B8) | G8: =SUMIFS($E$2:E8,$A$2:A8,A8) | H8: =SUMIFS($F$2:F8,$A$2:A8,A8) | I8: 3.0011964e+08 | J8: =IF(I8=0,"",C8/I8) | K8: =IF(I8=0,"",D8/I8) | L8: =IF(I8=0,"",E8/I8) | M8: =IF(I8=0,"",F8/I8)
A9: I_PH_TOBACCO_POLICY | B9: 2032 | C9: =SUMIFS('Annual_Cost'!$U$2:$U$807,'Annual_Cost'!$A$2:$A$807,A9,'Annual_Cost'!$C$2:$C$807,B9) | D9: =SUMIFS('Annual_Cost'!$V$2:$V$807,'Annual_Cost'!$A$2:$A$807,A9,'Annual_Cost'!$C$2:$C$807,B9) | E9: =SUMIFS('Annual_Cost'!$W$2:$W$807,'Annual_Cost'!$A$2:$A$807,A9,'Annual_Cost'!$C$2:$C$807,B9) | F9: =SUMIFS('Annual_Cost'!$X$2:$X$807,'Annual_Cost'!$A$2:$A$807,A9,'Annual_Cost'!$C$2:$C$807,B9) | G9: =SUMIFS($E$2:E9,$A$2:A9,A9) | H9: =SUMIFS($F$2:F9,$A$2:A9,A9) | I9: 3.0190463e+08 | J9: =IF(I9=0,"",C9/I9) | K9: =IF(I9=0,"",D9/I9) | L9: =IF(I9=0,"",E9/I9) | M9: =IF(I9=0,"",F9/I9)
A10: I_PH_TOBACCO_POLICY | B10: 2033 | C10: =SUMIFS('Annual_Cost'!$U$2:$U$807,'Annual_Cost'!$A$2:$A$807,A10,'Annual_Cost'!$C$2:$C$807,B10) | D10: =SUMIFS('Annual_Cost'!$V$2:$V$807,'Annual_Cost'!$A$2:$A$807,A10,'Annual_Cost'!$C$2:$C$807,B10) | E10: =SUMIFS('Annual_Cost'!$W$2:$W$807,'Annual_Cost'!$A$2:$A$807,A10,'Annual_Cost'!$C$2:$C$807,B10) | F10: =SUMIFS('Annual_Cost'!$X$2:$X$807,'Annual_Cost'!$A$2:$A$807,A10,'Annual_Cost'!$C$2:$C$807,B10) | G10: =SUMIFS($E$2:E10,$A$2:A10,A10) | H10: =SUMIFS($F$2:F10,$A$2:A10,A10) | I10: 3.0364428e+08 | J10: =IF(I10=0,"",C10/I10) | K10: =IF(I10=0,"",D10/I10) | L10: =IF(I10=0,"",E10/I10) | M10: =IF(I10=0,"",F10/I10)
A11: I_PH_TOBACCO_POLICY | B11: 2034 | C11: =SUMIFS('Annual_Cost'!$U$2:$U$807,'Annual_Cost'!$A$2:$A$807,A11,'Annual_Cost'!$C$2:$C$807,B11) | D11: =SUMIFS('Annual_Cost'!$V$2:$V$807,'Annual_Cost'!$A$2:$A$807,A11,'Annual_Cost'!$C$2:$C$807,B11) | E11: =SUMIFS('Annual_Cost'!$W$2:$W$807,'Annual_Cost'!$A$2:$A$807,A11,'Annual_Cost'!$C$2:$C$807,B11) | F11: =SUMIFS('Annual_Cost'!$X$2:$X$807,'Annual_Cost'!$A$2:$A$807,A11,'Annual_Cost'!$C$2:$C$807,B11) | G11: =SUMIFS($E$2:E11,$A$2:A11,A11) | H11: =SUMIFS($F$2:F11,$A$2:A11,A11) | I11: 3.0533254e+08 | J11: =IF(I11=0,"",C11/I11) | K11: =IF(I11=0,"",D11/I11) | L11: =IF(I11=0,"",E11/I11) | M11: =IF(I11=0,"",F11/I11)
A12: I_PH_TOBACCO_POLICY | B12: 2035 | C12: =SUMIFS('Annual_Cost'!$U$2:$U$807,'Annual_Cost'!$A$2:$A$807,A12,'Annual_Cost'!$C$2:$C$807,B12) | D12: =SUMIFS('Annual_Cost'!$V$2:$V$807,'Annual_Cost'!$A$2:$A$807,A12,'Annual_Cost'!$C$2:$C$807,B12) | E12: =SUMIFS('Annual_Cost'!$W$2:$W$807,'Annual_Cost'!$A$2:$A$807,A12,'Annual_Cost'!$C$2:$C$807,B12) | F12: =SUMIFS('Annual_Cost'!$X$2:$X$807,'Annual_Cost'!$A$2:$A$807,A12,'Annual_Cost'!$C$2:$C$807,B12) | G12: =SUMIFS($E$2:E12,$A$2:A12,A12) | H12: =SUMIFS($F$2:F12,$A$2:A12,A12) | I12: 3.0696465e+08 | J12: =IF(I12=0,"",C12/I12) | K12: =IF(I12=0,"",D12/I12) | L12: =IF(I12=0,"",E12/I12) | M12: =IF(I12=0,"",F12/I12)
A13: I_PH_TOBACCO_POLICY | B13: 2036 | C13: =SUMIFS('Annual_Cost'!$U$2:$U$807,'Annual_Cost'!$A$2:$A$807,A13,'Annual_Cost'!$C$2:$C$807,B13) | D13: =SUMIFS('Annual_Cost'!$V$2:$V$807,'Annual_Cost'!$A$2:$A$807,A13,'Annual_Cost'!$C$2:$C$807,B13) | E13: =SUMIFS('Annual_Cost'!$W$2:$W$807,'Annual_Cost'!$A$2:$A$807,A13,'Annual_Cost'!$C$2:$C$807,B13) | F13: =SUMIFS('Annual_Cost'!$X$2:$X$807,'Annual_Cost'!$A$2:$A$807,A13,'Annual_Cost'!$C$2:$C$807,B13) | G13: =SUMIFS($E$2:E13,$A$2:A13,A13) | H13: =SUMIFS($F$2:F13,$A$2:A13,A13) | I13: 3.0854277e+08 | J13: =IF(I13=0,"",C13/I13) | K13: =IF(I13=0,"",D13/I13) | L13: =IF(I13=0,"",E13/I13) | M13: =IF(I13=0,"",F13/I13)
... A235: all_public_health | B235: 2050 | C235: =SUMIFS('Annual_Cost'!$U$2:$U$807,'Annual_Cost'!$A$2:$A$807,A235,'Annual_Cost'!$C$2:$C$807,B235) | D235: =SUMIFS('Annual_Cost'!$V$2:$V$807,'Annual_Cost'!$A$2:$A$807,A235,'Annual_Cost'!$C$2:$C$807,B235) | E235: =SUMIFS('Annual_Cost'!$W$2:$W$807,'Annual_Cost'!$A$2:$A$807,A235,'Annual_Cost'!$C$2:$C$807,B235) | F235: =SUMIFS('Annual_Cost'!$X$2:$X$807,'Annual_Cost'!$A$2:$A$807,A235,'Annual_Cost'!$C$2:$C$807,B235) | G235: =SUMIFS($E$2:E235,$A$2:A235,A235) | H235: =SUMIFS($F$2:F235,$A$2:A235,A235) | I235: 3.2331204e+08 | J235: =IF(I235=0,"",C235/I235) | K235: =IF(I235=0,"",D235/I235) | L235: =IF(I235=0,"",E235/I235) | M235: =IF(I235=0,"",F235/I235)

Sheet Cost_Effectiveness
A1: scenario | B1: scenario_label | C1: deaths_averted | D1: cases_averted | E1: incremental_cost | F1: disc_incremental_cost | G1: cost_per_death_averted | H1: dominance | I1: reconciliation_status | J1: annual_cost_incremental_per_capita | K1: disc_cost_incremental_per_capita
A2: all_cascade_public_health | B2: 70-30-30 -> 70-70-70 cascade + all public-health interventions (combined) | C2: =SUMIFS('Annual_Mortality'!$I$2:$I$1639,'Annual_Mortality'!$A$2:$A$1639,A2) | D2: =SUMIFS('Annual_Mortality'!$J$2:$J$1639,'Annual_Mortality'!$A$2:$A$1639,A2) | E2: =SUMIFS('Budget_Impact'!$E$2:$E$235,'Budget_Impact'!$A$2:$A$235,A2) | F2: =SUMIFS('Budget_Impact'!$F$2:$F$235,'Budget_Impact'!$A$2:$A$235,A2) | G2: =IF(C2>0,F2/C2,"") | H2: =IF(AND(C2>0,F2<0),"Dominant (more health, lower cost)",IF(AND(C2<=0,F2>0),"Dominated (less/no health, higher cost)",IF(AND(C2<=0,F2<=0),"No deaths averted; ratio not defined","USD per death averted"))) | I2: =IF(AND(ABS(F2-SUMIFS('Budget_Impact'!$F$2:$F$235,'Budget_Impact'!$A$2:$A$235,A2))<='Calculation_Assumptions'!$B$11,ABS(C2-SUMIFS('Annual_Mortality'!$I$2:$I$1639,'Annual_Mortality'!$A$2:$A$1639,A2))<='Calculation_Assumptions'!$B$11),"consistent","mismatch") | J2: =IFERROR(AVERAGEIFS('Budget_Impact'!$L$2:$L$235,'Budget_Impact'!$A$2:$A$235,A2,'Budget_Impact'!$B$2:$B$235,">="&('Calculation_Assumptions'!$B$2+1)),"") | K2: =IFERROR(AVERAGEIFS('Budget_Impact'!$M$2:$M$235,'Budget_Impact'!$A$2:$A$235,A2,'Budget_Impact'!$B$2:$B$235,">="&('Calculation_Assumptions'!$B$2+1)),"")
A3: S_70_30_30_TO_70_70_70_I_PH_TOBACCO_TAX | B3: 70-30-30 -> 70-70-70 cascade + tobacco tax | C3: =SUMIFS('Annual_Mortality'!$I$2:$I$1639,'Annual_Mortality'!$A$2:$A$1639,A3) | D3: =SUMIFS('Annual_Mortality'!$J$2:$J$1639,'Annual_Mortality'!$A$2:$A$1639,A3) | E3: =SUMIFS('Budget_Impact'!$E$2:$E$235,'Budget_Impact'!$A$2:$A$235,A3) | F3: =SUMIFS('Budget_Impact'!$F$2:$F$235,'Budget_Impact'!$A$2:$A$235,A3) | G3: =IF(C3>0,F3/C3,"") | H3: =IF(AND(C3>0,F3<0),"Dominant (more health, lower cost)",IF(AND(C3<=0,F3>0),"Dominated (less/no health, higher cost)",IF(AND(C3<=0,F3<=0),"No deaths averted; ratio not defined","USD per death averted"))) | I3: =IF(AND(ABS(F3-SUMIFS('Budget_Impact'!$F$2:$F$235,'Budget_Impact'!$A$2:$A$235,A3))<='Calculation_Assumptions'!$B$11,ABS(C3-SUMIFS('Annual_Mortality'!$I$2:$I$1639,'Annual_Mortality'!$A$2:$A$1639,A3))<='Calculation_Assumptions'!$B$11),"consistent","mismatch") | J3: =IFERROR(AVERAGEIFS('Budget_Impact'!$L$2:$L$235,'Budget_Impact'!$A$2:$A$235,A3,'Budget_Impact'!$B$2:$B$235,">="&('Calculation_Assumptions'!$B$2+1)),"") | K3: =IFERROR(AVERAGEIFS('Budget_Impact'!$M$2:$M$235,'Budget_Impact'!$A$2:$A$235,A3,'Budget_Impact'!$B$2:$B$235,">="&('Calculation_Assumptions'!$B$2+1)),"")
A4: all_public_health | B4: All selected public-health interventions (combined) | C4: =SUMIFS('Annual_Mortality'!$I$2:$I$1639,'Annual_Mortality'!$A$2:$A$1639,A4) | D4: =SUMIFS('Annual_Mortality'!$J$2:$J$1639,'Annual_Mortality'!$A$2:$A$1639,A4) | E4: =SUMIFS('Budget_Impact'!$E$2:$E$235,'Budget_Impact'!$A$2:$A$235,A4) | F4: =SUMIFS('Budget_Impact'!$F$2:$F$235,'Budget_Impact'!$A$2:$A$235,A4) | G4: =IF(C4>0,F4/C4,"") | H4: =IF(AND(C4>0,F4<0),"Dominant (more health, lower cost)",IF(AND(C4<=0,F4>0),"Dominated (less/no health, higher cost)",IF(AND(C4<=0,F4<=0),"No deaths averted; ratio not defined","USD per death averted"))) | I4: =IF(AND(ABS(F4-SUMIFS('Budget_Impact'!$F$2:$F$235,'Budget_Impact'!$A$2:$A$235,A4))<='Calculation_Assumptions'!$B$11,ABS(C4-SUMIFS('Annual_Mortality'!$I$2:$I$1639,'Annual_Mortality'!$A$2:$A$1639,A4))<='Calculation_Assumptions'!$B$11),"consistent","mismatch") | J4: =IFERROR(AVERAGEIFS('Budget_Impact'!$L$2:$L$235,'Budget_Impact'!$A$2:$A$235,A4,'Budget_Impact'!$B$2:$B$235,">="&('Calculation_Assumptions'!$B$2+1)),"") | K4: =IFERROR(AVERAGEIFS('Budget_Impact'!$M$2:$M$235,'Budget_Impact'!$A$2:$A$235,A4,'Budget_Impact'!$B$2:$B$235,">="&('Calculation_Assumptions'!$B$2+1)),"")
A5: S_70_30_30_TO_70_70_70 | B5: 70-30-30 -> 70-70-70 hypertension/cholesterol + diabetes cascade | C5: =SUMIFS('Annual_Mortality'!$I$2:$I$1639,'Annual_Mortality'!$A$2:$A$1639,A5) | D5: =SUMIFS('Annual_Mortality'!$J$2:$J$1639,'Annual_Mortality'!$A$2:$A$1639,A5) | E5: =SUMIFS('Budget_Impact'!$E$2:$E$235,'Budget_Impact'!$A$2:$A$235,A5) | F5: =SUMIFS('Budget_Impact'!$F$2:$F$235,'Budget_Impact'!$A$2:$A$235,A5) | G5: =IF(C5>0,F5/C5,"") | H5: =IF(AND(C5>0,F5<0),"Dominant (more health, lower cost)",IF(AND(C5<=0,F5>0),"Dominated (less/no health, higher cost)",IF(AND(C5<=0,F5<=0),"No deaths averted; ratio not defined","USD per death averted"))) | I5: =IF(AND(ABS(F5-SUMIFS('Budget_Impact'!$F$2:$F$235,'Budget_Impact'!$A$2:$A$235,A5))<='Calculation_Assumptions'!$B$11,ABS(C5-SUMIFS('Annual_Mortality'!$I$2:$I$1639,'Annual_Mortality'!$A$2:$A$1639,A5))<='Calculation_Assumptions'!$B$11),"consistent","mismatch") | J5: =IFERROR(AVERAGEIFS('Budget_Impact'!$L$2:$L$235,'Budget_Impact'!$A$2:$A$235,A5,'Budget_Impact'!$B$2:$B$235,">="&('Calculation_Assumptions'!$B$2+1)),"") | K5: =IFERROR(AVERAGEIFS('Budget_Impact'!$M$2:$M$235,'Budget_Impact'!$A$2:$A$235,A5,'Budget_Impact'!$B$2:$B$235,">="&('Calculation_Assumptions'!$B$2+1)),"")
A6: I_PH_TOBACCO_TAX | B6: Tobacco tax | C6: =SUMIFS('Annual_Mortality'!$I$2:$I$1639,'Annual_Mortality'!$A$2:$A$1639,A6) | D6: =SUMIFS('Annual_Mortality'!$J$2:$J$1639,'Annual_Mortality'!$A$2:$A$1639,A6) | E6: =SUMIFS('Budget_Impact'!$E$2:$E$235,'Budget_Impact'!$A$2:$A$235,A6) | F6: =SUMIFS('Budget_Impact'!$F$2:$F$235,'Budget_Impact'!$A$2:$A$235,A6) | G6: =IF(C6>0,F6/C6,"") | H6: =IF(AND(C6>0,F6<0),"Dominant (more health, lower cost)",IF(AND(C6<=0,F6>0),"Dominated (less/no health, higher cost)",IF(AND(C6<=0,F6<=0),"No deaths averted; ratio not defined","USD per death averted"))) | I6: =IF(AND(ABS(F6-SUMIFS('Budget_Impact'!$F$2:$F$235,'Budget_Impact'!$A$2:$A$235,A6))<='Calculation_Assumptions'!$B$11,ABS(C6-SUMIFS('Annual_Mortality'!$I$2:$I$1639,'Annual_Mortality'!$A$2:$A$1639,A6))<='Calculation_Assumptions'!$B$11),"consistent","mismatch") | J6: =IFERROR(AVERAGEIFS('Budget_Impact'!$L$2:$L$235,'Budget_Impact'!$A$2:$A$235,A6,'Budget_Impact'!$B$2:$B$235,">="&('Calculation_Assumptions'!$B$2+1)),"") | K6: =IFERROR(AVERAGEIFS('Budget_Impact'!$M$2:$M$235,'Budget_Impact'!$A$2:$A$235,A6,'Budget_Impact'!$B$2:$B$235,">="&('Calculation_Assumptions'!$B$2+1)),"")
A7: I_PH_TOBACCO_POLICY | B7: Tobacco policy package | C7: =SUMIFS('Annual_Mortality'!$I$2:$I$1639,'Annual_Mortality'!$A$2:$A$1639,A7) | D7: =SUMIFS('Annual_Mortality'!$J$2:$J$1639,'Annual_Mortality'!$A$2:$A$1639,A7) | E7: =SUMIFS('Budget_Impact'!$E$2:$E$235,'Budget_Impact'!$A$2:$A$235,A7) | F7: =SUMIFS('Budget_Impact'!$F$2:$F$235,'Budget_Impact'!$A$2:$A$235,A7) | G7: =IF(C7>0,F7/C7,"") | H7: =IF(AND(C7>0,F7<0),"Dominant (more health, lower cost)",IF(AND(C7<=0,F7>0),"Dominated (less/no health, higher cost)",IF(AND(C7<=0,F7<=0),"No deaths averted; ratio not defined","USD per death averted"))) | I7: =IF(AND(ABS(F7-SUMIFS('Budget_Impact'!$F$2:$F$235,'Budget_Impact'!$A$2:$A$235,A7))<='Calculation_Assumptions'!$B$11,ABS(C7-SUMIFS('Annual_Mortality'!$I$2:$I$1639,'Annual_Mortality'!$A$2:$A$1639,A7))<='Calculation_Assumptions'!$B$11),"consistent","mismatch") | J7: =IFERROR(AVERAGEIFS('Budget_Impact'!$L$2:$L$235,'Budget_Impact'!$A$2:$A$235,A7,'Budget_Impact'!$B$2:$B$235,">="&('Calculation_Assumptions'!$B$2+1)),"") | K7: =IFERROR(AVERAGEIFS('Budget_Impact'!$M$2:$M$235,'Budget_Impact'!$A$2:$A$235,A7,'Budget_Impact'!$B$2:$B$235,">="&('Calculation_Assumptions'!$B$2+1)),"")
A8: I_PH_TOB_MEDIA | B8: Tobacco mass-media campaign | C8: =SUMIFS('Annual_Mortality'!$I$2:$I$1639,'Annual_Mortality'!$A$2:$A$1639,A8) | D8: =SUMIFS('Annual_Mortality'!$J$2:$J$1639,'Annual_Mortality'!$A$2:$A$1639,A8) | E8: =SUMIFS('Budget_Impact'!$E$2:$E$235,'Budget_Impact'!$A$2:$A$235,A8) | F8: =SUMIFS('Budget_Impact'!$F$2:$F$235,'Budget_Impact'!$A$2:$A$235,A8) | G8: =IF(C8>0,F8/C8,"") | H8: =IF(AND(C8>0,F8<0),"Dominant (more health, lower cost)",IF(AND(C8<=0,F8>0),"Dominated (less/no health, higher cost)",IF(AND(C8<=0,F8<=0),"No deaths averted; ratio not defined","USD per death averted"))) | I8: =IF(AND(ABS(F8-SUMIFS('Budget_Impact'!$F$2:$F$235,'Budget_Impact'!$A$2:$A$235,A8))<='Calculation_Assumptions'!$B$11,ABS(C8-SUMIFS('Annual_Mortality'!$I$2:$I$1639,'Annual_Mortality'!$A$2:$A$1639,A8))<='Calculation_Assumptions'!$B$11),"consistent","mismatch") | J8: =IFERROR(AVERAGEIFS('Budget_Impact'!$L$2:$L$235,'Budget_Impact'!$A$2:$A$235,A8,'Budget_Impact'!$B$2:$B$235,">="&('Calculation_Assumptions'!$B$2+1)),"") | K8: =IFERROR(AVERAGEIFS('Budget_Impact'!$M$2:$M$235,'Budget_Impact'!$A$2:$A$235,A8,'Budget_Impact'!$B$2:$B$235,">="&('Calculation_Assumptions'!$B$2+1)),"")
A9: I_PH_TOB_CLEAN_AIR | B9: Smoke-free / clean-air law | C9: =SUMIFS('Annual_Mortality'!$I$2:$I$1639,'Annual_Mortality'!$A$2:$A$1639,A9) | D9: =SUMIFS('Annual_Mortality'!$J$2:$J$1639,'Annual_Mortality'!$A$2:$A$1639,A9) | E9: =SUMIFS('Budget_Impact'!$E$2:$E$235,'Budget_Impact'!$A$2:$A$235,A9) | F9: =SUMIFS('Budget_Impact'!$F$2:$F$235,'Budget_Impact'!$A$2:$A$235,A9) | G9: =IF(C9>0,F9/C9,"") | H9: =IF(AND(C9>0,F9<0),"Dominant (more health, lower cost)",IF(AND(C9<=0,F9>0),"Dominated (less/no health, higher cost)",IF(AND(C9<=0,F9<=0),"No deaths averted; ratio not defined","USD per death averted"))) | I9: =IF(AND(ABS(F9-SUMIFS('Budget_Impact'!$F$2:$F$235,'Budget_Impact'!$A$2:$A$235,A9))<='Calculation_Assumptions'!$B$11,ABS(C9-SUMIFS('Annual_Mortality'!$I$2:$I$1639,'Annual_Mortality'!$A$2:$A$1639,A9))<='Calculation_Assumptions'!$B$11),"consistent","mismatch") | J9: =IFERROR(AVERAGEIFS('Budget_Impact'!$L$2:$L$235,'Budget_Impact'!$A$2:$A$235,A9,'Budget_Impact'!$B$2:$B$235,">="&('Calculation_Assumptions'!$B$2+1)),"") | K9: =IFERROR(AVERAGEIFS('Budget_Impact'!$M$2:$M$235,'Budget_Impact'!$A$2:$A$235,A9,'Budget_Impact'!$B$2:$B$235,">="&('Calculation_Assumptions'!$B$2+1)),"")
A10: I_PH_TOB_AD_BAN | B10: Tobacco advertising ban | C10: =SUMIFS('Annual_Mortality'!$I$2:$I$1639,'Annual_Mortality'!$A$2:$A$1639,A10) | D10: =SUMIFS('Annual_Mortality'!$J$2:$J$1639,'Annual_Mortality'!$A$2:$A$1639,A10) | E10: =SUMIFS('Budget_Impact'!$E$2:$E$235,'Budget_Impact'!$A$2:$A$235,A10) | F10: =SUMIFS('Budget_Impact'!$F$2:$F$235,'Budget_Impact'!$A$2:$A$235,A10) | G10: =IF(C10>0,F10/C10,"") | H10: =IF(AND(C10>0,F10<0),"Dominant (more health, lower cost)",IF(AND(C10<=0,F10>0),"Dominated (less/no health, higher cost)",IF(AND(C10<=0,F10<=0),"No deaths averted; ratio not defined","USD per death averted"))) | I10: =IF(AND(ABS(F10-SUMIFS('Budget_Impact'!$F$2:$F$235,'Budget_Impact'!$A$2:$A$235,A10))<='Calculation_Assumptions'!$B$11,ABS(C10-SUMIFS('Annual_Mortality'!$I$2:$I$1639,'Annual_Mortality'!$A$2:$A$1639,A10))<='Calculation_Assumptions'!$B$11),"consistent","mismatch") | J10: =IFERROR(AVERAGEIFS('Budget_Impact'!$L$2:$L$235,'Budget_Impact'!$A$2:$A$235,A10,'Budget_Impact'!$B$2:$B$235,">="&('Calculation_Assumptions'!$B$2+1)),"") | K10: =IFERROR(AVERAGEIFS('Budget_Impact'!$M$2:$M$235,'Budget_Impact'!$A$2:$A$235,A10,'Budget_Impact'!$B$2:$B$235,">="&('Calculation_Assumptions'!$B$2+1)),"")

Sheet Economic_Value
A1: scenario | B1: scenario_label | C1: year | D1: deaths_averted | E1: life_years_gained | F1: gni_pc_idn | G1: gni_pc_usa | H1: population | I1: le_avg_adult | J1: vsl_transfer_prefloor | K1: vsl_floor | L1: vsl_preferred | M1: vsl_over_gnipc | N1: vsl_gni100 | O1: vsl_gni160 | P1: vsly_preferred | Q1: econ_value_vsl_undisc | R1: econ_value_vsly_undisc | S1: econ_value_vsl100_undisc | T1: econ_value_vsl160_undisc | U1: disc_factor | V1: pv_vsl_pref | W1: pv_vsly_pref | X1: pv_vsl100 | Y1: pv_vsl160 | Z1: total_national_gni | AA1: pv_national_gni | AB1: annual_benefit_share_gni
A2: all_cascade_public_health | B2: 70-30-30 -> 70-70-70 cascade + all public-health interventions (combined) | C2: 2025 | D2: 2.4305666e-10 | E2: 7.1993322e-09 | F2: 13851.491 | G2: 74136.371 | H2: 2.8572124e+08 | I2: 37.51 | J2: ='Calculation_Assumptions'!$B$24*G2*(F2/G2)^'Calculation_Assumptions'!$B$25 | K2: ='Calculation_Assumptions'!$B$26*F2 | L2: =MAX(J2,K2) | M2: =IF(F2=0,"",L2/F2) | N2: ='Calculation_Assumptions'!$B$27*F2 | O2: ='Calculation_Assumptions'!$B$28*F2 | P2: =IF(I2=0,"",L2/I2) | Q2: =L2*D2 | R2: =P2*E2 | S2: =N2*D2 | T2: =O2*D2 | U2: =1/(1+'Calculation_Assumptions'!$B$21)^(C2-'Calculation_Assumptions'!$B$20) | V2: =Q2*U2 | W2: =R2*U2 | X2: =S2*U2 | Y2: =T2*U2 | Z2: =H2*F2 | AA2: =Z2*U2 | AB2: =IF(Z2=0,"",Q2/Z2)
A3: all_cascade_public_health | B3: 70-30-30 -> 70-70-70 cascade + all public-health interventions (combined) | C3: 2026 | D3: 12152.838 | E3: 200925.5 | F3: 14370.1 | G3: 75186.41 | H3: 2.8788678e+08 | I3: 37.5883 | J3: ='Calculation_Assumptions'!$B$24*G3*(F3/G3)^'Calculation_Assumptions'!$B$25 | K3: ='Calculation_Assumptions'!$B$26*F3 | L3: =MAX(J3,K3) | M3: =IF(F3=0,"",L3/F3) | N3: ='Calculation_Assumptions'!$B$27*F3 | O3: ='Calculation_Assumptions'!$B$28*F3 | P3: =IF(I3=0,"",L3/I3) | Q3: =L3*D3 | R3: =P3*E3 | S3: =N3*D3 | T3: =O3*D3 | U3: =1/(1+'Calculation_Assumptions'!$B$21)^(C3-'Calculation_Assumptions'!$B$20) | V3: =Q3*U3 | W3: =R3*U3 | X3: =S3*U3 | Y3: =T3*U3 | Z3: =H3*F3 | AA3: =Z3*U3 | AB3: =IF(Z3=0,"",Q3/Z3)
A4: all_cascade_public_health | B4: 70-30-30 -> 70-70-70 cascade + all public-health interventions (combined) | C4: 2027 | D4: 23661.21 | E4: 395531.61 | F4: 14908.127 | G4: 76251.321 | H4: 289986522 | I4: 37.6736 | J4: ='Calculation_Assumptions'!$B$24*G4*(F4/G4)^'Calculation_Assumptions'!$B$25 | K4: ='Calculation_Assumptions'!$B$26*F4 | L4: =MAX(J4,K4) | M4: =IF(F4=0,"",L4/F4) | N4: ='Calculation_Assumptions'!$B$27*F4 | O4: ='Calculation_Assumptions'!$B$28*F4 | P4: =IF(I4=0,"",L4/I4) | Q4: =L4*D4 | R4: =P4*E4 | S4: =N4*D4 | T4: =O4*D4 | U4: =1/(1+'Calculation_Assumptions'!$B$21)^(C4-'Calculation_Assumptions'!$B$20) | V4: =Q4*U4 | W4: =R4*U4 | X4: =S4*U4 | Y4: =T4*U4 | Z4: =H4*F4 | AA4: =Z4*U4 | AB4: =IF(Z4=0,"",Q4/Z4)
A5: all_cascade_public_health | B5: 70-30-30 -> 70-70-70 cascade + all public-health interventions (combined) | C5: 2028 | D5: 34973.39 | E5: 587441.03 | F5: 15466.297 | G5: 77331.315 | H5: 2.9201678e+08 | I5: 36.834 | J5: ='Calculation_Assumptions'!$B$24*G5*(F5/G5)^'Calculation_Assumptions'!$B$25 | K5: ='Calculation_Assumptions'!$B$26*F5 | L5: =MAX(J5,K5) | M5: =IF(F5=0,"",L5/F5) | N5: ='Calculation_Assumptions'!$B$27*F5 | O5: ='Calculation_Assumptions'!$B$28*F5 | P5: =IF(I5=0,"",L5/I5) | Q5: =L5*D5 | R5: =P5*E5 | S5: =N5*D5 | T5: =O5*D5 | U5: =1/(1+'Calculation_Assumptions'!$B$21)^(C5-'Calculation_Assumptions'!$B$20) | V5: =Q5*U5 | W5: =R5*U5 | X5: =S5*U5 | Y5: =T5*U5 | Z5: =H5*F5 | AA5: =Z5*U5 | AB5: =IF(Z5=0,"",Q5/Z5)
A6: all_cascade_public_health | B6: 70-30-30 -> 70-70-70 cascade + all public-health interventions (combined) | C6: 2029 | D6: 49051.472 | E6: 817634.82 | F6: 16045.366 | G6: 78426.606 | H6: 293978109 | I6: 36.9118 | J6: ='Calculation_Assumptions'!$B$24*G6*(F6/G6)^'Calculation_Assumptions'!$B$25 | K6: ='Calculation_Assumptions'!$B$26*F6 | L6: =MAX(J6,K6) | M6: =IF(F6=0,"",L6/F6) | N6: ='Calculation_Assumptions'!$B$27*F6 | O6: ='Calculation_Assumptions'!$B$28*F6 | P6: =IF(I6=0,"",L6/I6) | Q6: =L6*D6 | R6: =P6*E6 | S6: =N6*D6 | T6: =O6*D6 | U6: =1/(1+'Calculation_Assumptions'!$B$21)^(C6-'Calculation_Assumptions'!$B$20) | V6: =Q6*U6 | W6: =R6*U6 | X6: =S6*U6 | Y6: =T6*U6 | Z6: =H6*F6 | AA6: =Z6*U6 | AB6: =IF(Z6=0,"",Q6/Z6)
A7: all_cascade_public_health | B7: 70-30-30 -> 70-70-70 cascade + all public-health interventions (combined) | C7: 2030 | D7: 63080.899 | E7: 1046865.3 | F7: 16646.116 | G7: 79537.41 | H7: 295876648 | I7: 36.9927 | J7: ='Calculation_Assumptions'!$B$24*G7*(F7/G7)^'Calculation_Assumptions'!$B$25 | K7: ='Calculation_Assumptions'!$B$26*F7 | L7: =MAX(J7,K7) | M7: =IF(F7=0,"",L7/F7) | N7: ='Calculation_Assumptions'!$B$27*F7 | O7: ='Calculation_Assumptions'!$B$28*F7 | P7: =IF(I7=0,"",L7/I7) | Q7: =L7*D7 | R7: =P7*E7 | S7: =N7*D7 | T7: =O7*D7 | U7: =1/(1+'Calculation_Assumptions'!$B$21)^(C7-'Calculation_Assumptions'!$B$20) | V7: =Q7*U7 | W7: =R7*U7 | X7: =S7*U7 | Y7: =T7*U7 | Z7: =H7*F7 | AA7: =Z7*U7 | AB7: =IF(Z7=0,"",Q7/Z7)
A8: all_cascade_public_health | B8: 70-30-30 -> 70-70-70 cascade + all public-health interventions (combined) | C8: 2031 | D8: 65373.117 | E8: 1085724.6 | F8: 17161.073 | G8: 80420.157 | H8: 297719748 | I8: 37.0895 | J8: ='Calculation_Assumptions'!$B$24*G8*(F8/G8)^'Calculation_Assumptions'!$B$25 | K8: ='Calculation_Assumptions'!$B$26*F8 | L8: =MAX(J8,K8) | M8: =IF(F8=0,"",L8/F8) | N8: ='Calculation_Assumptions'!$B$27*F8 | O8: ='Calculation_Assumptions'!$B$28*F8 | P8: =IF(I8=0,"",L8/I8) | Q8: =L8*D8 | R8: =P8*E8 | S8: =N8*D8 | T8: =O8*D8 | U8: =1/(1+'Calculation_Assumptions'!$B$21)^(C8-'Calculation_Assumptions'!$B$20) | V8: =Q8*U8 | W8: =R8*U8 | X8: =S8*U8 | Y8: =T8*U8 | Z8: =H8*F8 | AA8: =Z8*U8 | AB8: =IF(Z8=0,"",Q8/Z8)
A9: all_cascade_public_health | B9: 70-30-30 -> 70-70-70 cascade + all public-health interventions (combined) | C9: 2032 | D9: 70541.754 | E9: 1159223.9 | F9: 17691.962 | G9: 81312.7 | H9: 2.9951066e+08 | I9: 37.1904 | J9: ='Calculation_Assumptions'!$B$24*G9*(F9/G9)^'Calculation_Assumptions'!$B$25 | K9: ='Calculation_Assumptions'!$B$26*F9 | L9: =MAX(J9,K9) | M9: =IF(F9=0,"",L9/F9) | N9: ='Calculation_Assumptions'!$B$27*F9 | O9: ='Calculation_Assumptions'!$B$28*F9 | P9: =IF(I9=0,"",L9/I9) | Q9: =L9*D9 | R9: =P9*E9 | S9: =N9*D9 | T9: =O9*D9 | U9: =1/(1+'Calculation_Assumptions'!$B$21)^(C9-'Calculation_Assumptions'!$B$20) | V9: =Q9*U9 | W9: =R9*U9 | X9: =S9*U9 | Y9: =T9*U9 | Z9: =H9*F9 | AA9: =Z9*U9 | AB9: =IF(Z9=0,"",Q9/Z9)
A10: all_cascade_public_health | B10: 70-30-30 -> 70-70-70 cascade + all public-health interventions (combined) | C10: 2033 | D10: 77470.532 | E10: 1255522.4 | F10: 18239.273 | G10: 82215.15 | H10: 3.0125098e+08 | I10: 37.2975 | J10: ='Calculation_Assumptions'!$B$24*G10*(F10/G10)^'Calculation_Assumptions'!$B$25 | K10: ='Calculation_Assumptions'!$B$26*F10 | L10: =MAX(J10,K10) | M10: =IF(F10=0,"",L10/F10) | N10: ='Calculation_Assumptions'!$B$27*F10 | O10: ='Calculation_Assumptions'!$B$28*F10 | P10: =IF(I10=0,"",L10/I10) | Q10: =L10*D10 | R10: =P10*E10 | S10: =N10*D10 | T10: =O10*D10 | U10: =1/(1+'Calculation_Assumptions'!$B$21)^(C10-'Calculation_Assumptions'!$B$20) | V10: =Q10*U10 | W10: =R10*U10 | X10: =S10*U10 | Y10: =T10*U10 | Z10: =H10*F10 | AA10: =Z10*U10 | AB10: =IF(Z10=0,"",Q10/Z10)
A11: all_cascade_public_health | B11: 70-30-30 -> 70-70-70 cascade + all public-health interventions (combined) | C11: 2034 | D11: 82794.481 | E11: 1332002.3 | F11: 18803.516 | G11: 83127.615 | H11: 302938573 | I11: 37.4064 | J11: ='Calculation_Assumptions'!$B$24*G11*(F11/G11)^'Calculation_Assumptions'!$B$25 | K11: ='Calculation_Assumptions'!$B$26*F11 | L11: =MAX(J11,K11) | M11: =IF(F11=0,"",L11/F11) | N11: ='Calculation_Assumptions'!$B$27*F11 | O11: ='Calculation_Assumptions'!$B$28*F11 | P11: =IF(I11=0,"",L11/I11) | Q11: =L11*D11 | R11: =P11*E11 | S11: =N11*D11 | T11: =O11*D11 | U11: =1/(1+'Calculation_Assumptions'!$B$21)^(C11-'Calculation_Assumptions'!$B$20) | V11: =Q11*U11 | W11: =R11*U11 | X11: =S11*U11 | Y11: =T11*U11 | Z11: =H11*F11 | AA11: =Z11*U11 | AB11: =IF(Z11=0,"",Q11/Z11)
A12: all_cascade_public_health | B12: 70-30-30 -> 70-70-70 cascade + all public-health interventions (combined) | C12: 2035 | D12: 89502.061 | E12: 1426902 | F12: 19385.215 | G12: 84050.207 | H12: 304566622 | I12: 37.5179 | J12: ='Calculation_Assumptions'!$B$24*G12*(F12/G12)^'Calculation_Assumptions'!$B$25 | K12: ='Calculation_Assumptions'!$B$26*F12 | L12: =MAX(J12,K12) | M12: =IF(F12=0,"",L12/F12) | N12: ='Calculation_Assumptions'!$B$27*F12 | O12: ='Calculation_Assumptions'!$B$28*F12 | P12: =IF(I12=0,"",L12/I12) | Q12: =L12*D12 | R12: =P12*E12 | S12: =N12*D12 | T12: =O12*D12 | U12: =1/(1+'Calculation_Assumptions'!$B$21)^(C12-'Calculation_Assumptions'!$B$20) | V12: =Q12*U12 | W12: =R12*U12 | X12: =S12*U12 | Y12: =T12*U12 | Z12: =H12*F12 | AA12: =Z12*U12 | AB12: =IF(Z12=0,"",Q12/Z12)
A13: all_cascade_public_health | B13: 70-30-30 -> 70-70-70 cascade + all public-health interventions (combined) | C13: 2036 | D13: 108119.51 | E13: 1664676.4 | F13: 19931.358 | G13: 84847.857 | H13: 306135098 | I13: 37.6267 | J13: ='Calculation_Assumptions'!$B$24*G13*(F13/G13)^'Calculation_Assumptions'!$B$25 | K13: ='Calculation_Assumptions'!$B$26*F13 | L13: =MAX(J13,K13) | M13: =IF(F13=0,"",L13/F13) | N13: ='Calculation_Assumptions'!$B$27*F13 | O13: ='Calculation_Assumptions'!$B$28*F13 | P13: =IF(I13=0,"",L13/I13) | Q13: =L13*D13 | R13: =P13*E13 | S13: =N13*D13 | T13: =O13*D13 | U13: =1/(1+'Calculation_Assumptions'!$B$21)^(C13-'Calculation_Assumptions'!$B$20) | V13: =Q13*U13 | W13: =R13*U13 | X13: =S13*U13 | Y13: =T13*U13 | Z13: =H13*F13 | AA13: =Z13*U13 | AB13: =IF(Z13=0,"",Q13/Z13)
... A235: S_70_30_30_TO_70_70_70_I_PH_TOBACCO_TAX | B235: 70-30-30 -> 70-70-70 cascade + tobacco tax | C235: 2050 | D235: 202008.33 | E235: 2938507 | F235: 28211.06 | G235: 95832.888 | H235: 3.2071295e+08 | I235: 38.286 | J235: ='Calculation_Assumptions'!$B$24*G235*(F235/G235)^'Calculation_Assumptions'!$B$25 | K235: ='Calculation_Assumptions'!$B$26*F235 | L235: =MAX(J235,K235) | M235: =IF(F235=0,"",L235/F235) | N235: ='Calculation_Assumptions'!$B$27*F235 | O235: ='Calculation_Assumptions'!$B$28*F235 | P235: =IF(I235=0,"",L235/I235) | Q235: =L235*D235 | R235: =P235*E235 | S235: =N235*D235 | T235: =O235*D235 | U235: =1/(1+'Calculation_Assumptions'!$B$21)^(C235-'Calculation_Assumptions'!$B$20) | V235: =Q235*U235 | W235: =R235*U235 | X235: =S235*U235 | Y235: =T235*U235 | Z235: =H235*F235 | AA235: =Z235*U235 | AB235: =IF(Z235=0,"",Q235/Z235)

Sheet Benefit_Cost
A1: scenario | B1: scenario_label | C1: intervention_family | D1: scenario_level | E1: valuation_method | F1: valuation_case | G1: pv_benefits | H1: pv_costs | I1: pv_net_benefit | J1: benefit_cost_ratio | K1: pv_national_gni | L1: benefit_gni_share | M1: decision | N1: scope_note
