Workbook

Sheet README
A1: Indonesia NCD FAIR Choices - cost & value workbook (formula edition)
A3: section | B3: detail
A4: Purpose | B4: Costing, budget impact and mortality-based cost-effectiveness for the FAIR Choices CVD interventions selected in indonesia_model_inputs.xlsx.
A5: How to read | B5: Grey cells are R-generated source values; light-blue cells are LIVE Excel formulas; pale-yellow cells on Calculation_Assumptions are editable controls. Change a yellow control and the blue results recompute. Calculation_Map lists every dependency.
A6: Scenarios | B6: Baseline + one scenario per selected valid intervention + a combined 'all' scenario. Membership derives only from the workbook selections (Model 04).
A7: Baseline pairing | B7: Deaths averted = baseline deaths - scenario deaths, matched at location x year x age x sex x cause (aggregated to year x cause here).
A8: CVD 40q30 | B8: CVD_40q30 / CVD_40q30_Age give the period probability of dying from the six CVD causes (ihd, istroke, hstroke, hhd, rhd, cmd) between exact ages 30 and 70, per scenario/HTN-target/year. The life table (m_x, q_x, l_x, l_{x+1}) is live Excel formula off grey CVD deaths and de-duplicated population; cvd_40q30 = 100*(1-l_70/l_30) reconciles to the Model 07 value. cvd_40q30 and the absolute reduction are PERCENT on a 0-100 scale (format 0.000), NOT Excel's fractional %.
A9: Model aggregates | B9: Annual_Mortality carries the R health aggregates (cases, deaths, baseline); Annual_Cost carries the full-precision R population quantity before the PIN fraction. The 157k-row state trace stays in the companion R workbook.
A10: Costing | B10: annual_cost = population_in_need x coverage(t) x frequency x unit_cost. PIN measure maps 'all'->eligible population, 'prevalence'->sick stock, 'incidence'->new cases.
A11: Shared costs | B11: Components flagged 'shared-count-once' (cost_join_key ...__C_SHARED) are counted once at intervention level, never once per affected cause (see Annual_Cost shared_duplicate_count and QA).
A12: Budget impact | B12: Budget impact reports UNDISCOUNTED baseline, scenario, incremental and cumulative incremental cost. Discounted costs are separate columns. The four *_cost_per_capita columns are LIVE formulae (= that year's cost / national_population); national_population (grey R-source) is each year's national Indonesia population from out_model/model_output_Indonesia_htncov2_aspirational.rds (baseline series, de-duplicated across cause). Annual_Cost carries the matching per-component per-capita formulae, and Cost_Effectiveness carries the scenario mean annual incremental/discounted per-capita (2026-2050).
A13: Cost-effectiveness | B13: USD per death averted = cumulative discounted incremental cost / cumulative (undiscounted) deaths averted over the horizon. Not a DALY-based ICER.
A14: Economic value | B14: Reference-Case benefit-cost analysis (2019 Robinson et al. Guidelines): Health_Outcomes (Model 07 averted deaths/YLL/YLD/DALY & life-years gained), Economic_Value (Model 08 VSL/VSLY source with LIVE VSL-transfer, floor, VSLY, discount and PV-benefit formulas) and Benefit_Cost (PV benefits, PV costs converted to the benefit basis, net benefit and BCR). Preferred VSL = MAX(160xGNIpc_US x (GNIpc_IDN/GNIpc_US)^1.5, 20xGNIpc_IDN); 100x/160x GNI sensitivities. PARTIAL mortality-benefit BCA -- not a full societal BCA, and distinct from Cost_Effectiveness (USD per death averted).
... A18: Deferred | B18: Health outcomes (deaths averted, YLL/YLD/DALY averted, life-years gained) now come from Model 07 (Health_Outcomes); life-expectancy and disability-weight sources are documented via Model 07.

Sheet Run_Metadata
A1: item | B1: value
A2: Workbook title | B2: Indonesia NCD FAIR Choices - cost & value
A3: Run date | B3: 2026-08-30
A4: Model / pipeline | B4: CVD FAIR Choices (Models 00-06 -> 09)
A5: Input workbook | B5: C:/Users/wrgar/OneDrive - UW/02Work/WorldBank-Indonesia/uw-wb-indonesia-ncd/data/indonesia_model_inputs.xlsx
A6: Model output source | B6: output/out_model/model_output_*.rds (Model 06)
A7: Location | B7: Indonesia
A8: Analysis years | B8: ='Calculation_Assumptions'!B2&"-"&'Calculation_Assumptions'!B3
A9: Baseline scenario | B9: ='Calculation_Assumptions'!B4
A10: Scenarios costed | B10: I_CVD_PRIMARY, I_HF_ACUTE, I_HF_CHRONIC, I_IHD_ACUTE, I_IHD_SECONDARY, I_STROKE_SECONDARY, I_T2D_TREATMENT, all
A11: Cost discount rate | B11: ='Calculation_Assumptions'!B5
A12: Cost price year | B12: ='Calculation_Assumptions'!B6
A13: Currency | B13: ='Calculation_Assumptions'!B7
A14: Economic perspective | B14: ='Calculation_Assumptions'!B8
A15: Coverage scale-up shape | B15: ='Calculation_Assumptions'!B9
A16: Downstream cost offsets | B16: ='Calculation_Assumptions'!B10
A17: Health outcomes (DALYs/YLL/YLD) | B17: Out of scope in this stage (deferred)
A18: R version | B18: R version 4.5.1 (2025-06-13 ucrt)
A19: openxlsx / data.table | B19: 4.2.8 / 1.17.8

Sheet Scenario_Catalog
A1: scenario | B1: scenario_label | C1: intervention_family | D1: scenario_level | E1: scenario_role | F1: parent_package_id | G1: intervention_ids | H1: n_interventions
A2: baseline | B2: Baseline (no new intervention) | C2: clinical | D2: baseline | H2: 0
A3: I_CVD_PRIMARY | B3: Primary prevention of CVD | C3: clinical | D3: standalone | G3: I_CVD_PRIMARY | H3: 1
A4: I_HF_ACUTE | B4: Acute heart-failure management | C4: clinical | D4: standalone | G4: I_HF_ACUTE | H4: 1
A5: I_HF_CHRONIC | B5: Chronic heart-failure management | C5: clinical | D5: standalone | G5: I_HF_CHRONIC | H5: 1
A6: I_IHD_ACUTE | B6: Treatment of acute coronary syndromes | C6: clinical | D6: standalone | G6: I_IHD_ACUTE | H6: 1
A7: I_IHD_SECONDARY | B7: Secondary prevention of ischemic heart disease | C7: clinical | D7: standalone | G7: I_IHD_SECONDARY | H7: 1
A8: I_STROKE_SECONDARY | B8: Secondary prevention of stroke | C8: clinical | D8: standalone | G8: I_STROKE_SECONDARY | H8: 1
A9: I_T2D_TREATMENT | B9: Longitudinal treatment of type 2 diabetes | C9: clinical | D9: standalone | G9: I_T2D_TREATMENT | H9: 1
A10: all | B10: All selected interventions (combined) | C10: clinical | D10: combined | G10: I_CVD_PRIMARY; I_HF_ACUTE; I_HF_CHRONIC; I_IHD_ACUTE; I_IHD_SECONDARY; I_STROKE_SECONDARY; I_T2D_TREATMENT | H10: 7

Sheet Selected_Interventions
A1: intervention_id | B1: intervention_cause_key | C1: intervention_name | D1: cause_id | E1: cause_code | F1: model_name | G1: transition_from | H1: transition_to | I1: model_transition | J1: effect_value | K1: affected_fraction | L1: baseline_coverage | M1: target_coverage | N1: start_year | O1: target_year | P1: adjusted_effect_at_target | Q1: cost_join_key | R1: cost_scope | S1: effect_review | T1: coverage_review | U1: key_count | V1: formula_status
A2: I_CVD_PRIMARY | B2: I_CVD_PRIMARY__C_HHD | C2: Primary prevention of CVD | D2: C_HHD | E2: hhd | F2: Hypertensive heart disease | G2: well | H2: sick | I2: incidence | J2: 0.47 | K2: 1 | L2: 0.31 | M2: 0.8 | N2: 2025 | O2: 2050 | P2: =IF(OR(J2="",K2="",L2="",M2=""),"",ROUND(K2*(J2*(M2-L2)/(1-J2*L2)),4)) | Q2: I_CVD_PRIMARY__C_SHARED | R2: shared-count-once | S2: Provisional | T2: Provisional | U2: =COUNTIF($B$2:$B$17,B2) | V2: =IF(U2=1,"OK","DUPLICATE KEY")
A3: I_CVD_PRIMARY | B3: I_CVD_PRIMARY__C_ICH | C3: Primary prevention of CVD | D3: C_ICH | E3: hstroke | F3: Intracerebral hemorrhage | G3: well | H3: sick | I3: incidence | J3: 0.49 | K3: 0.8 | L3: 0.31 | M3: 0.8 | N3: 2025 | O3: 2050 | P3: =IF(OR(J3="",K3="",L3="",M3=""),"",ROUND(K3*(J3*(M3-L3)/(1-J3*L3)),4)) | Q3: I_CVD_PRIMARY__C_SHARED | R3: shared-count-once | S3: Provisional | T3: Provisional | U3: =COUNTIF($B$2:$B$17,B3) | V3: =IF(U3=1,"OK","DUPLICATE KEY")
A4: I_CVD_PRIMARY | B4: I_CVD_PRIMARY__C_IHD | C4: Primary prevention of CVD | D4: C_IHD | E4: ihd | F4: Ischemic heart disease | G4: well | H4: sick | I4: incidence | J4: 0.58 | K4: 0.8 | L4: 0.31 | M4: 0.8 | N4: 2025 | O4: 2050 | P4: =IF(OR(J4="",K4="",L4="",M4=""),"",ROUND(K4*(J4*(M4-L4)/(1-J4*L4)),4)) | Q4: I_CVD_PRIMARY__C_SHARED | R4: shared-count-once | S4: Provisional | T4: Provisional | U4: =COUNTIF($B$2:$B$17,B4) | V4: =IF(U4=1,"OK","DUPLICATE KEY")
A5: I_CVD_PRIMARY | B5: I_CVD_PRIMARY__C_IS | C5: Primary prevention of CVD | D5: C_IS | E5: istroke | F5: Ischemic stroke | G5: well | H5: sick | I5: incidence | J5: 0.54 | K5: 0.8 | L5: 0.31 | M5: 0.8 | N5: 2025 | O5: 2050 | P5: =IF(OR(J5="",K5="",L5="",M5=""),"",ROUND(K5*(J5*(M5-L5)/(1-J5*L5)),4)) | Q5: I_CVD_PRIMARY__C_SHARED | R5: shared-count-once | S5: Provisional | T5: Provisional | U5: =COUNTIF($B$2:$B$17,B5) | V5: =IF(U5=1,"OK","DUPLICATE KEY")
A6: I_HF_ACUTE | B6: I_HF_ACUTE__C_CMP | C6: Acute heart-failure management | D6: C_CMP | E6: cmd | F6: Cardiomyopathy and myocarditis | G6: sick_hf | H6: dead_cmp | I6: case_fatality | J6: 0.74 | K6: 0.2 | L6: 0.31 | M6: 0.8 | N6: 2025 | O6: 2050 | P6: =IF(OR(J6="",K6="",L6="",M6=""),"",ROUND(K6*(J6*(M6-L6)/(1-J6*L6)),4)) | Q6: I_HF_ACUTE__C_CMP | R6: cause-specific | S6: Provisional | T6: Provisional | U6: =COUNTIF($B$2:$B$17,B6) | V6: =IF(U6=1,"OK","DUPLICATE KEY")
A7: I_HF_ACUTE | B7: I_HF_ACUTE__C_HHD | C7: Acute heart-failure management | D7: C_HHD | E7: hhd | F7: Hypertensive heart disease | G7: sick_hf | H7: dead_hhd | I7: case_fatality | J7: 0.74 | K7: 0.2 | L7: 0.31 | M7: 0.8 | N7: 2025 | O7: 2050 | P7: =IF(OR(J7="",K7="",L7="",M7=""),"",ROUND(K7*(J7*(M7-L7)/(1-J7*L7)),4)) | Q7: I_HF_ACUTE__C_HHD | R7: cause-specific | S7: Provisional | T7: Provisional | U7: =COUNTIF($B$2:$B$17,B7) | V7: =IF(U7=1,"OK","DUPLICATE KEY")
A8: I_HF_ACUTE | B8: I_HF_ACUTE__C_IHD | C8: Acute heart-failure management | D8: C_IHD | E8: ihd | F8: Ischemic heart disease | G8: sick_hf | H8: dead_ihd | I8: case_fatality | J8: 0.18 | K8: 0.05 | L8: 0.31 | M8: 0.8 | N8: 2025 | O8: 2050 | P8: =IF(OR(J8="",K8="",L8="",M8=""),"",ROUND(K8*(J8*(M8-L8)/(1-J8*L8)),4)) | Q8: I_HF_ACUTE__C_IHD | R8: cause-specific | S8: Provisional | T8: Provisional | U8: =COUNTIF($B$2:$B$17,B8) | V8: =IF(U8=1,"OK","DUPLICATE KEY")
A9: I_HF_CHRONIC | B9: I_HF_CHRONIC__C_CMP | C9: Chronic heart-failure management | D9: C_CMP | E9: cmd | F9: Cardiomyopathy and myocarditis | G9: sick_hf | H9: dead_cmp | I9: case_fatality | J9: 0.536 | K9: 0.8 | L9: 0.31 | M9: 0.8 | N9: 2025 | O9: 2050 | P9: =IF(OR(J9="",K9="",L9="",M9=""),"",ROUND(K9*(J9*(M9-L9)/(1-J9*L9)),4)) | Q9: I_HF_CHRONIC__C_CMP | R9: cause-specific | S9: Provisional | T9: Provisional | U9: =COUNTIF($B$2:$B$17,B9) | V9: =IF(U9=1,"OK","DUPLICATE KEY")
A10: I_HF_CHRONIC | B10: I_HF_CHRONIC__C_HHD | C10: Chronic heart-failure management | D10: C_HHD | E10: hhd | F10: Hypertensive heart disease | G10: sick_hf | H10: dead_hhd | I10: case_fatality | J10: 0.275 | K10: 0.8 | L10: 0.31 | M10: 0.8 | N10: 2025 | O10: 2050 | P10: =IF(OR(J10="",K10="",L10="",M10=""),"",ROUND(K10*(J10*(M10-L10)/(1-J10*L10)),4)) | Q10: I_HF_CHRONIC__C_HHD | R10: cause-specific | S10: Provisional | T10: Provisional | U10: =COUNTIF($B$2:$B$17,B10) | V10: =IF(U10=1,"OK","DUPLICATE KEY")
A11: I_HF_CHRONIC | B11: I_HF_CHRONIC__C_IHD | C11: Chronic heart-failure management | D11: C_IHD | E11: ihd | F11: Ischemic heart disease | G11: sick_hf | H11: dead_ihd | I11: case_fatality | J11: 0.093 | K11: 0.2 | L11: 0.31 | M11: 0.8 | N11: 2025 | O11: 2050 | P11: =IF(OR(J11="",K11="",L11="",M11=""),"",ROUND(K11*(J11*(M11-L11)/(1-J11*L11)),4)) | Q11: I_HF_CHRONIC__C_IHD | R11: cause-specific | S11: Provisional | T11: Provisional | U11: =COUNTIF($B$2:$B$17,B11) | V11: =IF(U11=1,"OK","DUPLICATE KEY")
A12: I_IHD_ACUTE | B12: I_IHD_ACUTE__C_IHD | C12: Treatment of acute coronary syndromes | D12: C_IHD | E12: ihd | F12: Ischemic heart disease | G12: sick | H12: dead_ihd | I12: case_fatality | J12: 0.2812 | K12: 0.5 | L12: 0.2 | M12: 0.8 | N12: 2025 | O12: 2050 | P12: =IF(OR(J12="",K12="",L12="",M12=""),"",ROUND(K12*(J12*(M12-L12)/(1-J12*L12)),4)) | Q12: I_IHD_ACUTE__C_IHD | R12: cause-specific | S12: Provisional | T12: Provisional | U12: =COUNTIF($B$2:$B$17,B12) | V12: =IF(U12=1,"OK","DUPLICATE KEY")
A13: I_IHD_SECONDARY | B13: I_IHD_SECONDARY__C_IHD | C13: Secondary prevention of ischemic heart disease | D13: C_IHD | E13: ihd | F13: Ischemic heart disease | G13: sick | H13: dead_ihd | I13: case_fatality | J13: 0.5822 | K13: 0.2 | L13: 0.31 | M13: 0.8 | N13: 2025 | O13: 2050 | P13: =IF(OR(J13="",K13="",L13="",M13=""),"",ROUND(K13*(J13*(M13-L13)/(1-J13*L13)),4)) | Q13: I_IHD_SECONDARY__C_IHD | R13: cause-specific | S13: Provisional | T13: Provisional | U13: =COUNTIF($B$2:$B$17,B13) | V13: =IF(U13=1,"OK","DUPLICATE KEY")
... A17: I_T2D_TREATMENT | B17: I_T2D_TREATMENT__C_IHD | C17: Longitudinal treatment of type 2 diabetes | D17: C_IHD | E17: ihd | F17: Ischemic heart disease | G17: sick | H17: dead_ihd | I17: case_fatality | J17: 0.15 | K17: 0.15 | L17: 0.16 | M17: 0.8 | N17: 2025 | O17: 2050 | P17: =IF(OR(J17="",K17="",L17="",M17=""),"",ROUND(K17*(J17*(M17-L17)/(1-J17*L17)),4)) | Q17: I_T2D_TREATMENT__C_T2D | R17: shared-count-once | S17: Review | T17: Provisional | U17: =COUNTIF($B$2:$B$17,B17) | V17: =IF(U17=1,"OK","DUPLICATE KEY")

Sheet Cost_Components
A1: cost_record_id | B1: cost_component_key | C1: cost_option | D1: intervention_id | E1: cause_id | F1: cause_code | G1: cost_join_key | H1: cost_scope | I1: cost_component | J1: population_in_need_measure | K1: population_in_need_fraction | L1: frequency_per_year | M1: c_age_start | N1: c_age_stop | O1: c_sex | P1: unit_cost_usd | Q1: price_year | R1: indonesia_adjusted_flag | S1: cov_baseline | T1: cov_target | U1: cov_start_year | V1: cov_target_year | W1: cost_review | X1: cost_ready
A2: COST_PRIMARY_TX_B | B2: CC_PRIMARY_HTN_STATIN | C2: Option B | D2: I_CVD_PRIMARY | E2: C_SHARED | G2: I_CVD_PRIMARY__C_SHARED | H2: shared-count-once | I2: Antihypertensives and statins for absolute CVD risk >20% | J2: all | K2: 0.3 | L2: 1 | M2: 30 | N2: 95 | O2: Both | P2: 40.487719 | Q2: 2023 | R2: 1 | S2: =IFERROR(INDEX('Selected_Interventions'!$L$2:$L$17,MATCH(G2,'Selected_Interventions'!$Q$2:$Q$17,0)),"") | T2: =IFERROR(INDEX('Selected_Interventions'!$M$2:$M$17,MATCH(G2,'Selected_Interventions'!$Q$2:$Q$17,0)),"") | U2: =IFERROR(INDEX('Selected_Interventions'!$N$2:$N$17,MATCH(G2,'Selected_Interventions'!$Q$2:$Q$17,0)),"") | V2: =IFERROR(INDEX('Selected_Interventions'!$O$2:$O$17,MATCH(G2,'Selected_Interventions'!$Q$2:$Q$17,0)),"") | W2: Alternative | X2: =IF(AND(P2<>"",P2>=0,S2<>"",K2<>"",K2>=0,K2<=1,OR(J2="all",J2="prevalence",J2="incidence")),1,0)
A3: COST_PRIMARY_SCREEN_B | B3: CC_PRIMARY_SCREENING | C3: Option B | D3: I_CVD_PRIMARY | E3: C_SHARED | G3: I_CVD_PRIMARY__C_SHARED | H3: shared-count-once | I3: CVD targeted screening | J3: all | K3: 0.2 | L3: 1 | M3: 30 | N3: 95 | O3: Both | P3: 2.7665219 | Q3: 2023 | R3: 1 | S3: =IFERROR(INDEX('Selected_Interventions'!$L$2:$L$17,MATCH(G3,'Selected_Interventions'!$Q$2:$Q$17,0)),"") | T3: =IFERROR(INDEX('Selected_Interventions'!$M$2:$M$17,MATCH(G3,'Selected_Interventions'!$Q$2:$Q$17,0)),"") | U3: =IFERROR(INDEX('Selected_Interventions'!$N$2:$N$17,MATCH(G3,'Selected_Interventions'!$Q$2:$Q$17,0)),"") | V3: =IFERROR(INDEX('Selected_Interventions'!$O$2:$O$17,MATCH(G3,'Selected_Interventions'!$Q$2:$Q$17,0)),"") | W3: Alternative | X3: =IF(AND(P3<>"",P3>=0,S3<>"",K3<>"",K3>=0,K3<=1,OR(J3="all",J3="prevalence",J3="incidence")),1,0)
A4: COST_HF_ACUTE_C_CMP | B4: CC_HF_ACUTE_C_CMP | C4: Base | D4: I_HF_ACUTE | E4: C_CMP | F4: cmd | G4: I_HF_ACUTE__C_CMP | H4: cause-specific | I4: Acute heart-failure management package | J4: prevalence | K4: 0.5 | L4: 1 | M4: 30 | N4: 95 | O4: Both | P4: 475 | Q4: 2023 | R4: 1 | S4: =IFERROR(INDEX('Selected_Interventions'!$L$2:$L$17,MATCH(G4,'Selected_Interventions'!$Q$2:$Q$17,0)),"") | T4: =IFERROR(INDEX('Selected_Interventions'!$M$2:$M$17,MATCH(G4,'Selected_Interventions'!$Q$2:$Q$17,0)),"") | U4: =IFERROR(INDEX('Selected_Interventions'!$N$2:$N$17,MATCH(G4,'Selected_Interventions'!$Q$2:$Q$17,0)),"") | V4: =IFERROR(INDEX('Selected_Interventions'!$O$2:$O$17,MATCH(G4,'Selected_Interventions'!$Q$2:$Q$17,0)),"") | W4: Provisional | X4: =IF(AND(P4<>"",P4>=0,S4<>"",K4<>"",K4>=0,K4<=1,OR(J4="all",J4="prevalence",J4="incidence")),1,0)
A5: COST_HF_ACUTE_C_HHD | B5: CC_HF_ACUTE_C_HHD | C5: Base | D5: I_HF_ACUTE | E5: C_HHD | F5: hhd | G5: I_HF_ACUTE__C_HHD | H5: cause-specific | I5: Acute heart-failure management package | J5: prevalence | K5: 0.5 | L5: 1 | M5: 30 | N5: 95 | O5: Both | P5: 475 | Q5: 2023 | R5: 1 | S5: =IFERROR(INDEX('Selected_Interventions'!$L$2:$L$17,MATCH(G5,'Selected_Interventions'!$Q$2:$Q$17,0)),"") | T5: =IFERROR(INDEX('Selected_Interventions'!$M$2:$M$17,MATCH(G5,'Selected_Interventions'!$Q$2:$Q$17,0)),"") | U5: =IFERROR(INDEX('Selected_Interventions'!$N$2:$N$17,MATCH(G5,'Selected_Interventions'!$Q$2:$Q$17,0)),"") | V5: =IFERROR(INDEX('Selected_Interventions'!$O$2:$O$17,MATCH(G5,'Selected_Interventions'!$Q$2:$Q$17,0)),"") | W5: Provisional | X5: =IF(AND(P5<>"",P5>=0,S5<>"",K5<>"",K5>=0,K5<=1,OR(J5="all",J5="prevalence",J5="incidence")),1,0)
A6: COST_HF_ACUTE_C_IHD | B6: CC_HF_ACUTE_C_IHD | C6: Base | D6: I_HF_ACUTE | E6: C_IHD | F6: ihd | G6: I_HF_ACUTE__C_IHD | H6: cause-specific | I6: Acute heart-failure management package | J6: prevalence | K6: 0.1 | L6: 1 | M6: 30 | N6: 95 | O6: Both | P6: 475 | Q6: 2023 | R6: 1 | S6: =IFERROR(INDEX('Selected_Interventions'!$L$2:$L$17,MATCH(G6,'Selected_Interventions'!$Q$2:$Q$17,0)),"") | T6: =IFERROR(INDEX('Selected_Interventions'!$M$2:$M$17,MATCH(G6,'Selected_Interventions'!$Q$2:$Q$17,0)),"") | U6: =IFERROR(INDEX('Selected_Interventions'!$N$2:$N$17,MATCH(G6,'Selected_Interventions'!$Q$2:$Q$17,0)),"") | V6: =IFERROR(INDEX('Selected_Interventions'!$O$2:$O$17,MATCH(G6,'Selected_Interventions'!$Q$2:$Q$17,0)),"") | W6: Provisional | X6: =IF(AND(P6<>"",P6>=0,S6<>"",K6<>"",K6>=0,K6<=1,OR(J6="all",J6="prevalence",J6="incidence")),1,0)
A7: COST_HF_CHRONIC_CMP_ECHO | B7: CC_HF_CHRONIC_CMP_ECHO | C7: Base | D7: I_HF_CHRONIC | E7: C_CMP | F7: cmd | G7: I_HF_CHRONIC__C_CMP | H7: cause-specific | I7: One cardiac echo per year | J7: prevalence | K7: 1 | L7: 1 | M7: 0 | N7: 95 | O7: Both | P7: 20 | Q7: 2023 | R7: 1 | S7: =IFERROR(INDEX('Selected_Interventions'!$L$2:$L$17,MATCH(G7,'Selected_Interventions'!$Q$2:$Q$17,0)),"") | T7: =IFERROR(INDEX('Selected_Interventions'!$M$2:$M$17,MATCH(G7,'Selected_Interventions'!$Q$2:$Q$17,0)),"") | U7: =IFERROR(INDEX('Selected_Interventions'!$N$2:$N$17,MATCH(G7,'Selected_Interventions'!$Q$2:$Q$17,0)),"") | V7: =IFERROR(INDEX('Selected_Interventions'!$O$2:$O$17,MATCH(G7,'Selected_Interventions'!$Q$2:$Q$17,0)),"") | W7: Provisional | X7: =IF(AND(P7<>"",P7>=0,S7<>"",K7<>"",K7>=0,K7<=1,OR(J7="all",J7="prevalence",J7="incidence")),1,0)
A8: COST_HF_CHRONIC_CMP_LAB_B | B8: CC_HF_CHRONIC_CMP_FOLLOWUP | C8: Option B | D8: I_HF_CHRONIC | E8: C_CMP | F8: cmd | G8: I_HF_CHRONIC__C_CMP | H8: cause-specific | I8: Lab tests and follow-up visits | J8: prevalence | K8: 1 | L8: 1 | M8: 0 | N8: 95 | O8: Both | P8: 64.943441 | Q8: 2023 | R8: 1 | S8: =IFERROR(INDEX('Selected_Interventions'!$L$2:$L$17,MATCH(G8,'Selected_Interventions'!$Q$2:$Q$17,0)),"") | T8: =IFERROR(INDEX('Selected_Interventions'!$M$2:$M$17,MATCH(G8,'Selected_Interventions'!$Q$2:$Q$17,0)),"") | U8: =IFERROR(INDEX('Selected_Interventions'!$N$2:$N$17,MATCH(G8,'Selected_Interventions'!$Q$2:$Q$17,0)),"") | V8: =IFERROR(INDEX('Selected_Interventions'!$O$2:$O$17,MATCH(G8,'Selected_Interventions'!$Q$2:$Q$17,0)),"") | W8: Alternative | X8: =IF(AND(P8<>"",P8>=0,S8<>"",K8<>"",K8>=0,K8<=1,OR(J8="all",J8="prevalence",J8="incidence")),1,0)
A9: COST_HF_CHRONIC_CMP_TX | B9: CC_HF_CHRONIC_CMP_TREATMENT | C9: Base | D9: I_HF_CHRONIC | E9: C_CMP | F9: cmd | G9: I_HF_CHRONIC__C_CMP | H9: cause-specific | I9: Treatment of heart failure | J9: prevalence | K9: 1 | L9: 1 | M9: 0 | N9: 95 | O9: Both | P9: 115.10623 | Q9: 2023 | R9: 1 | S9: =IFERROR(INDEX('Selected_Interventions'!$L$2:$L$17,MATCH(G9,'Selected_Interventions'!$Q$2:$Q$17,0)),"") | T9: =IFERROR(INDEX('Selected_Interventions'!$M$2:$M$17,MATCH(G9,'Selected_Interventions'!$Q$2:$Q$17,0)),"") | U9: =IFERROR(INDEX('Selected_Interventions'!$N$2:$N$17,MATCH(G9,'Selected_Interventions'!$Q$2:$Q$17,0)),"") | V9: =IFERROR(INDEX('Selected_Interventions'!$O$2:$O$17,MATCH(G9,'Selected_Interventions'!$Q$2:$Q$17,0)),"") | W9: Provisional | X9: =IF(AND(P9<>"",P9>=0,S9<>"",K9<>"",K9>=0,K9<=1,OR(J9="all",J9="prevalence",J9="incidence")),1,0)
A10: COST_HF_CHRONIC_HHD_ECHO | B10: CC_HF_CHRONIC_HHD_ECHO | C10: Base | D10: I_HF_CHRONIC | E10: C_HHD | F10: hhd | G10: I_HF_CHRONIC__C_HHD | H10: cause-specific | I10: One cardiac echo per year | J10: prevalence | K10: 1 | L10: 1 | M10: 30 | N10: 95 | O10: Both | P10: 20 | Q10: 2023 | R10: 1 | S10: =IFERROR(INDEX('Selected_Interventions'!$L$2:$L$17,MATCH(G10,'Selected_Interventions'!$Q$2:$Q$17,0)),"") | T10: =IFERROR(INDEX('Selected_Interventions'!$M$2:$M$17,MATCH(G10,'Selected_Interventions'!$Q$2:$Q$17,0)),"") | U10: =IFERROR(INDEX('Selected_Interventions'!$N$2:$N$17,MATCH(G10,'Selected_Interventions'!$Q$2:$Q$17,0)),"") | V10: =IFERROR(INDEX('Selected_Interventions'!$O$2:$O$17,MATCH(G10,'Selected_Interventions'!$Q$2:$Q$17,0)),"") | W10: Provisional | X10: =IF(AND(P10<>"",P10>=0,S10<>"",K10<>"",K10>=0,K10<=1,OR(J10="all",J10="prevalence",J10="incidence")),1,0)
A11: COST_HF_CHRONIC_HHD_LAB_B | B11: CC_HF_CHRONIC_HHD_FOLLOWUP | C11: Option B | D11: I_HF_CHRONIC | E11: C_HHD | F11: hhd | G11: I_HF_CHRONIC__C_HHD | H11: cause-specific | I11: Lab tests and follow-up visits | J11: prevalence | K11: 1 | L11: 1 | M11: 30 | N11: 95 | O11: Both | P11: 64.943441 | Q11: 2023 | R11: 1 | S11: =IFERROR(INDEX('Selected_Interventions'!$L$2:$L$17,MATCH(G11,'Selected_Interventions'!$Q$2:$Q$17,0)),"") | T11: =IFERROR(INDEX('Selected_Interventions'!$M$2:$M$17,MATCH(G11,'Selected_Interventions'!$Q$2:$Q$17,0)),"") | U11: =IFERROR(INDEX('Selected_Interventions'!$N$2:$N$17,MATCH(G11,'Selected_Interventions'!$Q$2:$Q$17,0)),"") | V11: =IFERROR(INDEX('Selected_Interventions'!$O$2:$O$17,MATCH(G11,'Selected_Interventions'!$Q$2:$Q$17,0)),"") | W11: Alternative | X11: =IF(AND(P11<>"",P11>=0,S11<>"",K11<>"",K11>=0,K11<=1,OR(J11="all",J11="prevalence",J11="incidence")),1,0)
A12: COST_HF_CHRONIC_HHD_TX | B12: CC_HF_CHRONIC_HHD_TREATMENT | C12: Base | D12: I_HF_CHRONIC | E12: C_HHD | F12: hhd | G12: I_HF_CHRONIC__C_HHD | H12: cause-specific | I12: Treatment of heart failure | J12: prevalence | K12: 1 | L12: 1 | M12: 0 | N12: 95 | O12: Both | P12: 115.10623 | Q12: 2023 | R12: 1 | S12: =IFERROR(INDEX('Selected_Interventions'!$L$2:$L$17,MATCH(G12,'Selected_Interventions'!$Q$2:$Q$17,0)),"") | T12: =IFERROR(INDEX('Selected_Interventions'!$M$2:$M$17,MATCH(G12,'Selected_Interventions'!$Q$2:$Q$17,0)),"") | U12: =IFERROR(INDEX('Selected_Interventions'!$N$2:$N$17,MATCH(G12,'Selected_Interventions'!$Q$2:$Q$17,0)),"") | V12: =IFERROR(INDEX('Selected_Interventions'!$O$2:$O$17,MATCH(G12,'Selected_Interventions'!$Q$2:$Q$17,0)),"") | W12: Provisional | X12: =IF(AND(P12<>"",P12>=0,S12<>"",K12<>"",K12>=0,K12<=1,OR(J12="all",J12="prevalence",J12="incidence")),1,0)
A13: COST_HF_CHRONIC_IHD_ECHO | B13: CC_HF_CHRONIC_IHD_ECHO | C13: Base | D13: I_HF_CHRONIC | E13: C_IHD | F13: ihd | G13: I_HF_CHRONIC__C_IHD | H13: cause-specific | I13: One cardiac echo per year | J13: prevalence | K13: 0.2 | L13: 1 | M13: 30 | N13: 95 | O13: Both | P13: 20 | Q13: 2023 | R13: 1 | S13: =IFERROR(INDEX('Selected_Interventions'!$L$2:$L$17,MATCH(G13,'Selected_Interventions'!$Q$2:$Q$17,0)),"") | T13: =IFERROR(INDEX('Selected_Interventions'!$M$2:$M$17,MATCH(G13,'Selected_Interventions'!$Q$2:$Q$17,0)),"") | U13: =IFERROR(INDEX('Selected_Interventions'!$N$2:$N$17,MATCH(G13,'Selected_Interventions'!$Q$2:$Q$17,0)),"") | V13: =IFERROR(INDEX('Selected_Interventions'!$O$2:$O$17,MATCH(G13,'Selected_Interventions'!$Q$2:$Q$17,0)),"") | W13: Provisional | X13: =IF(AND(P13<>"",P13>=0,S13<>"",K13<>"",K13>=0,K13<=1,OR(J13="all",J13="prevalence",J13="incidence")),1,0)
A14: COST_HF_CHRONIC_IHD_LAB | B14: CC_HF_CHRONIC_IHD_FOLLOWUP | C14: Missing | D14: I_HF_CHRONIC | E14: C_IHD | F14: ihd | G14: I_HF_CHRONIC__C_IHD | H14: cause-specific | I14: Lab tests and follow-up visits | J14: prevalence | K14: 0.2 | L14: 1 | M14: 30 | N14: 95 | O14: Both | P14: 7 | Q14: 2023 | R14: 1 | S14: =IFERROR(INDEX('Selected_Interventions'!$L$2:$L$17,MATCH(G14,'Selected_Interventions'!$Q$2:$Q$17,0)),"") | T14: =IFERROR(INDEX('Selected_Interventions'!$M$2:$M$17,MATCH(G14,'Selected_Interventions'!$Q$2:$Q$17,0)),"") | U14: =IFERROR(INDEX('Selected_Interventions'!$N$2:$N$17,MATCH(G14,'Selected_Interventions'!$Q$2:$Q$17,0)),"") | V14: =IFERROR(INDEX('Selected_Interventions'!$O$2:$O$17,MATCH(G14,'Selected_Interventions'!$Q$2:$Q$17,0)),"") | W14: Missing input | X14: =IF(AND(P14<>"",P14>=0,S14<>"",K14<>"",K14>=0,K14<=1,OR(J14="all",J14="prevalence",J14="incidence")),1,0)
A15: COST_HF_CHRONIC_IHD_TX | B15: CC_HF_CHRONIC_IHD_TREATMENT | C15: Base | D15: I_HF_CHRONIC | E15: C_IHD | F15: ihd | G15: I_HF_CHRONIC__C_IHD | H15: cause-specific | I15: Treatment of heart failure | J15: prevalence | K15: 0.2 | L15: 1 | M15: 30 | N15: 95 | O15: Both | P15: 29.216219 | Q15: 2023 | R15: 1 | S15: =IFERROR(INDEX('Selected_Interventions'!$L$2:$L$17,MATCH(G15,'Selected_Interventions'!$Q$2:$Q$17,0)),"") | T15: =IFERROR(INDEX('Selected_Interventions'!$M$2:$M$17,MATCH(G15,'Selected_Interventions'!$Q$2:$Q$17,0)),"") | U15: =IFERROR(INDEX('Selected_Interventions'!$N$2:$N$17,MATCH(G15,'Selected_Interventions'!$Q$2:$Q$17,0)),"") | V15: =IFERROR(INDEX('Selected_Interventions'!$O$2:$O$17,MATCH(G15,'Selected_Interventions'!$Q$2:$Q$17,0)),"") | W15: Provisional | X15: =IF(AND(P15<>"",P15>=0,S15<>"",K15<>"",K15>=0,K15<=1,OR(J15="all",J15="prevalence",J15="incidence")),1,0)
... A28: COST_T2D_SCREENING | B28: CC_T2D_SCREENING | C28: Base | D28: I_T2D_TREATMENT | E28: C_T2D | F28: dm2 | G28: I_T2D_TREATMENT__C_T2D | H28: cause-specific | I28: Diabetes opportunistic screening | J28: all | K28: 1e-05 | L28: 1 | M28: 30 | N28: 95 | O28: Both | P28: 0.70495848 | Q28: 2023 | R28: 1 | S28: =IFERROR(INDEX('Selected_Interventions'!$L$2:$L$17,MATCH(G28,'Selected_Interventions'!$Q$2:$Q$17,0)),"") | T28: =IFERROR(INDEX('Selected_Interventions'!$M$2:$M$17,MATCH(G28,'Selected_Interventions'!$Q$2:$Q$17,0)),"") | U28: =IFERROR(INDEX('Selected_Interventions'!$N$2:$N$17,MATCH(G28,'Selected_Interventions'!$Q$2:$Q$17,0)),"") | V28: =IFERROR(INDEX('Selected_Interventions'!$O$2:$O$17,MATCH(G28,'Selected_Interventions'!$Q$2:$Q$17,0)),"") | W28: Provisional | X28: =IF(AND(P28<>"",P28>=0,S28<>"",K28<>"",K28>=0,K28<=1,OR(J28="all",J28="prevalence",J28="incidence")),1,0)

Sheet Annual_Mortality
A1: scenario | B1: scenario_label | C1: year | D1: cause | E1: cases | F1: cause_deaths | G1: base_deaths | H1: deaths_averted | I1: base_cases | J1: cases_averted
A2: I_CVD_PRIMARY | B2: Primary prevention of CVD | C2: 2025 | D2: cmd | E2: 11293.859 | F2: 8456.0911 | G2: 8456.0911 | H2: =G2-F2 | I2: 11293.859 | J2: =I2-E2
A3: I_CVD_PRIMARY | B3: Primary prevention of CVD | C3: 2025 | D3: dm2 | E3: 796801.79 | F3: 124437.1 | G3: 124437.1 | H3: =G3-F3 | I3: 796801.79 | J3: =I3-E3
A4: I_CVD_PRIMARY | B4: Primary prevention of CVD | C4: 2025 | D4: hhd | E4: 109645.69 | F4: 70978.798 | G4: 70978.798 | H4: =G4-F4 | I4: 110599.34 | J4: =I4-E4
A5: I_CVD_PRIMARY | B5: Primary prevention of CVD | C5: 2025 | D5: hstroke | E5: 267826.2 | F5: 250549.93 | G5: 250549.93 | H5: =G5-F5 | I5: 269908.91 | J5: =I5-E5
A6: I_CVD_PRIMARY | B6: Primary prevention of CVD | C6: 2025 | D6: ihd | E6: 599698.41 | F6: 336235.04 | G6: 336235.04 | H6: =G6-F6 | I6: 605290.56 | J6: =I6-E6
A7: I_CVD_PRIMARY | B7: Primary prevention of CVD | C7: 2025 | D7: istroke | E7: 326007.22 | F7: 165181.23 | G7: 165181.23 | H7: =G7-F7 | I7: 328703.7 | J7: =I7-E7
A8: I_CVD_PRIMARY | B8: Primary prevention of CVD | C8: 2025 | D8: rhd | E8: 12601.519 | F8: 3955.3071 | G8: 3955.3071 | H8: =G8-F8 | I8: 12601.519 | J8: =I8-E8
A9: I_CVD_PRIMARY | B9: Primary prevention of CVD | C9: 2026 | D9: cmd | E9: 11413.94 | F9: 8503.0488 | G9: 8503.0488 | H9: =G9-F9 | I9: 11413.94 | J9: =I9-E9
A10: I_CVD_PRIMARY | B10: Primary prevention of CVD | C10: 2026 | D10: dm2 | E10: 813844.57 | F10: 128333.95 | G10: 128333.95 | H10: =G10-F10 | I10: 813844.57 | J10: =I10-E10
A11: I_CVD_PRIMARY | B11: Primary prevention of CVD | C11: 2026 | D11: hhd | E11: 111300.85 | F11: 72202.279 | G11: 72339.688 | H11: =G11-F11 | I11: 113261.47 | J11: =I11-E11
A12: I_CVD_PRIMARY | B12: Primary prevention of CVD | C12: 2026 | D12: hstroke | E12: 269967.39 | F12: 254049.92 | G12: 254910.75 | H12: =G12-F12 | I12: 274200.58 | J12: =I12-E12
A13: I_CVD_PRIMARY | B13: Primary prevention of CVD | C13: 2026 | D13: ihd | E13: 608641.54 | F13: 344584.48 | G13: 344917.06 | H13: =G13-F13 | I13: 620097.59 | J13: =I13-E13
... A1639: baseline | B1639: Baseline (no new intervention) | C1639: 2050 | D1639: rhd | E1639: 11458.332 | F1639: 1051.1139 | G1639: 1051.1139 | H1639: =G1639-F1639 | I1639: 11458.332 | J1639: =I1639-E1639

Sheet Health_Outcomes
A1: scenario | B1: scenario_label | C1: year | D1: modeled_deaths | E1: baseline_deaths | F1: deaths_averted | G1: modeled_cases | H1: baseline_cases | I1: cases_averted | J1: yll | K1: base_yll | L1: yll_averted | M1: yld | N1: base_yld | O1: yld_averted | P1: daly | Q1: base_daly | R1: dalys_averted | S1: life_years_gained
A2: all | B2: All selected interventions (combined) | C2: 2025 | D2: 956104.48 | E2: 959793.5 | F2: =E2-D2 | G2: 2123874.7 | H2: 2135199.7 | I2: =H2-G2 | J2: 13023884 | K2: 13078631 | L2: =K2-J2 | M2: 2438887.3 | N2: 2439867.8 | O2: =N2-M2 | P2: 15462771 | Q2: 15518499 | R2: =Q2-P2 | S2: =L2
A3: all | B3: All selected interventions (combined) | C3: 2026 | D3: 972035.78 | E3: 980780.31 | F3: =E3-D3 | G3: 2157946 | H3: 2181019.5 | I3: =H3-G3 | J3: 13248926 | K3: 13376482 | L3: =K3-J3 | M3: 2492339.1 | N3: 2495093.1 | O3: =N3-M3 | P3: 15741265 | Q3: 15871576 | R3: =Q3-P3 | S3: =L3
A4: all | B4: All selected interventions (combined) | C4: 2027 | D4: 988622.75 | E4: 1003320.8 | F4: =E4-D4 | G4: 2193121.1 | H4: 2228341.8 | I4: =H4-G4 | J4: 13463760 | K4: 13677395 | L4: =K4-J4 | M4: 2546012 | N4: 2551241 | O4: =N4-M4 | P4: 16009772 | Q4: 16228636 | R4: =Q4-P4 | S4: =L4
A5: all | B5: All selected interventions (combined) | C5: 2028 | D5: 1006065.7 | E5: 1027500.5 | F5: =E5-D5 | G5: 2240047 | H5: 2288120.7 | I5: =H5-G5 | J5: 13662648 | K5: 13973850 | L5: =K5-J5 | M5: 2600748.7 | N5: 2609119.5 | O5: =N5-M5 | P5: 16263397 | Q5: 16582969 | R5: =Q5-P5 | S5: =L5
A6: all | B6: All selected interventions (combined) | C6: 2029 | D6: 1024672.5 | E6: 1053610.4 | F6: =E6-D6 | G6: 2275548.3 | H6: 2336688.1 | I6: =H6-G6 | J6: 13870988 | K6: 14290695 | L6: =K6-J6 | M6: 2655281.6 | N6: 2667387.1 | O6: =N6-M6 | P6: 16526269 | Q6: 16958082 | R6: =Q6-P6 | S6: =L6
A7: all | B7: All selected interventions (combined) | C7: 2030 | D7: 1043719.7 | E7: 1080810.2 | F7: =E7-D7 | G7: 2312077.4 | H7: 2386448.8 | I7: =H7-G7 | J7: 14063696 | K7: 14601429 | L7: =K7-J7 | M7: 2709572.6 | N7: 2725934.8 | O7: =N7-M7 | P7: 16773269 | Q7: 17327364 | R7: =Q7-P7 | S7: =L7
A8: all | B8: All selected interventions (combined) | C8: 2031 | D8: 1061393.7 | E8: 1107157.6 | F8: =E8-D8 | G8: 2347388.5 | H8: 2435295.4 | I8: =H8-G8 | J8: 14246471 | K8: 14910263 | L8: =K8-J8 | M8: 2763634.3 | N8: 2784742.8 | O8: =N8-M8 | P8: 17010106 | Q8: 17695005 | R8: =Q8-P8 | S8: =L8
A9: all | B9: All selected interventions (combined) | C9: 2032 | D9: 1079033.1 | E9: 1133979.8 | F9: =E9-D9 | G9: 2384515.5 | H9: 2486226.9 | I9: =H9-G9 | J9: 14415633 | K9: 15212725 | L9: =K9-J9 | M9: 2817579.3 | N9: 2843886.5 | O9: =N9-M9 | P9: 17233212 | Q9: 18056611 | R9: =Q9-P9 | S9: =L9
A10: all | B10: All selected interventions (combined) | C10: 2033 | D10: 1095945.5 | E10: 1160519 | F10: =E10-D10 | G10: 2428027.3 | H10: 2544179.9 | I10: =H10-G10 | J10: 14561427 | K10: 15498147 | L10: =K10-J10 | M10: 2871971.4 | N10: 2903939 | O10: =N10-M10 | P10: 17433399 | Q10: 18402086 | R10: =Q10-P10 | S10: =L10
A11: all | B11: All selected interventions (combined) | C11: 2034 | D11: 1112752.9 | E11: 1187394.6 | F11: =E11-D11 | G11: 2460942.3 | H11: 2591241.8 | I11: =H11-G11 | J11: 14715676 | K11: 15799428 | L11: =K11-J11 | M11: 2925880 | N11: 2963891.1 | O11: =N11-M11 | P11: 17641556 | Q11: 18763320 | R11: =Q11-P11 | S11: =L11
A12: all | B12: All selected interventions (combined) | C12: 2035 | D12: 1129198.6 | E12: 1214326 | F12: =E12-D12 | G12: 2492871.2 | H12: 2637338.6 | I12: =H12-G12 | J12: 14856644 | K12: 16093446 | L12: =K12-J12 | M12: 2979169.9 | N12: 3023565.8 | O12: =N12-M12 | P12: 17835814 | Q12: 19117012 | R12: =Q12-P12 | S12: =L12
A13: all | B13: All selected interventions (combined) | C13: 2036 | D13: 1145993.2 | E13: 1242005.2 | F13: =E13-D13 | G13: 2528880.9 | H13: 2687815.4 | I13: =H13-G13 | J13: 14991946 | K13: 16387284 | L13: =K13-J13 | M13: 3032101.1 | N13: 3083207.2 | O13: =N13-M13 | P13: 18024047 | Q13: 19470491 | R13: =Q13-P13 | S13: =L13
... A209: I_T2D_TREATMENT | B209: Longitudinal treatment of type 2 diabetes | C209: 2050 | D209: 1563171.1 | E209: 1604008.5 | F209: =E209-D209 | G209: 3268647.8 | H209: 3257199.3 | I209: =H209-G209 | J209: 19040770 | K209: 19570013 | L209: =K209-J209 | M209: 3878765.6 | N209: 3846594.4 | O209: =N209-M209 | P209: 22919536 | Q209: 23416608 | R209: =Q209-P209 | S209: =L209

Sheet CVD_40q30
A1: location | B1: scenario | C1: scenario_label | D1: intervention_family | E1: scenario_role | F1: parent_package_id | G1: htn_target_scenario | H1: year | I1: cvd_40q30 | J1: baseline_cvd_40q30 | K1: absolute_reduction_pp | L1: percent_reduction | M1: cvd_40q30_r | N1: recon_status
A2: Indonesia | B2: I_CVD_PRIMARY | C2: Primary prevention of CVD | D2: clinical | G2: htncov2_aspirational | H2: 2025 | I2: =100*(1-(SUMIFS('CVD_40q30_Age'!$M$2:$M$9361,'CVD_40q30_Age'!$A$2:$A$9361,A2,'CVD_40q30_Age'!$B$2:$B$9361,B2,'CVD_40q30_Age'!$E$2:$E$9361,G2,'CVD_40q30_Age'!$F$2:$F$9361,H2,'CVD_40q30_Age'!$G$2:$G$9361,69))/(SUMIFS('CVD_40q30_Age'!$L$2:$L$9361,'CVD_40q30_Age'!$A$2:$A$9361,A2,'CVD_40q30_Age'!$B$2:$B$9361,B2,'CVD_40q30_Age'!$E$2:$E$9361,G2,'CVD_40q30_Age'!$F$2:$F$9361,H2,'CVD_40q30_Age'!$G$2:$G$9361,30))) | J2: =SUMIFS($I$2:$I$235,$A$2:$A$235,A2,$G$2:$G$235,G2,$H$2:$H$235,H2,$B$2:$B$235,"baseline") | K2: =J2-I2 | L2: =IF(J2=0,"",100*(J2-I2)/J2) | M2: 14.594863 | N2: =IF(ABS(I2-M2)<=0.001,"match","mismatch")
A3: Indonesia | B3: I_CVD_PRIMARY | C3: Primary prevention of CVD | D3: clinical | G3: htncov2_aspirational | H3: 2026 | I3: =100*(1-(SUMIFS('CVD_40q30_Age'!$M$2:$M$9361,'CVD_40q30_Age'!$A$2:$A$9361,A3,'CVD_40q30_Age'!$B$2:$B$9361,B3,'CVD_40q30_Age'!$E$2:$E$9361,G3,'CVD_40q30_Age'!$F$2:$F$9361,H3,'CVD_40q30_Age'!$G$2:$G$9361,69))/(SUMIFS('CVD_40q30_Age'!$L$2:$L$9361,'CVD_40q30_Age'!$A$2:$A$9361,A3,'CVD_40q30_Age'!$B$2:$B$9361,B3,'CVD_40q30_Age'!$E$2:$E$9361,G3,'CVD_40q30_Age'!$F$2:$F$9361,H3,'CVD_40q30_Age'!$G$2:$G$9361,30))) | J3: =SUMIFS($I$2:$I$235,$A$2:$A$235,A3,$G$2:$G$235,G3,$H$2:$H$235,H3,$B$2:$B$235,"baseline") | K3: =J3-I3 | L3: =IF(J3=0,"",100*(J3-I3)/J3) | M3: 14.497404 | N3: =IF(ABS(I3-M3)<=0.001,"match","mismatch")
A4: Indonesia | B4: I_CVD_PRIMARY | C4: Primary prevention of CVD | D4: clinical | G4: htncov2_aspirational | H4: 2027 | I4: =100*(1-(SUMIFS('CVD_40q30_Age'!$M$2:$M$9361,'CVD_40q30_Age'!$A$2:$A$9361,A4,'CVD_40q30_Age'!$B$2:$B$9361,B4,'CVD_40q30_Age'!$E$2:$E$9361,G4,'CVD_40q30_Age'!$F$2:$F$9361,H4,'CVD_40q30_Age'!$G$2:$G$9361,69))/(SUMIFS('CVD_40q30_Age'!$L$2:$L$9361,'CVD_40q30_Age'!$A$2:$A$9361,A4,'CVD_40q30_Age'!$B$2:$B$9361,B4,'CVD_40q30_Age'!$E$2:$E$9361,G4,'CVD_40q30_Age'!$F$2:$F$9361,H4,'CVD_40q30_Age'!$G$2:$G$9361,30))) | J4: =SUMIFS($I$2:$I$235,$A$2:$A$235,A4,$G$2:$G$235,G4,$H$2:$H$235,H4,$B$2:$B$235,"baseline") | K4: =J4-I4 | L4: =IF(J4=0,"",100*(J4-I4)/J4) | M4: 14.37425 | N4: =IF(ABS(I4-M4)<=0.001,"match","mismatch")
A5: Indonesia | B5: I_CVD_PRIMARY | C5: Primary prevention of CVD | D5: clinical | G5: htncov2_aspirational | H5: 2028 | I5: =100*(1-(SUMIFS('CVD_40q30_Age'!$M$2:$M$9361,'CVD_40q30_Age'!$A$2:$A$9361,A5,'CVD_40q30_Age'!$B$2:$B$9361,B5,'CVD_40q30_Age'!$E$2:$E$9361,G5,'CVD_40q30_Age'!$F$2:$F$9361,H5,'CVD_40q30_Age'!$G$2:$G$9361,69))/(SUMIFS('CVD_40q30_Age'!$L$2:$L$9361,'CVD_40q30_Age'!$A$2:$A$9361,A5,'CVD_40q30_Age'!$B$2:$B$9361,B5,'CVD_40q30_Age'!$E$2:$E$9361,G5,'CVD_40q30_Age'!$F$2:$F$9361,H5,'CVD_40q30_Age'!$G$2:$G$9361,30))) | J5: =SUMIFS($I$2:$I$235,$A$2:$A$235,A5,$G$2:$G$235,G5,$H$2:$H$235,H5,$B$2:$B$235,"baseline") | K5: =J5-I5 | L5: =IF(J5=0,"",100*(J5-I5)/J5) | M5: 14.238676 | N5: =IF(ABS(I5-M5)<=0.001,"match","mismatch")
A6: Indonesia | B6: I_CVD_PRIMARY | C6: Primary prevention of CVD | D6: clinical | G6: htncov2_aspirational | H6: 2029 | I6: =100*(1-(SUMIFS('CVD_40q30_Age'!$M$2:$M$9361,'CVD_40q30_Age'!$A$2:$A$9361,A6,'CVD_40q30_Age'!$B$2:$B$9361,B6,'CVD_40q30_Age'!$E$2:$E$9361,G6,'CVD_40q30_Age'!$F$2:$F$9361,H6,'CVD_40q30_Age'!$G$2:$G$9361,69))/(SUMIFS('CVD_40q30_Age'!$L$2:$L$9361,'CVD_40q30_Age'!$A$2:$A$9361,A6,'CVD_40q30_Age'!$B$2:$B$9361,B6,'CVD_40q30_Age'!$E$2:$E$9361,G6,'CVD_40q30_Age'!$F$2:$F$9361,H6,'CVD_40q30_Age'!$G$2:$G$9361,30))) | J6: =SUMIFS($I$2:$I$235,$A$2:$A$235,A6,$G$2:$G$235,G6,$H$2:$H$235,H6,$B$2:$B$235,"baseline") | K6: =J6-I6 | L6: =IF(J6=0,"",100*(J6-I6)/J6) | M6: 14.101328 | N6: =IF(ABS(I6-M6)<=0.001,"match","mismatch")
A7: Indonesia | B7: I_CVD_PRIMARY | C7: Primary prevention of CVD | D7: clinical | G7: htncov2_aspirational | H7: 2030 | I7: =100*(1-(SUMIFS('CVD_40q30_Age'!$M$2:$M$9361,'CVD_40q30_Age'!$A$2:$A$9361,A7,'CVD_40q30_Age'!$B$2:$B$9361,B7,'CVD_40q30_Age'!$E$2:$E$9361,G7,'CVD_40q30_Age'!$F$2:$F$9361,H7,'CVD_40q30_Age'!$G$2:$G$9361,69))/(SUMIFS('CVD_40q30_Age'!$L$2:$L$9361,'CVD_40q30_Age'!$A$2:$A$9361,A7,'CVD_40q30_Age'!$B$2:$B$9361,B7,'CVD_40q30_Age'!$E$2:$E$9361,G7,'CVD_40q30_Age'!$F$2:$F$9361,H7,'CVD_40q30_Age'!$G$2:$G$9361,30))) | J7: =SUMIFS($I$2:$I$235,$A$2:$A$235,A7,$G$2:$G$235,G7,$H$2:$H$235,H7,$B$2:$B$235,"baseline") | K7: =J7-I7 | L7: =IF(J7=0,"",100*(J7-I7)/J7) | M7: 13.948509 | N7: =IF(ABS(I7-M7)<=0.001,"match","mismatch")
A8: Indonesia | B8: I_CVD_PRIMARY | C8: Primary prevention of CVD | D8: clinical | G8: htncov2_aspirational | H8: 2031 | I8: =100*(1-(SUMIFS('CVD_40q30_Age'!$M$2:$M$9361,'CVD_40q30_Age'!$A$2:$A$9361,A8,'CVD_40q30_Age'!$B$2:$B$9361,B8,'CVD_40q30_Age'!$E$2:$E$9361,G8,'CVD_40q30_Age'!$F$2:$F$9361,H8,'CVD_40q30_Age'!$G$2:$G$9361,69))/(SUMIFS('CVD_40q30_Age'!$L$2:$L$9361,'CVD_40q30_Age'!$A$2:$A$9361,A8,'CVD_40q30_Age'!$B$2:$B$9361,B8,'CVD_40q30_Age'!$E$2:$E$9361,G8,'CVD_40q30_Age'!$F$2:$F$9361,H8,'CVD_40q30_Age'!$G$2:$G$9361,30))) | J8: =SUMIFS($I$2:$I$235,$A$2:$A$235,A8,$G$2:$G$235,G8,$H$2:$H$235,H8,$B$2:$B$235,"baseline") | K8: =J8-I8 | L8: =IF(J8=0,"",100*(J8-I8)/J8) | M8: 13.767799 | N8: =IF(ABS(I8-M8)<=0.001,"match","mismatch")
A9: Indonesia | B9: I_CVD_PRIMARY | C9: Primary prevention of CVD | D9: clinical | G9: htncov2_aspirational | H9: 2032 | I9: =100*(1-(SUMIFS('CVD_40q30_Age'!$M$2:$M$9361,'CVD_40q30_Age'!$A$2:$A$9361,A9,'CVD_40q30_Age'!$B$2:$B$9361,B9,'CVD_40q30_Age'!$E$2:$E$9361,G9,'CVD_40q30_Age'!$F$2:$F$9361,H9,'CVD_40q30_Age'!$G$2:$G$9361,69))/(SUMIFS('CVD_40q30_Age'!$L$2:$L$9361,'CVD_40q30_Age'!$A$2:$A$9361,A9,'CVD_40q30_Age'!$B$2:$B$9361,B9,'CVD_40q30_Age'!$E$2:$E$9361,G9,'CVD_40q30_Age'!$F$2:$F$9361,H9,'CVD_40q30_Age'!$G$2:$G$9361,30))) | J9: =SUMIFS($I$2:$I$235,$A$2:$A$235,A9,$G$2:$G$235,G9,$H$2:$H$235,H9,$B$2:$B$235,"baseline") | K9: =J9-I9 | L9: =IF(J9=0,"",100*(J9-I9)/J9) | M9: 13.575472 | N9: =IF(ABS(I9-M9)<=0.001,"match","mismatch")
A10: Indonesia | B10: I_CVD_PRIMARY | C10: Primary prevention of CVD | D10: clinical | G10: htncov2_aspirational | H10: 2033 | I10: =100*(1-(SUMIFS('CVD_40q30_Age'!$M$2:$M$9361,'CVD_40q30_Age'!$A$2:$A$9361,A10,'CVD_40q30_Age'!$B$2:$B$9361,B10,'CVD_40q30_Age'!$E$2:$E$9361,G10,'CVD_40q30_Age'!$F$2:$F$9361,H10,'CVD_40q30_Age'!$G$2:$G$9361,69))/(SUMIFS('CVD_40q30_Age'!$L$2:$L$9361,'CVD_40q30_Age'!$A$2:$A$9361,A10,'CVD_40q30_Age'!$B$2:$B$9361,B10,'CVD_40q30_Age'!$E$2:$E$9361,G10,'CVD_40q30_Age'!$F$2:$F$9361,H10,'CVD_40q30_Age'!$G$2:$G$9361,30))) | J10: =SUMIFS($I$2:$I$235,$A$2:$A$235,A10,$G$2:$G$235,G10,$H$2:$H$235,H10,$B$2:$B$235,"baseline") | K10: =J10-I10 | L10: =IF(J10=0,"",100*(J10-I10)/J10) | M10: 13.368501 | N10: =IF(ABS(I10-M10)<=0.001,"match","mismatch")
A11: Indonesia | B11: I_CVD_PRIMARY | C11: Primary prevention of CVD | D11: clinical | G11: htncov2_aspirational | H11: 2034 | I11: =100*(1-(SUMIFS('CVD_40q30_Age'!$M$2:$M$9361,'CVD_40q30_Age'!$A$2:$A$9361,A11,'CVD_40q30_Age'!$B$2:$B$9361,B11,'CVD_40q30_Age'!$E$2:$E$9361,G11,'CVD_40q30_Age'!$F$2:$F$9361,H11,'CVD_40q30_Age'!$G$2:$G$9361,69))/(SUMIFS('CVD_40q30_Age'!$L$2:$L$9361,'CVD_40q30_Age'!$A$2:$A$9361,A11,'CVD_40q30_Age'!$B$2:$B$9361,B11,'CVD_40q30_Age'!$E$2:$E$9361,G11,'CVD_40q30_Age'!$F$2:$F$9361,H11,'CVD_40q30_Age'!$G$2:$G$9361,30))) | J11: =SUMIFS($I$2:$I$235,$A$2:$A$235,A11,$G$2:$G$235,G11,$H$2:$H$235,H11,$B$2:$B$235,"baseline") | K11: =J11-I11 | L11: =IF(J11=0,"",100*(J11-I11)/J11) | M11: 13.164693 | N11: =IF(ABS(I11-M11)<=0.001,"match","mismatch")
A12: Indonesia | B12: I_CVD_PRIMARY | C12: Primary prevention of CVD | D12: clinical | G12: htncov2_aspirational | H12: 2035 | I12: =100*(1-(SUMIFS('CVD_40q30_Age'!$M$2:$M$9361,'CVD_40q30_Age'!$A$2:$A$9361,A12,'CVD_40q30_Age'!$B$2:$B$9361,B12,'CVD_40q30_Age'!$E$2:$E$9361,G12,'CVD_40q30_Age'!$F$2:$F$9361,H12,'CVD_40q30_Age'!$G$2:$G$9361,69))/(SUMIFS('CVD_40q30_Age'!$L$2:$L$9361,'CVD_40q30_Age'!$A$2:$A$9361,A12,'CVD_40q30_Age'!$B$2:$B$9361,B12,'CVD_40q30_Age'!$E$2:$E$9361,G12,'CVD_40q30_Age'!$F$2:$F$9361,H12,'CVD_40q30_Age'!$G$2:$G$9361,30))) | J12: =SUMIFS($I$2:$I$235,$A$2:$A$235,A12,$G$2:$G$235,G12,$H$2:$H$235,H12,$B$2:$B$235,"baseline") | K12: =J12-I12 | L12: =IF(J12=0,"",100*(J12-I12)/J12) | M12: 12.952108 | N12: =IF(ABS(I12-M12)<=0.001,"match","mismatch")
A13: Indonesia | B13: I_CVD_PRIMARY | C13: Primary prevention of CVD | D13: clinical | G13: htncov2_aspirational | H13: 2036 | I13: =100*(1-(SUMIFS('CVD_40q30_Age'!$M$2:$M$9361,'CVD_40q30_Age'!$A$2:$A$9361,A13,'CVD_40q30_Age'!$B$2:$B$9361,B13,'CVD_40q30_Age'!$E$2:$E$9361,G13,'CVD_40q30_Age'!$F$2:$F$9361,H13,'CVD_40q30_Age'!$G$2:$G$9361,69))/(SUMIFS('CVD_40q30_Age'!$L$2:$L$9361,'CVD_40q30_Age'!$A$2:$A$9361,A13,'CVD_40q30_Age'!$B$2:$B$9361,B13,'CVD_40q30_Age'!$E$2:$E$9361,G13,'CVD_40q30_Age'!$F$2:$F$9361,H13,'CVD_40q30_Age'!$G$2:$G$9361,30))) | J13: =SUMIFS($I$2:$I$235,$A$2:$A$235,A13,$G$2:$G$235,G13,$H$2:$H$235,H13,$B$2:$B$235,"baseline") | K13: =J13-I13 | L13: =IF(J13=0,"",100*(J13-I13)/J13) | M13: 12.744566 | N13: =IF(ABS(I13-M13)<=0.001,"match","mismatch")
... A235: Indonesia | B235: baseline | C235: Baseline (no new intervention) | D235: baseline | G235: htncov2_aspirational | H235: 2050 | I235: =100*(1-(SUMIFS('CVD_40q30_Age'!$M$2:$M$9361,'CVD_40q30_Age'!$A$2:$A$9361,A235,'CVD_40q30_Age'!$B$2:$B$9361,B235,'CVD_40q30_Age'!$E$2:$E$9361,G235,'CVD_40q30_Age'!$F$2:$F$9361,H235,'CVD_40q30_Age'!$G$2:$G$9361,69))/(SUMIFS('CVD_40q30_Age'!$L$2:$L$9361,'CVD_40q30_Age'!$A$2:$A$9361,A235,'CVD_40q30_Age'!$B$2:$B$9361,B235,'CVD_40q30_Age'!$E$2:$E$9361,G235,'CVD_40q30_Age'!$F$2:$F$9361,H235,'CVD_40q30_Age'!$G$2:$G$9361,30))) | J235: =SUMIFS($I$2:$I$235,$A$2:$A$235,A235,$G$2:$G$235,G235,$H$2:$H$235,H235,$B$2:$B$235,"baseline") | K235: =J235-I235 | L235: =IF(J235=0,"",100*(J235-I235)/J235) | M235: 11.686287 | N235: =IF(ABS(I235-M235)<=0.001,"match","mismatch")

Sheet CVD_40q30_Age
A1: location | B1: scenario | C1: scenario_label | D1: intervention_family | E1: htn_target_scenario | F1: year | G1: age | H1: cvd_deaths | I1: population | J1: m_x | K1: q_x | L1: l_x | M1: l_x_next
A2: Indonesia | B2: I_CVD_PRIMARY | C2: Primary prevention of CVD | D2: clinical | E2: htncov2_aspirational | F2: 2025 | G2: 30 | H2: 1282.1481 | I2: 4467259 | J2: =IF(I2>0,H2/I2,0) | K2: =1-EXP(-J2) | L2: =IF(G2=30,1,M1) | M2: =L2*(1-K2)
A3: Indonesia | B3: I_CVD_PRIMARY | C3: Primary prevention of CVD | D3: clinical | E3: htncov2_aspirational | F3: 2025 | G3: 31 | H3: 1315.2391 | I3: 4410712.4 | J3: =IF(I3>0,H3/I3,0) | K3: =1-EXP(-J3) | L3: =IF(G3=30,1,M2) | M3: =L3*(1-K3)
A4: Indonesia | B4: I_CVD_PRIMARY | C4: Primary prevention of CVD | D4: clinical | E4: htncov2_aspirational | F4: 2025 | G4: 32 | H4: 1358.3687 | I4: 4358505.8 | J4: =IF(I4>0,H4/I4,0) | K4: =1-EXP(-J4) | L4: =IF(G4=30,1,M3) | M4: =L4*(1-K4)
A5: Indonesia | B5: I_CVD_PRIMARY | C5: Primary prevention of CVD | D5: clinical | E5: htncov2_aspirational | F5: 2025 | G5: 33 | H5: 1441.8419 | I5: 4398745.9 | J5: =IF(I5>0,H5/I5,0) | K5: =1-EXP(-J5) | L5: =IF(G5=30,1,M4) | M5: =L5*(1-K5)
A6: Indonesia | B6: I_CVD_PRIMARY | C6: Primary prevention of CVD | D6: clinical | E6: htncov2_aspirational | F6: 2025 | G6: 34 | H6: 1533.7871 | I6: 4419468.6 | J6: =IF(I6>0,H6/I6,0) | K6: =1-EXP(-J6) | L6: =IF(G6=30,1,M5) | M6: =L6*(1-K6)
A7: Indonesia | B7: I_CVD_PRIMARY | C7: Primary prevention of CVD | D7: clinical | E7: htncov2_aspirational | F7: 2025 | G7: 35 | H7: 3016.1069 | I7: 6509663.4 | J7: =IF(I7>0,H7/I7,0) | K7: =1-EXP(-J7) | L7: =IF(G7=30,1,M6) | M7: =L7*(1-K7)
A8: Indonesia | B8: I_CVD_PRIMARY | C8: Primary prevention of CVD | D8: clinical | E8: htncov2_aspirational | F8: 2025 | G8: 36 | H8: 2254.7093 | I8: 4383096 | J8: =IF(I8>0,H8/I8,0) | K8: =1-EXP(-J8) | L8: =IF(G8=30,1,M7) | M8: =L8*(1-K8)
A9: Indonesia | B9: I_CVD_PRIMARY | C9: Primary prevention of CVD | D9: clinical | E9: htncov2_aspirational | F9: 2025 | G9: 37 | H9: 2406.7285 | I9: 4369642.3 | J9: =IF(I9>0,H9/I9,0) | K9: =1-EXP(-J9) | L9: =IF(G9=30,1,M8) | M9: =L9*(1-K9)
A10: Indonesia | B10: I_CVD_PRIMARY | C10: Primary prevention of CVD | D10: clinical | E10: htncov2_aspirational | F10: 2025 | G10: 38 | H10: 2504.2649 | I10: 4239505.9 | J10: =IF(I10>0,H10/I10,0) | K10: =1-EXP(-J10) | L10: =IF(G10=30,1,M9) | M10: =L10*(1-K10)
A11: Indonesia | B11: I_CVD_PRIMARY | C11: Primary prevention of CVD | D11: clinical | E11: htncov2_aspirational | F11: 2025 | G11: 39 | H11: 2668.8504 | I11: 4208510.7 | J11: =IF(I11>0,H11/I11,0) | K11: =1-EXP(-J11) | L11: =IF(G11=30,1,M10) | M11: =L11*(1-K11)
A12: Indonesia | B12: I_CVD_PRIMARY | C12: Primary prevention of CVD | D12: clinical | E12: htncov2_aspirational | F12: 2025 | G12: 40 | H12: 3657.3454 | I12: 4272859.9 | J12: =IF(I12>0,H12/I12,0) | K12: =1-EXP(-J12) | L12: =IF(G12=30,1,M11) | M12: =L12*(1-K12)
A13: Indonesia | B13: I_CVD_PRIMARY | C13: Primary prevention of CVD | D13: clinical | E13: htncov2_aspirational | F13: 2025 | G13: 41 | H13: 4027.1377 | I13: 4362484.7 | J13: =IF(I13>0,H13/I13,0) | K13: =1-EXP(-J13) | L13: =IF(G13=30,1,M12) | M13: =L13*(1-K13)
... A9361: Indonesia | B9361: baseline | C9361: Baseline (no new intervention) | D9361: baseline | E9361: htncov2_aspirational | F9361: 2050 | G9361: 69 | H9361: 35334.467 | I9361: 3180308.9 | J9361: =IF(I9361>0,H9361/I9361,0) | K9361: =1-EXP(-J9361) | L9361: =IF(G9361=30,1,M9360) | M9361: =L9361*(1-K9361)

Sheet Annual_Cost
A1: scenario | B1: year | C1: intervention_id | D1: cause_code | E1: cost_record_id | F1: cost_component_key | G1: cost_join_key | H1: cost_scope | I1: population_in_need_measure | J1: population_in_need_fraction | K1: coverage_scenario | L1: coverage_baseline | M1: frequency_per_year | N1: unit_cost_usd | O1: pin_scenario | P1: pin_baseline | Q1: annual_cost_baseline | R1: annual_cost_scenario | S1: annual_cost_incremental | T1: indonesia_adjusted_flag | U1: price_year | V1: discount_factor | W1: disc_cost_baseline | X1: disc_cost_scenario | Y1: disc_cost_incremental | Z1: cov_target | AA1: cov_start_year | AB1: cov_target_year | AC1: c_age_start | AD1: c_age_stop | AE1: c_sex | AF1: r_quantity_scenario | AG1: r_quantity_baseline | AH1: shared_duplicate_count | AI1: national_population | AJ1: annual_cost_baseline_per_capita | AK1: annual_cost_scenario_per_capita | AL1: annual_cost_incremental_per_capita | AM1: disc_cost_incremental_per_capita
A2: I_CVD_PRIMARY | B2: 2025 | C2: I_CVD_PRIMARY | E2: COST_PRIMARY_SCREEN_B | F2: CC_PRIMARY_SCREENING | G2: I_CVD_PRIMARY__C_SHARED | H2: shared-count-once | I2: all | J2: =IFERROR(INDEX('Cost_Components'!$K$2:$K$28,MATCH(E2,'Cost_Components'!$A$2:$A$28,0)),"") | K2: =IF(OR(L2="",Z2="",AA2="",AB2=""),"",IF(B2<AA2,L2,IF(B2>AB2,Z2,L2+(Z2-L2)*MIN(MAX((B2-AA2+1)/MAX(AB2-AA2+1,1),0),1)))) | L2: =IFERROR(INDEX('Cost_Components'!$S$2:$S$28,MATCH(E2,'Cost_Components'!$A$2:$A$28,0)),"") | M2: =IFERROR(INDEX('Cost_Components'!$L$2:$L$28,MATCH(E2,'Cost_Components'!$A$2:$A$28,0)),"") | N2: =IFERROR(INDEX('Cost_Components'!$P$2:$P$28,MATCH(E2,'Cost_Components'!$A$2:$A$28,0)),"") | O2: =AF2*J2 | P2: =AG2*J2 | Q2: =P2*L2*M2*N2 | R2: =O2*K2*M2*N2 | S2: =R2-Q2 | T2: =IFERROR(INDEX('Cost_Components'!$R$2:$R$28,MATCH(E2,'Cost_Components'!$A$2:$A$28,0)),"") | U2: =IFERROR(INDEX('Cost_Components'!$Q$2:$Q$28,MATCH(E2,'Cost_Components'!$A$2:$A$28,0)),"") | V2: =1/(1+'Calculation_Assumptions'!$B$5)^(B2-'Calculation_Assumptions'!$B$2) | W2: =Q2*V2 | X2: =R2*V2 | Y2: =S2*V2 | Z2: =IFERROR(INDEX('Cost_Components'!$T$2:$T$28,MATCH(E2,'Cost_Components'!$A$2:$A$28,0)),"") | AA2: =IFERROR(INDEX('Cost_Components'!$U$2:$U$28,MATCH(E2,'Cost_Components'!$A$2:$A$28,0)),"") | AB2: =IFERROR(INDEX('Cost_Components'!$V$2:$V$28,MATCH(E2,'Cost_Components'!$A$2:$A$28,0)),"") | AC2: =IFERROR(INDEX('Cost_Components'!$M$2:$M$28,MATCH(E2,'Cost_Components'!$A$2:$A$28,0)),"") | AD2: =IFERROR(INDEX('Cost_Components'!$N$2:$N$28,MATCH(E2,'Cost_Components'!$A$2:$A$28,0)),"") | AE2: =IFERROR(INDEX('Cost_Components'!$O$2:$O$28,MATCH(E2,'Cost_Components'!$A$2:$A$28,0)),"") | AF2: 1.5509319e+08 | AG2: 1.5509319e+08 | AH2: =IF(H2="shared-count-once",COUNTIFS($A$2:$A$1405,A2,$B$2:$B$1405,B2,$E$2:$E$1405,E2),1) | AI2: 2.8839191e+08 | AJ2: =IF(AI2=0,"",Q2/AI2) | AK2: =IF(AI2=0,"",R2/AI2) | AL2: =IF(AI2=0,"",S2/AI2) | AM2: =IF(AI2=0,"",Y2/AI2)
A3: I_CVD_PRIMARY | B3: 2026 | C3: I_CVD_PRIMARY | E3: COST_PRIMARY_SCREEN_B | F3: CC_PRIMARY_SCREENING | G3: I_CVD_PRIMARY__C_SHARED | H3: shared-count-once | I3: all | J3: =IFERROR(INDEX('Cost_Components'!$K$2:$K$28,MATCH(E3,'Cost_Components'!$A$2:$A$28,0)),"") | K3: =IF(OR(L3="",Z3="",AA3="",AB3=""),"",IF(B3<AA3,L3,IF(B3>AB3,Z3,L3+(Z3-L3)*MIN(MAX((B3-AA3+1)/MAX(AB3-AA3+1,1),0),1)))) | L3: =IFERROR(INDEX('Cost_Components'!$S$2:$S$28,MATCH(E3,'Cost_Components'!$A$2:$A$28,0)),"") | M3: =IFERROR(INDEX('Cost_Components'!$L$2:$L$28,MATCH(E3,'Cost_Components'!$A$2:$A$28,0)),"") | N3: =IFERROR(INDEX('Cost_Components'!$P$2:$P$28,MATCH(E3,'Cost_Components'!$A$2:$A$28,0)),"") | O3: =AF3*J3 | P3: =AG3*J3 | Q3: =P3*L3*M3*N3 | R3: =O3*K3*M3*N3 | S3: =R3-Q3 | T3: =IFERROR(INDEX('Cost_Components'!$R$2:$R$28,MATCH(E3,'Cost_Components'!$A$2:$A$28,0)),"") | U3: =IFERROR(INDEX('Cost_Components'!$Q$2:$Q$28,MATCH(E3,'Cost_Components'!$A$2:$A$28,0)),"") | V3: =1/(1+'Calculation_Assumptions'!$B$5)^(B3-'Calculation_Assumptions'!$B$2) | W3: =Q3*V3 | X3: =R3*V3 | Y3: =S3*V3 | Z3: =IFERROR(INDEX('Cost_Components'!$T$2:$T$28,MATCH(E3,'Cost_Components'!$A$2:$A$28,0)),"") | AA3: =IFERROR(INDEX('Cost_Components'!$U$2:$U$28,MATCH(E3,'Cost_Components'!$A$2:$A$28,0)),"") | AB3: =IFERROR(INDEX('Cost_Components'!$V$2:$V$28,MATCH(E3,'Cost_Components'!$A$2:$A$28,0)),"") | AC3: =IFERROR(INDEX('Cost_Components'!$M$2:$M$28,MATCH(E3,'Cost_Components'!$A$2:$A$28,0)),"") | AD3: =IFERROR(INDEX('Cost_Components'!$N$2:$N$28,MATCH(E3,'Cost_Components'!$A$2:$A$28,0)),"") | AE3: =IFERROR(INDEX('Cost_Components'!$O$2:$O$28,MATCH(E3,'Cost_Components'!$A$2:$A$28,0)),"") | AF3: 1.5750383e+08 | AG3: 1.5750383e+08 | AH3: =IF(H3="shared-count-once",COUNTIFS($A$2:$A$1405,A3,$B$2:$B$1405,B3,$E$2:$E$1405,E3),1) | AI3: 2.9047213e+08 | AJ3: =IF(AI3=0,"",Q3/AI3) | AK3: =IF(AI3=0,"",R3/AI3) | AL3: =IF(AI3=0,"",S3/AI3) | AM3: =IF(AI3=0,"",Y3/AI3)
A4: I_CVD_PRIMARY | B4: 2027 | C4: I_CVD_PRIMARY | E4: COST_PRIMARY_SCREEN_B | F4: CC_PRIMARY_SCREENING | G4: I_CVD_PRIMARY__C_SHARED | H4: shared-count-once | I4: all | J4: =IFERROR(INDEX('Cost_Components'!$K$2:$K$28,MATCH(E4,'Cost_Components'!$A$2:$A$28,0)),"") | K4: =IF(OR(L4="",Z4="",AA4="",AB4=""),"",IF(B4<AA4,L4,IF(B4>AB4,Z4,L4+(Z4-L4)*MIN(MAX((B4-AA4+1)/MAX(AB4-AA4+1,1),0),1)))) | L4: =IFERROR(INDEX('Cost_Components'!$S$2:$S$28,MATCH(E4,'Cost_Components'!$A$2:$A$28,0)),"") | M4: =IFERROR(INDEX('Cost_Components'!$L$2:$L$28,MATCH(E4,'Cost_Components'!$A$2:$A$28,0)),"") | N4: =IFERROR(INDEX('Cost_Components'!$P$2:$P$28,MATCH(E4,'Cost_Components'!$A$2:$A$28,0)),"") | O4: =AF4*J4 | P4: =AG4*J4 | Q4: =P4*L4*M4*N4 | R4: =O4*K4*M4*N4 | S4: =R4-Q4 | T4: =IFERROR(INDEX('Cost_Components'!$R$2:$R$28,MATCH(E4,'Cost_Components'!$A$2:$A$28,0)),"") | U4: =IFERROR(INDEX('Cost_Components'!$Q$2:$Q$28,MATCH(E4,'Cost_Components'!$A$2:$A$28,0)),"") | V4: =1/(1+'Calculation_Assumptions'!$B$5)^(B4-'Calculation_Assumptions'!$B$2) | W4: =Q4*V4 | X4: =R4*V4 | Y4: =S4*V4 | Z4: =IFERROR(INDEX('Cost_Components'!$T$2:$T$28,MATCH(E4,'Cost_Components'!$A$2:$A$28,0)),"") | AA4: =IFERROR(INDEX('Cost_Components'!$U$2:$U$28,MATCH(E4,'Cost_Components'!$A$2:$A$28,0)),"") | AB4: =IFERROR(INDEX('Cost_Components'!$V$2:$V$28,MATCH(E4,'Cost_Components'!$A$2:$A$28,0)),"") | AC4: =IFERROR(INDEX('Cost_Components'!$M$2:$M$28,MATCH(E4,'Cost_Components'!$A$2:$A$28,0)),"") | AD4: =IFERROR(INDEX('Cost_Components'!$N$2:$N$28,MATCH(E4,'Cost_Components'!$A$2:$A$28,0)),"") | AE4: =IFERROR(INDEX('Cost_Components'!$O$2:$O$28,MATCH(E4,'Cost_Components'!$A$2:$A$28,0)),"") | AF4: 1.5995862e+08 | AG4: 1.5995711e+08 | AH4: =IF(H4="shared-count-once",COUNTIFS($A$2:$A$1405,A4,$B$2:$B$1405,B4,$E$2:$E$1405,E4),1) | AI4: 2.9250508e+08 | AJ4: =IF(AI4=0,"",Q4/AI4) | AK4: =IF(AI4=0,"",R4/AI4) | AL4: =IF(AI4=0,"",S4/AI4) | AM4: =IF(AI4=0,"",Y4/AI4)
A5: I_CVD_PRIMARY | B5: 2028 | C5: I_CVD_PRIMARY | E5: COST_PRIMARY_SCREEN_B | F5: CC_PRIMARY_SCREENING | G5: I_CVD_PRIMARY__C_SHARED | H5: shared-count-once | I5: all | J5: =IFERROR(INDEX('Cost_Components'!$K$2:$K$28,MATCH(E5,'Cost_Components'!$A$2:$A$28,0)),"") | K5: =IF(OR(L5="",Z5="",AA5="",AB5=""),"",IF(B5<AA5,L5,IF(B5>AB5,Z5,L5+(Z5-L5)*MIN(MAX((B5-AA5+1)/MAX(AB5-AA5+1,1),0),1)))) | L5: =IFERROR(INDEX('Cost_Components'!$S$2:$S$28,MATCH(E5,'Cost_Components'!$A$2:$A$28,0)),"") | M5: =IFERROR(INDEX('Cost_Components'!$L$2:$L$28,MATCH(E5,'Cost_Components'!$A$2:$A$28,0)),"") | N5: =IFERROR(INDEX('Cost_Components'!$P$2:$P$28,MATCH(E5,'Cost_Components'!$A$2:$A$28,0)),"") | O5: =AF5*J5 | P5: =AG5*J5 | Q5: =P5*L5*M5*N5 | R5: =O5*K5*M5*N5 | S5: =R5-Q5 | T5: =IFERROR(INDEX('Cost_Components'!$R$2:$R$28,MATCH(E5,'Cost_Components'!$A$2:$A$28,0)),"") | U5: =IFERROR(INDEX('Cost_Components'!$Q$2:$Q$28,MATCH(E5,'Cost_Components'!$A$2:$A$28,0)),"") | V5: =1/(1+'Calculation_Assumptions'!$B$5)^(B5-'Calculation_Assumptions'!$B$2) | W5: =Q5*V5 | X5: =R5*V5 | Y5: =S5*V5 | Z5: =IFERROR(INDEX('Cost_Components'!$T$2:$T$28,MATCH(E5,'Cost_Components'!$A$2:$A$28,0)),"") | AA5: =IFERROR(INDEX('Cost_Components'!$U$2:$U$28,MATCH(E5,'Cost_Components'!$A$2:$A$28,0)),"") | AB5: =IFERROR(INDEX('Cost_Components'!$V$2:$V$28,MATCH(E5,'Cost_Components'!$A$2:$A$28,0)),"") | AC5: =IFERROR(INDEX('Cost_Components'!$M$2:$M$28,MATCH(E5,'Cost_Components'!$A$2:$A$28,0)),"") | AD5: =IFERROR(INDEX('Cost_Components'!$N$2:$N$28,MATCH(E5,'Cost_Components'!$A$2:$A$28,0)),"") | AE5: =IFERROR(INDEX('Cost_Components'!$O$2:$O$28,MATCH(E5,'Cost_Components'!$A$2:$A$28,0)),"") | AF5: 1.6220978e+08 | AG5: 1.6220434e+08 | AH5: =IF(H5="shared-count-once",COUNTIFS($A$2:$A$1405,A5,$B$2:$B$1405,B5,$E$2:$E$1405,E5),1) | AI5: 2.9448471e+08 | AJ5: =IF(AI5=0,"",Q5/AI5) | AK5: =IF(AI5=0,"",R5/AI5) | AL5: =IF(AI5=0,"",S5/AI5) | AM5: =IF(AI5=0,"",Y5/AI5)
A6: I_CVD_PRIMARY | B6: 2029 | C6: I_CVD_PRIMARY | E6: COST_PRIMARY_SCREEN_B | F6: CC_PRIMARY_SCREENING | G6: I_CVD_PRIMARY__C_SHARED | H6: shared-count-once | I6: all | J6: =IFERROR(INDEX('Cost_Components'!$K$2:$K$28,MATCH(E6,'Cost_Components'!$A$2:$A$28,0)),"") | K6: =IF(OR(L6="",Z6="",AA6="",AB6=""),"",IF(B6<AA6,L6,IF(B6>AB6,Z6,L6+(Z6-L6)*MIN(MAX((B6-AA6+1)/MAX(AB6-AA6+1,1),0),1)))) | L6: =IFERROR(INDEX('Cost_Components'!$S$2:$S$28,MATCH(E6,'Cost_Components'!$A$2:$A$28,0)),"") | M6: =IFERROR(INDEX('Cost_Components'!$L$2:$L$28,MATCH(E6,'Cost_Components'!$A$2:$A$28,0)),"") | N6: =IFERROR(INDEX('Cost_Components'!$P$2:$P$28,MATCH(E6,'Cost_Components'!$A$2:$A$28,0)),"") | O6: =AF6*J6 | P6: =AG6*J6 | Q6: =P6*L6*M6*N6 | R6: =O6*K6*M6*N6 | S6: =R6-Q6 | T6: =IFERROR(INDEX('Cost_Components'!$R$2:$R$28,MATCH(E6,'Cost_Components'!$A$2:$A$28,0)),"") | U6: =IFERROR(INDEX('Cost_Components'!$Q$2:$Q$28,MATCH(E6,'Cost_Components'!$A$2:$A$28,0)),"") | V6: =1/(1+'Calculation_Assumptions'!$B$5)^(B6-'Calculation_Assumptions'!$B$2) | W6: =Q6*V6 | X6: =R6*V6 | Y6: =S6*V6 | Z6: =IFERROR(INDEX('Cost_Components'!$T$2:$T$28,MATCH(E6,'Cost_Components'!$A$2:$A$28,0)),"") | AA6: =IFERROR(INDEX('Cost_Components'!$U$2:$U$28,MATCH(E6,'Cost_Components'!$A$2:$A$28,0)),"") | AB6: =IFERROR(INDEX('Cost_Components'!$V$2:$V$28,MATCH(E6,'Cost_Components'!$A$2:$A$28,0)),"") | AC6: =IFERROR(INDEX('Cost_Components'!$M$2:$M$28,MATCH(E6,'Cost_Components'!$A$2:$A$28,0)),"") | AD6: =IFERROR(INDEX('Cost_Components'!$N$2:$N$28,MATCH(E6,'Cost_Components'!$A$2:$A$28,0)),"") | AE6: =IFERROR(INDEX('Cost_Components'!$O$2:$O$28,MATCH(E6,'Cost_Components'!$A$2:$A$28,0)),"") | AF6: 1.6436709e+08 | AG6: 1.6435451e+08 | AH6: =IF(H6="shared-count-once",COUNTIFS($A$2:$A$1405,A6,$B$2:$B$1405,B6,$E$2:$E$1405,E6),1) | AI6: 2.9641403e+08 | AJ6: =IF(AI6=0,"",Q6/AI6) | AK6: =IF(AI6=0,"",R6/AI6) | AL6: =IF(AI6=0,"",S6/AI6) | AM6: =IF(AI6=0,"",Y6/AI6)
A7: I_CVD_PRIMARY | B7: 2030 | C7: I_CVD_PRIMARY | E7: COST_PRIMARY_SCREEN_B | F7: CC_PRIMARY_SCREENING | G7: I_CVD_PRIMARY__C_SHARED | H7: shared-count-once | I7: all | J7: =IFERROR(INDEX('Cost_Components'!$K$2:$K$28,MATCH(E7,'Cost_Components'!$A$2:$A$28,0)),"") | K7: =IF(OR(L7="",Z7="",AA7="",AB7=""),"",IF(B7<AA7,L7,IF(B7>AB7,Z7,L7+(Z7-L7)*MIN(MAX((B7-AA7+1)/MAX(AB7-AA7+1,1),0),1)))) | L7: =IFERROR(INDEX('Cost_Components'!$S$2:$S$28,MATCH(E7,'Cost_Components'!$A$2:$A$28,0)),"") | M7: =IFERROR(INDEX('Cost_Components'!$L$2:$L$28,MATCH(E7,'Cost_Components'!$A$2:$A$28,0)),"") | N7: =IFERROR(INDEX('Cost_Components'!$P$2:$P$28,MATCH(E7,'Cost_Components'!$A$2:$A$28,0)),"") | O7: =AF7*J7 | P7: =AG7*J7 | Q7: =P7*L7*M7*N7 | R7: =O7*K7*M7*N7 | S7: =R7-Q7 | T7: =IFERROR(INDEX('Cost_Components'!$R$2:$R$28,MATCH(E7,'Cost_Components'!$A$2:$A$28,0)),"") | U7: =IFERROR(INDEX('Cost_Components'!$Q$2:$Q$28,MATCH(E7,'Cost_Components'!$A$2:$A$28,0)),"") | V7: =1/(1+'Calculation_Assumptions'!$B$5)^(B7-'Calculation_Assumptions'!$B$2) | W7: =Q7*V7 | X7: =R7*V7 | Y7: =S7*V7 | Z7: =IFERROR(INDEX('Cost_Components'!$T$2:$T$28,MATCH(E7,'Cost_Components'!$A$2:$A$28,0)),"") | AA7: =IFERROR(INDEX('Cost_Components'!$U$2:$U$28,MATCH(E7,'Cost_Components'!$A$2:$A$28,0)),"") | AB7: =IFERROR(INDEX('Cost_Components'!$V$2:$V$28,MATCH(E7,'Cost_Components'!$A$2:$A$28,0)),"") | AC7: =IFERROR(INDEX('Cost_Components'!$M$2:$M$28,MATCH(E7,'Cost_Components'!$A$2:$A$28,0)),"") | AD7: =IFERROR(INDEX('Cost_Components'!$N$2:$N$28,MATCH(E7,'Cost_Components'!$A$2:$A$28,0)),"") | AE7: =IFERROR(INDEX('Cost_Components'!$O$2:$O$28,MATCH(E7,'Cost_Components'!$A$2:$A$28,0)),"") | AF7: 1.6643914e+08 | AG7: 1.6641555e+08 | AH7: =IF(H7="shared-count-once",COUNTIFS($A$2:$A$1405,A7,$B$2:$B$1405,B7,$E$2:$E$1405,E7),1) | AI7: 2.982894e+08 | AJ7: =IF(AI7=0,"",Q7/AI7) | AK7: =IF(AI7=0,"",R7/AI7) | AL7: =IF(AI7=0,"",S7/AI7) | AM7: =IF(AI7=0,"",Y7/AI7)
A8: I_CVD_PRIMARY | B8: 2031 | C8: I_CVD_PRIMARY | E8: COST_PRIMARY_SCREEN_B | F8: CC_PRIMARY_SCREENING | G8: I_CVD_PRIMARY__C_SHARED | H8: shared-count-once | I8: all | J8: =IFERROR(INDEX('Cost_Components'!$K$2:$K$28,MATCH(E8,'Cost_Components'!$A$2:$A$28,0)),"") | K8: =IF(OR(L8="",Z8="",AA8="",AB8=""),"",IF(B8<AA8,L8,IF(B8>AB8,Z8,L8+(Z8-L8)*MIN(MAX((B8-AA8+1)/MAX(AB8-AA8+1,1),0),1)))) | L8: =IFERROR(INDEX('Cost_Components'!$S$2:$S$28,MATCH(E8,'Cost_Components'!$A$2:$A$28,0)),"") | M8: =IFERROR(INDEX('Cost_Components'!$L$2:$L$28,MATCH(E8,'Cost_Components'!$A$2:$A$28,0)),"") | N8: =IFERROR(INDEX('Cost_Components'!$P$2:$P$28,MATCH(E8,'Cost_Components'!$A$2:$A$28,0)),"") | O8: =AF8*J8 | P8: =AG8*J8 | Q8: =P8*L8*M8*N8 | R8: =O8*K8*M8*N8 | S8: =R8-Q8 | T8: =IFERROR(INDEX('Cost_Components'!$R$2:$R$28,MATCH(E8,'Cost_Components'!$A$2:$A$28,0)),"") | U8: =IFERROR(INDEX('Cost_Components'!$Q$2:$Q$28,MATCH(E8,'Cost_Components'!$A$2:$A$28,0)),"") | V8: =1/(1+'Calculation_Assumptions'!$B$5)^(B8-'Calculation_Assumptions'!$B$2) | W8: =Q8*V8 | X8: =R8*V8 | Y8: =S8*V8 | Z8: =IFERROR(INDEX('Cost_Components'!$T$2:$T$28,MATCH(E8,'Cost_Components'!$A$2:$A$28,0)),"") | AA8: =IFERROR(INDEX('Cost_Components'!$U$2:$U$28,MATCH(E8,'Cost_Components'!$A$2:$A$28,0)),"") | AB8: =IFERROR(INDEX('Cost_Components'!$V$2:$V$28,MATCH(E8,'Cost_Components'!$A$2:$A$28,0)),"") | AC8: =IFERROR(INDEX('Cost_Components'!$M$2:$M$28,MATCH(E8,'Cost_Components'!$A$2:$A$28,0)),"") | AD8: =IFERROR(INDEX('Cost_Components'!$N$2:$N$28,MATCH(E8,'Cost_Components'!$A$2:$A$28,0)),"") | AE8: =IFERROR(INDEX('Cost_Components'!$O$2:$O$28,MATCH(E8,'Cost_Components'!$A$2:$A$28,0)),"") | AF8: 1.6850041e+08 | AG8: 1.6846129e+08 | AH8: =IF(H8="shared-count-once",COUNTIFS($A$2:$A$1405,A8,$B$2:$B$1405,B8,$E$2:$E$1405,E8),1) | AI8: 3.0011964e+08 | AJ8: =IF(AI8=0,"",Q8/AI8) | AK8: =IF(AI8=0,"",R8/AI8) | AL8: =IF(AI8=0,"",S8/AI8) | AM8: =IF(AI8=0,"",Y8/AI8)
A9: I_CVD_PRIMARY | B9: 2032 | C9: I_CVD_PRIMARY | E9: COST_PRIMARY_SCREEN_B | F9: CC_PRIMARY_SCREENING | G9: I_CVD_PRIMARY__C_SHARED | H9: shared-count-once | I9: all | J9: =IFERROR(INDEX('Cost_Components'!$K$2:$K$28,MATCH(E9,'Cost_Components'!$A$2:$A$28,0)),"") | K9: =IF(OR(L9="",Z9="",AA9="",AB9=""),"",IF(B9<AA9,L9,IF(B9>AB9,Z9,L9+(Z9-L9)*MIN(MAX((B9-AA9+1)/MAX(AB9-AA9+1,1),0),1)))) | L9: =IFERROR(INDEX('Cost_Components'!$S$2:$S$28,MATCH(E9,'Cost_Components'!$A$2:$A$28,0)),"") | M9: =IFERROR(INDEX('Cost_Components'!$L$2:$L$28,MATCH(E9,'Cost_Components'!$A$2:$A$28,0)),"") | N9: =IFERROR(INDEX('Cost_Components'!$P$2:$P$28,MATCH(E9,'Cost_Components'!$A$2:$A$28,0)),"") | O9: =AF9*J9 | P9: =AG9*J9 | Q9: =P9*L9*M9*N9 | R9: =O9*K9*M9*N9 | S9: =R9-Q9 | T9: =IFERROR(INDEX('Cost_Components'!$R$2:$R$28,MATCH(E9,'Cost_Components'!$A$2:$A$28,0)),"") | U9: =IFERROR(INDEX('Cost_Components'!$Q$2:$Q$28,MATCH(E9,'Cost_Components'!$A$2:$A$28,0)),"") | V9: =1/(1+'Calculation_Assumptions'!$B$5)^(B9-'Calculation_Assumptions'!$B$2) | W9: =Q9*V9 | X9: =R9*V9 | Y9: =S9*V9 | Z9: =IFERROR(INDEX('Cost_Components'!$T$2:$T$28,MATCH(E9,'Cost_Components'!$A$2:$A$28,0)),"") | AA9: =IFERROR(INDEX('Cost_Components'!$U$2:$U$28,MATCH(E9,'Cost_Components'!$A$2:$A$28,0)),"") | AB9: =IFERROR(INDEX('Cost_Components'!$V$2:$V$28,MATCH(E9,'Cost_Components'!$A$2:$A$28,0)),"") | AC9: =IFERROR(INDEX('Cost_Components'!$M$2:$M$28,MATCH(E9,'Cost_Components'!$A$2:$A$28,0)),"") | AD9: =IFERROR(INDEX('Cost_Components'!$N$2:$N$28,MATCH(E9,'Cost_Components'!$A$2:$A$28,0)),"") | AE9: =IFERROR(INDEX('Cost_Components'!$O$2:$O$28,MATCH(E9,'Cost_Components'!$A$2:$A$28,0)),"") | AF9: 1.7053619e+08 | AG9: 1.7047662e+08 | AH9: =IF(H9="shared-count-once",COUNTIFS($A$2:$A$1405,A9,$B$2:$B$1405,B9,$E$2:$E$1405,E9),1) | AI9: 3.0190463e+08 | AJ9: =IF(AI9=0,"",Q9/AI9) | AK9: =IF(AI9=0,"",R9/AI9) | AL9: =IF(AI9=0,"",S9/AI9) | AM9: =IF(AI9=0,"",Y9/AI9)
A10: I_CVD_PRIMARY | B10: 2033 | C10: I_CVD_PRIMARY | E10: COST_PRIMARY_SCREEN_B | F10: CC_PRIMARY_SCREENING | G10: I_CVD_PRIMARY__C_SHARED | H10: shared-count-once | I10: all | J10: =IFERROR(INDEX('Cost_Components'!$K$2:$K$28,MATCH(E10,'Cost_Components'!$A$2:$A$28,0)),"") | K10: =IF(OR(L10="",Z10="",AA10="",AB10=""),"",IF(B10<AA10,L10,IF(B10>AB10,Z10,L10+(Z10-L10)*MIN(MAX((B10-AA10+1)/MAX(AB10-AA10+1,1),0),1)))) | L10: =IFERROR(INDEX('Cost_Components'!$S$2:$S$28,MATCH(E10,'Cost_Components'!$A$2:$A$28,0)),"") | M10: =IFERROR(INDEX('Cost_Components'!$L$2:$L$28,MATCH(E10,'Cost_Components'!$A$2:$A$28,0)),"") | N10: =IFERROR(INDEX('Cost_Components'!$P$2:$P$28,MATCH(E10,'Cost_Components'!$A$2:$A$28,0)),"") | O10: =AF10*J10 | P10: =AG10*J10 | Q10: =P10*L10*M10*N10 | R10: =O10*K10*M10*N10 | S10: =R10-Q10 | T10: =IFERROR(INDEX('Cost_Components'!$R$2:$R$28,MATCH(E10,'Cost_Components'!$A$2:$A$28,0)),"") | U10: =IFERROR(INDEX('Cost_Components'!$Q$2:$Q$28,MATCH(E10,'Cost_Components'!$A$2:$A$28,0)),"") | V10: =1/(1+'Calculation_Assumptions'!$B$5)^(B10-'Calculation_Assumptions'!$B$2) | W10: =Q10*V10 | X10: =R10*V10 | Y10: =S10*V10 | Z10: =IFERROR(INDEX('Cost_Components'!$T$2:$T$28,MATCH(E10,'Cost_Components'!$A$2:$A$28,0)),"") | AA10: =IFERROR(INDEX('Cost_Components'!$U$2:$U$28,MATCH(E10,'Cost_Components'!$A$2:$A$28,0)),"") | AB10: =IFERROR(INDEX('Cost_Components'!$V$2:$V$28,MATCH(E10,'Cost_Components'!$A$2:$A$28,0)),"") | AC10: =IFERROR(INDEX('Cost_Components'!$M$2:$M$28,MATCH(E10,'Cost_Components'!$A$2:$A$28,0)),"") | AD10: =IFERROR(INDEX('Cost_Components'!$N$2:$N$28,MATCH(E10,'Cost_Components'!$A$2:$A$28,0)),"") | AE10: =IFERROR(INDEX('Cost_Components'!$O$2:$O$28,MATCH(E10,'Cost_Components'!$A$2:$A$28,0)),"") | AF10: 1.7254665e+08 | AG10: 1.7246151e+08 | AH10: =IF(H10="shared-count-once",COUNTIFS($A$2:$A$1405,A10,$B$2:$B$1405,B10,$E$2:$E$1405,E10),1) | AI10: 3.0364428e+08 | AJ10: =IF(AI10=0,"",Q10/AI10) | AK10: =IF(AI10=0,"",R10/AI10) | AL10: =IF(AI10=0,"",S10/AI10) | AM10: =IF(AI10=0,"",Y10/AI10)
A11: I_CVD_PRIMARY | B11: 2034 | C11: I_CVD_PRIMARY | E11: COST_PRIMARY_SCREEN_B | F11: CC_PRIMARY_SCREENING | G11: I_CVD_PRIMARY__C_SHARED | H11: shared-count-once | I11: all | J11: =IFERROR(INDEX('Cost_Components'!$K$2:$K$28,MATCH(E11,'Cost_Components'!$A$2:$A$28,0)),"") | K11: =IF(OR(L11="",Z11="",AA11="",AB11=""),"",IF(B11<AA11,L11,IF(B11>AB11,Z11,L11+(Z11-L11)*MIN(MAX((B11-AA11+1)/MAX(AB11-AA11+1,1),0),1)))) | L11: =IFERROR(INDEX('Cost_Components'!$S$2:$S$28,MATCH(E11,'Cost_Components'!$A$2:$A$28,0)),"") | M11: =IFERROR(INDEX('Cost_Components'!$L$2:$L$28,MATCH(E11,'Cost_Components'!$A$2:$A$28,0)),"") | N11: =IFERROR(INDEX('Cost_Components'!$P$2:$P$28,MATCH(E11,'Cost_Components'!$A$2:$A$28,0)),"") | O11: =AF11*J11 | P11: =AG11*J11 | Q11: =P11*L11*M11*N11 | R11: =O11*K11*M11*N11 | S11: =R11-Q11 | T11: =IFERROR(INDEX('Cost_Components'!$R$2:$R$28,MATCH(E11,'Cost_Components'!$A$2:$A$28,0)),"") | U11: =IFERROR(INDEX('Cost_Components'!$Q$2:$Q$28,MATCH(E11,'Cost_Components'!$A$2:$A$28,0)),"") | V11: =1/(1+'Calculation_Assumptions'!$B$5)^(B11-'Calculation_Assumptions'!$B$2) | W11: =Q11*V11 | X11: =R11*V11 | Y11: =S11*V11 | Z11: =IFERROR(INDEX('Cost_Components'!$T$2:$T$28,MATCH(E11,'Cost_Components'!$A$2:$A$28,0)),"") | AA11: =IFERROR(INDEX('Cost_Components'!$U$2:$U$28,MATCH(E11,'Cost_Components'!$A$2:$A$28,0)),"") | AB11: =IFERROR(INDEX('Cost_Components'!$V$2:$V$28,MATCH(E11,'Cost_Components'!$A$2:$A$28,0)),"") | AC11: =IFERROR(INDEX('Cost_Components'!$M$2:$M$28,MATCH(E11,'Cost_Components'!$A$2:$A$28,0)),"") | AD11: =IFERROR(INDEX('Cost_Components'!$N$2:$N$28,MATCH(E11,'Cost_Components'!$A$2:$A$28,0)),"") | AE11: =IFERROR(INDEX('Cost_Components'!$O$2:$O$28,MATCH(E11,'Cost_Components'!$A$2:$A$28,0)),"") | AF11: 1.7444641e+08 | AG11: 1.7446169e+08 | AH11: =IF(H11="shared-count-once",COUNTIFS($A$2:$A$1405,A11,$B$2:$B$1405,B11,$E$2:$E$1405,E11),1) | AI11: 3.0533254e+08 | AJ11: =IF(AI11=0,"",Q11/AI11) | AK11: =IF(AI11=0,"",R11/AI11) | AL11: =IF(AI11=0,"",S11/AI11) | AM11: =IF(AI11=0,"",Y11/AI11)
A12: I_CVD_PRIMARY | B12: 2035 | C12: I_CVD_PRIMARY | E12: COST_PRIMARY_SCREEN_B | F12: CC_PRIMARY_SCREENING | G12: I_CVD_PRIMARY__C_SHARED | H12: shared-count-once | I12: all | J12: =IFERROR(INDEX('Cost_Components'!$K$2:$K$28,MATCH(E12,'Cost_Components'!$A$2:$A$28,0)),"") | K12: =IF(OR(L12="",Z12="",AA12="",AB12=""),"",IF(B12<AA12,L12,IF(B12>AB12,Z12,L12+(Z12-L12)*MIN(MAX((B12-AA12+1)/MAX(AB12-AA12+1,1),0),1)))) | L12: =IFERROR(INDEX('Cost_Components'!$S$2:$S$28,MATCH(E12,'Cost_Components'!$A$2:$A$28,0)),"") | M12: =IFERROR(INDEX('Cost_Components'!$L$2:$L$28,MATCH(E12,'Cost_Components'!$A$2:$A$28,0)),"") | N12: =IFERROR(INDEX('Cost_Components'!$P$2:$P$28,MATCH(E12,'Cost_Components'!$A$2:$A$28,0)),"") | O12: =AF12*J12 | P12: =AG12*J12 | Q12: =P12*L12*M12*N12 | R12: =O12*K12*M12*N12 | S12: =R12-Q12 | T12: =IFERROR(INDEX('Cost_Components'!$R$2:$R$28,MATCH(E12,'Cost_Components'!$A$2:$A$28,0)),"") | U12: =IFERROR(INDEX('Cost_Components'!$Q$2:$Q$28,MATCH(E12,'Cost_Components'!$A$2:$A$28,0)),"") | V12: =1/(1+'Calculation_Assumptions'!$B$5)^(B12-'Calculation_Assumptions'!$B$2) | W12: =Q12*V12 | X12: =R12*V12 | Y12: =S12*V12 | Z12: =IFERROR(INDEX('Cost_Components'!$T$2:$T$28,MATCH(E12,'Cost_Components'!$A$2:$A$28,0)),"") | AA12: =IFERROR(INDEX('Cost_Components'!$U$2:$U$28,MATCH(E12,'Cost_Components'!$A$2:$A$28,0)),"") | AB12: =IFERROR(INDEX('Cost_Components'!$V$2:$V$28,MATCH(E12,'Cost_Components'!$A$2:$A$28,0)),"") | AC12: =IFERROR(INDEX('Cost_Components'!$M$2:$M$28,MATCH(E12,'Cost_Components'!$A$2:$A$28,0)),"") | AD12: =IFERROR(INDEX('Cost_Components'!$N$2:$N$28,MATCH(E12,'Cost_Components'!$A$2:$A$28,0)),"") | AE12: =IFERROR(INDEX('Cost_Components'!$O$2:$O$28,MATCH(E12,'Cost_Components'!$A$2:$A$28,0)),"") | AF12: 1.7658101e+08 | AG12: 1.7653877e+08 | AH12: =IF(H12="shared-count-once",COUNTIFS($A$2:$A$1405,A12,$B$2:$B$1405,B12,$E$2:$E$1405,E12),1) | AI12: 3.0696465e+08 | AJ12: =IF(AI12=0,"",Q12/AI12) | AK12: =IF(AI12=0,"",R12/AI12) | AL12: =IF(AI12=0,"",S12/AI12) | AM12: =IF(AI12=0,"",Y12/AI12)
A13: I_CVD_PRIMARY | B13: 2036 | C13: I_CVD_PRIMARY | E13: COST_PRIMARY_SCREEN_B | F13: CC_PRIMARY_SCREENING | G13: I_CVD_PRIMARY__C_SHARED | H13: shared-count-once | I13: all | J13: =IFERROR(INDEX('Cost_Components'!$K$2:$K$28,MATCH(E13,'Cost_Components'!$A$2:$A$28,0)),"") | K13: =IF(OR(L13="",Z13="",AA13="",AB13=""),"",IF(B13<AA13,L13,IF(B13>AB13,Z13,L13+(Z13-L13)*MIN(MAX((B13-AA13+1)/MAX(AB13-AA13+1,1),0),1)))) | L13: =IFERROR(INDEX('Cost_Components'!$S$2:$S$28,MATCH(E13,'Cost_Components'!$A$2:$A$28,0)),"") | M13: =IFERROR(INDEX('Cost_Components'!$L$2:$L$28,MATCH(E13,'Cost_Components'!$A$2:$A$28,0)),"") | N13: =IFERROR(INDEX('Cost_Components'!$P$2:$P$28,MATCH(E13,'Cost_Components'!$A$2:$A$28,0)),"") | O13: =AF13*J13 | P13: =AG13*J13 | Q13: =P13*L13*M13*N13 | R13: =O13*K13*M13*N13 | S13: =R13-Q13 | T13: =IFERROR(INDEX('Cost_Components'!$R$2:$R$28,MATCH(E13,'Cost_Components'!$A$2:$A$28,0)),"") | U13: =IFERROR(INDEX('Cost_Components'!$Q$2:$Q$28,MATCH(E13,'Cost_Components'!$A$2:$A$28,0)),"") | V13: =1/(1+'Calculation_Assumptions'!$B$5)^(B13-'Calculation_Assumptions'!$B$2) | W13: =Q13*V13 | X13: =R13*V13 | Y13: =S13*V13 | Z13: =IFERROR(INDEX('Cost_Components'!$T$2:$T$28,MATCH(E13,'Cost_Components'!$A$2:$A$28,0)),"") | AA13: =IFERROR(INDEX('Cost_Components'!$U$2:$U$28,MATCH(E13,'Cost_Components'!$A$2:$A$28,0)),"") | AB13: =IFERROR(INDEX('Cost_Components'!$V$2:$V$28,MATCH(E13,'Cost_Components'!$A$2:$A$28,0)),"") | AC13: =IFERROR(INDEX('Cost_Components'!$M$2:$M$28,MATCH(E13,'Cost_Components'!$A$2:$A$28,0)),"") | AD13: =IFERROR(INDEX('Cost_Components'!$N$2:$N$28,MATCH(E13,'Cost_Components'!$A$2:$A$28,0)),"") | AE13: =IFERROR(INDEX('Cost_Components'!$O$2:$O$28,MATCH(E13,'Cost_Components'!$A$2:$A$28,0)),"") | AF13: 1.7872829e+08 | AG13: 1.7862366e+08 | AH13: =IF(H13="shared-count-once",COUNTIFS($A$2:$A$1405,A13,$B$2:$B$1405,B13,$E$2:$E$1405,E13),1) | AI13: 3.0854277e+08 | AJ13: =IF(AI13=0,"",Q13/AI13) | AK13: =IF(AI13=0,"",R13/AI13) | AL13: =IF(AI13=0,"",S13/AI13) | AM13: =IF(AI13=0,"",Y13/AI13)
... A53: I_CVD_PRIMARY | B53: 2050 | C53: I_CVD_PRIMARY | E53: COST_PRIMARY_TX_B | F53: CC_PRIMARY_HTN_STATIN | G53: I_CVD_PRIMARY__C_SHARED | H53: shared-count-once | I53: all | J53: =IFERROR(INDEX('Cost_Components'!$K$2:$K$28,MATCH(E53,'Cost_Components'!$A$2:$A$28,0)),"") | K53: =IF(OR(L53="",Z53="",AA53="",AB53=""),"",IF(B53<AA53,L53,IF(B53>AB53,Z53,L53+(Z53-L53)*MIN(MAX((B53-AA53+1)/MAX(AB53-AA53+1,1),0),1)))) | L53: =IFERROR(INDEX('Cost_Components'!$S$2:$S$28,MATCH(E53,'Cost_Components'!$A$2:$A$28,0)),"") | M53: =IFERROR(INDEX('Cost_Components'!$L$2:$L$28,MATCH(E53,'Cost_Components'!$A$2:$A$28,0)),"") | N53: =IFERROR(INDEX('Cost_Components'!$P$2:$P$28,MATCH(E53,'Cost_Components'!$A$2:$A$28,0)),"") | O53: =AF53*J53 | P53: =AG53*J53 | Q53: =P53*L53*M53*N53 | R53: =O53*K53*M53*N53 | S53: =R53-Q53 | T53: =IFERROR(INDEX('Cost_Components'!$R$2:$R$28,MATCH(E53,'Cost_Components'!$A$2:$A$28,0)),"") | U53: =IFERROR(INDEX('Cost_Components'!$Q$2:$Q$28,MATCH(E53,'Cost_Components'!$A$2:$A$28,0)),"") | V53: =1/(1+'Calculation_Assumptions'!$B$5)^(B53-'Calculation_Assumptions'!$B$2) | W53: =Q53*V53 | X53: =R53*V53 | Y53: =S53*V53 | Z53: =IFERROR(INDEX('Cost_Components'!$T$2:$T$28,MATCH(E53,'Cost_Components'!$A$2:$A$28,0)),"") | AA53: =IFERROR(INDEX('Cost_Components'!$U$2:$U$28,MATCH(E53,'Cost_Components'!$A$2:$A$28,0)),"") | AB53: =IFERROR(INDEX('Cost_Components'!$V$2:$V$28,MATCH(E53,'Cost_Components'!$A$2:$A$28,0)),"") | AC53: =IFERROR(INDEX('Cost_Components'!$M$2:$M$28,MATCH(E53,'Cost_Components'!$A$2:$A$28,0)),"") | AD53: =IFERROR(INDEX('Cost_Components'!$N$2:$N$28,MATCH(E53,'Cost_Components'!$A$2:$A$28,0)),"") | AE53: =IFERROR(INDEX('Cost_Components'!$O$2:$O$28,MATCH(E53,'Cost_Components'!$A$2:$A$28,0)),"") | AF53: 2.0394969e+08 | AG53: 2.024798e+08 | AH53: =IF(H53="shared-count-once",COUNTIFS($A$2:$A$1405,A53,$B$2:$B$1405,B53,$E$2:$E$1405,E53),1) | AI53: 3.2331204e+08 | AJ53: =IF(AI53=0,"",Q53/AI53) | AK53: =IF(AI53=0,"",R53/AI53) | AL53: =IF(AI53=0,"",S53/AI53) | AM53: =IF(AI53=0,"",Y53/AI53)
A54: I_HF_ACUTE | B54: 2025 | C54: I_HF_ACUTE | D54: cmd | E54: COST_HF_ACUTE_C_CMP | F54: CC_HF_ACUTE_C_CMP | G54: I_HF_ACUTE__C_CMP | H54: cause-specific | I54: prevalence | J54: =IFERROR(INDEX('Cost_Components'!$K$2:$K$28,MATCH(E54,'Cost_Components'!$A$2:$A$28,0)),"") | K54: =IF(OR(L54="",Z54="",AA54="",AB54=""),"",IF(B54<AA54,L54,IF(B54>AB54,Z54,L54+(Z54-L54)*MIN(MAX((B54-AA54+1)/MAX(AB54-AA54+1,1),0),1)))) | L54: =IFERROR(INDEX('Cost_Components'!$S$2:$S$28,MATCH(E54,'Cost_Components'!$A$2:$A$28,0)),"") | M54: =IFERROR(INDEX('Cost_Components'!$L$2:$L$28,MATCH(E54,'Cost_Components'!$A$2:$A$28,0)),"") | N54: =IFERROR(INDEX('Cost_Components'!$P$2:$P$28,MATCH(E54,'Cost_Components'!$A$2:$A$28,0)),"") | O54: =AF54*J54 | P54: =AG54*J54 | Q54: =P54*L54*M54*N54 | R54: =O54*K54*M54*N54 | S54: =R54-Q54 | T54: =IFERROR(INDEX('Cost_Components'!$R$2:$R$28,MATCH(E54,'Cost_Components'!$A$2:$A$28,0)),"") | U54: =IFERROR(INDEX('Cost_Components'!$Q$2:$Q$28,MATCH(E54,'Cost_Components'!$A$2:$A$28,0)),"") | V54: =1/(1+'Calculation_Assumptions'!$B$5)^(B54-'Calculation_Assumptions'!$B$2) | W54: =Q54*V54 | X54: =R54*V54 | Y54: =S54*V54 | Z54: =IFERROR(INDEX('Cost_Components'!$T$2:$T$28,MATCH(E54,'Cost_Components'!$A$2:$A$28,0)),"") | AA54: =IFERROR(INDEX('Cost_Components'!$U$2:$U$28,MATCH(E54,'Cost_Components'!$A$2:$A$28,0)),"") | AB54: =IFERROR(INDEX('Cost_Components'!$V$2:$V$28,MATCH(E54,'Cost_Components'!$A$2:$A$28,0)),"") | AC54: =IFERROR(INDEX('Cost_Components'!$M$2:$M$28,MATCH(E54,'Cost_Components'!$A$2:$A$28,0)),"") | AD54: =IFERROR(INDEX('Cost_Components'!$N$2:$N$28,MATCH(E54,'Cost_Components'!$A$2:$A$28,0)),"") | AE54: =IFERROR(INDEX('Cost_Components'!$O$2:$O$28,MATCH(E54,'Cost_Components'!$A$2:$A$28,0)),"") | AF54: 49675.173 | AG54: 49646.074 | AH54: =IF(H54="shared-count-once",COUNTIFS($A$2:$A$1405,A54,$B$2:$B$1405,B54,$E$2:$E$1405,E54),1) | AI54: 2.8839191e+08 | AJ54: =IF(AI54=0,"",Q54/AI54) | AK54: =IF(AI54=0,"",R54/AI54) | AL54: =IF(AI54=0,"",S54/AI54) | AM54: =IF(AI54=0,"",Y54/AI54)
A55: I_HF_ACUTE | B55: 2026 | C55: I_HF_ACUTE | D55: cmd | E55: COST_HF_ACUTE_C_CMP | F55: CC_HF_ACUTE_C_CMP | G55: I_HF_ACUTE__C_CMP | H55: cause-specific | I55: prevalence | J55: =IFERROR(INDEX('Cost_Components'!$K$2:$K$28,MATCH(E55,'Cost_Components'!$A$2:$A$28,0)),"") | K55: =IF(OR(L55="",Z55="",AA55="",AB55=""),"",IF(B55<AA55,L55,IF(B55>AB55,Z55,L55+(Z55-L55)*MIN(MAX((B55-AA55+1)/MAX(AB55-AA55+1,1),0),1)))) | L55: =IFERROR(INDEX('Cost_Components'!$S$2:$S$28,MATCH(E55,'Cost_Components'!$A$2:$A$28,0)),"") | M55: =IFERROR(INDEX('Cost_Components'!$L$2:$L$28,MATCH(E55,'Cost_Components'!$A$2:$A$28,0)),"") | N55: =IFERROR(INDEX('Cost_Components'!$P$2:$P$28,MATCH(E55,'Cost_Components'!$A$2:$A$28,0)),"") | O55: =AF55*J55 | P55: =AG55*J55 | Q55: =P55*L55*M55*N55 | R55: =O55*K55*M55*N55 | S55: =R55-Q55 | T55: =IFERROR(INDEX('Cost_Components'!$R$2:$R$28,MATCH(E55,'Cost_Components'!$A$2:$A$28,0)),"") | U55: =IFERROR(INDEX('Cost_Components'!$Q$2:$Q$28,MATCH(E55,'Cost_Components'!$A$2:$A$28,0)),"") | V55: =1/(1+'Calculation_Assumptions'!$B$5)^(B55-'Calculation_Assumptions'!$B$2) | W55: =Q55*V55 | X55: =R55*V55 | Y55: =S55*V55 | Z55: =IFERROR(INDEX('Cost_Components'!$T$2:$T$28,MATCH(E55,'Cost_Components'!$A$2:$A$28,0)),"") | AA55: =IFERROR(INDEX('Cost_Components'!$U$2:$U$28,MATCH(E55,'Cost_Components'!$A$2:$A$28,0)),"") | AB55: =IFERROR(INDEX('Cost_Components'!$V$2:$V$28,MATCH(E55,'Cost_Components'!$A$2:$A$28,0)),"") | AC55: =IFERROR(INDEX('Cost_Components'!$M$2:$M$28,MATCH(E55,'Cost_Components'!$A$2:$A$28,0)),"") | AD55: =IFERROR(INDEX('Cost_Components'!$N$2:$N$28,MATCH(E55,'Cost_Components'!$A$2:$A$28,0)),"") | AE55: =IFERROR(INDEX('Cost_Components'!$O$2:$O$28,MATCH(E55,'Cost_Components'!$A$2:$A$28,0)),"") | AF55: 50702.634 | AG55: 50623.241 | AH55: =IF(H55="shared-count-once",COUNTIFS($A$2:$A$1405,A55,$B$2:$B$1405,B55,$E$2:$E$1405,E55),1) | AI55: 2.9047213e+08 | AJ55: =IF(AI55=0,"",Q55/AI55) | AK55: =IF(AI55=0,"",R55/AI55) | AL55: =IF(AI55=0,"",S55/AI55) | AM55: =IF(AI55=0,"",Y55/AI55)
A56: I_HF_ACUTE | B56: 2027 | C56: I_HF_ACUTE | D56: cmd | E56: COST_HF_ACUTE_C_CMP | F56: CC_HF_ACUTE_C_CMP | G56: I_HF_ACUTE__C_CMP | H56: cause-specific | I56: prevalence | J56: =IFERROR(INDEX('Cost_Components'!$K$2:$K$28,MATCH(E56,'Cost_Components'!$A$2:$A$28,0)),"") | K56: =IF(OR(L56="",Z56="",AA56="",AB56=""),"",IF(B56<AA56,L56,IF(B56>AB56,Z56,L56+(Z56-L56)*MIN(MAX((B56-AA56+1)/MAX(AB56-AA56+1,1),0),1)))) | L56: =IFERROR(INDEX('Cost_Components'!$S$2:$S$28,MATCH(E56,'Cost_Components'!$A$2:$A$28,0)),"") | M56: =IFERROR(INDEX('Cost_Components'!$L$2:$L$28,MATCH(E56,'Cost_Components'!$A$2:$A$28,0)),"") | N56: =IFERROR(INDEX('Cost_Components'!$P$2:$P$28,MATCH(E56,'Cost_Components'!$A$2:$A$28,0)),"") | O56: =AF56*J56 | P56: =AG56*J56 | Q56: =P56*L56*M56*N56 | R56: =O56*K56*M56*N56 | S56: =R56-Q56 | T56: =IFERROR(INDEX('Cost_Components'!$R$2:$R$28,MATCH(E56,'Cost_Components'!$A$2:$A$28,0)),"") | U56: =IFERROR(INDEX('Cost_Components'!$Q$2:$Q$28,MATCH(E56,'Cost_Components'!$A$2:$A$28,0)),"") | V56: =1/(1+'Calculation_Assumptions'!$B$5)^(B56-'Calculation_Assumptions'!$B$2) | W56: =Q56*V56 | X56: =R56*V56 | Y56: =S56*V56 | Z56: =IFERROR(INDEX('Cost_Components'!$T$2:$T$28,MATCH(E56,'Cost_Components'!$A$2:$A$28,0)),"") | AA56: =IFERROR(INDEX('Cost_Components'!$U$2:$U$28,MATCH(E56,'Cost_Components'!$A$2:$A$28,0)),"") | AB56: =IFERROR(INDEX('Cost_Components'!$V$2:$V$28,MATCH(E56,'Cost_Components'!$A$2:$A$28,0)),"") | AC56: =IFERROR(INDEX('Cost_Components'!$M$2:$M$28,MATCH(E56,'Cost_Components'!$A$2:$A$28,0)),"") | AD56: =IFERROR(INDEX('Cost_Components'!$N$2:$N$28,MATCH(E56,'Cost_Components'!$A$2:$A$28,0)),"") | AE56: =IFERROR(INDEX('Cost_Components'!$O$2:$O$28,MATCH(E56,'Cost_Components'!$A$2:$A$28,0)),"") | AF56: 51812.898 | AG56: 51666.345 | AH56: =IF(H56="shared-count-once",COUNTIFS($A$2:$A$1405,A56,$B$2:$B$1405,B56,$E$2:$E$1405,E56),1) | AI56: 2.9250508e+08 | AJ56: =IF(AI56=0,"",Q56/AI56) | AK56: =IF(AI56=0,"",R56/AI56) | AL56: =IF(AI56=0,"",S56/AI56) | AM56: =IF(AI56=0,"",Y56/AI56)
A57: I_HF_ACUTE | B57: 2028 | C57: I_HF_ACUTE | D57: cmd | E57: COST_HF_ACUTE_C_CMP | F57: CC_HF_ACUTE_C_CMP | G57: I_HF_ACUTE__C_CMP | H57: cause-specific | I57: prevalence | J57: =IFERROR(INDEX('Cost_Components'!$K$2:$K$28,MATCH(E57,'Cost_Components'!$A$2:$A$28,0)),"") | K57: =IF(OR(L57="",Z57="",AA57="",AB57=""),"",IF(B57<AA57,L57,IF(B57>AB57,Z57,L57+(Z57-L57)*MIN(MAX((B57-AA57+1)/MAX(AB57-AA57+1,1),0),1)))) | L57: =IFERROR(INDEX('Cost_Components'!$S$2:$S$28,MATCH(E57,'Cost_Components'!$A$2:$A$28,0)),"") | M57: =IFERROR(INDEX('Cost_Components'!$L$2:$L$28,MATCH(E57,'Cost_Components'!$A$2:$A$28,0)),"") | N57: =IFERROR(INDEX('Cost_Components'!$P$2:$P$28,MATCH(E57,'Cost_Components'!$A$2:$A$28,0)),"") | O57: =AF57*J57 | P57: =AG57*J57 | Q57: =P57*L57*M57*N57 | R57: =O57*K57*M57*N57 | S57: =R57-Q57 | T57: =IFERROR(INDEX('Cost_Components'!$R$2:$R$28,MATCH(E57,'Cost_Components'!$A$2:$A$28,0)),"") | U57: =IFERROR(INDEX('Cost_Components'!$Q$2:$Q$28,MATCH(E57,'Cost_Components'!$A$2:$A$28,0)),"") | V57: =1/(1+'Calculation_Assumptions'!$B$5)^(B57-'Calculation_Assumptions'!$B$2) | W57: =Q57*V57 | X57: =R57*V57 | Y57: =S57*V57 | Z57: =IFERROR(INDEX('Cost_Components'!$T$2:$T$28,MATCH(E57,'Cost_Components'!$A$2:$A$28,0)),"") | AA57: =IFERROR(INDEX('Cost_Components'!$U$2:$U$28,MATCH(E57,'Cost_Components'!$A$2:$A$28,0)),"") | AB57: =IFERROR(INDEX('Cost_Components'!$V$2:$V$28,MATCH(E57,'Cost_Components'!$A$2:$A$28,0)),"") | AC57: =IFERROR(INDEX('Cost_Components'!$M$2:$M$28,MATCH(E57,'Cost_Components'!$A$2:$A$28,0)),"") | AD57: =IFERROR(INDEX('Cost_Components'!$N$2:$N$28,MATCH(E57,'Cost_Components'!$A$2:$A$28,0)),"") | AE57: =IFERROR(INDEX('Cost_Components'!$O$2:$O$28,MATCH(E57,'Cost_Components'!$A$2:$A$28,0)),"") | AF57: 53148.616 | AG57: 52920.528 | AH57: =IF(H57="shared-count-once",COUNTIFS($A$2:$A$1405,A57,$B$2:$B$1405,B57,$E$2:$E$1405,E57),1) | AI57: 2.9448471e+08 | AJ57: =IF(AI57=0,"",Q57/AI57) | AK57: =IF(AI57=0,"",R57/AI57) | AL57: =IF(AI57=0,"",S57/AI57) | AM57: =IF(AI57=0,"",Y57/AI57)
A58: I_HF_ACUTE | B58: 2029 | C58: I_HF_ACUTE | D58: cmd | E58: COST_HF_ACUTE_C_CMP | F58: CC_HF_ACUTE_C_CMP | G58: I_HF_ACUTE__C_CMP | H58: cause-specific | I58: prevalence | J58: =IFERROR(INDEX('Cost_Components'!$K$2:$K$28,MATCH(E58,'Cost_Components'!$A$2:$A$28,0)),"") | K58: =IF(OR(L58="",Z58="",AA58="",AB58=""),"",IF(B58<AA58,L58,IF(B58>AB58,Z58,L58+(Z58-L58)*MIN(MAX((B58-AA58+1)/MAX(AB58-AA58+1,1),0),1)))) | L58: =IFERROR(INDEX('Cost_Components'!$S$2:$S$28,MATCH(E58,'Cost_Components'!$A$2:$A$28,0)),"") | M58: =IFERROR(INDEX('Cost_Components'!$L$2:$L$28,MATCH(E58,'Cost_Components'!$A$2:$A$28,0)),"") | N58: =IFERROR(INDEX('Cost_Components'!$P$2:$P$28,MATCH(E58,'Cost_Components'!$A$2:$A$28,0)),"") | O58: =AF58*J58 | P58: =AG58*J58 | Q58: =P58*L58*M58*N58 | R58: =O58*K58*M58*N58 | S58: =R58-Q58 | T58: =IFERROR(INDEX('Cost_Components'!$R$2:$R$28,MATCH(E58,'Cost_Components'!$A$2:$A$28,0)),"") | U58: =IFERROR(INDEX('Cost_Components'!$Q$2:$Q$28,MATCH(E58,'Cost_Components'!$A$2:$A$28,0)),"") | V58: =1/(1+'Calculation_Assumptions'!$B$5)^(B58-'Calculation_Assumptions'!$B$2) | W58: =Q58*V58 | X58: =R58*V58 | Y58: =S58*V58 | Z58: =IFERROR(INDEX('Cost_Components'!$T$2:$T$28,MATCH(E58,'Cost_Components'!$A$2:$A$28,0)),"") | AA58: =IFERROR(INDEX('Cost_Components'!$U$2:$U$28,MATCH(E58,'Cost_Components'!$A$2:$A$28,0)),"") | AB58: =IFERROR(INDEX('Cost_Components'!$V$2:$V$28,MATCH(E58,'Cost_Components'!$A$2:$A$28,0)),"") | AC58: =IFERROR(INDEX('Cost_Components'!$M$2:$M$28,MATCH(E58,'Cost_Components'!$A$2:$A$28,0)),"") | AD58: =IFERROR(INDEX('Cost_Components'!$N$2:$N$28,MATCH(E58,'Cost_Components'!$A$2:$A$28,0)),"") | AE58: =IFERROR(INDEX('Cost_Components'!$O$2:$O$28,MATCH(E58,'Cost_Components'!$A$2:$A$28,0)),"") | AF58: 54512.202 | AG58: 54189.784 | AH58: =IF(H58="shared-count-once",COUNTIFS($A$2:$A$1405,A58,$B$2:$B$1405,B58,$E$2:$E$1405,E58),1) | AI58: 2.9641403e+08 | AJ58: =IF(AI58=0,"",Q58/AI58) | AK58: =IF(AI58=0,"",R58/AI58) | AL58: =IF(AI58=0,"",S58/AI58) | AM58: =IF(AI58=0,"",Y58/AI58)
A59: I_HF_ACUTE | B59: 2030 | C59: I_HF_ACUTE | D59: cmd | E59: COST_HF_ACUTE_C_CMP | F59: CC_HF_ACUTE_C_CMP | G59: I_HF_ACUTE__C_CMP | H59: cause-specific | I59: prevalence | J59: =IFERROR(INDEX('Cost_Components'!$K$2:$K$28,MATCH(E59,'Cost_Components'!$A$2:$A$28,0)),"") | K59: =IF(OR(L59="",Z59="",AA59="",AB59=""),"",IF(B59<AA59,L59,IF(B59>AB59,Z59,L59+(Z59-L59)*MIN(MAX((B59-AA59+1)/MAX(AB59-AA59+1,1),0),1)))) | L59: =IFERROR(INDEX('Cost_Components'!$S$2:$S$28,MATCH(E59,'Cost_Components'!$A$2:$A$28,0)),"") | M59: =IFERROR(INDEX('Cost_Components'!$L$2:$L$28,MATCH(E59,'Cost_Components'!$A$2:$A$28,0)),"") | N59: =IFERROR(INDEX('Cost_Components'!$P$2:$P$28,MATCH(E59,'Cost_Components'!$A$2:$A$28,0)),"") | O59: =AF59*J59 | P59: =AG59*J59 | Q59: =P59*L59*M59*N59 | R59: =O59*K59*M59*N59 | S59: =R59-Q59 | T59: =IFERROR(INDEX('Cost_Components'!$R$2:$R$28,MATCH(E59,'Cost_Components'!$A$2:$A$28,0)),"") | U59: =IFERROR(INDEX('Cost_Components'!$Q$2:$Q$28,MATCH(E59,'Cost_Components'!$A$2:$A$28,0)),"") | V59: =1/(1+'Calculation_Assumptions'!$B$5)^(B59-'Calculation_Assumptions'!$B$2) | W59: =Q59*V59 | X59: =R59*V59 | Y59: =S59*V59 | Z59: =IFERROR(INDEX('Cost_Components'!$T$2:$T$28,MATCH(E59,'Cost_Components'!$A$2:$A$28,0)),"") | AA59: =IFERROR(INDEX('Cost_Components'!$U$2:$U$28,MATCH(E59,'Cost_Components'!$A$2:$A$28,0)),"") | AB59: =IFERROR(INDEX('Cost_Components'!$V$2:$V$28,MATCH(E59,'Cost_Components'!$A$2:$A$28,0)),"") | AC59: =IFERROR(INDEX('Cost_Components'!$M$2:$M$28,MATCH(E59,'Cost_Components'!$A$2:$A$28,0)),"") | AD59: =IFERROR(INDEX('Cost_Components'!$N$2:$N$28,MATCH(E59,'Cost_Components'!$A$2:$A$28,0)),"") | AE59: =IFERROR(INDEX('Cost_Components'!$O$2:$O$28,MATCH(E59,'Cost_Components'!$A$2:$A$28,0)),"") | AF59: 55932.479 | AG59: 55504.081 | AH59: =IF(H59="shared-count-once",COUNTIFS($A$2:$A$1405,A59,$B$2:$B$1405,B59,$E$2:$E$1405,E59),1) | AI59: 2.982894e+08 | AJ59: =IF(AI59=0,"",Q59/AI59) | AK59: =IF(AI59=0,"",R59/AI59) | AL59: =IF(AI59=0,"",S59/AI59) | AM59: =IF(AI59=0,"",Y59/AI59)
A60: I_HF_ACUTE | B60: 2031 | C60: I_HF_ACUTE | D60: cmd | E60: COST_HF_ACUTE_C_CMP | F60: CC_HF_ACUTE_C_CMP | G60: I_HF_ACUTE__C_CMP | H60: cause-specific | I60: prevalence | J60: =IFERROR(INDEX('Cost_Components'!$K$2:$K$28,MATCH(E60,'Cost_Components'!$A$2:$A$28,0)),"") | K60: =IF(OR(L60="",Z60="",AA60="",AB60=""),"",IF(B60<AA60,L60,IF(B60>AB60,Z60,L60+(Z60-L60)*MIN(MAX((B60-AA60+1)/MAX(AB60-AA60+1,1),0),1)))) | L60: =IFERROR(INDEX('Cost_Components'!$S$2:$S$28,MATCH(E60,'Cost_Components'!$A$2:$A$28,0)),"") | M60: =IFERROR(INDEX('Cost_Components'!$L$2:$L$28,MATCH(E60,'Cost_Components'!$A$2:$A$28,0)),"") | N60: =IFERROR(INDEX('Cost_Components'!$P$2:$P$28,MATCH(E60,'Cost_Components'!$A$2:$A$28,0)),"") | O60: =AF60*J60 | P60: =AG60*J60 | Q60: =P60*L60*M60*N60 | R60: =O60*K60*M60*N60 | S60: =R60-Q60 | T60: =IFERROR(INDEX('Cost_Components'!$R$2:$R$28,MATCH(E60,'Cost_Components'!$A$2:$A$28,0)),"") | U60: =IFERROR(INDEX('Cost_Components'!$Q$2:$Q$28,MATCH(E60,'Cost_Components'!$A$2:$A$28,0)),"") | V60: =1/(1+'Calculation_Assumptions'!$B$5)^(B60-'Calculation_Assumptions'!$B$2) | W60: =Q60*V60 | X60: =R60*V60 | Y60: =S60*V60 | Z60: =IFERROR(INDEX('Cost_Components'!$T$2:$T$28,MATCH(E60,'Cost_Components'!$A$2:$A$28,0)),"") | AA60: =IFERROR(INDEX('Cost_Components'!$U$2:$U$28,MATCH(E60,'Cost_Components'!$A$2:$A$28,0)),"") | AB60: =IFERROR(INDEX('Cost_Components'!$V$2:$V$28,MATCH(E60,'Cost_Components'!$A$2:$A$28,0)),"") | AC60: =IFERROR(INDEX('Cost_Components'!$M$2:$M$28,MATCH(E60,'Cost_Components'!$A$2:$A$28,0)),"") | AD60: =IFERROR(INDEX('Cost_Components'!$N$2:$N$28,MATCH(E60,'Cost_Components'!$A$2:$A$28,0)),"") | AE60: =IFERROR(INDEX('Cost_Components'!$O$2:$O$28,MATCH(E60,'Cost_Components'!$A$2:$A$28,0)),"") | AF60: 57382.98 | AG60: 56837.904 | AH60: =IF(H60="shared-count-once",COUNTIFS($A$2:$A$1405,A60,$B$2:$B$1405,B60,$E$2:$E$1405,E60),1) | AI60: 3.0011964e+08 | AJ60: =IF(AI60=0,"",Q60/AI60) | AK60: =IF(AI60=0,"",R60/AI60) | AL60: =IF(AI60=0,"",S60/AI60) | AM60: =IF(AI60=0,"",Y60/AI60)
A61: I_HF_ACUTE | B61: 2032 | C61: I_HF_ACUTE | D61: cmd | E61: COST_HF_ACUTE_C_CMP | F61: CC_HF_ACUTE_C_CMP | G61: I_HF_ACUTE__C_CMP | H61: cause-specific | I61: prevalence | J61: =IFERROR(INDEX('Cost_Components'!$K$2:$K$28,MATCH(E61,'Cost_Components'!$A$2:$A$28,0)),"") | K61: =IF(OR(L61="",Z61="",AA61="",AB61=""),"",IF(B61<AA61,L61,IF(B61>AB61,Z61,L61+(Z61-L61)*MIN(MAX((B61-AA61+1)/MAX(AB61-AA61+1,1),0),1)))) | L61: =IFERROR(INDEX('Cost_Components'!$S$2:$S$28,MATCH(E61,'Cost_Components'!$A$2:$A$28,0)),"") | M61: =IFERROR(INDEX('Cost_Components'!$L$2:$L$28,MATCH(E61,'Cost_Components'!$A$2:$A$28,0)),"") | N61: =IFERROR(INDEX('Cost_Components'!$P$2:$P$28,MATCH(E61,'Cost_Components'!$A$2:$A$28,0)),"") | O61: =AF61*J61 | P61: =AG61*J61 | Q61: =P61*L61*M61*N61 | R61: =O61*K61*M61*N61 | S61: =R61-Q61 | T61: =IFERROR(INDEX('Cost_Components'!$R$2:$R$28,MATCH(E61,'Cost_Components'!$A$2:$A$28,0)),"") | U61: =IFERROR(INDEX('Cost_Components'!$Q$2:$Q$28,MATCH(E61,'Cost_Components'!$A$2:$A$28,0)),"") | V61: =1/(1+'Calculation_Assumptions'!$B$5)^(B61-'Calculation_Assumptions'!$B$2) | W61: =Q61*V61 | X61: =R61*V61 | Y61: =S61*V61 | Z61: =IFERROR(INDEX('Cost_Components'!$T$2:$T$28,MATCH(E61,'Cost_Components'!$A$2:$A$28,0)),"") | AA61: =IFERROR(INDEX('Cost_Components'!$U$2:$U$28,MATCH(E61,'Cost_Components'!$A$2:$A$28,0)),"") | AB61: =IFERROR(INDEX('Cost_Components'!$V$2:$V$28,MATCH(E61,'Cost_Components'!$A$2:$A$28,0)),"") | AC61: =IFERROR(INDEX('Cost_Components'!$M$2:$M$28,MATCH(E61,'Cost_Components'!$A$2:$A$28,0)),"") | AD61: =IFERROR(INDEX('Cost_Components'!$N$2:$N$28,MATCH(E61,'Cost_Components'!$A$2:$A$28,0)),"") | AE61: =IFERROR(INDEX('Cost_Components'!$O$2:$O$28,MATCH(E61,'Cost_Components'!$A$2:$A$28,0)),"") | AF61: 58855.934 | AG61: 58184.138 | AH61: =IF(H61="shared-count-once",COUNTIFS($A$2:$A$1405,A61,$B$2:$B$1405,B61,$E$2:$E$1405,E61),1) | AI61: 3.0190463e+08 | AJ61: =IF(AI61=0,"",Q61/AI61) | AK61: =IF(AI61=0,"",R61/AI61) | AL61: =IF(AI61=0,"",S61/AI61) | AM61: =IF(AI61=0,"",Y61/AI61)
A62: I_HF_ACUTE | B62: 2033 | C62: I_HF_ACUTE | D62: cmd | E62: COST_HF_ACUTE_C_CMP | F62: CC_HF_ACUTE_C_CMP | G62: I_HF_ACUTE__C_CMP | H62: cause-specific | I62: prevalence | J62: =IFERROR(INDEX('Cost_Components'!$K$2:$K$28,MATCH(E62,'Cost_Components'!$A$2:$A$28,0)),"") | K62: =IF(OR(L62="",Z62="",AA62="",AB62=""),"",IF(B62<AA62,L62,IF(B62>AB62,Z62,L62+(Z62-L62)*MIN(MAX((B62-AA62+1)/MAX(AB62-AA62+1,1),0),1)))) | L62: =IFERROR(INDEX('Cost_Components'!$S$2:$S$28,MATCH(E62,'Cost_Components'!$A$2:$A$28,0)),"") | M62: =IFERROR(INDEX('Cost_Components'!$L$2:$L$28,MATCH(E62,'Cost_Components'!$A$2:$A$28,0)),"") | N62: =IFERROR(INDEX('Cost_Components'!$P$2:$P$28,MATCH(E62,'Cost_Components'!$A$2:$A$28,0)),"") | O62: =AF62*J62 | P62: =AG62*J62 | Q62: =P62*L62*M62*N62 | R62: =O62*K62*M62*N62 | S62: =R62-Q62 | T62: =IFERROR(INDEX('Cost_Components'!$R$2:$R$28,MATCH(E62,'Cost_Components'!$A$2:$A$28,0)),"") | U62: =IFERROR(INDEX('Cost_Components'!$Q$2:$Q$28,MATCH(E62,'Cost_Components'!$A$2:$A$28,0)),"") | V62: =1/(1+'Calculation_Assumptions'!$B$5)^(B62-'Calculation_Assumptions'!$B$2) | W62: =Q62*V62 | X62: =R62*V62 | Y62: =S62*V62 | Z62: =IFERROR(INDEX('Cost_Components'!$T$2:$T$28,MATCH(E62,'Cost_Components'!$A$2:$A$28,0)),"") | AA62: =IFERROR(INDEX('Cost_Components'!$U$2:$U$28,MATCH(E62,'Cost_Components'!$A$2:$A$28,0)),"") | AB62: =IFERROR(INDEX('Cost_Components'!$V$2:$V$28,MATCH(E62,'Cost_Components'!$A$2:$A$28,0)),"") | AC62: =IFERROR(INDEX('Cost_Components'!$M$2:$M$28,MATCH(E62,'Cost_Components'!$A$2:$A$28,0)),"") | AD62: =IFERROR(INDEX('Cost_Components'!$N$2:$N$28,MATCH(E62,'Cost_Components'!$A$2:$A$28,0)),"") | AE62: =IFERROR(INDEX('Cost_Components'!$O$2:$O$28,MATCH(E62,'Cost_Components'!$A$2:$A$28,0)),"") | AF62: 60337.332 | AG62: 59529.008 | AH62: =IF(H62="shared-count-once",COUNTIFS($A$2:$A$1405,A62,$B$2:$B$1405,B62,$E$2:$E$1405,E62),1) | AI62: 3.0364428e+08 | AJ62: =IF(AI62=0,"",Q62/AI62) | AK62: =IF(AI62=0,"",R62/AI62) | AL62: =IF(AI62=0,"",S62/AI62) | AM62: =IF(AI62=0,"",Y62/AI62)
A63: I_HF_ACUTE | B63: 2034 | C63: I_HF_ACUTE | D63: cmd | E63: COST_HF_ACUTE_C_CMP | F63: CC_HF_ACUTE_C_CMP | G63: I_HF_ACUTE__C_CMP | H63: cause-specific | I63: prevalence | J63: =IFERROR(INDEX('Cost_Components'!$K$2:$K$28,MATCH(E63,'Cost_Components'!$A$2:$A$28,0)),"") | K63: =IF(OR(L63="",Z63="",AA63="",AB63=""),"",IF(B63<AA63,L63,IF(B63>AB63,Z63,L63+(Z63-L63)*MIN(MAX((B63-AA63+1)/MAX(AB63-AA63+1,1),0),1)))) | L63: =IFERROR(INDEX('Cost_Components'!$S$2:$S$28,MATCH(E63,'Cost_Components'!$A$2:$A$28,0)),"") | M63: =IFERROR(INDEX('Cost_Components'!$L$2:$L$28,MATCH(E63,'Cost_Components'!$A$2:$A$28,0)),"") | N63: =IFERROR(INDEX('Cost_Components'!$P$2:$P$28,MATCH(E63,'Cost_Components'!$A$2:$A$28,0)),"") | O63: =AF63*J63 | P63: =AG63*J63 | Q63: =P63*L63*M63*N63 | R63: =O63*K63*M63*N63 | S63: =R63-Q63 | T63: =IFERROR(INDEX('Cost_Components'!$R$2:$R$28,MATCH(E63,'Cost_Components'!$A$2:$A$28,0)),"") | U63: =IFERROR(INDEX('Cost_Components'!$Q$2:$Q$28,MATCH(E63,'Cost_Components'!$A$2:$A$28,0)),"") | V63: =1/(1+'Calculation_Assumptions'!$B$5)^(B63-'Calculation_Assumptions'!$B$2) | W63: =Q63*V63 | X63: =R63*V63 | Y63: =S63*V63 | Z63: =IFERROR(INDEX('Cost_Components'!$T$2:$T$28,MATCH(E63,'Cost_Components'!$A$2:$A$28,0)),"") | AA63: =IFERROR(INDEX('Cost_Components'!$U$2:$U$28,MATCH(E63,'Cost_Components'!$A$2:$A$28,0)),"") | AB63: =IFERROR(INDEX('Cost_Components'!$V$2:$V$28,MATCH(E63,'Cost_Components'!$A$2:$A$28,0)),"") | AC63: =IFERROR(INDEX('Cost_Components'!$M$2:$M$28,MATCH(E63,'Cost_Components'!$A$2:$A$28,0)),"") | AD63: =IFERROR(INDEX('Cost_Components'!$N$2:$N$28,MATCH(E63,'Cost_Components'!$A$2:$A$28,0)),"") | AE63: =IFERROR(INDEX('Cost_Components'!$O$2:$O$28,MATCH(E63,'Cost_Components'!$A$2:$A$28,0)),"") | AF63: 61824.285 | AG63: 60869.948 | AH63: =IF(H63="shared-count-once",COUNTIFS($A$2:$A$1405,A63,$B$2:$B$1405,B63,$E$2:$E$1405,E63),1) | AI63: 3.0533254e+08 | AJ63: =IF(AI63=0,"",Q63/AI63) | AK63: =IF(AI63=0,"",R63/AI63) | AL63: =IF(AI63=0,"",S63/AI63) | AM63: =IF(AI63=0,"",Y63/AI63)
A64: I_HF_ACUTE | B64: 2035 | C64: I_HF_ACUTE | D64: cmd | E64: COST_HF_ACUTE_C_CMP | F64: CC_HF_ACUTE_C_CMP | G64: I_HF_ACUTE__C_CMP | H64: cause-specific | I64: prevalence | J64: =IFERROR(INDEX('Cost_Components'!$K$2:$K$28,MATCH(E64,'Cost_Components'!$A$2:$A$28,0)),"") | K64: =IF(OR(L64="",Z64="",AA64="",AB64=""),"",IF(B64<AA64,L64,IF(B64>AB64,Z64,L64+(Z64-L64)*MIN(MAX((B64-AA64+1)/MAX(AB64-AA64+1,1),0),1)))) | L64: =IFERROR(INDEX('Cost_Components'!$S$2:$S$28,MATCH(E64,'Cost_Components'!$A$2:$A$28,0)),"") | M64: =IFERROR(INDEX('Cost_Components'!$L$2:$L$28,MATCH(E64,'Cost_Components'!$A$2:$A$28,0)),"") | N64: =IFERROR(INDEX('Cost_Components'!$P$2:$P$28,MATCH(E64,'Cost_Components'!$A$2:$A$28,0)),"") | O64: =AF64*J64 | P64: =AG64*J64 | Q64: =P64*L64*M64*N64 | R64: =O64*K64*M64*N64 | S64: =R64-Q64 | T64: =IFERROR(INDEX('Cost_Components'!$R$2:$R$28,MATCH(E64,'Cost_Components'!$A$2:$A$28,0)),"") | U64: =IFERROR(INDEX('Cost_Components'!$Q$2:$Q$28,MATCH(E64,'Cost_Components'!$A$2:$A$28,0)),"") | V64: =1/(1+'Calculation_Assumptions'!$B$5)^(B64-'Calculation_Assumptions'!$B$2) | W64: =Q64*V64 | X64: =R64*V64 | Y64: =S64*V64 | Z64: =IFERROR(INDEX('Cost_Components'!$T$2:$T$28,MATCH(E64,'Cost_Components'!$A$2:$A$28,0)),"") | AA64: =IFERROR(INDEX('Cost_Components'!$U$2:$U$28,MATCH(E64,'Cost_Components'!$A$2:$A$28,0)),"") | AB64: =IFERROR(INDEX('Cost_Components'!$V$2:$V$28,MATCH(E64,'Cost_Components'!$A$2:$A$28,0)),"") | AC64: =IFERROR(INDEX('Cost_Components'!$M$2:$M$28,MATCH(E64,'Cost_Components'!$A$2:$A$28,0)),"") | AD64: =IFERROR(INDEX('Cost_Components'!$N$2:$N$28,MATCH(E64,'Cost_Components'!$A$2:$A$28,0)),"") | AE64: =IFERROR(INDEX('Cost_Components'!$O$2:$O$28,MATCH(E64,'Cost_Components'!$A$2:$A$28,0)),"") | AF64: 63405.501 | AG64: 62296.1 | AH64: =IF(H64="shared-count-once",COUNTIFS($A$2:$A$1405,A64,$B$2:$B$1405,B64,$E$2:$E$1405,E64),1) | AI64: 3.0696465e+08 | AJ64: =IF(AI64=0,"",Q64/AI64) | AK64: =IF(AI64=0,"",R64/AI64) | AL64: =IF(AI64=0,"",S64/AI64) | AM64: =IF(AI64=0,"",Y64/AI64)
A65: I_HF_ACUTE | B65: 2036 | C65: I_HF_ACUTE | D65: cmd | E65: COST_HF_ACUTE_C_CMP | F65: CC_HF_ACUTE_C_CMP | G65: I_HF_ACUTE__C_CMP | H65: cause-specific | I65: prevalence | J65: =IFERROR(INDEX('Cost_Components'!$K$2:$K$28,MATCH(E65,'Cost_Components'!$A$2:$A$28,0)),"") | K65: =IF(OR(L65="",Z65="",AA65="",AB65=""),"",IF(B65<AA65,L65,IF(B65>AB65,Z65,L65+(Z65-L65)*MIN(MAX((B65-AA65+1)/MAX(AB65-AA65+1,1),0),1)))) | L65: =IFERROR(INDEX('Cost_Components'!$S$2:$S$28,MATCH(E65,'Cost_Components'!$A$2:$A$28,0)),"") | M65: =IFERROR(INDEX('Cost_Components'!$L$2:$L$28,MATCH(E65,'Cost_Components'!$A$2:$A$28,0)),"") | N65: =IFERROR(INDEX('Cost_Components'!$P$2:$P$28,MATCH(E65,'Cost_Components'!$A$2:$A$28,0)),"") | O65: =AF65*J65 | P65: =AG65*J65 | Q65: =P65*L65*M65*N65 | R65: =O65*K65*M65*N65 | S65: =R65-Q65 | T65: =IFERROR(INDEX('Cost_Components'!$R$2:$R$28,MATCH(E65,'Cost_Components'!$A$2:$A$28,0)),"") | U65: =IFERROR(INDEX('Cost_Components'!$Q$2:$Q$28,MATCH(E65,'Cost_Components'!$A$2:$A$28,0)),"") | V65: =1/(1+'Calculation_Assumptions'!$B$5)^(B65-'Calculation_Assumptions'!$B$2) | W65: =Q65*V65 | X65: =R65*V65 | Y65: =S65*V65 | Z65: =IFERROR(INDEX('Cost_Components'!$T$2:$T$28,MATCH(E65,'Cost_Components'!$A$2:$A$28,0)),"") | AA65: =IFERROR(INDEX('Cost_Components'!$U$2:$U$28,MATCH(E65,'Cost_Components'!$A$2:$A$28,0)),"") | AB65: =IFERROR(INDEX('Cost_Components'!$V$2:$V$28,MATCH(E65,'Cost_Components'!$A$2:$A$28,0)),"") | AC65: =IFERROR(INDEX('Cost_Components'!$M$2:$M$28,MATCH(E65,'Cost_Components'!$A$2:$A$28,0)),"") | AD65: =IFERROR(INDEX('Cost_Components'!$N$2:$N$28,MATCH(E65,'Cost_Components'!$A$2:$A$28,0)),"") | AE65: =IFERROR(INDEX('Cost_Components'!$O$2:$O$28,MATCH(E65,'Cost_Components'!$A$2:$A$28,0)),"") | AF65: 65053.688 | AG65: 63780.093 | AH65: =IF(H65="shared-count-once",COUNTIFS($A$2:$A$1405,A65,$B$2:$B$1405,B65,$E$2:$E$1405,E65),1) | AI65: 3.0854277e+08 | AJ65: =IF(AI65=0,"",Q65/AI65) | AK65: =IF(AI65=0,"",R65/AI65) | AL65: =IF(AI65=0,"",S65/AI65) | AM65: =IF(AI65=0,"",Y65/AI65)
... A703: I_T2D_TREATMENT | B703: 2050 | C703: I_T2D_TREATMENT | D703: dm2 | E703: COST_T2D_INSULIN | F703: CC_T2D_INSULIN | G703: I_T2D_TREATMENT__C_T2D | H703: cause-specific | I703: prevalence | J703: =IFERROR(INDEX('Cost_Components'!$K$2:$K$28,MATCH(E703,'Cost_Components'!$A$2:$A$28,0)),"") | K703: =IF(OR(L703="",Z703="",AA703="",AB703=""),"",IF(B703<AA703,L703,IF(B703>AB703,Z703,L703+(Z703-L703)*MIN(MAX((B703-AA703+1)/MAX(AB703-AA703+1,1),0),1)))) | L703: =IFERROR(INDEX('Cost_Components'!$S$2:$S$28,MATCH(E703,'Cost_Components'!$A$2:$A$28,0)),"") | M703: =IFERROR(INDEX('Cost_Components'!$L$2:$L$28,MATCH(E703,'Cost_Components'!$A$2:$A$28,0)),"") | N703: =IFERROR(INDEX('Cost_Components'!$P$2:$P$28,MATCH(E703,'Cost_Components'!$A$2:$A$28,0)),"") | O703: =AF703*J703 | P703: =AG703*J703 | Q703: =P703*L703*M703*N703 | R703: =O703*K703*M703*N703 | S703: =R703-Q703 | T703: =IFERROR(INDEX('Cost_Components'!$R$2:$R$28,MATCH(E703,'Cost_Components'!$A$2:$A$28,0)),"") | U703: =IFERROR(INDEX('Cost_Components'!$Q$2:$Q$28,MATCH(E703,'Cost_Components'!$A$2:$A$28,0)),"") | V703: =1/(1+'Calculation_Assumptions'!$B$5)^(B703-'Calculation_Assumptions'!$B$2) | W703: =Q703*V703 | X703: =R703*V703 | Y703: =S703*V703 | Z703: =IFERROR(INDEX('Cost_Components'!$T$2:$T$28,MATCH(E703,'Cost_Components'!$A$2:$A$28,0)),"") | AA703: =IFERROR(INDEX('Cost_Components'!$U$2:$U$28,MATCH(E703,'Cost_Components'!$A$2:$A$28,0)),"") | AB703: =IFERROR(INDEX('Cost_Components'!$V$2:$V$28,MATCH(E703,'Cost_Components'!$A$2:$A$28,0)),"") | AC703: =IFERROR(INDEX('Cost_Components'!$M$2:$M$28,MATCH(E703,'Cost_Components'!$A$2:$A$28,0)),"") | AD703: =IFERROR(INDEX('Cost_Components'!$N$2:$N$28,MATCH(E703,'Cost_Components'!$A$2:$A$28,0)),"") | AE703: =IFERROR(INDEX('Cost_Components'!$O$2:$O$28,MATCH(E703,'Cost_Components'!$A$2:$A$28,0)),"") | AF703: 25339168 | AG703: 25030421 | AH703: =IF(H703="shared-count-once",COUNTIFS($A$2:$A$1405,A703,$B$2:$B$1405,B703,$E$2:$E$1405,E703),1) | AI703: 3.2331204e+08 | AJ703: =IF(AI703=0,"",Q703/AI703) | AK703: =IF(AI703=0,"",R703/AI703) | AL703: =IF(AI703=0,"",S703/AI703) | AM703: =IF(AI703=0,"",Y703/AI703)
A704: all | B704: 2025 | C704: I_CVD_PRIMARY | E704: COST_PRIMARY_SCREEN_B | F704: CC_PRIMARY_SCREENING | G704: I_CVD_PRIMARY__C_SHARED | H704: shared-count-once | I704: all | J704: =IFERROR(INDEX('Cost_Components'!$K$2:$K$28,MATCH(E704,'Cost_Components'!$A$2:$A$28,0)),"") | K704: =IF(OR(L704="",Z704="",AA704="",AB704=""),"",IF(B704<AA704,L704,IF(B704>AB704,Z704,L704+(Z704-L704)*MIN(MAX((B704-AA704+1)/MAX(AB704-AA704+1,1),0),1)))) | L704: =IFERROR(INDEX('Cost_Components'!$S$2:$S$28,MATCH(E704,'Cost_Components'!$A$2:$A$28,0)),"") | M704: =IFERROR(INDEX('Cost_Components'!$L$2:$L$28,MATCH(E704,'Cost_Components'!$A$2:$A$28,0)),"") | N704: =IFERROR(INDEX('Cost_Components'!$P$2:$P$28,MATCH(E704,'Cost_Components'!$A$2:$A$28,0)),"") | O704: =AF704*J704 | P704: =AG704*J704 | Q704: =P704*L704*M704*N704 | R704: =O704*K704*M704*N704 | S704: =R704-Q704 | T704: =IFERROR(INDEX('Cost_Components'!$R$2:$R$28,MATCH(E704,'Cost_Components'!$A$2:$A$28,0)),"") | U704: =IFERROR(INDEX('Cost_Components'!$Q$2:$Q$28,MATCH(E704,'Cost_Components'!$A$2:$A$28,0)),"") | V704: =1/(1+'Calculation_Assumptions'!$B$5)^(B704-'Calculation_Assumptions'!$B$2) | W704: =Q704*V704 | X704: =R704*V704 | Y704: =S704*V704 | Z704: =IFERROR(INDEX('Cost_Components'!$T$2:$T$28,MATCH(E704,'Cost_Components'!$A$2:$A$28,0)),"") | AA704: =IFERROR(INDEX('Cost_Components'!$U$2:$U$28,MATCH(E704,'Cost_Components'!$A$2:$A$28,0)),"") | AB704: =IFERROR(INDEX('Cost_Components'!$V$2:$V$28,MATCH(E704,'Cost_Components'!$A$2:$A$28,0)),"") | AC704: =IFERROR(INDEX('Cost_Components'!$M$2:$M$28,MATCH(E704,'Cost_Components'!$A$2:$A$28,0)),"") | AD704: =IFERROR(INDEX('Cost_Components'!$N$2:$N$28,MATCH(E704,'Cost_Components'!$A$2:$A$28,0)),"") | AE704: =IFERROR(INDEX('Cost_Components'!$O$2:$O$28,MATCH(E704,'Cost_Components'!$A$2:$A$28,0)),"") | AF704: 1.5509319e+08 | AG704: 1.5509319e+08 | AH704: =IF(H704="shared-count-once",COUNTIFS($A$2:$A$1405,A704,$B$2:$B$1405,B704,$E$2:$E$1405,E704),1) | AI704: 2.8839191e+08 | AJ704: =IF(AI704=0,"",Q704/AI704) | AK704: =IF(AI704=0,"",R704/AI704) | AL704: =IF(AI704=0,"",S704/AI704) | AM704: =IF(AI704=0,"",Y704/AI704)
A705: all | B705: 2026 | C705: I_CVD_PRIMARY | E705: COST_PRIMARY_SCREEN_B | F705: CC_PRIMARY_SCREENING | G705: I_CVD_PRIMARY__C_SHARED | H705: shared-count-once | I705: all | J705: =IFERROR(INDEX('Cost_Components'!$K$2:$K$28,MATCH(E705,'Cost_Components'!$A$2:$A$28,0)),"") | K705: =IF(OR(L705="",Z705="",AA705="",AB705=""),"",IF(B705<AA705,L705,IF(B705>AB705,Z705,L705+(Z705-L705)*MIN(MAX((B705-AA705+1)/MAX(AB705-AA705+1,1),0),1)))) | L705: =IFERROR(INDEX('Cost_Components'!$S$2:$S$28,MATCH(E705,'Cost_Components'!$A$2:$A$28,0)),"") | M705: =IFERROR(INDEX('Cost_Components'!$L$2:$L$28,MATCH(E705,'Cost_Components'!$A$2:$A$28,0)),"") | N705: =IFERROR(INDEX('Cost_Components'!$P$2:$P$28,MATCH(E705,'Cost_Components'!$A$2:$A$28,0)),"") | O705: =AF705*J705 | P705: =AG705*J705 | Q705: =P705*L705*M705*N705 | R705: =O705*K705*M705*N705 | S705: =R705-Q705 | T705: =IFERROR(INDEX('Cost_Components'!$R$2:$R$28,MATCH(E705,'Cost_Components'!$A$2:$A$28,0)),"") | U705: =IFERROR(INDEX('Cost_Components'!$Q$2:$Q$28,MATCH(E705,'Cost_Components'!$A$2:$A$28,0)),"") | V705: =1/(1+'Calculation_Assumptions'!$B$5)^(B705-'Calculation_Assumptions'!$B$2) | W705: =Q705*V705 | X705: =R705*V705 | Y705: =S705*V705 | Z705: =IFERROR(INDEX('Cost_Components'!$T$2:$T$28,MATCH(E705,'Cost_Components'!$A$2:$A$28,0)),"") | AA705: =IFERROR(INDEX('Cost_Components'!$U$2:$U$28,MATCH(E705,'Cost_Components'!$A$2:$A$28,0)),"") | AB705: =IFERROR(INDEX('Cost_Components'!$V$2:$V$28,MATCH(E705,'Cost_Components'!$A$2:$A$28,0)),"") | AC705: =IFERROR(INDEX('Cost_Components'!$M$2:$M$28,MATCH(E705,'Cost_Components'!$A$2:$A$28,0)),"") | AD705: =IFERROR(INDEX('Cost_Components'!$N$2:$N$28,MATCH(E705,'Cost_Components'!$A$2:$A$28,0)),"") | AE705: =IFERROR(INDEX('Cost_Components'!$O$2:$O$28,MATCH(E705,'Cost_Components'!$A$2:$A$28,0)),"") | AF705: 1.5750761e+08 | AG705: 1.5750383e+08 | AH705: =IF(H705="shared-count-once",COUNTIFS($A$2:$A$1405,A705,$B$2:$B$1405,B705,$E$2:$E$1405,E705),1) | AI705: 2.9047213e+08 | AJ705: =IF(AI705=0,"",Q705/AI705) | AK705: =IF(AI705=0,"",R705/AI705) | AL705: =IF(AI705=0,"",S705/AI705) | AM705: =IF(AI705=0,"",Y705/AI705)
A706: all | B706: 2027 | C706: I_CVD_PRIMARY | E706: COST_PRIMARY_SCREEN_B | F706: CC_PRIMARY_SCREENING | G706: I_CVD_PRIMARY__C_SHARED | H706: shared-count-once | I706: all | J706: =IFERROR(INDEX('Cost_Components'!$K$2:$K$28,MATCH(E706,'Cost_Components'!$A$2:$A$28,0)),"") | K706: =IF(OR(L706="",Z706="",AA706="",AB706=""),"",IF(B706<AA706,L706,IF(B706>AB706,Z706,L706+(Z706-L706)*MIN(MAX((B706-AA706+1)/MAX(AB706-AA706+1,1),0),1)))) | L706: =IFERROR(INDEX('Cost_Components'!$S$2:$S$28,MATCH(E706,'Cost_Components'!$A$2:$A$28,0)),"") | M706: =IFERROR(INDEX('Cost_Components'!$L$2:$L$28,MATCH(E706,'Cost_Components'!$A$2:$A$28,0)),"") | N706: =IFERROR(INDEX('Cost_Components'!$P$2:$P$28,MATCH(E706,'Cost_Components'!$A$2:$A$28,0)),"") | O706: =AF706*J706 | P706: =AG706*J706 | Q706: =P706*L706*M706*N706 | R706: =O706*K706*M706*N706 | S706: =R706-Q706 | T706: =IFERROR(INDEX('Cost_Components'!$R$2:$R$28,MATCH(E706,'Cost_Components'!$A$2:$A$28,0)),"") | U706: =IFERROR(INDEX('Cost_Components'!$Q$2:$Q$28,MATCH(E706,'Cost_Components'!$A$2:$A$28,0)),"") | V706: =1/(1+'Calculation_Assumptions'!$B$5)^(B706-'Calculation_Assumptions'!$B$2) | W706: =Q706*V706 | X706: =R706*V706 | Y706: =S706*V706 | Z706: =IFERROR(INDEX('Cost_Components'!$T$2:$T$28,MATCH(E706,'Cost_Components'!$A$2:$A$28,0)),"") | AA706: =IFERROR(INDEX('Cost_Components'!$U$2:$U$28,MATCH(E706,'Cost_Components'!$A$2:$A$28,0)),"") | AB706: =IFERROR(INDEX('Cost_Components'!$V$2:$V$28,MATCH(E706,'Cost_Components'!$A$2:$A$28,0)),"") | AC706: =IFERROR(INDEX('Cost_Components'!$M$2:$M$28,MATCH(E706,'Cost_Components'!$A$2:$A$28,0)),"") | AD706: =IFERROR(INDEX('Cost_Components'!$N$2:$N$28,MATCH(E706,'Cost_Components'!$A$2:$A$28,0)),"") | AE706: =IFERROR(INDEX('Cost_Components'!$O$2:$O$28,MATCH(E706,'Cost_Components'!$A$2:$A$28,0)),"") | AF706: 1.5994685e+08 | AG706: 1.5995711e+08 | AH706: =IF(H706="shared-count-once",COUNTIFS($A$2:$A$1405,A706,$B$2:$B$1405,B706,$E$2:$E$1405,E706),1) | AI706: 2.9250508e+08 | AJ706: =IF(AI706=0,"",Q706/AI706) | AK706: =IF(AI706=0,"",R706/AI706) | AL706: =IF(AI706=0,"",S706/AI706) | AM706: =IF(AI706=0,"",Y706/AI706)
A707: all | B707: 2028 | C707: I_CVD_PRIMARY | E707: COST_PRIMARY_SCREEN_B | F707: CC_PRIMARY_SCREENING | G707: I_CVD_PRIMARY__C_SHARED | H707: shared-count-once | I707: all | J707: =IFERROR(INDEX('Cost_Components'!$K$2:$K$28,MATCH(E707,'Cost_Components'!$A$2:$A$28,0)),"") | K707: =IF(OR(L707="",Z707="",AA707="",AB707=""),"",IF(B707<AA707,L707,IF(B707>AB707,Z707,L707+(Z707-L707)*MIN(MAX((B707-AA707+1)/MAX(AB707-AA707+1,1),0),1)))) | L707: =IFERROR(INDEX('Cost_Components'!$S$2:$S$28,MATCH(E707,'Cost_Components'!$A$2:$A$28,0)),"") | M707: =IFERROR(INDEX('Cost_Components'!$L$2:$L$28,MATCH(E707,'Cost_Components'!$A$2:$A$28,0)),"") | N707: =IFERROR(INDEX('Cost_Components'!$P$2:$P$28,MATCH(E707,'Cost_Components'!$A$2:$A$28,0)),"") | O707: =AF707*J707 | P707: =AG707*J707 | Q707: =P707*L707*M707*N707 | R707: =O707*K707*M707*N707 | S707: =R707-Q707 | T707: =IFERROR(INDEX('Cost_Components'!$R$2:$R$28,MATCH(E707,'Cost_Components'!$A$2:$A$28,0)),"") | U707: =IFERROR(INDEX('Cost_Components'!$Q$2:$Q$28,MATCH(E707,'Cost_Components'!$A$2:$A$28,0)),"") | V707: =1/(1+'Calculation_Assumptions'!$B$5)^(B707-'Calculation_Assumptions'!$B$2) | W707: =Q707*V707 | X707: =R707*V707 | Y707: =S707*V707 | Z707: =IFERROR(INDEX('Cost_Components'!$T$2:$T$28,MATCH(E707,'Cost_Components'!$A$2:$A$28,0)),"") | AA707: =IFERROR(INDEX('Cost_Components'!$U$2:$U$28,MATCH(E707,'Cost_Components'!$A$2:$A$28,0)),"") | AB707: =IFERROR(INDEX('Cost_Components'!$V$2:$V$28,MATCH(E707,'Cost_Components'!$A$2:$A$28,0)),"") | AC707: =IFERROR(INDEX('Cost_Components'!$M$2:$M$28,MATCH(E707,'Cost_Components'!$A$2:$A$28,0)),"") | AD707: =IFERROR(INDEX('Cost_Components'!$N$2:$N$28,MATCH(E707,'Cost_Components'!$A$2:$A$28,0)),"") | AE707: =IFERROR(INDEX('Cost_Components'!$O$2:$O$28,MATCH(E707,'Cost_Components'!$A$2:$A$28,0)),"") | AF707: 1.620559e+08 | AG707: 1.6220434e+08 | AH707: =IF(H707="shared-count-once",COUNTIFS($A$2:$A$1405,A707,$B$2:$B$1405,B707,$E$2:$E$1405,E707),1) | AI707: 2.9448471e+08 | AJ707: =IF(AI707=0,"",Q707/AI707) | AK707: =IF(AI707=0,"",R707/AI707) | AL707: =IF(AI707=0,"",S707/AI707) | AM707: =IF(AI707=0,"",Y707/AI707)
A708: all | B708: 2029 | C708: I_CVD_PRIMARY | E708: COST_PRIMARY_SCREEN_B | F708: CC_PRIMARY_SCREENING | G708: I_CVD_PRIMARY__C_SHARED | H708: shared-count-once | I708: all | J708: =IFERROR(INDEX('Cost_Components'!$K$2:$K$28,MATCH(E708,'Cost_Components'!$A$2:$A$28,0)),"") | K708: =IF(OR(L708="",Z708="",AA708="",AB708=""),"",IF(B708<AA708,L708,IF(B708>AB708,Z708,L708+(Z708-L708)*MIN(MAX((B708-AA708+1)/MAX(AB708-AA708+1,1),0),1)))) | L708: =IFERROR(INDEX('Cost_Components'!$S$2:$S$28,MATCH(E708,'Cost_Components'!$A$2:$A$28,0)),"") | M708: =IFERROR(INDEX('Cost_Components'!$L$2:$L$28,MATCH(E708,'Cost_Components'!$A$2:$A$28,0)),"") | N708: =IFERROR(INDEX('Cost_Components'!$P$2:$P$28,MATCH(E708,'Cost_Components'!$A$2:$A$28,0)),"") | O708: =AF708*J708 | P708: =AG708*J708 | Q708: =P708*L708*M708*N708 | R708: =O708*K708*M708*N708 | S708: =R708-Q708 | T708: =IFERROR(INDEX('Cost_Components'!$R$2:$R$28,MATCH(E708,'Cost_Components'!$A$2:$A$28,0)),"") | U708: =IFERROR(INDEX('Cost_Components'!$Q$2:$Q$28,MATCH(E708,'Cost_Components'!$A$2:$A$28,0)),"") | V708: =1/(1+'Calculation_Assumptions'!$B$5)^(B708-'Calculation_Assumptions'!$B$2) | W708: =Q708*V708 | X708: =R708*V708 | Y708: =S708*V708 | Z708: =IFERROR(INDEX('Cost_Components'!$T$2:$T$28,MATCH(E708,'Cost_Components'!$A$2:$A$28,0)),"") | AA708: =IFERROR(INDEX('Cost_Components'!$U$2:$U$28,MATCH(E708,'Cost_Components'!$A$2:$A$28,0)),"") | AB708: =IFERROR(INDEX('Cost_Components'!$V$2:$V$28,MATCH(E708,'Cost_Components'!$A$2:$A$28,0)),"") | AC708: =IFERROR(INDEX('Cost_Components'!$M$2:$M$28,MATCH(E708,'Cost_Components'!$A$2:$A$28,0)),"") | AD708: =IFERROR(INDEX('Cost_Components'!$N$2:$N$28,MATCH(E708,'Cost_Components'!$A$2:$A$28,0)),"") | AE708: =IFERROR(INDEX('Cost_Components'!$O$2:$O$28,MATCH(E708,'Cost_Components'!$A$2:$A$28,0)),"") | AF708: 1.6423139e+08 | AG708: 1.6435451e+08 | AH708: =IF(H708="shared-count-once",COUNTIFS($A$2:$A$1405,A708,$B$2:$B$1405,B708,$E$2:$E$1405,E708),1) | AI708: 2.9641403e+08 | AJ708: =IF(AI708=0,"",Q708/AI708) | AK708: =IF(AI708=0,"",R708/AI708) | AL708: =IF(AI708=0,"",S708/AI708) | AM708: =IF(AI708=0,"",Y708/AI708)
A709: all | B709: 2030 | C709: I_CVD_PRIMARY | E709: COST_PRIMARY_SCREEN_B | F709: CC_PRIMARY_SCREENING | G709: I_CVD_PRIMARY__C_SHARED | H709: shared-count-once | I709: all | J709: =IFERROR(INDEX('Cost_Components'!$K$2:$K$28,MATCH(E709,'Cost_Components'!$A$2:$A$28,0)),"") | K709: =IF(OR(L709="",Z709="",AA709="",AB709=""),"",IF(B709<AA709,L709,IF(B709>AB709,Z709,L709+(Z709-L709)*MIN(MAX((B709-AA709+1)/MAX(AB709-AA709+1,1),0),1)))) | L709: =IFERROR(INDEX('Cost_Components'!$S$2:$S$28,MATCH(E709,'Cost_Components'!$A$2:$A$28,0)),"") | M709: =IFERROR(INDEX('Cost_Components'!$L$2:$L$28,MATCH(E709,'Cost_Components'!$A$2:$A$28,0)),"") | N709: =IFERROR(INDEX('Cost_Components'!$P$2:$P$28,MATCH(E709,'Cost_Components'!$A$2:$A$28,0)),"") | O709: =AF709*J709 | P709: =AG709*J709 | Q709: =P709*L709*M709*N709 | R709: =O709*K709*M709*N709 | S709: =R709-Q709 | T709: =IFERROR(INDEX('Cost_Components'!$R$2:$R$28,MATCH(E709,'Cost_Components'!$A$2:$A$28,0)),"") | U709: =IFERROR(INDEX('Cost_Components'!$Q$2:$Q$28,MATCH(E709,'Cost_Components'!$A$2:$A$28,0)),"") | V709: =1/(1+'Calculation_Assumptions'!$B$5)^(B709-'Calculation_Assumptions'!$B$2) | W709: =Q709*V709 | X709: =R709*V709 | Y709: =S709*V709 | Z709: =IFERROR(INDEX('Cost_Components'!$T$2:$T$28,MATCH(E709,'Cost_Components'!$A$2:$A$28,0)),"") | AA709: =IFERROR(INDEX('Cost_Components'!$U$2:$U$28,MATCH(E709,'Cost_Components'!$A$2:$A$28,0)),"") | AB709: =IFERROR(INDEX('Cost_Components'!$V$2:$V$28,MATCH(E709,'Cost_Components'!$A$2:$A$28,0)),"") | AC709: =IFERROR(INDEX('Cost_Components'!$M$2:$M$28,MATCH(E709,'Cost_Components'!$A$2:$A$28,0)),"") | AD709: =IFERROR(INDEX('Cost_Components'!$N$2:$N$28,MATCH(E709,'Cost_Components'!$A$2:$A$28,0)),"") | AE709: =IFERROR(INDEX('Cost_Components'!$O$2:$O$28,MATCH(E709,'Cost_Components'!$A$2:$A$28,0)),"") | AF709: 1.6636149e+08 | AG709: 1.6641555e+08 | AH709: =IF(H709="shared-count-once",COUNTIFS($A$2:$A$1405,A709,$B$2:$B$1405,B709,$E$2:$E$1405,E709),1) | AI709: 2.982894e+08 | AJ709: =IF(AI709=0,"",Q709/AI709) | AK709: =IF(AI709=0,"",R709/AI709) | AL709: =IF(AI709=0,"",S709/AI709) | AM709: =IF(AI709=0,"",Y709/AI709)
A710: all | B710: 2031 | C710: I_CVD_PRIMARY | E710: COST_PRIMARY_SCREEN_B | F710: CC_PRIMARY_SCREENING | G710: I_CVD_PRIMARY__C_SHARED | H710: shared-count-once | I710: all | J710: =IFERROR(INDEX('Cost_Components'!$K$2:$K$28,MATCH(E710,'Cost_Components'!$A$2:$A$28,0)),"") | K710: =IF(OR(L710="",Z710="",AA710="",AB710=""),"",IF(B710<AA710,L710,IF(B710>AB710,Z710,L710+(Z710-L710)*MIN(MAX((B710-AA710+1)/MAX(AB710-AA710+1,1),0),1)))) | L710: =IFERROR(INDEX('Cost_Components'!$S$2:$S$28,MATCH(E710,'Cost_Components'!$A$2:$A$28,0)),"") | M710: =IFERROR(INDEX('Cost_Components'!$L$2:$L$28,MATCH(E710,'Cost_Components'!$A$2:$A$28,0)),"") | N710: =IFERROR(INDEX('Cost_Components'!$P$2:$P$28,MATCH(E710,'Cost_Components'!$A$2:$A$28,0)),"") | O710: =AF710*J710 | P710: =AG710*J710 | Q710: =P710*L710*M710*N710 | R710: =O710*K710*M710*N710 | S710: =R710-Q710 | T710: =IFERROR(INDEX('Cost_Components'!$R$2:$R$28,MATCH(E710,'Cost_Components'!$A$2:$A$28,0)),"") | U710: =IFERROR(INDEX('Cost_Components'!$Q$2:$Q$28,MATCH(E710,'Cost_Components'!$A$2:$A$28,0)),"") | V710: =1/(1+'Calculation_Assumptions'!$B$5)^(B710-'Calculation_Assumptions'!$B$2) | W710: =Q710*V710 | X710: =R710*V710 | Y710: =S710*V710 | Z710: =IFERROR(INDEX('Cost_Components'!$T$2:$T$28,MATCH(E710,'Cost_Components'!$A$2:$A$28,0)),"") | AA710: =IFERROR(INDEX('Cost_Components'!$U$2:$U$28,MATCH(E710,'Cost_Components'!$A$2:$A$28,0)),"") | AB710: =IFERROR(INDEX('Cost_Components'!$V$2:$V$28,MATCH(E710,'Cost_Components'!$A$2:$A$28,0)),"") | AC710: =IFERROR(INDEX('Cost_Components'!$M$2:$M$28,MATCH(E710,'Cost_Components'!$A$2:$A$28,0)),"") | AD710: =IFERROR(INDEX('Cost_Components'!$N$2:$N$28,MATCH(E710,'Cost_Components'!$A$2:$A$28,0)),"") | AE710: =IFERROR(INDEX('Cost_Components'!$O$2:$O$28,MATCH(E710,'Cost_Components'!$A$2:$A$28,0)),"") | AF710: 1.6846393e+08 | AG710: 1.6846129e+08 | AH710: =IF(H710="shared-count-once",COUNTIFS($A$2:$A$1405,A710,$B$2:$B$1405,B710,$E$2:$E$1405,E710),1) | AI710: 3.0011964e+08 | AJ710: =IF(AI710=0,"",Q710/AI710) | AK710: =IF(AI710=0,"",R710/AI710) | AL710: =IF(AI710=0,"",S710/AI710) | AM710: =IF(AI710=0,"",Y710/AI710)
A711: all | B711: 2032 | C711: I_CVD_PRIMARY | E711: COST_PRIMARY_SCREEN_B | F711: CC_PRIMARY_SCREENING | G711: I_CVD_PRIMARY__C_SHARED | H711: shared-count-once | I711: all | J711: =IFERROR(INDEX('Cost_Components'!$K$2:$K$28,MATCH(E711,'Cost_Components'!$A$2:$A$28,0)),"") | K711: =IF(OR(L711="",Z711="",AA711="",AB711=""),"",IF(B711<AA711,L711,IF(B711>AB711,Z711,L711+(Z711-L711)*MIN(MAX((B711-AA711+1)/MAX(AB711-AA711+1,1),0),1)))) | L711: =IFERROR(INDEX('Cost_Components'!$S$2:$S$28,MATCH(E711,'Cost_Components'!$A$2:$A$28,0)),"") | M711: =IFERROR(INDEX('Cost_Components'!$L$2:$L$28,MATCH(E711,'Cost_Components'!$A$2:$A$28,0)),"") | N711: =IFERROR(INDEX('Cost_Components'!$P$2:$P$28,MATCH(E711,'Cost_Components'!$A$2:$A$28,0)),"") | O711: =AF711*J711 | P711: =AG711*J711 | Q711: =P711*L711*M711*N711 | R711: =O711*K711*M711*N711 | S711: =R711-Q711 | T711: =IFERROR(INDEX('Cost_Components'!$R$2:$R$28,MATCH(E711,'Cost_Components'!$A$2:$A$28,0)),"") | U711: =IFERROR(INDEX('Cost_Components'!$Q$2:$Q$28,MATCH(E711,'Cost_Components'!$A$2:$A$28,0)),"") | V711: =1/(1+'Calculation_Assumptions'!$B$5)^(B711-'Calculation_Assumptions'!$B$2) | W711: =Q711*V711 | X711: =R711*V711 | Y711: =S711*V711 | Z711: =IFERROR(INDEX('Cost_Components'!$T$2:$T$28,MATCH(E711,'Cost_Components'!$A$2:$A$28,0)),"") | AA711: =IFERROR(INDEX('Cost_Components'!$U$2:$U$28,MATCH(E711,'Cost_Components'!$A$2:$A$28,0)),"") | AB711: =IFERROR(INDEX('Cost_Components'!$V$2:$V$28,MATCH(E711,'Cost_Components'!$A$2:$A$28,0)),"") | AC711: =IFERROR(INDEX('Cost_Components'!$M$2:$M$28,MATCH(E711,'Cost_Components'!$A$2:$A$28,0)),"") | AD711: =IFERROR(INDEX('Cost_Components'!$N$2:$N$28,MATCH(E711,'Cost_Components'!$A$2:$A$28,0)),"") | AE711: =IFERROR(INDEX('Cost_Components'!$O$2:$O$28,MATCH(E711,'Cost_Components'!$A$2:$A$28,0)),"") | AF711: 1.7054162e+08 | AG711: 1.7047662e+08 | AH711: =IF(H711="shared-count-once",COUNTIFS($A$2:$A$1405,A711,$B$2:$B$1405,B711,$E$2:$E$1405,E711),1) | AI711: 3.0190463e+08 | AJ711: =IF(AI711=0,"",Q711/AI711) | AK711: =IF(AI711=0,"",R711/AI711) | AL711: =IF(AI711=0,"",S711/AI711) | AM711: =IF(AI711=0,"",Y711/AI711)
A712: all | B712: 2033 | C712: I_CVD_PRIMARY | E712: COST_PRIMARY_SCREEN_B | F712: CC_PRIMARY_SCREENING | G712: I_CVD_PRIMARY__C_SHARED | H712: shared-count-once | I712: all | J712: =IFERROR(INDEX('Cost_Components'!$K$2:$K$28,MATCH(E712,'Cost_Components'!$A$2:$A$28,0)),"") | K712: =IF(OR(L712="",Z712="",AA712="",AB712=""),"",IF(B712<AA712,L712,IF(B712>AB712,Z712,L712+(Z712-L712)*MIN(MAX((B712-AA712+1)/MAX(AB712-AA712+1,1),0),1)))) | L712: =IFERROR(INDEX('Cost_Components'!$S$2:$S$28,MATCH(E712,'Cost_Components'!$A$2:$A$28,0)),"") | M712: =IFERROR(INDEX('Cost_Components'!$L$2:$L$28,MATCH(E712,'Cost_Components'!$A$2:$A$28,0)),"") | N712: =IFERROR(INDEX('Cost_Components'!$P$2:$P$28,MATCH(E712,'Cost_Components'!$A$2:$A$28,0)),"") | O712: =AF712*J712 | P712: =AG712*J712 | Q712: =P712*L712*M712*N712 | R712: =O712*K712*M712*N712 | S712: =R712-Q712 | T712: =IFERROR(INDEX('Cost_Components'!$R$2:$R$28,MATCH(E712,'Cost_Components'!$A$2:$A$28,0)),"") | U712: =IFERROR(INDEX('Cost_Components'!$Q$2:$Q$28,MATCH(E712,'Cost_Components'!$A$2:$A$28,0)),"") | V712: =1/(1+'Calculation_Assumptions'!$B$5)^(B712-'Calculation_Assumptions'!$B$2) | W712: =Q712*V712 | X712: =R712*V712 | Y712: =S712*V712 | Z712: =IFERROR(INDEX('Cost_Components'!$T$2:$T$28,MATCH(E712,'Cost_Components'!$A$2:$A$28,0)),"") | AA712: =IFERROR(INDEX('Cost_Components'!$U$2:$U$28,MATCH(E712,'Cost_Components'!$A$2:$A$28,0)),"") | AB712: =IFERROR(INDEX('Cost_Components'!$V$2:$V$28,MATCH(E712,'Cost_Components'!$A$2:$A$28,0)),"") | AC712: =IFERROR(INDEX('Cost_Components'!$M$2:$M$28,MATCH(E712,'Cost_Components'!$A$2:$A$28,0)),"") | AD712: =IFERROR(INDEX('Cost_Components'!$N$2:$N$28,MATCH(E712,'Cost_Components'!$A$2:$A$28,0)),"") | AE712: =IFERROR(INDEX('Cost_Components'!$O$2:$O$28,MATCH(E712,'Cost_Components'!$A$2:$A$28,0)),"") | AF712: 1.7259469e+08 | AG712: 1.7246151e+08 | AH712: =IF(H712="shared-count-once",COUNTIFS($A$2:$A$1405,A712,$B$2:$B$1405,B712,$E$2:$E$1405,E712),1) | AI712: 3.0364428e+08 | AJ712: =IF(AI712=0,"",Q712/AI712) | AK712: =IF(AI712=0,"",R712/AI712) | AL712: =IF(AI712=0,"",S712/AI712) | AM712: =IF(AI712=0,"",Y712/AI712)
A713: all | B713: 2034 | C713: I_CVD_PRIMARY | E713: COST_PRIMARY_SCREEN_B | F713: CC_PRIMARY_SCREENING | G713: I_CVD_PRIMARY__C_SHARED | H713: shared-count-once | I713: all | J713: =IFERROR(INDEX('Cost_Components'!$K$2:$K$28,MATCH(E713,'Cost_Components'!$A$2:$A$28,0)),"") | K713: =IF(OR(L713="",Z713="",AA713="",AB713=""),"",IF(B713<AA713,L713,IF(B713>AB713,Z713,L713+(Z713-L713)*MIN(MAX((B713-AA713+1)/MAX(AB713-AA713+1,1),0),1)))) | L713: =IFERROR(INDEX('Cost_Components'!$S$2:$S$28,MATCH(E713,'Cost_Components'!$A$2:$A$28,0)),"") | M713: =IFERROR(INDEX('Cost_Components'!$L$2:$L$28,MATCH(E713,'Cost_Components'!$A$2:$A$28,0)),"") | N713: =IFERROR(INDEX('Cost_Components'!$P$2:$P$28,MATCH(E713,'Cost_Components'!$A$2:$A$28,0)),"") | O713: =AF713*J713 | P713: =AG713*J713 | Q713: =P713*L713*M713*N713 | R713: =O713*K713*M713*N713 | S713: =R713-Q713 | T713: =IFERROR(INDEX('Cost_Components'!$R$2:$R$28,MATCH(E713,'Cost_Components'!$A$2:$A$28,0)),"") | U713: =IFERROR(INDEX('Cost_Components'!$Q$2:$Q$28,MATCH(E713,'Cost_Components'!$A$2:$A$28,0)),"") | V713: =1/(1+'Calculation_Assumptions'!$B$5)^(B713-'Calculation_Assumptions'!$B$2) | W713: =Q713*V713 | X713: =R713*V713 | Y713: =S713*V713 | Z713: =IFERROR(INDEX('Cost_Components'!$T$2:$T$28,MATCH(E713,'Cost_Components'!$A$2:$A$28,0)),"") | AA713: =IFERROR(INDEX('Cost_Components'!$U$2:$U$28,MATCH(E713,'Cost_Components'!$A$2:$A$28,0)),"") | AB713: =IFERROR(INDEX('Cost_Components'!$V$2:$V$28,MATCH(E713,'Cost_Components'!$A$2:$A$28,0)),"") | AC713: =IFERROR(INDEX('Cost_Components'!$M$2:$M$28,MATCH(E713,'Cost_Components'!$A$2:$A$28,0)),"") | AD713: =IFERROR(INDEX('Cost_Components'!$N$2:$N$28,MATCH(E713,'Cost_Components'!$A$2:$A$28,0)),"") | AE713: =IFERROR(INDEX('Cost_Components'!$O$2:$O$28,MATCH(E713,'Cost_Components'!$A$2:$A$28,0)),"") | AF713: 1.7466878e+08 | AG713: 1.7446169e+08 | AH713: =IF(H713="shared-count-once",COUNTIFS($A$2:$A$1405,A713,$B$2:$B$1405,B713,$E$2:$E$1405,E713),1) | AI713: 3.0533254e+08 | AJ713: =IF(AI713=0,"",Q713/AI713) | AK713: =IF(AI713=0,"",R713/AI713) | AL713: =IF(AI713=0,"",S713/AI713) | AM713: =IF(AI713=0,"",Y713/AI713)
A714: all | B714: 2035 | C714: I_CVD_PRIMARY | E714: COST_PRIMARY_SCREEN_B | F714: CC_PRIMARY_SCREENING | G714: I_CVD_PRIMARY__C_SHARED | H714: shared-count-once | I714: all | J714: =IFERROR(INDEX('Cost_Components'!$K$2:$K$28,MATCH(E714,'Cost_Components'!$A$2:$A$28,0)),"") | K714: =IF(OR(L714="",Z714="",AA714="",AB714=""),"",IF(B714<AA714,L714,IF(B714>AB714,Z714,L714+(Z714-L714)*MIN(MAX((B714-AA714+1)/MAX(AB714-AA714+1,1),0),1)))) | L714: =IFERROR(INDEX('Cost_Components'!$S$2:$S$28,MATCH(E714,'Cost_Components'!$A$2:$A$28,0)),"") | M714: =IFERROR(INDEX('Cost_Components'!$L$2:$L$28,MATCH(E714,'Cost_Components'!$A$2:$A$28,0)),"") | N714: =IFERROR(INDEX('Cost_Components'!$P$2:$P$28,MATCH(E714,'Cost_Components'!$A$2:$A$28,0)),"") | O714: =AF714*J714 | P714: =AG714*J714 | Q714: =P714*L714*M714*N714 | R714: =O714*K714*M714*N714 | S714: =R714-Q714 | T714: =IFERROR(INDEX('Cost_Components'!$R$2:$R$28,MATCH(E714,'Cost_Components'!$A$2:$A$28,0)),"") | U714: =IFERROR(INDEX('Cost_Components'!$Q$2:$Q$28,MATCH(E714,'Cost_Components'!$A$2:$A$28,0)),"") | V714: =1/(1+'Calculation_Assumptions'!$B$5)^(B714-'Calculation_Assumptions'!$B$2) | W714: =Q714*V714 | X714: =R714*V714 | Y714: =S714*V714 | Z714: =IFERROR(INDEX('Cost_Components'!$T$2:$T$28,MATCH(E714,'Cost_Components'!$A$2:$A$28,0)),"") | AA714: =IFERROR(INDEX('Cost_Components'!$U$2:$U$28,MATCH(E714,'Cost_Components'!$A$2:$A$28,0)),"") | AB714: =IFERROR(INDEX('Cost_Components'!$V$2:$V$28,MATCH(E714,'Cost_Components'!$A$2:$A$28,0)),"") | AC714: =IFERROR(INDEX('Cost_Components'!$M$2:$M$28,MATCH(E714,'Cost_Components'!$A$2:$A$28,0)),"") | AD714: =IFERROR(INDEX('Cost_Components'!$N$2:$N$28,MATCH(E714,'Cost_Components'!$A$2:$A$28,0)),"") | AE714: =IFERROR(INDEX('Cost_Components'!$O$2:$O$28,MATCH(E714,'Cost_Components'!$A$2:$A$28,0)),"") | AF714: 1.7682658e+08 | AG714: 1.7653877e+08 | AH714: =IF(H714="shared-count-once",COUNTIFS($A$2:$A$1405,A714,$B$2:$B$1405,B714,$E$2:$E$1405,E714),1) | AI714: 3.0696465e+08 | AJ714: =IF(AI714=0,"",Q714/AI714) | AK714: =IF(AI714=0,"",R714/AI714) | AL714: =IF(AI714=0,"",S714/AI714) | AM714: =IF(AI714=0,"",Y714/AI714)
A715: all | B715: 2036 | C715: I_CVD_PRIMARY | E715: COST_PRIMARY_SCREEN_B | F715: CC_PRIMARY_SCREENING | G715: I_CVD_PRIMARY__C_SHARED | H715: shared-count-once | I715: all | J715: =IFERROR(INDEX('Cost_Components'!$K$2:$K$28,MATCH(E715,'Cost_Components'!$A$2:$A$28,0)),"") | K715: =IF(OR(L715="",Z715="",AA715="",AB715=""),"",IF(B715<AA715,L715,IF(B715>AB715,Z715,L715+(Z715-L715)*MIN(MAX((B715-AA715+1)/MAX(AB715-AA715+1,1),0),1)))) | L715: =IFERROR(INDEX('Cost_Components'!$S$2:$S$28,MATCH(E715,'Cost_Components'!$A$2:$A$28,0)),"") | M715: =IFERROR(INDEX('Cost_Components'!$L$2:$L$28,MATCH(E715,'Cost_Components'!$A$2:$A$28,0)),"") | N715: =IFERROR(INDEX('Cost_Components'!$P$2:$P$28,MATCH(E715,'Cost_Components'!$A$2:$A$28,0)),"") | O715: =AF715*J715 | P715: =AG715*J715 | Q715: =P715*L715*M715*N715 | R715: =O715*K715*M715*N715 | S715: =R715-Q715 | T715: =IFERROR(INDEX('Cost_Components'!$R$2:$R$28,MATCH(E715,'Cost_Components'!$A$2:$A$28,0)),"") | U715: =IFERROR(INDEX('Cost_Components'!$Q$2:$Q$28,MATCH(E715,'Cost_Components'!$A$2:$A$28,0)),"") | V715: =1/(1+'Calculation_Assumptions'!$B$5)^(B715-'Calculation_Assumptions'!$B$2) | W715: =Q715*V715 | X715: =R715*V715 | Y715: =S715*V715 | Z715: =IFERROR(INDEX('Cost_Components'!$T$2:$T$28,MATCH(E715,'Cost_Components'!$A$2:$A$28,0)),"") | AA715: =IFERROR(INDEX('Cost_Components'!$U$2:$U$28,MATCH(E715,'Cost_Components'!$A$2:$A$28,0)),"") | AB715: =IFERROR(INDEX('Cost_Components'!$V$2:$V$28,MATCH(E715,'Cost_Components'!$A$2:$A$28,0)),"") | AC715: =IFERROR(INDEX('Cost_Components'!$M$2:$M$28,MATCH(E715,'Cost_Components'!$A$2:$A$28,0)),"") | AD715: =IFERROR(INDEX('Cost_Components'!$N$2:$N$28,MATCH(E715,'Cost_Components'!$A$2:$A$28,0)),"") | AE715: =IFERROR(INDEX('Cost_Components'!$O$2:$O$28,MATCH(E715,'Cost_Components'!$A$2:$A$28,0)),"") | AF715: 1.7899863e+08 | AG715: 1.7862366e+08 | AH715: =IF(H715="shared-count-once",COUNTIFS($A$2:$A$1405,A715,$B$2:$B$1405,B715,$E$2:$E$1405,E715),1) | AI715: 3.0854277e+08 | AJ715: =IF(AI715=0,"",Q715/AI715) | AK715: =IF(AI715=0,"",R715/AI715) | AL715: =IF(AI715=0,"",S715/AI715) | AM715: =IF(AI715=0,"",Y715/AI715)
... A755: all | B755: 2050 | C755: I_CVD_PRIMARY | E755: COST_PRIMARY_TX_B | F755: CC_PRIMARY_HTN_STATIN | G755: I_CVD_PRIMARY__C_SHARED | H755: shared-count-once | I755: all | J755: =IFERROR(INDEX('Cost_Components'!$K$2:$K$28,MATCH(E755,'Cost_Components'!$A$2:$A$28,0)),"") | K755: =IF(OR(L755="",Z755="",AA755="",AB755=""),"",IF(B755<AA755,L755,IF(B755>AB755,Z755,L755+(Z755-L755)*MIN(MAX((B755-AA755+1)/MAX(AB755-AA755+1,1),0),1)))) | L755: =IFERROR(INDEX('Cost_Components'!$S$2:$S$28,MATCH(E755,'Cost_Components'!$A$2:$A$28,0)),"") | M755: =IFERROR(INDEX('Cost_Components'!$L$2:$L$28,MATCH(E755,'Cost_Components'!$A$2:$A$28,0)),"") | N755: =IFERROR(INDEX('Cost_Components'!$P$2:$P$28,MATCH(E755,'Cost_Components'!$A$2:$A$28,0)),"") | O755: =AF755*J755 | P755: =AG755*J755 | Q755: =P755*L755*M755*N755 | R755: =O755*K755*M755*N755 | S755: =R755-Q755 | T755: =IFERROR(INDEX('Cost_Components'!$R$2:$R$28,MATCH(E755,'Cost_Components'!$A$2:$A$28,0)),"") | U755: =IFERROR(INDEX('Cost_Components'!$Q$2:$Q$28,MATCH(E755,'Cost_Components'!$A$2:$A$28,0)),"") | V755: =1/(1+'Calculation_Assumptions'!$B$5)^(B755-'Calculation_Assumptions'!$B$2) | W755: =Q755*V755 | X755: =R755*V755 | Y755: =S755*V755 | Z755: =IFERROR(INDEX('Cost_Components'!$T$2:$T$28,MATCH(E755,'Cost_Components'!$A$2:$A$28,0)),"") | AA755: =IFERROR(INDEX('Cost_Components'!$U$2:$U$28,MATCH(E755,'Cost_Components'!$A$2:$A$28,0)),"") | AB755: =IFERROR(INDEX('Cost_Components'!$V$2:$V$28,MATCH(E755,'Cost_Components'!$A$2:$A$28,0)),"") | AC755: =IFERROR(INDEX('Cost_Components'!$M$2:$M$28,MATCH(E755,'Cost_Components'!$A$2:$A$28,0)),"") | AD755: =IFERROR(INDEX('Cost_Components'!$N$2:$N$28,MATCH(E755,'Cost_Components'!$A$2:$A$28,0)),"") | AE755: =IFERROR(INDEX('Cost_Components'!$O$2:$O$28,MATCH(E755,'Cost_Components'!$A$2:$A$28,0)),"") | AF755: 2.0483387e+08 | AG755: 2.024798e+08 | AH755: =IF(H755="shared-count-once",COUNTIFS($A$2:$A$1405,A755,$B$2:$B$1405,B755,$E$2:$E$1405,E755),1) | AI755: 3.2331204e+08 | AJ755: =IF(AI755=0,"",Q755/AI755) | AK755: =IF(AI755=0,"",R755/AI755) | AL755: =IF(AI755=0,"",S755/AI755) | AM755: =IF(AI755=0,"",Y755/AI755)
A756: all | B756: 2025 | C756: I_HF_ACUTE | D756: cmd | E756: COST_HF_ACUTE_C_CMP | F756: CC_HF_ACUTE_C_CMP | G756: I_HF_ACUTE__C_CMP | H756: cause-specific | I756: prevalence | J756: =IFERROR(INDEX('Cost_Components'!$K$2:$K$28,MATCH(E756,'Cost_Components'!$A$2:$A$28,0)),"") | K756: =IF(OR(L756="",Z756="",AA756="",AB756=""),"",IF(B756<AA756,L756,IF(B756>AB756,Z756,L756+(Z756-L756)*MIN(MAX((B756-AA756+1)/MAX(AB756-AA756+1,1),0),1)))) | L756: =IFERROR(INDEX('Cost_Components'!$S$2:$S$28,MATCH(E756,'Cost_Components'!$A$2:$A$28,0)),"") | M756: =IFERROR(INDEX('Cost_Components'!$L$2:$L$28,MATCH(E756,'Cost_Components'!$A$2:$A$28,0)),"") | N756: =IFERROR(INDEX('Cost_Components'!$P$2:$P$28,MATCH(E756,'Cost_Components'!$A$2:$A$28,0)),"") | O756: =AF756*J756 | P756: =AG756*J756 | Q756: =P756*L756*M756*N756 | R756: =O756*K756*M756*N756 | S756: =R756-Q756 | T756: =IFERROR(INDEX('Cost_Components'!$R$2:$R$28,MATCH(E756,'Cost_Components'!$A$2:$A$28,0)),"") | U756: =IFERROR(INDEX('Cost_Components'!$Q$2:$Q$28,MATCH(E756,'Cost_Components'!$A$2:$A$28,0)),"") | V756: =1/(1+'Calculation_Assumptions'!$B$5)^(B756-'Calculation_Assumptions'!$B$2) | W756: =Q756*V756 | X756: =R756*V756 | Y756: =S756*V756 | Z756: =IFERROR(INDEX('Cost_Components'!$T$2:$T$28,MATCH(E756,'Cost_Components'!$A$2:$A$28,0)),"") | AA756: =IFERROR(INDEX('Cost_Components'!$U$2:$U$28,MATCH(E756,'Cost_Components'!$A$2:$A$28,0)),"") | AB756: =IFERROR(INDEX('Cost_Components'!$V$2:$V$28,MATCH(E756,'Cost_Components'!$A$2:$A$28,0)),"") | AC756: =IFERROR(INDEX('Cost_Components'!$M$2:$M$28,MATCH(E756,'Cost_Components'!$A$2:$A$28,0)),"") | AD756: =IFERROR(INDEX('Cost_Components'!$N$2:$N$28,MATCH(E756,'Cost_Components'!$A$2:$A$28,0)),"") | AE756: =IFERROR(INDEX('Cost_Components'!$O$2:$O$28,MATCH(E756,'Cost_Components'!$A$2:$A$28,0)),"") | AF756: 49728.391 | AG756: 49646.074 | AH756: =IF(H756="shared-count-once",COUNTIFS($A$2:$A$1405,A756,$B$2:$B$1405,B756,$E$2:$E$1405,E756),1) | AI756: 2.8839191e+08 | AJ756: =IF(AI756=0,"",Q756/AI756) | AK756: =IF(AI756=0,"",R756/AI756) | AL756: =IF(AI756=0,"",S756/AI756) | AM756: =IF(AI756=0,"",Y756/AI756)
A757: all | B757: 2026 | C757: I_HF_ACUTE | D757: cmd | E757: COST_HF_ACUTE_C_CMP | F757: CC_HF_ACUTE_C_CMP | G757: I_HF_ACUTE__C_CMP | H757: cause-specific | I757: prevalence | J757: =IFERROR(INDEX('Cost_Components'!$K$2:$K$28,MATCH(E757,'Cost_Components'!$A$2:$A$28,0)),"") | K757: =IF(OR(L757="",Z757="",AA757="",AB757=""),"",IF(B757<AA757,L757,IF(B757>AB757,Z757,L757+(Z757-L757)*MIN(MAX((B757-AA757+1)/MAX(AB757-AA757+1,1),0),1)))) | L757: =IFERROR(INDEX('Cost_Components'!$S$2:$S$28,MATCH(E757,'Cost_Components'!$A$2:$A$28,0)),"") | M757: =IFERROR(INDEX('Cost_Components'!$L$2:$L$28,MATCH(E757,'Cost_Components'!$A$2:$A$28,0)),"") | N757: =IFERROR(INDEX('Cost_Components'!$P$2:$P$28,MATCH(E757,'Cost_Components'!$A$2:$A$28,0)),"") | O757: =AF757*J757 | P757: =AG757*J757 | Q757: =P757*L757*M757*N757 | R757: =O757*K757*M757*N757 | S757: =R757-Q757 | T757: =IFERROR(INDEX('Cost_Components'!$R$2:$R$28,MATCH(E757,'Cost_Components'!$A$2:$A$28,0)),"") | U757: =IFERROR(INDEX('Cost_Components'!$Q$2:$Q$28,MATCH(E757,'Cost_Components'!$A$2:$A$28,0)),"") | V757: =1/(1+'Calculation_Assumptions'!$B$5)^(B757-'Calculation_Assumptions'!$B$2) | W757: =Q757*V757 | X757: =R757*V757 | Y757: =S757*V757 | Z757: =IFERROR(INDEX('Cost_Components'!$T$2:$T$28,MATCH(E757,'Cost_Components'!$A$2:$A$28,0)),"") | AA757: =IFERROR(INDEX('Cost_Components'!$U$2:$U$28,MATCH(E757,'Cost_Components'!$A$2:$A$28,0)),"") | AB757: =IFERROR(INDEX('Cost_Components'!$V$2:$V$28,MATCH(E757,'Cost_Components'!$A$2:$A$28,0)),"") | AC757: =IFERROR(INDEX('Cost_Components'!$M$2:$M$28,MATCH(E757,'Cost_Components'!$A$2:$A$28,0)),"") | AD757: =IFERROR(INDEX('Cost_Components'!$N$2:$N$28,MATCH(E757,'Cost_Components'!$A$2:$A$28,0)),"") | AE757: =IFERROR(INDEX('Cost_Components'!$O$2:$O$28,MATCH(E757,'Cost_Components'!$A$2:$A$28,0)),"") | AF757: 50854.54 | AG757: 50623.241 | AH757: =IF(H757="shared-count-once",COUNTIFS($A$2:$A$1405,A757,$B$2:$B$1405,B757,$E$2:$E$1405,E757),1) | AI757: 2.9047213e+08 | AJ757: =IF(AI757=0,"",Q757/AI757) | AK757: =IF(AI757=0,"",R757/AI757) | AL757: =IF(AI757=0,"",S757/AI757) | AM757: =IF(AI757=0,"",Y757/AI757)
A758: all | B758: 2027 | C758: I_HF_ACUTE | D758: cmd | E758: COST_HF_ACUTE_C_CMP | F758: CC_HF_ACUTE_C_CMP | G758: I_HF_ACUTE__C_CMP | H758: cause-specific | I758: prevalence | J758: =IFERROR(INDEX('Cost_Components'!$K$2:$K$28,MATCH(E758,'Cost_Components'!$A$2:$A$28,0)),"") | K758: =IF(OR(L758="",Z758="",AA758="",AB758=""),"",IF(B758<AA758,L758,IF(B758>AB758,Z758,L758+(Z758-L758)*MIN(MAX((B758-AA758+1)/MAX(AB758-AA758+1,1),0),1)))) | L758: =IFERROR(INDEX('Cost_Components'!$S$2:$S$28,MATCH(E758,'Cost_Components'!$A$2:$A$28,0)),"") | M758: =IFERROR(INDEX('Cost_Components'!$L$2:$L$28,MATCH(E758,'Cost_Components'!$A$2:$A$28,0)),"") | N758: =IFERROR(INDEX('Cost_Components'!$P$2:$P$28,MATCH(E758,'Cost_Components'!$A$2:$A$28,0)),"") | O758: =AF758*J758 | P758: =AG758*J758 | Q758: =P758*L758*M758*N758 | R758: =O758*K758*M758*N758 | S758: =R758-Q758 | T758: =IFERROR(INDEX('Cost_Components'!$R$2:$R$28,MATCH(E758,'Cost_Components'!$A$2:$A$28,0)),"") | U758: =IFERROR(INDEX('Cost_Components'!$Q$2:$Q$28,MATCH(E758,'Cost_Components'!$A$2:$A$28,0)),"") | V758: =1/(1+'Calculation_Assumptions'!$B$5)^(B758-'Calculation_Assumptions'!$B$2) | W758: =Q758*V758 | X758: =R758*V758 | Y758: =S758*V758 | Z758: =IFERROR(INDEX('Cost_Components'!$T$2:$T$28,MATCH(E758,'Cost_Components'!$A$2:$A$28,0)),"") | AA758: =IFERROR(INDEX('Cost_Components'!$U$2:$U$28,MATCH(E758,'Cost_Components'!$A$2:$A$28,0)),"") | AB758: =IFERROR(INDEX('Cost_Components'!$V$2:$V$28,MATCH(E758,'Cost_Components'!$A$2:$A$28,0)),"") | AC758: =IFERROR(INDEX('Cost_Components'!$M$2:$M$28,MATCH(E758,'Cost_Components'!$A$2:$A$28,0)),"") | AD758: =IFERROR(INDEX('Cost_Components'!$N$2:$N$28,MATCH(E758,'Cost_Components'!$A$2:$A$28,0)),"") | AE758: =IFERROR(INDEX('Cost_Components'!$O$2:$O$28,MATCH(E758,'Cost_Components'!$A$2:$A$28,0)),"") | AF758: 52103.618 | AG758: 51666.345 | AH758: =IF(H758="shared-count-once",COUNTIFS($A$2:$A$1405,A758,$B$2:$B$1405,B758,$E$2:$E$1405,E758),1) | AI758: 2.9250508e+08 | AJ758: =IF(AI758=0,"",Q758/AI758) | AK758: =IF(AI758=0,"",R758/AI758) | AL758: =IF(AI758=0,"",S758/AI758) | AM758: =IF(AI758=0,"",Y758/AI758)
A759: all | B759: 2028 | C759: I_HF_ACUTE | D759: cmd | E759: COST_HF_ACUTE_C_CMP | F759: CC_HF_ACUTE_C_CMP | G759: I_HF_ACUTE__C_CMP | H759: cause-specific | I759: prevalence | J759: =IFERROR(INDEX('Cost_Components'!$K$2:$K$28,MATCH(E759,'Cost_Components'!$A$2:$A$28,0)),"") | K759: =IF(OR(L759="",Z759="",AA759="",AB759=""),"",IF(B759<AA759,L759,IF(B759>AB759,Z759,L759+(Z759-L759)*MIN(MAX((B759-AA759+1)/MAX(AB759-AA759+1,1),0),1)))) | L759: =IFERROR(INDEX('Cost_Components'!$S$2:$S$28,MATCH(E759,'Cost_Components'!$A$2:$A$28,0)),"") | M759: =IFERROR(INDEX('Cost_Components'!$L$2:$L$28,MATCH(E759,'Cost_Components'!$A$2:$A$28,0)),"") | N759: =IFERROR(INDEX('Cost_Components'!$P$2:$P$28,MATCH(E759,'Cost_Components'!$A$2:$A$28,0)),"") | O759: =AF759*J759 | P759: =AG759*J759 | Q759: =P759*L759*M759*N759 | R759: =O759*K759*M759*N759 | S759: =R759-Q759 | T759: =IFERROR(INDEX('Cost_Components'!$R$2:$R$28,MATCH(E759,'Cost_Components'!$A$2:$A$28,0)),"") | U759: =IFERROR(INDEX('Cost_Components'!$Q$2:$Q$28,MATCH(E759,'Cost_Components'!$A$2:$A$28,0)),"") | V759: =1/(1+'Calculation_Assumptions'!$B$5)^(B759-'Calculation_Assumptions'!$B$2) | W759: =Q759*V759 | X759: =R759*V759 | Y759: =S759*V759 | Z759: =IFERROR(INDEX('Cost_Components'!$T$2:$T$28,MATCH(E759,'Cost_Components'!$A$2:$A$28,0)),"") | AA759: =IFERROR(INDEX('Cost_Components'!$U$2:$U$28,MATCH(E759,'Cost_Components'!$A$2:$A$28,0)),"") | AB759: =IFERROR(INDEX('Cost_Components'!$V$2:$V$28,MATCH(E759,'Cost_Components'!$A$2:$A$28,0)),"") | AC759: =IFERROR(INDEX('Cost_Components'!$M$2:$M$28,MATCH(E759,'Cost_Components'!$A$2:$A$28,0)),"") | AD759: =IFERROR(INDEX('Cost_Components'!$N$2:$N$28,MATCH(E759,'Cost_Components'!$A$2:$A$28,0)),"") | AE759: =IFERROR(INDEX('Cost_Components'!$O$2:$O$28,MATCH(E759,'Cost_Components'!$A$2:$A$28,0)),"") | AF759: 53615.121 | AG759: 52920.528 | AH759: =IF(H759="shared-count-once",COUNTIFS($A$2:$A$1405,A759,$B$2:$B$1405,B759,$E$2:$E$1405,E759),1) | AI759: 2.9448471e+08 | AJ759: =IF(AI759=0,"",Q759/AI759) | AK759: =IF(AI759=0,"",R759/AI759) | AL759: =IF(AI759=0,"",S759/AI759) | AM759: =IF(AI759=0,"",Y759/AI759)
A760: all | B760: 2029 | C760: I_HF_ACUTE | D760: cmd | E760: COST_HF_ACUTE_C_CMP | F760: CC_HF_ACUTE_C_CMP | G760: I_HF_ACUTE__C_CMP | H760: cause-specific | I760: prevalence | J760: =IFERROR(INDEX('Cost_Components'!$K$2:$K$28,MATCH(E760,'Cost_Components'!$A$2:$A$28,0)),"") | K760: =IF(OR(L760="",Z760="",AA760="",AB760=""),"",IF(B760<AA760,L760,IF(B760>AB760,Z760,L760+(Z760-L760)*MIN(MAX((B760-AA760+1)/MAX(AB760-AA760+1,1),0),1)))) | L760: =IFERROR(INDEX('Cost_Components'!$S$2:$S$28,MATCH(E760,'Cost_Components'!$A$2:$A$28,0)),"") | M760: =IFERROR(INDEX('Cost_Components'!$L$2:$L$28,MATCH(E760,'Cost_Components'!$A$2:$A$28,0)),"") | N760: =IFERROR(INDEX('Cost_Components'!$P$2:$P$28,MATCH(E760,'Cost_Components'!$A$2:$A$28,0)),"") | O760: =AF760*J760 | P760: =AG760*J760 | Q760: =P760*L760*M760*N760 | R760: =O760*K760*M760*N760 | S760: =R760-Q760 | T760: =IFERROR(INDEX('Cost_Components'!$R$2:$R$28,MATCH(E760,'Cost_Components'!$A$2:$A$28,0)),"") | U760: =IFERROR(INDEX('Cost_Components'!$Q$2:$Q$28,MATCH(E760,'Cost_Components'!$A$2:$A$28,0)),"") | V760: =1/(1+'Calculation_Assumptions'!$B$5)^(B760-'Calculation_Assumptions'!$B$2) | W760: =Q760*V760 | X760: =R760*V760 | Y760: =S760*V760 | Z760: =IFERROR(INDEX('Cost_Components'!$T$2:$T$28,MATCH(E760,'Cost_Components'!$A$2:$A$28,0)),"") | AA760: =IFERROR(INDEX('Cost_Components'!$U$2:$U$28,MATCH(E760,'Cost_Components'!$A$2:$A$28,0)),"") | AB760: =IFERROR(INDEX('Cost_Components'!$V$2:$V$28,MATCH(E760,'Cost_Components'!$A$2:$A$28,0)),"") | AC760: =IFERROR(INDEX('Cost_Components'!$M$2:$M$28,MATCH(E760,'Cost_Components'!$A$2:$A$28,0)),"") | AD760: =IFERROR(INDEX('Cost_Components'!$N$2:$N$28,MATCH(E760,'Cost_Components'!$A$2:$A$28,0)),"") | AE760: =IFERROR(INDEX('Cost_Components'!$O$2:$O$28,MATCH(E760,'Cost_Components'!$A$2:$A$28,0)),"") | AF760: 55189.562 | AG760: 54189.784 | AH760: =IF(H760="shared-count-once",COUNTIFS($A$2:$A$1405,A760,$B$2:$B$1405,B760,$E$2:$E$1405,E760),1) | AI760: 2.9641403e+08 | AJ760: =IF(AI760=0,"",Q760/AI760) | AK760: =IF(AI760=0,"",R760/AI760) | AL760: =IF(AI760=0,"",S760/AI760) | AM760: =IF(AI760=0,"",Y760/AI760)
A761: all | B761: 2030 | C761: I_HF_ACUTE | D761: cmd | E761: COST_HF_ACUTE_C_CMP | F761: CC_HF_ACUTE_C_CMP | G761: I_HF_ACUTE__C_CMP | H761: cause-specific | I761: prevalence | J761: =IFERROR(INDEX('Cost_Components'!$K$2:$K$28,MATCH(E761,'Cost_Components'!$A$2:$A$28,0)),"") | K761: =IF(OR(L761="",Z761="",AA761="",AB761=""),"",IF(B761<AA761,L761,IF(B761>AB761,Z761,L761+(Z761-L761)*MIN(MAX((B761-AA761+1)/MAX(AB761-AA761+1,1),0),1)))) | L761: =IFERROR(INDEX('Cost_Components'!$S$2:$S$28,MATCH(E761,'Cost_Components'!$A$2:$A$28,0)),"") | M761: =IFERROR(INDEX('Cost_Components'!$L$2:$L$28,MATCH(E761,'Cost_Components'!$A$2:$A$28,0)),"") | N761: =IFERROR(INDEX('Cost_Components'!$P$2:$P$28,MATCH(E761,'Cost_Components'!$A$2:$A$28,0)),"") | O761: =AF761*J761 | P761: =AG761*J761 | Q761: =P761*L761*M761*N761 | R761: =O761*K761*M761*N761 | S761: =R761-Q761 | T761: =IFERROR(INDEX('Cost_Components'!$R$2:$R$28,MATCH(E761,'Cost_Components'!$A$2:$A$28,0)),"") | U761: =IFERROR(INDEX('Cost_Components'!$Q$2:$Q$28,MATCH(E761,'Cost_Components'!$A$2:$A$28,0)),"") | V761: =1/(1+'Calculation_Assumptions'!$B$5)^(B761-'Calculation_Assumptions'!$B$2) | W761: =Q761*V761 | X761: =R761*V761 | Y761: =S761*V761 | Z761: =IFERROR(INDEX('Cost_Components'!$T$2:$T$28,MATCH(E761,'Cost_Components'!$A$2:$A$28,0)),"") | AA761: =IFERROR(INDEX('Cost_Components'!$U$2:$U$28,MATCH(E761,'Cost_Components'!$A$2:$A$28,0)),"") | AB761: =IFERROR(INDEX('Cost_Components'!$V$2:$V$28,MATCH(E761,'Cost_Components'!$A$2:$A$28,0)),"") | AC761: =IFERROR(INDEX('Cost_Components'!$M$2:$M$28,MATCH(E761,'Cost_Components'!$A$2:$A$28,0)),"") | AD761: =IFERROR(INDEX('Cost_Components'!$N$2:$N$28,MATCH(E761,'Cost_Components'!$A$2:$A$28,0)),"") | AE761: =IFERROR(INDEX('Cost_Components'!$O$2:$O$28,MATCH(E761,'Cost_Components'!$A$2:$A$28,0)),"") | AF761: 56852.831 | AG761: 55504.081 | AH761: =IF(H761="shared-count-once",COUNTIFS($A$2:$A$1405,A761,$B$2:$B$1405,B761,$E$2:$E$1405,E761),1) | AI761: 2.982894e+08 | AJ761: =IF(AI761=0,"",Q761/AI761) | AK761: =IF(AI761=0,"",R761/AI761) | AL761: =IF(AI761=0,"",S761/AI761) | AM761: =IF(AI761=0,"",Y761/AI761)
A762: all | B762: 2031 | C762: I_HF_ACUTE | D762: cmd | E762: COST_HF_ACUTE_C_CMP | F762: CC_HF_ACUTE_C_CMP | G762: I_HF_ACUTE__C_CMP | H762: cause-specific | I762: prevalence | J762: =IFERROR(INDEX('Cost_Components'!$K$2:$K$28,MATCH(E762,'Cost_Components'!$A$2:$A$28,0)),"") | K762: =IF(OR(L762="",Z762="",AA762="",AB762=""),"",IF(B762<AA762,L762,IF(B762>AB762,Z762,L762+(Z762-L762)*MIN(MAX((B762-AA762+1)/MAX(AB762-AA762+1,1),0),1)))) | L762: =IFERROR(INDEX('Cost_Components'!$S$2:$S$28,MATCH(E762,'Cost_Components'!$A$2:$A$28,0)),"") | M762: =IFERROR(INDEX('Cost_Components'!$L$2:$L$28,MATCH(E762,'Cost_Components'!$A$2:$A$28,0)),"") | N762: =IFERROR(INDEX('Cost_Components'!$P$2:$P$28,MATCH(E762,'Cost_Components'!$A$2:$A$28,0)),"") | O762: =AF762*J762 | P762: =AG762*J762 | Q762: =P762*L762*M762*N762 | R762: =O762*K762*M762*N762 | S762: =R762-Q762 | T762: =IFERROR(INDEX('Cost_Components'!$R$2:$R$28,MATCH(E762,'Cost_Components'!$A$2:$A$28,0)),"") | U762: =IFERROR(INDEX('Cost_Components'!$Q$2:$Q$28,MATCH(E762,'Cost_Components'!$A$2:$A$28,0)),"") | V762: =1/(1+'Calculation_Assumptions'!$B$5)^(B762-'Calculation_Assumptions'!$B$2) | W762: =Q762*V762 | X762: =R762*V762 | Y762: =S762*V762 | Z762: =IFERROR(INDEX('Cost_Components'!$T$2:$T$28,MATCH(E762,'Cost_Components'!$A$2:$A$28,0)),"") | AA762: =IFERROR(INDEX('Cost_Components'!$U$2:$U$28,MATCH(E762,'Cost_Components'!$A$2:$A$28,0)),"") | AB762: =IFERROR(INDEX('Cost_Components'!$V$2:$V$28,MATCH(E762,'Cost_Components'!$A$2:$A$28,0)),"") | AC762: =IFERROR(INDEX('Cost_Components'!$M$2:$M$28,MATCH(E762,'Cost_Components'!$A$2:$A$28,0)),"") | AD762: =IFERROR(INDEX('Cost_Components'!$N$2:$N$28,MATCH(E762,'Cost_Components'!$A$2:$A$28,0)),"") | AE762: =IFERROR(INDEX('Cost_Components'!$O$2:$O$28,MATCH(E762,'Cost_Components'!$A$2:$A$28,0)),"") | AF762: 58578.21 | AG762: 56837.904 | AH762: =IF(H762="shared-count-once",COUNTIFS($A$2:$A$1405,A762,$B$2:$B$1405,B762,$E$2:$E$1405,E762),1) | AI762: 3.0011964e+08 | AJ762: =IF(AI762=0,"",Q762/AI762) | AK762: =IF(AI762=0,"",R762/AI762) | AL762: =IF(AI762=0,"",S762/AI762) | AM762: =IF(AI762=0,"",Y762/AI762)
A763: all | B763: 2032 | C763: I_HF_ACUTE | D763: cmd | E763: COST_HF_ACUTE_C_CMP | F763: CC_HF_ACUTE_C_CMP | G763: I_HF_ACUTE__C_CMP | H763: cause-specific | I763: prevalence | J763: =IFERROR(INDEX('Cost_Components'!$K$2:$K$28,MATCH(E763,'Cost_Components'!$A$2:$A$28,0)),"") | K763: =IF(OR(L763="",Z763="",AA763="",AB763=""),"",IF(B763<AA763,L763,IF(B763>AB763,Z763,L763+(Z763-L763)*MIN(MAX((B763-AA763+1)/MAX(AB763-AA763+1,1),0),1)))) | L763: =IFERROR(INDEX('Cost_Components'!$S$2:$S$28,MATCH(E763,'Cost_Components'!$A$2:$A$28,0)),"") | M763: =IFERROR(INDEX('Cost_Components'!$L$2:$L$28,MATCH(E763,'Cost_Components'!$A$2:$A$28,0)),"") | N763: =IFERROR(INDEX('Cost_Components'!$P$2:$P$28,MATCH(E763,'Cost_Components'!$A$2:$A$28,0)),"") | O763: =AF763*J763 | P763: =AG763*J763 | Q763: =P763*L763*M763*N763 | R763: =O763*K763*M763*N763 | S763: =R763-Q763 | T763: =IFERROR(INDEX('Cost_Components'!$R$2:$R$28,MATCH(E763,'Cost_Components'!$A$2:$A$28,0)),"") | U763: =IFERROR(INDEX('Cost_Components'!$Q$2:$Q$28,MATCH(E763,'Cost_Components'!$A$2:$A$28,0)),"") | V763: =1/(1+'Calculation_Assumptions'!$B$5)^(B763-'Calculation_Assumptions'!$B$2) | W763: =Q763*V763 | X763: =R763*V763 | Y763: =S763*V763 | Z763: =IFERROR(INDEX('Cost_Components'!$T$2:$T$28,MATCH(E763,'Cost_Components'!$A$2:$A$28,0)),"") | AA763: =IFERROR(INDEX('Cost_Components'!$U$2:$U$28,MATCH(E763,'Cost_Components'!$A$2:$A$28,0)),"") | AB763: =IFERROR(INDEX('Cost_Components'!$V$2:$V$28,MATCH(E763,'Cost_Components'!$A$2:$A$28,0)),"") | AC763: =IFERROR(INDEX('Cost_Components'!$M$2:$M$28,MATCH(E763,'Cost_Components'!$A$2:$A$28,0)),"") | AD763: =IFERROR(INDEX('Cost_Components'!$N$2:$N$28,MATCH(E763,'Cost_Components'!$A$2:$A$28,0)),"") | AE763: =IFERROR(INDEX('Cost_Components'!$O$2:$O$28,MATCH(E763,'Cost_Components'!$A$2:$A$28,0)),"") | AF763: 60356.561 | AG763: 58184.138 | AH763: =IF(H763="shared-count-once",COUNTIFS($A$2:$A$1405,A763,$B$2:$B$1405,B763,$E$2:$E$1405,E763),1) | AI763: 3.0190463e+08 | AJ763: =IF(AI763=0,"",Q763/AI763) | AK763: =IF(AI763=0,"",R763/AI763) | AL763: =IF(AI763=0,"",S763/AI763) | AM763: =IF(AI763=0,"",Y763/AI763)
A764: all | B764: 2033 | C764: I_HF_ACUTE | D764: cmd | E764: COST_HF_ACUTE_C_CMP | F764: CC_HF_ACUTE_C_CMP | G764: I_HF_ACUTE__C_CMP | H764: cause-specific | I764: prevalence | J764: =IFERROR(INDEX('Cost_Components'!$K$2:$K$28,MATCH(E764,'Cost_Components'!$A$2:$A$28,0)),"") | K764: =IF(OR(L764="",Z764="",AA764="",AB764=""),"",IF(B764<AA764,L764,IF(B764>AB764,Z764,L764+(Z764-L764)*MIN(MAX((B764-AA764+1)/MAX(AB764-AA764+1,1),0),1)))) | L764: =IFERROR(INDEX('Cost_Components'!$S$2:$S$28,MATCH(E764,'Cost_Components'!$A$2:$A$28,0)),"") | M764: =IFERROR(INDEX('Cost_Components'!$L$2:$L$28,MATCH(E764,'Cost_Components'!$A$2:$A$28,0)),"") | N764: =IFERROR(INDEX('Cost_Components'!$P$2:$P$28,MATCH(E764,'Cost_Components'!$A$2:$A$28,0)),"") | O764: =AF764*J764 | P764: =AG764*J764 | Q764: =P764*L764*M764*N764 | R764: =O764*K764*M764*N764 | S764: =R764-Q764 | T764: =IFERROR(INDEX('Cost_Components'!$R$2:$R$28,MATCH(E764,'Cost_Components'!$A$2:$A$28,0)),"") | U764: =IFERROR(INDEX('Cost_Components'!$Q$2:$Q$28,MATCH(E764,'Cost_Components'!$A$2:$A$28,0)),"") | V764: =1/(1+'Calculation_Assumptions'!$B$5)^(B764-'Calculation_Assumptions'!$B$2) | W764: =Q764*V764 | X764: =R764*V764 | Y764: =S764*V764 | Z764: =IFERROR(INDEX('Cost_Components'!$T$2:$T$28,MATCH(E764,'Cost_Components'!$A$2:$A$28,0)),"") | AA764: =IFERROR(INDEX('Cost_Components'!$U$2:$U$28,MATCH(E764,'Cost_Components'!$A$2:$A$28,0)),"") | AB764: =IFERROR(INDEX('Cost_Components'!$V$2:$V$28,MATCH(E764,'Cost_Components'!$A$2:$A$28,0)),"") | AC764: =IFERROR(INDEX('Cost_Components'!$M$2:$M$28,MATCH(E764,'Cost_Components'!$A$2:$A$28,0)),"") | AD764: =IFERROR(INDEX('Cost_Components'!$N$2:$N$28,MATCH(E764,'Cost_Components'!$A$2:$A$28,0)),"") | AE764: =IFERROR(INDEX('Cost_Components'!$O$2:$O$28,MATCH(E764,'Cost_Components'!$A$2:$A$28,0)),"") | AF764: 62173.625 | AG764: 59529.008 | AH764: =IF(H764="shared-count-once",COUNTIFS($A$2:$A$1405,A764,$B$2:$B$1405,B764,$E$2:$E$1405,E764),1) | AI764: 3.0364428e+08 | AJ764: =IF(AI764=0,"",Q764/AI764) | AK764: =IF(AI764=0,"",R764/AI764) | AL764: =IF(AI764=0,"",S764/AI764) | AM764: =IF(AI764=0,"",Y764/AI764)
A765: all | B765: 2034 | C765: I_HF_ACUTE | D765: cmd | E765: COST_HF_ACUTE_C_CMP | F765: CC_HF_ACUTE_C_CMP | G765: I_HF_ACUTE__C_CMP | H765: cause-specific | I765: prevalence | J765: =IFERROR(INDEX('Cost_Components'!$K$2:$K$28,MATCH(E765,'Cost_Components'!$A$2:$A$28,0)),"") | K765: =IF(OR(L765="",Z765="",AA765="",AB765=""),"",IF(B765<AA765,L765,IF(B765>AB765,Z765,L765+(Z765-L765)*MIN(MAX((B765-AA765+1)/MAX(AB765-AA765+1,1),0),1)))) | L765: =IFERROR(INDEX('Cost_Components'!$S$2:$S$28,MATCH(E765,'Cost_Components'!$A$2:$A$28,0)),"") | M765: =IFERROR(INDEX('Cost_Components'!$L$2:$L$28,MATCH(E765,'Cost_Components'!$A$2:$A$28,0)),"") | N765: =IFERROR(INDEX('Cost_Components'!$P$2:$P$28,MATCH(E765,'Cost_Components'!$A$2:$A$28,0)),"") | O765: =AF765*J765 | P765: =AG765*J765 | Q765: =P765*L765*M765*N765 | R765: =O765*K765*M765*N765 | S765: =R765-Q765 | T765: =IFERROR(INDEX('Cost_Components'!$R$2:$R$28,MATCH(E765,'Cost_Components'!$A$2:$A$28,0)),"") | U765: =IFERROR(INDEX('Cost_Components'!$Q$2:$Q$28,MATCH(E765,'Cost_Components'!$A$2:$A$28,0)),"") | V765: =1/(1+'Calculation_Assumptions'!$B$5)^(B765-'Calculation_Assumptions'!$B$2) | W765: =Q765*V765 | X765: =R765*V765 | Y765: =S765*V765 | Z765: =IFERROR(INDEX('Cost_Components'!$T$2:$T$28,MATCH(E765,'Cost_Components'!$A$2:$A$28,0)),"") | AA765: =IFERROR(INDEX('Cost_Components'!$U$2:$U$28,MATCH(E765,'Cost_Components'!$A$2:$A$28,0)),"") | AB765: =IFERROR(INDEX('Cost_Components'!$V$2:$V$28,MATCH(E765,'Cost_Components'!$A$2:$A$28,0)),"") | AC765: =IFERROR(INDEX('Cost_Components'!$M$2:$M$28,MATCH(E765,'Cost_Components'!$A$2:$A$28,0)),"") | AD765: =IFERROR(INDEX('Cost_Components'!$N$2:$N$28,MATCH(E765,'Cost_Components'!$A$2:$A$28,0)),"") | AE765: =IFERROR(INDEX('Cost_Components'!$O$2:$O$28,MATCH(E765,'Cost_Components'!$A$2:$A$28,0)),"") | AF765: 64024.645 | AG765: 60869.948 | AH765: =IF(H765="shared-count-once",COUNTIFS($A$2:$A$1405,A765,$B$2:$B$1405,B765,$E$2:$E$1405,E765),1) | AI765: 3.0533254e+08 | AJ765: =IF(AI765=0,"",Q765/AI765) | AK765: =IF(AI765=0,"",R765/AI765) | AL765: =IF(AI765=0,"",S765/AI765) | AM765: =IF(AI765=0,"",Y765/AI765)
A766: all | B766: 2035 | C766: I_HF_ACUTE | D766: cmd | E766: COST_HF_ACUTE_C_CMP | F766: CC_HF_ACUTE_C_CMP | G766: I_HF_ACUTE__C_CMP | H766: cause-specific | I766: prevalence | J766: =IFERROR(INDEX('Cost_Components'!$K$2:$K$28,MATCH(E766,'Cost_Components'!$A$2:$A$28,0)),"") | K766: =IF(OR(L766="",Z766="",AA766="",AB766=""),"",IF(B766<AA766,L766,IF(B766>AB766,Z766,L766+(Z766-L766)*MIN(MAX((B766-AA766+1)/MAX(AB766-AA766+1,1),0),1)))) | L766: =IFERROR(INDEX('Cost_Components'!$S$2:$S$28,MATCH(E766,'Cost_Components'!$A$2:$A$28,0)),"") | M766: =IFERROR(INDEX('Cost_Components'!$L$2:$L$28,MATCH(E766,'Cost_Components'!$A$2:$A$28,0)),"") | N766: =IFERROR(INDEX('Cost_Components'!$P$2:$P$28,MATCH(E766,'Cost_Components'!$A$2:$A$28,0)),"") | O766: =AF766*J766 | P766: =AG766*J766 | Q766: =P766*L766*M766*N766 | R766: =O766*K766*M766*N766 | S766: =R766-Q766 | T766: =IFERROR(INDEX('Cost_Components'!$R$2:$R$28,MATCH(E766,'Cost_Components'!$A$2:$A$28,0)),"") | U766: =IFERROR(INDEX('Cost_Components'!$Q$2:$Q$28,MATCH(E766,'Cost_Components'!$A$2:$A$28,0)),"") | V766: =1/(1+'Calculation_Assumptions'!$B$5)^(B766-'Calculation_Assumptions'!$B$2) | W766: =Q766*V766 | X766: =R766*V766 | Y766: =S766*V766 | Z766: =IFERROR(INDEX('Cost_Components'!$T$2:$T$28,MATCH(E766,'Cost_Components'!$A$2:$A$28,0)),"") | AA766: =IFERROR(INDEX('Cost_Components'!$U$2:$U$28,MATCH(E766,'Cost_Components'!$A$2:$A$28,0)),"") | AB766: =IFERROR(INDEX('Cost_Components'!$V$2:$V$28,MATCH(E766,'Cost_Components'!$A$2:$A$28,0)),"") | AC766: =IFERROR(INDEX('Cost_Components'!$M$2:$M$28,MATCH(E766,'Cost_Components'!$A$2:$A$28,0)),"") | AD766: =IFERROR(INDEX('Cost_Components'!$N$2:$N$28,MATCH(E766,'Cost_Components'!$A$2:$A$28,0)),"") | AE766: =IFERROR(INDEX('Cost_Components'!$O$2:$O$28,MATCH(E766,'Cost_Components'!$A$2:$A$28,0)),"") | AF766: 66000.413 | AG766: 62296.1 | AH766: =IF(H766="shared-count-once",COUNTIFS($A$2:$A$1405,A766,$B$2:$B$1405,B766,$E$2:$E$1405,E766),1) | AI766: 3.0696465e+08 | AJ766: =IF(AI766=0,"",Q766/AI766) | AK766: =IF(AI766=0,"",R766/AI766) | AL766: =IF(AI766=0,"",S766/AI766) | AM766: =IF(AI766=0,"",Y766/AI766)
A767: all | B767: 2036 | C767: I_HF_ACUTE | D767: cmd | E767: COST_HF_ACUTE_C_CMP | F767: CC_HF_ACUTE_C_CMP | G767: I_HF_ACUTE__C_CMP | H767: cause-specific | I767: prevalence | J767: =IFERROR(INDEX('Cost_Components'!$K$2:$K$28,MATCH(E767,'Cost_Components'!$A$2:$A$28,0)),"") | K767: =IF(OR(L767="",Z767="",AA767="",AB767=""),"",IF(B767<AA767,L767,IF(B767>AB767,Z767,L767+(Z767-L767)*MIN(MAX((B767-AA767+1)/MAX(AB767-AA767+1,1),0),1)))) | L767: =IFERROR(INDEX('Cost_Components'!$S$2:$S$28,MATCH(E767,'Cost_Components'!$A$2:$A$28,0)),"") | M767: =IFERROR(INDEX('Cost_Components'!$L$2:$L$28,MATCH(E767,'Cost_Components'!$A$2:$A$28,0)),"") | N767: =IFERROR(INDEX('Cost_Components'!$P$2:$P$28,MATCH(E767,'Cost_Components'!$A$2:$A$28,0)),"") | O767: =AF767*J767 | P767: =AG767*J767 | Q767: =P767*L767*M767*N767 | R767: =O767*K767*M767*N767 | S767: =R767-Q767 | T767: =IFERROR(INDEX('Cost_Components'!$R$2:$R$28,MATCH(E767,'Cost_Components'!$A$2:$A$28,0)),"") | U767: =IFERROR(INDEX('Cost_Components'!$Q$2:$Q$28,MATCH(E767,'Cost_Components'!$A$2:$A$28,0)),"") | V767: =1/(1+'Calculation_Assumptions'!$B$5)^(B767-'Calculation_Assumptions'!$B$2) | W767: =Q767*V767 | X767: =R767*V767 | Y767: =S767*V767 | Z767: =IFERROR(INDEX('Cost_Components'!$T$2:$T$28,MATCH(E767,'Cost_Components'!$A$2:$A$28,0)),"") | AA767: =IFERROR(INDEX('Cost_Components'!$U$2:$U$28,MATCH(E767,'Cost_Components'!$A$2:$A$28,0)),"") | AB767: =IFERROR(INDEX('Cost_Components'!$V$2:$V$28,MATCH(E767,'Cost_Components'!$A$2:$A$28,0)),"") | AC767: =IFERROR(INDEX('Cost_Components'!$M$2:$M$28,MATCH(E767,'Cost_Components'!$A$2:$A$28,0)),"") | AD767: =IFERROR(INDEX('Cost_Components'!$N$2:$N$28,MATCH(E767,'Cost_Components'!$A$2:$A$28,0)),"") | AE767: =IFERROR(INDEX('Cost_Components'!$O$2:$O$28,MATCH(E767,'Cost_Components'!$A$2:$A$28,0)),"") | AF767: 68073.407 | AG767: 63780.093 | AH767: =IF(H767="shared-count-once",COUNTIFS($A$2:$A$1405,A767,$B$2:$B$1405,B767,$E$2:$E$1405,E767),1) | AI767: 3.0854277e+08 | AJ767: =IF(AI767=0,"",Q767/AI767) | AK767: =IF(AI767=0,"",R767/AI767) | AL767: =IF(AI767=0,"",S767/AI767) | AM767: =IF(AI767=0,"",Y767/AI767)
... A1405: all | B1405: 2050 | C1405: I_T2D_TREATMENT | D1405: dm2 | E1405: COST_T2D_INSULIN | F1405: CC_T2D_INSULIN | G1405: I_T2D_TREATMENT__C_T2D | H1405: cause-specific | I1405: prevalence | J1405: =IFERROR(INDEX('Cost_Components'!$K$2:$K$28,MATCH(E1405,'Cost_Components'!$A$2:$A$28,0)),"") | K1405: =IF(OR(L1405="",Z1405="",AA1405="",AB1405=""),"",IF(B1405<AA1405,L1405,IF(B1405>AB1405,Z1405,L1405+(Z1405-L1405)*MIN(MAX((B1405-AA1405+1)/MAX(AB1405-AA1405+1,1),0),1)))) | L1405: =IFERROR(INDEX('Cost_Components'!$S$2:$S$28,MATCH(E1405,'Cost_Components'!$A$2:$A$28,0)),"") | M1405: =IFERROR(INDEX('Cost_Components'!$L$2:$L$28,MATCH(E1405,'Cost_Components'!$A$2:$A$28,0)),"") | N1405: =IFERROR(INDEX('Cost_Components'!$P$2:$P$28,MATCH(E1405,'Cost_Components'!$A$2:$A$28,0)),"") | O1405: =AF1405*J1405 | P1405: =AG1405*J1405 | Q1405: =P1405*L1405*M1405*N1405 | R1405: =O1405*K1405*M1405*N1405 | S1405: =R1405-Q1405 | T1405: =IFERROR(INDEX('Cost_Components'!$R$2:$R$28,MATCH(E1405,'Cost_Components'!$A$2:$A$28,0)),"") | U1405: =IFERROR(INDEX('Cost_Components'!$Q$2:$Q$28,MATCH(E1405,'Cost_Components'!$A$2:$A$28,0)),"") | V1405: =1/(1+'Calculation_Assumptions'!$B$5)^(B1405-'Calculation_Assumptions'!$B$2) | W1405: =Q1405*V1405 | X1405: =R1405*V1405 | Y1405: =S1405*V1405 | Z1405: =IFERROR(INDEX('Cost_Components'!$T$2:$T$28,MATCH(E1405,'Cost_Components'!$A$2:$A$28,0)),"") | AA1405: =IFERROR(INDEX('Cost_Components'!$U$2:$U$28,MATCH(E1405,'Cost_Components'!$A$2:$A$28,0)),"") | AB1405: =IFERROR(INDEX('Cost_Components'!$V$2:$V$28,MATCH(E1405,'Cost_Components'!$A$2:$A$28,0)),"") | AC1405: =IFERROR(INDEX('Cost_Components'!$M$2:$M$28,MATCH(E1405,'Cost_Components'!$A$2:$A$28,0)),"") | AD1405: =IFERROR(INDEX('Cost_Components'!$N$2:$N$28,MATCH(E1405,'Cost_Components'!$A$2:$A$28,0)),"") | AE1405: =IFERROR(INDEX('Cost_Components'!$O$2:$O$28,MATCH(E1405,'Cost_Components'!$A$2:$A$28,0)),"") | AF1405: 25417343 | AG1405: 25030421 | AH1405: =IF(H1405="shared-count-once",COUNTIFS($A$2:$A$1405,A1405,$B$2:$B$1405,B1405,$E$2:$E$1405,E1405),1) | AI1405: 3.2331204e+08 | AJ1405: =IF(AI1405=0,"",Q1405/AI1405) | AK1405: =IF(AI1405=0,"",R1405/AI1405) | AL1405: =IF(AI1405=0,"",S1405/AI1405) | AM1405: =IF(AI1405=0,"",Y1405/AI1405)

Sheet Budget_Impact
A1: scenario | B1: year | C1: baseline_cost | D1: scenario_cost | E1: incremental_cost | F1: disc_incremental_cost | G1: cumulative_incremental_cost | H1: cumulative_disc_incremental_cost | I1: national_population | J1: baseline_cost_per_capita | K1: scenario_cost_per_capita | L1: incremental_cost_per_capita | M1: disc_incremental_cost_per_capita
A2: I_CVD_PRIMARY | B2: 2025 | C2: =SUMIFS('Annual_Cost'!$Q$2:$Q$1405,'Annual_Cost'!$A$2:$A$1405,A2,'Annual_Cost'!$B$2:$B$1405,B2) | D2: =SUMIFS('Annual_Cost'!$R$2:$R$1405,'Annual_Cost'!$A$2:$A$1405,A2,'Annual_Cost'!$B$2:$B$1405,B2) | E2: =SUMIFS('Annual_Cost'!$S$2:$S$1405,'Annual_Cost'!$A$2:$A$1405,A2,'Annual_Cost'!$B$2:$B$1405,B2) | F2: =SUMIFS('Annual_Cost'!$Y$2:$Y$1405,'Annual_Cost'!$A$2:$A$1405,A2,'Annual_Cost'!$B$2:$B$1405,B2) | G2: =SUMIFS($E$2:E2,$A$2:A2,A2) | H2: =SUMIFS($F$2:F2,$A$2:A2,A2) | I2: 2.8839191e+08 | J2: =IF(I2=0,"",C2/I2) | K2: =IF(I2=0,"",D2/I2) | L2: =IF(I2=0,"",E2/I2) | M2: =IF(I2=0,"",F2/I2)
A3: I_CVD_PRIMARY | B3: 2026 | C3: =SUMIFS('Annual_Cost'!$Q$2:$Q$1405,'Annual_Cost'!$A$2:$A$1405,A3,'Annual_Cost'!$B$2:$B$1405,B3) | D3: =SUMIFS('Annual_Cost'!$R$2:$R$1405,'Annual_Cost'!$A$2:$A$1405,A3,'Annual_Cost'!$B$2:$B$1405,B3) | E3: =SUMIFS('Annual_Cost'!$S$2:$S$1405,'Annual_Cost'!$A$2:$A$1405,A3,'Annual_Cost'!$B$2:$B$1405,B3) | F3: =SUMIFS('Annual_Cost'!$Y$2:$Y$1405,'Annual_Cost'!$A$2:$A$1405,A3,'Annual_Cost'!$B$2:$B$1405,B3) | G3: =SUMIFS($E$2:E3,$A$2:A3,A3) | H3: =SUMIFS($F$2:F3,$A$2:A3,A3) | I3: 2.9047213e+08 | J3: =IF(I3=0,"",C3/I3) | K3: =IF(I3=0,"",D3/I3) | L3: =IF(I3=0,"",E3/I3) | M3: =IF(I3=0,"",F3/I3)
A4: I_CVD_PRIMARY | B4: 2027 | C4: =SUMIFS('Annual_Cost'!$Q$2:$Q$1405,'Annual_Cost'!$A$2:$A$1405,A4,'Annual_Cost'!$B$2:$B$1405,B4) | D4: =SUMIFS('Annual_Cost'!$R$2:$R$1405,'Annual_Cost'!$A$2:$A$1405,A4,'Annual_Cost'!$B$2:$B$1405,B4) | E4: =SUMIFS('Annual_Cost'!$S$2:$S$1405,'Annual_Cost'!$A$2:$A$1405,A4,'Annual_Cost'!$B$2:$B$1405,B4) | F4: =SUMIFS('Annual_Cost'!$Y$2:$Y$1405,'Annual_Cost'!$A$2:$A$1405,A4,'Annual_Cost'!$B$2:$B$1405,B4) | G4: =SUMIFS($E$2:E4,$A$2:A4,A4) | H4: =SUMIFS($F$2:F4,$A$2:A4,A4) | I4: 2.9250508e+08 | J4: =IF(I4=0,"",C4/I4) | K4: =IF(I4=0,"",D4/I4) | L4: =IF(I4=0,"",E4/I4) | M4: =IF(I4=0,"",F4/I4)
A5: I_CVD_PRIMARY | B5: 2028 | C5: =SUMIFS('Annual_Cost'!$Q$2:$Q$1405,'Annual_Cost'!$A$2:$A$1405,A5,'Annual_Cost'!$B$2:$B$1405,B5) | D5: =SUMIFS('Annual_Cost'!$R$2:$R$1405,'Annual_Cost'!$A$2:$A$1405,A5,'Annual_Cost'!$B$2:$B$1405,B5) | E5: =SUMIFS('Annual_Cost'!$S$2:$S$1405,'Annual_Cost'!$A$2:$A$1405,A5,'Annual_Cost'!$B$2:$B$1405,B5) | F5: =SUMIFS('Annual_Cost'!$Y$2:$Y$1405,'Annual_Cost'!$A$2:$A$1405,A5,'Annual_Cost'!$B$2:$B$1405,B5) | G5: =SUMIFS($E$2:E5,$A$2:A5,A5) | H5: =SUMIFS($F$2:F5,$A$2:A5,A5) | I5: 2.9448471e+08 | J5: =IF(I5=0,"",C5/I5) | K5: =IF(I5=0,"",D5/I5) | L5: =IF(I5=0,"",E5/I5) | M5: =IF(I5=0,"",F5/I5)
A6: I_CVD_PRIMARY | B6: 2029 | C6: =SUMIFS('Annual_Cost'!$Q$2:$Q$1405,'Annual_Cost'!$A$2:$A$1405,A6,'Annual_Cost'!$B$2:$B$1405,B6) | D6: =SUMIFS('Annual_Cost'!$R$2:$R$1405,'Annual_Cost'!$A$2:$A$1405,A6,'Annual_Cost'!$B$2:$B$1405,B6) | E6: =SUMIFS('Annual_Cost'!$S$2:$S$1405,'Annual_Cost'!$A$2:$A$1405,A6,'Annual_Cost'!$B$2:$B$1405,B6) | F6: =SUMIFS('Annual_Cost'!$Y$2:$Y$1405,'Annual_Cost'!$A$2:$A$1405,A6,'Annual_Cost'!$B$2:$B$1405,B6) | G6: =SUMIFS($E$2:E6,$A$2:A6,A6) | H6: =SUMIFS($F$2:F6,$A$2:A6,A6) | I6: 2.9641403e+08 | J6: =IF(I6=0,"",C6/I6) | K6: =IF(I6=0,"",D6/I6) | L6: =IF(I6=0,"",E6/I6) | M6: =IF(I6=0,"",F6/I6)
A7: I_CVD_PRIMARY | B7: 2030 | C7: =SUMIFS('Annual_Cost'!$Q$2:$Q$1405,'Annual_Cost'!$A$2:$A$1405,A7,'Annual_Cost'!$B$2:$B$1405,B7) | D7: =SUMIFS('Annual_Cost'!$R$2:$R$1405,'Annual_Cost'!$A$2:$A$1405,A7,'Annual_Cost'!$B$2:$B$1405,B7) | E7: =SUMIFS('Annual_Cost'!$S$2:$S$1405,'Annual_Cost'!$A$2:$A$1405,A7,'Annual_Cost'!$B$2:$B$1405,B7) | F7: =SUMIFS('Annual_Cost'!$Y$2:$Y$1405,'Annual_Cost'!$A$2:$A$1405,A7,'Annual_Cost'!$B$2:$B$1405,B7) | G7: =SUMIFS($E$2:E7,$A$2:A7,A7) | H7: =SUMIFS($F$2:F7,$A$2:A7,A7) | I7: 2.982894e+08 | J7: =IF(I7=0,"",C7/I7) | K7: =IF(I7=0,"",D7/I7) | L7: =IF(I7=0,"",E7/I7) | M7: =IF(I7=0,"",F7/I7)
A8: I_CVD_PRIMARY | B8: 2031 | C8: =SUMIFS('Annual_Cost'!$Q$2:$Q$1405,'Annual_Cost'!$A$2:$A$1405,A8,'Annual_Cost'!$B$2:$B$1405,B8) | D8: =SUMIFS('Annual_Cost'!$R$2:$R$1405,'Annual_Cost'!$A$2:$A$1405,A8,'Annual_Cost'!$B$2:$B$1405,B8) | E8: =SUMIFS('Annual_Cost'!$S$2:$S$1405,'Annual_Cost'!$A$2:$A$1405,A8,'Annual_Cost'!$B$2:$B$1405,B8) | F8: =SUMIFS('Annual_Cost'!$Y$2:$Y$1405,'Annual_Cost'!$A$2:$A$1405,A8,'Annual_Cost'!$B$2:$B$1405,B8) | G8: =SUMIFS($E$2:E8,$A$2:A8,A8) | H8: =SUMIFS($F$2:F8,$A$2:A8,A8) | I8: 3.0011964e+08 | J8: =IF(I8=0,"",C8/I8) | K8: =IF(I8=0,"",D8/I8) | L8: =IF(I8=0,"",E8/I8) | M8: =IF(I8=0,"",F8/I8)
A9: I_CVD_PRIMARY | B9: 2032 | C9: =SUMIFS('Annual_Cost'!$Q$2:$Q$1405,'Annual_Cost'!$A$2:$A$1405,A9,'Annual_Cost'!$B$2:$B$1405,B9) | D9: =SUMIFS('Annual_Cost'!$R$2:$R$1405,'Annual_Cost'!$A$2:$A$1405,A9,'Annual_Cost'!$B$2:$B$1405,B9) | E9: =SUMIFS('Annual_Cost'!$S$2:$S$1405,'Annual_Cost'!$A$2:$A$1405,A9,'Annual_Cost'!$B$2:$B$1405,B9) | F9: =SUMIFS('Annual_Cost'!$Y$2:$Y$1405,'Annual_Cost'!$A$2:$A$1405,A9,'Annual_Cost'!$B$2:$B$1405,B9) | G9: =SUMIFS($E$2:E9,$A$2:A9,A9) | H9: =SUMIFS($F$2:F9,$A$2:A9,A9) | I9: 3.0190463e+08 | J9: =IF(I9=0,"",C9/I9) | K9: =IF(I9=0,"",D9/I9) | L9: =IF(I9=0,"",E9/I9) | M9: =IF(I9=0,"",F9/I9)
A10: I_CVD_PRIMARY | B10: 2033 | C10: =SUMIFS('Annual_Cost'!$Q$2:$Q$1405,'Annual_Cost'!$A$2:$A$1405,A10,'Annual_Cost'!$B$2:$B$1405,B10) | D10: =SUMIFS('Annual_Cost'!$R$2:$R$1405,'Annual_Cost'!$A$2:$A$1405,A10,'Annual_Cost'!$B$2:$B$1405,B10) | E10: =SUMIFS('Annual_Cost'!$S$2:$S$1405,'Annual_Cost'!$A$2:$A$1405,A10,'Annual_Cost'!$B$2:$B$1405,B10) | F10: =SUMIFS('Annual_Cost'!$Y$2:$Y$1405,'Annual_Cost'!$A$2:$A$1405,A10,'Annual_Cost'!$B$2:$B$1405,B10) | G10: =SUMIFS($E$2:E10,$A$2:A10,A10) | H10: =SUMIFS($F$2:F10,$A$2:A10,A10) | I10: 3.0364428e+08 | J10: =IF(I10=0,"",C10/I10) | K10: =IF(I10=0,"",D10/I10) | L10: =IF(I10=0,"",E10/I10) | M10: =IF(I10=0,"",F10/I10)
A11: I_CVD_PRIMARY | B11: 2034 | C11: =SUMIFS('Annual_Cost'!$Q$2:$Q$1405,'Annual_Cost'!$A$2:$A$1405,A11,'Annual_Cost'!$B$2:$B$1405,B11) | D11: =SUMIFS('Annual_Cost'!$R$2:$R$1405,'Annual_Cost'!$A$2:$A$1405,A11,'Annual_Cost'!$B$2:$B$1405,B11) | E11: =SUMIFS('Annual_Cost'!$S$2:$S$1405,'Annual_Cost'!$A$2:$A$1405,A11,'Annual_Cost'!$B$2:$B$1405,B11) | F11: =SUMIFS('Annual_Cost'!$Y$2:$Y$1405,'Annual_Cost'!$A$2:$A$1405,A11,'Annual_Cost'!$B$2:$B$1405,B11) | G11: =SUMIFS($E$2:E11,$A$2:A11,A11) | H11: =SUMIFS($F$2:F11,$A$2:A11,A11) | I11: 3.0533254e+08 | J11: =IF(I11=0,"",C11/I11) | K11: =IF(I11=0,"",D11/I11) | L11: =IF(I11=0,"",E11/I11) | M11: =IF(I11=0,"",F11/I11)
A12: I_CVD_PRIMARY | B12: 2035 | C12: =SUMIFS('Annual_Cost'!$Q$2:$Q$1405,'Annual_Cost'!$A$2:$A$1405,A12,'Annual_Cost'!$B$2:$B$1405,B12) | D12: =SUMIFS('Annual_Cost'!$R$2:$R$1405,'Annual_Cost'!$A$2:$A$1405,A12,'Annual_Cost'!$B$2:$B$1405,B12) | E12: =SUMIFS('Annual_Cost'!$S$2:$S$1405,'Annual_Cost'!$A$2:$A$1405,A12,'Annual_Cost'!$B$2:$B$1405,B12) | F12: =SUMIFS('Annual_Cost'!$Y$2:$Y$1405,'Annual_Cost'!$A$2:$A$1405,A12,'Annual_Cost'!$B$2:$B$1405,B12) | G12: =SUMIFS($E$2:E12,$A$2:A12,A12) | H12: =SUMIFS($F$2:F12,$A$2:A12,A12) | I12: 3.0696465e+08 | J12: =IF(I12=0,"",C12/I12) | K12: =IF(I12=0,"",D12/I12) | L12: =IF(I12=0,"",E12/I12) | M12: =IF(I12=0,"",F12/I12)
A13: I_CVD_PRIMARY | B13: 2036 | C13: =SUMIFS('Annual_Cost'!$Q$2:$Q$1405,'Annual_Cost'!$A$2:$A$1405,A13,'Annual_Cost'!$B$2:$B$1405,B13) | D13: =SUMIFS('Annual_Cost'!$R$2:$R$1405,'Annual_Cost'!$A$2:$A$1405,A13,'Annual_Cost'!$B$2:$B$1405,B13) | E13: =SUMIFS('Annual_Cost'!$S$2:$S$1405,'Annual_Cost'!$A$2:$A$1405,A13,'Annual_Cost'!$B$2:$B$1405,B13) | F13: =SUMIFS('Annual_Cost'!$Y$2:$Y$1405,'Annual_Cost'!$A$2:$A$1405,A13,'Annual_Cost'!$B$2:$B$1405,B13) | G13: =SUMIFS($E$2:E13,$A$2:A13,A13) | H13: =SUMIFS($F$2:F13,$A$2:A13,A13) | I13: 3.0854277e+08 | J13: =IF(I13=0,"",C13/I13) | K13: =IF(I13=0,"",D13/I13) | L13: =IF(I13=0,"",E13/I13) | M13: =IF(I13=0,"",F13/I13)
... A209: all | B209: 2050 | C209: =SUMIFS('Annual_Cost'!$Q$2:$Q$1405,'Annual_Cost'!$A$2:$A$1405,A209,'Annual_Cost'!$B$2:$B$1405,B209) | D209: =SUMIFS('Annual_Cost'!$R$2:$R$1405,'Annual_Cost'!$A$2:$A$1405,A209,'Annual_Cost'!$B$2:$B$1405,B209) | E209: =SUMIFS('Annual_Cost'!$S$2:$S$1405,'Annual_Cost'!$A$2:$A$1405,A209,'Annual_Cost'!$B$2:$B$1405,B209) | F209: =SUMIFS('Annual_Cost'!$Y$2:$Y$1405,'Annual_Cost'!$A$2:$A$1405,A209,'Annual_Cost'!$B$2:$B$1405,B209) | G209: =SUMIFS($E$2:E209,$A$2:A209,A209) | H209: =SUMIFS($F$2:F209,$A$2:A209,A209) | I209: 3.2331204e+08 | J209: =IF(I209=0,"",C209/I209) | K209: =IF(I209=0,"",D209/I209) | L209: =IF(I209=0,"",E209/I209) | M209: =IF(I209=0,"",F209/I209)

Sheet Cost_Effectiveness
A1: scenario | B1: scenario_label | C1: deaths_averted | D1: cases_averted | E1: incremental_cost | F1: disc_incremental_cost | G1: cost_per_death_averted | H1: dominance | I1: reconciliation_status | J1: annual_cost_incremental_per_capita | K1: disc_cost_incremental_per_capita
A2: all | B2: All selected interventions (combined) | C2: =SUMIFS('Annual_Mortality'!$H$2:$H$1639,'Annual_Mortality'!$A$2:$A$1639,A2) | D2: =SUMIFS('Annual_Mortality'!$J$2:$J$1639,'Annual_Mortality'!$A$2:$A$1639,A2) | E2: =SUMIFS('Budget_Impact'!$E$2:$E$209,'Budget_Impact'!$A$2:$A$209,A2) | F2: =SUMIFS('Budget_Impact'!$F$2:$F$209,'Budget_Impact'!$A$2:$A$209,A2) | G2: =IF(C2>0,F2/C2,"") | H2: =IF(AND(C2>0,F2<0),"Dominant (more health, lower cost)",IF(AND(C2<=0,F2>0),"Dominated (less/no health, higher cost)",IF(AND(C2<=0,F2<=0),"No deaths averted; ratio not defined","USD per death averted"))) | I2: =IF(AND(ABS(F2-SUMIFS('Budget_Impact'!$F$2:$F$209,'Budget_Impact'!$A$2:$A$209,A2))<='Calculation_Assumptions'!$B$11,ABS(C2-SUMIFS('Annual_Mortality'!$H$2:$H$1639,'Annual_Mortality'!$A$2:$A$1639,A2))<='Calculation_Assumptions'!$B$11),"consistent","mismatch") | J2: =IFERROR(AVERAGEIFS('Budget_Impact'!$L$2:$L$209,'Budget_Impact'!$A$2:$A$209,A2,'Budget_Impact'!$B$2:$B$209,">="&('Calculation_Assumptions'!$B$2+1)),"") | K2: =IFERROR(AVERAGEIFS('Budget_Impact'!$M$2:$M$209,'Budget_Impact'!$A$2:$A$209,A2,'Budget_Impact'!$B$2:$B$209,">="&('Calculation_Assumptions'!$B$2+1)),"")
A3: I_CVD_PRIMARY | B3: Primary prevention of CVD | C3: =SUMIFS('Annual_Mortality'!$H$2:$H$1639,'Annual_Mortality'!$A$2:$A$1639,A3) | D3: =SUMIFS('Annual_Mortality'!$J$2:$J$1639,'Annual_Mortality'!$A$2:$A$1639,A3) | E3: =SUMIFS('Budget_Impact'!$E$2:$E$209,'Budget_Impact'!$A$2:$A$209,A3) | F3: =SUMIFS('Budget_Impact'!$F$2:$F$209,'Budget_Impact'!$A$2:$A$209,A3) | G3: =IF(C3>0,F3/C3,"") | H3: =IF(AND(C3>0,F3<0),"Dominant (more health, lower cost)",IF(AND(C3<=0,F3>0),"Dominated (less/no health, higher cost)",IF(AND(C3<=0,F3<=0),"No deaths averted; ratio not defined","USD per death averted"))) | I3: =IF(AND(ABS(F3-SUMIFS('Budget_Impact'!$F$2:$F$209,'Budget_Impact'!$A$2:$A$209,A3))<='Calculation_Assumptions'!$B$11,ABS(C3-SUMIFS('Annual_Mortality'!$H$2:$H$1639,'Annual_Mortality'!$A$2:$A$1639,A3))<='Calculation_Assumptions'!$B$11),"consistent","mismatch") | J3: =IFERROR(AVERAGEIFS('Budget_Impact'!$L$2:$L$209,'Budget_Impact'!$A$2:$A$209,A3,'Budget_Impact'!$B$2:$B$209,">="&('Calculation_Assumptions'!$B$2+1)),"") | K3: =IFERROR(AVERAGEIFS('Budget_Impact'!$M$2:$M$209,'Budget_Impact'!$A$2:$A$209,A3,'Budget_Impact'!$B$2:$B$209,">="&('Calculation_Assumptions'!$B$2+1)),"")
A4: I_T2D_TREATMENT | B4: Longitudinal treatment of type 2 diabetes | C4: =SUMIFS('Annual_Mortality'!$H$2:$H$1639,'Annual_Mortality'!$A$2:$A$1639,A4) | D4: =SUMIFS('Annual_Mortality'!$J$2:$J$1639,'Annual_Mortality'!$A$2:$A$1639,A4) | E4: =SUMIFS('Budget_Impact'!$E$2:$E$209,'Budget_Impact'!$A$2:$A$209,A4) | F4: =SUMIFS('Budget_Impact'!$F$2:$F$209,'Budget_Impact'!$A$2:$A$209,A4) | G4: =IF(C4>0,F4/C4,"") | H4: =IF(AND(C4>0,F4<0),"Dominant (more health, lower cost)",IF(AND(C4<=0,F4>0),"Dominated (less/no health, higher cost)",IF(AND(C4<=0,F4<=0),"No deaths averted; ratio not defined","USD per death averted"))) | I4: =IF(AND(ABS(F4-SUMIFS('Budget_Impact'!$F$2:$F$209,'Budget_Impact'!$A$2:$A$209,A4))<='Calculation_Assumptions'!$B$11,ABS(C4-SUMIFS('Annual_Mortality'!$H$2:$H$1639,'Annual_Mortality'!$A$2:$A$1639,A4))<='Calculation_Assumptions'!$B$11),"consistent","mismatch") | J4: =IFERROR(AVERAGEIFS('Budget_Impact'!$L$2:$L$209,'Budget_Impact'!$A$2:$A$209,A4,'Budget_Impact'!$B$2:$B$209,">="&('Calculation_Assumptions'!$B$2+1)),"") | K4: =IFERROR(AVERAGEIFS('Budget_Impact'!$M$2:$M$209,'Budget_Impact'!$A$2:$A$209,A4,'Budget_Impact'!$B$2:$B$209,">="&('Calculation_Assumptions'!$B$2+1)),"")
A5: I_IHD_ACUTE | B5: Treatment of acute coronary syndromes | C5: =SUMIFS('Annual_Mortality'!$H$2:$H$1639,'Annual_Mortality'!$A$2:$A$1639,A5) | D5: =SUMIFS('Annual_Mortality'!$J$2:$J$1639,'Annual_Mortality'!$A$2:$A$1639,A5) | E5: =SUMIFS('Budget_Impact'!$E$2:$E$209,'Budget_Impact'!$A$2:$A$209,A5) | F5: =SUMIFS('Budget_Impact'!$F$2:$F$209,'Budget_Impact'!$A$2:$A$209,A5) | G5: =IF(C5>0,F5/C5,"") | H5: =IF(AND(C5>0,F5<0),"Dominant (more health, lower cost)",IF(AND(C5<=0,F5>0),"Dominated (less/no health, higher cost)",IF(AND(C5<=0,F5<=0),"No deaths averted; ratio not defined","USD per death averted"))) | I5: =IF(AND(ABS(F5-SUMIFS('Budget_Impact'!$F$2:$F$209,'Budget_Impact'!$A$2:$A$209,A5))<='Calculation_Assumptions'!$B$11,ABS(C5-SUMIFS('Annual_Mortality'!$H$2:$H$1639,'Annual_Mortality'!$A$2:$A$1639,A5))<='Calculation_Assumptions'!$B$11),"consistent","mismatch") | J5: =IFERROR(AVERAGEIFS('Budget_Impact'!$L$2:$L$209,'Budget_Impact'!$A$2:$A$209,A5,'Budget_Impact'!$B$2:$B$209,">="&('Calculation_Assumptions'!$B$2+1)),"") | K5: =IFERROR(AVERAGEIFS('Budget_Impact'!$M$2:$M$209,'Budget_Impact'!$A$2:$A$209,A5,'Budget_Impact'!$B$2:$B$209,">="&('Calculation_Assumptions'!$B$2+1)),"")
A6: I_IHD_SECONDARY | B6: Secondary prevention of ischemic heart disease | C6: =SUMIFS('Annual_Mortality'!$H$2:$H$1639,'Annual_Mortality'!$A$2:$A$1639,A6) | D6: =SUMIFS('Annual_Mortality'!$J$2:$J$1639,'Annual_Mortality'!$A$2:$A$1639,A6) | E6: =SUMIFS('Budget_Impact'!$E$2:$E$209,'Budget_Impact'!$A$2:$A$209,A6) | F6: =SUMIFS('Budget_Impact'!$F$2:$F$209,'Budget_Impact'!$A$2:$A$209,A6) | G6: =IF(C6>0,F6/C6,"") | H6: =IF(AND(C6>0,F6<0),"Dominant (more health, lower cost)",IF(AND(C6<=0,F6>0),"Dominated (less/no health, higher cost)",IF(AND(C6<=0,F6<=0),"No deaths averted; ratio not defined","USD per death averted"))) | I6: =IF(AND(ABS(F6-SUMIFS('Budget_Impact'!$F$2:$F$209,'Budget_Impact'!$A$2:$A$209,A6))<='Calculation_Assumptions'!$B$11,ABS(C6-SUMIFS('Annual_Mortality'!$H$2:$H$1639,'Annual_Mortality'!$A$2:$A$1639,A6))<='Calculation_Assumptions'!$B$11),"consistent","mismatch") | J6: =IFERROR(AVERAGEIFS('Budget_Impact'!$L$2:$L$209,'Budget_Impact'!$A$2:$A$209,A6,'Budget_Impact'!$B$2:$B$209,">="&('Calculation_Assumptions'!$B$2+1)),"") | K6: =IFERROR(AVERAGEIFS('Budget_Impact'!$M$2:$M$209,'Budget_Impact'!$A$2:$A$209,A6,'Budget_Impact'!$B$2:$B$209,">="&('Calculation_Assumptions'!$B$2+1)),"")
A7: I_HF_CHRONIC | B7: Chronic heart-failure management | C7: =SUMIFS('Annual_Mortality'!$H$2:$H$1639,'Annual_Mortality'!$A$2:$A$1639,A7) | D7: =SUMIFS('Annual_Mortality'!$J$2:$J$1639,'Annual_Mortality'!$A$2:$A$1639,A7) | E7: =SUMIFS('Budget_Impact'!$E$2:$E$209,'Budget_Impact'!$A$2:$A$209,A7) | F7: =SUMIFS('Budget_Impact'!$F$2:$F$209,'Budget_Impact'!$A$2:$A$209,A7) | G7: =IF(C7>0,F7/C7,"") | H7: =IF(AND(C7>0,F7<0),"Dominant (more health, lower cost)",IF(AND(C7<=0,F7>0),"Dominated (less/no health, higher cost)",IF(AND(C7<=0,F7<=0),"No deaths averted; ratio not defined","USD per death averted"))) | I7: =IF(AND(ABS(F7-SUMIFS('Budget_Impact'!$F$2:$F$209,'Budget_Impact'!$A$2:$A$209,A7))<='Calculation_Assumptions'!$B$11,ABS(C7-SUMIFS('Annual_Mortality'!$H$2:$H$1639,'Annual_Mortality'!$A$2:$A$1639,A7))<='Calculation_Assumptions'!$B$11),"consistent","mismatch") | J7: =IFERROR(AVERAGEIFS('Budget_Impact'!$L$2:$L$209,'Budget_Impact'!$A$2:$A$209,A7,'Budget_Impact'!$B$2:$B$209,">="&('Calculation_Assumptions'!$B$2+1)),"") | K7: =IFERROR(AVERAGEIFS('Budget_Impact'!$M$2:$M$209,'Budget_Impact'!$A$2:$A$209,A7,'Budget_Impact'!$B$2:$B$209,">="&('Calculation_Assumptions'!$B$2+1)),"")
A8: I_HF_ACUTE | B8: Acute heart-failure management | C8: =SUMIFS('Annual_Mortality'!$H$2:$H$1639,'Annual_Mortality'!$A$2:$A$1639,A8) | D8: =SUMIFS('Annual_Mortality'!$J$2:$J$1639,'Annual_Mortality'!$A$2:$A$1639,A8) | E8: =SUMIFS('Budget_Impact'!$E$2:$E$209,'Budget_Impact'!$A$2:$A$209,A8) | F8: =SUMIFS('Budget_Impact'!$F$2:$F$209,'Budget_Impact'!$A$2:$A$209,A8) | G8: =IF(C8>0,F8/C8,"") | H8: =IF(AND(C8>0,F8<0),"Dominant (more health, lower cost)",IF(AND(C8<=0,F8>0),"Dominated (less/no health, higher cost)",IF(AND(C8<=0,F8<=0),"No deaths averted; ratio not defined","USD per death averted"))) | I8: =IF(AND(ABS(F8-SUMIFS('Budget_Impact'!$F$2:$F$209,'Budget_Impact'!$A$2:$A$209,A8))<='Calculation_Assumptions'!$B$11,ABS(C8-SUMIFS('Annual_Mortality'!$H$2:$H$1639,'Annual_Mortality'!$A$2:$A$1639,A8))<='Calculation_Assumptions'!$B$11),"consistent","mismatch") | J8: =IFERROR(AVERAGEIFS('Budget_Impact'!$L$2:$L$209,'Budget_Impact'!$A$2:$A$209,A8,'Budget_Impact'!$B$2:$B$209,">="&('Calculation_Assumptions'!$B$2+1)),"") | K8: =IFERROR(AVERAGEIFS('Budget_Impact'!$M$2:$M$209,'Budget_Impact'!$A$2:$A$209,A8,'Budget_Impact'!$B$2:$B$209,">="&('Calculation_Assumptions'!$B$2+1)),"")
A9: I_STROKE_SECONDARY | B9: Secondary prevention of stroke | C9: =SUMIFS('Annual_Mortality'!$H$2:$H$1639,'Annual_Mortality'!$A$2:$A$1639,A9) | D9: =SUMIFS('Annual_Mortality'!$J$2:$J$1639,'Annual_Mortality'!$A$2:$A$1639,A9) | E9: =SUMIFS('Budget_Impact'!$E$2:$E$209,'Budget_Impact'!$A$2:$A$209,A9) | F9: =SUMIFS('Budget_Impact'!$F$2:$F$209,'Budget_Impact'!$A$2:$A$209,A9) | G9: =IF(C9>0,F9/C9,"") | H9: =IF(AND(C9>0,F9<0),"Dominant (more health, lower cost)",IF(AND(C9<=0,F9>0),"Dominated (less/no health, higher cost)",IF(AND(C9<=0,F9<=0),"No deaths averted; ratio not defined","USD per death averted"))) | I9: =IF(AND(ABS(F9-SUMIFS('Budget_Impact'!$F$2:$F$209,'Budget_Impact'!$A$2:$A$209,A9))<='Calculation_Assumptions'!$B$11,ABS(C9-SUMIFS('Annual_Mortality'!$H$2:$H$1639,'Annual_Mortality'!$A$2:$A$1639,A9))<='Calculation_Assumptions'!$B$11),"consistent","mismatch") | J9: =IFERROR(AVERAGEIFS('Budget_Impact'!$L$2:$L$209,'Budget_Impact'!$A$2:$A$209,A9,'Budget_Impact'!$B$2:$B$209,">="&('Calculation_Assumptions'!$B$2+1)),"") | K9: =IFERROR(AVERAGEIFS('Budget_Impact'!$M$2:$M$209,'Budget_Impact'!$A$2:$A$209,A9,'Budget_Impact'!$B$2:$B$209,">="&('Calculation_Assumptions'!$B$2+1)),"")

Sheet Economic_Value
A1: scenario | B1: scenario_label | C1: year | D1: deaths_averted | E1: life_years_gained | F1: gni_pc_idn | G1: gni_pc_usa | H1: population | I1: le_avg_adult | J1: vsl_transfer_prefloor | K1: vsl_floor | L1: vsl_preferred | M1: vsl_over_gnipc | N1: vsl_gni100 | O1: vsl_gni160 | P1: vsly_preferred | Q1: econ_value_vsl_undisc | R1: econ_value_vsly_undisc | S1: econ_value_vsl100_undisc | T1: econ_value_vsl160_undisc | U1: disc_factor | V1: pv_vsl_pref | W1: pv_vsly_pref | X1: pv_vsl100 | Y1: pv_vsl160 | Z1: total_national_gni | AA1: pv_national_gni | AB1: annual_benefit_share_gni
A2: all | B2: All selected interventions (combined) | C2: 2025 | D2: 3689.0157 | E2: 54746.732 | F2: 13851.491 | G2: 74136.371 | H2: 2.8572124e+08 | I2: 37.51 | J2: ='Calculation_Assumptions'!$B$25*G2*(F2/G2)^'Calculation_Assumptions'!$B$26 | K2: ='Calculation_Assumptions'!$B$27*F2 | L2: =MAX(J2,K2) | M2: =IF(F2=0,"",L2/F2) | N2: ='Calculation_Assumptions'!$B$28*F2 | O2: ='Calculation_Assumptions'!$B$29*F2 | P2: =IF(I2=0,"",L2/I2) | Q2: =L2*D2 | R2: =P2*E2 | S2: =N2*D2 | T2: =O2*D2 | U2: =1/(1+'Calculation_Assumptions'!$B$22)^(C2-'Calculation_Assumptions'!$B$21) | V2: =Q2*U2 | W2: =R2*U2 | X2: =S2*U2 | Y2: =T2*U2 | Z2: =H2*F2 | AA2: =Z2*U2 | AB2: =IF(Z2=0,"",Q2/Z2)
A3: all | B3: All selected interventions (combined) | C3: 2026 | D3: 8744.5229 | E3: 127556.64 | F3: 14370.1 | G3: 75186.41 | H3: 2.8788678e+08 | I3: 37.5883 | J3: ='Calculation_Assumptions'!$B$25*G3*(F3/G3)^'Calculation_Assumptions'!$B$26 | K3: ='Calculation_Assumptions'!$B$27*F3 | L3: =MAX(J3,K3) | M3: =IF(F3=0,"",L3/F3) | N3: ='Calculation_Assumptions'!$B$28*F3 | O3: ='Calculation_Assumptions'!$B$29*F3 | P3: =IF(I3=0,"",L3/I3) | Q3: =L3*D3 | R3: =P3*E3 | S3: =N3*D3 | T3: =O3*D3 | U3: =1/(1+'Calculation_Assumptions'!$B$22)^(C3-'Calculation_Assumptions'!$B$21) | V3: =Q3*U3 | W3: =R3*U3 | X3: =S3*U3 | Y3: =T3*U3 | Z3: =H3*F3 | AA3: =Z3*U3 | AB3: =IF(Z3=0,"",Q3/Z3)
A4: all | B4: All selected interventions (combined) | C4: 2027 | D4: 14698.041 | E4: 213634.9 | F4: 14908.127 | G4: 76251.321 | H4: 289986522 | I4: 37.6736 | J4: ='Calculation_Assumptions'!$B$25*G4*(F4/G4)^'Calculation_Assumptions'!$B$26 | K4: ='Calculation_Assumptions'!$B$27*F4 | L4: =MAX(J4,K4) | M4: =IF(F4=0,"",L4/F4) | N4: ='Calculation_Assumptions'!$B$28*F4 | O4: ='Calculation_Assumptions'!$B$29*F4 | P4: =IF(I4=0,"",L4/I4) | Q4: =L4*D4 | R4: =P4*E4 | S4: =N4*D4 | T4: =O4*D4 | U4: =1/(1+'Calculation_Assumptions'!$B$22)^(C4-'Calculation_Assumptions'!$B$21) | V4: =Q4*U4 | W4: =R4*U4 | X4: =S4*U4 | Y4: =T4*U4 | Z4: =H4*F4 | AA4: =Z4*U4 | AB4: =IF(Z4=0,"",Q4/Z4)
A5: all | B5: All selected interventions (combined) | C5: 2028 | D5: 21434.781 | E5: 311201.18 | F5: 15466.297 | G5: 77331.315 | H5: 2.9201678e+08 | I5: 36.834 | J5: ='Calculation_Assumptions'!$B$25*G5*(F5/G5)^'Calculation_Assumptions'!$B$26 | K5: ='Calculation_Assumptions'!$B$27*F5 | L5: =MAX(J5,K5) | M5: =IF(F5=0,"",L5/F5) | N5: ='Calculation_Assumptions'!$B$28*F5 | O5: ='Calculation_Assumptions'!$B$29*F5 | P5: =IF(I5=0,"",L5/I5) | Q5: =L5*D5 | R5: =P5*E5 | S5: =N5*D5 | T5: =O5*D5 | U5: =1/(1+'Calculation_Assumptions'!$B$22)^(C5-'Calculation_Assumptions'!$B$21) | V5: =Q5*U5 | W5: =R5*U5 | X5: =S5*U5 | Y5: =T5*U5 | Z5: =H5*F5 | AA5: =Z5*U5 | AB5: =IF(Z5=0,"",Q5/Z5)
A6: all | B6: All selected interventions (combined) | C6: 2029 | D6: 28937.929 | E6: 419707.3 | F6: 16045.366 | G6: 78426.606 | H6: 293978109 | I6: 36.9118 | J6: ='Calculation_Assumptions'!$B$25*G6*(F6/G6)^'Calculation_Assumptions'!$B$26 | K6: ='Calculation_Assumptions'!$B$27*F6 | L6: =MAX(J6,K6) | M6: =IF(F6=0,"",L6/F6) | N6: ='Calculation_Assumptions'!$B$28*F6 | O6: ='Calculation_Assumptions'!$B$29*F6 | P6: =IF(I6=0,"",L6/I6) | Q6: =L6*D6 | R6: =P6*E6 | S6: =N6*D6 | T6: =O6*D6 | U6: =1/(1+'Calculation_Assumptions'!$B$22)^(C6-'Calculation_Assumptions'!$B$21) | V6: =Q6*U6 | W6: =R6*U6 | X6: =S6*U6 | Y6: =T6*U6 | Z6: =H6*F6 | AA6: =Z6*U6 | AB6: =IF(Z6=0,"",Q6/Z6)
A7: all | B7: All selected interventions (combined) | C7: 2030 | D7: 37090.503 | E7: 537732.72 | F7: 16646.116 | G7: 79537.41 | H7: 295876648 | I7: 36.9927 | J7: ='Calculation_Assumptions'!$B$25*G7*(F7/G7)^'Calculation_Assumptions'!$B$26 | K7: ='Calculation_Assumptions'!$B$27*F7 | L7: =MAX(J7,K7) | M7: =IF(F7=0,"",L7/F7) | N7: ='Calculation_Assumptions'!$B$28*F7 | O7: ='Calculation_Assumptions'!$B$29*F7 | P7: =IF(I7=0,"",L7/I7) | Q7: =L7*D7 | R7: =P7*E7 | S7: =N7*D7 | T7: =O7*D7 | U7: =1/(1+'Calculation_Assumptions'!$B$22)^(C7-'Calculation_Assumptions'!$B$21) | V7: =Q7*U7 | W7: =R7*U7 | X7: =S7*U7 | Y7: =T7*U7 | Z7: =H7*F7 | AA7: =Z7*U7 | AB7: =IF(Z7=0,"",Q7/Z7)
A8: all | B8: All selected interventions (combined) | C8: 2031 | D8: 45763.911 | E8: 663791.39 | F8: 17161.073 | G8: 80420.157 | H8: 297719748 | I8: 37.0895 | J8: ='Calculation_Assumptions'!$B$25*G8*(F8/G8)^'Calculation_Assumptions'!$B$26 | K8: ='Calculation_Assumptions'!$B$27*F8 | L8: =MAX(J8,K8) | M8: =IF(F8=0,"",L8/F8) | N8: ='Calculation_Assumptions'!$B$28*F8 | O8: ='Calculation_Assumptions'!$B$29*F8 | P8: =IF(I8=0,"",L8/I8) | Q8: =L8*D8 | R8: =P8*E8 | S8: =N8*D8 | T8: =O8*D8 | U8: =1/(1+'Calculation_Assumptions'!$B$22)^(C8-'Calculation_Assumptions'!$B$21) | V8: =Q8*U8 | W8: =R8*U8 | X8: =S8*U8 | Y8: =T8*U8 | Z8: =H8*F8 | AA8: =Z8*U8 | AB8: =IF(Z8=0,"",Q8/Z8)
A9: all | B9: All selected interventions (combined) | C9: 2032 | D9: 54946.759 | E9: 797091.83 | F9: 17691.962 | G9: 81312.7 | H9: 2.9951066e+08 | I9: 37.1904 | J9: ='Calculation_Assumptions'!$B$25*G9*(F9/G9)^'Calculation_Assumptions'!$B$26 | K9: ='Calculation_Assumptions'!$B$27*F9 | L9: =MAX(J9,K9) | M9: =IF(F9=0,"",L9/F9) | N9: ='Calculation_Assumptions'!$B$28*F9 | O9: ='Calculation_Assumptions'!$B$29*F9 | P9: =IF(I9=0,"",L9/I9) | Q9: =L9*D9 | R9: =P9*E9 | S9: =N9*D9 | T9: =O9*D9 | U9: =1/(1+'Calculation_Assumptions'!$B$22)^(C9-'Calculation_Assumptions'!$B$21) | V9: =Q9*U9 | W9: =R9*U9 | X9: =S9*U9 | Y9: =T9*U9 | Z9: =H9*F9 | AA9: =Z9*U9 | AB9: =IF(Z9=0,"",Q9/Z9)
A10: all | B10: All selected interventions (combined) | C10: 2033 | D10: 64573.523 | E10: 936719.56 | F10: 18239.273 | G10: 82215.15 | H10: 3.0125098e+08 | I10: 37.2975 | J10: ='Calculation_Assumptions'!$B$25*G10*(F10/G10)^'Calculation_Assumptions'!$B$26 | K10: ='Calculation_Assumptions'!$B$27*F10 | L10: =MAX(J10,K10) | M10: =IF(F10=0,"",L10/F10) | N10: ='Calculation_Assumptions'!$B$28*F10 | O10: ='Calculation_Assumptions'!$B$29*F10 | P10: =IF(I10=0,"",L10/I10) | Q10: =L10*D10 | R10: =P10*E10 | S10: =N10*D10 | T10: =O10*D10 | U10: =1/(1+'Calculation_Assumptions'!$B$22)^(C10-'Calculation_Assumptions'!$B$21) | V10: =Q10*U10 | W10: =R10*U10 | X10: =S10*U10 | Y10: =T10*U10 | Z10: =H10*F10 | AA10: =Z10*U10 | AB10: =IF(Z10=0,"",Q10/Z10)
A11: all | B11: All selected interventions (combined) | C11: 2034 | D11: 74641.761 | E11: 1083752.8 | F11: 18803.516 | G11: 83127.615 | H11: 302938573 | I11: 37.4064 | J11: ='Calculation_Assumptions'!$B$25*G11*(F11/G11)^'Calculation_Assumptions'!$B$26 | K11: ='Calculation_Assumptions'!$B$27*F11 | L11: =MAX(J11,K11) | M11: =IF(F11=0,"",L11/F11) | N11: ='Calculation_Assumptions'!$B$28*F11 | O11: ='Calculation_Assumptions'!$B$29*F11 | P11: =IF(I11=0,"",L11/I11) | Q11: =L11*D11 | R11: =P11*E11 | S11: =N11*D11 | T11: =O11*D11 | U11: =1/(1+'Calculation_Assumptions'!$B$22)^(C11-'Calculation_Assumptions'!$B$21) | V11: =Q11*U11 | W11: =R11*U11 | X11: =S11*U11 | Y11: =T11*U11 | Z11: =H11*F11 | AA11: =Z11*U11 | AB11: =IF(Z11=0,"",Q11/Z11)
A12: all | B12: All selected interventions (combined) | C12: 2035 | D12: 85127.326 | E12: 1236802.1 | F12: 19385.215 | G12: 84050.207 | H12: 304566622 | I12: 37.5179 | J12: ='Calculation_Assumptions'!$B$25*G12*(F12/G12)^'Calculation_Assumptions'!$B$26 | K12: ='Calculation_Assumptions'!$B$27*F12 | L12: =MAX(J12,K12) | M12: =IF(F12=0,"",L12/F12) | N12: ='Calculation_Assumptions'!$B$28*F12 | O12: ='Calculation_Assumptions'!$B$29*F12 | P12: =IF(I12=0,"",L12/I12) | Q12: =L12*D12 | R12: =P12*E12 | S12: =N12*D12 | T12: =O12*D12 | U12: =1/(1+'Calculation_Assumptions'!$B$22)^(C12-'Calculation_Assumptions'!$B$21) | V12: =Q12*U12 | W12: =R12*U12 | X12: =S12*U12 | Y12: =T12*U12 | Z12: =H12*F12 | AA12: =Z12*U12 | AB12: =IF(Z12=0,"",Q12/Z12)
A13: all | B13: All selected interventions (combined) | C13: 2036 | D13: 96011.962 | E13: 1395337.7 | F13: 19931.358 | G13: 84847.857 | H13: 306135098 | I13: 37.6267 | J13: ='Calculation_Assumptions'!$B$25*G13*(F13/G13)^'Calculation_Assumptions'!$B$26 | K13: ='Calculation_Assumptions'!$B$27*F13 | L13: =MAX(J13,K13) | M13: =IF(F13=0,"",L13/F13) | N13: ='Calculation_Assumptions'!$B$28*F13 | O13: ='Calculation_Assumptions'!$B$29*F13 | P13: =IF(I13=0,"",L13/I13) | Q13: =L13*D13 | R13: =P13*E13 | S13: =N13*D13 | T13: =O13*D13 | U13: =1/(1+'Calculation_Assumptions'!$B$22)^(C13-'Calculation_Assumptions'!$B$21) | V13: =Q13*U13 | W13: =R13*U13 | X13: =S13*U13 | Y13: =T13*U13 | Z13: =H13*F13 | AA13: =Z13*U13 | AB13: =IF(Z13=0,"",Q13/Z13)
... A209: I_T2D_TREATMENT | B209: Longitudinal treatment of type 2 diabetes | C209: 2050 | D209: 40837.341 | E209: 529243.43 | F209: 28211.06 | G209: 95832.888 | H209: 3.2071295e+08 | I209: 38.286 | J209: ='Calculation_Assumptions'!$B$25*G209*(F209/G209)^'Calculation_Assumptions'!$B$26 | K209: ='Calculation_Assumptions'!$B$27*F209 | L209: =MAX(J209,K209) | M209: =IF(F209=0,"",L209/F209) | N209: ='Calculation_Assumptions'!$B$28*F209 | O209: ='Calculation_Assumptions'!$B$29*F209 | P209: =IF(I209=0,"",L209/I209) | Q209: =L209*D209 | R209: =P209*E209 | S209: =N209*D209 | T209: =O209*D209 | U209: =1/(1+'Calculation_Assumptions'!$B$22)^(C209-'Calculation_Assumptions'!$B$21) | V209: =Q209*U209 | W209: =R209*U209 | X209: =S209*U209 | Y209: =T209*U209 | Z209: =H209*F209 | AA209: =Z209*U209 | AB209: =IF(Z209=0,"",Q209/Z209)

Sheet Benefit_Cost
A1: scenario | B1: scenario_label | C1: intervention_family | D1: scenario_level | E1: valuation_method | F1: valuation_case | G1: pv_benefits | H1: pv_costs | I1: pv_net_benefit | J1: benefit_cost_ratio | K1: pv_national_gni | L1: benefit_gni_share | M1: decision | N1: scope_note
A2: I_CVD_PRIMARY | B2: Primary prevention of CVD | C2: clinical | D2: standalone | E2: VSL | F2: preferred (elasticity 1.5, 20x floor) | G2: =SUMIFS('Economic_Value'!$V$2:$V$209,'Economic_Value'!$A$2:$A$209,A2) | H2: =SUMPRODUCT(('Budget_Impact'!$A$2:$A$209=A2)*'Budget_Impact'!$E$2:$E$209*(1/(1+'Calculation_Assumptions'!$B$22)^('Budget_Impact'!$B$2:$B$209-'Calculation_Assumptions'!$B$21)))*'Calculation_Assumptions'!$B$34 | I2: =G2-H2 | J2: =IF(H2>0,G2/H2,"") | K2: =SUMIFS('Economic_Value'!$AA$2:$AA$209,'Economic_Value'!$A$2:$A$209,A2) | L2: =IF(K2=0,"",G2/K2) | M2: =IF(H2<=0,"cost-saving or ratio not meaningful (PV cost<=0)",IF(J2>=1,"benefits exceed costs (BCR>=1)","costs exceed benefits (BCR<1)")) | N2: Partial mortality-benefit BCA (preferred (elasticity 1.5, 20x floor)). Benefits = averted-mortality VSL/VSLY in PPP int$; costs = implementation/health-system converted to PPP int$ (market USD x cost_to_bca_currency_factor). Omits morbidity, productivity and downstream cost offsets.
A3: I_CVD_PRIMARY | B3: Primary prevention of CVD | C3: clinical | D3: standalone | E3: VSLY | F3: preferred (VSLY from preferred VSL) | G3: =SUMIFS('Economic_Value'!$W$2:$W$209,'Economic_Value'!$A$2:$A$209,A3) | H3: =SUMPRODUCT(('Budget_Impact'!$A$2:$A$209=A3)*'Budget_Impact'!$E$2:$E$209*(1/(1+'Calculation_Assumptions'!$B$22)^('Budget_Impact'!$B$2:$B$209-'Calculation_Assumptions'!$B$21)))*'Calculation_Assumptions'!$B$34 | I3: =G3-H3 | J3: =IF(H3>0,G3/H3,"") | K3: =SUMIFS('Economic_Value'!$AA$2:$AA$209,'Economic_Value'!$A$2:$A$209,A3) | L3: =IF(K3=0,"",G3/K3) | M3: =IF(H3<=0,"cost-saving or ratio not meaningful (PV cost<=0)",IF(J3>=1,"benefits exceed costs (BCR>=1)","costs exceed benefits (BCR<1)")) | N3: Partial mortality-benefit BCA (preferred (elasticity 1.5, 20x floor)). Benefits = averted-mortality VSL/VSLY in PPP int$; costs = implementation/health-system converted to PPP int$ (market USD x cost_to_bca_currency_factor). Omits morbidity, productivity and downstream cost offsets.
A4: I_CVD_PRIMARY | B4: Primary prevention of CVD | C4: clinical | D4: standalone | E4: VSL | F4: sensitivity: 100x GNI per capita | G4: =SUMIFS('Economic_Value'!$X$2:$X$209,'Economic_Value'!$A$2:$A$209,A4) | H4: =SUMPRODUCT(('Budget_Impact'!$A$2:$A$209=A4)*'Budget_Impact'!$E$2:$E$209*(1/(1+'Calculation_Assumptions'!$B$22)^('Budget_Impact'!$B$2:$B$209-'Calculation_Assumptions'!$B$21)))*'Calculation_Assumptions'!$B$34 | I4: =G4-H4 | J4: =IF(H4>0,G4/H4,"") | K4: =SUMIFS('Economic_Value'!$AA$2:$AA$209,'Economic_Value'!$A$2:$A$209,A4) | L4: =IF(K4=0,"",G4/K4) | M4: =IF(H4<=0,"cost-saving or ratio not meaningful (PV cost<=0)",IF(J4>=1,"benefits exceed costs (BCR>=1)","costs exceed benefits (BCR<1)")) | N4: Partial mortality-benefit BCA (preferred (elasticity 1.5, 20x floor)). Benefits = averted-mortality VSL/VSLY in PPP int$; costs = implementation/health-system converted to PPP int$ (market USD x cost_to_bca_currency_factor). Omits morbidity, productivity and downstream cost offsets.
A5: I_CVD_PRIMARY | B5: Primary prevention of CVD | C5: clinical | D5: standalone | E5: VSL | F5: sensitivity: 160x GNI per capita | G5: =SUMIFS('Economic_Value'!$Y$2:$Y$209,'Economic_Value'!$A$2:$A$209,A5) | H5: =SUMPRODUCT(('Budget_Impact'!$A$2:$A$209=A5)*'Budget_Impact'!$E$2:$E$209*(1/(1+'Calculation_Assumptions'!$B$22)^('Budget_Impact'!$B$2:$B$209-'Calculation_Assumptions'!$B$21)))*'Calculation_Assumptions'!$B$34 | I5: =G5-H5 | J5: =IF(H5>0,G5/H5,"") | K5: =SUMIFS('Economic_Value'!$AA$2:$AA$209,'Economic_Value'!$A$2:$A$209,A5) | L5: =IF(K5=0,"",G5/K5) | M5: =IF(H5<=0,"cost-saving or ratio not meaningful (PV cost<=0)",IF(J5>=1,"benefits exceed costs (BCR>=1)","costs exceed benefits (BCR<1)")) | N5: Partial mortality-benefit BCA (preferred (elasticity 1.5, 20x floor)). Benefits = averted-mortality VSL/VSLY in PPP int$; costs = implementation/health-system converted to PPP int$ (market USD x cost_to_bca_currency_factor). Omits morbidity, productivity and downstream cost offsets.
A6: I_HF_ACUTE | B6: Acute heart-failure management | C6: clinical | D6: standalone | E6: VSL | F6: preferred (elasticity 1.5, 20x floor) | G6: =SUMIFS('Economic_Value'!$V$2:$V$209,'Economic_Value'!$A$2:$A$209,A6) | H6: =SUMPRODUCT(('Budget_Impact'!$A$2:$A$209=A6)*'Budget_Impact'!$E$2:$E$209*(1/(1+'Calculation_Assumptions'!$B$22)^('Budget_Impact'!$B$2:$B$209-'Calculation_Assumptions'!$B$21)))*'Calculation_Assumptions'!$B$34 | I6: =G6-H6 | J6: =IF(H6>0,G6/H6,"") | K6: =SUMIFS('Economic_Value'!$AA$2:$AA$209,'Economic_Value'!$A$2:$A$209,A6) | L6: =IF(K6=0,"",G6/K6) | M6: =IF(H6<=0,"cost-saving or ratio not meaningful (PV cost<=0)",IF(J6>=1,"benefits exceed costs (BCR>=1)","costs exceed benefits (BCR<1)")) | N6: Partial mortality-benefit BCA (preferred (elasticity 1.5, 20x floor)). Benefits = averted-mortality VSL/VSLY in PPP int$; costs = implementation/health-system converted to PPP int$ (market USD x cost_to_bca_currency_factor). Omits morbidity, productivity and downstream cost offsets.
A7: I_HF_ACUTE | B7: Acute heart-failure management | C7: clinical | D7: standalone | E7: VSLY | F7: preferred (VSLY from preferred VSL) | G7: =SUMIFS('Economic_Value'!$W$2:$W$209,'Economic_Value'!$A$2:$A$209,A7) | H7: =SUMPRODUCT(('Budget_Impact'!$A$2:$A$209=A7)*'Budget_Impact'!$E$2:$E$209*(1/(1+'Calculation_Assumptions'!$B$22)^('Budget_Impact'!$B$2:$B$209-'Calculation_Assumptions'!$B$21)))*'Calculation_Assumptions'!$B$34 | I7: =G7-H7 | J7: =IF(H7>0,G7/H7,"") | K7: =SUMIFS('Economic_Value'!$AA$2:$AA$209,'Economic_Value'!$A$2:$A$209,A7) | L7: =IF(K7=0,"",G7/K7) | M7: =IF(H7<=0,"cost-saving or ratio not meaningful (PV cost<=0)",IF(J7>=1,"benefits exceed costs (BCR>=1)","costs exceed benefits (BCR<1)")) | N7: Partial mortality-benefit BCA (preferred (elasticity 1.5, 20x floor)). Benefits = averted-mortality VSL/VSLY in PPP int$; costs = implementation/health-system converted to PPP int$ (market USD x cost_to_bca_currency_factor). Omits morbidity, productivity and downstream cost offsets.
A8: I_HF_ACUTE | B8: Acute heart-failure management | C8: clinical | D8: standalone | E8: VSL | F8: sensitivity: 100x GNI per capita | G8: =SUMIFS('Economic_Value'!$X$2:$X$209,'Economic_Value'!$A$2:$A$209,A8) | H8: =SUMPRODUCT(('Budget_Impact'!$A$2:$A$209=A8)*'Budget_Impact'!$E$2:$E$209*(1/(1+'Calculation_Assumptions'!$B$22)^('Budget_Impact'!$B$2:$B$209-'Calculation_Assumptions'!$B$21)))*'Calculation_Assumptions'!$B$34 | I8: =G8-H8 | J8: =IF(H8>0,G8/H8,"") | K8: =SUMIFS('Economic_Value'!$AA$2:$AA$209,'Economic_Value'!$A$2:$A$209,A8) | L8: =IF(K8=0,"",G8/K8) | M8: =IF(H8<=0,"cost-saving or ratio not meaningful (PV cost<=0)",IF(J8>=1,"benefits exceed costs (BCR>=1)","costs exceed benefits (BCR<1)")) | N8: Partial mortality-benefit BCA (preferred (elasticity 1.5, 20x floor)). Benefits = averted-mortality VSL/VSLY in PPP int$; costs = implementation/health-system converted to PPP int$ (market USD x cost_to_bca_currency_factor). Omits morbidity, productivity and downstream cost offsets.
A9: I_HF_ACUTE | B9: Acute heart-failure management | C9: clinical | D9: standalone | E9: VSL | F9: sensitivity: 160x GNI per capita | G9: =SUMIFS('Economic_Value'!$Y$2:$Y$209,'Economic_Value'!$A$2:$A$209,A9) | H9: =SUMPRODUCT(('Budget_Impact'!$A$2:$A$209=A9)*'Budget_Impact'!$E$2:$E$209*(1/(1+'Calculation_Assumptions'!$B$22)^('Budget_Impact'!$B$2:$B$209-'Calculation_Assumptions'!$B$21)))*'Calculation_Assumptions'!$B$34 | I9: =G9-H9 | J9: =IF(H9>0,G9/H9,"") | K9: =SUMIFS('Economic_Value'!$AA$2:$AA$209,'Economic_Value'!$A$2:$A$209,A9) | L9: =IF(K9=0,"",G9/K9) | M9: =IF(H9<=0,"cost-saving or ratio not meaningful (PV cost<=0)",IF(J9>=1,"benefits exceed costs (BCR>=1)","costs exceed benefits (BCR<1)")) | N9: Partial mortality-benefit BCA (preferred (elasticity 1.5, 20x floor)). Benefits = averted-mortality VSL/VSLY in PPP int$; costs = implementation/health-system converted to PPP int$ (market USD x cost_to_bca_currency_factor). Omits morbidity, productivity and downstream cost offsets.
A10: I_HF_CHRONIC | B10: Chronic heart-failure management | C10: clinical | D10: standalone | E10: VSL | F10: preferred (elasticity 1.5, 20x floor) | G10: =SUMIFS('Economic_Value'!$V$2:$V$209,'Economic_Value'!$A$2:$A$209,A10) | H10: =SUMPRODUCT(('Budget_Impact'!$A$2:$A$209=A10)*'Budget_Impact'!$E$2:$E$209*(1/(1+'Calculation_Assumptions'!$B$22)^('Budget_Impact'!$B$2:$B$209-'Calculation_Assumptions'!$B$21)))*'Calculation_Assumptions'!$B$34 | I10: =G10-H10 | J10: =IF(H10>0,G10/H10,"") | K10: =SUMIFS('Economic_Value'!$AA$2:$AA$209,'Economic_Value'!$A$2:$A$209,A10) | L10: =IF(K10=0,"",G10/K10) | M10: =IF(H10<=0,"cost-saving or ratio not meaningful (PV cost<=0)",IF(J10>=1,"benefits exceed costs (BCR>=1)","costs exceed benefits (BCR<1)")) | N10: Partial mortality-benefit BCA (preferred (elasticity 1.5, 20x floor)). Benefits = averted-mortality VSL/VSLY in PPP int$; costs = implementation/health-system converted to PPP int$ (market USD x cost_to_bca_currency_factor). Omits morbidity, productivity and downstream cost offsets.
A11: I_HF_CHRONIC | B11: Chronic heart-failure management | C11: clinical | D11: standalone | E11: VSLY | F11: preferred (VSLY from preferred VSL) | G11: =SUMIFS('Economic_Value'!$W$2:$W$209,'Economic_Value'!$A$2:$A$209,A11) | H11: =SUMPRODUCT(('Budget_Impact'!$A$2:$A$209=A11)*'Budget_Impact'!$E$2:$E$209*(1/(1+'Calculation_Assumptions'!$B$22)^('Budget_Impact'!$B$2:$B$209-'Calculation_Assumptions'!$B$21)))*'Calculation_Assumptions'!$B$34 | I11: =G11-H11 | J11: =IF(H11>0,G11/H11,"") | K11: =SUMIFS('Economic_Value'!$AA$2:$AA$209,'Economic_Value'!$A$2:$A$209,A11) | L11: =IF(K11=0,"",G11/K11) | M11: =IF(H11<=0,"cost-saving or ratio not meaningful (PV cost<=0)",IF(J11>=1,"benefits exceed costs (BCR>=1)","costs exceed benefits (BCR<1)")) | N11: Partial mortality-benefit BCA (preferred (elasticity 1.5, 20x floor)). Benefits = averted-mortality VSL/VSLY in PPP int$; costs = implementation/health-system converted to PPP int$ (market USD x cost_to_bca_currency_factor). Omits morbidity, productivity and downstream cost offsets.
A12: I_HF_CHRONIC | B12: Chronic heart-failure management | C12: clinical | D12: standalone | E12: VSL | F12: sensitivity: 100x GNI per capita | G12: =SUMIFS('Economic_Value'!$X$2:$X$209,'Economic_Value'!$A$2:$A$209,A12) | H12: =SUMPRODUCT(('Budget_Impact'!$A$2:$A$209=A12)*'Budget_Impact'!$E$2:$E$209*(1/(1+'Calculation_Assumptions'!$B$22)^('Budget_Impact'!$B$2:$B$209-'Calculation_Assumptions'!$B$21)))*'Calculation_Assumptions'!$B$34 | I12: =G12-H12 | J12: =IF(H12>0,G12/H12,"") | K12: =SUMIFS('Economic_Value'!$AA$2:$AA$209,'Economic_Value'!$A$2:$A$209,A12) | L12: =IF(K12=0,"",G12/K12) | M12: =IF(H12<=0,"cost-saving or ratio not meaningful (PV cost<=0)",IF(J12>=1,"benefits exceed costs (BCR>=1)","costs exceed benefits (BCR<1)")) | N12: Partial mortality-benefit BCA (preferred (elasticity 1.5, 20x floor)). Benefits = averted-mortality VSL/VSLY in PPP int$; costs = implementation/health-system converted to PPP int$ (market USD x cost_to_bca_currency_factor). Omits morbidity, productivity and downstream cost offsets.
A13: I_HF_CHRONIC | B13: Chronic heart-failure management | C13: clinical | D13: standalone | E13: VSL | F13: sensitivity: 160x GNI per capita | G13: =SUMIFS('Economic_Value'!$Y$2:$Y$209,'Economic_Value'!$A$2:$A$209,A13) | H13: =SUMPRODUCT(('Budget_Impact'!$A$2:$A$209=A13)*'Budget_Impact'!$E$2:$E$209*(1/(1+'Calculation_Assumptions'!$B$22)^('Budget_Impact'!$B$2:$B$209-'Calculation_Assumptions'!$B$21)))*'Calculation_Assumptions'!$B$34 | I13: =G13-H13 | J13: =IF(H13>0,G13/H13,"") | K13: =SUMIFS('Economic_Value'!$AA$2:$AA$209,'Economic_Value'!$A$2:$A$209,A13) | L13: =IF(K13=0,"",G13/K13) | M13: =IF(H13<=0,"cost-saving or ratio not meaningful (PV cost<=0)",IF(J13>=1,"benefits exceed costs (BCR>=1)","costs exceed benefits (BCR<1)")) | N13: Partial mortality-benefit BCA (preferred (elasticity 1.5, 20x floor)). Benefits = averted-mortality VSL/VSLY in PPP int$; costs = implementation/health-system converted to PPP int$ (market USD x cost_to_bca_currency_factor). Omits morbidity, productivity and downstream cost offsets.
A14: I_IHD_ACUTE | B14: Treatment of acute coronary syndromes | C14: clinical | D14: standalone | E14: VSL | F14: preferred (elasticity 1.5, 20x floor) | G14: =SUMIFS('Economic_Value'!$V$2:$V$209,'Economic_Value'!$A$2:$A$209,A14) | H14: =SUMPRODUCT(('Budget_Impact'!$A$2:$A$209=A14)*'Budget_Impact'!$E$2:$E$209*(1/(1+'Calculation_Assumptions'!$B$22)^('Budget_Impact'!$B$2:$B$209-'Calculation_Assumptions'!$B$21)))*'Calculation_Assumptions'!$B$34 | I14: =G14-H14 | J14: =IF(H14>0,G14/H14,"") | K14: =SUMIFS('Economic_Value'!$AA$2:$AA$209,'Economic_Value'!$A$2:$A$209,A14) | L14: =IF(K14=0,"",G14/K14) | M14: =IF(H14<=0,"cost-saving or ratio not meaningful (PV cost<=0)",IF(J14>=1,"benefits exceed costs (BCR>=1)","costs exceed benefits (BCR<1)")) | N14: Partial mortality-benefit BCA (preferred (elasticity 1.5, 20x floor)). Benefits = averted-mortality VSL/VSLY in PPP int$; costs = implementation/health-system converted to PPP int$ (market USD x cost_to_bca_currency_factor). Omits morbidity, productivity and downstream cost offsets.
A15: I_IHD_ACUTE | B15: Treatment of acute coronary syndromes | C15: clinical | D15: standalone | E15: VSLY | F15: preferred (VSLY from preferred VSL) | G15: =SUMIFS('Economic_Value'!$W$2:$W$209,'Economic_Value'!$A$2:$A$209,A15) | H15: =SUMPRODUCT(('Budget_Impact'!$A$2:$A$209=A15)*'Budget_Impact'!$E$2:$E$209*(1/(1+'Calculation_Assumptions'!$B$22)^('Budget_Impact'!$B$2:$B$209-'Calculation_Assumptions'!$B$21)))*'Calculation_Assumptions'!$B$34 | I15: =G15-H15 | J15: =IF(H15>0,G15/H15,"") | K15: =SUMIFS('Economic_Value'!$AA$2:$AA$209,'Economic_Value'!$A$2:$A$209,A15) | L15: =IF(K15=0,"",G15/K15) | M15: =IF(H15<=0,"cost-saving or ratio not meaningful (PV cost<=0)",IF(J15>=1,"benefits exceed costs (BCR>=1)","costs exceed benefits (BCR<1)")) | N15: Partial mortality-benefit BCA (preferred (elasticity 1.5, 20x floor)). Benefits = averted-mortality VSL/VSLY in PPP int$; costs = implementation/health-system converted to PPP int$ (market USD x cost_to_bca_currency_factor). Omits morbidity, productivity and downstream cost offsets.
A16: I_IHD_ACUTE | B16: Treatment of acute coronary syndromes | C16: clinical | D16: standalone | E16: VSL | F16: sensitivity: 100x GNI per capita | G16: =SUMIFS('Economic_Value'!$X$2:$X$209,'Economic_Value'!$A$2:$A$209,A16) | H16: =SUMPRODUCT(('Budget_Impact'!$A$2:$A$209=A16)*'Budget_Impact'!$E$2:$E$209*(1/(1+'Calculation_Assumptions'!$B$22)^('Budget_Impact'!$B$2:$B$209-'Calculation_Assumptions'!$B$21)))*'Calculation_Assumptions'!$B$34 | I16: =G16-H16 | J16: =IF(H16>0,G16/H16,"") | K16: =SUMIFS('Economic_Value'!$AA$2:$AA$209,'Economic_Value'!$A$2:$A$209,A16) | L16: =IF(K16=0,"",G16/K16) | M16: =IF(H16<=0,"cost-saving or ratio not meaningful (PV cost<=0)",IF(J16>=1,"benefits exceed costs (BCR>=1)","costs exceed benefits (BCR<1)")) | N16: Partial mortality-benefit BCA (preferred (elasticity 1.5, 20x floor)). Benefits = averted-mortality VSL/VSLY in PPP int$; costs = implementation/health-system converted to PPP int$ (market USD x cost_to_bca_currency_factor). Omits morbidity, productivity and downstream cost offsets.
A17: I_IHD_ACUTE | B17: Treatment of acute coronary syndromes | C17: clinical | D17: standalone | E17: VSL | F17: sensitivity: 160x GNI per capita | G17: =SUMIFS('Economic_Value'!$Y$2:$Y$209,'Economic_Value'!$A$2:$A$209,A17) | H17: =SUMPRODUCT(('Budget_Impact'!$A$2:$A$209=A17)*'Budget_Impact'!$E$2:$E$209*(1/(1+'Calculation_Assumptions'!$B$22)^('Budget_Impact'!$B$2:$B$209-'Calculation_Assumptions'!$B$21)))*'Calculation_Assumptions'!$B$34 | I17: =G17-H17 | J17: =IF(H17>0,G17/H17,"") | K17: =SUMIFS('Economic_Value'!$AA$2:$AA$209,'Economic_Value'!$A$2:$A$209,A17) | L17: =IF(K17=0,"",G17/K17) | M17: =IF(H17<=0,"cost-saving or ratio not meaningful (PV cost<=0)",IF(J17>=1,"benefits exceed costs (BCR>=1)","costs exceed benefits (BCR<1)")) | N17: Partial mortality-benefit BCA (preferred (elasticity 1.5, 20x floor)). Benefits = averted-mortality VSL/VSLY in PPP int$; costs = implementation/health-system converted to PPP int$ (market USD x cost_to_bca_currency_factor). Omits morbidity, productivity and downstream cost offsets.
