Workbook

Sheet README
A1: Indonesia NCD - public-health cost & value workbook (formula edition)
A3: section | B3: detail
A4: Purpose | B4: Costing, budget impact and mortality-based cost-effectiveness for the public-health (fiscal/regulatory) policies selected in the public-health input workbook.
A5: How to read | B5: Grey cells are R-generated source values; light-blue cells are LIVE Excel formulas; pale-yellow cells on Calculation_Assumptions are editable controls. Change a yellow control and the blue results recompute. Calculation_Map lists the dependency chain.
A6: Scenarios | B6: Baseline + one standalone scenario per runnable intervention + one JOINT scenario per parent package (tobacco, salt) + a combined 'all_public_health' scenario. Membership and the tobacco/salt package structure derive from the workbook Scenario_Hierarchy (Model 04). Parent-package cases/deaths come from a single joint run, never summed from standalone children; package cost = sum of selected child costs. See Scenario_Hierarchy, Child_Intervention_Summary and Parent_Package_Summary.
A7: Baseline pairing | B7: Deaths averted = baseline deaths - scenario deaths, matched at year x cause (both-sex totals).
A8: Effect model | B8: Incidence effect = exposure-based: prevalence-shift RR (tobacco), log-linear RR per unit reduction (alcohol/sodium/SSB and the DEFAULT industrial-TFA path, RR per 1 percentage-point energy). The optional TFA PAF path (PAF x implementation gap) is used only when Assumptions.tfa_effect_method='PAF'. Fiscal levers use baseline->target tax change x price elasticity; regulatory levers use the none/partial/full implementation gap. NO clinical coverage-adjustment formula is used.
A9: Exposure path | B9: Achieved exposure pt(t) ramps linearly baseline->target over start_year..target_year, floored; exposure reductions are shown as formulas on Exposure_Targets.
A10: Lag | B10: immediate_after_full_implementation: effect tracks the exposure path. delayed_exponential_remaining_effect (tobacco): full target effect accrues as 1-(1-rate)^(years since start).
A11: Costing | B11: annual_cost = population(t) x PIN fraction x implementation_fraction(t) x frequency x unit_cost. Public-wide policies use the deduplicated total population (once per age/sex/year, never per cause).
A12: Shared costs | B12: Shared policy costs (cost_scope 'shared-count-once', ...__C_SHARED) are counted once per intervention/scenario/year, never once per affected cause.
A13: Budget impact | B13: Budget impact reports UNDISCOUNTED baseline, scenario, incremental and cumulative incremental cost; discounted incremental cost is a separate column.
A14: Cost-effectiveness | B14: USD per death averted = cumulative discounted incremental cost / cumulative (undiscounted) deaths averted. Not a DALY-based ICER; DALYs are deferred.
... A18: Deferred | B18: DALYs/YLL/YLD/disability weights are deferred; the principal cost-effectiveness result is USD per death averted.

Sheet Run_Metadata
A1: item | B1: value
A2: Workbook title | B2: Indonesia NCD public-health - cost & value
A3: Run date | B3: 2026-08-21
A4: Model / pipeline | B4: CVD FAIR Choices pipeline (Models 00-06 -> 09), public-health family
A5: Public-health input workbook | B5: C:/Users/wrgar/OneDrive - UW/02Work/WorldBank-Indonesia/uw-wb-indonesia-ncd/data/indonesia_model_inputs_public_health_updated.xlsx
A6: Model output source | B6: output/out_model/model_output_*.rds (Model 06)
A7: Location | B7: Indonesia
A8: Analysis years | B8: =Calculation_Assumptions!$B$2&"-"&Calculation_Assumptions!$B$3 -> 2025-2050
A9: Baseline scenario | B9: =Calculation_Assumptions!$B$4 -> baseline
A10: Scenarios costed | B10: I_PH_TOBACCO_TAX, I_PH_ALCOHOL_TAX, I_PH_TOB_CLEAN_AIR, I_PH_TOB_MEDIA, I_PH_TOB_AD_BAN, I_PH_ALCOHOL_POLICY, I_PH_SALT_REFORM, I_PH_SALT_FOPL, I_PH_SALT_MEDIA, I_PH_SALT_ENV, I_PH_TFA_POLICY, I_PH_SSB_TAX, I_PH_TOBACCO_POLICY, I_PH_SALT_POLICY, all_public_health
A11: Cost discount rate | B11: =Calculation_Assumptions!$B$8 -> 0.03
A12: Reporting price year | B12: 2023
A13: Currency | B13: USD
A14: Economic perspective | B14: health_system
A15: Policy start / target year | B15: 2026 / 2030
A16: Cost ramp years | B16: 3
A17: Health outcomes (DALYs/YLL/YLD) | B17: Out of scope in this stage (deferred)
A18: R version | B18: R version 4.5.1 (2025-06-13 ucrt)
A19: openxlsx / data.table | B19: 4.2.8 / 1.17.8
A20: TFA effect method | B20: RR
A21: Public-health scenarios (n) | B21: 15 comparators + baseline

Sheet Scenario_Hierarchy
A1: parent_scenario_id | B1: parent_scenario_name | C1: intervention_id | D1: intervention_name | E1: package_group | F1: scenario_role | G1: include_in_parent_scenario | H1: standalone_scenario_id | I1: parent_aggregation_rule | J1: outcome_reporting_rule | K1: cost_reporting_rule | L1: component_order | M1: source_note | N1: is_runnable | O1: is_parent_package
A2: I_PH_TOBACCO_TAX | B2: Tobacco tax | C2: I_PH_TOBACCO_TAX | D2: Tobacco tax | E2: Tobacco | F2: standalone | G2: 1 | H2: I_PH_TOBACCO_TAX | I2: single intervention | J2: report intervention | K2: report intervention cost | L2: 1 | M2: Fiscal | N2: TRUE | O2: FALSE
A3: I_PH_ALCOHOL_TAX | B3: Alcohol tax | C3: I_PH_ALCOHOL_TAX | D3: Alcohol tax | E3: Alcohol | F3: standalone | G3: 1 | H3: I_PH_ALCOHOL_TAX | I3: single intervention | J3: report intervention | K3: report intervention cost | L3: 1 | M3: Fiscal | N3: TRUE | O3: FALSE
A4: I_PH_TOBACCO_POLICY | B4: Tobacco policy package | C4: I_PH_TOB_CLEAN_AIR | D4: Smoke-free / clean-air law | E4: Tobacco | F4: child | G4: 1 | H4: I_PH_TOB_CLEAN_AIR | I4: run children jointly | J4: report child and parent | K4: sum child costs; rerun health jointly | L4: 1 | M4: MPOWER | N4: TRUE | O4: FALSE
A5: I_PH_TOBACCO_POLICY | B5: Tobacco policy package | C5: I_PH_TOB_MEDIA | D5: Tobacco mass-media campaign | E5: Tobacco | F5: child | G5: 1 | H5: I_PH_TOB_MEDIA | I5: run children jointly | J5: report child and parent | K5: sum child costs; rerun health jointly | L5: 2 | M5: MPOWER | N5: TRUE | O5: FALSE
A6: I_PH_TOBACCO_POLICY | B6: Tobacco policy package | C6: I_PH_TOB_AD_BAN | D6: Tobacco advertising ban | E6: Tobacco | F6: child | G6: 1 | H6: I_PH_TOB_AD_BAN | I6: run children jointly | J6: report child and parent | K6: sum child costs; rerun health jointly | L6: 3 | M6: MPOWER | N6: TRUE | O6: FALSE
A7: I_PH_ALCOHOL_POLICY | B7: Alcohol advertising policy | C7: I_PH_ALCOHOL_POLICY | D7: Alcohol advertising ban | E7: Alcohol | F7: standalone | G7: 1 | H7: I_PH_ALCOHOL_POLICY | I7: single intervention | J7: report intervention | K7: report intervention cost | L7: 1 | M7: Alcohol policy | N7: TRUE | O7: FALSE
A8: I_PH_SALT_POLICY | B8: Salt policy package | C8: I_PH_SALT_REFORM | D8: Mandatory sodium reformulation | E8: Diet | F8: child | G8: 1 | H8: I_PH_SALT_REFORM | I8: run children jointly | J8: report child and parent | K8: sum child costs; rerun health jointly | L8: 1 | M8: SHAKE | N8: TRUE | O8: FALSE
A9: I_PH_SALT_POLICY | B9: Salt policy package | C9: I_PH_SALT_FOPL | D9: Sodium front-of-pack labelling | E9: Diet | F9: child | G9: 1 | H9: I_PH_SALT_FOPL | I9: run children jointly | J9: report child and parent | K9: sum child costs; rerun health jointly | L9: 2 | M9: SHAKE | N9: TRUE | O9: FALSE
A10: I_PH_SALT_POLICY | B10: Salt policy package | C10: I_PH_SALT_MEDIA | D10: Sodium mass-media campaign | E10: Diet | F10: child | G10: 1 | H10: I_PH_SALT_MEDIA | I10: run children jointly | J10: report child and parent | K10: sum child costs; rerun health jointly | L10: 3 | M10: SHAKE | N10: TRUE | O10: FALSE
A11: I_PH_SALT_POLICY | B11: Salt policy package | C11: I_PH_SALT_ENV | D11: Supportive public-institution environment | E11: Diet | F11: child | G11: 1 | H11: I_PH_SALT_ENV | I11: run children jointly | J11: report child and parent | K11: sum child costs; rerun health jointly | L11: 4 | M11: SHAKE | N11: TRUE | O11: FALSE
A12: I_PH_TFA_POLICY | B12: Industrial TFA regulation | C12: I_PH_TFA_POLICY | D12: Industrial trans-fat elimination regulation | E12: Diet | F12: standalone | G12: 1 | H12: I_PH_TFA_POLICY | I12: single intervention | J12: report intervention | K12: report intervention cost | L12: 1 | M12: REPLACE | N12: TRUE | O12: FALSE
A13: I_PH_SSB_TAX | B13: SSB tax | C13: I_PH_SSB_TAX | D13: Sugar-sweetened beverage tax | E13: Diet | F13: standalone | G13: 1 | H13: I_PH_SSB_TAX | I13: single intervention | J13: report intervention | K13: report intervention cost | L13: 1 | M13: Fiscal | N13: TRUE | O13: FALSE

Sheet Selected_Interventions
A1: intervention_id | B1: intervention_cause_key | C1: intervention_name | D1: risk_id | E1: cause_id | F1: cause_code | G1: effect_model | H1: baseline_exposure | I1: target_exposure | J1: response_value | K1: paf_value | L1: lag_model | M1: lag_parameter | N1: exposure_start_year | O1: exposure_target_year | P1: full_effect_at_target | Q1: exposure_reduction_abs | R1: exposure_reduction_rel | S1: cost_join_key | T1: review_status | U1: key_count | V1: formula_status | W1: parent_package_id | X1: intervention_role | Y1: tfa_effect_method
A2: I_PH_ALCOHOL_POLICY | B2: I_PH_ALCOHOL_POLICY__C_CMYO | C2: Alcohol advertising ban | D2: R_ALCOHOL | E2: C_CMYO | F2: cmd | G2: direct_loglinear_rr_per_unit_reduction | H2: 0.1 | I2: 0.08655 | J2: 1.0131617 | L2: immediate_after_full_implementation | M2: 1 | N2: 2026 | O2: 2030 | P2: =1-1/(J2^(H2-I2)) -> 0.00017585416 | Q2: =H2-I2 -> 0.01345 | R2: =IF(H2=0,0,(H2-I2)/H2) -> 0.1345 | S2: I_PH_ALCOHOL_POLICY__C_SHARED | T2: Ready | U2: =COUNTIF($B$2:$B$49,B2) -> 1 | V2: =IF(U2=1,"OK","DUPLICATE KEY") -> OK | W2: I_PH_ALCOHOL_POLICY | X2: standalone | Y2: RR
A3: I_PH_ALCOHOL_POLICY | B3: I_PH_ALCOHOL_POLICY__C_HHD | C3: Alcohol advertising ban | D3: R_ALCOHOL | E3: C_HHD | F3: hhd | G3: direct_loglinear_rr_per_unit_reduction | H3: 0.1 | I3: 0.08655 | J3: 1.0331775 | L3: immediate_after_full_implementation | M3: 1 | N3: 2026 | O3: 2030 | P3: =1-1/(J3^(H3-I3)) -> 0.00043889841 | Q3: =H3-I3 -> 0.01345 | R3: =IF(H3=0,0,(H3-I3)/H3) -> 0.1345 | S3: I_PH_ALCOHOL_POLICY__C_SHARED | T3: Ready | U3: =COUNTIF($B$2:$B$49,B3) -> 1 | V3: =IF(U3=1,"OK","DUPLICATE KEY") -> OK | W3: I_PH_ALCOHOL_POLICY | X3: standalone | Y3: RR
A4: I_PH_ALCOHOL_POLICY | B4: I_PH_ALCOHOL_POLICY__C_ICH | C4: Alcohol advertising ban | D4: R_ALCOHOL | E4: C_ICH | F4: hstroke | G4: direct_loglinear_rr_per_unit_reduction | H4: 0.1 | I4: 0.08655 | J4: 1.02008 | L4: immediate_after_full_implementation | M4: 1 | N4: 2026 | O4: 2030 | P4: =1-1/(J4^(H4-I4)) -> 0.00026736396 | Q4: =H4-I4 -> 0.01345 | R4: =IF(H4=0,0,(H4-I4)/H4) -> 0.1345 | S4: I_PH_ALCOHOL_POLICY__C_SHARED | T4: Ready | U4: =COUNTIF($B$2:$B$49,B4) -> 1 | V4: =IF(U4=1,"OK","DUPLICATE KEY") -> OK | W4: I_PH_ALCOHOL_POLICY | X4: standalone | Y4: RR
A5: I_PH_ALCOHOL_POLICY | B5: I_PH_ALCOHOL_POLICY__C_IHD | C5: Alcohol advertising ban | D5: R_ALCOHOL | E5: C_IHD | F5: ihd | G5: direct_loglinear_rr_per_unit_reduction | H5: 0.1 | I5: 0.08655 | J5: 1.0088804 | L5: immediate_after_full_implementation | M5: 1 | N5: 2026 | O5: 2030 | P5: =1-1/(J5^(H5-I5)) -> 0.00011890689 | Q5: =H5-I5 -> 0.01345 | R5: =IF(H5=0,0,(H5-I5)/H5) -> 0.1345 | S5: I_PH_ALCOHOL_POLICY__C_SHARED | T5: Ready | U5: =COUNTIF($B$2:$B$49,B5) -> 1 | V5: =IF(U5=1,"OK","DUPLICATE KEY") -> OK | W5: I_PH_ALCOHOL_POLICY | X5: standalone | Y5: RR
A6: I_PH_ALCOHOL_POLICY | B6: I_PH_ALCOHOL_POLICY__C_IS | C6: Alcohol advertising ban | D6: R_ALCOHOL | E6: C_IS | F6: istroke | G6: direct_loglinear_rr_per_unit_reduction | H6: 0.1 | I6: 0.08655 | J6: 1.02008 | L6: immediate_after_full_implementation | M6: 1 | N6: 2026 | O6: 2030 | P6: =1-1/(J6^(H6-I6)) -> 0.00026736396 | Q6: =H6-I6 -> 0.01345 | R6: =IF(H6=0,0,(H6-I6)/H6) -> 0.1345 | S6: I_PH_ALCOHOL_POLICY__C_SHARED | T6: Ready | U6: =COUNTIF($B$2:$B$49,B6) -> 1 | V6: =IF(U6=1,"OK","DUPLICATE KEY") -> OK | W6: I_PH_ALCOHOL_POLICY | X6: standalone | Y6: RR
A7: I_PH_ALCOHOL_TAX | B7: I_PH_ALCOHOL_TAX__C_CMYO | C7: Alcohol tax | D7: R_ALCOHOL | E7: C_CMYO | F7: cmd | G7: direct_loglinear_rr_per_unit_reduction | H7: 0.1 | I7: 0.08775 | J7: 1.0131617 | L7: immediate_after_full_implementation | M7: 1 | N7: 2026 | O7: 2030 | P7: =1-1/(J7^(H7-I7)) -> 0.00016016582 | Q7: =H7-I7 -> 0.01225 | R7: =IF(H7=0,0,(H7-I7)/H7) -> 0.1225 | S7: I_PH_ALCOHOL_TAX__C_SHARED | T7: Ready | U7: =COUNTIF($B$2:$B$49,B7) -> 1 | V7: =IF(U7=1,"OK","DUPLICATE KEY") -> OK | W7: I_PH_ALCOHOL_TAX | X7: standalone | Y7: RR
A8: I_PH_ALCOHOL_TAX | B8: I_PH_ALCOHOL_TAX__C_HHD | C8: Alcohol tax | D8: R_ALCOHOL | E8: C_HHD | F8: hhd | G8: direct_loglinear_rr_per_unit_reduction | H8: 0.1 | I8: 0.08775 | J8: 1.0331775 | L8: immediate_after_full_implementation | M8: 1 | N8: 2026 | O8: 2030 | P8: =1-1/(J8^(H8-I8)) -> 0.00039974801 | Q8: =H8-I8 -> 0.01225 | R8: =IF(H8=0,0,(H8-I8)/H8) -> 0.1225 | S8: I_PH_ALCOHOL_TAX__C_SHARED | T8: Ready | U8: =COUNTIF($B$2:$B$49,B8) -> 1 | V8: =IF(U8=1,"OK","DUPLICATE KEY") -> OK | W8: I_PH_ALCOHOL_TAX | X8: standalone | Y8: RR
A9: I_PH_ALCOHOL_TAX | B9: I_PH_ALCOHOL_TAX__C_ICH | C9: Alcohol tax | D9: R_ALCOHOL | E9: C_ICH | F9: hstroke | G9: direct_loglinear_rr_per_unit_reduction | H9: 0.1 | I9: 0.08775 | J9: 1.02008 | L9: immediate_after_full_implementation | M9: 1 | N9: 2026 | O9: 2030 | P9: =1-1/(J9^(H9-I9)) -> 0.00024351283 | Q9: =H9-I9 -> 0.01225 | R9: =IF(H9=0,0,(H9-I9)/H9) -> 0.1225 | S9: I_PH_ALCOHOL_TAX__C_SHARED | T9: Ready | U9: =COUNTIF($B$2:$B$49,B9) -> 1 | V9: =IF(U9=1,"OK","DUPLICATE KEY") -> OK | W9: I_PH_ALCOHOL_TAX | X9: standalone | Y9: RR
A10: I_PH_ALCOHOL_TAX | B10: I_PH_ALCOHOL_TAX__C_IHD | C10: Alcohol tax | D10: R_ALCOHOL | E10: C_IHD | F10: ihd | G10: direct_loglinear_rr_per_unit_reduction | H10: 0.1 | I10: 0.08775 | J10: 1.0088804 | L10: immediate_after_full_implementation | M10: 1 | N10: 2026 | O10: 2030 | P10: =1-1/(J10^(H10-I10)) -> 0.00010829867 | Q10: =H10-I10 -> 0.01225 | R10: =IF(H10=0,0,(H10-I10)/H10) -> 0.1225 | S10: I_PH_ALCOHOL_TAX__C_SHARED | T10: Ready | U10: =COUNTIF($B$2:$B$49,B10) -> 1 | V10: =IF(U10=1,"OK","DUPLICATE KEY") -> OK | W10: I_PH_ALCOHOL_TAX | X10: standalone | Y10: RR
A11: I_PH_ALCOHOL_TAX | B11: I_PH_ALCOHOL_TAX__C_IS | C11: Alcohol tax | D11: R_ALCOHOL | E11: C_IS | F11: istroke | G11: direct_loglinear_rr_per_unit_reduction | H11: 0.1 | I11: 0.08775 | J11: 1.02008 | L11: immediate_after_full_implementation | M11: 1 | N11: 2026 | O11: 2030 | P11: =1-1/(J11^(H11-I11)) -> 0.00024351283 | Q11: =H11-I11 -> 0.01225 | R11: =IF(H11=0,0,(H11-I11)/H11) -> 0.1225 | S11: I_PH_ALCOHOL_TAX__C_SHARED | T11: Ready | U11: =COUNTIF($B$2:$B$49,B11) -> 1 | V11: =IF(U11=1,"OK","DUPLICATE KEY") -> OK | W11: I_PH_ALCOHOL_TAX | X11: standalone | Y11: RR
A12: I_PH_SALT_ENV | B12: I_PH_SALT_ENV__C_HHD | C12: Supportive public-institution environment | D12: R_SODIUM | E12: C_HHD | F12: hhd | G12: direct_loglinear_rr_per_unit_reduction | H12: 4.4 | I12: 4.246 | J12: 1.06 | L12: immediate_after_full_implementation | M12: 1 | N12: 2026 | O12: 2030 | P12: =1-1/(J12^(H12-I12)) -> 0.0089332709 | Q12: =H12-I12 -> 0.154 | R12: =IF(H12=0,0,(H12-I12)/H12) -> 0.035 | S12: I_PH_SALT_ENV__C_SHARED | T12: Ready | U12: =COUNTIF($B$2:$B$49,B12) -> 1 | V12: =IF(U12=1,"OK","DUPLICATE KEY") -> OK | W12: I_PH_SALT_POLICY | X12: child | Y12: RR
A13: I_PH_SALT_ENV | B13: I_PH_SALT_ENV__C_ICH | C13: Supportive public-institution environment | D13: R_SODIUM | E13: C_ICH | F13: hstroke | G13: direct_loglinear_rr_per_unit_reduction | H13: 4.4 | I13: 4.246 | J13: 1.06 | L13: immediate_after_full_implementation | M13: 1 | N13: 2026 | O13: 2030 | P13: =1-1/(J13^(H13-I13)) -> 0.0089332709 | Q13: =H13-I13 -> 0.154 | R13: =IF(H13=0,0,(H13-I13)/H13) -> 0.035 | S13: I_PH_SALT_ENV__C_SHARED | T13: Ready | U13: =COUNTIF($B$2:$B$49,B13) -> 1 | V13: =IF(U13=1,"OK","DUPLICATE KEY") -> OK | W13: I_PH_SALT_POLICY | X13: child | Y13: RR
... A33: I_PH_TFA_POLICY | B33: I_PH_TFA_POLICY__C_IHD | C33: Industrial trans-fat elimination regulation | D33: R_TFA | E33: C_IHD | F33: ihd | G33: direct_loglinear_rr_per_unit_reduction | H33: 0.48 | I33: 0.24 | J33: 1.1 | L33: immediate_after_full_implementation | M33: 1 | N33: 2026 | O33: 2030 | P33: =1-1/(J33^(H33-I33)) -> 0.022614807 | Q33: =H33-I33 -> 0.24 | R33: =IF(H33=0,0,(H33-I33)/H33) -> 0.5 | S33: I_PH_TFA_POLICY__C_SHARED | T33: Ready | U33: =COUNTIF($B$2:$B$49,B33) -> 1 | V33: =IF(U33=1,"OK","DUPLICATE KEY") -> OK | W33: I_PH_TFA_POLICY | X33: standalone | Y33: RR
A34: I_PH_TOBACCO_TAX | B34: I_PH_TOBACCO_TAX__C_T2DM | C34: Tobacco tax | D34: R_SMOKING | E34: C_T2DM | F34: dm2 | G34: direct_smoking_prevalence_shift_rr | H34: 0.303 | I34: 0.1982832 | J34: 1.37 | L34: delayed_exponential_remaining_effect | M34: 0.061514457 | N34: 2026 | O34: 2030 | P34: =1-(1+I34*(J34-1))/(1+H34*(J34-1)) -> 0.034839374 | Q34: =H34-I34 -> 0.1047168 | R34: =IF(H34=0,0,(H34-I34)/H34) -> 0.3456 | S34: I_PH_TOBACCO_TAX__C_SHARED | T34: Ready | U34: =COUNTIF($B$2:$B$49,B34) -> 1 | V34: =IF(U34=1,"OK","DUPLICATE KEY") -> OK | W34: I_PH_TOBACCO_TAX | X34: standalone | Y34: RR
A35: I_PH_TOBACCO_TAX | B35: I_PH_TOBACCO_TAX__C_ICH | C35: Tobacco tax | D35: R_SMOKING | E35: C_ICH | F35: hstroke | G35: direct_smoking_prevalence_shift_rr | H35: 0.303 | I35: 0.1982832 | J35: 1.19 | L35: delayed_exponential_remaining_effect | M35: 0.061514457 | N35: 2026 | O35: 2030 | P35: =1-(1+I35*(J35-1))/(1+H35*(J35-1)) -> 0.018813121 | Q35: =H35-I35 -> 0.1047168 | R35: =IF(H35=0,0,(H35-I35)/H35) -> 0.3456 | S35: I_PH_TOBACCO_TAX__C_SHARED | T35: Ready | U35: =COUNTIF($B$2:$B$49,B35) -> 1 | V35: =IF(U35=1,"OK","DUPLICATE KEY") -> OK | W35: I_PH_TOBACCO_TAX | X35: standalone | Y35: RR
A36: I_PH_TOBACCO_TAX | B36: I_PH_TOBACCO_TAX__C_IHD | C36: Tobacco tax | D36: R_SMOKING | E36: C_IHD | F36: ihd | G36: direct_smoking_prevalence_shift_rr | H36: 0.303 | I36: 0.1982832 | J36: 1.6 | L36: delayed_exponential_remaining_effect | M36: 0.061514457 | N36: 2026 | O36: 2030 | P36: =1-(1+I36*(J36-1))/(1+H36*(J36-1)) -> 0.053164732 | Q36: =H36-I36 -> 0.1047168 | R36: =IF(H36=0,0,(H36-I36)/H36) -> 0.3456 | S36: I_PH_TOBACCO_TAX__C_SHARED | T36: Ready | U36: =COUNTIF($B$2:$B$49,B36) -> 1 | V36: =IF(U36=1,"OK","DUPLICATE KEY") -> OK | W36: I_PH_TOBACCO_TAX | X36: standalone | Y36: RR
A37: I_PH_TOBACCO_TAX | B37: I_PH_TOBACCO_TAX__C_IS | C37: Tobacco tax | D37: R_SMOKING | E37: C_IS | F37: istroke | G37: direct_smoking_prevalence_shift_rr | H37: 0.303 | I37: 0.1982832 | J37: 1.38 | L37: delayed_exponential_remaining_effect | M37: 0.061514457 | N37: 2026 | O37: 2030 | P37: =1-(1+I37*(J37-1))/(1+H37*(J37-1)) -> 0.035683756 | Q37: =H37-I37 -> 0.1047168 | R37: =IF(H37=0,0,(H37-I37)/H37) -> 0.3456 | S37: I_PH_TOBACCO_TAX__C_SHARED | T37: Ready | U37: =COUNTIF($B$2:$B$49,B37) -> 1 | V37: =IF(U37=1,"OK","DUPLICATE KEY") -> OK | W37: I_PH_TOBACCO_TAX | X37: standalone | Y37: RR
A38: I_PH_TOB_AD_BAN | B38: I_PH_TOB_AD_BAN__C_T2DM | C38: Tobacco advertising ban | D38: R_SMOKING | E38: C_T2DM | F38: dm2 | G38: direct_smoking_prevalence_shift_rr | H38: 0.303 | I38: 0.29088 | J38: 1.37 | L38: delayed_exponential_remaining_effect | M38: 0.061514457 | N38: 2026 | O38: 2030 | P38: =1-(1+I38*(J38-1))/(1+H38*(J38-1)) -> 0.0040323349 | Q38: =H38-I38 -> 0.01212 | R38: =IF(H38=0,0,(H38-I38)/H38) -> 0.04 | S38: I_PH_TOB_AD_BAN__C_SHARED | T38: Ready | U38: =COUNTIF($B$2:$B$49,B38) -> 1 | V38: =IF(U38=1,"OK","DUPLICATE KEY") -> OK | W38: I_PH_TOBACCO_POLICY | X38: child | Y38: RR
A39: I_PH_TOB_AD_BAN | B39: I_PH_TOB_AD_BAN__C_ICH | C39: Tobacco advertising ban | D39: R_SMOKING | E39: C_ICH | F39: hstroke | G39: direct_smoking_prevalence_shift_rr | H39: 0.303 | I39: 0.29088 | J39: 1.19 | L39: delayed_exponential_remaining_effect | M39: 0.061514457 | N39: 2026 | O39: 2030 | P39: =1-(1+I39*(J39-1))/(1+H39*(J39-1)) -> 0.0021774445 | Q39: =H39-I39 -> 0.01212 | R39: =IF(H39=0,0,(H39-I39)/H39) -> 0.04 | S39: I_PH_TOB_AD_BAN__C_SHARED | T39: Ready | U39: =COUNTIF($B$2:$B$49,B39) -> 1 | V39: =IF(U39=1,"OK","DUPLICATE KEY") -> OK | W39: I_PH_TOBACCO_POLICY | X39: child | Y39: RR
A40: I_PH_TOB_AD_BAN | B40: I_PH_TOB_AD_BAN__C_IHD | C40: Tobacco advertising ban | D40: R_SMOKING | E40: C_IHD | F40: ihd | G40: direct_smoking_prevalence_shift_rr | H40: 0.303 | I40: 0.29088 | J40: 1.6 | L40: delayed_exponential_remaining_effect | M40: 0.061514457 | N40: 2026 | O40: 2030 | P40: =1-(1+I40*(J40-1))/(1+H40*(J40-1)) -> 0.0061533254 | Q40: =H40-I40 -> 0.01212 | R40: =IF(H40=0,0,(H40-I40)/H40) -> 0.04 | S40: I_PH_TOB_AD_BAN__C_SHARED | T40: Ready | U40: =COUNTIF($B$2:$B$49,B40) -> 1 | V40: =IF(U40=1,"OK","DUPLICATE KEY") -> OK | W40: I_PH_TOBACCO_POLICY | X40: child | Y40: RR
A41: I_PH_TOB_AD_BAN | B41: I_PH_TOB_AD_BAN__C_IS | C41: Tobacco advertising ban | D41: R_SMOKING | E41: C_IS | F41: istroke | G41: direct_smoking_prevalence_shift_rr | H41: 0.303 | I41: 0.29088 | J41: 1.38 | L41: delayed_exponential_remaining_effect | M41: 0.061514457 | N41: 2026 | O41: 2030 | P41: =1-(1+I41*(J41-1))/(1+H41*(J41-1)) -> 0.0041300644 | Q41: =H41-I41 -> 0.01212 | R41: =IF(H41=0,0,(H41-I41)/H41) -> 0.04 | S41: I_PH_TOB_AD_BAN__C_SHARED | T41: Ready | U41: =COUNTIF($B$2:$B$49,B41) -> 1 | V41: =IF(U41=1,"OK","DUPLICATE KEY") -> OK | W41: I_PH_TOBACCO_POLICY | X41: child | Y41: RR
A42: I_PH_TOB_CLEAN_AIR | B42: I_PH_TOB_CLEAN_AIR__C_T2DM | C42: Smoke-free / clean-air law | D42: R_SMOKING | E42: C_T2DM | F42: dm2 | G42: direct_smoking_prevalence_shift_rr | H42: 0.303 | I42: 0.286335 | J42: 1.37 | L42: delayed_exponential_remaining_effect | M42: 0.061514457 | N42: 2026 | O42: 2030 | P42: =1-(1+I42*(J42-1))/(1+H42*(J42-1)) -> 0.0055444605 | Q42: =H42-I42 -> 0.016665 | R42: =IF(H42=0,0,(H42-I42)/H42) -> 0.055 | S42: I_PH_TOB_CLEAN_AIR__C_SHARED | T42: Ready | U42: =COUNTIF($B$2:$B$49,B42) -> 1 | V42: =IF(U42=1,"OK","DUPLICATE KEY") -> OK | W42: I_PH_TOBACCO_POLICY | X42: child | Y42: RR
A43: I_PH_TOB_CLEAN_AIR | B43: I_PH_TOB_CLEAN_AIR__C_ICH | C43: Smoke-free / clean-air law | D43: R_SMOKING | E43: C_ICH | F43: hstroke | G43: direct_smoking_prevalence_shift_rr | H43: 0.303 | I43: 0.286335 | J43: 1.19 | L43: delayed_exponential_remaining_effect | M43: 0.061514457 | N43: 2026 | O43: 2030 | P43: =1-(1+I43*(J43-1))/(1+H43*(J43-1)) -> 0.0029939862 | Q43: =H43-I43 -> 0.016665 | R43: =IF(H43=0,0,(H43-I43)/H43) -> 0.055 | S43: I_PH_TOB_CLEAN_AIR__C_SHARED | T43: Ready | U43: =COUNTIF($B$2:$B$49,B43) -> 1 | V43: =IF(U43=1,"OK","DUPLICATE KEY") -> OK | W43: I_PH_TOBACCO_POLICY | X43: child | Y43: RR
A44: I_PH_TOB_CLEAN_AIR | B44: I_PH_TOB_CLEAN_AIR__C_IHD | C44: Smoke-free / clean-air law | D44: R_SMOKING | E44: C_IHD | F44: ihd | G44: direct_smoking_prevalence_shift_rr | H44: 0.303 | I44: 0.286335 | J44: 1.6 | L44: delayed_exponential_remaining_effect | M44: 0.061514457 | N44: 2026 | O44: 2030 | P44: =1-(1+I44*(J44-1))/(1+H44*(J44-1)) -> 0.0084608225 | Q44: =H44-I44 -> 0.016665 | R44: =IF(H44=0,0,(H44-I44)/H44) -> 0.055 | S44: I_PH_TOB_CLEAN_AIR__C_SHARED | T44: Ready | U44: =COUNTIF($B$2:$B$49,B44) -> 1 | V44: =IF(U44=1,"OK","DUPLICATE KEY") -> OK | W44: I_PH_TOBACCO_POLICY | X44: child | Y44: RR
A45: I_PH_TOB_CLEAN_AIR | B45: I_PH_TOB_CLEAN_AIR__C_IS | C45: Smoke-free / clean-air law | D45: R_SMOKING | E45: C_IS | F45: istroke | G45: direct_smoking_prevalence_shift_rr | H45: 0.303 | I45: 0.286335 | J45: 1.38 | L45: delayed_exponential_remaining_effect | M45: 0.061514457 | N45: 2026 | O45: 2030 | P45: =1-(1+I45*(J45-1))/(1+H45*(J45-1)) -> 0.0056788385 | Q45: =H45-I45 -> 0.016665 | R45: =IF(H45=0,0,(H45-I45)/H45) -> 0.055 | S45: I_PH_TOB_CLEAN_AIR__C_SHARED | T45: Ready | U45: =COUNTIF($B$2:$B$49,B45) -> 1 | V45: =IF(U45=1,"OK","DUPLICATE KEY") -> OK | W45: I_PH_TOBACCO_POLICY | X45: child | Y45: RR
... A49: I_PH_TOB_MEDIA | B49: I_PH_TOB_MEDIA__C_IS | C49: Tobacco mass-media campaign | D49: R_SMOKING | E49: C_IS | F49: istroke | G49: direct_smoking_prevalence_shift_rr | H49: 0.303 | I49: 0.283305 | J49: 1.38 | L49: delayed_exponential_remaining_effect | M49: 0.061514457 | N49: 2026 | O49: 2030 | P49: =1-(1+I49*(J49-1))/(1+H49*(J49-1)) -> 0.0067113546 | Q49: =H49-I49 -> 0.019695 | R49: =IF(H49=0,0,(H49-I49)/H49) -> 0.065 | S49: I_PH_TOB_MEDIA__C_SHARED | T49: Ready | U49: =COUNTIF($B$2:$B$49,B49) -> 1 | V49: =IF(U49=1,"OK","DUPLICATE KEY") -> OK | W49: I_PH_TOBACCO_POLICY | X49: child | Y49: RR

Sheet Blocked_Links
A1: note
A2: No blocked public-health links in this run.

Sheet Policy_Levers
A1: lever_id | B1: intervention_id | C1: component | D1: lever_method | E1: parent_package_id | F1: intervention_role | G1: fiscal_baseline_tax_level | H1: fiscal_target_tax_level | I1: fiscal_tax_level_unit | J1: regulatory_baseline_level | K1: regulatory_target_level | L1: regulatory_baseline_score | M1: regulatory_target_score | N1: effect_parameter | O1: implementation_gap | P1: implied_price_change | Q1: fiscal_tax_delta | R1: policy_reduction | S1: estimated_risk_reduction_wb | T1: review_status | U1: qa_status
A2: PL_TOB_TAX_SHARE | B2: I_PH_TOBACCO_TAX | C2: Tax share of final retail price | D2: tax_share_to_price_elasticity | E2: I_PH_TOBACCO_TAX | F2: standalone | G2: 0.57 | H2: 0.75 | I2: tax share of retail price | J2: partial | K2: partial | L2: 0.5 | M2: 0.5 | N2: -0.48 | O2: =IF(D2="regulatory_gap_multiplicative",MAX(0,M2-L2),"") | P2: =IF(D2="tax_share_to_price_elasticity",(1-G2)/(1-H2)-1,IF(D2="price_elasticity",Q2,"")) -> 0.72 | Q2: =IF(D2="price_elasticity",MAX(0,H2-G2),"") | R2: =IF(D2="regulatory_gap_multiplicative",N2*O2,IF(OR(D2="price_elasticity",D2="tax_share_to_price_elasticity"),ABS(N2)*P2,"")) -> 0.3456 | S2: 0.3456 | T2: Ready | U2: OK
A3: PL_ALC_PRICE | B3: I_PH_ALCOHOL_TAX | C3: Incremental retail-price increase versus current law | D3: price_elasticity | E3: I_PH_ALCOHOL_TAX | F3: standalone | G3: 0 | H3: 0.25 | I3: relative price change vs current law | J3: none | K3: none | L3: 0 | M3: 0 | N3: -0.49 | O3: =IF(D3="regulatory_gap_multiplicative",MAX(0,M3-L3),"") | P3: =IF(D3="tax_share_to_price_elasticity",(1-G3)/(1-H3)-1,IF(D3="price_elasticity",Q3,"")) -> 0.25 | Q3: =IF(D3="price_elasticity",MAX(0,H3-G3),"") -> 0.25 | R3: =IF(D3="regulatory_gap_multiplicative",N3*O3,IF(OR(D3="price_elasticity",D3="tax_share_to_price_elasticity"),ABS(N3)*P3,"")) -> 0.1225 | S3: 0.1225 | T3: Ready | U3: OK
A4: PL_TOB_CLEAN_AIR | B4: I_PH_TOB_CLEAN_AIR | C4: Smoking ban / clean-air law | D4: regulatory_gap_multiplicative | E4: I_PH_TOBACCO_POLICY | F4: child | J4: partial | K4: full | L4: 0.5 | M4: 1 | N4: 0.11 | O4: =IF(D4="regulatory_gap_multiplicative",MAX(0,M4-L4),"") -> 0.5 | P4: =IF(D4="tax_share_to_price_elasticity",(1-G4)/(1-H4)-1,IF(D4="price_elasticity",Q4,"")) | Q4: =IF(D4="price_elasticity",MAX(0,H4-G4),"") | R4: =IF(D4="regulatory_gap_multiplicative",N4*O4,IF(OR(D4="price_elasticity",D4="tax_share_to_price_elasticity"),ABS(N4)*P4,"")) -> 0.055 | S4: 0.055 | T4: Ready | U4: OK
A5: PL_TOB_MEDIA | B5: I_PH_TOB_MEDIA | C5: Highly publicised mass-media campaign | D5: regulatory_gap_multiplicative | E5: I_PH_TOBACCO_POLICY | F5: child | J5: none | K5: full | L5: 0 | M5: 1 | N5: 0.065 | O5: =IF(D5="regulatory_gap_multiplicative",MAX(0,M5-L5),"") -> 1 | P5: =IF(D5="tax_share_to_price_elasticity",(1-G5)/(1-H5)-1,IF(D5="price_elasticity",Q5,"")) | Q5: =IF(D5="price_elasticity",MAX(0,H5-G5),"") | R5: =IF(D5="regulatory_gap_multiplicative",N5*O5,IF(OR(D5="price_elasticity",D5="tax_share_to_price_elasticity"),ABS(N5)*P5,"")) -> 0.065 | S5: 0.065 | T5: Ready | U5: OK
A6: PL_TOB_AD_BAN | B6: I_PH_TOB_AD_BAN | C6: Advertising, promotion and sponsorship ban | D6: regulatory_gap_multiplicative | E6: I_PH_TOBACCO_POLICY | F6: child | J6: none | K6: full | L6: 0 | M6: 1 | N6: 0.04 | O6: =IF(D6="regulatory_gap_multiplicative",MAX(0,M6-L6),"") -> 1 | P6: =IF(D6="tax_share_to_price_elasticity",(1-G6)/(1-H6)-1,IF(D6="price_elasticity",Q6,"")) | Q6: =IF(D6="price_elasticity",MAX(0,H6-G6),"") | R6: =IF(D6="regulatory_gap_multiplicative",N6*O6,IF(OR(D6="price_elasticity",D6="tax_share_to_price_elasticity"),ABS(N6)*P6,"")) -> 0.04 | S6: 0.04 | T6: Ready | U6: OK
A7: PL_ALC_AD_BAN | B7: I_PH_ALCOHOL_POLICY | C7: Alcohol advertising ban | D7: regulatory_gap_multiplicative | E7: I_PH_ALCOHOL_POLICY | F7: standalone | J7: partial | K7: full | L7: 0.5 | M7: 1 | N7: 0.269 | O7: =IF(D7="regulatory_gap_multiplicative",MAX(0,M7-L7),"") -> 0.5 | P7: =IF(D7="tax_share_to_price_elasticity",(1-G7)/(1-H7)-1,IF(D7="price_elasticity",Q7,"")) | Q7: =IF(D7="price_elasticity",MAX(0,H7-G7),"") | R7: =IF(D7="regulatory_gap_multiplicative",N7*O7,IF(OR(D7="price_elasticity",D7="tax_share_to_price_elasticity"),ABS(N7)*P7,"")) -> 0.1345 | S7: 0.1345 | T7: Ready | U7: OK
A8: PL_SALT_REFORM | B8: I_PH_SALT_REFORM | C8: Mandatory product reformulation | D8: regulatory_gap_multiplicative | E8: I_PH_SALT_POLICY | F8: child | J8: partial | K8: full | L8: 0.5 | M8: 1 | N8: 0.2 | O8: =IF(D8="regulatory_gap_multiplicative",MAX(0,M8-L8),"") -> 0.5 | P8: =IF(D8="tax_share_to_price_elasticity",(1-G8)/(1-H8)-1,IF(D8="price_elasticity",Q8,"")) | Q8: =IF(D8="price_elasticity",MAX(0,H8-G8),"") | R8: =IF(D8="regulatory_gap_multiplicative",N8*O8,IF(OR(D8="price_elasticity",D8="tax_share_to_price_elasticity"),ABS(N8)*P8,"")) -> 0.1 | S8: 0.1 | T8: Ready | U8: OK
A9: PL_SALT_FOPL | B9: I_PH_SALT_FOPL | C9: Front-of-pack labelling | D9: regulatory_gap_multiplicative | E9: I_PH_SALT_POLICY | F9: child | J9: partial | K9: full | L9: 0.5 | M9: 1 | N9: 0.1 | O9: =IF(D9="regulatory_gap_multiplicative",MAX(0,M9-L9),"") -> 0.5 | P9: =IF(D9="tax_share_to_price_elasticity",(1-G9)/(1-H9)-1,IF(D9="price_elasticity",Q9,"")) | Q9: =IF(D9="price_elasticity",MAX(0,H9-G9),"") | R9: =IF(D9="regulatory_gap_multiplicative",N9*O9,IF(OR(D9="price_elasticity",D9="tax_share_to_price_elasticity"),ABS(N9)*P9,"")) -> 0.05 | S9: 0.05 | T9: Ready | U9: OK
A10: PL_SALT_MEDIA | B10: I_PH_SALT_MEDIA | C10: Mass-media campaign | D10: regulatory_gap_multiplicative | E10: I_PH_SALT_POLICY | F10: child | J10: partial | K10: partial | L10: 0.5 | M10: 0.5 | N10: 0.05 | O10: =IF(D10="regulatory_gap_multiplicative",MAX(0,M10-L10),"") -> 0 | P10: =IF(D10="tax_share_to_price_elasticity",(1-G10)/(1-H10)-1,IF(D10="price_elasticity",Q10,"")) | Q10: =IF(D10="price_elasticity",MAX(0,H10-G10),"") | R10: =IF(D10="regulatory_gap_multiplicative",N10*O10,IF(OR(D10="price_elasticity",D10="tax_share_to_price_elasticity"),ABS(N10)*P10,"")) -> 0 | S10: 0 | T10: Ready | U10: OK
A11: PL_SALT_ENV | B11: I_PH_SALT_ENV | C11: Public food procurement and supportive institutions | D11: regulatory_gap_multiplicative | E11: I_PH_SALT_POLICY | F11: child | J11: partial | K11: full | L11: 0.5 | M11: 1 | N11: 0.07 | O11: =IF(D11="regulatory_gap_multiplicative",MAX(0,M11-L11),"") -> 0.5 | P11: =IF(D11="tax_share_to_price_elasticity",(1-G11)/(1-H11)-1,IF(D11="price_elasticity",Q11,"")) | Q11: =IF(D11="price_elasticity",MAX(0,H11-G11),"") | R11: =IF(D11="regulatory_gap_multiplicative",N11*O11,IF(OR(D11="price_elasticity",D11="tax_share_to_price_elasticity"),ABS(N11)*P11,"")) -> 0.035 | S11: 0.035 | T11: Ready | U11: OK
A12: PL_TFA_REG | B12: I_PH_TFA_POLICY | C12: Best-practice industrial TFA regulation | D12: regulatory_gap_multiplicative | E12: I_PH_TFA_POLICY | F12: standalone | J12: partial | K12: full | L12: 0.5 | M12: 1 | N12: 1 | O12: =IF(D12="regulatory_gap_multiplicative",MAX(0,M12-L12),"") -> 0.5 | P12: =IF(D12="tax_share_to_price_elasticity",(1-G12)/(1-H12)-1,IF(D12="price_elasticity",Q12,"")) | Q12: =IF(D12="price_elasticity",MAX(0,H12-G12),"") | R12: =IF(D12="regulatory_gap_multiplicative",N12*O12,IF(OR(D12="price_elasticity",D12="tax_share_to_price_elasticity"),ABS(N12)*P12,"")) -> 0.5 | S12: 0.5 | T12: Ready | U12: OK
A13: PL_SSB_PRICE | B13: I_PH_SSB_TAX | C13: Incremental retail-price increase | D13: price_elasticity | E13: I_PH_SSB_TAX | F13: standalone | G13: 0 | H13: 0.2 | I13: relative price change vs baseline | J13: none | K13: full | L13: 0 | M13: 1 | N13: -0.875 | O13: =IF(D13="regulatory_gap_multiplicative",MAX(0,M13-L13),"") | P13: =IF(D13="tax_share_to_price_elasticity",(1-G13)/(1-H13)-1,IF(D13="price_elasticity",Q13,"")) -> 0.2 | Q13: =IF(D13="price_elasticity",MAX(0,H13-G13),"") -> 0.2 | R13: =IF(D13="regulatory_gap_multiplicative",N13*O13,IF(OR(D13="price_elasticity",D13="tax_share_to_price_elasticity"),ABS(N13)*P13,"")) -> 0.175 | S13: 0.175 | T13: Ready | U13: OK

Sheet Exposure_Targets
A1: intervention_id | B1: risk_id | C1: risk_exposure_measure | D1: exposure_unit | E1: baseline_exposure | F1: reduction_method | G1: red_or_target | H1: exposure_floor | I1: target_exposure | J1: absolute_reduction | K1: relative_reduction | L1: start_year | M1: target_year | N1: scale_up_shape | O1: review_status
A2: I_PH_ALCOHOL_POLICY | B2: R_ALCOHOL | C2: Alcohol consumption per adult | D2: litres pure alcohol/adult/year | E2: 0.1 | F2: relative | G2: 0.1345 | H2: 0 | I2: =MAX(H2,E2*(1-G2)) -> 0.08655 | J2: =E2-I2 -> 0.01345 | K2: =IF(E2=0,0,(E2-I2)/E2) -> 0.1345 | L2: 2026 | M2: 2030 | N2: linear | O2: Ready
A3: I_PH_ALCOHOL_TAX | B3: R_ALCOHOL | C3: Alcohol consumption per adult | D3: litres pure alcohol/adult/year | E3: 0.1 | F3: relative | G3: 0.1225 | H3: 0 | I3: =MAX(H3,E3*(1-G3)) -> 0.08775 | J3: =E3-I3 -> 0.01225 | K3: =IF(E3=0,0,(E3-I3)/E3) -> 0.1225 | L3: 2026 | M3: 2030 | N3: linear | O3: Baseline retained
A4: I_PH_SALT_ENV | B4: R_SODIUM | C4: Mean sodium intake | D4: g sodium/day | E4: 4.4 | F4: relative | G4: 0.035 | H4: 3 | I4: =MAX(H4,E4*(1-G4)) -> 4.246 | J4: =E4-I4 -> 0.154 | K4: =IF(E4=0,0,(E4-I4)/E4) -> 0.035 | L4: 2026 | M4: 2030 | N4: linear | O4: Ready
A5: I_PH_SALT_FOPL | B5: R_SODIUM | C5: Mean sodium intake | D5: g sodium/day | E5: 4.4 | F5: relative | G5: 0.05 | H5: 3 | I5: =MAX(H5,E5*(1-G5)) -> 4.18 | J5: =E5-I5 -> 0.22 | K5: =IF(E5=0,0,(E5-I5)/E5) -> 0.05 | L5: 2026 | M5: 2030 | N5: linear | O5: Ready
A6: I_PH_SALT_MEDIA | B6: R_SODIUM | C6: Mean sodium intake | D6: g sodium/day | E6: 4.4 | F6: relative | G6: 0 | H6: 3 | I6: =MAX(H6,E6*(1-G6)) -> 4.4 | J6: =E6-I6 -> 0 | K6: =IF(E6=0,0,(E6-I6)/E6) -> 0 | L6: 2026 | M6: 2030 | N6: linear | O6: Ready
A7: I_PH_SALT_REFORM | B7: R_SODIUM | C7: Mean sodium intake | D7: g sodium/day | E7: 4.4 | F7: relative | G7: 0.1 | H7: 3 | I7: =MAX(H7,E7*(1-G7)) -> 3.96 | J7: =E7-I7 -> 0.44 | K7: =IF(E7=0,0,(E7-I7)/E7) -> 0.1 | L7: 2026 | M7: 2030 | N7: linear | O7: Ready
A8: I_PH_SSB_TAX | B8: R_SSB | C8: Mean SSB intake | D8: 8 oz servings/adult/day | E8: 0.11428571 | F8: relative | G8: 0.175 | H8: 0 | I8: =MAX(H8,E8*(1-G8)) -> 0.094285714 | J8: =E8-I8 -> 0.02 | K8: =IF(E8=0,0,(E8-I8)/E8) -> 0.175 | L8: 2026 | M8: 2030 | N8: linear | O8: GDD 2020 mean
A9: I_PH_TFA_POLICY | B9: R_TFA | C9: Mean industrial trans-fat intake | D9: % energy | E9: 0.48 | F9: relative | G9: 0.5 | H9: 0 | I9: =MAX(H9,E9*(1-G9)) -> 0.24 | J9: =E9-I9 -> 0.24 | K9: =IF(E9=0,0,(E9-I9)/E9) -> 0.5 | L9: 2026 | M9: 2030 | N9: linear | O9: RR base case; PAF optional
A10: I_PH_TOBACCO_TAX | B10: R_SMOKING | C10: Smoking prevalence | D10: proportion | E10: 0.303 | F10: relative | G10: 0.3456 | H10: 0 | I10: =MAX(H10,E10*(1-G10)) -> 0.1982832 | J10: =E10-I10 -> 0.1047168 | K10: =IF(E10=0,0,(E10-I10)/E10) -> 0.3456 | L10: 2026 | M10: 2030 | N10: linear | O10: Baseline retained
A11: I_PH_TOB_AD_BAN | B11: R_SMOKING | C11: Smoking prevalence | D11: proportion | E11: 0.303 | F11: relative | G11: 0.04 | H11: 0 | I11: =MAX(H11,E11*(1-G11)) -> 0.29088 | J11: =E11-I11 -> 0.01212 | K11: =IF(E11=0,0,(E11-I11)/E11) -> 0.04 | L11: 2026 | M11: 2030 | N11: linear | O11: Ready
A12: I_PH_TOB_CLEAN_AIR | B12: R_SMOKING | C12: Smoking prevalence | D12: proportion | E12: 0.303 | F12: relative | G12: 0.055 | H12: 0 | I12: =MAX(H12,E12*(1-G12)) -> 0.286335 | J12: =E12-I12 -> 0.016665 | K12: =IF(E12=0,0,(E12-I12)/E12) -> 0.055 | L12: 2026 | M12: 2030 | N12: linear | O12: Ready
A13: I_PH_TOB_MEDIA | B13: R_SMOKING | C13: Smoking prevalence | D13: proportion | E13: 0.303 | F13: relative | G13: 0.065 | H13: 0 | I13: =MAX(H13,E13*(1-G13)) -> 0.283305 | J13: =E13-I13 -> 0.019695 | K13: =IF(E13=0,0,(E13-I13)/E13) -> 0.065 | L13: 2026 | M13: 2030 | N13: linear | O13: Ready

Sheet Effect_Parameters
A1: intervention_cause_key | B1: intervention_id | C1: cause_id | D1: cause_code | E1: effect_model | F1: response_parameter | G1: response_value | H1: paf_value | I1: lag_model | J1: lag_parameter | K1: baseline_exposure | L1: target_exposure | M1: full_effect_at_target | N1: model_transition | O1: valid | P1: review_status
A2: I_PH_ALCOHOL_POLICY__C_CMYO | B2: I_PH_ALCOHOL_POLICY | C2: C_CMYO | D2: cmd | E2: direct_loglinear_rr_per_unit_reduction | F2: RR per 1 L/year | G2: 1.0131617 | I2: immediate_after_full_implementation | J2: 1 | K2: 0.1 | L2: 0.08655 | M2: =1-1/(G2^(K2-L2)) -> 0.00017585416 | N2: incidence | O2: 1 | P2: Ready
A3: I_PH_ALCOHOL_POLICY__C_HHD | B3: I_PH_ALCOHOL_POLICY | C3: C_HHD | D3: hhd | E3: direct_loglinear_rr_per_unit_reduction | F3: RR per 1 L/year | G3: 1.0331775 | I3: immediate_after_full_implementation | J3: 1 | K3: 0.1 | L3: 0.08655 | M3: =1-1/(G3^(K3-L3)) -> 0.00043889841 | N3: incidence | O3: 1 | P3: Ready
A4: I_PH_ALCOHOL_POLICY__C_ICH | B4: I_PH_ALCOHOL_POLICY | C4: C_ICH | D4: hstroke | E4: direct_loglinear_rr_per_unit_reduction | F4: RR per 1 L/year | G4: 1.02008 | I4: immediate_after_full_implementation | J4: 1 | K4: 0.1 | L4: 0.08655 | M4: =1-1/(G4^(K4-L4)) -> 0.00026736396 | N4: incidence | O4: 1 | P4: Ready
A5: I_PH_ALCOHOL_POLICY__C_IHD | B5: I_PH_ALCOHOL_POLICY | C5: C_IHD | D5: ihd | E5: direct_loglinear_rr_per_unit_reduction | F5: RR per 1 L/year | G5: 1.0088804 | I5: immediate_after_full_implementation | J5: 1 | K5: 0.1 | L5: 0.08655 | M5: =1-1/(G5^(K5-L5)) -> 0.00011890689 | N5: incidence | O5: 1 | P5: Ready
A6: I_PH_ALCOHOL_POLICY__C_IS | B6: I_PH_ALCOHOL_POLICY | C6: C_IS | D6: istroke | E6: direct_loglinear_rr_per_unit_reduction | F6: RR per 1 L/year | G6: 1.02008 | I6: immediate_after_full_implementation | J6: 1 | K6: 0.1 | L6: 0.08655 | M6: =1-1/(G6^(K6-L6)) -> 0.00026736396 | N6: incidence | O6: 1 | P6: Ready
A7: I_PH_ALCOHOL_TAX__C_CMYO | B7: I_PH_ALCOHOL_TAX | C7: C_CMYO | D7: cmd | E7: direct_loglinear_rr_per_unit_reduction | F7: RR per 1 L/year | G7: 1.0131617 | I7: immediate_after_full_implementation | J7: 1 | K7: 0.1 | L7: 0.08775 | M7: =1-1/(G7^(K7-L7)) -> 0.00016016582 | N7: incidence | O7: 1 | P7: Ready
A8: I_PH_ALCOHOL_TAX__C_HHD | B8: I_PH_ALCOHOL_TAX | C8: C_HHD | D8: hhd | E8: direct_loglinear_rr_per_unit_reduction | F8: RR per 1 L/year | G8: 1.0331775 | I8: immediate_after_full_implementation | J8: 1 | K8: 0.1 | L8: 0.08775 | M8: =1-1/(G8^(K8-L8)) -> 0.00039974801 | N8: incidence | O8: 1 | P8: Ready
A9: I_PH_ALCOHOL_TAX__C_ICH | B9: I_PH_ALCOHOL_TAX | C9: C_ICH | D9: hstroke | E9: direct_loglinear_rr_per_unit_reduction | F9: RR per 1 L/year | G9: 1.02008 | I9: immediate_after_full_implementation | J9: 1 | K9: 0.1 | L9: 0.08775 | M9: =1-1/(G9^(K9-L9)) -> 0.00024351283 | N9: incidence | O9: 1 | P9: Ready
A10: I_PH_ALCOHOL_TAX__C_IHD | B10: I_PH_ALCOHOL_TAX | C10: C_IHD | D10: ihd | E10: direct_loglinear_rr_per_unit_reduction | F10: RR per 1 L/year | G10: 1.0088804 | I10: immediate_after_full_implementation | J10: 1 | K10: 0.1 | L10: 0.08775 | M10: =1-1/(G10^(K10-L10)) -> 0.00010829867 | N10: incidence | O10: 1 | P10: Ready
A11: I_PH_ALCOHOL_TAX__C_IS | B11: I_PH_ALCOHOL_TAX | C11: C_IS | D11: istroke | E11: direct_loglinear_rr_per_unit_reduction | F11: RR per 1 L/year | G11: 1.02008 | I11: immediate_after_full_implementation | J11: 1 | K11: 0.1 | L11: 0.08775 | M11: =1-1/(G11^(K11-L11)) -> 0.00024351283 | N11: incidence | O11: 1 | P11: Ready
A12: I_PH_SALT_ENV__C_HHD | B12: I_PH_SALT_ENV | C12: C_HHD | D12: hhd | E12: direct_loglinear_rr_per_unit_reduction | F12: RR per 1 g sodium/day | G12: 1.06 | I12: immediate_after_full_implementation | J12: 1 | K12: 4.4 | L12: 4.246 | M12: =1-1/(G12^(K12-L12)) -> 0.0089332709 | N12: incidence | O12: 1 | P12: Ready
A13: I_PH_SALT_ENV__C_ICH | B13: I_PH_SALT_ENV | C13: C_ICH | D13: hstroke | E13: direct_loglinear_rr_per_unit_reduction | F13: RR per 1 g sodium/day | G13: 1.06 | I13: immediate_after_full_implementation | J13: 1 | K13: 4.4 | L13: 4.246 | M13: =1-1/(G13^(K13-L13)) -> 0.0089332709 | N13: incidence | O13: 1 | P13: Ready
... A33: I_PH_TFA_POLICY__C_IHD | B33: I_PH_TFA_POLICY | C33: C_IHD | D33: ihd | E33: direct_loglinear_rr_per_unit_reduction | F33: RR per 1 percentage-point energy/day | G33: 1.1 | I33: immediate_after_full_implementation | J33: 1 | K33: 0.48 | L33: 0.24 | M33: =1-1/(G33^(K33-L33)) -> 0.022614807 | N33: incidence | O33: 1 | P33: Ready
A34: I_PH_TOBACCO_TAX__C_T2DM | B34: I_PH_TOBACCO_TAX | C34: C_T2DM | D34: dm2 | E34: direct_smoking_prevalence_shift_rr | F34: RR current smoker vs non-smoker | G34: 1.37 | I34: delayed_exponential_remaining_effect | J34: 0.061514457 | K34: 0.303 | L34: 0.1982832 | M34: =1-(1+L34*(G34-1))/(1+K34*(G34-1)) -> 0.034839374 | N34: incidence | O34: 1 | P34: Ready
A35: I_PH_TOBACCO_TAX__C_ICH | B35: I_PH_TOBACCO_TAX | C35: C_ICH | D35: hstroke | E35: direct_smoking_prevalence_shift_rr | F35: RR current smoker vs non-smoker | G35: 1.19 | I35: delayed_exponential_remaining_effect | J35: 0.061514457 | K35: 0.303 | L35: 0.1982832 | M35: =1-(1+L35*(G35-1))/(1+K35*(G35-1)) -> 0.018813121 | N35: incidence | O35: 1 | P35: Ready
A36: I_PH_TOBACCO_TAX__C_IHD | B36: I_PH_TOBACCO_TAX | C36: C_IHD | D36: ihd | E36: direct_smoking_prevalence_shift_rr | F36: RR current smoker vs non-smoker | G36: 1.6 | I36: delayed_exponential_remaining_effect | J36: 0.061514457 | K36: 0.303 | L36: 0.1982832 | M36: =1-(1+L36*(G36-1))/(1+K36*(G36-1)) -> 0.053164732 | N36: incidence | O36: 1 | P36: Ready
A37: I_PH_TOBACCO_TAX__C_IS | B37: I_PH_TOBACCO_TAX | C37: C_IS | D37: istroke | E37: direct_smoking_prevalence_shift_rr | F37: RR current smoker vs non-smoker | G37: 1.38 | I37: delayed_exponential_remaining_effect | J37: 0.061514457 | K37: 0.303 | L37: 0.1982832 | M37: =1-(1+L37*(G37-1))/(1+K37*(G37-1)) -> 0.035683756 | N37: incidence | O37: 1 | P37: Ready
A38: I_PH_TOB_AD_BAN__C_T2DM | B38: I_PH_TOB_AD_BAN | C38: C_T2DM | D38: dm2 | E38: direct_smoking_prevalence_shift_rr | F38: RR current smoker vs non-smoker | G38: 1.37 | I38: delayed_exponential_remaining_effect | J38: 0.061514457 | K38: 0.303 | L38: 0.29088 | M38: =1-(1+L38*(G38-1))/(1+K38*(G38-1)) -> 0.0040323349 | N38: incidence | O38: 1 | P38: Ready
A39: I_PH_TOB_AD_BAN__C_ICH | B39: I_PH_TOB_AD_BAN | C39: C_ICH | D39: hstroke | E39: direct_smoking_prevalence_shift_rr | F39: RR current smoker vs non-smoker | G39: 1.19 | I39: delayed_exponential_remaining_effect | J39: 0.061514457 | K39: 0.303 | L39: 0.29088 | M39: =1-(1+L39*(G39-1))/(1+K39*(G39-1)) -> 0.0021774445 | N39: incidence | O39: 1 | P39: Ready
A40: I_PH_TOB_AD_BAN__C_IHD | B40: I_PH_TOB_AD_BAN | C40: C_IHD | D40: ihd | E40: direct_smoking_prevalence_shift_rr | F40: RR current smoker vs non-smoker | G40: 1.6 | I40: delayed_exponential_remaining_effect | J40: 0.061514457 | K40: 0.303 | L40: 0.29088 | M40: =1-(1+L40*(G40-1))/(1+K40*(G40-1)) -> 0.0061533254 | N40: incidence | O40: 1 | P40: Ready
A41: I_PH_TOB_AD_BAN__C_IS | B41: I_PH_TOB_AD_BAN | C41: C_IS | D41: istroke | E41: direct_smoking_prevalence_shift_rr | F41: RR current smoker vs non-smoker | G41: 1.38 | I41: delayed_exponential_remaining_effect | J41: 0.061514457 | K41: 0.303 | L41: 0.29088 | M41: =1-(1+L41*(G41-1))/(1+K41*(G41-1)) -> 0.0041300644 | N41: incidence | O41: 1 | P41: Ready
A42: I_PH_TOB_CLEAN_AIR__C_T2DM | B42: I_PH_TOB_CLEAN_AIR | C42: C_T2DM | D42: dm2 | E42: direct_smoking_prevalence_shift_rr | F42: RR current smoker vs non-smoker | G42: 1.37 | I42: delayed_exponential_remaining_effect | J42: 0.061514457 | K42: 0.303 | L42: 0.286335 | M42: =1-(1+L42*(G42-1))/(1+K42*(G42-1)) -> 0.0055444605 | N42: incidence | O42: 1 | P42: Ready
A43: I_PH_TOB_CLEAN_AIR__C_ICH | B43: I_PH_TOB_CLEAN_AIR | C43: C_ICH | D43: hstroke | E43: direct_smoking_prevalence_shift_rr | F43: RR current smoker vs non-smoker | G43: 1.19 | I43: delayed_exponential_remaining_effect | J43: 0.061514457 | K43: 0.303 | L43: 0.286335 | M43: =1-(1+L43*(G43-1))/(1+K43*(G43-1)) -> 0.0029939862 | N43: incidence | O43: 1 | P43: Ready
A44: I_PH_TOB_CLEAN_AIR__C_IHD | B44: I_PH_TOB_CLEAN_AIR | C44: C_IHD | D44: ihd | E44: direct_smoking_prevalence_shift_rr | F44: RR current smoker vs non-smoker | G44: 1.6 | I44: delayed_exponential_remaining_effect | J44: 0.061514457 | K44: 0.303 | L44: 0.286335 | M44: =1-(1+L44*(G44-1))/(1+K44*(G44-1)) -> 0.0084608225 | N44: incidence | O44: 1 | P44: Ready
A45: I_PH_TOB_CLEAN_AIR__C_IS | B45: I_PH_TOB_CLEAN_AIR | C45: C_IS | D45: istroke | E45: direct_smoking_prevalence_shift_rr | F45: RR current smoker vs non-smoker | G45: 1.38 | I45: delayed_exponential_remaining_effect | J45: 0.061514457 | K45: 0.303 | L45: 0.286335 | M45: =1-(1+L45*(G45-1))/(1+K45*(G45-1)) -> 0.0056788385 | N45: incidence | O45: 1 | P45: Ready
... A49: I_PH_TOB_MEDIA__C_IS | B49: I_PH_TOB_MEDIA | C49: C_IS | D49: istroke | E49: direct_smoking_prevalence_shift_rr | F49: RR current smoker vs non-smoker | G49: 1.38 | I49: delayed_exponential_remaining_effect | J49: 0.061514457 | K49: 0.303 | L49: 0.283305 | M49: =1-(1+L49*(G49-1))/(1+K49*(G49-1)) -> 0.0067113546 | N49: incidence | O49: 1 | P49: Ready

Sheet Risk_Response
A1: response_key | B1: risk_id | C1: selection_status | D1: response_name | E1: age_start | F1: age_stop | G1: sex | H1: cause_id | I1: cause_scope | J1: source_effect_value | K1: source_effect_unit | L1: model_response_value | M1: model_response_unit | N1: derivation | O1: source | P1: selected_for_base_case | Q1: notes
A2: RR_SMOKING_IHD | B2: R_SMOKING | C2: Selected | D2: Current smoking RR - IHD | E2: 20 | F2: 95 | G2: Both | H2: C_IHD | I2: IHD | J2: 1.6 | K2: RR current vs non-smoker | L2: 1.6 | M2: RR current vs non-smoker | N2: model RR = source RR | O2: https://doi.org/10.1093/ije/dyi104 | P2: 1 | Q2: Applied to incidence
A3: RR_SMOKING_IS | B3: R_SMOKING | C3: Selected | D3: Current smoking RR - ischemic stroke | E3: 20 | F3: 95 | G3: Both | H3: C_IS | I3: Ischemic stroke | J3: 1.38 | K3: RR current vs non-smoker | L3: 1.38 | M3: RR current vs non-smoker | N3: model RR = source RR | O3: https://doi.org/10.1093/ije/dyi104 | P3: 1 | Q3: Direct estimate
A4: RR_SMOKING_ICH | B4: R_SMOKING | C4: Selected | D4: Current smoking RR - ICH | E4: 20 | F4: 95 | G4: Both | H4: C_ICH | I4: ICH | J4: 1.19 | K4: RR current vs non-smoker | L4: 1.19 | M4: RR current vs non-smoker | N4: model RR = source RR | O4: https://doi.org/10.1093/ije/dyi104 | P4: 1 | Q4: Hemorrhagic-stroke estimate
A5: RR_SMOKING_T2DM | B5: R_SMOKING | C5: Selected | D5: Current smoking RR - T2DM | E5: 20 | F5: 95 | G5: Both | H5: C_T2DM | I5: T2DM | J5: 1.37 | K5: RR current vs non-smoker | L5: 1.37 | M5: RR current vs non-smoker | N5: model RR = source RR | O5: https://doi.org/10.1016/S2213-8587(15)00316-2 | P5: 1 | Q5: Timing sensitivity
A6: RR_ALCOHOL_IHD_1L | B6: R_ALCOHOL | C6: Selected | D6: Alcohol dose response - IHD | E6: 20 | F6: 95 | G6: Both | H6: C_IHD | I6: IHD | J6: 1.06 | K6: HR per 100 g/week | L6: 1.0088804 | M6: RR per 1 L/year | N6: converted using 789 g/L and 52 weeks/year | O6: https://doi.org/10.1016/S0140-6736(18)30134-X | P6: 1 | Q6: Conservative proxy
A7: RR_ALCOHOL_IS_1L | B7: R_ALCOHOL | C7: Selected | D7: Alcohol dose response - ischemic stroke | E7: 20 | F7: 95 | G7: Both | H7: C_IS | I7: Ischemic stroke | J7: 1.14 | K7: HR per 100 g/week | L7: 1.02008 | M7: RR per 1 L/year | N7: converted using 789 g/L and 52 weeks/year | O7: https://doi.org/10.1016/S0140-6736(18)30134-X | P7: 1 | Q7: All-stroke proxy
A8: RR_ALCOHOL_ICH_1L | B8: R_ALCOHOL | C8: Selected | D8: Alcohol dose response - ICH | E8: 20 | F8: 95 | G8: Both | H8: C_ICH | I8: ICH | J8: 1.14 | K8: HR per 100 g/week | L8: 1.02008 | M8: RR per 1 L/year | N8: converted using 789 g/L and 52 weeks/year | O8: https://doi.org/10.1016/S0140-6736(18)30134-X | P8: 1 | Q8: All-stroke proxy
A9: RR_ALCOHOL_HHD_1L | B9: R_ALCOHOL | C9: Selected | D9: Alcohol dose response - HHD | E9: 20 | F9: 95 | G9: Both | H9: C_HHD | I9: HHD | J9: 1.24 | K9: HR per 100 g/week | L9: 1.0331775 | M9: RR per 1 L/year | N9: converted using 789 g/L and 52 weeks/year | O9: https://doi.org/10.1016/S0140-6736(18)30134-X | P9: 1 | Q9: Fatal hypertensive disease
A10: RR_ALCOHOL_CMYO_1L | B10: R_ALCOHOL | C10: Selected | D10: Alcohol dose response - cardiomyopathy | E10: 20 | F10: 95 | G10: Both | H10: C_CMYO | I10: Cardiomyopathy | J10: 1.09 | K10: HR per 100 g/week | L10: 1.0131617 | M10: RR per 1 L/year | N10: converted using 789 g/L and 52 weeks/year | O10: https://doi.org/10.1016/S0140-6736(18)30134-X | P10: 1 | Q10: Heart-failure proxy
A11: LAG_TOB_CVD | B11: R_SMOKING | C11: Selected | D11: Tobacco-CVD effect realization | E11: 20 | F11: 95 | G11: Both | H11: C_IHD|C_IS|C_ICH | I11: CVD | J11: 0.47 | K11: fraction by year 10 | L11: 0.061514457 | M11: annual remaining effect | N11: 1-(1-0.47)^(1/10) | O11: Watkins 2022; https://doi.org/10.1001/jama.2019.10298 | P11: 1 | Q11: Countdown lag
A12: LAG_TOB_T2DM_PROXY | B12: R_SMOKING | C12: Selected | D12: Tobacco-T2DM effect realization | E12: 20 | F12: 95 | G12: Both | H12: C_T2DM | I12: T2DM | J12: 0.47 | K12: proxy fraction by year 10 | L12: 0.061514457 | M12: annual remaining effect | N12: uses CVD lag | O12: Pan 2015; Watkins 2022 | P12: 1 | Q12: Proxy
A13: RR_SODIUM_1G | B13: R_SODIUM | C13: Selected | D13: Direct sodium-CVD response | E13: 0 | F13: 95 | G13: Both | H13: C_IHD|C_IS|C_ICH|C_HHD | I13: CVD | J13: 1.06 | K13: RR per 1 g sodium/day | L13: 1.06 | M13: RR per 1 g sodium/day | N13: model RR = source RR | O13: Watkins 2022 p 33 | P13: 1 | Q13: Countdown pathway
... A29: PAF_SSB_IDN_CVD_DEATH_2020 | B29: R_SSB | C29: Reference | D29: Indonesia CVD death PAF | E29: 20 | F29: 95 | G29: Both | H29: C_IHD|C_IS | I29: CVD deaths | J29: 0.008 | K29: fraction | L29: 0.008 | M29: proportion | N29: CRA | O29: https://doi.org/10.1038/s41591-024-03345-4 | P29: 0 | Q29: Validation

Sheet Cost_Components
A1: cost_record_id | B1: cost_component_key | C1: cost_join_key | D1: cost_scope | E1: intervention_id | F1: parent_package_id | G1: scenario_role | H1: cost_component | I1: population_in_need_measure | J1: population_in_need_fraction | K1: frequency_per_year | L1: unit_cost_usd | M1: cost_allocation_share | N1: package_total_cost_usd_per_capita | O1: allocation_method | P1: allocated_child_cost | Q1: price_year | R1: indonesia_adjusted_flag | S1: source_country | T1: review_status | U1: cost_ready | V1: notes
A2: COST_PH_ALC_POLICY | B2: CC_PH_ALC_POLICY | C2: I_PH_ALCOHOL_POLICY__C_SHARED | D2: shared-count-once | E2: I_PH_ALCOHOL_POLICY | F2: I_PH_ALCOHOL_POLICY | G2: standalone | H2: Annual intersectoral policy implementation | I2: all | J2: 1 | K2: 1 | L2: 0.0056 | M2: 1 | N2: 0.0056 | O2: direct source value | P2: =IFERROR(N2*M2,L2) -> 0.0056 | Q2: 2017 | R2: 0 | S2: China/proxy | T2: Review | U2: =IF(AND(L2>=0,J2<>"",J2>=0,J2<=1,OR(I2="all",I2="prevalence",I2="incidence")),1,0) -> 1 | V2: Requires Indonesia/price-year adjustment
A3: COST_PH_ALC_TAX | B3: CC_PH_ALC_TAX | C3: I_PH_ALCOHOL_TAX__C_SHARED | D3: shared-count-once | E3: I_PH_ALCOHOL_TAX | F3: I_PH_ALCOHOL_TAX | G3: standalone | H3: Annual intersectoral policy implementation | I3: all | J3: 1 | K3: 1 | L3: 0.004 | M3: 1 | N3: 0.004 | O3: direct source value | P3: =IFERROR(N3*M3,L3) -> 0.004 | Q3: 2017 | R3: 0 | S3: China/proxy | T3: Review | U3: =IF(AND(L3>=0,J3<>"",J3>=0,J3<=1,OR(I3="all",I3="prevalence",I3="incidence")),1,0) -> 1 | V3: Requires Indonesia/price-year adjustment
A4: COST_PH_SALT_ENV | B4: CC_PH_SALT_ENV | C4: I_PH_SALT_ENV__C_SHARED | D4: component-count-once | E4: I_PH_SALT_ENV | F4: I_PH_SALT_POLICY | G4: child | H4: Annual intersectoral policy implementation | I4: all | J4: 1 | K4: 1 | L4: 0.008775 | M4: 0.25 | N4: 0.0351 | O4: equal within package | P4: =IFERROR(N4*M4,L4) -> 0.008775 | Q4: 2017 | R4: 0 | S4: China/proxy | T4: Review | U4: =IF(AND(L4>=0,J4<>"",J4>=0,J4<=1,OR(I4="all",I4="prevalence",I4="incidence")),1,0) -> 1 | V4: Requires Indonesia/price-year adjustment
A5: COST_PH_SALT_FOPL | B5: CC_PH_SALT_FOPL | C5: I_PH_SALT_FOPL__C_SHARED | D5: component-count-once | E5: I_PH_SALT_FOPL | F5: I_PH_SALT_POLICY | G5: child | H5: Annual intersectoral policy implementation | I5: all | J5: 1 | K5: 1 | L5: 0.008775 | M5: 0.25 | N5: 0.0351 | O5: equal within package | P5: =IFERROR(N5*M5,L5) -> 0.008775 | Q5: 2017 | R5: 0 | S5: China/proxy | T5: Review | U5: =IF(AND(L5>=0,J5<>"",J5>=0,J5<=1,OR(I5="all",I5="prevalence",I5="incidence")),1,0) -> 1 | V5: Requires Indonesia/price-year adjustment
A6: COST_PH_SALT_MEDIA | B6: CC_PH_SALT_MEDIA | C6: I_PH_SALT_MEDIA__C_SHARED | D6: component-count-once | E6: I_PH_SALT_MEDIA | F6: I_PH_SALT_POLICY | G6: child | H6: Annual intersectoral policy implementation | I6: all | J6: 1 | K6: 1 | L6: 0.008775 | M6: 0.25 | N6: 0.0351 | O6: equal within package | P6: =IFERROR(N6*M6,L6) -> 0.008775 | Q6: 2017 | R6: 0 | S6: China/proxy | T6: Review | U6: =IF(AND(L6>=0,J6<>"",J6>=0,J6<=1,OR(I6="all",I6="prevalence",I6="incidence")),1,0) -> 1 | V6: Requires Indonesia/price-year adjustment
A7: COST_PH_SALT_REFORM | B7: CC_PH_SALT_REFORM | C7: I_PH_SALT_REFORM__C_SHARED | D7: component-count-once | E7: I_PH_SALT_REFORM | F7: I_PH_SALT_POLICY | G7: child | H7: Annual intersectoral policy implementation | I7: all | J7: 1 | K7: 1 | L7: 0.008775 | M7: 0.25 | N7: 0.0351 | O7: equal within package | P7: =IFERROR(N7*M7,L7) -> 0.008775 | Q7: 2017 | R7: 0 | S7: China/proxy | T7: Review | U7: =IF(AND(L7>=0,J7<>"",J7>=0,J7<=1,OR(I7="all",I7="prevalence",I7="incidence")),1,0) -> 1 | V7: Requires Indonesia/price-year adjustment
A8: COST_PH_SSB_TAX | B8: CC_PH_SSB_TAX | C8: I_PH_SSB_TAX__C_SHARED | D8: shared-count-once | E8: I_PH_SSB_TAX | F8: I_PH_SSB_TAX | G8: standalone | H8: Annual intersectoral policy implementation | I8: all | J8: 1 | K8: 1 | L8: 0.004 | M8: 1 | N8: 0.004 | O8: direct source value | P8: =IFERROR(N8*M8,L8) -> 0.004 | Q8: 2017 | R8: 0 | S8: China/proxy | T8: Review | U8: =IF(AND(L8>=0,J8<>"",J8>=0,J8<=1,OR(I8="all",I8="prevalence",I8="incidence")),1,0) -> 1 | V8: Requires Indonesia/price-year adjustment
A9: COST_PH_TFA | B9: CC_PH_TFA | C9: I_PH_TFA_POLICY__C_SHARED | D9: shared-count-once | E9: I_PH_TFA_POLICY | F9: I_PH_TFA_POLICY | G9: standalone | H9: Annual intersectoral policy implementation | I9: all | J9: 1 | K9: 1 | L9: 0.0087 | M9: 1 | N9: 0.0087 | O9: direct source value | P9: =IFERROR(N9*M9,L9) -> 0.0087 | Q9: 2017 | R9: 0 | S9: China/proxy | T9: Review | U9: =IF(AND(L9>=0,J9<>"",J9>=0,J9<=1,OR(I9="all",I9="prevalence",I9="incidence")),1,0) -> 1 | V9: Requires Indonesia/price-year adjustment
A10: COST_PH_TOB_TAX | B10: CC_PH_TOB_TAX | C10: I_PH_TOBACCO_TAX__C_SHARED | D10: shared-count-once | E10: I_PH_TOBACCO_TAX | F10: I_PH_TOBACCO_TAX | G10: standalone | H10: Annual intersectoral policy implementation | I10: all | J10: 1 | K10: 1 | L10: 0.004 | M10: 1 | N10: 0.004 | O10: direct source value | P10: =IFERROR(N10*M10,L10) -> 0.004 | Q10: 2017 | R10: 0 | S10: China/proxy | T10: Review | U10: =IF(AND(L10>=0,J10<>"",J10>=0,J10<=1,OR(I10="all",I10="prevalence",I10="incidence")),1,0) -> 1 | V10: Requires Indonesia/price-year adjustment
A11: COST_PH_TOB_AD_BAN | B11: CC_PH_TOB_AD_BAN | C11: I_PH_TOB_AD_BAN__C_SHARED | D11: component-count-once | E11: I_PH_TOB_AD_BAN | F11: I_PH_TOBACCO_POLICY | G11: child | H11: Annual intersectoral policy implementation | I11: all | J11: 1 | K11: 1 | L11: 0.0077 | M11: 0.33333333 | N11: 0.0231 | O11: equal within package | P11: =IFERROR(N11*M11,L11) -> 0.0077 | Q11: 2017 | R11: 0 | S11: China/proxy | T11: Review | U11: =IF(AND(L11>=0,J11<>"",J11>=0,J11<=1,OR(I11="all",I11="prevalence",I11="incidence")),1,0) -> 1 | V11: Requires Indonesia/price-year adjustment
A12: COST_PH_TOB_CLEAN_AIR | B12: CC_PH_TOB_CLEAN_AIR | C12: I_PH_TOB_CLEAN_AIR__C_SHARED | D12: component-count-once | E12: I_PH_TOB_CLEAN_AIR | F12: I_PH_TOBACCO_POLICY | G12: child | H12: Annual intersectoral policy implementation | I12: all | J12: 1 | K12: 1 | L12: 0.0077 | M12: 0.33333333 | N12: 0.0231 | O12: equal within package | P12: =IFERROR(N12*M12,L12) -> 0.0077 | Q12: 2017 | R12: 0 | S12: China/proxy | T12: Review | U12: =IF(AND(L12>=0,J12<>"",J12>=0,J12<=1,OR(I12="all",I12="prevalence",I12="incidence")),1,0) -> 1 | V12: Requires Indonesia/price-year adjustment
A13: COST_PH_TOB_MEDIA | B13: CC_PH_TOB_MEDIA | C13: I_PH_TOB_MEDIA__C_SHARED | D13: component-count-once | E13: I_PH_TOB_MEDIA | F13: I_PH_TOBACCO_POLICY | G13: child | H13: Annual intersectoral policy implementation | I13: all | J13: 1 | K13: 1 | L13: 0.0077 | M13: 0.33333333 | N13: 0.0231 | O13: equal within package | P13: =IFERROR(N13*M13,L13) -> 0.0077 | Q13: 2017 | R13: 0 | S13: China/proxy | T13: Review | U13: =IF(AND(L13>=0,J13<>"",J13>=0,J13<=1,OR(I13="all",I13="prevalence",I13="incidence")),1,0) -> 1 | V13: Requires Indonesia/price-year adjustment

Sheet Annual_Mortality
A1: scenario | B1: scenario_label | C1: year | D1: cause | E1: cases | F1: cause_deaths | G1: base_cases | H1: base_deaths | I1: deaths_averted | J1: cases_averted
A2: I_PH_ALCOHOL_POLICY | B2: Alcohol advertising ban | C2: 2025 | D2: cmd | E2: 12176.171 | F2: 8959.2701 | G2: 12176.171 | H2: 8959.2701 | I2: =H2-F2 -> 0 | J2: =G2-E2 -> 0
A3: I_PH_ALCOHOL_POLICY | B3: Alcohol advertising ban | C3: 2025 | D3: dm2 | E3: 1026758.6 | F3: 129383.32 | G3: 1026758.6 | H3: 129383.32 | I3: =H3-F3 -> 0 | J3: =G3-E3 -> 0
A4: I_PH_ALCOHOL_POLICY | B4: Alcohol advertising ban | C4: 2025 | D4: hhd | E4: 115291.16 | F4: 67656.559 | G4: 115291.16 | H4: 67656.559 | I4: =H4-F4 -> 0 | J4: =G4-E4 -> 0
A5: I_PH_ALCOHOL_POLICY | B5: Alcohol advertising ban | C5: 2025 | D5: hstroke | E5: 281662.55 | F5: 263295.7 | G5: 281662.55 | H5: 263295.7 | I5: =H5-F5 -> 0 | J5: =G5-E5 -> 0
A6: I_PH_ALCOHOL_POLICY | B6: Alcohol advertising ban | C6: 2025 | D6: ihd | E6: 612171.63 | F6: 335724.87 | G6: 612171.63 | H6: 335724.87 | I6: =H6-F6 -> 0 | J6: =G6-E6 -> 0
A7: I_PH_ALCOHOL_POLICY | B7: Alcohol advertising ban | C7: 2025 | D7: istroke | E7: 339642.13 | F7: 190841.88 | G7: 339642.13 | H7: 190841.88 | I7: =H7-F7 -> 0 | J7: =G7-E7 -> 0
A8: I_PH_ALCOHOL_POLICY | B8: Alcohol advertising ban | C8: 2025 | D8: rhd | E8: 39660.837 | F8: 5303.4223 | G8: 39660.837 | H8: 5303.4223 | I8: =H8-F8 -> 0 | J8: =G8-E8 -> 0
A9: I_PH_ALCOHOL_POLICY | B9: Alcohol advertising ban | C9: 2026 | D9: cmd | E9: 12568.523 | F9: 9271.1334 | G9: 12568.939 | H9: 9271.1334 | I9: =H9-F9 -> 0 | J9: =G9-E9 -> 0.41573588
A10: I_PH_ALCOHOL_POLICY | B10: Alcohol advertising ban | C10: 2026 | D10: dm2 | E10: 1042135.2 | F10: 137145.83 | G10: 1042135.2 | H10: 137145.83 | I10: =H10-F10 -> 0 | J10: =G10-E10 -> 0
A11: I_PH_ALCOHOL_POLICY | B11: Alcohol advertising ban | C11: 2026 | D11: hhd | E11: 114697.95 | F11: 70326.603 | G11: 114707.99 | H11: 70326.603 | I11: =H11-F11 -> 0 | J11: =G11-E11 -> 10.039487
A12: I_PH_ALCOHOL_POLICY | B12: Alcohol advertising ban | C12: 2026 | D12: hstroke | E12: 282707.86 | F12: 259504.47 | G12: 282722.54 | H12: 259504.47 | I12: =H12-F12 -> 0 | J12: =G12-E12 -> 14.681797
A13: I_PH_ALCOHOL_POLICY | B13: Alcohol advertising ban | C13: 2026 | D13: ihd | E13: 616775.66 | F13: 342960.14 | G13: 616790.03 | H13: 342960.14 | I13: =H13-F13 -> 0 | J13: =G13-E13 -> 14.364856
... A2731: all_public_health | B2731: All selected public-health interventions (combined) | C2731: 2050 | D2731: rhd | E2731: 33927.268 | F2731: 1888.5273 | G2731: 33926.479 | H2731: 1888.515 | I2731: =H2731-F2731 -> -0.012322747 | J2731: =G2731-E2731 -> -0.78926966

Sheet Annual_Cost
A1: scenario | B1: year | C1: intervention_id | D1: cost_record_id | E1: cost_component_key | F1: cost_join_key | G1: cost_scope | H1: population_in_need_measure | I1: population_in_need_fraction | J1: frequency_per_year | K1: unit_cost_usd | L1: pop_scenario | M1: pop_baseline | N1: cost_impl_frac | O1: pin_scenario | P1: pin_baseline | Q1: annual_cost_baseline | R1: annual_cost_scenario | S1: annual_cost_incremental | T1: discount_factor | U1: disc_cost_baseline | V1: disc_cost_scenario | W1: disc_cost_incremental | X1: indonesia_adjusted_flag | Y1: price_year | Z1: review_status | AA1: shared_duplicate_count
A2: I_PH_TOBACCO_TAX | B2: 2025 | C2: I_PH_TOBACCO_TAX | D2: COST_PH_TOB_TAX | E2: CC_PH_TOB_TAX | F2: I_PH_TOBACCO_TAX__C_SHARED | G2: shared-count-once | H2: all | I2: 1 | J2: 1 | K2: 0.004 | L2: 5.7513485e+08 | M2: 5.7513485e+08 | N2: =MIN(MAX((B2-Calculation_Assumptions!$B$5+1)/Calculation_Assumptions!$B$7,0),1) -> 0 | O2: =L2*I2 -> 5.7513485e+08 | P2: =M2*I2 -> 5.7513485e+08 | Q2: =P2*Calculation_Assumptions!$B$14*J2*K2 -> 0 | R2: =O2*N2*J2*K2 -> 0 | S2: =R2-Q2 -> 0 | T2: =1/(1+Calculation_Assumptions!$B$8)^(B2-Calculation_Assumptions!$B$2) -> 1 | U2: =Q2*T2 -> 0 | V2: =R2*T2 -> 0 | W2: =S2*T2 -> 0 | X2: 0 | Y2: 2017 | Z2: Review | AA2: =IF(G2="shared-count-once",COUNTIFS($A$2:$A$807,A2,$B$2:$B$807,B2,$D$2:$D$807,D2),1) -> 1
A3: I_PH_TOBACCO_TAX | B3: 2026 | C3: I_PH_TOBACCO_TAX | D3: COST_PH_TOB_TAX | E3: CC_PH_TOB_TAX | F3: I_PH_TOBACCO_TAX__C_SHARED | G3: shared-count-once | H3: all | I3: 1 | J3: 1 | K3: 0.004 | L3: 5.7926865e+08 | M3: 5.7926865e+08 | N3: =MIN(MAX((B3-Calculation_Assumptions!$B$5+1)/Calculation_Assumptions!$B$7,0),1) -> 0.33333333 | O3: =L3*I3 -> 5.7926865e+08 | P3: =M3*I3 -> 5.7926865e+08 | Q3: =P3*Calculation_Assumptions!$B$14*J3*K3 -> 0 | R3: =O3*N3*J3*K3 -> 772358.2 | S3: =R3-Q3 -> 772358.2 | T3: =1/(1+Calculation_Assumptions!$B$8)^(B3-Calculation_Assumptions!$B$2) -> 0.97087379 | U3: =Q3*T3 -> 0 | V3: =R3*T3 -> 749862.33 | W3: =S3*T3 -> 749862.33 | X3: 0 | Y3: 2017 | Z3: Review | AA3: =IF(G3="shared-count-once",COUNTIFS($A$2:$A$807,A3,$B$2:$B$807,B3,$D$2:$D$807,D3),1) -> 1
A4: I_PH_TOBACCO_TAX | B4: 2027 | C4: I_PH_TOBACCO_TAX | D4: COST_PH_TOB_TAX | E4: CC_PH_TOB_TAX | F4: I_PH_TOBACCO_TAX__C_SHARED | G4: shared-count-once | H4: all | I4: 1 | J4: 1 | K4: 0.004 | L4: 5.8303901e+08 | M4: 5.8303901e+08 | N4: =MIN(MAX((B4-Calculation_Assumptions!$B$5+1)/Calculation_Assumptions!$B$7,0),1) -> 0.66666667 | O4: =L4*I4 -> 5.8303901e+08 | P4: =M4*I4 -> 5.8303901e+08 | Q4: =P4*Calculation_Assumptions!$B$14*J4*K4 -> 0 | R4: =O4*N4*J4*K4 -> 1554770.7 | S4: =R4-Q4 -> 1554770.7 | T4: =1/(1+Calculation_Assumptions!$B$8)^(B4-Calculation_Assumptions!$B$2) -> 0.94259591 | U4: =Q4*T4 -> 0 | V4: =R4*T4 -> 1465520.5 | W4: =S4*T4 -> 1465520.5 | X4: 0 | Y4: 2017 | Z4: Review | AA4: =IF(G4="shared-count-once",COUNTIFS($A$2:$A$807,A4,$B$2:$B$807,B4,$D$2:$D$807,D4),1) -> 1
A5: I_PH_TOBACCO_TAX | B5: 2028 | C5: I_PH_TOBACCO_TAX | D5: COST_PH_TOB_TAX | E5: CC_PH_TOB_TAX | F5: I_PH_TOBACCO_TAX__C_SHARED | G5: shared-count-once | H5: all | I5: 1 | J5: 1 | K5: 0.004 | L5: 5.8703512e+08 | M5: 5.8703512e+08 | N5: =MIN(MAX((B5-Calculation_Assumptions!$B$5+1)/Calculation_Assumptions!$B$7,0),1) -> 1 | O5: =L5*I5 -> 5.8703512e+08 | P5: =M5*I5 -> 5.8703512e+08 | Q5: =P5*Calculation_Assumptions!$B$14*J5*K5 -> 0 | R5: =O5*N5*J5*K5 -> 2348140.5 | S5: =R5-Q5 -> 2348140.5 | T5: =1/(1+Calculation_Assumptions!$B$8)^(B5-Calculation_Assumptions!$B$2) -> 0.91514166 | U5: =Q5*T5 -> 0 | V5: =R5*T5 -> 2148881.2 | W5: =S5*T5 -> 2148881.2 | X5: 0 | Y5: 2017 | Z5: Review | AA5: =IF(G5="shared-count-once",COUNTIFS($A$2:$A$807,A5,$B$2:$B$807,B5,$D$2:$D$807,D5),1) -> 1
A6: I_PH_TOBACCO_TAX | B6: 2029 | C6: I_PH_TOBACCO_TAX | D6: COST_PH_TOB_TAX | E6: CC_PH_TOB_TAX | F6: I_PH_TOBACCO_TAX__C_SHARED | G6: shared-count-once | H6: all | I6: 1 | J6: 1 | K6: 0.004 | L6: 5.9096878e+08 | M6: 5.9096806e+08 | N6: =MIN(MAX((B6-Calculation_Assumptions!$B$5+1)/Calculation_Assumptions!$B$7,0),1) -> 1 | O6: =L6*I6 -> 5.9096878e+08 | P6: =M6*I6 -> 5.9096806e+08 | Q6: =P6*Calculation_Assumptions!$B$14*J6*K6 -> 0 | R6: =O6*N6*J6*K6 -> 2363875.1 | S6: =R6-Q6 -> 2363875.1 | T6: =1/(1+Calculation_Assumptions!$B$8)^(B6-Calculation_Assumptions!$B$2) -> 0.88848705 | U6: =Q6*T6 -> 0 | V6: =R6*T6 -> 2100272.4 | W6: =S6*T6 -> 2100272.4 | X6: 0 | Y6: 2017 | Z6: Review | AA6: =IF(G6="shared-count-once",COUNTIFS($A$2:$A$807,A6,$B$2:$B$807,B6,$D$2:$D$807,D6),1) -> 1
A7: I_PH_TOBACCO_TAX | B7: 2030 | C7: I_PH_TOBACCO_TAX | D7: COST_PH_TOB_TAX | E7: CC_PH_TOB_TAX | F7: I_PH_TOBACCO_TAX__C_SHARED | G7: shared-count-once | H7: all | I7: 1 | J7: 1 | K7: 0.004 | L7: 5.9481054e+08 | M7: 5.9480802e+08 | N7: =MIN(MAX((B7-Calculation_Assumptions!$B$5+1)/Calculation_Assumptions!$B$7,0),1) -> 1 | O7: =L7*I7 -> 5.9481054e+08 | P7: =M7*I7 -> 5.9480802e+08 | Q7: =P7*Calculation_Assumptions!$B$14*J7*K7 -> 0 | R7: =O7*N7*J7*K7 -> 2379242.2 | S7: =R7-Q7 -> 2379242.2 | T7: =1/(1+Calculation_Assumptions!$B$8)^(B7-Calculation_Assumptions!$B$2) -> 0.86260878 | U7: =Q7*T7 -> 0 | V7: =R7*T7 -> 2052355.2 | W7: =S7*T7 -> 2052355.2 | X7: 0 | Y7: 2017 | Z7: Review | AA7: =IF(G7="shared-count-once",COUNTIFS($A$2:$A$807,A7,$B$2:$B$807,B7,$D$2:$D$807,D7),1) -> 1
A8: I_PH_TOBACCO_TAX | B8: 2031 | C8: I_PH_TOBACCO_TAX | D8: COST_PH_TOB_TAX | E8: CC_PH_TOB_TAX | F8: I_PH_TOBACCO_TAX__C_SHARED | G8: shared-count-once | H8: all | I8: 1 | J8: 1 | K8: 0.004 | L8: 5.9857031e+08 | M8: 5.9858138e+08 | N8: =MIN(MAX((B8-Calculation_Assumptions!$B$5+1)/Calculation_Assumptions!$B$7,0),1) -> 1 | O8: =L8*I8 -> 5.9857031e+08 | P8: =M8*I8 -> 5.9858138e+08 | Q8: =P8*Calculation_Assumptions!$B$14*J8*K8 -> 0 | R8: =O8*N8*J8*K8 -> 2394281.2 | S8: =R8-Q8 -> 2394281.2 | T8: =1/(1+Calculation_Assumptions!$B$8)^(B8-Calculation_Assumptions!$B$2) -> 0.83748426 | U8: =Q8*T8 -> 0 | V8: =R8*T8 -> 2005172.8 | W8: =S8*T8 -> 2005172.8 | X8: 0 | Y8: 2017 | Z8: Review | AA8: =IF(G8="shared-count-once",COUNTIFS($A$2:$A$807,A8,$B$2:$B$807,B8,$D$2:$D$807,D8),1) -> 1
A9: I_PH_TOBACCO_TAX | B9: 2032 | C9: I_PH_TOBACCO_TAX | D9: COST_PH_TOB_TAX | E9: CC_PH_TOB_TAX | F9: I_PH_TOBACCO_TAX__C_SHARED | G9: shared-count-once | H9: all | I9: 1 | J9: 1 | K9: 0.004 | L9: 6.0227678e+08 | M9: 6.0228358e+08 | N9: =MIN(MAX((B9-Calculation_Assumptions!$B$5+1)/Calculation_Assumptions!$B$7,0),1) -> 1 | O9: =L9*I9 -> 6.0227678e+08 | P9: =M9*I9 -> 6.0228358e+08 | Q9: =P9*Calculation_Assumptions!$B$14*J9*K9 -> 0 | R9: =O9*N9*J9*K9 -> 2409107.1 | S9: =R9-Q9 -> 2409107.1 | T9: =1/(1+Calculation_Assumptions!$B$8)^(B9-Calculation_Assumptions!$B$2) -> 0.81309151 | U9: =Q9*T9 -> 0 | V9: =R9*T9 -> 1958824.5 | W9: =S9*T9 -> 1958824.5 | X9: 0 | Y9: 2017 | Z9: Review | AA9: =IF(G9="shared-count-once",COUNTIFS($A$2:$A$807,A9,$B$2:$B$807,B9,$D$2:$D$807,D9),1) -> 1
A10: I_PH_TOBACCO_TAX | B10: 2033 | C10: I_PH_TOBACCO_TAX | D10: COST_PH_TOB_TAX | E10: CC_PH_TOB_TAX | F10: I_PH_TOBACCO_TAX__C_SHARED | G10: shared-count-once | H10: all | I10: 1 | J10: 1 | K10: 0.004 | L10: 6.0591057e+08 | M10: 6.059119e+08 | N10: =MIN(MAX((B10-Calculation_Assumptions!$B$5+1)/Calculation_Assumptions!$B$7,0),1) -> 1 | O10: =L10*I10 -> 6.0591057e+08 | P10: =M10*I10 -> 6.059119e+08 | Q10: =P10*Calculation_Assumptions!$B$14*J10*K10 -> 0 | R10: =O10*N10*J10*K10 -> 2423642.3 | S10: =R10-Q10 -> 2423642.3 | T10: =1/(1+Calculation_Assumptions!$B$8)^(B10-Calculation_Assumptions!$B$2) -> 0.78940923 | U10: =Q10*T10 -> 0 | V10: =R10*T10 -> 1913245.6 | W10: =S10*T10 -> 1913245.6 | X10: 0 | Y10: 2017 | Z10: Review | AA10: =IF(G10="shared-count-once",COUNTIFS($A$2:$A$807,A10,$B$2:$B$807,B10,$D$2:$D$807,D10),1) -> 1
A11: I_PH_TOBACCO_TAX | B11: 2034 | C11: I_PH_TOBACCO_TAX | D11: COST_PH_TOB_TAX | E11: CC_PH_TOB_TAX | F11: I_PH_TOBACCO_TAX__C_SHARED | G11: shared-count-once | H11: all | I11: 1 | J11: 1 | K11: 0.004 | L11: 6.0946135e+08 | M11: 6.0945555e+08 | N11: =MIN(MAX((B11-Calculation_Assumptions!$B$5+1)/Calculation_Assumptions!$B$7,0),1) -> 1 | O11: =L11*I11 -> 6.0946135e+08 | P11: =M11*I11 -> 6.0945555e+08 | Q11: =P11*Calculation_Assumptions!$B$14*J11*K11 -> 0 | R11: =O11*N11*J11*K11 -> 2437845.4 | S11: =R11-Q11 -> 2437845.4 | T11: =1/(1+Calculation_Assumptions!$B$8)^(B11-Calculation_Assumptions!$B$2) -> 0.76641673 | U11: =Q11*T11 -> 0 | V11: =R11*T11 -> 1868405.5 | W11: =S11*T11 -> 1868405.5 | X11: 0 | Y11: 2017 | Z11: Review | AA11: =IF(G11="shared-count-once",COUNTIFS($A$2:$A$807,A11,$B$2:$B$807,B11,$D$2:$D$807,D11),1) -> 1
A12: I_PH_TOBACCO_TAX | B12: 2035 | C12: I_PH_TOBACCO_TAX | D12: COST_PH_TOB_TAX | E12: CC_PH_TOB_TAX | F12: I_PH_TOBACCO_TAX__C_SHARED | G12: shared-count-once | H12: all | I12: 1 | J12: 1 | K12: 0.004 | L12: 6.1291813e+08 | M12: 6.1288429e+08 | N12: =MIN(MAX((B12-Calculation_Assumptions!$B$5+1)/Calculation_Assumptions!$B$7,0),1) -> 1 | O12: =L12*I12 -> 6.1291813e+08 | P12: =M12*I12 -> 6.1288429e+08 | Q12: =P12*Calculation_Assumptions!$B$14*J12*K12 -> 0 | R12: =O12*N12*J12*K12 -> 2451672.5 | S12: =R12-Q12 -> 2451672.5 | T12: =1/(1+Calculation_Assumptions!$B$8)^(B12-Calculation_Assumptions!$B$2) -> 0.74409391 | U12: =Q12*T12 -> 0 | V12: =R12*T12 -> 1824274.6 | W12: =S12*T12 -> 1824274.6 | X12: 0 | Y12: 2017 | Z12: Review | AA12: =IF(G12="shared-count-once",COUNTIFS($A$2:$A$807,A12,$B$2:$B$807,B12,$D$2:$D$807,D12),1) -> 1
A13: I_PH_TOBACCO_TAX | B13: 2036 | C13: I_PH_TOBACCO_TAX | D13: COST_PH_TOB_TAX | E13: CC_PH_TOB_TAX | F13: I_PH_TOBACCO_TAX__C_SHARED | G13: shared-count-once | H13: all | I13: 1 | J13: 1 | K13: 0.004 | L13: 6.1628757e+08 | M13: 6.1626205e+08 | N13: =MIN(MAX((B13-Calculation_Assumptions!$B$5+1)/Calculation_Assumptions!$B$7,0),1) -> 1 | O13: =L13*I13 -> 6.1628757e+08 | P13: =M13*I13 -> 6.1626205e+08 | Q13: =P13*Calculation_Assumptions!$B$14*J13*K13 -> 0 | R13: =O13*N13*J13*K13 -> 2465150.3 | S13: =R13-Q13 -> 2465150.3 | T13: =1/(1+Calculation_Assumptions!$B$8)^(B13-Calculation_Assumptions!$B$2) -> 0.72242128 | U13: =Q13*T13 -> 0 | V13: =R13*T13 -> 1780877 | W13: =S13*T13 -> 1780877 | X13: 0 | Y13: 2017 | Z13: Review | AA13: =IF(G13="shared-count-once",COUNTIFS($A$2:$A$807,A13,$B$2:$B$807,B13,$D$2:$D$807,D13),1) -> 1
... A807: all_public_health | B807: 2050 | C807: I_PH_TOB_MEDIA | D807: COST_PH_TOB_MEDIA | E807: CC_PH_TOB_MEDIA | F807: I_PH_TOB_MEDIA__C_SHARED | G807: component-count-once | H807: all | I807: 1 | J807: 1 | K807: 0.0077 | L807: 6.5279915e+08 | M807: 6.5107446e+08 | N807: =MIN(MAX((B807-Calculation_Assumptions!$B$5+1)/Calculation_Assumptions!$B$7,0),1) -> 1 | O807: =L807*I807 -> 6.5279915e+08 | P807: =M807*I807 -> 6.5107446e+08 | Q807: =P807*Calculation_Assumptions!$B$14*J807*K807 -> 0 | R807: =O807*N807*J807*K807 -> 5026553.4 | S807: =R807-Q807 -> 5026553.4 | T807: =1/(1+Calculation_Assumptions!$B$8)^(B807-Calculation_Assumptions!$B$2) -> 0.47760557 | U807: =Q807*T807 -> 0 | V807: =R807*T807 -> 2400709.9 | W807: =S807*T807 -> 2400709.9 | X807: 0 | Y807: 2017 | Z807: Review | AA807: =IF(G807="shared-count-once",COUNTIFS($A$2:$A$807,A807,$B$2:$B$807,B807,$D$2:$D$807,D807),1) -> 1

Sheet Budget_Impact
A1: scenario | B1: year | C1: baseline_cost | D1: scenario_cost | E1: incremental_cost | F1: disc_incremental_cost | G1: cumulative_incremental_cost | H1: cumulative_disc_incremental_cost
A2: I_PH_ALCOHOL_POLICY | B2: 2025 | C2: =SUMIFS(Annual_Cost!$Q$2:$Q$807,Annual_Cost!$A$2:$A$807,A2,Annual_Cost!$B$2:$B$807,B2) -> 0 | D2: =SUMIFS(Annual_Cost!$R$2:$R$807,Annual_Cost!$A$2:$A$807,A2,Annual_Cost!$B$2:$B$807,B2) -> 0 | E2: =SUMIFS(Annual_Cost!$S$2:$S$807,Annual_Cost!$A$2:$A$807,A2,Annual_Cost!$B$2:$B$807,B2) -> 0 | F2: =SUMIFS(Annual_Cost!$W$2:$W$807,Annual_Cost!$A$2:$A$807,A2,Annual_Cost!$B$2:$B$807,B2) -> 0 | G2: =SUMIFS($E$2:E2,$A$2:A2,A2) -> 0 | H2: =SUMIFS($F$2:F2,$A$2:A2,A2) -> 0
A3: I_PH_ALCOHOL_POLICY | B3: 2026 | C3: =SUMIFS(Annual_Cost!$Q$2:$Q$807,Annual_Cost!$A$2:$A$807,A3,Annual_Cost!$B$2:$B$807,B3) -> 0 | D3: =SUMIFS(Annual_Cost!$R$2:$R$807,Annual_Cost!$A$2:$A$807,A3,Annual_Cost!$B$2:$B$807,B3) -> 1081301.5 | E3: =SUMIFS(Annual_Cost!$S$2:$S$807,Annual_Cost!$A$2:$A$807,A3,Annual_Cost!$B$2:$B$807,B3) -> 1081301.5 | F3: =SUMIFS(Annual_Cost!$W$2:$W$807,Annual_Cost!$A$2:$A$807,A3,Annual_Cost!$B$2:$B$807,B3) -> 1049807.3 | G3: =SUMIFS($E$2:E3,$A$2:A3,A3) -> 1081301.5 | H3: =SUMIFS($F$2:F3,$A$2:A3,A3) -> 1049807.3
A4: I_PH_ALCOHOL_POLICY | B4: 2027 | C4: =SUMIFS(Annual_Cost!$Q$2:$Q$807,Annual_Cost!$A$2:$A$807,A4,Annual_Cost!$B$2:$B$807,B4) -> 0 | D4: =SUMIFS(Annual_Cost!$R$2:$R$807,Annual_Cost!$A$2:$A$807,A4,Annual_Cost!$B$2:$B$807,B4) -> 2176679 | E4: =SUMIFS(Annual_Cost!$S$2:$S$807,Annual_Cost!$A$2:$A$807,A4,Annual_Cost!$B$2:$B$807,B4) -> 2176679 | F4: =SUMIFS(Annual_Cost!$W$2:$W$807,Annual_Cost!$A$2:$A$807,A4,Annual_Cost!$B$2:$B$807,B4) -> 2051728.7 | G4: =SUMIFS($E$2:E4,$A$2:A4,A4) -> 3257980.5 | H4: =SUMIFS($F$2:F4,$A$2:A4,A4) -> 3101536
A5: I_PH_ALCOHOL_POLICY | B5: 2028 | C5: =SUMIFS(Annual_Cost!$Q$2:$Q$807,Annual_Cost!$A$2:$A$807,A5,Annual_Cost!$B$2:$B$807,B5) -> 0 | D5: =SUMIFS(Annual_Cost!$R$2:$R$807,Annual_Cost!$A$2:$A$807,A5,Annual_Cost!$B$2:$B$807,B5) -> 3287396.8 | E5: =SUMIFS(Annual_Cost!$S$2:$S$807,Annual_Cost!$A$2:$A$807,A5,Annual_Cost!$B$2:$B$807,B5) -> 3287396.8 | F5: =SUMIFS(Annual_Cost!$W$2:$W$807,Annual_Cost!$A$2:$A$807,A5,Annual_Cost!$B$2:$B$807,B5) -> 3008433.7 | G5: =SUMIFS($E$2:E5,$A$2:A5,A5) -> 6545377.2 | H5: =SUMIFS($F$2:F5,$A$2:A5,A5) -> 6109969.7
A6: I_PH_ALCOHOL_POLICY | B6: 2029 | C6: =SUMIFS(Annual_Cost!$Q$2:$Q$807,Annual_Cost!$A$2:$A$807,A6,Annual_Cost!$B$2:$B$807,B6) -> 0 | D6: =SUMIFS(Annual_Cost!$R$2:$R$807,Annual_Cost!$A$2:$A$807,A6,Annual_Cost!$B$2:$B$807,B6) -> 3309421.5 | E6: =SUMIFS(Annual_Cost!$S$2:$S$807,Annual_Cost!$A$2:$A$807,A6,Annual_Cost!$B$2:$B$807,B6) -> 3309421.5 | F6: =SUMIFS(Annual_Cost!$W$2:$W$807,Annual_Cost!$A$2:$A$807,A6,Annual_Cost!$B$2:$B$807,B6) -> 2940378.2 | G6: =SUMIFS($E$2:E6,$A$2:A6,A6) -> 9854798.8 | H6: =SUMIFS($F$2:F6,$A$2:A6,A6) -> 9050347.9
A7: I_PH_ALCOHOL_POLICY | B7: 2030 | C7: =SUMIFS(Annual_Cost!$Q$2:$Q$807,Annual_Cost!$A$2:$A$807,A7,Annual_Cost!$B$2:$B$807,B7) -> 0 | D7: =SUMIFS(Annual_Cost!$R$2:$R$807,Annual_Cost!$A$2:$A$807,A7,Annual_Cost!$B$2:$B$807,B7) -> 3330925.8 | E7: =SUMIFS(Annual_Cost!$S$2:$S$807,Annual_Cost!$A$2:$A$807,A7,Annual_Cost!$B$2:$B$807,B7) -> 3330925.8 | F7: =SUMIFS(Annual_Cost!$W$2:$W$807,Annual_Cost!$A$2:$A$807,A7,Annual_Cost!$B$2:$B$807,B7) -> 2873285.9 | G7: =SUMIFS($E$2:E7,$A$2:A7,A7) -> 13185725 | H7: =SUMIFS($F$2:F7,$A$2:A7,A7) -> 11923634
A8: I_PH_ALCOHOL_POLICY | B8: 2031 | C8: =SUMIFS(Annual_Cost!$Q$2:$Q$807,Annual_Cost!$A$2:$A$807,A8,Annual_Cost!$B$2:$B$807,B8) -> 0 | D8: =SUMIFS(Annual_Cost!$R$2:$R$807,Annual_Cost!$A$2:$A$807,A8,Annual_Cost!$B$2:$B$807,B8) -> 3351101.3 | E8: =SUMIFS(Annual_Cost!$S$2:$S$807,Annual_Cost!$A$2:$A$807,A8,Annual_Cost!$B$2:$B$807,B8) -> 3351101.3 | F8: =SUMIFS(Annual_Cost!$W$2:$W$807,Annual_Cost!$A$2:$A$807,A8,Annual_Cost!$B$2:$B$807,B8) -> 2806494.6 | G8: =SUMIFS($E$2:E8,$A$2:A8,A8) -> 16536826 | H8: =SUMIFS($F$2:F8,$A$2:A8,A8) -> 14730128
A9: I_PH_ALCOHOL_POLICY | B9: 2032 | C9: =SUMIFS(Annual_Cost!$Q$2:$Q$807,Annual_Cost!$A$2:$A$807,A9,Annual_Cost!$B$2:$B$807,B9) -> 0 | D9: =SUMIFS(Annual_Cost!$R$2:$R$807,Annual_Cost!$A$2:$A$807,A9,Annual_Cost!$B$2:$B$807,B9) -> 3371958.8 | E9: =SUMIFS(Annual_Cost!$S$2:$S$807,Annual_Cost!$A$2:$A$807,A9,Annual_Cost!$B$2:$B$807,B9) -> 3371958.8 | F9: =SUMIFS(Annual_Cost!$W$2:$W$807,Annual_Cost!$A$2:$A$807,A9,Annual_Cost!$B$2:$B$807,B9) -> 2741711.1 | G9: =SUMIFS($E$2:E9,$A$2:A9,A9) -> 19908785 | H9: =SUMIFS($F$2:F9,$A$2:A9,A9) -> 17471839
A10: I_PH_ALCOHOL_POLICY | B10: 2033 | C10: =SUMIFS(Annual_Cost!$Q$2:$Q$807,Annual_Cost!$A$2:$A$807,A10,Annual_Cost!$B$2:$B$807,B10) -> 0 | D10: =SUMIFS(Annual_Cost!$R$2:$R$807,Annual_Cost!$A$2:$A$807,A10,Annual_Cost!$B$2:$B$807,B10) -> 3392296.2 | E10: =SUMIFS(Annual_Cost!$S$2:$S$807,Annual_Cost!$A$2:$A$807,A10,Annual_Cost!$B$2:$B$807,B10) -> 3392296.2 | F10: =SUMIFS(Annual_Cost!$W$2:$W$807,Annual_Cost!$A$2:$A$807,A10,Annual_Cost!$B$2:$B$807,B10) -> 2677909.9 | G10: =SUMIFS($E$2:E10,$A$2:A10,A10) -> 23301081 | H10: =SUMIFS($F$2:F10,$A$2:A10,A10) -> 20149749
A11: I_PH_ALCOHOL_POLICY | B11: 2034 | C11: =SUMIFS(Annual_Cost!$Q$2:$Q$807,Annual_Cost!$A$2:$A$807,A11,Annual_Cost!$B$2:$B$807,B11) -> 0 | D11: =SUMIFS(Annual_Cost!$R$2:$R$807,Annual_Cost!$A$2:$A$807,A11,Annual_Cost!$B$2:$B$807,B11) -> 3412244.4 | E11: =SUMIFS(Annual_Cost!$S$2:$S$807,Annual_Cost!$A$2:$A$807,A11,Annual_Cost!$B$2:$B$807,B11) -> 3412244.4 | F11: =SUMIFS(Annual_Cost!$W$2:$W$807,Annual_Cost!$A$2:$A$807,A11,Annual_Cost!$B$2:$B$807,B11) -> 2615201.2 | G11: =SUMIFS($E$2:E11,$A$2:A11,A11) -> 26713325 | H11: =SUMIFS($F$2:F11,$A$2:A11,A11) -> 22764951
A12: I_PH_ALCOHOL_POLICY | B12: 2035 | C12: =SUMIFS(Annual_Cost!$Q$2:$Q$807,Annual_Cost!$A$2:$A$807,A12,Annual_Cost!$B$2:$B$807,B12) -> 0 | D12: =SUMIFS(Annual_Cost!$R$2:$R$807,Annual_Cost!$A$2:$A$807,A12,Annual_Cost!$B$2:$B$807,B12) -> 3431650.4 | E12: =SUMIFS(Annual_Cost!$S$2:$S$807,Annual_Cost!$A$2:$A$807,A12,Annual_Cost!$B$2:$B$807,B12) -> 3431650.4 | F12: =SUMIFS(Annual_Cost!$W$2:$W$807,Annual_Cost!$A$2:$A$807,A12,Annual_Cost!$B$2:$B$807,B12) -> 2553470.2 | G12: =SUMIFS($E$2:E12,$A$2:A12,A12) -> 30144976 | H12: =SUMIFS($F$2:F12,$A$2:A12,A12) -> 25318421
A13: I_PH_ALCOHOL_POLICY | B13: 2036 | C13: =SUMIFS(Annual_Cost!$Q$2:$Q$807,Annual_Cost!$A$2:$A$807,A13,Annual_Cost!$B$2:$B$807,B13) -> 0 | D13: =SUMIFS(Annual_Cost!$R$2:$R$807,Annual_Cost!$A$2:$A$807,A13,Annual_Cost!$B$2:$B$807,B13) -> 3450547.2 | E13: =SUMIFS(Annual_Cost!$S$2:$S$807,Annual_Cost!$A$2:$A$807,A13,Annual_Cost!$B$2:$B$807,B13) -> 3450547.2 | F13: =SUMIFS(Annual_Cost!$W$2:$W$807,Annual_Cost!$A$2:$A$807,A13,Annual_Cost!$B$2:$B$807,B13) -> 2492748.7 | G13: =SUMIFS($E$2:E13,$A$2:A13,A13) -> 33595523 | H13: =SUMIFS($F$2:F13,$A$2:A13,A13) -> 27811170
... A391: all_public_health | B391: 2050 | C391: =SUMIFS(Annual_Cost!$Q$2:$Q$807,Annual_Cost!$A$2:$A$807,A391,Annual_Cost!$B$2:$B$807,B391) -> 0 | D391: =SUMIFS(Annual_Cost!$R$2:$R$807,Annual_Cost!$A$2:$A$807,A391,Annual_Cost!$B$2:$B$807,B391) -> 55161528 | E391: =SUMIFS(Annual_Cost!$S$2:$S$807,Annual_Cost!$A$2:$A$807,A391,Annual_Cost!$B$2:$B$807,B391) -> 55161528 | F391: =SUMIFS(Annual_Cost!$W$2:$W$807,Annual_Cost!$A$2:$A$807,A391,Annual_Cost!$B$2:$B$807,B391) -> 26345453 | G391: =SUMIFS($E$2:E391,$A$2:A391,A391) -> 1.2617526e+09 | H391: =SUMIFS($F$2:F391,$A$2:A391,A391) -> 8.5880047e+08

Sheet Cost_Effectiveness
A1: scenario | B1: scenario_label | C1: deaths_averted | D1: cases_averted | E1: incremental_cost | F1: disc_incremental_cost | G1: cost_per_death_averted | H1: dominance | I1: reconciliation_status | K1: deaths_averted | L1: cases_averted
A2: all_public_health | B2: All selected public-health interventions (combined) | C2: =SUMIFS(Annual_Mortality!$I$2:$I$2731,Annual_Mortality!$A$2:$A$2731,A2) -> 1194655.9 | D2: =SUMIFS(Annual_Mortality!$J$2:$J$2731,Annual_Mortality!$A$2:$A$2731,A2) -> 3429943.7 | E2: =SUMIFS(Budget_Impact!$E$2:$E$391,Budget_Impact!$A$2:$A$391,A2) -> 1.2617526e+09 | F2: =SUMIFS(Budget_Impact!$F$2:$F$391,Budget_Impact!$A$2:$A$391,A2) -> 8.5880047e+08 | G2: =IF(C2>0,F2/C2,"") -> 718.86847 | H2: =IF(AND(C2>0,F2<0),"Dominant (more health, lower cost)",IF(AND(C2<=0,F2>0),"Dominated (less/no health, higher cost)",IF(AND(C2<=0,F2<=0),"No deaths averted; ratio not defined","USD per death averted"))) -> USD per death averted | I2: =IF(AND(ABS(F2-SUMIFS(Budget_Impact!$F$2:$F$391,Budget_Impact!$A$2:$A$391,A2))<=Calculation_Assumptions!$B$15,ABS(C2-SUMIFS(Annual_Mortality!$I$2:$I$2731,Annual_Mortality!$A$2:$A$2731,A2))<=Calculation_Assumptions!$B$15),"consistent","mismatch") -> consistent | K2: 1599276.5 | L2: 3939514.9 | M2: =+C2/K2 -> 0.74699773 | N2: =+D2/L2 -> 0.87065128
A3: I_PH_SALT_POLICY | B3: Salt policy package | C3: =SUMIFS(Annual_Mortality!$I$2:$I$2731,Annual_Mortality!$A$2:$A$2731,A3) -> 667741.62 | D3: =SUMIFS(Annual_Mortality!$J$2:$J$2731,Annual_Mortality!$A$2:$A$2731,A3) -> 1411355.9 | E3: =SUMIFS(Budget_Impact!$E$2:$E$391,Budget_Impact!$A$2:$A$391,A3) -> 5.2392479e+08 | F3: =SUMIFS(Budget_Impact!$F$2:$F$391,Budget_Impact!$A$2:$A$391,A3) -> 3.5663637e+08 | G3: =IF(C3>0,F3/C3,"") -> 534.09337 | H3: =IF(AND(C3>0,F3<0),"Dominant (more health, lower cost)",IF(AND(C3<=0,F3>0),"Dominated (less/no health, higher cost)",IF(AND(C3<=0,F3<=0),"No deaths averted; ratio not defined","USD per death averted"))) -> USD per death averted | I3: =IF(AND(ABS(F3-SUMIFS(Budget_Impact!$F$2:$F$391,Budget_Impact!$A$2:$A$391,A3))<=Calculation_Assumptions!$B$15,ABS(C3-SUMIFS(Annual_Mortality!$I$2:$I$2731,Annual_Mortality!$A$2:$A$2731,A3))<=Calculation_Assumptions!$B$15),"consistent","mismatch") -> consistent | K3: 930142.18 | L3: 1725153.7 | M3: =+C3/K3 -> 0.71789199 | N3: =+D3/L3 -> 0.81810443
A4: I_PH_SALT_REFORM | B4: Mandatory sodium reformulation | C4: =SUMIFS(Annual_Mortality!$I$2:$I$2731,Annual_Mortality!$A$2:$A$2731,A4) -> 364091.2 | D4: =SUMIFS(Annual_Mortality!$J$2:$J$2731,Annual_Mortality!$A$2:$A$2731,A4) -> 769544.39 | E4: =SUMIFS(Budget_Impact!$E$2:$E$391,Budget_Impact!$A$2:$A$391,A4) -> 1.3094718e+08 | F4: =SUMIFS(Budget_Impact!$F$2:$F$391,Budget_Impact!$A$2:$A$391,A4) -> 89139638 | G4: =IF(C4>0,F4/C4,"") -> 244.82777 | H4: =IF(AND(C4>0,F4<0),"Dominant (more health, lower cost)",IF(AND(C4<=0,F4>0),"Dominated (less/no health, higher cost)",IF(AND(C4<=0,F4<=0),"No deaths averted; ratio not defined","USD per death averted"))) -> USD per death averted | I4: =IF(AND(ABS(F4-SUMIFS(Budget_Impact!$F$2:$F$391,Budget_Impact!$A$2:$A$391,A4))<=Calculation_Assumptions!$B$15,ABS(C4-SUMIFS(Annual_Mortality!$I$2:$I$2731,Annual_Mortality!$A$2:$A$2731,A4))<=Calculation_Assumptions!$B$15),"consistent","mismatch") -> consistent | K4: 506920.96 | L4: 939836.82 | M4: =+C4/K4 -> 0.71824058 | N4: =+D4/L4 -> 0.81880639
A5: I_PH_TOBACCO_TAX | B5: Tobacco tax | C5: =SUMIFS(Annual_Mortality!$I$2:$I$2731,Annual_Mortality!$A$2:$A$2731,A5) -> 258933.43 | D5: =SUMIFS(Annual_Mortality!$J$2:$J$2731,Annual_Mortality!$A$2:$A$2731,A5) -> 1098543.9 | E5: =SUMIFS(Budget_Impact!$E$2:$E$391,Budget_Impact!$A$2:$A$391,A5) -> 59680429 | F5: =SUMIFS(Budget_Impact!$F$2:$F$391,Budget_Impact!$A$2:$A$391,A5) -> 40626972 | G5: =IF(C5>0,F5/C5,"") -> 156.90122 | H5: =IF(AND(C5>0,F5<0),"Dominant (more health, lower cost)",IF(AND(C5<=0,F5>0),"Dominated (less/no health, higher cost)",IF(AND(C5<=0,F5<=0),"No deaths averted; ratio not defined","USD per death averted"))) -> USD per death averted | I5: =IF(AND(ABS(F5-SUMIFS(Budget_Impact!$F$2:$F$391,Budget_Impact!$A$2:$A$391,A5))<=Calculation_Assumptions!$B$15,ABS(C5-SUMIFS(Annual_Mortality!$I$2:$I$2731,Annual_Mortality!$A$2:$A$2731,A5))<=Calculation_Assumptions!$B$15),"consistent","mismatch") -> consistent | K5: 344357.5 | L5: 1220850.5 | M5: =+C5/K5 -> 0.75193202 | N5: =+D5/L5 -> 0.89981856
A6: I_PH_SALT_FOPL | B6: Sodium front-of-pack labelling | C6: =SUMIFS(Annual_Mortality!$I$2:$I$2731,Annual_Mortality!$A$2:$A$2731,A6) -> 182978.92 | D6: =SUMIFS(Annual_Mortality!$J$2:$J$2731,Annual_Mortality!$A$2:$A$2731,A6) -> 386741.83 | E6: =SUMIFS(Budget_Impact!$E$2:$E$391,Budget_Impact!$A$2:$A$391,A6) -> 1.309235e+08 | F6: =SUMIFS(Budget_Impact!$F$2:$F$391,Budget_Impact!$A$2:$A$391,A6) -> 89125743 | G6: =IF(C6>0,F6/C6,"") -> 487.08203 | H6: =IF(AND(C6>0,F6<0),"Dominant (more health, lower cost)",IF(AND(C6<=0,F6>0),"Dominated (less/no health, higher cost)",IF(AND(C6<=0,F6<=0),"No deaths averted; ratio not defined","USD per death averted"))) -> USD per death averted | I6: =IF(AND(ABS(F6-SUMIFS(Budget_Impact!$F$2:$F$391,Budget_Impact!$A$2:$A$391,A6))<=Calculation_Assumptions!$B$15,ABS(C6-SUMIFS(Annual_Mortality!$I$2:$I$2731,Annual_Mortality!$A$2:$A$2731,A6))<=Calculation_Assumptions!$B$15),"consistent","mismatch") -> consistent | K6: 254686.12 | L6: 472082.19 | M6: =+C6/K6 -> 0.71844872 | N6: =+D6/L6 -> 0.81922563
A7: I_PH_TFA_POLICY | B7: Industrial trans-fat elimination regulation | C7: =SUMIFS(Annual_Mortality!$I$2:$I$2731,Annual_Mortality!$A$2:$A$2731,A7) -> 133571.29 | D7: =SUMIFS(Annual_Mortality!$J$2:$J$2731,Annual_Mortality!$A$2:$A$2731,A7) -> 334789.09 | E7: =SUMIFS(Budget_Impact!$E$2:$E$391,Budget_Impact!$A$2:$A$391,A7) -> 1.2979178e+08 | F7: =SUMIFS(Budget_Impact!$F$2:$F$391,Budget_Impact!$A$2:$A$391,A7) -> 88356205 | G7: =IF(C7>0,F7/C7,"") -> 661.49097 | H7: =IF(AND(C7>0,F7<0),"Dominant (more health, lower cost)",IF(AND(C7<=0,F7>0),"Dominated (less/no health, higher cost)",IF(AND(C7<=0,F7<=0),"No deaths averted; ratio not defined","USD per death averted"))) -> USD per death averted | I7: =IF(AND(ABS(F7-SUMIFS(Budget_Impact!$F$2:$F$391,Budget_Impact!$A$2:$A$391,A7))<=Calculation_Assumptions!$B$15,ABS(C7-SUMIFS(Annual_Mortality!$I$2:$I$2731,Annual_Mortality!$A$2:$A$2731,A7))<=Calculation_Assumptions!$B$15),"consistent","mismatch") -> consistent | K7: 178538.44 | L7: 330912.97 | M7: =+C7/K7 -> 0.74813747 | N7: =+D7/L7 -> 1.0117134
A8: I_PH_SALT_ENV | B8: Supportive public-institution environment | C8: =SUMIFS(Annual_Mortality!$I$2:$I$2731,Annual_Mortality!$A$2:$A$2731,A8) -> 128281.94 | D8: =SUMIFS(Annual_Mortality!$J$2:$J$2731,Annual_Mortality!$A$2:$A$2731,A8) -> 271134.31 | E8: =SUMIFS(Budget_Impact!$E$2:$E$391,Budget_Impact!$A$2:$A$391,A8) -> 1.3091095e+08 | F8: =SUMIFS(Budget_Impact!$F$2:$F$391,Budget_Impact!$A$2:$A$391,A8) -> 89118158 | G8: =IF(C8>0,F8/C8,"") -> 694.70541 | H8: =IF(AND(C8>0,F8<0),"Dominant (more health, lower cost)",IF(AND(C8<=0,F8>0),"Dominated (less/no health, higher cost)",IF(AND(C8<=0,F8<=0),"No deaths averted; ratio not defined","USD per death averted"))) -> USD per death averted | I8: =IF(AND(ABS(F8-SUMIFS(Budget_Impact!$F$2:$F$391,Budget_Impact!$A$2:$A$391,A8))<=Calculation_Assumptions!$B$15,ABS(C8-SUMIFS(Annual_Mortality!$I$2:$I$2731,Annual_Mortality!$A$2:$A$2731,A8))<=Calculation_Assumptions!$B$15),"consistent","mismatch") -> consistent | K8: 158707.59 | L8: 562301.93 | M8: =+C8/K8 -> 0.80829115 | N8: =+D8/L8 -> 0.48218635
A9: I_PH_TOBACCO_POLICY | B9: Tobacco policy package | C9: =SUMIFS(Annual_Mortality!$I$2:$I$2731,Annual_Mortality!$A$2:$A$2731,A9) -> 119354.88 | D9: =SUMIFS(Annual_Mortality!$J$2:$J$2731,Annual_Mortality!$A$2:$A$2731,A9) -> 506117.1 | E9: =SUMIFS(Budget_Impact!$E$2:$E$391,Budget_Impact!$A$2:$A$391,A9) -> 3.4462018e+08 | F9: =SUMIFS(Budget_Impact!$F$2:$F$391,Budget_Impact!$A$2:$A$391,A9) -> 2.3460165e+08 | G9: =IF(C9>0,F9/C9,"") -> 1965.5808 | H9: =IF(AND(C9>0,F9<0),"Dominant (more health, lower cost)",IF(AND(C9<=0,F9>0),"Dominated (less/no health, higher cost)",IF(AND(C9<=0,F9<=0),"No deaths averted; ratio not defined","USD per death averted"))) -> USD per death averted | I9: =IF(AND(ABS(F9-SUMIFS(Budget_Impact!$F$2:$F$391,Budget_Impact!$A$2:$A$391,A9))<=Calculation_Assumptions!$B$15,ABS(C9-SUMIFS(Annual_Mortality!$I$2:$I$2731,Annual_Mortality!$A$2:$A$2731,A9))<=Calculation_Assumptions!$B$15),"consistent","mismatch") -> consistent | K9: 144888.77 | L9: 343401.54 | M9: =+C9/K9 -> 0.82376898 | N9: =+D9/L9 -> 1.4738347
A10: I_PH_TOB_MEDIA | B10: Tobacco mass-media campaign | C10: =SUMIFS(Annual_Mortality!$I$2:$I$2731,Annual_Mortality!$A$2:$A$2731,A10) -> 48633.086 | D10: =SUMIFS(Annual_Mortality!$J$2:$J$2731,Annual_Mortality!$A$2:$A$2731,A10) -> 206295.76 | E10: =SUMIFS(Budget_Impact!$E$2:$E$391,Budget_Impact!$A$2:$A$391,A10) -> 1.1486741e+08 | F10: =SUMIFS(Budget_Impact!$F$2:$F$391,Budget_Impact!$A$2:$A$391,A10) -> 78197380 | G10: =IF(C10>0,F10/C10,"") -> 1607.905 | H10: =IF(AND(C10>0,F10<0),"Dominant (more health, lower cost)",IF(AND(C10<=0,F10>0),"Dominated (less/no health, higher cost)",IF(AND(C10<=0,F10<=0),"No deaths averted; ratio not defined","USD per death averted"))) -> USD per death averted | I10: =IF(AND(ABS(F10-SUMIFS(Budget_Impact!$F$2:$F$391,Budget_Impact!$A$2:$A$391,A10))<=Calculation_Assumptions!$B$15,ABS(C10-SUMIFS(Annual_Mortality!$I$2:$I$2731,Annual_Mortality!$A$2:$A$2731,A10))<=Calculation_Assumptions!$B$15),"consistent","mismatch") -> consistent | K10: 64652.365 | L10: 229152.71 | M10: =+C10/K10 -> 0.75222439 | N10: =+D10/L10 -> 0.90025453
A11: I_PH_TOB_CLEAN_AIR | B11: Smoke-free / clean-air law | C11: =SUMIFS(Annual_Mortality!$I$2:$I$2731,Annual_Mortality!$A$2:$A$2731,A11) -> 41149.061 | D11: =SUMIFS(Annual_Mortality!$J$2:$J$2731,Annual_Mortality!$A$2:$A$2731,A11) -> 174548.41 | E11: =SUMIFS(Budget_Impact!$E$2:$E$391,Budget_Impact!$A$2:$A$391,A11) -> 1.1485496e+08 | F11: =SUMIFS(Budget_Impact!$F$2:$F$391,Budget_Impact!$A$2:$A$391,A11) -> 78187811 | G11: =IF(C11>0,F11/C11,"") -> 1900.1117 | H11: =IF(AND(C11>0,F11<0),"Dominant (more health, lower cost)",IF(AND(C11<=0,F11>0),"Dominated (less/no health, higher cost)",IF(AND(C11<=0,F11<=0),"No deaths averted; ratio not defined","USD per death averted"))) -> USD per death averted | I11: =IF(AND(ABS(F11-SUMIFS(Budget_Impact!$F$2:$F$391,Budget_Impact!$A$2:$A$391,A11))<=Calculation_Assumptions!$B$15,ABS(C11-SUMIFS(Annual_Mortality!$I$2:$I$2731,Annual_Mortality!$A$2:$A$2731,A11))<=Calculation_Assumptions!$B$15),"consistent","mismatch") -> consistent | K11: 54702.418 | L11: 193884.5 | M11: =+C11/K11 -> 0.75223478 | N11: =+D11/L11 -> 0.90027004
A12: I_PH_SSB_TAX | B12: Sugar-sweetened beverage tax | C12: =SUMIFS(Annual_Mortality!$I$2:$I$2731,Annual_Mortality!$A$2:$A$2731,A12) -> 34788.231 | D12: =SUMIFS(Annual_Mortality!$J$2:$J$2731,Annual_Mortality!$A$2:$A$2731,A12) -> 142391.3 | E12: =SUMIFS(Budget_Impact!$E$2:$E$391,Budget_Impact!$A$2:$A$391,A12) -> 59670660 | F12: =SUMIFS(Budget_Impact!$F$2:$F$391,Budget_Impact!$A$2:$A$391,A12) -> 40621571 | G12: =IF(C12>0,F12/C12,"") -> 1167.6814 | H12: =IF(AND(C12>0,F12<0),"Dominant (more health, lower cost)",IF(AND(C12<=0,F12>0),"Dominated (less/no health, higher cost)",IF(AND(C12<=0,F12<=0),"No deaths averted; ratio not defined","USD per death averted"))) -> USD per death averted | I12: =IF(AND(ABS(F12-SUMIFS(Budget_Impact!$F$2:$F$391,Budget_Impact!$A$2:$A$391,A12))<=Calculation_Assumptions!$B$15,ABS(C12-SUMIFS(Annual_Mortality!$I$2:$I$2731,Annual_Mortality!$A$2:$A$2731,A12))<=Calculation_Assumptions!$B$15),"consistent","mismatch") -> consistent | K12: 43286.748 | L12: 150767.71 | M12: =+C12/K12 -> 0.80366932 | N12: =+D12/L12 -> 0.94444167
A13: I_PH_TOB_AD_BAN | B13: Tobacco advertising ban | C13: =SUMIFS(Annual_Mortality!$I$2:$I$2731,Annual_Mortality!$A$2:$A$2731,A13) -> 29924.396 | D13: =SUMIFS(Annual_Mortality!$J$2:$J$2731,Annual_Mortality!$A$2:$A$2731,A13) -> 126933.88 | E13: =SUMIFS(Budget_Impact!$E$2:$E$391,Budget_Impact!$A$2:$A$391,A13) -> 1.1486585e+08 | F13: =SUMIFS(Budget_Impact!$F$2:$F$391,Budget_Impact!$A$2:$A$391,A13) -> 78196313 | G13: =IF(C13>0,F13/C13,"") -> 2613.1292 | H13: =IF(AND(C13>0,F13<0),"Dominant (more health, lower cost)",IF(AND(C13<=0,F13>0),"Dominated (less/no health, higher cost)",IF(AND(C13<=0,F13<=0),"No deaths averted; ratio not defined","USD per death averted"))) -> USD per death averted | I13: =IF(AND(ABS(F13-SUMIFS(Budget_Impact!$F$2:$F$391,Budget_Impact!$A$2:$A$391,A13))<=Calculation_Assumptions!$B$15,ABS(C13-SUMIFS(Annual_Mortality!$I$2:$I$2731,Annual_Mortality!$A$2:$A$2731,A13))<=Calculation_Assumptions!$B$15),"consistent","mismatch") -> consistent | K13: 39779.837 | L13: 140991.7 | M13: =+C13/K13 -> 0.75225035 | N13: =+D13/L13 -> 0.9002933
... A16: I_PH_SALT_MEDIA | B16: Sodium mass-media campaign | C16: =SUMIFS(Annual_Mortality!$I$2:$I$2731,Annual_Mortality!$A$2:$A$2731,A16) -> 0 | D16: =SUMIFS(Annual_Mortality!$J$2:$J$2731,Annual_Mortality!$A$2:$A$2731,A16) -> 0 | E16: =SUMIFS(Budget_Impact!$E$2:$E$391,Budget_Impact!$A$2:$A$391,A16) -> 1.3089977e+08 | F16: =SUMIFS(Budget_Impact!$F$2:$F$391,Budget_Impact!$A$2:$A$391,A16) -> 89112105 | G16: =IF(C16>0,F16/C16,"") | H16: =IF(AND(C16>0,F16<0),"Dominant (more health, lower cost)",IF(AND(C16<=0,F16>0),"Dominated (less/no health, higher cost)",IF(AND(C16<=0,F16<=0),"No deaths averted; ratio not defined","USD per death averted"))) -> Dominated (less/no health, higher cost) | I16: =IF(AND(ABS(F16-SUMIFS(Budget_Impact!$F$2:$F$391,Budget_Impact!$A$2:$A$391,A16))<=Calculation_Assumptions!$B$15,ABS(C16-SUMIFS(Annual_Mortality!$I$2:$I$2731,Annual_Mortality!$A$2:$A$2731,A16))<=Calculation_Assumptions!$B$15),"consistent","mismatch") -> consistent | K16: 0 | L16: 0 | M16: =+C16/K16 -> #DIV/0! | N16: =+D16/L16 -> #DIV/0!

Sheet Child_Intervention_Summary
A1: scenario | B1: scenario_label | C1: scenario_level | D1: scenario_role | E1: parent_package_id | F1: parent_package_name | G1: intervention_ids | H1: component_order | I1: modeled_cases | J1: baseline_cases | K1: cases_averted | L1: modeled_deaths | M1: baseline_deaths | N1: deaths_averted | O1: incremental_cost | P1: disc_incremental_cost | Q1: cost_per_case_averted | R1: cost_per_death_averted | S1: status
A2: I_PH_TOBACCO_TAX | B2: Tobacco tax | C2: standalone | D2: standalone | G2: I_PH_TOBACCO_TAX | H2: 1 | I2: =SUMIFS(Annual_Mortality!$E$2:$E$2731,Annual_Mortality!$A$2:$A$2731,A2) -> 69191609 | J2: =SUMIFS(Annual_Mortality!$G$2:$G$2731,Annual_Mortality!$A$2:$A$2731,A2) -> 70290153 | K2: =SUMIFS(Annual_Mortality!$J$2:$J$2731,Annual_Mortality!$A$2:$A$2731,A2) -> 1098543.9 | L2: =SUMIFS(Annual_Mortality!$F$2:$F$2731,Annual_Mortality!$A$2:$A$2731,A2) -> 30941167 | M2: =SUMIFS(Annual_Mortality!$H$2:$H$2731,Annual_Mortality!$A$2:$A$2731,A2) -> 31200100 | N2: =SUMIFS(Annual_Mortality!$I$2:$I$2731,Annual_Mortality!$A$2:$A$2731,A2) -> 258933.43 | O2: =SUMIFS(Budget_Impact!$E$2:$E$391,Budget_Impact!$A$2:$A$391,A2) -> 59680429 | P2: =SUMIFS(Budget_Impact!$F$2:$F$391,Budget_Impact!$A$2:$A$391,A2) -> 40626972 | Q2: =IF(K2>0,P2/K2,"") -> 36.982564 | R2: =IF(N2>0,P2/N2,"") -> 156.90122 | S2: =IF(AND(K2<=0,N2<=0),"no incremental health effect",IF(AND(P2<0,OR(K2>0,N2>0)),"Dominant (more health, lower cost)",IF(N2>0,"USD per death averted","USD per case averted"))) -> USD per death averted
A3: I_PH_ALCOHOL_TAX | B3: Alcohol tax | C3: standalone | D3: standalone | G3: I_PH_ALCOHOL_TAX | H3: 1 | I3: =SUMIFS(Annual_Mortality!$E$2:$E$2731,Annual_Mortality!$A$2:$A$2731,A3) -> 70284408 | J3: =SUMIFS(Annual_Mortality!$G$2:$G$2731,Annual_Mortality!$A$2:$A$2731,A3) -> 70290153 | K3: =SUMIFS(Annual_Mortality!$J$2:$J$2731,Annual_Mortality!$A$2:$A$2731,A3) -> 5745.6951 | L3: =SUMIFS(Annual_Mortality!$F$2:$F$2731,Annual_Mortality!$A$2:$A$2731,A3) -> 31197154 | M3: =SUMIFS(Annual_Mortality!$H$2:$H$2731,Annual_Mortality!$A$2:$A$2731,A3) -> 31200100 | N3: =SUMIFS(Annual_Mortality!$I$2:$I$2731,Annual_Mortality!$A$2:$A$2731,A3) -> 2946.3613 | O3: =SUMIFS(Budget_Impact!$E$2:$E$391,Budget_Impact!$A$2:$A$391,A3) -> 59669535 | P3: =SUMIFS(Budget_Impact!$F$2:$F$391,Budget_Impact!$A$2:$A$391,A3) -> 40620997 | Q3: =IF(K3>0,P3/K3,"") -> 7069.8142 | R3: =IF(N3>0,P3/N3,"") -> 13786.835 | S3: =IF(AND(K3<=0,N3<=0),"no incremental health effect",IF(AND(P3<0,OR(K3>0,N3>0)),"Dominant (more health, lower cost)",IF(N3>0,"USD per death averted","USD per case averted"))) -> USD per death averted
A4: I_PH_TOB_CLEAN_AIR | B4: Smoke-free / clean-air law | C4: standalone | D4: child | E4: I_PH_TOBACCO_POLICY | F4: Tobacco policy package | G4: I_PH_TOB_CLEAN_AIR | H4: 1 | I4: =SUMIFS(Annual_Mortality!$E$2:$E$2731,Annual_Mortality!$A$2:$A$2731,A4) -> 70115605 | J4: =SUMIFS(Annual_Mortality!$G$2:$G$2731,Annual_Mortality!$A$2:$A$2731,A4) -> 70290153 | K4: =SUMIFS(Annual_Mortality!$J$2:$J$2731,Annual_Mortality!$A$2:$A$2731,A4) -> 174548.41 | L4: =SUMIFS(Annual_Mortality!$F$2:$F$2731,Annual_Mortality!$A$2:$A$2731,A4) -> 31158951 | M4: =SUMIFS(Annual_Mortality!$H$2:$H$2731,Annual_Mortality!$A$2:$A$2731,A4) -> 31200100 | N4: =SUMIFS(Annual_Mortality!$I$2:$I$2731,Annual_Mortality!$A$2:$A$2731,A4) -> 41149.061 | O4: =SUMIFS(Budget_Impact!$E$2:$E$391,Budget_Impact!$A$2:$A$391,A4) -> 1.1485496e+08 | P4: =SUMIFS(Budget_Impact!$F$2:$F$391,Budget_Impact!$A$2:$A$391,A4) -> 78187811 | Q4: =IF(K4>0,P4/K4,"") -> 447.94343 | R4: =IF(N4>0,P4/N4,"") -> 1900.1117 | S4: =IF(AND(K4<=0,N4<=0),"no incremental health effect",IF(AND(P4<0,OR(K4>0,N4>0)),"Dominant (more health, lower cost)",IF(N4>0,"USD per death averted","USD per case averted"))) -> USD per death averted
A5: I_PH_TOB_MEDIA | B5: Tobacco mass-media campaign | C5: standalone | D5: child | E5: I_PH_TOBACCO_POLICY | F5: Tobacco policy package | G5: I_PH_TOB_MEDIA | H5: 2 | I5: =SUMIFS(Annual_Mortality!$E$2:$E$2731,Annual_Mortality!$A$2:$A$2731,A5) -> 70083858 | J5: =SUMIFS(Annual_Mortality!$G$2:$G$2731,Annual_Mortality!$A$2:$A$2731,A5) -> 70290153 | K5: =SUMIFS(Annual_Mortality!$J$2:$J$2731,Annual_Mortality!$A$2:$A$2731,A5) -> 206295.76 | L5: =SUMIFS(Annual_Mortality!$F$2:$F$2731,Annual_Mortality!$A$2:$A$2731,A5) -> 31151467 | M5: =SUMIFS(Annual_Mortality!$H$2:$H$2731,Annual_Mortality!$A$2:$A$2731,A5) -> 31200100 | N5: =SUMIFS(Annual_Mortality!$I$2:$I$2731,Annual_Mortality!$A$2:$A$2731,A5) -> 48633.086 | O5: =SUMIFS(Budget_Impact!$E$2:$E$391,Budget_Impact!$A$2:$A$391,A5) -> 1.1486741e+08 | P5: =SUMIFS(Budget_Impact!$F$2:$F$391,Budget_Impact!$A$2:$A$391,A5) -> 78197380 | Q5: =IF(K5>0,P5/K5,"") -> 379.05471 | R5: =IF(N5>0,P5/N5,"") -> 1607.905 | S5: =IF(AND(K5<=0,N5<=0),"no incremental health effect",IF(AND(P5<0,OR(K5>0,N5>0)),"Dominant (more health, lower cost)",IF(N5>0,"USD per death averted","USD per case averted"))) -> USD per death averted
A6: I_PH_TOB_AD_BAN | B6: Tobacco advertising ban | C6: standalone | D6: child | E6: I_PH_TOBACCO_POLICY | F6: Tobacco policy package | G6: I_PH_TOB_AD_BAN | H6: 3 | I6: =SUMIFS(Annual_Mortality!$E$2:$E$2731,Annual_Mortality!$A$2:$A$2731,A6) -> 70163220 | J6: =SUMIFS(Annual_Mortality!$G$2:$G$2731,Annual_Mortality!$A$2:$A$2731,A6) -> 70290153 | K6: =SUMIFS(Annual_Mortality!$J$2:$J$2731,Annual_Mortality!$A$2:$A$2731,A6) -> 126933.88 | L6: =SUMIFS(Annual_Mortality!$F$2:$F$2731,Annual_Mortality!$A$2:$A$2731,A6) -> 31170176 | M6: =SUMIFS(Annual_Mortality!$H$2:$H$2731,Annual_Mortality!$A$2:$A$2731,A6) -> 31200100 | N6: =SUMIFS(Annual_Mortality!$I$2:$I$2731,Annual_Mortality!$A$2:$A$2731,A6) -> 29924.396 | O6: =SUMIFS(Budget_Impact!$E$2:$E$391,Budget_Impact!$A$2:$A$391,A6) -> 1.1486585e+08 | P6: =SUMIFS(Budget_Impact!$F$2:$F$391,Budget_Impact!$A$2:$A$391,A6) -> 78196313 | Q6: =IF(K6>0,P6/K6,"") -> 616.03972 | R6: =IF(N6>0,P6/N6,"") -> 2613.1292 | S6: =IF(AND(K6<=0,N6<=0),"no incremental health effect",IF(AND(P6<0,OR(K6>0,N6>0)),"Dominant (more health, lower cost)",IF(N6>0,"USD per death averted","USD per case averted"))) -> USD per death averted
A7: I_PH_ALCOHOL_POLICY | B7: Alcohol advertising ban | C7: standalone | D7: standalone | G7: I_PH_ALCOHOL_POLICY | H7: 1 | I7: =SUMIFS(Annual_Mortality!$E$2:$E$2731,Annual_Mortality!$A$2:$A$2731,A7) -> 70283845 | J7: =SUMIFS(Annual_Mortality!$G$2:$G$2731,Annual_Mortality!$A$2:$A$2731,A7) -> 70290153 | K7: =SUMIFS(Annual_Mortality!$J$2:$J$2731,Annual_Mortality!$A$2:$A$2731,A7) -> 6308.4794 | L7: =SUMIFS(Annual_Mortality!$F$2:$F$2731,Annual_Mortality!$A$2:$A$2731,A7) -> 31196865 | M7: =SUMIFS(Annual_Mortality!$H$2:$H$2731,Annual_Mortality!$A$2:$A$2731,A7) -> 31200100 | N7: =SUMIFS(Annual_Mortality!$I$2:$I$2731,Annual_Mortality!$A$2:$A$2731,A7) -> 3234.9525 | O7: =SUMIFS(Budget_Impact!$E$2:$E$391,Budget_Impact!$A$2:$A$391,A7) -> 83530932 | P7: =SUMIFS(Budget_Impact!$F$2:$F$391,Budget_Impact!$A$2:$A$391,A7) -> 56864659 | Q7: =IF(K7>0,P7/K7,"") -> 9014.004 | R7: =IF(N7>0,P7/N7,"") -> 17578.205 | S7: =IF(AND(K7<=0,N7<=0),"no incremental health effect",IF(AND(P7<0,OR(K7>0,N7>0)),"Dominant (more health, lower cost)",IF(N7>0,"USD per death averted","USD per case averted"))) -> USD per death averted
A8: I_PH_SALT_REFORM | B8: Mandatory sodium reformulation | C8: standalone | D8: child | E8: I_PH_SALT_POLICY | F8: Salt policy package | G8: I_PH_SALT_REFORM | H8: 1 | I8: =SUMIFS(Annual_Mortality!$E$2:$E$2731,Annual_Mortality!$A$2:$A$2731,A8) -> 69520609 | J8: =SUMIFS(Annual_Mortality!$G$2:$G$2731,Annual_Mortality!$A$2:$A$2731,A8) -> 70290153 | K8: =SUMIFS(Annual_Mortality!$J$2:$J$2731,Annual_Mortality!$A$2:$A$2731,A8) -> 769544.39 | L8: =SUMIFS(Annual_Mortality!$F$2:$F$2731,Annual_Mortality!$A$2:$A$2731,A8) -> 30836009 | M8: =SUMIFS(Annual_Mortality!$H$2:$H$2731,Annual_Mortality!$A$2:$A$2731,A8) -> 31200100 | N8: =SUMIFS(Annual_Mortality!$I$2:$I$2731,Annual_Mortality!$A$2:$A$2731,A8) -> 364091.2 | O8: =SUMIFS(Budget_Impact!$E$2:$E$391,Budget_Impact!$A$2:$A$391,A8) -> 1.3094718e+08 | P8: =SUMIFS(Budget_Impact!$F$2:$F$391,Budget_Impact!$A$2:$A$391,A8) -> 89139638 | Q8: =IF(K8>0,P8/K8,"") -> 115.8343 | R8: =IF(N8>0,P8/N8,"") -> 244.82777 | S8: =IF(AND(K8<=0,N8<=0),"no incremental health effect",IF(AND(P8<0,OR(K8>0,N8>0)),"Dominant (more health, lower cost)",IF(N8>0,"USD per death averted","USD per case averted"))) -> USD per death averted
A9: I_PH_SALT_FOPL | B9: Sodium front-of-pack labelling | C9: standalone | D9: child | E9: I_PH_SALT_POLICY | F9: Salt policy package | G9: I_PH_SALT_FOPL | H9: 2 | I9: =SUMIFS(Annual_Mortality!$E$2:$E$2731,Annual_Mortality!$A$2:$A$2731,A9) -> 69903412 | J9: =SUMIFS(Annual_Mortality!$G$2:$G$2731,Annual_Mortality!$A$2:$A$2731,A9) -> 70290153 | K9: =SUMIFS(Annual_Mortality!$J$2:$J$2731,Annual_Mortality!$A$2:$A$2731,A9) -> 386741.83 | L9: =SUMIFS(Annual_Mortality!$F$2:$F$2731,Annual_Mortality!$A$2:$A$2731,A9) -> 31017121 | M9: =SUMIFS(Annual_Mortality!$H$2:$H$2731,Annual_Mortality!$A$2:$A$2731,A9) -> 31200100 | N9: =SUMIFS(Annual_Mortality!$I$2:$I$2731,Annual_Mortality!$A$2:$A$2731,A9) -> 182978.92 | O9: =SUMIFS(Budget_Impact!$E$2:$E$391,Budget_Impact!$A$2:$A$391,A9) -> 1.309235e+08 | P9: =SUMIFS(Budget_Impact!$F$2:$F$391,Budget_Impact!$A$2:$A$391,A9) -> 89125743 | Q9: =IF(K9>0,P9/K9,"") -> 230.45282 | R9: =IF(N9>0,P9/N9,"") -> 487.08203 | S9: =IF(AND(K9<=0,N9<=0),"no incremental health effect",IF(AND(P9<0,OR(K9>0,N9>0)),"Dominant (more health, lower cost)",IF(N9>0,"USD per death averted","USD per case averted"))) -> USD per death averted
A10: I_PH_SALT_MEDIA | B10: Sodium mass-media campaign | C10: standalone | D10: child | E10: I_PH_SALT_POLICY | F10: Salt policy package | G10: I_PH_SALT_MEDIA | H10: 3 | I10: =SUMIFS(Annual_Mortality!$E$2:$E$2731,Annual_Mortality!$A$2:$A$2731,A10) -> 70290153 | J10: =SUMIFS(Annual_Mortality!$G$2:$G$2731,Annual_Mortality!$A$2:$A$2731,A10) -> 70290153 | K10: =SUMIFS(Annual_Mortality!$J$2:$J$2731,Annual_Mortality!$A$2:$A$2731,A10) -> 0 | L10: =SUMIFS(Annual_Mortality!$F$2:$F$2731,Annual_Mortality!$A$2:$A$2731,A10) -> 31200100 | M10: =SUMIFS(Annual_Mortality!$H$2:$H$2731,Annual_Mortality!$A$2:$A$2731,A10) -> 31200100 | N10: =SUMIFS(Annual_Mortality!$I$2:$I$2731,Annual_Mortality!$A$2:$A$2731,A10) -> 0 | O10: =SUMIFS(Budget_Impact!$E$2:$E$391,Budget_Impact!$A$2:$A$391,A10) -> 1.3089977e+08 | P10: =SUMIFS(Budget_Impact!$F$2:$F$391,Budget_Impact!$A$2:$A$391,A10) -> 89112105 | Q10: =IF(K10>0,P10/K10,"") | R10: =IF(N10>0,P10/N10,"") | S10: =IF(AND(K10<=0,N10<=0),"no incremental health effect",IF(AND(P10<0,OR(K10>0,N10>0)),"Dominant (more health, lower cost)",IF(N10>0,"USD per death averted","USD per case averted"))) -> no incremental health effect
A11: I_PH_SALT_ENV | B11: Supportive public-institution environment | C11: standalone | D11: child | E11: I_PH_SALT_POLICY | F11: Salt policy package | G11: I_PH_SALT_ENV | H11: 4 | I11: =SUMIFS(Annual_Mortality!$E$2:$E$2731,Annual_Mortality!$A$2:$A$2731,A11) -> 70019019 | J11: =SUMIFS(Annual_Mortality!$G$2:$G$2731,Annual_Mortality!$A$2:$A$2731,A11) -> 70290153 | K11: =SUMIFS(Annual_Mortality!$J$2:$J$2731,Annual_Mortality!$A$2:$A$2731,A11) -> 271134.31 | L11: =SUMIFS(Annual_Mortality!$F$2:$F$2731,Annual_Mortality!$A$2:$A$2731,A11) -> 31071818 | M11: =SUMIFS(Annual_Mortality!$H$2:$H$2731,Annual_Mortality!$A$2:$A$2731,A11) -> 31200100 | N11: =SUMIFS(Annual_Mortality!$I$2:$I$2731,Annual_Mortality!$A$2:$A$2731,A11) -> 128281.94 | O11: =SUMIFS(Budget_Impact!$E$2:$E$391,Budget_Impact!$A$2:$A$391,A11) -> 1.3091095e+08 | P11: =SUMIFS(Budget_Impact!$F$2:$F$391,Budget_Impact!$A$2:$A$391,A11) -> 89118158 | Q11: =IF(K11>0,P11/K11,"") -> 328.68639 | R11: =IF(N11>0,P11/N11,"") -> 694.70541 | S11: =IF(AND(K11<=0,N11<=0),"no incremental health effect",IF(AND(P11<0,OR(K11>0,N11>0)),"Dominant (more health, lower cost)",IF(N11>0,"USD per death averted","USD per case averted"))) -> USD per death averted
A12: I_PH_TFA_POLICY | B12: Industrial trans-fat elimination regulation | C12: standalone | D12: standalone | G12: I_PH_TFA_POLICY | H12: 1 | I12: =SUMIFS(Annual_Mortality!$E$2:$E$2731,Annual_Mortality!$A$2:$A$2731,A12) -> 69955364 | J12: =SUMIFS(Annual_Mortality!$G$2:$G$2731,Annual_Mortality!$A$2:$A$2731,A12) -> 70290153 | K12: =SUMIFS(Annual_Mortality!$J$2:$J$2731,Annual_Mortality!$A$2:$A$2731,A12) -> 334789.09 | L12: =SUMIFS(Annual_Mortality!$F$2:$F$2731,Annual_Mortality!$A$2:$A$2731,A12) -> 31066529 | M12: =SUMIFS(Annual_Mortality!$H$2:$H$2731,Annual_Mortality!$A$2:$A$2731,A12) -> 31200100 | N12: =SUMIFS(Annual_Mortality!$I$2:$I$2731,Annual_Mortality!$A$2:$A$2731,A12) -> 133571.29 | O12: =SUMIFS(Budget_Impact!$E$2:$E$391,Budget_Impact!$A$2:$A$391,A12) -> 1.2979178e+08 | P12: =SUMIFS(Budget_Impact!$F$2:$F$391,Budget_Impact!$A$2:$A$391,A12) -> 88356205 | Q12: =IF(K12>0,P12/K12,"") -> 263.91602 | R12: =IF(N12>0,P12/N12,"") -> 661.49097 | S12: =IF(AND(K12<=0,N12<=0),"no incremental health effect",IF(AND(P12<0,OR(K12>0,N12>0)),"Dominant (more health, lower cost)",IF(N12>0,"USD per death averted","USD per case averted"))) -> USD per death averted
A13: I_PH_SSB_TAX | B13: Sugar-sweetened beverage tax | C13: standalone | D13: standalone | G13: I_PH_SSB_TAX | H13: 1 | I13: =SUMIFS(Annual_Mortality!$E$2:$E$2731,Annual_Mortality!$A$2:$A$2731,A13) -> 70147762 | J13: =SUMIFS(Annual_Mortality!$G$2:$G$2731,Annual_Mortality!$A$2:$A$2731,A13) -> 70290153 | K13: =SUMIFS(Annual_Mortality!$J$2:$J$2731,Annual_Mortality!$A$2:$A$2731,A13) -> 142391.3 | L13: =SUMIFS(Annual_Mortality!$F$2:$F$2731,Annual_Mortality!$A$2:$A$2731,A13) -> 31165312 | M13: =SUMIFS(Annual_Mortality!$H$2:$H$2731,Annual_Mortality!$A$2:$A$2731,A13) -> 31200100 | N13: =SUMIFS(Annual_Mortality!$I$2:$I$2731,Annual_Mortality!$A$2:$A$2731,A13) -> 34788.231 | O13: =SUMIFS(Budget_Impact!$E$2:$E$391,Budget_Impact!$A$2:$A$391,A13) -> 59670660 | P13: =SUMIFS(Budget_Impact!$F$2:$F$391,Budget_Impact!$A$2:$A$391,A13) -> 40621571 | Q13: =IF(K13>0,P13/K13,"") -> 285.28126 | R13: =IF(N13>0,P13/N13,"") -> 1167.6814 | S13: =IF(AND(K13<=0,N13<=0),"no incremental health effect",IF(AND(P13<0,OR(K13>0,N13>0)),"Dominant (more health, lower cost)",IF(N13>0,"USD per death averted","USD per case averted"))) -> USD per death averted

Sheet Parent_Package_Summary
A1: scenario | B1: scenario_label | C1: scenario_level | D1: scenario_role | E1: parent_package_id | F1: parent_package_name | G1: intervention_ids | H1: component_order | I1: modeled_cases | J1: baseline_cases | K1: cases_averted | L1: modeled_deaths | M1: baseline_deaths | N1: deaths_averted | O1: incremental_cost | P1: disc_incremental_cost | Q1: cost_per_case_averted | R1: cost_per_death_averted | S1: status
A2: I_PH_TOBACCO_POLICY | B2: Tobacco policy package | C2: package | D2: package | E2: I_PH_TOBACCO_POLICY | F2: Tobacco policy package | G2: I_PH_TOB_CLEAN_AIR; I_PH_TOB_MEDIA; I_PH_TOB_AD_BAN | I2: =SUMIFS(Annual_Mortality!$E$2:$E$2731,Annual_Mortality!$A$2:$A$2731,A2) -> 69784036 | J2: =SUMIFS(Annual_Mortality!$G$2:$G$2731,Annual_Mortality!$A$2:$A$2731,A2) -> 70290153 | K2: =SUMIFS(Annual_Mortality!$J$2:$J$2731,Annual_Mortality!$A$2:$A$2731,A2) -> 506117.1 | L2: =SUMIFS(Annual_Mortality!$F$2:$F$2731,Annual_Mortality!$A$2:$A$2731,A2) -> 31080745 | M2: =SUMIFS(Annual_Mortality!$H$2:$H$2731,Annual_Mortality!$A$2:$A$2731,A2) -> 31200100 | N2: =SUMIFS(Annual_Mortality!$I$2:$I$2731,Annual_Mortality!$A$2:$A$2731,A2) -> 119354.88 | O2: =SUMIFS(Budget_Impact!$E$2:$E$391,Budget_Impact!$A$2:$A$391,A2) -> 3.4462018e+08 | P2: =SUMIFS(Budget_Impact!$F$2:$F$391,Budget_Impact!$A$2:$A$391,A2) -> 2.3460165e+08 | Q2: =IF(K2>0,P2/K2,"") -> 463.53236 | R2: =IF(N2>0,P2/N2,"") -> 1965.5808 | S2: =IF(AND(K2<=0,N2<=0),"no incremental health effect",IF(AND(P2<0,OR(K2>0,N2>0)),"Dominant (more health, lower cost)",IF(N2>0,"USD per death averted","USD per case averted"))) -> USD per death averted
A3: I_PH_SALT_POLICY | B3: Salt policy package | C3: package | D3: package | E3: I_PH_SALT_POLICY | F3: Salt policy package | G3: I_PH_SALT_REFORM; I_PH_SALT_FOPL; I_PH_SALT_MEDIA; I_PH_SALT_ENV | I3: =SUMIFS(Annual_Mortality!$E$2:$E$2731,Annual_Mortality!$A$2:$A$2731,A3) -> 68878798 | J3: =SUMIFS(Annual_Mortality!$G$2:$G$2731,Annual_Mortality!$A$2:$A$2731,A3) -> 70290153 | K3: =SUMIFS(Annual_Mortality!$J$2:$J$2731,Annual_Mortality!$A$2:$A$2731,A3) -> 1411355.9 | L3: =SUMIFS(Annual_Mortality!$F$2:$F$2731,Annual_Mortality!$A$2:$A$2731,A3) -> 30532359 | M3: =SUMIFS(Annual_Mortality!$H$2:$H$2731,Annual_Mortality!$A$2:$A$2731,A3) -> 31200100 | N3: =SUMIFS(Annual_Mortality!$I$2:$I$2731,Annual_Mortality!$A$2:$A$2731,A3) -> 667741.62 | O3: =SUMIFS(Budget_Impact!$E$2:$E$391,Budget_Impact!$A$2:$A$391,A3) -> 5.2392479e+08 | P3: =SUMIFS(Budget_Impact!$F$2:$F$391,Budget_Impact!$A$2:$A$391,A3) -> 3.5663637e+08 | Q3: =IF(K3>0,P3/K3,"") -> 252.6906 | R3: =IF(N3>0,P3/N3,"") -> 534.09337 | S3: =IF(AND(K3<=0,N3<=0),"no incremental health effect",IF(AND(P3<0,OR(K3>0,N3>0)),"Dominant (more health, lower cost)",IF(N3>0,"USD per death averted","USD per case averted"))) -> USD per death averted
A4: all_public_health | B4: All selected public-health interventions (combined) | C4: combined | D4: combined | G4: I_PH_ALCOHOL_POLICY; I_PH_ALCOHOL_TAX; I_PH_SALT_ENV; I_PH_SALT_FOPL; I_PH_SALT_MEDIA; I_PH_SALT_REFORM; I_PH_SSB_TAX; I_PH_TFA_POLICY; I_PH_TOBACCO_TAX; I_PH_TOB_AD_BAN; I_PH_TOB_CLEAN_AIR; I_PH_TOB_MEDIA | I4: =SUMIFS(Annual_Mortality!$E$2:$E$2731,Annual_Mortality!$A$2:$A$2731,A4) -> 66860210 | J4: =SUMIFS(Annual_Mortality!$G$2:$G$2731,Annual_Mortality!$A$2:$A$2731,A4) -> 70290153 | K4: =SUMIFS(Annual_Mortality!$J$2:$J$2731,Annual_Mortality!$A$2:$A$2731,A4) -> 3429943.7 | L4: =SUMIFS(Annual_Mortality!$F$2:$F$2731,Annual_Mortality!$A$2:$A$2731,A4) -> 30005444 | M4: =SUMIFS(Annual_Mortality!$H$2:$H$2731,Annual_Mortality!$A$2:$A$2731,A4) -> 31200100 | N4: =SUMIFS(Annual_Mortality!$I$2:$I$2731,Annual_Mortality!$A$2:$A$2731,A4) -> 1194655.9 | O4: =SUMIFS(Budget_Impact!$E$2:$E$391,Budget_Impact!$A$2:$A$391,A4) -> 1.2617526e+09 | P4: =SUMIFS(Budget_Impact!$F$2:$F$391,Budget_Impact!$A$2:$A$391,A4) -> 8.5880047e+08 | Q4: =IF(K4>0,P4/K4,"") -> 250.38326 | R4: =IF(N4>0,P4/N4,"") -> 718.86847 | S4: =IF(AND(K4<=0,N4<=0),"no incremental health effect",IF(AND(P4<0,OR(K4>0,N4>0)),"Dominant (more health, lower cost)",IF(N4>0,"USD per death averted","USD per case averted"))) -> USD per death averted

Sheet Economic_Value
A1: note
A2: Economic value (value of statistical life, VSL/VSLY) is produced by Model 08 for the clinical CVD scenarios only.
A3: Model 08 does not currently run the public-health scenario ids (I_PH_* / all_public_health), so its monetary-value
A4: results cannot be reconciled against this run's public-health scenarios and are intentionally NOT reproduced here.
A5: The principal public-health result in this workbook is USD per death averted (Cost_Effectiveness).
A6: To populate a public-health economic-value view, re-run Model 08 on the public-health scenarios and extend this sheet.

Sheet QA_Checks
A1: check | B1: expected | C1: actual | D1: status | E1: note
A2: Selected intervention-cause key uniqueness | B2: 0 | C2: =COUNTIF(Selected_Interventions!$U$2:$U$49,">1") -> 0 | D2: =IF(C2=0,"PASS","FAIL") -> PASS | E2: Each selected link key appears once
A3: Workbook FAIL-level issues | B3: 0 | C3: =COUNTIF(Input_Diagnostic!$E$2:$E$25,"FAIL") -> 0 | D3: =IF(C3=0,"PASS","REVIEW") -> PASS | E3: Blocked links excluded (see Blocked_Links / Input_Diagnostic)
A4: Workbook REVIEW-level issues | B4: 0 | C4: =COUNTIF(Input_Diagnostic!$E$2:$E$25,"REVIEW") -> 24 | D4: =IF(C4=0,"PASS","REVIEW") -> REVIEW | E4: Flagged but usable (e.g. cost not Indonesia-adjusted; provisional PAF)
A5: Every scenario paired to baseline | B5: 0 | C5: =COUNTBLANK(Annual_Mortality!$H$2:$H$2731) -> 0 | D5: =IF(C5=0,"PASS","FAIL") -> PASS | E5: Deaths averted = baseline - scenario at matched year/cause
A6: Public-health transitions are well -> sick incidence | B6: 0 | C6: =COUNTIF(Effect_Parameters!$N$2:$N$49,"<>incidence") -> 0 | D6: =IF(C6=0,"PASS","FAIL") -> PASS | E6: All modeled public-health effects map to incidence (no case fatality)
A7: No impossible negative states | B7: 0 | C7: =Calculation_Assumptions!$B$17 -> 0 | D7: =IF(C7=0,"PASS","FAIL") -> PASS | E7: well/sick/new_cases/deaths/population >= 0
A8: Stock/flow identity pop = well + sick + all-cause deaths | B8: <= limit | C8: =Calculation_Assumptions!$B$18 -> 108.16 | D8: =IF(C8<=Calculation_Assumptions!$B$16,"PASS","REVIEW") -> PASS | E8: Per cause row; small residual from 95+ pooling / rounding
A9: Background mortality constant across cause | B9: 1 | C9: =Calculation_Assumptions!$B$19 -> 3 | D9: =IF(C9=1,"PASS","FAIL") -> FAIL | E9: all.mx taken once per stratum (population not duplicated across causes)
A10: Cost reconciliation (components -> budget impact) | B10: <= tol | C10: =ABS(SUM(Budget_Impact!$D$2:$D$391)-SUM(Annual_Cost!$R$2:$R$807))+ABS(SUM(Budget_Impact!$C$2:$C$391)-SUM(Annual_Cost!$Q$2:$Q$807)) -> 9.5367432e-07 | D10: =IF(C10<=Calculation_Assumptions!$B$15,"PASS","FAIL") -> PASS | E10: Excel component rows sum to Excel annual totals within tolerance
A11: Shared cost counted once per stratum/year | B11: 0 | C11: =COUNTIF(Annual_Cost!$AA$2:$AA$807,">1") -> 0 | D11: =IF(C11=0,"PASS","FAIL") -> PASS | E11: shared-count-once components appear once per scenario-year
A12: Annual reconciles to cumulative (budget impact) | B12: <= tol | C12: =ABS(SUMIFS(Budget_Impact!$G$2:$G$391,Budget_Impact!$B$2:$B$391,Calculation_Assumptions!$B$3)-SUM(Budget_Impact!$E$2:$E$391)) -> 9.5367432e-07 | D12: =IF(C12<=Calculation_Assumptions!$B$15,"PASS","FAIL") -> PASS | E12: Last-year cumulative equals the sum of annual incremental cost
A13: CEA reconciliation (detail -> summary) | B13: consistent | C13: =IF(COUNTIF(Cost_Effectiveness!$I$2:$I$16,"mismatch")=0,"consistent","mismatch") -> consistent | D13: =IF(C13="consistent","PASS","FAIL") -> PASS | E13: Every Cost_Effectiveness row's internal reconciliation is consistent
A14: Excel vs R: deaths averted (anchor) | B14: match R | C14: =INDEX(Cost_Effectiveness!$C$2:$C$16,MATCH(Calculation_Assumptions!$B$23,Cost_Effectiveness!$A$2:$A$16,0)) -> 1194655.9 | D14: =IF(ABS(C14-Calculation_Assumptions!$B$20)<=ABS(Calculation_Assumptions!$B$20)*0.000001+0.5,"PASS","FAIL") -> PASS | E14: Excel CEA deaths averted reconciles to the R engine value
A15: Excel vs R: discounted incremental cost (anchor) | B15: match R | C15: =INDEX(Cost_Effectiveness!$F$2:$F$16,MATCH(Calculation_Assumptions!$B$23,Cost_Effectiveness!$A$2:$A$16,0)) -> 8.5880047e+08 | D15: =IF(ABS(C15-Calculation_Assumptions!$B$21)<=ABS(Calculation_Assumptions!$B$21)*0.000001+1,"PASS","FAIL") -> PASS | E15: Excel CEA discounted incremental cost reconciles to the R engine value
A16: Excel vs R: cost per death averted (anchor) | B16: match R | C16: =INDEX(Cost_Effectiveness!$G$2:$G$16,MATCH(Calculation_Assumptions!$B$23,Cost_Effectiveness!$A$2:$A$16,0)) -> 718.86847 | D16: =IF(ABS(C16-Calculation_Assumptions!$B$22)<=ABS(Calculation_Assumptions!$B$22)*0.000001+1,"PASS","FAIL") -> PASS | E16: Excel CEA USD per death averted reconciles to the R engine value
A17: Tobacco package child count | B17: 3 | C17: =COUNTIFS(Scenario_Hierarchy!$A$2:$A$13,"I_PH_TOBACCO_POLICY",Scenario_Hierarchy!$F$2:$F$13,"child") -> 3 | D17: =IF(C17=3,"PASS","FAIL") -> PASS | E17: Scenario_Hierarchy: clean air, media, ad ban
A18: Salt package child count | B18: 4 | C18: =COUNTIFS(Scenario_Hierarchy!$A$2:$A$13,"I_PH_SALT_POLICY",Scenario_Hierarchy!$F$2:$F$13,"child") -> 4 | D18: =IF(C18=4,"PASS","FAIL") -> PASS | E18: Scenario_Hierarchy: reformulation, FOPL, media, institutions
A19: Child cost-allocation shares sum to 1 (per package) | B19: <= tol | C19: =ABS(SUMIFS(Cost_Components!$M$2:$M$13,Cost_Components!$F$2:$F$13,"I_PH_TOBACCO_POLICY")-1)+ABS(SUMIFS(Cost_Components!$M$2:$M$13,Cost_Components!$F$2:$F$13,"I_PH_SALT_POLICY")-1) -> 1.110223e-15 | D19: =IF(C19<=Calculation_Assumptions!$B$15,"PASS","FAIL") -> PASS | E19: Cost_Components allocation shares sum to 1 within each package (M13/M14)
A20: Parent packages produced as joint runs | B20: > 0 | C20: =MIN(COUNTIF(Annual_Mortality!$A$2:$A$2731,"I_PH_TOBACCO_POLICY"),COUNTIF(Annual_Mortality!$A$2:$A$2731,"I_PH_SALT_POLICY")) -> 182 | D20: =IF(C20>0,"PASS","FAIL") -> PASS | E20: Package cases/deaths come from a produced JOINT scenario, never summed from children

Sheet Input_Diagnostic
A1: scope | B1: item_key | C1: field | D1: problem | E1: severity
A2: ph_cost | B2: COST_PH_TOB_TAX | C2: indonesia_adjusted_flag | D2: cost not Indonesia-adjusted (proxy/review estimate; kept but flagged) | E2: REVIEW
A3: ph_cost | B3: COST_PH_ALC_TAX | C3: indonesia_adjusted_flag | D3: cost not Indonesia-adjusted (proxy/review estimate; kept but flagged) | E3: REVIEW
A4: ph_cost | B4: COST_PH_TOB_CLEAN_AIR | C4: indonesia_adjusted_flag | D4: cost not Indonesia-adjusted (proxy/review estimate; kept but flagged) | E4: REVIEW
A5: ph_cost | B5: COST_PH_TOB_MEDIA | C5: indonesia_adjusted_flag | D5: cost not Indonesia-adjusted (proxy/review estimate; kept but flagged) | E5: REVIEW
A6: ph_cost | B6: COST_PH_TOB_AD_BAN | C6: indonesia_adjusted_flag | D6: cost not Indonesia-adjusted (proxy/review estimate; kept but flagged) | E6: REVIEW
A7: ph_cost | B7: COST_PH_ALC_POLICY | C7: indonesia_adjusted_flag | D7: cost not Indonesia-adjusted (proxy/review estimate; kept but flagged) | E7: REVIEW
A8: ph_cost | B8: COST_PH_SALT_REFORM | C8: indonesia_adjusted_flag | D8: cost not Indonesia-adjusted (proxy/review estimate; kept but flagged) | E8: REVIEW
A9: ph_cost | B9: COST_PH_SALT_FOPL | C9: indonesia_adjusted_flag | D9: cost not Indonesia-adjusted (proxy/review estimate; kept but flagged) | E9: REVIEW
A10: ph_cost | B10: COST_PH_SALT_MEDIA | C10: indonesia_adjusted_flag | D10: cost not Indonesia-adjusted (proxy/review estimate; kept but flagged) | E10: REVIEW
A11: ph_cost | B11: COST_PH_SALT_ENV | C11: indonesia_adjusted_flag | D11: cost not Indonesia-adjusted (proxy/review estimate; kept but flagged) | E11: REVIEW
A12: ph_cost | B12: COST_PH_TFA | C12: indonesia_adjusted_flag | D12: cost not Indonesia-adjusted (proxy/review estimate; kept but flagged) | E12: REVIEW
... A25: ph_cost | B25: COST_PH_SSB_TAX | C25: price_year | D25: cost price year != reporting price year (2023) | E25: REVIEW

Sheet Methods_and_Sources
A1: method_id | B1: concept | C1: formula_or_rule | D1: source
A2: M01 | B2: Exposure target | C2: relative: max(floor, baseline*(1-reduction)); absolute: max(floor, baseline-reduction); level: max(floor, target) | D2: NCD Countdown supplement (Countdown_Methods sheet) + public-health input workbook
A3: M02 | B3: Exposure path | C3: pt(t) linear baseline->target over start_year..target_year, then held; floored at exposure_floor | D3: NCD Countdown supplement (Countdown_Methods sheet) + public-health input workbook
A4: M03 | B4: Regulatory score | C4: implementation score: none=0; partial=0.5; full=1 | D4: NCD Countdown supplement (Countdown_Methods sheet) + public-health input workbook
A5: M04 | B5: Regulatory effect | C5: implementation_gap = max(0, target_score - baseline_score); regulatory reduction = full_component_effect * implementation_gap | D5: NCD Countdown supplement (Countdown_Methods sheet) + public-health input workbook
A6: M05 | B6: Price-change tax | C6: fiscal_tax_delta = max(0, target_tax - baseline_tax); reduction = abs(price_elasticity) * implied_price_change | D6: NCD Countdown supplement (Countdown_Methods sheet) + public-health input workbook
A7: M06 | B7: Tax-share tax | C7: tobacco excise share: implied_price_change = (1 - baseline_share)/(1 - target_share) - 1 | D7: NCD Countdown supplement (Countdown_Methods sheet) + public-health input workbook
A8: M07 | B8: Prevalence-shift RR effect | C8: effect = 1 - (1 + pt*(RR-1)) / (1 + p0*(RR-1)) [tobacco smoking prevalence shift] | D8: NCD Countdown supplement (Countdown_Methods sheet) + public-health input workbook
A9: M08 | B9: Log-linear RR effect | C9: effect = 1 - 1/(RR^(p0-pt)) [alcohol, sodium, SSB, and DEFAULT industrial-TFA path: RR per 1 percentage-point energy, e.g. RR_TFA_IHD_1PCT=1.10 ~ sqrt(1.21)] | D9: NCD Countdown supplement (Countdown_Methods sheet) + public-health input workbook
A10: M09 | B10: TFA effect method (RR default / PAF optional) | C10: RR (default): log-linear RR per unit reduction, no PAF required. PAF (optional, tfa_effect_method=PAF): effect = optional_PAF * implementation_gap | D10: NCD Countdown supplement (Countdown_Methods sheet) + public-health input workbook
A11: M10 | B11: Effect lag | C11: immediate: effect tracks exposure path; delayed_exponential: full_effect * (1-(1-rate)^(years since start)) | D11: NCD Countdown supplement (Countdown_Methods sheet) + public-health input workbook
A12: M11 | B12: Incidence application | C12: cause-specific incidence x (1 - effect_t); multiple policies combine multiplicatively on the surviving fraction | D12: NCD Countdown supplement (Countdown_Methods sheet) + public-health input workbook
... A22: REF | B22: TFA source RR | C22: supporting cohort evidence | D22: https://www.ahajournals.org/doi/10.1161/JAHA.115.002891

Sheet Calculation_Assumptions
A1: parameter_id | B1: value | C1: unit | D1: role | E1: description | F1: source
A2: analysis_start_year | B2: 2025 | C2: year | D2: formula control | E2: First model and discount year | F2: indonesia_model_inputs_public_health_updated.xlsx
A3: analysis_end_year | B3: 2050 | C3: year | D3: formula control | E3: Last model year | F3: indonesia_model_inputs_public_health_updated.xlsx
A4: baseline_scenario_id | B4: baseline | C4: scenario id | D4: formula control | E4: No-new-policy comparator | F4: indonesia_model_inputs_public_health_updated.xlsx
A5: policy_start_year | B5: 2026 | C5: year | D5: formula control | E5: First policy implementation year | F5: indonesia_model_inputs_public_health_updated.xlsx
A6: exposure_target_year | B6: 2030 | C6: year | D6: formula control | E6: Year full exposure reduction is reached | F6: indonesia_model_inputs_public_health_updated.xlsx
A7: policy_cost_ramp_years | B7: 3 | C7: years | D7: formula control | E7: Years to full policy cost | F7: indonesia_model_inputs_public_health_updated.xlsx
A8: cost_discount_rate | B8: 0.03 | C8: proportion/year | D8: formula control | E8: Annual discount rate applied to costs | F8: indonesia_model_inputs_public_health_updated.xlsx
A9: reporting_price_year | B9: 2023 | C9: USD year | D9: formula control | E9: Reporting price year | F9: indonesia_model_inputs_public_health_updated.xlsx
A10: source_cost_price_year | B10: 2017 | C10: USD year | D10: formula control | E10: Price year of source unit costs | F10: indonesia_model_inputs_public_health_updated.xlsx
A11: currency | B11: USD | C11: currency | D11: metadata | E11: Reporting currency | F11: indonesia_model_inputs_public_health_updated.xlsx
A12: economic_perspective | B12: health_system | C12: text | D12: metadata | E12: Economic evaluation perspective | F12: indonesia_model_inputs_public_health_updated.xlsx
A13: scale_up_shape | B13: linear | C13: text | D13: formula control | E13: Cost/effect scale-up shape | F13: indonesia_model_inputs_public_health_updated.xlsx
A14: baseline_implementation_fraction | B14: 0 | C14: proportion | D14: formula control | E14: Baseline (counterfactual) policy implementation fraction | F14: Model 09
A15: formula_tolerance | B15: 0.001 | C15: USD/count | D15: QA control | E15: Absolute reconciliation tolerance | F15: Workbook QA rule
A16: stock_flow_residual_limit | B16: 1000 | C16: persons | D16: QA control | E16: Persons tolerance for the stock/flow identity check | F16: Workbook QA rule
A17: r_negative_state_count | B17: 0 | C17: count | D17: R QA source | E17: Impossible negative state count (R) | F17: Model 09 current run
A18: r_stock_flow_max_residual | B18: 108.16 | C18: persons | D18: R QA source | E18: Max stock/flow residual (R) | F18: Model 09 current run
A19: r_background_distinct_count | B19: 3 | C19: count | D19: R QA source | E19: Max distinct all-cause mx across cause (R) | F19: Model 09 current run
A20: r_deaths_averted_anchor | B20: 1194655.9 | C20: deaths | D20: R reconciliation source | E20: R deaths averted for the anchor scenario | F20: Model 09 current run (R CEA)
A21: r_disc_incremental_cost_anchor | B21: 8.5880047e+08 | C21: USD | D21: R reconciliation source | E21: R discounted incremental cost for the anchor scenario | F21: Model 09 current run (R CEA)
A22: r_cost_per_death_anchor | B22: 718.86847 | C22: USD/death | D22: R reconciliation source | E22: R USD per death averted for the anchor scenario | F22: Model 09 current run (R CEA)
A23: qa_anchor_scenario | B23: all_public_health | C23: scenario id | D23: R reconciliation source | E23: Scenario used for Excel-vs-R reconciliation | F23: Model 09 current run (R CEA)

Sheet Calculation_Map
A1: output_sheet | B1: formula_columns | C1: depends_on | D1: calculation
A2: Policy_Levers | B2: implementation_gap,implied_price_change,fiscal_tax_delta,policy_reduction | C2: lever_method + fiscal/regulatory inputs | D2: Regulatory gap, tax price change/delta, reproduced relative exposure reduction
A3: Selected_Interventions | B3: full_effect,reductions,key_count,status | C3: effect_model + exposures | D3: Full effect at target; exposure reductions; key uniqueness
A4: Exposure_Targets | B4: target,abs,rel | C4: baseline/method/reduction | D4: Exposure target and absolute/relative reductions
A5: Effect_Parameters | B5: full_effect | C5: effect_model + exposures | D5: Full effect at target
A6: Cost_Components | B6: allocated_child_cost,cost_ready | C6: cost inputs + allocation shares | D6: Child cost = package total x share; cost-readiness rule
A7: Annual_Mortality | B7: deaths_averted,cases_averted | C7: R deaths/cases | D7: Deaths and cases averted
A8: Annual_Cost | B8: impl_frac,PIN,annual+disc cost,shared QA | C8: Cost_Components; Calculation_Assumptions; R population | D8: Implementation fraction, PIN, annual/discounted cost, shared-cost QA
A9: Budget_Impact | B9: incremental+cumulative cost | C9: Annual_Cost | D9: Annual and cumulative cost by scenario
A10: Cost_Effectiveness | B10: health,cost,ICER,dominance,reconciliation | C10: Annual_Mortality; Budget_Impact; Calculation_Assumptions | D10: Cumulative health, cost, cost/death, dominance, reconciliation
A11: Child_Intervention_Summary | B11: modeled/baseline/averted,cost,ICER | C11: Annual_Mortality; Budget_Impact (standalone scenarios) | D11: Per child intervention: health, cost, cost per case/death averted, status
A12: Parent_Package_Summary | B12: modeled/baseline/averted,cost,ICER | C12: Annual_Mortality; Budget_Impact (JOINT package/combined runs) | D12: Per parent package (joint run) + combined: health, cost, cost per case/death averted
... A14: Run_Metadata | B14: B (subset) | C14: Calculation_Assumptions | D14: Metadata pulled from controls
