Workbook

Sheet README
A1: Indonesia NCD FAIR Choices - cost & value workbook (formula edition)
A3: section | B3: detail
A4: Purpose | B4: Costing, budget impact and mortality-based cost-effectiveness for the FAIR Choices CVD interventions selected in indonesia_model_inputs.xlsx.
A5: How to read | B5: Grey cells are R-generated source values; light-blue cells are LIVE Excel formulas; pale-yellow cells on Calculation_Assumptions are editable controls. Change a yellow control and the blue results recompute. Calculation_Map lists every dependency.
A6: Scenarios | B6: Baseline + one scenario per selected valid intervention + a combined 'all' scenario. Membership derives only from the workbook selections (Model 04).
A7: Baseline pairing | B7: Deaths averted = baseline deaths - scenario deaths, matched at location x year x age x sex x cause (aggregated to year x cause here).
A8: Model aggregates | B8: Annual_Mortality carries the R health aggregates (cases, deaths, baseline); Annual_Cost carries the full-precision R population quantity before the PIN fraction. The 157k-row state trace stays in the companion R workbook.
A9: Costing | B9: annual_cost = population_in_need x coverage(t) x frequency x unit_cost. PIN measure maps 'all'->eligible population, 'prevalence'->sick stock, 'incidence'->new cases.
A10: Shared costs | B10: Components flagged 'shared-count-once' (cost_join_key ...__C_SHARED) are counted once at intervention level, never once per affected cause (see Annual_Cost shared_duplicate_count and QA).
A11: Budget impact | B11: Budget impact reports UNDISCOUNTED baseline, scenario, incremental and cumulative incremental cost. Discounted costs are separate columns.
A12: Cost-effectiveness | B12: USD per death averted = cumulative discounted incremental cost / cumulative (undiscounted) deaths averted over the horizon. Not a DALY-based ICER.
A13: Economic value | B13: Value of statistical life (VSL/VSLY) is reused from Model 08 as R source values; only the cost link, supplementary benefit-cost ratio and net benefit are recalculated here.
A14: QA & reconciliation | B14: QA_Checks recomputes each invariant in Excel and reconciles the Excel cost-effectiveness headline against the R engine values stored on Calculation_Assumptions. PASS/FAIL/REVIEW are conditionally formatted.
... A17: Deferred | B17: DALYs, YLL, YLD, disability weights and life-expectancy outcomes are deferred to later work and are NOT in this workbook.

Sheet Run_Metadata
A1: item | B1: value
A2: Workbook title | B2: Indonesia NCD FAIR Choices - cost & value
A3: Run date | B3: 2026-08-21
A4: Model / pipeline | B4: CVD FAIR Choices (Models 00-06 -> 09)
A5: Input workbook | B5: C:/Users/wrgar/OneDrive - UW/02Work/WorldBank-Indonesia/uw-wb-indonesia-ncd/data/indonesia_model_inputs.xlsx
A6: Model output source | B6: output/out_model/model_output_*.rds (Model 06)
A7: Location | B7: Indonesia
A8: Analysis years | B8: ='Calculation_Assumptions'!B2&"-"&'Calculation_Assumptions'!B3
A9: Baseline scenario | B9: ='Calculation_Assumptions'!B4
A10: Scenarios costed | B10: I_CVD_PRIMARY, I_HF_ACUTE, I_HF_CHRONIC, I_IHD_SECONDARY, I_RHD_SECONDARY, I_RHD_SURGERY, I_STROKE_SECONDARY, I_T2D_TREATMENT, all
A11: Cost discount rate | B11: ='Calculation_Assumptions'!B5
A12: Cost price year | B12: ='Calculation_Assumptions'!B6
A13: Currency | B13: ='Calculation_Assumptions'!B7
A14: Economic perspective | B14: ='Calculation_Assumptions'!B8
A15: Coverage scale-up shape | B15: ='Calculation_Assumptions'!B9
A16: Downstream cost offsets | B16: ='Calculation_Assumptions'!B10
A17: Health outcomes (DALYs/YLL/YLD) | B17: Out of scope in this stage (deferred)
A18: R version | B18: R version 4.5.1 (2025-06-13 ucrt)
A19: openxlsx / data.table | B19: 4.2.8 / 1.17.8

Sheet Selected_Interventions
A1: intervention_id | B1: intervention_cause_key | C1: intervention_name | D1: cause_id | E1: cause_code | F1: model_name | G1: transition_from | H1: transition_to | I1: model_transition | J1: effect_value | K1: affected_fraction | L1: baseline_coverage | M1: target_coverage | N1: start_year | O1: target_year | P1: adjusted_effect_at_target | Q1: cost_join_key | R1: cost_scope | S1: effect_review | T1: coverage_review | U1: key_count | V1: formula_status
A2: I_CVD_PRIMARY | B2: I_CVD_PRIMARY__C_HHD | C2: Primary prevention of CVD | D2: C_HHD | E2: hhd | F2: Hypertensive heart disease | G2: well | H2: sick | I2: incidence | J2: 0.47 | K2: 1 | L2: 0.31 | M2: 0.8 | N2: 2025 | O2: 2050 | P2: =IF(OR(J2="",K2="",L2="",M2=""),"",ROUND(K2*(J2*(M2-L2)/(1-J2*L2)),4)) | Q2: I_CVD_PRIMARY__C_SHARED | R2: shared-count-once | S2: Provisional | T2: Provisional | U2: =COUNTIF($B$2:$B$18,B2) | V2: =IF(U2=1,"OK","DUPLICATE KEY")
A3: I_CVD_PRIMARY | B3: I_CVD_PRIMARY__C_ICH | C3: Primary prevention of CVD | D3: C_ICH | E3: hstroke | F3: Intracerebral hemorrhage | G3: well | H3: sick | I3: incidence | J3: 0.49 | K3: 0.8 | L3: 0.31 | M3: 0.8 | N3: 2025 | O3: 2050 | P3: =IF(OR(J3="",K3="",L3="",M3=""),"",ROUND(K3*(J3*(M3-L3)/(1-J3*L3)),4)) | Q3: I_CVD_PRIMARY__C_SHARED | R3: shared-count-once | S3: Provisional | T3: Provisional | U3: =COUNTIF($B$2:$B$18,B3) | V3: =IF(U3=1,"OK","DUPLICATE KEY")
A4: I_CVD_PRIMARY | B4: I_CVD_PRIMARY__C_IHD | C4: Primary prevention of CVD | D4: C_IHD | E4: ihd | F4: Ischemic heart disease | G4: well | H4: sick | I4: incidence | J4: 0.58 | K4: 0.8 | L4: 0.31 | M4: 0.8 | N4: 2025 | O4: 2050 | P4: =IF(OR(J4="",K4="",L4="",M4=""),"",ROUND(K4*(J4*(M4-L4)/(1-J4*L4)),4)) | Q4: I_CVD_PRIMARY__C_SHARED | R4: shared-count-once | S4: Provisional | T4: Provisional | U4: =COUNTIF($B$2:$B$18,B4) | V4: =IF(U4=1,"OK","DUPLICATE KEY")
A5: I_CVD_PRIMARY | B5: I_CVD_PRIMARY__C_IS | C5: Primary prevention of CVD | D5: C_IS | E5: istroke | F5: Ischemic stroke | G5: well | H5: sick | I5: incidence | J5: 0.54 | K5: 0.8 | L5: 0.31 | M5: 0.8 | N5: 2025 | O5: 2050 | P5: =IF(OR(J5="",K5="",L5="",M5=""),"",ROUND(K5*(J5*(M5-L5)/(1-J5*L5)),4)) | Q5: I_CVD_PRIMARY__C_SHARED | R5: shared-count-once | S5: Provisional | T5: Provisional | U5: =COUNTIF($B$2:$B$18,B5) | V5: =IF(U5=1,"OK","DUPLICATE KEY")
A6: I_HF_ACUTE | B6: I_HF_ACUTE__C_CMP | C6: Acute heart-failure management | D6: C_CMP | E6: cmd | F6: Cardiomyopathy and myocarditis | G6: sick_hf | H6: dead_cmp | I6: case_fatality | J6: 0.74 | K6: 0.2 | L6: 0.31 | M6: 0.8 | N6: 2025 | O6: 2050 | P6: =IF(OR(J6="",K6="",L6="",M6=""),"",ROUND(K6*(J6*(M6-L6)/(1-J6*L6)),4)) | Q6: I_HF_ACUTE__C_CMP | R6: cause-specific | S6: Provisional | T6: Provisional | U6: =COUNTIF($B$2:$B$18,B6) | V6: =IF(U6=1,"OK","DUPLICATE KEY")
A7: I_HF_ACUTE | B7: I_HF_ACUTE__C_HHD | C7: Acute heart-failure management | D7: C_HHD | E7: hhd | F7: Hypertensive heart disease | G7: sick_hf | H7: dead_hhd | I7: case_fatality | J7: 0.74 | K7: 0.2 | L7: 0.31 | M7: 0.8 | N7: 2025 | O7: 2050 | P7: =IF(OR(J7="",K7="",L7="",M7=""),"",ROUND(K7*(J7*(M7-L7)/(1-J7*L7)),4)) | Q7: I_HF_ACUTE__C_HHD | R7: cause-specific | S7: Provisional | T7: Provisional | U7: =COUNTIF($B$2:$B$18,B7) | V7: =IF(U7=1,"OK","DUPLICATE KEY")
A8: I_HF_ACUTE | B8: I_HF_ACUTE__C_IHD | C8: Acute heart-failure management | D8: C_IHD | E8: ihd | F8: Ischemic heart disease | G8: sick_hf | H8: dead_ihd | I8: case_fatality | J8: 0.18 | K8: 0.05 | L8: 0.31 | M8: 0.8 | N8: 2025 | O8: 2050 | P8: =IF(OR(J8="",K8="",L8="",M8=""),"",ROUND(K8*(J8*(M8-L8)/(1-J8*L8)),4)) | Q8: I_HF_ACUTE__C_IHD | R8: cause-specific | S8: Provisional | T8: Provisional | U8: =COUNTIF($B$2:$B$18,B8) | V8: =IF(U8=1,"OK","DUPLICATE KEY")
A9: I_HF_CHRONIC | B9: I_HF_CHRONIC__C_CMP | C9: Chronic heart-failure management | D9: C_CMP | E9: cmd | F9: Cardiomyopathy and myocarditis | G9: sick_hf | H9: dead_cmp | I9: case_fatality | J9: 0.536 | K9: 0.8 | L9: 0.31 | M9: 0.8 | N9: 2025 | O9: 2050 | P9: =IF(OR(J9="",K9="",L9="",M9=""),"",ROUND(K9*(J9*(M9-L9)/(1-J9*L9)),4)) | Q9: I_HF_CHRONIC__C_CMP | R9: cause-specific | S9: Provisional | T9: Provisional | U9: =COUNTIF($B$2:$B$18,B9) | V9: =IF(U9=1,"OK","DUPLICATE KEY")
A10: I_HF_CHRONIC | B10: I_HF_CHRONIC__C_HHD | C10: Chronic heart-failure management | D10: C_HHD | E10: hhd | F10: Hypertensive heart disease | G10: sick_hf | H10: dead_hhd | I10: case_fatality | J10: 0.275 | K10: 0.8 | L10: 0.31 | M10: 0.8 | N10: 2025 | O10: 2050 | P10: =IF(OR(J10="",K10="",L10="",M10=""),"",ROUND(K10*(J10*(M10-L10)/(1-J10*L10)),4)) | Q10: I_HF_CHRONIC__C_HHD | R10: cause-specific | S10: Provisional | T10: Provisional | U10: =COUNTIF($B$2:$B$18,B10) | V10: =IF(U10=1,"OK","DUPLICATE KEY")
A11: I_HF_CHRONIC | B11: I_HF_CHRONIC__C_IHD | C11: Chronic heart-failure management | D11: C_IHD | E11: ihd | F11: Ischemic heart disease | G11: sick_hf | H11: dead_ihd | I11: case_fatality | J11: 0.093 | K11: 0.2 | L11: 0.31 | M11: 0.8 | N11: 2025 | O11: 2050 | P11: =IF(OR(J11="",K11="",L11="",M11=""),"",ROUND(K11*(J11*(M11-L11)/(1-J11*L11)),4)) | Q11: I_HF_CHRONIC__C_IHD | R11: cause-specific | S11: Provisional | T11: Provisional | U11: =COUNTIF($B$2:$B$18,B11) | V11: =IF(U11=1,"OK","DUPLICATE KEY")
A12: I_IHD_SECONDARY | B12: I_IHD_SECONDARY__C_IHD | C12: Secondary prevention of ischemic heart disease | D12: C_IHD | E12: ihd | F12: Ischemic heart disease | G12: sick | H12: dead_ihd | I12: case_fatality | J12: 0.5822 | K12: 0.2 | L12: 0.31 | M12: 0.8 | N12: 2025 | O12: 2050 | P12: =IF(OR(J12="",K12="",L12="",M12=""),"",ROUND(K12*(J12*(M12-L12)/(1-J12*L12)),4)) | Q12: I_IHD_SECONDARY__C_IHD | R12: cause-specific | S12: Provisional | T12: Provisional | U12: =COUNTIF($B$2:$B$18,B12) | V12: =IF(U12=1,"OK","DUPLICATE KEY")
A13: I_RHD_SECONDARY | B13: I_RHD_SECONDARY__C_RHD | C13: RHD secondary prevention | D13: C_RHD | E13: rhd | F13: Rheumatic heart disease | G13: sick | H13: dead_rhd | I13: case_fatality | J13: 0.55 | K13: 1 | L13: 0.31 | M13: 0.8 | N13: 2025 | O13: 2050 | P13: =IF(OR(J13="",K13="",L13="",M13=""),"",ROUND(K13*(J13*(M13-L13)/(1-J13*L13)),4)) | Q13: I_RHD_SECONDARY__C_RHD | R13: cause-specific | S13: Provisional | T13: Provisional | U13: =COUNTIF($B$2:$B$18,B13) | V13: =IF(U13=1,"OK","DUPLICATE KEY")
... A18: I_T2D_TREATMENT | B18: I_T2D_TREATMENT__C_IHD | C18: Longitudinal treatment of type 2 diabetes | D18: C_IHD | E18: ihd | F18: Ischemic heart disease | G18: sick | H18: dead_ihd | I18: case_fatality | J18: 0.15 | K18: 0.15 | L18: 0.31 | M18: 0.8 | N18: 2025 | O18: 2050 | P18: =IF(OR(J18="",K18="",L18="",M18=""),"",ROUND(K18*(J18*(M18-L18)/(1-J18*L18)),4)) | Q18: I_T2D_TREATMENT__C_T2D | R18: shared-count-once | S18: Review | T18: Missing input | U18: =COUNTIF($B$2:$B$18,B18) | V18: =IF(U18=1,"OK","DUPLICATE KEY")

Sheet Cost_Components
A1: cost_record_id | B1: cost_component_key | C1: cost_option | D1: intervention_id | E1: cause_id | F1: cause_code | G1: cost_join_key | H1: cost_scope | I1: cost_component | J1: population_in_need_measure | K1: population_in_need_fraction | L1: frequency_per_year | M1: c_age_start | N1: c_age_stop | O1: c_sex | P1: unit_cost_usd | Q1: price_year | R1: indonesia_adjusted_flag | S1: cov_baseline | T1: cov_target | U1: cov_start_year | V1: cov_target_year | W1: cost_review | X1: cost_ready
A2: COST_PRIMARY_TX_A | B2: CC_PRIMARY_HTN_STATIN | C2: Option A (selected) | D2: I_CVD_PRIMARY | E2: C_SHARED | G2: I_CVD_PRIMARY__C_SHARED | H2: shared-count-once | I2: Antihypertensives and statins for absolute CVD risk >20% | J2: all | K2: 0.06 | L2: 1 | M2: 30 | N2: 95 | O2: Both | P2: 22.2296 | Q2: 2023 | R2: 1 | S2: =IFERROR(INDEX('Selected_Interventions'!$L$2:$L$18,MATCH(G2,'Selected_Interventions'!$Q$2:$Q$18,0)),"") | T2: =IFERROR(INDEX('Selected_Interventions'!$M$2:$M$18,MATCH(G2,'Selected_Interventions'!$Q$2:$Q$18,0)),"") | U2: =IFERROR(INDEX('Selected_Interventions'!$N$2:$N$18,MATCH(G2,'Selected_Interventions'!$Q$2:$Q$18,0)),"") | V2: =IFERROR(INDEX('Selected_Interventions'!$O$2:$O$18,MATCH(G2,'Selected_Interventions'!$Q$2:$Q$18,0)),"") | W2: Review | X2: =IF(AND(P2<>"",P2>=0,S2<>"",K2<>"",K2>=0,K2<=1,OR(J2="all",J2="prevalence",J2="incidence")),1,0)
A3: COST_PRIMARY_SCREEN_A | B3: CC_PRIMARY_SCREENING | C3: Option A (selected) | D3: I_CVD_PRIMARY | E3: C_SHARED | G3: I_CVD_PRIMARY__C_SHARED | H3: shared-count-once | I3: CVD targeted screening | J3: all | K3: 0.2 | L3: 1 | M3: 30 | N3: 95 | O3: Both | P3: 1.291584 | Q3: 2023 | R3: 1 | S3: =IFERROR(INDEX('Selected_Interventions'!$L$2:$L$18,MATCH(G3,'Selected_Interventions'!$Q$2:$Q$18,0)),"") | T3: =IFERROR(INDEX('Selected_Interventions'!$M$2:$M$18,MATCH(G3,'Selected_Interventions'!$Q$2:$Q$18,0)),"") | U3: =IFERROR(INDEX('Selected_Interventions'!$N$2:$N$18,MATCH(G3,'Selected_Interventions'!$Q$2:$Q$18,0)),"") | V3: =IFERROR(INDEX('Selected_Interventions'!$O$2:$O$18,MATCH(G3,'Selected_Interventions'!$Q$2:$Q$18,0)),"") | W3: Review | X3: =IF(AND(P3<>"",P3>=0,S3<>"",K3<>"",K3>=0,K3<=1,OR(J3="all",J3="prevalence",J3="incidence")),1,0)
A4: COST_HF_ACUTE_C_CMP | B4: CC_HF_ACUTE_C_CMP | C4: Base | D4: I_HF_ACUTE | E4: C_CMP | F4: cmd | G4: I_HF_ACUTE__C_CMP | H4: cause-specific | I4: Acute heart-failure management package | J4: prevalence | K4: 0.5 | L4: 1 | M4: 30 | N4: 95 | O4: Both | P4: 282.51284 | Q4: 2023 | R4: 1 | S4: =IFERROR(INDEX('Selected_Interventions'!$L$2:$L$18,MATCH(G4,'Selected_Interventions'!$Q$2:$Q$18,0)),"") | T4: =IFERROR(INDEX('Selected_Interventions'!$M$2:$M$18,MATCH(G4,'Selected_Interventions'!$Q$2:$Q$18,0)),"") | U4: =IFERROR(INDEX('Selected_Interventions'!$N$2:$N$18,MATCH(G4,'Selected_Interventions'!$Q$2:$Q$18,0)),"") | V4: =IFERROR(INDEX('Selected_Interventions'!$O$2:$O$18,MATCH(G4,'Selected_Interventions'!$Q$2:$Q$18,0)),"") | W4: Provisional | X4: =IF(AND(P4<>"",P4>=0,S4<>"",K4<>"",K4>=0,K4<=1,OR(J4="all",J4="prevalence",J4="incidence")),1,0)
A5: COST_HF_ACUTE_C_HHD | B5: CC_HF_ACUTE_C_HHD | C5: Base | D5: I_HF_ACUTE | E5: C_HHD | F5: hhd | G5: I_HF_ACUTE__C_HHD | H5: cause-specific | I5: Acute heart-failure management package | J5: prevalence | K5: 0.5 | L5: 1 | M5: 30 | N5: 95 | O5: Both | P5: 282.51284 | Q5: 2023 | R5: 1 | S5: =IFERROR(INDEX('Selected_Interventions'!$L$2:$L$18,MATCH(G5,'Selected_Interventions'!$Q$2:$Q$18,0)),"") | T5: =IFERROR(INDEX('Selected_Interventions'!$M$2:$M$18,MATCH(G5,'Selected_Interventions'!$Q$2:$Q$18,0)),"") | U5: =IFERROR(INDEX('Selected_Interventions'!$N$2:$N$18,MATCH(G5,'Selected_Interventions'!$Q$2:$Q$18,0)),"") | V5: =IFERROR(INDEX('Selected_Interventions'!$O$2:$O$18,MATCH(G5,'Selected_Interventions'!$Q$2:$Q$18,0)),"") | W5: Provisional | X5: =IF(AND(P5<>"",P5>=0,S5<>"",K5<>"",K5>=0,K5<=1,OR(J5="all",J5="prevalence",J5="incidence")),1,0)
A6: COST_HF_ACUTE_C_IHD | B6: CC_HF_ACUTE_C_IHD | C6: Base | D6: I_HF_ACUTE | E6: C_IHD | F6: ihd | G6: I_HF_ACUTE__C_IHD | H6: cause-specific | I6: Acute heart-failure management package | J6: prevalence | K6: 0.1 | L6: 1 | M6: 30 | N6: 95 | O6: Both | P6: 282.51284 | Q6: 2023 | R6: 1 | S6: =IFERROR(INDEX('Selected_Interventions'!$L$2:$L$18,MATCH(G6,'Selected_Interventions'!$Q$2:$Q$18,0)),"") | T6: =IFERROR(INDEX('Selected_Interventions'!$M$2:$M$18,MATCH(G6,'Selected_Interventions'!$Q$2:$Q$18,0)),"") | U6: =IFERROR(INDEX('Selected_Interventions'!$N$2:$N$18,MATCH(G6,'Selected_Interventions'!$Q$2:$Q$18,0)),"") | V6: =IFERROR(INDEX('Selected_Interventions'!$O$2:$O$18,MATCH(G6,'Selected_Interventions'!$Q$2:$Q$18,0)),"") | W6: Provisional | X6: =IF(AND(P6<>"",P6>=0,S6<>"",K6<>"",K6>=0,K6<=1,OR(J6="all",J6="prevalence",J6="incidence")),1,0)
A7: COST_HF_CHRONIC_CMP_ECHO | B7: CC_HF_CHRONIC_CMP_ECHO | C7: Base | D7: I_HF_CHRONIC | E7: C_CMP | F7: cmd | G7: I_HF_CHRONIC__C_CMP | H7: cause-specific | I7: One cardiac echo per year | J7: prevalence | K7: 1 | L7: 1 | M7: 0 | N7: 95 | O7: Both | P7: 5.133311 | Q7: 2023 | R7: 1 | S7: =IFERROR(INDEX('Selected_Interventions'!$L$2:$L$18,MATCH(G7,'Selected_Interventions'!$Q$2:$Q$18,0)),"") | T7: =IFERROR(INDEX('Selected_Interventions'!$M$2:$M$18,MATCH(G7,'Selected_Interventions'!$Q$2:$Q$18,0)),"") | U7: =IFERROR(INDEX('Selected_Interventions'!$N$2:$N$18,MATCH(G7,'Selected_Interventions'!$Q$2:$Q$18,0)),"") | V7: =IFERROR(INDEX('Selected_Interventions'!$O$2:$O$18,MATCH(G7,'Selected_Interventions'!$Q$2:$Q$18,0)),"") | W7: Provisional | X7: =IF(AND(P7<>"",P7>=0,S7<>"",K7<>"",K7>=0,K7<=1,OR(J7="all",J7="prevalence",J7="incidence")),1,0)
A8: COST_HF_CHRONIC_CMP_LAB_A | B8: CC_HF_CHRONIC_CMP_FOLLOWUP | C8: Option A (selected) | D8: I_HF_CHRONIC | E8: C_CMP | F8: cmd | G8: I_HF_CHRONIC__C_CMP | H8: cause-specific | I8: Lab tests and follow-up visits | J8: prevalence | K8: 1 | L8: 1 | M8: 0 | N8: 95 | O8: Both | P8: 35.362649 | Q8: 2023 | R8: 1 | S8: =IFERROR(INDEX('Selected_Interventions'!$L$2:$L$18,MATCH(G8,'Selected_Interventions'!$Q$2:$Q$18,0)),"") | T8: =IFERROR(INDEX('Selected_Interventions'!$M$2:$M$18,MATCH(G8,'Selected_Interventions'!$Q$2:$Q$18,0)),"") | U8: =IFERROR(INDEX('Selected_Interventions'!$N$2:$N$18,MATCH(G8,'Selected_Interventions'!$Q$2:$Q$18,0)),"") | V8: =IFERROR(INDEX('Selected_Interventions'!$O$2:$O$18,MATCH(G8,'Selected_Interventions'!$Q$2:$Q$18,0)),"") | W8: Review | X8: =IF(AND(P8<>"",P8>=0,S8<>"",K8<>"",K8>=0,K8<=1,OR(J8="all",J8="prevalence",J8="incidence")),1,0)
A9: COST_HF_CHRONIC_CMP_TX | B9: CC_HF_CHRONIC_CMP_TREATMENT | C9: Base | D9: I_HF_CHRONIC | E9: C_CMP | F9: cmd | G9: I_HF_CHRONIC__C_CMP | H9: cause-specific | I9: Treatment of heart failure | J9: prevalence | K9: 1 | L9: 1 | M9: 0 | N9: 95 | O9: Both | P9: 115.10623 | Q9: 2023 | R9: 1 | S9: =IFERROR(INDEX('Selected_Interventions'!$L$2:$L$18,MATCH(G9,'Selected_Interventions'!$Q$2:$Q$18,0)),"") | T9: =IFERROR(INDEX('Selected_Interventions'!$M$2:$M$18,MATCH(G9,'Selected_Interventions'!$Q$2:$Q$18,0)),"") | U9: =IFERROR(INDEX('Selected_Interventions'!$N$2:$N$18,MATCH(G9,'Selected_Interventions'!$Q$2:$Q$18,0)),"") | V9: =IFERROR(INDEX('Selected_Interventions'!$O$2:$O$18,MATCH(G9,'Selected_Interventions'!$Q$2:$Q$18,0)),"") | W9: Provisional | X9: =IF(AND(P9<>"",P9>=0,S9<>"",K9<>"",K9>=0,K9<=1,OR(J9="all",J9="prevalence",J9="incidence")),1,0)
A10: COST_HF_CHRONIC_HHD_ECHO | B10: CC_HF_CHRONIC_HHD_ECHO | C10: Base | D10: I_HF_CHRONIC | E10: C_HHD | F10: hhd | G10: I_HF_CHRONIC__C_HHD | H10: cause-specific | I10: One cardiac echo per year | J10: prevalence | K10: 1 | L10: 1 | M10: 30 | N10: 95 | O10: Both | P10: 5.133311 | Q10: 2023 | R10: 1 | S10: =IFERROR(INDEX('Selected_Interventions'!$L$2:$L$18,MATCH(G10,'Selected_Interventions'!$Q$2:$Q$18,0)),"") | T10: =IFERROR(INDEX('Selected_Interventions'!$M$2:$M$18,MATCH(G10,'Selected_Interventions'!$Q$2:$Q$18,0)),"") | U10: =IFERROR(INDEX('Selected_Interventions'!$N$2:$N$18,MATCH(G10,'Selected_Interventions'!$Q$2:$Q$18,0)),"") | V10: =IFERROR(INDEX('Selected_Interventions'!$O$2:$O$18,MATCH(G10,'Selected_Interventions'!$Q$2:$Q$18,0)),"") | W10: Provisional | X10: =IF(AND(P10<>"",P10>=0,S10<>"",K10<>"",K10>=0,K10<=1,OR(J10="all",J10="prevalence",J10="incidence")),1,0)
A11: COST_HF_CHRONIC_HHD_LAB_A | B11: CC_HF_CHRONIC_HHD_FOLLOWUP | C11: Option A (selected) | D11: I_HF_CHRONIC | E11: C_HHD | F11: hhd | G11: I_HF_CHRONIC__C_HHD | H11: cause-specific | I11: Lab tests and follow-up visits | J11: prevalence | K11: 1 | L11: 1 | M11: 30 | N11: 95 | O11: Both | P11: 35.362649 | Q11: 2023 | R11: 1 | S11: =IFERROR(INDEX('Selected_Interventions'!$L$2:$L$18,MATCH(G11,'Selected_Interventions'!$Q$2:$Q$18,0)),"") | T11: =IFERROR(INDEX('Selected_Interventions'!$M$2:$M$18,MATCH(G11,'Selected_Interventions'!$Q$2:$Q$18,0)),"") | U11: =IFERROR(INDEX('Selected_Interventions'!$N$2:$N$18,MATCH(G11,'Selected_Interventions'!$Q$2:$Q$18,0)),"") | V11: =IFERROR(INDEX('Selected_Interventions'!$O$2:$O$18,MATCH(G11,'Selected_Interventions'!$Q$2:$Q$18,0)),"") | W11: Review | X11: =IF(AND(P11<>"",P11>=0,S11<>"",K11<>"",K11>=0,K11<=1,OR(J11="all",J11="prevalence",J11="incidence")),1,0)
A12: COST_HF_CHRONIC_HHD_TX | B12: CC_HF_CHRONIC_HHD_TREATMENT | C12: Base | D12: I_HF_CHRONIC | E12: C_HHD | F12: hhd | G12: I_HF_CHRONIC__C_HHD | H12: cause-specific | I12: Treatment of heart failure | J12: prevalence | K12: 1 | L12: 1 | M12: 0 | N12: 95 | O12: Both | P12: 115.10623 | Q12: 2023 | R12: 1 | S12: =IFERROR(INDEX('Selected_Interventions'!$L$2:$L$18,MATCH(G12,'Selected_Interventions'!$Q$2:$Q$18,0)),"") | T12: =IFERROR(INDEX('Selected_Interventions'!$M$2:$M$18,MATCH(G12,'Selected_Interventions'!$Q$2:$Q$18,0)),"") | U12: =IFERROR(INDEX('Selected_Interventions'!$N$2:$N$18,MATCH(G12,'Selected_Interventions'!$Q$2:$Q$18,0)),"") | V12: =IFERROR(INDEX('Selected_Interventions'!$O$2:$O$18,MATCH(G12,'Selected_Interventions'!$Q$2:$Q$18,0)),"") | W12: Provisional | X12: =IF(AND(P12<>"",P12>=0,S12<>"",K12<>"",K12>=0,K12<=1,OR(J12="all",J12="prevalence",J12="incidence")),1,0)
A13: COST_HF_CHRONIC_IHD_ECHO | B13: CC_HF_CHRONIC_IHD_ECHO | C13: Base | D13: I_HF_CHRONIC | E13: C_IHD | F13: ihd | G13: I_HF_CHRONIC__C_IHD | H13: cause-specific | I13: One cardiac echo per year | J13: prevalence | K13: 0.2 | L13: 1 | M13: 30 | N13: 95 | O13: Both | P13: 5.133311 | Q13: 2023 | R13: 1 | S13: =IFERROR(INDEX('Selected_Interventions'!$L$2:$L$18,MATCH(G13,'Selected_Interventions'!$Q$2:$Q$18,0)),"") | T13: =IFERROR(INDEX('Selected_Interventions'!$M$2:$M$18,MATCH(G13,'Selected_Interventions'!$Q$2:$Q$18,0)),"") | U13: =IFERROR(INDEX('Selected_Interventions'!$N$2:$N$18,MATCH(G13,'Selected_Interventions'!$Q$2:$Q$18,0)),"") | V13: =IFERROR(INDEX('Selected_Interventions'!$O$2:$O$18,MATCH(G13,'Selected_Interventions'!$Q$2:$Q$18,0)),"") | W13: Provisional | X13: =IF(AND(P13<>"",P13>=0,S13<>"",K13<>"",K13>=0,K13<=1,OR(J13="all",J13="prevalence",J13="incidence")),1,0)
A14: COST_HF_CHRONIC_IHD_LAB | B14: CC_HF_CHRONIC_IHD_FOLLOWUP | C14: Missing | D14: I_HF_CHRONIC | E14: C_IHD | F14: ihd | G14: I_HF_CHRONIC__C_IHD | H14: cause-specific | I14: Lab tests and follow-up visits | J14: prevalence | K14: 0.2 | L14: 1 | M14: 30 | N14: 95 | O14: Both | P14: 7 | Q14: 2023 | R14: 1 | S14: =IFERROR(INDEX('Selected_Interventions'!$L$2:$L$18,MATCH(G14,'Selected_Interventions'!$Q$2:$Q$18,0)),"") | T14: =IFERROR(INDEX('Selected_Interventions'!$M$2:$M$18,MATCH(G14,'Selected_Interventions'!$Q$2:$Q$18,0)),"") | U14: =IFERROR(INDEX('Selected_Interventions'!$N$2:$N$18,MATCH(G14,'Selected_Interventions'!$Q$2:$Q$18,0)),"") | V14: =IFERROR(INDEX('Selected_Interventions'!$O$2:$O$18,MATCH(G14,'Selected_Interventions'!$Q$2:$Q$18,0)),"") | W14: Missing input | X14: =IF(AND(P14<>"",P14>=0,S14<>"",K14<>"",K14>=0,K14<=1,OR(J14="all",J14="prevalence",J14="incidence")),1,0)
A15: COST_HF_CHRONIC_IHD_TX | B15: CC_HF_CHRONIC_IHD_TREATMENT | C15: Base | D15: I_HF_CHRONIC | E15: C_IHD | F15: ihd | G15: I_HF_CHRONIC__C_IHD | H15: cause-specific | I15: Treatment of heart failure | J15: prevalence | K15: 0.2 | L15: 1 | M15: 30 | N15: 95 | O15: Both | P15: 29.216219 | Q15: 2023 | R15: 1 | S15: =IFERROR(INDEX('Selected_Interventions'!$L$2:$L$18,MATCH(G15,'Selected_Interventions'!$Q$2:$Q$18,0)),"") | T15: =IFERROR(INDEX('Selected_Interventions'!$M$2:$M$18,MATCH(G15,'Selected_Interventions'!$Q$2:$Q$18,0)),"") | U15: =IFERROR(INDEX('Selected_Interventions'!$N$2:$N$18,MATCH(G15,'Selected_Interventions'!$Q$2:$Q$18,0)),"") | V15: =IFERROR(INDEX('Selected_Interventions'!$O$2:$O$18,MATCH(G15,'Selected_Interventions'!$Q$2:$Q$18,0)),"") | W15: Provisional | X15: =IF(AND(P15<>"",P15>=0,S15<>"",K15<>"",K15>=0,K15<=1,OR(J15="all",J15="prevalence",J15="incidence")),1,0)
... A27: COST_T2D_TREATMENT | B27: CC_T2D_TREATMENT | C27: Base | D27: I_T2D_TREATMENT | E27: C_T2D | F27: dm2 | G27: I_T2D_TREATMENT__C_T2D | H27: cause-specific | I27: Diabetes screening and treatment | J27: prevalence | K27: 0.8 | L27: 1 | M27: 0 | N27: 95 | O27: Both | P27: 176.67 | Q27: 2014 | R27: 0 | S27: =IFERROR(INDEX('Selected_Interventions'!$L$2:$L$18,MATCH(G27,'Selected_Interventions'!$Q$2:$Q$18,0)),"") | T27: =IFERROR(INDEX('Selected_Interventions'!$M$2:$M$18,MATCH(G27,'Selected_Interventions'!$Q$2:$Q$18,0)),"") | U27: =IFERROR(INDEX('Selected_Interventions'!$N$2:$N$18,MATCH(G27,'Selected_Interventions'!$Q$2:$Q$18,0)),"") | V27: =IFERROR(INDEX('Selected_Interventions'!$O$2:$O$18,MATCH(G27,'Selected_Interventions'!$Q$2:$Q$18,0)),"") | W27: Review | X27: =IF(AND(P27<>"",P27>=0,S27<>"",K27<>"",K27>=0,K27<=1,OR(J27="all",J27="prevalence",J27="incidence")),1,0)

Sheet Annual_Mortality
A1: scenario | B1: scenario_label | C1: year | D1: cause | E1: cases | F1: cause_deaths | G1: base_deaths | H1: deaths_averted | I1: base_cases | J1: cases_averted
A2: I_CVD_PRIMARY | B2: Primary prevention of CVD | C2: 2025 | D2: cmd | E2: 12176.171 | F2: 8959.2701 | G2: 8959.2701 | H2: =G2-F2 | I2: 12176.171 | J2: =I2-E2
A3: I_CVD_PRIMARY | B3: Primary prevention of CVD | C3: 2025 | D3: dm2 | E3: 1026758.6 | F3: 129383.32 | G3: 129383.32 | H3: =G3-F3 | I3: 1026758.6 | J3: =I3-E3
A4: I_CVD_PRIMARY | B4: Primary prevention of CVD | C4: 2025 | D4: hhd | E4: 114347.21 | F4: 67656.559 | G4: 67656.559 | H4: =G4-F4 | I4: 115291.16 | J4: =I4-E4
A5: I_CVD_PRIMARY | B5: Primary prevention of CVD | C5: 2025 | D5: hstroke | E5: 279608.74 | F5: 263295.7 | G5: 263295.7 | H5: =G5-F5 | I5: 281662.55 | J5: =I5-E5
A6: I_CVD_PRIMARY | B6: Primary prevention of CVD | C6: 2025 | D6: ihd | E6: 606792.13 | F6: 335724.87 | G6: 335724.87 | H6: =G6-F6 | I6: 612171.63 | J6: =I6-E6
A7: I_CVD_PRIMARY | B7: Primary prevention of CVD | C7: 2025 | D7: istroke | E7: 337040.93 | F7: 190841.88 | G7: 190841.88 | H7: =G7-F7 | I7: 339642.13 | J7: =I7-E7
A8: I_CVD_PRIMARY | B8: Primary prevention of CVD | C8: 2025 | D8: rhd | E8: 39660.837 | F8: 5303.4223 | G8: 5303.4223 | H8: =G8-F8 | I8: 39660.837 | J8: =I8-E8
A9: I_CVD_PRIMARY | B9: Primary prevention of CVD | C9: 2026 | D9: cmd | E9: 12568.939 | F9: 9271.1334 | G9: 9271.1334 | H9: =G9-F9 | I9: 12568.939 | J9: =I9-E9
A10: I_CVD_PRIMARY | B10: Primary prevention of CVD | C10: 2026 | D10: dm2 | E10: 1042135.2 | F10: 137145.83 | G10: 137145.83 | H10: =G10-F10 | I10: 1042135.2 | J10: =I10-E10
A11: I_CVD_PRIMARY | B11: Primary prevention of CVD | C11: 2026 | D11: hhd | E11: 112796.49 | F11: 70191.013 | G11: 70326.603 | H11: =G11-F11 | I11: 114707.99 | J11: =I11-E11
A12: I_CVD_PRIMARY | B12: Primary prevention of CVD | C12: 2026 | D12: hstroke | E12: 278609.32 | F12: 258660.04 | G12: 259504.47 | H12: =G12-F12 | I12: 282722.54 | J12: =I12-E12
A13: I_CVD_PRIMARY | B13: Primary prevention of CVD | C13: 2026 | D13: ihd | E13: 605871.29 | F13: 342642.48 | G13: 342960.14 | H13: =G13-F13 | I13: 616790.03 | J13: =I13-E13
... A1821: baseline | B1821: Baseline (no new intervention) | C1821: 2050 | D1821: rhd | E1821: 33926.479 | F1821: 1888.515 | G1821: 1888.515 | H1821: =G1821-F1821 | I1821: 33926.479 | J1821: =I1821-E1821

Sheet Annual_Cost
A1: scenario | B1: year | C1: intervention_id | D1: cause_code | E1: cost_record_id | F1: cost_component_key | G1: cost_join_key | H1: cost_scope | I1: population_in_need_measure | J1: population_in_need_fraction | K1: coverage_scenario | L1: coverage_baseline | M1: frequency_per_year | N1: unit_cost_usd | O1: pin_scenario | P1: pin_baseline | Q1: annual_cost_baseline | R1: annual_cost_scenario | S1: annual_cost_incremental | T1: indonesia_adjusted_flag | U1: price_year | V1: discount_factor | W1: disc_cost_baseline | X1: disc_cost_scenario | Y1: disc_cost_incremental | Z1: cov_target | AA1: cov_start_year | AB1: cov_target_year | AC1: c_age_start | AD1: c_age_stop | AE1: c_sex | AF1: r_quantity_scenario | AG1: r_quantity_baseline | AH1: shared_duplicate_count
A2: I_CVD_PRIMARY | B2: 2025 | C2: I_CVD_PRIMARY | E2: COST_PRIMARY_SCREEN_A | F2: CC_PRIMARY_SCREENING | G2: I_CVD_PRIMARY__C_SHARED | H2: shared-count-once | I2: all | J2: =IFERROR(INDEX('Cost_Components'!$K$2:$K$27,MATCH(E2,'Cost_Components'!$A$2:$A$27,0)),"") | K2: =IF(OR(L2="",Z2="",AA2="",AB2=""),"",IF(B2<AA2,L2,IF(B2>AB2,Z2,L2+(Z2-L2)*MIN(MAX((B2-AA2+1)/MAX(AB2-AA2+1,1),0),1)))) | L2: =IFERROR(INDEX('Cost_Components'!$S$2:$S$27,MATCH(E2,'Cost_Components'!$A$2:$A$27,0)),"") | M2: =IFERROR(INDEX('Cost_Components'!$L$2:$L$27,MATCH(E2,'Cost_Components'!$A$2:$A$27,0)),"") | N2: =IFERROR(INDEX('Cost_Components'!$P$2:$P$27,MATCH(E2,'Cost_Components'!$A$2:$A$27,0)),"") | O2: =AF2*J2 | P2: =AG2*J2 | Q2: =P2*L2*M2*N2 | R2: =O2*K2*M2*N2 | S2: =R2-Q2 | T2: =IFERROR(INDEX('Cost_Components'!$R$2:$R$27,MATCH(E2,'Cost_Components'!$A$2:$A$27,0)),"") | U2: =IFERROR(INDEX('Cost_Components'!$Q$2:$Q$27,MATCH(E2,'Cost_Components'!$A$2:$A$27,0)),"") | V2: =1/(1+'Calculation_Assumptions'!$B$5)^(B2-'Calculation_Assumptions'!$B$2) | W2: =Q2*V2 | X2: =R2*V2 | Y2: =S2*V2 | Z2: =IFERROR(INDEX('Cost_Components'!$T$2:$T$27,MATCH(E2,'Cost_Components'!$A$2:$A$27,0)),"") | AA2: =IFERROR(INDEX('Cost_Components'!$U$2:$U$27,MATCH(E2,'Cost_Components'!$A$2:$A$27,0)),"") | AB2: =IFERROR(INDEX('Cost_Components'!$V$2:$V$27,MATCH(E2,'Cost_Components'!$A$2:$A$27,0)),"") | AC2: =IFERROR(INDEX('Cost_Components'!$M$2:$M$27,MATCH(E2,'Cost_Components'!$A$2:$A$27,0)),"") | AD2: =IFERROR(INDEX('Cost_Components'!$N$2:$N$27,MATCH(E2,'Cost_Components'!$A$2:$A$27,0)),"") | AE2: =IFERROR(INDEX('Cost_Components'!$O$2:$O$27,MATCH(E2,'Cost_Components'!$A$2:$A$27,0)),"") | AF2: 3.03073e+08 | AG2: 3.03073e+08 | AH2: =IF(H2="shared-count-once",COUNTIFS($A$2:$A$1353,A2,$B$2:$B$1353,B2,$E$2:$E$1353,E2),1)
A3: I_CVD_PRIMARY | B3: 2026 | C3: I_CVD_PRIMARY | E3: COST_PRIMARY_SCREEN_A | F3: CC_PRIMARY_SCREENING | G3: I_CVD_PRIMARY__C_SHARED | H3: shared-count-once | I3: all | J3: =IFERROR(INDEX('Cost_Components'!$K$2:$K$27,MATCH(E3,'Cost_Components'!$A$2:$A$27,0)),"") | K3: =IF(OR(L3="",Z3="",AA3="",AB3=""),"",IF(B3<AA3,L3,IF(B3>AB3,Z3,L3+(Z3-L3)*MIN(MAX((B3-AA3+1)/MAX(AB3-AA3+1,1),0),1)))) | L3: =IFERROR(INDEX('Cost_Components'!$S$2:$S$27,MATCH(E3,'Cost_Components'!$A$2:$A$27,0)),"") | M3: =IFERROR(INDEX('Cost_Components'!$L$2:$L$27,MATCH(E3,'Cost_Components'!$A$2:$A$27,0)),"") | N3: =IFERROR(INDEX('Cost_Components'!$P$2:$P$27,MATCH(E3,'Cost_Components'!$A$2:$A$27,0)),"") | O3: =AF3*J3 | P3: =AG3*J3 | Q3: =P3*L3*M3*N3 | R3: =O3*K3*M3*N3 | S3: =R3-Q3 | T3: =IFERROR(INDEX('Cost_Components'!$R$2:$R$27,MATCH(E3,'Cost_Components'!$A$2:$A$27,0)),"") | U3: =IFERROR(INDEX('Cost_Components'!$Q$2:$Q$27,MATCH(E3,'Cost_Components'!$A$2:$A$27,0)),"") | V3: =1/(1+'Calculation_Assumptions'!$B$5)^(B3-'Calculation_Assumptions'!$B$2) | W3: =Q3*V3 | X3: =R3*V3 | Y3: =S3*V3 | Z3: =IFERROR(INDEX('Cost_Components'!$T$2:$T$27,MATCH(E3,'Cost_Components'!$A$2:$A$27,0)),"") | AA3: =IFERROR(INDEX('Cost_Components'!$U$2:$U$27,MATCH(E3,'Cost_Components'!$A$2:$A$27,0)),"") | AB3: =IFERROR(INDEX('Cost_Components'!$V$2:$V$27,MATCH(E3,'Cost_Components'!$A$2:$A$27,0)),"") | AC3: =IFERROR(INDEX('Cost_Components'!$M$2:$M$27,MATCH(E3,'Cost_Components'!$A$2:$A$27,0)),"") | AD3: =IFERROR(INDEX('Cost_Components'!$N$2:$N$27,MATCH(E3,'Cost_Components'!$A$2:$A$27,0)),"") | AE3: =IFERROR(INDEX('Cost_Components'!$O$2:$O$27,MATCH(E3,'Cost_Components'!$A$2:$A$27,0)),"") | AF3: 3.0764667e+08 | AG3: 3.0764667e+08 | AH3: =IF(H3="shared-count-once",COUNTIFS($A$2:$A$1353,A3,$B$2:$B$1353,B3,$E$2:$E$1353,E3),1)
A4: I_CVD_PRIMARY | B4: 2027 | C4: I_CVD_PRIMARY | E4: COST_PRIMARY_SCREEN_A | F4: CC_PRIMARY_SCREENING | G4: I_CVD_PRIMARY__C_SHARED | H4: shared-count-once | I4: all | J4: =IFERROR(INDEX('Cost_Components'!$K$2:$K$27,MATCH(E4,'Cost_Components'!$A$2:$A$27,0)),"") | K4: =IF(OR(L4="",Z4="",AA4="",AB4=""),"",IF(B4<AA4,L4,IF(B4>AB4,Z4,L4+(Z4-L4)*MIN(MAX((B4-AA4+1)/MAX(AB4-AA4+1,1),0),1)))) | L4: =IFERROR(INDEX('Cost_Components'!$S$2:$S$27,MATCH(E4,'Cost_Components'!$A$2:$A$27,0)),"") | M4: =IFERROR(INDEX('Cost_Components'!$L$2:$L$27,MATCH(E4,'Cost_Components'!$A$2:$A$27,0)),"") | N4: =IFERROR(INDEX('Cost_Components'!$P$2:$P$27,MATCH(E4,'Cost_Components'!$A$2:$A$27,0)),"") | O4: =AF4*J4 | P4: =AG4*J4 | Q4: =P4*L4*M4*N4 | R4: =O4*K4*M4*N4 | S4: =R4-Q4 | T4: =IFERROR(INDEX('Cost_Components'!$R$2:$R$27,MATCH(E4,'Cost_Components'!$A$2:$A$27,0)),"") | U4: =IFERROR(INDEX('Cost_Components'!$Q$2:$Q$27,MATCH(E4,'Cost_Components'!$A$2:$A$27,0)),"") | V4: =1/(1+'Calculation_Assumptions'!$B$5)^(B4-'Calculation_Assumptions'!$B$2) | W4: =Q4*V4 | X4: =R4*V4 | Y4: =S4*V4 | Z4: =IFERROR(INDEX('Cost_Components'!$T$2:$T$27,MATCH(E4,'Cost_Components'!$A$2:$A$27,0)),"") | AA4: =IFERROR(INDEX('Cost_Components'!$U$2:$U$27,MATCH(E4,'Cost_Components'!$A$2:$A$27,0)),"") | AB4: =IFERROR(INDEX('Cost_Components'!$V$2:$V$27,MATCH(E4,'Cost_Components'!$A$2:$A$27,0)),"") | AC4: =IFERROR(INDEX('Cost_Components'!$M$2:$M$27,MATCH(E4,'Cost_Components'!$A$2:$A$27,0)),"") | AD4: =IFERROR(INDEX('Cost_Components'!$N$2:$N$27,MATCH(E4,'Cost_Components'!$A$2:$A$27,0)),"") | AE4: =IFERROR(INDEX('Cost_Components'!$O$2:$O$27,MATCH(E4,'Cost_Components'!$A$2:$A$27,0)),"") | AF4: 3.1226697e+08 | AG4: 3.119751e+08 | AH4: =IF(H4="shared-count-once",COUNTIFS($A$2:$A$1353,A4,$B$2:$B$1353,B4,$E$2:$E$1353,E4),1)
A5: I_CVD_PRIMARY | B5: 2028 | C5: I_CVD_PRIMARY | E5: COST_PRIMARY_SCREEN_A | F5: CC_PRIMARY_SCREENING | G5: I_CVD_PRIMARY__C_SHARED | H5: shared-count-once | I5: all | J5: =IFERROR(INDEX('Cost_Components'!$K$2:$K$27,MATCH(E5,'Cost_Components'!$A$2:$A$27,0)),"") | K5: =IF(OR(L5="",Z5="",AA5="",AB5=""),"",IF(B5<AA5,L5,IF(B5>AB5,Z5,L5+(Z5-L5)*MIN(MAX((B5-AA5+1)/MAX(AB5-AA5+1,1),0),1)))) | L5: =IFERROR(INDEX('Cost_Components'!$S$2:$S$27,MATCH(E5,'Cost_Components'!$A$2:$A$27,0)),"") | M5: =IFERROR(INDEX('Cost_Components'!$L$2:$L$27,MATCH(E5,'Cost_Components'!$A$2:$A$27,0)),"") | N5: =IFERROR(INDEX('Cost_Components'!$P$2:$P$27,MATCH(E5,'Cost_Components'!$A$2:$A$27,0)),"") | O5: =AF5*J5 | P5: =AG5*J5 | Q5: =P5*L5*M5*N5 | R5: =O5*K5*M5*N5 | S5: =R5-Q5 | T5: =IFERROR(INDEX('Cost_Components'!$R$2:$R$27,MATCH(E5,'Cost_Components'!$A$2:$A$27,0)),"") | U5: =IFERROR(INDEX('Cost_Components'!$Q$2:$Q$27,MATCH(E5,'Cost_Components'!$A$2:$A$27,0)),"") | V5: =1/(1+'Calculation_Assumptions'!$B$5)^(B5-'Calculation_Assumptions'!$B$2) | W5: =Q5*V5 | X5: =R5*V5 | Y5: =S5*V5 | Z5: =IFERROR(INDEX('Cost_Components'!$T$2:$T$27,MATCH(E5,'Cost_Components'!$A$2:$A$27,0)),"") | AA5: =IFERROR(INDEX('Cost_Components'!$U$2:$U$27,MATCH(E5,'Cost_Components'!$A$2:$A$27,0)),"") | AB5: =IFERROR(INDEX('Cost_Components'!$V$2:$V$27,MATCH(E5,'Cost_Components'!$A$2:$A$27,0)),"") | AC5: =IFERROR(INDEX('Cost_Components'!$M$2:$M$27,MATCH(E5,'Cost_Components'!$A$2:$A$27,0)),"") | AD5: =IFERROR(INDEX('Cost_Components'!$N$2:$N$27,MATCH(E5,'Cost_Components'!$A$2:$A$27,0)),"") | AE5: =IFERROR(INDEX('Cost_Components'!$O$2:$O$27,MATCH(E5,'Cost_Components'!$A$2:$A$27,0)),"") | AF5: 3.168103e+08 | AG5: 3.1653136e+08 | AH5: =IF(H5="shared-count-once",COUNTIFS($A$2:$A$1353,A5,$B$2:$B$1353,B5,$E$2:$E$1353,E5),1)
A6: I_CVD_PRIMARY | B6: 2029 | C6: I_CVD_PRIMARY | E6: COST_PRIMARY_SCREEN_A | F6: CC_PRIMARY_SCREENING | G6: I_CVD_PRIMARY__C_SHARED | H6: shared-count-once | I6: all | J6: =IFERROR(INDEX('Cost_Components'!$K$2:$K$27,MATCH(E6,'Cost_Components'!$A$2:$A$27,0)),"") | K6: =IF(OR(L6="",Z6="",AA6="",AB6=""),"",IF(B6<AA6,L6,IF(B6>AB6,Z6,L6+(Z6-L6)*MIN(MAX((B6-AA6+1)/MAX(AB6-AA6+1,1),0),1)))) | L6: =IFERROR(INDEX('Cost_Components'!$S$2:$S$27,MATCH(E6,'Cost_Components'!$A$2:$A$27,0)),"") | M6: =IFERROR(INDEX('Cost_Components'!$L$2:$L$27,MATCH(E6,'Cost_Components'!$A$2:$A$27,0)),"") | N6: =IFERROR(INDEX('Cost_Components'!$P$2:$P$27,MATCH(E6,'Cost_Components'!$A$2:$A$27,0)),"") | O6: =AF6*J6 | P6: =AG6*J6 | Q6: =P6*L6*M6*N6 | R6: =O6*K6*M6*N6 | S6: =R6-Q6 | T6: =IFERROR(INDEX('Cost_Components'!$R$2:$R$27,MATCH(E6,'Cost_Components'!$A$2:$A$27,0)),"") | U6: =IFERROR(INDEX('Cost_Components'!$Q$2:$Q$27,MATCH(E6,'Cost_Components'!$A$2:$A$27,0)),"") | V6: =1/(1+'Calculation_Assumptions'!$B$5)^(B6-'Calculation_Assumptions'!$B$2) | W6: =Q6*V6 | X6: =R6*V6 | Y6: =S6*V6 | Z6: =IFERROR(INDEX('Cost_Components'!$T$2:$T$27,MATCH(E6,'Cost_Components'!$A$2:$A$27,0)),"") | AA6: =IFERROR(INDEX('Cost_Components'!$U$2:$U$27,MATCH(E6,'Cost_Components'!$A$2:$A$27,0)),"") | AB6: =IFERROR(INDEX('Cost_Components'!$V$2:$V$27,MATCH(E6,'Cost_Components'!$A$2:$A$27,0)),"") | AC6: =IFERROR(INDEX('Cost_Components'!$M$2:$M$27,MATCH(E6,'Cost_Components'!$A$2:$A$27,0)),"") | AD6: =IFERROR(INDEX('Cost_Components'!$N$2:$N$27,MATCH(E6,'Cost_Components'!$A$2:$A$27,0)),"") | AE6: =IFERROR(INDEX('Cost_Components'!$O$2:$O$27,MATCH(E6,'Cost_Components'!$A$2:$A$27,0)),"") | AF6: 3.2119755e+08 | AG6: 3.2092558e+08 | AH6: =IF(H6="shared-count-once",COUNTIFS($A$2:$A$1353,A6,$B$2:$B$1353,B6,$E$2:$E$1353,E6),1)
A7: I_CVD_PRIMARY | B7: 2030 | C7: I_CVD_PRIMARY | E7: COST_PRIMARY_SCREEN_A | F7: CC_PRIMARY_SCREENING | G7: I_CVD_PRIMARY__C_SHARED | H7: shared-count-once | I7: all | J7: =IFERROR(INDEX('Cost_Components'!$K$2:$K$27,MATCH(E7,'Cost_Components'!$A$2:$A$27,0)),"") | K7: =IF(OR(L7="",Z7="",AA7="",AB7=""),"",IF(B7<AA7,L7,IF(B7>AB7,Z7,L7+(Z7-L7)*MIN(MAX((B7-AA7+1)/MAX(AB7-AA7+1,1),0),1)))) | L7: =IFERROR(INDEX('Cost_Components'!$S$2:$S$27,MATCH(E7,'Cost_Components'!$A$2:$A$27,0)),"") | M7: =IFERROR(INDEX('Cost_Components'!$L$2:$L$27,MATCH(E7,'Cost_Components'!$A$2:$A$27,0)),"") | N7: =IFERROR(INDEX('Cost_Components'!$P$2:$P$27,MATCH(E7,'Cost_Components'!$A$2:$A$27,0)),"") | O7: =AF7*J7 | P7: =AG7*J7 | Q7: =P7*L7*M7*N7 | R7: =O7*K7*M7*N7 | S7: =R7-Q7 | T7: =IFERROR(INDEX('Cost_Components'!$R$2:$R$27,MATCH(E7,'Cost_Components'!$A$2:$A$27,0)),"") | U7: =IFERROR(INDEX('Cost_Components'!$Q$2:$Q$27,MATCH(E7,'Cost_Components'!$A$2:$A$27,0)),"") | V7: =1/(1+'Calculation_Assumptions'!$B$5)^(B7-'Calculation_Assumptions'!$B$2) | W7: =Q7*V7 | X7: =R7*V7 | Y7: =S7*V7 | Z7: =IFERROR(INDEX('Cost_Components'!$T$2:$T$27,MATCH(E7,'Cost_Components'!$A$2:$A$27,0)),"") | AA7: =IFERROR(INDEX('Cost_Components'!$U$2:$U$27,MATCH(E7,'Cost_Components'!$A$2:$A$27,0)),"") | AB7: =IFERROR(INDEX('Cost_Components'!$V$2:$V$27,MATCH(E7,'Cost_Components'!$A$2:$A$27,0)),"") | AC7: =IFERROR(INDEX('Cost_Components'!$M$2:$M$27,MATCH(E7,'Cost_Components'!$A$2:$A$27,0)),"") | AD7: =IFERROR(INDEX('Cost_Components'!$N$2:$N$27,MATCH(E7,'Cost_Components'!$A$2:$A$27,0)),"") | AE7: =IFERROR(INDEX('Cost_Components'!$O$2:$O$27,MATCH(E7,'Cost_Components'!$A$2:$A$27,0)),"") | AF7: 3.2541001e+08 | AG7: 3.2513696e+08 | AH7: =IF(H7="shared-count-once",COUNTIFS($A$2:$A$1353,A7,$B$2:$B$1353,B7,$E$2:$E$1353,E7),1)
A8: I_CVD_PRIMARY | B8: 2031 | C8: I_CVD_PRIMARY | E8: COST_PRIMARY_SCREEN_A | F8: CC_PRIMARY_SCREENING | G8: I_CVD_PRIMARY__C_SHARED | H8: shared-count-once | I8: all | J8: =IFERROR(INDEX('Cost_Components'!$K$2:$K$27,MATCH(E8,'Cost_Components'!$A$2:$A$27,0)),"") | K8: =IF(OR(L8="",Z8="",AA8="",AB8=""),"",IF(B8<AA8,L8,IF(B8>AB8,Z8,L8+(Z8-L8)*MIN(MAX((B8-AA8+1)/MAX(AB8-AA8+1,1),0),1)))) | L8: =IFERROR(INDEX('Cost_Components'!$S$2:$S$27,MATCH(E8,'Cost_Components'!$A$2:$A$27,0)),"") | M8: =IFERROR(INDEX('Cost_Components'!$L$2:$L$27,MATCH(E8,'Cost_Components'!$A$2:$A$27,0)),"") | N8: =IFERROR(INDEX('Cost_Components'!$P$2:$P$27,MATCH(E8,'Cost_Components'!$A$2:$A$27,0)),"") | O8: =AF8*J8 | P8: =AG8*J8 | Q8: =P8*L8*M8*N8 | R8: =O8*K8*M8*N8 | S8: =R8-Q8 | T8: =IFERROR(INDEX('Cost_Components'!$R$2:$R$27,MATCH(E8,'Cost_Components'!$A$2:$A$27,0)),"") | U8: =IFERROR(INDEX('Cost_Components'!$Q$2:$Q$27,MATCH(E8,'Cost_Components'!$A$2:$A$27,0)),"") | V8: =1/(1+'Calculation_Assumptions'!$B$5)^(B8-'Calculation_Assumptions'!$B$2) | W8: =Q8*V8 | X8: =R8*V8 | Y8: =S8*V8 | Z8: =IFERROR(INDEX('Cost_Components'!$T$2:$T$27,MATCH(E8,'Cost_Components'!$A$2:$A$27,0)),"") | AA8: =IFERROR(INDEX('Cost_Components'!$U$2:$U$27,MATCH(E8,'Cost_Components'!$A$2:$A$27,0)),"") | AB8: =IFERROR(INDEX('Cost_Components'!$V$2:$V$27,MATCH(E8,'Cost_Components'!$A$2:$A$27,0)),"") | AC8: =IFERROR(INDEX('Cost_Components'!$M$2:$M$27,MATCH(E8,'Cost_Components'!$A$2:$A$27,0)),"") | AD8: =IFERROR(INDEX('Cost_Components'!$N$2:$N$27,MATCH(E8,'Cost_Components'!$A$2:$A$27,0)),"") | AE8: =IFERROR(INDEX('Cost_Components'!$O$2:$O$27,MATCH(E8,'Cost_Components'!$A$2:$A$27,0)),"") | AF8: 3.2937128e+08 | AG8: 3.2925981e+08 | AH8: =IF(H8="shared-count-once",COUNTIFS($A$2:$A$1353,A8,$B$2:$B$1353,B8,$E$2:$E$1353,E8),1)
A9: I_CVD_PRIMARY | B9: 2032 | C9: I_CVD_PRIMARY | E9: COST_PRIMARY_SCREEN_A | F9: CC_PRIMARY_SCREENING | G9: I_CVD_PRIMARY__C_SHARED | H9: shared-count-once | I9: all | J9: =IFERROR(INDEX('Cost_Components'!$K$2:$K$27,MATCH(E9,'Cost_Components'!$A$2:$A$27,0)),"") | K9: =IF(OR(L9="",Z9="",AA9="",AB9=""),"",IF(B9<AA9,L9,IF(B9>AB9,Z9,L9+(Z9-L9)*MIN(MAX((B9-AA9+1)/MAX(AB9-AA9+1,1),0),1)))) | L9: =IFERROR(INDEX('Cost_Components'!$S$2:$S$27,MATCH(E9,'Cost_Components'!$A$2:$A$27,0)),"") | M9: =IFERROR(INDEX('Cost_Components'!$L$2:$L$27,MATCH(E9,'Cost_Components'!$A$2:$A$27,0)),"") | N9: =IFERROR(INDEX('Cost_Components'!$P$2:$P$27,MATCH(E9,'Cost_Components'!$A$2:$A$27,0)),"") | O9: =AF9*J9 | P9: =AG9*J9 | Q9: =P9*L9*M9*N9 | R9: =O9*K9*M9*N9 | S9: =R9-Q9 | T9: =IFERROR(INDEX('Cost_Components'!$R$2:$R$27,MATCH(E9,'Cost_Components'!$A$2:$A$27,0)),"") | U9: =IFERROR(INDEX('Cost_Components'!$Q$2:$Q$27,MATCH(E9,'Cost_Components'!$A$2:$A$27,0)),"") | V9: =1/(1+'Calculation_Assumptions'!$B$5)^(B9-'Calculation_Assumptions'!$B$2) | W9: =Q9*V9 | X9: =R9*V9 | Y9: =S9*V9 | Z9: =IFERROR(INDEX('Cost_Components'!$T$2:$T$27,MATCH(E9,'Cost_Components'!$A$2:$A$27,0)),"") | AA9: =IFERROR(INDEX('Cost_Components'!$U$2:$U$27,MATCH(E9,'Cost_Components'!$A$2:$A$27,0)),"") | AB9: =IFERROR(INDEX('Cost_Components'!$V$2:$V$27,MATCH(E9,'Cost_Components'!$A$2:$A$27,0)),"") | AC9: =IFERROR(INDEX('Cost_Components'!$M$2:$M$27,MATCH(E9,'Cost_Components'!$A$2:$A$27,0)),"") | AD9: =IFERROR(INDEX('Cost_Components'!$N$2:$N$27,MATCH(E9,'Cost_Components'!$A$2:$A$27,0)),"") | AE9: =IFERROR(INDEX('Cost_Components'!$O$2:$O$27,MATCH(E9,'Cost_Components'!$A$2:$A$27,0)),"") | AF9: 3.3348393e+08 | AG9: 3.3333154e+08 | AH9: =IF(H9="shared-count-once",COUNTIFS($A$2:$A$1353,A9,$B$2:$B$1353,B9,$E$2:$E$1353,E9),1)
A10: I_CVD_PRIMARY | B10: 2033 | C10: I_CVD_PRIMARY | E10: COST_PRIMARY_SCREEN_A | F10: CC_PRIMARY_SCREENING | G10: I_CVD_PRIMARY__C_SHARED | H10: shared-count-once | I10: all | J10: =IFERROR(INDEX('Cost_Components'!$K$2:$K$27,MATCH(E10,'Cost_Components'!$A$2:$A$27,0)),"") | K10: =IF(OR(L10="",Z10="",AA10="",AB10=""),"",IF(B10<AA10,L10,IF(B10>AB10,Z10,L10+(Z10-L10)*MIN(MAX((B10-AA10+1)/MAX(AB10-AA10+1,1),0),1)))) | L10: =IFERROR(INDEX('Cost_Components'!$S$2:$S$27,MATCH(E10,'Cost_Components'!$A$2:$A$27,0)),"") | M10: =IFERROR(INDEX('Cost_Components'!$L$2:$L$27,MATCH(E10,'Cost_Components'!$A$2:$A$27,0)),"") | N10: =IFERROR(INDEX('Cost_Components'!$P$2:$P$27,MATCH(E10,'Cost_Components'!$A$2:$A$27,0)),"") | O10: =AF10*J10 | P10: =AG10*J10 | Q10: =P10*L10*M10*N10 | R10: =O10*K10*M10*N10 | S10: =R10-Q10 | T10: =IFERROR(INDEX('Cost_Components'!$R$2:$R$27,MATCH(E10,'Cost_Components'!$A$2:$A$27,0)),"") | U10: =IFERROR(INDEX('Cost_Components'!$Q$2:$Q$27,MATCH(E10,'Cost_Components'!$A$2:$A$27,0)),"") | V10: =1/(1+'Calculation_Assumptions'!$B$5)^(B10-'Calculation_Assumptions'!$B$2) | W10: =Q10*V10 | X10: =R10*V10 | Y10: =S10*V10 | Z10: =IFERROR(INDEX('Cost_Components'!$T$2:$T$27,MATCH(E10,'Cost_Components'!$A$2:$A$27,0)),"") | AA10: =IFERROR(INDEX('Cost_Components'!$U$2:$U$27,MATCH(E10,'Cost_Components'!$A$2:$A$27,0)),"") | AB10: =IFERROR(INDEX('Cost_Components'!$V$2:$V$27,MATCH(E10,'Cost_Components'!$A$2:$A$27,0)),"") | AC10: =IFERROR(INDEX('Cost_Components'!$M$2:$M$27,MATCH(E10,'Cost_Components'!$A$2:$A$27,0)),"") | AD10: =IFERROR(INDEX('Cost_Components'!$N$2:$N$27,MATCH(E10,'Cost_Components'!$A$2:$A$27,0)),"") | AE10: =IFERROR(INDEX('Cost_Components'!$O$2:$O$27,MATCH(E10,'Cost_Components'!$A$2:$A$27,0)),"") | AF10: 3.3755155e+08 | AG10: 3.373496e+08 | AH10: =IF(H10="shared-count-once",COUNTIFS($A$2:$A$1353,A10,$B$2:$B$1353,B10,$E$2:$E$1353,E10),1)
A11: I_CVD_PRIMARY | B11: 2034 | C11: I_CVD_PRIMARY | E11: COST_PRIMARY_SCREEN_A | F11: CC_PRIMARY_SCREENING | G11: I_CVD_PRIMARY__C_SHARED | H11: shared-count-once | I11: all | J11: =IFERROR(INDEX('Cost_Components'!$K$2:$K$27,MATCH(E11,'Cost_Components'!$A$2:$A$27,0)),"") | K11: =IF(OR(L11="",Z11="",AA11="",AB11=""),"",IF(B11<AA11,L11,IF(B11>AB11,Z11,L11+(Z11-L11)*MIN(MAX((B11-AA11+1)/MAX(AB11-AA11+1,1),0),1)))) | L11: =IFERROR(INDEX('Cost_Components'!$S$2:$S$27,MATCH(E11,'Cost_Components'!$A$2:$A$27,0)),"") | M11: =IFERROR(INDEX('Cost_Components'!$L$2:$L$27,MATCH(E11,'Cost_Components'!$A$2:$A$27,0)),"") | N11: =IFERROR(INDEX('Cost_Components'!$P$2:$P$27,MATCH(E11,'Cost_Components'!$A$2:$A$27,0)),"") | O11: =AF11*J11 | P11: =AG11*J11 | Q11: =P11*L11*M11*N11 | R11: =O11*K11*M11*N11 | S11: =R11-Q11 | T11: =IFERROR(INDEX('Cost_Components'!$R$2:$R$27,MATCH(E11,'Cost_Components'!$A$2:$A$27,0)),"") | U11: =IFERROR(INDEX('Cost_Components'!$Q$2:$Q$27,MATCH(E11,'Cost_Components'!$A$2:$A$27,0)),"") | V11: =1/(1+'Calculation_Assumptions'!$B$5)^(B11-'Calculation_Assumptions'!$B$2) | W11: =Q11*V11 | X11: =R11*V11 | Y11: =S11*V11 | Z11: =IFERROR(INDEX('Cost_Components'!$T$2:$T$27,MATCH(E11,'Cost_Components'!$A$2:$A$27,0)),"") | AA11: =IFERROR(INDEX('Cost_Components'!$U$2:$U$27,MATCH(E11,'Cost_Components'!$A$2:$A$27,0)),"") | AB11: =IFERROR(INDEX('Cost_Components'!$V$2:$V$27,MATCH(E11,'Cost_Components'!$A$2:$A$27,0)),"") | AC11: =IFERROR(INDEX('Cost_Components'!$M$2:$M$27,MATCH(E11,'Cost_Components'!$A$2:$A$27,0)),"") | AD11: =IFERROR(INDEX('Cost_Components'!$N$2:$N$27,MATCH(E11,'Cost_Components'!$A$2:$A$27,0)),"") | AE11: =IFERROR(INDEX('Cost_Components'!$O$2:$O$27,MATCH(E11,'Cost_Components'!$A$2:$A$27,0)),"") | AF11: 3.4161345e+08 | AG11: 3.4135282e+08 | AH11: =IF(H11="shared-count-once",COUNTIFS($A$2:$A$1353,A11,$B$2:$B$1353,B11,$E$2:$E$1353,E11),1)
A12: I_CVD_PRIMARY | B12: 2035 | C12: I_CVD_PRIMARY | E12: COST_PRIMARY_SCREEN_A | F12: CC_PRIMARY_SCREENING | G12: I_CVD_PRIMARY__C_SHARED | H12: shared-count-once | I12: all | J12: =IFERROR(INDEX('Cost_Components'!$K$2:$K$27,MATCH(E12,'Cost_Components'!$A$2:$A$27,0)),"") | K12: =IF(OR(L12="",Z12="",AA12="",AB12=""),"",IF(B12<AA12,L12,IF(B12>AB12,Z12,L12+(Z12-L12)*MIN(MAX((B12-AA12+1)/MAX(AB12-AA12+1,1),0),1)))) | L12: =IFERROR(INDEX('Cost_Components'!$S$2:$S$27,MATCH(E12,'Cost_Components'!$A$2:$A$27,0)),"") | M12: =IFERROR(INDEX('Cost_Components'!$L$2:$L$27,MATCH(E12,'Cost_Components'!$A$2:$A$27,0)),"") | N12: =IFERROR(INDEX('Cost_Components'!$P$2:$P$27,MATCH(E12,'Cost_Components'!$A$2:$A$27,0)),"") | O12: =AF12*J12 | P12: =AG12*J12 | Q12: =P12*L12*M12*N12 | R12: =O12*K12*M12*N12 | S12: =R12-Q12 | T12: =IFERROR(INDEX('Cost_Components'!$R$2:$R$27,MATCH(E12,'Cost_Components'!$A$2:$A$27,0)),"") | U12: =IFERROR(INDEX('Cost_Components'!$Q$2:$Q$27,MATCH(E12,'Cost_Components'!$A$2:$A$27,0)),"") | V12: =1/(1+'Calculation_Assumptions'!$B$5)^(B12-'Calculation_Assumptions'!$B$2) | W12: =Q12*V12 | X12: =R12*V12 | Y12: =S12*V12 | Z12: =IFERROR(INDEX('Cost_Components'!$T$2:$T$27,MATCH(E12,'Cost_Components'!$A$2:$A$27,0)),"") | AA12: =IFERROR(INDEX('Cost_Components'!$U$2:$U$27,MATCH(E12,'Cost_Components'!$A$2:$A$27,0)),"") | AB12: =IFERROR(INDEX('Cost_Components'!$V$2:$V$27,MATCH(E12,'Cost_Components'!$A$2:$A$27,0)),"") | AC12: =IFERROR(INDEX('Cost_Components'!$M$2:$M$27,MATCH(E12,'Cost_Components'!$A$2:$A$27,0)),"") | AD12: =IFERROR(INDEX('Cost_Components'!$N$2:$N$27,MATCH(E12,'Cost_Components'!$A$2:$A$27,0)),"") | AE12: =IFERROR(INDEX('Cost_Components'!$O$2:$O$27,MATCH(E12,'Cost_Components'!$A$2:$A$27,0)),"") | AF12: 3.4575846e+08 | AG12: 3.4542926e+08 | AH12: =IF(H12="shared-count-once",COUNTIFS($A$2:$A$1353,A12,$B$2:$B$1353,B12,$E$2:$E$1353,E12),1)
A13: I_CVD_PRIMARY | B13: 2036 | C13: I_CVD_PRIMARY | E13: COST_PRIMARY_SCREEN_A | F13: CC_PRIMARY_SCREENING | G13: I_CVD_PRIMARY__C_SHARED | H13: shared-count-once | I13: all | J13: =IFERROR(INDEX('Cost_Components'!$K$2:$K$27,MATCH(E13,'Cost_Components'!$A$2:$A$27,0)),"") | K13: =IF(OR(L13="",Z13="",AA13="",AB13=""),"",IF(B13<AA13,L13,IF(B13>AB13,Z13,L13+(Z13-L13)*MIN(MAX((B13-AA13+1)/MAX(AB13-AA13+1,1),0),1)))) | L13: =IFERROR(INDEX('Cost_Components'!$S$2:$S$27,MATCH(E13,'Cost_Components'!$A$2:$A$27,0)),"") | M13: =IFERROR(INDEX('Cost_Components'!$L$2:$L$27,MATCH(E13,'Cost_Components'!$A$2:$A$27,0)),"") | N13: =IFERROR(INDEX('Cost_Components'!$P$2:$P$27,MATCH(E13,'Cost_Components'!$A$2:$A$27,0)),"") | O13: =AF13*J13 | P13: =AG13*J13 | Q13: =P13*L13*M13*N13 | R13: =O13*K13*M13*N13 | S13: =R13-Q13 | T13: =IFERROR(INDEX('Cost_Components'!$R$2:$R$27,MATCH(E13,'Cost_Components'!$A$2:$A$27,0)),"") | U13: =IFERROR(INDEX('Cost_Components'!$Q$2:$Q$27,MATCH(E13,'Cost_Components'!$A$2:$A$27,0)),"") | V13: =1/(1+'Calculation_Assumptions'!$B$5)^(B13-'Calculation_Assumptions'!$B$2) | W13: =Q13*V13 | X13: =R13*V13 | Y13: =S13*V13 | Z13: =IFERROR(INDEX('Cost_Components'!$T$2:$T$27,MATCH(E13,'Cost_Components'!$A$2:$A$27,0)),"") | AA13: =IFERROR(INDEX('Cost_Components'!$U$2:$U$27,MATCH(E13,'Cost_Components'!$A$2:$A$27,0)),"") | AB13: =IFERROR(INDEX('Cost_Components'!$V$2:$V$27,MATCH(E13,'Cost_Components'!$A$2:$A$27,0)),"") | AC13: =IFERROR(INDEX('Cost_Components'!$M$2:$M$27,MATCH(E13,'Cost_Components'!$A$2:$A$27,0)),"") | AD13: =IFERROR(INDEX('Cost_Components'!$N$2:$N$27,MATCH(E13,'Cost_Components'!$A$2:$A$27,0)),"") | AE13: =IFERROR(INDEX('Cost_Components'!$O$2:$O$27,MATCH(E13,'Cost_Components'!$A$2:$A$27,0)),"") | AF13: 3.5004097e+08 | AG13: 3.4963346e+08 | AH13: =IF(H13="shared-count-once",COUNTIFS($A$2:$A$1353,A13,$B$2:$B$1353,B13,$E$2:$E$1353,E13),1)
... A53: I_CVD_PRIMARY | B53: 2050 | C53: I_CVD_PRIMARY | E53: COST_PRIMARY_TX_A | F53: CC_PRIMARY_HTN_STATIN | G53: I_CVD_PRIMARY__C_SHARED | H53: shared-count-once | I53: all | J53: =IFERROR(INDEX('Cost_Components'!$K$2:$K$27,MATCH(E53,'Cost_Components'!$A$2:$A$27,0)),"") | K53: =IF(OR(L53="",Z53="",AA53="",AB53=""),"",IF(B53<AA53,L53,IF(B53>AB53,Z53,L53+(Z53-L53)*MIN(MAX((B53-AA53+1)/MAX(AB53-AA53+1,1),0),1)))) | L53: =IFERROR(INDEX('Cost_Components'!$S$2:$S$27,MATCH(E53,'Cost_Components'!$A$2:$A$27,0)),"") | M53: =IFERROR(INDEX('Cost_Components'!$L$2:$L$27,MATCH(E53,'Cost_Components'!$A$2:$A$27,0)),"") | N53: =IFERROR(INDEX('Cost_Components'!$P$2:$P$27,MATCH(E53,'Cost_Components'!$A$2:$A$27,0)),"") | O53: =AF53*J53 | P53: =AG53*J53 | Q53: =P53*L53*M53*N53 | R53: =O53*K53*M53*N53 | S53: =R53-Q53 | T53: =IFERROR(INDEX('Cost_Components'!$R$2:$R$27,MATCH(E53,'Cost_Components'!$A$2:$A$27,0)),"") | U53: =IFERROR(INDEX('Cost_Components'!$Q$2:$Q$27,MATCH(E53,'Cost_Components'!$A$2:$A$27,0)),"") | V53: =1/(1+'Calculation_Assumptions'!$B$5)^(B53-'Calculation_Assumptions'!$B$2) | W53: =Q53*V53 | X53: =R53*V53 | Y53: =S53*V53 | Z53: =IFERROR(INDEX('Cost_Components'!$T$2:$T$27,MATCH(E53,'Cost_Components'!$A$2:$A$27,0)),"") | AA53: =IFERROR(INDEX('Cost_Components'!$U$2:$U$27,MATCH(E53,'Cost_Components'!$A$2:$A$27,0)),"") | AB53: =IFERROR(INDEX('Cost_Components'!$V$2:$V$27,MATCH(E53,'Cost_Components'!$A$2:$A$27,0)),"") | AC53: =IFERROR(INDEX('Cost_Components'!$M$2:$M$27,MATCH(E53,'Cost_Components'!$A$2:$A$27,0)),"") | AD53: =IFERROR(INDEX('Cost_Components'!$N$2:$N$27,MATCH(E53,'Cost_Components'!$A$2:$A$27,0)),"") | AE53: =IFERROR(INDEX('Cost_Components'!$O$2:$O$27,MATCH(E53,'Cost_Components'!$A$2:$A$27,0)),"") | AF53: 4.0071109e+08 | AG53: 3.9813254e+08 | AH53: =IF(H53="shared-count-once",COUNTIFS($A$2:$A$1353,A53,$B$2:$B$1353,B53,$E$2:$E$1353,E53),1)
A54: I_HF_ACUTE | B54: 2025 | C54: I_HF_ACUTE | D54: cmd | E54: COST_HF_ACUTE_C_CMP | F54: CC_HF_ACUTE_C_CMP | G54: I_HF_ACUTE__C_CMP | H54: cause-specific | I54: prevalence | J54: =IFERROR(INDEX('Cost_Components'!$K$2:$K$27,MATCH(E54,'Cost_Components'!$A$2:$A$27,0)),"") | K54: =IF(OR(L54="",Z54="",AA54="",AB54=""),"",IF(B54<AA54,L54,IF(B54>AB54,Z54,L54+(Z54-L54)*MIN(MAX((B54-AA54+1)/MAX(AB54-AA54+1,1),0),1)))) | L54: =IFERROR(INDEX('Cost_Components'!$S$2:$S$27,MATCH(E54,'Cost_Components'!$A$2:$A$27,0)),"") | M54: =IFERROR(INDEX('Cost_Components'!$L$2:$L$27,MATCH(E54,'Cost_Components'!$A$2:$A$27,0)),"") | N54: =IFERROR(INDEX('Cost_Components'!$P$2:$P$27,MATCH(E54,'Cost_Components'!$A$2:$A$27,0)),"") | O54: =AF54*J54 | P54: =AG54*J54 | Q54: =P54*L54*M54*N54 | R54: =O54*K54*M54*N54 | S54: =R54-Q54 | T54: =IFERROR(INDEX('Cost_Components'!$R$2:$R$27,MATCH(E54,'Cost_Components'!$A$2:$A$27,0)),"") | U54: =IFERROR(INDEX('Cost_Components'!$Q$2:$Q$27,MATCH(E54,'Cost_Components'!$A$2:$A$27,0)),"") | V54: =1/(1+'Calculation_Assumptions'!$B$5)^(B54-'Calculation_Assumptions'!$B$2) | W54: =Q54*V54 | X54: =R54*V54 | Y54: =S54*V54 | Z54: =IFERROR(INDEX('Cost_Components'!$T$2:$T$27,MATCH(E54,'Cost_Components'!$A$2:$A$27,0)),"") | AA54: =IFERROR(INDEX('Cost_Components'!$U$2:$U$27,MATCH(E54,'Cost_Components'!$A$2:$A$27,0)),"") | AB54: =IFERROR(INDEX('Cost_Components'!$V$2:$V$27,MATCH(E54,'Cost_Components'!$A$2:$A$27,0)),"") | AC54: =IFERROR(INDEX('Cost_Components'!$M$2:$M$27,MATCH(E54,'Cost_Components'!$A$2:$A$27,0)),"") | AD54: =IFERROR(INDEX('Cost_Components'!$N$2:$N$27,MATCH(E54,'Cost_Components'!$A$2:$A$27,0)),"") | AE54: =IFERROR(INDEX('Cost_Components'!$O$2:$O$27,MATCH(E54,'Cost_Components'!$A$2:$A$27,0)),"") | AF54: 53324.494 | AG54: 53296.123 | AH54: =IF(H54="shared-count-once",COUNTIFS($A$2:$A$1353,A54,$B$2:$B$1353,B54,$E$2:$E$1353,E54),1)
A55: I_HF_ACUTE | B55: 2026 | C55: I_HF_ACUTE | D55: cmd | E55: COST_HF_ACUTE_C_CMP | F55: CC_HF_ACUTE_C_CMP | G55: I_HF_ACUTE__C_CMP | H55: cause-specific | I55: prevalence | J55: =IFERROR(INDEX('Cost_Components'!$K$2:$K$27,MATCH(E55,'Cost_Components'!$A$2:$A$27,0)),"") | K55: =IF(OR(L55="",Z55="",AA55="",AB55=""),"",IF(B55<AA55,L55,IF(B55>AB55,Z55,L55+(Z55-L55)*MIN(MAX((B55-AA55+1)/MAX(AB55-AA55+1,1),0),1)))) | L55: =IFERROR(INDEX('Cost_Components'!$S$2:$S$27,MATCH(E55,'Cost_Components'!$A$2:$A$27,0)),"") | M55: =IFERROR(INDEX('Cost_Components'!$L$2:$L$27,MATCH(E55,'Cost_Components'!$A$2:$A$27,0)),"") | N55: =IFERROR(INDEX('Cost_Components'!$P$2:$P$27,MATCH(E55,'Cost_Components'!$A$2:$A$27,0)),"") | O55: =AF55*J55 | P55: =AG55*J55 | Q55: =P55*L55*M55*N55 | R55: =O55*K55*M55*N55 | S55: =R55-Q55 | T55: =IFERROR(INDEX('Cost_Components'!$R$2:$R$27,MATCH(E55,'Cost_Components'!$A$2:$A$27,0)),"") | U55: =IFERROR(INDEX('Cost_Components'!$Q$2:$Q$27,MATCH(E55,'Cost_Components'!$A$2:$A$27,0)),"") | V55: =1/(1+'Calculation_Assumptions'!$B$5)^(B55-'Calculation_Assumptions'!$B$2) | W55: =Q55*V55 | X55: =R55*V55 | Y55: =S55*V55 | Z55: =IFERROR(INDEX('Cost_Components'!$T$2:$T$27,MATCH(E55,'Cost_Components'!$A$2:$A$27,0)),"") | AA55: =IFERROR(INDEX('Cost_Components'!$U$2:$U$27,MATCH(E55,'Cost_Components'!$A$2:$A$27,0)),"") | AB55: =IFERROR(INDEX('Cost_Components'!$V$2:$V$27,MATCH(E55,'Cost_Components'!$A$2:$A$27,0)),"") | AC55: =IFERROR(INDEX('Cost_Components'!$M$2:$M$27,MATCH(E55,'Cost_Components'!$A$2:$A$27,0)),"") | AD55: =IFERROR(INDEX('Cost_Components'!$N$2:$N$27,MATCH(E55,'Cost_Components'!$A$2:$A$27,0)),"") | AE55: =IFERROR(INDEX('Cost_Components'!$O$2:$O$27,MATCH(E55,'Cost_Components'!$A$2:$A$27,0)),"") | AF55: 55224.558 | AG55: 55143.657 | AH55: =IF(H55="shared-count-once",COUNTIFS($A$2:$A$1353,A55,$B$2:$B$1353,B55,$E$2:$E$1353,E55),1)
A56: I_HF_ACUTE | B56: 2027 | C56: I_HF_ACUTE | D56: cmd | E56: COST_HF_ACUTE_C_CMP | F56: CC_HF_ACUTE_C_CMP | G56: I_HF_ACUTE__C_CMP | H56: cause-specific | I56: prevalence | J56: =IFERROR(INDEX('Cost_Components'!$K$2:$K$27,MATCH(E56,'Cost_Components'!$A$2:$A$27,0)),"") | K56: =IF(OR(L56="",Z56="",AA56="",AB56=""),"",IF(B56<AA56,L56,IF(B56>AB56,Z56,L56+(Z56-L56)*MIN(MAX((B56-AA56+1)/MAX(AB56-AA56+1,1),0),1)))) | L56: =IFERROR(INDEX('Cost_Components'!$S$2:$S$27,MATCH(E56,'Cost_Components'!$A$2:$A$27,0)),"") | M56: =IFERROR(INDEX('Cost_Components'!$L$2:$L$27,MATCH(E56,'Cost_Components'!$A$2:$A$27,0)),"") | N56: =IFERROR(INDEX('Cost_Components'!$P$2:$P$27,MATCH(E56,'Cost_Components'!$A$2:$A$27,0)),"") | O56: =AF56*J56 | P56: =AG56*J56 | Q56: =P56*L56*M56*N56 | R56: =O56*K56*M56*N56 | S56: =R56-Q56 | T56: =IFERROR(INDEX('Cost_Components'!$R$2:$R$27,MATCH(E56,'Cost_Components'!$A$2:$A$27,0)),"") | U56: =IFERROR(INDEX('Cost_Components'!$Q$2:$Q$27,MATCH(E56,'Cost_Components'!$A$2:$A$27,0)),"") | V56: =1/(1+'Calculation_Assumptions'!$B$5)^(B56-'Calculation_Assumptions'!$B$2) | W56: =Q56*V56 | X56: =R56*V56 | Y56: =S56*V56 | Z56: =IFERROR(INDEX('Cost_Components'!$T$2:$T$27,MATCH(E56,'Cost_Components'!$A$2:$A$27,0)),"") | AA56: =IFERROR(INDEX('Cost_Components'!$U$2:$U$27,MATCH(E56,'Cost_Components'!$A$2:$A$27,0)),"") | AB56: =IFERROR(INDEX('Cost_Components'!$V$2:$V$27,MATCH(E56,'Cost_Components'!$A$2:$A$27,0)),"") | AC56: =IFERROR(INDEX('Cost_Components'!$M$2:$M$27,MATCH(E56,'Cost_Components'!$A$2:$A$27,0)),"") | AD56: =IFERROR(INDEX('Cost_Components'!$N$2:$N$27,MATCH(E56,'Cost_Components'!$A$2:$A$27,0)),"") | AE56: =IFERROR(INDEX('Cost_Components'!$O$2:$O$27,MATCH(E56,'Cost_Components'!$A$2:$A$27,0)),"") | AF56: 57117.016 | AG56: 56962.574 | AH56: =IF(H56="shared-count-once",COUNTIFS($A$2:$A$1353,A56,$B$2:$B$1353,B56,$E$2:$E$1353,E56),1)
A57: I_HF_ACUTE | B57: 2028 | C57: I_HF_ACUTE | D57: cmd | E57: COST_HF_ACUTE_C_CMP | F57: CC_HF_ACUTE_C_CMP | G57: I_HF_ACUTE__C_CMP | H57: cause-specific | I57: prevalence | J57: =IFERROR(INDEX('Cost_Components'!$K$2:$K$27,MATCH(E57,'Cost_Components'!$A$2:$A$27,0)),"") | K57: =IF(OR(L57="",Z57="",AA57="",AB57=""),"",IF(B57<AA57,L57,IF(B57>AB57,Z57,L57+(Z57-L57)*MIN(MAX((B57-AA57+1)/MAX(AB57-AA57+1,1),0),1)))) | L57: =IFERROR(INDEX('Cost_Components'!$S$2:$S$27,MATCH(E57,'Cost_Components'!$A$2:$A$27,0)),"") | M57: =IFERROR(INDEX('Cost_Components'!$L$2:$L$27,MATCH(E57,'Cost_Components'!$A$2:$A$27,0)),"") | N57: =IFERROR(INDEX('Cost_Components'!$P$2:$P$27,MATCH(E57,'Cost_Components'!$A$2:$A$27,0)),"") | O57: =AF57*J57 | P57: =AG57*J57 | Q57: =P57*L57*M57*N57 | R57: =O57*K57*M57*N57 | S57: =R57-Q57 | T57: =IFERROR(INDEX('Cost_Components'!$R$2:$R$27,MATCH(E57,'Cost_Components'!$A$2:$A$27,0)),"") | U57: =IFERROR(INDEX('Cost_Components'!$Q$2:$Q$27,MATCH(E57,'Cost_Components'!$A$2:$A$27,0)),"") | V57: =1/(1+'Calculation_Assumptions'!$B$5)^(B57-'Calculation_Assumptions'!$B$2) | W57: =Q57*V57 | X57: =R57*V57 | Y57: =S57*V57 | Z57: =IFERROR(INDEX('Cost_Components'!$T$2:$T$27,MATCH(E57,'Cost_Components'!$A$2:$A$27,0)),"") | AA57: =IFERROR(INDEX('Cost_Components'!$U$2:$U$27,MATCH(E57,'Cost_Components'!$A$2:$A$27,0)),"") | AB57: =IFERROR(INDEX('Cost_Components'!$V$2:$V$27,MATCH(E57,'Cost_Components'!$A$2:$A$27,0)),"") | AC57: =IFERROR(INDEX('Cost_Components'!$M$2:$M$27,MATCH(E57,'Cost_Components'!$A$2:$A$27,0)),"") | AD57: =IFERROR(INDEX('Cost_Components'!$N$2:$N$27,MATCH(E57,'Cost_Components'!$A$2:$A$27,0)),"") | AE57: =IFERROR(INDEX('Cost_Components'!$O$2:$O$27,MATCH(E57,'Cost_Components'!$A$2:$A$27,0)),"") | AF57: 58991.035 | AG57: 58744.418 | AH57: =IF(H57="shared-count-once",COUNTIFS($A$2:$A$1353,A57,$B$2:$B$1353,B57,$E$2:$E$1353,E57),1)
A58: I_HF_ACUTE | B58: 2029 | C58: I_HF_ACUTE | D58: cmd | E58: COST_HF_ACUTE_C_CMP | F58: CC_HF_ACUTE_C_CMP | G58: I_HF_ACUTE__C_CMP | H58: cause-specific | I58: prevalence | J58: =IFERROR(INDEX('Cost_Components'!$K$2:$K$27,MATCH(E58,'Cost_Components'!$A$2:$A$27,0)),"") | K58: =IF(OR(L58="",Z58="",AA58="",AB58=""),"",IF(B58<AA58,L58,IF(B58>AB58,Z58,L58+(Z58-L58)*MIN(MAX((B58-AA58+1)/MAX(AB58-AA58+1,1),0),1)))) | L58: =IFERROR(INDEX('Cost_Components'!$S$2:$S$27,MATCH(E58,'Cost_Components'!$A$2:$A$27,0)),"") | M58: =IFERROR(INDEX('Cost_Components'!$L$2:$L$27,MATCH(E58,'Cost_Components'!$A$2:$A$27,0)),"") | N58: =IFERROR(INDEX('Cost_Components'!$P$2:$P$27,MATCH(E58,'Cost_Components'!$A$2:$A$27,0)),"") | O58: =AF58*J58 | P58: =AG58*J58 | Q58: =P58*L58*M58*N58 | R58: =O58*K58*M58*N58 | S58: =R58-Q58 | T58: =IFERROR(INDEX('Cost_Components'!$R$2:$R$27,MATCH(E58,'Cost_Components'!$A$2:$A$27,0)),"") | U58: =IFERROR(INDEX('Cost_Components'!$Q$2:$Q$27,MATCH(E58,'Cost_Components'!$A$2:$A$27,0)),"") | V58: =1/(1+'Calculation_Assumptions'!$B$5)^(B58-'Calculation_Assumptions'!$B$2) | W58: =Q58*V58 | X58: =R58*V58 | Y58: =S58*V58 | Z58: =IFERROR(INDEX('Cost_Components'!$T$2:$T$27,MATCH(E58,'Cost_Components'!$A$2:$A$27,0)),"") | AA58: =IFERROR(INDEX('Cost_Components'!$U$2:$U$27,MATCH(E58,'Cost_Components'!$A$2:$A$27,0)),"") | AB58: =IFERROR(INDEX('Cost_Components'!$V$2:$V$27,MATCH(E58,'Cost_Components'!$A$2:$A$27,0)),"") | AC58: =IFERROR(INDEX('Cost_Components'!$M$2:$M$27,MATCH(E58,'Cost_Components'!$A$2:$A$27,0)),"") | AD58: =IFERROR(INDEX('Cost_Components'!$N$2:$N$27,MATCH(E58,'Cost_Components'!$A$2:$A$27,0)),"") | AE58: =IFERROR(INDEX('Cost_Components'!$O$2:$O$27,MATCH(E58,'Cost_Components'!$A$2:$A$27,0)),"") | AF58: 60852.976 | AG58: 60497.402 | AH58: =IF(H58="shared-count-once",COUNTIFS($A$2:$A$1353,A58,$B$2:$B$1353,B58,$E$2:$E$1353,E58),1)
A59: I_HF_ACUTE | B59: 2030 | C59: I_HF_ACUTE | D59: cmd | E59: COST_HF_ACUTE_C_CMP | F59: CC_HF_ACUTE_C_CMP | G59: I_HF_ACUTE__C_CMP | H59: cause-specific | I59: prevalence | J59: =IFERROR(INDEX('Cost_Components'!$K$2:$K$27,MATCH(E59,'Cost_Components'!$A$2:$A$27,0)),"") | K59: =IF(OR(L59="",Z59="",AA59="",AB59=""),"",IF(B59<AA59,L59,IF(B59>AB59,Z59,L59+(Z59-L59)*MIN(MAX((B59-AA59+1)/MAX(AB59-AA59+1,1),0),1)))) | L59: =IFERROR(INDEX('Cost_Components'!$S$2:$S$27,MATCH(E59,'Cost_Components'!$A$2:$A$27,0)),"") | M59: =IFERROR(INDEX('Cost_Components'!$L$2:$L$27,MATCH(E59,'Cost_Components'!$A$2:$A$27,0)),"") | N59: =IFERROR(INDEX('Cost_Components'!$P$2:$P$27,MATCH(E59,'Cost_Components'!$A$2:$A$27,0)),"") | O59: =AF59*J59 | P59: =AG59*J59 | Q59: =P59*L59*M59*N59 | R59: =O59*K59*M59*N59 | S59: =R59-Q59 | T59: =IFERROR(INDEX('Cost_Components'!$R$2:$R$27,MATCH(E59,'Cost_Components'!$A$2:$A$27,0)),"") | U59: =IFERROR(INDEX('Cost_Components'!$Q$2:$Q$27,MATCH(E59,'Cost_Components'!$A$2:$A$27,0)),"") | V59: =1/(1+'Calculation_Assumptions'!$B$5)^(B59-'Calculation_Assumptions'!$B$2) | W59: =Q59*V59 | X59: =R59*V59 | Y59: =S59*V59 | Z59: =IFERROR(INDEX('Cost_Components'!$T$2:$T$27,MATCH(E59,'Cost_Components'!$A$2:$A$27,0)),"") | AA59: =IFERROR(INDEX('Cost_Components'!$U$2:$U$27,MATCH(E59,'Cost_Components'!$A$2:$A$27,0)),"") | AB59: =IFERROR(INDEX('Cost_Components'!$V$2:$V$27,MATCH(E59,'Cost_Components'!$A$2:$A$27,0)),"") | AC59: =IFERROR(INDEX('Cost_Components'!$M$2:$M$27,MATCH(E59,'Cost_Components'!$A$2:$A$27,0)),"") | AD59: =IFERROR(INDEX('Cost_Components'!$N$2:$N$27,MATCH(E59,'Cost_Components'!$A$2:$A$27,0)),"") | AE59: =IFERROR(INDEX('Cost_Components'!$O$2:$O$27,MATCH(E59,'Cost_Components'!$A$2:$A$27,0)),"") | AF59: 62711.973 | AG59: 62232.086 | AH59: =IF(H59="shared-count-once",COUNTIFS($A$2:$A$1353,A59,$B$2:$B$1353,B59,$E$2:$E$1353,E59),1)
A60: I_HF_ACUTE | B60: 2031 | C60: I_HF_ACUTE | D60: cmd | E60: COST_HF_ACUTE_C_CMP | F60: CC_HF_ACUTE_C_CMP | G60: I_HF_ACUTE__C_CMP | H60: cause-specific | I60: prevalence | J60: =IFERROR(INDEX('Cost_Components'!$K$2:$K$27,MATCH(E60,'Cost_Components'!$A$2:$A$27,0)),"") | K60: =IF(OR(L60="",Z60="",AA60="",AB60=""),"",IF(B60<AA60,L60,IF(B60>AB60,Z60,L60+(Z60-L60)*MIN(MAX((B60-AA60+1)/MAX(AB60-AA60+1,1),0),1)))) | L60: =IFERROR(INDEX('Cost_Components'!$S$2:$S$27,MATCH(E60,'Cost_Components'!$A$2:$A$27,0)),"") | M60: =IFERROR(INDEX('Cost_Components'!$L$2:$L$27,MATCH(E60,'Cost_Components'!$A$2:$A$27,0)),"") | N60: =IFERROR(INDEX('Cost_Components'!$P$2:$P$27,MATCH(E60,'Cost_Components'!$A$2:$A$27,0)),"") | O60: =AF60*J60 | P60: =AG60*J60 | Q60: =P60*L60*M60*N60 | R60: =O60*K60*M60*N60 | S60: =R60-Q60 | T60: =IFERROR(INDEX('Cost_Components'!$R$2:$R$27,MATCH(E60,'Cost_Components'!$A$2:$A$27,0)),"") | U60: =IFERROR(INDEX('Cost_Components'!$Q$2:$Q$27,MATCH(E60,'Cost_Components'!$A$2:$A$27,0)),"") | V60: =1/(1+'Calculation_Assumptions'!$B$5)^(B60-'Calculation_Assumptions'!$B$2) | W60: =Q60*V60 | X60: =R60*V60 | Y60: =S60*V60 | Z60: =IFERROR(INDEX('Cost_Components'!$T$2:$T$27,MATCH(E60,'Cost_Components'!$A$2:$A$27,0)),"") | AA60: =IFERROR(INDEX('Cost_Components'!$U$2:$U$27,MATCH(E60,'Cost_Components'!$A$2:$A$27,0)),"") | AB60: =IFERROR(INDEX('Cost_Components'!$V$2:$V$27,MATCH(E60,'Cost_Components'!$A$2:$A$27,0)),"") | AC60: =IFERROR(INDEX('Cost_Components'!$M$2:$M$27,MATCH(E60,'Cost_Components'!$A$2:$A$27,0)),"") | AD60: =IFERROR(INDEX('Cost_Components'!$N$2:$N$27,MATCH(E60,'Cost_Components'!$A$2:$A$27,0)),"") | AE60: =IFERROR(INDEX('Cost_Components'!$O$2:$O$27,MATCH(E60,'Cost_Components'!$A$2:$A$27,0)),"") | AF60: 64573.408 | AG60: 63955.031 | AH60: =IF(H60="shared-count-once",COUNTIFS($A$2:$A$1353,A60,$B$2:$B$1353,B60,$E$2:$E$1353,E60),1)
A61: I_HF_ACUTE | B61: 2032 | C61: I_HF_ACUTE | D61: cmd | E61: COST_HF_ACUTE_C_CMP | F61: CC_HF_ACUTE_C_CMP | G61: I_HF_ACUTE__C_CMP | H61: cause-specific | I61: prevalence | J61: =IFERROR(INDEX('Cost_Components'!$K$2:$K$27,MATCH(E61,'Cost_Components'!$A$2:$A$27,0)),"") | K61: =IF(OR(L61="",Z61="",AA61="",AB61=""),"",IF(B61<AA61,L61,IF(B61>AB61,Z61,L61+(Z61-L61)*MIN(MAX((B61-AA61+1)/MAX(AB61-AA61+1,1),0),1)))) | L61: =IFERROR(INDEX('Cost_Components'!$S$2:$S$27,MATCH(E61,'Cost_Components'!$A$2:$A$27,0)),"") | M61: =IFERROR(INDEX('Cost_Components'!$L$2:$L$27,MATCH(E61,'Cost_Components'!$A$2:$A$27,0)),"") | N61: =IFERROR(INDEX('Cost_Components'!$P$2:$P$27,MATCH(E61,'Cost_Components'!$A$2:$A$27,0)),"") | O61: =AF61*J61 | P61: =AG61*J61 | Q61: =P61*L61*M61*N61 | R61: =O61*K61*M61*N61 | S61: =R61-Q61 | T61: =IFERROR(INDEX('Cost_Components'!$R$2:$R$27,MATCH(E61,'Cost_Components'!$A$2:$A$27,0)),"") | U61: =IFERROR(INDEX('Cost_Components'!$Q$2:$Q$27,MATCH(E61,'Cost_Components'!$A$2:$A$27,0)),"") | V61: =1/(1+'Calculation_Assumptions'!$B$5)^(B61-'Calculation_Assumptions'!$B$2) | W61: =Q61*V61 | X61: =R61*V61 | Y61: =S61*V61 | Z61: =IFERROR(INDEX('Cost_Components'!$T$2:$T$27,MATCH(E61,'Cost_Components'!$A$2:$A$27,0)),"") | AA61: =IFERROR(INDEX('Cost_Components'!$U$2:$U$27,MATCH(E61,'Cost_Components'!$A$2:$A$27,0)),"") | AB61: =IFERROR(INDEX('Cost_Components'!$V$2:$V$27,MATCH(E61,'Cost_Components'!$A$2:$A$27,0)),"") | AC61: =IFERROR(INDEX('Cost_Components'!$M$2:$M$27,MATCH(E61,'Cost_Components'!$A$2:$A$27,0)),"") | AD61: =IFERROR(INDEX('Cost_Components'!$N$2:$N$27,MATCH(E61,'Cost_Components'!$A$2:$A$27,0)),"") | AE61: =IFERROR(INDEX('Cost_Components'!$O$2:$O$27,MATCH(E61,'Cost_Components'!$A$2:$A$27,0)),"") | AF61: 66460.897 | AG61: 65690.829 | AH61: =IF(H61="shared-count-once",COUNTIFS($A$2:$A$1353,A61,$B$2:$B$1353,B61,$E$2:$E$1353,E61),1)
A62: I_HF_ACUTE | B62: 2033 | C62: I_HF_ACUTE | D62: cmd | E62: COST_HF_ACUTE_C_CMP | F62: CC_HF_ACUTE_C_CMP | G62: I_HF_ACUTE__C_CMP | H62: cause-specific | I62: prevalence | J62: =IFERROR(INDEX('Cost_Components'!$K$2:$K$27,MATCH(E62,'Cost_Components'!$A$2:$A$27,0)),"") | K62: =IF(OR(L62="",Z62="",AA62="",AB62=""),"",IF(B62<AA62,L62,IF(B62>AB62,Z62,L62+(Z62-L62)*MIN(MAX((B62-AA62+1)/MAX(AB62-AA62+1,1),0),1)))) | L62: =IFERROR(INDEX('Cost_Components'!$S$2:$S$27,MATCH(E62,'Cost_Components'!$A$2:$A$27,0)),"") | M62: =IFERROR(INDEX('Cost_Components'!$L$2:$L$27,MATCH(E62,'Cost_Components'!$A$2:$A$27,0)),"") | N62: =IFERROR(INDEX('Cost_Components'!$P$2:$P$27,MATCH(E62,'Cost_Components'!$A$2:$A$27,0)),"") | O62: =AF62*J62 | P62: =AG62*J62 | Q62: =P62*L62*M62*N62 | R62: =O62*K62*M62*N62 | S62: =R62-Q62 | T62: =IFERROR(INDEX('Cost_Components'!$R$2:$R$27,MATCH(E62,'Cost_Components'!$A$2:$A$27,0)),"") | U62: =IFERROR(INDEX('Cost_Components'!$Q$2:$Q$27,MATCH(E62,'Cost_Components'!$A$2:$A$27,0)),"") | V62: =1/(1+'Calculation_Assumptions'!$B$5)^(B62-'Calculation_Assumptions'!$B$2) | W62: =Q62*V62 | X62: =R62*V62 | Y62: =S62*V62 | Z62: =IFERROR(INDEX('Cost_Components'!$T$2:$T$27,MATCH(E62,'Cost_Components'!$A$2:$A$27,0)),"") | AA62: =IFERROR(INDEX('Cost_Components'!$U$2:$U$27,MATCH(E62,'Cost_Components'!$A$2:$A$27,0)),"") | AB62: =IFERROR(INDEX('Cost_Components'!$V$2:$V$27,MATCH(E62,'Cost_Components'!$A$2:$A$27,0)),"") | AC62: =IFERROR(INDEX('Cost_Components'!$M$2:$M$27,MATCH(E62,'Cost_Components'!$A$2:$A$27,0)),"") | AD62: =IFERROR(INDEX('Cost_Components'!$N$2:$N$27,MATCH(E62,'Cost_Components'!$A$2:$A$27,0)),"") | AE62: =IFERROR(INDEX('Cost_Components'!$O$2:$O$27,MATCH(E62,'Cost_Components'!$A$2:$A$27,0)),"") | AF62: 68391.653 | AG62: 67457.385 | AH62: =IF(H62="shared-count-once",COUNTIFS($A$2:$A$1353,A62,$B$2:$B$1353,B62,$E$2:$E$1353,E62),1)
A63: I_HF_ACUTE | B63: 2034 | C63: I_HF_ACUTE | D63: cmd | E63: COST_HF_ACUTE_C_CMP | F63: CC_HF_ACUTE_C_CMP | G63: I_HF_ACUTE__C_CMP | H63: cause-specific | I63: prevalence | J63: =IFERROR(INDEX('Cost_Components'!$K$2:$K$27,MATCH(E63,'Cost_Components'!$A$2:$A$27,0)),"") | K63: =IF(OR(L63="",Z63="",AA63="",AB63=""),"",IF(B63<AA63,L63,IF(B63>AB63,Z63,L63+(Z63-L63)*MIN(MAX((B63-AA63+1)/MAX(AB63-AA63+1,1),0),1)))) | L63: =IFERROR(INDEX('Cost_Components'!$S$2:$S$27,MATCH(E63,'Cost_Components'!$A$2:$A$27,0)),"") | M63: =IFERROR(INDEX('Cost_Components'!$L$2:$L$27,MATCH(E63,'Cost_Components'!$A$2:$A$27,0)),"") | N63: =IFERROR(INDEX('Cost_Components'!$P$2:$P$27,MATCH(E63,'Cost_Components'!$A$2:$A$27,0)),"") | O63: =AF63*J63 | P63: =AG63*J63 | Q63: =P63*L63*M63*N63 | R63: =O63*K63*M63*N63 | S63: =R63-Q63 | T63: =IFERROR(INDEX('Cost_Components'!$R$2:$R$27,MATCH(E63,'Cost_Components'!$A$2:$A$27,0)),"") | U63: =IFERROR(INDEX('Cost_Components'!$Q$2:$Q$27,MATCH(E63,'Cost_Components'!$A$2:$A$27,0)),"") | V63: =1/(1+'Calculation_Assumptions'!$B$5)^(B63-'Calculation_Assumptions'!$B$2) | W63: =Q63*V63 | X63: =R63*V63 | Y63: =S63*V63 | Z63: =IFERROR(INDEX('Cost_Components'!$T$2:$T$27,MATCH(E63,'Cost_Components'!$A$2:$A$27,0)),"") | AA63: =IFERROR(INDEX('Cost_Components'!$U$2:$U$27,MATCH(E63,'Cost_Components'!$A$2:$A$27,0)),"") | AB63: =IFERROR(INDEX('Cost_Components'!$V$2:$V$27,MATCH(E63,'Cost_Components'!$A$2:$A$27,0)),"") | AC63: =IFERROR(INDEX('Cost_Components'!$M$2:$M$27,MATCH(E63,'Cost_Components'!$A$2:$A$27,0)),"") | AD63: =IFERROR(INDEX('Cost_Components'!$N$2:$N$27,MATCH(E63,'Cost_Components'!$A$2:$A$27,0)),"") | AE63: =IFERROR(INDEX('Cost_Components'!$O$2:$O$27,MATCH(E63,'Cost_Components'!$A$2:$A$27,0)),"") | AF63: 70375.676 | AG63: 69265.137 | AH63: =IF(H63="shared-count-once",COUNTIFS($A$2:$A$1353,A63,$B$2:$B$1353,B63,$E$2:$E$1353,E63),1)
A64: I_HF_ACUTE | B64: 2035 | C64: I_HF_ACUTE | D64: cmd | E64: COST_HF_ACUTE_C_CMP | F64: CC_HF_ACUTE_C_CMP | G64: I_HF_ACUTE__C_CMP | H64: cause-specific | I64: prevalence | J64: =IFERROR(INDEX('Cost_Components'!$K$2:$K$27,MATCH(E64,'Cost_Components'!$A$2:$A$27,0)),"") | K64: =IF(OR(L64="",Z64="",AA64="",AB64=""),"",IF(B64<AA64,L64,IF(B64>AB64,Z64,L64+(Z64-L64)*MIN(MAX((B64-AA64+1)/MAX(AB64-AA64+1,1),0),1)))) | L64: =IFERROR(INDEX('Cost_Components'!$S$2:$S$27,MATCH(E64,'Cost_Components'!$A$2:$A$27,0)),"") | M64: =IFERROR(INDEX('Cost_Components'!$L$2:$L$27,MATCH(E64,'Cost_Components'!$A$2:$A$27,0)),"") | N64: =IFERROR(INDEX('Cost_Components'!$P$2:$P$27,MATCH(E64,'Cost_Components'!$A$2:$A$27,0)),"") | O64: =AF64*J64 | P64: =AG64*J64 | Q64: =P64*L64*M64*N64 | R64: =O64*K64*M64*N64 | S64: =R64-Q64 | T64: =IFERROR(INDEX('Cost_Components'!$R$2:$R$27,MATCH(E64,'Cost_Components'!$A$2:$A$27,0)),"") | U64: =IFERROR(INDEX('Cost_Components'!$Q$2:$Q$27,MATCH(E64,'Cost_Components'!$A$2:$A$27,0)),"") | V64: =1/(1+'Calculation_Assumptions'!$B$5)^(B64-'Calculation_Assumptions'!$B$2) | W64: =Q64*V64 | X64: =R64*V64 | Y64: =S64*V64 | Z64: =IFERROR(INDEX('Cost_Components'!$T$2:$T$27,MATCH(E64,'Cost_Components'!$A$2:$A$27,0)),"") | AA64: =IFERROR(INDEX('Cost_Components'!$U$2:$U$27,MATCH(E64,'Cost_Components'!$A$2:$A$27,0)),"") | AB64: =IFERROR(INDEX('Cost_Components'!$V$2:$V$27,MATCH(E64,'Cost_Components'!$A$2:$A$27,0)),"") | AC64: =IFERROR(INDEX('Cost_Components'!$M$2:$M$27,MATCH(E64,'Cost_Components'!$A$2:$A$27,0)),"") | AD64: =IFERROR(INDEX('Cost_Components'!$N$2:$N$27,MATCH(E64,'Cost_Components'!$A$2:$A$27,0)),"") | AE64: =IFERROR(INDEX('Cost_Components'!$O$2:$O$27,MATCH(E64,'Cost_Components'!$A$2:$A$27,0)),"") | AF64: 72433.405 | AG64: 71134.821 | AH64: =IF(H64="shared-count-once",COUNTIFS($A$2:$A$1353,A64,$B$2:$B$1353,B64,$E$2:$E$1353,E64),1)
A65: I_HF_ACUTE | B65: 2036 | C65: I_HF_ACUTE | D65: cmd | E65: COST_HF_ACUTE_C_CMP | F65: CC_HF_ACUTE_C_CMP | G65: I_HF_ACUTE__C_CMP | H65: cause-specific | I65: prevalence | J65: =IFERROR(INDEX('Cost_Components'!$K$2:$K$27,MATCH(E65,'Cost_Components'!$A$2:$A$27,0)),"") | K65: =IF(OR(L65="",Z65="",AA65="",AB65=""),"",IF(B65<AA65,L65,IF(B65>AB65,Z65,L65+(Z65-L65)*MIN(MAX((B65-AA65+1)/MAX(AB65-AA65+1,1),0),1)))) | L65: =IFERROR(INDEX('Cost_Components'!$S$2:$S$27,MATCH(E65,'Cost_Components'!$A$2:$A$27,0)),"") | M65: =IFERROR(INDEX('Cost_Components'!$L$2:$L$27,MATCH(E65,'Cost_Components'!$A$2:$A$27,0)),"") | N65: =IFERROR(INDEX('Cost_Components'!$P$2:$P$27,MATCH(E65,'Cost_Components'!$A$2:$A$27,0)),"") | O65: =AF65*J65 | P65: =AG65*J65 | Q65: =P65*L65*M65*N65 | R65: =O65*K65*M65*N65 | S65: =R65-Q65 | T65: =IFERROR(INDEX('Cost_Components'!$R$2:$R$27,MATCH(E65,'Cost_Components'!$A$2:$A$27,0)),"") | U65: =IFERROR(INDEX('Cost_Components'!$Q$2:$Q$27,MATCH(E65,'Cost_Components'!$A$2:$A$27,0)),"") | V65: =1/(1+'Calculation_Assumptions'!$B$5)^(B65-'Calculation_Assumptions'!$B$2) | W65: =Q65*V65 | X65: =R65*V65 | Y65: =S65*V65 | Z65: =IFERROR(INDEX('Cost_Components'!$T$2:$T$27,MATCH(E65,'Cost_Components'!$A$2:$A$27,0)),"") | AA65: =IFERROR(INDEX('Cost_Components'!$U$2:$U$27,MATCH(E65,'Cost_Components'!$A$2:$A$27,0)),"") | AB65: =IFERROR(INDEX('Cost_Components'!$V$2:$V$27,MATCH(E65,'Cost_Components'!$A$2:$A$27,0)),"") | AC65: =IFERROR(INDEX('Cost_Components'!$M$2:$M$27,MATCH(E65,'Cost_Components'!$A$2:$A$27,0)),"") | AD65: =IFERROR(INDEX('Cost_Components'!$N$2:$N$27,MATCH(E65,'Cost_Components'!$A$2:$A$27,0)),"") | AE65: =IFERROR(INDEX('Cost_Components'!$O$2:$O$27,MATCH(E65,'Cost_Components'!$A$2:$A$27,0)),"") | AF65: 74584.061 | AG65: 73085.713 | AH65: =IF(H65="shared-count-once",COUNTIFS($A$2:$A$1353,A65,$B$2:$B$1353,B65,$E$2:$E$1353,E65),1)
... A677: I_T2D_TREATMENT | B677: 2050 | C677: I_T2D_TREATMENT | D677: dm2 | E677: COST_T2D_TREATMENT | F677: CC_T2D_TREATMENT | G677: I_T2D_TREATMENT__C_T2D | H677: cause-specific | I677: prevalence | J677: =IFERROR(INDEX('Cost_Components'!$K$2:$K$27,MATCH(E677,'Cost_Components'!$A$2:$A$27,0)),"") | K677: =IF(OR(L677="",Z677="",AA677="",AB677=""),"",IF(B677<AA677,L677,IF(B677>AB677,Z677,L677+(Z677-L677)*MIN(MAX((B677-AA677+1)/MAX(AB677-AA677+1,1),0),1)))) | L677: =IFERROR(INDEX('Cost_Components'!$S$2:$S$27,MATCH(E677,'Cost_Components'!$A$2:$A$27,0)),"") | M677: =IFERROR(INDEX('Cost_Components'!$L$2:$L$27,MATCH(E677,'Cost_Components'!$A$2:$A$27,0)),"") | N677: =IFERROR(INDEX('Cost_Components'!$P$2:$P$27,MATCH(E677,'Cost_Components'!$A$2:$A$27,0)),"") | O677: =AF677*J677 | P677: =AG677*J677 | Q677: =P677*L677*M677*N677 | R677: =O677*K677*M677*N677 | S677: =R677-Q677 | T677: =IFERROR(INDEX('Cost_Components'!$R$2:$R$27,MATCH(E677,'Cost_Components'!$A$2:$A$27,0)),"") | U677: =IFERROR(INDEX('Cost_Components'!$Q$2:$Q$27,MATCH(E677,'Cost_Components'!$A$2:$A$27,0)),"") | V677: =1/(1+'Calculation_Assumptions'!$B$5)^(B677-'Calculation_Assumptions'!$B$2) | W677: =Q677*V677 | X677: =R677*V677 | Y677: =S677*V677 | Z677: =IFERROR(INDEX('Cost_Components'!$T$2:$T$27,MATCH(E677,'Cost_Components'!$A$2:$A$27,0)),"") | AA677: =IFERROR(INDEX('Cost_Components'!$U$2:$U$27,MATCH(E677,'Cost_Components'!$A$2:$A$27,0)),"") | AB677: =IFERROR(INDEX('Cost_Components'!$V$2:$V$27,MATCH(E677,'Cost_Components'!$A$2:$A$27,0)),"") | AC677: =IFERROR(INDEX('Cost_Components'!$M$2:$M$27,MATCH(E677,'Cost_Components'!$A$2:$A$27,0)),"") | AD677: =IFERROR(INDEX('Cost_Components'!$N$2:$N$27,MATCH(E677,'Cost_Components'!$A$2:$A$27,0)),"") | AE677: =IFERROR(INDEX('Cost_Components'!$O$2:$O$27,MATCH(E677,'Cost_Components'!$A$2:$A$27,0)),"") | AF677: 28981881 | AG677: 28628880 | AH677: =IF(H677="shared-count-once",COUNTIFS($A$2:$A$1353,A677,$B$2:$B$1353,B677,$E$2:$E$1353,E677),1)
A678: all | B678: 2025 | C678: I_CVD_PRIMARY | E678: COST_PRIMARY_SCREEN_A | F678: CC_PRIMARY_SCREENING | G678: I_CVD_PRIMARY__C_SHARED | H678: shared-count-once | I678: all | J678: =IFERROR(INDEX('Cost_Components'!$K$2:$K$27,MATCH(E678,'Cost_Components'!$A$2:$A$27,0)),"") | K678: =IF(OR(L678="",Z678="",AA678="",AB678=""),"",IF(B678<AA678,L678,IF(B678>AB678,Z678,L678+(Z678-L678)*MIN(MAX((B678-AA678+1)/MAX(AB678-AA678+1,1),0),1)))) | L678: =IFERROR(INDEX('Cost_Components'!$S$2:$S$27,MATCH(E678,'Cost_Components'!$A$2:$A$27,0)),"") | M678: =IFERROR(INDEX('Cost_Components'!$L$2:$L$27,MATCH(E678,'Cost_Components'!$A$2:$A$27,0)),"") | N678: =IFERROR(INDEX('Cost_Components'!$P$2:$P$27,MATCH(E678,'Cost_Components'!$A$2:$A$27,0)),"") | O678: =AF678*J678 | P678: =AG678*J678 | Q678: =P678*L678*M678*N678 | R678: =O678*K678*M678*N678 | S678: =R678-Q678 | T678: =IFERROR(INDEX('Cost_Components'!$R$2:$R$27,MATCH(E678,'Cost_Components'!$A$2:$A$27,0)),"") | U678: =IFERROR(INDEX('Cost_Components'!$Q$2:$Q$27,MATCH(E678,'Cost_Components'!$A$2:$A$27,0)),"") | V678: =1/(1+'Calculation_Assumptions'!$B$5)^(B678-'Calculation_Assumptions'!$B$2) | W678: =Q678*V678 | X678: =R678*V678 | Y678: =S678*V678 | Z678: =IFERROR(INDEX('Cost_Components'!$T$2:$T$27,MATCH(E678,'Cost_Components'!$A$2:$A$27,0)),"") | AA678: =IFERROR(INDEX('Cost_Components'!$U$2:$U$27,MATCH(E678,'Cost_Components'!$A$2:$A$27,0)),"") | AB678: =IFERROR(INDEX('Cost_Components'!$V$2:$V$27,MATCH(E678,'Cost_Components'!$A$2:$A$27,0)),"") | AC678: =IFERROR(INDEX('Cost_Components'!$M$2:$M$27,MATCH(E678,'Cost_Components'!$A$2:$A$27,0)),"") | AD678: =IFERROR(INDEX('Cost_Components'!$N$2:$N$27,MATCH(E678,'Cost_Components'!$A$2:$A$27,0)),"") | AE678: =IFERROR(INDEX('Cost_Components'!$O$2:$O$27,MATCH(E678,'Cost_Components'!$A$2:$A$27,0)),"") | AF678: 3.03073e+08 | AG678: 3.03073e+08 | AH678: =IF(H678="shared-count-once",COUNTIFS($A$2:$A$1353,A678,$B$2:$B$1353,B678,$E$2:$E$1353,E678),1)
A679: all | B679: 2026 | C679: I_CVD_PRIMARY | E679: COST_PRIMARY_SCREEN_A | F679: CC_PRIMARY_SCREENING | G679: I_CVD_PRIMARY__C_SHARED | H679: shared-count-once | I679: all | J679: =IFERROR(INDEX('Cost_Components'!$K$2:$K$27,MATCH(E679,'Cost_Components'!$A$2:$A$27,0)),"") | K679: =IF(OR(L679="",Z679="",AA679="",AB679=""),"",IF(B679<AA679,L679,IF(B679>AB679,Z679,L679+(Z679-L679)*MIN(MAX((B679-AA679+1)/MAX(AB679-AA679+1,1),0),1)))) | L679: =IFERROR(INDEX('Cost_Components'!$S$2:$S$27,MATCH(E679,'Cost_Components'!$A$2:$A$27,0)),"") | M679: =IFERROR(INDEX('Cost_Components'!$L$2:$L$27,MATCH(E679,'Cost_Components'!$A$2:$A$27,0)),"") | N679: =IFERROR(INDEX('Cost_Components'!$P$2:$P$27,MATCH(E679,'Cost_Components'!$A$2:$A$27,0)),"") | O679: =AF679*J679 | P679: =AG679*J679 | Q679: =P679*L679*M679*N679 | R679: =O679*K679*M679*N679 | S679: =R679-Q679 | T679: =IFERROR(INDEX('Cost_Components'!$R$2:$R$27,MATCH(E679,'Cost_Components'!$A$2:$A$27,0)),"") | U679: =IFERROR(INDEX('Cost_Components'!$Q$2:$Q$27,MATCH(E679,'Cost_Components'!$A$2:$A$27,0)),"") | V679: =1/(1+'Calculation_Assumptions'!$B$5)^(B679-'Calculation_Assumptions'!$B$2) | W679: =Q679*V679 | X679: =R679*V679 | Y679: =S679*V679 | Z679: =IFERROR(INDEX('Cost_Components'!$T$2:$T$27,MATCH(E679,'Cost_Components'!$A$2:$A$27,0)),"") | AA679: =IFERROR(INDEX('Cost_Components'!$U$2:$U$27,MATCH(E679,'Cost_Components'!$A$2:$A$27,0)),"") | AB679: =IFERROR(INDEX('Cost_Components'!$V$2:$V$27,MATCH(E679,'Cost_Components'!$A$2:$A$27,0)),"") | AC679: =IFERROR(INDEX('Cost_Components'!$M$2:$M$27,MATCH(E679,'Cost_Components'!$A$2:$A$27,0)),"") | AD679: =IFERROR(INDEX('Cost_Components'!$N$2:$N$27,MATCH(E679,'Cost_Components'!$A$2:$A$27,0)),"") | AE679: =IFERROR(INDEX('Cost_Components'!$O$2:$O$27,MATCH(E679,'Cost_Components'!$A$2:$A$27,0)),"") | AF679: 3.0765177e+08 | AG679: 3.0764667e+08 | AH679: =IF(H679="shared-count-once",COUNTIFS($A$2:$A$1353,A679,$B$2:$B$1353,B679,$E$2:$E$1353,E679),1)
A680: all | B680: 2027 | C680: I_CVD_PRIMARY | E680: COST_PRIMARY_SCREEN_A | F680: CC_PRIMARY_SCREENING | G680: I_CVD_PRIMARY__C_SHARED | H680: shared-count-once | I680: all | J680: =IFERROR(INDEX('Cost_Components'!$K$2:$K$27,MATCH(E680,'Cost_Components'!$A$2:$A$27,0)),"") | K680: =IF(OR(L680="",Z680="",AA680="",AB680=""),"",IF(B680<AA680,L680,IF(B680>AB680,Z680,L680+(Z680-L680)*MIN(MAX((B680-AA680+1)/MAX(AB680-AA680+1,1),0),1)))) | L680: =IFERROR(INDEX('Cost_Components'!$S$2:$S$27,MATCH(E680,'Cost_Components'!$A$2:$A$27,0)),"") | M680: =IFERROR(INDEX('Cost_Components'!$L$2:$L$27,MATCH(E680,'Cost_Components'!$A$2:$A$27,0)),"") | N680: =IFERROR(INDEX('Cost_Components'!$P$2:$P$27,MATCH(E680,'Cost_Components'!$A$2:$A$27,0)),"") | O680: =AF680*J680 | P680: =AG680*J680 | Q680: =P680*L680*M680*N680 | R680: =O680*K680*M680*N680 | S680: =R680-Q680 | T680: =IFERROR(INDEX('Cost_Components'!$R$2:$R$27,MATCH(E680,'Cost_Components'!$A$2:$A$27,0)),"") | U680: =IFERROR(INDEX('Cost_Components'!$Q$2:$Q$27,MATCH(E680,'Cost_Components'!$A$2:$A$27,0)),"") | V680: =1/(1+'Calculation_Assumptions'!$B$5)^(B680-'Calculation_Assumptions'!$B$2) | W680: =Q680*V680 | X680: =R680*V680 | Y680: =S680*V680 | Z680: =IFERROR(INDEX('Cost_Components'!$T$2:$T$27,MATCH(E680,'Cost_Components'!$A$2:$A$27,0)),"") | AA680: =IFERROR(INDEX('Cost_Components'!$U$2:$U$27,MATCH(E680,'Cost_Components'!$A$2:$A$27,0)),"") | AB680: =IFERROR(INDEX('Cost_Components'!$V$2:$V$27,MATCH(E680,'Cost_Components'!$A$2:$A$27,0)),"") | AC680: =IFERROR(INDEX('Cost_Components'!$M$2:$M$27,MATCH(E680,'Cost_Components'!$A$2:$A$27,0)),"") | AD680: =IFERROR(INDEX('Cost_Components'!$N$2:$N$27,MATCH(E680,'Cost_Components'!$A$2:$A$27,0)),"") | AE680: =IFERROR(INDEX('Cost_Components'!$O$2:$O$27,MATCH(E680,'Cost_Components'!$A$2:$A$27,0)),"") | AF680: 3.12282e+08 | AG680: 3.119751e+08 | AH680: =IF(H680="shared-count-once",COUNTIFS($A$2:$A$1353,A680,$B$2:$B$1353,B680,$E$2:$E$1353,E680),1)
A681: all | B681: 2028 | C681: I_CVD_PRIMARY | E681: COST_PRIMARY_SCREEN_A | F681: CC_PRIMARY_SCREENING | G681: I_CVD_PRIMARY__C_SHARED | H681: shared-count-once | I681: all | J681: =IFERROR(INDEX('Cost_Components'!$K$2:$K$27,MATCH(E681,'Cost_Components'!$A$2:$A$27,0)),"") | K681: =IF(OR(L681="",Z681="",AA681="",AB681=""),"",IF(B681<AA681,L681,IF(B681>AB681,Z681,L681+(Z681-L681)*MIN(MAX((B681-AA681+1)/MAX(AB681-AA681+1,1),0),1)))) | L681: =IFERROR(INDEX('Cost_Components'!$S$2:$S$27,MATCH(E681,'Cost_Components'!$A$2:$A$27,0)),"") | M681: =IFERROR(INDEX('Cost_Components'!$L$2:$L$27,MATCH(E681,'Cost_Components'!$A$2:$A$27,0)),"") | N681: =IFERROR(INDEX('Cost_Components'!$P$2:$P$27,MATCH(E681,'Cost_Components'!$A$2:$A$27,0)),"") | O681: =AF681*J681 | P681: =AG681*J681 | Q681: =P681*L681*M681*N681 | R681: =O681*K681*M681*N681 | S681: =R681-Q681 | T681: =IFERROR(INDEX('Cost_Components'!$R$2:$R$27,MATCH(E681,'Cost_Components'!$A$2:$A$27,0)),"") | U681: =IFERROR(INDEX('Cost_Components'!$Q$2:$Q$27,MATCH(E681,'Cost_Components'!$A$2:$A$27,0)),"") | V681: =1/(1+'Calculation_Assumptions'!$B$5)^(B681-'Calculation_Assumptions'!$B$2) | W681: =Q681*V681 | X681: =R681*V681 | Y681: =S681*V681 | Z681: =IFERROR(INDEX('Cost_Components'!$T$2:$T$27,MATCH(E681,'Cost_Components'!$A$2:$A$27,0)),"") | AA681: =IFERROR(INDEX('Cost_Components'!$U$2:$U$27,MATCH(E681,'Cost_Components'!$A$2:$A$27,0)),"") | AB681: =IFERROR(INDEX('Cost_Components'!$V$2:$V$27,MATCH(E681,'Cost_Components'!$A$2:$A$27,0)),"") | AC681: =IFERROR(INDEX('Cost_Components'!$M$2:$M$27,MATCH(E681,'Cost_Components'!$A$2:$A$27,0)),"") | AD681: =IFERROR(INDEX('Cost_Components'!$N$2:$N$27,MATCH(E681,'Cost_Components'!$A$2:$A$27,0)),"") | AE681: =IFERROR(INDEX('Cost_Components'!$O$2:$O$27,MATCH(E681,'Cost_Components'!$A$2:$A$27,0)),"") | AF681: 3.1683993e+08 | AG681: 3.1653136e+08 | AH681: =IF(H681="shared-count-once",COUNTIFS($A$2:$A$1353,A681,$B$2:$B$1353,B681,$E$2:$E$1353,E681),1)
A682: all | B682: 2029 | C682: I_CVD_PRIMARY | E682: COST_PRIMARY_SCREEN_A | F682: CC_PRIMARY_SCREENING | G682: I_CVD_PRIMARY__C_SHARED | H682: shared-count-once | I682: all | J682: =IFERROR(INDEX('Cost_Components'!$K$2:$K$27,MATCH(E682,'Cost_Components'!$A$2:$A$27,0)),"") | K682: =IF(OR(L682="",Z682="",AA682="",AB682=""),"",IF(B682<AA682,L682,IF(B682>AB682,Z682,L682+(Z682-L682)*MIN(MAX((B682-AA682+1)/MAX(AB682-AA682+1,1),0),1)))) | L682: =IFERROR(INDEX('Cost_Components'!$S$2:$S$27,MATCH(E682,'Cost_Components'!$A$2:$A$27,0)),"") | M682: =IFERROR(INDEX('Cost_Components'!$L$2:$L$27,MATCH(E682,'Cost_Components'!$A$2:$A$27,0)),"") | N682: =IFERROR(INDEX('Cost_Components'!$P$2:$P$27,MATCH(E682,'Cost_Components'!$A$2:$A$27,0)),"") | O682: =AF682*J682 | P682: =AG682*J682 | Q682: =P682*L682*M682*N682 | R682: =O682*K682*M682*N682 | S682: =R682-Q682 | T682: =IFERROR(INDEX('Cost_Components'!$R$2:$R$27,MATCH(E682,'Cost_Components'!$A$2:$A$27,0)),"") | U682: =IFERROR(INDEX('Cost_Components'!$Q$2:$Q$27,MATCH(E682,'Cost_Components'!$A$2:$A$27,0)),"") | V682: =1/(1+'Calculation_Assumptions'!$B$5)^(B682-'Calculation_Assumptions'!$B$2) | W682: =Q682*V682 | X682: =R682*V682 | Y682: =S682*V682 | Z682: =IFERROR(INDEX('Cost_Components'!$T$2:$T$27,MATCH(E682,'Cost_Components'!$A$2:$A$27,0)),"") | AA682: =IFERROR(INDEX('Cost_Components'!$U$2:$U$27,MATCH(E682,'Cost_Components'!$A$2:$A$27,0)),"") | AB682: =IFERROR(INDEX('Cost_Components'!$V$2:$V$27,MATCH(E682,'Cost_Components'!$A$2:$A$27,0)),"") | AC682: =IFERROR(INDEX('Cost_Components'!$M$2:$M$27,MATCH(E682,'Cost_Components'!$A$2:$A$27,0)),"") | AD682: =IFERROR(INDEX('Cost_Components'!$N$2:$N$27,MATCH(E682,'Cost_Components'!$A$2:$A$27,0)),"") | AE682: =IFERROR(INDEX('Cost_Components'!$O$2:$O$27,MATCH(E682,'Cost_Components'!$A$2:$A$27,0)),"") | AF682: 3.2124634e+08 | AG682: 3.2092558e+08 | AH682: =IF(H682="shared-count-once",COUNTIFS($A$2:$A$1353,A682,$B$2:$B$1353,B682,$E$2:$E$1353,E682),1)
A683: all | B683: 2030 | C683: I_CVD_PRIMARY | E683: COST_PRIMARY_SCREEN_A | F683: CC_PRIMARY_SCREENING | G683: I_CVD_PRIMARY__C_SHARED | H683: shared-count-once | I683: all | J683: =IFERROR(INDEX('Cost_Components'!$K$2:$K$27,MATCH(E683,'Cost_Components'!$A$2:$A$27,0)),"") | K683: =IF(OR(L683="",Z683="",AA683="",AB683=""),"",IF(B683<AA683,L683,IF(B683>AB683,Z683,L683+(Z683-L683)*MIN(MAX((B683-AA683+1)/MAX(AB683-AA683+1,1),0),1)))) | L683: =IFERROR(INDEX('Cost_Components'!$S$2:$S$27,MATCH(E683,'Cost_Components'!$A$2:$A$27,0)),"") | M683: =IFERROR(INDEX('Cost_Components'!$L$2:$L$27,MATCH(E683,'Cost_Components'!$A$2:$A$27,0)),"") | N683: =IFERROR(INDEX('Cost_Components'!$P$2:$P$27,MATCH(E683,'Cost_Components'!$A$2:$A$27,0)),"") | O683: =AF683*J683 | P683: =AG683*J683 | Q683: =P683*L683*M683*N683 | R683: =O683*K683*M683*N683 | S683: =R683-Q683 | T683: =IFERROR(INDEX('Cost_Components'!$R$2:$R$27,MATCH(E683,'Cost_Components'!$A$2:$A$27,0)),"") | U683: =IFERROR(INDEX('Cost_Components'!$Q$2:$Q$27,MATCH(E683,'Cost_Components'!$A$2:$A$27,0)),"") | V683: =1/(1+'Calculation_Assumptions'!$B$5)^(B683-'Calculation_Assumptions'!$B$2) | W683: =Q683*V683 | X683: =R683*V683 | Y683: =S683*V683 | Z683: =IFERROR(INDEX('Cost_Components'!$T$2:$T$27,MATCH(E683,'Cost_Components'!$A$2:$A$27,0)),"") | AA683: =IFERROR(INDEX('Cost_Components'!$U$2:$U$27,MATCH(E683,'Cost_Components'!$A$2:$A$27,0)),"") | AB683: =IFERROR(INDEX('Cost_Components'!$V$2:$V$27,MATCH(E683,'Cost_Components'!$A$2:$A$27,0)),"") | AC683: =IFERROR(INDEX('Cost_Components'!$M$2:$M$27,MATCH(E683,'Cost_Components'!$A$2:$A$27,0)),"") | AD683: =IFERROR(INDEX('Cost_Components'!$N$2:$N$27,MATCH(E683,'Cost_Components'!$A$2:$A$27,0)),"") | AE683: =IFERROR(INDEX('Cost_Components'!$O$2:$O$27,MATCH(E683,'Cost_Components'!$A$2:$A$27,0)),"") | AF683: 3.2546585e+08 | AG683: 3.2513696e+08 | AH683: =IF(H683="shared-count-once",COUNTIFS($A$2:$A$1353,A683,$B$2:$B$1353,B683,$E$2:$E$1353,E683),1)
A684: all | B684: 2031 | C684: I_CVD_PRIMARY | E684: COST_PRIMARY_SCREEN_A | F684: CC_PRIMARY_SCREENING | G684: I_CVD_PRIMARY__C_SHARED | H684: shared-count-once | I684: all | J684: =IFERROR(INDEX('Cost_Components'!$K$2:$K$27,MATCH(E684,'Cost_Components'!$A$2:$A$27,0)),"") | K684: =IF(OR(L684="",Z684="",AA684="",AB684=""),"",IF(B684<AA684,L684,IF(B684>AB684,Z684,L684+(Z684-L684)*MIN(MAX((B684-AA684+1)/MAX(AB684-AA684+1,1),0),1)))) | L684: =IFERROR(INDEX('Cost_Components'!$S$2:$S$27,MATCH(E684,'Cost_Components'!$A$2:$A$27,0)),"") | M684: =IFERROR(INDEX('Cost_Components'!$L$2:$L$27,MATCH(E684,'Cost_Components'!$A$2:$A$27,0)),"") | N684: =IFERROR(INDEX('Cost_Components'!$P$2:$P$27,MATCH(E684,'Cost_Components'!$A$2:$A$27,0)),"") | O684: =AF684*J684 | P684: =AG684*J684 | Q684: =P684*L684*M684*N684 | R684: =O684*K684*M684*N684 | S684: =R684-Q684 | T684: =IFERROR(INDEX('Cost_Components'!$R$2:$R$27,MATCH(E684,'Cost_Components'!$A$2:$A$27,0)),"") | U684: =IFERROR(INDEX('Cost_Components'!$Q$2:$Q$27,MATCH(E684,'Cost_Components'!$A$2:$A$27,0)),"") | V684: =1/(1+'Calculation_Assumptions'!$B$5)^(B684-'Calculation_Assumptions'!$B$2) | W684: =Q684*V684 | X684: =R684*V684 | Y684: =S684*V684 | Z684: =IFERROR(INDEX('Cost_Components'!$T$2:$T$27,MATCH(E684,'Cost_Components'!$A$2:$A$27,0)),"") | AA684: =IFERROR(INDEX('Cost_Components'!$U$2:$U$27,MATCH(E684,'Cost_Components'!$A$2:$A$27,0)),"") | AB684: =IFERROR(INDEX('Cost_Components'!$V$2:$V$27,MATCH(E684,'Cost_Components'!$A$2:$A$27,0)),"") | AC684: =IFERROR(INDEX('Cost_Components'!$M$2:$M$27,MATCH(E684,'Cost_Components'!$A$2:$A$27,0)),"") | AD684: =IFERROR(INDEX('Cost_Components'!$N$2:$N$27,MATCH(E684,'Cost_Components'!$A$2:$A$27,0)),"") | AE684: =IFERROR(INDEX('Cost_Components'!$O$2:$O$27,MATCH(E684,'Cost_Components'!$A$2:$A$27,0)),"") | AF684: 3.2962568e+08 | AG684: 3.2925981e+08 | AH684: =IF(H684="shared-count-once",COUNTIFS($A$2:$A$1353,A684,$B$2:$B$1353,B684,$E$2:$E$1353,E684),1)
A685: all | B685: 2032 | C685: I_CVD_PRIMARY | E685: COST_PRIMARY_SCREEN_A | F685: CC_PRIMARY_SCREENING | G685: I_CVD_PRIMARY__C_SHARED | H685: shared-count-once | I685: all | J685: =IFERROR(INDEX('Cost_Components'!$K$2:$K$27,MATCH(E685,'Cost_Components'!$A$2:$A$27,0)),"") | K685: =IF(OR(L685="",Z685="",AA685="",AB685=""),"",IF(B685<AA685,L685,IF(B685>AB685,Z685,L685+(Z685-L685)*MIN(MAX((B685-AA685+1)/MAX(AB685-AA685+1,1),0),1)))) | L685: =IFERROR(INDEX('Cost_Components'!$S$2:$S$27,MATCH(E685,'Cost_Components'!$A$2:$A$27,0)),"") | M685: =IFERROR(INDEX('Cost_Components'!$L$2:$L$27,MATCH(E685,'Cost_Components'!$A$2:$A$27,0)),"") | N685: =IFERROR(INDEX('Cost_Components'!$P$2:$P$27,MATCH(E685,'Cost_Components'!$A$2:$A$27,0)),"") | O685: =AF685*J685 | P685: =AG685*J685 | Q685: =P685*L685*M685*N685 | R685: =O685*K685*M685*N685 | S685: =R685-Q685 | T685: =IFERROR(INDEX('Cost_Components'!$R$2:$R$27,MATCH(E685,'Cost_Components'!$A$2:$A$27,0)),"") | U685: =IFERROR(INDEX('Cost_Components'!$Q$2:$Q$27,MATCH(E685,'Cost_Components'!$A$2:$A$27,0)),"") | V685: =1/(1+'Calculation_Assumptions'!$B$5)^(B685-'Calculation_Assumptions'!$B$2) | W685: =Q685*V685 | X685: =R685*V685 | Y685: =S685*V685 | Z685: =IFERROR(INDEX('Cost_Components'!$T$2:$T$27,MATCH(E685,'Cost_Components'!$A$2:$A$27,0)),"") | AA685: =IFERROR(INDEX('Cost_Components'!$U$2:$U$27,MATCH(E685,'Cost_Components'!$A$2:$A$27,0)),"") | AB685: =IFERROR(INDEX('Cost_Components'!$V$2:$V$27,MATCH(E685,'Cost_Components'!$A$2:$A$27,0)),"") | AC685: =IFERROR(INDEX('Cost_Components'!$M$2:$M$27,MATCH(E685,'Cost_Components'!$A$2:$A$27,0)),"") | AD685: =IFERROR(INDEX('Cost_Components'!$N$2:$N$27,MATCH(E685,'Cost_Components'!$A$2:$A$27,0)),"") | AE685: =IFERROR(INDEX('Cost_Components'!$O$2:$O$27,MATCH(E685,'Cost_Components'!$A$2:$A$27,0)),"") | AF685: 3.3374767e+08 | AG685: 3.3333154e+08 | AH685: =IF(H685="shared-count-once",COUNTIFS($A$2:$A$1353,A685,$B$2:$B$1353,B685,$E$2:$E$1353,E685),1)
A686: all | B686: 2033 | C686: I_CVD_PRIMARY | E686: COST_PRIMARY_SCREEN_A | F686: CC_PRIMARY_SCREENING | G686: I_CVD_PRIMARY__C_SHARED | H686: shared-count-once | I686: all | J686: =IFERROR(INDEX('Cost_Components'!$K$2:$K$27,MATCH(E686,'Cost_Components'!$A$2:$A$27,0)),"") | K686: =IF(OR(L686="",Z686="",AA686="",AB686=""),"",IF(B686<AA686,L686,IF(B686>AB686,Z686,L686+(Z686-L686)*MIN(MAX((B686-AA686+1)/MAX(AB686-AA686+1,1),0),1)))) | L686: =IFERROR(INDEX('Cost_Components'!$S$2:$S$27,MATCH(E686,'Cost_Components'!$A$2:$A$27,0)),"") | M686: =IFERROR(INDEX('Cost_Components'!$L$2:$L$27,MATCH(E686,'Cost_Components'!$A$2:$A$27,0)),"") | N686: =IFERROR(INDEX('Cost_Components'!$P$2:$P$27,MATCH(E686,'Cost_Components'!$A$2:$A$27,0)),"") | O686: =AF686*J686 | P686: =AG686*J686 | Q686: =P686*L686*M686*N686 | R686: =O686*K686*M686*N686 | S686: =R686-Q686 | T686: =IFERROR(INDEX('Cost_Components'!$R$2:$R$27,MATCH(E686,'Cost_Components'!$A$2:$A$27,0)),"") | U686: =IFERROR(INDEX('Cost_Components'!$Q$2:$Q$27,MATCH(E686,'Cost_Components'!$A$2:$A$27,0)),"") | V686: =1/(1+'Calculation_Assumptions'!$B$5)^(B686-'Calculation_Assumptions'!$B$2) | W686: =Q686*V686 | X686: =R686*V686 | Y686: =S686*V686 | Z686: =IFERROR(INDEX('Cost_Components'!$T$2:$T$27,MATCH(E686,'Cost_Components'!$A$2:$A$27,0)),"") | AA686: =IFERROR(INDEX('Cost_Components'!$U$2:$U$27,MATCH(E686,'Cost_Components'!$A$2:$A$27,0)),"") | AB686: =IFERROR(INDEX('Cost_Components'!$V$2:$V$27,MATCH(E686,'Cost_Components'!$A$2:$A$27,0)),"") | AC686: =IFERROR(INDEX('Cost_Components'!$M$2:$M$27,MATCH(E686,'Cost_Components'!$A$2:$A$27,0)),"") | AD686: =IFERROR(INDEX('Cost_Components'!$N$2:$N$27,MATCH(E686,'Cost_Components'!$A$2:$A$27,0)),"") | AE686: =IFERROR(INDEX('Cost_Components'!$O$2:$O$27,MATCH(E686,'Cost_Components'!$A$2:$A$27,0)),"") | AF686: 3.3782965e+08 | AG686: 3.373496e+08 | AH686: =IF(H686="shared-count-once",COUNTIFS($A$2:$A$1353,A686,$B$2:$B$1353,B686,$E$2:$E$1353,E686),1)
A687: all | B687: 2034 | C687: I_CVD_PRIMARY | E687: COST_PRIMARY_SCREEN_A | F687: CC_PRIMARY_SCREENING | G687: I_CVD_PRIMARY__C_SHARED | H687: shared-count-once | I687: all | J687: =IFERROR(INDEX('Cost_Components'!$K$2:$K$27,MATCH(E687,'Cost_Components'!$A$2:$A$27,0)),"") | K687: =IF(OR(L687="",Z687="",AA687="",AB687=""),"",IF(B687<AA687,L687,IF(B687>AB687,Z687,L687+(Z687-L687)*MIN(MAX((B687-AA687+1)/MAX(AB687-AA687+1,1),0),1)))) | L687: =IFERROR(INDEX('Cost_Components'!$S$2:$S$27,MATCH(E687,'Cost_Components'!$A$2:$A$27,0)),"") | M687: =IFERROR(INDEX('Cost_Components'!$L$2:$L$27,MATCH(E687,'Cost_Components'!$A$2:$A$27,0)),"") | N687: =IFERROR(INDEX('Cost_Components'!$P$2:$P$27,MATCH(E687,'Cost_Components'!$A$2:$A$27,0)),"") | O687: =AF687*J687 | P687: =AG687*J687 | Q687: =P687*L687*M687*N687 | R687: =O687*K687*M687*N687 | S687: =R687-Q687 | T687: =IFERROR(INDEX('Cost_Components'!$R$2:$R$27,MATCH(E687,'Cost_Components'!$A$2:$A$27,0)),"") | U687: =IFERROR(INDEX('Cost_Components'!$Q$2:$Q$27,MATCH(E687,'Cost_Components'!$A$2:$A$27,0)),"") | V687: =1/(1+'Calculation_Assumptions'!$B$5)^(B687-'Calculation_Assumptions'!$B$2) | W687: =Q687*V687 | X687: =R687*V687 | Y687: =S687*V687 | Z687: =IFERROR(INDEX('Cost_Components'!$T$2:$T$27,MATCH(E687,'Cost_Components'!$A$2:$A$27,0)),"") | AA687: =IFERROR(INDEX('Cost_Components'!$U$2:$U$27,MATCH(E687,'Cost_Components'!$A$2:$A$27,0)),"") | AB687: =IFERROR(INDEX('Cost_Components'!$V$2:$V$27,MATCH(E687,'Cost_Components'!$A$2:$A$27,0)),"") | AC687: =IFERROR(INDEX('Cost_Components'!$M$2:$M$27,MATCH(E687,'Cost_Components'!$A$2:$A$27,0)),"") | AD687: =IFERROR(INDEX('Cost_Components'!$N$2:$N$27,MATCH(E687,'Cost_Components'!$A$2:$A$27,0)),"") | AE687: =IFERROR(INDEX('Cost_Components'!$O$2:$O$27,MATCH(E687,'Cost_Components'!$A$2:$A$27,0)),"") | AF687: 3.4191174e+08 | AG687: 3.4135282e+08 | AH687: =IF(H687="shared-count-once",COUNTIFS($A$2:$A$1353,A687,$B$2:$B$1353,B687,$E$2:$E$1353,E687),1)
A688: all | B688: 2035 | C688: I_CVD_PRIMARY | E688: COST_PRIMARY_SCREEN_A | F688: CC_PRIMARY_SCREENING | G688: I_CVD_PRIMARY__C_SHARED | H688: shared-count-once | I688: all | J688: =IFERROR(INDEX('Cost_Components'!$K$2:$K$27,MATCH(E688,'Cost_Components'!$A$2:$A$27,0)),"") | K688: =IF(OR(L688="",Z688="",AA688="",AB688=""),"",IF(B688<AA688,L688,IF(B688>AB688,Z688,L688+(Z688-L688)*MIN(MAX((B688-AA688+1)/MAX(AB688-AA688+1,1),0),1)))) | L688: =IFERROR(INDEX('Cost_Components'!$S$2:$S$27,MATCH(E688,'Cost_Components'!$A$2:$A$27,0)),"") | M688: =IFERROR(INDEX('Cost_Components'!$L$2:$L$27,MATCH(E688,'Cost_Components'!$A$2:$A$27,0)),"") | N688: =IFERROR(INDEX('Cost_Components'!$P$2:$P$27,MATCH(E688,'Cost_Components'!$A$2:$A$27,0)),"") | O688: =AF688*J688 | P688: =AG688*J688 | Q688: =P688*L688*M688*N688 | R688: =O688*K688*M688*N688 | S688: =R688-Q688 | T688: =IFERROR(INDEX('Cost_Components'!$R$2:$R$27,MATCH(E688,'Cost_Components'!$A$2:$A$27,0)),"") | U688: =IFERROR(INDEX('Cost_Components'!$Q$2:$Q$27,MATCH(E688,'Cost_Components'!$A$2:$A$27,0)),"") | V688: =1/(1+'Calculation_Assumptions'!$B$5)^(B688-'Calculation_Assumptions'!$B$2) | W688: =Q688*V688 | X688: =R688*V688 | Y688: =S688*V688 | Z688: =IFERROR(INDEX('Cost_Components'!$T$2:$T$27,MATCH(E688,'Cost_Components'!$A$2:$A$27,0)),"") | AA688: =IFERROR(INDEX('Cost_Components'!$U$2:$U$27,MATCH(E688,'Cost_Components'!$A$2:$A$27,0)),"") | AB688: =IFERROR(INDEX('Cost_Components'!$V$2:$V$27,MATCH(E688,'Cost_Components'!$A$2:$A$27,0)),"") | AC688: =IFERROR(INDEX('Cost_Components'!$M$2:$M$27,MATCH(E688,'Cost_Components'!$A$2:$A$27,0)),"") | AD688: =IFERROR(INDEX('Cost_Components'!$N$2:$N$27,MATCH(E688,'Cost_Components'!$A$2:$A$27,0)),"") | AE688: =IFERROR(INDEX('Cost_Components'!$O$2:$O$27,MATCH(E688,'Cost_Components'!$A$2:$A$27,0)),"") | AF688: 3.4610123e+08 | AG688: 3.4542926e+08 | AH688: =IF(H688="shared-count-once",COUNTIFS($A$2:$A$1353,A688,$B$2:$B$1353,B688,$E$2:$E$1353,E688),1)
A689: all | B689: 2036 | C689: I_CVD_PRIMARY | E689: COST_PRIMARY_SCREEN_A | F689: CC_PRIMARY_SCREENING | G689: I_CVD_PRIMARY__C_SHARED | H689: shared-count-once | I689: all | J689: =IFERROR(INDEX('Cost_Components'!$K$2:$K$27,MATCH(E689,'Cost_Components'!$A$2:$A$27,0)),"") | K689: =IF(OR(L689="",Z689="",AA689="",AB689=""),"",IF(B689<AA689,L689,IF(B689>AB689,Z689,L689+(Z689-L689)*MIN(MAX((B689-AA689+1)/MAX(AB689-AA689+1,1),0),1)))) | L689: =IFERROR(INDEX('Cost_Components'!$S$2:$S$27,MATCH(E689,'Cost_Components'!$A$2:$A$27,0)),"") | M689: =IFERROR(INDEX('Cost_Components'!$L$2:$L$27,MATCH(E689,'Cost_Components'!$A$2:$A$27,0)),"") | N689: =IFERROR(INDEX('Cost_Components'!$P$2:$P$27,MATCH(E689,'Cost_Components'!$A$2:$A$27,0)),"") | O689: =AF689*J689 | P689: =AG689*J689 | Q689: =P689*L689*M689*N689 | R689: =O689*K689*M689*N689 | S689: =R689-Q689 | T689: =IFERROR(INDEX('Cost_Components'!$R$2:$R$27,MATCH(E689,'Cost_Components'!$A$2:$A$27,0)),"") | U689: =IFERROR(INDEX('Cost_Components'!$Q$2:$Q$27,MATCH(E689,'Cost_Components'!$A$2:$A$27,0)),"") | V689: =1/(1+'Calculation_Assumptions'!$B$5)^(B689-'Calculation_Assumptions'!$B$2) | W689: =Q689*V689 | X689: =R689*V689 | Y689: =S689*V689 | Z689: =IFERROR(INDEX('Cost_Components'!$T$2:$T$27,MATCH(E689,'Cost_Components'!$A$2:$A$27,0)),"") | AA689: =IFERROR(INDEX('Cost_Components'!$U$2:$U$27,MATCH(E689,'Cost_Components'!$A$2:$A$27,0)),"") | AB689: =IFERROR(INDEX('Cost_Components'!$V$2:$V$27,MATCH(E689,'Cost_Components'!$A$2:$A$27,0)),"") | AC689: =IFERROR(INDEX('Cost_Components'!$M$2:$M$27,MATCH(E689,'Cost_Components'!$A$2:$A$27,0)),"") | AD689: =IFERROR(INDEX('Cost_Components'!$N$2:$N$27,MATCH(E689,'Cost_Components'!$A$2:$A$27,0)),"") | AE689: =IFERROR(INDEX('Cost_Components'!$O$2:$O$27,MATCH(E689,'Cost_Components'!$A$2:$A$27,0)),"") | AF689: 3.5039575e+08 | AG689: 3.4963346e+08 | AH689: =IF(H689="shared-count-once",COUNTIFS($A$2:$A$1353,A689,$B$2:$B$1353,B689,$E$2:$E$1353,E689),1)
... A729: all | B729: 2050 | C729: I_CVD_PRIMARY | E729: COST_PRIMARY_TX_A | F729: CC_PRIMARY_HTN_STATIN | G729: I_CVD_PRIMARY__C_SHARED | H729: shared-count-once | I729: all | J729: =IFERROR(INDEX('Cost_Components'!$K$2:$K$27,MATCH(E729,'Cost_Components'!$A$2:$A$27,0)),"") | K729: =IF(OR(L729="",Z729="",AA729="",AB729=""),"",IF(B729<AA729,L729,IF(B729>AB729,Z729,L729+(Z729-L729)*MIN(MAX((B729-AA729+1)/MAX(AB729-AA729+1,1),0),1)))) | L729: =IFERROR(INDEX('Cost_Components'!$S$2:$S$27,MATCH(E729,'Cost_Components'!$A$2:$A$27,0)),"") | M729: =IFERROR(INDEX('Cost_Components'!$L$2:$L$27,MATCH(E729,'Cost_Components'!$A$2:$A$27,0)),"") | N729: =IFERROR(INDEX('Cost_Components'!$P$2:$P$27,MATCH(E729,'Cost_Components'!$A$2:$A$27,0)),"") | O729: =AF729*J729 | P729: =AG729*J729 | Q729: =P729*L729*M729*N729 | R729: =O729*K729*M729*N729 | S729: =R729-Q729 | T729: =IFERROR(INDEX('Cost_Components'!$R$2:$R$27,MATCH(E729,'Cost_Components'!$A$2:$A$27,0)),"") | U729: =IFERROR(INDEX('Cost_Components'!$Q$2:$Q$27,MATCH(E729,'Cost_Components'!$A$2:$A$27,0)),"") | V729: =1/(1+'Calculation_Assumptions'!$B$5)^(B729-'Calculation_Assumptions'!$B$2) | W729: =Q729*V729 | X729: =R729*V729 | Y729: =S729*V729 | Z729: =IFERROR(INDEX('Cost_Components'!$T$2:$T$27,MATCH(E729,'Cost_Components'!$A$2:$A$27,0)),"") | AA729: =IFERROR(INDEX('Cost_Components'!$U$2:$U$27,MATCH(E729,'Cost_Components'!$A$2:$A$27,0)),"") | AB729: =IFERROR(INDEX('Cost_Components'!$V$2:$V$27,MATCH(E729,'Cost_Components'!$A$2:$A$27,0)),"") | AC729: =IFERROR(INDEX('Cost_Components'!$M$2:$M$27,MATCH(E729,'Cost_Components'!$A$2:$A$27,0)),"") | AD729: =IFERROR(INDEX('Cost_Components'!$N$2:$N$27,MATCH(E729,'Cost_Components'!$A$2:$A$27,0)),"") | AE729: =IFERROR(INDEX('Cost_Components'!$O$2:$O$27,MATCH(E729,'Cost_Components'!$A$2:$A$27,0)),"") | AF729: 4.0201035e+08 | AG729: 3.9813254e+08 | AH729: =IF(H729="shared-count-once",COUNTIFS($A$2:$A$1353,A729,$B$2:$B$1353,B729,$E$2:$E$1353,E729),1)
A730: all | B730: 2025 | C730: I_HF_ACUTE | D730: cmd | E730: COST_HF_ACUTE_C_CMP | F730: CC_HF_ACUTE_C_CMP | G730: I_HF_ACUTE__C_CMP | H730: cause-specific | I730: prevalence | J730: =IFERROR(INDEX('Cost_Components'!$K$2:$K$27,MATCH(E730,'Cost_Components'!$A$2:$A$27,0)),"") | K730: =IF(OR(L730="",Z730="",AA730="",AB730=""),"",IF(B730<AA730,L730,IF(B730>AB730,Z730,L730+(Z730-L730)*MIN(MAX((B730-AA730+1)/MAX(AB730-AA730+1,1),0),1)))) | L730: =IFERROR(INDEX('Cost_Components'!$S$2:$S$27,MATCH(E730,'Cost_Components'!$A$2:$A$27,0)),"") | M730: =IFERROR(INDEX('Cost_Components'!$L$2:$L$27,MATCH(E730,'Cost_Components'!$A$2:$A$27,0)),"") | N730: =IFERROR(INDEX('Cost_Components'!$P$2:$P$27,MATCH(E730,'Cost_Components'!$A$2:$A$27,0)),"") | O730: =AF730*J730 | P730: =AG730*J730 | Q730: =P730*L730*M730*N730 | R730: =O730*K730*M730*N730 | S730: =R730-Q730 | T730: =IFERROR(INDEX('Cost_Components'!$R$2:$R$27,MATCH(E730,'Cost_Components'!$A$2:$A$27,0)),"") | U730: =IFERROR(INDEX('Cost_Components'!$Q$2:$Q$27,MATCH(E730,'Cost_Components'!$A$2:$A$27,0)),"") | V730: =1/(1+'Calculation_Assumptions'!$B$5)^(B730-'Calculation_Assumptions'!$B$2) | W730: =Q730*V730 | X730: =R730*V730 | Y730: =S730*V730 | Z730: =IFERROR(INDEX('Cost_Components'!$T$2:$T$27,MATCH(E730,'Cost_Components'!$A$2:$A$27,0)),"") | AA730: =IFERROR(INDEX('Cost_Components'!$U$2:$U$27,MATCH(E730,'Cost_Components'!$A$2:$A$27,0)),"") | AB730: =IFERROR(INDEX('Cost_Components'!$V$2:$V$27,MATCH(E730,'Cost_Components'!$A$2:$A$27,0)),"") | AC730: =IFERROR(INDEX('Cost_Components'!$M$2:$M$27,MATCH(E730,'Cost_Components'!$A$2:$A$27,0)),"") | AD730: =IFERROR(INDEX('Cost_Components'!$N$2:$N$27,MATCH(E730,'Cost_Components'!$A$2:$A$27,0)),"") | AE730: =IFERROR(INDEX('Cost_Components'!$O$2:$O$27,MATCH(E730,'Cost_Components'!$A$2:$A$27,0)),"") | AF730: 53381.67 | AG730: 53296.123 | AH730: =IF(H730="shared-count-once",COUNTIFS($A$2:$A$1353,A730,$B$2:$B$1353,B730,$E$2:$E$1353,E730),1)
A731: all | B731: 2026 | C731: I_HF_ACUTE | D731: cmd | E731: COST_HF_ACUTE_C_CMP | F731: CC_HF_ACUTE_C_CMP | G731: I_HF_ACUTE__C_CMP | H731: cause-specific | I731: prevalence | J731: =IFERROR(INDEX('Cost_Components'!$K$2:$K$27,MATCH(E731,'Cost_Components'!$A$2:$A$27,0)),"") | K731: =IF(OR(L731="",Z731="",AA731="",AB731=""),"",IF(B731<AA731,L731,IF(B731>AB731,Z731,L731+(Z731-L731)*MIN(MAX((B731-AA731+1)/MAX(AB731-AA731+1,1),0),1)))) | L731: =IFERROR(INDEX('Cost_Components'!$S$2:$S$27,MATCH(E731,'Cost_Components'!$A$2:$A$27,0)),"") | M731: =IFERROR(INDEX('Cost_Components'!$L$2:$L$27,MATCH(E731,'Cost_Components'!$A$2:$A$27,0)),"") | N731: =IFERROR(INDEX('Cost_Components'!$P$2:$P$27,MATCH(E731,'Cost_Components'!$A$2:$A$27,0)),"") | O731: =AF731*J731 | P731: =AG731*J731 | Q731: =P731*L731*M731*N731 | R731: =O731*K731*M731*N731 | S731: =R731-Q731 | T731: =IFERROR(INDEX('Cost_Components'!$R$2:$R$27,MATCH(E731,'Cost_Components'!$A$2:$A$27,0)),"") | U731: =IFERROR(INDEX('Cost_Components'!$Q$2:$Q$27,MATCH(E731,'Cost_Components'!$A$2:$A$27,0)),"") | V731: =1/(1+'Calculation_Assumptions'!$B$5)^(B731-'Calculation_Assumptions'!$B$2) | W731: =Q731*V731 | X731: =R731*V731 | Y731: =S731*V731 | Z731: =IFERROR(INDEX('Cost_Components'!$T$2:$T$27,MATCH(E731,'Cost_Components'!$A$2:$A$27,0)),"") | AA731: =IFERROR(INDEX('Cost_Components'!$U$2:$U$27,MATCH(E731,'Cost_Components'!$A$2:$A$27,0)),"") | AB731: =IFERROR(INDEX('Cost_Components'!$V$2:$V$27,MATCH(E731,'Cost_Components'!$A$2:$A$27,0)),"") | AC731: =IFERROR(INDEX('Cost_Components'!$M$2:$M$27,MATCH(E731,'Cost_Components'!$A$2:$A$27,0)),"") | AD731: =IFERROR(INDEX('Cost_Components'!$N$2:$N$27,MATCH(E731,'Cost_Components'!$A$2:$A$27,0)),"") | AE731: =IFERROR(INDEX('Cost_Components'!$O$2:$O$27,MATCH(E731,'Cost_Components'!$A$2:$A$27,0)),"") | AF731: 55387.406 | AG731: 55143.657 | AH731: =IF(H731="shared-count-once",COUNTIFS($A$2:$A$1353,A731,$B$2:$B$1353,B731,$E$2:$E$1353,E731),1)
A732: all | B732: 2027 | C732: I_HF_ACUTE | D732: cmd | E732: COST_HF_ACUTE_C_CMP | F732: CC_HF_ACUTE_C_CMP | G732: I_HF_ACUTE__C_CMP | H732: cause-specific | I732: prevalence | J732: =IFERROR(INDEX('Cost_Components'!$K$2:$K$27,MATCH(E732,'Cost_Components'!$A$2:$A$27,0)),"") | K732: =IF(OR(L732="",Z732="",AA732="",AB732=""),"",IF(B732<AA732,L732,IF(B732>AB732,Z732,L732+(Z732-L732)*MIN(MAX((B732-AA732+1)/MAX(AB732-AA732+1,1),0),1)))) | L732: =IFERROR(INDEX('Cost_Components'!$S$2:$S$27,MATCH(E732,'Cost_Components'!$A$2:$A$27,0)),"") | M732: =IFERROR(INDEX('Cost_Components'!$L$2:$L$27,MATCH(E732,'Cost_Components'!$A$2:$A$27,0)),"") | N732: =IFERROR(INDEX('Cost_Components'!$P$2:$P$27,MATCH(E732,'Cost_Components'!$A$2:$A$27,0)),"") | O732: =AF732*J732 | P732: =AG732*J732 | Q732: =P732*L732*M732*N732 | R732: =O732*K732*M732*N732 | S732: =R732-Q732 | T732: =IFERROR(INDEX('Cost_Components'!$R$2:$R$27,MATCH(E732,'Cost_Components'!$A$2:$A$27,0)),"") | U732: =IFERROR(INDEX('Cost_Components'!$Q$2:$Q$27,MATCH(E732,'Cost_Components'!$A$2:$A$27,0)),"") | V732: =1/(1+'Calculation_Assumptions'!$B$5)^(B732-'Calculation_Assumptions'!$B$2) | W732: =Q732*V732 | X732: =R732*V732 | Y732: =S732*V732 | Z732: =IFERROR(INDEX('Cost_Components'!$T$2:$T$27,MATCH(E732,'Cost_Components'!$A$2:$A$27,0)),"") | AA732: =IFERROR(INDEX('Cost_Components'!$U$2:$U$27,MATCH(E732,'Cost_Components'!$A$2:$A$27,0)),"") | AB732: =IFERROR(INDEX('Cost_Components'!$V$2:$V$27,MATCH(E732,'Cost_Components'!$A$2:$A$27,0)),"") | AC732: =IFERROR(INDEX('Cost_Components'!$M$2:$M$27,MATCH(E732,'Cost_Components'!$A$2:$A$27,0)),"") | AD732: =IFERROR(INDEX('Cost_Components'!$N$2:$N$27,MATCH(E732,'Cost_Components'!$A$2:$A$27,0)),"") | AE732: =IFERROR(INDEX('Cost_Components'!$O$2:$O$27,MATCH(E732,'Cost_Components'!$A$2:$A$27,0)),"") | AF732: 57428.31 | AG732: 56962.574 | AH732: =IF(H732="shared-count-once",COUNTIFS($A$2:$A$1353,A732,$B$2:$B$1353,B732,$E$2:$E$1353,E732),1)
A733: all | B733: 2028 | C733: I_HF_ACUTE | D733: cmd | E733: COST_HF_ACUTE_C_CMP | F733: CC_HF_ACUTE_C_CMP | G733: I_HF_ACUTE__C_CMP | H733: cause-specific | I733: prevalence | J733: =IFERROR(INDEX('Cost_Components'!$K$2:$K$27,MATCH(E733,'Cost_Components'!$A$2:$A$27,0)),"") | K733: =IF(OR(L733="",Z733="",AA733="",AB733=""),"",IF(B733<AA733,L733,IF(B733>AB733,Z733,L733+(Z733-L733)*MIN(MAX((B733-AA733+1)/MAX(AB733-AA733+1,1),0),1)))) | L733: =IFERROR(INDEX('Cost_Components'!$S$2:$S$27,MATCH(E733,'Cost_Components'!$A$2:$A$27,0)),"") | M733: =IFERROR(INDEX('Cost_Components'!$L$2:$L$27,MATCH(E733,'Cost_Components'!$A$2:$A$27,0)),"") | N733: =IFERROR(INDEX('Cost_Components'!$P$2:$P$27,MATCH(E733,'Cost_Components'!$A$2:$A$27,0)),"") | O733: =AF733*J733 | P733: =AG733*J733 | Q733: =P733*L733*M733*N733 | R733: =O733*K733*M733*N733 | S733: =R733-Q733 | T733: =IFERROR(INDEX('Cost_Components'!$R$2:$R$27,MATCH(E733,'Cost_Components'!$A$2:$A$27,0)),"") | U733: =IFERROR(INDEX('Cost_Components'!$Q$2:$Q$27,MATCH(E733,'Cost_Components'!$A$2:$A$27,0)),"") | V733: =1/(1+'Calculation_Assumptions'!$B$5)^(B733-'Calculation_Assumptions'!$B$2) | W733: =Q733*V733 | X733: =R733*V733 | Y733: =S733*V733 | Z733: =IFERROR(INDEX('Cost_Components'!$T$2:$T$27,MATCH(E733,'Cost_Components'!$A$2:$A$27,0)),"") | AA733: =IFERROR(INDEX('Cost_Components'!$U$2:$U$27,MATCH(E733,'Cost_Components'!$A$2:$A$27,0)),"") | AB733: =IFERROR(INDEX('Cost_Components'!$V$2:$V$27,MATCH(E733,'Cost_Components'!$A$2:$A$27,0)),"") | AC733: =IFERROR(INDEX('Cost_Components'!$M$2:$M$27,MATCH(E733,'Cost_Components'!$A$2:$A$27,0)),"") | AD733: =IFERROR(INDEX('Cost_Components'!$N$2:$N$27,MATCH(E733,'Cost_Components'!$A$2:$A$27,0)),"") | AE733: =IFERROR(INDEX('Cost_Components'!$O$2:$O$27,MATCH(E733,'Cost_Components'!$A$2:$A$27,0)),"") | AF733: 59489.704 | AG733: 58744.418 | AH733: =IF(H733="shared-count-once",COUNTIFS($A$2:$A$1353,A733,$B$2:$B$1353,B733,$E$2:$E$1353,E733),1)
A734: all | B734: 2029 | C734: I_HF_ACUTE | D734: cmd | E734: COST_HF_ACUTE_C_CMP | F734: CC_HF_ACUTE_C_CMP | G734: I_HF_ACUTE__C_CMP | H734: cause-specific | I734: prevalence | J734: =IFERROR(INDEX('Cost_Components'!$K$2:$K$27,MATCH(E734,'Cost_Components'!$A$2:$A$27,0)),"") | K734: =IF(OR(L734="",Z734="",AA734="",AB734=""),"",IF(B734<AA734,L734,IF(B734>AB734,Z734,L734+(Z734-L734)*MIN(MAX((B734-AA734+1)/MAX(AB734-AA734+1,1),0),1)))) | L734: =IFERROR(INDEX('Cost_Components'!$S$2:$S$27,MATCH(E734,'Cost_Components'!$A$2:$A$27,0)),"") | M734: =IFERROR(INDEX('Cost_Components'!$L$2:$L$27,MATCH(E734,'Cost_Components'!$A$2:$A$27,0)),"") | N734: =IFERROR(INDEX('Cost_Components'!$P$2:$P$27,MATCH(E734,'Cost_Components'!$A$2:$A$27,0)),"") | O734: =AF734*J734 | P734: =AG734*J734 | Q734: =P734*L734*M734*N734 | R734: =O734*K734*M734*N734 | S734: =R734-Q734 | T734: =IFERROR(INDEX('Cost_Components'!$R$2:$R$27,MATCH(E734,'Cost_Components'!$A$2:$A$27,0)),"") | U734: =IFERROR(INDEX('Cost_Components'!$Q$2:$Q$27,MATCH(E734,'Cost_Components'!$A$2:$A$27,0)),"") | V734: =1/(1+'Calculation_Assumptions'!$B$5)^(B734-'Calculation_Assumptions'!$B$2) | W734: =Q734*V734 | X734: =R734*V734 | Y734: =S734*V734 | Z734: =IFERROR(INDEX('Cost_Components'!$T$2:$T$27,MATCH(E734,'Cost_Components'!$A$2:$A$27,0)),"") | AA734: =IFERROR(INDEX('Cost_Components'!$U$2:$U$27,MATCH(E734,'Cost_Components'!$A$2:$A$27,0)),"") | AB734: =IFERROR(INDEX('Cost_Components'!$V$2:$V$27,MATCH(E734,'Cost_Components'!$A$2:$A$27,0)),"") | AC734: =IFERROR(INDEX('Cost_Components'!$M$2:$M$27,MATCH(E734,'Cost_Components'!$A$2:$A$27,0)),"") | AD734: =IFERROR(INDEX('Cost_Components'!$N$2:$N$27,MATCH(E734,'Cost_Components'!$A$2:$A$27,0)),"") | AE734: =IFERROR(INDEX('Cost_Components'!$O$2:$O$27,MATCH(E734,'Cost_Components'!$A$2:$A$27,0)),"") | AF734: 61575.421 | AG734: 60497.402 | AH734: =IF(H734="shared-count-once",COUNTIFS($A$2:$A$1353,A734,$B$2:$B$1353,B734,$E$2:$E$1353,E734),1)
A735: all | B735: 2030 | C735: I_HF_ACUTE | D735: cmd | E735: COST_HF_ACUTE_C_CMP | F735: CC_HF_ACUTE_C_CMP | G735: I_HF_ACUTE__C_CMP | H735: cause-specific | I735: prevalence | J735: =IFERROR(INDEX('Cost_Components'!$K$2:$K$27,MATCH(E735,'Cost_Components'!$A$2:$A$27,0)),"") | K735: =IF(OR(L735="",Z735="",AA735="",AB735=""),"",IF(B735<AA735,L735,IF(B735>AB735,Z735,L735+(Z735-L735)*MIN(MAX((B735-AA735+1)/MAX(AB735-AA735+1,1),0),1)))) | L735: =IFERROR(INDEX('Cost_Components'!$S$2:$S$27,MATCH(E735,'Cost_Components'!$A$2:$A$27,0)),"") | M735: =IFERROR(INDEX('Cost_Components'!$L$2:$L$27,MATCH(E735,'Cost_Components'!$A$2:$A$27,0)),"") | N735: =IFERROR(INDEX('Cost_Components'!$P$2:$P$27,MATCH(E735,'Cost_Components'!$A$2:$A$27,0)),"") | O735: =AF735*J735 | P735: =AG735*J735 | Q735: =P735*L735*M735*N735 | R735: =O735*K735*M735*N735 | S735: =R735-Q735 | T735: =IFERROR(INDEX('Cost_Components'!$R$2:$R$27,MATCH(E735,'Cost_Components'!$A$2:$A$27,0)),"") | U735: =IFERROR(INDEX('Cost_Components'!$Q$2:$Q$27,MATCH(E735,'Cost_Components'!$A$2:$A$27,0)),"") | V735: =1/(1+'Calculation_Assumptions'!$B$5)^(B735-'Calculation_Assumptions'!$B$2) | W735: =Q735*V735 | X735: =R735*V735 | Y735: =S735*V735 | Z735: =IFERROR(INDEX('Cost_Components'!$T$2:$T$27,MATCH(E735,'Cost_Components'!$A$2:$A$27,0)),"") | AA735: =IFERROR(INDEX('Cost_Components'!$U$2:$U$27,MATCH(E735,'Cost_Components'!$A$2:$A$27,0)),"") | AB735: =IFERROR(INDEX('Cost_Components'!$V$2:$V$27,MATCH(E735,'Cost_Components'!$A$2:$A$27,0)),"") | AC735: =IFERROR(INDEX('Cost_Components'!$M$2:$M$27,MATCH(E735,'Cost_Components'!$A$2:$A$27,0)),"") | AD735: =IFERROR(INDEX('Cost_Components'!$N$2:$N$27,MATCH(E735,'Cost_Components'!$A$2:$A$27,0)),"") | AE735: =IFERROR(INDEX('Cost_Components'!$O$2:$O$27,MATCH(E735,'Cost_Components'!$A$2:$A$27,0)),"") | AF735: 63693.088 | AG735: 62232.086 | AH735: =IF(H735="shared-count-once",COUNTIFS($A$2:$A$1353,A735,$B$2:$B$1353,B735,$E$2:$E$1353,E735),1)
A736: all | B736: 2031 | C736: I_HF_ACUTE | D736: cmd | E736: COST_HF_ACUTE_C_CMP | F736: CC_HF_ACUTE_C_CMP | G736: I_HF_ACUTE__C_CMP | H736: cause-specific | I736: prevalence | J736: =IFERROR(INDEX('Cost_Components'!$K$2:$K$27,MATCH(E736,'Cost_Components'!$A$2:$A$27,0)),"") | K736: =IF(OR(L736="",Z736="",AA736="",AB736=""),"",IF(B736<AA736,L736,IF(B736>AB736,Z736,L736+(Z736-L736)*MIN(MAX((B736-AA736+1)/MAX(AB736-AA736+1,1),0),1)))) | L736: =IFERROR(INDEX('Cost_Components'!$S$2:$S$27,MATCH(E736,'Cost_Components'!$A$2:$A$27,0)),"") | M736: =IFERROR(INDEX('Cost_Components'!$L$2:$L$27,MATCH(E736,'Cost_Components'!$A$2:$A$27,0)),"") | N736: =IFERROR(INDEX('Cost_Components'!$P$2:$P$27,MATCH(E736,'Cost_Components'!$A$2:$A$27,0)),"") | O736: =AF736*J736 | P736: =AG736*J736 | Q736: =P736*L736*M736*N736 | R736: =O736*K736*M736*N736 | S736: =R736-Q736 | T736: =IFERROR(INDEX('Cost_Components'!$R$2:$R$27,MATCH(E736,'Cost_Components'!$A$2:$A$27,0)),"") | U736: =IFERROR(INDEX('Cost_Components'!$Q$2:$Q$27,MATCH(E736,'Cost_Components'!$A$2:$A$27,0)),"") | V736: =1/(1+'Calculation_Assumptions'!$B$5)^(B736-'Calculation_Assumptions'!$B$2) | W736: =Q736*V736 | X736: =R736*V736 | Y736: =S736*V736 | Z736: =IFERROR(INDEX('Cost_Components'!$T$2:$T$27,MATCH(E736,'Cost_Components'!$A$2:$A$27,0)),"") | AA736: =IFERROR(INDEX('Cost_Components'!$U$2:$U$27,MATCH(E736,'Cost_Components'!$A$2:$A$27,0)),"") | AB736: =IFERROR(INDEX('Cost_Components'!$V$2:$V$27,MATCH(E736,'Cost_Components'!$A$2:$A$27,0)),"") | AC736: =IFERROR(INDEX('Cost_Components'!$M$2:$M$27,MATCH(E736,'Cost_Components'!$A$2:$A$27,0)),"") | AD736: =IFERROR(INDEX('Cost_Components'!$N$2:$N$27,MATCH(E736,'Cost_Components'!$A$2:$A$27,0)),"") | AE736: =IFERROR(INDEX('Cost_Components'!$O$2:$O$27,MATCH(E736,'Cost_Components'!$A$2:$A$27,0)),"") | AF736: 65847.394 | AG736: 63955.031 | AH736: =IF(H736="shared-count-once",COUNTIFS($A$2:$A$1353,A736,$B$2:$B$1353,B736,$E$2:$E$1353,E736),1)
A737: all | B737: 2032 | C737: I_HF_ACUTE | D737: cmd | E737: COST_HF_ACUTE_C_CMP | F737: CC_HF_ACUTE_C_CMP | G737: I_HF_ACUTE__C_CMP | H737: cause-specific | I737: prevalence | J737: =IFERROR(INDEX('Cost_Components'!$K$2:$K$27,MATCH(E737,'Cost_Components'!$A$2:$A$27,0)),"") | K737: =IF(OR(L737="",Z737="",AA737="",AB737=""),"",IF(B737<AA737,L737,IF(B737>AB737,Z737,L737+(Z737-L737)*MIN(MAX((B737-AA737+1)/MAX(AB737-AA737+1,1),0),1)))) | L737: =IFERROR(INDEX('Cost_Components'!$S$2:$S$27,MATCH(E737,'Cost_Components'!$A$2:$A$27,0)),"") | M737: =IFERROR(INDEX('Cost_Components'!$L$2:$L$27,MATCH(E737,'Cost_Components'!$A$2:$A$27,0)),"") | N737: =IFERROR(INDEX('Cost_Components'!$P$2:$P$27,MATCH(E737,'Cost_Components'!$A$2:$A$27,0)),"") | O737: =AF737*J737 | P737: =AG737*J737 | Q737: =P737*L737*M737*N737 | R737: =O737*K737*M737*N737 | S737: =R737-Q737 | T737: =IFERROR(INDEX('Cost_Components'!$R$2:$R$27,MATCH(E737,'Cost_Components'!$A$2:$A$27,0)),"") | U737: =IFERROR(INDEX('Cost_Components'!$Q$2:$Q$27,MATCH(E737,'Cost_Components'!$A$2:$A$27,0)),"") | V737: =1/(1+'Calculation_Assumptions'!$B$5)^(B737-'Calculation_Assumptions'!$B$2) | W737: =Q737*V737 | X737: =R737*V737 | Y737: =S737*V737 | Z737: =IFERROR(INDEX('Cost_Components'!$T$2:$T$27,MATCH(E737,'Cost_Components'!$A$2:$A$27,0)),"") | AA737: =IFERROR(INDEX('Cost_Components'!$U$2:$U$27,MATCH(E737,'Cost_Components'!$A$2:$A$27,0)),"") | AB737: =IFERROR(INDEX('Cost_Components'!$V$2:$V$27,MATCH(E737,'Cost_Components'!$A$2:$A$27,0)),"") | AC737: =IFERROR(INDEX('Cost_Components'!$M$2:$M$27,MATCH(E737,'Cost_Components'!$A$2:$A$27,0)),"") | AD737: =IFERROR(INDEX('Cost_Components'!$N$2:$N$27,MATCH(E737,'Cost_Components'!$A$2:$A$27,0)),"") | AE737: =IFERROR(INDEX('Cost_Components'!$O$2:$O$27,MATCH(E737,'Cost_Components'!$A$2:$A$27,0)),"") | AF737: 68061.233 | AG737: 65690.829 | AH737: =IF(H737="shared-count-once",COUNTIFS($A$2:$A$1353,A737,$B$2:$B$1353,B737,$E$2:$E$1353,E737),1)
A738: all | B738: 2033 | C738: I_HF_ACUTE | D738: cmd | E738: COST_HF_ACUTE_C_CMP | F738: CC_HF_ACUTE_C_CMP | G738: I_HF_ACUTE__C_CMP | H738: cause-specific | I738: prevalence | J738: =IFERROR(INDEX('Cost_Components'!$K$2:$K$27,MATCH(E738,'Cost_Components'!$A$2:$A$27,0)),"") | K738: =IF(OR(L738="",Z738="",AA738="",AB738=""),"",IF(B738<AA738,L738,IF(B738>AB738,Z738,L738+(Z738-L738)*MIN(MAX((B738-AA738+1)/MAX(AB738-AA738+1,1),0),1)))) | L738: =IFERROR(INDEX('Cost_Components'!$S$2:$S$27,MATCH(E738,'Cost_Components'!$A$2:$A$27,0)),"") | M738: =IFERROR(INDEX('Cost_Components'!$L$2:$L$27,MATCH(E738,'Cost_Components'!$A$2:$A$27,0)),"") | N738: =IFERROR(INDEX('Cost_Components'!$P$2:$P$27,MATCH(E738,'Cost_Components'!$A$2:$A$27,0)),"") | O738: =AF738*J738 | P738: =AG738*J738 | Q738: =P738*L738*M738*N738 | R738: =O738*K738*M738*N738 | S738: =R738-Q738 | T738: =IFERROR(INDEX('Cost_Components'!$R$2:$R$27,MATCH(E738,'Cost_Components'!$A$2:$A$27,0)),"") | U738: =IFERROR(INDEX('Cost_Components'!$Q$2:$Q$27,MATCH(E738,'Cost_Components'!$A$2:$A$27,0)),"") | V738: =1/(1+'Calculation_Assumptions'!$B$5)^(B738-'Calculation_Assumptions'!$B$2) | W738: =Q738*V738 | X738: =R738*V738 | Y738: =S738*V738 | Z738: =IFERROR(INDEX('Cost_Components'!$T$2:$T$27,MATCH(E738,'Cost_Components'!$A$2:$A$27,0)),"") | AA738: =IFERROR(INDEX('Cost_Components'!$U$2:$U$27,MATCH(E738,'Cost_Components'!$A$2:$A$27,0)),"") | AB738: =IFERROR(INDEX('Cost_Components'!$V$2:$V$27,MATCH(E738,'Cost_Components'!$A$2:$A$27,0)),"") | AC738: =IFERROR(INDEX('Cost_Components'!$M$2:$M$27,MATCH(E738,'Cost_Components'!$A$2:$A$27,0)),"") | AD738: =IFERROR(INDEX('Cost_Components'!$N$2:$N$27,MATCH(E738,'Cost_Components'!$A$2:$A$27,0)),"") | AE738: =IFERROR(INDEX('Cost_Components'!$O$2:$O$27,MATCH(E738,'Cost_Components'!$A$2:$A$27,0)),"") | AF738: 70351.162 | AG738: 67457.385 | AH738: =IF(H738="shared-count-once",COUNTIFS($A$2:$A$1353,A738,$B$2:$B$1353,B738,$E$2:$E$1353,E738),1)
A739: all | B739: 2034 | C739: I_HF_ACUTE | D739: cmd | E739: COST_HF_ACUTE_C_CMP | F739: CC_HF_ACUTE_C_CMP | G739: I_HF_ACUTE__C_CMP | H739: cause-specific | I739: prevalence | J739: =IFERROR(INDEX('Cost_Components'!$K$2:$K$27,MATCH(E739,'Cost_Components'!$A$2:$A$27,0)),"") | K739: =IF(OR(L739="",Z739="",AA739="",AB739=""),"",IF(B739<AA739,L739,IF(B739>AB739,Z739,L739+(Z739-L739)*MIN(MAX((B739-AA739+1)/MAX(AB739-AA739+1,1),0),1)))) | L739: =IFERROR(INDEX('Cost_Components'!$S$2:$S$27,MATCH(E739,'Cost_Components'!$A$2:$A$27,0)),"") | M739: =IFERROR(INDEX('Cost_Components'!$L$2:$L$27,MATCH(E739,'Cost_Components'!$A$2:$A$27,0)),"") | N739: =IFERROR(INDEX('Cost_Components'!$P$2:$P$27,MATCH(E739,'Cost_Components'!$A$2:$A$27,0)),"") | O739: =AF739*J739 | P739: =AG739*J739 | Q739: =P739*L739*M739*N739 | R739: =O739*K739*M739*N739 | S739: =R739-Q739 | T739: =IFERROR(INDEX('Cost_Components'!$R$2:$R$27,MATCH(E739,'Cost_Components'!$A$2:$A$27,0)),"") | U739: =IFERROR(INDEX('Cost_Components'!$Q$2:$Q$27,MATCH(E739,'Cost_Components'!$A$2:$A$27,0)),"") | V739: =1/(1+'Calculation_Assumptions'!$B$5)^(B739-'Calculation_Assumptions'!$B$2) | W739: =Q739*V739 | X739: =R739*V739 | Y739: =S739*V739 | Z739: =IFERROR(INDEX('Cost_Components'!$T$2:$T$27,MATCH(E739,'Cost_Components'!$A$2:$A$27,0)),"") | AA739: =IFERROR(INDEX('Cost_Components'!$U$2:$U$27,MATCH(E739,'Cost_Components'!$A$2:$A$27,0)),"") | AB739: =IFERROR(INDEX('Cost_Components'!$V$2:$V$27,MATCH(E739,'Cost_Components'!$A$2:$A$27,0)),"") | AC739: =IFERROR(INDEX('Cost_Components'!$M$2:$M$27,MATCH(E739,'Cost_Components'!$A$2:$A$27,0)),"") | AD739: =IFERROR(INDEX('Cost_Components'!$N$2:$N$27,MATCH(E739,'Cost_Components'!$A$2:$A$27,0)),"") | AE739: =IFERROR(INDEX('Cost_Components'!$O$2:$O$27,MATCH(E739,'Cost_Components'!$A$2:$A$27,0)),"") | AF739: 72726.952 | AG739: 69265.137 | AH739: =IF(H739="shared-count-once",COUNTIFS($A$2:$A$1353,A739,$B$2:$B$1353,B739,$E$2:$E$1353,E739),1)
A740: all | B740: 2035 | C740: I_HF_ACUTE | D740: cmd | E740: COST_HF_ACUTE_C_CMP | F740: CC_HF_ACUTE_C_CMP | G740: I_HF_ACUTE__C_CMP | H740: cause-specific | I740: prevalence | J740: =IFERROR(INDEX('Cost_Components'!$K$2:$K$27,MATCH(E740,'Cost_Components'!$A$2:$A$27,0)),"") | K740: =IF(OR(L740="",Z740="",AA740="",AB740=""),"",IF(B740<AA740,L740,IF(B740>AB740,Z740,L740+(Z740-L740)*MIN(MAX((B740-AA740+1)/MAX(AB740-AA740+1,1),0),1)))) | L740: =IFERROR(INDEX('Cost_Components'!$S$2:$S$27,MATCH(E740,'Cost_Components'!$A$2:$A$27,0)),"") | M740: =IFERROR(INDEX('Cost_Components'!$L$2:$L$27,MATCH(E740,'Cost_Components'!$A$2:$A$27,0)),"") | N740: =IFERROR(INDEX('Cost_Components'!$P$2:$P$27,MATCH(E740,'Cost_Components'!$A$2:$A$27,0)),"") | O740: =AF740*J740 | P740: =AG740*J740 | Q740: =P740*L740*M740*N740 | R740: =O740*K740*M740*N740 | S740: =R740-Q740 | T740: =IFERROR(INDEX('Cost_Components'!$R$2:$R$27,MATCH(E740,'Cost_Components'!$A$2:$A$27,0)),"") | U740: =IFERROR(INDEX('Cost_Components'!$Q$2:$Q$27,MATCH(E740,'Cost_Components'!$A$2:$A$27,0)),"") | V740: =1/(1+'Calculation_Assumptions'!$B$5)^(B740-'Calculation_Assumptions'!$B$2) | W740: =Q740*V740 | X740: =R740*V740 | Y740: =S740*V740 | Z740: =IFERROR(INDEX('Cost_Components'!$T$2:$T$27,MATCH(E740,'Cost_Components'!$A$2:$A$27,0)),"") | AA740: =IFERROR(INDEX('Cost_Components'!$U$2:$U$27,MATCH(E740,'Cost_Components'!$A$2:$A$27,0)),"") | AB740: =IFERROR(INDEX('Cost_Components'!$V$2:$V$27,MATCH(E740,'Cost_Components'!$A$2:$A$27,0)),"") | AC740: =IFERROR(INDEX('Cost_Components'!$M$2:$M$27,MATCH(E740,'Cost_Components'!$A$2:$A$27,0)),"") | AD740: =IFERROR(INDEX('Cost_Components'!$N$2:$N$27,MATCH(E740,'Cost_Components'!$A$2:$A$27,0)),"") | AE740: =IFERROR(INDEX('Cost_Components'!$O$2:$O$27,MATCH(E740,'Cost_Components'!$A$2:$A$27,0)),"") | AF740: 75208.865 | AG740: 71134.821 | AH740: =IF(H740="shared-count-once",COUNTIFS($A$2:$A$1353,A740,$B$2:$B$1353,B740,$E$2:$E$1353,E740),1)
A741: all | B741: 2036 | C741: I_HF_ACUTE | D741: cmd | E741: COST_HF_ACUTE_C_CMP | F741: CC_HF_ACUTE_C_CMP | G741: I_HF_ACUTE__C_CMP | H741: cause-specific | I741: prevalence | J741: =IFERROR(INDEX('Cost_Components'!$K$2:$K$27,MATCH(E741,'Cost_Components'!$A$2:$A$27,0)),"") | K741: =IF(OR(L741="",Z741="",AA741="",AB741=""),"",IF(B741<AA741,L741,IF(B741>AB741,Z741,L741+(Z741-L741)*MIN(MAX((B741-AA741+1)/MAX(AB741-AA741+1,1),0),1)))) | L741: =IFERROR(INDEX('Cost_Components'!$S$2:$S$27,MATCH(E741,'Cost_Components'!$A$2:$A$27,0)),"") | M741: =IFERROR(INDEX('Cost_Components'!$L$2:$L$27,MATCH(E741,'Cost_Components'!$A$2:$A$27,0)),"") | N741: =IFERROR(INDEX('Cost_Components'!$P$2:$P$27,MATCH(E741,'Cost_Components'!$A$2:$A$27,0)),"") | O741: =AF741*J741 | P741: =AG741*J741 | Q741: =P741*L741*M741*N741 | R741: =O741*K741*M741*N741 | S741: =R741-Q741 | T741: =IFERROR(INDEX('Cost_Components'!$R$2:$R$27,MATCH(E741,'Cost_Components'!$A$2:$A$27,0)),"") | U741: =IFERROR(INDEX('Cost_Components'!$Q$2:$Q$27,MATCH(E741,'Cost_Components'!$A$2:$A$27,0)),"") | V741: =1/(1+'Calculation_Assumptions'!$B$5)^(B741-'Calculation_Assumptions'!$B$2) | W741: =Q741*V741 | X741: =R741*V741 | Y741: =S741*V741 | Z741: =IFERROR(INDEX('Cost_Components'!$T$2:$T$27,MATCH(E741,'Cost_Components'!$A$2:$A$27,0)),"") | AA741: =IFERROR(INDEX('Cost_Components'!$U$2:$U$27,MATCH(E741,'Cost_Components'!$A$2:$A$27,0)),"") | AB741: =IFERROR(INDEX('Cost_Components'!$V$2:$V$27,MATCH(E741,'Cost_Components'!$A$2:$A$27,0)),"") | AC741: =IFERROR(INDEX('Cost_Components'!$M$2:$M$27,MATCH(E741,'Cost_Components'!$A$2:$A$27,0)),"") | AD741: =IFERROR(INDEX('Cost_Components'!$N$2:$N$27,MATCH(E741,'Cost_Components'!$A$2:$A$27,0)),"") | AE741: =IFERROR(INDEX('Cost_Components'!$O$2:$O$27,MATCH(E741,'Cost_Components'!$A$2:$A$27,0)),"") | AF741: 77816.823 | AG741: 73085.713 | AH741: =IF(H741="shared-count-once",COUNTIFS($A$2:$A$1353,A741,$B$2:$B$1353,B741,$E$2:$E$1353,E741),1)
... A1353: all | B1353: 2050 | C1353: I_T2D_TREATMENT | D1353: dm2 | E1353: COST_T2D_TREATMENT | F1353: CC_T2D_TREATMENT | G1353: I_T2D_TREATMENT__C_T2D | H1353: cause-specific | I1353: prevalence | J1353: =IFERROR(INDEX('Cost_Components'!$K$2:$K$27,MATCH(E1353,'Cost_Components'!$A$2:$A$27,0)),"") | K1353: =IF(OR(L1353="",Z1353="",AA1353="",AB1353=""),"",IF(B1353<AA1353,L1353,IF(B1353>AB1353,Z1353,L1353+(Z1353-L1353)*MIN(MAX((B1353-AA1353+1)/MAX(AB1353-AA1353+1,1),0),1)))) | L1353: =IFERROR(INDEX('Cost_Components'!$S$2:$S$27,MATCH(E1353,'Cost_Components'!$A$2:$A$27,0)),"") | M1353: =IFERROR(INDEX('Cost_Components'!$L$2:$L$27,MATCH(E1353,'Cost_Components'!$A$2:$A$27,0)),"") | N1353: =IFERROR(INDEX('Cost_Components'!$P$2:$P$27,MATCH(E1353,'Cost_Components'!$A$2:$A$27,0)),"") | O1353: =AF1353*J1353 | P1353: =AG1353*J1353 | Q1353: =P1353*L1353*M1353*N1353 | R1353: =O1353*K1353*M1353*N1353 | S1353: =R1353-Q1353 | T1353: =IFERROR(INDEX('Cost_Components'!$R$2:$R$27,MATCH(E1353,'Cost_Components'!$A$2:$A$27,0)),"") | U1353: =IFERROR(INDEX('Cost_Components'!$Q$2:$Q$27,MATCH(E1353,'Cost_Components'!$A$2:$A$27,0)),"") | V1353: =1/(1+'Calculation_Assumptions'!$B$5)^(B1353-'Calculation_Assumptions'!$B$2) | W1353: =Q1353*V1353 | X1353: =R1353*V1353 | Y1353: =S1353*V1353 | Z1353: =IFERROR(INDEX('Cost_Components'!$T$2:$T$27,MATCH(E1353,'Cost_Components'!$A$2:$A$27,0)),"") | AA1353: =IFERROR(INDEX('Cost_Components'!$U$2:$U$27,MATCH(E1353,'Cost_Components'!$A$2:$A$27,0)),"") | AB1353: =IFERROR(INDEX('Cost_Components'!$V$2:$V$27,MATCH(E1353,'Cost_Components'!$A$2:$A$27,0)),"") | AC1353: =IFERROR(INDEX('Cost_Components'!$M$2:$M$27,MATCH(E1353,'Cost_Components'!$A$2:$A$27,0)),"") | AD1353: =IFERROR(INDEX('Cost_Components'!$N$2:$N$27,MATCH(E1353,'Cost_Components'!$A$2:$A$27,0)),"") | AE1353: =IFERROR(INDEX('Cost_Components'!$O$2:$O$27,MATCH(E1353,'Cost_Components'!$A$2:$A$27,0)),"") | AF1353: 29053311 | AG1353: 28628880 | AH1353: =IF(H1353="shared-count-once",COUNTIFS($A$2:$A$1353,A1353,$B$2:$B$1353,B1353,$E$2:$E$1353,E1353),1)

Sheet Budget_Impact
A1: scenario | B1: year | C1: baseline_cost | D1: scenario_cost | E1: incremental_cost | F1: disc_incremental_cost | G1: cumulative_incremental_cost | H1: cumulative_disc_incremental_cost
A2: I_CVD_PRIMARY | B2: 2025 | C2: =SUMIFS('Annual_Cost'!$Q$2:$Q$1353,'Annual_Cost'!$A$2:$A$1353,A2,'Annual_Cost'!$B$2:$B$1353,B2) | D2: =SUMIFS('Annual_Cost'!$R$2:$R$1353,'Annual_Cost'!$A$2:$A$1353,A2,'Annual_Cost'!$B$2:$B$1353,B2) | E2: =SUMIFS('Annual_Cost'!$S$2:$S$1353,'Annual_Cost'!$A$2:$A$1353,A2,'Annual_Cost'!$B$2:$B$1353,B2) | F2: =SUMIFS('Annual_Cost'!$Y$2:$Y$1353,'Annual_Cost'!$A$2:$A$1353,A2,'Annual_Cost'!$B$2:$B$1353,B2) | G2: =SUMIFS($E$2:E2,$A$2:A2,A2) | H2: =SUMIFS($F$2:F2,$A$2:A2,A2)
A3: I_CVD_PRIMARY | B3: 2026 | C3: =SUMIFS('Annual_Cost'!$Q$2:$Q$1353,'Annual_Cost'!$A$2:$A$1353,A3,'Annual_Cost'!$B$2:$B$1353,B3) | D3: =SUMIFS('Annual_Cost'!$R$2:$R$1353,'Annual_Cost'!$A$2:$A$1353,A3,'Annual_Cost'!$B$2:$B$1353,B3) | E3: =SUMIFS('Annual_Cost'!$S$2:$S$1353,'Annual_Cost'!$A$2:$A$1353,A3,'Annual_Cost'!$B$2:$B$1353,B3) | F3: =SUMIFS('Annual_Cost'!$Y$2:$Y$1353,'Annual_Cost'!$A$2:$A$1353,A3,'Annual_Cost'!$B$2:$B$1353,B3) | G3: =SUMIFS($E$2:E3,$A$2:A3,A3) | H3: =SUMIFS($F$2:F3,$A$2:A3,A3)
A4: I_CVD_PRIMARY | B4: 2027 | C4: =SUMIFS('Annual_Cost'!$Q$2:$Q$1353,'Annual_Cost'!$A$2:$A$1353,A4,'Annual_Cost'!$B$2:$B$1353,B4) | D4: =SUMIFS('Annual_Cost'!$R$2:$R$1353,'Annual_Cost'!$A$2:$A$1353,A4,'Annual_Cost'!$B$2:$B$1353,B4) | E4: =SUMIFS('Annual_Cost'!$S$2:$S$1353,'Annual_Cost'!$A$2:$A$1353,A4,'Annual_Cost'!$B$2:$B$1353,B4) | F4: =SUMIFS('Annual_Cost'!$Y$2:$Y$1353,'Annual_Cost'!$A$2:$A$1353,A4,'Annual_Cost'!$B$2:$B$1353,B4) | G4: =SUMIFS($E$2:E4,$A$2:A4,A4) | H4: =SUMIFS($F$2:F4,$A$2:A4,A4)
A5: I_CVD_PRIMARY | B5: 2028 | C5: =SUMIFS('Annual_Cost'!$Q$2:$Q$1353,'Annual_Cost'!$A$2:$A$1353,A5,'Annual_Cost'!$B$2:$B$1353,B5) | D5: =SUMIFS('Annual_Cost'!$R$2:$R$1353,'Annual_Cost'!$A$2:$A$1353,A5,'Annual_Cost'!$B$2:$B$1353,B5) | E5: =SUMIFS('Annual_Cost'!$S$2:$S$1353,'Annual_Cost'!$A$2:$A$1353,A5,'Annual_Cost'!$B$2:$B$1353,B5) | F5: =SUMIFS('Annual_Cost'!$Y$2:$Y$1353,'Annual_Cost'!$A$2:$A$1353,A5,'Annual_Cost'!$B$2:$B$1353,B5) | G5: =SUMIFS($E$2:E5,$A$2:A5,A5) | H5: =SUMIFS($F$2:F5,$A$2:A5,A5)
A6: I_CVD_PRIMARY | B6: 2029 | C6: =SUMIFS('Annual_Cost'!$Q$2:$Q$1353,'Annual_Cost'!$A$2:$A$1353,A6,'Annual_Cost'!$B$2:$B$1353,B6) | D6: =SUMIFS('Annual_Cost'!$R$2:$R$1353,'Annual_Cost'!$A$2:$A$1353,A6,'Annual_Cost'!$B$2:$B$1353,B6) | E6: =SUMIFS('Annual_Cost'!$S$2:$S$1353,'Annual_Cost'!$A$2:$A$1353,A6,'Annual_Cost'!$B$2:$B$1353,B6) | F6: =SUMIFS('Annual_Cost'!$Y$2:$Y$1353,'Annual_Cost'!$A$2:$A$1353,A6,'Annual_Cost'!$B$2:$B$1353,B6) | G6: =SUMIFS($E$2:E6,$A$2:A6,A6) | H6: =SUMIFS($F$2:F6,$A$2:A6,A6)
A7: I_CVD_PRIMARY | B7: 2030 | C7: =SUMIFS('Annual_Cost'!$Q$2:$Q$1353,'Annual_Cost'!$A$2:$A$1353,A7,'Annual_Cost'!$B$2:$B$1353,B7) | D7: =SUMIFS('Annual_Cost'!$R$2:$R$1353,'Annual_Cost'!$A$2:$A$1353,A7,'Annual_Cost'!$B$2:$B$1353,B7) | E7: =SUMIFS('Annual_Cost'!$S$2:$S$1353,'Annual_Cost'!$A$2:$A$1353,A7,'Annual_Cost'!$B$2:$B$1353,B7) | F7: =SUMIFS('Annual_Cost'!$Y$2:$Y$1353,'Annual_Cost'!$A$2:$A$1353,A7,'Annual_Cost'!$B$2:$B$1353,B7) | G7: =SUMIFS($E$2:E7,$A$2:A7,A7) | H7: =SUMIFS($F$2:F7,$A$2:A7,A7)
A8: I_CVD_PRIMARY | B8: 2031 | C8: =SUMIFS('Annual_Cost'!$Q$2:$Q$1353,'Annual_Cost'!$A$2:$A$1353,A8,'Annual_Cost'!$B$2:$B$1353,B8) | D8: =SUMIFS('Annual_Cost'!$R$2:$R$1353,'Annual_Cost'!$A$2:$A$1353,A8,'Annual_Cost'!$B$2:$B$1353,B8) | E8: =SUMIFS('Annual_Cost'!$S$2:$S$1353,'Annual_Cost'!$A$2:$A$1353,A8,'Annual_Cost'!$B$2:$B$1353,B8) | F8: =SUMIFS('Annual_Cost'!$Y$2:$Y$1353,'Annual_Cost'!$A$2:$A$1353,A8,'Annual_Cost'!$B$2:$B$1353,B8) | G8: =SUMIFS($E$2:E8,$A$2:A8,A8) | H8: =SUMIFS($F$2:F8,$A$2:A8,A8)
A9: I_CVD_PRIMARY | B9: 2032 | C9: =SUMIFS('Annual_Cost'!$Q$2:$Q$1353,'Annual_Cost'!$A$2:$A$1353,A9,'Annual_Cost'!$B$2:$B$1353,B9) | D9: =SUMIFS('Annual_Cost'!$R$2:$R$1353,'Annual_Cost'!$A$2:$A$1353,A9,'Annual_Cost'!$B$2:$B$1353,B9) | E9: =SUMIFS('Annual_Cost'!$S$2:$S$1353,'Annual_Cost'!$A$2:$A$1353,A9,'Annual_Cost'!$B$2:$B$1353,B9) | F9: =SUMIFS('Annual_Cost'!$Y$2:$Y$1353,'Annual_Cost'!$A$2:$A$1353,A9,'Annual_Cost'!$B$2:$B$1353,B9) | G9: =SUMIFS($E$2:E9,$A$2:A9,A9) | H9: =SUMIFS($F$2:F9,$A$2:A9,A9)
A10: I_CVD_PRIMARY | B10: 2033 | C10: =SUMIFS('Annual_Cost'!$Q$2:$Q$1353,'Annual_Cost'!$A$2:$A$1353,A10,'Annual_Cost'!$B$2:$B$1353,B10) | D10: =SUMIFS('Annual_Cost'!$R$2:$R$1353,'Annual_Cost'!$A$2:$A$1353,A10,'Annual_Cost'!$B$2:$B$1353,B10) | E10: =SUMIFS('Annual_Cost'!$S$2:$S$1353,'Annual_Cost'!$A$2:$A$1353,A10,'Annual_Cost'!$B$2:$B$1353,B10) | F10: =SUMIFS('Annual_Cost'!$Y$2:$Y$1353,'Annual_Cost'!$A$2:$A$1353,A10,'Annual_Cost'!$B$2:$B$1353,B10) | G10: =SUMIFS($E$2:E10,$A$2:A10,A10) | H10: =SUMIFS($F$2:F10,$A$2:A10,A10)
A11: I_CVD_PRIMARY | B11: 2034 | C11: =SUMIFS('Annual_Cost'!$Q$2:$Q$1353,'Annual_Cost'!$A$2:$A$1353,A11,'Annual_Cost'!$B$2:$B$1353,B11) | D11: =SUMIFS('Annual_Cost'!$R$2:$R$1353,'Annual_Cost'!$A$2:$A$1353,A11,'Annual_Cost'!$B$2:$B$1353,B11) | E11: =SUMIFS('Annual_Cost'!$S$2:$S$1353,'Annual_Cost'!$A$2:$A$1353,A11,'Annual_Cost'!$B$2:$B$1353,B11) | F11: =SUMIFS('Annual_Cost'!$Y$2:$Y$1353,'Annual_Cost'!$A$2:$A$1353,A11,'Annual_Cost'!$B$2:$B$1353,B11) | G11: =SUMIFS($E$2:E11,$A$2:A11,A11) | H11: =SUMIFS($F$2:F11,$A$2:A11,A11)
A12: I_CVD_PRIMARY | B12: 2035 | C12: =SUMIFS('Annual_Cost'!$Q$2:$Q$1353,'Annual_Cost'!$A$2:$A$1353,A12,'Annual_Cost'!$B$2:$B$1353,B12) | D12: =SUMIFS('Annual_Cost'!$R$2:$R$1353,'Annual_Cost'!$A$2:$A$1353,A12,'Annual_Cost'!$B$2:$B$1353,B12) | E12: =SUMIFS('Annual_Cost'!$S$2:$S$1353,'Annual_Cost'!$A$2:$A$1353,A12,'Annual_Cost'!$B$2:$B$1353,B12) | F12: =SUMIFS('Annual_Cost'!$Y$2:$Y$1353,'Annual_Cost'!$A$2:$A$1353,A12,'Annual_Cost'!$B$2:$B$1353,B12) | G12: =SUMIFS($E$2:E12,$A$2:A12,A12) | H12: =SUMIFS($F$2:F12,$A$2:A12,A12)
A13: I_CVD_PRIMARY | B13: 2036 | C13: =SUMIFS('Annual_Cost'!$Q$2:$Q$1353,'Annual_Cost'!$A$2:$A$1353,A13,'Annual_Cost'!$B$2:$B$1353,B13) | D13: =SUMIFS('Annual_Cost'!$R$2:$R$1353,'Annual_Cost'!$A$2:$A$1353,A13,'Annual_Cost'!$B$2:$B$1353,B13) | E13: =SUMIFS('Annual_Cost'!$S$2:$S$1353,'Annual_Cost'!$A$2:$A$1353,A13,'Annual_Cost'!$B$2:$B$1353,B13) | F13: =SUMIFS('Annual_Cost'!$Y$2:$Y$1353,'Annual_Cost'!$A$2:$A$1353,A13,'Annual_Cost'!$B$2:$B$1353,B13) | G13: =SUMIFS($E$2:E13,$A$2:A13,A13) | H13: =SUMIFS($F$2:F13,$A$2:A13,A13)
... A235: all | B235: 2050 | C235: =SUMIFS('Annual_Cost'!$Q$2:$Q$1353,'Annual_Cost'!$A$2:$A$1353,A235,'Annual_Cost'!$B$2:$B$1353,B235) | D235: =SUMIFS('Annual_Cost'!$R$2:$R$1353,'Annual_Cost'!$A$2:$A$1353,A235,'Annual_Cost'!$B$2:$B$1353,B235) | E235: =SUMIFS('Annual_Cost'!$S$2:$S$1353,'Annual_Cost'!$A$2:$A$1353,A235,'Annual_Cost'!$B$2:$B$1353,B235) | F235: =SUMIFS('Annual_Cost'!$Y$2:$Y$1353,'Annual_Cost'!$A$2:$A$1353,A235,'Annual_Cost'!$B$2:$B$1353,B235) | G235: =SUMIFS($E$2:E235,$A$2:A235,A235) | H235: =SUMIFS($F$2:F235,$A$2:A235,A235)

Sheet Cost_Effectiveness
A1: scenario | B1: scenario_label | C1: deaths_averted | D1: cases_averted | E1: incremental_cost | F1: disc_incremental_cost | G1: cost_per_death_averted | H1: dominance | I1: reconciliation_status
A2: all | B2: All selected interventions (combined) | C2: =SUMIFS('Annual_Mortality'!$H$2:$H$1821,'Annual_Mortality'!$A$2:$A$1821,A2) | D2: =SUMIFS('Annual_Mortality'!$J$2:$J$1821,'Annual_Mortality'!$A$2:$A$1821,A2) | E2: =SUMIFS('Budget_Impact'!$E$2:$E$235,'Budget_Impact'!$A$2:$A$235,A2) | F2: =SUMIFS('Budget_Impact'!$F$2:$F$235,'Budget_Impact'!$A$2:$A$235,A2) | G2: =IF(C2>0,F2/C2,"") | H2: =IF(AND(C2>0,F2<0),"Dominant (more health, lower cost)",IF(AND(C2<=0,F2>0),"Dominated (less/no health, higher cost)",IF(AND(C2<=0,F2<=0),"No deaths averted; ratio not defined","USD per death averted"))) | I2: =IF(AND(ABS(F2-SUMIFS('Budget_Impact'!$F$2:$F$235,'Budget_Impact'!$A$2:$A$235,A2))<='Calculation_Assumptions'!$B$11,ABS(C2-SUMIFS('Annual_Mortality'!$H$2:$H$1821,'Annual_Mortality'!$A$2:$A$1821,A2))<='Calculation_Assumptions'!$B$11),"consistent","mismatch")
A3: I_CVD_PRIMARY | B3: Primary prevention of CVD | C3: =SUMIFS('Annual_Mortality'!$H$2:$H$1821,'Annual_Mortality'!$A$2:$A$1821,A3) | D3: =SUMIFS('Annual_Mortality'!$J$2:$J$1821,'Annual_Mortality'!$A$2:$A$1821,A3) | E3: =SUMIFS('Budget_Impact'!$E$2:$E$235,'Budget_Impact'!$A$2:$A$235,A3) | F3: =SUMIFS('Budget_Impact'!$F$2:$F$235,'Budget_Impact'!$A$2:$A$235,A3) | G3: =IF(C3>0,F3/C3,"") | H3: =IF(AND(C3>0,F3<0),"Dominant (more health, lower cost)",IF(AND(C3<=0,F3>0),"Dominated (less/no health, higher cost)",IF(AND(C3<=0,F3<=0),"No deaths averted; ratio not defined","USD per death averted"))) | I3: =IF(AND(ABS(F3-SUMIFS('Budget_Impact'!$F$2:$F$235,'Budget_Impact'!$A$2:$A$235,A3))<='Calculation_Assumptions'!$B$11,ABS(C3-SUMIFS('Annual_Mortality'!$H$2:$H$1821,'Annual_Mortality'!$A$2:$A$1821,A3))<='Calculation_Assumptions'!$B$11),"consistent","mismatch")
A4: I_T2D_TREATMENT | B4: Longitudinal treatment of type 2 diabetes | C4: =SUMIFS('Annual_Mortality'!$H$2:$H$1821,'Annual_Mortality'!$A$2:$A$1821,A4) | D4: =SUMIFS('Annual_Mortality'!$J$2:$J$1821,'Annual_Mortality'!$A$2:$A$1821,A4) | E4: =SUMIFS('Budget_Impact'!$E$2:$E$235,'Budget_Impact'!$A$2:$A$235,A4) | F4: =SUMIFS('Budget_Impact'!$F$2:$F$235,'Budget_Impact'!$A$2:$A$235,A4) | G4: =IF(C4>0,F4/C4,"") | H4: =IF(AND(C4>0,F4<0),"Dominant (more health, lower cost)",IF(AND(C4<=0,F4>0),"Dominated (less/no health, higher cost)",IF(AND(C4<=0,F4<=0),"No deaths averted; ratio not defined","USD per death averted"))) | I4: =IF(AND(ABS(F4-SUMIFS('Budget_Impact'!$F$2:$F$235,'Budget_Impact'!$A$2:$A$235,A4))<='Calculation_Assumptions'!$B$11,ABS(C4-SUMIFS('Annual_Mortality'!$H$2:$H$1821,'Annual_Mortality'!$A$2:$A$1821,A4))<='Calculation_Assumptions'!$B$11),"consistent","mismatch")
A5: I_IHD_SECONDARY | B5: Secondary prevention of ischemic heart disease | C5: =SUMIFS('Annual_Mortality'!$H$2:$H$1821,'Annual_Mortality'!$A$2:$A$1821,A5) | D5: =SUMIFS('Annual_Mortality'!$J$2:$J$1821,'Annual_Mortality'!$A$2:$A$1821,A5) | E5: =SUMIFS('Budget_Impact'!$E$2:$E$235,'Budget_Impact'!$A$2:$A$235,A5) | F5: =SUMIFS('Budget_Impact'!$F$2:$F$235,'Budget_Impact'!$A$2:$A$235,A5) | G5: =IF(C5>0,F5/C5,"") | H5: =IF(AND(C5>0,F5<0),"Dominant (more health, lower cost)",IF(AND(C5<=0,F5>0),"Dominated (less/no health, higher cost)",IF(AND(C5<=0,F5<=0),"No deaths averted; ratio not defined","USD per death averted"))) | I5: =IF(AND(ABS(F5-SUMIFS('Budget_Impact'!$F$2:$F$235,'Budget_Impact'!$A$2:$A$235,A5))<='Calculation_Assumptions'!$B$11,ABS(C5-SUMIFS('Annual_Mortality'!$H$2:$H$1821,'Annual_Mortality'!$A$2:$A$1821,A5))<='Calculation_Assumptions'!$B$11),"consistent","mismatch")
A6: I_HF_CHRONIC | B6: Chronic heart-failure management | C6: =SUMIFS('Annual_Mortality'!$H$2:$H$1821,'Annual_Mortality'!$A$2:$A$1821,A6) | D6: =SUMIFS('Annual_Mortality'!$J$2:$J$1821,'Annual_Mortality'!$A$2:$A$1821,A6) | E6: =SUMIFS('Budget_Impact'!$E$2:$E$235,'Budget_Impact'!$A$2:$A$235,A6) | F6: =SUMIFS('Budget_Impact'!$F$2:$F$235,'Budget_Impact'!$A$2:$A$235,A6) | G6: =IF(C6>0,F6/C6,"") | H6: =IF(AND(C6>0,F6<0),"Dominant (more health, lower cost)",IF(AND(C6<=0,F6>0),"Dominated (less/no health, higher cost)",IF(AND(C6<=0,F6<=0),"No deaths averted; ratio not defined","USD per death averted"))) | I6: =IF(AND(ABS(F6-SUMIFS('Budget_Impact'!$F$2:$F$235,'Budget_Impact'!$A$2:$A$235,A6))<='Calculation_Assumptions'!$B$11,ABS(C6-SUMIFS('Annual_Mortality'!$H$2:$H$1821,'Annual_Mortality'!$A$2:$A$1821,A6))<='Calculation_Assumptions'!$B$11),"consistent","mismatch")
A7: I_HF_ACUTE | B7: Acute heart-failure management | C7: =SUMIFS('Annual_Mortality'!$H$2:$H$1821,'Annual_Mortality'!$A$2:$A$1821,A7) | D7: =SUMIFS('Annual_Mortality'!$J$2:$J$1821,'Annual_Mortality'!$A$2:$A$1821,A7) | E7: =SUMIFS('Budget_Impact'!$E$2:$E$235,'Budget_Impact'!$A$2:$A$235,A7) | F7: =SUMIFS('Budget_Impact'!$F$2:$F$235,'Budget_Impact'!$A$2:$A$235,A7) | G7: =IF(C7>0,F7/C7,"") | H7: =IF(AND(C7>0,F7<0),"Dominant (more health, lower cost)",IF(AND(C7<=0,F7>0),"Dominated (less/no health, higher cost)",IF(AND(C7<=0,F7<=0),"No deaths averted; ratio not defined","USD per death averted"))) | I7: =IF(AND(ABS(F7-SUMIFS('Budget_Impact'!$F$2:$F$235,'Budget_Impact'!$A$2:$A$235,A7))<='Calculation_Assumptions'!$B$11,ABS(C7-SUMIFS('Annual_Mortality'!$H$2:$H$1821,'Annual_Mortality'!$A$2:$A$1821,A7))<='Calculation_Assumptions'!$B$11),"consistent","mismatch")
A8: I_STROKE_SECONDARY | B8: Secondary prevention of stroke | C8: =SUMIFS('Annual_Mortality'!$H$2:$H$1821,'Annual_Mortality'!$A$2:$A$1821,A8) | D8: =SUMIFS('Annual_Mortality'!$J$2:$J$1821,'Annual_Mortality'!$A$2:$A$1821,A8) | E8: =SUMIFS('Budget_Impact'!$E$2:$E$235,'Budget_Impact'!$A$2:$A$235,A8) | F8: =SUMIFS('Budget_Impact'!$F$2:$F$235,'Budget_Impact'!$A$2:$A$235,A8) | G8: =IF(C8>0,F8/C8,"") | H8: =IF(AND(C8>0,F8<0),"Dominant (more health, lower cost)",IF(AND(C8<=0,F8>0),"Dominated (less/no health, higher cost)",IF(AND(C8<=0,F8<=0),"No deaths averted; ratio not defined","USD per death averted"))) | I8: =IF(AND(ABS(F8-SUMIFS('Budget_Impact'!$F$2:$F$235,'Budget_Impact'!$A$2:$A$235,A8))<='Calculation_Assumptions'!$B$11,ABS(C8-SUMIFS('Annual_Mortality'!$H$2:$H$1821,'Annual_Mortality'!$A$2:$A$1821,A8))<='Calculation_Assumptions'!$B$11),"consistent","mismatch")
A9: I_RHD_SECONDARY | B9: RHD secondary prevention | C9: =SUMIFS('Annual_Mortality'!$H$2:$H$1821,'Annual_Mortality'!$A$2:$A$1821,A9) | D9: =SUMIFS('Annual_Mortality'!$J$2:$J$1821,'Annual_Mortality'!$A$2:$A$1821,A9) | E9: =SUMIFS('Budget_Impact'!$E$2:$E$235,'Budget_Impact'!$A$2:$A$235,A9) | F9: =SUMIFS('Budget_Impact'!$F$2:$F$235,'Budget_Impact'!$A$2:$A$235,A9) | G9: =IF(C9>0,F9/C9,"") | H9: =IF(AND(C9>0,F9<0),"Dominant (more health, lower cost)",IF(AND(C9<=0,F9>0),"Dominated (less/no health, higher cost)",IF(AND(C9<=0,F9<=0),"No deaths averted; ratio not defined","USD per death averted"))) | I9: =IF(AND(ABS(F9-SUMIFS('Budget_Impact'!$F$2:$F$235,'Budget_Impact'!$A$2:$A$235,A9))<='Calculation_Assumptions'!$B$11,ABS(C9-SUMIFS('Annual_Mortality'!$H$2:$H$1821,'Annual_Mortality'!$A$2:$A$1821,A9))<='Calculation_Assumptions'!$B$11),"consistent","mismatch")
A10: I_RHD_SURGERY | B10: RHD cardiac surgery | C10: =SUMIFS('Annual_Mortality'!$H$2:$H$1821,'Annual_Mortality'!$A$2:$A$1821,A10) | D10: =SUMIFS('Annual_Mortality'!$J$2:$J$1821,'Annual_Mortality'!$A$2:$A$1821,A10) | E10: =SUMIFS('Budget_Impact'!$E$2:$E$235,'Budget_Impact'!$A$2:$A$235,A10) | F10: =SUMIFS('Budget_Impact'!$F$2:$F$235,'Budget_Impact'!$A$2:$A$235,A10) | G10: =IF(C10>0,F10/C10,"") | H10: =IF(AND(C10>0,F10<0),"Dominant (more health, lower cost)",IF(AND(C10<=0,F10>0),"Dominated (less/no health, higher cost)",IF(AND(C10<=0,F10<=0),"No deaths averted; ratio not defined","USD per death averted"))) | I10: =IF(AND(ABS(F10-SUMIFS('Budget_Impact'!$F$2:$F$235,'Budget_Impact'!$A$2:$A$235,A10))<='Calculation_Assumptions'!$B$11,ABS(C10-SUMIFS('Annual_Mortality'!$H$2:$H$1821,'Annual_Mortality'!$A$2:$A$1821,A10))<='Calculation_Assumptions'!$B$11),"consistent","mismatch")

Sheet Economic_Value
A1: note
A2: Model 08 output (08_vsl_results.rds) not found; economic value omitted.

Sheet QA_Checks
A1: check | B1: expected | C1: actual | D1: status | E1: note
A2: Intervention-cause key uniqueness | B2: 0 | C2: =COUNTIF('Selected_Interventions'!$U$2:$U$18,">1") | D2: =IF(C2=0,"PASS","FAIL") | E2: Each selected link key appears once
A3: Workbook FAIL-level issues | B3: 0 | C3: =COUNTIF('Input_Diagnostic'!$E$2:$E$3,"FAIL") | D3: =IF(C3=0,"PASS","REVIEW") | E3: Blocked links/scenarios excluded (see Selected_Interventions / Input_Diagnostic)
A4: Workbook REVIEW-level issues | B4: 0 | C4: =COUNTIF('Input_Diagnostic'!$E$2:$E$3,"REVIEW") | D4: =IF(C4=0,"PASS","REVIEW") | E4: Flagged but usable (e.g. cost not Indonesia-adjusted, missing optional component)
A5: Every scenario paired to baseline | B5: TRUE | C5: =COUNTBLANK('Annual_Mortality'!$G$2:$G$1821)=0 | D5: =IF(C5=TRUE,"PASS","FAIL") | E5: Deaths averted = baseline - scenario at matched location/year/cause
A6: No impossible negative states | B6: 0 | C6: ='Calculation_Assumptions'!$B$16 | D6: =IF(C6=0,"PASS","FAIL") | E6: well/sick/new_cases/cause_deaths/population >= 0
A7: Stock/flow identity pop = well + sick + all-cause deaths | B7: <= limit | C7: ='Calculation_Assumptions'!$B$14 | D7: =IF(C7<='Calculation_Assumptions'!$B$12,"PASS","REVIEW") | E7: Per cause row; small residual from 95+ pooling / rounding
A8: Background mortality constant across cause (not duplicated) | B8: 1 | C8: ='Calculation_Assumptions'!$B$15 | D8: =IF(C8=1,"PASS","FAIL") | E8: all.mx taken once per stratum in the R Background sheet
A9: Cost reconciliation (components -> budget impact) | B9: <= tol | C9: =ABS(SUM('Budget_Impact'!$D$2:$D$235)-SUM('Annual_Cost'!$R$2:$R$1353))+ABS(SUM('Budget_Impact'!$C$2:$C$235)-SUM('Annual_Cost'!$Q$2:$Q$1353)) | D9: =IF(C9<='Calculation_Assumptions'!$B$11,"PASS","FAIL") | E9: Excel component rows sum to Excel annual totals within tolerance
A10: Shared cost counted once per stratum/year | B10: 0 | C10: =COUNTIF('Annual_Cost'!$AH$2:$AH$1353,">1") | D10: =IF(C10=0,"PASS","FAIL") | E10: shared-count-once components appear once per scenario-year
A11: CEA reconciliation (detail -> summary ratio) | B11: consistent | C11: =IF(COUNTIF('Cost_Effectiveness'!$I$2:$I$10,"mismatch")=0,"consistent","mismatch") | D11: =IF(C11="consistent","PASS","FAIL") | E11: Every Cost_Effectiveness row's internal reconciliation is consistent
A12: Excel vs R: deaths averted (anchor scenario) | B12: match R | C12: =INDEX('Cost_Effectiveness'!$C$2:$C$10,MATCH('Calculation_Assumptions'!$B$20,'Cost_Effectiveness'!$A$2:$A$10,0)) | D12: =IF(ABS(C12-'Calculation_Assumptions'!$B$17)<=ABS('Calculation_Assumptions'!$B$17)*0.000001+0.5,"PASS","FAIL") | E12: Excel CEA deaths averted reconciles to the R engine value
A13: Excel vs R: discounted incremental cost (anchor scenario) | B13: match R | C13: =INDEX('Cost_Effectiveness'!$F$2:$F$10,MATCH('Calculation_Assumptions'!$B$20,'Cost_Effectiveness'!$A$2:$A$10,0)) | D13: =IF(ABS(C13-'Calculation_Assumptions'!$B$18)<=ABS('Calculation_Assumptions'!$B$18)*0.000001+1,"PASS","FAIL") | E13: Excel CEA discounted incremental cost reconciles to the R engine value
A14: Excel vs R: cost per death averted (anchor scenario) | B14: match R | C14: =INDEX('Cost_Effectiveness'!$G$2:$G$10,MATCH('Calculation_Assumptions'!$B$20,'Cost_Effectiveness'!$A$2:$A$10,0)) | D14: =IF(ABS(C14-'Calculation_Assumptions'!$B$19)<=ABS('Calculation_Assumptions'!$B$19)*0.000001+1,"PASS","FAIL") | E14: Excel CEA USD per death averted reconciles to the R engine value

Sheet Input_Diagnostic
A1: scope | B1: item_key | C1: field | D1: problem | E1: severity
A2: cost | B2: COST_T2D_TREATMENT | C2: indonesia_adjusted_flag | D2: cost not Indonesia-adjusted (flagged; not treated as ready) | E2: REVIEW
A3: cost | B3: COST_T2D_TREATMENT | C3: price_year | D3: cost price year != reporting price year (2023) | E3: REVIEW

Sheet Methods_and_Sources
A1: method_id | B1: concept | C1: formula_or_rule | D1: source
A2: M01 | B2: Incremental coverage | C2: delta_cov(t) = coverage(t) - baseline_coverage | D2: FairChoices_Methods sheet + https://fairchoices.w.uib.no/documentation/fairchoices-methods/
A3: M02 | B3: FAIR adjusted effect | C3: e_adj(t) = effect_value * delta_cov(t) / (1 - effect_value * baseline_coverage) | D3: FairChoices_Methods sheet + https://fairchoices.w.uib.no/documentation/fairchoices-methods/
A4: M03 | B4: Affected fraction | C4: transition_effect(t) = e_adj(t) * affected_fraction | D4: FairChoices_Methods sheet + https://fairchoices.w.uib.no/documentation/fairchoices-methods/
A5: M04 | B5: Adjusted transition | C5: p_scenario(t) = p_baseline(t) * (1 - transition_effect(t)); prevention->incidence (IR/eff_ir), management->case fatality (CF/eff_cf) | D5: FairChoices_Methods sheet + https://fairchoices.w.uib.no/documentation/fairchoices-methods/
A6: M05 | B6: HF/severe mapping | C6: workbook sick_hf / sick_severe collapse onto the single 'sick' state via affected_fraction; NO new Markov states | D6: Model 04 translation table (Indonesia Markov adaptation)
A7: M06 | B7: Annual component cost | C7: annual_cost = population_in_need * coverage(t) * frequency_per_year * unit_cost_usd | D7: FairChoices_Methods sheet / input workbook
A8: M07 | B8: Shared cost | C8: shared-count-once components counted once per intervention & eligible stratum, not once per affected cause | D8: FairChoices_Methods sheet / input workbook
A9: M08 | B9: Discounting | C9: discount_factor(t) = 1 / (1 + cost_discount_rate)^(t - analysis_start_year); costs discounted, death counts undiscounted | D9: FairChoices_Methods sheet / input workbook
A10: M09 | B10: Budget impact | C10: incremental = scenario_cost - baseline_cost (undiscounted headline; discounted reported separately) | D10: FairChoices_Methods sheet / input workbook
A11: M10 | B11: Cost-effectiveness | C11: USD per death averted = cumulative discounted incremental cost / cumulative deaths averted | D11: FairChoices_Methods sheet / input workbook
A12: M11 | B12: FAIR unit-cost markups | C12: not re-applied where indonesia_adjusted_flag = 1 (supplied adjusted costs already include them) | D12: FairChoices_Methods M08
... A15: M14 | B15: Economic value boundary | C15: Model 08 monetary value columns are R source values; only the cost link, supplementary BCR and net benefit are recalculated here. | D15: Model 08 / Model 09

Sheet Calculation_Assumptions
A1: parameter_id | B1: value | C1: unit | D1: role | E1: description | F1: source
A2: analysis_start_year | B2: 2025 | C2: year | D2: formula control | E2: First model and discount year | F2: indonesia_model_inputs.xlsx / Model 09
A3: analysis_end_year | B3: 2050 | C3: year | D3: formula control | E3: Last model year | F3: indonesia_model_inputs.xlsx / Model 09
A4: baseline_scenario_id | B4: baseline | C4: scenario id | D4: formula control | E4: Comparator used for health and cost calculations | F4: Model 04 / Model 09
A5: cost_discount_rate | B5: 0.03 | C5: proportion/year | D5: formula control | E5: Annual discount rate applied to costs only | F5: indonesia_model_inputs.xlsx / Model 09
A6: cost_price_year | B6: 2023 | C6: USD year | D6: metadata | E6: Reporting price year | F6: indonesia_model_inputs.xlsx
A7: currency | B7: USD | C7: currency | D7: metadata | E7: Workbook reporting currency | F7: indonesia_model_inputs.xlsx
A8: economic_perspective | B8: health_system | C8: text | D8: metadata | E8: Economic evaluation perspective | F8: indonesia_model_inputs.xlsx
A9: scale_up_shape | B9: linear | C9: text | D9: formula control | E9: Coverage increases linearly from start to target year | F9: indonesia_model_inputs.xlsx
A10: downstream_cost_offsets | B10: 0 | C10: 0/1 flag | D10: scope | E10: Downstream disease-cost offsets excluded at this stage | F10: indonesia_model_inputs.xlsx
A11: formula_tolerance | B11: 0.001 | C11: USD/count | D11: QA control | E11: Absolute reconciliation tolerance (internal Excel checks) | F11: Workbook QA rule
A12: stock_flow_residual_limit | B12: 1000 | C12: persons | D12: QA control | E12: Review threshold used by the R stock/flow check | F12: Model 09
A13: trace_precision | B13: 2 | C13: decimal places | D13: audit note | E13: Exported model traces are rounded; R quantity helpers keep full precision | F13: Model 09 export rule
A14: r_stock_flow_max_residual | B14: 108.16 | C14: persons | D14: R QA source | E14: Maximum stock/flow residual computed in R before export | F14: Model 09 current run
A15: r_background_distinct_count | B15: 3 | C15: count | D15: R QA source | E15: Max distinct all-cause mortality values across causes (R) | F15: Model 09 current run
A16: r_negative_state_count | B16: 0 | C16: count | D16: R QA source | E16: Count of impossible negative state/flow values (R) | F16: Model 09 current run
A17: r_deaths_averted_anchor | B17: 2560798.2 | C17: deaths | D17: R reconciliation source | E17: R engine deaths averted for the anchor scenario | F17: Model 09 current run (R CEA)
A18: r_disc_incremental_cost_anchor | B18: 8.4180027e+10 | C18: USD | D18: R reconciliation source | E18: R engine discounted incremental cost for the anchor scenario | F18: Model 09 current run (R CEA)
A19: r_cost_per_death_anchor | B19: 32872.574 | C19: USD/death | D19: R reconciliation source | E19: R engine USD per death averted for the anchor scenario | F19: Model 09 current run (R CEA)
A20: qa_anchor_scenario | B20: all | C20: scenario id | D20: R reconciliation source | E20: Scenario used for the Excel-vs-R reconciliation checks | F20: Model 09 current run (R CEA)

Sheet Calculation_Map
A1: output_sheet | B1: formula_columns | C1: depends_on | D1: calculation | E1: source_role
A2: Selected_Interventions | B2: P, U:V | C2: selected health links (J:M) | D2: Adjusted effect at target; key uniqueness/status | E2: Workbook formula
A3: Cost_Components | B3: S:V, X | C3: Selected_Interventions | D3: Coverage link (INDEX/MATCH) and cost-readiness rule | E3: Workbook formula
A4: Annual_Mortality | B4: H, J | C4: R aggregates E:G, I | D4: Deaths averted and cases averted | E4: Workbook formula
A5: Annual_Cost | B5: J:AE, AH | C5: Cost_Components; Calculation_Assumptions; R quantity AF:AG | D5: Coverage path, PIN, annual + discounted cost, shared-cost QA | E5: Workbook formula
A6: Annual_Cost | B6: AF:AG | C6: full-precision Model 06 output | D6: Scenario/baseline quantity before the PIN fraction | E6: R value exposed for audit
A7: Budget_Impact | B7: C:H | C7: Annual_Cost | D7: Annual and cumulative cost by scenario | E7: Workbook formula
A8: Cost_Effectiveness | B8: C:I | C8: Annual_Mortality; Budget_Impact; Calculation_Assumptions | D8: Cumulative health, cost, cost/death, dominance, reconciliation | E8: Workbook formula
A9: Economic_Value | B9: M:Q | C9: Cost_Effectiveness; Model 08 values B:L | D9: Cost link, supplementary benefit-cost ratio and net benefit | E9: Workbook formula
A10: QA_Checks | B10: C:D | C10: calculation + diagnostic sheets | D10: Invariant recomputation and Excel-vs-R reconciliation status | E10: Workbook formula
A11: Run_Metadata | B11: B8:B16 (subset) | C11: Calculation_Assumptions | D11: Metadata pulled from the assumptions controls | E11: Workbook formula
A12: Companion R workbook | B12: none | C12: Model 06 / Model 09 | D12: Detailed Model_State_Trace and Background_Mortality | E12: R source data
