Workbook

Sheet README
A1: Indonesia NCD model - public-health policy inputs
A3: Individual intervention inputs with nested tobacco and salt packages; TFA RR base case with optional PAF sensitivity
A5: Readiness | C5: Executable interventions | E5: Risk exposures | G5: Intervention-cause links
A6: =IF(COUNTIF(QA_Checks!$E$2:$E$25,"FAIL")=0,"READY","REVIEW REQUIRED") -> REVIEW REQUIRED | C6: =COUNTA(Exposure_Targets!$B$2:$B$13) -> 12 | E6: =COUNTA(Dictionaries!$F$2:$F$6) -> 5 | G6: =COUNTA(Intervention_Cause_Map!$A$2:$A$62) -> 61
A9: How to use the workbook
A10: 1 | B10: Policy_Levers contains separate fiscal baseline/target tax levels and regulatory none/partial/full fields; derived gaps and reductions are formulas.
A11: 2 | B11: Scenario_Hierarchy preserves I_PH_TOBACCO_POLICY and I_PH_SALT_POLICY while every component has its own intervention_id.
A12: 3 | B12: Exposure, cause links, effects and costs trace each intervention into modeling and cost effectiveness.
A13: 4 | B13: Run parent bundles jointly in the integrated model; do not add standalone child cases or deaths.
A14: 5 | B14: TFA defaults to RR: RR per 1 percentage-point energy = sqrt(1.21). Change Assumptions.tfa_effect_method only for optional PAF sensitivity.
A15: 6 | B15: Tobacco and salt child costs use provisional equal allocations that preserve package totals.
A17: Key interpretation and review items
A18: Resolved | B18: TFA RR no longer requires a PAF
A19: Resolved | B19: Tobacco and salt components have independent effect and cost keys
A20: Resolved | B20: Taxes use baseline-to-target changes and elasticity
A21: Resolved | B21: Regulations use none/partial/full with formula-derived effects
A22: Review | B22: Source costs require Indonesia and price-year adjustment
A23: Review | B23: Replace equal child cost shares when component-specific costs are available
A24: Caution | B24: Parent health outcomes require joint scenario runs
A25: New / Caution | B25: Tobacco CVD now includes uniquely keyed sick-to-dead proxy rows with Jha age-sex piecewise base timing. The exploratory SSB/T2DM mortality row remains disabled, and the attached R code still requires transition and lag-model support.

Sheet Assumptions
A1: parameter_id | B1: value | C1: unit | D1: base_case | E1: lower_bound | F1: upper_bound | G1: description | H1: source
A2: analysis_start_year | B2: 2025 | C2: year | D2: 2025 | E2: 2025 | F2: 2026 | G2: First modeled year | H2: Indonesia model scope
A3: analysis_end_year | B3: 2050 | C3: year | D3: 2050 | E3: 2030 | F3: 2050 | G3: Last modeled year | H3: Indonesia model scope
A4: policy_start_year | B4: 2026 | C4: year | D4: 2026 | E4: 2025 | F4: 2030 | G4: First implementation year | H4: Working scenario
A5: exposure_target_year | B5: 2030 | C5: year | D5: 2030 | E5: 2028 | F5: 2050 | G5: Year full exposure reduction is reached | H5: Working scenario
A6: policy_cost_ramp_years | B6: 3 | C6: years | D6: 3 | E6: 1 | F6: 5 | G6: Years to full policy implementation cost | H6: NCD Countdown supplement p 34
A7: cost_discount_rate | B7: 0.03 | C7: proportion/year | D7: 0.03 | E7: 0 | F7: 0.05 | G7: Annual discount rate for costs | H7: Match clinical workbook
A8: health_discount_rate | B8: 0.03 | C8: proportion/year | D8: 0.03 | E8: 0 | F8: 0.05 | G8: Annual discount rate for health outcomes | H8: Match clinical workbook
A9: reporting_price_year | B9: 2023 | C9: USD year | D9: 2023 | E9: 2020 | F9: 2024 | G9: Target reporting price year | H9: Match clinical workbook
A10: source_cost_price_year | B10: 2017 | C10: USD year | D10: 2017 | E10: 2017 | F10: 2017 | G10: Price year in source cost file | H10: PINandCosts0625(1).csv
A11: currency | B11: USD | C11: currency | D11: USD | E11: USD | F11: USD | G11: Reporting currency | H11: Working assumption
A12: scale_up_shape | B12: linear | C12: text | D12: linear | E12: linear | F12: linear | G12: Full reduction is phased in evenly | H12: NCD Countdown supplement p 34
A13: economic_perspective | B13: health_system | C13: text | D13: health_system | E13: health_system | F13: societal | G13: Economic evaluation perspective | H13: NCD Countdown
A14: tobacco_cvd_lag_rate | B14: 0.0616 | C14: annual fraction | D14: 0.0616 | E14: 0.04 | F14: 0.08 | G14: Sensitivity-only normalized exponential annual fraction; base case uses Jha age-sex piecewise scalars | H14: Cho et al. 2024; user-specified sensitivity
A15: sodium_exposure_floor | B15: 3 | C15: g sodium/day | D15: 3 | E15: 3 | F15: 3 | G15: No additional benefit below this exposure | H15: NCD Countdown p 33
A16: tfa_target_exposure | B16: 0.00317 | C16: % energy from industrial TFA | D16: 0 | E16: 0 | F16: 0.5 | G16: Target under full industrial-TFA elimination | H16: WHO REPLACE; editable
A17: constant_marginal_policy_cost | B17: 1 | C17: 0/1 flag | D17: 1 | E17: 0 | F17: 1 | G17: Policy cost proportional to implementation | H17: NCD Countdown limitation
A18: grams_pure_alcohol_per_litre | B18: 789 | C18: g/L | D18: 789 | E18: 789 | F18: 789 | G18: Alcohol dose-response conversion | H18: Standard conversion
A19: weeks_per_year | B19: 52 | C19: weeks/year | D19: 52 | E19: 52 | F19: 52.1775 | G19: Alcohol dose-response conversion | H19: Model convention
A20: ssb_tax_price_increase | B20: 0.2 | C20: relative price change | D20: 0.2 | E20: 0.1 | F20: 0.5 | G20: Target SSB retail-price increase | H20: https://www.who.int/publications/i/item/9789240091016/
A21: ssb_price_elasticity_indonesia | B21: -0.875 | C21: own-price elasticity | D21: -0.875 | E21: -0.93 | F21: -0.715 | G21: 20% price increase reduces mean demand 17.5% | H21: https://doi.org/10.1371/journal.pone.0293913
A22: ssb_tax_pass_through_global | B22: 0.82 | C22: proportion | D22: 0.82 | E22: 0.66 | F22: 0.98 | G22: Sensitivity parameter | H22: https://doi.org/10.1001/jamanetworkopen.2022.15276
A23: ssb_price_elasticity_global | B23: -1.59 | C23: own-price elasticity | D23: -1.59 | E23: -2.11 | F23: -1.08 | G23: Sensitivity parameter | H23: https://doi.org/10.1001/jamanetworkopen.2022.15276
A24: regulatory_none_score | B24: 0 | C24: implementation score | D24: 0 | E24: 0 | F24: 0 | G24: Numeric value for none | H24: User-requested convention
A25: regulatory_partial_score | B25: 0.5 | C25: implementation score | D25: 0.5 | E25: 0.5 | F25: 0.5 | G25: Partial to full applies half effect | H25: User-requested convention
A26: regulatory_full_score | B26: 1 | C26: implementation score | D26: 1 | E26: 1 | F26: 1 | G26: Numeric value for full | H26: User-requested convention
A27: tfa_effect_method | B27: RR | C27: RR/PAF switch | D27: RR | E27: RR | F27: PAF | G27: RR is base case; PAF is optional sensitivity | H27: User request
A28: tfa_optional_ihd_paf | C28: proportion | E28: 0 | F28: 1 | G28: Used only when TFA method is PAF | H28: Optional user input
A29: tobacco_cvd_lag_model_base | B29: jha_piecewise_shared_scalar | C29: text | D29: jha_piecewise_shared_scalar | E29: jha_piecewise_shared_scalar | F29: jha_piecewise_shared_scalar | G29: Base timing model for tobacco-CVD incidence and mortality | H29: https://doi.org/10.1056/EVIDoa2300272
A30: tobacco_cvd_lag_model_sensitivity | B30: normalized_exponential_lag | C30: text | D30: normalized_exponential_lag | E30: normalized_exponential_lag | F30: normalized_exponential_lag | G30: Sensitivity timing model; normalized to full effect at year 10 | H30: User-specified sensitivity
A31: tobacco_cvd_full_effect_year | B31: 10 | C31: years since cessation | D31: 10 | E31: 10 | F31: 10 | G31: Year at which the normalized exponential sensitivity reaches full effect | H31: Model convention
A32: tobacco_vascular_mortality_rr_male | B32: 2.9 | C32: HR current vs never smoker | D32: 2.9 | E32: 2.9 | F32: 2.9 | G32: Male vascular-mortality hazard ratio | H32: https://doi.org/10.1056/EVIDoa2300272
A33: tobacco_vascular_mortality_rr_female | B33: 3.1 | C33: HR current vs never smoker | D33: 3.1 | E33: 3.1 | F33: 3.1 | G33: Female vascular-mortality hazard ratio | H33: https://doi.org/10.1056/EVIDoa2300272
A34: tobacco_vascular_mortality_rr_pooled | B34: =AVERAGE(B32:B33) -> 3 | C34: HR current vs never smoker | D34: 3 | E34: 2.9 | F34: 3.1 | G34: Backward-compatible pooled value; R should use sex-specific values | H34: Average of Jha male and female HRs
A35: tobacco_vascular_erd_ge10_pooled | B35: 0.90125 | C35: proportion | D35: 0.90125 | E35: 0.90125 | F35: 0.90125 | G35: Mean age-sex ERD at 10+ years; used only for the illustrative pooled workbook formula | H35: Derived from Cho et al. 2024 Figure 2
A36: tobacco_age80_scalar_extrapolation | B36: use_age_60_79 | C36: text | D36: use_age_60_79 | E36: use_age_60_79 | F36: use_age_60_79 | G36: Apply 60-79 Jha scalars to ages 80+ | H36: Conservative extrapolation
A37: transition_probability_rr_method | B37: 1-(1-p0)^RR | C37: text | D37: 1-(1-p0)^RR | E37: 1-(1-p0)^RR | F37: 1-(1-p0)^RR | G37: Convert rate ratios to annual Markov probabilities through the continuous-rate scale | H37: Standard rate-to-probability conversion
A38: bca_base_year | B38: 2025 | C38: year | D38: 2025 | E38: 2025 | F38: 2026 | G38: Base year to which BCA benefits and costs are both discounted (single shared base year) | H38: Robinson et al. 2019 Reference Case Guidelines for BCA in Global Health & Development (CHDS/Harvard); = analysis_start_year
A39: bca_discount_rate_primary | B39: 0.03 | C39: proportion/year | D39: 0.03 | E39: 0.03 | F39: 0.05 | G39: Primary real discount rate applied to BOTH benefits and costs in the BCA | H39: Robinson et al. 2019 Reference Case Guidelines for BCA in Global Health & Development (CHDS/Harvard); context-specific primary rate
A40: bca_discount_rate_sensitivity_3pct | B40: 0.03 | C40: proportion/year | D40: 0.03 | E40: 0.03 | F40: 0.03 | G40: Standardized sensitivity discount rate (3%) | H40: Robinson et al. 2019 Reference Case Guidelines for BCA in Global Health & Development (CHDS/Harvard); standardized sensitivity
A41: bca_discount_rate_sensitivity_2x_gdp_pc_growth | B41: 0.08 | C41: proportion/year | D41: 0.08 | E41: 0.06 | F41: 0.1 | G41: Standardized sensitivity = 2x projected near-term real GDP per-capita growth; Model 08 recomputes from SSP2 | H41: Robinson et al. 2019 Reference Case Guidelines for BCA in Global Health & Development (CHDS/Harvard); IIASA SSP 3.1 (SSP2)
A42: vsl_us_gni_ratio | B42: 160 | C42: ratio (VSL/GNI per capita) | D42: 160 | E42: 100 | F42: 230 | G42: U.S. reference VSL-to-GNI-per-capita ratio used for the income transfer | H42: Robinson et al. 2019 Reference Case Guidelines for BCA in Global Health & Development (CHDS/Harvard)
A43: vsl_income_elasticity_preferred | B43: 1.5 | C43: elasticity | D43: 1.5 | E43: 1 | F43: 1.5 | G43: Income elasticity of VSL for LMIC extrapolation (preferred / reference case) | H43: Robinson et al. 2019 Reference Case Guidelines for BCA in Global Health & Development (CHDS/Harvard)
A44: vsl_floor_gni_multiple | B44: 20 | C44: ratio (VSL/GNI per capita) | D44: 20 | E44: 20 | F44: 20 | G44: Lower bound: transferred VSL not below this multiple of target-country GNI per capita | H44: Robinson et al. 2019 Reference Case Guidelines for BCA in Global Health & Development (CHDS/Harvard)
A45: vsl_sensitivity_gni_multiple_100 | B45: 100 | C45: ratio (VSL/GNI per capita) | D45: 100 | E45: 100 | F45: 100 | G45: Standardized sensitivity 1: VSL = 100 x target GNI per capita | H45: Robinson et al. 2019 Reference Case Guidelines for BCA in Global Health & Development (CHDS/Harvard)
A46: vsl_sensitivity_gni_multiple_160 | B46: 160 | C46: ratio (VSL/GNI per capita) | D46: 160 | E46: 160 | F46: 160 | G46: Standardized sensitivity 2: VSL = 160 x target GNI per capita | H46: Robinson et al. 2019 Reference Case Guidelines for BCA in Global Health & Development (CHDS/Harvard)
A47: vsly_adult_min_age | B47: 15 | C47: age (years) | D47: 15 | E47: 15 | F47: 20 | G47: Lower bound of adult (working-age) population for the VSLY average-adult-age denominator | H47: Robinson et al. 2019 Reference Case Guidelines for BCA in Global Health & Development (CHDS/Harvard); ILO/World Bank working age 15-64
A48: vsly_adult_max_age | B48: 64 | C48: age (years) | D48: 64 | E48: 64 | F48: 95 | G48: Upper bound of adult (working-age) population for the VSLY average-adult-age denominator | H48: ILO / World Bank working-age population 15-64
A49: bca_currency_basis | B49: PPP_international_dollars | C49: text | D49: PPP_international_dollars | G49: Common monetary basis for BCA benefits and costs; VSL is transferred using GNI per capita at PPP | H49: Robinson et al. 2019 Reference Case Guidelines for BCA in Global Health & Development (CHDS/Harvard)
A50: bca_price_year | B50: 2023 | C50: year | D50: 2023 | E50: 2020 | F50: 2024 | G50: Real price year for BCA benefits and costs (must match the cost price year) | H50: = cost_price_year / reporting_price_year
A51: cost_to_bca_currency_factor | B51: 3 | C51: int$ per market US$ | D51: 3 | E51: 2.7 | F51: 3.3 | G51: Multiplier converting market-exchange-rate USD costs to PPP international dollars (benefit basis); = 1 / WB ICP price-level ratio | H51: World Bank ICP PA.NUS.PPPC.RF (Indonesia price-level ratio ~0.33)
A52: bca_standing | B52: societal | C52: text | D52: societal | G52: Standing/perspective for the BCA (whose benefits and costs count) | H52: Robinson et al. 2019 Reference Case Guidelines for BCA in Global Health & Development (CHDS/Harvard)
A53: bca_scope | B53: partial_mortality_benefit | C53: text | D53: partial_mortality_benefit | G53: Scope: benefits limited to averted mortality (VSL/VSLY); costs limited to implementation/health-system. NOT a full societal BCA | H53: Model scope limitation

Sheet Dictionaries
A1: intervention_id | B1: intervention_name | C1: package_group | D1: definition | F1: risk_id | G1: risk_name | H1: exposure_measure | I1: exposure_unit | K1: cause_id | L1: cause_name | M1: model_name | N1: is_model_cause | O1: mapping_note
A2: I_PH_TOBACCO_TAX | B2: Tobacco tax | C2: Tobacco | D2: Tax share -> price -> smoking exposure | F2: R_SMOKING | G2: Smoking | H2: Smoking prevalence | I2: proportion | K2: C_RHD | L2: Rheumatic heart disease | M2: Rheumatic heart disease | N2: 1 | O2: No direct mapping
A3: I_PH_ALCOHOL_TAX | B3: Alcohol tax | C3: Alcohol | D3: Incremental retail-price change | F3: R_ALCOHOL | G3: Alcohol use | H3: Alcohol consumption per adult | I3: litres pure alcohol/adult/year | K3: C_IHD | L3: Ischemic heart disease | M3: Ischemic heart disease | N3: 1 | O3: Direct mapped effects
A4: I_PH_TOB_CLEAN_AIR | B4: Smoke-free / clean-air law | C4: Tobacco | D4: Child of I_PH_TOBACCO_POLICY | F4: R_SODIUM | G4: High sodium intake | H4: Mean sodium intake | I4: g sodium/day | K4: C_IS | L4: Ischemic stroke | M4: Ischemic stroke | N4: 1 | O4: Direct mapped effects
A5: I_PH_TOB_MEDIA | B5: Tobacco mass-media campaign | C5: Tobacco | D5: Child of I_PH_TOBACCO_POLICY | F5: R_TFA | G5: Trans-fat intake | H5: Mean industrial trans-fat intake | I5: % energy | K5: C_ICH | L5: Intracerebral hemorrhage | M5: Intracerebral hemorrhage | N5: 1 | O5: SSB uses proxy
A6: I_PH_TOB_AD_BAN | B6: Tobacco advertising ban | C6: Tobacco | D6: Child of I_PH_TOBACCO_POLICY | F6: R_SSB | G6: Sugar-sweetened beverage intake | H6: Mean SSB intake | I6: 8 oz servings/adult/day | K6: C_HHD | L6: Hypertensive heart disease | M6: Hypertensive heart disease | N6: 1 | O6: SSB uses proxy
A7: I_PH_ALCOHOL_POLICY | B7: Alcohol advertising ban | C7: Alcohol | D7: Individual regulatory intervention | K7: C_CMYO | L7: Cardiomyopathy and myocarditis | M7: Cardiomyopathy and myocarditis | N7: 1 | O7: Alcohol mapping
A8: I_PH_SALT_REFORM | B8: Mandatory sodium reformulation | C8: Diet | D8: Child of I_PH_SALT_POLICY | K8: C_T2DM | L8: Diabetes mellitus type 2 | M8: Diabetes mellitus type 2 | N8: 1 | O8: Smoking and SSB
A9: I_PH_SALT_FOPL | B9: Sodium front-of-pack labelling | C9: Diet | D9: Child of I_PH_SALT_POLICY | K9: C_IHD_HBG | L9: IHD attributable to high blood glucose | M9: IHD attributable to high blood glucose | N9: 1 | O9: Do not link separately
A10: I_PH_SALT_MEDIA | B10: Sodium mass-media campaign | C10: Diet | D10: Child of I_PH_SALT_POLICY | K10: C_SHARED | L10: Shared policy cost | M10: Not a disease model | N10: 0 | O10: Cost-only key
A11: I_PH_SALT_ENV | B11: Supportive public-institution environment | C11: Diet | D11: Child of I_PH_SALT_POLICY
A12: I_PH_TFA_POLICY | B12: Industrial trans-fat elimination regulation | C12: Diet | D12: RR base case; optional PAF
A13: I_PH_SSB_TAX | B13: Sugar-sweetened beverage tax | C13: Diet | D13: 20% retail-price target

Sheet Intervention_Cause_Map
A1: intervention_cause_key | B1: intervention_id | C1: risk_id | D1: intervention_name | E1: risk_name | F1: cause_id | G1: cause_name | H1: effect_key | I1: exposure_key | J1: cost_join_key | K1: cost_scope | L1: transition_from | M1: transition_to | N1: include_flag | O1: requires_cause_expansion | P1: notes | Q1: duplicate_count
A2: I_PH_TOBACCO_TAX__C_IHD | B2: I_PH_TOBACCO_TAX | C2: R_SMOKING | D2: Tobacco tax | E2: Smoking | F2: C_IHD | G2: Ischemic heart disease | H2: I_PH_TOBACCO_TAX__C_IHD | I2: I_PH_TOBACCO_TAX | J2: I_PH_TOBACCO_TAX__C_SHARED | K2: shared-count-once | L2: well | M2: sick | N2: 1 | O2: 0 | P2: Direct exposure-response incidence effect; report by intervention_id. | Q2: =COUNTIF($A$2:$A$62,A2) -> 1
A3: I_PH_TOBACCO_TAX__C_IS | B3: I_PH_TOBACCO_TAX | C3: R_SMOKING | D3: Tobacco tax | E3: Smoking | F3: C_IS | G3: Ischemic stroke | H3: I_PH_TOBACCO_TAX__C_IS | I3: I_PH_TOBACCO_TAX | J3: I_PH_TOBACCO_TAX__C_SHARED | K3: shared-count-once | L3: well | M3: sick | N3: 1 | O3: 0 | P3: Direct exposure-response incidence effect; report by intervention_id. | Q3: =COUNTIF($A$2:$A$62,A3) -> 1
A4: I_PH_TOBACCO_TAX__C_ICH | B4: I_PH_TOBACCO_TAX | C4: R_SMOKING | D4: Tobacco tax | E4: Smoking | F4: C_ICH | G4: Intracerebral hemorrhage | H4: I_PH_TOBACCO_TAX__C_ICH | I4: I_PH_TOBACCO_TAX | J4: I_PH_TOBACCO_TAX__C_SHARED | K4: shared-count-once | L4: well | M4: sick | N4: 1 | O4: 0 | P4: Direct exposure-response incidence effect; report by intervention_id. | Q4: =COUNTIF($A$2:$A$62,A4) -> 1
A5: I_PH_TOBACCO_TAX__C_T2DM | B5: I_PH_TOBACCO_TAX | C5: R_SMOKING | D5: Tobacco tax | E5: Smoking | F5: C_T2DM | G5: Diabetes mellitus type 2 | H5: I_PH_TOBACCO_TAX__C_T2DM | I5: I_PH_TOBACCO_TAX | J5: I_PH_TOBACCO_TAX__C_SHARED | K5: shared-count-once | L5: well | M5: sick | N5: 1 | O5: 0 | P5: Direct exposure-response incidence effect; report by intervention_id. | Q5: =COUNTIF($A$2:$A$62,A5) -> 1
A6: I_PH_ALCOHOL_TAX__C_IHD | B6: I_PH_ALCOHOL_TAX | C6: R_ALCOHOL | D6: Alcohol tax | E6: Alcohol use | F6: C_IHD | G6: Ischemic heart disease | H6: I_PH_ALCOHOL_TAX__C_IHD | I6: I_PH_ALCOHOL_TAX | J6: I_PH_ALCOHOL_TAX__C_SHARED | K6: shared-count-once | L6: well | M6: sick | N6: 0 | O6: 0 | P6: Direct exposure-response incidence effect; report by intervention_id. | Q6: =COUNTIF($A$2:$A$62,A6) -> 1
A7: I_PH_ALCOHOL_TAX__C_IS | B7: I_PH_ALCOHOL_TAX | C7: R_ALCOHOL | D7: Alcohol tax | E7: Alcohol use | F7: C_IS | G7: Ischemic stroke | H7: I_PH_ALCOHOL_TAX__C_IS | I7: I_PH_ALCOHOL_TAX | J7: I_PH_ALCOHOL_TAX__C_SHARED | K7: shared-count-once | L7: well | M7: sick | N7: 0 | O7: 0 | P7: Direct exposure-response incidence effect; report by intervention_id. | Q7: =COUNTIF($A$2:$A$62,A7) -> 1
A8: I_PH_ALCOHOL_TAX__C_ICH | B8: I_PH_ALCOHOL_TAX | C8: R_ALCOHOL | D8: Alcohol tax | E8: Alcohol use | F8: C_ICH | G8: Intracerebral hemorrhage | H8: I_PH_ALCOHOL_TAX__C_ICH | I8: I_PH_ALCOHOL_TAX | J8: I_PH_ALCOHOL_TAX__C_SHARED | K8: shared-count-once | L8: well | M8: sick | N8: 0 | O8: 0 | P8: Direct exposure-response incidence effect; report by intervention_id. | Q8: =COUNTIF($A$2:$A$62,A8) -> 1
A9: I_PH_ALCOHOL_TAX__C_HHD | B9: I_PH_ALCOHOL_TAX | C9: R_ALCOHOL | D9: Alcohol tax | E9: Alcohol use | F9: C_HHD | G9: Hypertensive heart disease | H9: I_PH_ALCOHOL_TAX__C_HHD | I9: I_PH_ALCOHOL_TAX | J9: I_PH_ALCOHOL_TAX__C_SHARED | K9: shared-count-once | L9: well | M9: sick | N9: 0 | O9: 0 | P9: Direct exposure-response incidence effect; report by intervention_id. | Q9: =COUNTIF($A$2:$A$62,A9) -> 1
A10: I_PH_ALCOHOL_TAX__C_CMYO | B10: I_PH_ALCOHOL_TAX | C10: R_ALCOHOL | D10: Alcohol tax | E10: Alcohol use | F10: C_CMYO | G10: Cardiomyopathy and myocarditis | H10: I_PH_ALCOHOL_TAX__C_CMYO | I10: I_PH_ALCOHOL_TAX | J10: I_PH_ALCOHOL_TAX__C_SHARED | K10: shared-count-once | L10: well | M10: sick | N10: 0 | O10: 0 | P10: Direct exposure-response incidence effect; report by intervention_id. | Q10: =COUNTIF($A$2:$A$62,A10) -> 1
A11: I_PH_TOB_CLEAN_AIR__C_IHD | B11: I_PH_TOB_CLEAN_AIR | C11: R_SMOKING | D11: Smoke-free / clean-air law | E11: Smoking | F11: C_IHD | G11: Ischemic heart disease | H11: I_PH_TOB_CLEAN_AIR__C_IHD | I11: I_PH_TOB_CLEAN_AIR | J11: I_PH_TOB_CLEAN_AIR__C_SHARED | K11: component-count-once | L11: well | M11: sick | N11: 1 | O11: 0 | P11: Direct exposure-response incidence effect; report by intervention_id. | Q11: =COUNTIF($A$2:$A$62,A11) -> 1
A12: I_PH_TOB_CLEAN_AIR__C_IS | B12: I_PH_TOB_CLEAN_AIR | C12: R_SMOKING | D12: Smoke-free / clean-air law | E12: Smoking | F12: C_IS | G12: Ischemic stroke | H12: I_PH_TOB_CLEAN_AIR__C_IS | I12: I_PH_TOB_CLEAN_AIR | J12: I_PH_TOB_CLEAN_AIR__C_SHARED | K12: component-count-once | L12: well | M12: sick | N12: 1 | O12: 0 | P12: Direct exposure-response incidence effect; report by intervention_id. | Q12: =COUNTIF($A$2:$A$62,A12) -> 1
A13: I_PH_TOB_CLEAN_AIR__C_ICH | B13: I_PH_TOB_CLEAN_AIR | C13: R_SMOKING | D13: Smoke-free / clean-air law | E13: Smoking | F13: C_ICH | G13: Intracerebral hemorrhage | H13: I_PH_TOB_CLEAN_AIR__C_ICH | I13: I_PH_TOB_CLEAN_AIR | J13: I_PH_TOB_CLEAN_AIR__C_SHARED | K13: component-count-once | L13: well | M13: sick | N13: 1 | O13: 0 | P13: Direct exposure-response incidence effect; report by intervention_id. | Q13: =COUNTIF($A$2:$A$62,A13) -> 1
... A62: I_PH_SSB_TAX__C_T2DM__SICK_DEAD | B62: I_PH_SSB_TAX | C62: R_SSB | D62: Sugar-sweetened beverage tax | E62: Sugar-sweetened beverage intake | F62: C_T2DM | G62: Diabetes mellitus type 2 | H62: I_PH_SSB_TAX__C_T2DM__SICK_DEAD | I62: I_PH_SSB_TAX | J62: I_PH_SSB_TAX__C_SHARED | K62: shared-count-once | L62: sick | M62: dead | N62: 0 | O62: 0 | P62: Exploratory and disabled: BMJ outcome is all-cause mortality among adults with T2DM, not diabetes-specific death. | Q62: =COUNTIF($A$2:$A$62,A62) -> 1

Sheet Policy_Levers
A1: lever_id | B1: intervention_id | C1: intervention_name | D1: component | E1: lever_method | F1: baseline_value | G1: target_value | H1: lever_unit | I1: effect_parameter | J1: effect_parameter_unit | K1: estimated_risk_reduction | L1: source | M1: review_status | N1: notes | O1: qa_status | P1: parent_package_id | Q1: parent_package_name | R1: intervention_role | S1: fiscal_baseline_tax_level | T1: fiscal_target_tax_level | U1: fiscal_tax_level_unit | V1: regulatory_baseline_level | W1: regulatory_target_level | X1: regulatory_baseline_score | Y1: regulatory_target_score | Z1: implementation_gap | AA1: implied_price_change | AB1: fiscal_tax_delta
A2: PL_TOB_TAX_SHARE | B2: I_PH_TOBACCO_TAX | C2: Tobacco tax | D2: Tax share of final retail price | E2: tax_share_to_price_elasticity | F2: =IF(OR(E2="tax_share_to_price_elasticity",E2="price_elasticity"),S2,X2) -> 0.65921 | G2: =IF(OR(E2="tax_share_to_price_elasticity",E2="price_elasticity"),T2,Y2) -> 0.75 | H2: =IF(OR(E2="tax_share_to_price_elasticity",E2="price_elasticity"),U2,"implementation score 0-1") -> tax share of retail price | I2: -0.48 | J2: price elasticity | K2: =IF(E2="tax_share_to_price_elasticity",MIN(1,ABS(I2)*AA2),IF(E2="price_elasticity",MIN(1,ABS(I2)*AA2),IF(E2="regulatory_gap_multiplicative",MIN(1,Z2*I2),""))) -> 0.1743168 | L2: WHO tobacco report 2025; Countdown p 32 | M2: Ready | N2: WHO reports Indonesia in >=75% group; baseline equals target. | O2: =IF(OR(E2="tax_share_to_price_elasticity",E2="price_elasticity"),IF(COUNT(S2,T2)<2,"MISSING FISCAL INPUT",IF(OR(K2<0,K2>1),"BAD REDUCTION","OK")),IF(OR(V2="",W2="",COUNT(X2,Y2)<2),"MISSING REGULATORY INPUT",IF(OR(K2<0,K2>1),"BAD REDUCTION","OK"))) -> OK | P2: I_PH_TOBACCO_TAX | Q2: Tobacco tax | R2: standalone | S2: 0.65921 | T2: 0.75 | U2: tax share of retail price | V2: partial | W2: partial | X2: =IF(V2="none",Assumptions!$B$24,IF(V2="partial",Assumptions!$B$25,IF(V2="full",Assumptions!$B$26,""))) -> 0.5 | Y2: =IF(W2="none",Assumptions!$B$24,IF(W2="partial",Assumptions!$B$25,IF(W2="full",Assumptions!$B$26,""))) -> 0.5 | Z2: =IF(COUNT(X2,Y2)<2,"",MAX(0,Y2-X2)) -> 0 | AA2: =IF(E2="tax_share_to_price_elasticity",IF(OR(COUNT(S2,T2)<2,T2>=1),"",MAX(0,(1-S2)/(1-T2)-1)),IF(E2="price_elasticity",IF(COUNT(S2,T2)<2,"",MAX(0,T2-S2)),0)) -> 0.36316 | AB2: =IF(OR(E2="tax_share_to_price_elasticity",E2="price_elasticity"),IF(COUNT(S2,T2)<2,"",T2-S2),0) -> 0.09079
A3: PL_ALC_PRICE | B3: I_PH_ALCOHOL_TAX | C3: Alcohol tax | D3: Incremental retail-price increase versus current law | E3: price_elasticity | F3: =IF(OR(E3="tax_share_to_price_elasticity",E3="price_elasticity"),S3,X3) -> 0 | G3: =IF(OR(E3="tax_share_to_price_elasticity",E3="price_elasticity"),T3,Y3) -> 0.25 | H3: =IF(OR(E3="tax_share_to_price_elasticity",E3="price_elasticity"),U3,"implementation score 0-1") -> relative price change vs current law | I3: -0.49 | J3: price elasticity | K3: =IF(E3="tax_share_to_price_elasticity",MIN(1,ABS(I3)*AA3),IF(E3="price_elasticity",MIN(1,ABS(I3)*AA3),IF(E3="regulatory_gap_multiplicative",MIN(1,Z3*I3),""))) -> 0.1225 | L3: Countdown p 31 | M3: Ready | N3: Baseline zero incremental change; target +25%. | O3: =IF(OR(E3="tax_share_to_price_elasticity",E3="price_elasticity"),IF(COUNT(S3,T3)<2,"MISSING FISCAL INPUT",IF(OR(K3<0,K3>1),"BAD REDUCTION","OK")),IF(OR(V3="",W3="",COUNT(X3,Y3)<2),"MISSING REGULATORY INPUT",IF(OR(K3<0,K3>1),"BAD REDUCTION","OK"))) -> OK | P3: I_PH_ALCOHOL_TAX | Q3: Alcohol tax | R3: standalone | S3: 0 | T3: 0.25 | U3: relative price change vs current law | V3: none | W3: none | X3: =IF(V3="none",Assumptions!$B$24,IF(V3="partial",Assumptions!$B$25,IF(V3="full",Assumptions!$B$26,""))) -> 0 | Y3: =IF(W3="none",Assumptions!$B$24,IF(W3="partial",Assumptions!$B$25,IF(W3="full",Assumptions!$B$26,""))) -> 0 | Z3: =IF(COUNT(X3,Y3)<2,"",MAX(0,Y3-X3)) -> 0 | AA3: =IF(E3="tax_share_to_price_elasticity",IF(OR(COUNT(S3,T3)<2,T3>=1),"",MAX(0,(1-S3)/(1-T3)-1)),IF(E3="price_elasticity",IF(COUNT(S3,T3)<2,"",MAX(0,T3-S3)),0)) -> 0.25 | AB3: =IF(OR(E3="tax_share_to_price_elasticity",E3="price_elasticity"),IF(COUNT(S3,T3)<2,"",T3-S3),0) -> 0.25
A4: PL_TOB_CLEAN_AIR | B4: I_PH_TOB_CLEAN_AIR | C4: Smoke-free / clean-air law | D4: Smoking ban / clean-air law | E4: regulatory_gap_multiplicative | F4: =IF(OR(E4="tax_share_to_price_elasticity",E4="price_elasticity"),S4,X4) -> 0.5 | G4: =IF(OR(E4="tax_share_to_price_elasticity",E4="price_elasticity"),T4,Y4) -> 1 | H4: =IF(OR(E4="tax_share_to_price_elasticity",E4="price_elasticity"),U4,"implementation score 0-1") -> implementation score 0-1 | I4: 0.11 | J4: full-policy relative smoking reduction | K4: =IF(E4="tax_share_to_price_elasticity",MIN(1,ABS(I4)*AA4),IF(E4="price_elasticity",MIN(1,ABS(I4)*AA4),IF(E4="regulatory_gap_multiplicative",MIN(1,Z4*I4),""))) -> 0.055 | L4: WHO NCD Progress Monitor 2025; Countdown p 32 | M4: Ready | N4: Baseline partial. | O4: =IF(OR(E4="tax_share_to_price_elasticity",E4="price_elasticity"),IF(COUNT(S4,T4)<2,"MISSING FISCAL INPUT",IF(OR(K4<0,K4>1),"BAD REDUCTION","OK")),IF(OR(V4="",W4="",COUNT(X4,Y4)<2),"MISSING REGULATORY INPUT",IF(OR(K4<0,K4>1),"BAD REDUCTION","OK"))) -> OK | P4: I_PH_TOBACCO_POLICY | Q4: Tobacco policy package | R4: child | V4: partial | W4: full | X4: =IF(V4="none",Assumptions!$B$24,IF(V4="partial",Assumptions!$B$25,IF(V4="full",Assumptions!$B$26,""))) -> 0.5 | Y4: =IF(W4="none",Assumptions!$B$24,IF(W4="partial",Assumptions!$B$25,IF(W4="full",Assumptions!$B$26,""))) -> 1 | Z4: =IF(COUNT(X4,Y4)<2,"",MAX(0,Y4-X4)) -> 0.5 | AA4: =IF(E4="tax_share_to_price_elasticity",IF(OR(COUNT(S4,T4)<2,T4>=1),"",MAX(0,(1-S4)/(1-T4)-1)),IF(E4="price_elasticity",IF(COUNT(S4,T4)<2,"",MAX(0,T4-S4)),0)) -> 0 | AB4: =IF(OR(E4="tax_share_to_price_elasticity",E4="price_elasticity"),IF(COUNT(S4,T4)<2,"",T4-S4),0) -> 0
A5: PL_TOB_MEDIA | B5: I_PH_TOB_MEDIA | C5: Tobacco mass-media campaign | D5: Highly publicised mass-media campaign | E5: regulatory_gap_multiplicative | F5: =IF(OR(E5="tax_share_to_price_elasticity",E5="price_elasticity"),S5,X5) -> 0 | G5: =IF(OR(E5="tax_share_to_price_elasticity",E5="price_elasticity"),T5,Y5) -> 1 | H5: =IF(OR(E5="tax_share_to_price_elasticity",E5="price_elasticity"),U5,"implementation score 0-1") -> implementation score 0-1 | I5: 0.065 | J5: full-policy relative smoking reduction | K5: =IF(E5="tax_share_to_price_elasticity",MIN(1,ABS(I5)*AA5),IF(E5="price_elasticity",MIN(1,ABS(I5)*AA5),IF(E5="regulatory_gap_multiplicative",MIN(1,Z5*I5),""))) -> 0.065 | L5: WHO NCD Progress Monitor 2025; Countdown p 32 | M5: Ready | N5: Baseline none. | O5: =IF(OR(E5="tax_share_to_price_elasticity",E5="price_elasticity"),IF(COUNT(S5,T5)<2,"MISSING FISCAL INPUT",IF(OR(K5<0,K5>1),"BAD REDUCTION","OK")),IF(OR(V5="",W5="",COUNT(X5,Y5)<2),"MISSING REGULATORY INPUT",IF(OR(K5<0,K5>1),"BAD REDUCTION","OK"))) -> OK | P5: I_PH_TOBACCO_POLICY | Q5: Tobacco policy package | R5: child | V5: none | W5: full | X5: =IF(V5="none",Assumptions!$B$24,IF(V5="partial",Assumptions!$B$25,IF(V5="full",Assumptions!$B$26,""))) -> 0 | Y5: =IF(W5="none",Assumptions!$B$24,IF(W5="partial",Assumptions!$B$25,IF(W5="full",Assumptions!$B$26,""))) -> 1 | Z5: =IF(COUNT(X5,Y5)<2,"",MAX(0,Y5-X5)) -> 1 | AA5: =IF(E5="tax_share_to_price_elasticity",IF(OR(COUNT(S5,T5)<2,T5>=1),"",MAX(0,(1-S5)/(1-T5)-1)),IF(E5="price_elasticity",IF(COUNT(S5,T5)<2,"",MAX(0,T5-S5)),0)) -> 0 | AB5: =IF(OR(E5="tax_share_to_price_elasticity",E5="price_elasticity"),IF(COUNT(S5,T5)<2,"",T5-S5),0) -> 0
A6: PL_TOB_AD_BAN | B6: I_PH_TOB_AD_BAN | C6: Tobacco advertising ban | D6: Advertising, promotion and sponsorship ban | E6: regulatory_gap_multiplicative | F6: =IF(OR(E6="tax_share_to_price_elasticity",E6="price_elasticity"),S6,X6) -> 0 | G6: =IF(OR(E6="tax_share_to_price_elasticity",E6="price_elasticity"),T6,Y6) -> 1 | H6: =IF(OR(E6="tax_share_to_price_elasticity",E6="price_elasticity"),U6,"implementation score 0-1") -> implementation score 0-1 | I6: 0.04 | J6: full-policy relative smoking reduction | K6: =IF(E6="tax_share_to_price_elasticity",MIN(1,ABS(I6)*AA6),IF(E6="price_elasticity",MIN(1,ABS(I6)*AA6),IF(E6="regulatory_gap_multiplicative",MIN(1,Z6*I6),""))) -> 0.04 | L6: WHO NCD Progress Monitor 2025; Countdown p 32 | M6: Ready | N6: Baseline none. | O6: =IF(OR(E6="tax_share_to_price_elasticity",E6="price_elasticity"),IF(COUNT(S6,T6)<2,"MISSING FISCAL INPUT",IF(OR(K6<0,K6>1),"BAD REDUCTION","OK")),IF(OR(V6="",W6="",COUNT(X6,Y6)<2),"MISSING REGULATORY INPUT",IF(OR(K6<0,K6>1),"BAD REDUCTION","OK"))) -> OK | P6: I_PH_TOBACCO_POLICY | Q6: Tobacco policy package | R6: child | V6: none | W6: full | X6: =IF(V6="none",Assumptions!$B$24,IF(V6="partial",Assumptions!$B$25,IF(V6="full",Assumptions!$B$26,""))) -> 0 | Y6: =IF(W6="none",Assumptions!$B$24,IF(W6="partial",Assumptions!$B$25,IF(W6="full",Assumptions!$B$26,""))) -> 1 | Z6: =IF(COUNT(X6,Y6)<2,"",MAX(0,Y6-X6)) -> 1 | AA6: =IF(E6="tax_share_to_price_elasticity",IF(OR(COUNT(S6,T6)<2,T6>=1),"",MAX(0,(1-S6)/(1-T6)-1)),IF(E6="price_elasticity",IF(COUNT(S6,T6)<2,"",MAX(0,T6-S6)),0)) -> 0 | AB6: =IF(OR(E6="tax_share_to_price_elasticity",E6="price_elasticity"),IF(COUNT(S6,T6)<2,"",T6-S6),0) -> 0
A7: PL_ALC_AD_BAN | B7: I_PH_ALCOHOL_POLICY | C7: Alcohol advertising ban | D7: Alcohol advertising ban | E7: regulatory_gap_multiplicative | F7: =IF(OR(E7="tax_share_to_price_elasticity",E7="price_elasticity"),S7,X7) -> 0.5 | G7: =IF(OR(E7="tax_share_to_price_elasticity",E7="price_elasticity"),T7,Y7) -> 1 | H7: =IF(OR(E7="tax_share_to_price_elasticity",E7="price_elasticity"),U7,"implementation score 0-1") -> implementation score 0-1 | I7: 0.269 | J7: full-policy relative alcohol reduction | K7: =IF(E7="tax_share_to_price_elasticity",MIN(1,ABS(I7)*AA7),IF(E7="price_elasticity",MIN(1,ABS(I7)*AA7),IF(E7="regulatory_gap_multiplicative",MIN(1,Z7*I7),""))) -> 0.1345 | L7: WHO NCD Progress Monitor 2025; Countdown p 31 | M7: Ready | N7: Full to full gives zero additional effect. | O7: =IF(OR(E7="tax_share_to_price_elasticity",E7="price_elasticity"),IF(COUNT(S7,T7)<2,"MISSING FISCAL INPUT",IF(OR(K7<0,K7>1),"BAD REDUCTION","OK")),IF(OR(V7="",W7="",COUNT(X7,Y7)<2),"MISSING REGULATORY INPUT",IF(OR(K7<0,K7>1),"BAD REDUCTION","OK"))) -> OK | P7: I_PH_ALCOHOL_POLICY | Q7: Alcohol advertising policy | R7: standalone | V7: partial | W7: full | X7: =IF(V7="none",Assumptions!$B$24,IF(V7="partial",Assumptions!$B$25,IF(V7="full",Assumptions!$B$26,""))) -> 0.5 | Y7: =IF(W7="none",Assumptions!$B$24,IF(W7="partial",Assumptions!$B$25,IF(W7="full",Assumptions!$B$26,""))) -> 1 | Z7: =IF(COUNT(X7,Y7)<2,"",MAX(0,Y7-X7)) -> 0.5 | AA7: =IF(E7="tax_share_to_price_elasticity",IF(OR(COUNT(S7,T7)<2,T7>=1),"",MAX(0,(1-S7)/(1-T7)-1)),IF(E7="price_elasticity",IF(COUNT(S7,T7)<2,"",MAX(0,T7-S7)),0)) -> 0 | AB7: =IF(OR(E7="tax_share_to_price_elasticity",E7="price_elasticity"),IF(COUNT(S7,T7)<2,"",T7-S7),0) -> 0
A8: PL_SALT_REFORM | B8: I_PH_SALT_REFORM | C8: Mandatory sodium reformulation | D8: Mandatory product reformulation | E8: regulatory_gap_multiplicative | F8: =IF(OR(E8="tax_share_to_price_elasticity",E8="price_elasticity"),S8,X8) -> 0.5 | G8: =IF(OR(E8="tax_share_to_price_elasticity",E8="price_elasticity"),T8,Y8) -> 1 | H8: =IF(OR(E8="tax_share_to_price_elasticity",E8="price_elasticity"),U8,"implementation score 0-1") -> implementation score 0-1 | I8: 0.2 | J8: full-policy relative sodium reduction | K8: =IF(E8="tax_share_to_price_elasticity",MIN(1,ABS(I8)*AA8),IF(E8="price_elasticity",MIN(1,ABS(I8)*AA8),IF(E8="regulatory_gap_multiplicative",MIN(1,Z8*I8),""))) -> 0.1 | L8: WHO Indonesia 2026; Countdown p 33 | M8: Ready | N8: Law adopted; technical benchmarks pending: partial. | O8: =IF(OR(E8="tax_share_to_price_elasticity",E8="price_elasticity"),IF(COUNT(S8,T8)<2,"MISSING FISCAL INPUT",IF(OR(K8<0,K8>1),"BAD REDUCTION","OK")),IF(OR(V8="",W8="",COUNT(X8,Y8)<2),"MISSING REGULATORY INPUT",IF(OR(K8<0,K8>1),"BAD REDUCTION","OK"))) -> OK | P8: I_PH_SALT_POLICY | Q8: Salt policy package | R8: child | V8: partial | W8: full | X8: =IF(V8="none",Assumptions!$B$24,IF(V8="partial",Assumptions!$B$25,IF(V8="full",Assumptions!$B$26,""))) -> 0.5 | Y8: =IF(W8="none",Assumptions!$B$24,IF(W8="partial",Assumptions!$B$25,IF(W8="full",Assumptions!$B$26,""))) -> 1 | Z8: =IF(COUNT(X8,Y8)<2,"",MAX(0,Y8-X8)) -> 0.5 | AA8: =IF(E8="tax_share_to_price_elasticity",IF(OR(COUNT(S8,T8)<2,T8>=1),"",MAX(0,(1-S8)/(1-T8)-1)),IF(E8="price_elasticity",IF(COUNT(S8,T8)<2,"",MAX(0,T8-S8)),0)) -> 0 | AB8: =IF(OR(E8="tax_share_to_price_elasticity",E8="price_elasticity"),IF(COUNT(S8,T8)<2,"",T8-S8),0) -> 0
A9: PL_SALT_FOPL | B9: I_PH_SALT_FOPL | C9: Sodium front-of-pack labelling | D9: Front-of-pack labelling | E9: regulatory_gap_multiplicative | F9: =IF(OR(E9="tax_share_to_price_elasticity",E9="price_elasticity"),S9,X9) -> 0.5 | G9: =IF(OR(E9="tax_share_to_price_elasticity",E9="price_elasticity"),T9,Y9) -> 1 | H9: =IF(OR(E9="tax_share_to_price_elasticity",E9="price_elasticity"),U9,"implementation score 0-1") -> implementation score 0-1 | I9: 0.1 | J9: full-policy relative sodium reduction | K9: =IF(E9="tax_share_to_price_elasticity",MIN(1,ABS(I9)*AA9),IF(E9="price_elasticity",MIN(1,ABS(I9)*AA9),IF(E9="regulatory_gap_multiplicative",MIN(1,Z9*I9),""))) -> 0.05 | L9: WHO Indonesia 2026; Countdown p 33 | M9: Ready | N9: Mandatory framework adopted; implementation ongoing: partial. | O9: =IF(OR(E9="tax_share_to_price_elasticity",E9="price_elasticity"),IF(COUNT(S9,T9)<2,"MISSING FISCAL INPUT",IF(OR(K9<0,K9>1),"BAD REDUCTION","OK")),IF(OR(V9="",W9="",COUNT(X9,Y9)<2),"MISSING REGULATORY INPUT",IF(OR(K9<0,K9>1),"BAD REDUCTION","OK"))) -> OK | P9: I_PH_SALT_POLICY | Q9: Salt policy package | R9: child | V9: partial | W9: full | X9: =IF(V9="none",Assumptions!$B$24,IF(V9="partial",Assumptions!$B$25,IF(V9="full",Assumptions!$B$26,""))) -> 0.5 | Y9: =IF(W9="none",Assumptions!$B$24,IF(W9="partial",Assumptions!$B$25,IF(W9="full",Assumptions!$B$26,""))) -> 1 | Z9: =IF(COUNT(X9,Y9)<2,"",MAX(0,Y9-X9)) -> 0.5 | AA9: =IF(E9="tax_share_to_price_elasticity",IF(OR(COUNT(S9,T9)<2,T9>=1),"",MAX(0,(1-S9)/(1-T9)-1)),IF(E9="price_elasticity",IF(COUNT(S9,T9)<2,"",MAX(0,T9-S9)),0)) -> 0 | AB9: =IF(OR(E9="tax_share_to_price_elasticity",E9="price_elasticity"),IF(COUNT(S9,T9)<2,"",T9-S9),0) -> 0
A10: PL_SALT_MEDIA | B10: I_PH_SALT_MEDIA | C10: Sodium mass-media campaign | D10: Mass-media campaign | E10: regulatory_gap_multiplicative | F10: =IF(OR(E10="tax_share_to_price_elasticity",E10="price_elasticity"),S10,X10) -> 0.5 | G10: =IF(OR(E10="tax_share_to_price_elasticity",E10="price_elasticity"),T10,Y10) -> 0.5 | H10: =IF(OR(E10="tax_share_to_price_elasticity",E10="price_elasticity"),U10,"implementation score 0-1") -> implementation score 0-1 | I10: 0.05 | J10: full-policy relative sodium reduction | K10: =IF(E10="tax_share_to_price_elasticity",MIN(1,ABS(I10)*AA10),IF(E10="price_elasticity",MIN(1,ABS(I10)*AA10),IF(E10="regulatory_gap_multiplicative",MIN(1,Z10*I10),""))) -> 0 | L10: WHO NCD Progress Monitor 2025; Countdown p 33 | M10: Ready | N10: Full to full gives zero additional effect. | O10: =IF(OR(E10="tax_share_to_price_elasticity",E10="price_elasticity"),IF(COUNT(S10,T10)<2,"MISSING FISCAL INPUT",IF(OR(K10<0,K10>1),"BAD REDUCTION","OK")),IF(OR(V10="",W10="",COUNT(X10,Y10)<2),"MISSING REGULATORY INPUT",IF(OR(K10<0,K10>1),"BAD REDUCTION","OK"))) -> OK | P10: I_PH_SALT_POLICY | Q10: Salt policy package | R10: child | V10: partial | W10: partial | X10: =IF(V10="none",Assumptions!$B$24,IF(V10="partial",Assumptions!$B$25,IF(V10="full",Assumptions!$B$26,""))) -> 0.5 | Y10: =IF(W10="none",Assumptions!$B$24,IF(W10="partial",Assumptions!$B$25,IF(W10="full",Assumptions!$B$26,""))) -> 0.5 | Z10: =IF(COUNT(X10,Y10)<2,"",MAX(0,Y10-X10)) -> 0 | AA10: =IF(E10="tax_share_to_price_elasticity",IF(OR(COUNT(S10,T10)<2,T10>=1),"",MAX(0,(1-S10)/(1-T10)-1)),IF(E10="price_elasticity",IF(COUNT(S10,T10)<2,"",MAX(0,T10-S10)),0)) -> 0 | AB10: =IF(OR(E10="tax_share_to_price_elasticity",E10="price_elasticity"),IF(COUNT(S10,T10)<2,"",T10-S10),0) -> 0
A11: PL_SALT_ENV | B11: I_PH_SALT_ENV | C11: Supportive public-institution environment | D11: Public food procurement and supportive institutions | E11: regulatory_gap_multiplicative | F11: =IF(OR(E11="tax_share_to_price_elasticity",E11="price_elasticity"),S11,X11) -> 0.5 | G11: =IF(OR(E11="tax_share_to_price_elasticity",E11="price_elasticity"),T11,Y11) -> 1 | H11: =IF(OR(E11="tax_share_to_price_elasticity",E11="price_elasticity"),U11,"implementation score 0-1") -> implementation score 0-1 | I11: 0.07 | J11: full-policy relative sodium reduction | K11: =IF(E11="tax_share_to_price_elasticity",MIN(1,ABS(I11)*AA11),IF(E11="price_elasticity",MIN(1,ABS(I11)*AA11),IF(E11="regulatory_gap_multiplicative",MIN(1,Z11*I11),""))) -> 0.035 | L11: WHO Indonesia 2026; Countdown p 33 | M11: Ready | N11: Healthy-zone implementation incomplete: partial. | O11: =IF(OR(E11="tax_share_to_price_elasticity",E11="price_elasticity"),IF(COUNT(S11,T11)<2,"MISSING FISCAL INPUT",IF(OR(K11<0,K11>1),"BAD REDUCTION","OK")),IF(OR(V11="",W11="",COUNT(X11,Y11)<2),"MISSING REGULATORY INPUT",IF(OR(K11<0,K11>1),"BAD REDUCTION","OK"))) -> OK | P11: I_PH_SALT_POLICY | Q11: Salt policy package | R11: child | V11: partial | W11: full | X11: =IF(V11="none",Assumptions!$B$24,IF(V11="partial",Assumptions!$B$25,IF(V11="full",Assumptions!$B$26,""))) -> 0.5 | Y11: =IF(W11="none",Assumptions!$B$24,IF(W11="partial",Assumptions!$B$25,IF(W11="full",Assumptions!$B$26,""))) -> 1 | Z11: =IF(COUNT(X11,Y11)<2,"",MAX(0,Y11-X11)) -> 0.5 | AA11: =IF(E11="tax_share_to_price_elasticity",IF(OR(COUNT(S11,T11)<2,T11>=1),"",MAX(0,(1-S11)/(1-T11)-1)),IF(E11="price_elasticity",IF(COUNT(S11,T11)<2,"",MAX(0,T11-S11)),0)) -> 0 | AB11: =IF(OR(E11="tax_share_to_price_elasticity",E11="price_elasticity"),IF(COUNT(S11,T11)<2,"",T11-S11),0) -> 0
A12: PL_TFA_REG | B12: I_PH_TFA_POLICY | C12: Industrial trans-fat elimination regulation | D12: Best-practice industrial TFA regulation | E12: regulatory_gap_multiplicative | F12: =IF(OR(E12="tax_share_to_price_elasticity",E12="price_elasticity"),S12,X12) -> 0.5 | G12: =IF(OR(E12="tax_share_to_price_elasticity",E12="price_elasticity"),T12,Y12) -> 1 | H12: =IF(OR(E12="tax_share_to_price_elasticity",E12="price_elasticity"),U12,"implementation score 0-1") -> implementation score 0-1 | I12: 1 | J12: full-policy relative industrial-TFA reduction | K12: =IF(E12="tax_share_to_price_elasticity",MIN(1,ABS(I12)*AA12),IF(E12="price_elasticity",MIN(1,ABS(I12)*AA12),IF(E12="regulatory_gap_multiplicative",MIN(1,Z12*I12),""))) -> 0.5 | L12: WHO Indonesia 2024/2026; REPLACE | M12: Ready | N12: Framework adopted but not fully implemented: partial. | O12: =IF(OR(E12="tax_share_to_price_elasticity",E12="price_elasticity"),IF(COUNT(S12,T12)<2,"MISSING FISCAL INPUT",IF(OR(K12<0,K12>1),"BAD REDUCTION","OK")),IF(OR(V12="",W12="",COUNT(X12,Y12)<2),"MISSING REGULATORY INPUT",IF(OR(K12<0,K12>1),"BAD REDUCTION","OK"))) -> OK | P12: I_PH_TFA_POLICY | Q12: Industrial TFA regulation | R12: standalone | V12: partial | W12: full | X12: =IF(V12="none",Assumptions!$B$24,IF(V12="partial",Assumptions!$B$25,IF(V12="full",Assumptions!$B$26,""))) -> 0.5 | Y12: =IF(W12="none",Assumptions!$B$24,IF(W12="partial",Assumptions!$B$25,IF(W12="full",Assumptions!$B$26,""))) -> 1 | Z12: =IF(COUNT(X12,Y12)<2,"",MAX(0,Y12-X12)) -> 0.5 | AA12: =IF(E12="tax_share_to_price_elasticity",IF(OR(COUNT(S12,T12)<2,T12>=1),"",MAX(0,(1-S12)/(1-T12)-1)),IF(E12="price_elasticity",IF(COUNT(S12,T12)<2,"",MAX(0,T12-S12)),0)) -> 0 | AB12: =IF(OR(E12="tax_share_to_price_elasticity",E12="price_elasticity"),IF(COUNT(S12,T12)<2,"",T12-S12),0) -> 0
A13: PL_SSB_PRICE | B13: I_PH_SSB_TAX | C13: Sugar-sweetened beverage tax | D13: Incremental retail-price increase | E13: price_elasticity | F13: =IF(OR(E13="tax_share_to_price_elasticity",E13="price_elasticity"),S13,X13) -> 0 | G13: =IF(OR(E13="tax_share_to_price_elasticity",E13="price_elasticity"),T13,Y13) -> 0.2 | H13: =IF(OR(E13="tax_share_to_price_elasticity",E13="price_elasticity"),U13,"implementation score 0-1") -> relative price change vs baseline | I13: =Assumptions!$B$21 -> -0.875 | J13: own-price elasticity | K13: =IF(E13="tax_share_to_price_elasticity",MIN(1,ABS(I13)*AA13),IF(E13="price_elasticity",MIN(1,ABS(I13)*AA13),IF(E13="regulatory_gap_multiplicative",MIN(1,Z13*I13),""))) -> 0.175 | L13: https://doi.org/10.1371/journal.pone.0293913; WHO 2024 | M13: Ready | N13: Baseline no national excise; target +20% consumer price. | O13: =IF(OR(E13="tax_share_to_price_elasticity",E13="price_elasticity"),IF(COUNT(S13,T13)<2,"MISSING FISCAL INPUT",IF(OR(K13<0,K13>1),"BAD REDUCTION","OK")),IF(OR(V13="",W13="",COUNT(X13,Y13)<2),"MISSING REGULATORY INPUT",IF(OR(K13<0,K13>1),"BAD REDUCTION","OK"))) -> OK | P13: I_PH_SSB_TAX | Q13: SSB tax | R13: standalone | S13: 0 | T13: =Assumptions!$B$20 -> 0.2 | U13: relative price change vs baseline | V13: none | W13: full | X13: =IF(V13="none",Assumptions!$B$24,IF(V13="partial",Assumptions!$B$25,IF(V13="full",Assumptions!$B$26,""))) -> 0 | Y13: =IF(W13="none",Assumptions!$B$24,IF(W13="partial",Assumptions!$B$25,IF(W13="full",Assumptions!$B$26,""))) -> 1 | Z13: =IF(COUNT(X13,Y13)<2,"",MAX(0,Y13-X13)) -> 1 | AA13: =IF(E13="tax_share_to_price_elasticity",IF(OR(COUNT(S13,T13)<2,T13>=1),"",MAX(0,(1-S13)/(1-T13)-1)),IF(E13="price_elasticity",IF(COUNT(S13,T13)<2,"",MAX(0,T13-S13)),0)) -> 0.2 | AB13: =IF(OR(E13="tax_share_to_price_elasticity",E13="price_elasticity"),IF(COUNT(S13,T13)<2,"",T13-S13),0) -> 0.2

Sheet Exposure_Targets
A1: exposure_input_id | B1: intervention_id | C1: risk_id | D1: intervention_name | E1: risk_exposure_measure | F1: exposure_unit | G1: baseline_exposure | H1: reduction_method | I1: desired_reduction_override | J1: recommended_reduction_or_target | K1: applied_reduction_or_target | L1: exposure_floor | M1: target_exposure | N1: absolute_reduction | O1: relative_reduction | P1: start_year | Q1: target_year | R1: scale_up_shape | S1: source | T1: review_status | U1: qa_status
A2: EXP_TOB_TAX | B2: I_PH_TOBACCO_TAX | C2: R_SMOKING | D2: Tobacco tax | E2: Smoking prevalence | F2: proportion | G2: 0.303 | H2: relative | J2: =SUMIF(Policy_Levers!$B$2:$B$13,B2,Policy_Levers!$K$2:$K$13) -> 0.1743168 | K2: =IF(ISBLANK(I2),J2,I2) -> 0.1743168 | L2: 0 | M2: =IF(OR(ISBLANK(G2),ISBLANK(K2)),"",IF(H2="relative",MAX(L2,G2*(1-K2)),IF(H2="absolute",MAX(L2,G2-K2),IF(H2="target",MAX(L2,K2),"")))) -> 0.25018201 | N2: =IF(ISBLANK(M2),"",G2-M2) -> 0.05281799 | O2: =IF(OR(ISBLANK(G2),G2=0,ISBLANK(N2)),"",N2/G2) -> 0.1743168 | P2: =Assumptions!$B$4 -> 2026 | Q2: =Assumptions!$B$5 -> 2030 | R2: =Assumptions!$B$12 -> linear | S2: WHO/GATS; fiscal method | T2: Baseline retained | U2: =IF(ISBLANK(G2),"MISSING EXPOSURE",IF(ISBLANK(K2),"MISSING REDUCTION",IF(OR(M2<L2,M2>G2,Q2<P2),"BAD INPUT","OK"))) -> OK
A3: EXP_ALC_TAX | B3: I_PH_ALCOHOL_TAX | C3: R_ALCOHOL | D3: Alcohol tax | E3: Alcohol consumption per adult | F3: litres pure alcohol/adult/year | G3: 0.1 | H3: relative | J3: =SUMIF(Policy_Levers!$B$2:$B$13,B3,Policy_Levers!$K$2:$K$13) -> 0.1225 | K3: =IF(ISBLANK(I3),J3,I3) -> 0.1225 | L3: 0 | M3: =IF(OR(ISBLANK(G3),ISBLANK(K3)),"",IF(H3="relative",MAX(L3,G3*(1-K3)),IF(H3="absolute",MAX(L3,G3-K3),IF(H3="target",MAX(L3,K3),"")))) -> 0.08775 | N3: =IF(ISBLANK(M3),"",G3-M3) -> 0.01225 | O3: =IF(OR(ISBLANK(G3),G3=0,ISBLANK(N3)),"",N3/G3) -> 0.1225 | P3: =Assumptions!$B$4 -> 2026 | Q3: =Assumptions!$B$5 -> 2030 | R3: =Assumptions!$B$12 -> linear | S3: Countdown elasticity | T3: Baseline retained | U3: =IF(ISBLANK(G3),"MISSING EXPOSURE",IF(ISBLANK(K3),"MISSING REDUCTION",IF(OR(M3<L3,M3>G3,Q3<P3),"BAD INPUT","OK"))) -> OK
A4: EXP_TOB_CLEAN_AIR | B4: I_PH_TOB_CLEAN_AIR | C4: R_SMOKING | D4: Smoke-free / clean-air law | E4: Smoking prevalence | F4: proportion | G4: 0.303 | H4: relative | J4: =SUMIF(Policy_Levers!$B$2:$B$13,B4,Policy_Levers!$K$2:$K$13) -> 0.055 | K4: =IF(ISBLANK(I4),J4,I4) -> 0.055 | L4: 0 | M4: =IF(OR(ISBLANK(G4),ISBLANK(K4)),"",IF(H4="relative",MAX(L4,G4*(1-K4)),IF(H4="absolute",MAX(L4,G4-K4),IF(H4="target",MAX(L4,K4),"")))) -> 0.286335 | N4: =IF(ISBLANK(M4),"",G4-M4) -> 0.016665 | O4: =IF(OR(ISBLANK(G4),G4=0,ISBLANK(N4)),"",N4/G4) -> 0.055 | P4: =Assumptions!$B$4 -> 2026 | Q4: =Assumptions!$B$5 -> 2030 | R4: =Assumptions!$B$12 -> linear | S4: WHO category + Countdown effect | T4: Ready | U4: =IF(ISBLANK(G4),"MISSING EXPOSURE",IF(ISBLANK(K4),"MISSING REDUCTION",IF(OR(M4<L4,M4>G4,Q4<P4),"BAD INPUT","OK"))) -> OK
A5: EXP_TOB_MEDIA | B5: I_PH_TOB_MEDIA | C5: R_SMOKING | D5: Tobacco mass-media campaign | E5: Smoking prevalence | F5: proportion | G5: 0.303 | H5: relative | J5: =SUMIF(Policy_Levers!$B$2:$B$13,B5,Policy_Levers!$K$2:$K$13) -> 0.065 | K5: =IF(ISBLANK(I5),J5,I5) -> 0.065 | L5: 0 | M5: =IF(OR(ISBLANK(G5),ISBLANK(K5)),"",IF(H5="relative",MAX(L5,G5*(1-K5)),IF(H5="absolute",MAX(L5,G5-K5),IF(H5="target",MAX(L5,K5),"")))) -> 0.283305 | N5: =IF(ISBLANK(M5),"",G5-M5) -> 0.019695 | O5: =IF(OR(ISBLANK(G5),G5=0,ISBLANK(N5)),"",N5/G5) -> 0.065 | P5: =Assumptions!$B$4 -> 2026 | Q5: =Assumptions!$B$5 -> 2030 | R5: =Assumptions!$B$12 -> linear | S5: WHO category + Countdown effect | T5: Ready | U5: =IF(ISBLANK(G5),"MISSING EXPOSURE",IF(ISBLANK(K5),"MISSING REDUCTION",IF(OR(M5<L5,M5>G5,Q5<P5),"BAD INPUT","OK"))) -> OK
A6: EXP_TOB_AD_BAN | B6: I_PH_TOB_AD_BAN | C6: R_SMOKING | D6: Tobacco advertising ban | E6: Smoking prevalence | F6: proportion | G6: 0.303 | H6: relative | J6: =SUMIF(Policy_Levers!$B$2:$B$13,B6,Policy_Levers!$K$2:$K$13) -> 0.04 | K6: =IF(ISBLANK(I6),J6,I6) -> 0.04 | L6: 0 | M6: =IF(OR(ISBLANK(G6),ISBLANK(K6)),"",IF(H6="relative",MAX(L6,G6*(1-K6)),IF(H6="absolute",MAX(L6,G6-K6),IF(H6="target",MAX(L6,K6),"")))) -> 0.29088 | N6: =IF(ISBLANK(M6),"",G6-M6) -> 0.01212 | O6: =IF(OR(ISBLANK(G6),G6=0,ISBLANK(N6)),"",N6/G6) -> 0.04 | P6: =Assumptions!$B$4 -> 2026 | Q6: =Assumptions!$B$5 -> 2030 | R6: =Assumptions!$B$12 -> linear | S6: WHO category + Countdown effect | T6: Ready | U6: =IF(ISBLANK(G6),"MISSING EXPOSURE",IF(ISBLANK(K6),"MISSING REDUCTION",IF(OR(M6<L6,M6>G6,Q6<P6),"BAD INPUT","OK"))) -> OK
A7: EXP_ALC_POLICY | B7: I_PH_ALCOHOL_POLICY | C7: R_ALCOHOL | D7: Alcohol advertising ban | E7: Alcohol consumption per adult | F7: litres pure alcohol/adult/year | G7: 0.1 | H7: relative | J7: =SUMIF(Policy_Levers!$B$2:$B$13,B7,Policy_Levers!$K$2:$K$13) -> 0.1345 | K7: =IF(ISBLANK(I7),J7,I7) -> 0.1345 | L7: 0 | M7: =IF(OR(ISBLANK(G7),ISBLANK(K7)),"",IF(H7="relative",MAX(L7,G7*(1-K7)),IF(H7="absolute",MAX(L7,G7-K7),IF(H7="target",MAX(L7,K7),"")))) -> 0.08655 | N7: =IF(ISBLANK(M7),"",G7-M7) -> 0.01345 | O7: =IF(OR(ISBLANK(G7),G7=0,ISBLANK(N7)),"",N7/G7) -> 0.1345 | P7: =Assumptions!$B$4 -> 2026 | Q7: =Assumptions!$B$5 -> 2030 | R7: =Assumptions!$B$12 -> linear | S7: WHO category + Countdown effect | T7: Ready | U7: =IF(ISBLANK(G7),"MISSING EXPOSURE",IF(ISBLANK(K7),"MISSING REDUCTION",IF(OR(M7<L7,M7>G7,Q7<P7),"BAD INPUT","OK"))) -> OK
A8: EXP_SALT_REFORM | B8: I_PH_SALT_REFORM | C8: R_SODIUM | D8: Mandatory sodium reformulation | E8: Mean sodium intake | F8: g sodium/day | G8: 4.4 | H8: relative | J8: =SUMIF(Policy_Levers!$B$2:$B$13,B8,Policy_Levers!$K$2:$K$13) -> 0.1 | K8: =IF(ISBLANK(I8),J8,I8) -> 0.1 | L8: 3 | M8: =IF(OR(ISBLANK(G8),ISBLANK(K8)),"",IF(H8="relative",MAX(L8,G8*(1-K8)),IF(H8="absolute",MAX(L8,G8-K8),IF(H8="target",MAX(L8,K8),"")))) -> 3.96 | N8: =IF(ISBLANK(M8),"",G8-M8) -> 0.44 | O8: =IF(OR(ISBLANK(G8),G8=0,ISBLANK(N8)),"",N8/G8) -> 0.1 | P8: =Assumptions!$B$4 -> 2026 | Q8: =Assumptions!$B$5 -> 2030 | R8: =Assumptions!$B$12 -> linear | S8: WHO category + Countdown effect | T8: Ready | U8: =IF(ISBLANK(G8),"MISSING EXPOSURE",IF(ISBLANK(K8),"MISSING REDUCTION",IF(OR(M8<L8,M8>G8,Q8<P8),"BAD INPUT","OK"))) -> OK
A9: EXP_SALT_FOPL | B9: I_PH_SALT_FOPL | C9: R_SODIUM | D9: Sodium front-of-pack labelling | E9: Mean sodium intake | F9: g sodium/day | G9: 4.4 | H9: relative | J9: =SUMIF(Policy_Levers!$B$2:$B$13,B9,Policy_Levers!$K$2:$K$13) -> 0.05 | K9: =IF(ISBLANK(I9),J9,I9) -> 0.05 | L9: 3 | M9: =IF(OR(ISBLANK(G9),ISBLANK(K9)),"",IF(H9="relative",MAX(L9,G9*(1-K9)),IF(H9="absolute",MAX(L9,G9-K9),IF(H9="target",MAX(L9,K9),"")))) -> 4.18 | N9: =IF(ISBLANK(M9),"",G9-M9) -> 0.22 | O9: =IF(OR(ISBLANK(G9),G9=0,ISBLANK(N9)),"",N9/G9) -> 0.05 | P9: =Assumptions!$B$4 -> 2026 | Q9: =Assumptions!$B$5 -> 2030 | R9: =Assumptions!$B$12 -> linear | S9: WHO category + Countdown effect | T9: Ready | U9: =IF(ISBLANK(G9),"MISSING EXPOSURE",IF(ISBLANK(K9),"MISSING REDUCTION",IF(OR(M9<L9,M9>G9,Q9<P9),"BAD INPUT","OK"))) -> OK
A10: EXP_SALT_MEDIA | B10: I_PH_SALT_MEDIA | C10: R_SODIUM | D10: Sodium mass-media campaign | E10: Mean sodium intake | F10: g sodium/day | G10: 4.4 | H10: relative | J10: =SUMIF(Policy_Levers!$B$2:$B$13,B10,Policy_Levers!$K$2:$K$13) -> 0 | K10: =IF(ISBLANK(I10),J10,I10) -> 0 | L10: 3 | M10: =IF(OR(ISBLANK(G10),ISBLANK(K10)),"",IF(H10="relative",MAX(L10,G10*(1-K10)),IF(H10="absolute",MAX(L10,G10-K10),IF(H10="target",MAX(L10,K10),"")))) -> 4.4 | N10: =IF(ISBLANK(M10),"",G10-M10) -> 0 | O10: =IF(OR(ISBLANK(G10),G10=0,ISBLANK(N10)),"",N10/G10) -> 0 | P10: =Assumptions!$B$4 -> 2026 | Q10: =Assumptions!$B$5 -> 2030 | R10: =Assumptions!$B$12 -> linear | S10: WHO category + Countdown effect | T10: Ready | U10: =IF(ISBLANK(G10),"MISSING EXPOSURE",IF(ISBLANK(K10),"MISSING REDUCTION",IF(OR(M10<L10,M10>G10,Q10<P10),"BAD INPUT","OK"))) -> OK
A11: EXP_SALT_ENV | B11: I_PH_SALT_ENV | C11: R_SODIUM | D11: Supportive public-institution environment | E11: Mean sodium intake | F11: g sodium/day | G11: 4.4 | H11: relative | J11: =SUMIF(Policy_Levers!$B$2:$B$13,B11,Policy_Levers!$K$2:$K$13) -> 0.035 | K11: =IF(ISBLANK(I11),J11,I11) -> 0.035 | L11: 3 | M11: =IF(OR(ISBLANK(G11),ISBLANK(K11)),"",IF(H11="relative",MAX(L11,G11*(1-K11)),IF(H11="absolute",MAX(L11,G11-K11),IF(H11="target",MAX(L11,K11),"")))) -> 4.246 | N11: =IF(ISBLANK(M11),"",G11-M11) -> 0.154 | O11: =IF(OR(ISBLANK(G11),G11=0,ISBLANK(N11)),"",N11/G11) -> 0.035 | P11: =Assumptions!$B$4 -> 2026 | Q11: =Assumptions!$B$5 -> 2030 | R11: =Assumptions!$B$12 -> linear | S11: WHO category + Countdown effect | T11: Ready | U11: =IF(ISBLANK(G11),"MISSING EXPOSURE",IF(ISBLANK(K11),"MISSING REDUCTION",IF(OR(M11<L11,M11>G11,Q11<P11),"BAD INPUT","OK"))) -> OK
A12: EXP_TFA_POLICY | B12: I_PH_TFA_POLICY | C12: R_TFA | D12: Industrial trans-fat elimination regulation | E12: Mean industrial trans-fat intake | F12: % energy | G12: 0.0317 | H12: relative | J12: =SUMIF(Policy_Levers!$B$2:$B$13,B12,Policy_Levers!$K$2:$K$13) -> 0.5 | K12: =IF(ISBLANK(I12),J12,I12) -> 0.5 | L12: 0 | M12: =IF(OR(ISBLANK(G12),ISBLANK(K12)),"",IF(H12="relative",MAX(L12,G12*(1-K12)),IF(H12="absolute",MAX(L12,G12-K12),IF(H12="target",MAX(L12,K12),"")))) -> 0.01585 | N12: =IF(ISBLANK(M12),"",G12-M12) -> 0.01585 | O12: =IF(OR(ISBLANK(G12),G12=0,ISBLANK(N12)),"",N12/G12) -> 0.5 | P12: =Assumptions!$B$4 -> 2026 | Q12: =Assumptions!$B$5 -> 2030 | R12: =Assumptions!$B$12 -> linear | S12: WHO regulatory gap + RR | T12: RR base case; PAF optional | U12: =IF(ISBLANK(G12),"MISSING EXPOSURE",IF(ISBLANK(K12),"MISSING REDUCTION",IF(OR(M12<L12,M12>G12,Q12<P12),"BAD INPUT","OK"))) -> OK
A13: EXP_SSB_TAX | B13: I_PH_SSB_TAX | C13: R_SSB | D13: Sugar-sweetened beverage tax | E13: Mean SSB intake | F13: 8 oz servings/adult/day | G13: 0.11428571 | H13: relative | J13: =SUMIF(Policy_Levers!$B$2:$B$13,B13,Policy_Levers!$K$2:$K$13) -> 0.175 | K13: =IF(ISBLANK(I13),J13,I13) -> 0.175 | L13: 0 | M13: =IF(OR(ISBLANK(G13),ISBLANK(K13)),"",IF(H13="relative",MAX(L13,G13*(1-K13)),IF(H13="absolute",MAX(L13,G13-K13),IF(H13="target",MAX(L13,K13),"")))) -> 0.094285714 | N13: =IF(ISBLANK(M13),"",G13-M13) -> 0.02 | O13: =IF(OR(ISBLANK(G13),G13=0,ISBLANK(N13)),"",N13/G13) -> 0.175 | P13: =Assumptions!$B$4 -> 2026 | Q13: =Assumptions!$B$5 -> 2030 | R13: =Assumptions!$B$12 -> linear | S13: Lara-Castor; Widarjono | T13: GDD 2020 mean | U13: =IF(ISBLANK(G13),"MISSING EXPOSURE",IF(ISBLANK(K13),"MISSING REDUCTION",IF(OR(M13<L13,M13>G13,Q13<P13),"BAD INPUT","OK"))) -> OK

Sheet Effect_Parameters
A1: effect_id | B1: intervention_cause_key | C1: intervention_id | D1: risk_id | E1: cause_id | F1: effect_model | G1: response_key | H1: response_parameter | I1: response_value | J1: response_unit | K1: paf_value | L1: paf_required_flag | M1: paf_threshold | N1: lag_model | O1: lag_parameter | P1: transition_from | Q1: transition_to | R1: source_file | S1: source_location | T1: review_status | U1: notes | V1: map_match_count | W1: qa_status
A2: EFF_001 | B2: I_PH_TOBACCO_TAX__C_IHD | C2: I_PH_TOBACCO_TAX | D2: R_SMOKING | E2: C_IHD | F2: direct_smoking_prevalence_shift_rr | G2: RR_SMOKING_IHD | H2: RR current smoker vs non-smoker | I2: =INDEX(Risk_Response!$L$2:$L$63,MATCH(G2,Risk_Response!$A$2:$A$63,0)) -> 1.6 | J2: relative risk | L2: 0 | N2: jha_piecewise_shared_scalar | O2: =SUMIF(Assumptions!$A$2:$A$37,"tobacco_cvd_lag_rate",Assumptions!$B$2:$B$37) -> 0.0616 | P2: well | Q2: sick | R2: APCSC; Cho et al. 2024 | S2: https://doi.org/10.1093/ije/dyi104; https://doi.org/10.1056/EVIDoa2300272 | T2: Ready | U2: Direct well-to-sick incidence effect. Base timing: Jha age-sex piecewise shared scalar; lag_parameter is sensitivity-only. | V2: =COUNTIF(Intervention_Cause_Map!$A$2:$A$62,B2) -> 1 | W2: =IF(V2<>1,"MAP ERROR",IF(NOT(OR(AND(P2="well",Q2="sick"),AND(P2="sick",Q2="dead"))),"REVIEW TRANSITION",IF(AND(L2=1,OR(ISBLANK(K2),K2<0,K2>1)),"MISSING PAF",IF(R2="","MISSING SOURCE",IF(OR(T2="Ready",T2=""),"OK","REVIEW"))))) -> OK
A3: EFF_002 | B3: I_PH_TOBACCO_TAX__C_IS | C3: I_PH_TOBACCO_TAX | D3: R_SMOKING | E3: C_IS | F3: direct_smoking_prevalence_shift_rr | G3: RR_SMOKING_IS | H3: RR current smoker vs non-smoker | I3: =INDEX(Risk_Response!$L$2:$L$63,MATCH(G3,Risk_Response!$A$2:$A$63,0)) -> 1.38 | J3: relative risk | L3: 0 | N3: jha_piecewise_shared_scalar | O3: =SUMIF(Assumptions!$A$2:$A$37,"tobacco_cvd_lag_rate",Assumptions!$B$2:$B$37) -> 0.0616 | P3: well | Q3: sick | R3: APCSC; Cho et al. 2024 | S3: https://doi.org/10.1093/ije/dyi104; https://doi.org/10.1056/EVIDoa2300272 | T3: Ready | U3: Direct well-to-sick incidence effect. Base timing: Jha age-sex piecewise shared scalar; lag_parameter is sensitivity-only. | V3: =COUNTIF(Intervention_Cause_Map!$A$2:$A$62,B3) -> 1 | W3: =IF(V3<>1,"MAP ERROR",IF(NOT(OR(AND(P3="well",Q3="sick"),AND(P3="sick",Q3="dead"))),"REVIEW TRANSITION",IF(AND(L3=1,OR(ISBLANK(K3),K3<0,K3>1)),"MISSING PAF",IF(R3="","MISSING SOURCE",IF(OR(T3="Ready",T3=""),"OK","REVIEW"))))) -> OK
A4: EFF_003 | B4: I_PH_TOBACCO_TAX__C_ICH | C4: I_PH_TOBACCO_TAX | D4: R_SMOKING | E4: C_ICH | F4: direct_smoking_prevalence_shift_rr | G4: RR_SMOKING_ICH | H4: RR current smoker vs non-smoker | I4: =INDEX(Risk_Response!$L$2:$L$63,MATCH(G4,Risk_Response!$A$2:$A$63,0)) -> 1.19 | J4: relative risk | L4: 0 | N4: jha_piecewise_shared_scalar | O4: =SUMIF(Assumptions!$A$2:$A$37,"tobacco_cvd_lag_rate",Assumptions!$B$2:$B$37) -> 0.0616 | P4: well | Q4: sick | R4: APCSC; Cho et al. 2024 | S4: https://doi.org/10.1093/ije/dyi104; https://doi.org/10.1056/EVIDoa2300272 | T4: Ready | U4: Direct well-to-sick incidence effect. Base timing: Jha age-sex piecewise shared scalar; lag_parameter is sensitivity-only. | V4: =COUNTIF(Intervention_Cause_Map!$A$2:$A$62,B4) -> 1 | W4: =IF(V4<>1,"MAP ERROR",IF(NOT(OR(AND(P4="well",Q4="sick"),AND(P4="sick",Q4="dead"))),"REVIEW TRANSITION",IF(AND(L4=1,OR(ISBLANK(K4),K4<0,K4>1)),"MISSING PAF",IF(R4="","MISSING SOURCE",IF(OR(T4="Ready",T4=""),"OK","REVIEW"))))) -> OK
A5: EFF_004 | B5: I_PH_TOBACCO_TAX__C_T2DM | C5: I_PH_TOBACCO_TAX | D5: R_SMOKING | E5: C_T2DM | F5: direct_smoking_prevalence_shift_rr | G5: RR_SMOKING_T2DM | H5: RR current smoker vs non-smoker | I5: =INDEX(Risk_Response!$L$2:$L$63,MATCH(G5,Risk_Response!$A$2:$A$63,0)) -> 1.37 | J5: relative risk | L5: 0 | N5: delayed_exponential_remaining_effect | O5: =Risk_Response!$L$12 -> 0.061514457 | P5: well | Q5: sick | R5: APCSC; Pan et al. | S5: https://doi.org/10.1016/S2213-8587(15)00316-2 | T5: Ready | U5: Direct well-to-sick incidence effect. | V5: =COUNTIF(Intervention_Cause_Map!$A$2:$A$62,B5) -> 1 | W5: =IF(V5<>1,"MAP ERROR",IF(NOT(OR(AND(P5="well",Q5="sick"),AND(P5="sick",Q5="dead"))),"REVIEW TRANSITION",IF(AND(L5=1,OR(ISBLANK(K5),K5<0,K5>1)),"MISSING PAF",IF(R5="","MISSING SOURCE",IF(OR(T5="Ready",T5=""),"OK","REVIEW"))))) -> OK
A6: EFF_005 | B6: I_PH_ALCOHOL_TAX__C_IHD | C6: I_PH_ALCOHOL_TAX | D6: R_ALCOHOL | E6: C_IHD | F6: direct_loglinear_rr_per_unit_reduction | G6: RR_ALCOHOL_IHD_1L | H6: RR per 1 L/year | I6: =INDEX(Risk_Response!$L$2:$L$63,MATCH(G6,Risk_Response!$A$2:$A$63,0)) -> 1.0088804 | J6: relative risk | L6: 0 | N6: immediate_after_full_implementation | O6: 1 | P6: well | Q6: sick | R6: Wood et al. 2018 | S6: https://doi.org/10.1016/S0140-6736(18)30134-X | T6: Ready | U6: Direct well-to-sick incidence effect. | V6: =COUNTIF(Intervention_Cause_Map!$A$2:$A$62,B6) -> 1 | W6: =IF(V6<>1,"MAP ERROR",IF(NOT(OR(AND(P6="well",Q6="sick"),AND(P6="sick",Q6="dead"))),"REVIEW TRANSITION",IF(AND(L6=1,OR(ISBLANK(K6),K6<0,K6>1)),"MISSING PAF",IF(R6="","MISSING SOURCE",IF(OR(T6="Ready",T6=""),"OK","REVIEW"))))) -> OK
A7: EFF_006 | B7: I_PH_ALCOHOL_TAX__C_IS | C7: I_PH_ALCOHOL_TAX | D7: R_ALCOHOL | E7: C_IS | F7: direct_loglinear_rr_per_unit_reduction | G7: RR_ALCOHOL_IS_1L | H7: RR per 1 L/year | I7: =INDEX(Risk_Response!$L$2:$L$63,MATCH(G7,Risk_Response!$A$2:$A$63,0)) -> 1.02008 | J7: relative risk | L7: 0 | N7: immediate_after_full_implementation | O7: 1 | P7: well | Q7: sick | R7: Wood et al. 2018 | S7: https://doi.org/10.1016/S0140-6736(18)30134-X | T7: Ready | U7: Direct well-to-sick incidence effect. | V7: =COUNTIF(Intervention_Cause_Map!$A$2:$A$62,B7) -> 1 | W7: =IF(V7<>1,"MAP ERROR",IF(NOT(OR(AND(P7="well",Q7="sick"),AND(P7="sick",Q7="dead"))),"REVIEW TRANSITION",IF(AND(L7=1,OR(ISBLANK(K7),K7<0,K7>1)),"MISSING PAF",IF(R7="","MISSING SOURCE",IF(OR(T7="Ready",T7=""),"OK","REVIEW"))))) -> OK
A8: EFF_007 | B8: I_PH_ALCOHOL_TAX__C_ICH | C8: I_PH_ALCOHOL_TAX | D8: R_ALCOHOL | E8: C_ICH | F8: direct_loglinear_rr_per_unit_reduction | G8: RR_ALCOHOL_ICH_1L | H8: RR per 1 L/year | I8: =INDEX(Risk_Response!$L$2:$L$63,MATCH(G8,Risk_Response!$A$2:$A$63,0)) -> 1.02008 | J8: relative risk | L8: 0 | N8: immediate_after_full_implementation | O8: 1 | P8: well | Q8: sick | R8: Wood et al. 2018 | S8: https://doi.org/10.1016/S0140-6736(18)30134-X | T8: Ready | U8: Direct well-to-sick incidence effect. | V8: =COUNTIF(Intervention_Cause_Map!$A$2:$A$62,B8) -> 1 | W8: =IF(V8<>1,"MAP ERROR",IF(NOT(OR(AND(P8="well",Q8="sick"),AND(P8="sick",Q8="dead"))),"REVIEW TRANSITION",IF(AND(L8=1,OR(ISBLANK(K8),K8<0,K8>1)),"MISSING PAF",IF(R8="","MISSING SOURCE",IF(OR(T8="Ready",T8=""),"OK","REVIEW"))))) -> OK
A9: EFF_008 | B9: I_PH_ALCOHOL_TAX__C_HHD | C9: I_PH_ALCOHOL_TAX | D9: R_ALCOHOL | E9: C_HHD | F9: direct_loglinear_rr_per_unit_reduction | G9: RR_ALCOHOL_HHD_1L | H9: RR per 1 L/year | I9: =INDEX(Risk_Response!$L$2:$L$63,MATCH(G9,Risk_Response!$A$2:$A$63,0)) -> 1.0331775 | J9: relative risk | L9: 0 | N9: immediate_after_full_implementation | O9: 1 | P9: well | Q9: sick | R9: Wood et al. 2018 | S9: https://doi.org/10.1016/S0140-6736(18)30134-X | T9: Ready | U9: Direct well-to-sick incidence effect. | V9: =COUNTIF(Intervention_Cause_Map!$A$2:$A$62,B9) -> 1 | W9: =IF(V9<>1,"MAP ERROR",IF(NOT(OR(AND(P9="well",Q9="sick"),AND(P9="sick",Q9="dead"))),"REVIEW TRANSITION",IF(AND(L9=1,OR(ISBLANK(K9),K9<0,K9>1)),"MISSING PAF",IF(R9="","MISSING SOURCE",IF(OR(T9="Ready",T9=""),"OK","REVIEW"))))) -> OK
A10: EFF_009 | B10: I_PH_ALCOHOL_TAX__C_CMYO | C10: I_PH_ALCOHOL_TAX | D10: R_ALCOHOL | E10: C_CMYO | F10: direct_loglinear_rr_per_unit_reduction | G10: RR_ALCOHOL_CMYO_1L | H10: RR per 1 L/year | I10: =INDEX(Risk_Response!$L$2:$L$63,MATCH(G10,Risk_Response!$A$2:$A$63,0)) -> 1.0131617 | J10: relative risk | L10: 0 | N10: immediate_after_full_implementation | O10: 1 | P10: well | Q10: sick | R10: Wood et al. 2018 | S10: https://doi.org/10.1016/S0140-6736(18)30134-X | T10: Ready | U10: Direct well-to-sick incidence effect. | V10: =COUNTIF(Intervention_Cause_Map!$A$2:$A$62,B10) -> 1 | W10: =IF(V10<>1,"MAP ERROR",IF(NOT(OR(AND(P10="well",Q10="sick"),AND(P10="sick",Q10="dead"))),"REVIEW TRANSITION",IF(AND(L10=1,OR(ISBLANK(K10),K10<0,K10>1)),"MISSING PAF",IF(R10="","MISSING SOURCE",IF(OR(T10="Ready",T10=""),"OK","REVIEW"))))) -> OK
A11: EFF_010 | B11: I_PH_TOB_CLEAN_AIR__C_IHD | C11: I_PH_TOB_CLEAN_AIR | D11: R_SMOKING | E11: C_IHD | F11: direct_smoking_prevalence_shift_rr | G11: RR_SMOKING_IHD | H11: RR current smoker vs non-smoker | I11: =INDEX(Risk_Response!$L$2:$L$63,MATCH(G11,Risk_Response!$A$2:$A$63,0)) -> 1.6 | J11: relative risk | L11: 0 | N11: jha_piecewise_shared_scalar | O11: =SUMIF(Assumptions!$A$2:$A$37,"tobacco_cvd_lag_rate",Assumptions!$B$2:$B$37) -> 0.0616 | P11: well | Q11: sick | R11: APCSC; Cho et al. 2024 | S11: https://doi.org/10.1093/ije/dyi104; https://doi.org/10.1056/EVIDoa2300272 | T11: Ready | U11: Direct well-to-sick incidence effect. Base timing: Jha age-sex piecewise shared scalar; lag_parameter is sensitivity-only. | V11: =COUNTIF(Intervention_Cause_Map!$A$2:$A$62,B11) -> 1 | W11: =IF(V11<>1,"MAP ERROR",IF(NOT(OR(AND(P11="well",Q11="sick"),AND(P11="sick",Q11="dead"))),"REVIEW TRANSITION",IF(AND(L11=1,OR(ISBLANK(K11),K11<0,K11>1)),"MISSING PAF",IF(R11="","MISSING SOURCE",IF(OR(T11="Ready",T11=""),"OK","REVIEW"))))) -> OK
A12: EFF_011 | B12: I_PH_TOB_CLEAN_AIR__C_IS | C12: I_PH_TOB_CLEAN_AIR | D12: R_SMOKING | E12: C_IS | F12: direct_smoking_prevalence_shift_rr | G12: RR_SMOKING_IS | H12: RR current smoker vs non-smoker | I12: =INDEX(Risk_Response!$L$2:$L$63,MATCH(G12,Risk_Response!$A$2:$A$63,0)) -> 1.38 | J12: relative risk | L12: 0 | N12: jha_piecewise_shared_scalar | O12: =SUMIF(Assumptions!$A$2:$A$37,"tobacco_cvd_lag_rate",Assumptions!$B$2:$B$37) -> 0.0616 | P12: well | Q12: sick | R12: APCSC; Cho et al. 2024 | S12: https://doi.org/10.1093/ije/dyi104; https://doi.org/10.1056/EVIDoa2300272 | T12: Ready | U12: Direct well-to-sick incidence effect. Base timing: Jha age-sex piecewise shared scalar; lag_parameter is sensitivity-only. | V12: =COUNTIF(Intervention_Cause_Map!$A$2:$A$62,B12) -> 1 | W12: =IF(V12<>1,"MAP ERROR",IF(NOT(OR(AND(P12="well",Q12="sick"),AND(P12="sick",Q12="dead"))),"REVIEW TRANSITION",IF(AND(L12=1,OR(ISBLANK(K12),K12<0,K12>1)),"MISSING PAF",IF(R12="","MISSING SOURCE",IF(OR(T12="Ready",T12=""),"OK","REVIEW"))))) -> OK
A13: EFF_012 | B13: I_PH_TOB_CLEAN_AIR__C_ICH | C13: I_PH_TOB_CLEAN_AIR | D13: R_SMOKING | E13: C_ICH | F13: direct_smoking_prevalence_shift_rr | G13: RR_SMOKING_ICH | H13: RR current smoker vs non-smoker | I13: =INDEX(Risk_Response!$L$2:$L$63,MATCH(G13,Risk_Response!$A$2:$A$63,0)) -> 1.19 | J13: relative risk | L13: 0 | N13: jha_piecewise_shared_scalar | O13: =SUMIF(Assumptions!$A$2:$A$37,"tobacco_cvd_lag_rate",Assumptions!$B$2:$B$37) -> 0.0616 | P13: well | Q13: sick | R13: APCSC; Cho et al. 2024 | S13: https://doi.org/10.1093/ije/dyi104; https://doi.org/10.1056/EVIDoa2300272 | T13: Ready | U13: Direct well-to-sick incidence effect. Base timing: Jha age-sex piecewise shared scalar; lag_parameter is sensitivity-only. | V13: =COUNTIF(Intervention_Cause_Map!$A$2:$A$62,B13) -> 1 | W13: =IF(V13<>1,"MAP ERROR",IF(NOT(OR(AND(P13="well",Q13="sick"),AND(P13="sick",Q13="dead"))),"REVIEW TRANSITION",IF(AND(L13=1,OR(ISBLANK(K13),K13<0,K13>1)),"MISSING PAF",IF(R13="","MISSING SOURCE",IF(OR(T13="Ready",T13=""),"OK","REVIEW"))))) -> OK
A14: EFF_013 | B14: I_PH_TOB_CLEAN_AIR__C_T2DM | C14: I_PH_TOB_CLEAN_AIR | D14: R_SMOKING | E14: C_T2DM | F14: direct_smoking_prevalence_shift_rr | G14: RR_SMOKING_T2DM | H14: RR current smoker vs non-smoker | I14: =INDEX(Risk_Response!$L$2:$L$63,MATCH(G14,Risk_Response!$A$2:$A$63,0)) -> 1.37 | J14: relative risk | L14: 0 | N14: delayed_exponential_remaining_effect | O14: =Risk_Response!$L$12 -> 0.061514457 | P14: well | Q14: sick | R14: APCSC; Pan et al. | S14: https://doi.org/10.1016/S2213-8587(15)00316-2 | T14: Ready | U14: Direct well-to-sick incidence effect. | V14: =COUNTIF(Intervention_Cause_Map!$A$2:$A$62,B14) -> 1 | W14: =IF(V14<>1,"MAP ERROR",IF(NOT(OR(AND(P14="well",Q14="sick"),AND(P14="sick",Q14="dead"))),"REVIEW TRANSITION",IF(AND(L14=1,OR(ISBLANK(K14),K14<0,K14>1)),"MISSING PAF",IF(R14="","MISSING SOURCE",IF(OR(T14="Ready",T14=""),"OK","REVIEW"))))) -> OK
A15: EFF_014 | B15: I_PH_TOB_MEDIA__C_IHD | C15: I_PH_TOB_MEDIA | D15: R_SMOKING | E15: C_IHD | F15: direct_smoking_prevalence_shift_rr | G15: RR_SMOKING_IHD | H15: RR current smoker vs non-smoker | I15: =INDEX(Risk_Response!$L$2:$L$63,MATCH(G15,Risk_Response!$A$2:$A$63,0)) -> 1.6 | J15: relative risk | L15: 0 | N15: jha_piecewise_shared_scalar | O15: =SUMIF(Assumptions!$A$2:$A$37,"tobacco_cvd_lag_rate",Assumptions!$B$2:$B$37) -> 0.0616 | P15: well | Q15: sick | R15: APCSC; Cho et al. 2024 | S15: https://doi.org/10.1093/ije/dyi104; https://doi.org/10.1056/EVIDoa2300272 | T15: Ready | U15: Direct well-to-sick incidence effect. Base timing: Jha age-sex piecewise shared scalar; lag_parameter is sensitivity-only. | V15: =COUNTIF(Intervention_Cause_Map!$A$2:$A$62,B15) -> 1 | W15: =IF(V15<>1,"MAP ERROR",IF(NOT(OR(AND(P15="well",Q15="sick"),AND(P15="sick",Q15="dead"))),"REVIEW TRANSITION",IF(AND(L15=1,OR(ISBLANK(K15),K15<0,K15>1)),"MISSING PAF",IF(R15="","MISSING SOURCE",IF(OR(T15="Ready",T15=""),"OK","REVIEW"))))) -> OK
A16: EFF_015 | B16: I_PH_TOB_MEDIA__C_IS | C16: I_PH_TOB_MEDIA | D16: R_SMOKING | E16: C_IS | F16: direct_smoking_prevalence_shift_rr | G16: RR_SMOKING_IS | H16: RR current smoker vs non-smoker | I16: =INDEX(Risk_Response!$L$2:$L$63,MATCH(G16,Risk_Response!$A$2:$A$63,0)) -> 1.38 | J16: relative risk | L16: 0 | N16: jha_piecewise_shared_scalar | O16: =SUMIF(Assumptions!$A$2:$A$37,"tobacco_cvd_lag_rate",Assumptions!$B$2:$B$37) -> 0.0616 | P16: well | Q16: sick | R16: APCSC; Cho et al. 2024 | S16: https://doi.org/10.1093/ije/dyi104; https://doi.org/10.1056/EVIDoa2300272 | T16: Ready | U16: Direct well-to-sick incidence effect. Base timing: Jha age-sex piecewise shared scalar; lag_parameter is sensitivity-only. | V16: =COUNTIF(Intervention_Cause_Map!$A$2:$A$62,B16) -> 1 | W16: =IF(V16<>1,"MAP ERROR",IF(NOT(OR(AND(P16="well",Q16="sick"),AND(P16="sick",Q16="dead"))),"REVIEW TRANSITION",IF(AND(L16=1,OR(ISBLANK(K16),K16<0,K16>1)),"MISSING PAF",IF(R16="","MISSING SOURCE",IF(OR(T16="Ready",T16=""),"OK","REVIEW"))))) -> OK
A17: EFF_016 | B17: I_PH_TOB_MEDIA__C_ICH | C17: I_PH_TOB_MEDIA | D17: R_SMOKING | E17: C_ICH | F17: direct_smoking_prevalence_shift_rr | G17: RR_SMOKING_ICH | H17: RR current smoker vs non-smoker | I17: =INDEX(Risk_Response!$L$2:$L$63,MATCH(G17,Risk_Response!$A$2:$A$63,0)) -> 1.19 | J17: relative risk | L17: 0 | N17: jha_piecewise_shared_scalar | O17: =SUMIF(Assumptions!$A$2:$A$37,"tobacco_cvd_lag_rate",Assumptions!$B$2:$B$37) -> 0.0616 | P17: well | Q17: sick | R17: APCSC; Cho et al. 2024 | S17: https://doi.org/10.1093/ije/dyi104; https://doi.org/10.1056/EVIDoa2300272 | T17: Ready | U17: Direct well-to-sick incidence effect. Base timing: Jha age-sex piecewise shared scalar; lag_parameter is sensitivity-only. | V17: =COUNTIF(Intervention_Cause_Map!$A$2:$A$62,B17) -> 1 | W17: =IF(V17<>1,"MAP ERROR",IF(NOT(OR(AND(P17="well",Q17="sick"),AND(P17="sick",Q17="dead"))),"REVIEW TRANSITION",IF(AND(L17=1,OR(ISBLANK(K17),K17<0,K17>1)),"MISSING PAF",IF(R17="","MISSING SOURCE",IF(OR(T17="Ready",T17=""),"OK","REVIEW"))))) -> OK
A18: EFF_017 | B18: I_PH_TOB_MEDIA__C_T2DM | C18: I_PH_TOB_MEDIA | D18: R_SMOKING | E18: C_T2DM | F18: direct_smoking_prevalence_shift_rr | G18: RR_SMOKING_T2DM | H18: RR current smoker vs non-smoker | I18: =INDEX(Risk_Response!$L$2:$L$63,MATCH(G18,Risk_Response!$A$2:$A$63,0)) -> 1.37 | J18: relative risk | L18: 0 | N18: delayed_exponential_remaining_effect | O18: =Risk_Response!$L$12 -> 0.061514457 | P18: well | Q18: sick | R18: APCSC; Pan et al. | S18: https://doi.org/10.1016/S2213-8587(15)00316-2 | T18: Ready | U18: Direct well-to-sick incidence effect. | V18: =COUNTIF(Intervention_Cause_Map!$A$2:$A$62,B18) -> 1 | W18: =IF(V18<>1,"MAP ERROR",IF(NOT(OR(AND(P18="well",Q18="sick"),AND(P18="sick",Q18="dead"))),"REVIEW TRANSITION",IF(AND(L18=1,OR(ISBLANK(K18),K18<0,K18>1)),"MISSING PAF",IF(R18="","MISSING SOURCE",IF(OR(T18="Ready",T18=""),"OK","REVIEW"))))) -> OK
A19: EFF_018 | B19: I_PH_TOB_AD_BAN__C_IHD | C19: I_PH_TOB_AD_BAN | D19: R_SMOKING | E19: C_IHD | F19: direct_smoking_prevalence_shift_rr | G19: RR_SMOKING_IHD | H19: RR current smoker vs non-smoker | I19: =INDEX(Risk_Response!$L$2:$L$63,MATCH(G19,Risk_Response!$A$2:$A$63,0)) -> 1.6 | J19: relative risk | L19: 0 | N19: jha_piecewise_shared_scalar | O19: =SUMIF(Assumptions!$A$2:$A$37,"tobacco_cvd_lag_rate",Assumptions!$B$2:$B$37) -> 0.0616 | P19: well | Q19: sick | R19: APCSC; Cho et al. 2024 | S19: https://doi.org/10.1093/ije/dyi104; https://doi.org/10.1056/EVIDoa2300272 | T19: Ready | U19: Direct well-to-sick incidence effect. Base timing: Jha age-sex piecewise shared scalar; lag_parameter is sensitivity-only. | V19: =COUNTIF(Intervention_Cause_Map!$A$2:$A$62,B19) -> 1 | W19: =IF(V19<>1,"MAP ERROR",IF(NOT(OR(AND(P19="well",Q19="sick"),AND(P19="sick",Q19="dead"))),"REVIEW TRANSITION",IF(AND(L19=1,OR(ISBLANK(K19),K19<0,K19>1)),"MISSING PAF",IF(R19="","MISSING SOURCE",IF(OR(T19="Ready",T19=""),"OK","REVIEW"))))) -> OK
A20: EFF_019 | B20: I_PH_TOB_AD_BAN__C_IS | C20: I_PH_TOB_AD_BAN | D20: R_SMOKING | E20: C_IS | F20: direct_smoking_prevalence_shift_rr | G20: RR_SMOKING_IS | H20: RR current smoker vs non-smoker | I20: =INDEX(Risk_Response!$L$2:$L$63,MATCH(G20,Risk_Response!$A$2:$A$63,0)) -> 1.38 | J20: relative risk | L20: 0 | N20: jha_piecewise_shared_scalar | O20: =SUMIF(Assumptions!$A$2:$A$37,"tobacco_cvd_lag_rate",Assumptions!$B$2:$B$37) -> 0.0616 | P20: well | Q20: sick | R20: APCSC; Cho et al. 2024 | S20: https://doi.org/10.1093/ije/dyi104; https://doi.org/10.1056/EVIDoa2300272 | T20: Ready | U20: Direct well-to-sick incidence effect. Base timing: Jha age-sex piecewise shared scalar; lag_parameter is sensitivity-only. | V20: =COUNTIF(Intervention_Cause_Map!$A$2:$A$62,B20) -> 1 | W20: =IF(V20<>1,"MAP ERROR",IF(NOT(OR(AND(P20="well",Q20="sick"),AND(P20="sick",Q20="dead"))),"REVIEW TRANSITION",IF(AND(L20=1,OR(ISBLANK(K20),K20<0,K20>1)),"MISSING PAF",IF(R20="","MISSING SOURCE",IF(OR(T20="Ready",T20=""),"OK","REVIEW"))))) -> OK
A21: EFF_020 | B21: I_PH_TOB_AD_BAN__C_ICH | C21: I_PH_TOB_AD_BAN | D21: R_SMOKING | E21: C_ICH | F21: direct_smoking_prevalence_shift_rr | G21: RR_SMOKING_ICH | H21: RR current smoker vs non-smoker | I21: =INDEX(Risk_Response!$L$2:$L$63,MATCH(G21,Risk_Response!$A$2:$A$63,0)) -> 1.19 | J21: relative risk | L21: 0 | N21: jha_piecewise_shared_scalar | O21: =SUMIF(Assumptions!$A$2:$A$37,"tobacco_cvd_lag_rate",Assumptions!$B$2:$B$37) -> 0.0616 | P21: well | Q21: sick | R21: APCSC; Cho et al. 2024 | S21: https://doi.org/10.1093/ije/dyi104; https://doi.org/10.1056/EVIDoa2300272 | T21: Ready | U21: Direct well-to-sick incidence effect. Base timing: Jha age-sex piecewise shared scalar; lag_parameter is sensitivity-only. | V21: =COUNTIF(Intervention_Cause_Map!$A$2:$A$62,B21) -> 1 | W21: =IF(V21<>1,"MAP ERROR",IF(NOT(OR(AND(P21="well",Q21="sick"),AND(P21="sick",Q21="dead"))),"REVIEW TRANSITION",IF(AND(L21=1,OR(ISBLANK(K21),K21<0,K21>1)),"MISSING PAF",IF(R21="","MISSING SOURCE",IF(OR(T21="Ready",T21=""),"OK","REVIEW"))))) -> OK
A22: EFF_021 | B22: I_PH_TOB_AD_BAN__C_T2DM | C22: I_PH_TOB_AD_BAN | D22: R_SMOKING | E22: C_T2DM | F22: direct_smoking_prevalence_shift_rr | G22: RR_SMOKING_T2DM | H22: RR current smoker vs non-smoker | I22: =INDEX(Risk_Response!$L$2:$L$63,MATCH(G22,Risk_Response!$A$2:$A$63,0)) -> 1.37 | J22: relative risk | L22: 0 | N22: delayed_exponential_remaining_effect | O22: =Risk_Response!$L$12 -> 0.061514457 | P22: well | Q22: sick | R22: APCSC; Pan et al. | S22: https://doi.org/10.1016/S2213-8587(15)00316-2 | T22: Ready | U22: Direct well-to-sick incidence effect. | V22: =COUNTIF(Intervention_Cause_Map!$A$2:$A$62,B22) -> 1 | W22: =IF(V22<>1,"MAP ERROR",IF(NOT(OR(AND(P22="well",Q22="sick"),AND(P22="sick",Q22="dead"))),"REVIEW TRANSITION",IF(AND(L22=1,OR(ISBLANK(K22),K22<0,K22>1)),"MISSING PAF",IF(R22="","MISSING SOURCE",IF(OR(T22="Ready",T22=""),"OK","REVIEW"))))) -> OK
A23: EFF_022 | B23: I_PH_ALCOHOL_POLICY__C_IHD | C23: I_PH_ALCOHOL_POLICY | D23: R_ALCOHOL | E23: C_IHD | F23: direct_loglinear_rr_per_unit_reduction | G23: RR_ALCOHOL_IHD_1L | H23: RR per 1 L/year | I23: =INDEX(Risk_Response!$L$2:$L$63,MATCH(G23,Risk_Response!$A$2:$A$63,0)) -> 1.0088804 | J23: relative risk | L23: 0 | N23: immediate_after_full_implementation | O23: 1 | P23: well | Q23: sick | R23: Wood et al. 2018 | S23: https://doi.org/10.1016/S0140-6736(18)30134-X | T23: Ready | U23: Direct well-to-sick incidence effect. | V23: =COUNTIF(Intervention_Cause_Map!$A$2:$A$62,B23) -> 1 | W23: =IF(V23<>1,"MAP ERROR",IF(NOT(OR(AND(P23="well",Q23="sick"),AND(P23="sick",Q23="dead"))),"REVIEW TRANSITION",IF(AND(L23=1,OR(ISBLANK(K23),K23<0,K23>1)),"MISSING PAF",IF(R23="","MISSING SOURCE",IF(OR(T23="Ready",T23=""),"OK","REVIEW"))))) -> OK
A24: EFF_023 | B24: I_PH_ALCOHOL_POLICY__C_IS | C24: I_PH_ALCOHOL_POLICY | D24: R_ALCOHOL | E24: C_IS | F24: direct_loglinear_rr_per_unit_reduction | G24: RR_ALCOHOL_IS_1L | H24: RR per 1 L/year | I24: =INDEX(Risk_Response!$L$2:$L$63,MATCH(G24,Risk_Response!$A$2:$A$63,0)) -> 1.02008 | J24: relative risk | L24: 0 | N24: immediate_after_full_implementation | O24: 1 | P24: well | Q24: sick | R24: Wood et al. 2018 | S24: https://doi.org/10.1016/S0140-6736(18)30134-X | T24: Ready | U24: Direct well-to-sick incidence effect. | V24: =COUNTIF(Intervention_Cause_Map!$A$2:$A$62,B24) -> 1 | W24: =IF(V24<>1,"MAP ERROR",IF(NOT(OR(AND(P24="well",Q24="sick"),AND(P24="sick",Q24="dead"))),"REVIEW TRANSITION",IF(AND(L24=1,OR(ISBLANK(K24),K24<0,K24>1)),"MISSING PAF",IF(R24="","MISSING SOURCE",IF(OR(T24="Ready",T24=""),"OK","REVIEW"))))) -> OK
A25: EFF_024 | B25: I_PH_ALCOHOL_POLICY__C_ICH | C25: I_PH_ALCOHOL_POLICY | D25: R_ALCOHOL | E25: C_ICH | F25: direct_loglinear_rr_per_unit_reduction | G25: RR_ALCOHOL_ICH_1L | H25: RR per 1 L/year | I25: =INDEX(Risk_Response!$L$2:$L$63,MATCH(G25,Risk_Response!$A$2:$A$63,0)) -> 1.02008 | J25: relative risk | L25: 0 | N25: immediate_after_full_implementation | O25: 1 | P25: well | Q25: sick | R25: Wood et al. 2018 | S25: https://doi.org/10.1016/S0140-6736(18)30134-X | T25: Ready | U25: Direct well-to-sick incidence effect. | V25: =COUNTIF(Intervention_Cause_Map!$A$2:$A$62,B25) -> 1 | W25: =IF(V25<>1,"MAP ERROR",IF(NOT(OR(AND(P25="well",Q25="sick"),AND(P25="sick",Q25="dead"))),"REVIEW TRANSITION",IF(AND(L25=1,OR(ISBLANK(K25),K25<0,K25>1)),"MISSING PAF",IF(R25="","MISSING SOURCE",IF(OR(T25="Ready",T25=""),"OK","REVIEW"))))) -> OK
A26: EFF_025 | B26: I_PH_ALCOHOL_POLICY__C_HHD | C26: I_PH_ALCOHOL_POLICY | D26: R_ALCOHOL | E26: C_HHD | F26: direct_loglinear_rr_per_unit_reduction | G26: RR_ALCOHOL_HHD_1L | H26: RR per 1 L/year | I26: =INDEX(Risk_Response!$L$2:$L$63,MATCH(G26,Risk_Response!$A$2:$A$63,0)) -> 1.0331775 | J26: relative risk | L26: 0 | N26: immediate_after_full_implementation | O26: 1 | P26: well | Q26: sick | R26: Wood et al. 2018 | S26: https://doi.org/10.1016/S0140-6736(18)30134-X | T26: Ready | U26: Direct well-to-sick incidence effect. | V26: =COUNTIF(Intervention_Cause_Map!$A$2:$A$62,B26) -> 1 | W26: =IF(V26<>1,"MAP ERROR",IF(NOT(OR(AND(P26="well",Q26="sick"),AND(P26="sick",Q26="dead"))),"REVIEW TRANSITION",IF(AND(L26=1,OR(ISBLANK(K26),K26<0,K26>1)),"MISSING PAF",IF(R26="","MISSING SOURCE",IF(OR(T26="Ready",T26=""),"OK","REVIEW"))))) -> OK
A27: EFF_026 | B27: I_PH_ALCOHOL_POLICY__C_CMYO | C27: I_PH_ALCOHOL_POLICY | D27: R_ALCOHOL | E27: C_CMYO | F27: direct_loglinear_rr_per_unit_reduction | G27: RR_ALCOHOL_CMYO_1L | H27: RR per 1 L/year | I27: =INDEX(Risk_Response!$L$2:$L$63,MATCH(G27,Risk_Response!$A$2:$A$63,0)) -> 1.0131617 | J27: relative risk | L27: 0 | N27: immediate_after_full_implementation | O27: 1 | P27: well | Q27: sick | R27: Wood et al. 2018 | S27: https://doi.org/10.1016/S0140-6736(18)30134-X | T27: Ready | U27: Direct well-to-sick incidence effect. | V27: =COUNTIF(Intervention_Cause_Map!$A$2:$A$62,B27) -> 1 | W27: =IF(V27<>1,"MAP ERROR",IF(NOT(OR(AND(P27="well",Q27="sick"),AND(P27="sick",Q27="dead"))),"REVIEW TRANSITION",IF(AND(L27=1,OR(ISBLANK(K27),K27<0,K27>1)),"MISSING PAF",IF(R27="","MISSING SOURCE",IF(OR(T27="Ready",T27=""),"OK","REVIEW"))))) -> OK
A28: EFF_027 | B28: I_PH_SALT_REFORM__C_IHD | C28: I_PH_SALT_REFORM | D28: R_SODIUM | E28: C_IHD | F28: direct_loglinear_rr_per_unit_reduction | G28: RR_SODIUM_1G | H28: RR per 1 g sodium/day | I28: =INDEX(Risk_Response!$L$2:$L$63,MATCH(G28,Risk_Response!$A$2:$A$63,0)) -> 1.06 | J28: relative risk | L28: 0 | N28: immediate_after_full_implementation | O28: 1 | P28: well | Q28: sick | R28: Watkins 2022 | S28: p 33 | T28: Ready | U28: Direct well-to-sick incidence effect. | V28: =COUNTIF(Intervention_Cause_Map!$A$2:$A$62,B28) -> 1 | W28: =IF(V28<>1,"MAP ERROR",IF(NOT(OR(AND(P28="well",Q28="sick"),AND(P28="sick",Q28="dead"))),"REVIEW TRANSITION",IF(AND(L28=1,OR(ISBLANK(K28),K28<0,K28>1)),"MISSING PAF",IF(R28="","MISSING SOURCE",IF(OR(T28="Ready",T28=""),"OK","REVIEW"))))) -> OK
A29: EFF_028 | B29: I_PH_SALT_REFORM__C_IS | C29: I_PH_SALT_REFORM | D29: R_SODIUM | E29: C_IS | F29: direct_loglinear_rr_per_unit_reduction | G29: RR_SODIUM_1G | H29: RR per 1 g sodium/day | I29: =INDEX(Risk_Response!$L$2:$L$63,MATCH(G29,Risk_Response!$A$2:$A$63,0)) -> 1.06 | J29: relative risk | L29: 0 | N29: immediate_after_full_implementation | O29: 1 | P29: well | Q29: sick | R29: Watkins 2022 | S29: p 33 | T29: Ready | U29: Direct well-to-sick incidence effect. | V29: =COUNTIF(Intervention_Cause_Map!$A$2:$A$62,B29) -> 1 | W29: =IF(V29<>1,"MAP ERROR",IF(NOT(OR(AND(P29="well",Q29="sick"),AND(P29="sick",Q29="dead"))),"REVIEW TRANSITION",IF(AND(L29=1,OR(ISBLANK(K29),K29<0,K29>1)),"MISSING PAF",IF(R29="","MISSING SOURCE",IF(OR(T29="Ready",T29=""),"OK","REVIEW"))))) -> OK
A30: EFF_029 | B30: I_PH_SALT_REFORM__C_ICH | C30: I_PH_SALT_REFORM | D30: R_SODIUM | E30: C_ICH | F30: direct_loglinear_rr_per_unit_reduction | G30: RR_SODIUM_1G | H30: RR per 1 g sodium/day | I30: =INDEX(Risk_Response!$L$2:$L$63,MATCH(G30,Risk_Response!$A$2:$A$63,0)) -> 1.06 | J30: relative risk | L30: 0 | N30: immediate_after_full_implementation | O30: 1 | P30: well | Q30: sick | R30: Watkins 2022 | S30: p 33 | T30: Ready | U30: Direct well-to-sick incidence effect. | V30: =COUNTIF(Intervention_Cause_Map!$A$2:$A$62,B30) -> 1 | W30: =IF(V30<>1,"MAP ERROR",IF(NOT(OR(AND(P30="well",Q30="sick"),AND(P30="sick",Q30="dead"))),"REVIEW TRANSITION",IF(AND(L30=1,OR(ISBLANK(K30),K30<0,K30>1)),"MISSING PAF",IF(R30="","MISSING SOURCE",IF(OR(T30="Ready",T30=""),"OK","REVIEW"))))) -> OK
A31: EFF_030 | B31: I_PH_SALT_REFORM__C_HHD | C31: I_PH_SALT_REFORM | D31: R_SODIUM | E31: C_HHD | F31: direct_loglinear_rr_per_unit_reduction | G31: RR_SODIUM_1G | H31: RR per 1 g sodium/day | I31: =INDEX(Risk_Response!$L$2:$L$63,MATCH(G31,Risk_Response!$A$2:$A$63,0)) -> 1.06 | J31: relative risk | L31: 0 | N31: immediate_after_full_implementation | O31: 1 | P31: well | Q31: sick | R31: Watkins 2022 | S31: p 33 | T31: Ready | U31: Direct well-to-sick incidence effect. | V31: =COUNTIF(Intervention_Cause_Map!$A$2:$A$62,B31) -> 1 | W31: =IF(V31<>1,"MAP ERROR",IF(NOT(OR(AND(P31="well",Q31="sick"),AND(P31="sick",Q31="dead"))),"REVIEW TRANSITION",IF(AND(L31=1,OR(ISBLANK(K31),K31<0,K31>1)),"MISSING PAF",IF(R31="","MISSING SOURCE",IF(OR(T31="Ready",T31=""),"OK","REVIEW"))))) -> OK
A32: EFF_031 | B32: I_PH_SALT_FOPL__C_IHD | C32: I_PH_SALT_FOPL | D32: R_SODIUM | E32: C_IHD | F32: direct_loglinear_rr_per_unit_reduction | G32: RR_SODIUM_1G | H32: RR per 1 g sodium/day | I32: =INDEX(Risk_Response!$L$2:$L$63,MATCH(G32,Risk_Response!$A$2:$A$63,0)) -> 1.06 | J32: relative risk | L32: 0 | N32: immediate_after_full_implementation | O32: 1 | P32: well | Q32: sick | R32: Watkins 2022 | S32: p 33 | T32: Ready | U32: Direct well-to-sick incidence effect. | V32: =COUNTIF(Intervention_Cause_Map!$A$2:$A$62,B32) -> 1 | W32: =IF(V32<>1,"MAP ERROR",IF(NOT(OR(AND(P32="well",Q32="sick"),AND(P32="sick",Q32="dead"))),"REVIEW TRANSITION",IF(AND(L32=1,OR(ISBLANK(K32),K32<0,K32>1)),"MISSING PAF",IF(R32="","MISSING SOURCE",IF(OR(T32="Ready",T32=""),"OK","REVIEW"))))) -> OK
A33: EFF_032 | B33: I_PH_SALT_FOPL__C_IS | C33: I_PH_SALT_FOPL | D33: R_SODIUM | E33: C_IS | F33: direct_loglinear_rr_per_unit_reduction | G33: RR_SODIUM_1G | H33: RR per 1 g sodium/day | I33: =INDEX(Risk_Response!$L$2:$L$63,MATCH(G33,Risk_Response!$A$2:$A$63,0)) -> 1.06 | J33: relative risk | L33: 0 | N33: immediate_after_full_implementation | O33: 1 | P33: well | Q33: sick | R33: Watkins 2022 | S33: p 33 | T33: Ready | U33: Direct well-to-sick incidence effect. | V33: =COUNTIF(Intervention_Cause_Map!$A$2:$A$62,B33) -> 1 | W33: =IF(V33<>1,"MAP ERROR",IF(NOT(OR(AND(P33="well",Q33="sick"),AND(P33="sick",Q33="dead"))),"REVIEW TRANSITION",IF(AND(L33=1,OR(ISBLANK(K33),K33<0,K33>1)),"MISSING PAF",IF(R33="","MISSING SOURCE",IF(OR(T33="Ready",T33=""),"OK","REVIEW"))))) -> OK
A34: EFF_033 | B34: I_PH_SALT_FOPL__C_ICH | C34: I_PH_SALT_FOPL | D34: R_SODIUM | E34: C_ICH | F34: direct_loglinear_rr_per_unit_reduction | G34: RR_SODIUM_1G | H34: RR per 1 g sodium/day | I34: =INDEX(Risk_Response!$L$2:$L$63,MATCH(G34,Risk_Response!$A$2:$A$63,0)) -> 1.06 | J34: relative risk | L34: 0 | N34: immediate_after_full_implementation | O34: 1 | P34: well | Q34: sick | R34: Watkins 2022 | S34: p 33 | T34: Ready | U34: Direct well-to-sick incidence effect. | V34: =COUNTIF(Intervention_Cause_Map!$A$2:$A$62,B34) -> 1 | W34: =IF(V34<>1,"MAP ERROR",IF(NOT(OR(AND(P34="well",Q34="sick"),AND(P34="sick",Q34="dead"))),"REVIEW TRANSITION",IF(AND(L34=1,OR(ISBLANK(K34),K34<0,K34>1)),"MISSING PAF",IF(R34="","MISSING SOURCE",IF(OR(T34="Ready",T34=""),"OK","REVIEW"))))) -> OK
... A43: EFF_042 | B43: I_PH_SALT_ENV__C_HHD | C43: I_PH_SALT_ENV | D43: R_SODIUM | E43: C_HHD | F43: direct_loglinear_rr_per_unit_reduction | G43: RR_SODIUM_1G | H43: RR per 1 g sodium/day | I43: =INDEX(Risk_Response!$L$2:$L$63,MATCH(G43,Risk_Response!$A$2:$A$63,0)) -> 1.06 | J43: relative risk | L43: 0 | N43: immediate_after_full_implementation | O43: 1 | P43: well | Q43: sick | R43: Watkins 2022 | S43: p 33 | T43: Ready | U43: Direct well-to-sick incidence effect. | V43: =COUNTIF(Intervention_Cause_Map!$A$2:$A$62,B43) -> 1 | W43: =IF(V43<>1,"MAP ERROR",IF(NOT(OR(AND(P43="well",Q43="sick"),AND(P43="sick",Q43="dead"))),"REVIEW TRANSITION",IF(AND(L43=1,OR(ISBLANK(K43),K43<0,K43>1)),"MISSING PAF",IF(R43="","MISSING SOURCE",IF(OR(T43="Ready",T43=""),"OK","REVIEW"))))) -> OK
A44: EFF_043 | B44: I_PH_TFA_POLICY__C_IHD | C44: I_PH_TFA_POLICY | D44: R_TFA | E44: C_IHD | F44: =IF(Assumptions!$B$27="PAF","tfa_attributable_ihd_PAF_x_regulatory_gap","direct_loglinear_rr_per_unit_reduction") -> direct_loglinear_rr_per_unit_reduction | G44: =IF(Assumptions!$B$27="PAF","PAF_TFA_IHD_OPTIONAL","RR_TFA_IHD_1PCT") -> RR_TFA_IHD_1PCT | H44: =IF(Assumptions!$B$27="PAF","Optional IHD PAF","RR per 1 percentage-point energy/day") -> RR per 1 percentage-point energy/day | I44: =INDEX(Risk_Response!$L$2:$L$63,MATCH(G44,Risk_Response!$A$2:$A$63,0)) -> 1.1 | J44: =IF(Assumptions!$B$27="PAF","proportion","relative risk") -> relative risk | K44: =IF(Assumptions!$B$27="PAF",Assumptions!$B$28,"") | L44: =IF(Assumptions!$B$27="PAF",1,0) -> 0 | N44: immediate_after_full_implementation | O44: 1 | P44: well | Q44: sick | R44: Kontis et al.; Wang et al. | S44: https://www.ahajournals.org/doi/10.1161/CIRCULATIONAHA.118.038160; https://www.ahajournals.org/doi/10.1161/JAHA.115.002891 | T44: Ready | U44: RR base case: sqrt(1.21) per 1% energy; PAF optional. | V44: =COUNTIF(Intervention_Cause_Map!$A$2:$A$62,B44) -> 1 | W44: =IF(V44<>1,"MAP ERROR",IF(NOT(OR(AND(P44="well",Q44="sick"),AND(P44="sick",Q44="dead"))),"REVIEW TRANSITION",IF(AND(L44=1,OR(ISBLANK(K44),K44<0,K44>1)),"MISSING PAF",IF(R44="","MISSING SOURCE",IF(OR(T44="Ready",T44=""),"OK","REVIEW"))))) -> OK
A45: EFF_044 | B45: I_PH_SSB_TAX__C_IHD | C45: I_PH_SSB_TAX | D45: R_SSB | E45: C_IHD | F45: direct_loglinear_rr_per_unit_reduction | G45: RR_SSB_IHD_1SERV | H45: RR per daily serving | I45: =INDEX(Risk_Response!$L$2:$L$63,MATCH(G45,Risk_Response!$A$2:$A$63,0)) -> 1.14 | J45: relative risk | L45: 0 | N45: immediate_after_full_implementation | O45: 1 | P45: well | Q45: sick | R45: Lara-Castor et al.; proxy study where noted | S45: https://doi.org/10.1038/s41591-024-03345-4 | T45: Ready | U45: Direct well-to-sick incidence effect. | V45: =COUNTIF(Intervention_Cause_Map!$A$2:$A$62,B45) -> 1 | W45: =IF(V45<>1,"MAP ERROR",IF(NOT(OR(AND(P45="well",Q45="sick"),AND(P45="sick",Q45="dead"))),"REVIEW TRANSITION",IF(AND(L45=1,OR(ISBLANK(K45),K45<0,K45>1)),"MISSING PAF",IF(R45="","MISSING SOURCE",IF(OR(T45="Ready",T45=""),"OK","REVIEW"))))) -> OK
A46: EFF_045 | B46: I_PH_SSB_TAX__C_IS | C46: I_PH_SSB_TAX | D46: R_SSB | E46: C_IS | F46: direct_loglinear_rr_per_unit_reduction | G46: RR_SSB_IS_1SERV | H46: RR per daily serving | I46: =INDEX(Risk_Response!$L$2:$L$63,MATCH(G46,Risk_Response!$A$2:$A$63,0)) -> 1.07 | J46: relative risk | L46: 0 | N46: immediate_after_full_implementation | O46: 1 | P46: well | Q46: sick | R46: Lara-Castor et al.; proxy study where noted | S46: https://doi.org/10.1038/s41591-024-03345-4 | T46: Ready | U46: Direct well-to-sick incidence effect. | V46: =COUNTIF(Intervention_Cause_Map!$A$2:$A$62,B46) -> 1 | W46: =IF(V46<>1,"MAP ERROR",IF(NOT(OR(AND(P46="well",Q46="sick"),AND(P46="sick",Q46="dead"))),"REVIEW TRANSITION",IF(AND(L46=1,OR(ISBLANK(K46),K46<0,K46>1)),"MISSING PAF",IF(R46="","MISSING SOURCE",IF(OR(T46="Ready",T46=""),"OK","REVIEW"))))) -> OK
A47: EFF_046 | B47: I_PH_SSB_TAX__C_ICH | C47: I_PH_SSB_TAX | D47: R_SSB | E47: C_ICH | F47: direct_loglinear_rr_per_unit_reduction | G47: RR_SSB_ICH_1SERV_PROXY | H47: RR per daily serving | I47: =INDEX(Risk_Response!$L$2:$L$63,MATCH(G47,Risk_Response!$A$2:$A$63,0)) -> 1.08 | J47: relative risk | L47: 0 | N47: immediate_after_full_implementation | O47: 1 | P47: well | Q47: sick | R47: Lara-Castor et al.; proxy study where noted | S47: https://doi.org/10.1016/j.advnut.2022.12.002 | T47: Ready | U47: Direct well-to-sick incidence effect. | V47: =COUNTIF(Intervention_Cause_Map!$A$2:$A$62,B47) -> 1 | W47: =IF(V47<>1,"MAP ERROR",IF(NOT(OR(AND(P47="well",Q47="sick"),AND(P47="sick",Q47="dead"))),"REVIEW TRANSITION",IF(AND(L47=1,OR(ISBLANK(K47),K47<0,K47>1)),"MISSING PAF",IF(R47="","MISSING SOURCE",IF(OR(T47="Ready",T47=""),"OK","REVIEW"))))) -> OK
A48: EFF_047 | B48: I_PH_SSB_TAX__C_HHD | C48: I_PH_SSB_TAX | D48: R_SSB | E48: C_HHD | F48: direct_loglinear_rr_per_unit_reduction | G48: RR_SSB_HHD_1SERV_PROXY | H48: RR per daily serving | I48: =INDEX(Risk_Response!$L$2:$L$63,MATCH(G48,Risk_Response!$A$2:$A$63,0)) -> 1.1 | J48: relative risk | L48: 0 | N48: immediate_after_full_implementation | O48: 1 | P48: well | Q48: sick | R48: Lara-Castor et al.; proxy study where noted | S48: https://doi.org/10.1007/s10654-020-00655-y | T48: Ready | U48: Direct well-to-sick incidence effect. | V48: =COUNTIF(Intervention_Cause_Map!$A$2:$A$62,B48) -> 1 | W48: =IF(V48<>1,"MAP ERROR",IF(NOT(OR(AND(P48="well",Q48="sick"),AND(P48="sick",Q48="dead"))),"REVIEW TRANSITION",IF(AND(L48=1,OR(ISBLANK(K48),K48<0,K48>1)),"MISSING PAF",IF(R48="","MISSING SOURCE",IF(OR(T48="Ready",T48=""),"OK","REVIEW"))))) -> OK
A49: EFF_048 | B49: I_PH_SSB_TAX__C_T2DM | C49: I_PH_SSB_TAX | D49: R_SSB | E49: C_T2DM | F49: direct_loglinear_rr_per_unit_reduction | G49: RR_SSB_T2DM_1SERV | H49: RR per daily serving | I49: =INDEX(Risk_Response!$L$2:$L$63,MATCH(G49,Risk_Response!$A$2:$A$63,0)) -> 1.18 | J49: relative risk | L49: 0 | N49: immediate_after_full_implementation | O49: 1 | P49: well | Q49: sick | R49: Lara-Castor et al.; proxy study where noted | S49: https://doi.org/10.1038/s41591-024-03345-4 | T49: Ready | U49: Direct well-to-sick incidence effect. | V49: =COUNTIF(Intervention_Cause_Map!$A$2:$A$62,B49) -> 1 | W49: =IF(V49<>1,"MAP ERROR",IF(NOT(OR(AND(P49="well",Q49="sick"),AND(P49="sick",Q49="dead"))),"REVIEW TRANSITION",IF(AND(L49=1,OR(ISBLANK(K49),K49<0,K49>1)),"MISSING PAF",IF(R49="","MISSING SOURCE",IF(OR(T49="Ready",T49=""),"OK","REVIEW"))))) -> OK
A50: EFF_049 | B50: I_PH_TOBACCO_TAX__C_IHD__SICK_DEAD | C50: I_PH_TOBACCO_TAX | D50: R_SMOKING | E50: C_IHD | F50: tobacco_mortality_prevalence_shift_rr | G50: HR_SMOKING_VASC_MORT_POOLED | H50: HR current vs never smoker; R uses sex-specific values | I50: =INDEX(Risk_Response!$L$2:$L$63,MATCH(G50,Risk_Response!$A$2:$A$63,0)) -> 3 | J50: hazard ratio | L50: 0 | N50: jha_piecewise_shared_scalar | O50: =SUMIF(Assumptions!$A$2:$A$37,"tobacco_cvd_lag_rate",Assumptions!$B$2:$B$37) -> 0.0616 | P50: sick | Q50: dead | R50: Cho et al. 2024 | S50: https://doi.org/10.1056/EVIDoa2300272 | T50: Proxy | U50: Vascular mortality is used as a labeled proxy for post-diagnosis case fatality; apply age-sex Jha scalars to annual quitting cohorts. | V50: =COUNTIF(Intervention_Cause_Map!$A$2:$A$62,B50) -> 1 | W50: =IF(V50<>1,"MAP ERROR",IF(NOT(OR(AND(P50="well",Q50="sick"),AND(P50="sick",Q50="dead"))),"REVIEW TRANSITION",IF(AND(L50=1,OR(ISBLANK(K50),K50<0,K50>1)),"MISSING PAF",IF(R50="","MISSING SOURCE",IF(OR(T50="Ready",T50=""),"OK","REVIEW"))))) -> REVIEW
A51: EFF_050 | B51: I_PH_TOBACCO_TAX__C_IS__SICK_DEAD | C51: I_PH_TOBACCO_TAX | D51: R_SMOKING | E51: C_IS | F51: tobacco_mortality_prevalence_shift_rr | G51: HR_SMOKING_VASC_MORT_POOLED | H51: HR current vs never smoker; R uses sex-specific values | I51: =INDEX(Risk_Response!$L$2:$L$63,MATCH(G51,Risk_Response!$A$2:$A$63,0)) -> 3 | J51: hazard ratio | L51: 0 | N51: jha_piecewise_shared_scalar | O51: =SUMIF(Assumptions!$A$2:$A$37,"tobacco_cvd_lag_rate",Assumptions!$B$2:$B$37) -> 0.0616 | P51: sick | Q51: dead | R51: Cho et al. 2024 | S51: https://doi.org/10.1056/EVIDoa2300272 | T51: Proxy | U51: Vascular mortality is used as a labeled proxy for post-diagnosis case fatality; apply age-sex Jha scalars to annual quitting cohorts. | V51: =COUNTIF(Intervention_Cause_Map!$A$2:$A$62,B51) -> 1 | W51: =IF(V51<>1,"MAP ERROR",IF(NOT(OR(AND(P51="well",Q51="sick"),AND(P51="sick",Q51="dead"))),"REVIEW TRANSITION",IF(AND(L51=1,OR(ISBLANK(K51),K51<0,K51>1)),"MISSING PAF",IF(R51="","MISSING SOURCE",IF(OR(T51="Ready",T51=""),"OK","REVIEW"))))) -> REVIEW
A52: EFF_051 | B52: I_PH_TOBACCO_TAX__C_ICH__SICK_DEAD | C52: I_PH_TOBACCO_TAX | D52: R_SMOKING | E52: C_ICH | F52: tobacco_mortality_prevalence_shift_rr | G52: HR_SMOKING_VASC_MORT_POOLED | H52: HR current vs never smoker; R uses sex-specific values | I52: =INDEX(Risk_Response!$L$2:$L$63,MATCH(G52,Risk_Response!$A$2:$A$63,0)) -> 3 | J52: hazard ratio | L52: 0 | N52: jha_piecewise_shared_scalar | O52: =SUMIF(Assumptions!$A$2:$A$37,"tobacco_cvd_lag_rate",Assumptions!$B$2:$B$37) -> 0.0616 | P52: sick | Q52: dead | R52: Cho et al. 2024 | S52: https://doi.org/10.1056/EVIDoa2300272 | T52: Proxy | U52: Vascular mortality is used as a labeled proxy for post-diagnosis case fatality; apply age-sex Jha scalars to annual quitting cohorts. | V52: =COUNTIF(Intervention_Cause_Map!$A$2:$A$62,B52) -> 1 | W52: =IF(V52<>1,"MAP ERROR",IF(NOT(OR(AND(P52="well",Q52="sick"),AND(P52="sick",Q52="dead"))),"REVIEW TRANSITION",IF(AND(L52=1,OR(ISBLANK(K52),K52<0,K52>1)),"MISSING PAF",IF(R52="","MISSING SOURCE",IF(OR(T52="Ready",T52=""),"OK","REVIEW"))))) -> REVIEW
A53: EFF_052 | B53: I_PH_TOB_CLEAN_AIR__C_IHD__SICK_DEAD | C53: I_PH_TOB_CLEAN_AIR | D53: R_SMOKING | E53: C_IHD | F53: tobacco_mortality_prevalence_shift_rr | G53: HR_SMOKING_VASC_MORT_POOLED | H53: HR current vs never smoker; R uses sex-specific values | I53: =INDEX(Risk_Response!$L$2:$L$63,MATCH(G53,Risk_Response!$A$2:$A$63,0)) -> 3 | J53: hazard ratio | L53: 0 | N53: jha_piecewise_shared_scalar | O53: =SUMIF(Assumptions!$A$2:$A$37,"tobacco_cvd_lag_rate",Assumptions!$B$2:$B$37) -> 0.0616 | P53: sick | Q53: dead | R53: Cho et al. 2024 | S53: https://doi.org/10.1056/EVIDoa2300272 | T53: Proxy | U53: Vascular mortality is used as a labeled proxy for post-diagnosis case fatality; apply age-sex Jha scalars to annual quitting cohorts. | V53: =COUNTIF(Intervention_Cause_Map!$A$2:$A$62,B53) -> 1 | W53: =IF(V53<>1,"MAP ERROR",IF(NOT(OR(AND(P53="well",Q53="sick"),AND(P53="sick",Q53="dead"))),"REVIEW TRANSITION",IF(AND(L53=1,OR(ISBLANK(K53),K53<0,K53>1)),"MISSING PAF",IF(R53="","MISSING SOURCE",IF(OR(T53="Ready",T53=""),"OK","REVIEW"))))) -> REVIEW
A54: EFF_053 | B54: I_PH_TOB_CLEAN_AIR__C_IS__SICK_DEAD | C54: I_PH_TOB_CLEAN_AIR | D54: R_SMOKING | E54: C_IS | F54: tobacco_mortality_prevalence_shift_rr | G54: HR_SMOKING_VASC_MORT_POOLED | H54: HR current vs never smoker; R uses sex-specific values | I54: =INDEX(Risk_Response!$L$2:$L$63,MATCH(G54,Risk_Response!$A$2:$A$63,0)) -> 3 | J54: hazard ratio | L54: 0 | N54: jha_piecewise_shared_scalar | O54: =SUMIF(Assumptions!$A$2:$A$37,"tobacco_cvd_lag_rate",Assumptions!$B$2:$B$37) -> 0.0616 | P54: sick | Q54: dead | R54: Cho et al. 2024 | S54: https://doi.org/10.1056/EVIDoa2300272 | T54: Proxy | U54: Vascular mortality is used as a labeled proxy for post-diagnosis case fatality; apply age-sex Jha scalars to annual quitting cohorts. | V54: =COUNTIF(Intervention_Cause_Map!$A$2:$A$62,B54) -> 1 | W54: =IF(V54<>1,"MAP ERROR",IF(NOT(OR(AND(P54="well",Q54="sick"),AND(P54="sick",Q54="dead"))),"REVIEW TRANSITION",IF(AND(L54=1,OR(ISBLANK(K54),K54<0,K54>1)),"MISSING PAF",IF(R54="","MISSING SOURCE",IF(OR(T54="Ready",T54=""),"OK","REVIEW"))))) -> REVIEW
A55: EFF_054 | B55: I_PH_TOB_CLEAN_AIR__C_ICH__SICK_DEAD | C55: I_PH_TOB_CLEAN_AIR | D55: R_SMOKING | E55: C_ICH | F55: tobacco_mortality_prevalence_shift_rr | G55: HR_SMOKING_VASC_MORT_POOLED | H55: HR current vs never smoker; R uses sex-specific values | I55: =INDEX(Risk_Response!$L$2:$L$63,MATCH(G55,Risk_Response!$A$2:$A$63,0)) -> 3 | J55: hazard ratio | L55: 0 | N55: jha_piecewise_shared_scalar | O55: =SUMIF(Assumptions!$A$2:$A$37,"tobacco_cvd_lag_rate",Assumptions!$B$2:$B$37) -> 0.0616 | P55: sick | Q55: dead | R55: Cho et al. 2024 | S55: https://doi.org/10.1056/EVIDoa2300272 | T55: Proxy | U55: Vascular mortality is used as a labeled proxy for post-diagnosis case fatality; apply age-sex Jha scalars to annual quitting cohorts. | V55: =COUNTIF(Intervention_Cause_Map!$A$2:$A$62,B55) -> 1 | W55: =IF(V55<>1,"MAP ERROR",IF(NOT(OR(AND(P55="well",Q55="sick"),AND(P55="sick",Q55="dead"))),"REVIEW TRANSITION",IF(AND(L55=1,OR(ISBLANK(K55),K55<0,K55>1)),"MISSING PAF",IF(R55="","MISSING SOURCE",IF(OR(T55="Ready",T55=""),"OK","REVIEW"))))) -> REVIEW
A56: EFF_055 | B56: I_PH_TOB_MEDIA__C_IHD__SICK_DEAD | C56: I_PH_TOB_MEDIA | D56: R_SMOKING | E56: C_IHD | F56: tobacco_mortality_prevalence_shift_rr | G56: HR_SMOKING_VASC_MORT_POOLED | H56: HR current vs never smoker; R uses sex-specific values | I56: =INDEX(Risk_Response!$L$2:$L$63,MATCH(G56,Risk_Response!$A$2:$A$63,0)) -> 3 | J56: hazard ratio | L56: 0 | N56: jha_piecewise_shared_scalar | O56: =SUMIF(Assumptions!$A$2:$A$37,"tobacco_cvd_lag_rate",Assumptions!$B$2:$B$37) -> 0.0616 | P56: sick | Q56: dead | R56: Cho et al. 2024 | S56: https://doi.org/10.1056/EVIDoa2300272 | T56: Proxy | U56: Vascular mortality is used as a labeled proxy for post-diagnosis case fatality; apply age-sex Jha scalars to annual quitting cohorts. | V56: =COUNTIF(Intervention_Cause_Map!$A$2:$A$62,B56) -> 1 | W56: =IF(V56<>1,"MAP ERROR",IF(NOT(OR(AND(P56="well",Q56="sick"),AND(P56="sick",Q56="dead"))),"REVIEW TRANSITION",IF(AND(L56=1,OR(ISBLANK(K56),K56<0,K56>1)),"MISSING PAF",IF(R56="","MISSING SOURCE",IF(OR(T56="Ready",T56=""),"OK","REVIEW"))))) -> REVIEW
A57: EFF_056 | B57: I_PH_TOB_MEDIA__C_IS__SICK_DEAD | C57: I_PH_TOB_MEDIA | D57: R_SMOKING | E57: C_IS | F57: tobacco_mortality_prevalence_shift_rr | G57: HR_SMOKING_VASC_MORT_POOLED | H57: HR current vs never smoker; R uses sex-specific values | I57: =INDEX(Risk_Response!$L$2:$L$63,MATCH(G57,Risk_Response!$A$2:$A$63,0)) -> 3 | J57: hazard ratio | L57: 0 | N57: jha_piecewise_shared_scalar | O57: =SUMIF(Assumptions!$A$2:$A$37,"tobacco_cvd_lag_rate",Assumptions!$B$2:$B$37) -> 0.0616 | P57: sick | Q57: dead | R57: Cho et al. 2024 | S57: https://doi.org/10.1056/EVIDoa2300272 | T57: Proxy | U57: Vascular mortality is used as a labeled proxy for post-diagnosis case fatality; apply age-sex Jha scalars to annual quitting cohorts. | V57: =COUNTIF(Intervention_Cause_Map!$A$2:$A$62,B57) -> 1 | W57: =IF(V57<>1,"MAP ERROR",IF(NOT(OR(AND(P57="well",Q57="sick"),AND(P57="sick",Q57="dead"))),"REVIEW TRANSITION",IF(AND(L57=1,OR(ISBLANK(K57),K57<0,K57>1)),"MISSING PAF",IF(R57="","MISSING SOURCE",IF(OR(T57="Ready",T57=""),"OK","REVIEW"))))) -> REVIEW
A58: EFF_057 | B58: I_PH_TOB_MEDIA__C_ICH__SICK_DEAD | C58: I_PH_TOB_MEDIA | D58: R_SMOKING | E58: C_ICH | F58: tobacco_mortality_prevalence_shift_rr | G58: HR_SMOKING_VASC_MORT_POOLED | H58: HR current vs never smoker; R uses sex-specific values | I58: =INDEX(Risk_Response!$L$2:$L$63,MATCH(G58,Risk_Response!$A$2:$A$63,0)) -> 3 | J58: hazard ratio | L58: 0 | N58: jha_piecewise_shared_scalar | O58: =SUMIF(Assumptions!$A$2:$A$37,"tobacco_cvd_lag_rate",Assumptions!$B$2:$B$37) -> 0.0616 | P58: sick | Q58: dead | R58: Cho et al. 2024 | S58: https://doi.org/10.1056/EVIDoa2300272 | T58: Proxy | U58: Vascular mortality is used as a labeled proxy for post-diagnosis case fatality; apply age-sex Jha scalars to annual quitting cohorts. | V58: =COUNTIF(Intervention_Cause_Map!$A$2:$A$62,B58) -> 1 | W58: =IF(V58<>1,"MAP ERROR",IF(NOT(OR(AND(P58="well",Q58="sick"),AND(P58="sick",Q58="dead"))),"REVIEW TRANSITION",IF(AND(L58=1,OR(ISBLANK(K58),K58<0,K58>1)),"MISSING PAF",IF(R58="","MISSING SOURCE",IF(OR(T58="Ready",T58=""),"OK","REVIEW"))))) -> REVIEW
A59: EFF_058 | B59: I_PH_TOB_AD_BAN__C_IHD__SICK_DEAD | C59: I_PH_TOB_AD_BAN | D59: R_SMOKING | E59: C_IHD | F59: tobacco_mortality_prevalence_shift_rr | G59: HR_SMOKING_VASC_MORT_POOLED | H59: HR current vs never smoker; R uses sex-specific values | I59: =INDEX(Risk_Response!$L$2:$L$63,MATCH(G59,Risk_Response!$A$2:$A$63,0)) -> 3 | J59: hazard ratio | L59: 0 | N59: jha_piecewise_shared_scalar | O59: =SUMIF(Assumptions!$A$2:$A$37,"tobacco_cvd_lag_rate",Assumptions!$B$2:$B$37) -> 0.0616 | P59: sick | Q59: dead | R59: Cho et al. 2024 | S59: https://doi.org/10.1056/EVIDoa2300272 | T59: Proxy | U59: Vascular mortality is used as a labeled proxy for post-diagnosis case fatality; apply age-sex Jha scalars to annual quitting cohorts. | V59: =COUNTIF(Intervention_Cause_Map!$A$2:$A$62,B59) -> 1 | W59: =IF(V59<>1,"MAP ERROR",IF(NOT(OR(AND(P59="well",Q59="sick"),AND(P59="sick",Q59="dead"))),"REVIEW TRANSITION",IF(AND(L59=1,OR(ISBLANK(K59),K59<0,K59>1)),"MISSING PAF",IF(R59="","MISSING SOURCE",IF(OR(T59="Ready",T59=""),"OK","REVIEW"))))) -> REVIEW
A60: EFF_059 | B60: I_PH_TOB_AD_BAN__C_IS__SICK_DEAD | C60: I_PH_TOB_AD_BAN | D60: R_SMOKING | E60: C_IS | F60: tobacco_mortality_prevalence_shift_rr | G60: HR_SMOKING_VASC_MORT_POOLED | H60: HR current vs never smoker; R uses sex-specific values | I60: =INDEX(Risk_Response!$L$2:$L$63,MATCH(G60,Risk_Response!$A$2:$A$63,0)) -> 3 | J60: hazard ratio | L60: 0 | N60: jha_piecewise_shared_scalar | O60: =SUMIF(Assumptions!$A$2:$A$37,"tobacco_cvd_lag_rate",Assumptions!$B$2:$B$37) -> 0.0616 | P60: sick | Q60: dead | R60: Cho et al. 2024 | S60: https://doi.org/10.1056/EVIDoa2300272 | T60: Proxy | U60: Vascular mortality is used as a labeled proxy for post-diagnosis case fatality; apply age-sex Jha scalars to annual quitting cohorts. | V60: =COUNTIF(Intervention_Cause_Map!$A$2:$A$62,B60) -> 1 | W60: =IF(V60<>1,"MAP ERROR",IF(NOT(OR(AND(P60="well",Q60="sick"),AND(P60="sick",Q60="dead"))),"REVIEW TRANSITION",IF(AND(L60=1,OR(ISBLANK(K60),K60<0,K60>1)),"MISSING PAF",IF(R60="","MISSING SOURCE",IF(OR(T60="Ready",T60=""),"OK","REVIEW"))))) -> REVIEW
A61: EFF_060 | B61: I_PH_TOB_AD_BAN__C_ICH__SICK_DEAD | C61: I_PH_TOB_AD_BAN | D61: R_SMOKING | E61: C_ICH | F61: tobacco_mortality_prevalence_shift_rr | G61: HR_SMOKING_VASC_MORT_POOLED | H61: HR current vs never smoker; R uses sex-specific values | I61: =INDEX(Risk_Response!$L$2:$L$63,MATCH(G61,Risk_Response!$A$2:$A$63,0)) -> 3 | J61: hazard ratio | L61: 0 | N61: jha_piecewise_shared_scalar | O61: =SUMIF(Assumptions!$A$2:$A$37,"tobacco_cvd_lag_rate",Assumptions!$B$2:$B$37) -> 0.0616 | P61: sick | Q61: dead | R61: Cho et al. 2024 | S61: https://doi.org/10.1056/EVIDoa2300272 | T61: Proxy | U61: Vascular mortality is used as a labeled proxy for post-diagnosis case fatality; apply age-sex Jha scalars to annual quitting cohorts. | V61: =COUNTIF(Intervention_Cause_Map!$A$2:$A$62,B61) -> 1 | W61: =IF(V61<>1,"MAP ERROR",IF(NOT(OR(AND(P61="well",Q61="sick"),AND(P61="sick",Q61="dead"))),"REVIEW TRANSITION",IF(AND(L61=1,OR(ISBLANK(K61),K61<0,K61>1)),"MISSING PAF",IF(R61="","MISSING SOURCE",IF(OR(T61="Ready",T61=""),"OK","REVIEW"))))) -> REVIEW
A62: EFF_061 | B62: I_PH_SSB_TAX__C_T2DM__SICK_DEAD | C62: I_PH_SSB_TAX | D62: R_SSB | E62: C_T2DM | F62: direct_loglinear_rr_per_unit_reduction | G62: RR_SSB_T2DM_ALLCAUSE_MORT_1SERV | H62: HR per daily serving | I62: =INDEX(Risk_Response!$L$2:$L$63,MATCH(G62,Risk_Response!$A$2:$A$63,0)) -> 1.08 | J62: hazard ratio | L62: 0 | N62: immediate_after_full_implementation | O62: 1 | P62: sick | Q62: dead | R62: Ma et al. 2023 | S62: https://doi.org/10.1136/bmj-2022-073406 | T62: Exploratory | U62: Disabled by default. Use only if the T2DM sick-to-dead transition represents all-cause mortality; not diabetes-specific death. | V62: =COUNTIF(Intervention_Cause_Map!$A$2:$A$62,B62) -> 1 | W62: =IF(V62<>1,"MAP ERROR",IF(NOT(OR(AND(P62="well",Q62="sick"),AND(P62="sick",Q62="dead"))),"REVIEW TRANSITION",IF(AND(L62=1,OR(ISBLANK(K62),K62<0,K62>1)),"MISSING PAF",IF(R62="","MISSING SOURCE",IF(OR(T62="Ready",T62=""),"OK","REVIEW"))))) -> REVIEW

Sheet Risk_Response
A1: response_key | B1: risk_id | C1: selection_status | D1: response_name | E1: age_start | F1: age_stop | G1: sex | H1: cause_id | I1: cause_scope | J1: source_effect_value | K1: source_effect_unit | L1: model_response_value | M1: model_response_unit | N1: derivation | O1: source | P1: selected_for_base_case | Q1: notes
A2: RR_SMOKING_IHD | B2: R_SMOKING | C2: Selected | D2: Current smoking RR - IHD | E2: 20 | F2: 95 | G2: Both | H2: C_IHD | I2: IHD | J2: 1.6 | K2: RR current vs non-smoker | L2: =J2 -> 1.6 | M2: RR current vs non-smoker | N2: model RR = source RR | O2: https://doi.org/10.1093/ije/dyi104 | P2: 1 | Q2: Applied to incidence
A3: RR_SMOKING_IS | B3: R_SMOKING | C3: Selected | D3: Current smoking RR - ischemic stroke | E3: 20 | F3: 95 | G3: Both | H3: C_IS | I3: Ischemic stroke | J3: 1.38 | K3: RR current vs non-smoker | L3: =J3 -> 1.38 | M3: RR current vs non-smoker | N3: model RR = source RR | O3: https://doi.org/10.1093/ije/dyi104 | P3: 1 | Q3: Direct estimate
A4: RR_SMOKING_ICH | B4: R_SMOKING | C4: Selected | D4: Current smoking RR - ICH | E4: 20 | F4: 95 | G4: Both | H4: C_ICH | I4: ICH | J4: 1.19 | K4: RR current vs non-smoker | L4: =J4 -> 1.19 | M4: RR current vs non-smoker | N4: model RR = source RR | O4: https://doi.org/10.1093/ije/dyi104 | P4: 1 | Q4: Hemorrhagic-stroke estimate
A5: RR_SMOKING_T2DM | B5: R_SMOKING | C5: Selected | D5: Current smoking RR - T2DM | E5: 20 | F5: 95 | G5: Both | H5: C_T2DM | I5: T2DM | J5: 1.37 | K5: RR current vs non-smoker | L5: =J5 -> 1.37 | M5: RR current vs non-smoker | N5: model RR = source RR | O5: https://doi.org/10.1016/S2213-8587(15)00316-2 | P5: 1 | Q5: Timing sensitivity
A6: RR_ALCOHOL_IHD_1L | B6: R_ALCOHOL | C6: Selected | D6: Alcohol dose response - IHD | E6: 20 | F6: 95 | G6: Both | H6: C_IHD | I6: IHD | J6: 1.06 | K6: HR per 100 g/week | L6: =J6^(1/(100*Assumptions!$B$19/Assumptions!$B$18)) -> 1.0088804 | M6: RR per 1 L/year | N6: converted using 789 g/L and 52 weeks/year | O6: https://doi.org/10.1016/S0140-6736(18)30134-X | P6: 1 | Q6: Conservative proxy
A7: RR_ALCOHOL_IS_1L | B7: R_ALCOHOL | C7: Selected | D7: Alcohol dose response - ischemic stroke | E7: 20 | F7: 95 | G7: Both | H7: C_IS | I7: Ischemic stroke | J7: 1.14 | K7: HR per 100 g/week | L7: =J7^(1/(100*Assumptions!$B$19/Assumptions!$B$18)) -> 1.02008 | M7: RR per 1 L/year | N7: converted using 789 g/L and 52 weeks/year | O7: https://doi.org/10.1016/S0140-6736(18)30134-X | P7: 1 | Q7: All-stroke proxy
A8: RR_ALCOHOL_ICH_1L | B8: R_ALCOHOL | C8: Selected | D8: Alcohol dose response - ICH | E8: 20 | F8: 95 | G8: Both | H8: C_ICH | I8: ICH | J8: 1.14 | K8: HR per 100 g/week | L8: =J8^(1/(100*Assumptions!$B$19/Assumptions!$B$18)) -> 1.02008 | M8: RR per 1 L/year | N8: converted using 789 g/L and 52 weeks/year | O8: https://doi.org/10.1016/S0140-6736(18)30134-X | P8: 1 | Q8: All-stroke proxy
A9: RR_ALCOHOL_HHD_1L | B9: R_ALCOHOL | C9: Selected | D9: Alcohol dose response - HHD | E9: 20 | F9: 95 | G9: Both | H9: C_HHD | I9: HHD | J9: 1.24 | K9: HR per 100 g/week | L9: =J9^(1/(100*Assumptions!$B$19/Assumptions!$B$18)) -> 1.0331775 | M9: RR per 1 L/year | N9: converted using 789 g/L and 52 weeks/year | O9: https://doi.org/10.1016/S0140-6736(18)30134-X | P9: 1 | Q9: Fatal hypertensive disease
A10: RR_ALCOHOL_CMYO_1L | B10: R_ALCOHOL | C10: Selected | D10: Alcohol dose response - cardiomyopathy | E10: 20 | F10: 95 | G10: Both | H10: C_CMYO | I10: Cardiomyopathy | J10: 1.09 | K10: HR per 100 g/week | L10: =J10^(1/(100*Assumptions!$B$19/Assumptions!$B$18)) -> 1.0131617 | M10: RR per 1 L/year | N10: converted using 789 g/L and 52 weeks/year | O10: https://doi.org/10.1016/S0140-6736(18)30134-X | P10: 1 | Q10: Heart-failure proxy
A11: LAG_TOB_CVD | B11: R_SMOKING | C11: Sensitivity | D11: Normalized exponential tobacco-CVD lag | E11: 20 | F11: 95 | G11: Both | H11: C_IHD|C_IS|C_ICH | I11: CVD | J11: 0.0616 | K11: annual fraction | L11: 0.0616 | M11: annual fraction | N11: normalized to 100% at year 10 | O11: User-specified; Cho et al. 2024 timing sensitivity | P11: 0 | Q11: Sensitivity only; base case is jha_piecewise_shared_scalar
A12: LAG_TOB_T2DM_PROXY | B12: R_SMOKING | C12: Selected | D12: Tobacco-T2DM effect realization | E12: 20 | F12: 95 | G12: Both | H12: C_T2DM | I12: T2DM | J12: 0.47 | K12: proxy fraction by year 10 | L12: =1-(1-J12)^(1/10) -> 0.061514457 | M12: annual remaining effect | N12: uses CVD lag | O12: Pan 2015; Watkins 2022 | P12: 1 | Q12: Proxy
A13: RR_SODIUM_1G | B13: R_SODIUM | C13: Selected | D13: Direct sodium-CVD response | E13: 0 | F13: 95 | G13: Both | H13: C_IHD|C_IS|C_ICH|C_HHD | I13: CVD | J13: 1.06 | K13: RR per 1 g sodium/day | L13: =J13 -> 1.06 | M13: RR per 1 g sodium/day | N13: model RR = source RR | O13: Watkins 2022 p 33 | P13: 1 | Q13: Countdown pathway
A14: RR_TFA_IHD_1PCT | B14: R_TFA | C14: Selected | D14: Industrial TFA RR - total IHD | E14: 0 | F14: 95 | G14: Both | H14: C_IHD | I14: IHD | J14: =+SQRT(1.21) -> 1.1 | K14: RR per 2 percentage-points energy/day | L14: =J14 -> 1.1 | M14: RR per 1 percentage-point energy/day | N14: sqrt(source RR) under log-linearity | O14: https://www.ahajournals.org/doi/10.1161/CIRCULATIONAHA.118.038160; https://www.ahajournals.org/doi/10.1161/JAHA.115.002891 | P14: 1 | Q14: sqrt(1.21)=1.10 approximately
A15: PAF_TFA_IHD_OPTIONAL | B15: R_TFA | C15: Optional | D15: Optional TFA-attributable IHD fraction | E15: 0 | F15: 95 | G15: Both | H15: C_IHD | I15: IHD | J15: =Assumptions!$B$28 -> 0 | K15: proportion | L15: =J15 -> 0 | M15: proportion | N15: links to Assumptions | O15: Optional user input | P15: 0 | Q15: Used only in PAF mode
A16: TFA_SCORE_0 | B16: R_TFA | C16: Reference | D16: Legacy WHO score 0 | E16: 0 | F16: 95 | G16: Both | H16: C_IHD | I16: TFA-attributable IHD | J16: 1 | K16: proportion reduced | L16: =J16 -> 1 | M16: proportion reduced | N16: legacy only | O16: Watkins 2022 pp 33-34 | P16: 0 | Q16: Not used by default
A17: TFA_SCORE_1 | B17: R_TFA | C17: Reference | D17: Legacy WHO score 1 | E17: 0 | F17: 95 | G17: Both | H17: C_IHD | I17: TFA-attributable IHD | J17: 1 | K17: proportion reduced | L17: =J17 -> 1 | M17: proportion reduced | N17: legacy only | O17: Watkins 2022 pp 33-34 | P17: 0 | Q17: Not used by default
A18: TFA_SCORE_2 | B18: R_TFA | C18: Reference | D18: Legacy WHO score 2 | E18: 0 | F18: 95 | G18: Both | H18: C_IHD | I18: TFA-attributable IHD | J18: 1 | K18: proportion reduced | L18: =J18 -> 1 | M18: proportion reduced | N18: legacy only | O18: Watkins 2022 pp 33-34 | P18: 0 | Q18: Not used by default
A19: TFA_SCORE_3 | B19: R_TFA | C19: Reference | D19: Legacy WHO score 3 | E19: 0 | F19: 95 | G19: Both | H19: C_IHD | I19: TFA-attributable IHD | J19: 0.297 | K19: proportion reduced | L19: 0.297 | M19: proportion reduced | N19: legacy only | O19: Watkins 2022 pp 33-34 | P19: 0 | Q19: Not used by default
A20: TFA_SCORE_4 | B20: R_TFA | C20: Reference | D20: Legacy WHO score 4 | E20: 0 | F20: 95 | G20: Both | H20: C_IHD | I20: TFA-attributable IHD | J20: 0 | K20: proportion reduced | L20: 0 | M20: proportion reduced | N20: legacy only | O20: Watkins 2022 pp 33-34 | P20: 0 | Q20: Not used by default
A21: RR_SSB_IHD_1SERV | B21: R_SSB | C21: Selected | D21: SSB direct RR - IHD | E21: 20 | F21: 95 | G21: Both | H21: C_IHD | I21: IHD | J21: 1.14 | K21: RR per serving/day | L21: 1.14 | M21: RR per serving/day | N21: direct RR | O21: https://doi.org/10.1038/s41591-024-03345-4 | P21: 1 | Q21: Primary
A22: RR_SSB_IS_1SERV | B22: R_SSB | C22: Selected | D22: SSB direct RR - ischemic stroke | E22: 20 | F22: 95 | G22: Both | H22: C_IS | I22: Ischemic stroke | J22: 1.07 | K22: RR per serving/day | L22: 1.07 | M22: RR per serving/day | N22: direct RR | O22: https://doi.org/10.1038/s41591-024-03345-4 | P22: 1 | Q22: Primary
A23: RR_SSB_ICH_1SERV_PROXY | B23: R_SSB | C23: Selected | D23: SSB RR - ICH proxy | E23: 20 | F23: 95 | G23: Both | H23: C_ICH | I23: ICH | J23: 1.08 | K23: HR per 250 mL/day | L23: 1.08 | M23: RR per serving/day | N23: total-stroke proxy | O23: https://doi.org/10.1016/j.advnut.2022.12.002 | P23: 1 | Q23: Proxy
A24: RR_SSB_HHD_1SERV_PROXY | B24: R_SSB | C24: Selected | D24: SSB RR - HHD proxy | E24: 20 | F24: 95 | G24: Both | H24: C_HHD | I24: HHD | J24: 1.1 | K24: RR per 250 mL/day | L24: 1.1 | M24: RR per serving/day | N24: hypertension proxy | O24: https://doi.org/10.1007/s10654-020-00655-y | P24: 1 | Q24: Proxy
A25: RR_SSB_T2DM_1SERV | B25: R_SSB | C25: Selected | D25: SSB direct RR - T2DM | E25: 20 | F25: 95 | G25: Both | H25: C_T2DM | I25: T2DM | J25: 1.18 | K25: RR per serving/day | L25: 1.18 | M25: RR per serving/day | N25: direct RR | O25: https://doi.org/10.1038/s41591-024-03345-4 | P25: 1 | Q25: Primary
A26: PAF_SSB_IDN_T2DM_INC_2020 | B26: R_SSB | C26: Reference | D26: Indonesia T2DM incidence PAF | E26: 20 | F26: 95 | G26: Both | H26: C_T2DM | I26: T2DM incidence | J26: 0.024 | K26: fraction | L26: 0.024 | M26: proportion | N26: CRA | O26: https://doi.org/10.1038/s41591-024-03345-4 | P26: 0 | Q26: Validation
A27: PAF_SSB_IDN_CVD_INC_2020 | B27: R_SSB | C27: Reference | D27: Indonesia CVD incidence PAF | E27: 20 | F27: 95 | G27: Both | H27: C_IHD|C_IS | I27: CVD incidence | J27: 0.009 | K27: fraction | L27: 0.009 | M27: proportion | N27: CRA | O27: https://doi.org/10.1038/s41591-024-03345-4 | P27: 0 | Q27: Validation
A28: PAF_SSB_IDN_T2DM_DEATH_2020 | B28: R_SSB | C28: Reference | D28: Indonesia T2DM death PAF | E28: 20 | F28: 95 | G28: Both | H28: C_T2DM | I28: T2DM deaths | J28: 0.012 | K28: fraction | L28: 0.012 | M28: proportion | N28: CRA | O28: https://doi.org/10.1038/s41591-024-03345-4 | P28: 0 | Q28: Validation
A29: PAF_SSB_IDN_CVD_DEATH_2020 | B29: R_SSB | C29: Reference | D29: Indonesia CVD death PAF | E29: 20 | F29: 95 | G29: Both | H29: C_IHD|C_IS | I29: CVD deaths | J29: 0.008 | K29: fraction | L29: 0.008 | M29: proportion | N29: CRA | O29: https://doi.org/10.1038/s41591-024-03345-4 | P29: 0 | Q29: Validation
A30: HR_SMOKING_VASC_MORT_MALE | B30: R_SMOKING | C30: Selected | D30: Current smoking HR - vascular mortality, male | E30: 20 | F30: 95 | G30: Male | H30: C_IHD|C_IS|C_ICH | I30: Vascular mortality | J30: 2.9 | K30: HR current vs never smoker | L30: 2.9 | M30: HR current vs never smoker | N30: model HR = source HR | O30: https://doi.org/10.1056/EVIDoa2300272 | P30: 1 | Q30: Sex-specific value for sick-to-dead proxy pathway
A31: HR_SMOKING_VASC_MORT_FEMALE | B31: R_SMOKING | C31: Selected | D31: Current smoking HR - vascular mortality, female | E31: 20 | F31: 95 | G31: Female | H31: C_IHD|C_IS|C_ICH | I31: Vascular mortality | J31: 3.1 | K31: HR current vs never smoker | L31: 3.1 | M31: HR current vs never smoker | N31: model HR = source HR | O31: https://doi.org/10.1056/EVIDoa2300272 | P31: 1 | Q31: Sex-specific value for sick-to-dead proxy pathway
A32: HR_SMOKING_VASC_MORT_POOLED | B32: R_SMOKING | C32: Selected | D32: Current smoking HR - vascular mortality, pooled | E32: 20 | F32: 95 | G32: Both | H32: C_IHD|C_IS|C_ICH | I32: Vascular mortality | J32: 3 | K32: HR current vs never smoker | L32: =AVERAGE(L30:L31) -> 3 | M32: HR current vs never smoker | N32: mean of male and female HRs | O32: https://doi.org/10.1056/EVIDoa2300272 | P32: 1 | Q32: Backward-compatible response_value; R should use sex-specific values
A33: SCALAR_JHA_M_20_39_LT3 | B33: R_SMOKING | C33: Selected | D33: Jha shared tobacco-CVD scalar: Male, 20-39, <3 years | E33: 20 | F33: 39 | G33: Male | H33: C_IHD|C_IS|C_ICH | I33: Shared timing scalar; cessation <3 years | J33: 0.9 | K33: ERD proportion | L33: 1 | M33: fraction of 10+ year effect | N33: min(1, ERD_duration / ERD_10plus) | O33: https://doi.org/10.1056/EVIDoa2300272 | P33: 1 | Q33: Applied to annual quitting cohorts for incidence and sick-to-dead
A34: SCALAR_JHA_M_20_39_Y3_9 | B34: R_SMOKING | C34: Selected | D34: Jha shared tobacco-CVD scalar: Male, 20-39, 3-9 years | E34: 20 | F34: 39 | G34: Male | H34: C_IHD|C_IS|C_ICH | I34: Shared timing scalar; cessation 3-9 years | J34: 0.92 | K34: ERD proportion | L34: 1 | M34: fraction of 10+ year effect | N34: min(1, ERD_duration / ERD_10plus) | O34: https://doi.org/10.1056/EVIDoa2300272 | P34: 1 | Q34: Applied to annual quitting cohorts for incidence and sick-to-dead
A35: SCALAR_JHA_M_20_39_GE10 | B35: R_SMOKING | C35: Selected | D35: Jha shared tobacco-CVD scalar: Male, 20-39, 10+ years | E35: 20 | F35: 39 | G35: Male | H35: C_IHD|C_IS|C_ICH | I35: Shared timing scalar; cessation 10+ years | J35: 0.84 | K35: ERD proportion | L35: 1 | M35: fraction of 10+ year effect | N35: min(1, ERD_duration / ERD_10plus) | O35: https://doi.org/10.1056/EVIDoa2300272 | P35: 1 | Q35: Applied to annual quitting cohorts for incidence and sick-to-dead
A36: SCALAR_JHA_M_40_49_LT3 | B36: R_SMOKING | C36: Selected | D36: Jha shared tobacco-CVD scalar: Male, 40-49, <3 years | E36: 40 | F36: 49 | G36: Male | H36: C_IHD|C_IS|C_ICH | I36: Shared timing scalar; cessation <3 years | J36: 0.61 | K36: ERD proportion | L36: 0.63541667 | M36: fraction of 10+ year effect | N36: min(1, ERD_duration / ERD_10plus) | O36: https://doi.org/10.1056/EVIDoa2300272 | P36: 1 | Q36: Applied to annual quitting cohorts for incidence and sick-to-dead
A37: SCALAR_JHA_M_40_49_Y3_9 | B37: R_SMOKING | C37: Selected | D37: Jha shared tobacco-CVD scalar: Male, 40-49, 3-9 years | E37: 40 | F37: 49 | G37: Male | H37: C_IHD|C_IS|C_ICH | I37: Shared timing scalar; cessation 3-9 years | J37: 0.8 | K37: ERD proportion | L37: 0.83333333 | M37: fraction of 10+ year effect | N37: min(1, ERD_duration / ERD_10plus) | O37: https://doi.org/10.1056/EVIDoa2300272 | P37: 1 | Q37: Applied to annual quitting cohorts for incidence and sick-to-dead
A38: SCALAR_JHA_M_40_49_GE10 | B38: R_SMOKING | C38: Selected | D38: Jha shared tobacco-CVD scalar: Male, 40-49, 10+ years | E38: 40 | F38: 49 | G38: Male | H38: C_IHD|C_IS|C_ICH | I38: Shared timing scalar; cessation 10+ years | J38: 0.96 | K38: ERD proportion | L38: 1 | M38: fraction of 10+ year effect | N38: min(1, ERD_duration / ERD_10plus) | O38: https://doi.org/10.1056/EVIDoa2300272 | P38: 1 | Q38: Applied to annual quitting cohorts for incidence and sick-to-dead
A39: SCALAR_JHA_M_50_59_LT3 | B39: R_SMOKING | C39: Selected | D39: Jha shared tobacco-CVD scalar: Male, 50-59, <3 years | E39: 50 | F39: 59 | G39: Male | H39: C_IHD|C_IS|C_ICH | I39: Shared timing scalar; cessation <3 years | J39: 0.54 | K39: ERD proportion | L39: 0.58695652 | M39: fraction of 10+ year effect | N39: min(1, ERD_duration / ERD_10plus) | O39: https://doi.org/10.1056/EVIDoa2300272 | P39: 1 | Q39: Applied to annual quitting cohorts for incidence and sick-to-dead
A40: SCALAR_JHA_M_50_59_Y3_9 | B40: R_SMOKING | C40: Selected | D40: Jha shared tobacco-CVD scalar: Male, 50-59, 3-9 years | E40: 50 | F40: 59 | G40: Male | H40: C_IHD|C_IS|C_ICH | I40: Shared timing scalar; cessation 3-9 years | J40: 0.64 | K40: ERD proportion | L40: 0.69565217 | M40: fraction of 10+ year effect | N40: min(1, ERD_duration / ERD_10plus) | O40: https://doi.org/10.1056/EVIDoa2300272 | P40: 1 | Q40: Applied to annual quitting cohorts for incidence and sick-to-dead
A41: SCALAR_JHA_M_50_59_GE10 | B41: R_SMOKING | C41: Selected | D41: Jha shared tobacco-CVD scalar: Male, 50-59, 10+ years | E41: 50 | F41: 59 | G41: Male | H41: C_IHD|C_IS|C_ICH | I41: Shared timing scalar; cessation 10+ years | J41: 0.92 | K41: ERD proportion | L41: 1 | M41: fraction of 10+ year effect | N41: min(1, ERD_duration / ERD_10plus) | O41: https://doi.org/10.1056/EVIDoa2300272 | P41: 1 | Q41: Applied to annual quitting cohorts for incidence and sick-to-dead
A42: SCALAR_JHA_M_60_79_LT3 | B42: R_SMOKING | C42: Selected | D42: Jha shared tobacco-CVD scalar: Male, 60-79, <3 years | E42: 60 | F42: 79 | G42: Male | H42: C_IHD|C_IS|C_ICH | I42: Shared timing scalar; cessation <3 years | J42: 0.33 | K42: ERD proportion | L42: 0.39759036 | M42: fraction of 10+ year effect | N42: min(1, ERD_duration / ERD_10plus) | O42: https://doi.org/10.1056/EVIDoa2300272 | P42: 1 | Q42: Applied to annual quitting cohorts for incidence and sick-to-dead
A43: SCALAR_JHA_M_60_79_Y3_9 | B43: R_SMOKING | C43: Selected | D43: Jha shared tobacco-CVD scalar: Male, 60-79, 3-9 years | E43: 60 | F43: 79 | G43: Male | H43: C_IHD|C_IS|C_ICH | I43: Shared timing scalar; cessation 3-9 years | J43: 0.46 | K43: ERD proportion | L43: 0.55421687 | M43: fraction of 10+ year effect | N43: min(1, ERD_duration / ERD_10plus) | O43: https://doi.org/10.1056/EVIDoa2300272 | P43: 1 | Q43: Applied to annual quitting cohorts for incidence and sick-to-dead
A44: SCALAR_JHA_M_60_79_GE10 | B44: R_SMOKING | C44: Selected | D44: Jha shared tobacco-CVD scalar: Male, 60-79, 10+ years | E44: 60 | F44: 79 | G44: Male | H44: C_IHD|C_IS|C_ICH | I44: Shared timing scalar; cessation 10+ years | J44: 0.83 | K44: ERD proportion | L44: 1 | M44: fraction of 10+ year effect | N44: min(1, ERD_duration / ERD_10plus) | O44: https://doi.org/10.1056/EVIDoa2300272 | P44: 1 | Q44: Applied to annual quitting cohorts for incidence and sick-to-dead
... A63: RR_SSB_T2DM_ALLCAUSE_MORT_1SERV | B63: R_SSB | C63: Sensitivity | D63: SSB HR - all-cause mortality among adults with T2DM | E63: 20 | F63: 95 | G63: Both | H63: C_T2DM | I63: All-cause mortality among adults with T2DM | J63: 1.08 | K63: HR per serving/day | L63: 1.08 | M63: HR per serving/day | N63: direct dose-response HR | O63: https://doi.org/10.1136/bmj-2022-073406 | P63: 0 | Q63: Exploratory only; not diabetes-specific death; use only if sick-to-dead is all-cause mortality

Sheet Model_Input_View
A1: intervention_cause_key | B1: intervention_name | C1: risk_name | D1: cause_name | E1: transition_from | F1: transition_to | G1: baseline_exposure | H1: target_exposure | I1: absolute_reduction | J1: relative_reduction | K1: effect_model | L1: response_value | M1: paf_value | N1: lag_model | O1: illustrative_full_effect | P1: cost_join_key | Q1: cost_scope | R1: selected_policy_cost_usd_per_capita | S1: review_status
A2: I_PH_TOBACCO_TAX__C_IHD | B2: Tobacco tax | C2: Smoking | D2: Ischemic heart disease | E2: well | F2: sick | G2: =SUMIF(Exposure_Targets!$B$2:$B$13,INDEX(Intervention_Cause_Map!$B$2:$B$62,MATCH(A2,Intervention_Cause_Map!$A$2:$A$62,0)),Exposure_Targets!$G$2:$G$13) -> 0.303 | H2: =SUMIF(Exposure_Targets!$B$2:$B$13,INDEX(Intervention_Cause_Map!$B$2:$B$62,MATCH(A2,Intervention_Cause_Map!$A$2:$A$62,0)),Exposure_Targets!$M$2:$M$13) -> 0.25018201 | I2: =G2-H2 -> 0.05281799 | J2: =IF(G2=0,0,I2/G2) -> 0.1743168 | K2: =INDEX(Effect_Parameters!$F$2:$F$62,MATCH(A2,Effect_Parameters!$B$2:$B$62,0)) -> direct_smoking_prevalence_shift_rr | L2: =INDEX(Effect_Parameters!$I$2:$I$62,MATCH(A2,Effect_Parameters!$B$2:$B$62,0)) -> 1.6 | M2: =INDEX(Effect_Parameters!$K$2:$K$62,MATCH(A2,Effect_Parameters!$B$2:$B$62,0)) -> 0 | N2: =INDEX(Effect_Parameters!$N$2:$N$62,MATCH(A2,Effect_Parameters!$B$2:$B$62,0)) -> jha_piecewise_shared_scalar | O2: =IF(K2="direct_smoking_prevalence_shift_rr",IF(OR(ISBLANK(G2),ISBLANK(H2),ISBLANK(L2)),"",1-(1+H2*(L2-1))/(1+G2*(L2-1))),IF(K2="tobacco_mortality_prevalence_shift_rr",IF(OR(ISBLANK(G2),ISBLANK(H2),ISBLANK(L2)),"",1-(1+H2*(L2-1)+(G2-H2)*(1-SUMIF(Assumptions!$A$2:$A$37,"tobacco_vascular_erd_ge10_pooled",Assumptions!$B$2:$B$37))*(L2-1))/(1+G2*(L2-1))),IF(K2="direct_loglinear_rr_per_unit_reduction",IF(OR(ISBLANK(L2),ISBLANK(I2)),"",1-1/(L2^I2)),IF(K2="tfa_attributable_ihd_PAF_x_regulatory_gap",IF(ISBLANK(M2),"",M2*SUMIF(Policy_Levers!$B$2:$B$13,INDEX(Intervention_Cause_Map!$B$2:$B$62,MATCH(A2,Intervention_Cause_Map!$A$2:$A$62,0)),Policy_Levers!$Z$2:$Z$13)),"")))) -> 0.0268157 | P2: =INDEX(Intervention_Cause_Map!$J$2:$J$62,MATCH(A2,Intervention_Cause_Map!$A$2:$A$62,0)) -> I_PH_TOBACCO_TAX__C_SHARED | Q2: =INDEX(Intervention_Cause_Map!$K$2:$K$62,MATCH(A2,Intervention_Cause_Map!$A$2:$A$62,0)) -> shared-count-once | R2: =SUMIFS(Cost_Components!$S$2:$S$15,Cost_Components!$G$2:$G$15,P2,Cost_Components!$D$2:$D$15,1) -> 0.04 | S2: =IF(COUNTIF(Effect_Parameters!$B$2:$B$62,A2)<>1,"LINK ERROR",IF(INDEX(Intervention_Cause_Map!$N$2:$N$62,MATCH(A2,Intervention_Cause_Map!$A$2:$A$62,0))=0,"EXPLORATORY - DISABLED",IF(AND(E2="sick",F2="dead"),"R UPDATE REQUIRED","READY FOR MODEL"))) -> READY FOR MODEL
A3: I_PH_TOBACCO_TAX__C_IS | B3: Tobacco tax | C3: Smoking | D3: Ischemic stroke | E3: well | F3: sick | G3: =SUMIF(Exposure_Targets!$B$2:$B$13,INDEX(Intervention_Cause_Map!$B$2:$B$62,MATCH(A3,Intervention_Cause_Map!$A$2:$A$62,0)),Exposure_Targets!$G$2:$G$13) -> 0.303 | H3: =SUMIF(Exposure_Targets!$B$2:$B$13,INDEX(Intervention_Cause_Map!$B$2:$B$62,MATCH(A3,Intervention_Cause_Map!$A$2:$A$62,0)),Exposure_Targets!$M$2:$M$13) -> 0.25018201 | I3: =G3-H3 -> 0.05281799 | J3: =IF(G3=0,0,I3/G3) -> 0.1743168 | K3: =INDEX(Effect_Parameters!$F$2:$F$62,MATCH(A3,Effect_Parameters!$B$2:$B$62,0)) -> direct_smoking_prevalence_shift_rr | L3: =INDEX(Effect_Parameters!$I$2:$I$62,MATCH(A3,Effect_Parameters!$B$2:$B$62,0)) -> 1.38 | M3: =INDEX(Effect_Parameters!$K$2:$K$62,MATCH(A3,Effect_Parameters!$B$2:$B$62,0)) -> 0 | N3: =INDEX(Effect_Parameters!$N$2:$N$62,MATCH(A3,Effect_Parameters!$B$2:$B$62,0)) -> jha_piecewise_shared_scalar | O3: =IF(K3="direct_smoking_prevalence_shift_rr",IF(OR(ISBLANK(G3),ISBLANK(H3),ISBLANK(L3)),"",1-(1+H3*(L3-1))/(1+G3*(L3-1))),IF(K3="tobacco_mortality_prevalence_shift_rr",IF(OR(ISBLANK(G3),ISBLANK(H3),ISBLANK(L3)),"",1-(1+H3*(L3-1)+(G3-H3)*(1-SUMIF(Assumptions!$A$2:$A$37,"tobacco_vascular_erd_ge10_pooled",Assumptions!$B$2:$B$37))*(L3-1))/(1+G3*(L3-1))),IF(K3="direct_loglinear_rr_per_unit_reduction",IF(OR(ISBLANK(L3),ISBLANK(I3)),"",1-1/(L3^I3)),IF(K3="tfa_attributable_ihd_PAF_x_regulatory_gap",IF(ISBLANK(M3),"",M3*SUMIF(Policy_Levers!$B$2:$B$13,INDEX(Intervention_Cause_Map!$B$2:$B$62,MATCH(A3,Intervention_Cause_Map!$A$2:$A$62,0)),Policy_Levers!$Z$2:$Z$13)),"")))) -> 0.01799849 | P3: =INDEX(Intervention_Cause_Map!$J$2:$J$62,MATCH(A3,Intervention_Cause_Map!$A$2:$A$62,0)) -> I_PH_TOBACCO_TAX__C_SHARED | Q3: =INDEX(Intervention_Cause_Map!$K$2:$K$62,MATCH(A3,Intervention_Cause_Map!$A$2:$A$62,0)) -> shared-count-once | R3: =SUMIFS(Cost_Components!$S$2:$S$15,Cost_Components!$G$2:$G$15,P3,Cost_Components!$D$2:$D$15,1) -> 0.04 | S3: =IF(COUNTIF(Effect_Parameters!$B$2:$B$62,A3)<>1,"LINK ERROR",IF(INDEX(Intervention_Cause_Map!$N$2:$N$62,MATCH(A3,Intervention_Cause_Map!$A$2:$A$62,0))=0,"EXPLORATORY - DISABLED",IF(AND(E3="sick",F3="dead"),"R UPDATE REQUIRED","READY FOR MODEL"))) -> READY FOR MODEL
A4: I_PH_TOBACCO_TAX__C_ICH | B4: Tobacco tax | C4: Smoking | D4: Intracerebral hemorrhage | E4: well | F4: sick | G4: =SUMIF(Exposure_Targets!$B$2:$B$13,INDEX(Intervention_Cause_Map!$B$2:$B$62,MATCH(A4,Intervention_Cause_Map!$A$2:$A$62,0)),Exposure_Targets!$G$2:$G$13) -> 0.303 | H4: =SUMIF(Exposure_Targets!$B$2:$B$13,INDEX(Intervention_Cause_Map!$B$2:$B$62,MATCH(A4,Intervention_Cause_Map!$A$2:$A$62,0)),Exposure_Targets!$M$2:$M$13) -> 0.25018201 | I4: =G4-H4 -> 0.05281799 | J4: =IF(G4=0,0,I4/G4) -> 0.1743168 | K4: =INDEX(Effect_Parameters!$F$2:$F$62,MATCH(A4,Effect_Parameters!$B$2:$B$62,0)) -> direct_smoking_prevalence_shift_rr | L4: =INDEX(Effect_Parameters!$I$2:$I$62,MATCH(A4,Effect_Parameters!$B$2:$B$62,0)) -> 1.19 | M4: =INDEX(Effect_Parameters!$K$2:$K$62,MATCH(A4,Effect_Parameters!$B$2:$B$62,0)) -> 0 | N4: =INDEX(Effect_Parameters!$N$2:$N$62,MATCH(A4,Effect_Parameters!$B$2:$B$62,0)) -> jha_piecewise_shared_scalar | O4: =IF(K4="direct_smoking_prevalence_shift_rr",IF(OR(ISBLANK(G4),ISBLANK(H4),ISBLANK(L4)),"",1-(1+H4*(L4-1))/(1+G4*(L4-1))),IF(K4="tobacco_mortality_prevalence_shift_rr",IF(OR(ISBLANK(G4),ISBLANK(H4),ISBLANK(L4)),"",1-(1+H4*(L4-1)+(G4-H4)*(1-SUMIF(Assumptions!$A$2:$A$37,"tobacco_vascular_erd_ge10_pooled",Assumptions!$B$2:$B$37))*(L4-1))/(1+G4*(L4-1))),IF(K4="direct_loglinear_rr_per_unit_reduction",IF(OR(ISBLANK(L4),ISBLANK(I4)),"",1-1/(L4^I4)),IF(K4="tfa_attributable_ihd_PAF_x_regulatory_gap",IF(ISBLANK(M4),"",M4*SUMIF(Policy_Levers!$B$2:$B$13,INDEX(Intervention_Cause_Map!$B$2:$B$62,MATCH(A4,Intervention_Cause_Map!$A$2:$A$62,0)),Policy_Levers!$Z$2:$Z$13)),"")))) -> 0.009489129 | P4: =INDEX(Intervention_Cause_Map!$J$2:$J$62,MATCH(A4,Intervention_Cause_Map!$A$2:$A$62,0)) -> I_PH_TOBACCO_TAX__C_SHARED | Q4: =INDEX(Intervention_Cause_Map!$K$2:$K$62,MATCH(A4,Intervention_Cause_Map!$A$2:$A$62,0)) -> shared-count-once | R4: =SUMIFS(Cost_Components!$S$2:$S$15,Cost_Components!$G$2:$G$15,P4,Cost_Components!$D$2:$D$15,1) -> 0.04 | S4: =IF(COUNTIF(Effect_Parameters!$B$2:$B$62,A4)<>1,"LINK ERROR",IF(INDEX(Intervention_Cause_Map!$N$2:$N$62,MATCH(A4,Intervention_Cause_Map!$A$2:$A$62,0))=0,"EXPLORATORY - DISABLED",IF(AND(E4="sick",F4="dead"),"R UPDATE REQUIRED","READY FOR MODEL"))) -> READY FOR MODEL
A5: I_PH_TOBACCO_TAX__C_T2DM | B5: Tobacco tax | C5: Smoking | D5: Diabetes mellitus type 2 | E5: well | F5: sick | G5: =SUMIF(Exposure_Targets!$B$2:$B$13,INDEX(Intervention_Cause_Map!$B$2:$B$62,MATCH(A5,Intervention_Cause_Map!$A$2:$A$62,0)),Exposure_Targets!$G$2:$G$13) -> 0.303 | H5: =SUMIF(Exposure_Targets!$B$2:$B$13,INDEX(Intervention_Cause_Map!$B$2:$B$62,MATCH(A5,Intervention_Cause_Map!$A$2:$A$62,0)),Exposure_Targets!$M$2:$M$13) -> 0.25018201 | I5: =G5-H5 -> 0.05281799 | J5: =IF(G5=0,0,I5/G5) -> 0.1743168 | K5: =INDEX(Effect_Parameters!$F$2:$F$62,MATCH(A5,Effect_Parameters!$B$2:$B$62,0)) -> direct_smoking_prevalence_shift_rr | L5: =INDEX(Effect_Parameters!$I$2:$I$62,MATCH(A5,Effect_Parameters!$B$2:$B$62,0)) -> 1.37 | M5: =INDEX(Effect_Parameters!$K$2:$K$62,MATCH(A5,Effect_Parameters!$B$2:$B$62,0)) -> 0 | N5: =INDEX(Effect_Parameters!$N$2:$N$62,MATCH(A5,Effect_Parameters!$B$2:$B$62,0)) -> delayed_exponential_remaining_effect | O5: =IF(K5="direct_smoking_prevalence_shift_rr",IF(OR(ISBLANK(G5),ISBLANK(H5),ISBLANK(L5)),"",1-(1+H5*(L5-1))/(1+G5*(L5-1))),IF(K5="tobacco_mortality_prevalence_shift_rr",IF(OR(ISBLANK(G5),ISBLANK(H5),ISBLANK(L5)),"",1-(1+H5*(L5-1)+(G5-H5)*(1-SUMIF(Assumptions!$A$2:$A$37,"tobacco_vascular_erd_ge10_pooled",Assumptions!$B$2:$B$37))*(L5-1))/(1+G5*(L5-1))),IF(K5="direct_loglinear_rr_per_unit_reduction",IF(OR(ISBLANK(L5),ISBLANK(I5)),"",1-1/(L5^I5)),IF(K5="tfa_attributable_ihd_PAF_x_regulatory_gap",IF(ISBLANK(M5),"",M5*SUMIF(Policy_Levers!$B$2:$B$13,INDEX(Intervention_Cause_Map!$B$2:$B$62,MATCH(A5,Intervention_Cause_Map!$A$2:$A$62,0)),Policy_Levers!$Z$2:$Z$13)),"")))) -> 0.017572593 | P5: =INDEX(Intervention_Cause_Map!$J$2:$J$62,MATCH(A5,Intervention_Cause_Map!$A$2:$A$62,0)) -> I_PH_TOBACCO_TAX__C_SHARED | Q5: =INDEX(Intervention_Cause_Map!$K$2:$K$62,MATCH(A5,Intervention_Cause_Map!$A$2:$A$62,0)) -> shared-count-once | R5: =SUMIFS(Cost_Components!$S$2:$S$15,Cost_Components!$G$2:$G$15,P5,Cost_Components!$D$2:$D$15,1) -> 0.04 | S5: =IF(COUNTIF(Effect_Parameters!$B$2:$B$62,A5)<>1,"LINK ERROR",IF(INDEX(Intervention_Cause_Map!$N$2:$N$62,MATCH(A5,Intervention_Cause_Map!$A$2:$A$62,0))=0,"EXPLORATORY - DISABLED",IF(AND(E5="sick",F5="dead"),"R UPDATE REQUIRED","READY FOR MODEL"))) -> READY FOR MODEL
A6: I_PH_ALCOHOL_TAX__C_IHD | B6: Alcohol tax | C6: Alcohol use | D6: Ischemic heart disease | E6: well | F6: sick | G6: =SUMIF(Exposure_Targets!$B$2:$B$13,INDEX(Intervention_Cause_Map!$B$2:$B$62,MATCH(A6,Intervention_Cause_Map!$A$2:$A$62,0)),Exposure_Targets!$G$2:$G$13) -> 0.1 | H6: =SUMIF(Exposure_Targets!$B$2:$B$13,INDEX(Intervention_Cause_Map!$B$2:$B$62,MATCH(A6,Intervention_Cause_Map!$A$2:$A$62,0)),Exposure_Targets!$M$2:$M$13) -> 0.08775 | I6: =G6-H6 -> 0.01225 | J6: =IF(G6=0,0,I6/G6) -> 0.1225 | K6: =INDEX(Effect_Parameters!$F$2:$F$62,MATCH(A6,Effect_Parameters!$B$2:$B$62,0)) -> direct_loglinear_rr_per_unit_reduction | L6: =INDEX(Effect_Parameters!$I$2:$I$62,MATCH(A6,Effect_Parameters!$B$2:$B$62,0)) -> 1.0088804 | M6: =INDEX(Effect_Parameters!$K$2:$K$62,MATCH(A6,Effect_Parameters!$B$2:$B$62,0)) -> 0 | N6: =INDEX(Effect_Parameters!$N$2:$N$62,MATCH(A6,Effect_Parameters!$B$2:$B$62,0)) -> immediate_after_full_implementation | O6: =IF(K6="direct_smoking_prevalence_shift_rr",IF(OR(ISBLANK(G6),ISBLANK(H6),ISBLANK(L6)),"",1-(1+H6*(L6-1))/(1+G6*(L6-1))),IF(K6="tobacco_mortality_prevalence_shift_rr",IF(OR(ISBLANK(G6),ISBLANK(H6),ISBLANK(L6)),"",1-(1+H6*(L6-1)+(G6-H6)*(1-SUMIF(Assumptions!$A$2:$A$37,"tobacco_vascular_erd_ge10_pooled",Assumptions!$B$2:$B$37))*(L6-1))/(1+G6*(L6-1))),IF(K6="direct_loglinear_rr_per_unit_reduction",IF(OR(ISBLANK(L6),ISBLANK(I6)),"",1-1/(L6^I6)),IF(K6="tfa_attributable_ihd_PAF_x_regulatory_gap",IF(ISBLANK(M6),"",M6*SUMIF(Policy_Levers!$B$2:$B$13,INDEX(Intervention_Cause_Map!$B$2:$B$62,MATCH(A6,Intervention_Cause_Map!$A$2:$A$62,0)),Policy_Levers!$Z$2:$Z$13)),"")))) -> 0.00010829867 | P6: =INDEX(Intervention_Cause_Map!$J$2:$J$62,MATCH(A6,Intervention_Cause_Map!$A$2:$A$62,0)) -> I_PH_ALCOHOL_TAX__C_SHARED | Q6: =INDEX(Intervention_Cause_Map!$K$2:$K$62,MATCH(A6,Intervention_Cause_Map!$A$2:$A$62,0)) -> shared-count-once | R6: =SUMIFS(Cost_Components!$S$2:$S$15,Cost_Components!$G$2:$G$15,P6,Cost_Components!$D$2:$D$15,1) -> 0.04 | S6: =IF(COUNTIF(Effect_Parameters!$B$2:$B$62,A6)<>1,"LINK ERROR",IF(INDEX(Intervention_Cause_Map!$N$2:$N$62,MATCH(A6,Intervention_Cause_Map!$A$2:$A$62,0))=0,"EXPLORATORY - DISABLED",IF(AND(E6="sick",F6="dead"),"R UPDATE REQUIRED","READY FOR MODEL"))) -> EXPLORATORY - DISABLED
A7: I_PH_ALCOHOL_TAX__C_IS | B7: Alcohol tax | C7: Alcohol use | D7: Ischemic stroke | E7: well | F7: sick | G7: =SUMIF(Exposure_Targets!$B$2:$B$13,INDEX(Intervention_Cause_Map!$B$2:$B$62,MATCH(A7,Intervention_Cause_Map!$A$2:$A$62,0)),Exposure_Targets!$G$2:$G$13) -> 0.1 | H7: =SUMIF(Exposure_Targets!$B$2:$B$13,INDEX(Intervention_Cause_Map!$B$2:$B$62,MATCH(A7,Intervention_Cause_Map!$A$2:$A$62,0)),Exposure_Targets!$M$2:$M$13) -> 0.08775 | I7: =G7-H7 -> 0.01225 | J7: =IF(G7=0,0,I7/G7) -> 0.1225 | K7: =INDEX(Effect_Parameters!$F$2:$F$62,MATCH(A7,Effect_Parameters!$B$2:$B$62,0)) -> direct_loglinear_rr_per_unit_reduction | L7: =INDEX(Effect_Parameters!$I$2:$I$62,MATCH(A7,Effect_Parameters!$B$2:$B$62,0)) -> 1.02008 | M7: =INDEX(Effect_Parameters!$K$2:$K$62,MATCH(A7,Effect_Parameters!$B$2:$B$62,0)) -> 0 | N7: =INDEX(Effect_Parameters!$N$2:$N$62,MATCH(A7,Effect_Parameters!$B$2:$B$62,0)) -> immediate_after_full_implementation | O7: =IF(K7="direct_smoking_prevalence_shift_rr",IF(OR(ISBLANK(G7),ISBLANK(H7),ISBLANK(L7)),"",1-(1+H7*(L7-1))/(1+G7*(L7-1))),IF(K7="tobacco_mortality_prevalence_shift_rr",IF(OR(ISBLANK(G7),ISBLANK(H7),ISBLANK(L7)),"",1-(1+H7*(L7-1)+(G7-H7)*(1-SUMIF(Assumptions!$A$2:$A$37,"tobacco_vascular_erd_ge10_pooled",Assumptions!$B$2:$B$37))*(L7-1))/(1+G7*(L7-1))),IF(K7="direct_loglinear_rr_per_unit_reduction",IF(OR(ISBLANK(L7),ISBLANK(I7)),"",1-1/(L7^I7)),IF(K7="tfa_attributable_ihd_PAF_x_regulatory_gap",IF(ISBLANK(M7),"",M7*SUMIF(Policy_Levers!$B$2:$B$13,INDEX(Intervention_Cause_Map!$B$2:$B$62,MATCH(A7,Intervention_Cause_Map!$A$2:$A$62,0)),Policy_Levers!$Z$2:$Z$13)),"")))) -> 0.00024351283 | P7: =INDEX(Intervention_Cause_Map!$J$2:$J$62,MATCH(A7,Intervention_Cause_Map!$A$2:$A$62,0)) -> I_PH_ALCOHOL_TAX__C_SHARED | Q7: =INDEX(Intervention_Cause_Map!$K$2:$K$62,MATCH(A7,Intervention_Cause_Map!$A$2:$A$62,0)) -> shared-count-once | R7: =SUMIFS(Cost_Components!$S$2:$S$15,Cost_Components!$G$2:$G$15,P7,Cost_Components!$D$2:$D$15,1) -> 0.04 | S7: =IF(COUNTIF(Effect_Parameters!$B$2:$B$62,A7)<>1,"LINK ERROR",IF(INDEX(Intervention_Cause_Map!$N$2:$N$62,MATCH(A7,Intervention_Cause_Map!$A$2:$A$62,0))=0,"EXPLORATORY - DISABLED",IF(AND(E7="sick",F7="dead"),"R UPDATE REQUIRED","READY FOR MODEL"))) -> EXPLORATORY - DISABLED
A8: I_PH_ALCOHOL_TAX__C_ICH | B8: Alcohol tax | C8: Alcohol use | D8: Intracerebral hemorrhage | E8: well | F8: sick | G8: =SUMIF(Exposure_Targets!$B$2:$B$13,INDEX(Intervention_Cause_Map!$B$2:$B$62,MATCH(A8,Intervention_Cause_Map!$A$2:$A$62,0)),Exposure_Targets!$G$2:$G$13) -> 0.1 | H8: =SUMIF(Exposure_Targets!$B$2:$B$13,INDEX(Intervention_Cause_Map!$B$2:$B$62,MATCH(A8,Intervention_Cause_Map!$A$2:$A$62,0)),Exposure_Targets!$M$2:$M$13) -> 0.08775 | I8: =G8-H8 -> 0.01225 | J8: =IF(G8=0,0,I8/G8) -> 0.1225 | K8: =INDEX(Effect_Parameters!$F$2:$F$62,MATCH(A8,Effect_Parameters!$B$2:$B$62,0)) -> direct_loglinear_rr_per_unit_reduction | L8: =INDEX(Effect_Parameters!$I$2:$I$62,MATCH(A8,Effect_Parameters!$B$2:$B$62,0)) -> 1.02008 | M8: =INDEX(Effect_Parameters!$K$2:$K$62,MATCH(A8,Effect_Parameters!$B$2:$B$62,0)) -> 0 | N8: =INDEX(Effect_Parameters!$N$2:$N$62,MATCH(A8,Effect_Parameters!$B$2:$B$62,0)) -> immediate_after_full_implementation | O8: =IF(K8="direct_smoking_prevalence_shift_rr",IF(OR(ISBLANK(G8),ISBLANK(H8),ISBLANK(L8)),"",1-(1+H8*(L8-1))/(1+G8*(L8-1))),IF(K8="tobacco_mortality_prevalence_shift_rr",IF(OR(ISBLANK(G8),ISBLANK(H8),ISBLANK(L8)),"",1-(1+H8*(L8-1)+(G8-H8)*(1-SUMIF(Assumptions!$A$2:$A$37,"tobacco_vascular_erd_ge10_pooled",Assumptions!$B$2:$B$37))*(L8-1))/(1+G8*(L8-1))),IF(K8="direct_loglinear_rr_per_unit_reduction",IF(OR(ISBLANK(L8),ISBLANK(I8)),"",1-1/(L8^I8)),IF(K8="tfa_attributable_ihd_PAF_x_regulatory_gap",IF(ISBLANK(M8),"",M8*SUMIF(Policy_Levers!$B$2:$B$13,INDEX(Intervention_Cause_Map!$B$2:$B$62,MATCH(A8,Intervention_Cause_Map!$A$2:$A$62,0)),Policy_Levers!$Z$2:$Z$13)),"")))) -> 0.00024351283 | P8: =INDEX(Intervention_Cause_Map!$J$2:$J$62,MATCH(A8,Intervention_Cause_Map!$A$2:$A$62,0)) -> I_PH_ALCOHOL_TAX__C_SHARED | Q8: =INDEX(Intervention_Cause_Map!$K$2:$K$62,MATCH(A8,Intervention_Cause_Map!$A$2:$A$62,0)) -> shared-count-once | R8: =SUMIFS(Cost_Components!$S$2:$S$15,Cost_Components!$G$2:$G$15,P8,Cost_Components!$D$2:$D$15,1) -> 0.04 | S8: =IF(COUNTIF(Effect_Parameters!$B$2:$B$62,A8)<>1,"LINK ERROR",IF(INDEX(Intervention_Cause_Map!$N$2:$N$62,MATCH(A8,Intervention_Cause_Map!$A$2:$A$62,0))=0,"EXPLORATORY - DISABLED",IF(AND(E8="sick",F8="dead"),"R UPDATE REQUIRED","READY FOR MODEL"))) -> EXPLORATORY - DISABLED
A9: I_PH_ALCOHOL_TAX__C_HHD | B9: Alcohol tax | C9: Alcohol use | D9: Hypertensive heart disease | E9: well | F9: sick | G9: =SUMIF(Exposure_Targets!$B$2:$B$13,INDEX(Intervention_Cause_Map!$B$2:$B$62,MATCH(A9,Intervention_Cause_Map!$A$2:$A$62,0)),Exposure_Targets!$G$2:$G$13) -> 0.1 | H9: =SUMIF(Exposure_Targets!$B$2:$B$13,INDEX(Intervention_Cause_Map!$B$2:$B$62,MATCH(A9,Intervention_Cause_Map!$A$2:$A$62,0)),Exposure_Targets!$M$2:$M$13) -> 0.08775 | I9: =G9-H9 -> 0.01225 | J9: =IF(G9=0,0,I9/G9) -> 0.1225 | K9: =INDEX(Effect_Parameters!$F$2:$F$62,MATCH(A9,Effect_Parameters!$B$2:$B$62,0)) -> direct_loglinear_rr_per_unit_reduction | L9: =INDEX(Effect_Parameters!$I$2:$I$62,MATCH(A9,Effect_Parameters!$B$2:$B$62,0)) -> 1.0331775 | M9: =INDEX(Effect_Parameters!$K$2:$K$62,MATCH(A9,Effect_Parameters!$B$2:$B$62,0)) -> 0 | N9: =INDEX(Effect_Parameters!$N$2:$N$62,MATCH(A9,Effect_Parameters!$B$2:$B$62,0)) -> immediate_after_full_implementation | O9: =IF(K9="direct_smoking_prevalence_shift_rr",IF(OR(ISBLANK(G9),ISBLANK(H9),ISBLANK(L9)),"",1-(1+H9*(L9-1))/(1+G9*(L9-1))),IF(K9="tobacco_mortality_prevalence_shift_rr",IF(OR(ISBLANK(G9),ISBLANK(H9),ISBLANK(L9)),"",1-(1+H9*(L9-1)+(G9-H9)*(1-SUMIF(Assumptions!$A$2:$A$37,"tobacco_vascular_erd_ge10_pooled",Assumptions!$B$2:$B$37))*(L9-1))/(1+G9*(L9-1))),IF(K9="direct_loglinear_rr_per_unit_reduction",IF(OR(ISBLANK(L9),ISBLANK(I9)),"",1-1/(L9^I9)),IF(K9="tfa_attributable_ihd_PAF_x_regulatory_gap",IF(ISBLANK(M9),"",M9*SUMIF(Policy_Levers!$B$2:$B$13,INDEX(Intervention_Cause_Map!$B$2:$B$62,MATCH(A9,Intervention_Cause_Map!$A$2:$A$62,0)),Policy_Levers!$Z$2:$Z$13)),"")))) -> 0.00039974801 | P9: =INDEX(Intervention_Cause_Map!$J$2:$J$62,MATCH(A9,Intervention_Cause_Map!$A$2:$A$62,0)) -> I_PH_ALCOHOL_TAX__C_SHARED | Q9: =INDEX(Intervention_Cause_Map!$K$2:$K$62,MATCH(A9,Intervention_Cause_Map!$A$2:$A$62,0)) -> shared-count-once | R9: =SUMIFS(Cost_Components!$S$2:$S$15,Cost_Components!$G$2:$G$15,P9,Cost_Components!$D$2:$D$15,1) -> 0.04 | S9: =IF(COUNTIF(Effect_Parameters!$B$2:$B$62,A9)<>1,"LINK ERROR",IF(INDEX(Intervention_Cause_Map!$N$2:$N$62,MATCH(A9,Intervention_Cause_Map!$A$2:$A$62,0))=0,"EXPLORATORY - DISABLED",IF(AND(E9="sick",F9="dead"),"R UPDATE REQUIRED","READY FOR MODEL"))) -> EXPLORATORY - DISABLED
A10: I_PH_ALCOHOL_TAX__C_CMYO | B10: Alcohol tax | C10: Alcohol use | D10: Cardiomyopathy and myocarditis | E10: well | F10: sick | G10: =SUMIF(Exposure_Targets!$B$2:$B$13,INDEX(Intervention_Cause_Map!$B$2:$B$62,MATCH(A10,Intervention_Cause_Map!$A$2:$A$62,0)),Exposure_Targets!$G$2:$G$13) -> 0.1 | H10: =SUMIF(Exposure_Targets!$B$2:$B$13,INDEX(Intervention_Cause_Map!$B$2:$B$62,MATCH(A10,Intervention_Cause_Map!$A$2:$A$62,0)),Exposure_Targets!$M$2:$M$13) -> 0.08775 | I10: =G10-H10 -> 0.01225 | J10: =IF(G10=0,0,I10/G10) -> 0.1225 | K10: =INDEX(Effect_Parameters!$F$2:$F$62,MATCH(A10,Effect_Parameters!$B$2:$B$62,0)) -> direct_loglinear_rr_per_unit_reduction | L10: =INDEX(Effect_Parameters!$I$2:$I$62,MATCH(A10,Effect_Parameters!$B$2:$B$62,0)) -> 1.0131617 | M10: =INDEX(Effect_Parameters!$K$2:$K$62,MATCH(A10,Effect_Parameters!$B$2:$B$62,0)) -> 0 | N10: =INDEX(Effect_Parameters!$N$2:$N$62,MATCH(A10,Effect_Parameters!$B$2:$B$62,0)) -> immediate_after_full_implementation | O10: =IF(K10="direct_smoking_prevalence_shift_rr",IF(OR(ISBLANK(G10),ISBLANK(H10),ISBLANK(L10)),"",1-(1+H10*(L10-1))/(1+G10*(L10-1))),IF(K10="tobacco_mortality_prevalence_shift_rr",IF(OR(ISBLANK(G10),ISBLANK(H10),ISBLANK(L10)),"",1-(1+H10*(L10-1)+(G10-H10)*(1-SUMIF(Assumptions!$A$2:$A$37,"tobacco_vascular_erd_ge10_pooled",Assumptions!$B$2:$B$37))*(L10-1))/(1+G10*(L10-1))),IF(K10="direct_loglinear_rr_per_unit_reduction",IF(OR(ISBLANK(L10),ISBLANK(I10)),"",1-1/(L10^I10)),IF(K10="tfa_attributable_ihd_PAF_x_regulatory_gap",IF(ISBLANK(M10),"",M10*SUMIF(Policy_Levers!$B$2:$B$13,INDEX(Intervention_Cause_Map!$B$2:$B$62,MATCH(A10,Intervention_Cause_Map!$A$2:$A$62,0)),Policy_Levers!$Z$2:$Z$13)),"")))) -> 0.00016016582 | P10: =INDEX(Intervention_Cause_Map!$J$2:$J$62,MATCH(A10,Intervention_Cause_Map!$A$2:$A$62,0)) -> I_PH_ALCOHOL_TAX__C_SHARED | Q10: =INDEX(Intervention_Cause_Map!$K$2:$K$62,MATCH(A10,Intervention_Cause_Map!$A$2:$A$62,0)) -> shared-count-once | R10: =SUMIFS(Cost_Components!$S$2:$S$15,Cost_Components!$G$2:$G$15,P10,Cost_Components!$D$2:$D$15,1) -> 0.04 | S10: =IF(COUNTIF(Effect_Parameters!$B$2:$B$62,A10)<>1,"LINK ERROR",IF(INDEX(Intervention_Cause_Map!$N$2:$N$62,MATCH(A10,Intervention_Cause_Map!$A$2:$A$62,0))=0,"EXPLORATORY - DISABLED",IF(AND(E10="sick",F10="dead"),"R UPDATE REQUIRED","READY FOR MODEL"))) -> EXPLORATORY - DISABLED
A11: I_PH_TOB_CLEAN_AIR__C_IHD | B11: Smoke-free / clean-air law | C11: Smoking | D11: Ischemic heart disease | E11: well | F11: sick | G11: =SUMIF(Exposure_Targets!$B$2:$B$13,INDEX(Intervention_Cause_Map!$B$2:$B$62,MATCH(A11,Intervention_Cause_Map!$A$2:$A$62,0)),Exposure_Targets!$G$2:$G$13) -> 0.303 | H11: =SUMIF(Exposure_Targets!$B$2:$B$13,INDEX(Intervention_Cause_Map!$B$2:$B$62,MATCH(A11,Intervention_Cause_Map!$A$2:$A$62,0)),Exposure_Targets!$M$2:$M$13) -> 0.286335 | I11: =G11-H11 -> 0.016665 | J11: =IF(G11=0,0,I11/G11) -> 0.055 | K11: =INDEX(Effect_Parameters!$F$2:$F$62,MATCH(A11,Effect_Parameters!$B$2:$B$62,0)) -> direct_smoking_prevalence_shift_rr | L11: =INDEX(Effect_Parameters!$I$2:$I$62,MATCH(A11,Effect_Parameters!$B$2:$B$62,0)) -> 1.6 | M11: =INDEX(Effect_Parameters!$K$2:$K$62,MATCH(A11,Effect_Parameters!$B$2:$B$62,0)) -> 0 | N11: =INDEX(Effect_Parameters!$N$2:$N$62,MATCH(A11,Effect_Parameters!$B$2:$B$62,0)) -> jha_piecewise_shared_scalar | O11: =IF(K11="direct_smoking_prevalence_shift_rr",IF(OR(ISBLANK(G11),ISBLANK(H11),ISBLANK(L11)),"",1-(1+H11*(L11-1))/(1+G11*(L11-1))),IF(K11="tobacco_mortality_prevalence_shift_rr",IF(OR(ISBLANK(G11),ISBLANK(H11),ISBLANK(L11)),"",1-(1+H11*(L11-1)+(G11-H11)*(1-SUMIF(Assumptions!$A$2:$A$37,"tobacco_vascular_erd_ge10_pooled",Assumptions!$B$2:$B$37))*(L11-1))/(1+G11*(L11-1))),IF(K11="direct_loglinear_rr_per_unit_reduction",IF(OR(ISBLANK(L11),ISBLANK(I11)),"",1-1/(L11^I11)),IF(K11="tfa_attributable_ihd_PAF_x_regulatory_gap",IF(ISBLANK(M11),"",M11*SUMIF(Policy_Levers!$B$2:$B$13,INDEX(Intervention_Cause_Map!$B$2:$B$62,MATCH(A11,Intervention_Cause_Map!$A$2:$A$62,0)),Policy_Levers!$Z$2:$Z$13)),"")))) -> 0.0084608225 | P11: =INDEX(Intervention_Cause_Map!$J$2:$J$62,MATCH(A11,Intervention_Cause_Map!$A$2:$A$62,0)) -> I_PH_TOB_CLEAN_AIR__C_SHARED | Q11: =INDEX(Intervention_Cause_Map!$K$2:$K$62,MATCH(A11,Intervention_Cause_Map!$A$2:$A$62,0)) -> component-count-once | R11: =SUMIFS(Cost_Components!$S$2:$S$15,Cost_Components!$G$2:$G$15,P11,Cost_Components!$D$2:$D$15,1) -> 0.0077 | S11: =IF(COUNTIF(Effect_Parameters!$B$2:$B$62,A11)<>1,"LINK ERROR",IF(INDEX(Intervention_Cause_Map!$N$2:$N$62,MATCH(A11,Intervention_Cause_Map!$A$2:$A$62,0))=0,"EXPLORATORY - DISABLED",IF(AND(E11="sick",F11="dead"),"R UPDATE REQUIRED","READY FOR MODEL"))) -> READY FOR MODEL
A12: I_PH_TOB_CLEAN_AIR__C_IS | B12: Smoke-free / clean-air law | C12: Smoking | D12: Ischemic stroke | E12: well | F12: sick | G12: =SUMIF(Exposure_Targets!$B$2:$B$13,INDEX(Intervention_Cause_Map!$B$2:$B$62,MATCH(A12,Intervention_Cause_Map!$A$2:$A$62,0)),Exposure_Targets!$G$2:$G$13) -> 0.303 | H12: =SUMIF(Exposure_Targets!$B$2:$B$13,INDEX(Intervention_Cause_Map!$B$2:$B$62,MATCH(A12,Intervention_Cause_Map!$A$2:$A$62,0)),Exposure_Targets!$M$2:$M$13) -> 0.286335 | I12: =G12-H12 -> 0.016665 | J12: =IF(G12=0,0,I12/G12) -> 0.055 | K12: =INDEX(Effect_Parameters!$F$2:$F$62,MATCH(A12,Effect_Parameters!$B$2:$B$62,0)) -> direct_smoking_prevalence_shift_rr | L12: =INDEX(Effect_Parameters!$I$2:$I$62,MATCH(A12,Effect_Parameters!$B$2:$B$62,0)) -> 1.38 | M12: =INDEX(Effect_Parameters!$K$2:$K$62,MATCH(A12,Effect_Parameters!$B$2:$B$62,0)) -> 0 | N12: =INDEX(Effect_Parameters!$N$2:$N$62,MATCH(A12,Effect_Parameters!$B$2:$B$62,0)) -> jha_piecewise_shared_scalar | O12: =IF(K12="direct_smoking_prevalence_shift_rr",IF(OR(ISBLANK(G12),ISBLANK(H12),ISBLANK(L12)),"",1-(1+H12*(L12-1))/(1+G12*(L12-1))),IF(K12="tobacco_mortality_prevalence_shift_rr",IF(OR(ISBLANK(G12),ISBLANK(H12),ISBLANK(L12)),"",1-(1+H12*(L12-1)+(G12-H12)*(1-SUMIF(Assumptions!$A$2:$A$37,"tobacco_vascular_erd_ge10_pooled",Assumptions!$B$2:$B$37))*(L12-1))/(1+G12*(L12-1))),IF(K12="direct_loglinear_rr_per_unit_reduction",IF(OR(ISBLANK(L12),ISBLANK(I12)),"",1-1/(L12^I12)),IF(K12="tfa_attributable_ihd_PAF_x_regulatory_gap",IF(ISBLANK(M12),"",M12*SUMIF(Policy_Levers!$B$2:$B$13,INDEX(Intervention_Cause_Map!$B$2:$B$62,MATCH(A12,Intervention_Cause_Map!$A$2:$A$62,0)),Policy_Levers!$Z$2:$Z$13)),"")))) -> 0.0056788385 | P12: =INDEX(Intervention_Cause_Map!$J$2:$J$62,MATCH(A12,Intervention_Cause_Map!$A$2:$A$62,0)) -> I_PH_TOB_CLEAN_AIR__C_SHARED | Q12: =INDEX(Intervention_Cause_Map!$K$2:$K$62,MATCH(A12,Intervention_Cause_Map!$A$2:$A$62,0)) -> component-count-once | R12: =SUMIFS(Cost_Components!$S$2:$S$15,Cost_Components!$G$2:$G$15,P12,Cost_Components!$D$2:$D$15,1) -> 0.0077 | S12: =IF(COUNTIF(Effect_Parameters!$B$2:$B$62,A12)<>1,"LINK ERROR",IF(INDEX(Intervention_Cause_Map!$N$2:$N$62,MATCH(A12,Intervention_Cause_Map!$A$2:$A$62,0))=0,"EXPLORATORY - DISABLED",IF(AND(E12="sick",F12="dead"),"R UPDATE REQUIRED","READY FOR MODEL"))) -> READY FOR MODEL
A13: I_PH_TOB_CLEAN_AIR__C_ICH | B13: Smoke-free / clean-air law | C13: Smoking | D13: Intracerebral hemorrhage | E13: well | F13: sick | G13: =SUMIF(Exposure_Targets!$B$2:$B$13,INDEX(Intervention_Cause_Map!$B$2:$B$62,MATCH(A13,Intervention_Cause_Map!$A$2:$A$62,0)),Exposure_Targets!$G$2:$G$13) -> 0.303 | H13: =SUMIF(Exposure_Targets!$B$2:$B$13,INDEX(Intervention_Cause_Map!$B$2:$B$62,MATCH(A13,Intervention_Cause_Map!$A$2:$A$62,0)),Exposure_Targets!$M$2:$M$13) -> 0.286335 | I13: =G13-H13 -> 0.016665 | J13: =IF(G13=0,0,I13/G13) -> 0.055 | K13: =INDEX(Effect_Parameters!$F$2:$F$62,MATCH(A13,Effect_Parameters!$B$2:$B$62,0)) -> direct_smoking_prevalence_shift_rr | L13: =INDEX(Effect_Parameters!$I$2:$I$62,MATCH(A13,Effect_Parameters!$B$2:$B$62,0)) -> 1.19 | M13: =INDEX(Effect_Parameters!$K$2:$K$62,MATCH(A13,Effect_Parameters!$B$2:$B$62,0)) -> 0 | N13: =INDEX(Effect_Parameters!$N$2:$N$62,MATCH(A13,Effect_Parameters!$B$2:$B$62,0)) -> jha_piecewise_shared_scalar | O13: =IF(K13="direct_smoking_prevalence_shift_rr",IF(OR(ISBLANK(G13),ISBLANK(H13),ISBLANK(L13)),"",1-(1+H13*(L13-1))/(1+G13*(L13-1))),IF(K13="tobacco_mortality_prevalence_shift_rr",IF(OR(ISBLANK(G13),ISBLANK(H13),ISBLANK(L13)),"",1-(1+H13*(L13-1)+(G13-H13)*(1-SUMIF(Assumptions!$A$2:$A$37,"tobacco_vascular_erd_ge10_pooled",Assumptions!$B$2:$B$37))*(L13-1))/(1+G13*(L13-1))),IF(K13="direct_loglinear_rr_per_unit_reduction",IF(OR(ISBLANK(L13),ISBLANK(I13)),"",1-1/(L13^I13)),IF(K13="tfa_attributable_ihd_PAF_x_regulatory_gap",IF(ISBLANK(M13),"",M13*SUMIF(Policy_Levers!$B$2:$B$13,INDEX(Intervention_Cause_Map!$B$2:$B$62,MATCH(A13,Intervention_Cause_Map!$A$2:$A$62,0)),Policy_Levers!$Z$2:$Z$13)),"")))) -> 0.0029939862 | P13: =INDEX(Intervention_Cause_Map!$J$2:$J$62,MATCH(A13,Intervention_Cause_Map!$A$2:$A$62,0)) -> I_PH_TOB_CLEAN_AIR__C_SHARED | Q13: =INDEX(Intervention_Cause_Map!$K$2:$K$62,MATCH(A13,Intervention_Cause_Map!$A$2:$A$62,0)) -> component-count-once | R13: =SUMIFS(Cost_Components!$S$2:$S$15,Cost_Components!$G$2:$G$15,P13,Cost_Components!$D$2:$D$15,1) -> 0.0077 | S13: =IF(COUNTIF(Effect_Parameters!$B$2:$B$62,A13)<>1,"LINK ERROR",IF(INDEX(Intervention_Cause_Map!$N$2:$N$62,MATCH(A13,Intervention_Cause_Map!$A$2:$A$62,0))=0,"EXPLORATORY - DISABLED",IF(AND(E13="sick",F13="dead"),"R UPDATE REQUIRED","READY FOR MODEL"))) -> READY FOR MODEL
... A62: I_PH_SSB_TAX__C_T2DM__SICK_DEAD | B62: Sugar-sweetened beverage tax | C62: Sugar-sweetened beverage intake | D62: Diabetes mellitus type 2 | E62: sick | F62: dead | G62: =SUMIF(Exposure_Targets!$B$2:$B$13,INDEX(Intervention_Cause_Map!$B$2:$B$62,MATCH(A62,Intervention_Cause_Map!$A$2:$A$62,0)),Exposure_Targets!$G$2:$G$13) -> 0.11428571 | H62: =SUMIF(Exposure_Targets!$B$2:$B$13,INDEX(Intervention_Cause_Map!$B$2:$B$62,MATCH(A62,Intervention_Cause_Map!$A$2:$A$62,0)),Exposure_Targets!$M$2:$M$13) -> 0.094285714 | I62: =G62-H62 -> 0.02 | J62: =IF(G62=0,0,I62/G62) -> 0.175 | K62: =INDEX(Effect_Parameters!$F$2:$F$62,MATCH(A62,Effect_Parameters!$B$2:$B$62,0)) -> direct_loglinear_rr_per_unit_reduction | L62: =INDEX(Effect_Parameters!$I$2:$I$62,MATCH(A62,Effect_Parameters!$B$2:$B$62,0)) -> 1.08 | M62: =INDEX(Effect_Parameters!$K$2:$K$62,MATCH(A62,Effect_Parameters!$B$2:$B$62,0)) -> 0 | N62: =INDEX(Effect_Parameters!$N$2:$N$62,MATCH(A62,Effect_Parameters!$B$2:$B$62,0)) -> immediate_after_full_implementation | O62: =IF(K62="direct_smoking_prevalence_shift_rr",IF(OR(ISBLANK(G62),ISBLANK(H62),ISBLANK(L62)),"",1-(1+H62*(L62-1))/(1+G62*(L62-1))),IF(K62="tobacco_mortality_prevalence_shift_rr",IF(OR(ISBLANK(G62),ISBLANK(H62),ISBLANK(L62)),"",1-(1+H62*(L62-1)+(G62-H62)*(1-SUMIF(Assumptions!$A$2:$A$37,"tobacco_vascular_erd_ge10_pooled",Assumptions!$B$2:$B$37))*(L62-1))/(1+G62*(L62-1))),IF(K62="direct_loglinear_rr_per_unit_reduction",IF(OR(ISBLANK(L62),ISBLANK(I62)),"",1-1/(L62^I62)),IF(K62="tfa_attributable_ihd_PAF_x_regulatory_gap",IF(ISBLANK(M62),"",M62*SUMIF(Policy_Levers!$B$2:$B$13,INDEX(Intervention_Cause_Map!$B$2:$B$62,MATCH(A62,Intervention_Cause_Map!$A$2:$A$62,0)),Policy_Levers!$Z$2:$Z$13)),"")))) -> 0.0015380368 | P62: =INDEX(Intervention_Cause_Map!$J$2:$J$62,MATCH(A62,Intervention_Cause_Map!$A$2:$A$62,0)) -> I_PH_SSB_TAX__C_SHARED | Q62: =INDEX(Intervention_Cause_Map!$K$2:$K$62,MATCH(A62,Intervention_Cause_Map!$A$2:$A$62,0)) -> shared-count-once | R62: =SUMIFS(Cost_Components!$S$2:$S$15,Cost_Components!$G$2:$G$15,P62,Cost_Components!$D$2:$D$15,1) -> 0.04 | S62: =IF(COUNTIF(Effect_Parameters!$B$2:$B$62,A62)<>1,"LINK ERROR",IF(INDEX(Intervention_Cause_Map!$N$2:$N$62,MATCH(A62,Intervention_Cause_Map!$A$2:$A$62,0))=0,"EXPLORATORY - DISABLED",IF(AND(E62="sick",F62="dead"),"R UPDATE REQUIRED","READY FOR MODEL"))) -> EXPLORATORY - DISABLED

Sheet Cost_Components
A1: cost_record_id | B1: cost_component_key | C1: cost_option | D1: selected_for_base_case | E1: intervention_id | F1: cause_id | G1: cost_join_key | H1: intervention_name | I1: cause_name | J1: cost_component | K1: population_in_need_measure | L1: population_in_need_fraction | M1: cost_unit | N1: frequency_per_year | O1: age_start | P1: age_stop | Q1: sex | R1: platform | S1: unit_cost_usd | T1: price_year | U1: indonesia_adjusted_flag | V1: source_country | W1: source_file | X1: source_row | Y1: review_status | Z1: notes | AA1: map_match_count | AB1: selection_count | AC1: qa_status | AD1: parent_package_id | AE1: cost_allocation_share | AF1: package_total_cost_usd_per_capita | AG1: allocation_method | AH1: scenario_role
A2: COST_PH_TOB_TAX | B2: CC_PH_TOB_TAX | C2: Base | D2: 1 | E2: I_PH_TOBACCO_TAX | F2: C_SHARED | G2: I_PH_TOBACCO_TAX__C_SHARED | H2: Tobacco tax | I2: Shared policy cost | J2: Annual intersectoral policy implementation | K2: population | L2: 1 | M2: USD per capita-year | N2: 1 | O2: 0 | P2: 95 | Q2: Both | R2: Intersectoral | S2: 0.04 | T2: 2017 | U2: 0 | V2: China/proxy | W2: PINandCosts0625(1).csv | X2: row 53 | Y2: Review | Z2: Requires Indonesia/price-year adjustment | AA2: =COUNTIF(Intervention_Cause_Map!$J$2:$J$49,G2) -> 4 | AB2: =COUNTIFS($G$2:$G$15,G2,$D$2:$D$15,1) -> 1 | AC2: =IF(AH2="parent_reference","REFERENCE ONLY",IF(AA2<1,"BAD KEY",IF(S2="","MISSING COST",IF(U2=0,"REVIEW ADJUSTMENT",IF(AB2<>1,"CHECK SELECTION","OK"))))) -> REVIEW ADJUSTMENT | AD2: I_PH_TOBACCO_TAX | AE2: 1 | AF2: 0.004 | AG2: direct source value | AH2: standalone
A3: COST_PH_ALC_TAX | B3: CC_PH_ALC_TAX | C3: Base | D3: 1 | E3: I_PH_ALCOHOL_TAX | F3: C_SHARED | G3: I_PH_ALCOHOL_TAX__C_SHARED | H3: Alcohol tax | I3: Shared policy cost | J3: Annual intersectoral policy implementation | K3: population | L3: 1 | M3: USD per capita-year | N3: 1 | O3: 0 | P3: 95 | Q3: Both | R3: Intersectoral | S3: 0.04 | T3: 2017 | U3: 0 | V3: China/proxy | W3: PINandCosts0625(1).csv | X3: row 54 | Y3: Review | Z3: Requires Indonesia/price-year adjustment | AA3: =COUNTIF(Intervention_Cause_Map!$J$2:$J$49,G3) -> 5 | AB3: =COUNTIFS($G$2:$G$15,G3,$D$2:$D$15,1) -> 1 | AC3: =IF(AH3="parent_reference","REFERENCE ONLY",IF(AA3<1,"BAD KEY",IF(S3="","MISSING COST",IF(U3=0,"REVIEW ADJUSTMENT",IF(AB3<>1,"CHECK SELECTION","OK"))))) -> REVIEW ADJUSTMENT | AD3: I_PH_ALCOHOL_TAX | AE3: 1 | AF3: 0.004 | AG3: direct source value | AH3: standalone
A4: COST_REF_TOB_POLICY | B4: CC_REF_TOB_POLICY | C4: Reference | D4: 0 | E4: I_PH_TOBACCO_POLICY | F4: C_SHARED | G4: I_PH_TOBACCO_POLICY__C_SHARED | H4: Tobacco policy package | I4: Shared policy cost | J4: Package total retained for allocation | K4: population | L4: 1 | M4: USD per capita-year | N4: 1 | O4: 0 | P4: 95 | Q4: Both | R4: Intersectoral | S4: 0.0231 | T4: 2017 | U4: 0 | V4: China/proxy | W4: PINandCosts0625(1).csv | X4: row 55 | Y4: Reference | Z4: Not modeled directly; allocated to children | AA4: =COUNTIF(Intervention_Cause_Map!$J$2:$J$49,G4) -> 0 | AB4: =COUNTIFS($G$2:$G$15,G4,$D$2:$D$15,1) -> 0 | AC4: =IF(AH4="parent_reference","REFERENCE ONLY",IF(AA4<1,"BAD KEY",IF(S4="","MISSING COST",IF(U4=0,"REVIEW ADJUSTMENT",IF(AB4<>1,"CHECK SELECTION","OK"))))) -> REFERENCE ONLY | AD4: I_PH_TOBACCO_POLICY | AE4: 1 | AF4: 0.0231 | AG4: package reference | AH4: parent_reference
A5: COST_PH_TOB_CLEAN_AIR | B5: CC_PH_TOB_CLEAN_AIR | C5: Base | D5: 1 | E5: I_PH_TOB_CLEAN_AIR | F5: C_SHARED | G5: I_PH_TOB_CLEAN_AIR__C_SHARED | H5: Smoke-free / clean-air law | I5: Shared policy cost | J5: Annual intersectoral policy implementation | K5: population | L5: 1 | M5: USD per capita-year | N5: 1 | O5: 0 | P5: 95 | Q5: Both | R5: Intersectoral | S5: =AE5*AF5 -> 0.0077 | T5: 2017 | U5: 0 | V5: China/proxy | W5: PINandCosts0625(1).csv | X5: row 55 allocated | Y5: Review | Z5: Requires Indonesia/price-year adjustment | AA5: =COUNTIF(Intervention_Cause_Map!$J$2:$J$49,G5) -> 4 | AB5: =COUNTIFS($G$2:$G$15,G5,$D$2:$D$15,1) -> 1 | AC5: =IF(AH5="parent_reference","REFERENCE ONLY",IF(AA5<1,"BAD KEY",IF(S5="","MISSING COST",IF(U5=0,"REVIEW ADJUSTMENT",IF(AB5<>1,"CHECK SELECTION","OK"))))) -> REVIEW ADJUSTMENT | AD5: I_PH_TOBACCO_POLICY | AE5: =1/COUNTIFS(Scenario_Hierarchy!$A$2:$A$13,AD5,Scenario_Hierarchy!$F$2:$F$13,"child") -> 0.33333333 | AF5: =$S$4 -> 0.0231 | AG5: equal within package | AH5: child
A6: COST_PH_TOB_MEDIA | B6: CC_PH_TOB_MEDIA | C6: Base | D6: 1 | E6: I_PH_TOB_MEDIA | F6: C_SHARED | G6: I_PH_TOB_MEDIA__C_SHARED | H6: Tobacco mass-media campaign | I6: Shared policy cost | J6: Annual intersectoral policy implementation | K6: population | L6: 1 | M6: USD per capita-year | N6: 1 | O6: 0 | P6: 95 | Q6: Both | R6: Intersectoral | S6: =AE6*AF6 -> 0.0077 | T6: 2017 | U6: 0 | V6: China/proxy | W6: PINandCosts0625(1).csv | X6: row 55 allocated | Y6: Review | Z6: Requires Indonesia/price-year adjustment | AA6: =COUNTIF(Intervention_Cause_Map!$J$2:$J$49,G6) -> 4 | AB6: =COUNTIFS($G$2:$G$15,G6,$D$2:$D$15,1) -> 1 | AC6: =IF(AH6="parent_reference","REFERENCE ONLY",IF(AA6<1,"BAD KEY",IF(S6="","MISSING COST",IF(U6=0,"REVIEW ADJUSTMENT",IF(AB6<>1,"CHECK SELECTION","OK"))))) -> REVIEW ADJUSTMENT | AD6: I_PH_TOBACCO_POLICY | AE6: =1/COUNTIFS(Scenario_Hierarchy!$A$2:$A$13,AD6,Scenario_Hierarchy!$F$2:$F$13,"child") -> 0.33333333 | AF6: =$S$4 -> 0.0231 | AG6: equal within package | AH6: child
A7: COST_PH_TOB_AD_BAN | B7: CC_PH_TOB_AD_BAN | C7: Base | D7: 1 | E7: I_PH_TOB_AD_BAN | F7: C_SHARED | G7: I_PH_TOB_AD_BAN__C_SHARED | H7: Tobacco advertising ban | I7: Shared policy cost | J7: Annual intersectoral policy implementation | K7: population | L7: 1 | M7: USD per capita-year | N7: 1 | O7: 0 | P7: 95 | Q7: Both | R7: Intersectoral | S7: =AE7*AF7 -> 0.0077 | T7: 2017 | U7: 0 | V7: China/proxy | W7: PINandCosts0625(1).csv | X7: row 55 allocated | Y7: Review | Z7: Requires Indonesia/price-year adjustment | AA7: =COUNTIF(Intervention_Cause_Map!$J$2:$J$49,G7) -> 4 | AB7: =COUNTIFS($G$2:$G$15,G7,$D$2:$D$15,1) -> 1 | AC7: =IF(AH7="parent_reference","REFERENCE ONLY",IF(AA7<1,"BAD KEY",IF(S7="","MISSING COST",IF(U7=0,"REVIEW ADJUSTMENT",IF(AB7<>1,"CHECK SELECTION","OK"))))) -> REVIEW ADJUSTMENT | AD7: I_PH_TOBACCO_POLICY | AE7: =1/COUNTIFS(Scenario_Hierarchy!$A$2:$A$13,AD7,Scenario_Hierarchy!$F$2:$F$13,"child") -> 0.33333333 | AF7: =$S$4 -> 0.0231 | AG7: equal within package | AH7: child
A8: COST_PH_ALC_POLICY | B8: CC_PH_ALC_POLICY | C8: Base | D8: 1 | E8: I_PH_ALCOHOL_POLICY | F8: C_SHARED | G8: I_PH_ALCOHOL_POLICY__C_SHARED | H8: Alcohol advertising ban | I8: Shared policy cost | J8: Annual intersectoral policy implementation | K8: population | L8: 1 | M8: USD per capita-year | N8: 1 | O8: 0 | P8: 95 | Q8: Both | R8: Intersectoral | S8: 0.0056 | T8: 2017 | U8: 0 | V8: China/proxy | W8: PINandCosts0625(1).csv | X8: row 56 | Y8: Review | Z8: Requires Indonesia/price-year adjustment | AA8: =COUNTIF(Intervention_Cause_Map!$J$2:$J$49,G8) -> 5 | AB8: =COUNTIFS($G$2:$G$15,G8,$D$2:$D$15,1) -> 1 | AC8: =IF(AH8="parent_reference","REFERENCE ONLY",IF(AA8<1,"BAD KEY",IF(S8="","MISSING COST",IF(U8=0,"REVIEW ADJUSTMENT",IF(AB8<>1,"CHECK SELECTION","OK"))))) -> REVIEW ADJUSTMENT | AD8: I_PH_ALCOHOL_POLICY | AE8: 1 | AF8: 0.0056 | AG8: direct source value | AH8: standalone
A9: COST_REF_SALT_POLICY | B9: CC_REF_SALT_POLICY | C9: Reference | D9: 0 | E9: I_PH_SALT_POLICY | F9: C_SHARED | G9: I_PH_SALT_POLICY__C_SHARED | H9: Salt policy package | I9: Shared policy cost | J9: Package total retained for allocation | K9: population | L9: 1 | M9: USD per capita-year | N9: 1 | O9: 0 | P9: 95 | Q9: Both | R9: Intersectoral | S9: 0.0351 | T9: 2017 | U9: 0 | V9: China/proxy | W9: PINandCosts0625(1).csv | X9: row 57 | Y9: Reference | Z9: Not modeled directly; allocated to children | AA9: =COUNTIF(Intervention_Cause_Map!$J$2:$J$49,G9) -> 0 | AB9: =COUNTIFS($G$2:$G$15,G9,$D$2:$D$15,1) -> 0 | AC9: =IF(AH9="parent_reference","REFERENCE ONLY",IF(AA9<1,"BAD KEY",IF(S9="","MISSING COST",IF(U9=0,"REVIEW ADJUSTMENT",IF(AB9<>1,"CHECK SELECTION","OK"))))) -> REFERENCE ONLY | AD9: I_PH_SALT_POLICY | AE9: 1 | AF9: 0.0351 | AG9: package reference | AH9: parent_reference
A10: COST_PH_SALT_REFORM | B10: CC_PH_SALT_REFORM | C10: Base | D10: 1 | E10: I_PH_SALT_REFORM | F10: C_SHARED | G10: I_PH_SALT_REFORM__C_SHARED | H10: Mandatory sodium reformulation | I10: Shared policy cost | J10: Annual intersectoral policy implementation | K10: population | L10: 1 | M10: USD per capita-year | N10: 1 | O10: 0 | P10: 95 | Q10: Both | R10: Intersectoral | S10: =AE10*AF10 -> 0.008775 | T10: 2017 | U10: 0 | V10: China/proxy | W10: PINandCosts0625(1).csv | X10: row 57 allocated | Y10: Review | Z10: Requires Indonesia/price-year adjustment | AA10: =COUNTIF(Intervention_Cause_Map!$J$2:$J$49,G10) -> 4 | AB10: =COUNTIFS($G$2:$G$15,G10,$D$2:$D$15,1) -> 1 | AC10: =IF(AH10="parent_reference","REFERENCE ONLY",IF(AA10<1,"BAD KEY",IF(S10="","MISSING COST",IF(U10=0,"REVIEW ADJUSTMENT",IF(AB10<>1,"CHECK SELECTION","OK"))))) -> REVIEW ADJUSTMENT | AD10: I_PH_SALT_POLICY | AE10: =1/COUNTIFS(Scenario_Hierarchy!$A$2:$A$13,AD10,Scenario_Hierarchy!$F$2:$F$13,"child") -> 0.25 | AF10: =$S$9 -> 0.0351 | AG10: equal within package | AH10: child
A11: COST_PH_SALT_FOPL | B11: CC_PH_SALT_FOPL | C11: Base | D11: 1 | E11: I_PH_SALT_FOPL | F11: C_SHARED | G11: I_PH_SALT_FOPL__C_SHARED | H11: Sodium front-of-pack labelling | I11: Shared policy cost | J11: Annual intersectoral policy implementation | K11: population | L11: 1 | M11: USD per capita-year | N11: 1 | O11: 0 | P11: 95 | Q11: Both | R11: Intersectoral | S11: =AE11*AF11 -> 0.008775 | T11: 2017 | U11: 0 | V11: China/proxy | W11: PINandCosts0625(1).csv | X11: row 57 allocated | Y11: Review | Z11: Requires Indonesia/price-year adjustment | AA11: =COUNTIF(Intervention_Cause_Map!$J$2:$J$49,G11) -> 4 | AB11: =COUNTIFS($G$2:$G$15,G11,$D$2:$D$15,1) -> 1 | AC11: =IF(AH11="parent_reference","REFERENCE ONLY",IF(AA11<1,"BAD KEY",IF(S11="","MISSING COST",IF(U11=0,"REVIEW ADJUSTMENT",IF(AB11<>1,"CHECK SELECTION","OK"))))) -> REVIEW ADJUSTMENT | AD11: I_PH_SALT_POLICY | AE11: =1/COUNTIFS(Scenario_Hierarchy!$A$2:$A$13,AD11,Scenario_Hierarchy!$F$2:$F$13,"child") -> 0.25 | AF11: =$S$9 -> 0.0351 | AG11: equal within package | AH11: child
A12: COST_PH_SALT_MEDIA | B12: CC_PH_SALT_MEDIA | C12: Base | D12: 1 | E12: I_PH_SALT_MEDIA | F12: C_SHARED | G12: I_PH_SALT_MEDIA__C_SHARED | H12: Sodium mass-media campaign | I12: Shared policy cost | J12: Annual intersectoral policy implementation | K12: population | L12: 1 | M12: USD per capita-year | N12: 1 | O12: 0 | P12: 95 | Q12: Both | R12: Intersectoral | S12: =AE12*AF12 -> 0.008775 | T12: 2017 | U12: 0 | V12: China/proxy | W12: PINandCosts0625(1).csv | X12: row 57 allocated | Y12: Review | Z12: Requires Indonesia/price-year adjustment | AA12: =COUNTIF(Intervention_Cause_Map!$J$2:$J$49,G12) -> 4 | AB12: =COUNTIFS($G$2:$G$15,G12,$D$2:$D$15,1) -> 1 | AC12: =IF(AH12="parent_reference","REFERENCE ONLY",IF(AA12<1,"BAD KEY",IF(S12="","MISSING COST",IF(U12=0,"REVIEW ADJUSTMENT",IF(AB12<>1,"CHECK SELECTION","OK"))))) -> REVIEW ADJUSTMENT | AD12: I_PH_SALT_POLICY | AE12: =1/COUNTIFS(Scenario_Hierarchy!$A$2:$A$13,AD12,Scenario_Hierarchy!$F$2:$F$13,"child") -> 0.25 | AF12: =$S$9 -> 0.0351 | AG12: equal within package | AH12: child
A13: COST_PH_SALT_ENV | B13: CC_PH_SALT_ENV | C13: Base | D13: 1 | E13: I_PH_SALT_ENV | F13: C_SHARED | G13: I_PH_SALT_ENV__C_SHARED | H13: Supportive public-institution environment | I13: Shared policy cost | J13: Annual intersectoral policy implementation | K13: population | L13: 1 | M13: USD per capita-year | N13: 1 | O13: 0 | P13: 95 | Q13: Both | R13: Intersectoral | S13: =AE13*AF13 -> 0.008775 | T13: 2017 | U13: 0 | V13: China/proxy | W13: PINandCosts0625(1).csv | X13: row 57 allocated | Y13: Review | Z13: Requires Indonesia/price-year adjustment | AA13: =COUNTIF(Intervention_Cause_Map!$J$2:$J$49,G13) -> 4 | AB13: =COUNTIFS($G$2:$G$15,G13,$D$2:$D$15,1) -> 1 | AC13: =IF(AH13="parent_reference","REFERENCE ONLY",IF(AA13<1,"BAD KEY",IF(S13="","MISSING COST",IF(U13=0,"REVIEW ADJUSTMENT",IF(AB13<>1,"CHECK SELECTION","OK"))))) -> REVIEW ADJUSTMENT | AD13: I_PH_SALT_POLICY | AE13: =1/COUNTIFS(Scenario_Hierarchy!$A$2:$A$13,AD13,Scenario_Hierarchy!$F$2:$F$13,"child") -> 0.25 | AF13: =$S$9 -> 0.0351 | AG13: equal within package | AH13: child
A14: COST_PH_TFA | B14: CC_PH_TFA | C14: Base | D14: 1 | E14: I_PH_TFA_POLICY | F14: C_SHARED | G14: I_PH_TFA_POLICY__C_SHARED | H14: Industrial trans-fat elimination regulation | I14: Shared policy cost | J14: Annual intersectoral policy implementation | K14: population | L14: 1 | M14: USD per capita-year | N14: 1 | O14: 0 | P14: 95 | Q14: Both | R14: Intersectoral | S14: 0.0087 | T14: 2017 | U14: 0 | V14: China/proxy | W14: PINandCosts0625(1).csv | X14: row 58 | Y14: Review | Z14: Requires Indonesia/price-year adjustment | AA14: =COUNTIF(Intervention_Cause_Map!$J$2:$J$49,G14) -> 1 | AB14: =COUNTIFS($G$2:$G$15,G14,$D$2:$D$15,1) -> 1 | AC14: =IF(AH14="parent_reference","REFERENCE ONLY",IF(AA14<1,"BAD KEY",IF(S14="","MISSING COST",IF(U14=0,"REVIEW ADJUSTMENT",IF(AB14<>1,"CHECK SELECTION","OK"))))) -> REVIEW ADJUSTMENT | AD14: I_PH_TFA_POLICY | AE14: 1 | AF14: 0.0087 | AG14: direct source value | AH14: standalone
A15: COST_PH_SSB_TAX | B15: CC_PH_SSB_TAX | C15: Base | D15: 1 | E15: I_PH_SSB_TAX | F15: C_SHARED | G15: I_PH_SSB_TAX__C_SHARED | H15: Sugar-sweetened beverage tax | I15: Shared policy cost | J15: Annual intersectoral policy implementation | K15: population | L15: 1 | M15: USD per capita-year | N15: 1 | O15: 0 | P15: 95 | Q15: Both | R15: Intersectoral | S15: 0.04 | T15: 2017 | U15: 0 | V15: China/proxy | W15: PINandCosts0625(1).csv | X15: tax proxy | Y15: Review | Z15: Requires Indonesia/price-year adjustment | AA15: =COUNTIF(Intervention_Cause_Map!$J$2:$J$49,G15) -> 5 | AB15: =COUNTIFS($G$2:$G$15,G15,$D$2:$D$15,1) -> 1 | AC15: =IF(AH15="parent_reference","REFERENCE ONLY",IF(AA15<1,"BAD KEY",IF(S15="","MISSING COST",IF(U15=0,"REVIEW ADJUSTMENT",IF(AB15<>1,"CHECK SELECTION","OK"))))) -> REVIEW ADJUSTMENT | AD15: I_PH_SSB_TAX | AE15: 1 | AF15: 0.004 | AG15: direct source value | AH15: standalone

Sheet Countdown_Methods
A1: method_id | B1: concept | C1: formula_or_rule | D1: implemented_in | E1: linkage_key | F1: Indonesia interpretation
A2: M01 | B2: Individual intervention unit | C2: Each scalable component has its own intervention_id, exposure, links, effects and cost key | D2: Scenario_Hierarchy | E2: intervention_id | F2: Report cases, deaths, costs and cost effectiveness by component
A3: M02 | B3: Nested package scenario | C3: Run all children jointly; do not sum child health outcomes | D3: Scenario_Hierarchy | E3: parent_scenario_id | F3: Preserves I_PH_TOBACCO_POLICY and I_PH_SALT_POLICY
A4: M03 | B4: Regulatory score | C4: none=0; partial=0.5; full=1 | D4: Assumptions; Policy_Levers | E4: intervention_id | F4: none->full full effect; partial->full half; full->full zero
A5: M04 | B5: Regulatory effect | C5: reduction=full_component_effect*max(0,target_score-baseline_score) | D5: Policy_Levers | E5: intervention_id | F5: Each regulation separately scalable
A6: M05 | B6: Price-change tax | C6: price_change=max(0,target-baseline); reduction=abs(elasticity)*price_change | D6: Policy_Levers | E6: intervention_id | F6: Alcohol and SSB taxes
A7: M06 | B7: Tax-share tax | C7: price_change=(1-baseline_share)/(1-target_share)-1 | D7: Policy_Levers | E7: intervention_id | F7: Tobacco tax
A8: M07 | B8: Exposure target | C8: target=max(floor,baseline*(1-relative_reduction)) | D8: Exposure_Targets | E8: intervention_id | F8: One row per intervention
A9: M08 | B9: Tobacco response | C9: 1-[1+target_p*(RR-1)]/[1+baseline_p*(RR-1)] | D9: Model_Input_View | E9: intervention_cause_key | F9: No PAF
A10: M09 | B10: Log-linear response | C10: 1-1/(RR_per_unit^absolute_reduction) | D10: Model_Input_View | E10: intervention_cause_key | F10: Alcohol, sodium, TFA RR and SSB
A11: M10 | B11: TFA RR conversion | C11: RR per 1% energy=sqrt(1.21) | D11: Risk_Response | E11: RR_TFA_IHD_1PCT | F11: Approximately 1.10
A12: M11 | B12: Optional TFA PAF | C12: If method=PAF: effect=optional_PAF*implementation_gap | D12: Assumptions; Model_Input_View | E12: I_PH_TFA_POLICY | F12: Does not block RR base case
... A17: Key reference values | B17: Value | C17: Unit | D17: Source | E17: Status | F17: Note
A18: TFA source RR | B18: 1.21 | C18: RR per 2 percentage-points energy | D18: https://www.ahajournals.org/doi/10.1161/CIRCULATIONAHA.118.038160 | E18: Base case source | F18: Square-root conversion
A19: TFA model RR | B19: 1.1 | C19: approximate RR per 1 percentage-point energy | D19: https://www.ahajournals.org/doi/10.1161/JAHA.115.002891 | E19: Base case | F19: Formula retains precision
A20: Indonesia tobacco tax baseline | B20: 0.75 | C20: minimum retail-price tax share | D20: WHO tobacco report 2025 | E20: Base case | F20: WHO best-practice group
A21: Indonesia SSB response | B21: 0.175 | C21: relative consumption reduction | D21: https://doi.org/10.1371/journal.pone.0293913 | E21: Base case | F21: 20% price increase
A22: M16 | B22: Tobacco mortality full effect | C22: RRq=1+(1-ERD_10plus)*(RRc-1); RRfull=[1+pt(RRc-1)+(p0-pt)(RRq-1)]/[1+p0(RRc-1)] | D22: Model_Input_View; R implementation | E22: sick -> dead | F22: Jha vascular mortality is a sensitivity/proxy for post-diagnosis case fatality
A23: M17 | B23: Rate-ratio probability conversion | C23: p1=1-(1-p0)^RR_effective | D23: R transition update | E23: well -> sick; sick -> dead | F23: Do not multiply annual probabilities directly by a rate ratio
A24: M18 | B24: SSB mortality sensitivity | C24: RR=1.08 per serving/day through the SSB intake mediation path | D24: Risk_Response; Effect_Parameters | E24: I_PH_SSB_TAX__C_T2DM__SICK_DEAD | F24: Disabled by default; outcome is all-cause mortality among adults with T2DM

Sheet Scope_and_Sources
A1: item | B1: decision | C1: reason | D1: domain | F1: source | G1: use | H1: location | I1: notes
A2: Tobacco tax | B2: Include individually | C2: Fiscal baseline and target levels drive exposure | D2: Public health | F2: WHO tobacco report 2025 | G2: Indonesia tobacco tax baseline | H2: https://www.who.int/publications/i/item/9789240112063 | I2: Indonesia in >=75% group
A3: Tobacco package | B3: Preserve as parent | C3: Three children modeled separately and jointly | D3: Scenario design | F3: WHO NCD Progress Monitor 2025 | G3: None/partial/full categories | H3: https://cdn.who.int/media/docs/default-source/ncds/ncd-surveillance/pm2024-profiles.pdf | I3: Tobacco, alcohol and healthy-diet measures
A4: Alcohol tax | B4: Include individually | C4: Incremental price change through elasticity | D4: Public health | F4: WHO Indonesia 2026 | G4: Current food-policy implementation | H4: https://www.who.int/indonesia/news/detail/27-01-2026-indonesia-develops-new-regulations-to-tackle-unhealthy-food-consumption | I4: Technical implementation ongoing
A5: Alcohol advertising ban | B5: Include individually | C5: Regulatory categories drive incremental effect | D5: Public health | F5: WHO Indonesia 2024 | G5: TFA baseline | H5: https://www.who.int/indonesia/news/detail/17-06-2024-op-ed--eliminate-trans-fat-for-a-healthier--more-productive-indonesia | I5: Best-practice regulation not fully implemented
A6: Salt package | B6: Preserve as parent | C6: Four SHAKE children modeled separately and jointly | D6: Scenario design | F6: Kontis et al. 2019 | G6: TFA RR context | H6: https://www.ahajournals.org/doi/10.1161/CIRCULATIONAHA.118.038160 | I6: 21% higher IHD risk per 2% energy
A7: Industrial TFA regulation | B7: RR base case | C7: Exposure change and RR; PAF optional | D7: Model integration | F7: Wang et al. 2016 | G7: TFA risk per exposure | H7: https://www.ahajournals.org/doi/10.1161/JAHA.115.002891 | I7: CHD burden response
A8: SSB tax | B8: Include individually | C8: Tax change -> elasticity -> exposure | D8: Public health | F8: NCD Countdown supplement | G8: Component effects and scale-up | H8: Watkins 2022 pp 31-34 | I8: Primary methods
A9: Package health outcomes | B9: Rerun jointly | C9: Do not sum overlapping child cases/deaths | D9: Model integration | F9: PINandCosts0625(1).csv | G9: Package policy costs | H9: rows 53-58 | I9: 2017 USD China; adjust for Indonesia
A10: Package costs | B10: Sum children | C10: Parent reference cost allocated and excluded | D10: Economic evaluation | F10: Widarjono et al. 2023 | G10: Indonesia SSB elasticity | H10: https://doi.org/10.1371/journal.pone.0293913 | I10: 2021 SUSENAS
A11: Tobacco sick-to-dead | B11: Include as labeled proxy | C11: Jha vascular mortality supports magnitude and timing but is not post-diagnosis case fatality | D11: Sensitivity analysis | F11: Lara-Castor et al. 2025 | G11: SSB exposure and RRs | H11: https://doi.org/10.1038/s41591-024-03345-4 | I11: Direct and validation inputs
A12: SSB sick-to-dead | B12: Include disabled by default | C12: All-cause mortality among adults with T2DM is not diabetes-specific death | D12: Exploratory sensitivity | F12: APCSC | G12: Smoking RRs | H12: https://doi.org/10.1093/ije/dyi104 | I12: IHD and stroke
A13: SSB mortality synthesis | B13: Context only | C13: Recent synthesis supports a high-versus-low mortality association but does not replace the dose-response input | D13: Evidence review | F13: Wood et al. 2018 | G13: Alcohol response | H13: https://doi.org/10.1016/S0140-6736(18)30134-X | I13: Converted per litre/year

Sheet QA_Checks
A1: check_id | B1: check | C1: expected | D1: actual | E1: status | F1: interpretation
A2: QA01 | B2: Duplicate intervention-cause keys | C2: 0 | D2: =COUNTIF(Intervention_Cause_Map!$Q$2:$Q$62,">1") -> 0 | E2: =IF(D2=C2,"PASS","FAIL") -> PASS | F2: Each link key appears once
A3: QA02 | B3: Exposure rows with missing/bad inputs | C3: 0 | D3: =COUNTIF(Exposure_Targets!$U$2:$U$13,"<>OK") -> 0 | E3: =IF(D3=C3,"PASS","FAIL") -> PASS | F3: Every intervention has exposure input
A4: QA03 | B4: Policy levers with missing/bad fiscal or regulatory inputs | C4: 0 | D4: =COUNTIF(Policy_Levers!$O$2:$O$13,"<>OK") -> 0 | E4: =IF(D4=C4,"PASS","FAIL") -> PASS | F4: Separate tax/regulation fields
A5: QA04 | B5: Effect rows requiring review | C5: 13 | D5: =COUNTIF(Effect_Parameters!$W$2:$W$62,"<>OK") -> 13 | E5: =IF(D5=C5,"PASS","FAIL") -> PASS | F5: Twelve tobacco mortality proxy rows plus one exploratory SSB mortality row are intentionally marked REVIEW
A6: QA05 | B6: Selected costs not localized for Indonesia | C6: 0 | D6: =COUNTIFS(Cost_Components!$D$2:$D$15,1,Cost_Components!$AC$2:$AC$15,"<>OK") -> 12 | E6: =IF(D6=C6,"PASS","FAIL") -> FAIL | F6: Source costs still require adjustment
A7: QA06 | B7: Interventions without exactly one exposure row | C7: 0 | D7: =ABS(COUNTA(Scenario_Hierarchy!$C$2:$C$13)-COUNTA(Exposure_Targets!$B$2:$B$13)) -> 0 | E7: =IF(D7=C7,"PASS","FAIL") -> PASS | F7: Twelve interventions
A8: QA07 | B8: Links without exactly one effect row | C8: 0 | D8: =ABS(COUNTA(Intervention_Cause_Map!$A$2:$A$62)-COUNTA(Effect_Parameters!$B$2:$B$62)) -> 0 | E8: =IF(D8=C8,"PASS","FAIL") -> PASS | F8: Sixty-one uniquely keyed transition links
A9: QA08 | B9: Links requiring cause expansion | C9: 0 | D9: =SUM(Intervention_Cause_Map!$O$2:$O$62) -> 0 | E9: =IF(D9=C9,"PASS","FAIL") -> PASS | F9: No unresolved cause expansion
A10: QA09 | B10: Links outside allowed transition pairs | C10: 0 | D10: =COUNTA(Intervention_Cause_Map!$A$2:$A$62)-COUNTIFS(Intervention_Cause_Map!$L$2:$L$62,"well",Intervention_Cause_Map!$M$2:$M$62,"sick")-COUNTIFS(Intervention_Cause_Map!$L$2:$L$62,"sick",Intervention_Cause_Map!$M$2:$M$62,"dead") -> 0 | E10: =IF(D10=C10,"PASS","FAIL") -> PASS | F10: Allowed: well -> sick incidence and sick -> dead case fatality
A11: QA10 | B11: Effect rows missing a source | C11: 0 | D11: =COUNTBLANK(Effect_Parameters!$R$2:$R$62) -> 0 | E11: =IF(D11=C11,"PASS","FAIL") -> PASS | F11: Every effect cites a source
A12: QA11 | B12: Direct-RR risks requiring a PAF in RR mode | C12: 0 | D12: =IF(Assumptions!$B$27="RR",COUNTIFS(Effect_Parameters!$D$2:$D$62,"R_TFA",Effect_Parameters!$L$2:$L$62,1),0)+COUNTIFS(Effect_Parameters!$D$2:$D$62,"R_SMOKING",Effect_Parameters!$L$2:$L$62,1)+COUNTIFS(Effect_Parameters!$D$2:$D$62,"R_ALCOHOL",Effect_Parameters!$L$2:$L$62,1)+COUNTIFS(Effect_Parameters!$D$2:$D$62,"R_SODIUM",Effect_Parameters!$L$2:$L$62,1)+COUNTIFS(Effect_Parameters!$D$2:$D$62,"R_SSB",Effect_Parameters!$L$2:$L$62,1) -> 0 | E12: =IF(D12=C12,"PASS","FAIL") -> PASS | F12: RR base case is PAF-independent
A13: QA12 | B13: Separate IHD-high-blood-glucose links | C13: 0 | D13: =COUNTIF(Intervention_Cause_Map!$F$2:$F$62,"C_IHD_HBG") -> 0 | E13: =IF(D13=C13,"PASS","FAIL") -> PASS | F13: Avoid double counting
A14: QA13 | B14: Regulatory levels outside none/partial/full | C14: 0 | D14: =COUNTIFS(Policy_Levers!$E$2:$E$13,"regulatory_gap_multiplicative",Policy_Levers!$V$2:$V$13,"<>none",Policy_Levers!$V$2:$V$13,"<>partial",Policy_Levers!$V$2:$V$13,"<>full")+COUNTIFS(Policy_Levers!$E$2:$E$13,"regulatory_gap_multiplicative",Policy_Levers!$W$2:$W$13,"<>none",Policy_Levers!$W$2:$W$13,"<>partial",Policy_Levers!$W$2:$W$13,"<>full") -> 0 | E14: =IF(D14=C14,"PASS","FAIL") -> PASS | F14: Only requested categories
A15: QA14 | B15: Tax rows missing fiscal baseline/target | C15: 0 | D15: =COUNTIFS(Policy_Levers!$E$2:$E$13,"tax_share_to_price_elasticity",Policy_Levers!$S$2:$S$13,"")+COUNTIFS(Policy_Levers!$E$2:$E$13,"tax_share_to_price_elasticity",Policy_Levers!$T$2:$T$13,"")+COUNTIFS(Policy_Levers!$E$2:$E$13,"price_elasticity",Policy_Levers!$S$2:$S$13,"")+COUNTIFS(Policy_Levers!$E$2:$E$13,"price_elasticity",Policy_Levers!$T$2:$T$13,"") -> 0 | E15: =IF(D15=C15,"PASS","FAIL") -> PASS | F15: Explicit fiscal levels
A16: QA15 | B16: Child interventions missing parent | C16: 0 | D16: =COUNTIFS(Scenario_Hierarchy!$F$2:$F$13,"child",Scenario_Hierarchy!$A$2:$A$13,"") -> 0 | E16: =IF(D16=C16,"PASS","FAIL") -> PASS | F16: Nested children require parent
A17: QA16 | B17: Tobacco child count differs from 3 | C17: 0 | D17: =ABS(COUNTIF(Scenario_Hierarchy!$A$2:$A$13,"I_PH_TOBACCO_POLICY")-3) -> 0 | E17: =IF(D17=C17,"PASS","FAIL") -> PASS | F17: Clean air, media, ad ban
A18: QA17 | B18: Salt child count differs from 4 | C18: 0 | D18: =ABS(COUNTIF(Scenario_Hierarchy!$A$2:$A$13,"I_PH_SALT_POLICY")-4) -> 0 | E18: =IF(D18=C18,"PASS","FAIL") -> PASS | F18: Reformulation, FOPL, media, institutions
A19: QA18 | B19: Tobacco child cost shares do not sum to 1 | C19: 0 | D19: =IF(ABS(SUMIFS(Cost_Components!$AE$2:$AE$15,Cost_Components!$AD$2:$AD$15,"I_PH_TOBACCO_POLICY",Cost_Components!$AH$2:$AH$15,"child")-1)<0.000001,0,1) -> 0 | E19: =IF(D19=C19,"PASS","FAIL") -> PASS | F19: Preserve package cost
A20: QA19 | B20: Salt child cost shares do not sum to 1 | C20: 0 | D20: =IF(ABS(SUMIFS(Cost_Components!$AE$2:$AE$15,Cost_Components!$AD$2:$AD$15,"I_PH_SALT_POLICY",Cost_Components!$AH$2:$AH$15,"child")-1)<0.000001,0,1) -> 0 | E20: =IF(D20=C20,"PASS","FAIL") -> PASS | F20: Preserve package cost
A21: QA20 | B21: Sick -> dead link count | C21: 13 | D21: =COUNTIFS(Intervention_Cause_Map!$L$2:$L$62,"sick",Intervention_Cause_Map!$M$2:$M$62,"dead") -> 13 | E21: =IF(D21=C21,"PASS","FAIL") -> PASS | F21: Twelve tobacco links plus one exploratory SSB link
A22: QA21 | B22: Tobacco CVD sick -> dead link count | C22: 12 | D22: =COUNTIFS(Intervention_Cause_Map!$C$2:$C$62,"R_SMOKING",Intervention_Cause_Map!$L$2:$L$62,"sick",Intervention_Cause_Map!$M$2:$M$62,"dead") -> 12 | E22: =IF(D22=C22,"PASS","FAIL") -> PASS | F22: Four tobacco policies x three CVD causes
A23: QA22 | B23: SSB mortality links enabled for base case | C23: 0 | D23: =SUMIFS(Intervention_Cause_Map!$N$2:$N$62,Intervention_Cause_Map!$A$2:$A$62,"I_PH_SSB_TAX__C_T2DM__SICK_DEAD") -> 0 | E23: =IF(D23=C23,"PASS","FAIL") -> PASS | F23: Exploratory SSB mortality remains disabled by default
A24: QA23 | B24: Sick -> dead effects missing a source | C24: 0 | D24: =COUNTIFS(Effect_Parameters!$P$2:$P$62,"sick",Effect_Parameters!$Q$2:$Q$62,"dead",Effect_Parameters!$R$2:$R$62,"") -> 0 | E24: =IF(D24=C24,"PASS","FAIL") -> PASS | F24: Every mortality effect cites its evidence
A25: QA24 | B25: Tobacco CVD links not using Jha base timing | C25: 0 | D25: =COUNTIFS(Effect_Parameters!$D$2:$D$62,"R_SMOKING",Effect_Parameters!$E$2:$E$62,"C_IHD",Effect_Parameters!$N$2:$N$62,"<>jha_piecewise_shared_scalar")+COUNTIFS(Effect_Parameters!$D$2:$D$62,"R_SMOKING",Effect_Parameters!$E$2:$E$62,"C_IS",Effect_Parameters!$N$2:$N$62,"<>jha_piecewise_shared_scalar")+COUNTIFS(Effect_Parameters!$D$2:$D$62,"R_SMOKING",Effect_Parameters!$E$2:$E$62,"C_ICH",Effect_Parameters!$N$2:$N$62,"<>jha_piecewise_shared_scalar") -> 0 | E25: =IF(D25=C25,"PASS","FAIL") -> PASS | F25: All tobacco CVD incidence and mortality links use jha_piecewise_shared_scalar

Sheet Scenario_Hierarchy
A1: parent_scenario_id | B1: parent_scenario_name | C1: intervention_id | D1: intervention_name | E1: package_group | F1: scenario_role | G1: include_in_parent_scenario | H1: standalone_scenario_id | I1: parent_aggregation_rule | J1: outcome_reporting_rule | K1: cost_reporting_rule | L1: component_order | M1: source_note
A2: I_PH_TOBACCO_TAX | B2: Tobacco tax | C2: I_PH_TOBACCO_TAX | D2: Tobacco tax | E2: Tobacco | F2: standalone | G2: 1 | H2: I_PH_TOBACCO_TAX | I2: single intervention | J2: report intervention | K2: report intervention cost | L2: 1 | M2: Fiscal
A3: I_PH_ALCOHOL_TAX | B3: Alcohol tax | C3: I_PH_ALCOHOL_TAX | D3: Alcohol tax | E3: Alcohol | F3: standalone | G3: 1 | H3: I_PH_ALCOHOL_TAX | I3: single intervention | J3: report intervention | K3: report intervention cost | L3: 1 | M3: Fiscal
A4: I_PH_TOBACCO_POLICY | B4: Tobacco policy package | C4: I_PH_TOB_CLEAN_AIR | D4: Smoke-free / clean-air law | E4: Tobacco | F4: child | G4: 1 | H4: I_PH_TOB_CLEAN_AIR | I4: run children jointly | J4: report child and parent | K4: sum child costs; rerun health jointly | L4: 1 | M4: MPOWER
A5: I_PH_TOBACCO_POLICY | B5: Tobacco policy package | C5: I_PH_TOB_MEDIA | D5: Tobacco mass-media campaign | E5: Tobacco | F5: child | G5: 1 | H5: I_PH_TOB_MEDIA | I5: run children jointly | J5: report child and parent | K5: sum child costs; rerun health jointly | L5: 2 | M5: MPOWER
A6: I_PH_TOBACCO_POLICY | B6: Tobacco policy package | C6: I_PH_TOB_AD_BAN | D6: Tobacco advertising ban | E6: Tobacco | F6: child | G6: 1 | H6: I_PH_TOB_AD_BAN | I6: run children jointly | J6: report child and parent | K6: sum child costs; rerun health jointly | L6: 3 | M6: MPOWER
A7: I_PH_ALCOHOL_POLICY | B7: Alcohol advertising policy | C7: I_PH_ALCOHOL_POLICY | D7: Alcohol advertising ban | E7: Alcohol | F7: standalone | G7: 1 | H7: I_PH_ALCOHOL_POLICY | I7: single intervention | J7: report intervention | K7: report intervention cost | L7: 1 | M7: Alcohol policy
A8: I_PH_SALT_POLICY | B8: Salt policy package | C8: I_PH_SALT_REFORM | D8: Mandatory sodium reformulation | E8: Diet | F8: child | G8: 1 | H8: I_PH_SALT_REFORM | I8: run children jointly | J8: report child and parent | K8: sum child costs; rerun health jointly | L8: 1 | M8: SHAKE
A9: I_PH_SALT_POLICY | B9: Salt policy package | C9: I_PH_SALT_FOPL | D9: Sodium front-of-pack labelling | E9: Diet | F9: child | G9: 1 | H9: I_PH_SALT_FOPL | I9: run children jointly | J9: report child and parent | K9: sum child costs; rerun health jointly | L9: 2 | M9: SHAKE
A10: I_PH_SALT_POLICY | B10: Salt policy package | C10: I_PH_SALT_MEDIA | D10: Sodium mass-media campaign | E10: Diet | F10: child | G10: 1 | H10: I_PH_SALT_MEDIA | I10: run children jointly | J10: report child and parent | K10: sum child costs; rerun health jointly | L10: 3 | M10: SHAKE
A11: I_PH_SALT_POLICY | B11: Salt policy package | C11: I_PH_SALT_ENV | D11: Supportive public-institution environment | E11: Diet | F11: child | G11: 1 | H11: I_PH_SALT_ENV | I11: run children jointly | J11: report child and parent | K11: sum child costs; rerun health jointly | L11: 4 | M11: SHAKE
A12: I_PH_TFA_POLICY | B12: Industrial TFA regulation | C12: I_PH_TFA_POLICY | D12: Industrial trans-fat elimination regulation | E12: Diet | F12: standalone | G12: 1 | H12: I_PH_TFA_POLICY | I12: single intervention | J12: report intervention | K12: report intervention cost | L12: 1 | M12: REPLACE
A13: I_PH_SSB_TAX | B13: SSB tax | C13: I_PH_SSB_TAX | D13: Sugar-sweetened beverage tax | E13: Diet | F13: standalone | G13: 1 | H13: I_PH_SSB_TAX | I13: single intervention | J13: report intervention | K13: report intervention cost | L13: 1 | M13: Fiscal
