Workbook

Sheet README
A1: Indonesia 70-30-30 to 70-70-70 — stand-alone input workbook
A3: Formula-driven cascade inputs • NCD-RisC hypertension and diabetes • cholesterol coverage follows hypertension
A5: Readiness | C5: Interventions | E5: Model causes | G5: Intervention-cause links
A6: =QA_Checks!E14 -> MODEL INTEGRATION REQUIRED | C6: =COUNTA(Dictionaries!A2:A3) -> 2 | E6: =COUNTIF(Dictionaries!H2:H6,1) -> 5 | G6: =COUNTA(Intervention_Cause_Map!A2:A7) -> 6
A9: How to use the workbook
A10: 1 | B10: Edit yellow cells only; light-blue cells are formulas or derived values.
A11: 2 | B11: Review Coverage to audit baseline and target cascade arithmetic; 13.65% and 41.65% are used exactly.
A12: 3 | B12: Use Coverage_Trajectory for annual intervention coverage and Model_Input_View for model-ready transition multipliers.
A13: 4 | B13: Run the accompanying R script to create CSV/RDS handoff files; it recomputes formulas from raw inputs.
A14: 5 | B14: Health outcomes require the calibrated Markov baseline and scenario runner; national cost formulae are supplied in the companion results workbook.
A16: Key review items retained explicitly
A17: Missing | B17: Calibrated national Markov baseline RDS and scenario runner were not supplied; deaths, cases, and life-years cannot yet be recalculated.
A18: Review | B18: Diabetes control is an editable 34.21% among-treated baseline derived from the 2023 national care cascade and cross-checked against a peer-reviewed 32.0% estimate.
A19: Ready | B19: Exact effective coverage is 13.65% in 2030 and 41.65% in 2040; no rounded override is applied.
A20: Missing | B20: Provincial cascade and calibrated disease-burden inputs are absent; the provincial sheet is illustrative only.
A21: Ready | B21: Updated diabetes screening, non-insulin management, and insulin-management costs are Indonesia-adjusted 2023 USD inputs.
A23: Color legend: yellow = editable input • light blue = formula/derived • green = valid • orange/red = review or missing

Sheet Assumptions
A1: parameter_id | B1: value | C1: unit | D1: base_case | E1: lower_bound | F1: upper_bound | G1: description | H1: source
A2: analysis_start_year | B2: 2025 | C2: year | D2: 2025 | E2: 2025 | F2: 2025 | G2: First modeled year | H2: Agreed analysis horizon
A3: analysis_end_year | B3: 2050 | C3: year | D3: 2050 | E3: 2050 | F3: 2050 | G3: Last modeled year | H3: Agreed analysis horizon
A4: first_target_year | B4: 2030 | C4: year | D4: 2030 | E4: 2030 | F4: 2030 | G4: Year to achieve 70-30-30 | H4: World Bank/UW request, 27 Aug 2026
A5: final_target_year | B5: 2040 | C5: year | D5: 2040 | E5: 2040 | F5: 2040 | G5: Year to achieve 70-70-70 | H5: World Bank/UW request, 27 Aug 2026
A6: target_diagnosis_share | B6: 0.7 | C6: proportion | D6: 0.7 | E6: 0.7 | F6: 0.7 | G6: Diagnosis step for both targets | H6: World Bank/UW request
A7: first_target_treatment_conditional | B7: 0.3 | C7: proportion | D7: 0.3 | E7: 0.3 | F7: 0.3 | G7: Treated among diagnosed in 2030 | H7: 70-30-30 definition
A8: first_target_control_conditional | B8: 0.3 | C8: proportion | D8: 0.3 | E8: 0.3 | F8: 0.3 | G8: Controlled among treated in 2030 | H8: 70-30-30 definition
A9: final_target_treatment_conditional | B9: 0.7 | C9: proportion | D9: 0.7 | E9: 0.7 | F9: 0.7 | G9: Treated among diagnosed in 2040 | H9: 70-70-70 definition
A10: final_target_control_conditional | B10: 0.7 | C10: proportion | D10: 0.7 | E10: 0.7 | F10: 0.7 | G10: Controlled among treated in 2040 | H10: 70-70-70 definition
A11: treated_uncontrolled_effect_fraction | B11: 0.5 | C11: share of full effect | D11: 0.5 | E11: 0.5 | F11: 0.5 | G11: Effect received when treated but uncontrolled | H11: World Bank/UW request
A12: first_target_effective_coverage_exact | B12: =B6*B7*(B8+(1-B8)*B11) -> 0.1365 | C12: proportion | D12: 0.1365 | E12: 0.1365 | F12: 0.1365 | G12: Exact 70-30-30 effective coverage; no rounding override | H12: World Bank/UW cascade specification
A13: final_target_effective_coverage_exact | B13: =B6*B9*(B10+(1-B10)*B11) -> 0.4165 | C13: proportion | D13: 0.4165 | E13: 0.4165 | F13: 0.4165 | G13: Exact 70-70-70 effective coverage; no rounding override | H13: World Bank/UW cascade specification
A14: diabetes_baseline_control_among_treated | B14: 0.34210526 | C14: proportion | D14: 0.34210526 | E14: 0.32 | F14: 0.363 | G14: Derived as 6.5% controlled / 19.0% treated in the 2023 national diabetes cascade; editable | H14: Muharram et al. medRxiv 2026; peer-reviewed national estimate 32.0% HbA1c<7%
A15: diabetes_baseline_diagnosis_conditioning | B15: 1 | C15: proportion | D15: 1 | E15: 1 | F15: 1 | G15: Conditions directly on all people with diabetes so reported treatment is reproduced | H15: Explicit modeling assumption
A16: cholesterol_coverage_proxy | B16: hypertension | C16: text | D16: hypertension | E16: hypertension | F16: hypertension | G16: Cholesterol coverage follows hypertension coverage | H16: World Bank/UW request
A17: scale_up_shape | B17: piecewise_linear | C17: text | D17: piecewise_linear | E17: piecewise_linear | F17: piecewise_linear | G17: Linear to 2030, then linear to 2040 | H17: World Bank/UW request
A18: post_target_rule | B18: hold | C18: text | D18: hold | E18: hold | F18: hold | G18: Maintain achieved level after 2040 | H18: World Bank/UW request
A19: prevent_coverage_backsliding | B19: 1 | C19: 0/1 | D19: 1 | E19: 0 | F19: 1 | G19: When a measured baseline already exceeds a milestone, retain baseline rather than scale down | H19: Scale-up interpretation
A20: scenario_id | B20: S_70_30_30_TO_70_70_70 | C20: text | D20: S_70_30_30_TO_70_70_70 | G20: Stable scenario identifier | H20: This analysis
A21: model_baseline_rds | C21: path | G21: Calibrated national baseline RDS; required for health outcomes | H21: Not supplied
A22: model_runner_script | C22: path | G22: Existing Markov scenario runner; required for health outcomes | H22: Not supplied
A23: model_output_directory | B23: output/70_30_30_to_70_70_70 | C23: path | D23: output/70_30_30_to_70_70_70 | G23: Dedicated output directory | H23: This analysis
A24: cost_discount_rate | B24: 0.03 | C24: proportion/year | D24: 0.03 | E24: 0 | F24: 0.05 | G24: Annual cost discount rate | H24: Supplied Indonesia input workbook
A25: health_discount_rate | B25: 0.03 | C25: proportion/year | D25: 0.03 | E25: 0 | F25: 0.05 | G25: Annual health discount rate | H25: Supplied Indonesia input workbook
A26: cost_price_year | B26: 2023 | C26: USD year | D26: 2023 | E26: 2023 | F26: 2023 | G26: Reporting price year | H26: Supplied Indonesia input workbook
A27: currency | B27: USD | C27: currency | D27: USD | E27: USD | F27: USD | G27: Reporting currency | H27: Supplied Indonesia input workbook
A28: downstream_cost_offsets | B28: 0 | C28: 0/1 flag | D28: 0 | E28: 0 | F28: 1 | G28: Include downstream disease-cost offsets | H28: input_file.xlsx
A29: economic_perspective | B29: health_system | C29: text | D29: health_system | E29: health_system | F29: societal | G29: Economic evaluation perspective | H29: Working assumption
A30: bca_base_year | B30: 2025 | C30: year | D30: 2025 | E30: 2025 | F30: 2026 | G30: Base year to which BCA benefits and costs are both discounted (single shared base year) | H30: Robinson et al. 2019 Reference Case Guidelines for BCA in Global Health & Development (CHDS/Harvard); = analysis_start_year
A31: bca_discount_rate_primary | B31: 0.03 | C31: proportion/year | D31: 0.03 | E31: 0.03 | F31: 0.05 | G31: Primary real discount rate applied to BOTH benefits and costs in the BCA | H31: Robinson et al. 2019 Reference Case Guidelines for BCA in Global Health & Development (CHDS/Harvard); context-specific primary rate
A32: bca_discount_rate_sensitivity_3pct | B32: 0.03 | C32: proportion/year | D32: 0.03 | E32: 0.03 | F32: 0.03 | G32: Standardized sensitivity discount rate (3%) | H32: Robinson et al. 2019 Reference Case Guidelines for BCA in Global Health & Development (CHDS/Harvard); standardized sensitivity
A33: bca_discount_rate_sensitivity_2x_gdp_pc_growth | B33: 0.08 | C33: proportion/year | D33: 0.08 | E33: 0.06 | F33: 0.1 | G33: Standardized sensitivity = 2x projected near-term real GDP per-capita growth; Model 08 recomputes from SSP2 | H33: Robinson et al. 2019 Reference Case Guidelines for BCA in Global Health & Development (CHDS/Harvard); IIASA SSP 3.1 (SSP2)
A34: vsl_us_gni_ratio | B34: 160 | C34: ratio (VSL/GNI per capita) | D34: 160 | E34: 100 | F34: 230 | G34: U.S. reference VSL-to-GNI-per-capita ratio used for the income transfer | H34: Robinson et al. 2019 Reference Case Guidelines for BCA in Global Health & Development (CHDS/Harvard)
A35: vsl_income_elasticity_preferred | B35: 1.5 | C35: elasticity | D35: 1.5 | E35: 1 | F35: 1.5 | G35: Income elasticity of VSL for LMIC extrapolation (preferred / reference case) | H35: Robinson et al. 2019 Reference Case Guidelines for BCA in Global Health & Development (CHDS/Harvard)
A36: vsl_floor_gni_multiple | B36: 20 | C36: ratio (VSL/GNI per capita) | D36: 20 | E36: 20 | F36: 20 | G36: Lower bound: transferred VSL not below this multiple of target-country GNI per capita | H36: Robinson et al. 2019 Reference Case Guidelines for BCA in Global Health & Development (CHDS/Harvard)
A37: vsl_sensitivity_gni_multiple_100 | B37: 100 | C37: ratio (VSL/GNI per capita) | D37: 100 | E37: 100 | F37: 100 | G37: Standardized sensitivity 1: VSL = 100 x target GNI per capita | H37: Robinson et al. 2019 Reference Case Guidelines for BCA in Global Health & Development (CHDS/Harvard)
A38: vsl_sensitivity_gni_multiple_160 | B38: 160 | C38: ratio (VSL/GNI per capita) | D38: 160 | E38: 160 | F38: 160 | G38: Standardized sensitivity 2: VSL = 160 x target GNI per capita | H38: Robinson et al. 2019 Reference Case Guidelines for BCA in Global Health & Development (CHDS/Harvard)
... A40: vsly_adult_max_age | B40: 64 | C40: age (years) | D40: 64 | E40: 64 | F40: 95 | G40: Upper bound of adult (working-age) population for the VSLY average-adult-age denominator | H40: ILO / World Bank working-age population 15-64
A41: bca_currency_basis | B41: PPP_international_dollars | C41: text | D41: PPP_international_dollars | G41: Common monetary basis for BCA benefits and costs; VSL is transferred using GNI per capita at PPP | H41: Robinson et al. 2019 Reference Case Guidelines for BCA in Global Health & Development (CHDS/Harvard)
A42: bca_price_year | B42: 2023 | C42: year | D42: 2023 | E42: 2020 | F42: 2024 | G42: Real price year for BCA benefits and costs (must match the cost price year) | H42: = cost_price_year / reporting_price_year
A43: cost_to_bca_currency_factor | B43: 3 | C43: int$ per market US$ | D43: 3 | E43: 2.7 | F43: 3.3 | G43: Multiplier converting market-exchange-rate USD costs to PPP international dollars (benefit basis); = 1 / WB ICP price-level ratio | H43: World Bank ICP PA.NUS.PPPC.RF (Indonesia price-level ratio ~0.33)
A44: bca_standing | B44: societal | C44: text | D44: societal | G44: Standing/perspective for the BCA (whose benefits and costs count) | H44: Robinson et al. 2019 Reference Case Guidelines for BCA in Global Health & Development (CHDS/Harvard)
A45: bca_scope | B45: partial_mortality_benefit | C45: text | D45: partial_mortality_benefit | G45: Scope: benefits limited to averted mortality (VSL/VSLY); costs limited to implementation/health-system. NOT a full societal BCA | H45: Model scope limitation

Sheet Dictionaries
A1: intervention_id | B1: intervention_name | C1: package_group | D1: definition | E1: cause_id | F1: cause_name | G1: model_name | H1: is_model_cause
A2: I_CVD_PRIMARY | B2: Primary prevention of CVD | C2: Primary CVD prevention | D2: Hypertension treatment plus statin coverage, using the agreed cascade | E2: C_IHD | F2: Ischemic heart disease | G2: Ischemic heart disease | H2: 1
A3: I_T2D_TREATMENT | B3: Longitudinal treatment of type 2 diabetes | C3: Diabetes treatment | D3: Treatment affects direct diabetes deaths and IHD attributable to high blood glucose | E3: C_IS | F3: Ischemic stroke | G3: Ischemic stroke | H3: 1
E4: C_ICH | F4: Intracerebral hemorrhage | G4: Intracerebral hemorrhage | H4: 1
E5: C_HHD | F5: Hypertensive heart disease | G5: Hypertensive heart disease | H5: 1
E6: C_T2D | F6: Diabetes mellitus type 2 | G6: Type 2 diabetes | H6: 1
E7: C_SHARED | F7: Shared intervention cost | G7: Not a disease model | H7: 0

Sheet Intervention_Cause_Map
A1: intervention_cause_key | B1: intervention_id | C1: intervention_name | D1: cause_id | E1: cause_name | F1: model_name | G1: transition_from | H1: transition_to | I1: effect_key | J1: cost_join_key | K1: cost_scope | L1: include_flag | M1: notes
A2: I_CVD_PRIMARY__C_IHD | B2: I_CVD_PRIMARY | C2: Primary prevention of CVD | D2: C_IHD | E2: Ischemic heart disease | F2: Ischemic heart disease | G2: well | H2: sick | I2: I_CVD_PRIMARY__C_IHD | J2: I_CVD_PRIMARY__C_SHARED | K2: shared-count-once | L2: 1 | M2: Hypertension and statin coverage follow the same cascade
A3: I_CVD_PRIMARY__C_IS | B3: I_CVD_PRIMARY | C3: Primary prevention of CVD | D3: C_IS | E3: Ischemic stroke | F3: Ischemic stroke | G3: well | H3: sick | I3: I_CVD_PRIMARY__C_IS | J3: I_CVD_PRIMARY__C_SHARED | K3: shared-count-once | L3: 1 | M3: Hypertension and statin coverage follow the same cascade
A4: I_CVD_PRIMARY__C_ICH | B4: I_CVD_PRIMARY | C4: Primary prevention of CVD | D4: C_ICH | E4: Intracerebral hemorrhage | F4: Intracerebral hemorrhage | G4: well | H4: sick | I4: I_CVD_PRIMARY__C_ICH | J4: I_CVD_PRIMARY__C_SHARED | K4: shared-count-once | L4: 1 | M4: Hypertension and statin coverage follow the same cascade
A5: I_CVD_PRIMARY__C_HHD | B5: I_CVD_PRIMARY | C5: Primary prevention of CVD | D5: C_HHD | E5: Hypertensive heart disease | F5: Hypertensive heart disease | G5: well | H5: sick | I5: I_CVD_PRIMARY__C_HHD | J5: I_CVD_PRIMARY__C_SHARED | K5: shared-count-once | L5: 1 | M5: Hypertension coverage drives this link
A6: I_T2D_TREATMENT__C_T2D | B6: I_T2D_TREATMENT | C6: Longitudinal treatment of type 2 diabetes | D6: C_T2D | E6: Diabetes mellitus type 2 | F6: Type 2 diabetes | G6: sick | H6: dead_t2d | I6: I_T2D_TREATMENT__C_T2D | J6: I_T2D_TREATMENT__C_T2D | K6: cause-specific | L6: 1 | M6: Direct diabetes mortality effect
A7: I_T2D_TREATMENT__C_IHD | B7: I_T2D_TREATMENT | C7: Longitudinal treatment of type 2 diabetes | D7: C_IHD | E7: IHD attributable to high blood glucose | F7: Ischemic heart disease | G7: sick | H7: dead_ihd | I7: I_T2D_TREATMENT__C_IHD | J7: I_T2D_TREATMENT__C_T2D | K7: shared-count-once | L7: 1 | M7: Count diabetes treatment cost once

Sheet Effect_Sizes
A1: effect_id | B1: intervention_cause_key | C1: intervention_id | D1: cause_id | E1: intervention_name | F1: cause_name | G1: transition_from | H1: transition_to | I1: effect_measure | J1: effect_value | K1: affected_fraction | L1: age_start | M1: age_stop | N1: sex | O1: source_file | P1: source_row | Q1: review_status | R1: notes | S1: map_match_count | T1: qa_status
A2: E_PRIMARY_IHD | B2: I_CVD_PRIMARY__C_IHD | C2: I_CVD_PRIMARY | D2: C_IHD | E2: Primary prevention of CVD | F2: Ischemic heart disease | G2: well | H2: sick | I2: relative_risk_reduction | J2: 0.58 | K2: 0.8 | L2: 30 | M2: 80 | N2: Both | O2: taxonomy_effect_size.xlsx | P2: Sheet 1, row 136 | Q2: Provisional | R2: Average Fair Choices hypertension/statin effect | S2: =COUNTIF(Intervention_Cause_Map!$A$2:$A$7,B2) -> 1 | T2: =IF(S2<>1,"BAD KEY",IF(OR(J2<0,J2>1,K2<0,K2>1),"BAD VALUE","OK")) -> OK
A3: E_PRIMARY_IS | B3: I_CVD_PRIMARY__C_IS | C3: I_CVD_PRIMARY | D3: C_IS | E3: Primary prevention of CVD | F3: Ischemic stroke | G3: well | H3: sick | I3: relative_risk_reduction | J3: 0.54 | K3: 0.8 | L3: 30 | M3: 80 | N3: Both | O3: taxonomy_effect_size.xlsx | P3: Sheet 1, row 133 | Q3: Provisional | R3: Average Fair Choices hypertension/statin effect | S3: =COUNTIF(Intervention_Cause_Map!$A$2:$A$7,B3) -> 1 | T3: =IF(S3<>1,"BAD KEY",IF(OR(J3<0,J3>1,K3<0,K3>1),"BAD VALUE","OK")) -> OK
A4: E_PRIMARY_ICH | B4: I_CVD_PRIMARY__C_ICH | C4: I_CVD_PRIMARY | D4: C_ICH | E4: Primary prevention of CVD | F4: Intracerebral hemorrhage | G4: well | H4: sick | I4: relative_risk_reduction | J4: 0.49 | K4: 0.8 | L4: 30 | M4: 80 | N4: Both | O4: taxonomy_effect_size.xlsx | P4: Sheet 1, row 134 | Q4: Provisional | R4: Average Fair Choices hypertension/statin effect | S4: =COUNTIF(Intervention_Cause_Map!$A$2:$A$7,B4) -> 1 | T4: =IF(S4<>1,"BAD KEY",IF(OR(J4<0,J4>1,K4<0,K4>1),"BAD VALUE","OK")) -> OK
A5: E_PRIMARY_HHD | B5: I_CVD_PRIMARY__C_HHD | C5: I_CVD_PRIMARY | D5: C_HHD | E5: Primary prevention of CVD | F5: Hypertensive heart disease | G5: well | H5: sick | I5: relative_risk_reduction | J5: 0.47 | K5: 1 | L5: 30 | M5: 80 | N5: Both | O5: taxonomy_effect_size.xlsx | P5: Sheet 1, row 135 | Q5: Provisional | R5: Average Fair Choices hypertension/statin effect | S5: =COUNTIF(Intervention_Cause_Map!$A$2:$A$7,B5) -> 1 | T5: =IF(S5<>1,"BAD KEY",IF(OR(J5<0,J5>1,K5<0,K5>1),"BAD VALUE","OK")) -> OK
A6: E_T2D_DIRECT | B6: I_T2D_TREATMENT__C_T2D | C6: I_T2D_TREATMENT | D6: C_T2D | E6: Longitudinal treatment of type 2 diabetes | F6: Diabetes mellitus type 2 | G6: sick | H6: dead_t2d | I6: relative_risk_reduction | J6: 0.28 | K6: 1 | L6: 0 | M6: 95 | N6: Both | O6: taxonomy_effect_size.xlsx | P6: Sheet 1, row 173 | Q6: Provisional | R6: Direct diabetes mortality effect | S6: =COUNTIF(Intervention_Cause_Map!$A$2:$A$7,B6) -> 1 | T6: =IF(S6<>1,"BAD KEY",IF(OR(J6<0,J6>1,K6<0,K6>1),"BAD VALUE","OK")) -> OK
A7: E_T2D_IHD_HBG | B7: I_T2D_TREATMENT__C_IHD | C7: I_T2D_TREATMENT | D7: C_IHD | E7: Longitudinal treatment of type 2 diabetes | F7: IHD attributable to high blood glucose | G7: sick | H7: dead_ihd | I7: relative_risk_reduction | J7: 0.15 | K7: 0.15 | L7: 0 | M7: 95 | N7: Both | O7: taxonomy_effect_size.xlsx | P7: Sheet 1, row 174 | Q7: Review | R7: Confirm attributable-fraction implementation | S7: =COUNTIF(Intervention_Cause_Map!$A$2:$A$7,B7) -> 1 | T7: =IF(S7<>1,"BAD KEY",IF(OR(J7<0,J7>1,K7<0,K7>1),"BAD VALUE","OK")) -> OK

Sheet Coverage
A1: coverage_id | B1: risk_factor_id | C1: risk_factor_name | D1: sex | E1: milestone | F1: year | G1: diagnosis_step | H1: treatment_step_conditional | I1: control_step_conditional | J1: diagnosed_share_all_condition | K1: treated_share_all_condition | L1: controlled_share_all_condition | M1: treated_uncontrolled_share | N1: partial_effect_fraction | O1: exact_effective_coverage | P1: policy_effective_coverage_override | Q1: model_effective_coverage | R1: source | S1: assumption_note | T1: qa_status
A2: CVG_RF_HTN_Men_BASE | B2: RF_HTN | C2: Hypertension | D2: Men | E2: Baseline | F2: 2025 | G2: =Raw_NCDRisC!H2 -> 0.29011104 | H2: =Raw_NCDRisC!I2/Raw_NCDRisC!H2 -> 0.53038727 | I2: =Raw_NCDRisC!J2/Raw_NCDRisC!I2 -> 0.23288796 | J2: =G2 -> 0.29011104 | K2: =G2*H2 -> 0.1538712 | L2: =K2*I2 -> 0.035834751 | M2: =K2-L2 -> 0.11803645 | N2: =Assumptions!$B$11 -> 0.5 | O2: =L2+N2*M2 -> 0.094852977 | Q2: =IF(P2="",O2,P2) -> 0.094852977 | R2: NCD-RisC 2019 hypertension cascade | S2: Observed diagnosed, treated, and controlled shares. | T2: =IF(OR(G2<0,G2>1,H2<0,H2>1,I2<0,I2>1,Q2<0,Q2>1),"BAD","OK") -> OK
A3: CVG_RF_HTN_Men_2030 | B3: RF_HTN | C3: Hypertension | D3: Men | E3: 70-30-30 | F3: 2030 | G3: =Assumptions!$B$6 -> 0.7 | H3: =Assumptions!$B$7 -> 0.3 | I3: =Assumptions!$B$8 -> 0.3 | J3: =G3 -> 0.7 | K3: =G3*H3 -> 0.21 | L3: =K3*I3 -> 0.063 | M3: =K3-L3 -> 0.147 | N3: =Assumptions!$B$11 -> 0.5 | O3: =L3+N3*M3 -> 0.1365 | Q3: =O3 -> 0.1365 | R3: World Bank/UW policy target | S3: Exact cascade arithmetic is used without a rounded override. | T3: =IF(OR(G3<0,G3>1,H3<0,H3>1,I3<0,I3>1,Q3<0,Q3>1),"BAD","OK") -> OK
A4: CVG_RF_HTN_Men_2040 | B4: RF_HTN | C4: Hypertension | D4: Men | E4: 70-70-70 | F4: 2040 | G4: =Assumptions!$B$6 -> 0.7 | H4: =Assumptions!$B$9 -> 0.7 | I4: =Assumptions!$B$10 -> 0.7 | J4: =G4 -> 0.7 | K4: =G4*H4 -> 0.49 | L4: =K4*I4 -> 0.343 | M4: =K4-L4 -> 0.147 | N4: =Assumptions!$B$11 -> 0.5 | O4: =L4+N4*M4 -> 0.4165 | Q4: =O4 -> 0.4165 | R4: World Bank/UW policy target | S4: Exact cascade arithmetic is used without a rounded override. | T4: =IF(OR(G4<0,G4>1,H4<0,H4>1,I4<0,I4>1,Q4<0,Q4>1),"BAD","OK") -> OK
A5: CVG_RF_HTN_Women_BASE | B5: RF_HTN | C5: Hypertension | D5: Women | E5: Baseline | F5: 2025 | G5: =Raw_NCDRisC!H3 -> 0.40958943 | H5: =Raw_NCDRisC!I3/Raw_NCDRisC!H3 -> 0.52283352 | I5: =Raw_NCDRisC!J3/Raw_NCDRisC!I3 -> 0.23915523 | J5: =G5 -> 0.40958943 | K5: =G5*H5 -> 0.21414708 | L5: =K5*I5 -> 0.051214394 | M5: =K5-L5 -> 0.16293269 | N5: =Assumptions!$B$11 -> 0.5 | O5: =L5+N5*M5 -> 0.13268074 | Q5: =IF(P5="",O5,P5) -> 0.13268074 | R5: NCD-RisC 2019 hypertension cascade | S5: Observed diagnosed, treated, and controlled shares. | T5: =IF(OR(G5<0,G5>1,H5<0,H5>1,I5<0,I5>1,Q5<0,Q5>1),"BAD","OK") -> OK
A6: CVG_RF_HTN_Women_2030 | B6: RF_HTN | C6: Hypertension | D6: Women | E6: 70-30-30 | F6: 2030 | G6: =Assumptions!$B$6 -> 0.7 | H6: =Assumptions!$B$7 -> 0.3 | I6: =Assumptions!$B$8 -> 0.3 | J6: =G6 -> 0.7 | K6: =G6*H6 -> 0.21 | L6: =K6*I6 -> 0.063 | M6: =K6-L6 -> 0.147 | N6: =Assumptions!$B$11 -> 0.5 | O6: =L6+N6*M6 -> 0.1365 | Q6: =O6 -> 0.1365 | R6: World Bank/UW policy target | S6: Exact cascade arithmetic is used without a rounded override. | T6: =IF(OR(G6<0,G6>1,H6<0,H6>1,I6<0,I6>1,Q6<0,Q6>1),"BAD","OK") -> OK
A7: CVG_RF_HTN_Women_2040 | B7: RF_HTN | C7: Hypertension | D7: Women | E7: 70-70-70 | F7: 2040 | G7: =Assumptions!$B$6 -> 0.7 | H7: =Assumptions!$B$9 -> 0.7 | I7: =Assumptions!$B$10 -> 0.7 | J7: =G7 -> 0.7 | K7: =G7*H7 -> 0.49 | L7: =K7*I7 -> 0.343 | M7: =K7-L7 -> 0.147 | N7: =Assumptions!$B$11 -> 0.5 | O7: =L7+N7*M7 -> 0.4165 | Q7: =O7 -> 0.4165 | R7: World Bank/UW policy target | S7: Exact cascade arithmetic is used without a rounded override. | T7: =IF(OR(G7<0,G7>1,H7<0,H7>1,I7<0,I7>1,Q7<0,Q7>1),"BAD","OK") -> OK
A8: CVG_RF_T2D_Men_BASE | B8: RF_T2D | C8: Type 2 diabetes | D8: Men | E8: Baseline | F8: 2025 | G8: =Assumptions!$B$15 -> 1 | H8: =Raw_NCDRisC!I4 -> 0.19418973 | I8: =Assumptions!$B$14 -> 0.34210526 | J8: =G8 -> 1 | K8: =G8*H8 -> 0.19418973 | L8: =K8*I8 -> 0.066433328 | M8: =K8-L8 -> 0.1277564 | N8: =Assumptions!$B$11 -> 0.5 | O8: =L8+N8*M8 -> 0.13031153 | Q8: =IF(P8="",O8,P8) -> 0.13031153 | R8: NCD-RisC 2022 diabetes treatment | S8: Control among treated is the editable national baseline in Assumptions; NCD-RisC supplies treatment. | T8: =IF(OR(G8<0,G8>1,H8<0,H8>1,I8<0,I8>1,Q8<0,Q8>1),"BAD","OK") -> OK
A9: CVG_RF_T2D_Men_2030 | B9: RF_T2D | C9: Type 2 diabetes | D9: Men | E9: 70-30-30 | F9: 2030 | G9: =Assumptions!$B$6 -> 0.7 | H9: =Assumptions!$B$7 -> 0.3 | I9: =Assumptions!$B$8 -> 0.3 | J9: =G9 -> 0.7 | K9: =G9*H9 -> 0.21 | L9: =K9*I9 -> 0.063 | M9: =K9-L9 -> 0.147 | N9: =Assumptions!$B$11 -> 0.5 | O9: =L9+N9*M9 -> 0.1365 | Q9: =O9 -> 0.1365 | R9: World Bank/UW policy target | S9: Exact cascade arithmetic is used without a rounded override. | T9: =IF(OR(G9<0,G9>1,H9<0,H9>1,I9<0,I9>1,Q9<0,Q9>1),"BAD","OK") -> OK
A10: CVG_RF_T2D_Men_2040 | B10: RF_T2D | C10: Type 2 diabetes | D10: Men | E10: 70-70-70 | F10: 2040 | G10: =Assumptions!$B$6 -> 0.7 | H10: =Assumptions!$B$9 -> 0.7 | I10: =Assumptions!$B$10 -> 0.7 | J10: =G10 -> 0.7 | K10: =G10*H10 -> 0.49 | L10: =K10*I10 -> 0.343 | M10: =K10-L10 -> 0.147 | N10: =Assumptions!$B$11 -> 0.5 | O10: =L10+N10*M10 -> 0.4165 | Q10: =O10 -> 0.4165 | R10: World Bank/UW policy target | S10: Exact cascade arithmetic is used without a rounded override. | T10: =IF(OR(G10<0,G10>1,H10<0,H10>1,I10<0,I10>1,Q10<0,Q10>1),"BAD","OK") -> OK
A11: CVG_RF_T2D_Women_BASE | B11: RF_T2D | C11: Type 2 diabetes | D11: Women | E11: Baseline | F11: 2025 | G11: =Assumptions!$B$15 -> 1 | H11: =Raw_NCDRisC!I5 -> 0.24665382 | I11: =Assumptions!$B$14 -> 0.34210526 | J11: =G11 -> 1 | K11: =G11*H11 -> 0.24665382 | L11: =K11*I11 -> 0.084381571 | M11: =K11-L11 -> 0.16227225 | N11: =Assumptions!$B$11 -> 0.5 | O11: =L11+N11*M11 -> 0.1655177 | Q11: =IF(P11="",O11,P11) -> 0.1655177 | R11: NCD-RisC 2022 diabetes treatment | S11: Control among treated is the editable national baseline in Assumptions; NCD-RisC supplies treatment. | T11: =IF(OR(G11<0,G11>1,H11<0,H11>1,I11<0,I11>1,Q11<0,Q11>1),"BAD","OK") -> OK
A12: CVG_RF_T2D_Women_2030 | B12: RF_T2D | C12: Type 2 diabetes | D12: Women | E12: 70-30-30 | F12: 2030 | G12: =Assumptions!$B$6 -> 0.7 | H12: =Assumptions!$B$7 -> 0.3 | I12: =Assumptions!$B$8 -> 0.3 | J12: =G12 -> 0.7 | K12: =G12*H12 -> 0.21 | L12: =K12*I12 -> 0.063 | M12: =K12-L12 -> 0.147 | N12: =Assumptions!$B$11 -> 0.5 | O12: =L12+N12*M12 -> 0.1365 | Q12: =O12 -> 0.1365 | R12: World Bank/UW policy target | S12: Exact cascade arithmetic is used without a rounded override. | T12: =IF(OR(G12<0,G12>1,H12<0,H12>1,I12<0,I12>1,Q12<0,Q12>1),"BAD","OK") -> OK
A13: CVG_RF_T2D_Women_2040 | B13: RF_T2D | C13: Type 2 diabetes | D13: Women | E13: 70-70-70 | F13: 2040 | G13: =Assumptions!$B$6 -> 0.7 | H13: =Assumptions!$B$9 -> 0.7 | I13: =Assumptions!$B$10 -> 0.7 | J13: =G13 -> 0.7 | K13: =G13*H13 -> 0.49 | L13: =K13*I13 -> 0.343 | M13: =K13-L13 -> 0.147 | N13: =Assumptions!$B$11 -> 0.5 | O13: =L13+N13*M13 -> 0.4165 | Q13: =O13 -> 0.4165 | R13: World Bank/UW policy target | S13: Exact cascade arithmetic is used without a rounded override. | T13: =IF(OR(G13<0,G13>1,H13<0,H13>1,I13<0,I13>1,Q13<0,Q13>1),"BAD","OK") -> OK
A14: CVG_RF_CHOL_Men_BASE | B14: RF_CHOL | C14: Cholesterol | D14: Men | E14: Baseline | F14: 2025 | G14: =G2 -> 0.29011104 | H14: =H2 -> 0.53038727 | I14: =I2 -> 0.23288796 | J14: =G14 -> 0.29011104 | K14: =G14*H14 -> 0.1538712 | L14: =K14*I14 -> 0.035834751 | M14: =K14-L14 -> 0.11803645 | N14: =Assumptions!$B$11 -> 0.5 | O14: =L14+N14*M14 -> 0.094852977 | Q14: =IF(P14="",O14,P14) -> 0.094852977 | R14: Proxy from hypertension coverage | S14: Cholesterol treatment coverage follows hypertension coverage. | T14: =IF(OR(G14<0,G14>1,H14<0,H14>1,I14<0,I14>1,Q14<0,Q14>1),"BAD","OK") -> OK
A15: CVG_RF_CHOL_Men_2030 | B15: RF_CHOL | C15: Cholesterol | D15: Men | E15: 70-30-30 | F15: 2030 | G15: =Assumptions!$B$6 -> 0.7 | H15: =Assumptions!$B$7 -> 0.3 | I15: =Assumptions!$B$8 -> 0.3 | J15: =G15 -> 0.7 | K15: =G15*H15 -> 0.21 | L15: =K15*I15 -> 0.063 | M15: =K15-L15 -> 0.147 | N15: =Assumptions!$B$11 -> 0.5 | O15: =L15+N15*M15 -> 0.1365 | Q15: =O15 -> 0.1365 | R15: World Bank/UW policy target | S15: Exact cascade arithmetic is used without a rounded override. | T15: =IF(OR(G15<0,G15>1,H15<0,H15>1,I15<0,I15>1,Q15<0,Q15>1),"BAD","OK") -> OK
A16: CVG_RF_CHOL_Men_2040 | B16: RF_CHOL | C16: Cholesterol | D16: Men | E16: 70-70-70 | F16: 2040 | G16: =Assumptions!$B$6 -> 0.7 | H16: =Assumptions!$B$9 -> 0.7 | I16: =Assumptions!$B$10 -> 0.7 | J16: =G16 -> 0.7 | K16: =G16*H16 -> 0.49 | L16: =K16*I16 -> 0.343 | M16: =K16-L16 -> 0.147 | N16: =Assumptions!$B$11 -> 0.5 | O16: =L16+N16*M16 -> 0.4165 | Q16: =O16 -> 0.4165 | R16: World Bank/UW policy target | S16: Exact cascade arithmetic is used without a rounded override. | T16: =IF(OR(G16<0,G16>1,H16<0,H16>1,I16<0,I16>1,Q16<0,Q16>1),"BAD","OK") -> OK
A17: CVG_RF_CHOL_Women_BASE | B17: RF_CHOL | C17: Cholesterol | D17: Women | E17: Baseline | F17: 2025 | G17: =G5 -> 0.40958943 | H17: =H5 -> 0.52283352 | I17: =I5 -> 0.23915523 | J17: =G17 -> 0.40958943 | K17: =G17*H17 -> 0.21414708 | L17: =K17*I17 -> 0.051214394 | M17: =K17-L17 -> 0.16293269 | N17: =Assumptions!$B$11 -> 0.5 | O17: =L17+N17*M17 -> 0.13268074 | Q17: =IF(P17="",O17,P17) -> 0.13268074 | R17: Proxy from hypertension coverage | S17: Cholesterol treatment coverage follows hypertension coverage. | T17: =IF(OR(G17<0,G17>1,H17<0,H17>1,I17<0,I17>1,Q17<0,Q17>1),"BAD","OK") -> OK
A18: CVG_RF_CHOL_Women_2030 | B18: RF_CHOL | C18: Cholesterol | D18: Women | E18: 70-30-30 | F18: 2030 | G18: =Assumptions!$B$6 -> 0.7 | H18: =Assumptions!$B$7 -> 0.3 | I18: =Assumptions!$B$8 -> 0.3 | J18: =G18 -> 0.7 | K18: =G18*H18 -> 0.21 | L18: =K18*I18 -> 0.063 | M18: =K18-L18 -> 0.147 | N18: =Assumptions!$B$11 -> 0.5 | O18: =L18+N18*M18 -> 0.1365 | Q18: =O18 -> 0.1365 | R18: World Bank/UW policy target | S18: Exact cascade arithmetic is used without a rounded override. | T18: =IF(OR(G18<0,G18>1,H18<0,H18>1,I18<0,I18>1,Q18<0,Q18>1),"BAD","OK") -> OK
A19: CVG_RF_CHOL_Women_2040 | B19: RF_CHOL | C19: Cholesterol | D19: Women | E19: 70-70-70 | F19: 2040 | G19: =Assumptions!$B$6 -> 0.7 | H19: =Assumptions!$B$9 -> 0.7 | I19: =Assumptions!$B$10 -> 0.7 | J19: =G19 -> 0.7 | K19: =G19*H19 -> 0.49 | L19: =K19*I19 -> 0.343 | M19: =K19-L19 -> 0.147 | N19: =Assumptions!$B$11 -> 0.5 | O19: =L19+N19*M19 -> 0.4165 | Q19: =O19 -> 0.4165 | R19: World Bank/UW policy target | S19: Exact cascade arithmetic is used without a rounded override. | T19: =IF(OR(G19<0,G19>1,H19<0,H19>1,I19<0,I19>1,Q19<0,Q19>1),"BAD","OK") -> OK

Sheet Coverage_Trajectory
A1: trajectory_id | B1: scenario_id | C1: intervention_id | D1: intervention_name | E1: risk_factor_id | F1: sex | G1: year | H1: baseline_effective_coverage | I1: target_2030 | J1: target_2040 | K1: scenario_effective_coverage | L1: status_quo_effective_coverage | M1: annual_change | N1: phase | O1: source_note | P1: qa_status
A2: I_CVD_PRIMARY_Men_2025 | B2: S_70_30_30_TO_70_70_70 | C2: I_CVD_PRIMARY | D2: Primary prevention of CVD | E2: RF_HTN | F2: Men | G2: 2025 | H2: =Coverage!Q2 -> 0.094852977 | I2: =IF(Assumptions!$B$19=1,MAX(H2,Coverage!Q3),Coverage!Q3) -> 0.1365 | J2: =IF(Assumptions!$B$19=1,MAX(H2,Coverage!Q4),Coverage!Q4) -> 0.4165 | K2: =IF(G2<=Assumptions!$B$4,H2+(I2-H2)*(G2-Assumptions!$B$2)/(Assumptions!$B$4-Assumptions!$B$2),IF(G2<=Assumptions!$B$5,I2+(J2-I2)*(G2-Assumptions!$B$4)/(Assumptions!$B$5-Assumptions!$B$4),J2)) -> 0.094852977 | L2: =H2 -> 0.094852977 | M2: 0 | N2: Scale to 70-30-30 | O2: Piecewise linear scale-up; hold after 2040 | P2: =IF(OR(K2<0,K2>1,M2<0),"BAD","OK") -> OK
A3: I_CVD_PRIMARY_Men_2026 | B3: S_70_30_30_TO_70_70_70 | C3: I_CVD_PRIMARY | D3: Primary prevention of CVD | E3: RF_HTN | F3: Men | G3: 2026 | H3: =Coverage!Q2 -> 0.094852977 | I3: =IF(Assumptions!$B$19=1,MAX(H3,Coverage!Q3),Coverage!Q3) -> 0.1365 | J3: =IF(Assumptions!$B$19=1,MAX(H3,Coverage!Q4),Coverage!Q4) -> 0.4165 | K3: =IF(G3<=Assumptions!$B$4,H3+(I3-H3)*(G3-Assumptions!$B$2)/(Assumptions!$B$4-Assumptions!$B$2),IF(G3<=Assumptions!$B$5,I3+(J3-I3)*(G3-Assumptions!$B$4)/(Assumptions!$B$5-Assumptions!$B$4),J3)) -> 0.10318238 | L3: =H3 -> 0.094852977 | M3: =K3-K2 -> 0.0083294046 | N3: Scale to 70-30-30 | O3: Piecewise linear scale-up; hold after 2040 | P3: =IF(OR(K3<0,K3>1,M3<0),"BAD","OK") -> OK
A4: I_CVD_PRIMARY_Men_2027 | B4: S_70_30_30_TO_70_70_70 | C4: I_CVD_PRIMARY | D4: Primary prevention of CVD | E4: RF_HTN | F4: Men | G4: 2027 | H4: =Coverage!Q2 -> 0.094852977 | I4: =IF(Assumptions!$B$19=1,MAX(H4,Coverage!Q3),Coverage!Q3) -> 0.1365 | J4: =IF(Assumptions!$B$19=1,MAX(H4,Coverage!Q4),Coverage!Q4) -> 0.4165 | K4: =IF(G4<=Assumptions!$B$4,H4+(I4-H4)*(G4-Assumptions!$B$2)/(Assumptions!$B$4-Assumptions!$B$2),IF(G4<=Assumptions!$B$5,I4+(J4-I4)*(G4-Assumptions!$B$4)/(Assumptions!$B$5-Assumptions!$B$4),J4)) -> 0.11151179 | L4: =H4 -> 0.094852977 | M4: =K4-K3 -> 0.0083294046 | N4: Scale to 70-30-30 | O4: Piecewise linear scale-up; hold after 2040 | P4: =IF(OR(K4<0,K4>1,M4<0),"BAD","OK") -> OK
A5: I_CVD_PRIMARY_Men_2028 | B5: S_70_30_30_TO_70_70_70 | C5: I_CVD_PRIMARY | D5: Primary prevention of CVD | E5: RF_HTN | F5: Men | G5: 2028 | H5: =Coverage!Q2 -> 0.094852977 | I5: =IF(Assumptions!$B$19=1,MAX(H5,Coverage!Q3),Coverage!Q3) -> 0.1365 | J5: =IF(Assumptions!$B$19=1,MAX(H5,Coverage!Q4),Coverage!Q4) -> 0.4165 | K5: =IF(G5<=Assumptions!$B$4,H5+(I5-H5)*(G5-Assumptions!$B$2)/(Assumptions!$B$4-Assumptions!$B$2),IF(G5<=Assumptions!$B$5,I5+(J5-I5)*(G5-Assumptions!$B$4)/(Assumptions!$B$5-Assumptions!$B$4),J5)) -> 0.11984119 | L5: =H5 -> 0.094852977 | M5: =K5-K4 -> 0.0083294046 | N5: Scale to 70-30-30 | O5: Piecewise linear scale-up; hold after 2040 | P5: =IF(OR(K5<0,K5>1,M5<0),"BAD","OK") -> OK
A6: I_CVD_PRIMARY_Men_2029 | B6: S_70_30_30_TO_70_70_70 | C6: I_CVD_PRIMARY | D6: Primary prevention of CVD | E6: RF_HTN | F6: Men | G6: 2029 | H6: =Coverage!Q2 -> 0.094852977 | I6: =IF(Assumptions!$B$19=1,MAX(H6,Coverage!Q3),Coverage!Q3) -> 0.1365 | J6: =IF(Assumptions!$B$19=1,MAX(H6,Coverage!Q4),Coverage!Q4) -> 0.4165 | K6: =IF(G6<=Assumptions!$B$4,H6+(I6-H6)*(G6-Assumptions!$B$2)/(Assumptions!$B$4-Assumptions!$B$2),IF(G6<=Assumptions!$B$5,I6+(J6-I6)*(G6-Assumptions!$B$4)/(Assumptions!$B$5-Assumptions!$B$4),J6)) -> 0.1281706 | L6: =H6 -> 0.094852977 | M6: =K6-K5 -> 0.0083294046 | N6: Scale to 70-30-30 | O6: Piecewise linear scale-up; hold after 2040 | P6: =IF(OR(K6<0,K6>1,M6<0),"BAD","OK") -> OK
A7: I_CVD_PRIMARY_Men_2030 | B7: S_70_30_30_TO_70_70_70 | C7: I_CVD_PRIMARY | D7: Primary prevention of CVD | E7: RF_HTN | F7: Men | G7: 2030 | H7: =Coverage!Q2 -> 0.094852977 | I7: =IF(Assumptions!$B$19=1,MAX(H7,Coverage!Q3),Coverage!Q3) -> 0.1365 | J7: =IF(Assumptions!$B$19=1,MAX(H7,Coverage!Q4),Coverage!Q4) -> 0.4165 | K7: =IF(G7<=Assumptions!$B$4,H7+(I7-H7)*(G7-Assumptions!$B$2)/(Assumptions!$B$4-Assumptions!$B$2),IF(G7<=Assumptions!$B$5,I7+(J7-I7)*(G7-Assumptions!$B$4)/(Assumptions!$B$5-Assumptions!$B$4),J7)) -> 0.1365 | L7: =H7 -> 0.094852977 | M7: =K7-K6 -> 0.0083294046 | N7: Scale to 70-30-30 | O7: Piecewise linear scale-up; hold after 2040 | P7: =IF(OR(K7<0,K7>1,M7<0),"BAD","OK") -> OK
A8: I_CVD_PRIMARY_Men_2031 | B8: S_70_30_30_TO_70_70_70 | C8: I_CVD_PRIMARY | D8: Primary prevention of CVD | E8: RF_HTN | F8: Men | G8: 2031 | H8: =Coverage!Q2 -> 0.094852977 | I8: =IF(Assumptions!$B$19=1,MAX(H8,Coverage!Q3),Coverage!Q3) -> 0.1365 | J8: =IF(Assumptions!$B$19=1,MAX(H8,Coverage!Q4),Coverage!Q4) -> 0.4165 | K8: =IF(G8<=Assumptions!$B$4,H8+(I8-H8)*(G8-Assumptions!$B$2)/(Assumptions!$B$4-Assumptions!$B$2),IF(G8<=Assumptions!$B$5,I8+(J8-I8)*(G8-Assumptions!$B$4)/(Assumptions!$B$5-Assumptions!$B$4),J8)) -> 0.1645 | L8: =H8 -> 0.094852977 | M8: =K8-K7 -> 0.028 | N8: Scale to 70-70-70 | O8: Piecewise linear scale-up; hold after 2040 | P8: =IF(OR(K8<0,K8>1,M8<0),"BAD","OK") -> OK
A9: I_CVD_PRIMARY_Men_2032 | B9: S_70_30_30_TO_70_70_70 | C9: I_CVD_PRIMARY | D9: Primary prevention of CVD | E9: RF_HTN | F9: Men | G9: 2032 | H9: =Coverage!Q2 -> 0.094852977 | I9: =IF(Assumptions!$B$19=1,MAX(H9,Coverage!Q3),Coverage!Q3) -> 0.1365 | J9: =IF(Assumptions!$B$19=1,MAX(H9,Coverage!Q4),Coverage!Q4) -> 0.4165 | K9: =IF(G9<=Assumptions!$B$4,H9+(I9-H9)*(G9-Assumptions!$B$2)/(Assumptions!$B$4-Assumptions!$B$2),IF(G9<=Assumptions!$B$5,I9+(J9-I9)*(G9-Assumptions!$B$4)/(Assumptions!$B$5-Assumptions!$B$4),J9)) -> 0.1925 | L9: =H9 -> 0.094852977 | M9: =K9-K8 -> 0.028 | N9: Scale to 70-70-70 | O9: Piecewise linear scale-up; hold after 2040 | P9: =IF(OR(K9<0,K9>1,M9<0),"BAD","OK") -> OK
A10: I_CVD_PRIMARY_Men_2033 | B10: S_70_30_30_TO_70_70_70 | C10: I_CVD_PRIMARY | D10: Primary prevention of CVD | E10: RF_HTN | F10: Men | G10: 2033 | H10: =Coverage!Q2 -> 0.094852977 | I10: =IF(Assumptions!$B$19=1,MAX(H10,Coverage!Q3),Coverage!Q3) -> 0.1365 | J10: =IF(Assumptions!$B$19=1,MAX(H10,Coverage!Q4),Coverage!Q4) -> 0.4165 | K10: =IF(G10<=Assumptions!$B$4,H10+(I10-H10)*(G10-Assumptions!$B$2)/(Assumptions!$B$4-Assumptions!$B$2),IF(G10<=Assumptions!$B$5,I10+(J10-I10)*(G10-Assumptions!$B$4)/(Assumptions!$B$5-Assumptions!$B$4),J10)) -> 0.2205 | L10: =H10 -> 0.094852977 | M10: =K10-K9 -> 0.028 | N10: Scale to 70-70-70 | O10: Piecewise linear scale-up; hold after 2040 | P10: =IF(OR(K10<0,K10>1,M10<0),"BAD","OK") -> OK
A11: I_CVD_PRIMARY_Men_2034 | B11: S_70_30_30_TO_70_70_70 | C11: I_CVD_PRIMARY | D11: Primary prevention of CVD | E11: RF_HTN | F11: Men | G11: 2034 | H11: =Coverage!Q2 -> 0.094852977 | I11: =IF(Assumptions!$B$19=1,MAX(H11,Coverage!Q3),Coverage!Q3) -> 0.1365 | J11: =IF(Assumptions!$B$19=1,MAX(H11,Coverage!Q4),Coverage!Q4) -> 0.4165 | K11: =IF(G11<=Assumptions!$B$4,H11+(I11-H11)*(G11-Assumptions!$B$2)/(Assumptions!$B$4-Assumptions!$B$2),IF(G11<=Assumptions!$B$5,I11+(J11-I11)*(G11-Assumptions!$B$4)/(Assumptions!$B$5-Assumptions!$B$4),J11)) -> 0.2485 | L11: =H11 -> 0.094852977 | M11: =K11-K10 -> 0.028 | N11: Scale to 70-70-70 | O11: Piecewise linear scale-up; hold after 2040 | P11: =IF(OR(K11<0,K11>1,M11<0),"BAD","OK") -> OK
A12: I_CVD_PRIMARY_Men_2035 | B12: S_70_30_30_TO_70_70_70 | C12: I_CVD_PRIMARY | D12: Primary prevention of CVD | E12: RF_HTN | F12: Men | G12: 2035 | H12: =Coverage!Q2 -> 0.094852977 | I12: =IF(Assumptions!$B$19=1,MAX(H12,Coverage!Q3),Coverage!Q3) -> 0.1365 | J12: =IF(Assumptions!$B$19=1,MAX(H12,Coverage!Q4),Coverage!Q4) -> 0.4165 | K12: =IF(G12<=Assumptions!$B$4,H12+(I12-H12)*(G12-Assumptions!$B$2)/(Assumptions!$B$4-Assumptions!$B$2),IF(G12<=Assumptions!$B$5,I12+(J12-I12)*(G12-Assumptions!$B$4)/(Assumptions!$B$5-Assumptions!$B$4),J12)) -> 0.2765 | L12: =H12 -> 0.094852977 | M12: =K12-K11 -> 0.028 | N12: Scale to 70-70-70 | O12: Piecewise linear scale-up; hold after 2040 | P12: =IF(OR(K12<0,K12>1,M12<0),"BAD","OK") -> OK
A13: I_CVD_PRIMARY_Men_2036 | B13: S_70_30_30_TO_70_70_70 | C13: I_CVD_PRIMARY | D13: Primary prevention of CVD | E13: RF_HTN | F13: Men | G13: 2036 | H13: =Coverage!Q2 -> 0.094852977 | I13: =IF(Assumptions!$B$19=1,MAX(H13,Coverage!Q3),Coverage!Q3) -> 0.1365 | J13: =IF(Assumptions!$B$19=1,MAX(H13,Coverage!Q4),Coverage!Q4) -> 0.4165 | K13: =IF(G13<=Assumptions!$B$4,H13+(I13-H13)*(G13-Assumptions!$B$2)/(Assumptions!$B$4-Assumptions!$B$2),IF(G13<=Assumptions!$B$5,I13+(J13-I13)*(G13-Assumptions!$B$4)/(Assumptions!$B$5-Assumptions!$B$4),J13)) -> 0.3045 | L13: =H13 -> 0.094852977 | M13: =K13-K12 -> 0.028 | N13: Scale to 70-70-70 | O13: Piecewise linear scale-up; hold after 2040 | P13: =IF(OR(K13<0,K13>1,M13<0),"BAD","OK") -> OK
A14: I_CVD_PRIMARY_Men_2037 | B14: S_70_30_30_TO_70_70_70 | C14: I_CVD_PRIMARY | D14: Primary prevention of CVD | E14: RF_HTN | F14: Men | G14: 2037 | H14: =Coverage!Q2 -> 0.094852977 | I14: =IF(Assumptions!$B$19=1,MAX(H14,Coverage!Q3),Coverage!Q3) -> 0.1365 | J14: =IF(Assumptions!$B$19=1,MAX(H14,Coverage!Q4),Coverage!Q4) -> 0.4165 | K14: =IF(G14<=Assumptions!$B$4,H14+(I14-H14)*(G14-Assumptions!$B$2)/(Assumptions!$B$4-Assumptions!$B$2),IF(G14<=Assumptions!$B$5,I14+(J14-I14)*(G14-Assumptions!$B$4)/(Assumptions!$B$5-Assumptions!$B$4),J14)) -> 0.3325 | L14: =H14 -> 0.094852977 | M14: =K14-K13 -> 0.028 | N14: Scale to 70-70-70 | O14: Piecewise linear scale-up; hold after 2040 | P14: =IF(OR(K14<0,K14>1,M14<0),"BAD","OK") -> OK
A15: I_CVD_PRIMARY_Men_2038 | B15: S_70_30_30_TO_70_70_70 | C15: I_CVD_PRIMARY | D15: Primary prevention of CVD | E15: RF_HTN | F15: Men | G15: 2038 | H15: =Coverage!Q2 -> 0.094852977 | I15: =IF(Assumptions!$B$19=1,MAX(H15,Coverage!Q3),Coverage!Q3) -> 0.1365 | J15: =IF(Assumptions!$B$19=1,MAX(H15,Coverage!Q4),Coverage!Q4) -> 0.4165 | K15: =IF(G15<=Assumptions!$B$4,H15+(I15-H15)*(G15-Assumptions!$B$2)/(Assumptions!$B$4-Assumptions!$B$2),IF(G15<=Assumptions!$B$5,I15+(J15-I15)*(G15-Assumptions!$B$4)/(Assumptions!$B$5-Assumptions!$B$4),J15)) -> 0.3605 | L15: =H15 -> 0.094852977 | M15: =K15-K14 -> 0.028 | N15: Scale to 70-70-70 | O15: Piecewise linear scale-up; hold after 2040 | P15: =IF(OR(K15<0,K15>1,M15<0),"BAD","OK") -> OK
A16: I_CVD_PRIMARY_Men_2039 | B16: S_70_30_30_TO_70_70_70 | C16: I_CVD_PRIMARY | D16: Primary prevention of CVD | E16: RF_HTN | F16: Men | G16: 2039 | H16: =Coverage!Q2 -> 0.094852977 | I16: =IF(Assumptions!$B$19=1,MAX(H16,Coverage!Q3),Coverage!Q3) -> 0.1365 | J16: =IF(Assumptions!$B$19=1,MAX(H16,Coverage!Q4),Coverage!Q4) -> 0.4165 | K16: =IF(G16<=Assumptions!$B$4,H16+(I16-H16)*(G16-Assumptions!$B$2)/(Assumptions!$B$4-Assumptions!$B$2),IF(G16<=Assumptions!$B$5,I16+(J16-I16)*(G16-Assumptions!$B$4)/(Assumptions!$B$5-Assumptions!$B$4),J16)) -> 0.3885 | L16: =H16 -> 0.094852977 | M16: =K16-K15 -> 0.028 | N16: Scale to 70-70-70 | O16: Piecewise linear scale-up; hold after 2040 | P16: =IF(OR(K16<0,K16>1,M16<0),"BAD","OK") -> OK
A17: I_CVD_PRIMARY_Men_2040 | B17: S_70_30_30_TO_70_70_70 | C17: I_CVD_PRIMARY | D17: Primary prevention of CVD | E17: RF_HTN | F17: Men | G17: 2040 | H17: =Coverage!Q2 -> 0.094852977 | I17: =IF(Assumptions!$B$19=1,MAX(H17,Coverage!Q3),Coverage!Q3) -> 0.1365 | J17: =IF(Assumptions!$B$19=1,MAX(H17,Coverage!Q4),Coverage!Q4) -> 0.4165 | K17: =IF(G17<=Assumptions!$B$4,H17+(I17-H17)*(G17-Assumptions!$B$2)/(Assumptions!$B$4-Assumptions!$B$2),IF(G17<=Assumptions!$B$5,I17+(J17-I17)*(G17-Assumptions!$B$4)/(Assumptions!$B$5-Assumptions!$B$4),J17)) -> 0.4165 | L17: =H17 -> 0.094852977 | M17: =K17-K16 -> 0.028 | N17: Scale to 70-70-70 | O17: Piecewise linear scale-up; hold after 2040 | P17: =IF(OR(K17<0,K17>1,M17<0),"BAD","OK") -> OK
A18: I_CVD_PRIMARY_Men_2041 | B18: S_70_30_30_TO_70_70_70 | C18: I_CVD_PRIMARY | D18: Primary prevention of CVD | E18: RF_HTN | F18: Men | G18: 2041 | H18: =Coverage!Q2 -> 0.094852977 | I18: =IF(Assumptions!$B$19=1,MAX(H18,Coverage!Q3),Coverage!Q3) -> 0.1365 | J18: =IF(Assumptions!$B$19=1,MAX(H18,Coverage!Q4),Coverage!Q4) -> 0.4165 | K18: =IF(G18<=Assumptions!$B$4,H18+(I18-H18)*(G18-Assumptions!$B$2)/(Assumptions!$B$4-Assumptions!$B$2),IF(G18<=Assumptions!$B$5,I18+(J18-I18)*(G18-Assumptions!$B$4)/(Assumptions!$B$5-Assumptions!$B$4),J18)) -> 0.4165 | L18: =H18 -> 0.094852977 | M18: =K18-K17 -> 0 | N18: Maintain 70-70-70 | O18: Piecewise linear scale-up; hold after 2040 | P18: =IF(OR(K18<0,K18>1,M18<0),"BAD","OK") -> OK
A19: I_CVD_PRIMARY_Men_2042 | B19: S_70_30_30_TO_70_70_70 | C19: I_CVD_PRIMARY | D19: Primary prevention of CVD | E19: RF_HTN | F19: Men | G19: 2042 | H19: =Coverage!Q2 -> 0.094852977 | I19: =IF(Assumptions!$B$19=1,MAX(H19,Coverage!Q3),Coverage!Q3) -> 0.1365 | J19: =IF(Assumptions!$B$19=1,MAX(H19,Coverage!Q4),Coverage!Q4) -> 0.4165 | K19: =IF(G19<=Assumptions!$B$4,H19+(I19-H19)*(G19-Assumptions!$B$2)/(Assumptions!$B$4-Assumptions!$B$2),IF(G19<=Assumptions!$B$5,I19+(J19-I19)*(G19-Assumptions!$B$4)/(Assumptions!$B$5-Assumptions!$B$4),J19)) -> 0.4165 | L19: =H19 -> 0.094852977 | M19: =K19-K18 -> 0 | N19: Maintain 70-70-70 | O19: Piecewise linear scale-up; hold after 2040 | P19: =IF(OR(K19<0,K19>1,M19<0),"BAD","OK") -> OK
A20: I_CVD_PRIMARY_Men_2043 | B20: S_70_30_30_TO_70_70_70 | C20: I_CVD_PRIMARY | D20: Primary prevention of CVD | E20: RF_HTN | F20: Men | G20: 2043 | H20: =Coverage!Q2 -> 0.094852977 | I20: =IF(Assumptions!$B$19=1,MAX(H20,Coverage!Q3),Coverage!Q3) -> 0.1365 | J20: =IF(Assumptions!$B$19=1,MAX(H20,Coverage!Q4),Coverage!Q4) -> 0.4165 | K20: =IF(G20<=Assumptions!$B$4,H20+(I20-H20)*(G20-Assumptions!$B$2)/(Assumptions!$B$4-Assumptions!$B$2),IF(G20<=Assumptions!$B$5,I20+(J20-I20)*(G20-Assumptions!$B$4)/(Assumptions!$B$5-Assumptions!$B$4),J20)) -> 0.4165 | L20: =H20 -> 0.094852977 | M20: =K20-K19 -> 0 | N20: Maintain 70-70-70 | O20: Piecewise linear scale-up; hold after 2040 | P20: =IF(OR(K20<0,K20>1,M20<0),"BAD","OK") -> OK
A21: I_CVD_PRIMARY_Men_2044 | B21: S_70_30_30_TO_70_70_70 | C21: I_CVD_PRIMARY | D21: Primary prevention of CVD | E21: RF_HTN | F21: Men | G21: 2044 | H21: =Coverage!Q2 -> 0.094852977 | I21: =IF(Assumptions!$B$19=1,MAX(H21,Coverage!Q3),Coverage!Q3) -> 0.1365 | J21: =IF(Assumptions!$B$19=1,MAX(H21,Coverage!Q4),Coverage!Q4) -> 0.4165 | K21: =IF(G21<=Assumptions!$B$4,H21+(I21-H21)*(G21-Assumptions!$B$2)/(Assumptions!$B$4-Assumptions!$B$2),IF(G21<=Assumptions!$B$5,I21+(J21-I21)*(G21-Assumptions!$B$4)/(Assumptions!$B$5-Assumptions!$B$4),J21)) -> 0.4165 | L21: =H21 -> 0.094852977 | M21: =K21-K20 -> 0 | N21: Maintain 70-70-70 | O21: Piecewise linear scale-up; hold after 2040 | P21: =IF(OR(K21<0,K21>1,M21<0),"BAD","OK") -> OK
A22: I_CVD_PRIMARY_Men_2045 | B22: S_70_30_30_TO_70_70_70 | C22: I_CVD_PRIMARY | D22: Primary prevention of CVD | E22: RF_HTN | F22: Men | G22: 2045 | H22: =Coverage!Q2 -> 0.094852977 | I22: =IF(Assumptions!$B$19=1,MAX(H22,Coverage!Q3),Coverage!Q3) -> 0.1365 | J22: =IF(Assumptions!$B$19=1,MAX(H22,Coverage!Q4),Coverage!Q4) -> 0.4165 | K22: =IF(G22<=Assumptions!$B$4,H22+(I22-H22)*(G22-Assumptions!$B$2)/(Assumptions!$B$4-Assumptions!$B$2),IF(G22<=Assumptions!$B$5,I22+(J22-I22)*(G22-Assumptions!$B$4)/(Assumptions!$B$5-Assumptions!$B$4),J22)) -> 0.4165 | L22: =H22 -> 0.094852977 | M22: =K22-K21 -> 0 | N22: Maintain 70-70-70 | O22: Piecewise linear scale-up; hold after 2040 | P22: =IF(OR(K22<0,K22>1,M22<0),"BAD","OK") -> OK
A23: I_CVD_PRIMARY_Men_2046 | B23: S_70_30_30_TO_70_70_70 | C23: I_CVD_PRIMARY | D23: Primary prevention of CVD | E23: RF_HTN | F23: Men | G23: 2046 | H23: =Coverage!Q2 -> 0.094852977 | I23: =IF(Assumptions!$B$19=1,MAX(H23,Coverage!Q3),Coverage!Q3) -> 0.1365 | J23: =IF(Assumptions!$B$19=1,MAX(H23,Coverage!Q4),Coverage!Q4) -> 0.4165 | K23: =IF(G23<=Assumptions!$B$4,H23+(I23-H23)*(G23-Assumptions!$B$2)/(Assumptions!$B$4-Assumptions!$B$2),IF(G23<=Assumptions!$B$5,I23+(J23-I23)*(G23-Assumptions!$B$4)/(Assumptions!$B$5-Assumptions!$B$4),J23)) -> 0.4165 | L23: =H23 -> 0.094852977 | M23: =K23-K22 -> 0 | N23: Maintain 70-70-70 | O23: Piecewise linear scale-up; hold after 2040 | P23: =IF(OR(K23<0,K23>1,M23<0),"BAD","OK") -> OK
A24: I_CVD_PRIMARY_Men_2047 | B24: S_70_30_30_TO_70_70_70 | C24: I_CVD_PRIMARY | D24: Primary prevention of CVD | E24: RF_HTN | F24: Men | G24: 2047 | H24: =Coverage!Q2 -> 0.094852977 | I24: =IF(Assumptions!$B$19=1,MAX(H24,Coverage!Q3),Coverage!Q3) -> 0.1365 | J24: =IF(Assumptions!$B$19=1,MAX(H24,Coverage!Q4),Coverage!Q4) -> 0.4165 | K24: =IF(G24<=Assumptions!$B$4,H24+(I24-H24)*(G24-Assumptions!$B$2)/(Assumptions!$B$4-Assumptions!$B$2),IF(G24<=Assumptions!$B$5,I24+(J24-I24)*(G24-Assumptions!$B$4)/(Assumptions!$B$5-Assumptions!$B$4),J24)) -> 0.4165 | L24: =H24 -> 0.094852977 | M24: =K24-K23 -> 0 | N24: Maintain 70-70-70 | O24: Piecewise linear scale-up; hold after 2040 | P24: =IF(OR(K24<0,K24>1,M24<0),"BAD","OK") -> OK
A25: I_CVD_PRIMARY_Men_2048 | B25: S_70_30_30_TO_70_70_70 | C25: I_CVD_PRIMARY | D25: Primary prevention of CVD | E25: RF_HTN | F25: Men | G25: 2048 | H25: =Coverage!Q2 -> 0.094852977 | I25: =IF(Assumptions!$B$19=1,MAX(H25,Coverage!Q3),Coverage!Q3) -> 0.1365 | J25: =IF(Assumptions!$B$19=1,MAX(H25,Coverage!Q4),Coverage!Q4) -> 0.4165 | K25: =IF(G25<=Assumptions!$B$4,H25+(I25-H25)*(G25-Assumptions!$B$2)/(Assumptions!$B$4-Assumptions!$B$2),IF(G25<=Assumptions!$B$5,I25+(J25-I25)*(G25-Assumptions!$B$4)/(Assumptions!$B$5-Assumptions!$B$4),J25)) -> 0.4165 | L25: =H25 -> 0.094852977 | M25: =K25-K24 -> 0 | N25: Maintain 70-70-70 | O25: Piecewise linear scale-up; hold after 2040 | P25: =IF(OR(K25<0,K25>1,M25<0),"BAD","OK") -> OK
A26: I_CVD_PRIMARY_Men_2049 | B26: S_70_30_30_TO_70_70_70 | C26: I_CVD_PRIMARY | D26: Primary prevention of CVD | E26: RF_HTN | F26: Men | G26: 2049 | H26: =Coverage!Q2 -> 0.094852977 | I26: =IF(Assumptions!$B$19=1,MAX(H26,Coverage!Q3),Coverage!Q3) -> 0.1365 | J26: =IF(Assumptions!$B$19=1,MAX(H26,Coverage!Q4),Coverage!Q4) -> 0.4165 | K26: =IF(G26<=Assumptions!$B$4,H26+(I26-H26)*(G26-Assumptions!$B$2)/(Assumptions!$B$4-Assumptions!$B$2),IF(G26<=Assumptions!$B$5,I26+(J26-I26)*(G26-Assumptions!$B$4)/(Assumptions!$B$5-Assumptions!$B$4),J26)) -> 0.4165 | L26: =H26 -> 0.094852977 | M26: =K26-K25 -> 0 | N26: Maintain 70-70-70 | O26: Piecewise linear scale-up; hold after 2040 | P26: =IF(OR(K26<0,K26>1,M26<0),"BAD","OK") -> OK
A27: I_CVD_PRIMARY_Men_2050 | B27: S_70_30_30_TO_70_70_70 | C27: I_CVD_PRIMARY | D27: Primary prevention of CVD | E27: RF_HTN | F27: Men | G27: 2050 | H27: =Coverage!Q2 -> 0.094852977 | I27: =IF(Assumptions!$B$19=1,MAX(H27,Coverage!Q3),Coverage!Q3) -> 0.1365 | J27: =IF(Assumptions!$B$19=1,MAX(H27,Coverage!Q4),Coverage!Q4) -> 0.4165 | K27: =IF(G27<=Assumptions!$B$4,H27+(I27-H27)*(G27-Assumptions!$B$2)/(Assumptions!$B$4-Assumptions!$B$2),IF(G27<=Assumptions!$B$5,I27+(J27-I27)*(G27-Assumptions!$B$4)/(Assumptions!$B$5-Assumptions!$B$4),J27)) -> 0.4165 | L27: =H27 -> 0.094852977 | M27: =K27-K26 -> 0 | N27: Maintain 70-70-70 | O27: Piecewise linear scale-up; hold after 2040 | P27: =IF(OR(K27<0,K27>1,M27<0),"BAD","OK") -> OK
A28: I_CVD_PRIMARY_Women_2025 | B28: S_70_30_30_TO_70_70_70 | C28: I_CVD_PRIMARY | D28: Primary prevention of CVD | E28: RF_HTN | F28: Women | G28: 2025 | H28: =Coverage!Q5 -> 0.13268074 | I28: =IF(Assumptions!$B$19=1,MAX(H28,Coverage!Q6),Coverage!Q6) -> 0.1365 | J28: =IF(Assumptions!$B$19=1,MAX(H28,Coverage!Q7),Coverage!Q7) -> 0.4165 | K28: =IF(G28<=Assumptions!$B$4,H28+(I28-H28)*(G28-Assumptions!$B$2)/(Assumptions!$B$4-Assumptions!$B$2),IF(G28<=Assumptions!$B$5,I28+(J28-I28)*(G28-Assumptions!$B$4)/(Assumptions!$B$5-Assumptions!$B$4),J28)) -> 0.13268074 | L28: =H28 -> 0.13268074 | M28: 0 | N28: Scale to 70-30-30 | O28: Piecewise linear scale-up; hold after 2040 | P28: =IF(OR(K28<0,K28>1,M28<0),"BAD","OK") -> OK
A29: I_CVD_PRIMARY_Women_2026 | B29: S_70_30_30_TO_70_70_70 | C29: I_CVD_PRIMARY | D29: Primary prevention of CVD | E29: RF_HTN | F29: Women | G29: 2026 | H29: =Coverage!Q5 -> 0.13268074 | I29: =IF(Assumptions!$B$19=1,MAX(H29,Coverage!Q6),Coverage!Q6) -> 0.1365 | J29: =IF(Assumptions!$B$19=1,MAX(H29,Coverage!Q7),Coverage!Q7) -> 0.4165 | K29: =IF(G29<=Assumptions!$B$4,H29+(I29-H29)*(G29-Assumptions!$B$2)/(Assumptions!$B$4-Assumptions!$B$2),IF(G29<=Assumptions!$B$5,I29+(J29-I29)*(G29-Assumptions!$B$4)/(Assumptions!$B$5-Assumptions!$B$4),J29)) -> 0.13344459 | L29: =H29 -> 0.13268074 | M29: =K29-K28 -> 0.00076385241 | N29: Scale to 70-30-30 | O29: Piecewise linear scale-up; hold after 2040 | P29: =IF(OR(K29<0,K29>1,M29<0),"BAD","OK") -> OK
A30: I_CVD_PRIMARY_Women_2027 | B30: S_70_30_30_TO_70_70_70 | C30: I_CVD_PRIMARY | D30: Primary prevention of CVD | E30: RF_HTN | F30: Women | G30: 2027 | H30: =Coverage!Q5 -> 0.13268074 | I30: =IF(Assumptions!$B$19=1,MAX(H30,Coverage!Q6),Coverage!Q6) -> 0.1365 | J30: =IF(Assumptions!$B$19=1,MAX(H30,Coverage!Q7),Coverage!Q7) -> 0.4165 | K30: =IF(G30<=Assumptions!$B$4,H30+(I30-H30)*(G30-Assumptions!$B$2)/(Assumptions!$B$4-Assumptions!$B$2),IF(G30<=Assumptions!$B$5,I30+(J30-I30)*(G30-Assumptions!$B$4)/(Assumptions!$B$5-Assumptions!$B$4),J30)) -> 0.13420844 | L30: =H30 -> 0.13268074 | M30: =K30-K29 -> 0.00076385241 | N30: Scale to 70-30-30 | O30: Piecewise linear scale-up; hold after 2040 | P30: =IF(OR(K30<0,K30>1,M30<0),"BAD","OK") -> OK
A31: I_CVD_PRIMARY_Women_2028 | B31: S_70_30_30_TO_70_70_70 | C31: I_CVD_PRIMARY | D31: Primary prevention of CVD | E31: RF_HTN | F31: Women | G31: 2028 | H31: =Coverage!Q5 -> 0.13268074 | I31: =IF(Assumptions!$B$19=1,MAX(H31,Coverage!Q6),Coverage!Q6) -> 0.1365 | J31: =IF(Assumptions!$B$19=1,MAX(H31,Coverage!Q7),Coverage!Q7) -> 0.4165 | K31: =IF(G31<=Assumptions!$B$4,H31+(I31-H31)*(G31-Assumptions!$B$2)/(Assumptions!$B$4-Assumptions!$B$2),IF(G31<=Assumptions!$B$5,I31+(J31-I31)*(G31-Assumptions!$B$4)/(Assumptions!$B$5-Assumptions!$B$4),J31)) -> 0.1349723 | L31: =H31 -> 0.13268074 | M31: =K31-K30 -> 0.00076385241 | N31: Scale to 70-30-30 | O31: Piecewise linear scale-up; hold after 2040 | P31: =IF(OR(K31<0,K31>1,M31<0),"BAD","OK") -> OK
A32: I_CVD_PRIMARY_Women_2029 | B32: S_70_30_30_TO_70_70_70 | C32: I_CVD_PRIMARY | D32: Primary prevention of CVD | E32: RF_HTN | F32: Women | G32: 2029 | H32: =Coverage!Q5 -> 0.13268074 | I32: =IF(Assumptions!$B$19=1,MAX(H32,Coverage!Q6),Coverage!Q6) -> 0.1365 | J32: =IF(Assumptions!$B$19=1,MAX(H32,Coverage!Q7),Coverage!Q7) -> 0.4165 | K32: =IF(G32<=Assumptions!$B$4,H32+(I32-H32)*(G32-Assumptions!$B$2)/(Assumptions!$B$4-Assumptions!$B$2),IF(G32<=Assumptions!$B$5,I32+(J32-I32)*(G32-Assumptions!$B$4)/(Assumptions!$B$5-Assumptions!$B$4),J32)) -> 0.13573615 | L32: =H32 -> 0.13268074 | M32: =K32-K31 -> 0.00076385241 | N32: Scale to 70-30-30 | O32: Piecewise linear scale-up; hold after 2040 | P32: =IF(OR(K32<0,K32>1,M32<0),"BAD","OK") -> OK
A33: I_CVD_PRIMARY_Women_2030 | B33: S_70_30_30_TO_70_70_70 | C33: I_CVD_PRIMARY | D33: Primary prevention of CVD | E33: RF_HTN | F33: Women | G33: 2030 | H33: =Coverage!Q5 -> 0.13268074 | I33: =IF(Assumptions!$B$19=1,MAX(H33,Coverage!Q6),Coverage!Q6) -> 0.1365 | J33: =IF(Assumptions!$B$19=1,MAX(H33,Coverage!Q7),Coverage!Q7) -> 0.4165 | K33: =IF(G33<=Assumptions!$B$4,H33+(I33-H33)*(G33-Assumptions!$B$2)/(Assumptions!$B$4-Assumptions!$B$2),IF(G33<=Assumptions!$B$5,I33+(J33-I33)*(G33-Assumptions!$B$4)/(Assumptions!$B$5-Assumptions!$B$4),J33)) -> 0.1365 | L33: =H33 -> 0.13268074 | M33: =K33-K32 -> 0.00076385241 | N33: Scale to 70-30-30 | O33: Piecewise linear scale-up; hold after 2040 | P33: =IF(OR(K33<0,K33>1,M33<0),"BAD","OK") -> OK
A34: I_CVD_PRIMARY_Women_2031 | B34: S_70_30_30_TO_70_70_70 | C34: I_CVD_PRIMARY | D34: Primary prevention of CVD | E34: RF_HTN | F34: Women | G34: 2031 | H34: =Coverage!Q5 -> 0.13268074 | I34: =IF(Assumptions!$B$19=1,MAX(H34,Coverage!Q6),Coverage!Q6) -> 0.1365 | J34: =IF(Assumptions!$B$19=1,MAX(H34,Coverage!Q7),Coverage!Q7) -> 0.4165 | K34: =IF(G34<=Assumptions!$B$4,H34+(I34-H34)*(G34-Assumptions!$B$2)/(Assumptions!$B$4-Assumptions!$B$2),IF(G34<=Assumptions!$B$5,I34+(J34-I34)*(G34-Assumptions!$B$4)/(Assumptions!$B$5-Assumptions!$B$4),J34)) -> 0.1645 | L34: =H34 -> 0.13268074 | M34: =K34-K33 -> 0.028 | N34: Scale to 70-70-70 | O34: Piecewise linear scale-up; hold after 2040 | P34: =IF(OR(K34<0,K34>1,M34<0),"BAD","OK") -> OK
A35: I_CVD_PRIMARY_Women_2032 | B35: S_70_30_30_TO_70_70_70 | C35: I_CVD_PRIMARY | D35: Primary prevention of CVD | E35: RF_HTN | F35: Women | G35: 2032 | H35: =Coverage!Q5 -> 0.13268074 | I35: =IF(Assumptions!$B$19=1,MAX(H35,Coverage!Q6),Coverage!Q6) -> 0.1365 | J35: =IF(Assumptions!$B$19=1,MAX(H35,Coverage!Q7),Coverage!Q7) -> 0.4165 | K35: =IF(G35<=Assumptions!$B$4,H35+(I35-H35)*(G35-Assumptions!$B$2)/(Assumptions!$B$4-Assumptions!$B$2),IF(G35<=Assumptions!$B$5,I35+(J35-I35)*(G35-Assumptions!$B$4)/(Assumptions!$B$5-Assumptions!$B$4),J35)) -> 0.1925 | L35: =H35 -> 0.13268074 | M35: =K35-K34 -> 0.028 | N35: Scale to 70-70-70 | O35: Piecewise linear scale-up; hold after 2040 | P35: =IF(OR(K35<0,K35>1,M35<0),"BAD","OK") -> OK
A36: I_CVD_PRIMARY_Women_2033 | B36: S_70_30_30_TO_70_70_70 | C36: I_CVD_PRIMARY | D36: Primary prevention of CVD | E36: RF_HTN | F36: Women | G36: 2033 | H36: =Coverage!Q5 -> 0.13268074 | I36: =IF(Assumptions!$B$19=1,MAX(H36,Coverage!Q6),Coverage!Q6) -> 0.1365 | J36: =IF(Assumptions!$B$19=1,MAX(H36,Coverage!Q7),Coverage!Q7) -> 0.4165 | K36: =IF(G36<=Assumptions!$B$4,H36+(I36-H36)*(G36-Assumptions!$B$2)/(Assumptions!$B$4-Assumptions!$B$2),IF(G36<=Assumptions!$B$5,I36+(J36-I36)*(G36-Assumptions!$B$4)/(Assumptions!$B$5-Assumptions!$B$4),J36)) -> 0.2205 | L36: =H36 -> 0.13268074 | M36: =K36-K35 -> 0.028 | N36: Scale to 70-70-70 | O36: Piecewise linear scale-up; hold after 2040 | P36: =IF(OR(K36<0,K36>1,M36<0),"BAD","OK") -> OK
A37: I_CVD_PRIMARY_Women_2034 | B37: S_70_30_30_TO_70_70_70 | C37: I_CVD_PRIMARY | D37: Primary prevention of CVD | E37: RF_HTN | F37: Women | G37: 2034 | H37: =Coverage!Q5 -> 0.13268074 | I37: =IF(Assumptions!$B$19=1,MAX(H37,Coverage!Q6),Coverage!Q6) -> 0.1365 | J37: =IF(Assumptions!$B$19=1,MAX(H37,Coverage!Q7),Coverage!Q7) -> 0.4165 | K37: =IF(G37<=Assumptions!$B$4,H37+(I37-H37)*(G37-Assumptions!$B$2)/(Assumptions!$B$4-Assumptions!$B$2),IF(G37<=Assumptions!$B$5,I37+(J37-I37)*(G37-Assumptions!$B$4)/(Assumptions!$B$5-Assumptions!$B$4),J37)) -> 0.2485 | L37: =H37 -> 0.13268074 | M37: =K37-K36 -> 0.028 | N37: Scale to 70-70-70 | O37: Piecewise linear scale-up; hold after 2040 | P37: =IF(OR(K37<0,K37>1,M37<0),"BAD","OK") -> OK
A38: I_CVD_PRIMARY_Women_2035 | B38: S_70_30_30_TO_70_70_70 | C38: I_CVD_PRIMARY | D38: Primary prevention of CVD | E38: RF_HTN | F38: Women | G38: 2035 | H38: =Coverage!Q5 -> 0.13268074 | I38: =IF(Assumptions!$B$19=1,MAX(H38,Coverage!Q6),Coverage!Q6) -> 0.1365 | J38: =IF(Assumptions!$B$19=1,MAX(H38,Coverage!Q7),Coverage!Q7) -> 0.4165 | K38: =IF(G38<=Assumptions!$B$4,H38+(I38-H38)*(G38-Assumptions!$B$2)/(Assumptions!$B$4-Assumptions!$B$2),IF(G38<=Assumptions!$B$5,I38+(J38-I38)*(G38-Assumptions!$B$4)/(Assumptions!$B$5-Assumptions!$B$4),J38)) -> 0.2765 | L38: =H38 -> 0.13268074 | M38: =K38-K37 -> 0.028 | N38: Scale to 70-70-70 | O38: Piecewise linear scale-up; hold after 2040 | P38: =IF(OR(K38<0,K38>1,M38<0),"BAD","OK") -> OK
A39: I_CVD_PRIMARY_Women_2036 | B39: S_70_30_30_TO_70_70_70 | C39: I_CVD_PRIMARY | D39: Primary prevention of CVD | E39: RF_HTN | F39: Women | G39: 2036 | H39: =Coverage!Q5 -> 0.13268074 | I39: =IF(Assumptions!$B$19=1,MAX(H39,Coverage!Q6),Coverage!Q6) -> 0.1365 | J39: =IF(Assumptions!$B$19=1,MAX(H39,Coverage!Q7),Coverage!Q7) -> 0.4165 | K39: =IF(G39<=Assumptions!$B$4,H39+(I39-H39)*(G39-Assumptions!$B$2)/(Assumptions!$B$4-Assumptions!$B$2),IF(G39<=Assumptions!$B$5,I39+(J39-I39)*(G39-Assumptions!$B$4)/(Assumptions!$B$5-Assumptions!$B$4),J39)) -> 0.3045 | L39: =H39 -> 0.13268074 | M39: =K39-K38 -> 0.028 | N39: Scale to 70-70-70 | O39: Piecewise linear scale-up; hold after 2040 | P39: =IF(OR(K39<0,K39>1,M39<0),"BAD","OK") -> OK
A40: I_CVD_PRIMARY_Women_2037 | B40: S_70_30_30_TO_70_70_70 | C40: I_CVD_PRIMARY | D40: Primary prevention of CVD | E40: RF_HTN | F40: Women | G40: 2037 | H40: =Coverage!Q5 -> 0.13268074 | I40: =IF(Assumptions!$B$19=1,MAX(H40,Coverage!Q6),Coverage!Q6) -> 0.1365 | J40: =IF(Assumptions!$B$19=1,MAX(H40,Coverage!Q7),Coverage!Q7) -> 0.4165 | K40: =IF(G40<=Assumptions!$B$4,H40+(I40-H40)*(G40-Assumptions!$B$2)/(Assumptions!$B$4-Assumptions!$B$2),IF(G40<=Assumptions!$B$5,I40+(J40-I40)*(G40-Assumptions!$B$4)/(Assumptions!$B$5-Assumptions!$B$4),J40)) -> 0.3325 | L40: =H40 -> 0.13268074 | M40: =K40-K39 -> 0.028 | N40: Scale to 70-70-70 | O40: Piecewise linear scale-up; hold after 2040 | P40: =IF(OR(K40<0,K40>1,M40<0),"BAD","OK") -> OK
A41: I_CVD_PRIMARY_Women_2038 | B41: S_70_30_30_TO_70_70_70 | C41: I_CVD_PRIMARY | D41: Primary prevention of CVD | E41: RF_HTN | F41: Women | G41: 2038 | H41: =Coverage!Q5 -> 0.13268074 | I41: =IF(Assumptions!$B$19=1,MAX(H41,Coverage!Q6),Coverage!Q6) -> 0.1365 | J41: =IF(Assumptions!$B$19=1,MAX(H41,Coverage!Q7),Coverage!Q7) -> 0.4165 | K41: =IF(G41<=Assumptions!$B$4,H41+(I41-H41)*(G41-Assumptions!$B$2)/(Assumptions!$B$4-Assumptions!$B$2),IF(G41<=Assumptions!$B$5,I41+(J41-I41)*(G41-Assumptions!$B$4)/(Assumptions!$B$5-Assumptions!$B$4),J41)) -> 0.3605 | L41: =H41 -> 0.13268074 | M41: =K41-K40 -> 0.028 | N41: Scale to 70-70-70 | O41: Piecewise linear scale-up; hold after 2040 | P41: =IF(OR(K41<0,K41>1,M41<0),"BAD","OK") -> OK
A42: I_CVD_PRIMARY_Women_2039 | B42: S_70_30_30_TO_70_70_70 | C42: I_CVD_PRIMARY | D42: Primary prevention of CVD | E42: RF_HTN | F42: Women | G42: 2039 | H42: =Coverage!Q5 -> 0.13268074 | I42: =IF(Assumptions!$B$19=1,MAX(H42,Coverage!Q6),Coverage!Q6) -> 0.1365 | J42: =IF(Assumptions!$B$19=1,MAX(H42,Coverage!Q7),Coverage!Q7) -> 0.4165 | K42: =IF(G42<=Assumptions!$B$4,H42+(I42-H42)*(G42-Assumptions!$B$2)/(Assumptions!$B$4-Assumptions!$B$2),IF(G42<=Assumptions!$B$5,I42+(J42-I42)*(G42-Assumptions!$B$4)/(Assumptions!$B$5-Assumptions!$B$4),J42)) -> 0.3885 | L42: =H42 -> 0.13268074 | M42: =K42-K41 -> 0.028 | N42: Scale to 70-70-70 | O42: Piecewise linear scale-up; hold after 2040 | P42: =IF(OR(K42<0,K42>1,M42<0),"BAD","OK") -> OK
A43: I_CVD_PRIMARY_Women_2040 | B43: S_70_30_30_TO_70_70_70 | C43: I_CVD_PRIMARY | D43: Primary prevention of CVD | E43: RF_HTN | F43: Women | G43: 2040 | H43: =Coverage!Q5 -> 0.13268074 | I43: =IF(Assumptions!$B$19=1,MAX(H43,Coverage!Q6),Coverage!Q6) -> 0.1365 | J43: =IF(Assumptions!$B$19=1,MAX(H43,Coverage!Q7),Coverage!Q7) -> 0.4165 | K43: =IF(G43<=Assumptions!$B$4,H43+(I43-H43)*(G43-Assumptions!$B$2)/(Assumptions!$B$4-Assumptions!$B$2),IF(G43<=Assumptions!$B$5,I43+(J43-I43)*(G43-Assumptions!$B$4)/(Assumptions!$B$5-Assumptions!$B$4),J43)) -> 0.4165 | L43: =H43 -> 0.13268074 | M43: =K43-K42 -> 0.028 | N43: Scale to 70-70-70 | O43: Piecewise linear scale-up; hold after 2040 | P43: =IF(OR(K43<0,K43>1,M43<0),"BAD","OK") -> OK
A44: I_CVD_PRIMARY_Women_2041 | B44: S_70_30_30_TO_70_70_70 | C44: I_CVD_PRIMARY | D44: Primary prevention of CVD | E44: RF_HTN | F44: Women | G44: 2041 | H44: =Coverage!Q5 -> 0.13268074 | I44: =IF(Assumptions!$B$19=1,MAX(H44,Coverage!Q6),Coverage!Q6) -> 0.1365 | J44: =IF(Assumptions!$B$19=1,MAX(H44,Coverage!Q7),Coverage!Q7) -> 0.4165 | K44: =IF(G44<=Assumptions!$B$4,H44+(I44-H44)*(G44-Assumptions!$B$2)/(Assumptions!$B$4-Assumptions!$B$2),IF(G44<=Assumptions!$B$5,I44+(J44-I44)*(G44-Assumptions!$B$4)/(Assumptions!$B$5-Assumptions!$B$4),J44)) -> 0.4165 | L44: =H44 -> 0.13268074 | M44: =K44-K43 -> 0 | N44: Maintain 70-70-70 | O44: Piecewise linear scale-up; hold after 2040 | P44: =IF(OR(K44<0,K44>1,M44<0),"BAD","OK") -> OK
A45: I_CVD_PRIMARY_Women_2042 | B45: S_70_30_30_TO_70_70_70 | C45: I_CVD_PRIMARY | D45: Primary prevention of CVD | E45: RF_HTN | F45: Women | G45: 2042 | H45: =Coverage!Q5 -> 0.13268074 | I45: =IF(Assumptions!$B$19=1,MAX(H45,Coverage!Q6),Coverage!Q6) -> 0.1365 | J45: =IF(Assumptions!$B$19=1,MAX(H45,Coverage!Q7),Coverage!Q7) -> 0.4165 | K45: =IF(G45<=Assumptions!$B$4,H45+(I45-H45)*(G45-Assumptions!$B$2)/(Assumptions!$B$4-Assumptions!$B$2),IF(G45<=Assumptions!$B$5,I45+(J45-I45)*(G45-Assumptions!$B$4)/(Assumptions!$B$5-Assumptions!$B$4),J45)) -> 0.4165 | L45: =H45 -> 0.13268074 | M45: =K45-K44 -> 0 | N45: Maintain 70-70-70 | O45: Piecewise linear scale-up; hold after 2040 | P45: =IF(OR(K45<0,K45>1,M45<0),"BAD","OK") -> OK
A46: I_CVD_PRIMARY_Women_2043 | B46: S_70_30_30_TO_70_70_70 | C46: I_CVD_PRIMARY | D46: Primary prevention of CVD | E46: RF_HTN | F46: Women | G46: 2043 | H46: =Coverage!Q5 -> 0.13268074 | I46: =IF(Assumptions!$B$19=1,MAX(H46,Coverage!Q6),Coverage!Q6) -> 0.1365 | J46: =IF(Assumptions!$B$19=1,MAX(H46,Coverage!Q7),Coverage!Q7) -> 0.4165 | K46: =IF(G46<=Assumptions!$B$4,H46+(I46-H46)*(G46-Assumptions!$B$2)/(Assumptions!$B$4-Assumptions!$B$2),IF(G46<=Assumptions!$B$5,I46+(J46-I46)*(G46-Assumptions!$B$4)/(Assumptions!$B$5-Assumptions!$B$4),J46)) -> 0.4165 | L46: =H46 -> 0.13268074 | M46: =K46-K45 -> 0 | N46: Maintain 70-70-70 | O46: Piecewise linear scale-up; hold after 2040 | P46: =IF(OR(K46<0,K46>1,M46<0),"BAD","OK") -> OK
A47: I_CVD_PRIMARY_Women_2044 | B47: S_70_30_30_TO_70_70_70 | C47: I_CVD_PRIMARY | D47: Primary prevention of CVD | E47: RF_HTN | F47: Women | G47: 2044 | H47: =Coverage!Q5 -> 0.13268074 | I47: =IF(Assumptions!$B$19=1,MAX(H47,Coverage!Q6),Coverage!Q6) -> 0.1365 | J47: =IF(Assumptions!$B$19=1,MAX(H47,Coverage!Q7),Coverage!Q7) -> 0.4165 | K47: =IF(G47<=Assumptions!$B$4,H47+(I47-H47)*(G47-Assumptions!$B$2)/(Assumptions!$B$4-Assumptions!$B$2),IF(G47<=Assumptions!$B$5,I47+(J47-I47)*(G47-Assumptions!$B$4)/(Assumptions!$B$5-Assumptions!$B$4),J47)) -> 0.4165 | L47: =H47 -> 0.13268074 | M47: =K47-K46 -> 0 | N47: Maintain 70-70-70 | O47: Piecewise linear scale-up; hold after 2040 | P47: =IF(OR(K47<0,K47>1,M47<0),"BAD","OK") -> OK
A48: I_CVD_PRIMARY_Women_2045 | B48: S_70_30_30_TO_70_70_70 | C48: I_CVD_PRIMARY | D48: Primary prevention of CVD | E48: RF_HTN | F48: Women | G48: 2045 | H48: =Coverage!Q5 -> 0.13268074 | I48: =IF(Assumptions!$B$19=1,MAX(H48,Coverage!Q6),Coverage!Q6) -> 0.1365 | J48: =IF(Assumptions!$B$19=1,MAX(H48,Coverage!Q7),Coverage!Q7) -> 0.4165 | K48: =IF(G48<=Assumptions!$B$4,H48+(I48-H48)*(G48-Assumptions!$B$2)/(Assumptions!$B$4-Assumptions!$B$2),IF(G48<=Assumptions!$B$5,I48+(J48-I48)*(G48-Assumptions!$B$4)/(Assumptions!$B$5-Assumptions!$B$4),J48)) -> 0.4165 | L48: =H48 -> 0.13268074 | M48: =K48-K47 -> 0 | N48: Maintain 70-70-70 | O48: Piecewise linear scale-up; hold after 2040 | P48: =IF(OR(K48<0,K48>1,M48<0),"BAD","OK") -> OK
A49: I_CVD_PRIMARY_Women_2046 | B49: S_70_30_30_TO_70_70_70 | C49: I_CVD_PRIMARY | D49: Primary prevention of CVD | E49: RF_HTN | F49: Women | G49: 2046 | H49: =Coverage!Q5 -> 0.13268074 | I49: =IF(Assumptions!$B$19=1,MAX(H49,Coverage!Q6),Coverage!Q6) -> 0.1365 | J49: =IF(Assumptions!$B$19=1,MAX(H49,Coverage!Q7),Coverage!Q7) -> 0.4165 | K49: =IF(G49<=Assumptions!$B$4,H49+(I49-H49)*(G49-Assumptions!$B$2)/(Assumptions!$B$4-Assumptions!$B$2),IF(G49<=Assumptions!$B$5,I49+(J49-I49)*(G49-Assumptions!$B$4)/(Assumptions!$B$5-Assumptions!$B$4),J49)) -> 0.4165 | L49: =H49 -> 0.13268074 | M49: =K49-K48 -> 0 | N49: Maintain 70-70-70 | O49: Piecewise linear scale-up; hold after 2040 | P49: =IF(OR(K49<0,K49>1,M49<0),"BAD","OK") -> OK
A50: I_CVD_PRIMARY_Women_2047 | B50: S_70_30_30_TO_70_70_70 | C50: I_CVD_PRIMARY | D50: Primary prevention of CVD | E50: RF_HTN | F50: Women | G50: 2047 | H50: =Coverage!Q5 -> 0.13268074 | I50: =IF(Assumptions!$B$19=1,MAX(H50,Coverage!Q6),Coverage!Q6) -> 0.1365 | J50: =IF(Assumptions!$B$19=1,MAX(H50,Coverage!Q7),Coverage!Q7) -> 0.4165 | K50: =IF(G50<=Assumptions!$B$4,H50+(I50-H50)*(G50-Assumptions!$B$2)/(Assumptions!$B$4-Assumptions!$B$2),IF(G50<=Assumptions!$B$5,I50+(J50-I50)*(G50-Assumptions!$B$4)/(Assumptions!$B$5-Assumptions!$B$4),J50)) -> 0.4165 | L50: =H50 -> 0.13268074 | M50: =K50-K49 -> 0 | N50: Maintain 70-70-70 | O50: Piecewise linear scale-up; hold after 2040 | P50: =IF(OR(K50<0,K50>1,M50<0),"BAD","OK") -> OK
A51: I_CVD_PRIMARY_Women_2048 | B51: S_70_30_30_TO_70_70_70 | C51: I_CVD_PRIMARY | D51: Primary prevention of CVD | E51: RF_HTN | F51: Women | G51: 2048 | H51: =Coverage!Q5 -> 0.13268074 | I51: =IF(Assumptions!$B$19=1,MAX(H51,Coverage!Q6),Coverage!Q6) -> 0.1365 | J51: =IF(Assumptions!$B$19=1,MAX(H51,Coverage!Q7),Coverage!Q7) -> 0.4165 | K51: =IF(G51<=Assumptions!$B$4,H51+(I51-H51)*(G51-Assumptions!$B$2)/(Assumptions!$B$4-Assumptions!$B$2),IF(G51<=Assumptions!$B$5,I51+(J51-I51)*(G51-Assumptions!$B$4)/(Assumptions!$B$5-Assumptions!$B$4),J51)) -> 0.4165 | L51: =H51 -> 0.13268074 | M51: =K51-K50 -> 0 | N51: Maintain 70-70-70 | O51: Piecewise linear scale-up; hold after 2040 | P51: =IF(OR(K51<0,K51>1,M51<0),"BAD","OK") -> OK
A52: I_CVD_PRIMARY_Women_2049 | B52: S_70_30_30_TO_70_70_70 | C52: I_CVD_PRIMARY | D52: Primary prevention of CVD | E52: RF_HTN | F52: Women | G52: 2049 | H52: =Coverage!Q5 -> 0.13268074 | I52: =IF(Assumptions!$B$19=1,MAX(H52,Coverage!Q6),Coverage!Q6) -> 0.1365 | J52: =IF(Assumptions!$B$19=1,MAX(H52,Coverage!Q7),Coverage!Q7) -> 0.4165 | K52: =IF(G52<=Assumptions!$B$4,H52+(I52-H52)*(G52-Assumptions!$B$2)/(Assumptions!$B$4-Assumptions!$B$2),IF(G52<=Assumptions!$B$5,I52+(J52-I52)*(G52-Assumptions!$B$4)/(Assumptions!$B$5-Assumptions!$B$4),J52)) -> 0.4165 | L52: =H52 -> 0.13268074 | M52: =K52-K51 -> 0 | N52: Maintain 70-70-70 | O52: Piecewise linear scale-up; hold after 2040 | P52: =IF(OR(K52<0,K52>1,M52<0),"BAD","OK") -> OK
A53: I_CVD_PRIMARY_Women_2050 | B53: S_70_30_30_TO_70_70_70 | C53: I_CVD_PRIMARY | D53: Primary prevention of CVD | E53: RF_HTN | F53: Women | G53: 2050 | H53: =Coverage!Q5 -> 0.13268074 | I53: =IF(Assumptions!$B$19=1,MAX(H53,Coverage!Q6),Coverage!Q6) -> 0.1365 | J53: =IF(Assumptions!$B$19=1,MAX(H53,Coverage!Q7),Coverage!Q7) -> 0.4165 | K53: =IF(G53<=Assumptions!$B$4,H53+(I53-H53)*(G53-Assumptions!$B$2)/(Assumptions!$B$4-Assumptions!$B$2),IF(G53<=Assumptions!$B$5,I53+(J53-I53)*(G53-Assumptions!$B$4)/(Assumptions!$B$5-Assumptions!$B$4),J53)) -> 0.4165 | L53: =H53 -> 0.13268074 | M53: =K53-K52 -> 0 | N53: Maintain 70-70-70 | O53: Piecewise linear scale-up; hold after 2040 | P53: =IF(OR(K53<0,K53>1,M53<0),"BAD","OK") -> OK
A54: I_T2D_TREATMENT_Men_2025 | B54: S_70_30_30_TO_70_70_70 | C54: I_T2D_TREATMENT | D54: Longitudinal treatment of type 2 diabetes | E54: RF_T2D | F54: Men | G54: 2025 | H54: =Coverage!Q8 -> 0.13031153 | I54: =IF(Assumptions!$B$19=1,MAX(H54,Coverage!Q9),Coverage!Q9) -> 0.1365 | J54: =IF(Assumptions!$B$19=1,MAX(H54,Coverage!Q10),Coverage!Q10) -> 0.4165 | K54: =IF(G54<=Assumptions!$B$4,H54+(I54-H54)*(G54-Assumptions!$B$2)/(Assumptions!$B$4-Assumptions!$B$2),IF(G54<=Assumptions!$B$5,I54+(J54-I54)*(G54-Assumptions!$B$4)/(Assumptions!$B$5-Assumptions!$B$4),J54)) -> 0.13031153 | L54: =H54 -> 0.13031153 | M54: 0 | N54: Scale to 70-30-30 | O54: Piecewise linear scale-up; hold after 2040 | P54: =IF(OR(K54<0,K54>1,M54<0),"BAD","OK") -> OK
A55: I_T2D_TREATMENT_Men_2026 | B55: S_70_30_30_TO_70_70_70 | C55: I_T2D_TREATMENT | D55: Longitudinal treatment of type 2 diabetes | E55: RF_T2D | F55: Men | G55: 2026 | H55: =Coverage!Q8 -> 0.13031153 | I55: =IF(Assumptions!$B$19=1,MAX(H55,Coverage!Q9),Coverage!Q9) -> 0.1365 | J55: =IF(Assumptions!$B$19=1,MAX(H55,Coverage!Q10),Coverage!Q10) -> 0.4165 | K55: =IF(G55<=Assumptions!$B$4,H55+(I55-H55)*(G55-Assumptions!$B$2)/(Assumptions!$B$4-Assumptions!$B$2),IF(G55<=Assumptions!$B$5,I55+(J55-I55)*(G55-Assumptions!$B$4)/(Assumptions!$B$5-Assumptions!$B$4),J55)) -> 0.13154922 | L55: =H55 -> 0.13031153 | M55: =K55-K54 -> 0.0012376944 | N55: Scale to 70-30-30 | O55: Piecewise linear scale-up; hold after 2040 | P55: =IF(OR(K55<0,K55>1,M55<0),"BAD","OK") -> OK
A56: I_T2D_TREATMENT_Men_2027 | B56: S_70_30_30_TO_70_70_70 | C56: I_T2D_TREATMENT | D56: Longitudinal treatment of type 2 diabetes | E56: RF_T2D | F56: Men | G56: 2027 | H56: =Coverage!Q8 -> 0.13031153 | I56: =IF(Assumptions!$B$19=1,MAX(H56,Coverage!Q9),Coverage!Q9) -> 0.1365 | J56: =IF(Assumptions!$B$19=1,MAX(H56,Coverage!Q10),Coverage!Q10) -> 0.4165 | K56: =IF(G56<=Assumptions!$B$4,H56+(I56-H56)*(G56-Assumptions!$B$2)/(Assumptions!$B$4-Assumptions!$B$2),IF(G56<=Assumptions!$B$5,I56+(J56-I56)*(G56-Assumptions!$B$4)/(Assumptions!$B$5-Assumptions!$B$4),J56)) -> 0.13278692 | L56: =H56 -> 0.13031153 | M56: =K56-K55 -> 0.0012376944 | N56: Scale to 70-30-30 | O56: Piecewise linear scale-up; hold after 2040 | P56: =IF(OR(K56<0,K56>1,M56<0),"BAD","OK") -> OK
A57: I_T2D_TREATMENT_Men_2028 | B57: S_70_30_30_TO_70_70_70 | C57: I_T2D_TREATMENT | D57: Longitudinal treatment of type 2 diabetes | E57: RF_T2D | F57: Men | G57: 2028 | H57: =Coverage!Q8 -> 0.13031153 | I57: =IF(Assumptions!$B$19=1,MAX(H57,Coverage!Q9),Coverage!Q9) -> 0.1365 | J57: =IF(Assumptions!$B$19=1,MAX(H57,Coverage!Q10),Coverage!Q10) -> 0.4165 | K57: =IF(G57<=Assumptions!$B$4,H57+(I57-H57)*(G57-Assumptions!$B$2)/(Assumptions!$B$4-Assumptions!$B$2),IF(G57<=Assumptions!$B$5,I57+(J57-I57)*(G57-Assumptions!$B$4)/(Assumptions!$B$5-Assumptions!$B$4),J57)) -> 0.13402461 | L57: =H57 -> 0.13031153 | M57: =K57-K56 -> 0.0012376944 | N57: Scale to 70-30-30 | O57: Piecewise linear scale-up; hold after 2040 | P57: =IF(OR(K57<0,K57>1,M57<0),"BAD","OK") -> OK
A58: I_T2D_TREATMENT_Men_2029 | B58: S_70_30_30_TO_70_70_70 | C58: I_T2D_TREATMENT | D58: Longitudinal treatment of type 2 diabetes | E58: RF_T2D | F58: Men | G58: 2029 | H58: =Coverage!Q8 -> 0.13031153 | I58: =IF(Assumptions!$B$19=1,MAX(H58,Coverage!Q9),Coverage!Q9) -> 0.1365 | J58: =IF(Assumptions!$B$19=1,MAX(H58,Coverage!Q10),Coverage!Q10) -> 0.4165 | K58: =IF(G58<=Assumptions!$B$4,H58+(I58-H58)*(G58-Assumptions!$B$2)/(Assumptions!$B$4-Assumptions!$B$2),IF(G58<=Assumptions!$B$5,I58+(J58-I58)*(G58-Assumptions!$B$4)/(Assumptions!$B$5-Assumptions!$B$4),J58)) -> 0.13526231 | L58: =H58 -> 0.13031153 | M58: =K58-K57 -> 0.0012376944 | N58: Scale to 70-30-30 | O58: Piecewise linear scale-up; hold after 2040 | P58: =IF(OR(K58<0,K58>1,M58<0),"BAD","OK") -> OK
A59: I_T2D_TREATMENT_Men_2030 | B59: S_70_30_30_TO_70_70_70 | C59: I_T2D_TREATMENT | D59: Longitudinal treatment of type 2 diabetes | E59: RF_T2D | F59: Men | G59: 2030 | H59: =Coverage!Q8 -> 0.13031153 | I59: =IF(Assumptions!$B$19=1,MAX(H59,Coverage!Q9),Coverage!Q9) -> 0.1365 | J59: =IF(Assumptions!$B$19=1,MAX(H59,Coverage!Q10),Coverage!Q10) -> 0.4165 | K59: =IF(G59<=Assumptions!$B$4,H59+(I59-H59)*(G59-Assumptions!$B$2)/(Assumptions!$B$4-Assumptions!$B$2),IF(G59<=Assumptions!$B$5,I59+(J59-I59)*(G59-Assumptions!$B$4)/(Assumptions!$B$5-Assumptions!$B$4),J59)) -> 0.1365 | L59: =H59 -> 0.13031153 | M59: =K59-K58 -> 0.0012376944 | N59: Scale to 70-30-30 | O59: Piecewise linear scale-up; hold after 2040 | P59: =IF(OR(K59<0,K59>1,M59<0),"BAD","OK") -> OK
A60: I_T2D_TREATMENT_Men_2031 | B60: S_70_30_30_TO_70_70_70 | C60: I_T2D_TREATMENT | D60: Longitudinal treatment of type 2 diabetes | E60: RF_T2D | F60: Men | G60: 2031 | H60: =Coverage!Q8 -> 0.13031153 | I60: =IF(Assumptions!$B$19=1,MAX(H60,Coverage!Q9),Coverage!Q9) -> 0.1365 | J60: =IF(Assumptions!$B$19=1,MAX(H60,Coverage!Q10),Coverage!Q10) -> 0.4165 | K60: =IF(G60<=Assumptions!$B$4,H60+(I60-H60)*(G60-Assumptions!$B$2)/(Assumptions!$B$4-Assumptions!$B$2),IF(G60<=Assumptions!$B$5,I60+(J60-I60)*(G60-Assumptions!$B$4)/(Assumptions!$B$5-Assumptions!$B$4),J60)) -> 0.1645 | L60: =H60 -> 0.13031153 | M60: =K60-K59 -> 0.028 | N60: Scale to 70-70-70 | O60: Piecewise linear scale-up; hold after 2040 | P60: =IF(OR(K60<0,K60>1,M60<0),"BAD","OK") -> OK
A61: I_T2D_TREATMENT_Men_2032 | B61: S_70_30_30_TO_70_70_70 | C61: I_T2D_TREATMENT | D61: Longitudinal treatment of type 2 diabetes | E61: RF_T2D | F61: Men | G61: 2032 | H61: =Coverage!Q8 -> 0.13031153 | I61: =IF(Assumptions!$B$19=1,MAX(H61,Coverage!Q9),Coverage!Q9) -> 0.1365 | J61: =IF(Assumptions!$B$19=1,MAX(H61,Coverage!Q10),Coverage!Q10) -> 0.4165 | K61: =IF(G61<=Assumptions!$B$4,H61+(I61-H61)*(G61-Assumptions!$B$2)/(Assumptions!$B$4-Assumptions!$B$2),IF(G61<=Assumptions!$B$5,I61+(J61-I61)*(G61-Assumptions!$B$4)/(Assumptions!$B$5-Assumptions!$B$4),J61)) -> 0.1925 | L61: =H61 -> 0.13031153 | M61: =K61-K60 -> 0.028 | N61: Scale to 70-70-70 | O61: Piecewise linear scale-up; hold after 2040 | P61: =IF(OR(K61<0,K61>1,M61<0),"BAD","OK") -> OK
A62: I_T2D_TREATMENT_Men_2033 | B62: S_70_30_30_TO_70_70_70 | C62: I_T2D_TREATMENT | D62: Longitudinal treatment of type 2 diabetes | E62: RF_T2D | F62: Men | G62: 2033 | H62: =Coverage!Q8 -> 0.13031153 | I62: =IF(Assumptions!$B$19=1,MAX(H62,Coverage!Q9),Coverage!Q9) -> 0.1365 | J62: =IF(Assumptions!$B$19=1,MAX(H62,Coverage!Q10),Coverage!Q10) -> 0.4165 | K62: =IF(G62<=Assumptions!$B$4,H62+(I62-H62)*(G62-Assumptions!$B$2)/(Assumptions!$B$4-Assumptions!$B$2),IF(G62<=Assumptions!$B$5,I62+(J62-I62)*(G62-Assumptions!$B$4)/(Assumptions!$B$5-Assumptions!$B$4),J62)) -> 0.2205 | L62: =H62 -> 0.13031153 | M62: =K62-K61 -> 0.028 | N62: Scale to 70-70-70 | O62: Piecewise linear scale-up; hold after 2040 | P62: =IF(OR(K62<0,K62>1,M62<0),"BAD","OK") -> OK
A63: I_T2D_TREATMENT_Men_2034 | B63: S_70_30_30_TO_70_70_70 | C63: I_T2D_TREATMENT | D63: Longitudinal treatment of type 2 diabetes | E63: RF_T2D | F63: Men | G63: 2034 | H63: =Coverage!Q8 -> 0.13031153 | I63: =IF(Assumptions!$B$19=1,MAX(H63,Coverage!Q9),Coverage!Q9) -> 0.1365 | J63: =IF(Assumptions!$B$19=1,MAX(H63,Coverage!Q10),Coverage!Q10) -> 0.4165 | K63: =IF(G63<=Assumptions!$B$4,H63+(I63-H63)*(G63-Assumptions!$B$2)/(Assumptions!$B$4-Assumptions!$B$2),IF(G63<=Assumptions!$B$5,I63+(J63-I63)*(G63-Assumptions!$B$4)/(Assumptions!$B$5-Assumptions!$B$4),J63)) -> 0.2485 | L63: =H63 -> 0.13031153 | M63: =K63-K62 -> 0.028 | N63: Scale to 70-70-70 | O63: Piecewise linear scale-up; hold after 2040 | P63: =IF(OR(K63<0,K63>1,M63<0),"BAD","OK") -> OK
A64: I_T2D_TREATMENT_Men_2035 | B64: S_70_30_30_TO_70_70_70 | C64: I_T2D_TREATMENT | D64: Longitudinal treatment of type 2 diabetes | E64: RF_T2D | F64: Men | G64: 2035 | H64: =Coverage!Q8 -> 0.13031153 | I64: =IF(Assumptions!$B$19=1,MAX(H64,Coverage!Q9),Coverage!Q9) -> 0.1365 | J64: =IF(Assumptions!$B$19=1,MAX(H64,Coverage!Q10),Coverage!Q10) -> 0.4165 | K64: =IF(G64<=Assumptions!$B$4,H64+(I64-H64)*(G64-Assumptions!$B$2)/(Assumptions!$B$4-Assumptions!$B$2),IF(G64<=Assumptions!$B$5,I64+(J64-I64)*(G64-Assumptions!$B$4)/(Assumptions!$B$5-Assumptions!$B$4),J64)) -> 0.2765 | L64: =H64 -> 0.13031153 | M64: =K64-K63 -> 0.028 | N64: Scale to 70-70-70 | O64: Piecewise linear scale-up; hold after 2040 | P64: =IF(OR(K64<0,K64>1,M64<0),"BAD","OK") -> OK
A65: I_T2D_TREATMENT_Men_2036 | B65: S_70_30_30_TO_70_70_70 | C65: I_T2D_TREATMENT | D65: Longitudinal treatment of type 2 diabetes | E65: RF_T2D | F65: Men | G65: 2036 | H65: =Coverage!Q8 -> 0.13031153 | I65: =IF(Assumptions!$B$19=1,MAX(H65,Coverage!Q9),Coverage!Q9) -> 0.1365 | J65: =IF(Assumptions!$B$19=1,MAX(H65,Coverage!Q10),Coverage!Q10) -> 0.4165 | K65: =IF(G65<=Assumptions!$B$4,H65+(I65-H65)*(G65-Assumptions!$B$2)/(Assumptions!$B$4-Assumptions!$B$2),IF(G65<=Assumptions!$B$5,I65+(J65-I65)*(G65-Assumptions!$B$4)/(Assumptions!$B$5-Assumptions!$B$4),J65)) -> 0.3045 | L65: =H65 -> 0.13031153 | M65: =K65-K64 -> 0.028 | N65: Scale to 70-70-70 | O65: Piecewise linear scale-up; hold after 2040 | P65: =IF(OR(K65<0,K65>1,M65<0),"BAD","OK") -> OK
A66: I_T2D_TREATMENT_Men_2037 | B66: S_70_30_30_TO_70_70_70 | C66: I_T2D_TREATMENT | D66: Longitudinal treatment of type 2 diabetes | E66: RF_T2D | F66: Men | G66: 2037 | H66: =Coverage!Q8 -> 0.13031153 | I66: =IF(Assumptions!$B$19=1,MAX(H66,Coverage!Q9),Coverage!Q9) -> 0.1365 | J66: =IF(Assumptions!$B$19=1,MAX(H66,Coverage!Q10),Coverage!Q10) -> 0.4165 | K66: =IF(G66<=Assumptions!$B$4,H66+(I66-H66)*(G66-Assumptions!$B$2)/(Assumptions!$B$4-Assumptions!$B$2),IF(G66<=Assumptions!$B$5,I66+(J66-I66)*(G66-Assumptions!$B$4)/(Assumptions!$B$5-Assumptions!$B$4),J66)) -> 0.3325 | L66: =H66 -> 0.13031153 | M66: =K66-K65 -> 0.028 | N66: Scale to 70-70-70 | O66: Piecewise linear scale-up; hold after 2040 | P66: =IF(OR(K66<0,K66>1,M66<0),"BAD","OK") -> OK
A67: I_T2D_TREATMENT_Men_2038 | B67: S_70_30_30_TO_70_70_70 | C67: I_T2D_TREATMENT | D67: Longitudinal treatment of type 2 diabetes | E67: RF_T2D | F67: Men | G67: 2038 | H67: =Coverage!Q8 -> 0.13031153 | I67: =IF(Assumptions!$B$19=1,MAX(H67,Coverage!Q9),Coverage!Q9) -> 0.1365 | J67: =IF(Assumptions!$B$19=1,MAX(H67,Coverage!Q10),Coverage!Q10) -> 0.4165 | K67: =IF(G67<=Assumptions!$B$4,H67+(I67-H67)*(G67-Assumptions!$B$2)/(Assumptions!$B$4-Assumptions!$B$2),IF(G67<=Assumptions!$B$5,I67+(J67-I67)*(G67-Assumptions!$B$4)/(Assumptions!$B$5-Assumptions!$B$4),J67)) -> 0.3605 | L67: =H67 -> 0.13031153 | M67: =K67-K66 -> 0.028 | N67: Scale to 70-70-70 | O67: Piecewise linear scale-up; hold after 2040 | P67: =IF(OR(K67<0,K67>1,M67<0),"BAD","OK") -> OK
A68: I_T2D_TREATMENT_Men_2039 | B68: S_70_30_30_TO_70_70_70 | C68: I_T2D_TREATMENT | D68: Longitudinal treatment of type 2 diabetes | E68: RF_T2D | F68: Men | G68: 2039 | H68: =Coverage!Q8 -> 0.13031153 | I68: =IF(Assumptions!$B$19=1,MAX(H68,Coverage!Q9),Coverage!Q9) -> 0.1365 | J68: =IF(Assumptions!$B$19=1,MAX(H68,Coverage!Q10),Coverage!Q10) -> 0.4165 | K68: =IF(G68<=Assumptions!$B$4,H68+(I68-H68)*(G68-Assumptions!$B$2)/(Assumptions!$B$4-Assumptions!$B$2),IF(G68<=Assumptions!$B$5,I68+(J68-I68)*(G68-Assumptions!$B$4)/(Assumptions!$B$5-Assumptions!$B$4),J68)) -> 0.3885 | L68: =H68 -> 0.13031153 | M68: =K68-K67 -> 0.028 | N68: Scale to 70-70-70 | O68: Piecewise linear scale-up; hold after 2040 | P68: =IF(OR(K68<0,K68>1,M68<0),"BAD","OK") -> OK
A69: I_T2D_TREATMENT_Men_2040 | B69: S_70_30_30_TO_70_70_70 | C69: I_T2D_TREATMENT | D69: Longitudinal treatment of type 2 diabetes | E69: RF_T2D | F69: Men | G69: 2040 | H69: =Coverage!Q8 -> 0.13031153 | I69: =IF(Assumptions!$B$19=1,MAX(H69,Coverage!Q9),Coverage!Q9) -> 0.1365 | J69: =IF(Assumptions!$B$19=1,MAX(H69,Coverage!Q10),Coverage!Q10) -> 0.4165 | K69: =IF(G69<=Assumptions!$B$4,H69+(I69-H69)*(G69-Assumptions!$B$2)/(Assumptions!$B$4-Assumptions!$B$2),IF(G69<=Assumptions!$B$5,I69+(J69-I69)*(G69-Assumptions!$B$4)/(Assumptions!$B$5-Assumptions!$B$4),J69)) -> 0.4165 | L69: =H69 -> 0.13031153 | M69: =K69-K68 -> 0.028 | N69: Scale to 70-70-70 | O69: Piecewise linear scale-up; hold after 2040 | P69: =IF(OR(K69<0,K69>1,M69<0),"BAD","OK") -> OK
A70: I_T2D_TREATMENT_Men_2041 | B70: S_70_30_30_TO_70_70_70 | C70: I_T2D_TREATMENT | D70: Longitudinal treatment of type 2 diabetes | E70: RF_T2D | F70: Men | G70: 2041 | H70: =Coverage!Q8 -> 0.13031153 | I70: =IF(Assumptions!$B$19=1,MAX(H70,Coverage!Q9),Coverage!Q9) -> 0.1365 | J70: =IF(Assumptions!$B$19=1,MAX(H70,Coverage!Q10),Coverage!Q10) -> 0.4165 | K70: =IF(G70<=Assumptions!$B$4,H70+(I70-H70)*(G70-Assumptions!$B$2)/(Assumptions!$B$4-Assumptions!$B$2),IF(G70<=Assumptions!$B$5,I70+(J70-I70)*(G70-Assumptions!$B$4)/(Assumptions!$B$5-Assumptions!$B$4),J70)) -> 0.4165 | L70: =H70 -> 0.13031153 | M70: =K70-K69 -> 0 | N70: Maintain 70-70-70 | O70: Piecewise linear scale-up; hold after 2040 | P70: =IF(OR(K70<0,K70>1,M70<0),"BAD","OK") -> OK
A71: I_T2D_TREATMENT_Men_2042 | B71: S_70_30_30_TO_70_70_70 | C71: I_T2D_TREATMENT | D71: Longitudinal treatment of type 2 diabetes | E71: RF_T2D | F71: Men | G71: 2042 | H71: =Coverage!Q8 -> 0.13031153 | I71: =IF(Assumptions!$B$19=1,MAX(H71,Coverage!Q9),Coverage!Q9) -> 0.1365 | J71: =IF(Assumptions!$B$19=1,MAX(H71,Coverage!Q10),Coverage!Q10) -> 0.4165 | K71: =IF(G71<=Assumptions!$B$4,H71+(I71-H71)*(G71-Assumptions!$B$2)/(Assumptions!$B$4-Assumptions!$B$2),IF(G71<=Assumptions!$B$5,I71+(J71-I71)*(G71-Assumptions!$B$4)/(Assumptions!$B$5-Assumptions!$B$4),J71)) -> 0.4165 | L71: =H71 -> 0.13031153 | M71: =K71-K70 -> 0 | N71: Maintain 70-70-70 | O71: Piecewise linear scale-up; hold after 2040 | P71: =IF(OR(K71<0,K71>1,M71<0),"BAD","OK") -> OK
A72: I_T2D_TREATMENT_Men_2043 | B72: S_70_30_30_TO_70_70_70 | C72: I_T2D_TREATMENT | D72: Longitudinal treatment of type 2 diabetes | E72: RF_T2D | F72: Men | G72: 2043 | H72: =Coverage!Q8 -> 0.13031153 | I72: =IF(Assumptions!$B$19=1,MAX(H72,Coverage!Q9),Coverage!Q9) -> 0.1365 | J72: =IF(Assumptions!$B$19=1,MAX(H72,Coverage!Q10),Coverage!Q10) -> 0.4165 | K72: =IF(G72<=Assumptions!$B$4,H72+(I72-H72)*(G72-Assumptions!$B$2)/(Assumptions!$B$4-Assumptions!$B$2),IF(G72<=Assumptions!$B$5,I72+(J72-I72)*(G72-Assumptions!$B$4)/(Assumptions!$B$5-Assumptions!$B$4),J72)) -> 0.4165 | L72: =H72 -> 0.13031153 | M72: =K72-K71 -> 0 | N72: Maintain 70-70-70 | O72: Piecewise linear scale-up; hold after 2040 | P72: =IF(OR(K72<0,K72>1,M72<0),"BAD","OK") -> OK
A73: I_T2D_TREATMENT_Men_2044 | B73: S_70_30_30_TO_70_70_70 | C73: I_T2D_TREATMENT | D73: Longitudinal treatment of type 2 diabetes | E73: RF_T2D | F73: Men | G73: 2044 | H73: =Coverage!Q8 -> 0.13031153 | I73: =IF(Assumptions!$B$19=1,MAX(H73,Coverage!Q9),Coverage!Q9) -> 0.1365 | J73: =IF(Assumptions!$B$19=1,MAX(H73,Coverage!Q10),Coverage!Q10) -> 0.4165 | K73: =IF(G73<=Assumptions!$B$4,H73+(I73-H73)*(G73-Assumptions!$B$2)/(Assumptions!$B$4-Assumptions!$B$2),IF(G73<=Assumptions!$B$5,I73+(J73-I73)*(G73-Assumptions!$B$4)/(Assumptions!$B$5-Assumptions!$B$4),J73)) -> 0.4165 | L73: =H73 -> 0.13031153 | M73: =K73-K72 -> 0 | N73: Maintain 70-70-70 | O73: Piecewise linear scale-up; hold after 2040 | P73: =IF(OR(K73<0,K73>1,M73<0),"BAD","OK") -> OK
A74: I_T2D_TREATMENT_Men_2045 | B74: S_70_30_30_TO_70_70_70 | C74: I_T2D_TREATMENT | D74: Longitudinal treatment of type 2 diabetes | E74: RF_T2D | F74: Men | G74: 2045 | H74: =Coverage!Q8 -> 0.13031153 | I74: =IF(Assumptions!$B$19=1,MAX(H74,Coverage!Q9),Coverage!Q9) -> 0.1365 | J74: =IF(Assumptions!$B$19=1,MAX(H74,Coverage!Q10),Coverage!Q10) -> 0.4165 | K74: =IF(G74<=Assumptions!$B$4,H74+(I74-H74)*(G74-Assumptions!$B$2)/(Assumptions!$B$4-Assumptions!$B$2),IF(G74<=Assumptions!$B$5,I74+(J74-I74)*(G74-Assumptions!$B$4)/(Assumptions!$B$5-Assumptions!$B$4),J74)) -> 0.4165 | L74: =H74 -> 0.13031153 | M74: =K74-K73 -> 0 | N74: Maintain 70-70-70 | O74: Piecewise linear scale-up; hold after 2040 | P74: =IF(OR(K74<0,K74>1,M74<0),"BAD","OK") -> OK
A75: I_T2D_TREATMENT_Men_2046 | B75: S_70_30_30_TO_70_70_70 | C75: I_T2D_TREATMENT | D75: Longitudinal treatment of type 2 diabetes | E75: RF_T2D | F75: Men | G75: 2046 | H75: =Coverage!Q8 -> 0.13031153 | I75: =IF(Assumptions!$B$19=1,MAX(H75,Coverage!Q9),Coverage!Q9) -> 0.1365 | J75: =IF(Assumptions!$B$19=1,MAX(H75,Coverage!Q10),Coverage!Q10) -> 0.4165 | K75: =IF(G75<=Assumptions!$B$4,H75+(I75-H75)*(G75-Assumptions!$B$2)/(Assumptions!$B$4-Assumptions!$B$2),IF(G75<=Assumptions!$B$5,I75+(J75-I75)*(G75-Assumptions!$B$4)/(Assumptions!$B$5-Assumptions!$B$4),J75)) -> 0.4165 | L75: =H75 -> 0.13031153 | M75: =K75-K74 -> 0 | N75: Maintain 70-70-70 | O75: Piecewise linear scale-up; hold after 2040 | P75: =IF(OR(K75<0,K75>1,M75<0),"BAD","OK") -> OK
A76: I_T2D_TREATMENT_Men_2047 | B76: S_70_30_30_TO_70_70_70 | C76: I_T2D_TREATMENT | D76: Longitudinal treatment of type 2 diabetes | E76: RF_T2D | F76: Men | G76: 2047 | H76: =Coverage!Q8 -> 0.13031153 | I76: =IF(Assumptions!$B$19=1,MAX(H76,Coverage!Q9),Coverage!Q9) -> 0.1365 | J76: =IF(Assumptions!$B$19=1,MAX(H76,Coverage!Q10),Coverage!Q10) -> 0.4165 | K76: =IF(G76<=Assumptions!$B$4,H76+(I76-H76)*(G76-Assumptions!$B$2)/(Assumptions!$B$4-Assumptions!$B$2),IF(G76<=Assumptions!$B$5,I76+(J76-I76)*(G76-Assumptions!$B$4)/(Assumptions!$B$5-Assumptions!$B$4),J76)) -> 0.4165 | L76: =H76 -> 0.13031153 | M76: =K76-K75 -> 0 | N76: Maintain 70-70-70 | O76: Piecewise linear scale-up; hold after 2040 | P76: =IF(OR(K76<0,K76>1,M76<0),"BAD","OK") -> OK
A77: I_T2D_TREATMENT_Men_2048 | B77: S_70_30_30_TO_70_70_70 | C77: I_T2D_TREATMENT | D77: Longitudinal treatment of type 2 diabetes | E77: RF_T2D | F77: Men | G77: 2048 | H77: =Coverage!Q8 -> 0.13031153 | I77: =IF(Assumptions!$B$19=1,MAX(H77,Coverage!Q9),Coverage!Q9) -> 0.1365 | J77: =IF(Assumptions!$B$19=1,MAX(H77,Coverage!Q10),Coverage!Q10) -> 0.4165 | K77: =IF(G77<=Assumptions!$B$4,H77+(I77-H77)*(G77-Assumptions!$B$2)/(Assumptions!$B$4-Assumptions!$B$2),IF(G77<=Assumptions!$B$5,I77+(J77-I77)*(G77-Assumptions!$B$4)/(Assumptions!$B$5-Assumptions!$B$4),J77)) -> 0.4165 | L77: =H77 -> 0.13031153 | M77: =K77-K76 -> 0 | N77: Maintain 70-70-70 | O77: Piecewise linear scale-up; hold after 2040 | P77: =IF(OR(K77<0,K77>1,M77<0),"BAD","OK") -> OK
A78: I_T2D_TREATMENT_Men_2049 | B78: S_70_30_30_TO_70_70_70 | C78: I_T2D_TREATMENT | D78: Longitudinal treatment of type 2 diabetes | E78: RF_T2D | F78: Men | G78: 2049 | H78: =Coverage!Q8 -> 0.13031153 | I78: =IF(Assumptions!$B$19=1,MAX(H78,Coverage!Q9),Coverage!Q9) -> 0.1365 | J78: =IF(Assumptions!$B$19=1,MAX(H78,Coverage!Q10),Coverage!Q10) -> 0.4165 | K78: =IF(G78<=Assumptions!$B$4,H78+(I78-H78)*(G78-Assumptions!$B$2)/(Assumptions!$B$4-Assumptions!$B$2),IF(G78<=Assumptions!$B$5,I78+(J78-I78)*(G78-Assumptions!$B$4)/(Assumptions!$B$5-Assumptions!$B$4),J78)) -> 0.4165 | L78: =H78 -> 0.13031153 | M78: =K78-K77 -> 0 | N78: Maintain 70-70-70 | O78: Piecewise linear scale-up; hold after 2040 | P78: =IF(OR(K78<0,K78>1,M78<0),"BAD","OK") -> OK
A79: I_T2D_TREATMENT_Men_2050 | B79: S_70_30_30_TO_70_70_70 | C79: I_T2D_TREATMENT | D79: Longitudinal treatment of type 2 diabetes | E79: RF_T2D | F79: Men | G79: 2050 | H79: =Coverage!Q8 -> 0.13031153 | I79: =IF(Assumptions!$B$19=1,MAX(H79,Coverage!Q9),Coverage!Q9) -> 0.1365 | J79: =IF(Assumptions!$B$19=1,MAX(H79,Coverage!Q10),Coverage!Q10) -> 0.4165 | K79: =IF(G79<=Assumptions!$B$4,H79+(I79-H79)*(G79-Assumptions!$B$2)/(Assumptions!$B$4-Assumptions!$B$2),IF(G79<=Assumptions!$B$5,I79+(J79-I79)*(G79-Assumptions!$B$4)/(Assumptions!$B$5-Assumptions!$B$4),J79)) -> 0.4165 | L79: =H79 -> 0.13031153 | M79: =K79-K78 -> 0 | N79: Maintain 70-70-70 | O79: Piecewise linear scale-up; hold after 2040 | P79: =IF(OR(K79<0,K79>1,M79<0),"BAD","OK") -> OK
A80: I_T2D_TREATMENT_Women_2025 | B80: S_70_30_30_TO_70_70_70 | C80: I_T2D_TREATMENT | D80: Longitudinal treatment of type 2 diabetes | E80: RF_T2D | F80: Women | G80: 2025 | H80: =Coverage!Q11 -> 0.1655177 | I80: =IF(Assumptions!$B$19=1,MAX(H80,Coverage!Q12),Coverage!Q12) -> 0.1655177 | J80: =IF(Assumptions!$B$19=1,MAX(H80,Coverage!Q13),Coverage!Q13) -> 0.4165 | K80: =IF(G80<=Assumptions!$B$4,H80+(I80-H80)*(G80-Assumptions!$B$2)/(Assumptions!$B$4-Assumptions!$B$2),IF(G80<=Assumptions!$B$5,I80+(J80-I80)*(G80-Assumptions!$B$4)/(Assumptions!$B$5-Assumptions!$B$4),J80)) -> 0.1655177 | L80: =H80 -> 0.1655177 | M80: 0 | N80: Scale to 70-30-30 | O80: Piecewise linear scale-up; hold after 2040 | P80: =IF(OR(K80<0,K80>1,M80<0),"BAD","OK") -> OK
A81: I_T2D_TREATMENT_Women_2026 | B81: S_70_30_30_TO_70_70_70 | C81: I_T2D_TREATMENT | D81: Longitudinal treatment of type 2 diabetes | E81: RF_T2D | F81: Women | G81: 2026 | H81: =Coverage!Q11 -> 0.1655177 | I81: =IF(Assumptions!$B$19=1,MAX(H81,Coverage!Q12),Coverage!Q12) -> 0.1655177 | J81: =IF(Assumptions!$B$19=1,MAX(H81,Coverage!Q13),Coverage!Q13) -> 0.4165 | K81: =IF(G81<=Assumptions!$B$4,H81+(I81-H81)*(G81-Assumptions!$B$2)/(Assumptions!$B$4-Assumptions!$B$2),IF(G81<=Assumptions!$B$5,I81+(J81-I81)*(G81-Assumptions!$B$4)/(Assumptions!$B$5-Assumptions!$B$4),J81)) -> 0.1655177 | L81: =H81 -> 0.1655177 | M81: =K81-K80 -> 0 | N81: Scale to 70-30-30 | O81: Piecewise linear scale-up; hold after 2040 | P81: =IF(OR(K81<0,K81>1,M81<0),"BAD","OK") -> OK
A82: I_T2D_TREATMENT_Women_2027 | B82: S_70_30_30_TO_70_70_70 | C82: I_T2D_TREATMENT | D82: Longitudinal treatment of type 2 diabetes | E82: RF_T2D | F82: Women | G82: 2027 | H82: =Coverage!Q11 -> 0.1655177 | I82: =IF(Assumptions!$B$19=1,MAX(H82,Coverage!Q12),Coverage!Q12) -> 0.1655177 | J82: =IF(Assumptions!$B$19=1,MAX(H82,Coverage!Q13),Coverage!Q13) -> 0.4165 | K82: =IF(G82<=Assumptions!$B$4,H82+(I82-H82)*(G82-Assumptions!$B$2)/(Assumptions!$B$4-Assumptions!$B$2),IF(G82<=Assumptions!$B$5,I82+(J82-I82)*(G82-Assumptions!$B$4)/(Assumptions!$B$5-Assumptions!$B$4),J82)) -> 0.1655177 | L82: =H82 -> 0.1655177 | M82: =K82-K81 -> 0 | N82: Scale to 70-30-30 | O82: Piecewise linear scale-up; hold after 2040 | P82: =IF(OR(K82<0,K82>1,M82<0),"BAD","OK") -> OK
A83: I_T2D_TREATMENT_Women_2028 | B83: S_70_30_30_TO_70_70_70 | C83: I_T2D_TREATMENT | D83: Longitudinal treatment of type 2 diabetes | E83: RF_T2D | F83: Women | G83: 2028 | H83: =Coverage!Q11 -> 0.1655177 | I83: =IF(Assumptions!$B$19=1,MAX(H83,Coverage!Q12),Coverage!Q12) -> 0.1655177 | J83: =IF(Assumptions!$B$19=1,MAX(H83,Coverage!Q13),Coverage!Q13) -> 0.4165 | K83: =IF(G83<=Assumptions!$B$4,H83+(I83-H83)*(G83-Assumptions!$B$2)/(Assumptions!$B$4-Assumptions!$B$2),IF(G83<=Assumptions!$B$5,I83+(J83-I83)*(G83-Assumptions!$B$4)/(Assumptions!$B$5-Assumptions!$B$4),J83)) -> 0.1655177 | L83: =H83 -> 0.1655177 | M83: =K83-K82 -> 0 | N83: Scale to 70-30-30 | O83: Piecewise linear scale-up; hold after 2040 | P83: =IF(OR(K83<0,K83>1,M83<0),"BAD","OK") -> OK
A84: I_T2D_TREATMENT_Women_2029 | B84: S_70_30_30_TO_70_70_70 | C84: I_T2D_TREATMENT | D84: Longitudinal treatment of type 2 diabetes | E84: RF_T2D | F84: Women | G84: 2029 | H84: =Coverage!Q11 -> 0.1655177 | I84: =IF(Assumptions!$B$19=1,MAX(H84,Coverage!Q12),Coverage!Q12) -> 0.1655177 | J84: =IF(Assumptions!$B$19=1,MAX(H84,Coverage!Q13),Coverage!Q13) -> 0.4165 | K84: =IF(G84<=Assumptions!$B$4,H84+(I84-H84)*(G84-Assumptions!$B$2)/(Assumptions!$B$4-Assumptions!$B$2),IF(G84<=Assumptions!$B$5,I84+(J84-I84)*(G84-Assumptions!$B$4)/(Assumptions!$B$5-Assumptions!$B$4),J84)) -> 0.1655177 | L84: =H84 -> 0.1655177 | M84: =K84-K83 -> 0 | N84: Scale to 70-30-30 | O84: Piecewise linear scale-up; hold after 2040 | P84: =IF(OR(K84<0,K84>1,M84<0),"BAD","OK") -> OK
A85: I_T2D_TREATMENT_Women_2030 | B85: S_70_30_30_TO_70_70_70 | C85: I_T2D_TREATMENT | D85: Longitudinal treatment of type 2 diabetes | E85: RF_T2D | F85: Women | G85: 2030 | H85: =Coverage!Q11 -> 0.1655177 | I85: =IF(Assumptions!$B$19=1,MAX(H85,Coverage!Q12),Coverage!Q12) -> 0.1655177 | J85: =IF(Assumptions!$B$19=1,MAX(H85,Coverage!Q13),Coverage!Q13) -> 0.4165 | K85: =IF(G85<=Assumptions!$B$4,H85+(I85-H85)*(G85-Assumptions!$B$2)/(Assumptions!$B$4-Assumptions!$B$2),IF(G85<=Assumptions!$B$5,I85+(J85-I85)*(G85-Assumptions!$B$4)/(Assumptions!$B$5-Assumptions!$B$4),J85)) -> 0.1655177 | L85: =H85 -> 0.1655177 | M85: =K85-K84 -> 0 | N85: Scale to 70-30-30 | O85: Piecewise linear scale-up; hold after 2040 | P85: =IF(OR(K85<0,K85>1,M85<0),"BAD","OK") -> OK
A86: I_T2D_TREATMENT_Women_2031 | B86: S_70_30_30_TO_70_70_70 | C86: I_T2D_TREATMENT | D86: Longitudinal treatment of type 2 diabetes | E86: RF_T2D | F86: Women | G86: 2031 | H86: =Coverage!Q11 -> 0.1655177 | I86: =IF(Assumptions!$B$19=1,MAX(H86,Coverage!Q12),Coverage!Q12) -> 0.1655177 | J86: =IF(Assumptions!$B$19=1,MAX(H86,Coverage!Q13),Coverage!Q13) -> 0.4165 | K86: =IF(G86<=Assumptions!$B$4,H86+(I86-H86)*(G86-Assumptions!$B$2)/(Assumptions!$B$4-Assumptions!$B$2),IF(G86<=Assumptions!$B$5,I86+(J86-I86)*(G86-Assumptions!$B$4)/(Assumptions!$B$5-Assumptions!$B$4),J86)) -> 0.19061593 | L86: =H86 -> 0.1655177 | M86: =K86-K85 -> 0.02509823 | N86: Scale to 70-70-70 | O86: Piecewise linear scale-up; hold after 2040 | P86: =IF(OR(K86<0,K86>1,M86<0),"BAD","OK") -> OK
A87: I_T2D_TREATMENT_Women_2032 | B87: S_70_30_30_TO_70_70_70 | C87: I_T2D_TREATMENT | D87: Longitudinal treatment of type 2 diabetes | E87: RF_T2D | F87: Women | G87: 2032 | H87: =Coverage!Q11 -> 0.1655177 | I87: =IF(Assumptions!$B$19=1,MAX(H87,Coverage!Q12),Coverage!Q12) -> 0.1655177 | J87: =IF(Assumptions!$B$19=1,MAX(H87,Coverage!Q13),Coverage!Q13) -> 0.4165 | K87: =IF(G87<=Assumptions!$B$4,H87+(I87-H87)*(G87-Assumptions!$B$2)/(Assumptions!$B$4-Assumptions!$B$2),IF(G87<=Assumptions!$B$5,I87+(J87-I87)*(G87-Assumptions!$B$4)/(Assumptions!$B$5-Assumptions!$B$4),J87)) -> 0.21571416 | L87: =H87 -> 0.1655177 | M87: =K87-K86 -> 0.02509823 | N87: Scale to 70-70-70 | O87: Piecewise linear scale-up; hold after 2040 | P87: =IF(OR(K87<0,K87>1,M87<0),"BAD","OK") -> OK
A88: I_T2D_TREATMENT_Women_2033 | B88: S_70_30_30_TO_70_70_70 | C88: I_T2D_TREATMENT | D88: Longitudinal treatment of type 2 diabetes | E88: RF_T2D | F88: Women | G88: 2033 | H88: =Coverage!Q11 -> 0.1655177 | I88: =IF(Assumptions!$B$19=1,MAX(H88,Coverage!Q12),Coverage!Q12) -> 0.1655177 | J88: =IF(Assumptions!$B$19=1,MAX(H88,Coverage!Q13),Coverage!Q13) -> 0.4165 | K88: =IF(G88<=Assumptions!$B$4,H88+(I88-H88)*(G88-Assumptions!$B$2)/(Assumptions!$B$4-Assumptions!$B$2),IF(G88<=Assumptions!$B$5,I88+(J88-I88)*(G88-Assumptions!$B$4)/(Assumptions!$B$5-Assumptions!$B$4),J88)) -> 0.24081239 | L88: =H88 -> 0.1655177 | M88: =K88-K87 -> 0.02509823 | N88: Scale to 70-70-70 | O88: Piecewise linear scale-up; hold after 2040 | P88: =IF(OR(K88<0,K88>1,M88<0),"BAD","OK") -> OK
A89: I_T2D_TREATMENT_Women_2034 | B89: S_70_30_30_TO_70_70_70 | C89: I_T2D_TREATMENT | D89: Longitudinal treatment of type 2 diabetes | E89: RF_T2D | F89: Women | G89: 2034 | H89: =Coverage!Q11 -> 0.1655177 | I89: =IF(Assumptions!$B$19=1,MAX(H89,Coverage!Q12),Coverage!Q12) -> 0.1655177 | J89: =IF(Assumptions!$B$19=1,MAX(H89,Coverage!Q13),Coverage!Q13) -> 0.4165 | K89: =IF(G89<=Assumptions!$B$4,H89+(I89-H89)*(G89-Assumptions!$B$2)/(Assumptions!$B$4-Assumptions!$B$2),IF(G89<=Assumptions!$B$5,I89+(J89-I89)*(G89-Assumptions!$B$4)/(Assumptions!$B$5-Assumptions!$B$4),J89)) -> 0.26591062 | L89: =H89 -> 0.1655177 | M89: =K89-K88 -> 0.02509823 | N89: Scale to 70-70-70 | O89: Piecewise linear scale-up; hold after 2040 | P89: =IF(OR(K89<0,K89>1,M89<0),"BAD","OK") -> OK
A90: I_T2D_TREATMENT_Women_2035 | B90: S_70_30_30_TO_70_70_70 | C90: I_T2D_TREATMENT | D90: Longitudinal treatment of type 2 diabetes | E90: RF_T2D | F90: Women | G90: 2035 | H90: =Coverage!Q11 -> 0.1655177 | I90: =IF(Assumptions!$B$19=1,MAX(H90,Coverage!Q12),Coverage!Q12) -> 0.1655177 | J90: =IF(Assumptions!$B$19=1,MAX(H90,Coverage!Q13),Coverage!Q13) -> 0.4165 | K90: =IF(G90<=Assumptions!$B$4,H90+(I90-H90)*(G90-Assumptions!$B$2)/(Assumptions!$B$4-Assumptions!$B$2),IF(G90<=Assumptions!$B$5,I90+(J90-I90)*(G90-Assumptions!$B$4)/(Assumptions!$B$5-Assumptions!$B$4),J90)) -> 0.29100885 | L90: =H90 -> 0.1655177 | M90: =K90-K89 -> 0.02509823 | N90: Scale to 70-70-70 | O90: Piecewise linear scale-up; hold after 2040 | P90: =IF(OR(K90<0,K90>1,M90<0),"BAD","OK") -> OK
A91: I_T2D_TREATMENT_Women_2036 | B91: S_70_30_30_TO_70_70_70 | C91: I_T2D_TREATMENT | D91: Longitudinal treatment of type 2 diabetes | E91: RF_T2D | F91: Women | G91: 2036 | H91: =Coverage!Q11 -> 0.1655177 | I91: =IF(Assumptions!$B$19=1,MAX(H91,Coverage!Q12),Coverage!Q12) -> 0.1655177 | J91: =IF(Assumptions!$B$19=1,MAX(H91,Coverage!Q13),Coverage!Q13) -> 0.4165 | K91: =IF(G91<=Assumptions!$B$4,H91+(I91-H91)*(G91-Assumptions!$B$2)/(Assumptions!$B$4-Assumptions!$B$2),IF(G91<=Assumptions!$B$5,I91+(J91-I91)*(G91-Assumptions!$B$4)/(Assumptions!$B$5-Assumptions!$B$4),J91)) -> 0.31610708 | L91: =H91 -> 0.1655177 | M91: =K91-K90 -> 0.02509823 | N91: Scale to 70-70-70 | O91: Piecewise linear scale-up; hold after 2040 | P91: =IF(OR(K91<0,K91>1,M91<0),"BAD","OK") -> OK
A92: I_T2D_TREATMENT_Women_2037 | B92: S_70_30_30_TO_70_70_70 | C92: I_T2D_TREATMENT | D92: Longitudinal treatment of type 2 diabetes | E92: RF_T2D | F92: Women | G92: 2037 | H92: =Coverage!Q11 -> 0.1655177 | I92: =IF(Assumptions!$B$19=1,MAX(H92,Coverage!Q12),Coverage!Q12) -> 0.1655177 | J92: =IF(Assumptions!$B$19=1,MAX(H92,Coverage!Q13),Coverage!Q13) -> 0.4165 | K92: =IF(G92<=Assumptions!$B$4,H92+(I92-H92)*(G92-Assumptions!$B$2)/(Assumptions!$B$4-Assumptions!$B$2),IF(G92<=Assumptions!$B$5,I92+(J92-I92)*(G92-Assumptions!$B$4)/(Assumptions!$B$5-Assumptions!$B$4),J92)) -> 0.34120531 | L92: =H92 -> 0.1655177 | M92: =K92-K91 -> 0.02509823 | N92: Scale to 70-70-70 | O92: Piecewise linear scale-up; hold after 2040 | P92: =IF(OR(K92<0,K92>1,M92<0),"BAD","OK") -> OK
A93: I_T2D_TREATMENT_Women_2038 | B93: S_70_30_30_TO_70_70_70 | C93: I_T2D_TREATMENT | D93: Longitudinal treatment of type 2 diabetes | E93: RF_T2D | F93: Women | G93: 2038 | H93: =Coverage!Q11 -> 0.1655177 | I93: =IF(Assumptions!$B$19=1,MAX(H93,Coverage!Q12),Coverage!Q12) -> 0.1655177 | J93: =IF(Assumptions!$B$19=1,MAX(H93,Coverage!Q13),Coverage!Q13) -> 0.4165 | K93: =IF(G93<=Assumptions!$B$4,H93+(I93-H93)*(G93-Assumptions!$B$2)/(Assumptions!$B$4-Assumptions!$B$2),IF(G93<=Assumptions!$B$5,I93+(J93-I93)*(G93-Assumptions!$B$4)/(Assumptions!$B$5-Assumptions!$B$4),J93)) -> 0.36630354 | L93: =H93 -> 0.1655177 | M93: =K93-K92 -> 0.02509823 | N93: Scale to 70-70-70 | O93: Piecewise linear scale-up; hold after 2040 | P93: =IF(OR(K93<0,K93>1,M93<0),"BAD","OK") -> OK
A94: I_T2D_TREATMENT_Women_2039 | B94: S_70_30_30_TO_70_70_70 | C94: I_T2D_TREATMENT | D94: Longitudinal treatment of type 2 diabetes | E94: RF_T2D | F94: Women | G94: 2039 | H94: =Coverage!Q11 -> 0.1655177 | I94: =IF(Assumptions!$B$19=1,MAX(H94,Coverage!Q12),Coverage!Q12) -> 0.1655177 | J94: =IF(Assumptions!$B$19=1,MAX(H94,Coverage!Q13),Coverage!Q13) -> 0.4165 | K94: =IF(G94<=Assumptions!$B$4,H94+(I94-H94)*(G94-Assumptions!$B$2)/(Assumptions!$B$4-Assumptions!$B$2),IF(G94<=Assumptions!$B$5,I94+(J94-I94)*(G94-Assumptions!$B$4)/(Assumptions!$B$5-Assumptions!$B$4),J94)) -> 0.39140177 | L94: =H94 -> 0.1655177 | M94: =K94-K93 -> 0.02509823 | N94: Scale to 70-70-70 | O94: Piecewise linear scale-up; hold after 2040 | P94: =IF(OR(K94<0,K94>1,M94<0),"BAD","OK") -> OK
A95: I_T2D_TREATMENT_Women_2040 | B95: S_70_30_30_TO_70_70_70 | C95: I_T2D_TREATMENT | D95: Longitudinal treatment of type 2 diabetes | E95: RF_T2D | F95: Women | G95: 2040 | H95: =Coverage!Q11 -> 0.1655177 | I95: =IF(Assumptions!$B$19=1,MAX(H95,Coverage!Q12),Coverage!Q12) -> 0.1655177 | J95: =IF(Assumptions!$B$19=1,MAX(H95,Coverage!Q13),Coverage!Q13) -> 0.4165 | K95: =IF(G95<=Assumptions!$B$4,H95+(I95-H95)*(G95-Assumptions!$B$2)/(Assumptions!$B$4-Assumptions!$B$2),IF(G95<=Assumptions!$B$5,I95+(J95-I95)*(G95-Assumptions!$B$4)/(Assumptions!$B$5-Assumptions!$B$4),J95)) -> 0.4165 | L95: =H95 -> 0.1655177 | M95: =K95-K94 -> 0.02509823 | N95: Scale to 70-70-70 | O95: Piecewise linear scale-up; hold after 2040 | P95: =IF(OR(K95<0,K95>1,M95<0),"BAD","OK") -> OK
A96: I_T2D_TREATMENT_Women_2041 | B96: S_70_30_30_TO_70_70_70 | C96: I_T2D_TREATMENT | D96: Longitudinal treatment of type 2 diabetes | E96: RF_T2D | F96: Women | G96: 2041 | H96: =Coverage!Q11 -> 0.1655177 | I96: =IF(Assumptions!$B$19=1,MAX(H96,Coverage!Q12),Coverage!Q12) -> 0.1655177 | J96: =IF(Assumptions!$B$19=1,MAX(H96,Coverage!Q13),Coverage!Q13) -> 0.4165 | K96: =IF(G96<=Assumptions!$B$4,H96+(I96-H96)*(G96-Assumptions!$B$2)/(Assumptions!$B$4-Assumptions!$B$2),IF(G96<=Assumptions!$B$5,I96+(J96-I96)*(G96-Assumptions!$B$4)/(Assumptions!$B$5-Assumptions!$B$4),J96)) -> 0.4165 | L96: =H96 -> 0.1655177 | M96: =K96-K95 -> 0 | N96: Maintain 70-70-70 | O96: Piecewise linear scale-up; hold after 2040 | P96: =IF(OR(K96<0,K96>1,M96<0),"BAD","OK") -> OK
A97: I_T2D_TREATMENT_Women_2042 | B97: S_70_30_30_TO_70_70_70 | C97: I_T2D_TREATMENT | D97: Longitudinal treatment of type 2 diabetes | E97: RF_T2D | F97: Women | G97: 2042 | H97: =Coverage!Q11 -> 0.1655177 | I97: =IF(Assumptions!$B$19=1,MAX(H97,Coverage!Q12),Coverage!Q12) -> 0.1655177 | J97: =IF(Assumptions!$B$19=1,MAX(H97,Coverage!Q13),Coverage!Q13) -> 0.4165 | K97: =IF(G97<=Assumptions!$B$4,H97+(I97-H97)*(G97-Assumptions!$B$2)/(Assumptions!$B$4-Assumptions!$B$2),IF(G97<=Assumptions!$B$5,I97+(J97-I97)*(G97-Assumptions!$B$4)/(Assumptions!$B$5-Assumptions!$B$4),J97)) -> 0.4165 | L97: =H97 -> 0.1655177 | M97: =K97-K96 -> 0 | N97: Maintain 70-70-70 | O97: Piecewise linear scale-up; hold after 2040 | P97: =IF(OR(K97<0,K97>1,M97<0),"BAD","OK") -> OK
A98: I_T2D_TREATMENT_Women_2043 | B98: S_70_30_30_TO_70_70_70 | C98: I_T2D_TREATMENT | D98: Longitudinal treatment of type 2 diabetes | E98: RF_T2D | F98: Women | G98: 2043 | H98: =Coverage!Q11 -> 0.1655177 | I98: =IF(Assumptions!$B$19=1,MAX(H98,Coverage!Q12),Coverage!Q12) -> 0.1655177 | J98: =IF(Assumptions!$B$19=1,MAX(H98,Coverage!Q13),Coverage!Q13) -> 0.4165 | K98: =IF(G98<=Assumptions!$B$4,H98+(I98-H98)*(G98-Assumptions!$B$2)/(Assumptions!$B$4-Assumptions!$B$2),IF(G98<=Assumptions!$B$5,I98+(J98-I98)*(G98-Assumptions!$B$4)/(Assumptions!$B$5-Assumptions!$B$4),J98)) -> 0.4165 | L98: =H98 -> 0.1655177 | M98: =K98-K97 -> 0 | N98: Maintain 70-70-70 | O98: Piecewise linear scale-up; hold after 2040 | P98: =IF(OR(K98<0,K98>1,M98<0),"BAD","OK") -> OK
A99: I_T2D_TREATMENT_Women_2044 | B99: S_70_30_30_TO_70_70_70 | C99: I_T2D_TREATMENT | D99: Longitudinal treatment of type 2 diabetes | E99: RF_T2D | F99: Women | G99: 2044 | H99: =Coverage!Q11 -> 0.1655177 | I99: =IF(Assumptions!$B$19=1,MAX(H99,Coverage!Q12),Coverage!Q12) -> 0.1655177 | J99: =IF(Assumptions!$B$19=1,MAX(H99,Coverage!Q13),Coverage!Q13) -> 0.4165 | K99: =IF(G99<=Assumptions!$B$4,H99+(I99-H99)*(G99-Assumptions!$B$2)/(Assumptions!$B$4-Assumptions!$B$2),IF(G99<=Assumptions!$B$5,I99+(J99-I99)*(G99-Assumptions!$B$4)/(Assumptions!$B$5-Assumptions!$B$4),J99)) -> 0.4165 | L99: =H99 -> 0.1655177 | M99: =K99-K98 -> 0 | N99: Maintain 70-70-70 | O99: Piecewise linear scale-up; hold after 2040 | P99: =IF(OR(K99<0,K99>1,M99<0),"BAD","OK") -> OK
A100: I_T2D_TREATMENT_Women_2045 | B100: S_70_30_30_TO_70_70_70 | C100: I_T2D_TREATMENT | D100: Longitudinal treatment of type 2 diabetes | E100: RF_T2D | F100: Women | G100: 2045 | H100: =Coverage!Q11 -> 0.1655177 | I100: =IF(Assumptions!$B$19=1,MAX(H100,Coverage!Q12),Coverage!Q12) -> 0.1655177 | J100: =IF(Assumptions!$B$19=1,MAX(H100,Coverage!Q13),Coverage!Q13) -> 0.4165 | K100: =IF(G100<=Assumptions!$B$4,H100+(I100-H100)*(G100-Assumptions!$B$2)/(Assumptions!$B$4-Assumptions!$B$2),IF(G100<=Assumptions!$B$5,I100+(J100-I100)*(G100-Assumptions!$B$4)/(Assumptions!$B$5-Assumptions!$B$4),J100)) -> 0.4165 | L100: =H100 -> 0.1655177 | M100: =K100-K99 -> 0 | N100: Maintain 70-70-70 | O100: Piecewise linear scale-up; hold after 2040 | P100: =IF(OR(K100<0,K100>1,M100<0),"BAD","OK") -> OK
...

Sheet Cost_Components
A1: cost_record_id | B1: cost_component_key | C1: cost_option | D1: selected_for_base_case | E1: intervention_id | F1: cause_id | G1: cost_join_key | H1: intervention_name | I1: cause_name | J1: cost_component | K1: population_in_need_measure | L1: population_in_need_fraction | M1: cost_unit | N1: frequency_per_year | O1: age_start | P1: age_stop | Q1: sex | R1: platform | S1: unit_cost_usd | T1: price_year | U1: indonesia_adjusted_flag | V1: source_country | W1: source_file | X1: source_row | Y1: review_status | Z1: notes | AA1: map_match_count | AB1: selection_count | AC1: qa_status
A2: COST_PRIMARY_SCREEN_A | B2: CC_PRIMARY_SCREENING | C2: Option A (selected) | D2: 0 | E2: I_CVD_PRIMARY | F2: C_SHARED | G2: I_CVD_PRIMARY__C_SHARED | H2: Primary prevention of CVD | I2: Shared primary CVD cost | J2: CVD targeted screening | K2: all | L2: 0.2 | M2: USD per eligible person-year | N2: 1 | O2: 30 | P2: 95 | Q2: Both | R2: Health center | S2: 1.291584 | T2: 2023 | U2: 1 | V2: Tanzania | W2: indonesia_model_inputs(7).xlsx | X2: Cost_Components row 4 | Y2: Review | Z2: Lower salary-adjustment option; confirm selection | AA2: =COUNTIF(Intervention_Cause_Map!$J$2:$J$7,G2) -> 4 | AB2: =SUMIF($B$2:$B$8,B2,$D$2:$D$8) -> 1 | AC2: =IF(AA2<1,"BAD KEY",IF(S2="","MISSING COST",IF(U2=0,"REVIEW ADJUSTMENT",IF(AB2<>1,"CHECK SELECTION","OK")))) -> OK
A3: COST_PRIMARY_SCREEN_B | B3: CC_PRIMARY_SCREENING | C3: Option B | D3: 1 | E3: I_CVD_PRIMARY | F3: C_SHARED | G3: I_CVD_PRIMARY__C_SHARED | H3: Primary prevention of CVD | I3: Shared primary CVD cost | J3: CVD targeted screening | K3: all | L3: 0.2 | M3: USD per eligible person-year | N3: 1 | O3: 30 | P3: 95 | Q3: Both | R3: Health center | S3: 2.766522 | T3: 2023 | U3: 1 | V3: Tanzania | W3: indonesia_model_inputs(7).xlsx | X3: Cost_Components row 5 | Y3: Alternative | Z3: Alternative salary-adjustment option | AA3: =COUNTIF(Intervention_Cause_Map!$J$2:$J$7,G3) -> 4 | AB3: =SUMIF($B$2:$B$8,B3,$D$2:$D$8) -> 1 | AC3: =IF(AA3<1,"BAD KEY",IF(S3="","MISSING COST",IF(U3=0,"REVIEW ADJUSTMENT",IF(AB3<>1,"CHECK SELECTION","OK")))) -> OK
A4: COST_PRIMARY_TX_A | B4: CC_PRIMARY_HTN_STATIN | C4: Option A (selected) | D4: 0 | E4: I_CVD_PRIMARY | F4: C_SHARED | G4: I_CVD_PRIMARY__C_SHARED | H4: Primary prevention of CVD | I4: Shared primary CVD cost | J4: Antihypertensives and statins for absolute CVD risk >20% | K4: all | L4: 0.06 | M4: USD per eligible person-year | N4: 1 | O4: 30 | P4: 95 | Q4: Both | R4: Health center | S4: 22.2296 | T4: 2023 | U4: 1 | V4: Tanzania | W4: indonesia_model_inputs(7).xlsx | X4: Cost_Components row 6 | Y4: Review | Z4: Lower salary-adjustment option; confirm selection | AA4: =COUNTIF(Intervention_Cause_Map!$J$2:$J$7,G4) -> 4 | AB4: =SUMIF($B$2:$B$8,B4,$D$2:$D$8) -> 1 | AC4: =IF(AA4<1,"BAD KEY",IF(S4="","MISSING COST",IF(U4=0,"REVIEW ADJUSTMENT",IF(AB4<>1,"CHECK SELECTION","OK")))) -> OK
A5: COST_PRIMARY_TX_B | B5: CC_PRIMARY_HTN_STATIN | C5: Option B | D5: 1 | E5: I_CVD_PRIMARY | F5: C_SHARED | G5: I_CVD_PRIMARY__C_SHARED | H5: Primary prevention of CVD | I5: Shared primary CVD cost | J5: Antihypertensives and statins for absolute CVD risk >20% | K5: all | L5: 0.06 | M5: USD per eligible person-year | N5: 1 | O5: 30 | P5: 95 | Q5: Both | R5: Health center | S5: 40.487719 | T5: 2023 | U5: 1 | V5: Tanzania | W5: indonesia_model_inputs(7).xlsx | X5: Cost_Components row 7 | Y5: Alternative | Z5: Alternative salary-adjustment option | AA5: =COUNTIF(Intervention_Cause_Map!$J$2:$J$7,G5) -> 4 | AB5: =SUMIF($B$2:$B$8,B5,$D$2:$D$8) -> 1 | AC5: =IF(AA5<1,"BAD KEY",IF(S5="","MISSING COST",IF(U5=0,"REVIEW ADJUSTMENT",IF(AB5<>1,"CHECK SELECTION","OK")))) -> OK
A6: COST_T2D_SCREEN | B6: CC_T2D_SCREENING | C6: Base | D6: 1 | E6: I_T2D_TREATMENT | F6: C_T2D | G6: I_T2D_TREATMENT__C_T2D | H6: Longitudinal treatment of type 2 diabetes | I6: Shared diabetes cost | J6: Diabetes opportunistic screening | K6: all | L6: 1e-05 | M6: 2023 USD per eligible person-year | N6: 1 | O6: 30 | P6: 95 | Q6: Both | R6: Health center | S6: 0.70495848 | T6: 2023 | U6: 1 | V6: India adjusted to Indonesia | W6: cvd_unit_cost_indonesia_1_dm(1).xlsx | X6: cvd_unit_cost_indonesia row 50 | Y6: Ready | Z6: Matched to the all-population diabetes screening row in the updated PIN file | AA6: =COUNTIF(Intervention_Cause_Map!$J$2:$J$7,G6) -> 2 | AB6: =SUMIF($B$2:$B$8,B6,$D$2:$D$8) -> 1 | AC6: =IF(AA6<1,"BAD KEY",IF(S6="","MISSING COST",IF(U6=0,"REVIEW ADJUSTMENT",IF(AB6<>1,"CHECK SELECTION","OK")))) -> OK
A7: COST_T2D_NONINSULIN | B7: CC_T2D_NONINSULIN | C7: Base | D7: 1 | E7: I_T2D_TREATMENT | F7: C_T2D | G7: I_T2D_TREATMENT__C_T2D | H7: Longitudinal treatment of type 2 diabetes | I7: Diabetes mellitus type 2 | J7: Diabetes management, non insulin dependent | K7: prevalence | L7: 0.6 | M7: 2023 USD per patient-year | N7: 1 | O7: 30 | P7: 95 | Q7: Both | R7: Health center | S7: =752.576232260719*0.3 -> 225.77287 | T7: 2023 | U7: 1 | V7: Bangladesh adjusted to Indonesia | W7: cvd_unit_cost_indonesia_1_dm(1).xlsx | X7: cvd_unit_cost_indonesia row 51 | Y7: Ready | Z7: Matched by treated population and cost magnitude to the non-insulin component in the updated PIN file | AA7: =COUNTIF(Intervention_Cause_Map!$J$2:$J$7,G7) -> 2 | AB7: =SUMIF($B$2:$B$8,B7,$D$2:$D$8) -> 1 | AC7: =IF(AA7<1,"BAD KEY",IF(S7="","MISSING COST",IF(U7=0,"REVIEW ADJUSTMENT",IF(AB7<>1,"CHECK SELECTION","OK")))) -> OK
A8: COST_T2D_INSULIN | B8: CC_T2D_INSULIN | C8: Base | D8: 1 | E8: I_T2D_TREATMENT | F8: C_T2D | G8: I_T2D_TREATMENT__C_T2D | H8: Longitudinal treatment of type 2 diabetes | I8: Diabetes mellitus type 2 | J8: Diabetes management, insulin dependent | K8: prevalence | L8: 0.2 | M8: 2023 USD per patient-year | N8: 1 | O8: 30 | P8: 95 | Q8: Both | R8: Health center | S8: =1154.03552166169*0.3 -> 346.21066 | T8: 2023 | U8: 1 | V8: Bangladesh adjusted to Indonesia | W8: cvd_unit_cost_indonesia_1_dm(1).xlsx | X8: cvd_unit_cost_indonesia row 52 | Y8: Ready | Z8: Matched by treated population and cost magnitude to the insulin component in the updated PIN file | AA8: =COUNTIF(Intervention_Cause_Map!$J$2:$J$7,G8) -> 2 | AB8: =SUMIF($B$2:$B$8,B8,$D$2:$D$8) -> 1 | AC8: =IF(AA8<1,"BAD KEY",IF(S8="","MISSING COST",IF(U8=0,"REVIEW ADJUSTMENT",IF(AB8<>1,"CHECK SELECTION","OK")))) -> OK

Sheet Model_Input_View
A1: effect_run_id | B1: intervention_cause_key | C1: intervention_id | D1: intervention_name | E1: cause_id | F1: cause_name | G1: sex | H1: year | I1: transition_from | J1: transition_to | K1: effect_value | L1: affected_fraction | M1: baseline_effective_coverage | N1: scenario_effective_coverage | O1: coverage_increase | P1: fairchoices_adjusted_effect | Q1: adjusted_effect_on_transition | R1: transition_multiplier | S1: source | T1: qa_status
A2: I_CVD_PRIMARY__C_IHD_Men_2025 | B2: I_CVD_PRIMARY__C_IHD | C2: I_CVD_PRIMARY | D2: Primary prevention of CVD | E2: C_IHD | F2: Ischemic heart disease | G2: Men | H2: 2025 | I2: well | J2: sick | K2: =Effect_Sizes!J2 -> 0.58 | L2: =Effect_Sizes!K2 -> 0.8 | M2: =Coverage_Trajectory!H2 -> 0.094852977 | N2: =Coverage_Trajectory!K2 -> 0.094852977 | O2: =N2-M2 -> 0 | P2: =IF(O2=0,0,K2*O2/(1-K2*M2)) -> 0 | Q2: =P2*L2 -> 0 | R2: =1-Q2 -> 1 | S2: taxonomy_effect_size.xlsx, Sheet 1, row 136 | T2: =IF(OR(R2<0,R2>1),"BAD","OK") -> OK
A3: I_CVD_PRIMARY__C_IHD_Men_2026 | B3: I_CVD_PRIMARY__C_IHD | C3: I_CVD_PRIMARY | D3: Primary prevention of CVD | E3: C_IHD | F3: Ischemic heart disease | G3: Men | H3: 2026 | I3: well | J3: sick | K3: =Effect_Sizes!J2 -> 0.58 | L3: =Effect_Sizes!K2 -> 0.8 | M3: =Coverage_Trajectory!H3 -> 0.094852977 | N3: =Coverage_Trajectory!K3 -> 0.10318238 | O3: =N3-M3 -> 0.0083294046 | P3: =IF(O3=0,0,K3*O3/(1-K3*M3)) -> 0.0051123069 | Q3: =P3*L3 -> 0.0040898455 | R3: =1-Q3 -> 0.99591015 | S3: taxonomy_effect_size.xlsx, Sheet 1, row 136 | T3: =IF(OR(R3<0,R3>1),"BAD","OK") -> OK
A4: I_CVD_PRIMARY__C_IHD_Men_2027 | B4: I_CVD_PRIMARY__C_IHD | C4: I_CVD_PRIMARY | D4: Primary prevention of CVD | E4: C_IHD | F4: Ischemic heart disease | G4: Men | H4: 2027 | I4: well | J4: sick | K4: =Effect_Sizes!J2 -> 0.58 | L4: =Effect_Sizes!K2 -> 0.8 | M4: =Coverage_Trajectory!H4 -> 0.094852977 | N4: =Coverage_Trajectory!K4 -> 0.11151179 | O4: =N4-M4 -> 0.016658809 | P4: =IF(O4=0,0,K4*O4/(1-K4*M4)) -> 0.010224614 | Q4: =P4*L4 -> 0.008179691 | R4: =1-Q4 -> 0.99182031 | S4: taxonomy_effect_size.xlsx, Sheet 1, row 136 | T4: =IF(OR(R4<0,R4>1),"BAD","OK") -> OK
A5: I_CVD_PRIMARY__C_IHD_Men_2028 | B5: I_CVD_PRIMARY__C_IHD | C5: I_CVD_PRIMARY | D5: Primary prevention of CVD | E5: C_IHD | F5: Ischemic heart disease | G5: Men | H5: 2028 | I5: well | J5: sick | K5: =Effect_Sizes!J2 -> 0.58 | L5: =Effect_Sizes!K2 -> 0.8 | M5: =Coverage_Trajectory!H5 -> 0.094852977 | N5: =Coverage_Trajectory!K5 -> 0.11984119 | O5: =N5-M5 -> 0.024988214 | P5: =IF(O5=0,0,K5*O5/(1-K5*M5)) -> 0.015336921 | Q5: =P5*L5 -> 0.012269536 | R5: =1-Q5 -> 0.98773046 | S5: taxonomy_effect_size.xlsx, Sheet 1, row 136 | T5: =IF(OR(R5<0,R5>1),"BAD","OK") -> OK
A6: I_CVD_PRIMARY__C_IHD_Men_2029 | B6: I_CVD_PRIMARY__C_IHD | C6: I_CVD_PRIMARY | D6: Primary prevention of CVD | E6: C_IHD | F6: Ischemic heart disease | G6: Men | H6: 2029 | I6: well | J6: sick | K6: =Effect_Sizes!J2 -> 0.58 | L6: =Effect_Sizes!K2 -> 0.8 | M6: =Coverage_Trajectory!H6 -> 0.094852977 | N6: =Coverage_Trajectory!K6 -> 0.1281706 | O6: =N6-M6 -> 0.033317619 | P6: =IF(O6=0,0,K6*O6/(1-K6*M6)) -> 0.020449227 | Q6: =P6*L6 -> 0.016359382 | R6: =1-Q6 -> 0.98364062 | S6: taxonomy_effect_size.xlsx, Sheet 1, row 136 | T6: =IF(OR(R6<0,R6>1),"BAD","OK") -> OK
A7: I_CVD_PRIMARY__C_IHD_Men_2030 | B7: I_CVD_PRIMARY__C_IHD | C7: I_CVD_PRIMARY | D7: Primary prevention of CVD | E7: C_IHD | F7: Ischemic heart disease | G7: Men | H7: 2030 | I7: well | J7: sick | K7: =Effect_Sizes!J2 -> 0.58 | L7: =Effect_Sizes!K2 -> 0.8 | M7: =Coverage_Trajectory!H7 -> 0.094852977 | N7: =Coverage_Trajectory!K7 -> 0.1365 | O7: =N7-M7 -> 0.041647023 | P7: =IF(O7=0,0,K7*O7/(1-K7*M7)) -> 0.025561534 | Q7: =P7*L7 -> 0.020449227 | R7: =1-Q7 -> 0.97955077 | S7: taxonomy_effect_size.xlsx, Sheet 1, row 136 | T7: =IF(OR(R7<0,R7>1),"BAD","OK") -> OK
A8: I_CVD_PRIMARY__C_IHD_Men_2031 | B8: I_CVD_PRIMARY__C_IHD | C8: I_CVD_PRIMARY | D8: Primary prevention of CVD | E8: C_IHD | F8: Ischemic heart disease | G8: Men | H8: 2031 | I8: well | J8: sick | K8: =Effect_Sizes!J2 -> 0.58 | L8: =Effect_Sizes!K2 -> 0.8 | M8: =Coverage_Trajectory!H8 -> 0.094852977 | N8: =Coverage_Trajectory!K8 -> 0.1645 | O8: =N8-M8 -> 0.069647023 | P8: =IF(O8=0,0,K8*O8/(1-K8*M8)) -> 0.042746987 | Q8: =P8*L8 -> 0.03419759 | R8: =1-Q8 -> 0.96580241 | S8: taxonomy_effect_size.xlsx, Sheet 1, row 136 | T8: =IF(OR(R8<0,R8>1),"BAD","OK") -> OK
A9: I_CVD_PRIMARY__C_IHD_Men_2032 | B9: I_CVD_PRIMARY__C_IHD | C9: I_CVD_PRIMARY | D9: Primary prevention of CVD | E9: C_IHD | F9: Ischemic heart disease | G9: Men | H9: 2032 | I9: well | J9: sick | K9: =Effect_Sizes!J2 -> 0.58 | L9: =Effect_Sizes!K2 -> 0.8 | M9: =Coverage_Trajectory!H9 -> 0.094852977 | N9: =Coverage_Trajectory!K9 -> 0.1925 | O9: =N9-M9 -> 0.097647023 | P9: =IF(O9=0,0,K9*O9/(1-K9*M9)) -> 0.05993244 | Q9: =P9*L9 -> 0.047945952 | R9: =1-Q9 -> 0.95205405 | S9: taxonomy_effect_size.xlsx, Sheet 1, row 136 | T9: =IF(OR(R9<0,R9>1),"BAD","OK") -> OK
A10: I_CVD_PRIMARY__C_IHD_Men_2033 | B10: I_CVD_PRIMARY__C_IHD | C10: I_CVD_PRIMARY | D10: Primary prevention of CVD | E10: C_IHD | F10: Ischemic heart disease | G10: Men | H10: 2033 | I10: well | J10: sick | K10: =Effect_Sizes!J2 -> 0.58 | L10: =Effect_Sizes!K2 -> 0.8 | M10: =Coverage_Trajectory!H10 -> 0.094852977 | N10: =Coverage_Trajectory!K10 -> 0.2205 | O10: =N10-M10 -> 0.12564702 | P10: =IF(O10=0,0,K10*O10/(1-K10*M10)) -> 0.077117893 | Q10: =P10*L10 -> 0.061694315 | R10: =1-Q10 -> 0.93830569 | S10: taxonomy_effect_size.xlsx, Sheet 1, row 136 | T10: =IF(OR(R10<0,R10>1),"BAD","OK") -> OK
A11: I_CVD_PRIMARY__C_IHD_Men_2034 | B11: I_CVD_PRIMARY__C_IHD | C11: I_CVD_PRIMARY | D11: Primary prevention of CVD | E11: C_IHD | F11: Ischemic heart disease | G11: Men | H11: 2034 | I11: well | J11: sick | K11: =Effect_Sizes!J2 -> 0.58 | L11: =Effect_Sizes!K2 -> 0.8 | M11: =Coverage_Trajectory!H11 -> 0.094852977 | N11: =Coverage_Trajectory!K11 -> 0.2485 | O11: =N11-M11 -> 0.15364702 | P11: =IF(O11=0,0,K11*O11/(1-K11*M11)) -> 0.094303346 | Q11: =P11*L11 -> 0.075442677 | R11: =1-Q11 -> 0.92455732 | S11: taxonomy_effect_size.xlsx, Sheet 1, row 136 | T11: =IF(OR(R11<0,R11>1),"BAD","OK") -> OK
A12: I_CVD_PRIMARY__C_IHD_Men_2035 | B12: I_CVD_PRIMARY__C_IHD | C12: I_CVD_PRIMARY | D12: Primary prevention of CVD | E12: C_IHD | F12: Ischemic heart disease | G12: Men | H12: 2035 | I12: well | J12: sick | K12: =Effect_Sizes!J2 -> 0.58 | L12: =Effect_Sizes!K2 -> 0.8 | M12: =Coverage_Trajectory!H12 -> 0.094852977 | N12: =Coverage_Trajectory!K12 -> 0.2765 | O12: =N12-M12 -> 0.18164702 | P12: =IF(O12=0,0,K12*O12/(1-K12*M12)) -> 0.1114888 | Q12: =P12*L12 -> 0.089191039 | R12: =1-Q12 -> 0.91080896 | S12: taxonomy_effect_size.xlsx, Sheet 1, row 136 | T12: =IF(OR(R12<0,R12>1),"BAD","OK") -> OK
A13: I_CVD_PRIMARY__C_IHD_Men_2036 | B13: I_CVD_PRIMARY__C_IHD | C13: I_CVD_PRIMARY | D13: Primary prevention of CVD | E13: C_IHD | F13: Ischemic heart disease | G13: Men | H13: 2036 | I13: well | J13: sick | K13: =Effect_Sizes!J2 -> 0.58 | L13: =Effect_Sizes!K2 -> 0.8 | M13: =Coverage_Trajectory!H13 -> 0.094852977 | N13: =Coverage_Trajectory!K13 -> 0.3045 | O13: =N13-M13 -> 0.20964702 | P13: =IF(O13=0,0,K13*O13/(1-K13*M13)) -> 0.12867425 | Q13: =P13*L13 -> 0.1029394 | R13: =1-Q13 -> 0.8970606 | S13: taxonomy_effect_size.xlsx, Sheet 1, row 136 | T13: =IF(OR(R13<0,R13>1),"BAD","OK") -> OK
A14: I_CVD_PRIMARY__C_IHD_Men_2037 | B14: I_CVD_PRIMARY__C_IHD | C14: I_CVD_PRIMARY | D14: Primary prevention of CVD | E14: C_IHD | F14: Ischemic heart disease | G14: Men | H14: 2037 | I14: well | J14: sick | K14: =Effect_Sizes!J2 -> 0.58 | L14: =Effect_Sizes!K2 -> 0.8 | M14: =Coverage_Trajectory!H14 -> 0.094852977 | N14: =Coverage_Trajectory!K14 -> 0.3325 | O14: =N14-M14 -> 0.23764702 | P14: =IF(O14=0,0,K14*O14/(1-K14*M14)) -> 0.14585971 | Q14: =P14*L14 -> 0.11668776 | R14: =1-Q14 -> 0.88331224 | S14: taxonomy_effect_size.xlsx, Sheet 1, row 136 | T14: =IF(OR(R14<0,R14>1),"BAD","OK") -> OK
A15: I_CVD_PRIMARY__C_IHD_Men_2038 | B15: I_CVD_PRIMARY__C_IHD | C15: I_CVD_PRIMARY | D15: Primary prevention of CVD | E15: C_IHD | F15: Ischemic heart disease | G15: Men | H15: 2038 | I15: well | J15: sick | K15: =Effect_Sizes!J2 -> 0.58 | L15: =Effect_Sizes!K2 -> 0.8 | M15: =Coverage_Trajectory!H15 -> 0.094852977 | N15: =Coverage_Trajectory!K15 -> 0.3605 | O15: =N15-M15 -> 0.26564702 | P15: =IF(O15=0,0,K15*O15/(1-K15*M15)) -> 0.16304516 | Q15: =P15*L15 -> 0.13043613 | R15: =1-Q15 -> 0.86956387 | S15: taxonomy_effect_size.xlsx, Sheet 1, row 136 | T15: =IF(OR(R15<0,R15>1),"BAD","OK") -> OK
A16: I_CVD_PRIMARY__C_IHD_Men_2039 | B16: I_CVD_PRIMARY__C_IHD | C16: I_CVD_PRIMARY | D16: Primary prevention of CVD | E16: C_IHD | F16: Ischemic heart disease | G16: Men | H16: 2039 | I16: well | J16: sick | K16: =Effect_Sizes!J2 -> 0.58 | L16: =Effect_Sizes!K2 -> 0.8 | M16: =Coverage_Trajectory!H16 -> 0.094852977 | N16: =Coverage_Trajectory!K16 -> 0.3885 | O16: =N16-M16 -> 0.29364702 | P16: =IF(O16=0,0,K16*O16/(1-K16*M16)) -> 0.18023061 | Q16: =P16*L16 -> 0.14418449 | R16: =1-Q16 -> 0.85581551 | S16: taxonomy_effect_size.xlsx, Sheet 1, row 136 | T16: =IF(OR(R16<0,R16>1),"BAD","OK") -> OK
A17: I_CVD_PRIMARY__C_IHD_Men_2040 | B17: I_CVD_PRIMARY__C_IHD | C17: I_CVD_PRIMARY | D17: Primary prevention of CVD | E17: C_IHD | F17: Ischemic heart disease | G17: Men | H17: 2040 | I17: well | J17: sick | K17: =Effect_Sizes!J2 -> 0.58 | L17: =Effect_Sizes!K2 -> 0.8 | M17: =Coverage_Trajectory!H17 -> 0.094852977 | N17: =Coverage_Trajectory!K17 -> 0.4165 | O17: =N17-M17 -> 0.32164702 | P17: =IF(O17=0,0,K17*O17/(1-K17*M17)) -> 0.19741606 | Q17: =P17*L17 -> 0.15793285 | R17: =1-Q17 -> 0.84206715 | S17: taxonomy_effect_size.xlsx, Sheet 1, row 136 | T17: =IF(OR(R17<0,R17>1),"BAD","OK") -> OK
A18: I_CVD_PRIMARY__C_IHD_Men_2041 | B18: I_CVD_PRIMARY__C_IHD | C18: I_CVD_PRIMARY | D18: Primary prevention of CVD | E18: C_IHD | F18: Ischemic heart disease | G18: Men | H18: 2041 | I18: well | J18: sick | K18: =Effect_Sizes!J2 -> 0.58 | L18: =Effect_Sizes!K2 -> 0.8 | M18: =Coverage_Trajectory!H18 -> 0.094852977 | N18: =Coverage_Trajectory!K18 -> 0.4165 | O18: =N18-M18 -> 0.32164702 | P18: =IF(O18=0,0,K18*O18/(1-K18*M18)) -> 0.19741606 | Q18: =P18*L18 -> 0.15793285 | R18: =1-Q18 -> 0.84206715 | S18: taxonomy_effect_size.xlsx, Sheet 1, row 136 | T18: =IF(OR(R18<0,R18>1),"BAD","OK") -> OK
A19: I_CVD_PRIMARY__C_IHD_Men_2042 | B19: I_CVD_PRIMARY__C_IHD | C19: I_CVD_PRIMARY | D19: Primary prevention of CVD | E19: C_IHD | F19: Ischemic heart disease | G19: Men | H19: 2042 | I19: well | J19: sick | K19: =Effect_Sizes!J2 -> 0.58 | L19: =Effect_Sizes!K2 -> 0.8 | M19: =Coverage_Trajectory!H19 -> 0.094852977 | N19: =Coverage_Trajectory!K19 -> 0.4165 | O19: =N19-M19 -> 0.32164702 | P19: =IF(O19=0,0,K19*O19/(1-K19*M19)) -> 0.19741606 | Q19: =P19*L19 -> 0.15793285 | R19: =1-Q19 -> 0.84206715 | S19: taxonomy_effect_size.xlsx, Sheet 1, row 136 | T19: =IF(OR(R19<0,R19>1),"BAD","OK") -> OK
A20: I_CVD_PRIMARY__C_IHD_Men_2043 | B20: I_CVD_PRIMARY__C_IHD | C20: I_CVD_PRIMARY | D20: Primary prevention of CVD | E20: C_IHD | F20: Ischemic heart disease | G20: Men | H20: 2043 | I20: well | J20: sick | K20: =Effect_Sizes!J2 -> 0.58 | L20: =Effect_Sizes!K2 -> 0.8 | M20: =Coverage_Trajectory!H20 -> 0.094852977 | N20: =Coverage_Trajectory!K20 -> 0.4165 | O20: =N20-M20 -> 0.32164702 | P20: =IF(O20=0,0,K20*O20/(1-K20*M20)) -> 0.19741606 | Q20: =P20*L20 -> 0.15793285 | R20: =1-Q20 -> 0.84206715 | S20: taxonomy_effect_size.xlsx, Sheet 1, row 136 | T20: =IF(OR(R20<0,R20>1),"BAD","OK") -> OK
A21: I_CVD_PRIMARY__C_IHD_Men_2044 | B21: I_CVD_PRIMARY__C_IHD | C21: I_CVD_PRIMARY | D21: Primary prevention of CVD | E21: C_IHD | F21: Ischemic heart disease | G21: Men | H21: 2044 | I21: well | J21: sick | K21: =Effect_Sizes!J2 -> 0.58 | L21: =Effect_Sizes!K2 -> 0.8 | M21: =Coverage_Trajectory!H21 -> 0.094852977 | N21: =Coverage_Trajectory!K21 -> 0.4165 | O21: =N21-M21 -> 0.32164702 | P21: =IF(O21=0,0,K21*O21/(1-K21*M21)) -> 0.19741606 | Q21: =P21*L21 -> 0.15793285 | R21: =1-Q21 -> 0.84206715 | S21: taxonomy_effect_size.xlsx, Sheet 1, row 136 | T21: =IF(OR(R21<0,R21>1),"BAD","OK") -> OK
A22: I_CVD_PRIMARY__C_IHD_Men_2045 | B22: I_CVD_PRIMARY__C_IHD | C22: I_CVD_PRIMARY | D22: Primary prevention of CVD | E22: C_IHD | F22: Ischemic heart disease | G22: Men | H22: 2045 | I22: well | J22: sick | K22: =Effect_Sizes!J2 -> 0.58 | L22: =Effect_Sizes!K2 -> 0.8 | M22: =Coverage_Trajectory!H22 -> 0.094852977 | N22: =Coverage_Trajectory!K22 -> 0.4165 | O22: =N22-M22 -> 0.32164702 | P22: =IF(O22=0,0,K22*O22/(1-K22*M22)) -> 0.19741606 | Q22: =P22*L22 -> 0.15793285 | R22: =1-Q22 -> 0.84206715 | S22: taxonomy_effect_size.xlsx, Sheet 1, row 136 | T22: =IF(OR(R22<0,R22>1),"BAD","OK") -> OK
A23: I_CVD_PRIMARY__C_IHD_Men_2046 | B23: I_CVD_PRIMARY__C_IHD | C23: I_CVD_PRIMARY | D23: Primary prevention of CVD | E23: C_IHD | F23: Ischemic heart disease | G23: Men | H23: 2046 | I23: well | J23: sick | K23: =Effect_Sizes!J2 -> 0.58 | L23: =Effect_Sizes!K2 -> 0.8 | M23: =Coverage_Trajectory!H23 -> 0.094852977 | N23: =Coverage_Trajectory!K23 -> 0.4165 | O23: =N23-M23 -> 0.32164702 | P23: =IF(O23=0,0,K23*O23/(1-K23*M23)) -> 0.19741606 | Q23: =P23*L23 -> 0.15793285 | R23: =1-Q23 -> 0.84206715 | S23: taxonomy_effect_size.xlsx, Sheet 1, row 136 | T23: =IF(OR(R23<0,R23>1),"BAD","OK") -> OK
A24: I_CVD_PRIMARY__C_IHD_Men_2047 | B24: I_CVD_PRIMARY__C_IHD | C24: I_CVD_PRIMARY | D24: Primary prevention of CVD | E24: C_IHD | F24: Ischemic heart disease | G24: Men | H24: 2047 | I24: well | J24: sick | K24: =Effect_Sizes!J2 -> 0.58 | L24: =Effect_Sizes!K2 -> 0.8 | M24: =Coverage_Trajectory!H24 -> 0.094852977 | N24: =Coverage_Trajectory!K24 -> 0.4165 | O24: =N24-M24 -> 0.32164702 | P24: =IF(O24=0,0,K24*O24/(1-K24*M24)) -> 0.19741606 | Q24: =P24*L24 -> 0.15793285 | R24: =1-Q24 -> 0.84206715 | S24: taxonomy_effect_size.xlsx, Sheet 1, row 136 | T24: =IF(OR(R24<0,R24>1),"BAD","OK") -> OK
A25: I_CVD_PRIMARY__C_IHD_Men_2048 | B25: I_CVD_PRIMARY__C_IHD | C25: I_CVD_PRIMARY | D25: Primary prevention of CVD | E25: C_IHD | F25: Ischemic heart disease | G25: Men | H25: 2048 | I25: well | J25: sick | K25: =Effect_Sizes!J2 -> 0.58 | L25: =Effect_Sizes!K2 -> 0.8 | M25: =Coverage_Trajectory!H25 -> 0.094852977 | N25: =Coverage_Trajectory!K25 -> 0.4165 | O25: =N25-M25 -> 0.32164702 | P25: =IF(O25=0,0,K25*O25/(1-K25*M25)) -> 0.19741606 | Q25: =P25*L25 -> 0.15793285 | R25: =1-Q25 -> 0.84206715 | S25: taxonomy_effect_size.xlsx, Sheet 1, row 136 | T25: =IF(OR(R25<0,R25>1),"BAD","OK") -> OK
A26: I_CVD_PRIMARY__C_IHD_Men_2049 | B26: I_CVD_PRIMARY__C_IHD | C26: I_CVD_PRIMARY | D26: Primary prevention of CVD | E26: C_IHD | F26: Ischemic heart disease | G26: Men | H26: 2049 | I26: well | J26: sick | K26: =Effect_Sizes!J2 -> 0.58 | L26: =Effect_Sizes!K2 -> 0.8 | M26: =Coverage_Trajectory!H26 -> 0.094852977 | N26: =Coverage_Trajectory!K26 -> 0.4165 | O26: =N26-M26 -> 0.32164702 | P26: =IF(O26=0,0,K26*O26/(1-K26*M26)) -> 0.19741606 | Q26: =P26*L26 -> 0.15793285 | R26: =1-Q26 -> 0.84206715 | S26: taxonomy_effect_size.xlsx, Sheet 1, row 136 | T26: =IF(OR(R26<0,R26>1),"BAD","OK") -> OK
A27: I_CVD_PRIMARY__C_IHD_Men_2050 | B27: I_CVD_PRIMARY__C_IHD | C27: I_CVD_PRIMARY | D27: Primary prevention of CVD | E27: C_IHD | F27: Ischemic heart disease | G27: Men | H27: 2050 | I27: well | J27: sick | K27: =Effect_Sizes!J2 -> 0.58 | L27: =Effect_Sizes!K2 -> 0.8 | M27: =Coverage_Trajectory!H27 -> 0.094852977 | N27: =Coverage_Trajectory!K27 -> 0.4165 | O27: =N27-M27 -> 0.32164702 | P27: =IF(O27=0,0,K27*O27/(1-K27*M27)) -> 0.19741606 | Q27: =P27*L27 -> 0.15793285 | R27: =1-Q27 -> 0.84206715 | S27: taxonomy_effect_size.xlsx, Sheet 1, row 136 | T27: =IF(OR(R27<0,R27>1),"BAD","OK") -> OK
A28: I_CVD_PRIMARY__C_IHD_Women_2025 | B28: I_CVD_PRIMARY__C_IHD | C28: I_CVD_PRIMARY | D28: Primary prevention of CVD | E28: C_IHD | F28: Ischemic heart disease | G28: Women | H28: 2025 | I28: well | J28: sick | K28: =Effect_Sizes!J2 -> 0.58 | L28: =Effect_Sizes!K2 -> 0.8 | M28: =Coverage_Trajectory!H28 -> 0.13268074 | N28: =Coverage_Trajectory!K28 -> 0.13268074 | O28: =N28-M28 -> 0 | P28: =IF(O28=0,0,K28*O28/(1-K28*M28)) -> 0 | Q28: =P28*L28 -> 0 | R28: =1-Q28 -> 1 | S28: taxonomy_effect_size.xlsx, Sheet 1, row 136 | T28: =IF(OR(R28<0,R28>1),"BAD","OK") -> OK
A29: I_CVD_PRIMARY__C_IHD_Women_2026 | B29: I_CVD_PRIMARY__C_IHD | C29: I_CVD_PRIMARY | D29: Primary prevention of CVD | E29: C_IHD | F29: Ischemic heart disease | G29: Women | H29: 2026 | I29: well | J29: sick | K29: =Effect_Sizes!J2 -> 0.58 | L29: =Effect_Sizes!K2 -> 0.8 | M29: =Coverage_Trajectory!H29 -> 0.13268074 | N29: =Coverage_Trajectory!K29 -> 0.13344459 | O29: =N29-M29 -> 0.00076385241 | P29: =IF(O29=0,0,K29*O29/(1-K29*M29)) -> 0.00047997044 | Q29: =P29*L29 -> 0.00038397635 | R29: =1-Q29 -> 0.99961602 | S29: taxonomy_effect_size.xlsx, Sheet 1, row 136 | T29: =IF(OR(R29<0,R29>1),"BAD","OK") -> OK
A30: I_CVD_PRIMARY__C_IHD_Women_2027 | B30: I_CVD_PRIMARY__C_IHD | C30: I_CVD_PRIMARY | D30: Primary prevention of CVD | E30: C_IHD | F30: Ischemic heart disease | G30: Women | H30: 2027 | I30: well | J30: sick | K30: =Effect_Sizes!J2 -> 0.58 | L30: =Effect_Sizes!K2 -> 0.8 | M30: =Coverage_Trajectory!H30 -> 0.13268074 | N30: =Coverage_Trajectory!K30 -> 0.13420844 | O30: =N30-M30 -> 0.0015277048 | P30: =IF(O30=0,0,K30*O30/(1-K30*M30)) -> 0.00095994088 | Q30: =P30*L30 -> 0.00076795271 | R30: =1-Q30 -> 0.99923205 | S30: taxonomy_effect_size.xlsx, Sheet 1, row 136 | T30: =IF(OR(R30<0,R30>1),"BAD","OK") -> OK
A31: I_CVD_PRIMARY__C_IHD_Women_2028 | B31: I_CVD_PRIMARY__C_IHD | C31: I_CVD_PRIMARY | D31: Primary prevention of CVD | E31: C_IHD | F31: Ischemic heart disease | G31: Women | H31: 2028 | I31: well | J31: sick | K31: =Effect_Sizes!J2 -> 0.58 | L31: =Effect_Sizes!K2 -> 0.8 | M31: =Coverage_Trajectory!H31 -> 0.13268074 | N31: =Coverage_Trajectory!K31 -> 0.1349723 | O31: =N31-M31 -> 0.0022915572 | P31: =IF(O31=0,0,K31*O31/(1-K31*M31)) -> 0.0014399113 | Q31: =P31*L31 -> 0.0011519291 | R31: =1-Q31 -> 0.99884807 | S31: taxonomy_effect_size.xlsx, Sheet 1, row 136 | T31: =IF(OR(R31<0,R31>1),"BAD","OK") -> OK
A32: I_CVD_PRIMARY__C_IHD_Women_2029 | B32: I_CVD_PRIMARY__C_IHD | C32: I_CVD_PRIMARY | D32: Primary prevention of CVD | E32: C_IHD | F32: Ischemic heart disease | G32: Women | H32: 2029 | I32: well | J32: sick | K32: =Effect_Sizes!J2 -> 0.58 | L32: =Effect_Sizes!K2 -> 0.8 | M32: =Coverage_Trajectory!H32 -> 0.13268074 | N32: =Coverage_Trajectory!K32 -> 0.13573615 | O32: =N32-M32 -> 0.0030554096 | P32: =IF(O32=0,0,K32*O32/(1-K32*M32)) -> 0.0019198818 | Q32: =P32*L32 -> 0.0015359054 | R32: =1-Q32 -> 0.99846409 | S32: taxonomy_effect_size.xlsx, Sheet 1, row 136 | T32: =IF(OR(R32<0,R32>1),"BAD","OK") -> OK
A33: I_CVD_PRIMARY__C_IHD_Women_2030 | B33: I_CVD_PRIMARY__C_IHD | C33: I_CVD_PRIMARY | D33: Primary prevention of CVD | E33: C_IHD | F33: Ischemic heart disease | G33: Women | H33: 2030 | I33: well | J33: sick | K33: =Effect_Sizes!J2 -> 0.58 | L33: =Effect_Sizes!K2 -> 0.8 | M33: =Coverage_Trajectory!H33 -> 0.13268074 | N33: =Coverage_Trajectory!K33 -> 0.1365 | O33: =N33-M33 -> 0.0038192621 | P33: =IF(O33=0,0,K33*O33/(1-K33*M33)) -> 0.0023998522 | Q33: =P33*L33 -> 0.0019198818 | R33: =1-Q33 -> 0.99808012 | S33: taxonomy_effect_size.xlsx, Sheet 1, row 136 | T33: =IF(OR(R33<0,R33>1),"BAD","OK") -> OK
A34: I_CVD_PRIMARY__C_IHD_Women_2031 | B34: I_CVD_PRIMARY__C_IHD | C34: I_CVD_PRIMARY | D34: Primary prevention of CVD | E34: C_IHD | F34: Ischemic heart disease | G34: Women | H34: 2031 | I34: well | J34: sick | K34: =Effect_Sizes!J2 -> 0.58 | L34: =Effect_Sizes!K2 -> 0.8 | M34: =Coverage_Trajectory!H34 -> 0.13268074 | N34: =Coverage_Trajectory!K34 -> 0.1645 | O34: =N34-M34 -> 0.031819262 | P34: =IF(O34=0,0,K34*O34/(1-K34*M34)) -> 0.019993791 | Q34: =P34*L34 -> 0.015995033 | R34: =1-Q34 -> 0.98400497 | S34: taxonomy_effect_size.xlsx, Sheet 1, row 136 | T34: =IF(OR(R34<0,R34>1),"BAD","OK") -> OK
A35: I_CVD_PRIMARY__C_IHD_Women_2032 | B35: I_CVD_PRIMARY__C_IHD | C35: I_CVD_PRIMARY | D35: Primary prevention of CVD | E35: C_IHD | F35: Ischemic heart disease | G35: Women | H35: 2032 | I35: well | J35: sick | K35: =Effect_Sizes!J2 -> 0.58 | L35: =Effect_Sizes!K2 -> 0.8 | M35: =Coverage_Trajectory!H35 -> 0.13268074 | N35: =Coverage_Trajectory!K35 -> 0.1925 | O35: =N35-M35 -> 0.059819262 | P35: =IF(O35=0,0,K35*O35/(1-K35*M35)) -> 0.037587729 | Q35: =P35*L35 -> 0.030070183 | R35: =1-Q35 -> 0.96992982 | S35: taxonomy_effect_size.xlsx, Sheet 1, row 136 | T35: =IF(OR(R35<0,R35>1),"BAD","OK") -> OK
A36: I_CVD_PRIMARY__C_IHD_Women_2033 | B36: I_CVD_PRIMARY__C_IHD | C36: I_CVD_PRIMARY | D36: Primary prevention of CVD | E36: C_IHD | F36: Ischemic heart disease | G36: Women | H36: 2033 | I36: well | J36: sick | K36: =Effect_Sizes!J2 -> 0.58 | L36: =Effect_Sizes!K2 -> 0.8 | M36: =Coverage_Trajectory!H36 -> 0.13268074 | N36: =Coverage_Trajectory!K36 -> 0.2205 | O36: =N36-M36 -> 0.087819262 | P36: =IF(O36=0,0,K36*O36/(1-K36*M36)) -> 0.055181668 | Q36: =P36*L36 -> 0.044145334 | R36: =1-Q36 -> 0.95585467 | S36: taxonomy_effect_size.xlsx, Sheet 1, row 136 | T36: =IF(OR(R36<0,R36>1),"BAD","OK") -> OK
A37: I_CVD_PRIMARY__C_IHD_Women_2034 | B37: I_CVD_PRIMARY__C_IHD | C37: I_CVD_PRIMARY | D37: Primary prevention of CVD | E37: C_IHD | F37: Ischemic heart disease | G37: Women | H37: 2034 | I37: well | J37: sick | K37: =Effect_Sizes!J2 -> 0.58 | L37: =Effect_Sizes!K2 -> 0.8 | M37: =Coverage_Trajectory!H37 -> 0.13268074 | N37: =Coverage_Trajectory!K37 -> 0.2485 | O37: =N37-M37 -> 0.11581926 | P37: =IF(O37=0,0,K37*O37/(1-K37*M37)) -> 0.072775606 | Q37: =P37*L37 -> 0.058220485 | R37: =1-Q37 -> 0.94177951 | S37: taxonomy_effect_size.xlsx, Sheet 1, row 136 | T37: =IF(OR(R37<0,R37>1),"BAD","OK") -> OK
A38: I_CVD_PRIMARY__C_IHD_Women_2035 | B38: I_CVD_PRIMARY__C_IHD | C38: I_CVD_PRIMARY | D38: Primary prevention of CVD | E38: C_IHD | F38: Ischemic heart disease | G38: Women | H38: 2035 | I38: well | J38: sick | K38: =Effect_Sizes!J2 -> 0.58 | L38: =Effect_Sizes!K2 -> 0.8 | M38: =Coverage_Trajectory!H38 -> 0.13268074 | N38: =Coverage_Trajectory!K38 -> 0.2765 | O38: =N38-M38 -> 0.14381926 | P38: =IF(O38=0,0,K38*O38/(1-K38*M38)) -> 0.090369545 | Q38: =P38*L38 -> 0.072295636 | R38: =1-Q38 -> 0.92770436 | S38: taxonomy_effect_size.xlsx, Sheet 1, row 136 | T38: =IF(OR(R38<0,R38>1),"BAD","OK") -> OK
A39: I_CVD_PRIMARY__C_IHD_Women_2036 | B39: I_CVD_PRIMARY__C_IHD | C39: I_CVD_PRIMARY | D39: Primary prevention of CVD | E39: C_IHD | F39: Ischemic heart disease | G39: Women | H39: 2036 | I39: well | J39: sick | K39: =Effect_Sizes!J2 -> 0.58 | L39: =Effect_Sizes!K2 -> 0.8 | M39: =Coverage_Trajectory!H39 -> 0.13268074 | N39: =Coverage_Trajectory!K39 -> 0.3045 | O39: =N39-M39 -> 0.17181926 | P39: =IF(O39=0,0,K39*O39/(1-K39*M39)) -> 0.10796348 | Q39: =P39*L39 -> 0.086370787 | R39: =1-Q39 -> 0.91362921 | S39: taxonomy_effect_size.xlsx, Sheet 1, row 136 | T39: =IF(OR(R39<0,R39>1),"BAD","OK") -> OK
A40: I_CVD_PRIMARY__C_IHD_Women_2037 | B40: I_CVD_PRIMARY__C_IHD | C40: I_CVD_PRIMARY | D40: Primary prevention of CVD | E40: C_IHD | F40: Ischemic heart disease | G40: Women | H40: 2037 | I40: well | J40: sick | K40: =Effect_Sizes!J2 -> 0.58 | L40: =Effect_Sizes!K2 -> 0.8 | M40: =Coverage_Trajectory!H40 -> 0.13268074 | N40: =Coverage_Trajectory!K40 -> 0.3325 | O40: =N40-M40 -> 0.19981926 | P40: =IF(O40=0,0,K40*O40/(1-K40*M40)) -> 0.12555742 | Q40: =P40*L40 -> 0.10044594 | R40: =1-Q40 -> 0.89955406 | S40: taxonomy_effect_size.xlsx, Sheet 1, row 136 | T40: =IF(OR(R40<0,R40>1),"BAD","OK") -> OK
A41: I_CVD_PRIMARY__C_IHD_Women_2038 | B41: I_CVD_PRIMARY__C_IHD | C41: I_CVD_PRIMARY | D41: Primary prevention of CVD | E41: C_IHD | F41: Ischemic heart disease | G41: Women | H41: 2038 | I41: well | J41: sick | K41: =Effect_Sizes!J2 -> 0.58 | L41: =Effect_Sizes!K2 -> 0.8 | M41: =Coverage_Trajectory!H41 -> 0.13268074 | N41: =Coverage_Trajectory!K41 -> 0.3605 | O41: =N41-M41 -> 0.22781926 | P41: =IF(O41=0,0,K41*O41/(1-K41*M41)) -> 0.14315136 | Q41: =P41*L41 -> 0.11452109 | R41: =1-Q41 -> 0.88547891 | S41: taxonomy_effect_size.xlsx, Sheet 1, row 136 | T41: =IF(OR(R41<0,R41>1),"BAD","OK") -> OK
A42: I_CVD_PRIMARY__C_IHD_Women_2039 | B42: I_CVD_PRIMARY__C_IHD | C42: I_CVD_PRIMARY | D42: Primary prevention of CVD | E42: C_IHD | F42: Ischemic heart disease | G42: Women | H42: 2039 | I42: well | J42: sick | K42: =Effect_Sizes!J2 -> 0.58 | L42: =Effect_Sizes!K2 -> 0.8 | M42: =Coverage_Trajectory!H42 -> 0.13268074 | N42: =Coverage_Trajectory!K42 -> 0.3885 | O42: =N42-M42 -> 0.25581926 | P42: =IF(O42=0,0,K42*O42/(1-K42*M42)) -> 0.1607453 | Q42: =P42*L42 -> 0.12859624 | R42: =1-Q42 -> 0.87140376 | S42: taxonomy_effect_size.xlsx, Sheet 1, row 136 | T42: =IF(OR(R42<0,R42>1),"BAD","OK") -> OK
A43: I_CVD_PRIMARY__C_IHD_Women_2040 | B43: I_CVD_PRIMARY__C_IHD | C43: I_CVD_PRIMARY | D43: Primary prevention of CVD | E43: C_IHD | F43: Ischemic heart disease | G43: Women | H43: 2040 | I43: well | J43: sick | K43: =Effect_Sizes!J2 -> 0.58 | L43: =Effect_Sizes!K2 -> 0.8 | M43: =Coverage_Trajectory!H43 -> 0.13268074 | N43: =Coverage_Trajectory!K43 -> 0.4165 | O43: =N43-M43 -> 0.28381926 | P43: =IF(O43=0,0,K43*O43/(1-K43*M43)) -> 0.17833924 | Q43: =P43*L43 -> 0.14267139 | R43: =1-Q43 -> 0.85732861 | S43: taxonomy_effect_size.xlsx, Sheet 1, row 136 | T43: =IF(OR(R43<0,R43>1),"BAD","OK") -> OK
A44: I_CVD_PRIMARY__C_IHD_Women_2041 | B44: I_CVD_PRIMARY__C_IHD | C44: I_CVD_PRIMARY | D44: Primary prevention of CVD | E44: C_IHD | F44: Ischemic heart disease | G44: Women | H44: 2041 | I44: well | J44: sick | K44: =Effect_Sizes!J2 -> 0.58 | L44: =Effect_Sizes!K2 -> 0.8 | M44: =Coverage_Trajectory!H44 -> 0.13268074 | N44: =Coverage_Trajectory!K44 -> 0.4165 | O44: =N44-M44 -> 0.28381926 | P44: =IF(O44=0,0,K44*O44/(1-K44*M44)) -> 0.17833924 | Q44: =P44*L44 -> 0.14267139 | R44: =1-Q44 -> 0.85732861 | S44: taxonomy_effect_size.xlsx, Sheet 1, row 136 | T44: =IF(OR(R44<0,R44>1),"BAD","OK") -> OK
A45: I_CVD_PRIMARY__C_IHD_Women_2042 | B45: I_CVD_PRIMARY__C_IHD | C45: I_CVD_PRIMARY | D45: Primary prevention of CVD | E45: C_IHD | F45: Ischemic heart disease | G45: Women | H45: 2042 | I45: well | J45: sick | K45: =Effect_Sizes!J2 -> 0.58 | L45: =Effect_Sizes!K2 -> 0.8 | M45: =Coverage_Trajectory!H45 -> 0.13268074 | N45: =Coverage_Trajectory!K45 -> 0.4165 | O45: =N45-M45 -> 0.28381926 | P45: =IF(O45=0,0,K45*O45/(1-K45*M45)) -> 0.17833924 | Q45: =P45*L45 -> 0.14267139 | R45: =1-Q45 -> 0.85732861 | S45: taxonomy_effect_size.xlsx, Sheet 1, row 136 | T45: =IF(OR(R45<0,R45>1),"BAD","OK") -> OK
A46: I_CVD_PRIMARY__C_IHD_Women_2043 | B46: I_CVD_PRIMARY__C_IHD | C46: I_CVD_PRIMARY | D46: Primary prevention of CVD | E46: C_IHD | F46: Ischemic heart disease | G46: Women | H46: 2043 | I46: well | J46: sick | K46: =Effect_Sizes!J2 -> 0.58 | L46: =Effect_Sizes!K2 -> 0.8 | M46: =Coverage_Trajectory!H46 -> 0.13268074 | N46: =Coverage_Trajectory!K46 -> 0.4165 | O46: =N46-M46 -> 0.28381926 | P46: =IF(O46=0,0,K46*O46/(1-K46*M46)) -> 0.17833924 | Q46: =P46*L46 -> 0.14267139 | R46: =1-Q46 -> 0.85732861 | S46: taxonomy_effect_size.xlsx, Sheet 1, row 136 | T46: =IF(OR(R46<0,R46>1),"BAD","OK") -> OK
A47: I_CVD_PRIMARY__C_IHD_Women_2044 | B47: I_CVD_PRIMARY__C_IHD | C47: I_CVD_PRIMARY | D47: Primary prevention of CVD | E47: C_IHD | F47: Ischemic heart disease | G47: Women | H47: 2044 | I47: well | J47: sick | K47: =Effect_Sizes!J2 -> 0.58 | L47: =Effect_Sizes!K2 -> 0.8 | M47: =Coverage_Trajectory!H47 -> 0.13268074 | N47: =Coverage_Trajectory!K47 -> 0.4165 | O47: =N47-M47 -> 0.28381926 | P47: =IF(O47=0,0,K47*O47/(1-K47*M47)) -> 0.17833924 | Q47: =P47*L47 -> 0.14267139 | R47: =1-Q47 -> 0.85732861 | S47: taxonomy_effect_size.xlsx, Sheet 1, row 136 | T47: =IF(OR(R47<0,R47>1),"BAD","OK") -> OK
A48: I_CVD_PRIMARY__C_IHD_Women_2045 | B48: I_CVD_PRIMARY__C_IHD | C48: I_CVD_PRIMARY | D48: Primary prevention of CVD | E48: C_IHD | F48: Ischemic heart disease | G48: Women | H48: 2045 | I48: well | J48: sick | K48: =Effect_Sizes!J2 -> 0.58 | L48: =Effect_Sizes!K2 -> 0.8 | M48: =Coverage_Trajectory!H48 -> 0.13268074 | N48: =Coverage_Trajectory!K48 -> 0.4165 | O48: =N48-M48 -> 0.28381926 | P48: =IF(O48=0,0,K48*O48/(1-K48*M48)) -> 0.17833924 | Q48: =P48*L48 -> 0.14267139 | R48: =1-Q48 -> 0.85732861 | S48: taxonomy_effect_size.xlsx, Sheet 1, row 136 | T48: =IF(OR(R48<0,R48>1),"BAD","OK") -> OK
A49: I_CVD_PRIMARY__C_IHD_Women_2046 | B49: I_CVD_PRIMARY__C_IHD | C49: I_CVD_PRIMARY | D49: Primary prevention of CVD | E49: C_IHD | F49: Ischemic heart disease | G49: Women | H49: 2046 | I49: well | J49: sick | K49: =Effect_Sizes!J2 -> 0.58 | L49: =Effect_Sizes!K2 -> 0.8 | M49: =Coverage_Trajectory!H49 -> 0.13268074 | N49: =Coverage_Trajectory!K49 -> 0.4165 | O49: =N49-M49 -> 0.28381926 | P49: =IF(O49=0,0,K49*O49/(1-K49*M49)) -> 0.17833924 | Q49: =P49*L49 -> 0.14267139 | R49: =1-Q49 -> 0.85732861 | S49: taxonomy_effect_size.xlsx, Sheet 1, row 136 | T49: =IF(OR(R49<0,R49>1),"BAD","OK") -> OK
A50: I_CVD_PRIMARY__C_IHD_Women_2047 | B50: I_CVD_PRIMARY__C_IHD | C50: I_CVD_PRIMARY | D50: Primary prevention of CVD | E50: C_IHD | F50: Ischemic heart disease | G50: Women | H50: 2047 | I50: well | J50: sick | K50: =Effect_Sizes!J2 -> 0.58 | L50: =Effect_Sizes!K2 -> 0.8 | M50: =Coverage_Trajectory!H50 -> 0.13268074 | N50: =Coverage_Trajectory!K50 -> 0.4165 | O50: =N50-M50 -> 0.28381926 | P50: =IF(O50=0,0,K50*O50/(1-K50*M50)) -> 0.17833924 | Q50: =P50*L50 -> 0.14267139 | R50: =1-Q50 -> 0.85732861 | S50: taxonomy_effect_size.xlsx, Sheet 1, row 136 | T50: =IF(OR(R50<0,R50>1),"BAD","OK") -> OK
A51: I_CVD_PRIMARY__C_IHD_Women_2048 | B51: I_CVD_PRIMARY__C_IHD | C51: I_CVD_PRIMARY | D51: Primary prevention of CVD | E51: C_IHD | F51: Ischemic heart disease | G51: Women | H51: 2048 | I51: well | J51: sick | K51: =Effect_Sizes!J2 -> 0.58 | L51: =Effect_Sizes!K2 -> 0.8 | M51: =Coverage_Trajectory!H51 -> 0.13268074 | N51: =Coverage_Trajectory!K51 -> 0.4165 | O51: =N51-M51 -> 0.28381926 | P51: =IF(O51=0,0,K51*O51/(1-K51*M51)) -> 0.17833924 | Q51: =P51*L51 -> 0.14267139 | R51: =1-Q51 -> 0.85732861 | S51: taxonomy_effect_size.xlsx, Sheet 1, row 136 | T51: =IF(OR(R51<0,R51>1),"BAD","OK") -> OK
A52: I_CVD_PRIMARY__C_IHD_Women_2049 | B52: I_CVD_PRIMARY__C_IHD | C52: I_CVD_PRIMARY | D52: Primary prevention of CVD | E52: C_IHD | F52: Ischemic heart disease | G52: Women | H52: 2049 | I52: well | J52: sick | K52: =Effect_Sizes!J2 -> 0.58 | L52: =Effect_Sizes!K2 -> 0.8 | M52: =Coverage_Trajectory!H52 -> 0.13268074 | N52: =Coverage_Trajectory!K52 -> 0.4165 | O52: =N52-M52 -> 0.28381926 | P52: =IF(O52=0,0,K52*O52/(1-K52*M52)) -> 0.17833924 | Q52: =P52*L52 -> 0.14267139 | R52: =1-Q52 -> 0.85732861 | S52: taxonomy_effect_size.xlsx, Sheet 1, row 136 | T52: =IF(OR(R52<0,R52>1),"BAD","OK") -> OK
A53: I_CVD_PRIMARY__C_IHD_Women_2050 | B53: I_CVD_PRIMARY__C_IHD | C53: I_CVD_PRIMARY | D53: Primary prevention of CVD | E53: C_IHD | F53: Ischemic heart disease | G53: Women | H53: 2050 | I53: well | J53: sick | K53: =Effect_Sizes!J2 -> 0.58 | L53: =Effect_Sizes!K2 -> 0.8 | M53: =Coverage_Trajectory!H53 -> 0.13268074 | N53: =Coverage_Trajectory!K53 -> 0.4165 | O53: =N53-M53 -> 0.28381926 | P53: =IF(O53=0,0,K53*O53/(1-K53*M53)) -> 0.17833924 | Q53: =P53*L53 -> 0.14267139 | R53: =1-Q53 -> 0.85732861 | S53: taxonomy_effect_size.xlsx, Sheet 1, row 136 | T53: =IF(OR(R53<0,R53>1),"BAD","OK") -> OK
A54: I_CVD_PRIMARY__C_IS_Men_2025 | B54: I_CVD_PRIMARY__C_IS | C54: I_CVD_PRIMARY | D54: Primary prevention of CVD | E54: C_IS | F54: Ischemic stroke | G54: Men | H54: 2025 | I54: well | J54: sick | K54: =Effect_Sizes!J3 -> 0.54 | L54: =Effect_Sizes!K3 -> 0.8 | M54: =Coverage_Trajectory!H2 -> 0.094852977 | N54: =Coverage_Trajectory!K2 -> 0.094852977 | O54: =N54-M54 -> 0 | P54: =IF(O54=0,0,K54*O54/(1-K54*M54)) -> 0 | Q54: =P54*L54 -> 0 | R54: =1-Q54 -> 1 | S54: taxonomy_effect_size.xlsx, Sheet 1, row 133 | T54: =IF(OR(R54<0,R54>1),"BAD","OK") -> OK
A55: I_CVD_PRIMARY__C_IS_Men_2026 | B55: I_CVD_PRIMARY__C_IS | C55: I_CVD_PRIMARY | D55: Primary prevention of CVD | E55: C_IS | F55: Ischemic stroke | G55: Men | H55: 2026 | I55: well | J55: sick | K55: =Effect_Sizes!J3 -> 0.54 | L55: =Effect_Sizes!K3 -> 0.8 | M55: =Coverage_Trajectory!H3 -> 0.094852977 | N55: =Coverage_Trajectory!K3 -> 0.10318238 | O55: =N55-M55 -> 0.0083294046 | P55: =IF(O55=0,0,K55*O55/(1-K55*M55)) -> 0.0047407 | Q55: =P55*L55 -> 0.00379256 | R55: =1-Q55 -> 0.99620744 | S55: taxonomy_effect_size.xlsx, Sheet 1, row 133 | T55: =IF(OR(R55<0,R55>1),"BAD","OK") -> OK
A56: I_CVD_PRIMARY__C_IS_Men_2027 | B56: I_CVD_PRIMARY__C_IS | C56: I_CVD_PRIMARY | D56: Primary prevention of CVD | E56: C_IS | F56: Ischemic stroke | G56: Men | H56: 2027 | I56: well | J56: sick | K56: =Effect_Sizes!J3 -> 0.54 | L56: =Effect_Sizes!K3 -> 0.8 | M56: =Coverage_Trajectory!H4 -> 0.094852977 | N56: =Coverage_Trajectory!K4 -> 0.11151179 | O56: =N56-M56 -> 0.016658809 | P56: =IF(O56=0,0,K56*O56/(1-K56*M56)) -> 0.0094814001 | Q56: =P56*L56 -> 0.0075851201 | R56: =1-Q56 -> 0.99241488 | S56: taxonomy_effect_size.xlsx, Sheet 1, row 133 | T56: =IF(OR(R56<0,R56>1),"BAD","OK") -> OK
A57: I_CVD_PRIMARY__C_IS_Men_2028 | B57: I_CVD_PRIMARY__C_IS | C57: I_CVD_PRIMARY | D57: Primary prevention of CVD | E57: C_IS | F57: Ischemic stroke | G57: Men | H57: 2028 | I57: well | J57: sick | K57: =Effect_Sizes!J3 -> 0.54 | L57: =Effect_Sizes!K3 -> 0.8 | M57: =Coverage_Trajectory!H5 -> 0.094852977 | N57: =Coverage_Trajectory!K5 -> 0.11984119 | O57: =N57-M57 -> 0.024988214 | P57: =IF(O57=0,0,K57*O57/(1-K57*M57)) -> 0.0142221 | Q57: =P57*L57 -> 0.01137768 | R57: =1-Q57 -> 0.98862232 | S57: taxonomy_effect_size.xlsx, Sheet 1, row 133 | T57: =IF(OR(R57<0,R57>1),"BAD","OK") -> OK
A58: I_CVD_PRIMARY__C_IS_Men_2029 | B58: I_CVD_PRIMARY__C_IS | C58: I_CVD_PRIMARY | D58: Primary prevention of CVD | E58: C_IS | F58: Ischemic stroke | G58: Men | H58: 2029 | I58: well | J58: sick | K58: =Effect_Sizes!J3 -> 0.54 | L58: =Effect_Sizes!K3 -> 0.8 | M58: =Coverage_Trajectory!H6 -> 0.094852977 | N58: =Coverage_Trajectory!K6 -> 0.1281706 | O58: =N58-M58 -> 0.033317619 | P58: =IF(O58=0,0,K58*O58/(1-K58*M58)) -> 0.0189628 | Q58: =P58*L58 -> 0.01517024 | R58: =1-Q58 -> 0.98482976 | S58: taxonomy_effect_size.xlsx, Sheet 1, row 133 | T58: =IF(OR(R58<0,R58>1),"BAD","OK") -> OK
A59: I_CVD_PRIMARY__C_IS_Men_2030 | B59: I_CVD_PRIMARY__C_IS | C59: I_CVD_PRIMARY | D59: Primary prevention of CVD | E59: C_IS | F59: Ischemic stroke | G59: Men | H59: 2030 | I59: well | J59: sick | K59: =Effect_Sizes!J3 -> 0.54 | L59: =Effect_Sizes!K3 -> 0.8 | M59: =Coverage_Trajectory!H7 -> 0.094852977 | N59: =Coverage_Trajectory!K7 -> 0.1365 | O59: =N59-M59 -> 0.041647023 | P59: =IF(O59=0,0,K59*O59/(1-K59*M59)) -> 0.0237035 | Q59: =P59*L59 -> 0.0189628 | R59: =1-Q59 -> 0.9810372 | S59: taxonomy_effect_size.xlsx, Sheet 1, row 133 | T59: =IF(OR(R59<0,R59>1),"BAD","OK") -> OK
A60: I_CVD_PRIMARY__C_IS_Men_2031 | B60: I_CVD_PRIMARY__C_IS | C60: I_CVD_PRIMARY | D60: Primary prevention of CVD | E60: C_IS | F60: Ischemic stroke | G60: Men | H60: 2031 | I60: well | J60: sick | K60: =Effect_Sizes!J3 -> 0.54 | L60: =Effect_Sizes!K3 -> 0.8 | M60: =Coverage_Trajectory!H8 -> 0.094852977 | N60: =Coverage_Trajectory!K8 -> 0.1645 | O60: =N60-M60 -> 0.069647023 | P60: =IF(O60=0,0,K60*O60/(1-K60*M60)) -> 0.039639765 | Q60: =P60*L60 -> 0.031711812 | R60: =1-Q60 -> 0.96828819 | S60: taxonomy_effect_size.xlsx, Sheet 1, row 133 | T60: =IF(OR(R60<0,R60>1),"BAD","OK") -> OK
A61: I_CVD_PRIMARY__C_IS_Men_2032 | B61: I_CVD_PRIMARY__C_IS | C61: I_CVD_PRIMARY | D61: Primary prevention of CVD | E61: C_IS | F61: Ischemic stroke | G61: Men | H61: 2032 | I61: well | J61: sick | K61: =Effect_Sizes!J3 -> 0.54 | L61: =Effect_Sizes!K3 -> 0.8 | M61: =Coverage_Trajectory!H9 -> 0.094852977 | N61: =Coverage_Trajectory!K9 -> 0.1925 | O61: =N61-M61 -> 0.097647023 | P61: =IF(O61=0,0,K61*O61/(1-K61*M61)) -> 0.055576031 | Q61: =P61*L61 -> 0.044460824 | R61: =1-Q61 -> 0.95553918 | S61: taxonomy_effect_size.xlsx, Sheet 1, row 133 | T61: =IF(OR(R61<0,R61>1),"BAD","OK") -> OK
A62: I_CVD_PRIMARY__C_IS_Men_2033 | B62: I_CVD_PRIMARY__C_IS | C62: I_CVD_PRIMARY | D62: Primary prevention of CVD | E62: C_IS | F62: Ischemic stroke | G62: Men | H62: 2033 | I62: well | J62: sick | K62: =Effect_Sizes!J3 -> 0.54 | L62: =Effect_Sizes!K3 -> 0.8 | M62: =Coverage_Trajectory!H10 -> 0.094852977 | N62: =Coverage_Trajectory!K10 -> 0.2205 | O62: =N62-M62 -> 0.12564702 | P62: =IF(O62=0,0,K62*O62/(1-K62*M62)) -> 0.071512296 | Q62: =P62*L62 -> 0.057209837 | R62: =1-Q62 -> 0.94279016 | S62: taxonomy_effect_size.xlsx, Sheet 1, row 133 | T62: =IF(OR(R62<0,R62>1),"BAD","OK") -> OK
A63: I_CVD_PRIMARY__C_IS_Men_2034 | B63: I_CVD_PRIMARY__C_IS | C63: I_CVD_PRIMARY | D63: Primary prevention of CVD | E63: C_IS | F63: Ischemic stroke | G63: Men | H63: 2034 | I63: well | J63: sick | K63: =Effect_Sizes!J3 -> 0.54 | L63: =Effect_Sizes!K3 -> 0.8 | M63: =Coverage_Trajectory!H11 -> 0.094852977 | N63: =Coverage_Trajectory!K11 -> 0.2485 | O63: =N63-M63 -> 0.15364702 | P63: =IF(O63=0,0,K63*O63/(1-K63*M63)) -> 0.087448561 | Q63: =P63*L63 -> 0.069958849 | R63: =1-Q63 -> 0.93004115 | S63: taxonomy_effect_size.xlsx, Sheet 1, row 133 | T63: =IF(OR(R63<0,R63>1),"BAD","OK") -> OK
A64: I_CVD_PRIMARY__C_IS_Men_2035 | B64: I_CVD_PRIMARY__C_IS | C64: I_CVD_PRIMARY | D64: Primary prevention of CVD | E64: C_IS | F64: Ischemic stroke | G64: Men | H64: 2035 | I64: well | J64: sick | K64: =Effect_Sizes!J3 -> 0.54 | L64: =Effect_Sizes!K3 -> 0.8 | M64: =Coverage_Trajectory!H12 -> 0.094852977 | N64: =Coverage_Trajectory!K12 -> 0.2765 | O64: =N64-M64 -> 0.18164702 | P64: =IF(O64=0,0,K64*O64/(1-K64*M64)) -> 0.10338483 | Q64: =P64*L64 -> 0.082707861 | R64: =1-Q64 -> 0.91729214 | S64: taxonomy_effect_size.xlsx, Sheet 1, row 133 | T64: =IF(OR(R64<0,R64>1),"BAD","OK") -> OK
A65: I_CVD_PRIMARY__C_IS_Men_2036 | B65: I_CVD_PRIMARY__C_IS | C65: I_CVD_PRIMARY | D65: Primary prevention of CVD | E65: C_IS | F65: Ischemic stroke | G65: Men | H65: 2036 | I65: well | J65: sick | K65: =Effect_Sizes!J3 -> 0.54 | L65: =Effect_Sizes!K3 -> 0.8 | M65: =Coverage_Trajectory!H13 -> 0.094852977 | N65: =Coverage_Trajectory!K13 -> 0.3045 | O65: =N65-M65 -> 0.20964702 | P65: =IF(O65=0,0,K65*O65/(1-K65*M65)) -> 0.11932109 | Q65: =P65*L65 -> 0.095456873 | R65: =1-Q65 -> 0.90454313 | S65: taxonomy_effect_size.xlsx, Sheet 1, row 133 | T65: =IF(OR(R65<0,R65>1),"BAD","OK") -> OK
A66: I_CVD_PRIMARY__C_IS_Men_2037 | B66: I_CVD_PRIMARY__C_IS | C66: I_CVD_PRIMARY | D66: Primary prevention of CVD | E66: C_IS | F66: Ischemic stroke | G66: Men | H66: 2037 | I66: well | J66: sick | K66: =Effect_Sizes!J3 -> 0.54 | L66: =Effect_Sizes!K3 -> 0.8 | M66: =Coverage_Trajectory!H14 -> 0.094852977 | N66: =Coverage_Trajectory!K14 -> 0.3325 | O66: =N66-M66 -> 0.23764702 | P66: =IF(O66=0,0,K66*O66/(1-K66*M66)) -> 0.13525736 | Q66: =P66*L66 -> 0.10820589 | R66: =1-Q66 -> 0.89179411 | S66: taxonomy_effect_size.xlsx, Sheet 1, row 133 | T66: =IF(OR(R66<0,R66>1),"BAD","OK") -> OK
A67: I_CVD_PRIMARY__C_IS_Men_2038 | B67: I_CVD_PRIMARY__C_IS | C67: I_CVD_PRIMARY | D67: Primary prevention of CVD | E67: C_IS | F67: Ischemic stroke | G67: Men | H67: 2038 | I67: well | J67: sick | K67: =Effect_Sizes!J3 -> 0.54 | L67: =Effect_Sizes!K3 -> 0.8 | M67: =Coverage_Trajectory!H15 -> 0.094852977 | N67: =Coverage_Trajectory!K15 -> 0.3605 | O67: =N67-M67 -> 0.26564702 | P67: =IF(O67=0,0,K67*O67/(1-K67*M67)) -> 0.15119362 | Q67: =P67*L67 -> 0.1209549 | R67: =1-Q67 -> 0.8790451 | S67: taxonomy_effect_size.xlsx, Sheet 1, row 133 | T67: =IF(OR(R67<0,R67>1),"BAD","OK") -> OK
A68: I_CVD_PRIMARY__C_IS_Men_2039 | B68: I_CVD_PRIMARY__C_IS | C68: I_CVD_PRIMARY | D68: Primary prevention of CVD | E68: C_IS | F68: Ischemic stroke | G68: Men | H68: 2039 | I68: well | J68: sick | K68: =Effect_Sizes!J3 -> 0.54 | L68: =Effect_Sizes!K3 -> 0.8 | M68: =Coverage_Trajectory!H16 -> 0.094852977 | N68: =Coverage_Trajectory!K16 -> 0.3885 | O68: =N68-M68 -> 0.29364702 | P68: =IF(O68=0,0,K68*O68/(1-K68*M68)) -> 0.16712989 | Q68: =P68*L68 -> 0.13370391 | R68: =1-Q68 -> 0.86629609 | S68: taxonomy_effect_size.xlsx, Sheet 1, row 133 | T68: =IF(OR(R68<0,R68>1),"BAD","OK") -> OK
A69: I_CVD_PRIMARY__C_IS_Men_2040 | B69: I_CVD_PRIMARY__C_IS | C69: I_CVD_PRIMARY | D69: Primary prevention of CVD | E69: C_IS | F69: Ischemic stroke | G69: Men | H69: 2040 | I69: well | J69: sick | K69: =Effect_Sizes!J3 -> 0.54 | L69: =Effect_Sizes!K3 -> 0.8 | M69: =Coverage_Trajectory!H17 -> 0.094852977 | N69: =Coverage_Trajectory!K17 -> 0.4165 | O69: =N69-M69 -> 0.32164702 | P69: =IF(O69=0,0,K69*O69/(1-K69*M69)) -> 0.18306615 | Q69: =P69*L69 -> 0.14645292 | R69: =1-Q69 -> 0.85354708 | S69: taxonomy_effect_size.xlsx, Sheet 1, row 133 | T69: =IF(OR(R69<0,R69>1),"BAD","OK") -> OK
A70: I_CVD_PRIMARY__C_IS_Men_2041 | B70: I_CVD_PRIMARY__C_IS | C70: I_CVD_PRIMARY | D70: Primary prevention of CVD | E70: C_IS | F70: Ischemic stroke | G70: Men | H70: 2041 | I70: well | J70: sick | K70: =Effect_Sizes!J3 -> 0.54 | L70: =Effect_Sizes!K3 -> 0.8 | M70: =Coverage_Trajectory!H18 -> 0.094852977 | N70: =Coverage_Trajectory!K18 -> 0.4165 | O70: =N70-M70 -> 0.32164702 | P70: =IF(O70=0,0,K70*O70/(1-K70*M70)) -> 0.18306615 | Q70: =P70*L70 -> 0.14645292 | R70: =1-Q70 -> 0.85354708 | S70: taxonomy_effect_size.xlsx, Sheet 1, row 133 | T70: =IF(OR(R70<0,R70>1),"BAD","OK") -> OK
A71: I_CVD_PRIMARY__C_IS_Men_2042 | B71: I_CVD_PRIMARY__C_IS | C71: I_CVD_PRIMARY | D71: Primary prevention of CVD | E71: C_IS | F71: Ischemic stroke | G71: Men | H71: 2042 | I71: well | J71: sick | K71: =Effect_Sizes!J3 -> 0.54 | L71: =Effect_Sizes!K3 -> 0.8 | M71: =Coverage_Trajectory!H19 -> 0.094852977 | N71: =Coverage_Trajectory!K19 -> 0.4165 | O71: =N71-M71 -> 0.32164702 | P71: =IF(O71=0,0,K71*O71/(1-K71*M71)) -> 0.18306615 | Q71: =P71*L71 -> 0.14645292 | R71: =1-Q71 -> 0.85354708 | S71: taxonomy_effect_size.xlsx, Sheet 1, row 133 | T71: =IF(OR(R71<0,R71>1),"BAD","OK") -> OK
A72: I_CVD_PRIMARY__C_IS_Men_2043 | B72: I_CVD_PRIMARY__C_IS | C72: I_CVD_PRIMARY | D72: Primary prevention of CVD | E72: C_IS | F72: Ischemic stroke | G72: Men | H72: 2043 | I72: well | J72: sick | K72: =Effect_Sizes!J3 -> 0.54 | L72: =Effect_Sizes!K3 -> 0.8 | M72: =Coverage_Trajectory!H20 -> 0.094852977 | N72: =Coverage_Trajectory!K20 -> 0.4165 | O72: =N72-M72 -> 0.32164702 | P72: =IF(O72=0,0,K72*O72/(1-K72*M72)) -> 0.18306615 | Q72: =P72*L72 -> 0.14645292 | R72: =1-Q72 -> 0.85354708 | S72: taxonomy_effect_size.xlsx, Sheet 1, row 133 | T72: =IF(OR(R72<0,R72>1),"BAD","OK") -> OK
A73: I_CVD_PRIMARY__C_IS_Men_2044 | B73: I_CVD_PRIMARY__C_IS | C73: I_CVD_PRIMARY | D73: Primary prevention of CVD | E73: C_IS | F73: Ischemic stroke | G73: Men | H73: 2044 | I73: well | J73: sick | K73: =Effect_Sizes!J3 -> 0.54 | L73: =Effect_Sizes!K3 -> 0.8 | M73: =Coverage_Trajectory!H21 -> 0.094852977 | N73: =Coverage_Trajectory!K21 -> 0.4165 | O73: =N73-M73 -> 0.32164702 | P73: =IF(O73=0,0,K73*O73/(1-K73*M73)) -> 0.18306615 | Q73: =P73*L73 -> 0.14645292 | R73: =1-Q73 -> 0.85354708 | S73: taxonomy_effect_size.xlsx, Sheet 1, row 133 | T73: =IF(OR(R73<0,R73>1),"BAD","OK") -> OK
A74: I_CVD_PRIMARY__C_IS_Men_2045 | B74: I_CVD_PRIMARY__C_IS | C74: I_CVD_PRIMARY | D74: Primary prevention of CVD | E74: C_IS | F74: Ischemic stroke | G74: Men | H74: 2045 | I74: well | J74: sick | K74: =Effect_Sizes!J3 -> 0.54 | L74: =Effect_Sizes!K3 -> 0.8 | M74: =Coverage_Trajectory!H22 -> 0.094852977 | N74: =Coverage_Trajectory!K22 -> 0.4165 | O74: =N74-M74 -> 0.32164702 | P74: =IF(O74=0,0,K74*O74/(1-K74*M74)) -> 0.18306615 | Q74: =P74*L74 -> 0.14645292 | R74: =1-Q74 -> 0.85354708 | S74: taxonomy_effect_size.xlsx, Sheet 1, row 133 | T74: =IF(OR(R74<0,R74>1),"BAD","OK") -> OK
A75: I_CVD_PRIMARY__C_IS_Men_2046 | B75: I_CVD_PRIMARY__C_IS | C75: I_CVD_PRIMARY | D75: Primary prevention of CVD | E75: C_IS | F75: Ischemic stroke | G75: Men | H75: 2046 | I75: well | J75: sick | K75: =Effect_Sizes!J3 -> 0.54 | L75: =Effect_Sizes!K3 -> 0.8 | M75: =Coverage_Trajectory!H23 -> 0.094852977 | N75: =Coverage_Trajectory!K23 -> 0.4165 | O75: =N75-M75 -> 0.32164702 | P75: =IF(O75=0,0,K75*O75/(1-K75*M75)) -> 0.18306615 | Q75: =P75*L75 -> 0.14645292 | R75: =1-Q75 -> 0.85354708 | S75: taxonomy_effect_size.xlsx, Sheet 1, row 133 | T75: =IF(OR(R75<0,R75>1),"BAD","OK") -> OK
A76: I_CVD_PRIMARY__C_IS_Men_2047 | B76: I_CVD_PRIMARY__C_IS | C76: I_CVD_PRIMARY | D76: Primary prevention of CVD | E76: C_IS | F76: Ischemic stroke | G76: Men | H76: 2047 | I76: well | J76: sick | K76: =Effect_Sizes!J3 -> 0.54 | L76: =Effect_Sizes!K3 -> 0.8 | M76: =Coverage_Trajectory!H24 -> 0.094852977 | N76: =Coverage_Trajectory!K24 -> 0.4165 | O76: =N76-M76 -> 0.32164702 | P76: =IF(O76=0,0,K76*O76/(1-K76*M76)) -> 0.18306615 | Q76: =P76*L76 -> 0.14645292 | R76: =1-Q76 -> 0.85354708 | S76: taxonomy_effect_size.xlsx, Sheet 1, row 133 | T76: =IF(OR(R76<0,R76>1),"BAD","OK") -> OK
A77: I_CVD_PRIMARY__C_IS_Men_2048 | B77: I_CVD_PRIMARY__C_IS | C77: I_CVD_PRIMARY | D77: Primary prevention of CVD | E77: C_IS | F77: Ischemic stroke | G77: Men | H77: 2048 | I77: well | J77: sick | K77: =Effect_Sizes!J3 -> 0.54 | L77: =Effect_Sizes!K3 -> 0.8 | M77: =Coverage_Trajectory!H25 -> 0.094852977 | N77: =Coverage_Trajectory!K25 -> 0.4165 | O77: =N77-M77 -> 0.32164702 | P77: =IF(O77=0,0,K77*O77/(1-K77*M77)) -> 0.18306615 | Q77: =P77*L77 -> 0.14645292 | R77: =1-Q77 -> 0.85354708 | S77: taxonomy_effect_size.xlsx, Sheet 1, row 133 | T77: =IF(OR(R77<0,R77>1),"BAD","OK") -> OK
A78: I_CVD_PRIMARY__C_IS_Men_2049 | B78: I_CVD_PRIMARY__C_IS | C78: I_CVD_PRIMARY | D78: Primary prevention of CVD | E78: C_IS | F78: Ischemic stroke | G78: Men | H78: 2049 | I78: well | J78: sick | K78: =Effect_Sizes!J3 -> 0.54 | L78: =Effect_Sizes!K3 -> 0.8 | M78: =Coverage_Trajectory!H26 -> 0.094852977 | N78: =Coverage_Trajectory!K26 -> 0.4165 | O78: =N78-M78 -> 0.32164702 | P78: =IF(O78=0,0,K78*O78/(1-K78*M78)) -> 0.18306615 | Q78: =P78*L78 -> 0.14645292 | R78: =1-Q78 -> 0.85354708 | S78: taxonomy_effect_size.xlsx, Sheet 1, row 133 | T78: =IF(OR(R78<0,R78>1),"BAD","OK") -> OK
A79: I_CVD_PRIMARY__C_IS_Men_2050 | B79: I_CVD_PRIMARY__C_IS | C79: I_CVD_PRIMARY | D79: Primary prevention of CVD | E79: C_IS | F79: Ischemic stroke | G79: Men | H79: 2050 | I79: well | J79: sick | K79: =Effect_Sizes!J3 -> 0.54 | L79: =Effect_Sizes!K3 -> 0.8 | M79: =Coverage_Trajectory!H27 -> 0.094852977 | N79: =Coverage_Trajectory!K27 -> 0.4165 | O79: =N79-M79 -> 0.32164702 | P79: =IF(O79=0,0,K79*O79/(1-K79*M79)) -> 0.18306615 | Q79: =P79*L79 -> 0.14645292 | R79: =1-Q79 -> 0.85354708 | S79: taxonomy_effect_size.xlsx, Sheet 1, row 133 | T79: =IF(OR(R79<0,R79>1),"BAD","OK") -> OK
A80: I_CVD_PRIMARY__C_IS_Women_2025 | B80: I_CVD_PRIMARY__C_IS | C80: I_CVD_PRIMARY | D80: Primary prevention of CVD | E80: C_IS | F80: Ischemic stroke | G80: Women | H80: 2025 | I80: well | J80: sick | K80: =Effect_Sizes!J3 -> 0.54 | L80: =Effect_Sizes!K3 -> 0.8 | M80: =Coverage_Trajectory!H28 -> 0.13268074 | N80: =Coverage_Trajectory!K28 -> 0.13268074 | O80: =N80-M80 -> 0 | P80: =IF(O80=0,0,K80*O80/(1-K80*M80)) -> 0 | Q80: =P80*L80 -> 0 | R80: =1-Q80 -> 1 | S80: taxonomy_effect_size.xlsx, Sheet 1, row 133 | T80: =IF(OR(R80<0,R80>1),"BAD","OK") -> OK
A81: I_CVD_PRIMARY__C_IS_Women_2026 | B81: I_CVD_PRIMARY__C_IS | C81: I_CVD_PRIMARY | D81: Primary prevention of CVD | E81: C_IS | F81: Ischemic stroke | G81: Women | H81: 2026 | I81: well | J81: sick | K81: =Effect_Sizes!J3 -> 0.54 | L81: =Effect_Sizes!K3 -> 0.8 | M81: =Coverage_Trajectory!H29 -> 0.13268074 | N81: =Coverage_Trajectory!K29 -> 0.13344459 | O81: =N81-M81 -> 0.00076385241 | P81: =IF(O81=0,0,K81*O81/(1-K81*M81)) -> 0.00044431436 | Q81: =P81*L81 -> 0.00035545149 | R81: =1-Q81 -> 0.99964455 | S81: taxonomy_effect_size.xlsx, Sheet 1, row 133 | T81: =IF(OR(R81<0,R81>1),"BAD","OK") -> OK
A82: I_CVD_PRIMARY__C_IS_Women_2027 | B82: I_CVD_PRIMARY__C_IS | C82: I_CVD_PRIMARY | D82: Primary prevention of CVD | E82: C_IS | F82: Ischemic stroke | G82: Women | H82: 2027 | I82: well | J82: sick | K82: =Effect_Sizes!J3 -> 0.54 | L82: =Effect_Sizes!K3 -> 0.8 | M82: =Coverage_Trajectory!H30 -> 0.13268074 | N82: =Coverage_Trajectory!K30 -> 0.13420844 | O82: =N82-M82 -> 0.0015277048 | P82: =IF(O82=0,0,K82*O82/(1-K82*M82)) -> 0.00088862872 | Q82: =P82*L82 -> 0.00071090297 | R82: =1-Q82 -> 0.9992891 | S82: taxonomy_effect_size.xlsx, Sheet 1, row 133 | T82: =IF(OR(R82<0,R82>1),"BAD","OK") -> OK
A83: I_CVD_PRIMARY__C_IS_Women_2028 | B83: I_CVD_PRIMARY__C_IS | C83: I_CVD_PRIMARY | D83: Primary prevention of CVD | E83: C_IS | F83: Ischemic stroke | G83: Women | H83: 2028 | I83: well | J83: sick | K83: =Effect_Sizes!J3 -> 0.54 | L83: =Effect_Sizes!K3 -> 0.8 | M83: =Coverage_Trajectory!H31 -> 0.13268074 | N83: =Coverage_Trajectory!K31 -> 0.1349723 | O83: =N83-M83 -> 0.0022915572 | P83: =IF(O83=0,0,K83*O83/(1-K83*M83)) -> 0.0013329431 | Q83: =P83*L83 -> 0.0010663545 | R83: =1-Q83 -> 0.99893365 | S83: taxonomy_effect_size.xlsx, Sheet 1, row 133 | T83: =IF(OR(R83<0,R83>1),"BAD","OK") -> OK
A84: I_CVD_PRIMARY__C_IS_Women_2029 | B84: I_CVD_PRIMARY__C_IS | C84: I_CVD_PRIMARY | D84: Primary prevention of CVD | E84: C_IS | F84: Ischemic stroke | G84: Women | H84: 2029 | I84: well | J84: sick | K84: =Effect_Sizes!J3 -> 0.54 | L84: =Effect_Sizes!K3 -> 0.8 | M84: =Coverage_Trajectory!H32 -> 0.13268074 | N84: =Coverage_Trajectory!K32 -> 0.13573615 | O84: =N84-M84 -> 0.0030554096 | P84: =IF(O84=0,0,K84*O84/(1-K84*M84)) -> 0.0017772574 | Q84: =P84*L84 -> 0.0014218059 | R84: =1-Q84 -> 0.99857819 | S84: taxonomy_effect_size.xlsx, Sheet 1, row 133 | T84: =IF(OR(R84<0,R84>1),"BAD","OK") -> OK
A85: I_CVD_PRIMARY__C_IS_Women_2030 | B85: I_CVD_PRIMARY__C_IS | C85: I_CVD_PRIMARY | D85: Primary prevention of CVD | E85: C_IS | F85: Ischemic stroke | G85: Women | H85: 2030 | I85: well | J85: sick | K85: =Effect_Sizes!J3 -> 0.54 | L85: =Effect_Sizes!K3 -> 0.8 | M85: =Coverage_Trajectory!H33 -> 0.13268074 | N85: =Coverage_Trajectory!K33 -> 0.1365 | O85: =N85-M85 -> 0.0038192621 | P85: =IF(O85=0,0,K85*O85/(1-K85*M85)) -> 0.0022215718 | Q85: =P85*L85 -> 0.0017772574 | R85: =1-Q85 -> 0.99822274 | S85: taxonomy_effect_size.xlsx, Sheet 1, row 133 | T85: =IF(OR(R85<0,R85>1),"BAD","OK") -> OK
A86: I_CVD_PRIMARY__C_IS_Women_2031 | B86: I_CVD_PRIMARY__C_IS | C86: I_CVD_PRIMARY | D86: Primary prevention of CVD | E86: C_IS | F86: Ischemic stroke | G86: Women | H86: 2031 | I86: well | J86: sick | K86: =Effect_Sizes!J3 -> 0.54 | L86: =Effect_Sizes!K3 -> 0.8 | M86: =Coverage_Trajectory!H34 -> 0.13268074 | N86: =Coverage_Trajectory!K34 -> 0.1645 | O86: =N86-M86 -> 0.031819262 | P86: =IF(O86=0,0,K86*O86/(1-K86*M86)) -> 0.01850849 | Q86: =P86*L86 -> 0.014806792 | R86: =1-Q86 -> 0.98519321 | S86: taxonomy_effect_size.xlsx, Sheet 1, row 133 | T86: =IF(OR(R86<0,R86>1),"BAD","OK") -> OK
A87: I_CVD_PRIMARY__C_IS_Women_2032 | B87: I_CVD_PRIMARY__C_IS | C87: I_CVD_PRIMARY | D87: Primary prevention of CVD | E87: C_IS | F87: Ischemic stroke | G87: Women | H87: 2032 | I87: well | J87: sick | K87: =Effect_Sizes!J3 -> 0.54 | L87: =Effect_Sizes!K3 -> 0.8 | M87: =Coverage_Trajectory!H35 -> 0.13268074 | N87: =Coverage_Trajectory!K35 -> 0.1925 | O87: =N87-M87 -> 0.059819262 | P87: =IF(O87=0,0,K87*O87/(1-K87*M87)) -> 0.034795409 | Q87: =P87*L87 -> 0.027836327 | R87: =1-Q87 -> 0.97216367 | S87: taxonomy_effect_size.xlsx, Sheet 1, row 133 | T87: =IF(OR(R87<0,R87>1),"BAD","OK") -> OK
A88: I_CVD_PRIMARY__C_IS_Women_2033 | B88: I_CVD_PRIMARY__C_IS | C88: I_CVD_PRIMARY | D88: Primary prevention of CVD | E88: C_IS | F88: Ischemic stroke | G88: Women | H88: 2033 | I88: well | J88: sick | K88: =Effect_Sizes!J3 -> 0.54 | L88: =Effect_Sizes!K3 -> 0.8 | M88: =Coverage_Trajectory!H36 -> 0.13268074 | N88: =Coverage_Trajectory!K36 -> 0.2205 | O88: =N88-M88 -> 0.087819262 | P88: =IF(O88=0,0,K88*O88/(1-K88*M88)) -> 0.051082328 | Q88: =P88*L88 -> 0.040865862 | R88: =1-Q88 -> 0.95913414 | S88: taxonomy_effect_size.xlsx, Sheet 1, row 133 | T88: =IF(OR(R88<0,R88>1),"BAD","OK") -> OK
A89: I_CVD_PRIMARY__C_IS_Women_2034 | B89: I_CVD_PRIMARY__C_IS | C89: I_CVD_PRIMARY | D89: Primary prevention of CVD | E89: C_IS | F89: Ischemic stroke | G89: Women | H89: 2034 | I89: well | J89: sick | K89: =Effect_Sizes!J3 -> 0.54 | L89: =Effect_Sizes!K3 -> 0.8 | M89: =Coverage_Trajectory!H37 -> 0.13268074 | N89: =Coverage_Trajectory!K37 -> 0.2485 | O89: =N89-M89 -> 0.11581926 | P89: =IF(O89=0,0,K89*O89/(1-K89*M89)) -> 0.067369246 | Q89: =P89*L89 -> 0.053895397 | R89: =1-Q89 -> 0.9461046 | S89: taxonomy_effect_size.xlsx, Sheet 1, row 133 | T89: =IF(OR(R89<0,R89>1),"BAD","OK") -> OK
A90: I_CVD_PRIMARY__C_IS_Women_2035 | B90: I_CVD_PRIMARY__C_IS | C90: I_CVD_PRIMARY | D90: Primary prevention of CVD | E90: C_IS | F90: Ischemic stroke | G90: Women | H90: 2035 | I90: well | J90: sick | K90: =Effect_Sizes!J3 -> 0.54 | L90: =Effect_Sizes!K3 -> 0.8 | M90: =Coverage_Trajectory!H38 -> 0.13268074 | N90: =Coverage_Trajectory!K38 -> 0.2765 | O90: =N90-M90 -> 0.14381926 | P90: =IF(O90=0,0,K90*O90/(1-K90*M90)) -> 0.083656165 | Q90: =P90*L90 -> 0.066924932 | R90: =1-Q90 -> 0.93307507 | S90: taxonomy_effect_size.xlsx, Sheet 1, row 133 | T90: =IF(OR(R90<0,R90>1),"BAD","OK") -> OK
A91: I_CVD_PRIMARY__C_IS_Women_2036 | B91: I_CVD_PRIMARY__C_IS | C91: I_CVD_PRIMARY | D91: Primary prevention of CVD | E91: C_IS | F91: Ischemic stroke | G91: Women | H91: 2036 | I91: well | J91: sick | K91: =Effect_Sizes!J3 -> 0.54 | L91: =Effect_Sizes!K3 -> 0.8 | M91: =Coverage_Trajectory!H39 -> 0.13268074 | N91: =Coverage_Trajectory!K39 -> 0.3045 | O91: =N91-M91 -> 0.17181926 | P91: =IF(O91=0,0,K91*O91/(1-K91*M91)) -> 0.099943083 | Q91: =P91*L91 -> 0.079954467 | R91: =1-Q91 -> 0.92004553 | S91: taxonomy_effect_size.xlsx, Sheet 1, row 133 | T91: =IF(OR(R91<0,R91>1),"BAD","OK") -> OK
A92: I_CVD_PRIMARY__C_IS_Women_2037 | B92: I_CVD_PRIMARY__C_IS | C92: I_CVD_PRIMARY | D92: Primary prevention of CVD | E92: C_IS | F92: Ischemic stroke | G92: Women | H92: 2037 | I92: well | J92: sick | K92: =Effect_Sizes!J3 -> 0.54 | L92: =Effect_Sizes!K3 -> 0.8 | M92: =Coverage_Trajectory!H40 -> 0.13268074 | N92: =Coverage_Trajectory!K40 -> 0.3325 | O92: =N92-M92 -> 0.19981926 | P92: =IF(O92=0,0,K92*O92/(1-K92*M92)) -> 0.11623 | Q92: =P92*L92 -> 0.092984002 | R92: =1-Q92 -> 0.907016 | S92: taxonomy_effect_size.xlsx, Sheet 1, row 133 | T92: =IF(OR(R92<0,R92>1),"BAD","OK") -> OK
A93: I_CVD_PRIMARY__C_IS_Women_2038 | B93: I_CVD_PRIMARY__C_IS | C93: I_CVD_PRIMARY | D93: Primary prevention of CVD | E93: C_IS | F93: Ischemic stroke | G93: Women | H93: 2038 | I93: well | J93: sick | K93: =Effect_Sizes!J3 -> 0.54 | L93: =Effect_Sizes!K3 -> 0.8 | M93: =Coverage_Trajectory!H41 -> 0.13268074 | N93: =Coverage_Trajectory!K41 -> 0.3605 | O93: =N93-M93 -> 0.22781926 | P93: =IF(O93=0,0,K93*O93/(1-K93*M93)) -> 0.13251692 | Q93: =P93*L93 -> 0.10601354 | R93: =1-Q93 -> 0.89398646 | S93: taxonomy_effect_size.xlsx, Sheet 1, row 133 | T93: =IF(OR(R93<0,R93>1),"BAD","OK") -> OK
A94: I_CVD_PRIMARY__C_IS_Women_2039 | B94: I_CVD_PRIMARY__C_IS | C94: I_CVD_PRIMARY | D94: Primary prevention of CVD | E94: C_IS | F94: Ischemic stroke | G94: Women | H94: 2039 | I94: well | J94: sick | K94: =Effect_Sizes!J3 -> 0.54 | L94: =Effect_Sizes!K3 -> 0.8 | M94: =Coverage_Trajectory!H42 -> 0.13268074 | N94: =Coverage_Trajectory!K42 -> 0.3885 | O94: =N94-M94 -> 0.25581926 | P94: =IF(O94=0,0,K94*O94/(1-K94*M94)) -> 0.14880384 | Q94: =P94*L94 -> 0.11904307 | R94: =1-Q94 -> 0.88095693 | S94: taxonomy_effect_size.xlsx, Sheet 1, row 133 | T94: =IF(OR(R94<0,R94>1),"BAD","OK") -> OK
A95: I_CVD_PRIMARY__C_IS_Women_2040 | B95: I_CVD_PRIMARY__C_IS | C95: I_CVD_PRIMARY | D95: Primary prevention of CVD | E95: C_IS | F95: Ischemic stroke | G95: Women | H95: 2040 | I95: well | J95: sick | K95: =Effect_Sizes!J3 -> 0.54 | L95: =Effect_Sizes!K3 -> 0.8 | M95: =Coverage_Trajectory!H43 -> 0.13268074 | N95: =Coverage_Trajectory!K43 -> 0.4165 | O95: =N95-M95 -> 0.28381926 | P95: =IF(O95=0,0,K95*O95/(1-K95*M95)) -> 0.16509076 | Q95: =P95*L95 -> 0.13207261 | R95: =1-Q95 -> 0.86792739 | S95: taxonomy_effect_size.xlsx, Sheet 1, row 133 | T95: =IF(OR(R95<0,R95>1),"BAD","OK") -> OK
A96: I_CVD_PRIMARY__C_IS_Women_2041 | B96: I_CVD_PRIMARY__C_IS | C96: I_CVD_PRIMARY | D96: Primary prevention of CVD | E96: C_IS | F96: Ischemic stroke | G96: Women | H96: 2041 | I96: well | J96: sick | K96: =Effect_Sizes!J3 -> 0.54 | L96: =Effect_Sizes!K3 -> 0.8 | M96: =Coverage_Trajectory!H44 -> 0.13268074 | N96: =Coverage_Trajectory!K44 -> 0.4165 | O96: =N96-M96 -> 0.28381926 | P96: =IF(O96=0,0,K96*O96/(1-K96*M96)) -> 0.16509076 | Q96: =P96*L96 -> 0.13207261 | R96: =1-Q96 -> 0.86792739 | S96: taxonomy_effect_size.xlsx, Sheet 1, row 133 | T96: =IF(OR(R96<0,R96>1),"BAD","OK") -> OK
A97: I_CVD_PRIMARY__C_IS_Women_2042 | B97: I_CVD_PRIMARY__C_IS | C97: I_CVD_PRIMARY | D97: Primary prevention of CVD | E97: C_IS | F97: Ischemic stroke | G97: Women | H97: 2042 | I97: well | J97: sick | K97: =Effect_Sizes!J3 -> 0.54 | L97: =Effect_Sizes!K3 -> 0.8 | M97: =Coverage_Trajectory!H45 -> 0.13268074 | N97: =Coverage_Trajectory!K45 -> 0.4165 | O97: =N97-M97 -> 0.28381926 | P97: =IF(O97=0,0,K97*O97/(1-K97*M97)) -> 0.16509076 | Q97: =P97*L97 -> 0.13207261 | R97: =1-Q97 -> 0.86792739 | S97: taxonomy_effect_size.xlsx, Sheet 1, row 133 | T97: =IF(OR(R97<0,R97>1),"BAD","OK") -> OK
A98: I_CVD_PRIMARY__C_IS_Women_2043 | B98: I_CVD_PRIMARY__C_IS | C98: I_CVD_PRIMARY | D98: Primary prevention of CVD | E98: C_IS | F98: Ischemic stroke | G98: Women | H98: 2043 | I98: well | J98: sick | K98: =Effect_Sizes!J3 -> 0.54 | L98: =Effect_Sizes!K3 -> 0.8 | M98: =Coverage_Trajectory!H46 -> 0.13268074 | N98: =Coverage_Trajectory!K46 -> 0.4165 | O98: =N98-M98 -> 0.28381926 | P98: =IF(O98=0,0,K98*O98/(1-K98*M98)) -> 0.16509076 | Q98: =P98*L98 -> 0.13207261 | R98: =1-Q98 -> 0.86792739 | S98: taxonomy_effect_size.xlsx, Sheet 1, row 133 | T98: =IF(OR(R98<0,R98>1),"BAD","OK") -> OK
A99: I_CVD_PRIMARY__C_IS_Women_2044 | B99: I_CVD_PRIMARY__C_IS | C99: I_CVD_PRIMARY | D99: Primary prevention of CVD | E99: C_IS | F99: Ischemic stroke | G99: Women | H99: 2044 | I99: well | J99: sick | K99: =Effect_Sizes!J3 -> 0.54 | L99: =Effect_Sizes!K3 -> 0.8 | M99: =Coverage_Trajectory!H47 -> 0.13268074 | N99: =Coverage_Trajectory!K47 -> 0.4165 | O99: =N99-M99 -> 0.28381926 | P99: =IF(O99=0,0,K99*O99/(1-K99*M99)) -> 0.16509076 | Q99: =P99*L99 -> 0.13207261 | R99: =1-Q99 -> 0.86792739 | S99: taxonomy_effect_size.xlsx, Sheet 1, row 133 | T99: =IF(OR(R99<0,R99>1),"BAD","OK") -> OK
A100: I_CVD_PRIMARY__C_IS_Women_2045 | B100: I_CVD_PRIMARY__C_IS | C100: I_CVD_PRIMARY | D100: Primary prevention of CVD | E100: C_IS | F100: Ischemic stroke | G100: Women | H100: 2045 | I100: well | J100: sick | K100: =Effect_Sizes!J3 -> 0.54 | L100: =Effect_Sizes!K3 -> 0.8 | M100: =Coverage_Trajectory!H48 -> 0.13268074 | N100: =Coverage_Trajectory!K48 -> 0.4165 | O100: =N100-M100 -> 0.28381926 | P100: =IF(O100=0,0,K100*O100/(1-K100*M100)) -> 0.16509076 | Q100: =P100*L100 -> 0.13207261 | R100: =1-Q100 -> 0.86792739 | S100: taxonomy_effect_size.xlsx, Sheet 1, row 133 | T100: =IF(OR(R100<0,R100>1),"BAD","OK") -> OK
...

Sheet FairChoices_Methods
A1: method_id | B1: concept | C1: formula_or_rule | D1: implemented_in | E1: linkage_key | F1: Indonesia interpretation
A2: M01 | B2: Target cascade | C2: treated = diagnosis × conditional treatment; controlled = treated × conditional control | D2: Coverage | E2: risk_factor_id + sex + milestone | F2: Uses conditional cascade steps.
A3: M02 | B3: Treated but uncontrolled | C3: treated_uncontrolled = treated - controlled | D3: Coverage | E3: risk_factor_id + sex + milestone | F3: 14.7% under both policy targets.
A4: M03 | B4: Effective coverage | C4: effective = controlled + partial_effect × treated_uncontrolled | D4: Coverage | E4: risk_factor_id + sex + milestone | F4: Partial effect is 50%.
A5: M04 | B5: Exact policy coverage | C5: model_coverage = exact effective coverage | D5: Coverage | E5: risk_factor_id + sex + milestone | F5: Uses 13.65% and 41.65% without rounded overrides.
A6: M05 | B6: Baseline hypertension | C6: effective = controlled + 0.5 × (treated - controlled) | D6: Coverage | E6: sex | F6: NCD-RisC 2019.
A7: M06 | B7: Baseline diabetes | C7: effective = controlled + 0.5 × (treated - controlled); controlled = treated × control_among_treated | D7: Coverage | E7: sex | F7: Control among treated is editable; base case 34.210526%.
A8: M07 | B8: Cholesterol proxy | C8: coverage_cholesterol = coverage_hypertension | D8: Coverage | E8: sex | F8: Requested assumption.
A9: M08 | B9: Piecewise scale-up | C9: linear baseline→2030; linear 2030→2040; hold after 2040 | D9: Coverage_Trajectory | E9: intervention_id + sex + year | F9: Targets are maintained through 2050.
A10: M09 | B10: Fair Choices effect | C10: e_adj = e_crude × delta_coverage / (1 - e_crude × baseline_coverage) | D10: Model_Input_View | E10: intervention_cause_key + sex + year | F10: Same convention as current Indonesia workbook.
A11: M10 | B11: Transition multiplier | C11: multiplier = 1 - e_adj × affected_fraction | D11: Model_Input_View | E11: intervention_cause_key + sex + year | F11: Multiply the named baseline transition before each annual cycle.

Sheet Raw_NCDRisC
A1: data_id | B1: risk_factor_id | C1: risk_factor_name | D1: sex | E1: source_year | F1: age_scope | G1: prevalence | H1: diagnosed_among_condition | I1: treated_among_condition | J1: controlled_among_condition | K1: mean_total_cholesterol_mmol_l | L1: mean_non_hdl_cholesterol_mmol_l | M1: mean_hdl_cholesterol_mmol_l | N1: source_file | O1: source_row | P1: source_url | Q1: notes
A2: NCDR_HTN_M | B2: RF_HTN | C2: Hypertension | D2: Men | E2: 2019 | F2: Age-standardised, 30-79 years | G2: 0.35887584 | H2: 0.29011104 | I2: 0.1538712 | J2: 0.035834751 | N2: NCDRisk Indonesia age standarized.xlsx | O2: rows 15-16 | P2: https://ncdrisc.org/data-downloads-hypertension.html | Q2: Proportions are among people with hypertension.
A3: NCDR_HTN_W | B3: RF_HTN | C3: Hypertension | D3: Women | E3: 2019 | F3: Age-standardised, 30-79 years | G3: 0.44502373 | H3: 0.40958943 | I3: 0.21414708 | J3: 0.051214394 | N3: NCDRisk Indonesia age standarized.xlsx | O3: rows 15-17 | P3: https://ncdrisc.org/data-downloads-hypertension.html | Q3: Proportions are among people with hypertension.
A4: NCDR_T2D_M | B4: RF_T2D | C4: Type 2 diabetes | D4: Men | E4: 2022 | F4: Age-standardised; prevalence 18+, treatment 30+ | G4: 0.10851895 | I4: 0.19418973 | N4: NCDRisk Indonesia age standarized.xlsx | O4: rows 9-10 | P4: https://doi.org/10.1016/S0140-6736(24)02317-1 | Q4: Attached extract reports treatment but not glycemic control.
A5: NCDR_T2D_W | B5: RF_T2D | C5: Type 2 diabetes | D5: Women | E5: 2022 | F5: Age-standardised; prevalence 18+, treatment 30+ | G5: 0.1453189 | I5: 0.24665382 | N5: NCDRisk Indonesia age standarized.xlsx | O5: rows 9-11 | P5: https://doi.org/10.1016/S0140-6736(24)02317-1 | Q5: Attached extract reports treatment but not glycemic control.
A6: NCDR_CHOL_M | B6: RF_CHOL | C6: Cholesterol | D6: Men | E6: 2018 | F6: Age-standardised | K6: 4.5820286 | L6: 3.5439558 | M6: 1.1010819 | N6: NCDRisk Indonesia age standarized.xlsx | O6: rows 3-4 | P6: https://www.ncdrisc.org/data-downloads-base.html | Q6: Concentrations retained for provenance; treatment coverage follows hypertension.
A7: NCDR_CHOL_W | B7: RF_CHOL | C7: Cholesterol | D7: Women | E7: 2018 | F7: Age-standardised | K7: 4.9367474 | L7: 3.7478952 | M7: 1.3172598 | N7: NCDRisk Indonesia age standarized.xlsx | O7: rows 3-5 | P7: https://www.ncdrisc.org/data-downloads-base.html | Q7: Concentrations retained for provenance; treatment coverage follows hypertension.

Sheet Provincial_Framework
A1: province_code | B1: province_name | C1: baseline_primary_effective_coverage | D1: baseline_diabetes_effective_coverage | E1: baseline_source | F1: capacity_multiplier | G1: illustrative_target_2030 | H1: illustrative_target_2040 | I1: status | J1: caveat
A2: 11 | B2: Aceh | E2: Local cascade data required | F2: 1 | G2: =Assumptions!$B$12*F2 -> 0.1365 | H2: =Assumptions!$B$13*F2 -> 0.4165 | I2: Illustrative only | J2: PLACEHOLDER - NOT AN EMPIRICAL RESULT
A3: 12 | B3: North Sumatra | E3: Local cascade data required | F3: 1 | G3: =Assumptions!$B$12*F3 -> 0.1365 | H3: =Assumptions!$B$13*F3 -> 0.4165 | I3: Illustrative only | J3: PLACEHOLDER - NOT AN EMPIRICAL RESULT
A4: 13 | B4: West Sumatra | E4: Local cascade data required | F4: 1 | G4: =Assumptions!$B$12*F4 -> 0.1365 | H4: =Assumptions!$B$13*F4 -> 0.4165 | I4: Illustrative only | J4: PLACEHOLDER - NOT AN EMPIRICAL RESULT
A5: 14 | B5: Riau | E5: Local cascade data required | F5: 1 | G5: =Assumptions!$B$12*F5 -> 0.1365 | H5: =Assumptions!$B$13*F5 -> 0.4165 | I5: Illustrative only | J5: PLACEHOLDER - NOT AN EMPIRICAL RESULT
A6: 15 | B6: Jambi | E6: Local cascade data required | F6: 1 | G6: =Assumptions!$B$12*F6 -> 0.1365 | H6: =Assumptions!$B$13*F6 -> 0.4165 | I6: Illustrative only | J6: PLACEHOLDER - NOT AN EMPIRICAL RESULT
A7: 16 | B7: South Sumatra | E7: Local cascade data required | F7: 1 | G7: =Assumptions!$B$12*F7 -> 0.1365 | H7: =Assumptions!$B$13*F7 -> 0.4165 | I7: Illustrative only | J7: PLACEHOLDER - NOT AN EMPIRICAL RESULT
A8: 17 | B8: Bengkulu | E8: Local cascade data required | F8: 1 | G8: =Assumptions!$B$12*F8 -> 0.1365 | H8: =Assumptions!$B$13*F8 -> 0.4165 | I8: Illustrative only | J8: PLACEHOLDER - NOT AN EMPIRICAL RESULT
A9: 18 | B9: Lampung | E9: Local cascade data required | F9: 1 | G9: =Assumptions!$B$12*F9 -> 0.1365 | H9: =Assumptions!$B$13*F9 -> 0.4165 | I9: Illustrative only | J9: PLACEHOLDER - NOT AN EMPIRICAL RESULT
A10: 19 | B10: Bangka Belitung Islands | E10: Local cascade data required | F10: 1 | G10: =Assumptions!$B$12*F10 -> 0.1365 | H10: =Assumptions!$B$13*F10 -> 0.4165 | I10: Illustrative only | J10: PLACEHOLDER - NOT AN EMPIRICAL RESULT
A11: 21 | B11: Riau Islands | E11: Local cascade data required | F11: 1 | G11: =Assumptions!$B$12*F11 -> 0.1365 | H11: =Assumptions!$B$13*F11 -> 0.4165 | I11: Illustrative only | J11: PLACEHOLDER - NOT AN EMPIRICAL RESULT
A12: 31 | B12: DKI Jakarta | E12: Local cascade data required | F12: 1 | G12: =Assumptions!$B$12*F12 -> 0.1365 | H12: =Assumptions!$B$13*F12 -> 0.4165 | I12: Illustrative only | J12: PLACEHOLDER - NOT AN EMPIRICAL RESULT
A13: 32 | B13: West Java | E13: Local cascade data required | F13: 1 | G13: =Assumptions!$B$12*F13 -> 0.1365 | H13: =Assumptions!$B$13*F13 -> 0.4165 | I13: Illustrative only | J13: PLACEHOLDER - NOT AN EMPIRICAL RESULT
... A39: 96 | B39: Southwest Papua | E39: Local cascade data required | F39: 1 | G39: =Assumptions!$B$12*F39 -> 0.1365 | H39: =Assumptions!$B$13*F39 -> 0.4165 | I39: Illustrative only | J39: PLACEHOLDER - NOT AN EMPIRICAL RESULT

Sheet Scope_and_Sources
A1: source_or_item | B1: use | C1: location | D1: url | E1: notes
A2: NCD-RisC hypertension | B2: Baseline hypertension prevalence, diagnosis, treatment, and control by sex | C2: NCDRisk Indonesia age standarized.xlsx | D2: https://ncdrisc.org/data-downloads-hypertension.html | E2: 2019; age-standardised 30-79 years
A3: NCD-RisC diabetes | B3: Baseline diabetes prevalence and treatment by sex | C3: NCDRisk Indonesia age standarized.xlsx | D3: https://doi.org/10.1016/S0140-6736(24)02317-1 | E3: 2022; control not supplied
A4: Indonesia diabetes cascade | B4: Editable baseline glycemic control among treated | C4: Muharram et al. 2026 medRxiv | D4: https://doi.org/10.64898/2026.07.29.26359228 | E4: 2023 national survey: 19.0% treated and 6.5% controlled among all diabetes; ratio = 34.210526%
A5: Indonesia diabetes care performance | B5: Peer-reviewed control-rate cross-check | C5: Lancet Regional Health - Western Pacific 2025 | D5: https://doi.org/10.1016/j.lanwpc.2025.101759 | E5: 2023 national survey: 32.0% (95% CI 27.6-36.3) had HbA1c <7%
A6: NCD-RisC cholesterol | B6: Mean cholesterol concentrations; coverage proxy provenance | C6: NCDRisk Indonesia age standarized.xlsx | D6: https://www.ncdrisc.org/data-downloads-base.html | E6: 2018; coverage follows hypertension
A7: Indonesia model inputs | B7: Effect sizes, affected fractions, cost structure, color and naming conventions | C7: indonesia_model_inputs(7).xlsx | E7: Supplied reference workbook
A8: Updated diabetes PIN | B8: Diabetes screening and treatment population-in-need fractions | C8: cvd_input_file_PIN_dm(1).csv | E8: Screening 20%; non-insulin management 60%; insulin management 20%
A9: Updated unit costs | B9: Indonesia-adjusted diabetes unit costs in 2023 USD | C9: cvd_unit_cost_indonesia_1_dm(1).xlsx | E9: Rows 50-52; adjustment_2_salary_usd / unit cost + ancillary
A10: World Bank/UW request | B10: 70-30-30 by 2030; 70-70-70 by 2040; half effect if treated but uncontrolled | C10: Inbox - William R Garcia - Outlook- DCP slides(1).pdf | E10: 27 Aug 2026
A11: Technical plan | B11: Primary-prevention cascade and provincial framework | C11: UW Technical plan for DCP-Indonesia May-Aug 2026 (2)(1).docx | E11: Analysis 1
A12: Limitation | B12: National health and cost outcomes | C12: Not available | E12: Calibrated Markov baseline and runner were not supplied
A13: Limitation | B13: Provincial results | C13: Not available | E13: Province-level cascade and calibrated burden were not supplied

Sheet QA_Checks
A1: check_id | B1: check | C1: expected | D1: actual | E1: status | F1: interpretation
A2: QA01 | B2: Exact 70-30-30 effective coverage | C2: 0.1365 | D2: =Coverage!O3 -> 0.1365 | E2: =IF(ABS(D2-C2)<0.0000001,"PASS","FAIL") -> PASS | F2: 70% × 30% × 30%, with half effect for treated-uncontrolled
A3: QA02 | B3: Model uses exact 70-30-30 coverage | C3: 0.1365 | D3: =Coverage!Q3 -> 0.1365 | E3: =IF(ABS(D3-C3)<0.0000001,"PASS","FAIL") -> PASS | F3: No rounded override
A4: QA03 | B4: Exact 70-70-70 effective coverage | C4: 0.4165 | D4: =Coverage!O4 -> 0.4165 | E4: =IF(ABS(D4-C4)<0.0000001,"PASS","FAIL") -> PASS | F4: 70% × 70% × 70%, with half effect for treated-uncontrolled
A5: QA04 | B5: Model uses exact 70-70-70 coverage | C5: 0.4165 | D5: =Coverage!Q4 -> 0.4165 | E5: =IF(ABS(D5-C5)<0.0000001,"PASS","FAIL") -> PASS | F5: No rounded override
A6: QA05 | B6: Coverage rows with bad values | C6: 0 | D6: =COUNTIF(Coverage!$T$2:$T$19,"BAD") -> 0 | E6: =IF(D6=C6,"PASS","FAIL") -> PASS | F6: All probabilities remain within 0-100%
A7: QA06 | B7: Trajectory rows with bad or decreasing coverage | C7: 0 | D7: =COUNTIF(Coverage_Trajectory!$P$2:$P$105,"BAD") -> 0 | E7: =IF(D7=C7,"PASS","FAIL") -> PASS | F7: Scale-up is monotonic
A8: QA07 | B8: Model input rows with invalid multipliers | C8: 0 | D8: =COUNTIF(Model_Input_View!$T$2:$T$313,"BAD") -> 0 | E8: =IF(D8=C8,"PASS","FAIL") -> PASS | F8: Transition multipliers remain in 0-1
A9: QA08 | B9: Included links missing effect rows | C9: 0 | D9: =COUNTIF(Effect_Sizes!$T$2:$T$7,"BAD KEY") -> 0 | E9: =IF(D9=C9,"PASS","FAIL") -> PASS | F9: Every included link has one effect
A10: QA09 | B10: Selected cost rows requiring review | C10: 0 | D10: =COUNTIF(Cost_Components!$AC$2:$AC$8,"REVIEW ADJUSTMENT") -> 0 | E10: =IF(D10=C10,"PASS","FAIL") -> PASS | F10: All selected diabetes costs are Indonesia-adjusted 2023 USD
A11: QA10 | B11: Baseline model path supplied | C11: 1 | D11: =IF(Assumptions!$B$21="",0,1) -> 0 | E11: =IF(D11=C11,"PASS","MISSING") -> MISSING | F11: Required for deaths and cases
A12: QA11 | B12: Model runner path supplied | C12: 1 | D12: =IF(Assumptions!$B$22="",0,1) -> 0 | E12: =IF(D12=C12,"PASS","MISSING") -> MISSING | F12: Required for national health outcomes
A13: QA12 | B13: Formula and structure checks | C13: 0 | D13: =COUNTIF(E2:E9,"FAIL") -> 0 | E13: =IF(D13=0,"PASS","FAIL") -> PASS | F13: Core cascade calculations only
A14: QA13 | B14: Overall readiness | C14: MODEL INTEGRATION REQUIRED | D14: =IF(OR(E11="MISSING",E12="MISSING"),"MODEL INTEGRATION REQUIRED",IF(COUNTIF(E2:E13,"FAIL")=0,"READY TO RUN","REVIEW REQUIRED")) -> MODEL INTEGRATION REQUIRED | E14: =D14 -> MODEL INTEGRATION REQUIRED | F14: No mortality result is created without the model

Sheet ChangesLog
A1: date | B1: area | C1: description | D1: source_or_reason
A2: 2026-08-27 | B2: Scope | C2: Created stand-alone 70-30-30 to 70-70-70 analysis package | D2: New analysis
A3: 2026-08-27 | B3: Coverage | C3: Removed rounded overrides; model uses exact 13.65% and 41.65% effective coverage | D3: World Bank/UW request
A4: 2026-08-27 | B4: Baseline | C4: Replaced generic 31% proxy with sex-specific NCD-RisC cascade values | D4: NCD-RisC
A5: 2026-08-27 | B5: Diabetes | C5: Added editable 34.210526% control-among-treated baseline from the 2023 national care cascade | D5: Muharram et al. 2026
A6: 2026-08-27 | B6: Costs | C6: Added updated diabetes screening, non-insulin, and insulin-management PIN and Indonesia-adjusted 2023 USD costs | D6: Updated DM PIN and unit-cost files
A7: 2026-08-27 | B7: Cholesterol | C7: Set treatment coverage equal to hypertension coverage | D7: Requested assumption
A8: 2026-08-27 | B8: Provincial | C8: Added clearly labeled illustrative 38-province framework | D8: Local data pending
